package com.tencent.biz.pubaccount.readinjoy.config;

final class AladdinConfigServlet$2
  implements Runnable
{
  /* Error */
  public void run()
  {
    // Byte code:
    //   0: aconst_null
    //   1: astore_1
    //   2: new 16	java/io/OutputStreamWriter
    //   5: dup
    //   6: new 18	java/io/FileOutputStream
    //   9: dup
    //   10: getstatic 24	java/io/File:separator	Ljava/lang/String;
    //   13: iconst_4
    //   14: anewarray 26	java/lang/String
    //   17: dup
    //   18: iconst_0
    //   19: invokestatic 32	android/os/Environment:getExternalStorageDirectory	()Ljava/io/File;
    //   22: invokevirtual 36	java/io/File:getAbsolutePath	()Ljava/lang/String;
    //   25: aastore
    //   26: dup
    //   27: iconst_1
    //   28: ldc 38
    //   30: aastore
    //   31: dup
    //   32: iconst_2
    //   33: ldc 40
    //   35: aastore
    //   36: dup
    //   37: iconst_3
    //   38: ldc 42
    //   40: aastore
    //   41: invokestatic 48	java/util/Arrays:asList	([Ljava/lang/Object;)Ljava/util/List;
    //   44: invokestatic 54	android/text/TextUtils:join	(Ljava/lang/CharSequence;Ljava/lang/Iterable;)Ljava/lang/String;
    //   47: invokespecial 57	java/io/FileOutputStream:<init>	(Ljava/lang/String;)V
    //   50: invokespecial 60	java/io/OutputStreamWriter:<init>	(Ljava/io/OutputStream;)V
    //   53: astore_2
    //   54: aload_2
    //   55: astore_1
    //   56: aload_2
    //   57: invokestatic 65	bcez:c	()Ljava/lang/String;
    //   60: invokevirtual 68	java/io/OutputStreamWriter:write	(Ljava/lang/String;)V
    //   63: aload_2
    //   64: astore_1
    //   65: aload_2
    //   66: invokevirtual 71	java/io/OutputStreamWriter:close	()V
    //   69: aload_2
    //   70: astore_1
    //   71: ldc 73
    //   73: iconst_1
    //   74: ldc 75
    //   76: invokestatic 81	com/tencent/qphone/base/util/QLog:i	(Ljava/lang/String;ILjava/lang/String;)V
    //   79: aload_2
    //   80: ifnull +7 -> 87
    //   83: aload_2
    //   84: invokevirtual 71	java/io/OutputStreamWriter:close	()V
    //   87: return
    //   88: astore_1
    //   89: ldc 73
    //   91: iconst_1
    //   92: ldc 83
    //   94: aload_1
    //   95: invokestatic 87	com/tencent/qphone/base/util/QLog:e	(Ljava/lang/String;ILjava/lang/String;Ljava/lang/Throwable;)V
    //   98: return
    //   99: astore_3
    //   100: aconst_null
    //   101: astore_2
    //   102: aload_2
    //   103: astore_1
    //   104: ldc 73
    //   106: iconst_1
    //   107: ldc 83
    //   109: aload_3
    //   110: invokestatic 87	com/tencent/qphone/base/util/QLog:e	(Ljava/lang/String;ILjava/lang/String;Ljava/lang/Throwable;)V
    //   113: aload_2
    //   114: ifnull -27 -> 87
    //   117: aload_2
    //   118: invokevirtual 71	java/io/OutputStreamWriter:close	()V
    //   121: return
    //   122: astore_1
    //   123: ldc 73
    //   125: iconst_1
    //   126: ldc 83
    //   128: aload_1
    //   129: invokestatic 87	com/tencent/qphone/base/util/QLog:e	(Ljava/lang/String;ILjava/lang/String;Ljava/lang/Throwable;)V
    //   132: return
    //   133: astore_3
    //   134: aload_1
    //   135: astore_2
    //   136: aload_3
    //   137: astore_1
    //   138: aload_2
    //   139: ifnull +7 -> 146
    //   142: aload_2
    //   143: invokevirtual 71	java/io/OutputStreamWriter:close	()V
    //   146: aload_1
    //   147: athrow
    //   148: astore_2
    //   149: ldc 73
    //   151: iconst_1
    //   152: ldc 83
    //   154: aload_2
    //   155: invokestatic 87	com/tencent/qphone/base/util/QLog:e	(Ljava/lang/String;ILjava/lang/String;Ljava/lang/Throwable;)V
    //   158: goto -12 -> 146
    //   161: astore_3
    //   162: aload_1
    //   163: astore_2
    //   164: aload_3
    //   165: astore_1
    //   166: goto -28 -> 138
    //   169: astore_3
    //   170: goto -68 -> 102
    // Local variable table:
    //   start	length	slot	name	signature
    //   0	173	0	this	2
    //   1	70	1	localObject1	Object
    //   88	7	1	localException1	java.lang.Exception
    //   103	1	1	localObject2	Object
    //   122	13	1	localException2	java.lang.Exception
    //   137	29	1	localObject3	Object
    //   53	90	2	localObject4	Object
    //   148	7	2	localException3	java.lang.Exception
    //   163	1	2	localObject5	Object
    //   99	11	3	localException4	java.lang.Exception
    //   133	4	3	localObject6	Object
    //   161	4	3	localObject7	Object
    //   169	1	3	localException5	java.lang.Exception
    // Exception table:
    //   from	to	target	type
    //   83	87	88	java/lang/Exception
    //   2	54	99	java/lang/Exception
    //   117	121	122	java/lang/Exception
    //   2	54	133	finally
    //   142	146	148	java/lang/Exception
    //   56	63	161	finally
    //   65	69	161	finally
    //   71	79	161	finally
    //   104	113	161	finally
    //   56	63	169	java/lang/Exception
    //   65	69	169	java/lang/Exception
    //   71	79	169	java/lang/Exception
  }
}


/* Location:           L:\local\mybackup\temp\qq_apk\com.tencent.mobileqq\classes5.jar
 * Qualified Name:     com.tencent.biz.pubaccount.readinjoy.config.AladdinConfigServlet.2
 * JD-Core Version:    0.7.0.1
 */