package kotlin.l.b.a.b.e.c;

import com.tencent.matrix.trace.core.AppMethodBeat;
import java.io.InputStream;
import java.util.ArrayList;
import java.util.Collections;
import java.util.List;
import kotlin.l.b.a.b.e.a.h;
import kotlin.l.b.a.b.e.a.k;
import kotlin.l.b.a.b.e.a.m;
import kotlin.l.b.a.b.e.a.p;
import kotlin.l.b.a.b.e.a.r;
import kotlin.l.b.a.b.h.aa.a;
import kotlin.l.b.a.b.h.g;
import kotlin.l.b.a.b.h.i;
import kotlin.l.b.a.b.h.i.a;
import kotlin.l.b.a.b.h.i.e;
import kotlin.l.b.a.b.h.k.a;
import kotlin.l.b.a.b.h.k.b;
import kotlin.l.b.a.b.h.r;
import kotlin.l.b.a.b.h.t;

public final class a
{
  public static final i.e<a.p, List<kotlin.l.b.a.b.e.a.a>> ajce;
  public static final i.e<a.r, List<kotlin.l.b.a.b.e.a.a>> ajcf;
  public static final i.e<kotlin.l.b.a.b.e.a.c, b> ajdl;
  public static final i.e<a.h, b> ajdm;
  public static final i.e<a.h, Integer> ajdn;
  public static final i.e<a.m, c> ajdo;
  public static final i.e<a.m, Integer> ajdp;
  public static final i.e<a.p, Boolean> ajdq;
  public static final i.e<kotlin.l.b.a.b.e.a.b, Integer> ajdr;
  public static final i.e<kotlin.l.b.a.b.e.a.b, List<a.m>> ajds;
  public static final i.e<kotlin.l.b.a.b.e.a.b, Integer> ajdt;
  public static final i.e<kotlin.l.b.a.b.e.a.b, Integer> ajdu;
  public static final i.e<a.k, Integer> ajdv;
  public static final i.e<a.k, List<a.m>> ajdw;
  
  static
  {
    AppMethodBeat.i(59218);
    ajdl = i.a(kotlin.l.b.a.b.e.a.c.kuh(), b.kxf(), b.kxf(), 100, aa.a.ajfP, b.class);
    ajdm = i.a(a.h.kuO(), b.kxf(), b.kxf(), 100, aa.a.ajfP, b.class);
    ajdn = i.a(a.h.kuO(), Integer.valueOf(0), null, 101, aa.a.ajfJ, Integer.class);
    ajdo = i.a(a.m.kvk(), c.kxk(), c.kxk(), 100, aa.a.ajfP, c.class);
    ajdp = i.a(a.m.kvk(), Integer.valueOf(0), null, 101, aa.a.ajfJ, Integer.class);
    ajce = i.a(a.p.kvH(), kotlin.l.b.a.b.e.a.a.ktd(), 100, aa.a.ajfP, kotlin.l.b.a.b.e.a.a.class);
    ajdq = i.a(a.p.kvH(), Boolean.FALSE, null, 101, aa.a.ajfM, Boolean.class);
    ajcf = i.a(a.r.kwo(), kotlin.l.b.a.b.e.a.a.ktd(), 100, aa.a.ajfP, kotlin.l.b.a.b.e.a.a.class);
    ajdr = i.a(kotlin.l.b.a.b.e.a.b.ktK(), Integer.valueOf(0), null, 101, aa.a.ajfJ, Integer.class);
    ajds = i.a(kotlin.l.b.a.b.e.a.b.ktK(), a.m.kvk(), 102, aa.a.ajfP, a.m.class);
    ajdt = i.a(kotlin.l.b.a.b.e.a.b.ktK(), Integer.valueOf(0), null, 103, aa.a.ajfJ, Integer.class);
    ajdu = i.a(kotlin.l.b.a.b.e.a.b.ktK(), Integer.valueOf(0), null, 104, aa.a.ajfJ, Integer.class);
    ajdv = i.a(a.k.kuY(), Integer.valueOf(0), null, 101, aa.a.ajfJ, Integer.class);
    ajdw = i.a(a.k.kuY(), a.m.kvk(), 102, aa.a.ajfP, a.m.class);
    AppMethodBeat.o(59218);
  }
  
  public static void a(g paramg)
  {
    AppMethodBeat.i(59217);
    paramg.a(ajdl);
    paramg.a(ajdm);
    paramg.a(ajdn);
    paramg.a(ajdo);
    paramg.a(ajdp);
    paramg.a(ajce);
    paramg.a(ajdq);
    paramg.a(ajcf);
    paramg.a(ajdr);
    paramg.a(ajds);
    paramg.a(ajdt);
    paramg.a(ajdu);
    paramg.a(ajdv);
    paramg.a(ajdw);
    AppMethodBeat.o(59217);
  }
  
  public static final class a
    extends i
    implements b
  {
    public static t<a> aiYa;
    private static final a ajdx;
    private final kotlin.l.b.a.b.h.d aiXZ;
    public int aiZC;
    public int ajdy;
    private int bitField0_;
    private int dRJ = -1;
    private byte memoizedIsInitialized = -1;
    
    static
    {
      AppMethodBeat.i(59109);
      aiYa = new kotlin.l.b.a.b.h.b() {};
      a locala = new a();
      ajdx = locala;
      locala.ktf();
      AppMethodBeat.o(59109);
    }
    
    private a()
    {
      this.aiXZ = kotlin.l.b.a.b.h.d.ajeU;
    }
    
    /* Error */
    private a(kotlin.l.b.a.b.h.e parame, g paramg)
    {
      // Byte code:
      //   0: aload_0
      //   1: invokespecial 52	kotlin/l/b/a/b/h/i:<init>	()V
      //   4: ldc 69
      //   6: invokestatic 36	com/tencent/matrix/trace/core/AppMethodBeat:i	(I)V
      //   9: aload_0
      //   10: iconst_m1
      //   11: putfield 54	kotlin/l/b/a/b/e/c/a$a:memoizedIsInitialized	B
      //   14: aload_0
      //   15: iconst_m1
      //   16: putfield 56	kotlin/l/b/a/b/e/c/a$a:dRJ	I
      //   19: aload_0
      //   20: invokespecial 47	kotlin/l/b/a/b/e/c/a$a:ktf	()V
      //   23: invokestatic 73	kotlin/l/b/a/b/h/d:kya	()Lkotlin/l/b/a/b/h/d$b;
      //   26: astore 5
      //   28: aload 5
      //   30: iconst_1
      //   31: invokestatic 78	kotlin/l/b/a/b/h/f:i	(Ljava/io/OutputStream;I)Lkotlin/l/b/a/b/h/f;
      //   34: astore 6
      //   36: iconst_0
      //   37: istore_3
      //   38: iload_3
      //   39: ifne +169 -> 208
      //   42: aload_1
      //   43: invokevirtual 84	kotlin/l/b/a/b/h/e:aac	()I
      //   46: istore 4
      //   48: iload 4
      //   50: lookupswitch	default:+242->292, 0:+245->295, 8:+52->102, 16:+112->162
      //   85: aload_1
      //   86: aload 6
      //   88: aload_2
      //   89: iload 4
      //   91: invokevirtual 87	kotlin/l/b/a/b/e/c/a$a:a	(Lkotlin/l/b/a/b/h/e;Lkotlin/l/b/a/b/h/f;Lkotlin/l/b/a/b/h/g;I)Z
      //   94: ifne -56 -> 38
      //   97: iconst_1
      //   98: istore_3
      //   99: goto -61 -> 38
      //   102: aload_0
      //   103: aload_0
      //   104: getfield 89	kotlin/l/b/a/b/e/c/a$a:bitField0_	I
      //   107: iconst_1
      //   108: ior
      //   109: putfield 89	kotlin/l/b/a/b/e/c/a$a:bitField0_	I
      //   112: aload_0
      //   113: aload_1
      //   114: invokevirtual 92	kotlin/l/b/a/b/h/e:aar	()I
      //   117: putfield 94	kotlin/l/b/a/b/e/c/a$a:aiZC	I
      //   120: goto -82 -> 38
      //   123: astore_1
      //   124: aload_1
      //   125: aload_0
      //   126: putfield 98	kotlin/l/b/a/b/h/l:ajfp	Lkotlin/l/b/a/b/h/r;
      //   129: ldc 69
      //   131: invokestatic 50	com/tencent/matrix/trace/core/AppMethodBeat:o	(I)V
      //   134: aload_1
      //   135: athrow
      //   136: astore_1
      //   137: aload 6
      //   139: invokevirtual 101	kotlin/l/b/a/b/h/f:flush	()V
      //   142: aload_0
      //   143: aload 5
      //   145: invokevirtual 107	kotlin/l/b/a/b/h/d$b:kyc	()Lkotlin/l/b/a/b/h/d;
      //   148: putfield 63	kotlin/l/b/a/b/e/c/a$a:aiXZ	Lkotlin/l/b/a/b/h/d;
      //   151: aload_0
      //   152: invokevirtual 110	kotlin/l/b/a/b/e/c/a$a:makeExtensionsImmutable	()V
      //   155: ldc 69
      //   157: invokestatic 50	com/tencent/matrix/trace/core/AppMethodBeat:o	(I)V
      //   160: aload_1
      //   161: athrow
      //   162: aload_0
      //   163: aload_0
      //   164: getfield 89	kotlin/l/b/a/b/e/c/a$a:bitField0_	I
      //   167: iconst_2
      //   168: ior
      //   169: putfield 89	kotlin/l/b/a/b/e/c/a$a:bitField0_	I
      //   172: aload_0
      //   173: aload_1
      //   174: invokevirtual 92	kotlin/l/b/a/b/h/e:aar	()I
      //   177: putfield 112	kotlin/l/b/a/b/e/c/a$a:ajdy	I
      //   180: goto -142 -> 38
      //   183: astore_1
      //   184: new 66	kotlin/l/b/a/b/h/l
      //   187: dup
      //   188: aload_1
      //   189: invokevirtual 116	java/io/IOException:getMessage	()Ljava/lang/String;
      //   192: invokespecial 119	kotlin/l/b/a/b/h/l:<init>	(Ljava/lang/String;)V
      //   195: astore_1
      //   196: aload_1
      //   197: aload_0
      //   198: putfield 98	kotlin/l/b/a/b/h/l:ajfp	Lkotlin/l/b/a/b/h/r;
      //   201: ldc 69
      //   203: invokestatic 50	com/tencent/matrix/trace/core/AppMethodBeat:o	(I)V
      //   206: aload_1
      //   207: athrow
      //   208: aload 6
      //   210: invokevirtual 101	kotlin/l/b/a/b/h/f:flush	()V
      //   213: aload_0
      //   214: aload 5
      //   216: invokevirtual 107	kotlin/l/b/a/b/h/d$b:kyc	()Lkotlin/l/b/a/b/h/d;
      //   219: putfield 63	kotlin/l/b/a/b/e/c/a$a:aiXZ	Lkotlin/l/b/a/b/h/d;
      //   222: aload_0
      //   223: invokevirtual 110	kotlin/l/b/a/b/e/c/a$a:makeExtensionsImmutable	()V
      //   226: ldc 69
      //   228: invokestatic 50	com/tencent/matrix/trace/core/AppMethodBeat:o	(I)V
      //   231: return
      //   232: astore_1
      //   233: aload_0
      //   234: aload 5
      //   236: invokevirtual 107	kotlin/l/b/a/b/h/d$b:kyc	()Lkotlin/l/b/a/b/h/d;
      //   239: putfield 63	kotlin/l/b/a/b/e/c/a$a:aiXZ	Lkotlin/l/b/a/b/h/d;
      //   242: goto -20 -> 222
      //   245: astore_1
      //   246: aload_0
      //   247: aload 5
      //   249: invokevirtual 107	kotlin/l/b/a/b/h/d$b:kyc	()Lkotlin/l/b/a/b/h/d;
      //   252: putfield 63	kotlin/l/b/a/b/e/c/a$a:aiXZ	Lkotlin/l/b/a/b/h/d;
      //   255: ldc 69
      //   257: invokestatic 50	com/tencent/matrix/trace/core/AppMethodBeat:o	(I)V
      //   260: aload_1
      //   261: athrow
      //   262: astore_2
      //   263: aload_0
      //   264: aload 5
      //   266: invokevirtual 107	kotlin/l/b/a/b/h/d$b:kyc	()Lkotlin/l/b/a/b/h/d;
      //   269: putfield 63	kotlin/l/b/a/b/e/c/a$a:aiXZ	Lkotlin/l/b/a/b/h/d;
      //   272: goto -121 -> 151
      //   275: astore_1
      //   276: aload_0
      //   277: aload 5
      //   279: invokevirtual 107	kotlin/l/b/a/b/h/d$b:kyc	()Lkotlin/l/b/a/b/h/d;
      //   282: putfield 63	kotlin/l/b/a/b/e/c/a$a:aiXZ	Lkotlin/l/b/a/b/h/d;
      //   285: ldc 69
      //   287: invokestatic 50	com/tencent/matrix/trace/core/AppMethodBeat:o	(I)V
      //   290: aload_1
      //   291: athrow
      //   292: goto -208 -> 84
      //   295: iconst_1
      //   296: istore_3
      //   297: goto -259 -> 38
      // Local variable table:
      //   start	length	slot	name	signature
      //   0	300	0	this	a
      //   0	300	1	parame	kotlin.l.b.a.b.h.e
      //   0	300	2	paramg	g
      //   37	260	3	i	int
      //   46	44	4	j	int
      //   26	252	5	localb	kotlin.l.b.a.b.h.d.b
      //   34	175	6	localf	kotlin.l.b.a.b.h.f
      // Exception table:
      //   from	to	target	type
      //   42	48	123	kotlin/l/b/a/b/h/l
      //   84	97	123	kotlin/l/b/a/b/h/l
      //   102	120	123	kotlin/l/b/a/b/h/l
      //   162	180	123	kotlin/l/b/a/b/h/l
      //   42	48	136	finally
      //   84	97	136	finally
      //   102	120	136	finally
      //   124	136	136	finally
      //   162	180	136	finally
      //   184	208	136	finally
      //   42	48	183	java/io/IOException
      //   84	97	183	java/io/IOException
      //   102	120	183	java/io/IOException
      //   162	180	183	java/io/IOException
      //   208	213	232	java/io/IOException
      //   208	213	245	finally
      //   137	142	262	java/io/IOException
      //   137	142	275	finally
    }
    
    private a(i.a parama)
    {
      super();
      this.aiXZ = parama.aiXZ;
    }
    
    public static a a(a parama)
    {
      AppMethodBeat.i(59105);
      parama = a.kxe().c(parama);
      AppMethodBeat.o(59105);
      return parama;
    }
    
    private void ktf()
    {
      this.aiZC = 0;
      this.ajdy = 0;
    }
    
    public static a kwZ()
    {
      return ajdx;
    }
    
    public final void a(kotlin.l.b.a.b.h.f paramf)
    {
      AppMethodBeat.i(59103);
      getSerializedSize();
      if ((this.bitField0_ & 0x1) == 1) {
        paramf.cF(1, this.aiZC);
      }
      if ((this.bitField0_ & 0x2) == 2) {
        paramf.cF(2, this.ajdy);
      }
      paramf.e(this.aiXZ);
      AppMethodBeat.o(59103);
    }
    
    public final int getSerializedSize()
    {
      AppMethodBeat.i(59104);
      int i = this.dRJ;
      if (i != -1)
      {
        AppMethodBeat.o(59104);
        return i;
      }
      i = 0;
      if ((this.bitField0_ & 0x1) == 1) {
        i = kotlin.l.b.a.b.h.f.cJ(1, this.aiZC) + 0;
      }
      int j = i;
      if ((this.bitField0_ & 0x2) == 2) {
        j = i + kotlin.l.b.a.b.h.f.cJ(2, this.ajdy);
      }
      i = j + this.aiXZ.size();
      this.dRJ = i;
      AppMethodBeat.o(59104);
      return i;
    }
    
    public final boolean hasName()
    {
      return (this.bitField0_ & 0x1) == 1;
    }
    
    public final boolean isInitialized()
    {
      int i = this.memoizedIsInitialized;
      if (i == 1) {
        return true;
      }
      if (i == 0) {
        return false;
      }
      this.memoizedIsInitialized = 1;
      return true;
    }
    
    public final boolean kxa()
    {
      return (this.bitField0_ & 0x2) == 2;
    }
    
    public final a kxb()
    {
      AppMethodBeat.i(59106);
      a locala = a.kxe().c(this);
      AppMethodBeat.o(59106);
      return locala;
    }
    
    public static final class a
      extends i.a<a.a, a>
      implements b
    {
      private int aiZC;
      private int ajdy;
      private int bitField0_;
      
      /* Error */
      private a B(kotlin.l.b.a.b.h.e parame, g paramg)
      {
        // Byte code:
        //   0: ldc 26
        //   2: invokestatic 32	com/tencent/matrix/trace/core/AppMethodBeat:i	(I)V
        //   5: aconst_null
        //   6: astore_3
        //   7: getstatic 36	kotlin/l/b/a/b/e/c/a$a:aiYa	Lkotlin/l/b/a/b/h/t;
        //   10: aload_1
        //   11: aload_2
        //   12: invokeinterface 41 3 0
        //   17: checkcast 9	kotlin/l/b/a/b/e/c/a$a
        //   20: astore_1
        //   21: aload_1
        //   22: ifnull +9 -> 31
        //   25: aload_0
        //   26: aload_1
        //   27: invokevirtual 45	kotlin/l/b/a/b/e/c/a$a$a:c	(Lkotlin/l/b/a/b/e/c/a$a;)Lkotlin/l/b/a/b/e/c/a$a$a;
        //   30: pop
        //   31: ldc 26
        //   33: invokestatic 48	com/tencent/matrix/trace/core/AppMethodBeat:o	(I)V
        //   36: aload_0
        //   37: areturn
        //   38: astore_1
        //   39: aload_1
        //   40: getfield 52	kotlin/l/b/a/b/h/l:ajfp	Lkotlin/l/b/a/b/h/r;
        //   43: checkcast 9	kotlin/l/b/a/b/e/c/a$a
        //   46: astore_2
        //   47: ldc 26
        //   49: invokestatic 48	com/tencent/matrix/trace/core/AppMethodBeat:o	(I)V
        //   52: aload_1
        //   53: athrow
        //   54: astore_1
        //   55: aload_2
        //   56: ifnull +9 -> 65
        //   59: aload_0
        //   60: aload_2
        //   61: invokevirtual 45	kotlin/l/b/a/b/e/c/a$a$a:c	(Lkotlin/l/b/a/b/e/c/a$a;)Lkotlin/l/b/a/b/e/c/a$a$a;
        //   64: pop
        //   65: ldc 26
        //   67: invokestatic 48	com/tencent/matrix/trace/core/AppMethodBeat:o	(I)V
        //   70: aload_1
        //   71: athrow
        //   72: astore_1
        //   73: aload_3
        //   74: astore_2
        //   75: goto -20 -> 55
        // Local variable table:
        //   start	length	slot	name	signature
        //   0	78	0	this	a
        //   0	78	1	parame	kotlin.l.b.a.b.h.e
        //   0	78	2	paramg	g
        //   6	68	3	localObject	Object
        // Exception table:
        //   from	to	target	type
        //   7	21	38	kotlin/l/b/a/b/h/l
        //   47	54	54	finally
        //   7	21	72	finally
        //   39	47	72	finally
      }
      
      private a aMa(int paramInt)
      {
        this.bitField0_ |= 0x1;
        this.aiZC = paramInt;
        return this;
      }
      
      private a aMb(int paramInt)
      {
        this.bitField0_ |= 0x2;
        this.ajdy = paramInt;
        return this;
      }
      
      private a kxc()
      {
        AppMethodBeat.i(59088);
        a locala = new a().c(kxd());
        AppMethodBeat.o(59088);
        return locala;
      }
      
      public final a c(a.a parama)
      {
        AppMethodBeat.i(59090);
        if (parama == a.a.kwZ())
        {
          AppMethodBeat.o(59090);
          return this;
        }
        if (parama.hasName()) {
          aMa(parama.aiZC);
        }
        if (parama.kxa()) {
          aMb(parama.ajdy);
        }
        this.aiXZ = this.aiXZ.a(a.a.b(parama));
        AppMethodBeat.o(59090);
        return this;
      }
      
      public final boolean isInitialized()
      {
        return true;
      }
      
      public final a.a kxd()
      {
        int i = 1;
        AppMethodBeat.i(59089);
        a.a locala = new a.a(this, (byte)0);
        int k = this.bitField0_;
        if ((k & 0x1) == 1) {}
        for (;;)
        {
          a.a.a(locala, this.aiZC);
          int j = i;
          if ((k & 0x2) == 2) {
            j = i | 0x2;
          }
          a.a.b(locala, this.ajdy);
          a.a.c(locala, j);
          AppMethodBeat.o(59089);
          return locala;
          i = 0;
        }
      }
    }
  }
  
  public static final class b
    extends i
    implements c
  {
    public static t<b> aiYa;
    private static final b ajdz;
    private final kotlin.l.b.a.b.h.d aiXZ;
    public int aiZC;
    public int ajdy;
    private int bitField0_;
    private int dRJ = -1;
    private byte memoizedIsInitialized = -1;
    
    static
    {
      AppMethodBeat.i(59132);
      aiYa = new kotlin.l.b.a.b.h.b() {};
      b localb = new b();
      ajdz = localb;
      localb.ktf();
      AppMethodBeat.o(59132);
    }
    
    private b()
    {
      this.aiXZ = kotlin.l.b.a.b.h.d.ajeU;
    }
    
    /* Error */
    private b(kotlin.l.b.a.b.h.e parame, g paramg)
    {
      // Byte code:
      //   0: aload_0
      //   1: invokespecial 53	kotlin/l/b/a/b/h/i:<init>	()V
      //   4: ldc 70
      //   6: invokestatic 37	com/tencent/matrix/trace/core/AppMethodBeat:i	(I)V
      //   9: aload_0
      //   10: iconst_m1
      //   11: putfield 55	kotlin/l/b/a/b/e/c/a$b:memoizedIsInitialized	B
      //   14: aload_0
      //   15: iconst_m1
      //   16: putfield 57	kotlin/l/b/a/b/e/c/a$b:dRJ	I
      //   19: aload_0
      //   20: invokespecial 48	kotlin/l/b/a/b/e/c/a$b:ktf	()V
      //   23: invokestatic 74	kotlin/l/b/a/b/h/d:kya	()Lkotlin/l/b/a/b/h/d$b;
      //   26: astore 5
      //   28: aload 5
      //   30: iconst_1
      //   31: invokestatic 79	kotlin/l/b/a/b/h/f:i	(Ljava/io/OutputStream;I)Lkotlin/l/b/a/b/h/f;
      //   34: astore 6
      //   36: iconst_0
      //   37: istore_3
      //   38: iload_3
      //   39: ifne +169 -> 208
      //   42: aload_1
      //   43: invokevirtual 85	kotlin/l/b/a/b/h/e:aac	()I
      //   46: istore 4
      //   48: iload 4
      //   50: lookupswitch	default:+242->292, 0:+245->295, 8:+52->102, 16:+112->162
      //   85: aload_1
      //   86: aload 6
      //   88: aload_2
      //   89: iload 4
      //   91: invokevirtual 88	kotlin/l/b/a/b/e/c/a$b:a	(Lkotlin/l/b/a/b/h/e;Lkotlin/l/b/a/b/h/f;Lkotlin/l/b/a/b/h/g;I)Z
      //   94: ifne -56 -> 38
      //   97: iconst_1
      //   98: istore_3
      //   99: goto -61 -> 38
      //   102: aload_0
      //   103: aload_0
      //   104: getfield 90	kotlin/l/b/a/b/e/c/a$b:bitField0_	I
      //   107: iconst_1
      //   108: ior
      //   109: putfield 90	kotlin/l/b/a/b/e/c/a$b:bitField0_	I
      //   112: aload_0
      //   113: aload_1
      //   114: invokevirtual 93	kotlin/l/b/a/b/h/e:aar	()I
      //   117: putfield 95	kotlin/l/b/a/b/e/c/a$b:aiZC	I
      //   120: goto -82 -> 38
      //   123: astore_1
      //   124: aload_1
      //   125: aload_0
      //   126: putfield 99	kotlin/l/b/a/b/h/l:ajfp	Lkotlin/l/b/a/b/h/r;
      //   129: ldc 70
      //   131: invokestatic 51	com/tencent/matrix/trace/core/AppMethodBeat:o	(I)V
      //   134: aload_1
      //   135: athrow
      //   136: astore_1
      //   137: aload 6
      //   139: invokevirtual 102	kotlin/l/b/a/b/h/f:flush	()V
      //   142: aload_0
      //   143: aload 5
      //   145: invokevirtual 108	kotlin/l/b/a/b/h/d$b:kyc	()Lkotlin/l/b/a/b/h/d;
      //   148: putfield 64	kotlin/l/b/a/b/e/c/a$b:aiXZ	Lkotlin/l/b/a/b/h/d;
      //   151: aload_0
      //   152: invokevirtual 111	kotlin/l/b/a/b/e/c/a$b:makeExtensionsImmutable	()V
      //   155: ldc 70
      //   157: invokestatic 51	com/tencent/matrix/trace/core/AppMethodBeat:o	(I)V
      //   160: aload_1
      //   161: athrow
      //   162: aload_0
      //   163: aload_0
      //   164: getfield 90	kotlin/l/b/a/b/e/c/a$b:bitField0_	I
      //   167: iconst_2
      //   168: ior
      //   169: putfield 90	kotlin/l/b/a/b/e/c/a$b:bitField0_	I
      //   172: aload_0
      //   173: aload_1
      //   174: invokevirtual 93	kotlin/l/b/a/b/h/e:aar	()I
      //   177: putfield 113	kotlin/l/b/a/b/e/c/a$b:ajdy	I
      //   180: goto -142 -> 38
      //   183: astore_1
      //   184: new 67	kotlin/l/b/a/b/h/l
      //   187: dup
      //   188: aload_1
      //   189: invokevirtual 117	java/io/IOException:getMessage	()Ljava/lang/String;
      //   192: invokespecial 120	kotlin/l/b/a/b/h/l:<init>	(Ljava/lang/String;)V
      //   195: astore_1
      //   196: aload_1
      //   197: aload_0
      //   198: putfield 99	kotlin/l/b/a/b/h/l:ajfp	Lkotlin/l/b/a/b/h/r;
      //   201: ldc 70
      //   203: invokestatic 51	com/tencent/matrix/trace/core/AppMethodBeat:o	(I)V
      //   206: aload_1
      //   207: athrow
      //   208: aload 6
      //   210: invokevirtual 102	kotlin/l/b/a/b/h/f:flush	()V
      //   213: aload_0
      //   214: aload 5
      //   216: invokevirtual 108	kotlin/l/b/a/b/h/d$b:kyc	()Lkotlin/l/b/a/b/h/d;
      //   219: putfield 64	kotlin/l/b/a/b/e/c/a$b:aiXZ	Lkotlin/l/b/a/b/h/d;
      //   222: aload_0
      //   223: invokevirtual 111	kotlin/l/b/a/b/e/c/a$b:makeExtensionsImmutable	()V
      //   226: ldc 70
      //   228: invokestatic 51	com/tencent/matrix/trace/core/AppMethodBeat:o	(I)V
      //   231: return
      //   232: astore_1
      //   233: aload_0
      //   234: aload 5
      //   236: invokevirtual 108	kotlin/l/b/a/b/h/d$b:kyc	()Lkotlin/l/b/a/b/h/d;
      //   239: putfield 64	kotlin/l/b/a/b/e/c/a$b:aiXZ	Lkotlin/l/b/a/b/h/d;
      //   242: goto -20 -> 222
      //   245: astore_1
      //   246: aload_0
      //   247: aload 5
      //   249: invokevirtual 108	kotlin/l/b/a/b/h/d$b:kyc	()Lkotlin/l/b/a/b/h/d;
      //   252: putfield 64	kotlin/l/b/a/b/e/c/a$b:aiXZ	Lkotlin/l/b/a/b/h/d;
      //   255: ldc 70
      //   257: invokestatic 51	com/tencent/matrix/trace/core/AppMethodBeat:o	(I)V
      //   260: aload_1
      //   261: athrow
      //   262: astore_2
      //   263: aload_0
      //   264: aload 5
      //   266: invokevirtual 108	kotlin/l/b/a/b/h/d$b:kyc	()Lkotlin/l/b/a/b/h/d;
      //   269: putfield 64	kotlin/l/b/a/b/e/c/a$b:aiXZ	Lkotlin/l/b/a/b/h/d;
      //   272: goto -121 -> 151
      //   275: astore_1
      //   276: aload_0
      //   277: aload 5
      //   279: invokevirtual 108	kotlin/l/b/a/b/h/d$b:kyc	()Lkotlin/l/b/a/b/h/d;
      //   282: putfield 64	kotlin/l/b/a/b/e/c/a$b:aiXZ	Lkotlin/l/b/a/b/h/d;
      //   285: ldc 70
      //   287: invokestatic 51	com/tencent/matrix/trace/core/AppMethodBeat:o	(I)V
      //   290: aload_1
      //   291: athrow
      //   292: goto -208 -> 84
      //   295: iconst_1
      //   296: istore_3
      //   297: goto -259 -> 38
      // Local variable table:
      //   start	length	slot	name	signature
      //   0	300	0	this	b
      //   0	300	1	parame	kotlin.l.b.a.b.h.e
      //   0	300	2	paramg	g
      //   37	260	3	i	int
      //   46	44	4	j	int
      //   26	252	5	localb	kotlin.l.b.a.b.h.d.b
      //   34	175	6	localf	kotlin.l.b.a.b.h.f
      // Exception table:
      //   from	to	target	type
      //   42	48	123	kotlin/l/b/a/b/h/l
      //   84	97	123	kotlin/l/b/a/b/h/l
      //   102	120	123	kotlin/l/b/a/b/h/l
      //   162	180	123	kotlin/l/b/a/b/h/l
      //   42	48	136	finally
      //   84	97	136	finally
      //   102	120	136	finally
      //   124	136	136	finally
      //   162	180	136	finally
      //   184	208	136	finally
      //   42	48	183	java/io/IOException
      //   84	97	183	java/io/IOException
      //   102	120	183	java/io/IOException
      //   162	180	183	java/io/IOException
      //   208	213	232	java/io/IOException
      //   208	213	245	finally
      //   137	142	262	java/io/IOException
      //   137	142	275	finally
    }
    
    private b(i.a parama)
    {
      super();
      this.aiXZ = parama.aiXZ;
    }
    
    public static a a(b paramb)
    {
      AppMethodBeat.i(59128);
      paramb = a.kxj().c(paramb);
      AppMethodBeat.o(59128);
      return paramb;
    }
    
    private void ktf()
    {
      this.aiZC = 0;
      this.ajdy = 0;
    }
    
    public static b kxf()
    {
      return ajdz;
    }
    
    public final void a(kotlin.l.b.a.b.h.f paramf)
    {
      AppMethodBeat.i(59126);
      getSerializedSize();
      if ((this.bitField0_ & 0x1) == 1) {
        paramf.cF(1, this.aiZC);
      }
      if ((this.bitField0_ & 0x2) == 2) {
        paramf.cF(2, this.ajdy);
      }
      paramf.e(this.aiXZ);
      AppMethodBeat.o(59126);
    }
    
    public final int getSerializedSize()
    {
      AppMethodBeat.i(59127);
      int i = this.dRJ;
      if (i != -1)
      {
        AppMethodBeat.o(59127);
        return i;
      }
      i = 0;
      if ((this.bitField0_ & 0x1) == 1) {
        i = kotlin.l.b.a.b.h.f.cJ(1, this.aiZC) + 0;
      }
      int j = i;
      if ((this.bitField0_ & 0x2) == 2) {
        j = i + kotlin.l.b.a.b.h.f.cJ(2, this.ajdy);
      }
      i = j + this.aiXZ.size();
      this.dRJ = i;
      AppMethodBeat.o(59127);
      return i;
    }
    
    public final boolean hasName()
    {
      return (this.bitField0_ & 0x1) == 1;
    }
    
    public final boolean isInitialized()
    {
      int i = this.memoizedIsInitialized;
      if (i == 1) {
        return true;
      }
      if (i == 0) {
        return false;
      }
      this.memoizedIsInitialized = 1;
      return true;
    }
    
    public final boolean kxa()
    {
      return (this.bitField0_ & 0x2) == 2;
    }
    
    public final a kxg()
    {
      AppMethodBeat.i(59129);
      a locala = a.kxj().c(this);
      AppMethodBeat.o(59129);
      return locala;
    }
    
    public static final class a
      extends i.a<a.b, a>
      implements c
    {
      private int aiZC;
      private int ajdy;
      private int bitField0_;
      
      /* Error */
      private a C(kotlin.l.b.a.b.h.e parame, g paramg)
      {
        // Byte code:
        //   0: ldc 27
        //   2: invokestatic 33	com/tencent/matrix/trace/core/AppMethodBeat:i	(I)V
        //   5: aconst_null
        //   6: astore_3
        //   7: getstatic 37	kotlin/l/b/a/b/e/c/a$b:aiYa	Lkotlin/l/b/a/b/h/t;
        //   10: aload_1
        //   11: aload_2
        //   12: invokeinterface 42 3 0
        //   17: checkcast 9	kotlin/l/b/a/b/e/c/a$b
        //   20: astore_1
        //   21: aload_1
        //   22: ifnull +9 -> 31
        //   25: aload_0
        //   26: aload_1
        //   27: invokevirtual 46	kotlin/l/b/a/b/e/c/a$b$a:c	(Lkotlin/l/b/a/b/e/c/a$b;)Lkotlin/l/b/a/b/e/c/a$b$a;
        //   30: pop
        //   31: ldc 27
        //   33: invokestatic 49	com/tencent/matrix/trace/core/AppMethodBeat:o	(I)V
        //   36: aload_0
        //   37: areturn
        //   38: astore_1
        //   39: aload_1
        //   40: getfield 53	kotlin/l/b/a/b/h/l:ajfp	Lkotlin/l/b/a/b/h/r;
        //   43: checkcast 9	kotlin/l/b/a/b/e/c/a$b
        //   46: astore_2
        //   47: ldc 27
        //   49: invokestatic 49	com/tencent/matrix/trace/core/AppMethodBeat:o	(I)V
        //   52: aload_1
        //   53: athrow
        //   54: astore_1
        //   55: aload_2
        //   56: ifnull +9 -> 65
        //   59: aload_0
        //   60: aload_2
        //   61: invokevirtual 46	kotlin/l/b/a/b/e/c/a$b$a:c	(Lkotlin/l/b/a/b/e/c/a$b;)Lkotlin/l/b/a/b/e/c/a$b$a;
        //   64: pop
        //   65: ldc 27
        //   67: invokestatic 49	com/tencent/matrix/trace/core/AppMethodBeat:o	(I)V
        //   70: aload_1
        //   71: athrow
        //   72: astore_1
        //   73: aload_3
        //   74: astore_2
        //   75: goto -20 -> 55
        // Local variable table:
        //   start	length	slot	name	signature
        //   0	78	0	this	a
        //   0	78	1	parame	kotlin.l.b.a.b.h.e
        //   0	78	2	paramg	g
        //   6	68	3	localObject	Object
        // Exception table:
        //   from	to	target	type
        //   7	21	38	kotlin/l/b/a/b/h/l
        //   47	54	54	finally
        //   7	21	72	finally
        //   39	47	72	finally
      }
      
      private a aMc(int paramInt)
      {
        this.bitField0_ |= 0x1;
        this.aiZC = paramInt;
        return this;
      }
      
      private a aMd(int paramInt)
      {
        this.bitField0_ |= 0x2;
        this.ajdy = paramInt;
        return this;
      }
      
      private a kxh()
      {
        AppMethodBeat.i(59111);
        a locala = new a().c(kxi());
        AppMethodBeat.o(59111);
        return locala;
      }
      
      public final a c(a.b paramb)
      {
        AppMethodBeat.i(59113);
        if (paramb == a.b.kxf())
        {
          AppMethodBeat.o(59113);
          return this;
        }
        if (paramb.hasName()) {
          aMc(paramb.aiZC);
        }
        if (paramb.kxa()) {
          aMd(paramb.ajdy);
        }
        this.aiXZ = this.aiXZ.a(a.b.b(paramb));
        AppMethodBeat.o(59113);
        return this;
      }
      
      public final boolean isInitialized()
      {
        return true;
      }
      
      public final a.b kxi()
      {
        int i = 1;
        AppMethodBeat.i(59112);
        a.b localb = new a.b(this, (byte)0);
        int k = this.bitField0_;
        if ((k & 0x1) == 1) {}
        for (;;)
        {
          a.b.a(localb, this.aiZC);
          int j = i;
          if ((k & 0x2) == 2) {
            j = i | 0x2;
          }
          a.b.b(localb, this.ajdy);
          a.b.c(localb, j);
          AppMethodBeat.o(59112);
          return localb;
          i = 0;
        }
      }
    }
  }
  
  public static final class c
    extends i
    implements d
  {
    public static t<c> aiYa;
    private static final c ajdA;
    private final kotlin.l.b.a.b.h.d aiXZ;
    public a.a ajdB;
    public a.b ajdC;
    public a.b ajdD;
    public a.b ajdE;
    private int bitField0_;
    private int dRJ = -1;
    private byte memoizedIsInitialized = -1;
    
    static
    {
      AppMethodBeat.i(59159);
      aiYa = new kotlin.l.b.a.b.h.b() {};
      c localc = new c();
      ajdA = localc;
      localc.ktf();
      AppMethodBeat.o(59159);
    }
    
    private c()
    {
      this.aiXZ = kotlin.l.b.a.b.h.d.ajeU;
    }
    
    /* Error */
    private c(kotlin.l.b.a.b.h.e parame, g paramg)
    {
      // Byte code:
      //   0: aload_0
      //   1: invokespecial 57	kotlin/l/b/a/b/h/i:<init>	()V
      //   4: ldc 74
      //   6: invokestatic 41	com/tencent/matrix/trace/core/AppMethodBeat:i	(I)V
      //   9: aload_0
      //   10: iconst_m1
      //   11: putfield 59	kotlin/l/b/a/b/e/c/a$c:memoizedIsInitialized	B
      //   14: aload_0
      //   15: iconst_m1
      //   16: putfield 61	kotlin/l/b/a/b/e/c/a$c:dRJ	I
      //   19: aload_0
      //   20: invokespecial 52	kotlin/l/b/a/b/e/c/a$c:ktf	()V
      //   23: invokestatic 78	kotlin/l/b/a/b/h/d:kya	()Lkotlin/l/b/a/b/h/d$b;
      //   26: astore 6
      //   28: aload 6
      //   30: iconst_1
      //   31: invokestatic 83	kotlin/l/b/a/b/h/f:i	(Ljava/io/OutputStream;I)Lkotlin/l/b/a/b/h/f;
      //   34: astore 7
      //   36: iconst_0
      //   37: istore_3
      //   38: iload_3
      //   39: ifne +430 -> 469
      //   42: aload_1
      //   43: invokevirtual 89	kotlin/l/b/a/b/h/e:aac	()I
      //   46: istore 4
      //   48: iload 4
      //   50: lookupswitch	default:+527->577, 0:+530->580, 10:+68->118, 18:+178->228, 26:+274->324, 34:+345->395
      //   101: aload_1
      //   102: aload 7
      //   104: aload_2
      //   105: iload 4
      //   107: invokevirtual 92	kotlin/l/b/a/b/e/c/a$c:a	(Lkotlin/l/b/a/b/h/e;Lkotlin/l/b/a/b/h/f;Lkotlin/l/b/a/b/h/g;I)Z
      //   110: ifne -72 -> 38
      //   113: iconst_1
      //   114: istore_3
      //   115: goto -77 -> 38
      //   118: aload_0
      //   119: getfield 94	kotlin/l/b/a/b/e/c/a$c:bitField0_	I
      //   122: iconst_1
      //   123: iand
      //   124: iconst_1
      //   125: if_icmpne +446 -> 571
      //   128: aload_0
      //   129: getfield 96	kotlin/l/b/a/b/e/c/a$c:ajdB	Lkotlin/l/b/a/b/e/c/a$a;
      //   132: invokevirtual 102	kotlin/l/b/a/b/e/c/a$a:kxb	()Lkotlin/l/b/a/b/e/c/a$a$a;
      //   135: astore 5
      //   137: aload_0
      //   138: aload_1
      //   139: getstatic 103	kotlin/l/b/a/b/e/c/a$a:aiYa	Lkotlin/l/b/a/b/h/t;
      //   142: aload_2
      //   143: invokevirtual 106	kotlin/l/b/a/b/h/e:a	(Lkotlin/l/b/a/b/h/t;Lkotlin/l/b/a/b/h/g;)Lkotlin/l/b/a/b/h/r;
      //   146: checkcast 98	kotlin/l/b/a/b/e/c/a$a
      //   149: putfield 96	kotlin/l/b/a/b/e/c/a$c:ajdB	Lkotlin/l/b/a/b/e/c/a$a;
      //   152: aload 5
      //   154: ifnull +22 -> 176
      //   157: aload 5
      //   159: aload_0
      //   160: getfield 96	kotlin/l/b/a/b/e/c/a$c:ajdB	Lkotlin/l/b/a/b/e/c/a$a;
      //   163: invokevirtual 111	kotlin/l/b/a/b/e/c/a$a$a:c	(Lkotlin/l/b/a/b/e/c/a$a;)Lkotlin/l/b/a/b/e/c/a$a$a;
      //   166: pop
      //   167: aload_0
      //   168: aload 5
      //   170: invokevirtual 115	kotlin/l/b/a/b/e/c/a$a$a:kxd	()Lkotlin/l/b/a/b/e/c/a$a;
      //   173: putfield 96	kotlin/l/b/a/b/e/c/a$c:ajdB	Lkotlin/l/b/a/b/e/c/a$a;
      //   176: aload_0
      //   177: aload_0
      //   178: getfield 94	kotlin/l/b/a/b/e/c/a$c:bitField0_	I
      //   181: iconst_1
      //   182: ior
      //   183: putfield 94	kotlin/l/b/a/b/e/c/a$c:bitField0_	I
      //   186: goto -148 -> 38
      //   189: astore_1
      //   190: aload_1
      //   191: aload_0
      //   192: putfield 119	kotlin/l/b/a/b/h/l:ajfp	Lkotlin/l/b/a/b/h/r;
      //   195: ldc 74
      //   197: invokestatic 55	com/tencent/matrix/trace/core/AppMethodBeat:o	(I)V
      //   200: aload_1
      //   201: athrow
      //   202: astore_1
      //   203: aload 7
      //   205: invokevirtual 122	kotlin/l/b/a/b/h/f:flush	()V
      //   208: aload_0
      //   209: aload 6
      //   211: invokevirtual 128	kotlin/l/b/a/b/h/d$b:kyc	()Lkotlin/l/b/a/b/h/d;
      //   214: putfield 68	kotlin/l/b/a/b/e/c/a$c:aiXZ	Lkotlin/l/b/a/b/h/d;
      //   217: aload_0
      //   218: invokevirtual 131	kotlin/l/b/a/b/e/c/a$c:makeExtensionsImmutable	()V
      //   221: ldc 74
      //   223: invokestatic 55	com/tencent/matrix/trace/core/AppMethodBeat:o	(I)V
      //   226: aload_1
      //   227: athrow
      //   228: aload_0
      //   229: getfield 94	kotlin/l/b/a/b/e/c/a$c:bitField0_	I
      //   232: iconst_2
      //   233: iand
      //   234: iconst_2
      //   235: if_icmpne +330 -> 565
      //   238: aload_0
      //   239: getfield 133	kotlin/l/b/a/b/e/c/a$c:ajdC	Lkotlin/l/b/a/b/e/c/a$b;
      //   242: invokevirtual 139	kotlin/l/b/a/b/e/c/a$b:kxg	()Lkotlin/l/b/a/b/e/c/a$b$a;
      //   245: astore 5
      //   247: aload_0
      //   248: aload_1
      //   249: getstatic 140	kotlin/l/b/a/b/e/c/a$b:aiYa	Lkotlin/l/b/a/b/h/t;
      //   252: aload_2
      //   253: invokevirtual 106	kotlin/l/b/a/b/h/e:a	(Lkotlin/l/b/a/b/h/t;Lkotlin/l/b/a/b/h/g;)Lkotlin/l/b/a/b/h/r;
      //   256: checkcast 135	kotlin/l/b/a/b/e/c/a$b
      //   259: putfield 133	kotlin/l/b/a/b/e/c/a$c:ajdC	Lkotlin/l/b/a/b/e/c/a$b;
      //   262: aload 5
      //   264: ifnull +22 -> 286
      //   267: aload 5
      //   269: aload_0
      //   270: getfield 133	kotlin/l/b/a/b/e/c/a$c:ajdC	Lkotlin/l/b/a/b/e/c/a$b;
      //   273: invokevirtual 145	kotlin/l/b/a/b/e/c/a$b$a:c	(Lkotlin/l/b/a/b/e/c/a$b;)Lkotlin/l/b/a/b/e/c/a$b$a;
      //   276: pop
      //   277: aload_0
      //   278: aload 5
      //   280: invokevirtual 149	kotlin/l/b/a/b/e/c/a$b$a:kxi	()Lkotlin/l/b/a/b/e/c/a$b;
      //   283: putfield 133	kotlin/l/b/a/b/e/c/a$c:ajdC	Lkotlin/l/b/a/b/e/c/a$b;
      //   286: aload_0
      //   287: aload_0
      //   288: getfield 94	kotlin/l/b/a/b/e/c/a$c:bitField0_	I
      //   291: iconst_2
      //   292: ior
      //   293: putfield 94	kotlin/l/b/a/b/e/c/a$c:bitField0_	I
      //   296: goto -258 -> 38
      //   299: astore_1
      //   300: new 71	kotlin/l/b/a/b/h/l
      //   303: dup
      //   304: aload_1
      //   305: invokevirtual 153	java/io/IOException:getMessage	()Ljava/lang/String;
      //   308: invokespecial 156	kotlin/l/b/a/b/h/l:<init>	(Ljava/lang/String;)V
      //   311: astore_1
      //   312: aload_1
      //   313: aload_0
      //   314: putfield 119	kotlin/l/b/a/b/h/l:ajfp	Lkotlin/l/b/a/b/h/r;
      //   317: ldc 74
      //   319: invokestatic 55	com/tencent/matrix/trace/core/AppMethodBeat:o	(I)V
      //   322: aload_1
      //   323: athrow
      //   324: aload_0
      //   325: getfield 94	kotlin/l/b/a/b/e/c/a$c:bitField0_	I
      //   328: iconst_4
      //   329: iand
      //   330: iconst_4
      //   331: if_icmpne +228 -> 559
      //   334: aload_0
      //   335: getfield 158	kotlin/l/b/a/b/e/c/a$c:ajdD	Lkotlin/l/b/a/b/e/c/a$b;
      //   338: invokevirtual 139	kotlin/l/b/a/b/e/c/a$b:kxg	()Lkotlin/l/b/a/b/e/c/a$b$a;
      //   341: astore 5
      //   343: aload_0
      //   344: aload_1
      //   345: getstatic 140	kotlin/l/b/a/b/e/c/a$b:aiYa	Lkotlin/l/b/a/b/h/t;
      //   348: aload_2
      //   349: invokevirtual 106	kotlin/l/b/a/b/h/e:a	(Lkotlin/l/b/a/b/h/t;Lkotlin/l/b/a/b/h/g;)Lkotlin/l/b/a/b/h/r;
      //   352: checkcast 135	kotlin/l/b/a/b/e/c/a$b
      //   355: putfield 158	kotlin/l/b/a/b/e/c/a$c:ajdD	Lkotlin/l/b/a/b/e/c/a$b;
      //   358: aload 5
      //   360: ifnull +22 -> 382
      //   363: aload 5
      //   365: aload_0
      //   366: getfield 158	kotlin/l/b/a/b/e/c/a$c:ajdD	Lkotlin/l/b/a/b/e/c/a$b;
      //   369: invokevirtual 145	kotlin/l/b/a/b/e/c/a$b$a:c	(Lkotlin/l/b/a/b/e/c/a$b;)Lkotlin/l/b/a/b/e/c/a$b$a;
      //   372: pop
      //   373: aload_0
      //   374: aload 5
      //   376: invokevirtual 149	kotlin/l/b/a/b/e/c/a$b$a:kxi	()Lkotlin/l/b/a/b/e/c/a$b;
      //   379: putfield 158	kotlin/l/b/a/b/e/c/a$c:ajdD	Lkotlin/l/b/a/b/e/c/a$b;
      //   382: aload_0
      //   383: aload_0
      //   384: getfield 94	kotlin/l/b/a/b/e/c/a$c:bitField0_	I
      //   387: iconst_4
      //   388: ior
      //   389: putfield 94	kotlin/l/b/a/b/e/c/a$c:bitField0_	I
      //   392: goto -354 -> 38
      //   395: aload_0
      //   396: getfield 94	kotlin/l/b/a/b/e/c/a$c:bitField0_	I
      //   399: bipush 8
      //   401: iand
      //   402: bipush 8
      //   404: if_icmpne +149 -> 553
      //   407: aload_0
      //   408: getfield 160	kotlin/l/b/a/b/e/c/a$c:ajdE	Lkotlin/l/b/a/b/e/c/a$b;
      //   411: invokevirtual 139	kotlin/l/b/a/b/e/c/a$b:kxg	()Lkotlin/l/b/a/b/e/c/a$b$a;
      //   414: astore 5
      //   416: aload_0
      //   417: aload_1
      //   418: getstatic 140	kotlin/l/b/a/b/e/c/a$b:aiYa	Lkotlin/l/b/a/b/h/t;
      //   421: aload_2
      //   422: invokevirtual 106	kotlin/l/b/a/b/h/e:a	(Lkotlin/l/b/a/b/h/t;Lkotlin/l/b/a/b/h/g;)Lkotlin/l/b/a/b/h/r;
      //   425: checkcast 135	kotlin/l/b/a/b/e/c/a$b
      //   428: putfield 160	kotlin/l/b/a/b/e/c/a$c:ajdE	Lkotlin/l/b/a/b/e/c/a$b;
      //   431: aload 5
      //   433: ifnull +22 -> 455
      //   436: aload 5
      //   438: aload_0
      //   439: getfield 160	kotlin/l/b/a/b/e/c/a$c:ajdE	Lkotlin/l/b/a/b/e/c/a$b;
      //   442: invokevirtual 145	kotlin/l/b/a/b/e/c/a$b$a:c	(Lkotlin/l/b/a/b/e/c/a$b;)Lkotlin/l/b/a/b/e/c/a$b$a;
      //   445: pop
      //   446: aload_0
      //   447: aload 5
      //   449: invokevirtual 149	kotlin/l/b/a/b/e/c/a$b$a:kxi	()Lkotlin/l/b/a/b/e/c/a$b;
      //   452: putfield 160	kotlin/l/b/a/b/e/c/a$c:ajdE	Lkotlin/l/b/a/b/e/c/a$b;
      //   455: aload_0
      //   456: aload_0
      //   457: getfield 94	kotlin/l/b/a/b/e/c/a$c:bitField0_	I
      //   460: bipush 8
      //   462: ior
      //   463: putfield 94	kotlin/l/b/a/b/e/c/a$c:bitField0_	I
      //   466: goto -428 -> 38
      //   469: aload 7
      //   471: invokevirtual 122	kotlin/l/b/a/b/h/f:flush	()V
      //   474: aload_0
      //   475: aload 6
      //   477: invokevirtual 128	kotlin/l/b/a/b/h/d$b:kyc	()Lkotlin/l/b/a/b/h/d;
      //   480: putfield 68	kotlin/l/b/a/b/e/c/a$c:aiXZ	Lkotlin/l/b/a/b/h/d;
      //   483: aload_0
      //   484: invokevirtual 131	kotlin/l/b/a/b/e/c/a$c:makeExtensionsImmutable	()V
      //   487: ldc 74
      //   489: invokestatic 55	com/tencent/matrix/trace/core/AppMethodBeat:o	(I)V
      //   492: return
      //   493: astore_1
      //   494: aload_0
      //   495: aload 6
      //   497: invokevirtual 128	kotlin/l/b/a/b/h/d$b:kyc	()Lkotlin/l/b/a/b/h/d;
      //   500: putfield 68	kotlin/l/b/a/b/e/c/a$c:aiXZ	Lkotlin/l/b/a/b/h/d;
      //   503: goto -20 -> 483
      //   506: astore_1
      //   507: aload_0
      //   508: aload 6
      //   510: invokevirtual 128	kotlin/l/b/a/b/h/d$b:kyc	()Lkotlin/l/b/a/b/h/d;
      //   513: putfield 68	kotlin/l/b/a/b/e/c/a$c:aiXZ	Lkotlin/l/b/a/b/h/d;
      //   516: ldc 74
      //   518: invokestatic 55	com/tencent/matrix/trace/core/AppMethodBeat:o	(I)V
      //   521: aload_1
      //   522: athrow
      //   523: astore_2
      //   524: aload_0
      //   525: aload 6
      //   527: invokevirtual 128	kotlin/l/b/a/b/h/d$b:kyc	()Lkotlin/l/b/a/b/h/d;
      //   530: putfield 68	kotlin/l/b/a/b/e/c/a$c:aiXZ	Lkotlin/l/b/a/b/h/d;
      //   533: goto -316 -> 217
      //   536: astore_1
      //   537: aload_0
      //   538: aload 6
      //   540: invokevirtual 128	kotlin/l/b/a/b/h/d$b:kyc	()Lkotlin/l/b/a/b/h/d;
      //   543: putfield 68	kotlin/l/b/a/b/e/c/a$c:aiXZ	Lkotlin/l/b/a/b/h/d;
      //   546: ldc 74
      //   548: invokestatic 55	com/tencent/matrix/trace/core/AppMethodBeat:o	(I)V
      //   551: aload_1
      //   552: athrow
      //   553: aconst_null
      //   554: astore 5
      //   556: goto -140 -> 416
      //   559: aconst_null
      //   560: astore 5
      //   562: goto -219 -> 343
      //   565: aconst_null
      //   566: astore 5
      //   568: goto -321 -> 247
      //   571: aconst_null
      //   572: astore 5
      //   574: goto -437 -> 137
      //   577: goto -477 -> 100
      //   580: iconst_1
      //   581: istore_3
      //   582: goto -544 -> 38
      // Local variable table:
      //   start	length	slot	name	signature
      //   0	585	0	this	c
      //   0	585	1	parame	kotlin.l.b.a.b.h.e
      //   0	585	2	paramg	g
      //   37	545	3	i	int
      //   46	60	4	j	int
      //   135	438	5	localObject	Object
      //   26	513	6	localb	kotlin.l.b.a.b.h.d.b
      //   34	436	7	localf	kotlin.l.b.a.b.h.f
      // Exception table:
      //   from	to	target	type
      //   42	48	189	kotlin/l/b/a/b/h/l
      //   100	113	189	kotlin/l/b/a/b/h/l
      //   118	137	189	kotlin/l/b/a/b/h/l
      //   137	152	189	kotlin/l/b/a/b/h/l
      //   157	176	189	kotlin/l/b/a/b/h/l
      //   176	186	189	kotlin/l/b/a/b/h/l
      //   228	247	189	kotlin/l/b/a/b/h/l
      //   247	262	189	kotlin/l/b/a/b/h/l
      //   267	286	189	kotlin/l/b/a/b/h/l
      //   286	296	189	kotlin/l/b/a/b/h/l
      //   324	343	189	kotlin/l/b/a/b/h/l
      //   343	358	189	kotlin/l/b/a/b/h/l
      //   363	382	189	kotlin/l/b/a/b/h/l
      //   382	392	189	kotlin/l/b/a/b/h/l
      //   395	416	189	kotlin/l/b/a/b/h/l
      //   416	431	189	kotlin/l/b/a/b/h/l
      //   436	455	189	kotlin/l/b/a/b/h/l
      //   455	466	189	kotlin/l/b/a/b/h/l
      //   42	48	202	finally
      //   100	113	202	finally
      //   118	137	202	finally
      //   137	152	202	finally
      //   157	176	202	finally
      //   176	186	202	finally
      //   190	202	202	finally
      //   228	247	202	finally
      //   247	262	202	finally
      //   267	286	202	finally
      //   286	296	202	finally
      //   300	324	202	finally
      //   324	343	202	finally
      //   343	358	202	finally
      //   363	382	202	finally
      //   382	392	202	finally
      //   395	416	202	finally
      //   416	431	202	finally
      //   436	455	202	finally
      //   455	466	202	finally
      //   42	48	299	java/io/IOException
      //   100	113	299	java/io/IOException
      //   118	137	299	java/io/IOException
      //   137	152	299	java/io/IOException
      //   157	176	299	java/io/IOException
      //   176	186	299	java/io/IOException
      //   228	247	299	java/io/IOException
      //   247	262	299	java/io/IOException
      //   267	286	299	java/io/IOException
      //   286	296	299	java/io/IOException
      //   324	343	299	java/io/IOException
      //   343	358	299	java/io/IOException
      //   363	382	299	java/io/IOException
      //   382	392	299	java/io/IOException
      //   395	416	299	java/io/IOException
      //   416	431	299	java/io/IOException
      //   436	455	299	java/io/IOException
      //   455	466	299	java/io/IOException
      //   469	474	493	java/io/IOException
      //   469	474	506	finally
      //   203	208	523	java/io/IOException
      //   203	208	536	finally
    }
    
    private c(i.a parama)
    {
      super();
      this.aiXZ = parama.aiXZ;
    }
    
    private void ktf()
    {
      AppMethodBeat.i(59154);
      this.ajdB = a.a.kwZ();
      this.ajdC = a.b.kxf();
      this.ajdD = a.b.kxf();
      this.ajdE = a.b.kxf();
      AppMethodBeat.o(59154);
    }
    
    public static c kxk()
    {
      return ajdA;
    }
    
    public final void a(kotlin.l.b.a.b.h.f paramf)
    {
      AppMethodBeat.i(59155);
      getSerializedSize();
      if ((this.bitField0_ & 0x1) == 1) {
        paramf.a(1, this.ajdB);
      }
      if ((this.bitField0_ & 0x2) == 2) {
        paramf.a(2, this.ajdC);
      }
      if ((this.bitField0_ & 0x4) == 4) {
        paramf.a(3, this.ajdD);
      }
      if ((this.bitField0_ & 0x8) == 8) {
        paramf.a(4, this.ajdE);
      }
      paramf.e(this.aiXZ);
      AppMethodBeat.o(59155);
    }
    
    public final int getSerializedSize()
    {
      AppMethodBeat.i(59156);
      int i = this.dRJ;
      if (i != -1)
      {
        AppMethodBeat.o(59156);
        return i;
      }
      int j = 0;
      if ((this.bitField0_ & 0x1) == 1) {
        j = kotlin.l.b.a.b.h.f.c(1, this.ajdB) + 0;
      }
      i = j;
      if ((this.bitField0_ & 0x2) == 2) {
        i = j + kotlin.l.b.a.b.h.f.c(2, this.ajdC);
      }
      j = i;
      if ((this.bitField0_ & 0x4) == 4) {
        j = i + kotlin.l.b.a.b.h.f.c(3, this.ajdD);
      }
      i = j;
      if ((this.bitField0_ & 0x8) == 8) {
        i = j + kotlin.l.b.a.b.h.f.c(4, this.ajdE);
      }
      i += this.aiXZ.size();
      this.dRJ = i;
      AppMethodBeat.o(59156);
      return i;
    }
    
    public final boolean isInitialized()
    {
      int i = this.memoizedIsInitialized;
      if (i == 1) {
        return true;
      }
      if (i == 0) {
        return false;
      }
      this.memoizedIsInitialized = 1;
      return true;
    }
    
    public final boolean kxl()
    {
      return (this.bitField0_ & 0x1) == 1;
    }
    
    public final boolean kxm()
    {
      return (this.bitField0_ & 0x2) == 2;
    }
    
    public final boolean kxn()
    {
      return (this.bitField0_ & 0x4) == 4;
    }
    
    public final boolean kxo()
    {
      return (this.bitField0_ & 0x8) == 8;
    }
    
    public static final class a
      extends i.a<a.c, a>
      implements d
    {
      private a.a ajdB;
      private a.b ajdC;
      private a.b ajdD;
      private a.b ajdE;
      private int bitField0_;
      
      private a()
      {
        AppMethodBeat.i(59134);
        this.ajdB = a.a.kwZ();
        this.ajdC = a.b.kxf();
        this.ajdD = a.b.kxf();
        this.ajdE = a.b.kxf();
        AppMethodBeat.o(59134);
      }
      
      /* Error */
      private a D(kotlin.l.b.a.b.h.e parame, g paramg)
      {
        // Byte code:
        //   0: ldc 61
        //   2: invokestatic 32	com/tencent/matrix/trace/core/AppMethodBeat:i	(I)V
        //   5: aconst_null
        //   6: astore_3
        //   7: getstatic 65	kotlin/l/b/a/b/e/c/a$c:aiYa	Lkotlin/l/b/a/b/h/t;
        //   10: aload_1
        //   11: aload_2
        //   12: invokeinterface 70 3 0
        //   17: checkcast 9	kotlin/l/b/a/b/e/c/a$c
        //   20: astore_1
        //   21: aload_1
        //   22: ifnull +9 -> 31
        //   25: aload_0
        //   26: aload_1
        //   27: invokevirtual 74	kotlin/l/b/a/b/e/c/a$c$a:b	(Lkotlin/l/b/a/b/e/c/a$c;)Lkotlin/l/b/a/b/e/c/a$c$a;
        //   30: pop
        //   31: ldc 61
        //   33: invokestatic 55	com/tencent/matrix/trace/core/AppMethodBeat:o	(I)V
        //   36: aload_0
        //   37: areturn
        //   38: astore_1
        //   39: aload_1
        //   40: getfield 78	kotlin/l/b/a/b/h/l:ajfp	Lkotlin/l/b/a/b/h/r;
        //   43: checkcast 9	kotlin/l/b/a/b/e/c/a$c
        //   46: astore_2
        //   47: ldc 61
        //   49: invokestatic 55	com/tencent/matrix/trace/core/AppMethodBeat:o	(I)V
        //   52: aload_1
        //   53: athrow
        //   54: astore_1
        //   55: aload_2
        //   56: ifnull +9 -> 65
        //   59: aload_0
        //   60: aload_2
        //   61: invokevirtual 74	kotlin/l/b/a/b/e/c/a$c$a:b	(Lkotlin/l/b/a/b/e/c/a$c;)Lkotlin/l/b/a/b/e/c/a$c$a;
        //   64: pop
        //   65: ldc 61
        //   67: invokestatic 55	com/tencent/matrix/trace/core/AppMethodBeat:o	(I)V
        //   70: aload_1
        //   71: athrow
        //   72: astore_1
        //   73: aload_3
        //   74: astore_2
        //   75: goto -20 -> 55
        // Local variable table:
        //   start	length	slot	name	signature
        //   0	78	0	this	a
        //   0	78	1	parame	kotlin.l.b.a.b.h.e
        //   0	78	2	paramg	g
        //   6	68	3	localObject	Object
        // Exception table:
        //   from	to	target	type
        //   7	21	38	kotlin/l/b/a/b/h/l
        //   47	54	54	finally
        //   7	21	72	finally
        //   39	47	72	finally
      }
      
      private a d(a.a parama)
      {
        AppMethodBeat.i(59139);
        if (((this.bitField0_ & 0x1) == 1) && (this.ajdB != a.a.kwZ())) {}
        for (this.ajdB = a.a.a(this.ajdB).c(parama).kxd();; this.ajdB = parama)
        {
          this.bitField0_ |= 0x1;
          AppMethodBeat.o(59139);
          return this;
        }
      }
      
      private a d(a.b paramb)
      {
        AppMethodBeat.i(59140);
        if (((this.bitField0_ & 0x2) == 2) && (this.ajdC != a.b.kxf())) {}
        for (this.ajdC = a.b.a(this.ajdC).c(paramb).kxi();; this.ajdC = paramb)
        {
          this.bitField0_ |= 0x2;
          AppMethodBeat.o(59140);
          return this;
        }
      }
      
      private a e(a.b paramb)
      {
        AppMethodBeat.i(59141);
        if (((this.bitField0_ & 0x4) == 4) && (this.ajdD != a.b.kxf())) {}
        for (this.ajdD = a.b.a(this.ajdD).c(paramb).kxi();; this.ajdD = paramb)
        {
          this.bitField0_ |= 0x4;
          AppMethodBeat.o(59141);
          return this;
        }
      }
      
      private a f(a.b paramb)
      {
        AppMethodBeat.i(59142);
        if (((this.bitField0_ & 0x8) == 8) && (this.ajdE != a.b.kxf())) {}
        for (this.ajdE = a.b.a(this.ajdE).c(paramb).kxi();; this.ajdE = paramb)
        {
          this.bitField0_ |= 0x8;
          AppMethodBeat.o(59142);
          return this;
        }
      }
      
      private a kxp()
      {
        AppMethodBeat.i(59135);
        a locala = new a().b(kxq());
        AppMethodBeat.o(59135);
        return locala;
      }
      
      private a.c kxq()
      {
        int j = 1;
        AppMethodBeat.i(59136);
        a.c localc = new a.c(this, (byte)0);
        int k = this.bitField0_;
        if ((k & 0x1) == 1) {}
        for (;;)
        {
          a.c.a(localc, this.ajdB);
          int i = j;
          if ((k & 0x2) == 2) {
            i = j | 0x2;
          }
          a.c.a(localc, this.ajdC);
          j = i;
          if ((k & 0x4) == 4) {
            j = i | 0x4;
          }
          a.c.b(localc, this.ajdD);
          i = j;
          if ((k & 0x8) == 8) {
            i = j | 0x8;
          }
          a.c.c(localc, this.ajdE);
          a.c.a(localc, i);
          AppMethodBeat.o(59136);
          return localc;
          j = 0;
        }
      }
      
      public final a b(a.c paramc)
      {
        AppMethodBeat.i(59137);
        if (paramc == a.c.kxk())
        {
          AppMethodBeat.o(59137);
          return this;
        }
        if (paramc.kxl()) {
          d(paramc.ajdB);
        }
        if (paramc.kxm()) {
          d(paramc.ajdC);
        }
        if (paramc.kxn()) {
          e(paramc.ajdD);
        }
        if (paramc.kxo()) {
          f(paramc.ajdE);
        }
        this.aiXZ = this.aiXZ.a(a.c.a(paramc));
        AppMethodBeat.o(59137);
        return this;
      }
      
      public final boolean isInitialized()
      {
        return true;
      }
    }
  }
  
  public static final class d
    extends i
    implements f
  {
    public static t<d> aiYa;
    private static final d ajdF;
    private final kotlin.l.b.a.b.h.d aiXZ;
    public List<b> ajdG;
    public List<Integer> ajdH;
    private int ajdI = -1;
    private int dRJ = -1;
    private byte memoizedIsInitialized = -1;
    
    static
    {
      AppMethodBeat.i(59216);
      aiYa = new kotlin.l.b.a.b.h.b() {};
      d locald = new d();
      ajdF = locald;
      locald.ktf();
      AppMethodBeat.o(59216);
    }
    
    private d()
    {
      this.aiXZ = kotlin.l.b.a.b.h.d.ajeU;
    }
    
    /* Error */
    private d(kotlin.l.b.a.b.h.e parame, g paramg)
    {
      // Byte code:
      //   0: aload_0
      //   1: invokespecial 67	kotlin/l/b/a/b/h/i:<init>	()V
      //   4: ldc 86
      //   6: invokestatic 51	com/tencent/matrix/trace/core/AppMethodBeat:i	(I)V
      //   9: aload_0
      //   10: iconst_m1
      //   11: putfield 69	kotlin/l/b/a/b/e/c/a$d:ajdI	I
      //   14: aload_0
      //   15: iconst_m1
      //   16: putfield 71	kotlin/l/b/a/b/e/c/a$d:memoizedIsInitialized	B
      //   19: aload_0
      //   20: iconst_m1
      //   21: putfield 73	kotlin/l/b/a/b/e/c/a$d:dRJ	I
      //   24: aload_0
      //   25: invokespecial 62	kotlin/l/b/a/b/e/c/a$d:ktf	()V
      //   28: invokestatic 90	kotlin/l/b/a/b/h/d:kya	()Lkotlin/l/b/a/b/h/d$b;
      //   31: astore 10
      //   33: aload 10
      //   35: iconst_1
      //   36: invokestatic 95	kotlin/l/b/a/b/h/f:i	(Ljava/io/OutputStream;I)Lkotlin/l/b/a/b/h/f;
      //   39: astore 11
      //   41: iconst_0
      //   42: istore 5
      //   44: iconst_0
      //   45: istore_3
      //   46: iload 5
      //   48: ifne +499 -> 547
      //   51: iload_3
      //   52: istore 6
      //   54: iload_3
      //   55: istore 7
      //   57: iload_3
      //   58: istore 8
      //   60: aload_1
      //   61: invokevirtual 101	kotlin/l/b/a/b/h/e:aac	()I
      //   64: istore 4
      //   66: iload 4
      //   68: lookupswitch	default:+621->689, 0:+624->692, 10:+72->140, 40:+133->201, 42:+193->261
      //   113: istore 6
      //   115: iload_3
      //   116: istore 7
      //   118: iload_3
      //   119: istore 8
      //   121: aload_0
      //   122: aload_1
      //   123: aload 11
      //   125: aload_2
      //   126: iload 4
      //   128: invokevirtual 104	kotlin/l/b/a/b/e/c/a$d:a	(Lkotlin/l/b/a/b/h/e;Lkotlin/l/b/a/b/h/f;Lkotlin/l/b/a/b/h/g;I)Z
      //   131: ifne -85 -> 46
      //   134: iconst_1
      //   135: istore 5
      //   137: goto -91 -> 46
      //   140: iload_3
      //   141: iconst_1
      //   142: iand
      //   143: iconst_1
      //   144: if_icmpeq +542 -> 686
      //   147: iload_3
      //   148: istore 6
      //   150: iload_3
      //   151: istore 7
      //   153: iload_3
      //   154: istore 8
      //   156: aload_0
      //   157: new 106	java/util/ArrayList
      //   160: dup
      //   161: invokespecial 107	java/util/ArrayList:<init>	()V
      //   164: putfield 109	kotlin/l/b/a/b/e/c/a$d:ajdG	Ljava/util/List;
      //   167: iload_3
      //   168: iconst_1
      //   169: ior
      //   170: istore_3
      //   171: iload_3
      //   172: istore 4
      //   174: iload_3
      //   175: istore 6
      //   177: iload_3
      //   178: istore 7
      //   180: aload_0
      //   181: getfield 109	kotlin/l/b/a/b/e/c/a$d:ajdG	Ljava/util/List;
      //   184: aload_1
      //   185: getstatic 110	kotlin/l/b/a/b/e/c/a$d$b:aiYa	Lkotlin/l/b/a/b/h/t;
      //   188: aload_2
      //   189: invokevirtual 113	kotlin/l/b/a/b/h/e:a	(Lkotlin/l/b/a/b/h/t;Lkotlin/l/b/a/b/h/g;)Lkotlin/l/b/a/b/h/r;
      //   192: invokeinterface 119 2 0
      //   197: pop
      //   198: goto -152 -> 46
      //   201: iload_3
      //   202: iconst_2
      //   203: iand
      //   204: iconst_2
      //   205: if_icmpeq +478 -> 683
      //   208: iload_3
      //   209: istore 6
      //   211: iload_3
      //   212: istore 7
      //   214: iload_3
      //   215: istore 8
      //   217: aload_0
      //   218: new 106	java/util/ArrayList
      //   221: dup
      //   222: invokespecial 107	java/util/ArrayList:<init>	()V
      //   225: putfield 121	kotlin/l/b/a/b/e/c/a$d:ajdH	Ljava/util/List;
      //   228: iload_3
      //   229: iconst_2
      //   230: ior
      //   231: istore_3
      //   232: iload_3
      //   233: istore 4
      //   235: iload_3
      //   236: istore 6
      //   238: iload_3
      //   239: istore 7
      //   241: aload_0
      //   242: getfield 121	kotlin/l/b/a/b/e/c/a$d:ajdH	Ljava/util/List;
      //   245: aload_1
      //   246: invokevirtual 124	kotlin/l/b/a/b/h/e:aar	()I
      //   249: invokestatic 130	java/lang/Integer:valueOf	(I)Ljava/lang/Integer;
      //   252: invokeinterface 119 2 0
      //   257: pop
      //   258: goto -212 -> 46
      //   261: iload_3
      //   262: istore 6
      //   264: iload_3
      //   265: istore 7
      //   267: iload_3
      //   268: istore 8
      //   270: aload_1
      //   271: aload_1
      //   272: invokevirtual 124	kotlin/l/b/a/b/h/e:aar	()I
      //   275: invokevirtual 134	kotlin/l/b/a/b/h/e:jO	(I)I
      //   278: istore 9
      //   280: iload_3
      //   281: istore 4
      //   283: iload_3
      //   284: iconst_2
      //   285: iand
      //   286: iconst_2
      //   287: if_icmpeq +47 -> 334
      //   290: iload_3
      //   291: istore 4
      //   293: iload_3
      //   294: istore 6
      //   296: iload_3
      //   297: istore 7
      //   299: iload_3
      //   300: istore 8
      //   302: aload_1
      //   303: invokevirtual 137	kotlin/l/b/a/b/h/e:aat	()I
      //   306: ifle +28 -> 334
      //   309: iload_3
      //   310: istore 6
      //   312: iload_3
      //   313: istore 7
      //   315: iload_3
      //   316: istore 8
      //   318: aload_0
      //   319: new 106	java/util/ArrayList
      //   322: dup
      //   323: invokespecial 107	java/util/ArrayList:<init>	()V
      //   326: putfield 121	kotlin/l/b/a/b/e/c/a$d:ajdH	Ljava/util/List;
      //   329: iload_3
      //   330: iconst_2
      //   331: ior
      //   332: istore 4
      //   334: iload 4
      //   336: istore 6
      //   338: iload 4
      //   340: istore 7
      //   342: iload 4
      //   344: istore 8
      //   346: aload_1
      //   347: invokevirtual 137	kotlin/l/b/a/b/h/e:aat	()I
      //   350: ifle +128 -> 478
      //   353: iload 4
      //   355: istore 6
      //   357: iload 4
      //   359: istore 7
      //   361: iload 4
      //   363: istore 8
      //   365: aload_0
      //   366: getfield 121	kotlin/l/b/a/b/e/c/a$d:ajdH	Ljava/util/List;
      //   369: aload_1
      //   370: invokevirtual 124	kotlin/l/b/a/b/h/e:aar	()I
      //   373: invokestatic 130	java/lang/Integer:valueOf	(I)Ljava/lang/Integer;
      //   376: invokeinterface 119 2 0
      //   381: pop
      //   382: goto -48 -> 334
      //   385: astore_1
      //   386: iload 6
      //   388: istore 7
      //   390: iload 7
      //   392: istore 4
      //   394: aload_1
      //   395: aload_0
      //   396: putfield 141	kotlin/l/b/a/b/h/l:ajfp	Lkotlin/l/b/a/b/h/r;
      //   399: iload 7
      //   401: istore 4
      //   403: ldc 86
      //   405: invokestatic 65	com/tencent/matrix/trace/core/AppMethodBeat:o	(I)V
      //   408: iload 7
      //   410: istore 4
      //   412: aload_1
      //   413: athrow
      //   414: astore_1
      //   415: iload 4
      //   417: iconst_1
      //   418: iand
      //   419: iconst_1
      //   420: if_icmpne +14 -> 434
      //   423: aload_0
      //   424: aload_0
      //   425: getfield 109	kotlin/l/b/a/b/e/c/a$d:ajdG	Ljava/util/List;
      //   428: invokestatic 147	java/util/Collections:unmodifiableList	(Ljava/util/List;)Ljava/util/List;
      //   431: putfield 109	kotlin/l/b/a/b/e/c/a$d:ajdG	Ljava/util/List;
      //   434: iload 4
      //   436: iconst_2
      //   437: iand
      //   438: iconst_2
      //   439: if_icmpne +14 -> 453
      //   442: aload_0
      //   443: aload_0
      //   444: getfield 121	kotlin/l/b/a/b/e/c/a$d:ajdH	Ljava/util/List;
      //   447: invokestatic 147	java/util/Collections:unmodifiableList	(Ljava/util/List;)Ljava/util/List;
      //   450: putfield 121	kotlin/l/b/a/b/e/c/a$d:ajdH	Ljava/util/List;
      //   453: aload 11
      //   455: invokevirtual 150	kotlin/l/b/a/b/h/f:flush	()V
      //   458: aload_0
      //   459: aload 10
      //   461: invokevirtual 156	kotlin/l/b/a/b/h/d$b:kyc	()Lkotlin/l/b/a/b/h/d;
      //   464: putfield 80	kotlin/l/b/a/b/e/c/a$d:aiXZ	Lkotlin/l/b/a/b/h/d;
      //   467: aload_0
      //   468: invokevirtual 159	kotlin/l/b/a/b/e/c/a$d:makeExtensionsImmutable	()V
      //   471: ldc 86
      //   473: invokestatic 65	com/tencent/matrix/trace/core/AppMethodBeat:o	(I)V
      //   476: aload_1
      //   477: athrow
      //   478: iload 4
      //   480: istore 6
      //   482: iload 4
      //   484: istore 7
      //   486: iload 4
      //   488: istore 8
      //   490: aload_1
      //   491: iload 9
      //   493: invokevirtual 162	kotlin/l/b/a/b/h/e:jP	(I)V
      //   496: iload 4
      //   498: istore_3
      //   499: goto -453 -> 46
      //   502: astore_1
      //   503: iload 7
      //   505: istore 6
      //   507: iload 6
      //   509: istore 4
      //   511: new 83	kotlin/l/b/a/b/h/l
      //   514: dup
      //   515: aload_1
      //   516: invokevirtual 166	java/io/IOException:getMessage	()Ljava/lang/String;
      //   519: invokespecial 169	kotlin/l/b/a/b/h/l:<init>	(Ljava/lang/String;)V
      //   522: astore_1
      //   523: iload 6
      //   525: istore 4
      //   527: aload_1
      //   528: aload_0
      //   529: putfield 141	kotlin/l/b/a/b/h/l:ajfp	Lkotlin/l/b/a/b/h/r;
      //   532: iload 6
      //   534: istore 4
      //   536: ldc 86
      //   538: invokestatic 65	com/tencent/matrix/trace/core/AppMethodBeat:o	(I)V
      //   541: iload 6
      //   543: istore 4
      //   545: aload_1
      //   546: athrow
      //   547: iload_3
      //   548: iconst_1
      //   549: iand
      //   550: iconst_1
      //   551: if_icmpne +14 -> 565
      //   554: aload_0
      //   555: aload_0
      //   556: getfield 109	kotlin/l/b/a/b/e/c/a$d:ajdG	Ljava/util/List;
      //   559: invokestatic 147	java/util/Collections:unmodifiableList	(Ljava/util/List;)Ljava/util/List;
      //   562: putfield 109	kotlin/l/b/a/b/e/c/a$d:ajdG	Ljava/util/List;
      //   565: iload_3
      //   566: iconst_2
      //   567: iand
      //   568: iconst_2
      //   569: if_icmpne +14 -> 583
      //   572: aload_0
      //   573: aload_0
      //   574: getfield 121	kotlin/l/b/a/b/e/c/a$d:ajdH	Ljava/util/List;
      //   577: invokestatic 147	java/util/Collections:unmodifiableList	(Ljava/util/List;)Ljava/util/List;
      //   580: putfield 121	kotlin/l/b/a/b/e/c/a$d:ajdH	Ljava/util/List;
      //   583: aload 11
      //   585: invokevirtual 150	kotlin/l/b/a/b/h/f:flush	()V
      //   588: aload_0
      //   589: aload 10
      //   591: invokevirtual 156	kotlin/l/b/a/b/h/d$b:kyc	()Lkotlin/l/b/a/b/h/d;
      //   594: putfield 80	kotlin/l/b/a/b/e/c/a$d:aiXZ	Lkotlin/l/b/a/b/h/d;
      //   597: aload_0
      //   598: invokevirtual 159	kotlin/l/b/a/b/e/c/a$d:makeExtensionsImmutable	()V
      //   601: ldc 86
      //   603: invokestatic 65	com/tencent/matrix/trace/core/AppMethodBeat:o	(I)V
      //   606: return
      //   607: astore_1
      //   608: aload_0
      //   609: aload 10
      //   611: invokevirtual 156	kotlin/l/b/a/b/h/d$b:kyc	()Lkotlin/l/b/a/b/h/d;
      //   614: putfield 80	kotlin/l/b/a/b/e/c/a$d:aiXZ	Lkotlin/l/b/a/b/h/d;
      //   617: goto -20 -> 597
      //   620: astore_1
      //   621: aload_0
      //   622: aload 10
      //   624: invokevirtual 156	kotlin/l/b/a/b/h/d$b:kyc	()Lkotlin/l/b/a/b/h/d;
      //   627: putfield 80	kotlin/l/b/a/b/e/c/a$d:aiXZ	Lkotlin/l/b/a/b/h/d;
      //   630: ldc 86
      //   632: invokestatic 65	com/tencent/matrix/trace/core/AppMethodBeat:o	(I)V
      //   635: aload_1
      //   636: athrow
      //   637: astore_2
      //   638: aload_0
      //   639: aload 10
      //   641: invokevirtual 156	kotlin/l/b/a/b/h/d$b:kyc	()Lkotlin/l/b/a/b/h/d;
      //   644: putfield 80	kotlin/l/b/a/b/e/c/a$d:aiXZ	Lkotlin/l/b/a/b/h/d;
      //   647: goto -180 -> 467
      //   650: astore_1
      //   651: aload_0
      //   652: aload 10
      //   654: invokevirtual 156	kotlin/l/b/a/b/h/d$b:kyc	()Lkotlin/l/b/a/b/h/d;
      //   657: putfield 80	kotlin/l/b/a/b/e/c/a$d:aiXZ	Lkotlin/l/b/a/b/h/d;
      //   660: ldc 86
      //   662: invokestatic 65	com/tencent/matrix/trace/core/AppMethodBeat:o	(I)V
      //   665: aload_1
      //   666: athrow
      //   667: astore_1
      //   668: iload 8
      //   670: istore 4
      //   672: goto -257 -> 415
      //   675: astore_1
      //   676: goto -169 -> 507
      //   679: astore_1
      //   680: goto -290 -> 390
      //   683: goto -451 -> 232
      //   686: goto -515 -> 171
      //   689: goto -577 -> 112
      //   692: iconst_1
      //   693: istore 5
      //   695: goto -649 -> 46
      // Local variable table:
      //   start	length	slot	name	signature
      //   0	698	0	this	d
      //   0	698	1	parame	kotlin.l.b.a.b.h.e
      //   0	698	2	paramg	g
      //   45	523	3	i	int
      //   64	607	4	j	int
      //   42	652	5	k	int
      //   52	490	6	m	int
      //   55	449	7	n	int
      //   58	611	8	i1	int
      //   278	214	9	i2	int
      //   31	622	10	localb	kotlin.l.b.a.b.h.d.b
      //   39	545	11	localf	kotlin.l.b.a.b.h.f
      // Exception table:
      //   from	to	target	type
      //   60	66	385	kotlin/l/b/a/b/h/l
      //   121	134	385	kotlin/l/b/a/b/h/l
      //   156	167	385	kotlin/l/b/a/b/h/l
      //   217	228	385	kotlin/l/b/a/b/h/l
      //   270	280	385	kotlin/l/b/a/b/h/l
      //   302	309	385	kotlin/l/b/a/b/h/l
      //   318	329	385	kotlin/l/b/a/b/h/l
      //   346	353	385	kotlin/l/b/a/b/h/l
      //   365	382	385	kotlin/l/b/a/b/h/l
      //   490	496	385	kotlin/l/b/a/b/h/l
      //   180	198	414	finally
      //   241	258	414	finally
      //   394	399	414	finally
      //   403	408	414	finally
      //   412	414	414	finally
      //   511	523	414	finally
      //   527	532	414	finally
      //   536	541	414	finally
      //   545	547	414	finally
      //   60	66	502	java/io/IOException
      //   121	134	502	java/io/IOException
      //   156	167	502	java/io/IOException
      //   217	228	502	java/io/IOException
      //   270	280	502	java/io/IOException
      //   302	309	502	java/io/IOException
      //   318	329	502	java/io/IOException
      //   346	353	502	java/io/IOException
      //   365	382	502	java/io/IOException
      //   490	496	502	java/io/IOException
      //   583	588	607	java/io/IOException
      //   583	588	620	finally
      //   453	458	637	java/io/IOException
      //   453	458	650	finally
      //   60	66	667	finally
      //   121	134	667	finally
      //   156	167	667	finally
      //   217	228	667	finally
      //   270	280	667	finally
      //   302	309	667	finally
      //   318	329	667	finally
      //   346	353	667	finally
      //   365	382	667	finally
      //   490	496	667	finally
      //   180	198	675	java/io/IOException
      //   241	258	675	java/io/IOException
      //   180	198	679	kotlin/l/b/a/b/h/l
      //   241	258	679	kotlin/l/b/a/b/h/l
    }
    
    private d(i.a parama)
    {
      super();
      this.aiXZ = parama.aiXZ;
    }
    
    public static d f(InputStream paramInputStream, g paramg)
    {
      AppMethodBeat.i(59213);
      paramInputStream = (d)aiYa.i(paramInputStream, paramg);
      AppMethodBeat.o(59213);
      return paramInputStream;
    }
    
    private void ktf()
    {
      AppMethodBeat.i(59210);
      this.ajdG = Collections.emptyList();
      this.ajdH = Collections.emptyList();
      AppMethodBeat.o(59210);
    }
    
    public static d kxs()
    {
      return ajdF;
    }
    
    public final void a(kotlin.l.b.a.b.h.f paramf)
    {
      int j = 0;
      AppMethodBeat.i(59211);
      getSerializedSize();
      int i = 0;
      while (i < this.ajdG.size())
      {
        paramf.a(1, (r)this.ajdG.get(i));
        i += 1;
      }
      i = j;
      if (this.ajdH.size() > 0)
      {
        paramf.lI(42);
        paramf.lI(this.ajdI);
        i = j;
      }
      while (i < this.ajdH.size())
      {
        paramf.kd(((Integer)this.ajdH.get(i)).intValue());
        i += 1;
      }
      paramf.e(this.aiXZ);
      AppMethodBeat.o(59211);
    }
    
    public final int getSerializedSize()
    {
      AppMethodBeat.i(59212);
      int i = this.dRJ;
      if (i != -1)
      {
        AppMethodBeat.o(59212);
        return i;
      }
      int j = 0;
      i = 0;
      while (j < this.ajdG.size())
      {
        i += kotlin.l.b.a.b.h.f.c(1, (r)this.ajdG.get(j));
        j += 1;
      }
      int k = 0;
      int m;
      for (j = 0; k < this.ajdH.size(); j = m + j)
      {
        m = kotlin.l.b.a.b.h.f.kp(((Integer)this.ajdH.get(k)).intValue());
        k += 1;
      }
      k = i + j;
      i = k;
      if (!this.ajdH.isEmpty()) {
        i = k + 1 + kotlin.l.b.a.b.h.f.kp(j);
      }
      this.ajdI = j;
      i += this.aiXZ.size();
      this.dRJ = i;
      AppMethodBeat.o(59212);
      return i;
    }
    
    public final boolean isInitialized()
    {
      int i = this.memoizedIsInitialized;
      if (i == 1) {
        return true;
      }
      if (i == 0) {
        return false;
      }
      this.memoizedIsInitialized = 1;
      return true;
    }
    
    public static final class a
      extends i.a<a.d, a>
      implements f
    {
      private List<a.d.b> ajdG;
      private List<Integer> ajdH;
      private int bitField0_;
      
      private a()
      {
        AppMethodBeat.i(59161);
        this.ajdG = Collections.emptyList();
        this.ajdH = Collections.emptyList();
        AppMethodBeat.o(59161);
      }
      
      /* Error */
      private a E(kotlin.l.b.a.b.h.e parame, g paramg)
      {
        // Byte code:
        //   0: ldc 50
        //   2: invokestatic 31	com/tencent/matrix/trace/core/AppMethodBeat:i	(I)V
        //   5: aconst_null
        //   6: astore_3
        //   7: getstatic 54	kotlin/l/b/a/b/e/c/a$d:aiYa	Lkotlin/l/b/a/b/h/t;
        //   10: aload_1
        //   11: aload_2
        //   12: invokeinterface 59 3 0
        //   17: checkcast 9	kotlin/l/b/a/b/e/c/a$d
        //   20: astore_1
        //   21: aload_1
        //   22: ifnull +9 -> 31
        //   25: aload_0
        //   26: aload_1
        //   27: invokevirtual 62	kotlin/l/b/a/b/e/c/a$d$a:d	(Lkotlin/l/b/a/b/e/c/a$d;)Lkotlin/l/b/a/b/e/c/a$d$a;
        //   30: pop
        //   31: ldc 50
        //   33: invokestatic 44	com/tencent/matrix/trace/core/AppMethodBeat:o	(I)V
        //   36: aload_0
        //   37: areturn
        //   38: astore_1
        //   39: aload_1
        //   40: getfield 66	kotlin/l/b/a/b/h/l:ajfp	Lkotlin/l/b/a/b/h/r;
        //   43: checkcast 9	kotlin/l/b/a/b/e/c/a$d
        //   46: astore_2
        //   47: ldc 50
        //   49: invokestatic 44	com/tencent/matrix/trace/core/AppMethodBeat:o	(I)V
        //   52: aload_1
        //   53: athrow
        //   54: astore_1
        //   55: aload_2
        //   56: ifnull +9 -> 65
        //   59: aload_0
        //   60: aload_2
        //   61: invokevirtual 62	kotlin/l/b/a/b/e/c/a$d$a:d	(Lkotlin/l/b/a/b/e/c/a$d;)Lkotlin/l/b/a/b/e/c/a$d$a;
        //   64: pop
        //   65: ldc 50
        //   67: invokestatic 44	com/tencent/matrix/trace/core/AppMethodBeat:o	(I)V
        //   70: aload_1
        //   71: athrow
        //   72: astore_1
        //   73: aload_3
        //   74: astore_2
        //   75: goto -20 -> 55
        // Local variable table:
        //   start	length	slot	name	signature
        //   0	78	0	this	a
        //   0	78	1	parame	kotlin.l.b.a.b.h.e
        //   0	78	2	paramg	g
        //   6	68	3	localObject	Object
        // Exception table:
        //   from	to	target	type
        //   7	21	38	kotlin/l/b/a/b/h/l
        //   47	54	54	finally
        //   7	21	72	finally
        //   39	47	72	finally
      }
      
      private a kxt()
      {
        AppMethodBeat.i(59162);
        a locala = new a().d(kxu());
        AppMethodBeat.o(59162);
        return locala;
      }
      
      private a.d kxu()
      {
        AppMethodBeat.i(59163);
        a.d locald = new a.d(this, (byte)0);
        if ((this.bitField0_ & 0x1) == 1)
        {
          this.ajdG = Collections.unmodifiableList(this.ajdG);
          this.bitField0_ &= 0xFFFFFFFE;
        }
        a.d.a(locald, this.ajdG);
        if ((this.bitField0_ & 0x2) == 2)
        {
          this.ajdH = Collections.unmodifiableList(this.ajdH);
          this.bitField0_ &= 0xFFFFFFFD;
        }
        a.d.b(locald, this.ajdH);
        AppMethodBeat.o(59163);
        return locald;
      }
      
      private void kxv()
      {
        AppMethodBeat.i(59166);
        if ((this.bitField0_ & 0x1) != 1)
        {
          this.ajdG = new ArrayList(this.ajdG);
          this.bitField0_ |= 0x1;
        }
        AppMethodBeat.o(59166);
      }
      
      private void kxw()
      {
        AppMethodBeat.i(59167);
        if ((this.bitField0_ & 0x2) != 2)
        {
          this.ajdH = new ArrayList(this.ajdH);
          this.bitField0_ |= 0x2;
        }
        AppMethodBeat.o(59167);
      }
      
      public final a d(a.d paramd)
      {
        AppMethodBeat.i(59164);
        if (paramd == a.d.kxs())
        {
          AppMethodBeat.o(59164);
          return this;
        }
        if (!a.d.a(paramd).isEmpty())
        {
          if (this.ajdG.isEmpty())
          {
            this.ajdG = a.d.a(paramd);
            this.bitField0_ &= 0xFFFFFFFE;
          }
        }
        else if (!a.d.b(paramd).isEmpty())
        {
          if (!this.ajdH.isEmpty()) {
            break label148;
          }
          this.ajdH = a.d.b(paramd);
          this.bitField0_ &= 0xFFFFFFFD;
        }
        for (;;)
        {
          this.aiXZ = this.aiXZ.a(a.d.c(paramd));
          AppMethodBeat.o(59164);
          return this;
          kxv();
          this.ajdG.addAll(a.d.a(paramd));
          break;
          label148:
          kxw();
          this.ajdH.addAll(a.d.b(paramd));
        }
      }
      
      public final boolean isInitialized()
      {
        return true;
      }
    }
    
    public static final class b
      extends i
      implements e
    {
      public static t<b> aiYa;
      private static final b ajdJ;
      private final kotlin.l.b.a.b.h.d aiXZ;
      public int ajdK;
      public int ajdL;
      public Object ajdM;
      public b ajdN;
      public List<Integer> ajdO;
      private int ajdP = -1;
      public List<Integer> ajdQ;
      private int ajdR = -1;
      private int bitField0_;
      private int dRJ = -1;
      private byte memoizedIsInitialized = -1;
      
      static
      {
        AppMethodBeat.i(59208);
        aiYa = new kotlin.l.b.a.b.h.b() {};
        b localb = new b();
        ajdJ = localb;
        localb.ktf();
        AppMethodBeat.o(59208);
      }
      
      private b()
      {
        this.aiXZ = kotlin.l.b.a.b.h.d.ajeU;
      }
      
      /* Error */
      private b(kotlin.l.b.a.b.h.e parame, g paramg)
      {
        // Byte code:
        //   0: aload_0
        //   1: invokespecial 70	kotlin/l/b/a/b/h/i:<init>	()V
        //   4: ldc 91
        //   6: invokestatic 54	com/tencent/matrix/trace/core/AppMethodBeat:i	(I)V
        //   9: aload_0
        //   10: iconst_m1
        //   11: putfield 72	kotlin/l/b/a/b/e/c/a$d$b:ajdP	I
        //   14: aload_0
        //   15: iconst_m1
        //   16: putfield 74	kotlin/l/b/a/b/e/c/a$d$b:ajdR	I
        //   19: aload_0
        //   20: iconst_m1
        //   21: putfield 76	kotlin/l/b/a/b/e/c/a$d$b:memoizedIsInitialized	B
        //   24: aload_0
        //   25: iconst_m1
        //   26: putfield 78	kotlin/l/b/a/b/e/c/a$d$b:dRJ	I
        //   29: aload_0
        //   30: invokespecial 65	kotlin/l/b/a/b/e/c/a$d$b:ktf	()V
        //   33: iconst_0
        //   34: istore_3
        //   35: invokestatic 95	kotlin/l/b/a/b/h/d:kya	()Lkotlin/l/b/a/b/h/d$b;
        //   38: astore 10
        //   40: aload 10
        //   42: iconst_1
        //   43: invokestatic 100	kotlin/l/b/a/b/h/f:i	(Ljava/io/OutputStream;I)Lkotlin/l/b/a/b/h/f;
        //   46: astore 11
        //   48: iconst_0
        //   49: istore 8
        //   51: iload 8
        //   53: ifne +952 -> 1005
        //   56: iload_3
        //   57: istore 5
        //   59: iload_3
        //   60: istore 4
        //   62: iload_3
        //   63: istore 6
        //   65: aload_1
        //   66: invokevirtual 106	kotlin/l/b/a/b/h/e:aac	()I
        //   69: istore 7
        //   71: iload 7
        //   73: lookupswitch	default:+1056->1129, 0:+1059->1132, 8:+111->184, 16:+243->316, 24:+323->396, 32:+432->505, 34:+505->578, 40:+656->729, 42:+729->802, 50:+880->953
        //   157: istore 5
        //   159: iload_3
        //   160: istore 4
        //   162: iload_3
        //   163: istore 6
        //   165: aload_0
        //   166: aload_1
        //   167: aload 11
        //   169: aload_2
        //   170: iload 7
        //   172: invokevirtual 109	kotlin/l/b/a/b/e/c/a$d$b:a	(Lkotlin/l/b/a/b/h/e;Lkotlin/l/b/a/b/h/f;Lkotlin/l/b/a/b/h/g;I)Z
        //   175: ifne -124 -> 51
        //   178: iconst_1
        //   179: istore 8
        //   181: goto -130 -> 51
        //   184: iload_3
        //   185: istore 5
        //   187: iload_3
        //   188: istore 4
        //   190: iload_3
        //   191: istore 6
        //   193: aload_0
        //   194: aload_0
        //   195: getfield 111	kotlin/l/b/a/b/e/c/a$d$b:bitField0_	I
        //   198: iconst_1
        //   199: ior
        //   200: putfield 111	kotlin/l/b/a/b/e/c/a$d$b:bitField0_	I
        //   203: iload_3
        //   204: istore 5
        //   206: iload_3
        //   207: istore 4
        //   209: iload_3
        //   210: istore 6
        //   212: aload_0
        //   213: aload_1
        //   214: invokevirtual 114	kotlin/l/b/a/b/h/e:aar	()I
        //   217: putfield 116	kotlin/l/b/a/b/e/c/a$d$b:ajdK	I
        //   220: goto -169 -> 51
        //   223: astore_1
        //   224: iload 5
        //   226: istore 4
        //   228: aload_1
        //   229: aload_0
        //   230: putfield 120	kotlin/l/b/a/b/h/l:ajfp	Lkotlin/l/b/a/b/h/r;
        //   233: iload 5
        //   235: istore 4
        //   237: ldc 91
        //   239: invokestatic 68	com/tencent/matrix/trace/core/AppMethodBeat:o	(I)V
        //   242: iload 5
        //   244: istore 4
        //   246: aload_1
        //   247: athrow
        //   248: astore_1
        //   249: iload 4
        //   251: bipush 16
        //   253: iand
        //   254: bipush 16
        //   256: if_icmpne +14 -> 270
        //   259: aload_0
        //   260: aload_0
        //   261: getfield 122	kotlin/l/b/a/b/e/c/a$d$b:ajdO	Ljava/util/List;
        //   264: invokestatic 128	java/util/Collections:unmodifiableList	(Ljava/util/List;)Ljava/util/List;
        //   267: putfield 122	kotlin/l/b/a/b/e/c/a$d$b:ajdO	Ljava/util/List;
        //   270: iload 4
        //   272: bipush 32
        //   274: iand
        //   275: bipush 32
        //   277: if_icmpne +14 -> 291
        //   280: aload_0
        //   281: aload_0
        //   282: getfield 130	kotlin/l/b/a/b/e/c/a$d$b:ajdQ	Ljava/util/List;
        //   285: invokestatic 128	java/util/Collections:unmodifiableList	(Ljava/util/List;)Ljava/util/List;
        //   288: putfield 130	kotlin/l/b/a/b/e/c/a$d$b:ajdQ	Ljava/util/List;
        //   291: aload 11
        //   293: invokevirtual 133	kotlin/l/b/a/b/h/f:flush	()V
        //   296: aload_0
        //   297: aload 10
        //   299: invokevirtual 139	kotlin/l/b/a/b/h/d$b:kyc	()Lkotlin/l/b/a/b/h/d;
        //   302: putfield 85	kotlin/l/b/a/b/e/c/a$d$b:aiXZ	Lkotlin/l/b/a/b/h/d;
        //   305: aload_0
        //   306: invokevirtual 142	kotlin/l/b/a/b/e/c/a$d$b:makeExtensionsImmutable	()V
        //   309: ldc 91
        //   311: invokestatic 68	com/tencent/matrix/trace/core/AppMethodBeat:o	(I)V
        //   314: aload_1
        //   315: athrow
        //   316: iload_3
        //   317: istore 5
        //   319: iload_3
        //   320: istore 4
        //   322: iload_3
        //   323: istore 6
        //   325: aload_0
        //   326: aload_0
        //   327: getfield 111	kotlin/l/b/a/b/e/c/a$d$b:bitField0_	I
        //   330: iconst_2
        //   331: ior
        //   332: putfield 111	kotlin/l/b/a/b/e/c/a$d$b:bitField0_	I
        //   335: iload_3
        //   336: istore 5
        //   338: iload_3
        //   339: istore 4
        //   341: iload_3
        //   342: istore 6
        //   344: aload_0
        //   345: aload_1
        //   346: invokevirtual 114	kotlin/l/b/a/b/h/e:aar	()I
        //   349: putfield 144	kotlin/l/b/a/b/e/c/a$d$b:ajdL	I
        //   352: goto -301 -> 51
        //   355: astore_1
        //   356: iload 6
        //   358: istore 4
        //   360: new 88	kotlin/l/b/a/b/h/l
        //   363: dup
        //   364: aload_1
        //   365: invokevirtual 148	java/io/IOException:getMessage	()Ljava/lang/String;
        //   368: invokespecial 151	kotlin/l/b/a/b/h/l:<init>	(Ljava/lang/String;)V
        //   371: astore_1
        //   372: iload 6
        //   374: istore 4
        //   376: aload_1
        //   377: aload_0
        //   378: putfield 120	kotlin/l/b/a/b/h/l:ajfp	Lkotlin/l/b/a/b/h/r;
        //   381: iload 6
        //   383: istore 4
        //   385: ldc 91
        //   387: invokestatic 68	com/tencent/matrix/trace/core/AppMethodBeat:o	(I)V
        //   390: iload 6
        //   392: istore 4
        //   394: aload_1
        //   395: athrow
        //   396: iload_3
        //   397: istore 5
        //   399: iload_3
        //   400: istore 4
        //   402: iload_3
        //   403: istore 6
        //   405: aload_1
        //   406: invokevirtual 114	kotlin/l/b/a/b/h/e:aar	()I
        //   409: istore 9
        //   411: iload_3
        //   412: istore 5
        //   414: iload_3
        //   415: istore 4
        //   417: iload_3
        //   418: istore 6
        //   420: iload 9
        //   422: invokestatic 155	kotlin/l/b/a/b/e/c/a$d$b$b:aMg	(I)Lkotlin/l/b/a/b/e/c/a$d$b$b;
        //   425: astore 12
        //   427: aload 12
        //   429: ifnonnull +38 -> 467
        //   432: iload_3
        //   433: istore 5
        //   435: iload_3
        //   436: istore 4
        //   438: iload_3
        //   439: istore 6
        //   441: aload 11
        //   443: iload 7
        //   445: invokevirtual 158	kotlin/l/b/a/b/h/f:lI	(I)V
        //   448: iload_3
        //   449: istore 5
        //   451: iload_3
        //   452: istore 4
        //   454: iload_3
        //   455: istore 6
        //   457: aload 11
        //   459: iload 9
        //   461: invokevirtual 158	kotlin/l/b/a/b/h/f:lI	(I)V
        //   464: goto -413 -> 51
        //   467: iload_3
        //   468: istore 5
        //   470: iload_3
        //   471: istore 4
        //   473: iload_3
        //   474: istore 6
        //   476: aload_0
        //   477: aload_0
        //   478: getfield 111	kotlin/l/b/a/b/e/c/a$d$b:bitField0_	I
        //   481: bipush 8
        //   483: ior
        //   484: putfield 111	kotlin/l/b/a/b/e/c/a$d$b:bitField0_	I
        //   487: iload_3
        //   488: istore 5
        //   490: iload_3
        //   491: istore 4
        //   493: iload_3
        //   494: istore 6
        //   496: aload_0
        //   497: aload 12
        //   499: putfield 160	kotlin/l/b/a/b/e/c/a$d$b:ajdN	Lkotlin/l/b/a/b/e/c/a$d$b$b;
        //   502: goto -451 -> 51
        //   505: iload_3
        //   506: istore 7
        //   508: iload_3
        //   509: bipush 16
        //   511: iand
        //   512: bipush 16
        //   514: if_icmpeq +29 -> 543
        //   517: iload_3
        //   518: istore 5
        //   520: iload_3
        //   521: istore 4
        //   523: iload_3
        //   524: istore 6
        //   526: aload_0
        //   527: new 162	java/util/ArrayList
        //   530: dup
        //   531: invokespecial 163	java/util/ArrayList:<init>	()V
        //   534: putfield 122	kotlin/l/b/a/b/e/c/a$d$b:ajdO	Ljava/util/List;
        //   537: iload_3
        //   538: bipush 16
        //   540: ior
        //   541: istore 7
        //   543: iload 7
        //   545: istore 5
        //   547: iload 7
        //   549: istore 4
        //   551: iload 7
        //   553: istore 6
        //   555: aload_0
        //   556: getfield 122	kotlin/l/b/a/b/e/c/a$d$b:ajdO	Ljava/util/List;
        //   559: aload_1
        //   560: invokevirtual 114	kotlin/l/b/a/b/h/e:aar	()I
        //   563: invokestatic 169	java/lang/Integer:valueOf	(I)Ljava/lang/Integer;
        //   566: invokeinterface 175 2 0
        //   571: pop
        //   572: iload 7
        //   574: istore_3
        //   575: goto -524 -> 51
        //   578: iload_3
        //   579: istore 5
        //   581: iload_3
        //   582: istore 4
        //   584: iload_3
        //   585: istore 6
        //   587: aload_1
        //   588: aload_1
        //   589: invokevirtual 114	kotlin/l/b/a/b/h/e:aar	()I
        //   592: invokevirtual 179	kotlin/l/b/a/b/h/e:jO	(I)I
        //   595: istore 9
        //   597: iload_3
        //   598: istore 7
        //   600: iload_3
        //   601: bipush 16
        //   603: iand
        //   604: bipush 16
        //   606: if_icmpeq +48 -> 654
        //   609: iload_3
        //   610: istore 5
        //   612: iload_3
        //   613: istore 4
        //   615: iload_3
        //   616: istore 6
        //   618: iload_3
        //   619: istore 7
        //   621: aload_1
        //   622: invokevirtual 182	kotlin/l/b/a/b/h/e:aat	()I
        //   625: ifle +29 -> 654
        //   628: iload_3
        //   629: istore 5
        //   631: iload_3
        //   632: istore 4
        //   634: iload_3
        //   635: istore 6
        //   637: aload_0
        //   638: new 162	java/util/ArrayList
        //   641: dup
        //   642: invokespecial 163	java/util/ArrayList:<init>	()V
        //   645: putfield 122	kotlin/l/b/a/b/e/c/a$d$b:ajdO	Ljava/util/List;
        //   648: iload_3
        //   649: bipush 16
        //   651: ior
        //   652: istore 7
        //   654: iload 7
        //   656: istore 5
        //   658: iload 7
        //   660: istore 4
        //   662: iload 7
        //   664: istore 6
        //   666: aload_1
        //   667: invokevirtual 182	kotlin/l/b/a/b/h/e:aat	()I
        //   670: ifle +35 -> 705
        //   673: iload 7
        //   675: istore 5
        //   677: iload 7
        //   679: istore 4
        //   681: iload 7
        //   683: istore 6
        //   685: aload_0
        //   686: getfield 122	kotlin/l/b/a/b/e/c/a$d$b:ajdO	Ljava/util/List;
        //   689: aload_1
        //   690: invokevirtual 114	kotlin/l/b/a/b/h/e:aar	()I
        //   693: invokestatic 169	java/lang/Integer:valueOf	(I)Ljava/lang/Integer;
        //   696: invokeinterface 175 2 0
        //   701: pop
        //   702: goto -48 -> 654
        //   705: iload 7
        //   707: istore 5
        //   709: iload 7
        //   711: istore 4
        //   713: iload 7
        //   715: istore 6
        //   717: aload_1
        //   718: iload 9
        //   720: invokevirtual 185	kotlin/l/b/a/b/h/e:jP	(I)V
        //   723: iload 7
        //   725: istore_3
        //   726: goto -675 -> 51
        //   729: iload_3
        //   730: istore 7
        //   732: iload_3
        //   733: bipush 32
        //   735: iand
        //   736: bipush 32
        //   738: if_icmpeq +29 -> 767
        //   741: iload_3
        //   742: istore 5
        //   744: iload_3
        //   745: istore 4
        //   747: iload_3
        //   748: istore 6
        //   750: aload_0
        //   751: new 162	java/util/ArrayList
        //   754: dup
        //   755: invokespecial 163	java/util/ArrayList:<init>	()V
        //   758: putfield 130	kotlin/l/b/a/b/e/c/a$d$b:ajdQ	Ljava/util/List;
        //   761: iload_3
        //   762: bipush 32
        //   764: ior
        //   765: istore 7
        //   767: iload 7
        //   769: istore 5
        //   771: iload 7
        //   773: istore 4
        //   775: iload 7
        //   777: istore 6
        //   779: aload_0
        //   780: getfield 130	kotlin/l/b/a/b/e/c/a$d$b:ajdQ	Ljava/util/List;
        //   783: aload_1
        //   784: invokevirtual 114	kotlin/l/b/a/b/h/e:aar	()I
        //   787: invokestatic 169	java/lang/Integer:valueOf	(I)Ljava/lang/Integer;
        //   790: invokeinterface 175 2 0
        //   795: pop
        //   796: iload 7
        //   798: istore_3
        //   799: goto -748 -> 51
        //   802: iload_3
        //   803: istore 5
        //   805: iload_3
        //   806: istore 4
        //   808: iload_3
        //   809: istore 6
        //   811: aload_1
        //   812: aload_1
        //   813: invokevirtual 114	kotlin/l/b/a/b/h/e:aar	()I
        //   816: invokevirtual 179	kotlin/l/b/a/b/h/e:jO	(I)I
        //   819: istore 9
        //   821: iload_3
        //   822: istore 7
        //   824: iload_3
        //   825: bipush 32
        //   827: iand
        //   828: bipush 32
        //   830: if_icmpeq +48 -> 878
        //   833: iload_3
        //   834: istore 5
        //   836: iload_3
        //   837: istore 4
        //   839: iload_3
        //   840: istore 6
        //   842: iload_3
        //   843: istore 7
        //   845: aload_1
        //   846: invokevirtual 182	kotlin/l/b/a/b/h/e:aat	()I
        //   849: ifle +29 -> 878
        //   852: iload_3
        //   853: istore 5
        //   855: iload_3
        //   856: istore 4
        //   858: iload_3
        //   859: istore 6
        //   861: aload_0
        //   862: new 162	java/util/ArrayList
        //   865: dup
        //   866: invokespecial 163	java/util/ArrayList:<init>	()V
        //   869: putfield 130	kotlin/l/b/a/b/e/c/a$d$b:ajdQ	Ljava/util/List;
        //   872: iload_3
        //   873: bipush 32
        //   875: ior
        //   876: istore 7
        //   878: iload 7
        //   880: istore 5
        //   882: iload 7
        //   884: istore 4
        //   886: iload 7
        //   888: istore 6
        //   890: aload_1
        //   891: invokevirtual 182	kotlin/l/b/a/b/h/e:aat	()I
        //   894: ifle +35 -> 929
        //   897: iload 7
        //   899: istore 5
        //   901: iload 7
        //   903: istore 4
        //   905: iload 7
        //   907: istore 6
        //   909: aload_0
        //   910: getfield 130	kotlin/l/b/a/b/e/c/a$d$b:ajdQ	Ljava/util/List;
        //   913: aload_1
        //   914: invokevirtual 114	kotlin/l/b/a/b/h/e:aar	()I
        //   917: invokestatic 169	java/lang/Integer:valueOf	(I)Ljava/lang/Integer;
        //   920: invokeinterface 175 2 0
        //   925: pop
        //   926: goto -48 -> 878
        //   929: iload 7
        //   931: istore 5
        //   933: iload 7
        //   935: istore 4
        //   937: iload 7
        //   939: istore 6
        //   941: aload_1
        //   942: iload 9
        //   944: invokevirtual 185	kotlin/l/b/a/b/h/e:jP	(I)V
        //   947: iload 7
        //   949: istore_3
        //   950: goto -899 -> 51
        //   953: iload_3
        //   954: istore 5
        //   956: iload_3
        //   957: istore 4
        //   959: iload_3
        //   960: istore 6
        //   962: aload_1
        //   963: invokevirtual 188	kotlin/l/b/a/b/h/e:kyd	()Lkotlin/l/b/a/b/h/d;
        //   966: astore 12
        //   968: iload_3
        //   969: istore 5
        //   971: iload_3
        //   972: istore 4
        //   974: iload_3
        //   975: istore 6
        //   977: aload_0
        //   978: aload_0
        //   979: getfield 111	kotlin/l/b/a/b/e/c/a$d$b:bitField0_	I
        //   982: iconst_4
        //   983: ior
        //   984: putfield 111	kotlin/l/b/a/b/e/c/a$d$b:bitField0_	I
        //   987: iload_3
        //   988: istore 5
        //   990: iload_3
        //   991: istore 4
        //   993: iload_3
        //   994: istore 6
        //   996: aload_0
        //   997: aload 12
        //   999: putfield 190	kotlin/l/b/a/b/e/c/a$d$b:ajdM	Ljava/lang/Object;
        //   1002: goto -951 -> 51
        //   1005: iload_3
        //   1006: bipush 16
        //   1008: iand
        //   1009: bipush 16
        //   1011: if_icmpne +14 -> 1025
        //   1014: aload_0
        //   1015: aload_0
        //   1016: getfield 122	kotlin/l/b/a/b/e/c/a$d$b:ajdO	Ljava/util/List;
        //   1019: invokestatic 128	java/util/Collections:unmodifiableList	(Ljava/util/List;)Ljava/util/List;
        //   1022: putfield 122	kotlin/l/b/a/b/e/c/a$d$b:ajdO	Ljava/util/List;
        //   1025: iload_3
        //   1026: bipush 32
        //   1028: iand
        //   1029: bipush 32
        //   1031: if_icmpne +14 -> 1045
        //   1034: aload_0
        //   1035: aload_0
        //   1036: getfield 130	kotlin/l/b/a/b/e/c/a$d$b:ajdQ	Ljava/util/List;
        //   1039: invokestatic 128	java/util/Collections:unmodifiableList	(Ljava/util/List;)Ljava/util/List;
        //   1042: putfield 130	kotlin/l/b/a/b/e/c/a$d$b:ajdQ	Ljava/util/List;
        //   1045: aload 11
        //   1047: invokevirtual 133	kotlin/l/b/a/b/h/f:flush	()V
        //   1050: aload_0
        //   1051: aload 10
        //   1053: invokevirtual 139	kotlin/l/b/a/b/h/d$b:kyc	()Lkotlin/l/b/a/b/h/d;
        //   1056: putfield 85	kotlin/l/b/a/b/e/c/a$d$b:aiXZ	Lkotlin/l/b/a/b/h/d;
        //   1059: aload_0
        //   1060: invokevirtual 142	kotlin/l/b/a/b/e/c/a$d$b:makeExtensionsImmutable	()V
        //   1063: ldc 91
        //   1065: invokestatic 68	com/tencent/matrix/trace/core/AppMethodBeat:o	(I)V
        //   1068: return
        //   1069: astore_1
        //   1070: aload_0
        //   1071: aload 10
        //   1073: invokevirtual 139	kotlin/l/b/a/b/h/d$b:kyc	()Lkotlin/l/b/a/b/h/d;
        //   1076: putfield 85	kotlin/l/b/a/b/e/c/a$d$b:aiXZ	Lkotlin/l/b/a/b/h/d;
        //   1079: goto -20 -> 1059
        //   1082: astore_1
        //   1083: aload_0
        //   1084: aload 10
        //   1086: invokevirtual 139	kotlin/l/b/a/b/h/d$b:kyc	()Lkotlin/l/b/a/b/h/d;
        //   1089: putfield 85	kotlin/l/b/a/b/e/c/a$d$b:aiXZ	Lkotlin/l/b/a/b/h/d;
        //   1092: ldc 91
        //   1094: invokestatic 68	com/tencent/matrix/trace/core/AppMethodBeat:o	(I)V
        //   1097: aload_1
        //   1098: athrow
        //   1099: astore_2
        //   1100: aload_0
        //   1101: aload 10
        //   1103: invokevirtual 139	kotlin/l/b/a/b/h/d$b:kyc	()Lkotlin/l/b/a/b/h/d;
        //   1106: putfield 85	kotlin/l/b/a/b/e/c/a$d$b:aiXZ	Lkotlin/l/b/a/b/h/d;
        //   1109: goto -804 -> 305
        //   1112: astore_1
        //   1113: aload_0
        //   1114: aload 10
        //   1116: invokevirtual 139	kotlin/l/b/a/b/h/d$b:kyc	()Lkotlin/l/b/a/b/h/d;
        //   1119: putfield 85	kotlin/l/b/a/b/e/c/a$d$b:aiXZ	Lkotlin/l/b/a/b/h/d;
        //   1122: ldc 91
        //   1124: invokestatic 68	com/tencent/matrix/trace/core/AppMethodBeat:o	(I)V
        //   1127: aload_1
        //   1128: athrow
        //   1129: goto -973 -> 156
        //   1132: iconst_1
        //   1133: istore 8
        //   1135: goto -1084 -> 51
        // Local variable table:
        //   start	length	slot	name	signature
        //   0	1138	0	this	b
        //   0	1138	1	parame	kotlin.l.b.a.b.h.e
        //   0	1138	2	paramg	g
        //   34	995	3	i	int
        //   60	932	4	j	int
        //   57	932	5	k	int
        //   63	932	6	m	int
        //   69	879	7	n	int
        //   49	1085	8	i1	int
        //   409	534	9	i2	int
        //   38	1077	10	localb	kotlin.l.b.a.b.h.d.b
        //   46	1000	11	localf	kotlin.l.b.a.b.h.f
        //   425	573	12	localObject	Object
        // Exception table:
        //   from	to	target	type
        //   65	71	223	kotlin/l/b/a/b/h/l
        //   165	178	223	kotlin/l/b/a/b/h/l
        //   193	203	223	kotlin/l/b/a/b/h/l
        //   212	220	223	kotlin/l/b/a/b/h/l
        //   325	335	223	kotlin/l/b/a/b/h/l
        //   344	352	223	kotlin/l/b/a/b/h/l
        //   405	411	223	kotlin/l/b/a/b/h/l
        //   420	427	223	kotlin/l/b/a/b/h/l
        //   441	448	223	kotlin/l/b/a/b/h/l
        //   457	464	223	kotlin/l/b/a/b/h/l
        //   476	487	223	kotlin/l/b/a/b/h/l
        //   496	502	223	kotlin/l/b/a/b/h/l
        //   526	537	223	kotlin/l/b/a/b/h/l
        //   555	572	223	kotlin/l/b/a/b/h/l
        //   587	597	223	kotlin/l/b/a/b/h/l
        //   621	628	223	kotlin/l/b/a/b/h/l
        //   637	648	223	kotlin/l/b/a/b/h/l
        //   666	673	223	kotlin/l/b/a/b/h/l
        //   685	702	223	kotlin/l/b/a/b/h/l
        //   717	723	223	kotlin/l/b/a/b/h/l
        //   750	761	223	kotlin/l/b/a/b/h/l
        //   779	796	223	kotlin/l/b/a/b/h/l
        //   811	821	223	kotlin/l/b/a/b/h/l
        //   845	852	223	kotlin/l/b/a/b/h/l
        //   861	872	223	kotlin/l/b/a/b/h/l
        //   890	897	223	kotlin/l/b/a/b/h/l
        //   909	926	223	kotlin/l/b/a/b/h/l
        //   941	947	223	kotlin/l/b/a/b/h/l
        //   962	968	223	kotlin/l/b/a/b/h/l
        //   977	987	223	kotlin/l/b/a/b/h/l
        //   996	1002	223	kotlin/l/b/a/b/h/l
        //   65	71	248	finally
        //   165	178	248	finally
        //   193	203	248	finally
        //   212	220	248	finally
        //   228	233	248	finally
        //   237	242	248	finally
        //   246	248	248	finally
        //   325	335	248	finally
        //   344	352	248	finally
        //   360	372	248	finally
        //   376	381	248	finally
        //   385	390	248	finally
        //   394	396	248	finally
        //   405	411	248	finally
        //   420	427	248	finally
        //   441	448	248	finally
        //   457	464	248	finally
        //   476	487	248	finally
        //   496	502	248	finally
        //   526	537	248	finally
        //   555	572	248	finally
        //   587	597	248	finally
        //   621	628	248	finally
        //   637	648	248	finally
        //   666	673	248	finally
        //   685	702	248	finally
        //   717	723	248	finally
        //   750	761	248	finally
        //   779	796	248	finally
        //   811	821	248	finally
        //   845	852	248	finally
        //   861	872	248	finally
        //   890	897	248	finally
        //   909	926	248	finally
        //   941	947	248	finally
        //   962	968	248	finally
        //   977	987	248	finally
        //   996	1002	248	finally
        //   65	71	355	java/io/IOException
        //   165	178	355	java/io/IOException
        //   193	203	355	java/io/IOException
        //   212	220	355	java/io/IOException
        //   325	335	355	java/io/IOException
        //   344	352	355	java/io/IOException
        //   405	411	355	java/io/IOException
        //   420	427	355	java/io/IOException
        //   441	448	355	java/io/IOException
        //   457	464	355	java/io/IOException
        //   476	487	355	java/io/IOException
        //   496	502	355	java/io/IOException
        //   526	537	355	java/io/IOException
        //   555	572	355	java/io/IOException
        //   587	597	355	java/io/IOException
        //   621	628	355	java/io/IOException
        //   637	648	355	java/io/IOException
        //   666	673	355	java/io/IOException
        //   685	702	355	java/io/IOException
        //   717	723	355	java/io/IOException
        //   750	761	355	java/io/IOException
        //   779	796	355	java/io/IOException
        //   811	821	355	java/io/IOException
        //   845	852	355	java/io/IOException
        //   861	872	355	java/io/IOException
        //   890	897	355	java/io/IOException
        //   909	926	355	java/io/IOException
        //   941	947	355	java/io/IOException
        //   962	968	355	java/io/IOException
        //   977	987	355	java/io/IOException
        //   996	1002	355	java/io/IOException
        //   1045	1050	1069	java/io/IOException
        //   1045	1050	1082	finally
        //   291	296	1099	java/io/IOException
        //   291	296	1112	finally
      }
      
      private b(i.a parama)
      {
        super();
        this.aiXZ = parama.aiXZ;
      }
      
      private void ktf()
      {
        AppMethodBeat.i(59203);
        this.ajdK = 1;
        this.ajdL = 0;
        this.ajdM = "";
        this.ajdN = b.ajdS;
        this.ajdO = Collections.emptyList();
        this.ajdQ = Collections.emptyList();
        AppMethodBeat.o(59203);
      }
      
      private kotlin.l.b.a.b.h.d kxC()
      {
        AppMethodBeat.i(59202);
        Object localObject = this.ajdM;
        if ((localObject instanceof String))
        {
          localObject = kotlin.l.b.a.b.h.d.bJj((String)localObject);
          this.ajdM = localObject;
          AppMethodBeat.o(59202);
          return localObject;
        }
        localObject = (kotlin.l.b.a.b.h.d)localObject;
        AppMethodBeat.o(59202);
        return localObject;
      }
      
      public static b kxy()
      {
        return ajdJ;
      }
      
      public final void a(kotlin.l.b.a.b.h.f paramf)
      {
        int j = 0;
        AppMethodBeat.i(59204);
        getSerializedSize();
        if ((this.bitField0_ & 0x1) == 1) {
          paramf.cF(1, this.ajdK);
        }
        if ((this.bitField0_ & 0x2) == 2) {
          paramf.cF(2, this.ajdL);
        }
        if ((this.bitField0_ & 0x8) == 8) {
          paramf.cP(3, this.ajdN.value);
        }
        if (this.ajdO.size() > 0)
        {
          paramf.lI(34);
          paramf.lI(this.ajdP);
        }
        int i = 0;
        while (i < this.ajdO.size())
        {
          paramf.kd(((Integer)this.ajdO.get(i)).intValue());
          i += 1;
        }
        i = j;
        if (this.ajdQ.size() > 0)
        {
          paramf.lI(42);
          paramf.lI(this.ajdR);
          i = j;
        }
        while (i < this.ajdQ.size())
        {
          paramf.kd(((Integer)this.ajdQ.get(i)).intValue());
          i += 1;
        }
        if ((this.bitField0_ & 0x4) == 4) {
          paramf.a(6, kxC());
        }
        paramf.e(this.aiXZ);
        AppMethodBeat.o(59204);
      }
      
      public final int getSerializedSize()
      {
        AppMethodBeat.i(59205);
        int i = this.dRJ;
        if (i != -1)
        {
          AppMethodBeat.o(59205);
          return i;
        }
        if ((this.bitField0_ & 0x1) == 1) {}
        for (i = kotlin.l.b.a.b.h.f.cJ(1, this.ajdK) + 0;; i = 0)
        {
          int j = i;
          if ((this.bitField0_ & 0x2) == 2) {
            j = i + kotlin.l.b.a.b.h.f.cJ(2, this.ajdL);
          }
          if ((this.bitField0_ & 0x8) == 8) {}
          for (i = j + kotlin.l.b.a.b.h.f.cM(3, this.ajdN.value);; i = j)
          {
            int k = 0;
            j = 0;
            while (k < this.ajdO.size())
            {
              j += kotlin.l.b.a.b.h.f.kp(((Integer)this.ajdO.get(k)).intValue());
              k += 1;
            }
            i += j;
            if (!this.ajdO.isEmpty()) {
              i = i + 1 + kotlin.l.b.a.b.h.f.kp(j);
            }
            for (;;)
            {
              this.ajdP = j;
              k = 0;
              int m;
              for (j = 0; k < this.ajdQ.size(); j = m + j)
              {
                m = kotlin.l.b.a.b.h.f.kp(((Integer)this.ajdQ.get(k)).intValue());
                k += 1;
              }
              k = i + j;
              i = k;
              if (!this.ajdQ.isEmpty()) {
                i = k + 1 + kotlin.l.b.a.b.h.f.kp(j);
              }
              this.ajdR = j;
              j = i;
              if ((this.bitField0_ & 0x4) == 4) {
                j = i + kotlin.l.b.a.b.h.f.c(kxC());
              }
              i = j + this.aiXZ.size();
              this.dRJ = i;
              AppMethodBeat.o(59205);
              return i;
            }
          }
        }
      }
      
      public final boolean isInitialized()
      {
        int i = this.memoizedIsInitialized;
        if (i == 1) {
          return true;
        }
        if (i == 0) {
          return false;
        }
        this.memoizedIsInitialized = 1;
        return true;
      }
      
      public final boolean kxA()
      {
        return (this.bitField0_ & 0x2) == 2;
      }
      
      public final boolean kxB()
      {
        return (this.bitField0_ & 0x4) == 4;
      }
      
      public final boolean kxD()
      {
        return (this.bitField0_ & 0x8) == 8;
      }
      
      public final boolean kxz()
      {
        return (this.bitField0_ & 0x1) == 1;
      }
      
      public static final class a
        extends i.a<a.d.b, a>
        implements e
      {
        private int ajdK;
        private int ajdL;
        private Object ajdM;
        private a.d.b.b ajdN;
        private List<Integer> ajdO;
        private List<Integer> ajdQ;
        private int bitField0_;
        
        private a()
        {
          AppMethodBeat.i(59179);
          this.ajdK = 1;
          this.ajdM = "";
          this.ajdN = a.d.b.b.ajdS;
          this.ajdO = Collections.emptyList();
          this.ajdQ = Collections.emptyList();
          AppMethodBeat.o(59179);
        }
        
        /* Error */
        private a F(kotlin.l.b.a.b.h.e parame, g paramg)
        {
          // Byte code:
          //   0: ldc 71
          //   2: invokestatic 39	com/tencent/matrix/trace/core/AppMethodBeat:i	(I)V
          //   5: aconst_null
          //   6: astore_3
          //   7: getstatic 75	kotlin/l/b/a/b/e/c/a$d$b:aiYa	Lkotlin/l/b/a/b/h/t;
          //   10: aload_1
          //   11: aload_2
          //   12: invokeinterface 80 3 0
          //   17: checkcast 14	kotlin/l/b/a/b/e/c/a$d$b
          //   20: astore_1
          //   21: aload_1
          //   22: ifnull +9 -> 31
          //   25: aload_0
          //   26: aload_1
          //   27: invokevirtual 84	kotlin/l/b/a/b/e/c/a$d$b$a:e	(Lkotlin/l/b/a/b/e/c/a$d$b;)Lkotlin/l/b/a/b/e/c/a$d$b$a;
          //   30: pop
          //   31: ldc 71
          //   33: invokestatic 65	com/tencent/matrix/trace/core/AppMethodBeat:o	(I)V
          //   36: aload_0
          //   37: areturn
          //   38: astore_1
          //   39: aload_1
          //   40: getfield 88	kotlin/l/b/a/b/h/l:ajfp	Lkotlin/l/b/a/b/h/r;
          //   43: checkcast 14	kotlin/l/b/a/b/e/c/a$d$b
          //   46: astore_2
          //   47: ldc 71
          //   49: invokestatic 65	com/tencent/matrix/trace/core/AppMethodBeat:o	(I)V
          //   52: aload_1
          //   53: athrow
          //   54: astore_1
          //   55: aload_2
          //   56: ifnull +9 -> 65
          //   59: aload_0
          //   60: aload_2
          //   61: invokevirtual 84	kotlin/l/b/a/b/e/c/a$d$b$a:e	(Lkotlin/l/b/a/b/e/c/a$d$b;)Lkotlin/l/b/a/b/e/c/a$d$b$a;
          //   64: pop
          //   65: ldc 71
          //   67: invokestatic 65	com/tencent/matrix/trace/core/AppMethodBeat:o	(I)V
          //   70: aload_1
          //   71: athrow
          //   72: astore_1
          //   73: aload_3
          //   74: astore_2
          //   75: goto -20 -> 55
          // Local variable table:
          //   start	length	slot	name	signature
          //   0	78	0	this	a
          //   0	78	1	parame	kotlin.l.b.a.b.h.e
          //   0	78	2	paramg	g
          //   6	68	3	localObject	Object
          // Exception table:
          //   from	to	target	type
          //   7	21	38	kotlin/l/b/a/b/h/l
          //   47	54	54	finally
          //   7	21	72	finally
          //   39	47	72	finally
        }
        
        private a a(a.d.b.b paramb)
        {
          AppMethodBeat.i(59184);
          if (paramb == null)
          {
            paramb = new NullPointerException();
            AppMethodBeat.o(59184);
            throw paramb;
          }
          this.bitField0_ |= 0x8;
          this.ajdN = paramb;
          AppMethodBeat.o(59184);
          return this;
        }
        
        private a aMe(int paramInt)
        {
          this.bitField0_ |= 0x1;
          this.ajdK = paramInt;
          return this;
        }
        
        private a aMf(int paramInt)
        {
          this.bitField0_ |= 0x2;
          this.ajdL = paramInt;
          return this;
        }
        
        private a kxE()
        {
          AppMethodBeat.i(59180);
          a locala = new a().e(kxF());
          AppMethodBeat.o(59180);
          return locala;
        }
        
        private a.d.b kxF()
        {
          int j = 1;
          AppMethodBeat.i(59181);
          a.d.b localb = new a.d.b(this, (byte)0);
          int k = this.bitField0_;
          if ((k & 0x1) == 1) {}
          for (;;)
          {
            a.d.b.a(localb, this.ajdK);
            int i = j;
            if ((k & 0x2) == 2) {
              i = j | 0x2;
            }
            a.d.b.b(localb, this.ajdL);
            j = i;
            if ((k & 0x4) == 4) {
              j = i | 0x4;
            }
            a.d.b.a(localb, this.ajdM);
            i = j;
            if ((k & 0x8) == 8) {
              i = j | 0x8;
            }
            a.d.b.a(localb, this.ajdN);
            if ((this.bitField0_ & 0x10) == 16)
            {
              this.ajdO = Collections.unmodifiableList(this.ajdO);
              this.bitField0_ &= 0xFFFFFFEF;
            }
            a.d.b.a(localb, this.ajdO);
            if ((this.bitField0_ & 0x20) == 32)
            {
              this.ajdQ = Collections.unmodifiableList(this.ajdQ);
              this.bitField0_ &= 0xFFFFFFDF;
            }
            a.d.b.b(localb, this.ajdQ);
            a.d.b.c(localb, i);
            AppMethodBeat.o(59181);
            return localb;
            j = 0;
          }
        }
        
        private void kxG()
        {
          AppMethodBeat.i(59185);
          if ((this.bitField0_ & 0x10) != 16)
          {
            this.ajdO = new ArrayList(this.ajdO);
            this.bitField0_ |= 0x10;
          }
          AppMethodBeat.o(59185);
        }
        
        private void kxH()
        {
          AppMethodBeat.i(59186);
          if ((this.bitField0_ & 0x20) != 32)
          {
            this.ajdQ = new ArrayList(this.ajdQ);
            this.bitField0_ |= 0x20;
          }
          AppMethodBeat.o(59186);
        }
        
        public final a e(a.d.b paramb)
        {
          AppMethodBeat.i(59182);
          if (paramb == a.d.b.kxy())
          {
            AppMethodBeat.o(59182);
            return this;
          }
          if (paramb.kxz()) {
            aMe(paramb.ajdK);
          }
          if (paramb.kxA()) {
            aMf(paramb.ajdL);
          }
          if (paramb.kxB())
          {
            this.bitField0_ |= 0x4;
            this.ajdM = a.d.b.a(paramb);
          }
          if (paramb.kxD()) {
            a(paramb.ajdN);
          }
          if (!a.d.b.b(paramb).isEmpty())
          {
            if (this.ajdO.isEmpty())
            {
              this.ajdO = a.d.b.b(paramb);
              this.bitField0_ &= 0xFFFFFFEF;
            }
          }
          else if (!a.d.b.c(paramb).isEmpty())
          {
            if (!this.ajdQ.isEmpty()) {
              break label221;
            }
            this.ajdQ = a.d.b.c(paramb);
            this.bitField0_ &= 0xFFFFFFDF;
          }
          for (;;)
          {
            this.aiXZ = this.aiXZ.a(a.d.b.d(paramb));
            AppMethodBeat.o(59182);
            return this;
            kxG();
            this.ajdO.addAll(a.d.b.b(paramb));
            break;
            label221:
            kxH();
            this.ajdQ.addAll(a.d.b.c(paramb));
          }
        }
        
        public final boolean isInitialized()
        {
          return true;
        }
      }
      
      public static enum b
        implements k.a
      {
        private static k.b<b> aiYE;
        final int value;
        
        static
        {
          AppMethodBeat.i(59200);
          ajdS = new b("NONE", 0, 0);
          ajdT = new b("INTERNAL_TO_CLASS_ID", 1, 1);
          ajdU = new b("DESC_TO_CLASS_ID", 2, 2);
          ajdV = new b[] { ajdS, ajdT, ajdU };
          aiYE = new k.b() {};
          AppMethodBeat.o(59200);
        }
        
        private b(int paramInt)
        {
          this.value = paramInt;
        }
        
        public static b aMg(int paramInt)
        {
          switch (paramInt)
          {
          default: 
            return null;
          case 0: 
            return ajdS;
          case 1: 
            return ajdT;
          }
          return ajdU;
        }
        
        public final int getNumber()
        {
          return this.value;
        }
      }
    }
  }
}


/* Location:           L:\local\mybackup\temp\qq_apk\com.tencent.mm\classes11.jar
 * Qualified Name:     kotlin.l.b.a.b.e.c.a
 * JD-Core Version:    0.7.0.1
 */