package com.tencent.mm.plugin.trafficmonitor;

import android.os.Process;
import com.tencent.matrix.trace.core.AppMethodBeat;
import com.tencent.mm.vfs.u;
import java.util.HashMap;
import java.util.Map;

public class b
  implements c
{
  private static b TRW;
  private final u NET_DEV_FILE;
  private final Map<Integer, Long> TRK;
  private final Map<Integer, Long> TRL;
  private final Map<Integer, Long> TRM;
  private final Map<Integer, Long> TRN;
  private final Map<Integer, Long> TRO;
  private final Map<Integer, Long> TRP;
  private final Map<Integer, Long> TRQ;
  private final Map<Integer, Long> TRR;
  private final Map<Integer, Long> TRS;
  private final Map<Integer, Long> TRT;
  private final Map<Integer, Long> TRU;
  private final Map<Integer, Long> TRV;
  private final u XT_STATS_FILE;
  
  private b()
  {
    AppMethodBeat.i(260736);
    this.TRO = new HashMap();
    this.TRP = new HashMap();
    this.TRQ = new HashMap();
    this.TRR = new HashMap();
    this.TRS = new HashMap();
    this.TRT = new HashMap();
    this.TRU = new HashMap();
    this.TRV = new HashMap();
    this.TRK = new HashMap();
    this.TRL = new HashMap();
    this.TRM = new HashMap();
    this.TRN = new HashMap();
    Object localObject1 = new u("/proc/" + Process.myPid() + "/net/dev");
    if (((u)localObject1).jKV()) {}
    for (;;)
    {
      this.NET_DEV_FILE = ((u)localObject1);
      u localu = new u("/proc/net/xt_qtaguid/stats");
      localObject1 = localObject2;
      if (localu.jKV()) {
        localObject1 = localu;
      }
      this.XT_STATS_FILE = ((u)localObject1);
      AppMethodBeat.o(260736);
      return;
      localObject1 = null;
    }
  }
  
  /* Error */
  public static b hPk()
  {
    // Byte code:
    //   0: ldc 109
    //   2: invokestatic 36	com/tencent/matrix/trace/core/AppMethodBeat:i	(I)V
    //   5: ldc 2
    //   7: monitorenter
    //   8: getstatic 111	com/tencent/mm/plugin/trafficmonitor/b:TRW	Lcom/tencent/mm/plugin/trafficmonitor/b;
    //   11: ifnonnull +19 -> 30
    //   14: ldc 2
    //   16: monitorenter
    //   17: new 2	com/tencent/mm/plugin/trafficmonitor/b
    //   20: dup
    //   21: invokespecial 112	com/tencent/mm/plugin/trafficmonitor/b:<init>	()V
    //   24: putstatic 111	com/tencent/mm/plugin/trafficmonitor/b:TRW	Lcom/tencent/mm/plugin/trafficmonitor/b;
    //   27: ldc 2
    //   29: monitorexit
    //   30: ldc 2
    //   32: monitorexit
    //   33: getstatic 111	com/tencent/mm/plugin/trafficmonitor/b:TRW	Lcom/tencent/mm/plugin/trafficmonitor/b;
    //   36: astore_0
    //   37: ldc 109
    //   39: invokestatic 105	com/tencent/matrix/trace/core/AppMethodBeat:o	(I)V
    //   42: aload_0
    //   43: areturn
    //   44: astore_0
    //   45: ldc 2
    //   47: monitorexit
    //   48: ldc 109
    //   50: invokestatic 105	com/tencent/matrix/trace/core/AppMethodBeat:o	(I)V
    //   53: aload_0
    //   54: athrow
    //   55: astore_0
    //   56: ldc 2
    //   58: monitorexit
    //   59: ldc 109
    //   61: invokestatic 105	com/tencent/matrix/trace/core/AppMethodBeat:o	(I)V
    //   64: aload_0
    //   65: athrow
    // Local variable table:
    //   start	length	slot	name	signature
    //   36	7	0	localb	b
    //   44	10	0	localObject1	Object
    //   55	10	0	localObject2	Object
    // Exception table:
    //   from	to	target	type
    //   17	30	44	finally
    //   8	17	55	finally
    //   30	33	55	finally
    //   45	55	55	finally
  }
  
  public final long apg(int paramInt)
  {
    AppMethodBeat.i(123881);
    if (this.TRU == null)
    {
      AppMethodBeat.o(123881);
      return 0L;
    }
    if (this.TRU.get(Integer.valueOf(paramInt)) == null)
    {
      AppMethodBeat.o(123881);
      return 0L;
    }
    if (((Long)this.TRU.get(Integer.valueOf(paramInt))).longValue() > 0L)
    {
      long l = ((Long)this.TRU.get(Integer.valueOf(paramInt))).longValue();
      AppMethodBeat.o(123881);
      return l;
    }
    AppMethodBeat.o(123881);
    return 0L;
  }
  
  public final long aph(int paramInt)
  {
    AppMethodBeat.i(123882);
    if (this.TRV == null)
    {
      AppMethodBeat.o(123882);
      return 0L;
    }
    if (this.TRV.get(Integer.valueOf(paramInt)) == null)
    {
      AppMethodBeat.o(123882);
      return 0L;
    }
    if (((Long)this.TRV.get(Integer.valueOf(paramInt))).longValue() > 0L)
    {
      long l = ((Long)this.TRV.get(Integer.valueOf(paramInt))).longValue();
      AppMethodBeat.o(123882);
      return l;
    }
    AppMethodBeat.o(123882);
    return 0L;
  }
  
  public final long api(int paramInt)
  {
    AppMethodBeat.i(123883);
    if (this.TRS == null)
    {
      AppMethodBeat.o(123883);
      return 0L;
    }
    if (this.TRS.get(Integer.valueOf(paramInt)) == null)
    {
      AppMethodBeat.o(123883);
      return 0L;
    }
    if (((Long)this.TRS.get(Integer.valueOf(paramInt))).longValue() > 0L)
    {
      long l = ((Long)this.TRS.get(Integer.valueOf(paramInt))).longValue();
      AppMethodBeat.o(123883);
      return l;
    }
    AppMethodBeat.o(123883);
    return 0L;
  }
  
  public final long apj(int paramInt)
  {
    AppMethodBeat.i(123884);
    if (this.TRT == null)
    {
      AppMethodBeat.o(123884);
      return 0L;
    }
    if (this.TRT.get(Integer.valueOf(paramInt)) == null)
    {
      AppMethodBeat.o(123884);
      return 0L;
    }
    if (((Long)this.TRT.get(Integer.valueOf(paramInt))).longValue() > 0L)
    {
      long l = ((Long)this.TRT.get(Integer.valueOf(paramInt))).longValue();
      AppMethodBeat.o(123884);
      return l;
    }
    AppMethodBeat.o(123884);
    return 0L;
  }
  
  public final void iF(int paramInt)
  {
    AppMethodBeat.i(123885);
    this.TRP.put(Integer.valueOf(paramInt), Long.valueOf(-1L));
    this.TRO.put(Integer.valueOf(paramInt), Long.valueOf(-1L));
    this.TRR.put(Integer.valueOf(paramInt), Long.valueOf(-1L));
    this.TRQ.put(Integer.valueOf(paramInt), Long.valueOf(-1L));
    this.TRL.put(Integer.valueOf(paramInt), Long.valueOf(-1L));
    this.TRK.put(Integer.valueOf(paramInt), Long.valueOf(-1L));
    this.TRN.put(Integer.valueOf(paramInt), Long.valueOf(-1L));
    this.TRM.put(Integer.valueOf(paramInt), Long.valueOf(-1L));
    update(paramInt);
    AppMethodBeat.o(123885);
  }
  
  public final void sE(int paramInt)
  {
    AppMethodBeat.i(123878);
    this.TRO.put(Integer.valueOf(paramInt), Long.valueOf(0L));
    this.TRP.put(Integer.valueOf(paramInt), Long.valueOf(0L));
    this.TRQ.put(Integer.valueOf(paramInt), Long.valueOf(0L));
    this.TRR.put(Integer.valueOf(paramInt), Long.valueOf(0L));
    this.TRS.put(Integer.valueOf(paramInt), Long.valueOf(0L));
    this.TRT.put(Integer.valueOf(paramInt), Long.valueOf(0L));
    this.TRU.put(Integer.valueOf(paramInt), Long.valueOf(0L));
    this.TRV.put(Integer.valueOf(paramInt), Long.valueOf(0L));
    this.TRK.put(Integer.valueOf(paramInt), Long.valueOf(0L));
    this.TRL.put(Integer.valueOf(paramInt), Long.valueOf(0L));
    this.TRM.put(Integer.valueOf(paramInt), Long.valueOf(0L));
    this.TRN.put(Integer.valueOf(paramInt), Long.valueOf(0L));
    AppMethodBeat.o(123878);
  }
  
  /* Error */
  public final void update(int paramInt)
  {
    // Byte code:
    //   0: ldc 158
    //   2: invokestatic 36	com/tencent/matrix/trace/core/AppMethodBeat:i	(I)V
    //   5: lconst_0
    //   6: lstore 7
    //   8: lconst_0
    //   9: lstore 5
    //   11: lconst_0
    //   12: lstore 9
    //   14: lconst_0
    //   15: lstore_3
    //   16: lconst_0
    //   17: lstore 13
    //   19: lconst_0
    //   20: lstore 11
    //   22: aconst_null
    //   23: astore 15
    //   25: aload_0
    //   26: getfield 98	com/tencent/mm/plugin/trafficmonitor/b:NET_DEV_FILE	Lcom/tencent/mm/vfs/u;
    //   29: ifnull +625 -> 654
    //   32: new 160	java/io/BufferedReader
    //   35: dup
    //   36: new 162	com/tencent/mm/vfs/ab
    //   39: dup
    //   40: aload_0
    //   41: getfield 98	com/tencent/mm/plugin/trafficmonitor/b:NET_DEV_FILE	Lcom/tencent/mm/vfs/u;
    //   44: invokespecial 165	com/tencent/mm/vfs/ab:<init>	(Lcom/tencent/mm/vfs/u;)V
    //   47: invokespecial 168	java/io/BufferedReader:<init>	(Ljava/io/Reader;)V
    //   50: astore 17
    //   52: aload 17
    //   54: astore 15
    //   56: aload 17
    //   58: astore 16
    //   60: aload 17
    //   62: invokevirtual 171	java/io/BufferedReader:readLine	()Ljava/lang/String;
    //   65: pop
    //   66: aload 17
    //   68: astore 15
    //   70: aload 17
    //   72: astore 16
    //   74: aload 17
    //   76: invokevirtual 171	java/io/BufferedReader:readLine	()Ljava/lang/String;
    //   79: pop
    //   80: aload 17
    //   82: astore 15
    //   84: aload 17
    //   86: astore 16
    //   88: aload 17
    //   90: invokevirtual 171	java/io/BufferedReader:readLine	()Ljava/lang/String;
    //   93: astore 18
    //   95: aload 18
    //   97: ifnull +198 -> 295
    //   100: aload 17
    //   102: astore 15
    //   104: aload 17
    //   106: astore 16
    //   108: aload 18
    //   110: ldc 173
    //   112: invokevirtual 179	java/lang/String:split	(Ljava/lang/String;)[Ljava/lang/String;
    //   115: astore 18
    //   117: aload 17
    //   119: astore 15
    //   121: aload 17
    //   123: astore 16
    //   125: aload 18
    //   127: iconst_0
    //   128: aaload
    //   129: invokevirtual 182	java/lang/String:length	()I
    //   132: ifne +1815 -> 1947
    //   135: iconst_1
    //   136: istore_2
    //   137: aload 17
    //   139: astore 15
    //   141: aload 17
    //   143: astore 16
    //   145: aload 18
    //   147: iload_2
    //   148: aaload
    //   149: ldc 184
    //   151: invokevirtual 188	java/lang/String:equals	(Ljava/lang/Object;)Z
    //   154: ifne +1790 -> 1944
    //   157: aload 17
    //   159: astore 15
    //   161: aload 17
    //   163: astore 16
    //   165: aload 18
    //   167: iload_2
    //   168: aaload
    //   169: ldc 190
    //   171: invokevirtual 194	java/lang/String:startsWith	(Ljava/lang/String;)Z
    //   174: ifne +23 -> 197
    //   177: aload 17
    //   179: astore 15
    //   181: aload 17
    //   183: astore 16
    //   185: aload 18
    //   187: iload_2
    //   188: aaload
    //   189: ldc 196
    //   191: invokevirtual 194	java/lang/String:startsWith	(Ljava/lang/String;)Z
    //   194: ifeq +53 -> 247
    //   197: aload 17
    //   199: astore 15
    //   201: aload 17
    //   203: astore 16
    //   205: lload 7
    //   207: aload 18
    //   209: iload_2
    //   210: bipush 9
    //   212: iadd
    //   213: aaload
    //   214: lconst_0
    //   215: invokestatic 202	com/tencent/mm/sdk/platformtools/Util:getLong	(Ljava/lang/String;J)J
    //   218: ladd
    //   219: lstore 7
    //   221: aload 17
    //   223: astore 15
    //   225: aload 17
    //   227: astore 16
    //   229: aload 18
    //   231: iload_2
    //   232: iconst_1
    //   233: iadd
    //   234: aaload
    //   235: lconst_0
    //   236: invokestatic 202	com/tencent/mm/sdk/platformtools/Util:getLong	(Ljava/lang/String;J)J
    //   239: lload 5
    //   241: ladd
    //   242: lstore 5
    //   244: goto -164 -> 80
    //   247: aload 17
    //   249: astore 15
    //   251: aload 17
    //   253: astore 16
    //   255: lload 9
    //   257: aload 18
    //   259: iload_2
    //   260: bipush 9
    //   262: iadd
    //   263: aaload
    //   264: lconst_0
    //   265: invokestatic 202	com/tencent/mm/sdk/platformtools/Util:getLong	(Ljava/lang/String;J)J
    //   268: ladd
    //   269: lstore 9
    //   271: aload 17
    //   273: astore 15
    //   275: aload 17
    //   277: astore 16
    //   279: aload 18
    //   281: iload_2
    //   282: iconst_1
    //   283: iadd
    //   284: aaload
    //   285: lconst_0
    //   286: invokestatic 202	com/tencent/mm/sdk/platformtools/Util:getLong	(Ljava/lang/String;J)J
    //   289: lload_3
    //   290: ladd
    //   291: lstore_3
    //   292: goto +1660 -> 1952
    //   295: aload 17
    //   297: astore 15
    //   299: aload 17
    //   301: astore 16
    //   303: aload_0
    //   304: getfield 57	com/tencent/mm/plugin/trafficmonitor/b:TRK	Ljava/util/Map;
    //   307: iload_1
    //   308: invokestatic 121	java/lang/Integer:valueOf	(I)Ljava/lang/Integer;
    //   311: invokeinterface 127 2 0
    //   316: checkcast 129	java/lang/Long
    //   319: invokevirtual 133	java/lang/Long:longValue	()J
    //   322: lconst_0
    //   323: lcmp
    //   324: ifge +30 -> 354
    //   327: aload 17
    //   329: astore 15
    //   331: aload 17
    //   333: astore 16
    //   335: aload_0
    //   336: getfield 57	com/tencent/mm/plugin/trafficmonitor/b:TRK	Ljava/util/Map;
    //   339: iload_1
    //   340: invokestatic 121	java/lang/Integer:valueOf	(I)Ljava/lang/Integer;
    //   343: lload 7
    //   345: invokestatic 146	java/lang/Long:valueOf	(J)Ljava/lang/Long;
    //   348: invokeinterface 150 3 0
    //   353: pop
    //   354: aload 17
    //   356: astore 15
    //   358: aload 17
    //   360: astore 16
    //   362: aload_0
    //   363: getfield 59	com/tencent/mm/plugin/trafficmonitor/b:TRL	Ljava/util/Map;
    //   366: iload_1
    //   367: invokestatic 121	java/lang/Integer:valueOf	(I)Ljava/lang/Integer;
    //   370: invokeinterface 127 2 0
    //   375: checkcast 129	java/lang/Long
    //   378: invokevirtual 133	java/lang/Long:longValue	()J
    //   381: lconst_0
    //   382: lcmp
    //   383: ifge +30 -> 413
    //   386: aload 17
    //   388: astore 15
    //   390: aload 17
    //   392: astore 16
    //   394: aload_0
    //   395: getfield 59	com/tencent/mm/plugin/trafficmonitor/b:TRL	Ljava/util/Map;
    //   398: iload_1
    //   399: invokestatic 121	java/lang/Integer:valueOf	(I)Ljava/lang/Integer;
    //   402: lload 5
    //   404: invokestatic 146	java/lang/Long:valueOf	(J)Ljava/lang/Long;
    //   407: invokeinterface 150 3 0
    //   412: pop
    //   413: aload 17
    //   415: astore 15
    //   417: aload 17
    //   419: astore 16
    //   421: aload_0
    //   422: getfield 61	com/tencent/mm/plugin/trafficmonitor/b:TRM	Ljava/util/Map;
    //   425: iload_1
    //   426: invokestatic 121	java/lang/Integer:valueOf	(I)Ljava/lang/Integer;
    //   429: invokeinterface 127 2 0
    //   434: checkcast 129	java/lang/Long
    //   437: invokevirtual 133	java/lang/Long:longValue	()J
    //   440: lconst_0
    //   441: lcmp
    //   442: ifge +30 -> 472
    //   445: aload 17
    //   447: astore 15
    //   449: aload 17
    //   451: astore 16
    //   453: aload_0
    //   454: getfield 61	com/tencent/mm/plugin/trafficmonitor/b:TRM	Ljava/util/Map;
    //   457: iload_1
    //   458: invokestatic 121	java/lang/Integer:valueOf	(I)Ljava/lang/Integer;
    //   461: lload 9
    //   463: invokestatic 146	java/lang/Long:valueOf	(J)Ljava/lang/Long;
    //   466: invokeinterface 150 3 0
    //   471: pop
    //   472: aload 17
    //   474: astore 15
    //   476: aload 17
    //   478: astore 16
    //   480: aload_0
    //   481: getfield 63	com/tencent/mm/plugin/trafficmonitor/b:TRN	Ljava/util/Map;
    //   484: iload_1
    //   485: invokestatic 121	java/lang/Integer:valueOf	(I)Ljava/lang/Integer;
    //   488: invokeinterface 127 2 0
    //   493: checkcast 129	java/lang/Long
    //   496: invokevirtual 133	java/lang/Long:longValue	()J
    //   499: lconst_0
    //   500: lcmp
    //   501: ifge +29 -> 530
    //   504: aload 17
    //   506: astore 15
    //   508: aload 17
    //   510: astore 16
    //   512: aload_0
    //   513: getfield 63	com/tencent/mm/plugin/trafficmonitor/b:TRN	Ljava/util/Map;
    //   516: iload_1
    //   517: invokestatic 121	java/lang/Integer:valueOf	(I)Ljava/lang/Integer;
    //   520: lload_3
    //   521: invokestatic 146	java/lang/Long:valueOf	(J)Ljava/lang/Long;
    //   524: invokeinterface 150 3 0
    //   529: pop
    //   530: aload 17
    //   532: astore 15
    //   534: aload 17
    //   536: astore 16
    //   538: aload_0
    //   539: getfield 57	com/tencent/mm/plugin/trafficmonitor/b:TRK	Ljava/util/Map;
    //   542: iload_1
    //   543: invokestatic 121	java/lang/Integer:valueOf	(I)Ljava/lang/Integer;
    //   546: lload 7
    //   548: invokestatic 146	java/lang/Long:valueOf	(J)Ljava/lang/Long;
    //   551: invokeinterface 150 3 0
    //   556: pop
    //   557: aload 17
    //   559: astore 15
    //   561: aload 17
    //   563: astore 16
    //   565: aload_0
    //   566: getfield 59	com/tencent/mm/plugin/trafficmonitor/b:TRL	Ljava/util/Map;
    //   569: iload_1
    //   570: invokestatic 121	java/lang/Integer:valueOf	(I)Ljava/lang/Integer;
    //   573: lload 5
    //   575: invokestatic 146	java/lang/Long:valueOf	(J)Ljava/lang/Long;
    //   578: invokeinterface 150 3 0
    //   583: pop
    //   584: aload 17
    //   586: astore 15
    //   588: aload 17
    //   590: astore 16
    //   592: aload_0
    //   593: getfield 61	com/tencent/mm/plugin/trafficmonitor/b:TRM	Ljava/util/Map;
    //   596: iload_1
    //   597: invokestatic 121	java/lang/Integer:valueOf	(I)Ljava/lang/Integer;
    //   600: lload 9
    //   602: invokestatic 146	java/lang/Long:valueOf	(J)Ljava/lang/Long;
    //   605: invokeinterface 150 3 0
    //   610: pop
    //   611: aload 17
    //   613: astore 15
    //   615: aload 17
    //   617: astore 16
    //   619: aload_0
    //   620: getfield 63	com/tencent/mm/plugin/trafficmonitor/b:TRN	Ljava/util/Map;
    //   623: iload_1
    //   624: invokestatic 121	java/lang/Integer:valueOf	(I)Ljava/lang/Integer;
    //   627: lload_3
    //   628: invokestatic 146	java/lang/Long:valueOf	(J)Ljava/lang/Long;
    //   631: invokeinterface 150 3 0
    //   636: pop
    //   637: aload 17
    //   639: astore 15
    //   641: aload 17
    //   643: astore 16
    //   645: aload 17
    //   647: invokestatic 206	com/tencent/mm/sdk/platformtools/Util:qualityClose	(Ljava/io/Closeable;)V
    //   650: aload 17
    //   652: astore 15
    //   654: aload 15
    //   656: astore 16
    //   658: aload_0
    //   659: getfield 102	com/tencent/mm/plugin/trafficmonitor/b:XT_STATS_FILE	Lcom/tencent/mm/vfs/u;
    //   662: ifnull +999 -> 1661
    //   665: invokestatic 209	android/os/Process:myUid	()I
    //   668: istore_2
    //   669: new 160	java/io/BufferedReader
    //   672: dup
    //   673: new 162	com/tencent/mm/vfs/ab
    //   676: dup
    //   677: aload_0
    //   678: getfield 102	com/tencent/mm/plugin/trafficmonitor/b:XT_STATS_FILE	Lcom/tencent/mm/vfs/u;
    //   681: invokespecial 165	com/tencent/mm/vfs/ab:<init>	(Lcom/tencent/mm/vfs/u;)V
    //   684: invokespecial 168	java/io/BufferedReader:<init>	(Ljava/io/Reader;)V
    //   687: astore 17
    //   689: aload 17
    //   691: astore 15
    //   693: aload 17
    //   695: astore 16
    //   697: aload 17
    //   699: invokevirtual 171	java/io/BufferedReader:readLine	()Ljava/lang/String;
    //   702: pop
    //   703: lconst_0
    //   704: lstore_3
    //   705: lconst_0
    //   706: lstore 9
    //   708: lload 13
    //   710: lstore 5
    //   712: lload 11
    //   714: lstore 7
    //   716: aload 17
    //   718: astore 15
    //   720: aload 17
    //   722: astore 16
    //   724: aload 17
    //   726: invokevirtual 171	java/io/BufferedReader:readLine	()Ljava/lang/String;
    //   729: astore 18
    //   731: aload 18
    //   733: ifnull +155 -> 888
    //   736: aload 17
    //   738: astore 15
    //   740: aload 17
    //   742: astore 16
    //   744: aload 18
    //   746: ldc 211
    //   748: invokevirtual 179	java/lang/String:split	(Ljava/lang/String;)[Ljava/lang/String;
    //   751: astore 18
    //   753: aload 17
    //   755: astore 15
    //   757: aload 17
    //   759: astore 16
    //   761: aload 18
    //   763: iconst_3
    //   764: aaload
    //   765: iconst_0
    //   766: invokestatic 215	com/tencent/mm/sdk/platformtools/Util:getInt	(Ljava/lang/String;I)I
    //   769: iload_2
    //   770: if_icmpne -54 -> 716
    //   773: aload 18
    //   775: iconst_1
    //   776: aaload
    //   777: astore 19
    //   779: aload 17
    //   781: astore 15
    //   783: aload 17
    //   785: astore 16
    //   787: aload 18
    //   789: iconst_5
    //   790: aaload
    //   791: lconst_0
    //   792: invokestatic 202	com/tencent/mm/sdk/platformtools/Util:getLong	(Ljava/lang/String;J)J
    //   795: lstore 13
    //   797: aload 17
    //   799: astore 15
    //   801: aload 17
    //   803: astore 16
    //   805: aload 18
    //   807: bipush 7
    //   809: aaload
    //   810: lconst_0
    //   811: invokestatic 202	com/tencent/mm/sdk/platformtools/Util:getLong	(Ljava/lang/String;J)J
    //   814: lstore 11
    //   816: aload 17
    //   818: astore 15
    //   820: aload 17
    //   822: astore 16
    //   824: aload 19
    //   826: ldc 190
    //   828: invokevirtual 194	java/lang/String:startsWith	(Ljava/lang/String;)Z
    //   831: ifne +1124 -> 1955
    //   834: aload 17
    //   836: astore 15
    //   838: aload 17
    //   840: astore 16
    //   842: aload 19
    //   844: ldc 196
    //   846: invokevirtual 194	java/lang/String:startsWith	(Ljava/lang/String;)Z
    //   849: ifeq +6 -> 855
    //   852: goto +1103 -> 1955
    //   855: aload 17
    //   857: astore 15
    //   859: aload 17
    //   861: astore 16
    //   863: aload 19
    //   865: ldc 184
    //   867: invokevirtual 188	java/lang/String:equals	(Ljava/lang/Object;)Z
    //   870: ifne +1071 -> 1941
    //   873: lload_3
    //   874: lload 13
    //   876: ladd
    //   877: lstore_3
    //   878: lload 9
    //   880: lload 11
    //   882: ladd
    //   883: lstore 9
    //   885: goto +1087 -> 1972
    //   888: aload 17
    //   890: astore 15
    //   892: aload 17
    //   894: astore 16
    //   896: aload_0
    //   897: getfield 43	com/tencent/mm/plugin/trafficmonitor/b:TRP	Ljava/util/Map;
    //   900: iload_1
    //   901: invokestatic 121	java/lang/Integer:valueOf	(I)Ljava/lang/Integer;
    //   904: invokeinterface 127 2 0
    //   909: checkcast 129	java/lang/Long
    //   912: invokevirtual 133	java/lang/Long:longValue	()J
    //   915: lconst_0
    //   916: lcmp
    //   917: ifge +30 -> 947
    //   920: aload 17
    //   922: astore 15
    //   924: aload 17
    //   926: astore 16
    //   928: aload_0
    //   929: getfield 43	com/tencent/mm/plugin/trafficmonitor/b:TRP	Ljava/util/Map;
    //   932: iload_1
    //   933: invokestatic 121	java/lang/Integer:valueOf	(I)Ljava/lang/Integer;
    //   936: lload 7
    //   938: invokestatic 146	java/lang/Long:valueOf	(J)Ljava/lang/Long;
    //   941: invokeinterface 150 3 0
    //   946: pop
    //   947: aload 17
    //   949: astore 15
    //   951: aload 17
    //   953: astore 16
    //   955: aload_0
    //   956: getfield 41	com/tencent/mm/plugin/trafficmonitor/b:TRO	Ljava/util/Map;
    //   959: iload_1
    //   960: invokestatic 121	java/lang/Integer:valueOf	(I)Ljava/lang/Integer;
    //   963: invokeinterface 127 2 0
    //   968: checkcast 129	java/lang/Long
    //   971: invokevirtual 133	java/lang/Long:longValue	()J
    //   974: lconst_0
    //   975: lcmp
    //   976: ifge +30 -> 1006
    //   979: aload 17
    //   981: astore 15
    //   983: aload 17
    //   985: astore 16
    //   987: aload_0
    //   988: getfield 41	com/tencent/mm/plugin/trafficmonitor/b:TRO	Ljava/util/Map;
    //   991: iload_1
    //   992: invokestatic 121	java/lang/Integer:valueOf	(I)Ljava/lang/Integer;
    //   995: lload 5
    //   997: invokestatic 146	java/lang/Long:valueOf	(J)Ljava/lang/Long;
    //   1000: invokeinterface 150 3 0
    //   1005: pop
    //   1006: aload 17
    //   1008: astore 15
    //   1010: aload 17
    //   1012: astore 16
    //   1014: aload_0
    //   1015: getfield 47	com/tencent/mm/plugin/trafficmonitor/b:TRR	Ljava/util/Map;
    //   1018: iload_1
    //   1019: invokestatic 121	java/lang/Integer:valueOf	(I)Ljava/lang/Integer;
    //   1022: invokeinterface 127 2 0
    //   1027: checkcast 129	java/lang/Long
    //   1030: invokevirtual 133	java/lang/Long:longValue	()J
    //   1033: lconst_0
    //   1034: lcmp
    //   1035: ifge +29 -> 1064
    //   1038: aload 17
    //   1040: astore 15
    //   1042: aload 17
    //   1044: astore 16
    //   1046: aload_0
    //   1047: getfield 47	com/tencent/mm/plugin/trafficmonitor/b:TRR	Ljava/util/Map;
    //   1050: iload_1
    //   1051: invokestatic 121	java/lang/Integer:valueOf	(I)Ljava/lang/Integer;
    //   1054: lload_3
    //   1055: invokestatic 146	java/lang/Long:valueOf	(J)Ljava/lang/Long;
    //   1058: invokeinterface 150 3 0
    //   1063: pop
    //   1064: aload 17
    //   1066: astore 15
    //   1068: aload 17
    //   1070: astore 16
    //   1072: aload_0
    //   1073: getfield 45	com/tencent/mm/plugin/trafficmonitor/b:TRQ	Ljava/util/Map;
    //   1076: iload_1
    //   1077: invokestatic 121	java/lang/Integer:valueOf	(I)Ljava/lang/Integer;
    //   1080: invokeinterface 127 2 0
    //   1085: checkcast 129	java/lang/Long
    //   1088: invokevirtual 133	java/lang/Long:longValue	()J
    //   1091: lconst_0
    //   1092: lcmp
    //   1093: ifge +30 -> 1123
    //   1096: aload 17
    //   1098: astore 15
    //   1100: aload 17
    //   1102: astore 16
    //   1104: aload_0
    //   1105: getfield 45	com/tencent/mm/plugin/trafficmonitor/b:TRQ	Ljava/util/Map;
    //   1108: iload_1
    //   1109: invokestatic 121	java/lang/Integer:valueOf	(I)Ljava/lang/Integer;
    //   1112: lload 9
    //   1114: invokestatic 146	java/lang/Long:valueOf	(J)Ljava/lang/Long;
    //   1117: invokeinterface 150 3 0
    //   1122: pop
    //   1123: aload 17
    //   1125: astore 15
    //   1127: aload 17
    //   1129: astore 16
    //   1131: aload_0
    //   1132: getfield 49	com/tencent/mm/plugin/trafficmonitor/b:TRS	Ljava/util/Map;
    //   1135: astore 18
    //   1137: aload 17
    //   1139: astore 15
    //   1141: aload 17
    //   1143: astore 16
    //   1145: lload 5
    //   1147: aload_0
    //   1148: getfield 41	com/tencent/mm/plugin/trafficmonitor/b:TRO	Ljava/util/Map;
    //   1151: iload_1
    //   1152: invokestatic 121	java/lang/Integer:valueOf	(I)Ljava/lang/Integer;
    //   1155: invokeinterface 127 2 0
    //   1160: checkcast 129	java/lang/Long
    //   1163: invokevirtual 133	java/lang/Long:longValue	()J
    //   1166: lcmp
    //   1167: iflt +505 -> 1672
    //   1170: aload 17
    //   1172: astore 15
    //   1174: aload 17
    //   1176: astore 16
    //   1178: lload 5
    //   1180: aload_0
    //   1181: getfield 41	com/tencent/mm/plugin/trafficmonitor/b:TRO	Ljava/util/Map;
    //   1184: iload_1
    //   1185: invokestatic 121	java/lang/Integer:valueOf	(I)Ljava/lang/Integer;
    //   1188: invokeinterface 127 2 0
    //   1193: checkcast 129	java/lang/Long
    //   1196: invokevirtual 133	java/lang/Long:longValue	()J
    //   1199: lsub
    //   1200: lstore 11
    //   1202: aload 17
    //   1204: astore 15
    //   1206: aload 17
    //   1208: astore 16
    //   1210: aload 18
    //   1212: iload_1
    //   1213: invokestatic 121	java/lang/Integer:valueOf	(I)Ljava/lang/Integer;
    //   1216: lload 11
    //   1218: invokestatic 146	java/lang/Long:valueOf	(J)Ljava/lang/Long;
    //   1221: invokeinterface 150 3 0
    //   1226: pop
    //   1227: aload 17
    //   1229: astore 15
    //   1231: aload 17
    //   1233: astore 16
    //   1235: aload_0
    //   1236: getfield 51	com/tencent/mm/plugin/trafficmonitor/b:TRT	Ljava/util/Map;
    //   1239: astore 18
    //   1241: aload 17
    //   1243: astore 15
    //   1245: aload 17
    //   1247: astore 16
    //   1249: lload 7
    //   1251: aload_0
    //   1252: getfield 43	com/tencent/mm/plugin/trafficmonitor/b:TRP	Ljava/util/Map;
    //   1255: iload_1
    //   1256: invokestatic 121	java/lang/Integer:valueOf	(I)Ljava/lang/Integer;
    //   1259: invokeinterface 127 2 0
    //   1264: checkcast 129	java/lang/Long
    //   1267: invokevirtual 133	java/lang/Long:longValue	()J
    //   1270: lcmp
    //   1271: iflt +408 -> 1679
    //   1274: aload 17
    //   1276: astore 15
    //   1278: aload 17
    //   1280: astore 16
    //   1282: lload 7
    //   1284: aload_0
    //   1285: getfield 43	com/tencent/mm/plugin/trafficmonitor/b:TRP	Ljava/util/Map;
    //   1288: iload_1
    //   1289: invokestatic 121	java/lang/Integer:valueOf	(I)Ljava/lang/Integer;
    //   1292: invokeinterface 127 2 0
    //   1297: checkcast 129	java/lang/Long
    //   1300: invokevirtual 133	java/lang/Long:longValue	()J
    //   1303: lsub
    //   1304: lstore 11
    //   1306: aload 17
    //   1308: astore 15
    //   1310: aload 17
    //   1312: astore 16
    //   1314: aload 18
    //   1316: iload_1
    //   1317: invokestatic 121	java/lang/Integer:valueOf	(I)Ljava/lang/Integer;
    //   1320: lload 11
    //   1322: invokestatic 146	java/lang/Long:valueOf	(J)Ljava/lang/Long;
    //   1325: invokeinterface 150 3 0
    //   1330: pop
    //   1331: aload 17
    //   1333: astore 15
    //   1335: aload 17
    //   1337: astore 16
    //   1339: aload_0
    //   1340: getfield 53	com/tencent/mm/plugin/trafficmonitor/b:TRU	Ljava/util/Map;
    //   1343: astore 18
    //   1345: aload 17
    //   1347: astore 15
    //   1349: aload 17
    //   1351: astore 16
    //   1353: lload 9
    //   1355: aload_0
    //   1356: getfield 45	com/tencent/mm/plugin/trafficmonitor/b:TRQ	Ljava/util/Map;
    //   1359: iload_1
    //   1360: invokestatic 121	java/lang/Integer:valueOf	(I)Ljava/lang/Integer;
    //   1363: invokeinterface 127 2 0
    //   1368: checkcast 129	java/lang/Long
    //   1371: invokevirtual 133	java/lang/Long:longValue	()J
    //   1374: lcmp
    //   1375: iflt +311 -> 1686
    //   1378: aload 17
    //   1380: astore 15
    //   1382: aload 17
    //   1384: astore 16
    //   1386: lload 9
    //   1388: aload_0
    //   1389: getfield 45	com/tencent/mm/plugin/trafficmonitor/b:TRQ	Ljava/util/Map;
    //   1392: iload_1
    //   1393: invokestatic 121	java/lang/Integer:valueOf	(I)Ljava/lang/Integer;
    //   1396: invokeinterface 127 2 0
    //   1401: checkcast 129	java/lang/Long
    //   1404: invokevirtual 133	java/lang/Long:longValue	()J
    //   1407: lsub
    //   1408: lstore 11
    //   1410: aload 17
    //   1412: astore 15
    //   1414: aload 17
    //   1416: astore 16
    //   1418: aload 18
    //   1420: iload_1
    //   1421: invokestatic 121	java/lang/Integer:valueOf	(I)Ljava/lang/Integer;
    //   1424: lload 11
    //   1426: invokestatic 146	java/lang/Long:valueOf	(J)Ljava/lang/Long;
    //   1429: invokeinterface 150 3 0
    //   1434: pop
    //   1435: aload 17
    //   1437: astore 15
    //   1439: aload 17
    //   1441: astore 16
    //   1443: aload_0
    //   1444: getfield 55	com/tencent/mm/plugin/trafficmonitor/b:TRV	Ljava/util/Map;
    //   1447: astore 18
    //   1449: aload 17
    //   1451: astore 15
    //   1453: aload 17
    //   1455: astore 16
    //   1457: lload_3
    //   1458: aload_0
    //   1459: getfield 47	com/tencent/mm/plugin/trafficmonitor/b:TRR	Ljava/util/Map;
    //   1462: iload_1
    //   1463: invokestatic 121	java/lang/Integer:valueOf	(I)Ljava/lang/Integer;
    //   1466: invokeinterface 127 2 0
    //   1471: checkcast 129	java/lang/Long
    //   1474: invokevirtual 133	java/lang/Long:longValue	()J
    //   1477: lcmp
    //   1478: iflt +215 -> 1693
    //   1481: aload 17
    //   1483: astore 15
    //   1485: aload 17
    //   1487: astore 16
    //   1489: lload_3
    //   1490: aload_0
    //   1491: getfield 47	com/tencent/mm/plugin/trafficmonitor/b:TRR	Ljava/util/Map;
    //   1494: iload_1
    //   1495: invokestatic 121	java/lang/Integer:valueOf	(I)Ljava/lang/Integer;
    //   1498: invokeinterface 127 2 0
    //   1503: checkcast 129	java/lang/Long
    //   1506: invokevirtual 133	java/lang/Long:longValue	()J
    //   1509: lsub
    //   1510: lstore 11
    //   1512: aload 17
    //   1514: astore 15
    //   1516: aload 17
    //   1518: astore 16
    //   1520: aload 18
    //   1522: iload_1
    //   1523: invokestatic 121	java/lang/Integer:valueOf	(I)Ljava/lang/Integer;
    //   1526: lload 11
    //   1528: invokestatic 146	java/lang/Long:valueOf	(J)Ljava/lang/Long;
    //   1531: invokeinterface 150 3 0
    //   1536: pop
    //   1537: aload 17
    //   1539: astore 15
    //   1541: aload 17
    //   1543: astore 16
    //   1545: aload_0
    //   1546: getfield 41	com/tencent/mm/plugin/trafficmonitor/b:TRO	Ljava/util/Map;
    //   1549: iload_1
    //   1550: invokestatic 121	java/lang/Integer:valueOf	(I)Ljava/lang/Integer;
    //   1553: lload 5
    //   1555: invokestatic 146	java/lang/Long:valueOf	(J)Ljava/lang/Long;
    //   1558: invokeinterface 150 3 0
    //   1563: pop
    //   1564: aload 17
    //   1566: astore 15
    //   1568: aload 17
    //   1570: astore 16
    //   1572: aload_0
    //   1573: getfield 43	com/tencent/mm/plugin/trafficmonitor/b:TRP	Ljava/util/Map;
    //   1576: iload_1
    //   1577: invokestatic 121	java/lang/Integer:valueOf	(I)Ljava/lang/Integer;
    //   1580: lload 7
    //   1582: invokestatic 146	java/lang/Long:valueOf	(J)Ljava/lang/Long;
    //   1585: invokeinterface 150 3 0
    //   1590: pop
    //   1591: aload 17
    //   1593: astore 15
    //   1595: aload 17
    //   1597: astore 16
    //   1599: aload_0
    //   1600: getfield 45	com/tencent/mm/plugin/trafficmonitor/b:TRQ	Ljava/util/Map;
    //   1603: iload_1
    //   1604: invokestatic 121	java/lang/Integer:valueOf	(I)Ljava/lang/Integer;
    //   1607: lload 9
    //   1609: invokestatic 146	java/lang/Long:valueOf	(J)Ljava/lang/Long;
    //   1612: invokeinterface 150 3 0
    //   1617: pop
    //   1618: aload 17
    //   1620: astore 15
    //   1622: aload 17
    //   1624: astore 16
    //   1626: aload_0
    //   1627: getfield 47	com/tencent/mm/plugin/trafficmonitor/b:TRR	Ljava/util/Map;
    //   1630: iload_1
    //   1631: invokestatic 121	java/lang/Integer:valueOf	(I)Ljava/lang/Integer;
    //   1634: lload_3
    //   1635: invokestatic 146	java/lang/Long:valueOf	(J)Ljava/lang/Long;
    //   1638: invokeinterface 150 3 0
    //   1643: pop
    //   1644: aload 17
    //   1646: astore 15
    //   1648: aload 17
    //   1650: astore 16
    //   1652: aload 17
    //   1654: invokestatic 206	com/tencent/mm/sdk/platformtools/Util:qualityClose	(Ljava/io/Closeable;)V
    //   1657: aload 17
    //   1659: astore 16
    //   1661: aload 16
    //   1663: invokestatic 206	com/tencent/mm/sdk/platformtools/Util:qualityClose	(Ljava/io/Closeable;)V
    //   1666: ldc 158
    //   1668: invokestatic 105	com/tencent/matrix/trace/core/AppMethodBeat:o	(I)V
    //   1671: return
    //   1672: lload 5
    //   1674: lstore 11
    //   1676: goto -474 -> 1202
    //   1679: lload 7
    //   1681: lstore 11
    //   1683: goto -377 -> 1306
    //   1686: lload 9
    //   1688: lstore 11
    //   1690: goto -280 -> 1410
    //   1693: lload_3
    //   1694: lstore 11
    //   1696: goto -184 -> 1512
    //   1699: astore 15
    //   1701: aconst_null
    //   1702: astore 16
    //   1704: aload 16
    //   1706: astore 15
    //   1708: aload_0
    //   1709: getfield 49	com/tencent/mm/plugin/trafficmonitor/b:TRS	Ljava/util/Map;
    //   1712: iload_1
    //   1713: invokestatic 121	java/lang/Integer:valueOf	(I)Ljava/lang/Integer;
    //   1716: lconst_0
    //   1717: invokestatic 146	java/lang/Long:valueOf	(J)Ljava/lang/Long;
    //   1720: invokeinterface 150 3 0
    //   1725: pop
    //   1726: aload 16
    //   1728: astore 15
    //   1730: aload_0
    //   1731: getfield 51	com/tencent/mm/plugin/trafficmonitor/b:TRT	Ljava/util/Map;
    //   1734: iload_1
    //   1735: invokestatic 121	java/lang/Integer:valueOf	(I)Ljava/lang/Integer;
    //   1738: lconst_0
    //   1739: invokestatic 146	java/lang/Long:valueOf	(J)Ljava/lang/Long;
    //   1742: invokeinterface 150 3 0
    //   1747: pop
    //   1748: aload 16
    //   1750: astore 15
    //   1752: aload_0
    //   1753: getfield 53	com/tencent/mm/plugin/trafficmonitor/b:TRU	Ljava/util/Map;
    //   1756: iload_1
    //   1757: invokestatic 121	java/lang/Integer:valueOf	(I)Ljava/lang/Integer;
    //   1760: lconst_0
    //   1761: invokestatic 146	java/lang/Long:valueOf	(J)Ljava/lang/Long;
    //   1764: invokeinterface 150 3 0
    //   1769: pop
    //   1770: aload 16
    //   1772: astore 15
    //   1774: aload_0
    //   1775: getfield 55	com/tencent/mm/plugin/trafficmonitor/b:TRV	Ljava/util/Map;
    //   1778: iload_1
    //   1779: invokestatic 121	java/lang/Integer:valueOf	(I)Ljava/lang/Integer;
    //   1782: lconst_0
    //   1783: invokestatic 146	java/lang/Long:valueOf	(J)Ljava/lang/Long;
    //   1786: invokeinterface 150 3 0
    //   1791: pop
    //   1792: aload 16
    //   1794: astore 15
    //   1796: aload_0
    //   1797: getfield 41	com/tencent/mm/plugin/trafficmonitor/b:TRO	Ljava/util/Map;
    //   1800: iload_1
    //   1801: invokestatic 121	java/lang/Integer:valueOf	(I)Ljava/lang/Integer;
    //   1804: ldc2_w 142
    //   1807: invokestatic 146	java/lang/Long:valueOf	(J)Ljava/lang/Long;
    //   1810: invokeinterface 150 3 0
    //   1815: pop
    //   1816: aload 16
    //   1818: astore 15
    //   1820: aload_0
    //   1821: getfield 43	com/tencent/mm/plugin/trafficmonitor/b:TRP	Ljava/util/Map;
    //   1824: iload_1
    //   1825: invokestatic 121	java/lang/Integer:valueOf	(I)Ljava/lang/Integer;
    //   1828: ldc2_w 142
    //   1831: invokestatic 146	java/lang/Long:valueOf	(J)Ljava/lang/Long;
    //   1834: invokeinterface 150 3 0
    //   1839: pop
    //   1840: aload 16
    //   1842: astore 15
    //   1844: aload_0
    //   1845: getfield 45	com/tencent/mm/plugin/trafficmonitor/b:TRQ	Ljava/util/Map;
    //   1848: iload_1
    //   1849: invokestatic 121	java/lang/Integer:valueOf	(I)Ljava/lang/Integer;
    //   1852: ldc2_w 142
    //   1855: invokestatic 146	java/lang/Long:valueOf	(J)Ljava/lang/Long;
    //   1858: invokeinterface 150 3 0
    //   1863: pop
    //   1864: aload 16
    //   1866: astore 15
    //   1868: aload_0
    //   1869: getfield 47	com/tencent/mm/plugin/trafficmonitor/b:TRR	Ljava/util/Map;
    //   1872: iload_1
    //   1873: invokestatic 121	java/lang/Integer:valueOf	(I)Ljava/lang/Integer;
    //   1876: ldc2_w 142
    //   1879: invokestatic 146	java/lang/Long:valueOf	(J)Ljava/lang/Long;
    //   1882: invokeinterface 150 3 0
    //   1887: pop
    //   1888: aload 16
    //   1890: invokestatic 206	com/tencent/mm/sdk/platformtools/Util:qualityClose	(Ljava/io/Closeable;)V
    //   1893: ldc 158
    //   1895: invokestatic 105	com/tencent/matrix/trace/core/AppMethodBeat:o	(I)V
    //   1898: return
    //   1899: astore 16
    //   1901: aconst_null
    //   1902: astore 15
    //   1904: aload 15
    //   1906: invokestatic 206	com/tencent/mm/sdk/platformtools/Util:qualityClose	(Ljava/io/Closeable;)V
    //   1909: ldc 158
    //   1911: invokestatic 105	com/tencent/matrix/trace/core/AppMethodBeat:o	(I)V
    //   1914: aload 16
    //   1916: athrow
    //   1917: astore 16
    //   1919: goto -15 -> 1904
    //   1922: astore 16
    //   1924: goto -20 -> 1904
    //   1927: astore 15
    //   1929: goto -225 -> 1704
    //   1932: astore 16
    //   1934: aload 15
    //   1936: astore 16
    //   1938: goto -234 -> 1704
    //   1941: goto +31 -> 1972
    //   1944: goto +8 -> 1952
    //   1947: iconst_0
    //   1948: istore_2
    //   1949: goto -1812 -> 137
    //   1952: goto -1872 -> 80
    //   1955: lload 7
    //   1957: lload 13
    //   1959: ladd
    //   1960: lstore 7
    //   1962: lload 5
    //   1964: lload 11
    //   1966: ladd
    //   1967: lstore 5
    //   1969: goto -1253 -> 716
    //   1972: goto -1256 -> 716
    // Local variable table:
    //   start	length	slot	name	signature
    //   0	1975	0	this	b
    //   0	1975	1	paramInt	int
    //   136	1813	2	i	int
    //   15	1679	3	l1	long
    //   9	1959	5	l2	long
    //   6	1955	7	l3	long
    //   12	1675	9	l4	long
    //   20	1945	11	l5	long
    //   17	1941	13	l6	long
    //   23	1624	15	localObject1	Object
    //   1699	1	15	localException1	java.lang.Exception
    //   1706	199	15	localObject2	Object
    //   1927	8	15	localException2	java.lang.Exception
    //   58	1831	16	localObject3	Object
    //   1899	16	16	localObject4	Object
    //   1917	1	16	localObject5	Object
    //   1922	1	16	localObject6	Object
    //   1932	1	16	localException3	java.lang.Exception
    //   1936	1	16	localException4	java.lang.Exception
    //   50	1608	17	localBufferedReader	java.io.BufferedReader
    //   93	1428	18	localObject7	Object
    //   777	87	19	localObject8	Object
    // Exception table:
    //   from	to	target	type
    //   25	52	1699	java/lang/Exception
    //   25	52	1899	finally
    //   60	66	1917	finally
    //   74	80	1917	finally
    //   88	95	1917	finally
    //   108	117	1917	finally
    //   125	135	1917	finally
    //   145	157	1917	finally
    //   165	177	1917	finally
    //   185	197	1917	finally
    //   205	221	1917	finally
    //   229	244	1917	finally
    //   255	271	1917	finally
    //   279	292	1917	finally
    //   303	327	1917	finally
    //   335	354	1917	finally
    //   362	386	1917	finally
    //   394	413	1917	finally
    //   421	445	1917	finally
    //   453	472	1917	finally
    //   480	504	1917	finally
    //   512	530	1917	finally
    //   538	557	1917	finally
    //   565	584	1917	finally
    //   592	611	1917	finally
    //   619	637	1917	finally
    //   645	650	1917	finally
    //   697	703	1917	finally
    //   724	731	1917	finally
    //   744	753	1917	finally
    //   761	773	1917	finally
    //   787	797	1917	finally
    //   805	816	1917	finally
    //   824	834	1917	finally
    //   842	852	1917	finally
    //   863	873	1917	finally
    //   896	920	1917	finally
    //   928	947	1917	finally
    //   955	979	1917	finally
    //   987	1006	1917	finally
    //   1014	1038	1917	finally
    //   1046	1064	1917	finally
    //   1072	1096	1917	finally
    //   1104	1123	1917	finally
    //   1131	1137	1917	finally
    //   1145	1170	1917	finally
    //   1178	1202	1917	finally
    //   1210	1227	1917	finally
    //   1235	1241	1917	finally
    //   1249	1274	1917	finally
    //   1282	1306	1917	finally
    //   1314	1331	1917	finally
    //   1339	1345	1917	finally
    //   1353	1378	1917	finally
    //   1386	1410	1917	finally
    //   1418	1435	1917	finally
    //   1443	1449	1917	finally
    //   1457	1481	1917	finally
    //   1489	1512	1917	finally
    //   1520	1537	1917	finally
    //   1545	1564	1917	finally
    //   1572	1591	1917	finally
    //   1599	1618	1917	finally
    //   1626	1644	1917	finally
    //   1652	1657	1917	finally
    //   1708	1726	1917	finally
    //   1730	1748	1917	finally
    //   1752	1770	1917	finally
    //   1774	1792	1917	finally
    //   1796	1816	1917	finally
    //   1820	1840	1917	finally
    //   1844	1864	1917	finally
    //   1868	1888	1917	finally
    //   658	689	1922	finally
    //   60	66	1927	java/lang/Exception
    //   74	80	1927	java/lang/Exception
    //   88	95	1927	java/lang/Exception
    //   108	117	1927	java/lang/Exception
    //   125	135	1927	java/lang/Exception
    //   145	157	1927	java/lang/Exception
    //   165	177	1927	java/lang/Exception
    //   185	197	1927	java/lang/Exception
    //   205	221	1927	java/lang/Exception
    //   229	244	1927	java/lang/Exception
    //   255	271	1927	java/lang/Exception
    //   279	292	1927	java/lang/Exception
    //   303	327	1927	java/lang/Exception
    //   335	354	1927	java/lang/Exception
    //   362	386	1927	java/lang/Exception
    //   394	413	1927	java/lang/Exception
    //   421	445	1927	java/lang/Exception
    //   453	472	1927	java/lang/Exception
    //   480	504	1927	java/lang/Exception
    //   512	530	1927	java/lang/Exception
    //   538	557	1927	java/lang/Exception
    //   565	584	1927	java/lang/Exception
    //   592	611	1927	java/lang/Exception
    //   619	637	1927	java/lang/Exception
    //   645	650	1927	java/lang/Exception
    //   697	703	1927	java/lang/Exception
    //   724	731	1927	java/lang/Exception
    //   744	753	1927	java/lang/Exception
    //   761	773	1927	java/lang/Exception
    //   787	797	1927	java/lang/Exception
    //   805	816	1927	java/lang/Exception
    //   824	834	1927	java/lang/Exception
    //   842	852	1927	java/lang/Exception
    //   863	873	1927	java/lang/Exception
    //   896	920	1927	java/lang/Exception
    //   928	947	1927	java/lang/Exception
    //   955	979	1927	java/lang/Exception
    //   987	1006	1927	java/lang/Exception
    //   1014	1038	1927	java/lang/Exception
    //   1046	1064	1927	java/lang/Exception
    //   1072	1096	1927	java/lang/Exception
    //   1104	1123	1927	java/lang/Exception
    //   1131	1137	1927	java/lang/Exception
    //   1145	1170	1927	java/lang/Exception
    //   1178	1202	1927	java/lang/Exception
    //   1210	1227	1927	java/lang/Exception
    //   1235	1241	1927	java/lang/Exception
    //   1249	1274	1927	java/lang/Exception
    //   1282	1306	1927	java/lang/Exception
    //   1314	1331	1927	java/lang/Exception
    //   1339	1345	1927	java/lang/Exception
    //   1353	1378	1927	java/lang/Exception
    //   1386	1410	1927	java/lang/Exception
    //   1418	1435	1927	java/lang/Exception
    //   1443	1449	1927	java/lang/Exception
    //   1457	1481	1927	java/lang/Exception
    //   1489	1512	1927	java/lang/Exception
    //   1520	1537	1927	java/lang/Exception
    //   1545	1564	1927	java/lang/Exception
    //   1572	1591	1927	java/lang/Exception
    //   1599	1618	1927	java/lang/Exception
    //   1626	1644	1927	java/lang/Exception
    //   1652	1657	1927	java/lang/Exception
    //   658	689	1932	java/lang/Exception
  }
}


/* Location:           L:\local\mybackup\temp\qq_apk\com.tencent.mm\classes4.jar
 * Qualified Name:     com.tencent.mm.plugin.trafficmonitor.b
 * JD-Core Version:    0.7.0.1
 */