package com.tencent.mobileqq.log;

class VipWebViewReportLog$LoadConfigRbl
  implements Runnable
{
  /* Error */
  public void run()
  {
    // Byte code:
    //   0: invokestatic 20	java/lang/System:currentTimeMillis	()J
    //   3: lstore_3
    //   4: new 22	java/lang/StringBuilder
    //   7: dup
    //   8: invokespecial 23	java/lang/StringBuilder:<init>	()V
    //   11: astore 5
    //   13: aload 5
    //   15: ldc 25
    //   17: invokevirtual 29	java/lang/StringBuilder:append	(Ljava/lang/String;)Ljava/lang/StringBuilder;
    //   20: pop
    //   21: aload 5
    //   23: lload_3
    //   24: invokevirtual 32	java/lang/StringBuilder:append	(J)Ljava/lang/StringBuilder;
    //   27: pop
    //   28: ldc 34
    //   30: iconst_1
    //   31: aload 5
    //   33: invokevirtual 38	java/lang/StringBuilder:toString	()Ljava/lang/String;
    //   36: invokestatic 44	com/tencent/qphone/base/util/QLog:d	(Ljava/lang/String;ILjava/lang/String;)V
    //   39: getstatic 50	com/tencent/mobileqq/log/VipWebViewReportLog:f	Ljava/lang/String;
    //   42: invokestatic 56	com/tencent/mobileqq/utils/FileUtils:deleteDirectory	(Ljava/lang/String;)V
    //   45: invokestatic 60	com/tencent/qphone/base/util/QLog:isColorLevel	()Z
    //   48: ifeq +39 -> 87
    //   51: ldc 34
    //   53: iconst_2
    //   54: ldc 62
    //   56: invokestatic 44	com/tencent/qphone/base/util/QLog:d	(Ljava/lang/String;ILjava/lang/String;)V
    //   59: goto +28 -> 87
    //   62: astore 5
    //   64: ldc 34
    //   66: iconst_1
    //   67: iconst_2
    //   68: anewarray 4	java/lang/Object
    //   71: dup
    //   72: iconst_0
    //   73: ldc 64
    //   75: aastore
    //   76: dup
    //   77: iconst_1
    //   78: aload 5
    //   80: invokevirtual 65	java/lang/Exception:toString	()Ljava/lang/String;
    //   83: aastore
    //   84: invokestatic 69	com/tencent/qphone/base/util/QLog:e	(Ljava/lang/String;I[Ljava/lang/Object;)V
    //   87: invokestatic 72	com/tencent/mobileqq/log/VipWebViewReportLog:e	()Lmqq/app/AppRuntime;
    //   90: ifnull +75 -> 165
    //   93: new 22	java/lang/StringBuilder
    //   96: dup
    //   97: invokespecial 23	java/lang/StringBuilder:<init>	()V
    //   100: astore 5
    //   102: aload 5
    //   104: invokestatic 72	com/tencent/mobileqq/log/VipWebViewReportLog:e	()Lmqq/app/AppRuntime;
    //   107: invokevirtual 78	mqq/app/AppRuntime:getApplication	()Lmqq/app/MobileQQ;
    //   110: invokevirtual 84	mqq/app/MobileQQ:getFilesDir	()Ljava/io/File;
    //   113: invokevirtual 87	java/lang/StringBuilder:append	(Ljava/lang/Object;)Ljava/lang/StringBuilder;
    //   116: pop
    //   117: aload 5
    //   119: getstatic 92	java/io/File:separator	Ljava/lang/String;
    //   122: invokevirtual 29	java/lang/StringBuilder:append	(Ljava/lang/String;)Ljava/lang/StringBuilder;
    //   125: pop
    //   126: aload 5
    //   128: getstatic 95	com/tencent/mobileqq/log/VipWebViewReportLog:g	Ljava/lang/String;
    //   131: invokevirtual 29	java/lang/StringBuilder:append	(Ljava/lang/String;)Ljava/lang/StringBuilder;
    //   134: pop
    //   135: aload 5
    //   137: invokestatic 72	com/tencent/mobileqq/log/VipWebViewReportLog:e	()Lmqq/app/AppRuntime;
    //   140: invokevirtual 98	mqq/app/AppRuntime:getAccount	()Ljava/lang/String;
    //   143: invokevirtual 29	java/lang/StringBuilder:append	(Ljava/lang/String;)Ljava/lang/StringBuilder;
    //   146: pop
    //   147: aload 5
    //   149: ldc 100
    //   151: invokevirtual 29	java/lang/StringBuilder:append	(Ljava/lang/String;)Ljava/lang/StringBuilder;
    //   154: pop
    //   155: aload 5
    //   157: invokevirtual 38	java/lang/StringBuilder:toString	()Ljava/lang/String;
    //   160: astore 5
    //   162: goto +7 -> 169
    //   165: ldc 102
    //   167: astore 5
    //   169: new 89	java/io/File
    //   172: dup
    //   173: aload 5
    //   175: invokespecial 104	java/io/File:<init>	(Ljava/lang/String;)V
    //   178: astore 5
    //   180: aload 5
    //   182: invokevirtual 107	java/io/File:exists	()Z
    //   185: ifeq +307 -> 492
    //   188: ldc 34
    //   190: iconst_1
    //   191: ldc 109
    //   193: invokestatic 44	com/tencent/qphone/base/util/QLog:d	(Ljava/lang/String;ILjava/lang/String;)V
    //   196: iconst_0
    //   197: putstatic 112	com/tencent/mobileqq/log/VipWebViewReportLog:e	I
    //   200: invokestatic 115	com/tencent/mobileqq/log/VipWebViewReportLog:f	()I
    //   203: invokestatic 119	com/tencent/mobileqq/log/VipWebViewReportLog:a	(I)I
    //   206: pop
    //   207: aload 5
    //   209: invokestatic 123	com/tencent/mobileqq/utils/FileUtils:readFileContent	(Ljava/io/File;)Ljava/lang/String;
    //   212: astore 5
    //   214: aload 5
    //   216: invokestatic 129	android/text/TextUtils:isEmpty	(Ljava/lang/CharSequence;)Z
    //   219: ifne +205 -> 424
    //   222: new 131	org/json/JSONObject
    //   225: dup
    //   226: aload 5
    //   228: invokespecial 132	org/json/JSONObject:<init>	(Ljava/lang/String;)V
    //   231: astore 5
    //   233: aload 5
    //   235: ldc 134
    //   237: iconst_1
    //   238: invokevirtual 138	org/json/JSONObject:optBoolean	(Ljava/lang/String;Z)Z
    //   241: putstatic 142	com/tencent/mobileqq/log/VipWebViewReportLog:c	Z
    //   244: aload 5
    //   246: ldc 144
    //   248: iconst_1
    //   249: invokevirtual 138	org/json/JSONObject:optBoolean	(Ljava/lang/String;Z)Z
    //   252: putstatic 146	com/tencent/mobileqq/log/VipWebViewReportLog:d	Z
    //   255: aload 5
    //   257: ldc 148
    //   259: invokevirtual 152	org/json/JSONObject:has	(Ljava/lang/String;)Z
    //   262: ifeq +87 -> 349
    //   265: aload 5
    //   267: ldc 148
    //   269: invokevirtual 156	org/json/JSONObject:getJSONArray	(Ljava/lang/String;)Lorg/json/JSONArray;
    //   272: astore 6
    //   274: aload 6
    //   276: invokevirtual 161	org/json/JSONArray:length	()I
    //   279: istore_2
    //   280: iconst_0
    //   281: istore_1
    //   282: iload_1
    //   283: iload_2
    //   284: if_icmpge +25 -> 309
    //   287: getstatic 165	com/tencent/mobileqq/log/VipWebViewReportLog:b	Ljava/util/Set;
    //   290: aload 6
    //   292: iload_1
    //   293: invokevirtual 169	org/json/JSONArray:getString	(I)Ljava/lang/String;
    //   296: invokeinterface 175 2 0
    //   301: pop
    //   302: iload_1
    //   303: iconst_1
    //   304: iadd
    //   305: istore_1
    //   306: goto -24 -> 282
    //   309: new 22	java/lang/StringBuilder
    //   312: dup
    //   313: invokespecial 23	java/lang/StringBuilder:<init>	()V
    //   316: astore 6
    //   318: aload 6
    //   320: ldc 177
    //   322: invokevirtual 29	java/lang/StringBuilder:append	(Ljava/lang/String;)Ljava/lang/StringBuilder;
    //   325: pop
    //   326: aload 6
    //   328: getstatic 165	com/tencent/mobileqq/log/VipWebViewReportLog:b	Ljava/util/Set;
    //   331: invokevirtual 87	java/lang/StringBuilder:append	(Ljava/lang/Object;)Ljava/lang/StringBuilder;
    //   334: pop
    //   335: ldc 34
    //   337: iconst_1
    //   338: aload 6
    //   340: invokevirtual 38	java/lang/StringBuilder:toString	()Ljava/lang/String;
    //   343: invokestatic 44	com/tencent/qphone/base/util/QLog:d	(Ljava/lang/String;ILjava/lang/String;)V
    //   346: goto +42 -> 388
    //   349: new 22	java/lang/StringBuilder
    //   352: dup
    //   353: invokespecial 23	java/lang/StringBuilder:<init>	()V
    //   356: astore 6
    //   358: aload 6
    //   360: ldc 179
    //   362: invokevirtual 29	java/lang/StringBuilder:append	(Ljava/lang/String;)Ljava/lang/StringBuilder;
    //   365: pop
    //   366: aload 6
    //   368: aload 5
    //   370: invokevirtual 180	org/json/JSONObject:toString	()Ljava/lang/String;
    //   373: invokevirtual 29	java/lang/StringBuilder:append	(Ljava/lang/String;)Ljava/lang/StringBuilder;
    //   376: pop
    //   377: ldc 34
    //   379: iconst_1
    //   380: aload 6
    //   382: invokevirtual 38	java/lang/StringBuilder:toString	()Ljava/lang/String;
    //   385: invokestatic 44	com/tencent/qphone/base/util/QLog:d	(Ljava/lang/String;ILjava/lang/String;)V
    //   388: getstatic 146	com/tencent/mobileqq/log/VipWebViewReportLog:d	Z
    //   391: ifeq +26 -> 417
    //   394: aload 5
    //   396: ldc 148
    //   398: invokevirtual 152	org/json/JSONObject:has	(Ljava/lang/String;)Z
    //   401: ifeq +6 -> 407
    //   404: goto +13 -> 417
    //   407: getstatic 184	com/tencent/mobileqq/log/VipWebViewReportLog:l	Ljava/util/concurrent/atomic/AtomicInteger;
    //   410: iconst_0
    //   411: invokevirtual 190	java/util/concurrent/atomic/AtomicInteger:set	(I)V
    //   414: goto +10 -> 424
    //   417: getstatic 184	com/tencent/mobileqq/log/VipWebViewReportLog:l	Ljava/util/concurrent/atomic/AtomicInteger;
    //   420: iconst_2
    //   421: invokevirtual 190	java/util/concurrent/atomic/AtomicInteger:set	(I)V
    //   424: invokestatic 192	com/tencent/mobileqq/log/VipWebViewReportLog:d	()V
    //   427: goto +121 -> 548
    //   430: astore 5
    //   432: goto +54 -> 486
    //   435: astore 5
    //   437: getstatic 184	com/tencent/mobileqq/log/VipWebViewReportLog:l	Ljava/util/concurrent/atomic/AtomicInteger;
    //   440: iconst_0
    //   441: invokevirtual 190	java/util/concurrent/atomic/AtomicInteger:set	(I)V
    //   444: new 22	java/lang/StringBuilder
    //   447: dup
    //   448: invokespecial 23	java/lang/StringBuilder:<init>	()V
    //   451: astore 6
    //   453: aload 6
    //   455: ldc 194
    //   457: invokevirtual 29	java/lang/StringBuilder:append	(Ljava/lang/String;)Ljava/lang/StringBuilder;
    //   460: pop
    //   461: aload 6
    //   463: aload 5
    //   465: invokevirtual 65	java/lang/Exception:toString	()Ljava/lang/String;
    //   468: invokevirtual 29	java/lang/StringBuilder:append	(Ljava/lang/String;)Ljava/lang/StringBuilder;
    //   471: pop
    //   472: ldc 34
    //   474: iconst_1
    //   475: aload 6
    //   477: invokevirtual 38	java/lang/StringBuilder:toString	()Ljava/lang/String;
    //   480: invokestatic 44	com/tencent/qphone/base/util/QLog:d	(Ljava/lang/String;ILjava/lang/String;)V
    //   483: goto -59 -> 424
    //   486: invokestatic 192	com/tencent/mobileqq/log/VipWebViewReportLog:d	()V
    //   489: aload 5
    //   491: athrow
    //   492: invokestatic 115	com/tencent/mobileqq/log/VipWebViewReportLog:f	()I
    //   495: invokestatic 119	com/tencent/mobileqq/log/VipWebViewReportLog:a	(I)I
    //   498: pop
    //   499: invokestatic 192	com/tencent/mobileqq/log/VipWebViewReportLog:d	()V
    //   502: new 22	java/lang/StringBuilder
    //   505: dup
    //   506: invokespecial 23	java/lang/StringBuilder:<init>	()V
    //   509: astore 6
    //   511: aload 6
    //   513: ldc 196
    //   515: invokevirtual 29	java/lang/StringBuilder:append	(Ljava/lang/String;)Ljava/lang/StringBuilder;
    //   518: pop
    //   519: aload 6
    //   521: aload 5
    //   523: invokevirtual 199	java/io/File:getPath	()Ljava/lang/String;
    //   526: invokevirtual 29	java/lang/StringBuilder:append	(Ljava/lang/String;)Ljava/lang/StringBuilder;
    //   529: pop
    //   530: ldc 34
    //   532: iconst_1
    //   533: aload 6
    //   535: invokevirtual 38	java/lang/StringBuilder:toString	()Ljava/lang/String;
    //   538: invokestatic 44	com/tencent/qphone/base/util/QLog:d	(Ljava/lang/String;ILjava/lang/String;)V
    //   541: getstatic 184	com/tencent/mobileqq/log/VipWebViewReportLog:l	Ljava/util/concurrent/atomic/AtomicInteger;
    //   544: iconst_0
    //   545: invokevirtual 190	java/util/concurrent/atomic/AtomicInteger:set	(I)V
    //   548: new 22	java/lang/StringBuilder
    //   551: dup
    //   552: invokespecial 23	java/lang/StringBuilder:<init>	()V
    //   555: astore 5
    //   557: aload 5
    //   559: ldc 201
    //   561: invokevirtual 29	java/lang/StringBuilder:append	(Ljava/lang/String;)Ljava/lang/StringBuilder;
    //   564: pop
    //   565: aload 5
    //   567: invokestatic 20	java/lang/System:currentTimeMillis	()J
    //   570: lload_3
    //   571: lsub
    //   572: invokevirtual 32	java/lang/StringBuilder:append	(J)Ljava/lang/StringBuilder;
    //   575: pop
    //   576: ldc 34
    //   578: iconst_1
    //   579: aload 5
    //   581: invokevirtual 38	java/lang/StringBuilder:toString	()Ljava/lang/String;
    //   584: invokestatic 44	com/tencent/qphone/base/util/QLog:d	(Ljava/lang/String;ILjava/lang/String;)V
    //   587: return
    // Local variable table:
    //   start	length	slot	name	signature
    //   0	588	0	this	LoadConfigRbl
    //   281	25	1	i	int
    //   279	6	2	j	int
    //   3	568	3	l	long
    //   11	21	5	localStringBuilder1	java.lang.StringBuilder
    //   62	17	5	localException1	java.lang.Exception
    //   100	295	5	localObject1	Object
    //   430	1	5	localObject2	Object
    //   435	87	5	localException2	java.lang.Exception
    //   555	25	5	localStringBuilder2	java.lang.StringBuilder
    //   272	262	6	localObject3	Object
    // Exception table:
    //   from	to	target	type
    //   39	59	62	java/lang/Exception
    //   207	280	430	finally
    //   287	302	430	finally
    //   309	346	430	finally
    //   349	388	430	finally
    //   388	404	430	finally
    //   407	414	430	finally
    //   417	424	430	finally
    //   437	483	430	finally
    //   207	280	435	java/lang/Exception
    //   287	302	435	java/lang/Exception
    //   309	346	435	java/lang/Exception
    //   349	388	435	java/lang/Exception
    //   388	404	435	java/lang/Exception
    //   407	414	435	java/lang/Exception
    //   417	424	435	java/lang/Exception
  }
}


/* Location:           L:\local\mybackup\temp\qq_apk\com.tencent.mobileqq\classes9.jar
 * Qualified Name:     com.tencent.mobileqq.log.VipWebViewReportLog.LoadConfigRbl
 * JD-Core Version:    0.7.0.1
 */