import com.tencent.mobileqq.activity.NearbyActivity;

public class emc
  implements Runnable
{
  public emc(NearbyActivity paramNearbyActivity, boolean paramBoolean) {}
  
  /* Error */
  public void run()
  {
    // Byte code:
    //   0: aload_0
    //   1: getfield 13	emc:jdField_a_of_type_ComTencentMobileqqActivityNearbyActivity	Lcom/tencent/mobileqq/activity/NearbyActivity;
    //   4: getfield 30	com/tencent/mobileqq/activity/NearbyActivity:app	Lcom/tencent/mobileqq/app/QQAppInterface;
    //   7: iconst_1
    //   8: invokevirtual 36	com/tencent/mobileqq/app/QQAppInterface:e	(Z)V
    //   11: aload_0
    //   12: getfield 13	emc:jdField_a_of_type_ComTencentMobileqqActivityNearbyActivity	Lcom/tencent/mobileqq/activity/NearbyActivity;
    //   15: aload_0
    //   16: getfield 15	emc:jdField_a_of_type_Boolean	Z
    //   19: invokestatic 38	com/tencent/mobileqq/activity/NearbyActivity:a	(Lcom/tencent/mobileqq/activity/NearbyActivity;Z)V
    //   22: aload_0
    //   23: getfield 13	emc:jdField_a_of_type_ComTencentMobileqqActivityNearbyActivity	Lcom/tencent/mobileqq/activity/NearbyActivity;
    //   26: invokestatic 41	com/tencent/mobileqq/activity/NearbyActivity:a	(Lcom/tencent/mobileqq/activity/NearbyActivity;)Lcom/tencent/mobileqq/dating/CarrierHelper;
    //   29: ldc 43
    //   31: invokevirtual 48	com/tencent/mobileqq/dating/CarrierHelper:a	(Ljava/lang/String;)V
    //   34: aload_0
    //   35: getfield 15	emc:jdField_a_of_type_Boolean	Z
    //   38: ifne +189 -> 227
    //   41: new 50	java/io/ObjectInputStream
    //   44: dup
    //   45: new 52	java/io/BufferedInputStream
    //   48: dup
    //   49: aload_0
    //   50: getfield 13	emc:jdField_a_of_type_ComTencentMobileqqActivityNearbyActivity	Lcom/tencent/mobileqq/activity/NearbyActivity;
    //   53: new 54	java/lang/StringBuilder
    //   56: dup
    //   57: invokespecial 55	java/lang/StringBuilder:<init>	()V
    //   60: aload_0
    //   61: getfield 13	emc:jdField_a_of_type_ComTencentMobileqqActivityNearbyActivity	Lcom/tencent/mobileqq/activity/NearbyActivity;
    //   64: getfield 30	com/tencent/mobileqq/activity/NearbyActivity:app	Lcom/tencent/mobileqq/app/QQAppInterface;
    //   67: invokevirtual 58	com/tencent/mobileqq/app/QQAppInterface:a	()Ljava/lang/String;
    //   70: invokevirtual 62	java/lang/StringBuilder:append	(Ljava/lang/String;)Ljava/lang/StringBuilder;
    //   73: ldc 64
    //   75: invokevirtual 62	java/lang/StringBuilder:append	(Ljava/lang/String;)Ljava/lang/StringBuilder;
    //   78: invokevirtual 67	java/lang/StringBuilder:toString	()Ljava/lang/String;
    //   81: invokevirtual 71	com/tencent/mobileqq/activity/NearbyActivity:openFileInput	(Ljava/lang/String;)Ljava/io/FileInputStream;
    //   84: invokespecial 74	java/io/BufferedInputStream:<init>	(Ljava/io/InputStream;)V
    //   87: invokespecial 75	java/io/ObjectInputStream:<init>	(Ljava/io/InputStream;)V
    //   90: astore_2
    //   91: aload_2
    //   92: astore_1
    //   93: aload_2
    //   94: invokevirtual 79	java/io/ObjectInputStream:readObject	()Ljava/lang/Object;
    //   97: checkcast 81	java/util/List
    //   100: astore_3
    //   101: aload_3
    //   102: ifnull +45 -> 147
    //   105: aload_2
    //   106: astore_1
    //   107: aload_3
    //   108: invokeinterface 85 1 0
    //   113: ifle +34 -> 147
    //   116: aload_2
    //   117: astore_1
    //   118: aload_3
    //   119: iconst_0
    //   120: invokeinterface 89 2 0
    //   125: instanceof 91
    //   128: ifeq +19 -> 147
    //   131: aload_2
    //   132: astore_1
    //   133: aload_0
    //   134: getfield 13	emc:jdField_a_of_type_ComTencentMobileqqActivityNearbyActivity	Lcom/tencent/mobileqq/activity/NearbyActivity;
    //   137: invokestatic 94	com/tencent/mobileqq/activity/NearbyActivity:a	(Lcom/tencent/mobileqq/activity/NearbyActivity;)Ljava/util/List;
    //   140: aload_3
    //   141: invokeinterface 98 2 0
    //   146: pop
    //   147: aload_2
    //   148: astore_1
    //   149: aload_0
    //   150: getfield 13	emc:jdField_a_of_type_ComTencentMobileqqActivityNearbyActivity	Lcom/tencent/mobileqq/activity/NearbyActivity;
    //   153: aload_2
    //   154: invokevirtual 102	java/io/ObjectInputStream:readLong	()J
    //   157: invokestatic 105	com/tencent/mobileqq/activity/NearbyActivity:a	(Lcom/tencent/mobileqq/activity/NearbyActivity;J)J
    //   160: pop2
    //   161: aload_2
    //   162: ifnull +7 -> 169
    //   165: aload_2
    //   166: invokevirtual 108	java/io/ObjectInputStream:close	()V
    //   169: aload_0
    //   170: getfield 13	emc:jdField_a_of_type_ComTencentMobileqqActivityNearbyActivity	Lcom/tencent/mobileqq/activity/NearbyActivity;
    //   173: invokestatic 111	com/tencent/mobileqq/activity/NearbyActivity:a	(Lcom/tencent/mobileqq/activity/NearbyActivity;)Lcom/tencent/mobileqq/dating/NearbyBannerMgr;
    //   176: ifnonnull +51 -> 227
    //   179: aload_0
    //   180: getfield 13	emc:jdField_a_of_type_ComTencentMobileqqActivityNearbyActivity	Lcom/tencent/mobileqq/activity/NearbyActivity;
    //   183: invokestatic 94	com/tencent/mobileqq/activity/NearbyActivity:a	(Lcom/tencent/mobileqq/activity/NearbyActivity;)Ljava/util/List;
    //   186: invokeinterface 85 1 0
    //   191: ifle +36 -> 227
    //   194: aload_0
    //   195: getfield 13	emc:jdField_a_of_type_ComTencentMobileqqActivityNearbyActivity	Lcom/tencent/mobileqq/activity/NearbyActivity;
    //   198: new 113	com/tencent/mobileqq/dating/NearbyBannerMgr
    //   201: dup
    //   202: aload_0
    //   203: getfield 13	emc:jdField_a_of_type_ComTencentMobileqqActivityNearbyActivity	Lcom/tencent/mobileqq/activity/NearbyActivity;
    //   206: aload_0
    //   207: getfield 13	emc:jdField_a_of_type_ComTencentMobileqqActivityNearbyActivity	Lcom/tencent/mobileqq/activity/NearbyActivity;
    //   210: invokestatic 116	com/tencent/mobileqq/activity/NearbyActivity:a	(Lcom/tencent/mobileqq/activity/NearbyActivity;)Lemp;
    //   213: aload_0
    //   214: getfield 13	emc:jdField_a_of_type_ComTencentMobileqqActivityNearbyActivity	Lcom/tencent/mobileqq/activity/NearbyActivity;
    //   217: invokestatic 94	com/tencent/mobileqq/activity/NearbyActivity:a	(Lcom/tencent/mobileqq/activity/NearbyActivity;)Ljava/util/List;
    //   220: invokespecial 119	com/tencent/mobileqq/dating/NearbyBannerMgr:<init>	(Lcom/tencent/mobileqq/activity/NearbyActivity;Landroid/os/Handler;Ljava/util/List;)V
    //   223: invokestatic 122	com/tencent/mobileqq/activity/NearbyActivity:a	(Lcom/tencent/mobileqq/activity/NearbyActivity;Lcom/tencent/mobileqq/dating/NearbyBannerMgr;)Lcom/tencent/mobileqq/dating/NearbyBannerMgr;
    //   226: pop
    //   227: aload_0
    //   228: getfield 13	emc:jdField_a_of_type_ComTencentMobileqqActivityNearbyActivity	Lcom/tencent/mobileqq/activity/NearbyActivity;
    //   231: new 124	emd
    //   234: dup
    //   235: aload_0
    //   236: invokespecial 127	emd:<init>	(Lemc;)V
    //   239: invokevirtual 131	com/tencent/mobileqq/activity/NearbyActivity:runOnUiThread	(Ljava/lang/Runnable;)V
    //   242: aload_0
    //   243: getfield 13	emc:jdField_a_of_type_ComTencentMobileqqActivityNearbyActivity	Lcom/tencent/mobileqq/activity/NearbyActivity;
    //   246: aload_0
    //   247: getfield 13	emc:jdField_a_of_type_ComTencentMobileqqActivityNearbyActivity	Lcom/tencent/mobileqq/activity/NearbyActivity;
    //   250: getfield 30	com/tencent/mobileqq/activity/NearbyActivity:app	Lcom/tencent/mobileqq/app/QQAppInterface;
    //   253: invokevirtual 58	com/tencent/mobileqq/app/QQAppInterface:a	()Ljava/lang/String;
    //   256: iconst_0
    //   257: invokevirtual 135	com/tencent/mobileqq/activity/NearbyActivity:getSharedPreferences	(Ljava/lang/String;I)Landroid/content/SharedPreferences;
    //   260: invokeinterface 141 1 0
    //   265: ldc 143
    //   267: invokestatic 148	java/lang/System:currentTimeMillis	()J
    //   270: invokeinterface 154 4 0
    //   275: invokeinterface 158 1 0
    //   280: pop
    //   281: return
    //   282: astore_1
    //   283: invokestatic 163	com/tencent/qphone/base/util/QLog:isColorLevel	()Z
    //   286: ifeq -117 -> 169
    //   289: ldc 165
    //   291: iconst_2
    //   292: new 54	java/lang/StringBuilder
    //   295: dup
    //   296: invokespecial 55	java/lang/StringBuilder:<init>	()V
    //   299: ldc 167
    //   301: invokevirtual 62	java/lang/StringBuilder:append	(Ljava/lang/String;)Ljava/lang/StringBuilder;
    //   304: aload_1
    //   305: invokevirtual 170	java/io/IOException:getMessage	()Ljava/lang/String;
    //   308: invokevirtual 62	java/lang/StringBuilder:append	(Ljava/lang/String;)Ljava/lang/StringBuilder;
    //   311: invokevirtual 67	java/lang/StringBuilder:toString	()Ljava/lang/String;
    //   314: invokestatic 174	com/tencent/qphone/base/util/QLog:d	(Ljava/lang/String;ILjava/lang/String;)V
    //   317: goto -148 -> 169
    //   320: astore_3
    //   321: aconst_null
    //   322: astore_2
    //   323: aload_2
    //   324: astore_1
    //   325: invokestatic 163	com/tencent/qphone/base/util/QLog:isColorLevel	()Z
    //   328: ifeq +33 -> 361
    //   331: aload_2
    //   332: astore_1
    //   333: ldc 165
    //   335: iconst_2
    //   336: new 54	java/lang/StringBuilder
    //   339: dup
    //   340: invokespecial 55	java/lang/StringBuilder:<init>	()V
    //   343: ldc 176
    //   345: invokevirtual 62	java/lang/StringBuilder:append	(Ljava/lang/String;)Ljava/lang/StringBuilder;
    //   348: aload_3
    //   349: invokevirtual 177	java/lang/Exception:getMessage	()Ljava/lang/String;
    //   352: invokevirtual 62	java/lang/StringBuilder:append	(Ljava/lang/String;)Ljava/lang/StringBuilder;
    //   355: invokevirtual 67	java/lang/StringBuilder:toString	()Ljava/lang/String;
    //   358: invokestatic 174	com/tencent/qphone/base/util/QLog:d	(Ljava/lang/String;ILjava/lang/String;)V
    //   361: aload_2
    //   362: ifnull +7 -> 369
    //   365: aload_2
    //   366: invokevirtual 108	java/io/ObjectInputStream:close	()V
    //   369: aload_0
    //   370: getfield 13	emc:jdField_a_of_type_ComTencentMobileqqActivityNearbyActivity	Lcom/tencent/mobileqq/activity/NearbyActivity;
    //   373: invokestatic 111	com/tencent/mobileqq/activity/NearbyActivity:a	(Lcom/tencent/mobileqq/activity/NearbyActivity;)Lcom/tencent/mobileqq/dating/NearbyBannerMgr;
    //   376: ifnonnull -149 -> 227
    //   379: aload_0
    //   380: getfield 13	emc:jdField_a_of_type_ComTencentMobileqqActivityNearbyActivity	Lcom/tencent/mobileqq/activity/NearbyActivity;
    //   383: invokestatic 94	com/tencent/mobileqq/activity/NearbyActivity:a	(Lcom/tencent/mobileqq/activity/NearbyActivity;)Ljava/util/List;
    //   386: invokeinterface 85 1 0
    //   391: ifle -164 -> 227
    //   394: aload_0
    //   395: getfield 13	emc:jdField_a_of_type_ComTencentMobileqqActivityNearbyActivity	Lcom/tencent/mobileqq/activity/NearbyActivity;
    //   398: new 113	com/tencent/mobileqq/dating/NearbyBannerMgr
    //   401: dup
    //   402: aload_0
    //   403: getfield 13	emc:jdField_a_of_type_ComTencentMobileqqActivityNearbyActivity	Lcom/tencent/mobileqq/activity/NearbyActivity;
    //   406: aload_0
    //   407: getfield 13	emc:jdField_a_of_type_ComTencentMobileqqActivityNearbyActivity	Lcom/tencent/mobileqq/activity/NearbyActivity;
    //   410: invokestatic 116	com/tencent/mobileqq/activity/NearbyActivity:a	(Lcom/tencent/mobileqq/activity/NearbyActivity;)Lemp;
    //   413: aload_0
    //   414: getfield 13	emc:jdField_a_of_type_ComTencentMobileqqActivityNearbyActivity	Lcom/tencent/mobileqq/activity/NearbyActivity;
    //   417: invokestatic 94	com/tencent/mobileqq/activity/NearbyActivity:a	(Lcom/tencent/mobileqq/activity/NearbyActivity;)Ljava/util/List;
    //   420: invokespecial 119	com/tencent/mobileqq/dating/NearbyBannerMgr:<init>	(Lcom/tencent/mobileqq/activity/NearbyActivity;Landroid/os/Handler;Ljava/util/List;)V
    //   423: invokestatic 122	com/tencent/mobileqq/activity/NearbyActivity:a	(Lcom/tencent/mobileqq/activity/NearbyActivity;Lcom/tencent/mobileqq/dating/NearbyBannerMgr;)Lcom/tencent/mobileqq/dating/NearbyBannerMgr;
    //   426: pop
    //   427: goto -200 -> 227
    //   430: astore_1
    //   431: invokestatic 163	com/tencent/qphone/base/util/QLog:isColorLevel	()Z
    //   434: ifeq -65 -> 369
    //   437: ldc 165
    //   439: iconst_2
    //   440: new 54	java/lang/StringBuilder
    //   443: dup
    //   444: invokespecial 55	java/lang/StringBuilder:<init>	()V
    //   447: ldc 167
    //   449: invokevirtual 62	java/lang/StringBuilder:append	(Ljava/lang/String;)Ljava/lang/StringBuilder;
    //   452: aload_1
    //   453: invokevirtual 170	java/io/IOException:getMessage	()Ljava/lang/String;
    //   456: invokevirtual 62	java/lang/StringBuilder:append	(Ljava/lang/String;)Ljava/lang/StringBuilder;
    //   459: invokevirtual 67	java/lang/StringBuilder:toString	()Ljava/lang/String;
    //   462: invokestatic 174	com/tencent/qphone/base/util/QLog:d	(Ljava/lang/String;ILjava/lang/String;)V
    //   465: goto -96 -> 369
    //   468: astore_2
    //   469: aconst_null
    //   470: astore_1
    //   471: aload_1
    //   472: ifnull +7 -> 479
    //   475: aload_1
    //   476: invokevirtual 108	java/io/ObjectInputStream:close	()V
    //   479: aload_0
    //   480: getfield 13	emc:jdField_a_of_type_ComTencentMobileqqActivityNearbyActivity	Lcom/tencent/mobileqq/activity/NearbyActivity;
    //   483: invokestatic 111	com/tencent/mobileqq/activity/NearbyActivity:a	(Lcom/tencent/mobileqq/activity/NearbyActivity;)Lcom/tencent/mobileqq/dating/NearbyBannerMgr;
    //   486: ifnonnull +51 -> 537
    //   489: aload_0
    //   490: getfield 13	emc:jdField_a_of_type_ComTencentMobileqqActivityNearbyActivity	Lcom/tencent/mobileqq/activity/NearbyActivity;
    //   493: invokestatic 94	com/tencent/mobileqq/activity/NearbyActivity:a	(Lcom/tencent/mobileqq/activity/NearbyActivity;)Ljava/util/List;
    //   496: invokeinterface 85 1 0
    //   501: ifle +36 -> 537
    //   504: aload_0
    //   505: getfield 13	emc:jdField_a_of_type_ComTencentMobileqqActivityNearbyActivity	Lcom/tencent/mobileqq/activity/NearbyActivity;
    //   508: new 113	com/tencent/mobileqq/dating/NearbyBannerMgr
    //   511: dup
    //   512: aload_0
    //   513: getfield 13	emc:jdField_a_of_type_ComTencentMobileqqActivityNearbyActivity	Lcom/tencent/mobileqq/activity/NearbyActivity;
    //   516: aload_0
    //   517: getfield 13	emc:jdField_a_of_type_ComTencentMobileqqActivityNearbyActivity	Lcom/tencent/mobileqq/activity/NearbyActivity;
    //   520: invokestatic 116	com/tencent/mobileqq/activity/NearbyActivity:a	(Lcom/tencent/mobileqq/activity/NearbyActivity;)Lemp;
    //   523: aload_0
    //   524: getfield 13	emc:jdField_a_of_type_ComTencentMobileqqActivityNearbyActivity	Lcom/tencent/mobileqq/activity/NearbyActivity;
    //   527: invokestatic 94	com/tencent/mobileqq/activity/NearbyActivity:a	(Lcom/tencent/mobileqq/activity/NearbyActivity;)Ljava/util/List;
    //   530: invokespecial 119	com/tencent/mobileqq/dating/NearbyBannerMgr:<init>	(Lcom/tencent/mobileqq/activity/NearbyActivity;Landroid/os/Handler;Ljava/util/List;)V
    //   533: invokestatic 122	com/tencent/mobileqq/activity/NearbyActivity:a	(Lcom/tencent/mobileqq/activity/NearbyActivity;Lcom/tencent/mobileqq/dating/NearbyBannerMgr;)Lcom/tencent/mobileqq/dating/NearbyBannerMgr;
    //   536: pop
    //   537: aload_2
    //   538: athrow
    //   539: astore_1
    //   540: invokestatic 163	com/tencent/qphone/base/util/QLog:isColorLevel	()Z
    //   543: ifeq -64 -> 479
    //   546: ldc 165
    //   548: iconst_2
    //   549: new 54	java/lang/StringBuilder
    //   552: dup
    //   553: invokespecial 55	java/lang/StringBuilder:<init>	()V
    //   556: ldc 167
    //   558: invokevirtual 62	java/lang/StringBuilder:append	(Ljava/lang/String;)Ljava/lang/StringBuilder;
    //   561: aload_1
    //   562: invokevirtual 170	java/io/IOException:getMessage	()Ljava/lang/String;
    //   565: invokevirtual 62	java/lang/StringBuilder:append	(Ljava/lang/String;)Ljava/lang/StringBuilder;
    //   568: invokevirtual 67	java/lang/StringBuilder:toString	()Ljava/lang/String;
    //   571: invokestatic 174	com/tencent/qphone/base/util/QLog:d	(Ljava/lang/String;ILjava/lang/String;)V
    //   574: goto -95 -> 479
    //   577: astore_2
    //   578: goto -107 -> 471
    //   581: astore_3
    //   582: goto -259 -> 323
    // Local variable table:
    //   start	length	slot	name	signature
    //   0	585	0	this	emc
    //   92	57	1	localObjectInputStream1	java.io.ObjectInputStream
    //   282	23	1	localIOException1	java.io.IOException
    //   324	9	1	localObjectInputStream2	java.io.ObjectInputStream
    //   430	23	1	localIOException2	java.io.IOException
    //   470	6	1	localObject1	Object
    //   539	23	1	localIOException3	java.io.IOException
    //   90	276	2	localObjectInputStream3	java.io.ObjectInputStream
    //   468	70	2	localObject2	Object
    //   577	1	2	localObject3	Object
    //   100	41	3	localList	java.util.List
    //   320	29	3	localException1	java.lang.Exception
    //   581	1	3	localException2	java.lang.Exception
    // Exception table:
    //   from	to	target	type
    //   165	169	282	java/io/IOException
    //   41	91	320	java/lang/Exception
    //   365	369	430	java/io/IOException
    //   41	91	468	finally
    //   475	479	539	java/io/IOException
    //   93	101	577	finally
    //   107	116	577	finally
    //   118	131	577	finally
    //   133	147	577	finally
    //   149	161	577	finally
    //   325	331	577	finally
    //   333	361	577	finally
    //   93	101	581	java/lang/Exception
    //   107	116	581	java/lang/Exception
    //   118	131	581	java/lang/Exception
    //   133	147	581	java/lang/Exception
    //   149	161	581	java/lang/Exception
  }
}


/* Location:           L:\local\mybackup\temp\qq_apk\com.tencent.minihd.qq\assets\exlibs.2.jar\classes.jar
 * Qualified Name:     emc
 * JD-Core Version:    0.7.0.1
 */