import com.tencent.mobileqq.activity.RegisterPhoneNumActivity;
import mqq.observer.AccountObserver;

public class exw
  extends AccountObserver
{
  public exw(RegisterPhoneNumActivity paramRegisterPhoneNumActivity) {}
  
  /* Error */
  public void onRegQueryAccountResp(boolean paramBoolean, int paramInt, byte[] paramArrayOfByte)
  {
    // Byte code:
    //   0: invokestatic 26	com/tencent/qphone/base/util/QLog:isColorLevel	()Z
    //   3: ifeq +37 -> 40
    //   6: ldc 28
    //   8: iconst_2
    //   9: new 30	java/lang/StringBuilder
    //   12: dup
    //   13: invokespecial 31	java/lang/StringBuilder:<init>	()V
    //   16: ldc 33
    //   18: invokevirtual 37	java/lang/StringBuilder:append	(Ljava/lang/String;)Ljava/lang/StringBuilder;
    //   21: iload_1
    //   22: invokevirtual 40	java/lang/StringBuilder:append	(Z)Ljava/lang/StringBuilder;
    //   25: ldc 42
    //   27: invokevirtual 37	java/lang/StringBuilder:append	(Ljava/lang/String;)Ljava/lang/StringBuilder;
    //   30: iload_2
    //   31: invokevirtual 45	java/lang/StringBuilder:append	(I)Ljava/lang/StringBuilder;
    //   34: invokevirtual 49	java/lang/StringBuilder:toString	()Ljava/lang/String;
    //   37: invokestatic 53	com/tencent/qphone/base/util/QLog:d	(Ljava/lang/String;ILjava/lang/String;)V
    //   40: invokestatic 26	com/tencent/qphone/base/util/QLog:isColorLevel	()Z
    //   43: ifeq +11 -> 54
    //   46: ldc 55
    //   48: iconst_2
    //   49: ldc 57
    //   51: invokestatic 53	com/tencent/qphone/base/util/QLog:d	(Ljava/lang/String;ILjava/lang/String;)V
    //   54: aload_0
    //   55: getfield 10	exw:a	Lcom/tencent/mobileqq/activity/RegisterPhoneNumActivity;
    //   58: invokevirtual 62	com/tencent/mobileqq/activity/RegisterPhoneNumActivity:isFinishing	()Z
    //   61: ifeq +4 -> 65
    //   64: return
    //   65: iload_1
    //   66: ifne +63 -> 129
    //   69: aload_0
    //   70: getfield 10	exw:a	Lcom/tencent/mobileqq/activity/RegisterPhoneNumActivity;
    //   73: invokevirtual 65	com/tencent/mobileqq/activity/RegisterPhoneNumActivity:e	()V
    //   76: new 67	java/lang/String
    //   79: dup
    //   80: aload_3
    //   81: ldc 69
    //   83: invokespecial 72	java/lang/String:<init>	([BLjava/lang/String;)V
    //   86: astore_3
    //   87: aload_3
    //   88: astore 4
    //   90: aload_3
    //   91: invokestatic 78	android/text/TextUtils:isEmpty	(Ljava/lang/CharSequence;)Z
    //   94: ifeq +14 -> 108
    //   97: aload_0
    //   98: getfield 10	exw:a	Lcom/tencent/mobileqq/activity/RegisterPhoneNumActivity;
    //   101: ldc 79
    //   103: invokevirtual 83	com/tencent/mobileqq/activity/RegisterPhoneNumActivity:getString	(I)Ljava/lang/String;
    //   106: astore 4
    //   108: aload_0
    //   109: getfield 10	exw:a	Lcom/tencent/mobileqq/activity/RegisterPhoneNumActivity;
    //   112: aload 4
    //   114: iconst_1
    //   115: invokevirtual 86	com/tencent/mobileqq/activity/RegisterPhoneNumActivity:a	(Ljava/lang/String;I)V
    //   118: return
    //   119: astore_3
    //   120: aload_3
    //   121: invokevirtual 89	java/io/UnsupportedEncodingException:printStackTrace	()V
    //   124: aconst_null
    //   125: astore_3
    //   126: goto -39 -> 87
    //   129: aload_3
    //   130: ifnull +342 -> 472
    //   133: new 67	java/lang/String
    //   136: dup
    //   137: aload_3
    //   138: ldc 69
    //   140: invokespecial 72	java/lang/String:<init>	([BLjava/lang/String;)V
    //   143: astore_3
    //   144: invokestatic 26	com/tencent/qphone/base/util/QLog:isColorLevel	()Z
    //   147: ifeq +37 -> 184
    //   150: ldc 55
    //   152: iconst_2
    //   153: new 30	java/lang/StringBuilder
    //   156: dup
    //   157: invokespecial 31	java/lang/StringBuilder:<init>	()V
    //   160: ldc 91
    //   162: invokevirtual 37	java/lang/StringBuilder:append	(Ljava/lang/String;)Ljava/lang/StringBuilder;
    //   165: iload_2
    //   166: invokevirtual 45	java/lang/StringBuilder:append	(I)Ljava/lang/StringBuilder;
    //   169: ldc 93
    //   171: invokevirtual 37	java/lang/StringBuilder:append	(Ljava/lang/String;)Ljava/lang/StringBuilder;
    //   174: aload_3
    //   175: invokevirtual 37	java/lang/StringBuilder:append	(Ljava/lang/String;)Ljava/lang/StringBuilder;
    //   178: invokevirtual 49	java/lang/StringBuilder:toString	()Ljava/lang/String;
    //   181: invokestatic 53	com/tencent/qphone/base/util/QLog:d	(Ljava/lang/String;ILjava/lang/String;)V
    //   184: iload_2
    //   185: tableswitch	default:+39 -> 224, 0:+93->278, 1:+110->295, 2:+134->319, 3:+186->371, 4:+39->224, 5:+238->423
    //   225: getfield 10	exw:a	Lcom/tencent/mobileqq/activity/RegisterPhoneNumActivity;
    //   228: invokevirtual 65	com/tencent/mobileqq/activity/RegisterPhoneNumActivity:e	()V
    //   231: aload_3
    //   232: astore 4
    //   234: aload_3
    //   235: invokestatic 78	android/text/TextUtils:isEmpty	(Ljava/lang/CharSequence;)Z
    //   238: ifeq +17 -> 255
    //   241: aload_0
    //   242: getfield 10	exw:a	Lcom/tencent/mobileqq/activity/RegisterPhoneNumActivity;
    //   245: invokevirtual 97	com/tencent/mobileqq/activity/RegisterPhoneNumActivity:getResources	()Landroid/content/res/Resources;
    //   248: ldc 79
    //   250: invokevirtual 100	android/content/res/Resources:getString	(I)Ljava/lang/String;
    //   253: astore 4
    //   255: aload_0
    //   256: getfield 10	exw:a	Lcom/tencent/mobileqq/activity/RegisterPhoneNumActivity;
    //   259: aload 4
    //   261: iconst_1
    //   262: invokevirtual 86	com/tencent/mobileqq/activity/RegisterPhoneNumActivity:a	(Ljava/lang/String;I)V
    //   265: return
    //   266: astore 4
    //   268: aconst_null
    //   269: astore_3
    //   270: aload 4
    //   272: invokevirtual 101	java/lang/Exception:printStackTrace	()V
    //   275: goto -91 -> 184
    //   278: aload_0
    //   279: getfield 10	exw:a	Lcom/tencent/mobileqq/activity/RegisterPhoneNumActivity;
    //   282: iconst_0
    //   283: invokestatic 105	com/tencent/mobileqq/activity/RegisterPhoneNumActivity:b	(Lcom/tencent/mobileqq/activity/RegisterPhoneNumActivity;Z)Z
    //   286: pop
    //   287: aload_0
    //   288: getfield 10	exw:a	Lcom/tencent/mobileqq/activity/RegisterPhoneNumActivity;
    //   291: invokestatic 107	com/tencent/mobileqq/activity/RegisterPhoneNumActivity:a	(Lcom/tencent/mobileqq/activity/RegisterPhoneNumActivity;)V
    //   294: return
    //   295: aload_0
    //   296: getfield 10	exw:a	Lcom/tencent/mobileqq/activity/RegisterPhoneNumActivity;
    //   299: invokevirtual 65	com/tencent/mobileqq/activity/RegisterPhoneNumActivity:e	()V
    //   302: aload_0
    //   303: getfield 10	exw:a	Lcom/tencent/mobileqq/activity/RegisterPhoneNumActivity;
    //   306: iconst_1
    //   307: invokestatic 105	com/tencent/mobileqq/activity/RegisterPhoneNumActivity:b	(Lcom/tencent/mobileqq/activity/RegisterPhoneNumActivity;Z)Z
    //   310: pop
    //   311: aload_0
    //   312: getfield 10	exw:a	Lcom/tencent/mobileqq/activity/RegisterPhoneNumActivity;
    //   315: invokestatic 107	com/tencent/mobileqq/activity/RegisterPhoneNumActivity:a	(Lcom/tencent/mobileqq/activity/RegisterPhoneNumActivity;)V
    //   318: return
    //   319: aload_0
    //   320: getfield 10	exw:a	Lcom/tencent/mobileqq/activity/RegisterPhoneNumActivity;
    //   323: invokevirtual 65	com/tencent/mobileqq/activity/RegisterPhoneNumActivity:e	()V
    //   326: aload_0
    //   327: getfield 10	exw:a	Lcom/tencent/mobileqq/activity/RegisterPhoneNumActivity;
    //   330: getfield 111	com/tencent/mobileqq/activity/RegisterPhoneNumActivity:app	Lcom/tencent/mobileqq/app/QQAppInterface;
    //   333: aload_0
    //   334: getfield 10	exw:a	Lcom/tencent/mobileqq/activity/RegisterPhoneNumActivity;
    //   337: aload_0
    //   338: getfield 10	exw:a	Lcom/tencent/mobileqq/activity/RegisterPhoneNumActivity;
    //   341: getfield 114	com/tencent/mobileqq/activity/RegisterPhoneNumActivity:d	Ljava/lang/String;
    //   344: aload_0
    //   345: getfield 10	exw:a	Lcom/tencent/mobileqq/activity/RegisterPhoneNumActivity;
    //   348: getfield 116	com/tencent/mobileqq/activity/RegisterPhoneNumActivity:e	Ljava/lang/String;
    //   351: aload_0
    //   352: getfield 10	exw:a	Lcom/tencent/mobileqq/activity/RegisterPhoneNumActivity;
    //   355: getfield 119	com/tencent/mobileqq/activity/RegisterPhoneNumActivity:f	Ljava/lang/String;
    //   358: ldc 121
    //   360: invokestatic 126	com/tencent/mobileqq/activity/RegisterVerifyCodeActivity:a	(Lcom/tencent/mobileqq/app/QQAppInterface;Landroid/content/Context;Ljava/lang/String;Ljava/lang/String;Ljava/lang/String;Ljava/lang/String;)V
    //   363: aload_0
    //   364: getfield 10	exw:a	Lcom/tencent/mobileqq/activity/RegisterPhoneNumActivity;
    //   367: invokevirtual 129	com/tencent/mobileqq/activity/RegisterPhoneNumActivity:finish	()V
    //   370: return
    //   371: aload_0
    //   372: getfield 10	exw:a	Lcom/tencent/mobileqq/activity/RegisterPhoneNumActivity;
    //   375: invokevirtual 65	com/tencent/mobileqq/activity/RegisterPhoneNumActivity:e	()V
    //   378: aload_0
    //   379: getfield 10	exw:a	Lcom/tencent/mobileqq/activity/RegisterPhoneNumActivity;
    //   382: getfield 111	com/tencent/mobileqq/activity/RegisterPhoneNumActivity:app	Lcom/tencent/mobileqq/app/QQAppInterface;
    //   385: aload_0
    //   386: getfield 10	exw:a	Lcom/tencent/mobileqq/activity/RegisterPhoneNumActivity;
    //   389: aload_0
    //   390: getfield 10	exw:a	Lcom/tencent/mobileqq/activity/RegisterPhoneNumActivity;
    //   393: getfield 114	com/tencent/mobileqq/activity/RegisterPhoneNumActivity:d	Ljava/lang/String;
    //   396: aload_0
    //   397: getfield 10	exw:a	Lcom/tencent/mobileqq/activity/RegisterPhoneNumActivity;
    //   400: getfield 116	com/tencent/mobileqq/activity/RegisterPhoneNumActivity:e	Ljava/lang/String;
    //   403: aload_0
    //   404: getfield 10	exw:a	Lcom/tencent/mobileqq/activity/RegisterPhoneNumActivity;
    //   407: getfield 119	com/tencent/mobileqq/activity/RegisterPhoneNumActivity:f	Ljava/lang/String;
    //   410: ldc 121
    //   412: invokestatic 126	com/tencent/mobileqq/activity/RegisterVerifyCodeActivity:a	(Lcom/tencent/mobileqq/app/QQAppInterface;Landroid/content/Context;Ljava/lang/String;Ljava/lang/String;Ljava/lang/String;Ljava/lang/String;)V
    //   415: aload_0
    //   416: getfield 10	exw:a	Lcom/tencent/mobileqq/activity/RegisterPhoneNumActivity;
    //   419: invokevirtual 129	com/tencent/mobileqq/activity/RegisterPhoneNumActivity:finish	()V
    //   422: return
    //   423: aload_0
    //   424: getfield 10	exw:a	Lcom/tencent/mobileqq/activity/RegisterPhoneNumActivity;
    //   427: invokevirtual 65	com/tencent/mobileqq/activity/RegisterPhoneNumActivity:e	()V
    //   430: aload_3
    //   431: invokestatic 78	android/text/TextUtils:isEmpty	(Ljava/lang/CharSequence;)Z
    //   434: ifne +13 -> 447
    //   437: aload_0
    //   438: getfield 10	exw:a	Lcom/tencent/mobileqq/activity/RegisterPhoneNumActivity;
    //   441: aconst_null
    //   442: aload_3
    //   443: invokevirtual 132	com/tencent/mobileqq/activity/RegisterPhoneNumActivity:a	(Ljava/lang/String;Ljava/lang/String;)V
    //   446: return
    //   447: aload_0
    //   448: getfield 10	exw:a	Lcom/tencent/mobileqq/activity/RegisterPhoneNumActivity;
    //   451: ldc 133
    //   453: invokevirtual 83	com/tencent/mobileqq/activity/RegisterPhoneNumActivity:getString	(I)Ljava/lang/String;
    //   456: astore_3
    //   457: aload_0
    //   458: getfield 10	exw:a	Lcom/tencent/mobileqq/activity/RegisterPhoneNumActivity;
    //   461: aconst_null
    //   462: aload_3
    //   463: invokevirtual 132	com/tencent/mobileqq/activity/RegisterPhoneNumActivity:a	(Ljava/lang/String;Ljava/lang/String;)V
    //   466: return
    //   467: astore 4
    //   469: goto -199 -> 270
    //   472: aconst_null
    //   473: astore_3
    //   474: goto -330 -> 144
    // Local variable table:
    //   start	length	slot	name	signature
    //   0	477	0	this	exw
    //   0	477	1	paramBoolean	boolean
    //   0	477	2	paramInt	int
    //   0	477	3	paramArrayOfByte	byte[]
    //   88	172	4	localObject	java.lang.Object
    //   266	5	4	localException1	java.lang.Exception
    //   467	1	4	localException2	java.lang.Exception
    // Exception table:
    //   from	to	target	type
    //   76	87	119	java/io/UnsupportedEncodingException
    //   133	144	266	java/lang/Exception
    //   144	184	467	java/lang/Exception
  }
  
  /* Error */
  public void onRegisterCommitMobileResp(boolean paramBoolean, int paramInt, byte[] paramArrayOfByte1, byte[] paramArrayOfByte2)
  {
    // Byte code:
    //   0: aconst_null
    //   1: astore 8
    //   3: aconst_null
    //   4: astore 7
    //   6: invokestatic 26	com/tencent/qphone/base/util/QLog:isColorLevel	()Z
    //   9: ifeq +11 -> 20
    //   12: ldc 55
    //   14: iconst_2
    //   15: ldc 137
    //   17: invokestatic 53	com/tencent/qphone/base/util/QLog:d	(Ljava/lang/String;ILjava/lang/String;)V
    //   20: aload_3
    //   21: ifnull +344 -> 365
    //   24: new 67	java/lang/String
    //   27: dup
    //   28: aload_3
    //   29: ldc 69
    //   31: invokespecial 72	java/lang/String:<init>	([BLjava/lang/String;)V
    //   34: astore 5
    //   36: aload 5
    //   38: astore 6
    //   40: invokestatic 26	com/tencent/qphone/base/util/QLog:isColorLevel	()Z
    //   43: ifeq +42 -> 85
    //   46: ldc 55
    //   48: iconst_2
    //   49: new 30	java/lang/StringBuilder
    //   52: dup
    //   53: invokespecial 31	java/lang/StringBuilder:<init>	()V
    //   56: ldc 139
    //   58: invokevirtual 37	java/lang/StringBuilder:append	(Ljava/lang/String;)Ljava/lang/StringBuilder;
    //   61: iload_2
    //   62: invokevirtual 45	java/lang/StringBuilder:append	(I)Ljava/lang/StringBuilder;
    //   65: ldc 93
    //   67: invokevirtual 37	java/lang/StringBuilder:append	(Ljava/lang/String;)Ljava/lang/StringBuilder;
    //   70: aload 5
    //   72: invokevirtual 37	java/lang/StringBuilder:append	(Ljava/lang/String;)Ljava/lang/StringBuilder;
    //   75: invokevirtual 49	java/lang/StringBuilder:toString	()Ljava/lang/String;
    //   78: invokestatic 53	com/tencent/qphone/base/util/QLog:d	(Ljava/lang/String;ILjava/lang/String;)V
    //   81: aload 5
    //   83: astore 6
    //   85: aload_0
    //   86: getfield 10	exw:a	Lcom/tencent/mobileqq/activity/RegisterPhoneNumActivity;
    //   89: invokevirtual 62	com/tencent/mobileqq/activity/RegisterPhoneNumActivity:isFinishing	()Z
    //   92: ifeq +21 -> 113
    //   95: return
    //   96: astore 6
    //   98: aconst_null
    //   99: astore 5
    //   101: aload 6
    //   103: invokevirtual 101	java/lang/Exception:printStackTrace	()V
    //   106: aload 5
    //   108: astore 6
    //   110: goto -25 -> 85
    //   113: iload_2
    //   114: iconst_3
    //   115: if_icmpeq +10 -> 125
    //   118: aload_0
    //   119: getfield 10	exw:a	Lcom/tencent/mobileqq/activity/RegisterPhoneNumActivity;
    //   122: invokevirtual 65	com/tencent/mobileqq/activity/RegisterPhoneNumActivity:e	()V
    //   125: iload_1
    //   126: ifne +34 -> 160
    //   129: aload 6
    //   131: astore_3
    //   132: aload 6
    //   134: invokestatic 78	android/text/TextUtils:isEmpty	(Ljava/lang/CharSequence;)Z
    //   137: ifeq +13 -> 150
    //   140: aload_0
    //   141: getfield 10	exw:a	Lcom/tencent/mobileqq/activity/RegisterPhoneNumActivity;
    //   144: ldc 79
    //   146: invokevirtual 83	com/tencent/mobileqq/activity/RegisterPhoneNumActivity:getString	(I)Ljava/lang/String;
    //   149: astore_3
    //   150: aload_0
    //   151: getfield 10	exw:a	Lcom/tencent/mobileqq/activity/RegisterPhoneNumActivity;
    //   154: aload_3
    //   155: iconst_1
    //   156: invokevirtual 86	com/tencent/mobileqq/activity/RegisterPhoneNumActivity:a	(Ljava/lang/String;I)V
    //   159: return
    //   160: iload_2
    //   161: tableswitch	default:+31 -> 192, 0:+42->203, 1:+135->296, 2:+50->211, 3:+143->304
    //   193: getfield 10	exw:a	Lcom/tencent/mobileqq/activity/RegisterPhoneNumActivity;
    //   196: ldc 79
    //   198: iconst_1
    //   199: invokevirtual 142	com/tencent/mobileqq/activity/RegisterPhoneNumActivity:a	(II)V
    //   202: return
    //   203: aload_0
    //   204: getfield 10	exw:a	Lcom/tencent/mobileqq/activity/RegisterPhoneNumActivity;
    //   207: invokevirtual 144	com/tencent/mobileqq/activity/RegisterPhoneNumActivity:a	()V
    //   210: return
    //   211: new 67	java/lang/String
    //   214: dup
    //   215: aload 4
    //   217: ldc 69
    //   219: invokespecial 72	java/lang/String:<init>	([BLjava/lang/String;)V
    //   222: astore 4
    //   224: new 67	java/lang/String
    //   227: dup
    //   228: aload_3
    //   229: ldc 69
    //   231: invokespecial 72	java/lang/String:<init>	([BLjava/lang/String;)V
    //   234: astore_3
    //   235: aload 4
    //   237: invokestatic 78	android/text/TextUtils:isEmpty	(Ljava/lang/CharSequence;)Z
    //   240: ifne +10 -> 250
    //   243: aload_3
    //   244: invokestatic 78	android/text/TextUtils:isEmpty	(Ljava/lang/CharSequence;)Z
    //   247: ifeq +38 -> 285
    //   250: aload_0
    //   251: getfield 10	exw:a	Lcom/tencent/mobileqq/activity/RegisterPhoneNumActivity;
    //   254: ldc 79
    //   256: iconst_1
    //   257: invokevirtual 142	com/tencent/mobileqq/activity/RegisterPhoneNumActivity:a	(II)V
    //   260: return
    //   261: astore 4
    //   263: aload 4
    //   265: invokevirtual 89	java/io/UnsupportedEncodingException:printStackTrace	()V
    //   268: aconst_null
    //   269: astore 4
    //   271: goto -47 -> 224
    //   274: astore_3
    //   275: aload_3
    //   276: invokevirtual 89	java/io/UnsupportedEncodingException:printStackTrace	()V
    //   279: aload 7
    //   281: astore_3
    //   282: goto -47 -> 235
    //   285: aload_0
    //   286: getfield 10	exw:a	Lcom/tencent/mobileqq/activity/RegisterPhoneNumActivity;
    //   289: aload 4
    //   291: aload_3
    //   292: invokestatic 147	com/tencent/mobileqq/activity/RegisterPhoneNumActivity:a	(Lcom/tencent/mobileqq/activity/RegisterPhoneNumActivity;Ljava/lang/String;Ljava/lang/String;)V
    //   295: return
    //   296: aload_0
    //   297: getfield 10	exw:a	Lcom/tencent/mobileqq/activity/RegisterPhoneNumActivity;
    //   300: invokevirtual 144	com/tencent/mobileqq/activity/RegisterPhoneNumActivity:a	()V
    //   303: return
    //   304: new 67	java/lang/String
    //   307: dup
    //   308: aload_3
    //   309: ldc 69
    //   311: invokespecial 72	java/lang/String:<init>	([BLjava/lang/String;)V
    //   314: astore_3
    //   315: aload_3
    //   316: invokestatic 78	android/text/TextUtils:isEmpty	(Ljava/lang/CharSequence;)Z
    //   319: ifeq +25 -> 344
    //   322: aload_0
    //   323: getfield 10	exw:a	Lcom/tencent/mobileqq/activity/RegisterPhoneNumActivity;
    //   326: ldc 79
    //   328: iconst_1
    //   329: invokevirtual 142	com/tencent/mobileqq/activity/RegisterPhoneNumActivity:a	(II)V
    //   332: return
    //   333: astore_3
    //   334: aload_3
    //   335: invokevirtual 89	java/io/UnsupportedEncodingException:printStackTrace	()V
    //   338: aload 8
    //   340: astore_3
    //   341: goto -26 -> 315
    //   344: aload_0
    //   345: getfield 10	exw:a	Lcom/tencent/mobileqq/activity/RegisterPhoneNumActivity;
    //   348: aload_3
    //   349: invokestatic 150	com/tencent/mobileqq/activity/RegisterPhoneNumActivity:a	(Lcom/tencent/mobileqq/activity/RegisterPhoneNumActivity;Ljava/lang/String;)V
    //   352: aload_0
    //   353: getfield 10	exw:a	Lcom/tencent/mobileqq/activity/RegisterPhoneNumActivity;
    //   356: invokevirtual 65	com/tencent/mobileqq/activity/RegisterPhoneNumActivity:e	()V
    //   359: return
    //   360: astore 6
    //   362: goto -261 -> 101
    //   365: aconst_null
    //   366: astore 5
    //   368: goto -332 -> 36
    // Local variable table:
    //   start	length	slot	name	signature
    //   0	371	0	this	exw
    //   0	371	1	paramBoolean	boolean
    //   0	371	2	paramInt	int
    //   0	371	3	paramArrayOfByte1	byte[]
    //   0	371	4	paramArrayOfByte2	byte[]
    //   34	333	5	str1	java.lang.String
    //   38	46	6	str2	java.lang.String
    //   96	6	6	localException1	java.lang.Exception
    //   108	25	6	str3	java.lang.String
    //   360	1	6	localException2	java.lang.Exception
    //   4	276	7	localObject1	java.lang.Object
    //   1	338	8	localObject2	java.lang.Object
    // Exception table:
    //   from	to	target	type
    //   24	36	96	java/lang/Exception
    //   211	224	261	java/io/UnsupportedEncodingException
    //   224	235	274	java/io/UnsupportedEncodingException
    //   304	315	333	java/io/UnsupportedEncodingException
    //   40	81	360	java/lang/Exception
  }
}


/* Location:           L:\local\mybackup\temp\qq_apk\com.tencent.minihd.qq\assets\exlibs.2.jar\classes.jar
 * Qualified Name:     exw
 * JD-Core Version:    0.7.0.1
 */