package com.tencent.mobileqq.emosm.api.impl;

class EmoticonManagerServiceImpl$24
  implements Runnable
{
  EmoticonManagerServiceImpl$24(EmoticonManagerServiceImpl paramEmoticonManagerServiceImpl, int paramInt) {}
  
  /* Error */
  public void run()
  {
    // Byte code:
    //   0: aconst_null
    //   1: astore 7
    //   3: aconst_null
    //   4: astore 6
    //   6: aload 6
    //   8: astore 4
    //   10: aload 7
    //   12: astore 5
    //   14: invokestatic 31	com/tencent/qphone/base/util/QLog:isColorLevel	()Z
    //   17: ifeq +19 -> 36
    //   20: aload 6
    //   22: astore 4
    //   24: aload 7
    //   26: astore 5
    //   28: ldc 33
    //   30: iconst_2
    //   31: ldc 35
    //   33: invokestatic 39	com/tencent/qphone/base/util/QLog:d	(Ljava/lang/String;ILjava/lang/String;)V
    //   36: aload 6
    //   38: astore 4
    //   40: aload 7
    //   42: astore 5
    //   44: aload_0
    //   45: getfield 14	com/tencent/mobileqq/emosm/api/impl/EmoticonManagerServiceImpl$24:this$0	Lcom/tencent/mobileqq/emosm/api/impl/EmoticonManagerServiceImpl;
    //   48: getfield 45	com/tencent/mobileqq/emosm/api/impl/EmoticonManagerServiceImpl:app	Lcom/tencent/common/app/business/BaseQQAppInterface;
    //   51: ldc 47
    //   53: iconst_1
    //   54: aconst_null
    //   55: invokestatic 53	com/tencent/mobileqq/vas/updatesystem/VasUpdateUtil:b	(Lmqq/app/AppRuntime;Ljava/lang/String;ZLcom/tencent/mobileqq/vas/updatesystem/callback/CallBacker;)Lcom/google/gson/stream/JsonReader;
    //   58: astore 6
    //   60: aload 6
    //   62: ifnonnull +38 -> 100
    //   65: aload 6
    //   67: astore 4
    //   69: aload 6
    //   71: astore 5
    //   73: ldc 33
    //   75: iconst_1
    //   76: ldc 55
    //   78: invokestatic 39	com/tencent/qphone/base/util/QLog:d	(Ljava/lang/String;ILjava/lang/String;)V
    //   81: aload 6
    //   83: ifnull +16 -> 99
    //   86: aload 6
    //   88: invokevirtual 60	com/google/gson/stream/JsonReader:close	()V
    //   91: return
    //   92: astore 4
    //   94: aload 4
    //   96: invokevirtual 63	java/io/IOException:printStackTrace	()V
    //   99: return
    //   100: aload 6
    //   102: astore 4
    //   104: aload 6
    //   106: astore 5
    //   108: new 65	java/util/HashMap
    //   111: dup
    //   112: invokespecial 66	java/util/HashMap:<init>	()V
    //   115: astore 7
    //   117: aload 6
    //   119: astore 4
    //   121: aload 6
    //   123: astore 5
    //   125: aload 6
    //   127: invokevirtual 69	com/google/gson/stream/JsonReader:beginObject	()V
    //   130: iconst_0
    //   131: istore_1
    //   132: aload 6
    //   134: astore 4
    //   136: aload 6
    //   138: astore 5
    //   140: aload 6
    //   142: invokevirtual 72	com/google/gson/stream/JsonReader:hasNext	()Z
    //   145: ifeq +227 -> 372
    //   148: aload 6
    //   150: astore 4
    //   152: aload 6
    //   154: astore 5
    //   156: ldc 74
    //   158: aload 6
    //   160: invokevirtual 78	com/google/gson/stream/JsonReader:nextName	()Ljava/lang/String;
    //   163: invokevirtual 84	java/lang/String:equals	(Ljava/lang/Object;)Z
    //   166: ifeq +190 -> 356
    //   169: aload 6
    //   171: astore 4
    //   173: aload 6
    //   175: astore 5
    //   177: aload 6
    //   179: invokevirtual 69	com/google/gson/stream/JsonReader:beginObject	()V
    //   182: aload 6
    //   184: astore 4
    //   186: aload 6
    //   188: astore 5
    //   190: aload 6
    //   192: invokevirtual 72	com/google/gson/stream/JsonReader:hasNext	()Z
    //   195: ifeq +143 -> 338
    //   198: aload 6
    //   200: astore 4
    //   202: aload 6
    //   204: astore 5
    //   206: aload 6
    //   208: invokevirtual 78	com/google/gson/stream/JsonReader:nextName	()Ljava/lang/String;
    //   211: astore 8
    //   213: aload 6
    //   215: astore 4
    //   217: aload 6
    //   219: astore 5
    //   221: aload_0
    //   222: getfield 16	com/tencent/mobileqq/emosm/api/impl/EmoticonManagerServiceImpl$24:a	I
    //   225: istore_1
    //   226: aload 6
    //   228: astore 4
    //   230: aload 6
    //   232: astore 5
    //   234: aload_0
    //   235: getfield 16	com/tencent/mobileqq/emosm/api/impl/EmoticonManagerServiceImpl$24:a	I
    //   238: iconst_3
    //   239: if_icmpne +5 -> 244
    //   242: iconst_2
    //   243: istore_1
    //   244: aload 6
    //   246: astore 4
    //   248: aload 6
    //   250: astore 5
    //   252: aload 6
    //   254: invokevirtual 87	com/google/gson/stream/JsonReader:beginArray	()V
    //   257: iconst_0
    //   258: istore_2
    //   259: aload 6
    //   261: astore 4
    //   263: aload 6
    //   265: astore 5
    //   267: aload 6
    //   269: invokevirtual 72	com/google/gson/stream/JsonReader:hasNext	()Z
    //   272: ifeq +50 -> 322
    //   275: aload 6
    //   277: astore 4
    //   279: aload 6
    //   281: astore 5
    //   283: aload 6
    //   285: invokevirtual 91	com/google/gson/stream/JsonReader:nextInt	()I
    //   288: istore_3
    //   289: iload_2
    //   290: iload_1
    //   291: if_icmpne +311 -> 602
    //   294: aload 6
    //   296: astore 4
    //   298: aload 6
    //   300: astore 5
    //   302: aload 7
    //   304: aload 8
    //   306: invokevirtual 94	java/lang/String:toLowerCase	()Ljava/lang/String;
    //   309: iload_3
    //   310: invokestatic 100	java/lang/Integer:valueOf	(I)Ljava/lang/Integer;
    //   313: invokeinterface 106 3 0
    //   318: pop
    //   319: goto +283 -> 602
    //   322: aload 6
    //   324: astore 4
    //   326: aload 6
    //   328: astore 5
    //   330: aload 6
    //   332: invokevirtual 109	com/google/gson/stream/JsonReader:endArray	()V
    //   335: goto -153 -> 182
    //   338: aload 6
    //   340: astore 4
    //   342: aload 6
    //   344: astore 5
    //   346: aload 6
    //   348: invokevirtual 112	com/google/gson/stream/JsonReader:endObject	()V
    //   351: iconst_1
    //   352: istore_1
    //   353: goto -221 -> 132
    //   356: aload 6
    //   358: astore 4
    //   360: aload 6
    //   362: astore 5
    //   364: aload 6
    //   366: invokevirtual 115	com/google/gson/stream/JsonReader:skipValue	()V
    //   369: goto -237 -> 132
    //   372: aload 6
    //   374: astore 4
    //   376: aload 6
    //   378: astore 5
    //   380: aload 6
    //   382: invokevirtual 112	com/google/gson/stream/JsonReader:endObject	()V
    //   385: iload_1
    //   386: ifne +38 -> 424
    //   389: aload 6
    //   391: astore 4
    //   393: aload 6
    //   395: astore 5
    //   397: ldc 33
    //   399: iconst_1
    //   400: ldc 117
    //   402: invokestatic 39	com/tencent/qphone/base/util/QLog:d	(Ljava/lang/String;ILjava/lang/String;)V
    //   405: aload 6
    //   407: ifnull +16 -> 423
    //   410: aload 6
    //   412: invokevirtual 60	com/google/gson/stream/JsonReader:close	()V
    //   415: return
    //   416: astore 4
    //   418: aload 4
    //   420: invokevirtual 63	java/io/IOException:printStackTrace	()V
    //   423: return
    //   424: aload 6
    //   426: astore 4
    //   428: aload 6
    //   430: astore 5
    //   432: aload_0
    //   433: getfield 14	com/tencent/mobileqq/emosm/api/impl/EmoticonManagerServiceImpl$24:this$0	Lcom/tencent/mobileqq/emosm/api/impl/EmoticonManagerServiceImpl;
    //   436: getfield 121	com/tencent/mobileqq/emosm/api/impl/EmoticonManagerServiceImpl:uiHandler	Landroid/os/Handler;
    //   439: ifnull +32 -> 471
    //   442: aload 6
    //   444: astore 4
    //   446: aload 6
    //   448: astore 5
    //   450: aload_0
    //   451: getfield 14	com/tencent/mobileqq/emosm/api/impl/EmoticonManagerServiceImpl$24:this$0	Lcom/tencent/mobileqq/emosm/api/impl/EmoticonManagerServiceImpl;
    //   454: getfield 121	com/tencent/mobileqq/emosm/api/impl/EmoticonManagerServiceImpl:uiHandler	Landroid/os/Handler;
    //   457: new 123	com/tencent/mobileqq/emosm/api/impl/EmoticonManagerServiceImpl$24$1
    //   460: dup
    //   461: aload_0
    //   462: aload 7
    //   464: invokespecial 126	com/tencent/mobileqq/emosm/api/impl/EmoticonManagerServiceImpl$24$1:<init>	(Lcom/tencent/mobileqq/emosm/api/impl/EmoticonManagerServiceImpl$24;Ljava/util/Map;)V
    //   467: invokevirtual 132	android/os/Handler:post	(Ljava/lang/Runnable;)Z
    //   470: pop
    //   471: aload 6
    //   473: ifnull +99 -> 572
    //   476: aload 6
    //   478: invokevirtual 60	com/google/gson/stream/JsonReader:close	()V
    //   481: return
    //   482: astore 5
    //   484: goto +89 -> 573
    //   487: astore 6
    //   489: aload 5
    //   491: astore 4
    //   493: invokestatic 31	com/tencent/qphone/base/util/QLog:isColorLevel	()Z
    //   496: ifeq +58 -> 554
    //   499: aload 5
    //   501: astore 4
    //   503: new 134	java/lang/StringBuilder
    //   506: dup
    //   507: invokespecial 135	java/lang/StringBuilder:<init>	()V
    //   510: astore 7
    //   512: aload 5
    //   514: astore 4
    //   516: aload 7
    //   518: ldc 137
    //   520: invokevirtual 141	java/lang/StringBuilder:append	(Ljava/lang/String;)Ljava/lang/StringBuilder;
    //   523: pop
    //   524: aload 5
    //   526: astore 4
    //   528: aload 7
    //   530: aload 6
    //   532: invokevirtual 144	java/lang/Throwable:getMessage	()Ljava/lang/String;
    //   535: invokevirtual 141	java/lang/StringBuilder:append	(Ljava/lang/String;)Ljava/lang/StringBuilder;
    //   538: pop
    //   539: aload 5
    //   541: astore 4
    //   543: ldc 33
    //   545: iconst_2
    //   546: aload 7
    //   548: invokevirtual 147	java/lang/StringBuilder:toString	()Ljava/lang/String;
    //   551: invokestatic 150	com/tencent/qphone/base/util/QLog:e	(Ljava/lang/String;ILjava/lang/String;)V
    //   554: aload 5
    //   556: ifnull +16 -> 572
    //   559: aload 5
    //   561: invokevirtual 60	com/google/gson/stream/JsonReader:close	()V
    //   564: return
    //   565: astore 4
    //   567: aload 4
    //   569: invokevirtual 63	java/io/IOException:printStackTrace	()V
    //   572: return
    //   573: aload 4
    //   575: ifnull +18 -> 593
    //   578: aload 4
    //   580: invokevirtual 60	com/google/gson/stream/JsonReader:close	()V
    //   583: goto +10 -> 593
    //   586: astore 4
    //   588: aload 4
    //   590: invokevirtual 63	java/io/IOException:printStackTrace	()V
    //   593: goto +6 -> 599
    //   596: aload 5
    //   598: athrow
    //   599: goto -3 -> 596
    //   602: iload_2
    //   603: iconst_1
    //   604: iadd
    //   605: istore_2
    //   606: goto -347 -> 259
    // Local variable table:
    //   start	length	slot	name	signature
    //   0	609	0	this	24
    //   131	255	1	i	int
    //   258	348	2	j	int
    //   288	22	3	k	int
    //   8	60	4	localJsonReader1	com.google.gson.stream.JsonReader
    //   92	3	4	localIOException1	java.io.IOException
    //   102	290	4	localJsonReader2	com.google.gson.stream.JsonReader
    //   416	3	4	localIOException2	java.io.IOException
    //   426	116	4	localObject1	Object
    //   565	14	4	localIOException3	java.io.IOException
    //   586	3	4	localIOException4	java.io.IOException
    //   12	437	5	localObject2	Object
    //   482	115	5	localObject3	Object
    //   4	473	6	localJsonReader3	com.google.gson.stream.JsonReader
    //   487	44	6	localThrowable	java.lang.Throwable
    //   1	546	7	localObject4	Object
    //   211	94	8	str	java.lang.String
    // Exception table:
    //   from	to	target	type
    //   86	91	92	java/io/IOException
    //   410	415	416	java/io/IOException
    //   14	20	482	finally
    //   28	36	482	finally
    //   44	60	482	finally
    //   73	81	482	finally
    //   108	117	482	finally
    //   125	130	482	finally
    //   140	148	482	finally
    //   156	169	482	finally
    //   177	182	482	finally
    //   190	198	482	finally
    //   206	213	482	finally
    //   221	226	482	finally
    //   234	242	482	finally
    //   252	257	482	finally
    //   267	275	482	finally
    //   283	289	482	finally
    //   302	319	482	finally
    //   330	335	482	finally
    //   346	351	482	finally
    //   364	369	482	finally
    //   380	385	482	finally
    //   397	405	482	finally
    //   432	442	482	finally
    //   450	471	482	finally
    //   493	499	482	finally
    //   503	512	482	finally
    //   516	524	482	finally
    //   528	539	482	finally
    //   543	554	482	finally
    //   14	20	487	java/lang/Throwable
    //   28	36	487	java/lang/Throwable
    //   44	60	487	java/lang/Throwable
    //   73	81	487	java/lang/Throwable
    //   108	117	487	java/lang/Throwable
    //   125	130	487	java/lang/Throwable
    //   140	148	487	java/lang/Throwable
    //   156	169	487	java/lang/Throwable
    //   177	182	487	java/lang/Throwable
    //   190	198	487	java/lang/Throwable
    //   206	213	487	java/lang/Throwable
    //   221	226	487	java/lang/Throwable
    //   234	242	487	java/lang/Throwable
    //   252	257	487	java/lang/Throwable
    //   267	275	487	java/lang/Throwable
    //   283	289	487	java/lang/Throwable
    //   302	319	487	java/lang/Throwable
    //   330	335	487	java/lang/Throwable
    //   346	351	487	java/lang/Throwable
    //   364	369	487	java/lang/Throwable
    //   380	385	487	java/lang/Throwable
    //   397	405	487	java/lang/Throwable
    //   432	442	487	java/lang/Throwable
    //   450	471	487	java/lang/Throwable
    //   476	481	565	java/io/IOException
    //   559	564	565	java/io/IOException
    //   578	583	586	java/io/IOException
  }
}


/* Location:           L:\local\mybackup\temp\qq_apk\com.tencent.mobileqq\classes8.jar
 * Qualified Name:     com.tencent.mobileqq.emosm.api.impl.EmoticonManagerServiceImpl.24
 * JD-Core Version:    0.7.0.1
 */