package com.huawei.hms.hatool;

import android.content.Context;
import android.util.Pair;
import java.util.List;

public class k0
  implements m0
{
  public Context a = b.f();
  public String b;
  public String c;
  public String d;
  
  public k0(String paramString1, String paramString2, String paramString3)
  {
    this.b = paramString1;
    this.c = paramString2;
    this.d = paramString3;
  }
  
  public final void a(String paramString, List<q> paramList)
  {
    paramString = s0.a(paramString);
    new t(paramList, (String)paramString.first, (String)paramString.second, this.d).a();
  }
  
  /* Error */
  public void run()
  {
    // Byte code:
    //   0: ldc 65
    //   2: ldc 67
    //   4: invokestatic 72	com/huawei/hms/hatool/y:c	(Ljava/lang/String;Ljava/lang/String;)V
    //   7: aload_0
    //   8: getfield 25	com/huawei/hms/hatool/k0:a	Landroid/content/Context;
    //   11: invokestatic 77	com/huawei/hms/hatool/p0:a	(Landroid/content/Context;)Z
    //   14: istore_2
    //   15: iload_2
    //   16: ifeq +16 -> 32
    //   19: ldc 65
    //   21: ldc 79
    //   23: invokestatic 72	com/huawei/hms/hatool/y:c	(Ljava/lang/String;Ljava/lang/String;)V
    //   26: aload_0
    //   27: ldc 81
    //   29: putfield 29	com/huawei/hms/hatool/k0:c	Ljava/lang/String;
    //   32: aload_0
    //   33: getfield 25	com/huawei/hms/hatool/k0:a	Landroid/content/Context;
    //   36: aload_0
    //   37: getfield 27	com/huawei/hms/hatool/k0:b	Ljava/lang/String;
    //   40: aload_0
    //   41: getfield 29	com/huawei/hms/hatool/k0:c	Ljava/lang/String;
    //   44: invokestatic 86	com/huawei/hms/hatool/w:a	(Landroid/content/Context;Ljava/lang/String;Ljava/lang/String;)Ljava/util/Map;
    //   47: astore_3
    //   48: aload_3
    //   49: invokeinterface 92 1 0
    //   54: istore_1
    //   55: iload_1
    //   56: ifne +114 -> 170
    //   59: ldc 65
    //   61: ldc 94
    //   63: iconst_2
    //   64: anewarray 4	java/lang/Object
    //   67: dup
    //   68: iconst_0
    //   69: aload_0
    //   70: getfield 27	com/huawei/hms/hatool/k0:b	Ljava/lang/String;
    //   73: aastore
    //   74: dup
    //   75: iconst_1
    //   76: aload_0
    //   77: getfield 29	com/huawei/hms/hatool/k0:c	Ljava/lang/String;
    //   80: aastore
    //   81: invokestatic 97	com/huawei/hms/hatool/y:b	(Ljava/lang/String;Ljava/lang/String;[Ljava/lang/Object;)V
    //   84: ldc 81
    //   86: aload_0
    //   87: getfield 29	com/huawei/hms/hatool/k0:c	Ljava/lang/String;
    //   90: invokevirtual 101	java/lang/String:equals	(Ljava/lang/Object;)Z
    //   93: ifeq +30 -> 123
    //   96: aload_0
    //   97: getfield 25	com/huawei/hms/hatool/k0:a	Landroid/content/Context;
    //   100: ldc 103
    //   102: iconst_0
    //   103: anewarray 48	java/lang/String
    //   106: invokestatic 108	com/huawei/hms/hatool/g0:a	(Landroid/content/Context;Ljava/lang/String;[Ljava/lang/String;)V
    //   109: aload_0
    //   110: getfield 25	com/huawei/hms/hatool/k0:a	Landroid/content/Context;
    //   113: ldc 110
    //   115: iconst_0
    //   116: anewarray 48	java/lang/String
    //   119: invokestatic 108	com/huawei/hms/hatool/g0:a	(Landroid/content/Context;Ljava/lang/String;[Ljava/lang/String;)V
    //   122: return
    //   123: aload_0
    //   124: getfield 27	com/huawei/hms/hatool/k0:b	Ljava/lang/String;
    //   127: aload_0
    //   128: getfield 29	com/huawei/hms/hatool/k0:c	Ljava/lang/String;
    //   131: invokestatic 113	com/huawei/hms/hatool/s0:a	(Ljava/lang/String;Ljava/lang/String;)Ljava/lang/String;
    //   134: astore_3
    //   135: aload_0
    //   136: getfield 25	com/huawei/hms/hatool/k0:a	Landroid/content/Context;
    //   139: ldc 103
    //   141: iconst_1
    //   142: anewarray 48	java/lang/String
    //   145: dup
    //   146: iconst_0
    //   147: aload_3
    //   148: aastore
    //   149: invokestatic 108	com/huawei/hms/hatool/g0:a	(Landroid/content/Context;Ljava/lang/String;[Ljava/lang/String;)V
    //   152: aload_0
    //   153: getfield 25	com/huawei/hms/hatool/k0:a	Landroid/content/Context;
    //   156: ldc 110
    //   158: iconst_1
    //   159: anewarray 48	java/lang/String
    //   162: dup
    //   163: iconst_0
    //   164: aload_3
    //   165: aastore
    //   166: invokestatic 108	com/huawei/hms/hatool/g0:a	(Landroid/content/Context;Ljava/lang/String;[Ljava/lang/String;)V
    //   169: return
    //   170: aload_3
    //   171: invokeinterface 117 1 0
    //   176: invokeinterface 123 1 0
    //   181: astore_3
    //   182: aload_3
    //   183: invokeinterface 129 1 0
    //   188: ifeq +41 -> 229
    //   191: aload_3
    //   192: invokeinterface 133 1 0
    //   197: checkcast 135	java/util/Map$Entry
    //   200: astore 4
    //   202: aload_0
    //   203: aload 4
    //   205: invokeinterface 138 1 0
    //   210: checkcast 48	java/lang/String
    //   213: aload 4
    //   215: invokeinterface 141 1 0
    //   220: checkcast 143	java/util/List
    //   223: invokevirtual 145	com/huawei/hms/hatool/k0:a	(Ljava/lang/String;Ljava/util/List;)V
    //   226: goto -44 -> 182
    //   229: ldc 81
    //   231: aload_0
    //   232: getfield 29	com/huawei/hms/hatool/k0:c	Ljava/lang/String;
    //   235: invokevirtual 101	java/lang/String:equals	(Ljava/lang/Object;)Z
    //   238: ifeq +32 -> 270
    //   241: aload_0
    //   242: getfield 25	com/huawei/hms/hatool/k0:a	Landroid/content/Context;
    //   245: ldc 103
    //   247: iconst_0
    //   248: anewarray 48	java/lang/String
    //   251: invokestatic 108	com/huawei/hms/hatool/g0:a	(Landroid/content/Context;Ljava/lang/String;[Ljava/lang/String;)V
    //   254: aload_0
    //   255: getfield 25	com/huawei/hms/hatool/k0:a	Landroid/content/Context;
    //   258: ldc 110
    //   260: iconst_0
    //   261: anewarray 48	java/lang/String
    //   264: invokestatic 108	com/huawei/hms/hatool/g0:a	(Landroid/content/Context;Ljava/lang/String;[Ljava/lang/String;)V
    //   267: goto +309 -> 576
    //   270: aload_0
    //   271: getfield 27	com/huawei/hms/hatool/k0:b	Ljava/lang/String;
    //   274: aload_0
    //   275: getfield 29	com/huawei/hms/hatool/k0:c	Ljava/lang/String;
    //   278: invokestatic 113	com/huawei/hms/hatool/s0:a	(Ljava/lang/String;Ljava/lang/String;)Ljava/lang/String;
    //   281: astore_3
    //   282: aload_0
    //   283: getfield 25	com/huawei/hms/hatool/k0:a	Landroid/content/Context;
    //   286: ldc 103
    //   288: iconst_1
    //   289: anewarray 48	java/lang/String
    //   292: dup
    //   293: iconst_0
    //   294: aload_3
    //   295: aastore
    //   296: invokestatic 108	com/huawei/hms/hatool/g0:a	(Landroid/content/Context;Ljava/lang/String;[Ljava/lang/String;)V
    //   299: aload_0
    //   300: getfield 25	com/huawei/hms/hatool/k0:a	Landroid/content/Context;
    //   303: ldc 110
    //   305: iconst_1
    //   306: anewarray 48	java/lang/String
    //   309: dup
    //   310: iconst_0
    //   311: aload_3
    //   312: aastore
    //   313: invokestatic 108	com/huawei/hms/hatool/g0:a	(Landroid/content/Context;Ljava/lang/String;[Ljava/lang/String;)V
    //   316: goto +260 -> 576
    //   319: astore_3
    //   320: goto +274 -> 594
    //   323: astore_3
    //   324: new 147	java/lang/StringBuilder
    //   327: dup
    //   328: invokespecial 148	java/lang/StringBuilder:<init>	()V
    //   331: astore 4
    //   333: aload 4
    //   335: ldc 150
    //   337: invokevirtual 154	java/lang/StringBuilder:append	(Ljava/lang/String;)Ljava/lang/StringBuilder;
    //   340: pop
    //   341: aload 4
    //   343: aload_3
    //   344: invokevirtual 158	java/lang/Exception:getMessage	()Ljava/lang/String;
    //   347: invokevirtual 154	java/lang/StringBuilder:append	(Ljava/lang/String;)Ljava/lang/StringBuilder;
    //   350: pop
    //   351: ldc 65
    //   353: aload 4
    //   355: invokevirtual 161	java/lang/StringBuilder:toString	()Ljava/lang/String;
    //   358: invokestatic 164	com/huawei/hms/hatool/y:e	(Ljava/lang/String;Ljava/lang/String;)V
    //   361: ldc 81
    //   363: aload_0
    //   364: getfield 29	com/huawei/hms/hatool/k0:c	Ljava/lang/String;
    //   367: invokevirtual 101	java/lang/String:equals	(Ljava/lang/Object;)Z
    //   370: ifeq +32 -> 402
    //   373: aload_0
    //   374: getfield 25	com/huawei/hms/hatool/k0:a	Landroid/content/Context;
    //   377: ldc 103
    //   379: iconst_0
    //   380: anewarray 48	java/lang/String
    //   383: invokestatic 108	com/huawei/hms/hatool/g0:a	(Landroid/content/Context;Ljava/lang/String;[Ljava/lang/String;)V
    //   386: aload_0
    //   387: getfield 25	com/huawei/hms/hatool/k0:a	Landroid/content/Context;
    //   390: ldc 110
    //   392: iconst_0
    //   393: anewarray 48	java/lang/String
    //   396: invokestatic 108	com/huawei/hms/hatool/g0:a	(Landroid/content/Context;Ljava/lang/String;[Ljava/lang/String;)V
    //   399: goto +177 -> 576
    //   402: aload_0
    //   403: getfield 27	com/huawei/hms/hatool/k0:b	Ljava/lang/String;
    //   406: aload_0
    //   407: getfield 29	com/huawei/hms/hatool/k0:c	Ljava/lang/String;
    //   410: invokestatic 113	com/huawei/hms/hatool/s0:a	(Ljava/lang/String;Ljava/lang/String;)Ljava/lang/String;
    //   413: astore_3
    //   414: aload_0
    //   415: getfield 25	com/huawei/hms/hatool/k0:a	Landroid/content/Context;
    //   418: ldc 103
    //   420: iconst_1
    //   421: anewarray 48	java/lang/String
    //   424: dup
    //   425: iconst_0
    //   426: aload_3
    //   427: aastore
    //   428: invokestatic 108	com/huawei/hms/hatool/g0:a	(Landroid/content/Context;Ljava/lang/String;[Ljava/lang/String;)V
    //   431: aload_0
    //   432: getfield 25	com/huawei/hms/hatool/k0:a	Landroid/content/Context;
    //   435: ldc 110
    //   437: iconst_1
    //   438: anewarray 48	java/lang/String
    //   441: dup
    //   442: iconst_0
    //   443: aload_3
    //   444: aastore
    //   445: invokestatic 108	com/huawei/hms/hatool/g0:a	(Landroid/content/Context;Ljava/lang/String;[Ljava/lang/String;)V
    //   448: goto +128 -> 576
    //   451: astore_3
    //   452: new 147	java/lang/StringBuilder
    //   455: dup
    //   456: invokespecial 148	java/lang/StringBuilder:<init>	()V
    //   459: astore 4
    //   461: aload 4
    //   463: ldc 166
    //   465: invokevirtual 154	java/lang/StringBuilder:append	(Ljava/lang/String;)Ljava/lang/StringBuilder;
    //   468: pop
    //   469: aload 4
    //   471: aload_3
    //   472: invokevirtual 167	java/lang/IllegalArgumentException:getMessage	()Ljava/lang/String;
    //   475: invokevirtual 154	java/lang/StringBuilder:append	(Ljava/lang/String;)Ljava/lang/StringBuilder;
    //   478: pop
    //   479: ldc 65
    //   481: aload 4
    //   483: invokevirtual 161	java/lang/StringBuilder:toString	()Ljava/lang/String;
    //   486: invokestatic 164	com/huawei/hms/hatool/y:e	(Ljava/lang/String;Ljava/lang/String;)V
    //   489: ldc 81
    //   491: aload_0
    //   492: getfield 29	com/huawei/hms/hatool/k0:c	Ljava/lang/String;
    //   495: invokevirtual 101	java/lang/String:equals	(Ljava/lang/Object;)Z
    //   498: ifeq +32 -> 530
    //   501: aload_0
    //   502: getfield 25	com/huawei/hms/hatool/k0:a	Landroid/content/Context;
    //   505: ldc 103
    //   507: iconst_0
    //   508: anewarray 48	java/lang/String
    //   511: invokestatic 108	com/huawei/hms/hatool/g0:a	(Landroid/content/Context;Ljava/lang/String;[Ljava/lang/String;)V
    //   514: aload_0
    //   515: getfield 25	com/huawei/hms/hatool/k0:a	Landroid/content/Context;
    //   518: ldc 110
    //   520: iconst_0
    //   521: anewarray 48	java/lang/String
    //   524: invokestatic 108	com/huawei/hms/hatool/g0:a	(Landroid/content/Context;Ljava/lang/String;[Ljava/lang/String;)V
    //   527: goto +49 -> 576
    //   530: aload_0
    //   531: getfield 27	com/huawei/hms/hatool/k0:b	Ljava/lang/String;
    //   534: aload_0
    //   535: getfield 29	com/huawei/hms/hatool/k0:c	Ljava/lang/String;
    //   538: invokestatic 113	com/huawei/hms/hatool/s0:a	(Ljava/lang/String;Ljava/lang/String;)Ljava/lang/String;
    //   541: astore_3
    //   542: aload_0
    //   543: getfield 25	com/huawei/hms/hatool/k0:a	Landroid/content/Context;
    //   546: ldc 103
    //   548: iconst_1
    //   549: anewarray 48	java/lang/String
    //   552: dup
    //   553: iconst_0
    //   554: aload_3
    //   555: aastore
    //   556: invokestatic 108	com/huawei/hms/hatool/g0:a	(Landroid/content/Context;Ljava/lang/String;[Ljava/lang/String;)V
    //   559: aload_0
    //   560: getfield 25	com/huawei/hms/hatool/k0:a	Landroid/content/Context;
    //   563: ldc 110
    //   565: iconst_1
    //   566: anewarray 48	java/lang/String
    //   569: dup
    //   570: iconst_0
    //   571: aload_3
    //   572: aastore
    //   573: invokestatic 108	com/huawei/hms/hatool/g0:a	(Landroid/content/Context;Ljava/lang/String;[Ljava/lang/String;)V
    //   576: iload_2
    //   577: ifeq +16 -> 593
    //   580: ldc 65
    //   582: ldc 169
    //   584: invokestatic 72	com/huawei/hms/hatool/y:c	(Ljava/lang/String;Ljava/lang/String;)V
    //   587: invokestatic 174	com/huawei/hms/hatool/d0:f	()Lcom/huawei/hms/hatool/d0;
    //   590: invokevirtual 176	com/huawei/hms/hatool/d0:b	()V
    //   593: return
    //   594: ldc 81
    //   596: aload_0
    //   597: getfield 29	com/huawei/hms/hatool/k0:c	Ljava/lang/String;
    //   600: invokevirtual 101	java/lang/String:equals	(Ljava/lang/Object;)Z
    //   603: ifeq +32 -> 635
    //   606: aload_0
    //   607: getfield 25	com/huawei/hms/hatool/k0:a	Landroid/content/Context;
    //   610: ldc 103
    //   612: iconst_0
    //   613: anewarray 48	java/lang/String
    //   616: invokestatic 108	com/huawei/hms/hatool/g0:a	(Landroid/content/Context;Ljava/lang/String;[Ljava/lang/String;)V
    //   619: aload_0
    //   620: getfield 25	com/huawei/hms/hatool/k0:a	Landroid/content/Context;
    //   623: ldc 110
    //   625: iconst_0
    //   626: anewarray 48	java/lang/String
    //   629: invokestatic 108	com/huawei/hms/hatool/g0:a	(Landroid/content/Context;Ljava/lang/String;[Ljava/lang/String;)V
    //   632: goto +52 -> 684
    //   635: aload_0
    //   636: getfield 27	com/huawei/hms/hatool/k0:b	Ljava/lang/String;
    //   639: aload_0
    //   640: getfield 29	com/huawei/hms/hatool/k0:c	Ljava/lang/String;
    //   643: invokestatic 113	com/huawei/hms/hatool/s0:a	(Ljava/lang/String;Ljava/lang/String;)Ljava/lang/String;
    //   646: astore 4
    //   648: aload_0
    //   649: getfield 25	com/huawei/hms/hatool/k0:a	Landroid/content/Context;
    //   652: ldc 103
    //   654: iconst_1
    //   655: anewarray 48	java/lang/String
    //   658: dup
    //   659: iconst_0
    //   660: aload 4
    //   662: aastore
    //   663: invokestatic 108	com/huawei/hms/hatool/g0:a	(Landroid/content/Context;Ljava/lang/String;[Ljava/lang/String;)V
    //   666: aload_0
    //   667: getfield 25	com/huawei/hms/hatool/k0:a	Landroid/content/Context;
    //   670: ldc 110
    //   672: iconst_1
    //   673: anewarray 48	java/lang/String
    //   676: dup
    //   677: iconst_0
    //   678: aload 4
    //   680: aastore
    //   681: invokestatic 108	com/huawei/hms/hatool/g0:a	(Landroid/content/Context;Ljava/lang/String;[Ljava/lang/String;)V
    //   684: goto +5 -> 689
    //   687: aload_3
    //   688: athrow
    //   689: goto -2 -> 687
    // Local variable table:
    //   start	length	slot	name	signature
    //   0	692	0	this	k0
    //   54	2	1	i	int
    //   14	563	2	bool	boolean
    //   47	265	3	localObject1	Object
    //   319	1	3	localObject2	Object
    //   323	21	3	localException	java.lang.Exception
    //   413	31	3	str1	String
    //   451	21	3	localIllegalArgumentException	java.lang.IllegalArgumentException
    //   541	147	3	str2	String
    //   200	479	4	localObject3	Object
    // Exception table:
    //   from	to	target	type
    //   32	55	319	finally
    //   59	84	319	finally
    //   170	182	319	finally
    //   182	226	319	finally
    //   324	361	319	finally
    //   452	489	319	finally
    //   32	55	323	java/lang/Exception
    //   59	84	323	java/lang/Exception
    //   170	182	323	java/lang/Exception
    //   182	226	323	java/lang/Exception
    //   32	55	451	java/lang/IllegalArgumentException
    //   59	84	451	java/lang/IllegalArgumentException
    //   170	182	451	java/lang/IllegalArgumentException
    //   182	226	451	java/lang/IllegalArgumentException
  }
}


/* Location:           L:\local\mybackup\temp\qq_apk\com.tencent.mobileqq\classes.jar
 * Qualified Name:     com.huawei.hms.hatool.k0
 * JD-Core Version:    0.7.0.1
 */