package com.tencent.mobileqq.activity.aio;

class CustomizeStrategyFactory$SkinRedPacketStrategy$1
  implements Runnable
{
  CustomizeStrategyFactory$SkinRedPacketStrategy$1(CustomizeStrategyFactory.e parame, CustomizeStrategyFactory.RedPacketInfo paramRedPacketInfo) {}
  
  /* Error */
  public void run()
  {
    // Byte code:
    //   0: invokestatic 31	com/tencent/mobileqq/activity/aio/CustomizeStrategyFactory:a	()Lcom/tencent/mobileqq/activity/aio/CustomizeStrategyFactory;
    //   3: getfield 35	com/tencent/mobileqq/activity/aio/CustomizeStrategyFactory:bdM	Z
    //   6: ifeq +20 -> 26
    //   9: getstatic 39	com/tencent/mobileqq/activity/aio/CustomizeStrategyFactory:cm	[B
    //   12: astore_1
    //   13: aload_1
    //   14: monitorenter
    //   15: getstatic 39	com/tencent/mobileqq/activity/aio/CustomizeStrategyFactory:cm	[B
    //   18: ldc2_w 40
    //   21: invokevirtual 45	java/lang/Object:wait	(J)V
    //   24: aload_1
    //   25: monitorexit
    //   26: invokestatic 51	com/tencent/qphone/base/util/QLog:isColorLevel	()Z
    //   29: ifeq +11 -> 40
    //   32: ldc 53
    //   34: iconst_2
    //   35: ldc 55
    //   37: invokestatic 59	com/tencent/qphone/base/util/QLog:d	(Ljava/lang/String;ILjava/lang/String;)V
    //   40: aload_0
    //   41: getfield 14	com/tencent/mobileqq/activity/aio/CustomizeStrategyFactory$SkinRedPacketStrategy$1:this$0	Lcom/tencent/mobileqq/activity/aio/CustomizeStrategyFactory$e;
    //   44: getfield 64	com/tencent/mobileqq/activity/aio/CustomizeStrategyFactory$e:a	Lcom/tencent/mobileqq/activity/qwallet/preload/PreloadManager;
    //   47: ifnull +13 -> 60
    //   50: aload_0
    //   51: getfield 14	com/tencent/mobileqq/activity/aio/CustomizeStrategyFactory$SkinRedPacketStrategy$1:this$0	Lcom/tencent/mobileqq/activity/aio/CustomizeStrategyFactory$e;
    //   54: getfield 68	com/tencent/mobileqq/activity/aio/CustomizeStrategyFactory$e:b	Laaai;
    //   57: ifnonnull +27 -> 84
    //   60: invokestatic 31	com/tencent/mobileqq/activity/aio/CustomizeStrategyFactory:a	()Lcom/tencent/mobileqq/activity/aio/CustomizeStrategyFactory;
    //   63: aload_0
    //   64: getfield 16	com/tencent/mobileqq/activity/aio/CustomizeStrategyFactory$SkinRedPacketStrategy$1:val$info	Lcom/tencent/mobileqq/activity/aio/CustomizeStrategyFactory$RedPacketInfo;
    //   67: invokevirtual 71	com/tencent/mobileqq/activity/aio/CustomizeStrategyFactory:b	(Lcom/tencent/mobileqq/activity/aio/CustomizeStrategyFactory$RedPacketInfo;)V
    //   70: return
    //   71: astore_2
    //   72: aload_1
    //   73: monitorexit
    //   74: aload_2
    //   75: athrow
    //   76: astore_1
    //   77: aload_1
    //   78: invokevirtual 74	java/lang/InterruptedException:printStackTrace	()V
    //   81: goto -55 -> 26
    //   84: aload_0
    //   85: getfield 14	com/tencent/mobileqq/activity/aio/CustomizeStrategyFactory$SkinRedPacketStrategy$1:this$0	Lcom/tencent/mobileqq/activity/aio/CustomizeStrategyFactory$e;
    //   88: aload_0
    //   89: getfield 14	com/tencent/mobileqq/activity/aio/CustomizeStrategyFactory$SkinRedPacketStrategy$1:this$0	Lcom/tencent/mobileqq/activity/aio/CustomizeStrategyFactory$e;
    //   92: getfield 64	com/tencent/mobileqq/activity/aio/CustomizeStrategyFactory$e:a	Lcom/tencent/mobileqq/activity/qwallet/preload/PreloadManager;
    //   95: aload_0
    //   96: getfield 14	com/tencent/mobileqq/activity/aio/CustomizeStrategyFactory$SkinRedPacketStrategy$1:this$0	Lcom/tencent/mobileqq/activity/aio/CustomizeStrategyFactory$e;
    //   99: getfield 68	com/tencent/mobileqq/activity/aio/CustomizeStrategyFactory$e:b	Laaai;
    //   102: aload_0
    //   103: getfield 16	com/tencent/mobileqq/activity/aio/CustomizeStrategyFactory$SkinRedPacketStrategy$1:val$info	Lcom/tencent/mobileqq/activity/aio/CustomizeStrategyFactory$RedPacketInfo;
    //   106: invokestatic 77	com/tencent/mobileqq/activity/aio/CustomizeStrategyFactory$e:a	(Lcom/tencent/mobileqq/activity/aio/CustomizeStrategyFactory$e;Lcom/tencent/mobileqq/activity/qwallet/preload/PreloadManager;Laaai;Lcom/tencent/mobileqq/activity/aio/CustomizeStrategyFactory$RedPacketInfo;)V
    //   109: return
    //   110: astore_1
    //   111: aload_1
    //   112: invokevirtual 78	java/lang/Throwable:printStackTrace	()V
    //   115: return
    // Local variable table:
    //   start	length	slot	name	signature
    //   0	116	0	this	1
    //   76	2	1	localInterruptedException	java.lang.InterruptedException
    //   110	2	1	localThrowable	java.lang.Throwable
    //   71	4	2	localObject	Object
    // Exception table:
    //   from	to	target	type
    //   15	26	71	finally
    //   72	74	71	finally
    //   9	15	76	java/lang/InterruptedException
    //   74	76	76	java/lang/InterruptedException
    //   26	40	110	java/lang/Throwable
    //   40	60	110	java/lang/Throwable
    //   60	70	110	java/lang/Throwable
    //   84	109	110	java/lang/Throwable
  }
}


/* Location:           L:\local\mybackup\temp\qq_apk\com.tencent.tim\classes7.jar
 * Qualified Name:     com.tencent.mobileqq.activity.aio.CustomizeStrategyFactory.SkinRedPacketStrategy.1
 * JD-Core Version:    0.7.0.1
 */