package com.tencent.mobileqq.secspy;

import tencent.im.s2c.msgtype0x210.submsgtype0x7c.submsgtype0x7c.MsgBody;

class SecSpyFileManager$2
  implements Runnable
{
  SecSpyFileManager$2(SecSpyFileManager paramSecSpyFileManager, submsgtype0x7c.MsgBody paramMsgBody, int paramInt) {}
  
  /* Error */
  public void run()
  {
    // Byte code:
    //   0: iconst_0
    //   1: istore 8
    //   3: iconst_0
    //   4: istore 9
    //   6: iconst_0
    //   7: istore 10
    //   9: iconst_0
    //   10: istore 7
    //   12: aload_0
    //   13: getfield 17	com/tencent/mobileqq/secspy/SecSpyFileManager$2:jdField_a_of_type_TencentImS2cMsgtype0x210Submsgtype0x7cSubmsgtype0x7c$MsgBody	Ltencent/im/s2c/msgtype0x210/submsgtype0x7c/submsgtype0x7c$MsgBody;
    //   16: getfield 42	tencent/im/s2c/msgtype0x210/submsgtype0x7c/submsgtype0x7c$MsgBody:int32_cmd	Lcom/tencent/mobileqq/pb/PBInt32Field;
    //   19: invokevirtual 48	com/tencent/mobileqq/pb/PBInt32Field:get	()I
    //   22: istore_1
    //   23: aload_0
    //   24: getfield 17	com/tencent/mobileqq/secspy/SecSpyFileManager$2:jdField_a_of_type_TencentImS2cMsgtype0x210Submsgtype0x7cSubmsgtype0x7c$MsgBody	Ltencent/im/s2c/msgtype0x210/submsgtype0x7c/submsgtype0x7c$MsgBody;
    //   27: getfield 52	tencent/im/s2c/msgtype0x210/submsgtype0x7c/submsgtype0x7c$MsgBody:uint64_seq	Lcom/tencent/mobileqq/pb/PBUInt64Field;
    //   30: invokevirtual 57	com/tencent/mobileqq/pb/PBUInt64Field:get	()J
    //   33: lstore 13
    //   35: aload_0
    //   36: getfield 17	com/tencent/mobileqq/secspy/SecSpyFileManager$2:jdField_a_of_type_TencentImS2cMsgtype0x210Submsgtype0x7cSubmsgtype0x7c$MsgBody	Ltencent/im/s2c/msgtype0x210/submsgtype0x7c/submsgtype0x7c$MsgBody;
    //   39: getfield 61	tencent/im/s2c/msgtype0x210/submsgtype0x7c/submsgtype0x7c$MsgBody:rpt_string_cmd_ext	Lcom/tencent/mobileqq/pb/PBRepeatField;
    //   42: iconst_0
    //   43: invokevirtual 66	com/tencent/mobileqq/pb/PBRepeatField:get	(I)Ljava/lang/Object;
    //   46: checkcast 68	java/lang/String
    //   49: astore 18
    //   51: aload_0
    //   52: getfield 17	com/tencent/mobileqq/secspy/SecSpyFileManager$2:jdField_a_of_type_TencentImS2cMsgtype0x210Submsgtype0x7cSubmsgtype0x7c$MsgBody	Ltencent/im/s2c/msgtype0x210/submsgtype0x7c/submsgtype0x7c$MsgBody;
    //   55: getfield 71	tencent/im/s2c/msgtype0x210/submsgtype0x7c/submsgtype0x7c$MsgBody:rpt_string_seq_ext	Lcom/tencent/mobileqq/pb/PBRepeatField;
    //   58: invokevirtual 75	com/tencent/mobileqq/pb/PBRepeatField:has	()Z
    //   61: ifeq +397 -> 458
    //   64: aload_0
    //   65: getfield 17	com/tencent/mobileqq/secspy/SecSpyFileManager$2:jdField_a_of_type_TencentImS2cMsgtype0x210Submsgtype0x7cSubmsgtype0x7c$MsgBody	Ltencent/im/s2c/msgtype0x210/submsgtype0x7c/submsgtype0x7c$MsgBody;
    //   68: getfield 71	tencent/im/s2c/msgtype0x210/submsgtype0x7c/submsgtype0x7c$MsgBody:rpt_string_seq_ext	Lcom/tencent/mobileqq/pb/PBRepeatField;
    //   71: iconst_0
    //   72: invokevirtual 66	com/tencent/mobileqq/pb/PBRepeatField:get	(I)Ljava/lang/Object;
    //   75: checkcast 68	java/lang/String
    //   78: astore 17
    //   80: iload 8
    //   82: istore 4
    //   84: iload 9
    //   86: istore 5
    //   88: iload 10
    //   90: istore_3
    //   91: ldc 77
    //   93: iconst_1
    //   94: new 79	java/lang/StringBuilder
    //   97: dup
    //   98: invokespecial 80	java/lang/StringBuilder:<init>	()V
    //   101: ldc 82
    //   103: invokevirtual 86	java/lang/StringBuilder:append	(Ljava/lang/String;)Ljava/lang/StringBuilder;
    //   106: iload_1
    //   107: invokevirtual 89	java/lang/StringBuilder:append	(I)Ljava/lang/StringBuilder;
    //   110: ldc 91
    //   112: invokevirtual 86	java/lang/StringBuilder:append	(Ljava/lang/String;)Ljava/lang/StringBuilder;
    //   115: lload 13
    //   117: invokevirtual 94	java/lang/StringBuilder:append	(J)Ljava/lang/StringBuilder;
    //   120: ldc 96
    //   122: invokevirtual 86	java/lang/StringBuilder:append	(Ljava/lang/String;)Ljava/lang/StringBuilder;
    //   125: aload 18
    //   127: invokevirtual 86	java/lang/StringBuilder:append	(Ljava/lang/String;)Ljava/lang/StringBuilder;
    //   130: ldc 98
    //   132: invokevirtual 86	java/lang/StringBuilder:append	(Ljava/lang/String;)Ljava/lang/StringBuilder;
    //   135: aload 17
    //   137: invokevirtual 86	java/lang/StringBuilder:append	(Ljava/lang/String;)Ljava/lang/StringBuilder;
    //   140: invokevirtual 102	java/lang/StringBuilder:toString	()Ljava/lang/String;
    //   143: invokestatic 108	com/tencent/qphone/base/util/QLog:d	(Ljava/lang/String;ILjava/lang/String;)V
    //   146: iload 8
    //   148: istore 4
    //   150: iload 9
    //   152: istore 5
    //   154: iload 10
    //   156: istore_3
    //   157: aload_0
    //   158: getfield 15	com/tencent/mobileqq/secspy/SecSpyFileManager$2:this$0	Lcom/tencent/mobileqq/secspy/SecSpyFileManager;
    //   161: lload 13
    //   163: iconst_1
    //   164: iconst_0
    //   165: anewarray 4	java/lang/Object
    //   168: invokevirtual 113	com/tencent/mobileqq/secspy/SecSpyFileManager:a	(JI[Ljava/lang/Object;)V
    //   171: iload_1
    //   172: lookupswitch	default:+204->376, 1:+293->465, 2:+488->660, 3:+683->855, 4:+902->1074, 257:+1337->1509, 258:+1466->1638, 259:+1984->2156, 260:+2317->2489, 261:+2670->2842, 262:+3062->3234, 263:+3199->3371, 264:+3393->3565, 265:+3564->3736, 266:+3701->3873, 267:+4186->4358, 268:+4473->4645, 269:+4610->4782, 270:+4867->5039, 271:+5154->5326, 272:+5531->5703, 275:+6222->6394, 276:+6309->6481, 280:+6486->6658, 291:+6675->6847
    //   377: iconst_4
    //   378: istore 6
    //   380: iload_1
    //   381: bipush 10
    //   383: if_icmpge +74 -> 457
    //   386: iload 6
    //   388: ifne +69 -> 457
    //   391: aload_0
    //   392: getfield 19	com/tencent/mobileqq/secspy/SecSpyFileManager$2:jdField_a_of_type_Int	I
    //   395: ifle +62 -> 457
    //   398: invokestatic 116	com/tencent/qphone/base/util/QLog:isColorLevel	()Z
    //   401: ifeq +33 -> 434
    //   404: ldc 77
    //   406: iconst_2
    //   407: new 79	java/lang/StringBuilder
    //   410: dup
    //   411: invokespecial 80	java/lang/StringBuilder:<init>	()V
    //   414: ldc 118
    //   416: invokevirtual 86	java/lang/StringBuilder:append	(Ljava/lang/String;)Ljava/lang/StringBuilder;
    //   419: aload_0
    //   420: getfield 19	com/tencent/mobileqq/secspy/SecSpyFileManager$2:jdField_a_of_type_Int	I
    //   423: iconst_1
    //   424: isub
    //   425: invokevirtual 89	java/lang/StringBuilder:append	(I)Ljava/lang/StringBuilder;
    //   428: invokevirtual 102	java/lang/StringBuilder:toString	()Ljava/lang/String;
    //   431: invokestatic 108	com/tencent/qphone/base/util/QLog:d	(Ljava/lang/String;ILjava/lang/String;)V
    //   434: ldc2_w 119
    //   437: invokestatic 126	java/lang/Thread:sleep	(J)V
    //   440: aload_0
    //   441: getfield 15	com/tencent/mobileqq/secspy/SecSpyFileManager$2:this$0	Lcom/tencent/mobileqq/secspy/SecSpyFileManager;
    //   444: aload_0
    //   445: getfield 17	com/tencent/mobileqq/secspy/SecSpyFileManager$2:jdField_a_of_type_TencentImS2cMsgtype0x210Submsgtype0x7cSubmsgtype0x7c$MsgBody	Ltencent/im/s2c/msgtype0x210/submsgtype0x7c/submsgtype0x7c$MsgBody;
    //   448: aload_0
    //   449: getfield 19	com/tencent/mobileqq/secspy/SecSpyFileManager$2:jdField_a_of_type_Int	I
    //   452: iconst_1
    //   453: isub
    //   454: invokevirtual 129	com/tencent/mobileqq/secspy/SecSpyFileManager:a	(Ltencent/im/s2c/msgtype0x210/submsgtype0x7c/submsgtype0x7c$MsgBody;I)V
    //   457: return
    //   458: ldc 131
    //   460: astore 17
    //   462: goto -382 -> 80
    //   465: iload 8
    //   467: istore 4
    //   469: iload 9
    //   471: istore 5
    //   473: iload 10
    //   475: istore_3
    //   476: aload_0
    //   477: getfield 15	com/tencent/mobileqq/secspy/SecSpyFileManager$2:this$0	Lcom/tencent/mobileqq/secspy/SecSpyFileManager;
    //   480: lload 13
    //   482: iconst_2
    //   483: iconst_0
    //   484: anewarray 4	java/lang/Object
    //   487: invokevirtual 113	com/tencent/mobileqq/secspy/SecSpyFileManager:a	(JI[Ljava/lang/Object;)V
    //   490: iload 8
    //   492: istore 4
    //   494: iload 9
    //   496: istore 5
    //   498: iload 10
    //   500: istore_3
    //   501: aload_0
    //   502: getfield 15	com/tencent/mobileqq/secspy/SecSpyFileManager$2:this$0	Lcom/tencent/mobileqq/secspy/SecSpyFileManager;
    //   505: aload 18
    //   507: lload 13
    //   509: aload 17
    //   511: iconst_0
    //   512: invokevirtual 134	com/tencent/mobileqq/secspy/SecSpyFileManager:a	(Ljava/lang/String;JLjava/lang/String;Z)Z
    //   515: istore 7
    //   517: iload 7
    //   519: istore 6
    //   521: iload 7
    //   523: ifeq -143 -> 380
    //   526: iload 7
    //   528: istore 4
    //   530: iload 7
    //   532: istore 5
    //   534: iload 7
    //   536: istore_3
    //   537: aload_0
    //   538: getfield 15	com/tencent/mobileqq/secspy/SecSpyFileManager$2:this$0	Lcom/tencent/mobileqq/secspy/SecSpyFileManager;
    //   541: lload 13
    //   543: iconst_0
    //   544: iconst_0
    //   545: anewarray 4	java/lang/Object
    //   548: invokevirtual 113	com/tencent/mobileqq/secspy/SecSpyFileManager:a	(JI[Ljava/lang/Object;)V
    //   551: iload 7
    //   553: istore 6
    //   555: goto -175 -> 380
    //   558: astore 17
    //   560: iload 4
    //   562: istore_3
    //   563: invokestatic 116	com/tencent/qphone/base/util/QLog:isColorLevel	()Z
    //   566: ifeq +16 -> 582
    //   569: iload 4
    //   571: istore_3
    //   572: ldc 77
    //   574: iconst_2
    //   575: ldc 136
    //   577: aload 17
    //   579: invokestatic 140	com/tencent/qphone/base/util/QLog:e	(Ljava/lang/String;ILjava/lang/String;Ljava/lang/Throwable;)V
    //   582: iload_1
    //   583: bipush 10
    //   585: if_icmpge -128 -> 457
    //   588: iload 4
    //   590: ifne -133 -> 457
    //   593: aload_0
    //   594: getfield 19	com/tencent/mobileqq/secspy/SecSpyFileManager$2:jdField_a_of_type_Int	I
    //   597: ifle -140 -> 457
    //   600: invokestatic 116	com/tencent/qphone/base/util/QLog:isColorLevel	()Z
    //   603: ifeq +33 -> 636
    //   606: ldc 77
    //   608: iconst_2
    //   609: new 79	java/lang/StringBuilder
    //   612: dup
    //   613: invokespecial 80	java/lang/StringBuilder:<init>	()V
    //   616: ldc 118
    //   618: invokevirtual 86	java/lang/StringBuilder:append	(Ljava/lang/String;)Ljava/lang/StringBuilder;
    //   621: aload_0
    //   622: getfield 19	com/tencent/mobileqq/secspy/SecSpyFileManager$2:jdField_a_of_type_Int	I
    //   625: iconst_1
    //   626: isub
    //   627: invokevirtual 89	java/lang/StringBuilder:append	(I)Ljava/lang/StringBuilder;
    //   630: invokevirtual 102	java/lang/StringBuilder:toString	()Ljava/lang/String;
    //   633: invokestatic 108	com/tencent/qphone/base/util/QLog:d	(Ljava/lang/String;ILjava/lang/String;)V
    //   636: ldc2_w 119
    //   639: invokestatic 126	java/lang/Thread:sleep	(J)V
    //   642: aload_0
    //   643: getfield 15	com/tencent/mobileqq/secspy/SecSpyFileManager$2:this$0	Lcom/tencent/mobileqq/secspy/SecSpyFileManager;
    //   646: aload_0
    //   647: getfield 17	com/tencent/mobileqq/secspy/SecSpyFileManager$2:jdField_a_of_type_TencentImS2cMsgtype0x210Submsgtype0x7cSubmsgtype0x7c$MsgBody	Ltencent/im/s2c/msgtype0x210/submsgtype0x7c/submsgtype0x7c$MsgBody;
    //   650: aload_0
    //   651: getfield 19	com/tencent/mobileqq/secspy/SecSpyFileManager$2:jdField_a_of_type_Int	I
    //   654: iconst_1
    //   655: isub
    //   656: invokevirtual 129	com/tencent/mobileqq/secspy/SecSpyFileManager:a	(Ltencent/im/s2c/msgtype0x210/submsgtype0x7c/submsgtype0x7c$MsgBody;I)V
    //   659: return
    //   660: iload 8
    //   662: istore 4
    //   664: iload 9
    //   666: istore 5
    //   668: iload 10
    //   670: istore_3
    //   671: aload_0
    //   672: getfield 15	com/tencent/mobileqq/secspy/SecSpyFileManager$2:this$0	Lcom/tencent/mobileqq/secspy/SecSpyFileManager;
    //   675: lload 13
    //   677: iconst_2
    //   678: iconst_0
    //   679: anewarray 4	java/lang/Object
    //   682: invokevirtual 113	com/tencent/mobileqq/secspy/SecSpyFileManager:a	(JI[Ljava/lang/Object;)V
    //   685: iload 8
    //   687: istore 4
    //   689: iload 9
    //   691: istore 5
    //   693: iload 10
    //   695: istore_3
    //   696: aload_0
    //   697: getfield 15	com/tencent/mobileqq/secspy/SecSpyFileManager$2:this$0	Lcom/tencent/mobileqq/secspy/SecSpyFileManager;
    //   700: aload 18
    //   702: lload 13
    //   704: aload 17
    //   706: iconst_1
    //   707: invokevirtual 134	com/tencent/mobileqq/secspy/SecSpyFileManager:a	(Ljava/lang/String;JLjava/lang/String;Z)Z
    //   710: istore 7
    //   712: iload 7
    //   714: istore 6
    //   716: iload 7
    //   718: ifeq -338 -> 380
    //   721: iload 7
    //   723: istore 4
    //   725: iload 7
    //   727: istore 5
    //   729: iload 7
    //   731: istore_3
    //   732: aload_0
    //   733: getfield 15	com/tencent/mobileqq/secspy/SecSpyFileManager$2:this$0	Lcom/tencent/mobileqq/secspy/SecSpyFileManager;
    //   736: lload 13
    //   738: iconst_0
    //   739: iconst_0
    //   740: anewarray 4	java/lang/Object
    //   743: invokevirtual 113	com/tencent/mobileqq/secspy/SecSpyFileManager:a	(JI[Ljava/lang/Object;)V
    //   746: iload 7
    //   748: istore 6
    //   750: goto -370 -> 380
    //   753: astore 17
    //   755: iload 5
    //   757: istore_3
    //   758: invokestatic 116	com/tencent/qphone/base/util/QLog:isColorLevel	()Z
    //   761: ifeq +16 -> 777
    //   764: iload 5
    //   766: istore_3
    //   767: ldc 77
    //   769: iconst_2
    //   770: ldc 142
    //   772: aload 17
    //   774: invokestatic 140	com/tencent/qphone/base/util/QLog:e	(Ljava/lang/String;ILjava/lang/String;Ljava/lang/Throwable;)V
    //   777: iload_1
    //   778: bipush 10
    //   780: if_icmpge -323 -> 457
    //   783: iload 5
    //   785: ifne -328 -> 457
    //   788: aload_0
    //   789: getfield 19	com/tencent/mobileqq/secspy/SecSpyFileManager$2:jdField_a_of_type_Int	I
    //   792: ifle -335 -> 457
    //   795: invokestatic 116	com/tencent/qphone/base/util/QLog:isColorLevel	()Z
    //   798: ifeq +33 -> 831
    //   801: ldc 77
    //   803: iconst_2
    //   804: new 79	java/lang/StringBuilder
    //   807: dup
    //   808: invokespecial 80	java/lang/StringBuilder:<init>	()V
    //   811: ldc 118
    //   813: invokevirtual 86	java/lang/StringBuilder:append	(Ljava/lang/String;)Ljava/lang/StringBuilder;
    //   816: aload_0
    //   817: getfield 19	com/tencent/mobileqq/secspy/SecSpyFileManager$2:jdField_a_of_type_Int	I
    //   820: iconst_1
    //   821: isub
    //   822: invokevirtual 89	java/lang/StringBuilder:append	(I)Ljava/lang/StringBuilder;
    //   825: invokevirtual 102	java/lang/StringBuilder:toString	()Ljava/lang/String;
    //   828: invokestatic 108	com/tencent/qphone/base/util/QLog:d	(Ljava/lang/String;ILjava/lang/String;)V
    //   831: ldc2_w 119
    //   834: invokestatic 126	java/lang/Thread:sleep	(J)V
    //   837: aload_0
    //   838: getfield 15	com/tencent/mobileqq/secspy/SecSpyFileManager$2:this$0	Lcom/tencent/mobileqq/secspy/SecSpyFileManager;
    //   841: aload_0
    //   842: getfield 17	com/tencent/mobileqq/secspy/SecSpyFileManager$2:jdField_a_of_type_TencentImS2cMsgtype0x210Submsgtype0x7cSubmsgtype0x7c$MsgBody	Ltencent/im/s2c/msgtype0x210/submsgtype0x7c/submsgtype0x7c$MsgBody;
    //   845: aload_0
    //   846: getfield 19	com/tencent/mobileqq/secspy/SecSpyFileManager$2:jdField_a_of_type_Int	I
    //   849: iconst_1
    //   850: isub
    //   851: invokevirtual 129	com/tencent/mobileqq/secspy/SecSpyFileManager:a	(Ltencent/im/s2c/msgtype0x210/submsgtype0x7c/submsgtype0x7c$MsgBody;I)V
    //   854: return
    //   855: iload 7
    //   857: istore 6
    //   859: iload 8
    //   861: istore 4
    //   863: iload 9
    //   865: istore 5
    //   867: iload 10
    //   869: istore_3
    //   870: aload 18
    //   872: invokestatic 148	android/text/TextUtils:isEmpty	(Ljava/lang/CharSequence;)Z
    //   875: ifne -495 -> 380
    //   878: iload 8
    //   880: istore 4
    //   882: iload 9
    //   884: istore 5
    //   886: iload 10
    //   888: istore_3
    //   889: aload_0
    //   890: getfield 15	com/tencent/mobileqq/secspy/SecSpyFileManager$2:this$0	Lcom/tencent/mobileqq/secspy/SecSpyFileManager;
    //   893: aload 18
    //   895: invokevirtual 151	com/tencent/mobileqq/secspy/SecSpyFileManager:a	(Ljava/lang/String;)Ljava/io/File;
    //   898: astore 17
    //   900: aload 17
    //   902: ifnull +6062 -> 6964
    //   905: iload 8
    //   907: istore 4
    //   909: iload 9
    //   911: istore 5
    //   913: iload 10
    //   915: istore_3
    //   916: aload 17
    //   918: invokevirtual 156	java/io/File:exists	()Z
    //   921: ifeq +6043 -> 6964
    //   924: iload 8
    //   926: istore 4
    //   928: iload 9
    //   930: istore 5
    //   932: iload 10
    //   934: istore_3
    //   935: aload 17
    //   937: invokevirtual 159	java/io/File:isFile	()Z
    //   940: ifeq +6024 -> 6964
    //   943: iload 8
    //   945: istore 4
    //   947: iload 9
    //   949: istore 5
    //   951: iload 10
    //   953: istore_3
    //   954: invokestatic 116	com/tencent/qphone/base/util/QLog:isColorLevel	()Z
    //   957: ifeq +40 -> 997
    //   960: iload 8
    //   962: istore 4
    //   964: iload 9
    //   966: istore 5
    //   968: iload 10
    //   970: istore_3
    //   971: ldc 77
    //   973: iconst_2
    //   974: new 79	java/lang/StringBuilder
    //   977: dup
    //   978: invokespecial 80	java/lang/StringBuilder:<init>	()V
    //   981: ldc 161
    //   983: invokevirtual 86	java/lang/StringBuilder:append	(Ljava/lang/String;)Ljava/lang/StringBuilder;
    //   986: aload 18
    //   988: invokevirtual 86	java/lang/StringBuilder:append	(Ljava/lang/String;)Ljava/lang/StringBuilder;
    //   991: invokevirtual 102	java/lang/StringBuilder:toString	()Ljava/lang/String;
    //   994: invokestatic 108	com/tencent/qphone/base/util/QLog:d	(Ljava/lang/String;ILjava/lang/String;)V
    //   997: iload 8
    //   999: istore 4
    //   1001: iload 9
    //   1003: istore 5
    //   1005: iload 10
    //   1007: istore_3
    //   1008: aload 17
    //   1010: invokevirtual 164	java/io/File:delete	()Z
    //   1013: pop
    //   1014: iload 8
    //   1016: istore 4
    //   1018: iload 9
    //   1020: istore 5
    //   1022: iload 10
    //   1024: istore_3
    //   1025: aload 17
    //   1027: invokevirtual 167	java/io/File:createNewFile	()Z
    //   1030: pop
    //   1031: iconst_1
    //   1032: istore 4
    //   1034: aload_0
    //   1035: getfield 15	com/tencent/mobileqq/secspy/SecSpyFileManager$2:this$0	Lcom/tencent/mobileqq/secspy/SecSpyFileManager;
    //   1038: lload 13
    //   1040: iconst_0
    //   1041: iconst_0
    //   1042: anewarray 4	java/lang/Object
    //   1045: invokevirtual 113	com/tencent/mobileqq/secspy/SecSpyFileManager:a	(JI[Ljava/lang/Object;)V
    //   1048: iload 4
    //   1050: istore_3
    //   1051: invokestatic 116	com/tencent/qphone/base/util/QLog:isColorLevel	()Z
    //   1054: ifeq +14 -> 1068
    //   1057: ldc 77
    //   1059: iconst_2
    //   1060: ldc 169
    //   1062: invokestatic 108	com/tencent/qphone/base/util/QLog:d	(Ljava/lang/String;ILjava/lang/String;)V
    //   1065: iload 4
    //   1067: istore_3
    //   1068: iload_3
    //   1069: istore 6
    //   1071: goto -691 -> 380
    //   1074: iload 7
    //   1076: istore 6
    //   1078: iload 8
    //   1080: istore 4
    //   1082: iload 9
    //   1084: istore 5
    //   1086: iload 10
    //   1088: istore_3
    //   1089: aload_0
    //   1090: getfield 17	com/tencent/mobileqq/secspy/SecSpyFileManager$2:jdField_a_of_type_TencentImS2cMsgtype0x210Submsgtype0x7cSubmsgtype0x7c$MsgBody	Ltencent/im/s2c/msgtype0x210/submsgtype0x7c/submsgtype0x7c$MsgBody;
    //   1093: getfield 61	tencent/im/s2c/msgtype0x210/submsgtype0x7c/submsgtype0x7c$MsgBody:rpt_string_cmd_ext	Lcom/tencent/mobileqq/pb/PBRepeatField;
    //   1096: invokevirtual 172	com/tencent/mobileqq/pb/PBRepeatField:size	()I
    //   1099: iconst_2
    //   1100: if_icmplt -720 -> 380
    //   1103: iload 8
    //   1105: istore 4
    //   1107: iload 9
    //   1109: istore 5
    //   1111: iload 10
    //   1113: istore_3
    //   1114: aload_0
    //   1115: getfield 17	com/tencent/mobileqq/secspy/SecSpyFileManager$2:jdField_a_of_type_TencentImS2cMsgtype0x210Submsgtype0x7cSubmsgtype0x7c$MsgBody	Ltencent/im/s2c/msgtype0x210/submsgtype0x7c/submsgtype0x7c$MsgBody;
    //   1118: getfield 61	tencent/im/s2c/msgtype0x210/submsgtype0x7c/submsgtype0x7c$MsgBody:rpt_string_cmd_ext	Lcom/tencent/mobileqq/pb/PBRepeatField;
    //   1121: iconst_1
    //   1122: invokevirtual 66	com/tencent/mobileqq/pb/PBRepeatField:get	(I)Ljava/lang/Object;
    //   1125: checkcast 68	java/lang/String
    //   1128: astore 17
    //   1130: iload 7
    //   1132: istore 6
    //   1134: iload 8
    //   1136: istore 4
    //   1138: iload 9
    //   1140: istore 5
    //   1142: iload 10
    //   1144: istore_3
    //   1145: aload 18
    //   1147: invokestatic 148	android/text/TextUtils:isEmpty	(Ljava/lang/CharSequence;)Z
    //   1150: ifne -770 -> 380
    //   1153: iload 7
    //   1155: istore 6
    //   1157: iload 8
    //   1159: istore 4
    //   1161: iload 9
    //   1163: istore 5
    //   1165: iload 10
    //   1167: istore_3
    //   1168: aload 17
    //   1170: invokestatic 148	android/text/TextUtils:isEmpty	(Ljava/lang/CharSequence;)Z
    //   1173: ifne -793 -> 380
    //   1176: iload 8
    //   1178: istore 4
    //   1180: iload 9
    //   1182: istore 5
    //   1184: iload 10
    //   1186: istore_3
    //   1187: invokestatic 116	com/tencent/qphone/base/util/QLog:isColorLevel	()Z
    //   1190: ifeq +50 -> 1240
    //   1193: iload 8
    //   1195: istore 4
    //   1197: iload 9
    //   1199: istore 5
    //   1201: iload 10
    //   1203: istore_3
    //   1204: ldc 77
    //   1206: iconst_2
    //   1207: new 79	java/lang/StringBuilder
    //   1210: dup
    //   1211: invokespecial 80	java/lang/StringBuilder:<init>	()V
    //   1214: ldc 174
    //   1216: invokevirtual 86	java/lang/StringBuilder:append	(Ljava/lang/String;)Ljava/lang/StringBuilder;
    //   1219: aload 18
    //   1221: invokevirtual 86	java/lang/StringBuilder:append	(Ljava/lang/String;)Ljava/lang/StringBuilder;
    //   1224: ldc 176
    //   1226: invokevirtual 86	java/lang/StringBuilder:append	(Ljava/lang/String;)Ljava/lang/StringBuilder;
    //   1229: aload 17
    //   1231: invokevirtual 86	java/lang/StringBuilder:append	(Ljava/lang/String;)Ljava/lang/StringBuilder;
    //   1234: invokevirtual 102	java/lang/StringBuilder:toString	()Ljava/lang/String;
    //   1237: invokestatic 108	com/tencent/qphone/base/util/QLog:d	(Ljava/lang/String;ILjava/lang/String;)V
    //   1240: iload 8
    //   1242: istore 4
    //   1244: iload 9
    //   1246: istore 5
    //   1248: iload 10
    //   1250: istore_3
    //   1251: aload_0
    //   1252: getfield 15	com/tencent/mobileqq/secspy/SecSpyFileManager$2:this$0	Lcom/tencent/mobileqq/secspy/SecSpyFileManager;
    //   1255: aload 18
    //   1257: invokevirtual 151	com/tencent/mobileqq/secspy/SecSpyFileManager:a	(Ljava/lang/String;)Ljava/io/File;
    //   1260: astore 18
    //   1262: iload 8
    //   1264: istore 4
    //   1266: iload 9
    //   1268: istore 5
    //   1270: iload 10
    //   1272: istore_3
    //   1273: aload_0
    //   1274: getfield 15	com/tencent/mobileqq/secspy/SecSpyFileManager$2:this$0	Lcom/tencent/mobileqq/secspy/SecSpyFileManager;
    //   1277: aload 17
    //   1279: invokevirtual 151	com/tencent/mobileqq/secspy/SecSpyFileManager:a	(Ljava/lang/String;)Ljava/io/File;
    //   1282: astore 17
    //   1284: iload 7
    //   1286: istore 6
    //   1288: aload 18
    //   1290: ifnull -910 -> 380
    //   1293: iload 7
    //   1295: istore 6
    //   1297: aload 17
    //   1299: ifnull -919 -> 380
    //   1302: iload 7
    //   1304: istore 6
    //   1306: iload 8
    //   1308: istore 4
    //   1310: iload 9
    //   1312: istore 5
    //   1314: iload 10
    //   1316: istore_3
    //   1317: aload 18
    //   1319: invokevirtual 156	java/io/File:exists	()Z
    //   1322: ifeq -942 -> 380
    //   1325: iload 8
    //   1327: istore 4
    //   1329: iload 9
    //   1331: istore 5
    //   1333: iload 10
    //   1335: istore_3
    //   1336: aload 18
    //   1338: aload 17
    //   1340: invokevirtual 180	java/io/File:renameTo	(Ljava/io/File;)Z
    //   1343: pop
    //   1344: iconst_1
    //   1345: istore 8
    //   1347: iconst_1
    //   1348: istore 9
    //   1350: iconst_1
    //   1351: istore 10
    //   1353: iconst_1
    //   1354: istore 7
    //   1356: iload 8
    //   1358: istore 4
    //   1360: iload 9
    //   1362: istore 5
    //   1364: iload 10
    //   1366: istore_3
    //   1367: aload_0
    //   1368: getfield 15	com/tencent/mobileqq/secspy/SecSpyFileManager$2:this$0	Lcom/tencent/mobileqq/secspy/SecSpyFileManager;
    //   1371: lload 13
    //   1373: iconst_0
    //   1374: iconst_0
    //   1375: anewarray 4	java/lang/Object
    //   1378: invokevirtual 113	com/tencent/mobileqq/secspy/SecSpyFileManager:a	(JI[Ljava/lang/Object;)V
    //   1381: iload 7
    //   1383: istore 6
    //   1385: iload 8
    //   1387: istore 4
    //   1389: iload 9
    //   1391: istore 5
    //   1393: iload 10
    //   1395: istore_3
    //   1396: invokestatic 116	com/tencent/qphone/base/util/QLog:isColorLevel	()Z
    //   1399: ifeq -1019 -> 380
    //   1402: iload 8
    //   1404: istore 4
    //   1406: iload 9
    //   1408: istore 5
    //   1410: iload 10
    //   1412: istore_3
    //   1413: ldc 77
    //   1415: iconst_2
    //   1416: ldc 182
    //   1418: invokestatic 108	com/tencent/qphone/base/util/QLog:d	(Ljava/lang/String;ILjava/lang/String;)V
    //   1421: iload 7
    //   1423: istore 6
    //   1425: goto -1045 -> 380
    //   1428: astore 17
    //   1430: iload_1
    //   1431: bipush 10
    //   1433: if_icmpge +73 -> 1506
    //   1436: iload_3
    //   1437: ifne +69 -> 1506
    //   1440: aload_0
    //   1441: getfield 19	com/tencent/mobileqq/secspy/SecSpyFileManager$2:jdField_a_of_type_Int	I
    //   1444: ifle +62 -> 1506
    //   1447: invokestatic 116	com/tencent/qphone/base/util/QLog:isColorLevel	()Z
    //   1450: ifeq +33 -> 1483
    //   1453: ldc 77
    //   1455: iconst_2
    //   1456: new 79	java/lang/StringBuilder
    //   1459: dup
    //   1460: invokespecial 80	java/lang/StringBuilder:<init>	()V
    //   1463: ldc 118
    //   1465: invokevirtual 86	java/lang/StringBuilder:append	(Ljava/lang/String;)Ljava/lang/StringBuilder;
    //   1468: aload_0
    //   1469: getfield 19	com/tencent/mobileqq/secspy/SecSpyFileManager$2:jdField_a_of_type_Int	I
    //   1472: iconst_1
    //   1473: isub
    //   1474: invokevirtual 89	java/lang/StringBuilder:append	(I)Ljava/lang/StringBuilder;
    //   1477: invokevirtual 102	java/lang/StringBuilder:toString	()Ljava/lang/String;
    //   1480: invokestatic 108	com/tencent/qphone/base/util/QLog:d	(Ljava/lang/String;ILjava/lang/String;)V
    //   1483: ldc2_w 119
    //   1486: invokestatic 126	java/lang/Thread:sleep	(J)V
    //   1489: aload_0
    //   1490: getfield 15	com/tencent/mobileqq/secspy/SecSpyFileManager$2:this$0	Lcom/tencent/mobileqq/secspy/SecSpyFileManager;
    //   1493: aload_0
    //   1494: getfield 17	com/tencent/mobileqq/secspy/SecSpyFileManager$2:jdField_a_of_type_TencentImS2cMsgtype0x210Submsgtype0x7cSubmsgtype0x7c$MsgBody	Ltencent/im/s2c/msgtype0x210/submsgtype0x7c/submsgtype0x7c$MsgBody;
    //   1497: aload_0
    //   1498: getfield 19	com/tencent/mobileqq/secspy/SecSpyFileManager$2:jdField_a_of_type_Int	I
    //   1501: iconst_1
    //   1502: isub
    //   1503: invokevirtual 129	com/tencent/mobileqq/secspy/SecSpyFileManager:a	(Ltencent/im/s2c/msgtype0x210/submsgtype0x7c/submsgtype0x7c$MsgBody;I)V
    //   1506: aload 17
    //   1508: athrow
    //   1509: iload 8
    //   1511: istore 4
    //   1513: iload 9
    //   1515: istore 5
    //   1517: iload 10
    //   1519: istore_3
    //   1520: aload_0
    //   1521: getfield 15	com/tencent/mobileqq/secspy/SecSpyFileManager$2:this$0	Lcom/tencent/mobileqq/secspy/SecSpyFileManager;
    //   1524: getfield 185	com/tencent/mobileqq/secspy/SecSpyFileManager:jdField_a_of_type_ComTencentMobileqqUnifiedebugUnifiedDebugManager	Lcom/tencent/mobileqq/unifiedebug/UnifiedDebugManager;
    //   1527: aload_0
    //   1528: getfield 15	com/tencent/mobileqq/secspy/SecSpyFileManager$2:this$0	Lcom/tencent/mobileqq/secspy/SecSpyFileManager;
    //   1531: getfield 188	com/tencent/mobileqq/secspy/SecSpyFileManager:jdField_a_of_type_ComTencentMobileqqAppQQAppInterface	Lcom/tencent/mobileqq/app/QQAppInterface;
    //   1534: invokevirtual 194	com/tencent/mobileqq/app/QQAppInterface:getApplication	()Lmqq/app/MobileQQ;
    //   1537: invokevirtual 199	com/tencent/mobileqq/unifiedebug/UnifiedDebugManager:a	(Landroid/content/Context;)Lcom/tencent/mobileqq/unifiedebug/UnifiedDebugManager$TerminalInfo;
    //   1540: astore 17
    //   1542: iload 8
    //   1544: istore 4
    //   1546: iload 9
    //   1548: istore 5
    //   1550: iload 10
    //   1552: istore_3
    //   1553: aload_0
    //   1554: getfield 15	com/tencent/mobileqq/secspy/SecSpyFileManager$2:this$0	Lcom/tencent/mobileqq/secspy/SecSpyFileManager;
    //   1557: lload 13
    //   1559: aload 17
    //   1561: invokevirtual 204	com/tencent/mobileqq/unifiedebug/UnifiedDebugManager$TerminalInfo:a	()Lorg/json/JSONObject;
    //   1564: invokevirtual 207	com/tencent/mobileqq/secspy/SecSpyFileManager:a	(JLorg/json/JSONObject;)V
    //   1567: iload 7
    //   1569: istore 6
    //   1571: iload 8
    //   1573: istore 4
    //   1575: iload 9
    //   1577: istore 5
    //   1579: iload 10
    //   1581: istore_3
    //   1582: invokestatic 116	com/tencent/qphone/base/util/QLog:isColorLevel	()Z
    //   1585: ifeq -1205 -> 380
    //   1588: iload 8
    //   1590: istore 4
    //   1592: iload 9
    //   1594: istore 5
    //   1596: iload 10
    //   1598: istore_3
    //   1599: ldc 77
    //   1601: iconst_2
    //   1602: new 79	java/lang/StringBuilder
    //   1605: dup
    //   1606: invokespecial 80	java/lang/StringBuilder:<init>	()V
    //   1609: ldc 209
    //   1611: invokevirtual 86	java/lang/StringBuilder:append	(Ljava/lang/String;)Ljava/lang/StringBuilder;
    //   1614: aload 17
    //   1616: invokevirtual 204	com/tencent/mobileqq/unifiedebug/UnifiedDebugManager$TerminalInfo:a	()Lorg/json/JSONObject;
    //   1619: invokevirtual 212	org/json/JSONObject:toString	()Ljava/lang/String;
    //   1622: invokevirtual 86	java/lang/StringBuilder:append	(Ljava/lang/String;)Ljava/lang/StringBuilder;
    //   1625: invokevirtual 102	java/lang/StringBuilder:toString	()Ljava/lang/String;
    //   1628: invokestatic 108	com/tencent/qphone/base/util/QLog:d	(Ljava/lang/String;ILjava/lang/String;)V
    //   1631: iload 7
    //   1633: istore 6
    //   1635: goto -1255 -> 380
    //   1638: iload 8
    //   1640: istore 4
    //   1642: iload 9
    //   1644: istore 5
    //   1646: iload 10
    //   1648: istore_3
    //   1649: new 211	org/json/JSONObject
    //   1652: dup
    //   1653: aload 18
    //   1655: invokespecial 215	org/json/JSONObject:<init>	(Ljava/lang/String;)V
    //   1658: astore 18
    //   1660: iload 8
    //   1662: istore 4
    //   1664: iload 9
    //   1666: istore 5
    //   1668: iload 10
    //   1670: istore_3
    //   1671: aload 18
    //   1673: ldc 217
    //   1675: iconst_0
    //   1676: invokevirtual 221	org/json/JSONObject:optBoolean	(Ljava/lang/String;Z)Z
    //   1679: ifeq +327 -> 2006
    //   1682: iload 8
    //   1684: istore 4
    //   1686: iload 9
    //   1688: istore 5
    //   1690: iload 10
    //   1692: istore_3
    //   1693: new 223	java/util/Date
    //   1696: dup
    //   1697: aload 18
    //   1699: ldc 225
    //   1701: invokevirtual 229	org/json/JSONObject:getLong	(Ljava/lang/String;)J
    //   1704: ldc2_w 119
    //   1707: lmul
    //   1708: invokespecial 231	java/util/Date:<init>	(J)V
    //   1711: astore 18
    //   1713: iload 8
    //   1715: istore 4
    //   1717: iload 9
    //   1719: istore 5
    //   1721: iload 10
    //   1723: istore_3
    //   1724: new 233	java/text/SimpleDateFormat
    //   1727: dup
    //   1728: ldc 235
    //   1730: invokespecial 236	java/text/SimpleDateFormat:<init>	(Ljava/lang/String;)V
    //   1733: aload 18
    //   1735: invokevirtual 240	java/text/SimpleDateFormat:format	(Ljava/util/Date;)Ljava/lang/String;
    //   1738: astore 18
    //   1740: iload 8
    //   1742: istore 4
    //   1744: iload 9
    //   1746: istore 5
    //   1748: iload 10
    //   1750: istore_3
    //   1751: new 242	android/content/Intent
    //   1754: dup
    //   1755: ldc 244
    //   1757: invokespecial 245	android/content/Intent:<init>	(Ljava/lang/String;)V
    //   1760: astore 19
    //   1762: iload 8
    //   1764: istore 4
    //   1766: iload 9
    //   1768: istore 5
    //   1770: iload 10
    //   1772: istore_3
    //   1773: ldc 247
    //   1775: invokestatic 253	com/tencent/mobileqq/qroute/QRoute:api	(Ljava/lang/Class;)Lcom/tencent/mobileqq/qroute/QRouteApi;
    //   1778: checkcast 247	com/tencent/mobileqq/webview/api/IWebProcessPreload
    //   1781: invokeinterface 256 1 0
    //   1786: ifeq +179 -> 1965
    //   1789: iload 8
    //   1791: istore 4
    //   1793: iload 9
    //   1795: istore 5
    //   1797: iload 10
    //   1799: istore_3
    //   1800: aload_0
    //   1801: getfield 15	com/tencent/mobileqq/secspy/SecSpyFileManager$2:this$0	Lcom/tencent/mobileqq/secspy/SecSpyFileManager;
    //   1804: getfield 188	com/tencent/mobileqq/secspy/SecSpyFileManager:jdField_a_of_type_ComTencentMobileqqAppQQAppInterface	Lcom/tencent/mobileqq/app/QQAppInterface;
    //   1807: invokevirtual 260	com/tencent/mobileqq/app/QQAppInterface:getApp	()Lcom/tencent/qphone/base/util/BaseApplication;
    //   1810: invokestatic 266	com/tencent/smtt/sdk/QbSdk:getTbsVersion	(Landroid/content/Context;)I
    //   1813: ldc_w 267
    //   1816: if_icmplt +149 -> 1965
    //   1819: iload 8
    //   1821: istore 4
    //   1823: iload 9
    //   1825: istore 5
    //   1827: iload 10
    //   1829: istore_3
    //   1830: aload 19
    //   1832: ldc_w 269
    //   1835: aload 18
    //   1837: invokevirtual 273	android/content/Intent:putExtra	(Ljava/lang/String;Ljava/lang/String;)Landroid/content/Intent;
    //   1840: pop
    //   1841: iload 8
    //   1843: istore 4
    //   1845: iload 9
    //   1847: istore 5
    //   1849: iload 10
    //   1851: istore_3
    //   1852: aload 19
    //   1854: ldc_w 275
    //   1857: aload_0
    //   1858: getfield 15	com/tencent/mobileqq/secspy/SecSpyFileManager$2:this$0	Lcom/tencent/mobileqq/secspy/SecSpyFileManager;
    //   1861: getfield 188	com/tencent/mobileqq/secspy/SecSpyFileManager:jdField_a_of_type_ComTencentMobileqqAppQQAppInterface	Lcom/tencent/mobileqq/app/QQAppInterface;
    //   1864: invokevirtual 278	com/tencent/mobileqq/app/QQAppInterface:getCurrentAccountUin	()Ljava/lang/String;
    //   1867: invokevirtual 273	android/content/Intent:putExtra	(Ljava/lang/String;Ljava/lang/String;)Landroid/content/Intent;
    //   1870: pop
    //   1871: iload 8
    //   1873: istore 4
    //   1875: iload 9
    //   1877: istore 5
    //   1879: iload 10
    //   1881: istore_3
    //   1882: aload 19
    //   1884: ldc_w 280
    //   1887: new 282	com/tencent/mobileqq/secspy/SecSpyFileManager$2$1
    //   1890: dup
    //   1891: aload_0
    //   1892: aload_0
    //   1893: getfield 15	com/tencent/mobileqq/secspy/SecSpyFileManager$2:this$0	Lcom/tencent/mobileqq/secspy/SecSpyFileManager;
    //   1896: getfield 285	com/tencent/mobileqq/secspy/SecSpyFileManager:jdField_a_of_type_AndroidOsHandler	Landroid/os/Handler;
    //   1899: aload 18
    //   1901: aload 17
    //   1903: invokespecial 288	com/tencent/mobileqq/secspy/SecSpyFileManager$2$1:<init>	(Lcom/tencent/mobileqq/secspy/SecSpyFileManager$2;Landroid/os/Handler;Ljava/lang/String;Ljava/lang/String;)V
    //   1906: invokevirtual 291	android/content/Intent:putExtra	(Ljava/lang/String;Landroid/os/Parcelable;)Landroid/content/Intent;
    //   1909: pop
    //   1910: iload 8
    //   1912: istore 4
    //   1914: iload 9
    //   1916: istore 5
    //   1918: iload 10
    //   1920: istore_3
    //   1921: aload 19
    //   1923: ldc_w 293
    //   1926: lload 13
    //   1928: invokevirtual 296	android/content/Intent:putExtra	(Ljava/lang/String;J)Landroid/content/Intent;
    //   1931: pop
    //   1932: iload 8
    //   1934: istore 4
    //   1936: iload 9
    //   1938: istore 5
    //   1940: iload 10
    //   1942: istore_3
    //   1943: aload_0
    //   1944: getfield 15	com/tencent/mobileqq/secspy/SecSpyFileManager$2:this$0	Lcom/tencent/mobileqq/secspy/SecSpyFileManager;
    //   1947: getfield 188	com/tencent/mobileqq/secspy/SecSpyFileManager:jdField_a_of_type_ComTencentMobileqqAppQQAppInterface	Lcom/tencent/mobileqq/app/QQAppInterface;
    //   1950: invokevirtual 194	com/tencent/mobileqq/app/QQAppInterface:getApplication	()Lmqq/app/MobileQQ;
    //   1953: aload 19
    //   1955: invokevirtual 302	mqq/app/MobileQQ:sendBroadcast	(Landroid/content/Intent;)V
    //   1958: iload 7
    //   1960: istore 6
    //   1962: goto -1582 -> 380
    //   1965: iload 8
    //   1967: istore 4
    //   1969: iload 9
    //   1971: istore 5
    //   1973: iload 10
    //   1975: istore_3
    //   1976: aload_0
    //   1977: getfield 15	com/tencent/mobileqq/secspy/SecSpyFileManager$2:this$0	Lcom/tencent/mobileqq/secspy/SecSpyFileManager;
    //   1980: aload 18
    //   1982: aload_0
    //   1983: getfield 15	com/tencent/mobileqq/secspy/SecSpyFileManager$2:this$0	Lcom/tencent/mobileqq/secspy/SecSpyFileManager;
    //   1986: getfield 188	com/tencent/mobileqq/secspy/SecSpyFileManager:jdField_a_of_type_ComTencentMobileqqAppQQAppInterface	Lcom/tencent/mobileqq/app/QQAppInterface;
    //   1989: invokevirtual 278	com/tencent/mobileqq/app/QQAppInterface:getCurrentAccountUin	()Ljava/lang/String;
    //   1992: lload 13
    //   1994: aload 17
    //   1996: invokestatic 305	com/tencent/mobileqq/secspy/SecSpyFileManager:a	(Lcom/tencent/mobileqq/secspy/SecSpyFileManager;Ljava/lang/String;Ljava/lang/String;JLjava/lang/String;)V
    //   1999: iload 7
    //   2001: istore 6
    //   2003: goto -1623 -> 380
    //   2006: iload 8
    //   2008: istore 4
    //   2010: iload 9
    //   2012: istore 5
    //   2014: iload 10
    //   2016: istore_3
    //   2017: aload 18
    //   2019: ldc 225
    //   2021: invokevirtual 229	org/json/JSONObject:getLong	(Ljava/lang/String;)J
    //   2024: lstore 11
    //   2026: iload 8
    //   2028: istore 4
    //   2030: iload 9
    //   2032: istore 5
    //   2034: iload 10
    //   2036: istore_3
    //   2037: aload 18
    //   2039: ldc_w 307
    //   2042: invokevirtual 229	org/json/JSONObject:getLong	(Ljava/lang/String;)J
    //   2045: lstore 15
    //   2047: iload 8
    //   2049: istore 4
    //   2051: iload 9
    //   2053: istore 5
    //   2055: iload 10
    //   2057: istore_3
    //   2058: aload_0
    //   2059: getfield 15	com/tencent/mobileqq/secspy/SecSpyFileManager$2:this$0	Lcom/tencent/mobileqq/secspy/SecSpyFileManager;
    //   2062: getfield 185	com/tencent/mobileqq/secspy/SecSpyFileManager:jdField_a_of_type_ComTencentMobileqqUnifiedebugUnifiedDebugManager	Lcom/tencent/mobileqq/unifiedebug/UnifiedDebugManager;
    //   2065: lload 11
    //   2067: ldc2_w 119
    //   2070: lmul
    //   2071: lload 15
    //   2073: ldc2_w 119
    //   2076: lmul
    //   2077: invokevirtual 310	com/tencent/mobileqq/unifiedebug/UnifiedDebugManager:a	(JJ)Ljava/lang/String;
    //   2080: astore 18
    //   2082: iload 8
    //   2084: istore 4
    //   2086: iload 9
    //   2088: istore 5
    //   2090: iload 10
    //   2092: istore_3
    //   2093: aload_0
    //   2094: getfield 15	com/tencent/mobileqq/secspy/SecSpyFileManager$2:this$0	Lcom/tencent/mobileqq/secspy/SecSpyFileManager;
    //   2097: aload 18
    //   2099: lload 13
    //   2101: aload 17
    //   2103: iconst_1
    //   2104: invokevirtual 313	com/tencent/mobileqq/secspy/SecSpyFileManager:a	(Ljava/lang/String;JLjava/lang/String;Z)V
    //   2107: iload 7
    //   2109: istore 6
    //   2111: goto -1731 -> 380
    //   2114: astore 17
    //   2116: iload 8
    //   2118: istore 4
    //   2120: iload 9
    //   2122: istore 5
    //   2124: iload 10
    //   2126: istore_3
    //   2127: aload_0
    //   2128: getfield 15	com/tencent/mobileqq/secspy/SecSpyFileManager$2:this$0	Lcom/tencent/mobileqq/secspy/SecSpyFileManager;
    //   2131: lload 13
    //   2133: iconst_m1
    //   2134: iconst_1
    //   2135: anewarray 4	java/lang/Object
    //   2138: dup
    //   2139: iconst_0
    //   2140: aload 17
    //   2142: invokevirtual 316	org/json/JSONException:getMessage	()Ljava/lang/String;
    //   2145: aastore
    //   2146: invokevirtual 113	com/tencent/mobileqq/secspy/SecSpyFileManager:a	(JI[Ljava/lang/Object;)V
    //   2149: iload 7
    //   2151: istore 6
    //   2153: goto -1773 -> 380
    //   2156: iload 8
    //   2158: istore 4
    //   2160: iload 9
    //   2162: istore 5
    //   2164: iload 10
    //   2166: istore_3
    //   2167: new 211	org/json/JSONObject
    //   2170: dup
    //   2171: aload 18
    //   2173: invokespecial 215	org/json/JSONObject:<init>	(Ljava/lang/String;)V
    //   2176: ldc_w 318
    //   2179: invokevirtual 322	org/json/JSONObject:optString	(Ljava/lang/String;)Ljava/lang/String;
    //   2182: astore 17
    //   2184: iload 8
    //   2186: istore 4
    //   2188: iload 9
    //   2190: istore 5
    //   2192: iload 10
    //   2194: istore_3
    //   2195: aload 17
    //   2197: invokestatic 148	android/text/TextUtils:isEmpty	(Ljava/lang/CharSequence;)Z
    //   2200: ifne +251 -> 2451
    //   2203: iload 8
    //   2205: istore 4
    //   2207: iload 9
    //   2209: istore 5
    //   2211: iload 10
    //   2213: istore_3
    //   2214: aload_0
    //   2215: getfield 15	com/tencent/mobileqq/secspy/SecSpyFileManager$2:this$0	Lcom/tencent/mobileqq/secspy/SecSpyFileManager;
    //   2218: getfield 185	com/tencent/mobileqq/secspy/SecSpyFileManager:jdField_a_of_type_ComTencentMobileqqUnifiedebugUnifiedDebugManager	Lcom/tencent/mobileqq/unifiedebug/UnifiedDebugManager;
    //   2221: aload 17
    //   2223: invokevirtual 324	com/tencent/mobileqq/unifiedebug/UnifiedDebugManager:a	(Ljava/lang/String;)Ljava/lang/String;
    //   2226: astore 17
    //   2228: iload 8
    //   2230: istore 4
    //   2232: iload 9
    //   2234: istore 5
    //   2236: iload 10
    //   2238: istore_3
    //   2239: aload_0
    //   2240: getfield 15	com/tencent/mobileqq/secspy/SecSpyFileManager$2:this$0	Lcom/tencent/mobileqq/secspy/SecSpyFileManager;
    //   2243: aload 17
    //   2245: invokevirtual 151	com/tencent/mobileqq/secspy/SecSpyFileManager:a	(Ljava/lang/String;)Ljava/io/File;
    //   2248: astore 18
    //   2250: aload 18
    //   2252: ifnull +143 -> 2395
    //   2255: iload 8
    //   2257: istore 4
    //   2259: iload 9
    //   2261: istore 5
    //   2263: iload 10
    //   2265: istore_3
    //   2266: aload 18
    //   2268: invokevirtual 156	java/io/File:exists	()Z
    //   2271: ifeq +124 -> 2395
    //   2274: iload 8
    //   2276: istore 4
    //   2278: iload 9
    //   2280: istore 5
    //   2282: iload 10
    //   2284: istore_3
    //   2285: aload 18
    //   2287: invokevirtual 327	java/io/File:isDirectory	()Z
    //   2290: istore 6
    //   2292: iload 6
    //   2294: ifeq +101 -> 2395
    //   2297: iload 8
    //   2299: istore 4
    //   2301: iload 9
    //   2303: istore 5
    //   2305: iload 10
    //   2307: istore_3
    //   2308: aload_0
    //   2309: getfield 15	com/tencent/mobileqq/secspy/SecSpyFileManager$2:this$0	Lcom/tencent/mobileqq/secspy/SecSpyFileManager;
    //   2312: getfield 185	com/tencent/mobileqq/secspy/SecSpyFileManager:jdField_a_of_type_ComTencentMobileqqUnifiedebugUnifiedDebugManager	Lcom/tencent/mobileqq/unifiedebug/UnifiedDebugManager;
    //   2315: aload 18
    //   2317: aload 17
    //   2319: invokevirtual 330	com/tencent/mobileqq/unifiedebug/UnifiedDebugManager:a	(Ljava/io/File;Ljava/lang/String;)Lorg/json/JSONObject;
    //   2322: astore 17
    //   2324: iload 8
    //   2326: istore 4
    //   2328: iload 9
    //   2330: istore 5
    //   2332: iload 10
    //   2334: istore_3
    //   2335: aload_0
    //   2336: getfield 15	com/tencent/mobileqq/secspy/SecSpyFileManager$2:this$0	Lcom/tencent/mobileqq/secspy/SecSpyFileManager;
    //   2339: lload 13
    //   2341: aload 17
    //   2343: invokevirtual 207	com/tencent/mobileqq/secspy/SecSpyFileManager:a	(JLorg/json/JSONObject;)V
    //   2346: iload 7
    //   2348: istore 6
    //   2350: goto -1970 -> 380
    //   2353: astore 17
    //   2355: iload 8
    //   2357: istore 4
    //   2359: iload 9
    //   2361: istore 5
    //   2363: iload 10
    //   2365: istore_3
    //   2366: aload_0
    //   2367: getfield 15	com/tencent/mobileqq/secspy/SecSpyFileManager$2:this$0	Lcom/tencent/mobileqq/secspy/SecSpyFileManager;
    //   2370: lload 13
    //   2372: iconst_m1
    //   2373: iconst_1
    //   2374: anewarray 4	java/lang/Object
    //   2377: dup
    //   2378: iconst_0
    //   2379: aload 17
    //   2381: invokevirtual 316	org/json/JSONException:getMessage	()Ljava/lang/String;
    //   2384: aastore
    //   2385: invokevirtual 113	com/tencent/mobileqq/secspy/SecSpyFileManager:a	(JI[Ljava/lang/Object;)V
    //   2388: iload 7
    //   2390: istore 6
    //   2392: goto -2012 -> 380
    //   2395: iload 8
    //   2397: istore 4
    //   2399: iload 9
    //   2401: istore 5
    //   2403: iload 10
    //   2405: istore_3
    //   2406: aload_0
    //   2407: getfield 15	com/tencent/mobileqq/secspy/SecSpyFileManager$2:this$0	Lcom/tencent/mobileqq/secspy/SecSpyFileManager;
    //   2410: lload 13
    //   2412: iconst_m1
    //   2413: iconst_1
    //   2414: anewarray 4	java/lang/Object
    //   2417: dup
    //   2418: iconst_0
    //   2419: new 79	java/lang/StringBuilder
    //   2422: dup
    //   2423: invokespecial 80	java/lang/StringBuilder:<init>	()V
    //   2426: ldc_w 332
    //   2429: invokevirtual 86	java/lang/StringBuilder:append	(Ljava/lang/String;)Ljava/lang/StringBuilder;
    //   2432: aload 17
    //   2434: invokevirtual 86	java/lang/StringBuilder:append	(Ljava/lang/String;)Ljava/lang/StringBuilder;
    //   2437: invokevirtual 102	java/lang/StringBuilder:toString	()Ljava/lang/String;
    //   2440: aastore
    //   2441: invokevirtual 113	com/tencent/mobileqq/secspy/SecSpyFileManager:a	(JI[Ljava/lang/Object;)V
    //   2444: iload 7
    //   2446: istore 6
    //   2448: goto -2068 -> 380
    //   2451: iload 8
    //   2453: istore 4
    //   2455: iload 9
    //   2457: istore 5
    //   2459: iload 10
    //   2461: istore_3
    //   2462: aload_0
    //   2463: getfield 15	com/tencent/mobileqq/secspy/SecSpyFileManager$2:this$0	Lcom/tencent/mobileqq/secspy/SecSpyFileManager;
    //   2466: lload 13
    //   2468: iconst_m1
    //   2469: iconst_1
    //   2470: anewarray 4	java/lang/Object
    //   2473: dup
    //   2474: iconst_0
    //   2475: ldc_w 334
    //   2478: aastore
    //   2479: invokevirtual 113	com/tencent/mobileqq/secspy/SecSpyFileManager:a	(JI[Ljava/lang/Object;)V
    //   2482: iload 7
    //   2484: istore 6
    //   2486: goto -2106 -> 380
    //   2489: iload 8
    //   2491: istore 4
    //   2493: iload 9
    //   2495: istore 5
    //   2497: iload 10
    //   2499: istore_3
    //   2500: new 211	org/json/JSONObject
    //   2503: dup
    //   2504: aload 18
    //   2506: invokespecial 215	org/json/JSONObject:<init>	(Ljava/lang/String;)V
    //   2509: astore 18
    //   2511: iload 8
    //   2513: istore 4
    //   2515: iload 9
    //   2517: istore 5
    //   2519: iload 10
    //   2521: istore_3
    //   2522: aload 18
    //   2524: ldc_w 318
    //   2527: invokevirtual 322	org/json/JSONObject:optString	(Ljava/lang/String;)Ljava/lang/String;
    //   2530: astore 19
    //   2532: iload 8
    //   2534: istore 4
    //   2536: iload 9
    //   2538: istore 5
    //   2540: iload 10
    //   2542: istore_3
    //   2543: aload 18
    //   2545: ldc_w 336
    //   2548: invokevirtual 340	org/json/JSONObject:optJSONArray	(Ljava/lang/String;)Lorg/json/JSONArray;
    //   2551: astore 18
    //   2553: aload 18
    //   2555: ifnull +249 -> 2804
    //   2558: iload 8
    //   2560: istore 4
    //   2562: iload 9
    //   2564: istore 5
    //   2566: iload 10
    //   2568: istore_3
    //   2569: aload 18
    //   2571: invokevirtual 345	org/json/JSONArray:length	()I
    //   2574: ifle +230 -> 2804
    //   2577: iload 8
    //   2579: istore 4
    //   2581: iload 9
    //   2583: istore 5
    //   2585: iload 10
    //   2587: istore_3
    //   2588: aload_0
    //   2589: getfield 15	com/tencent/mobileqq/secspy/SecSpyFileManager$2:this$0	Lcom/tencent/mobileqq/secspy/SecSpyFileManager;
    //   2592: getfield 185	com/tencent/mobileqq/secspy/SecSpyFileManager:jdField_a_of_type_ComTencentMobileqqUnifiedebugUnifiedDebugManager	Lcom/tencent/mobileqq/unifiedebug/UnifiedDebugManager;
    //   2595: aload 19
    //   2597: invokevirtual 324	com/tencent/mobileqq/unifiedebug/UnifiedDebugManager:a	(Ljava/lang/String;)Ljava/lang/String;
    //   2600: astore 20
    //   2602: iload 8
    //   2604: istore 4
    //   2606: iload 9
    //   2608: istore 5
    //   2610: iload 10
    //   2612: istore_3
    //   2613: aload_0
    //   2614: getfield 15	com/tencent/mobileqq/secspy/SecSpyFileManager$2:this$0	Lcom/tencent/mobileqq/secspy/SecSpyFileManager;
    //   2617: aload 20
    //   2619: invokevirtual 151	com/tencent/mobileqq/secspy/SecSpyFileManager:a	(Ljava/lang/String;)Ljava/io/File;
    //   2622: astore 19
    //   2624: aload 19
    //   2626: ifnull +122 -> 2748
    //   2629: iload 8
    //   2631: istore 4
    //   2633: iload 9
    //   2635: istore 5
    //   2637: iload 10
    //   2639: istore_3
    //   2640: aload 19
    //   2642: invokevirtual 156	java/io/File:exists	()Z
    //   2645: ifeq +103 -> 2748
    //   2648: iload 8
    //   2650: istore 4
    //   2652: iload 9
    //   2654: istore 5
    //   2656: iload 10
    //   2658: istore_3
    //   2659: aload 19
    //   2661: invokevirtual 327	java/io/File:isDirectory	()Z
    //   2664: ifeq +84 -> 2748
    //   2667: iload 8
    //   2669: istore 4
    //   2671: iload 9
    //   2673: istore 5
    //   2675: iload 10
    //   2677: istore_3
    //   2678: aload_0
    //   2679: getfield 15	com/tencent/mobileqq/secspy/SecSpyFileManager$2:this$0	Lcom/tencent/mobileqq/secspy/SecSpyFileManager;
    //   2682: aload 18
    //   2684: invokevirtual 348	com/tencent/mobileqq/secspy/SecSpyFileManager:a	(Lorg/json/JSONArray;)Ljava/util/List;
    //   2687: astore 18
    //   2689: iload 8
    //   2691: istore 4
    //   2693: iload 9
    //   2695: istore 5
    //   2697: iload 10
    //   2699: istore_3
    //   2700: aload_0
    //   2701: getfield 15	com/tencent/mobileqq/secspy/SecSpyFileManager$2:this$0	Lcom/tencent/mobileqq/secspy/SecSpyFileManager;
    //   2704: getfield 185	com/tencent/mobileqq/secspy/SecSpyFileManager:jdField_a_of_type_ComTencentMobileqqUnifiedebugUnifiedDebugManager	Lcom/tencent/mobileqq/unifiedebug/UnifiedDebugManager;
    //   2707: aload 19
    //   2709: aload 18
    //   2711: invokevirtual 351	com/tencent/mobileqq/unifiedebug/UnifiedDebugManager:a	(Ljava/io/File;Ljava/util/List;)Ljava/lang/String;
    //   2714: astore 18
    //   2716: iload 8
    //   2718: istore 4
    //   2720: iload 9
    //   2722: istore 5
    //   2724: iload 10
    //   2726: istore_3
    //   2727: aload_0
    //   2728: getfield 15	com/tencent/mobileqq/secspy/SecSpyFileManager$2:this$0	Lcom/tencent/mobileqq/secspy/SecSpyFileManager;
    //   2731: aload 18
    //   2733: lload 13
    //   2735: aload 17
    //   2737: iconst_1
    //   2738: invokevirtual 313	com/tencent/mobileqq/secspy/SecSpyFileManager:a	(Ljava/lang/String;JLjava/lang/String;Z)V
    //   2741: iload 7
    //   2743: istore 6
    //   2745: goto -2365 -> 380
    //   2748: iload 8
    //   2750: istore 4
    //   2752: iload 9
    //   2754: istore 5
    //   2756: iload 10
    //   2758: istore_3
    //   2759: aload_0
    //   2760: getfield 15	com/tencent/mobileqq/secspy/SecSpyFileManager$2:this$0	Lcom/tencent/mobileqq/secspy/SecSpyFileManager;
    //   2763: lload 13
    //   2765: iconst_m1
    //   2766: iconst_1
    //   2767: anewarray 4	java/lang/Object
    //   2770: dup
    //   2771: iconst_0
    //   2772: new 79	java/lang/StringBuilder
    //   2775: dup
    //   2776: invokespecial 80	java/lang/StringBuilder:<init>	()V
    //   2779: ldc_w 332
    //   2782: invokevirtual 86	java/lang/StringBuilder:append	(Ljava/lang/String;)Ljava/lang/StringBuilder;
    //   2785: aload 20
    //   2787: invokevirtual 86	java/lang/StringBuilder:append	(Ljava/lang/String;)Ljava/lang/StringBuilder;
    //   2790: invokevirtual 102	java/lang/StringBuilder:toString	()Ljava/lang/String;
    //   2793: aastore
    //   2794: invokevirtual 113	com/tencent/mobileqq/secspy/SecSpyFileManager:a	(JI[Ljava/lang/Object;)V
    //   2797: iload 7
    //   2799: istore 6
    //   2801: goto -2421 -> 380
    //   2804: iload 8
    //   2806: istore 4
    //   2808: iload 9
    //   2810: istore 5
    //   2812: iload 10
    //   2814: istore_3
    //   2815: aload_0
    //   2816: getfield 15	com/tencent/mobileqq/secspy/SecSpyFileManager$2:this$0	Lcom/tencent/mobileqq/secspy/SecSpyFileManager;
    //   2819: lload 13
    //   2821: iconst_m1
    //   2822: iconst_1
    //   2823: anewarray 4	java/lang/Object
    //   2826: dup
    //   2827: iconst_0
    //   2828: ldc_w 353
    //   2831: aastore
    //   2832: invokevirtual 113	com/tencent/mobileqq/secspy/SecSpyFileManager:a	(JI[Ljava/lang/Object;)V
    //   2835: iload 7
    //   2837: istore 6
    //   2839: goto -2459 -> 380
    //   2842: iload 8
    //   2844: istore 4
    //   2846: iload 9
    //   2848: istore 5
    //   2850: iload 10
    //   2852: istore_3
    //   2853: new 211	org/json/JSONObject
    //   2856: dup
    //   2857: aload 18
    //   2859: invokespecial 215	org/json/JSONObject:<init>	(Ljava/lang/String;)V
    //   2862: astore 17
    //   2864: iload 8
    //   2866: istore 4
    //   2868: iload 9
    //   2870: istore 5
    //   2872: iload 10
    //   2874: istore_3
    //   2875: aload 17
    //   2877: ldc_w 318
    //   2880: invokevirtual 322	org/json/JSONObject:optString	(Ljava/lang/String;)Ljava/lang/String;
    //   2883: astore 18
    //   2885: iload 8
    //   2887: istore 4
    //   2889: iload 9
    //   2891: istore 5
    //   2893: iload 10
    //   2895: istore_3
    //   2896: aload 17
    //   2898: ldc_w 336
    //   2901: invokevirtual 340	org/json/JSONObject:optJSONArray	(Ljava/lang/String;)Lorg/json/JSONArray;
    //   2904: astore 17
    //   2906: aload 17
    //   2908: ifnull +288 -> 3196
    //   2911: iload 8
    //   2913: istore 4
    //   2915: iload 9
    //   2917: istore 5
    //   2919: iload 10
    //   2921: istore_3
    //   2922: aload 17
    //   2924: invokevirtual 345	org/json/JSONArray:length	()I
    //   2927: ifle +269 -> 3196
    //   2930: iload 8
    //   2932: istore 4
    //   2934: iload 9
    //   2936: istore 5
    //   2938: iload 10
    //   2940: istore_3
    //   2941: aload_0
    //   2942: getfield 15	com/tencent/mobileqq/secspy/SecSpyFileManager$2:this$0	Lcom/tencent/mobileqq/secspy/SecSpyFileManager;
    //   2945: getfield 185	com/tencent/mobileqq/secspy/SecSpyFileManager:jdField_a_of_type_ComTencentMobileqqUnifiedebugUnifiedDebugManager	Lcom/tencent/mobileqq/unifiedebug/UnifiedDebugManager;
    //   2948: aload 18
    //   2950: invokevirtual 324	com/tencent/mobileqq/unifiedebug/UnifiedDebugManager:a	(Ljava/lang/String;)Ljava/lang/String;
    //   2953: astore 19
    //   2955: iload 8
    //   2957: istore 4
    //   2959: iload 9
    //   2961: istore 5
    //   2963: iload 10
    //   2965: istore_3
    //   2966: aload_0
    //   2967: getfield 15	com/tencent/mobileqq/secspy/SecSpyFileManager$2:this$0	Lcom/tencent/mobileqq/secspy/SecSpyFileManager;
    //   2970: aload 19
    //   2972: invokevirtual 151	com/tencent/mobileqq/secspy/SecSpyFileManager:a	(Ljava/lang/String;)Ljava/io/File;
    //   2975: astore 18
    //   2977: aload 18
    //   2979: ifnull +161 -> 3140
    //   2982: iload 8
    //   2984: istore 4
    //   2986: iload 9
    //   2988: istore 5
    //   2990: iload 10
    //   2992: istore_3
    //   2993: aload 18
    //   2995: invokevirtual 156	java/io/File:exists	()Z
    //   2998: ifeq +142 -> 3140
    //   3001: iload 8
    //   3003: istore 4
    //   3005: iload 9
    //   3007: istore 5
    //   3009: iload 10
    //   3011: istore_3
    //   3012: aload 18
    //   3014: invokevirtual 327	java/io/File:isDirectory	()Z
    //   3017: ifeq +123 -> 3140
    //   3020: iload 8
    //   3022: istore 4
    //   3024: iload 9
    //   3026: istore 5
    //   3028: iload 10
    //   3030: istore_3
    //   3031: aload_0
    //   3032: getfield 15	com/tencent/mobileqq/secspy/SecSpyFileManager$2:this$0	Lcom/tencent/mobileqq/secspy/SecSpyFileManager;
    //   3035: aload 17
    //   3037: invokevirtual 348	com/tencent/mobileqq/secspy/SecSpyFileManager:a	(Lorg/json/JSONArray;)Ljava/util/List;
    //   3040: astore 17
    //   3042: iload 8
    //   3044: istore 4
    //   3046: iload 9
    //   3048: istore 5
    //   3050: iload 10
    //   3052: istore_3
    //   3053: aload_0
    //   3054: getfield 15	com/tencent/mobileqq/secspy/SecSpyFileManager$2:this$0	Lcom/tencent/mobileqq/secspy/SecSpyFileManager;
    //   3057: getfield 185	com/tencent/mobileqq/secspy/SecSpyFileManager:jdField_a_of_type_ComTencentMobileqqUnifiedebugUnifiedDebugManager	Lcom/tencent/mobileqq/unifiedebug/UnifiedDebugManager;
    //   3060: aload 18
    //   3062: aload 17
    //   3064: invokevirtual 356	com/tencent/mobileqq/unifiedebug/UnifiedDebugManager:a	(Ljava/io/File;Ljava/util/List;)Z
    //   3067: ifeq +35 -> 3102
    //   3070: iload 8
    //   3072: istore 4
    //   3074: iload 9
    //   3076: istore 5
    //   3078: iload 10
    //   3080: istore_3
    //   3081: aload_0
    //   3082: getfield 15	com/tencent/mobileqq/secspy/SecSpyFileManager$2:this$0	Lcom/tencent/mobileqq/secspy/SecSpyFileManager;
    //   3085: lload 13
    //   3087: iconst_0
    //   3088: iconst_0
    //   3089: anewarray 4	java/lang/Object
    //   3092: invokevirtual 113	com/tencent/mobileqq/secspy/SecSpyFileManager:a	(JI[Ljava/lang/Object;)V
    //   3095: iload 7
    //   3097: istore 6
    //   3099: goto -2719 -> 380
    //   3102: iload 8
    //   3104: istore 4
    //   3106: iload 9
    //   3108: istore 5
    //   3110: iload 10
    //   3112: istore_3
    //   3113: aload_0
    //   3114: getfield 15	com/tencent/mobileqq/secspy/SecSpyFileManager$2:this$0	Lcom/tencent/mobileqq/secspy/SecSpyFileManager;
    //   3117: lload 13
    //   3119: iconst_m1
    //   3120: iconst_1
    //   3121: anewarray 4	java/lang/Object
    //   3124: dup
    //   3125: iconst_0
    //   3126: ldc_w 358
    //   3129: aastore
    //   3130: invokevirtual 113	com/tencent/mobileqq/secspy/SecSpyFileManager:a	(JI[Ljava/lang/Object;)V
    //   3133: iload 7
    //   3135: istore 6
    //   3137: goto -2757 -> 380
    //   3140: iload 8
    //   3142: istore 4
    //   3144: iload 9
    //   3146: istore 5
    //   3148: iload 10
    //   3150: istore_3
    //   3151: aload_0
    //   3152: getfield 15	com/tencent/mobileqq/secspy/SecSpyFileManager$2:this$0	Lcom/tencent/mobileqq/secspy/SecSpyFileManager;
    //   3155: lload 13
    //   3157: iconst_m1
    //   3158: iconst_1
    //   3159: anewarray 4	java/lang/Object
    //   3162: dup
    //   3163: iconst_0
    //   3164: new 79	java/lang/StringBuilder
    //   3167: dup
    //   3168: invokespecial 80	java/lang/StringBuilder:<init>	()V
    //   3171: ldc_w 332
    //   3174: invokevirtual 86	java/lang/StringBuilder:append	(Ljava/lang/String;)Ljava/lang/StringBuilder;
    //   3177: aload 19
    //   3179: invokevirtual 86	java/lang/StringBuilder:append	(Ljava/lang/String;)Ljava/lang/StringBuilder;
    //   3182: invokevirtual 102	java/lang/StringBuilder:toString	()Ljava/lang/String;
    //   3185: aastore
    //   3186: invokevirtual 113	com/tencent/mobileqq/secspy/SecSpyFileManager:a	(JI[Ljava/lang/Object;)V
    //   3189: iload 7
    //   3191: istore 6
    //   3193: goto -2813 -> 380
    //   3196: iload 8
    //   3198: istore 4
    //   3200: iload 9
    //   3202: istore 5
    //   3204: iload 10
    //   3206: istore_3
    //   3207: aload_0
    //   3208: getfield 15	com/tencent/mobileqq/secspy/SecSpyFileManager$2:this$0	Lcom/tencent/mobileqq/secspy/SecSpyFileManager;
    //   3211: lload 13
    //   3213: iconst_m1
    //   3214: iconst_1
    //   3215: anewarray 4	java/lang/Object
    //   3218: dup
    //   3219: iconst_0
    //   3220: ldc_w 353
    //   3223: aastore
    //   3224: invokevirtual 113	com/tencent/mobileqq/secspy/SecSpyFileManager:a	(JI[Ljava/lang/Object;)V
    //   3227: iload 7
    //   3229: istore 6
    //   3231: goto -2851 -> 380
    //   3234: iload 8
    //   3236: istore 4
    //   3238: iload 10
    //   3240: istore_3
    //   3241: aload_0
    //   3242: getfield 15	com/tencent/mobileqq/secspy/SecSpyFileManager$2:this$0	Lcom/tencent/mobileqq/secspy/SecSpyFileManager;
    //   3245: getfield 185	com/tencent/mobileqq/secspy/SecSpyFileManager:jdField_a_of_type_ComTencentMobileqqUnifiedebugUnifiedDebugManager	Lcom/tencent/mobileqq/unifiedebug/UnifiedDebugManager;
    //   3248: aload_0
    //   3249: getfield 15	com/tencent/mobileqq/secspy/SecSpyFileManager$2:this$0	Lcom/tencent/mobileqq/secspy/SecSpyFileManager;
    //   3252: getfield 188	com/tencent/mobileqq/secspy/SecSpyFileManager:jdField_a_of_type_ComTencentMobileqqAppQQAppInterface	Lcom/tencent/mobileqq/app/QQAppInterface;
    //   3255: invokevirtual 194	com/tencent/mobileqq/app/QQAppInterface:getApplication	()Lmqq/app/MobileQQ;
    //   3258: invokevirtual 361	com/tencent/mobileqq/unifiedebug/UnifiedDebugManager:a	(Landroid/content/Context;)Ljava/util/List;
    //   3261: astore 17
    //   3263: iload 8
    //   3265: istore 4
    //   3267: iload 10
    //   3269: istore_3
    //   3270: new 211	org/json/JSONObject
    //   3273: dup
    //   3274: invokespecial 362	org/json/JSONObject:<init>	()V
    //   3277: astore 18
    //   3279: iload 8
    //   3281: istore 4
    //   3283: iload 10
    //   3285: istore_3
    //   3286: aload 18
    //   3288: ldc_w 364
    //   3291: aload_0
    //   3292: getfield 15	com/tencent/mobileqq/secspy/SecSpyFileManager$2:this$0	Lcom/tencent/mobileqq/secspy/SecSpyFileManager;
    //   3295: aload 17
    //   3297: invokevirtual 367	com/tencent/mobileqq/secspy/SecSpyFileManager:a	(Ljava/util/Collection;)Lorg/json/JSONArray;
    //   3300: invokevirtual 371	org/json/JSONObject:put	(Ljava/lang/String;Ljava/lang/Object;)Lorg/json/JSONObject;
    //   3303: pop
    //   3304: iload 8
    //   3306: istore 4
    //   3308: iload 10
    //   3310: istore_3
    //   3311: aload_0
    //   3312: getfield 15	com/tencent/mobileqq/secspy/SecSpyFileManager$2:this$0	Lcom/tencent/mobileqq/secspy/SecSpyFileManager;
    //   3315: lload 13
    //   3317: aload 18
    //   3319: invokevirtual 207	com/tencent/mobileqq/secspy/SecSpyFileManager:a	(JLorg/json/JSONObject;)V
    //   3322: iload 7
    //   3324: istore 6
    //   3326: goto -2946 -> 380
    //   3329: astore 17
    //   3331: iload 8
    //   3333: istore 4
    //   3335: iload 9
    //   3337: istore 5
    //   3339: iload 10
    //   3341: istore_3
    //   3342: aload_0
    //   3343: getfield 15	com/tencent/mobileqq/secspy/SecSpyFileManager$2:this$0	Lcom/tencent/mobileqq/secspy/SecSpyFileManager;
    //   3346: lload 13
    //   3348: iconst_m1
    //   3349: iconst_1
    //   3350: anewarray 4	java/lang/Object
    //   3353: dup
    //   3354: iconst_0
    //   3355: aload 17
    //   3357: invokevirtual 372	java/lang/Exception:getMessage	()Ljava/lang/String;
    //   3360: aastore
    //   3361: invokevirtual 113	com/tencent/mobileqq/secspy/SecSpyFileManager:a	(JI[Ljava/lang/Object;)V
    //   3364: iload 7
    //   3366: istore 6
    //   3368: goto -2988 -> 380
    //   3371: iload 8
    //   3373: istore 4
    //   3375: iload 9
    //   3377: istore 5
    //   3379: iload 10
    //   3381: istore_3
    //   3382: new 211	org/json/JSONObject
    //   3385: dup
    //   3386: aload 18
    //   3388: invokespecial 215	org/json/JSONObject:<init>	(Ljava/lang/String;)V
    //   3391: ldc_w 364
    //   3394: invokevirtual 340	org/json/JSONObject:optJSONArray	(Ljava/lang/String;)Lorg/json/JSONArray;
    //   3397: astore 18
    //   3399: aload 18
    //   3401: ifnull +126 -> 3527
    //   3404: iload 8
    //   3406: istore 4
    //   3408: iload 9
    //   3410: istore 5
    //   3412: iload 10
    //   3414: istore_3
    //   3415: aload_0
    //   3416: getfield 15	com/tencent/mobileqq/secspy/SecSpyFileManager$2:this$0	Lcom/tencent/mobileqq/secspy/SecSpyFileManager;
    //   3419: aload 18
    //   3421: invokevirtual 348	com/tencent/mobileqq/secspy/SecSpyFileManager:a	(Lorg/json/JSONArray;)Ljava/util/List;
    //   3424: astore 18
    //   3426: iload 8
    //   3428: istore 4
    //   3430: iload 10
    //   3432: istore_3
    //   3433: aload_0
    //   3434: getfield 15	com/tencent/mobileqq/secspy/SecSpyFileManager$2:this$0	Lcom/tencent/mobileqq/secspy/SecSpyFileManager;
    //   3437: getfield 185	com/tencent/mobileqq/secspy/SecSpyFileManager:jdField_a_of_type_ComTencentMobileqqUnifiedebugUnifiedDebugManager	Lcom/tencent/mobileqq/unifiedebug/UnifiedDebugManager;
    //   3440: aload_0
    //   3441: getfield 15	com/tencent/mobileqq/secspy/SecSpyFileManager$2:this$0	Lcom/tencent/mobileqq/secspy/SecSpyFileManager;
    //   3444: getfield 188	com/tencent/mobileqq/secspy/SecSpyFileManager:jdField_a_of_type_ComTencentMobileqqAppQQAppInterface	Lcom/tencent/mobileqq/app/QQAppInterface;
    //   3447: invokevirtual 194	com/tencent/mobileqq/app/QQAppInterface:getApplication	()Lmqq/app/MobileQQ;
    //   3450: aload 18
    //   3452: invokevirtual 375	com/tencent/mobileqq/unifiedebug/UnifiedDebugManager:a	(Landroid/content/Context;Ljava/util/List;)Ljava/lang/String;
    //   3455: astore 18
    //   3457: iload 8
    //   3459: istore 4
    //   3461: iload 10
    //   3463: istore_3
    //   3464: aload_0
    //   3465: getfield 15	com/tencent/mobileqq/secspy/SecSpyFileManager$2:this$0	Lcom/tencent/mobileqq/secspy/SecSpyFileManager;
    //   3468: aload 18
    //   3470: lload 13
    //   3472: aload 17
    //   3474: iconst_1
    //   3475: invokevirtual 313	com/tencent/mobileqq/secspy/SecSpyFileManager:a	(Ljava/lang/String;JLjava/lang/String;Z)V
    //   3478: iload 7
    //   3480: istore 6
    //   3482: goto -3102 -> 380
    //   3485: astore 17
    //   3487: iload 8
    //   3489: istore 4
    //   3491: iload 9
    //   3493: istore 5
    //   3495: iload 10
    //   3497: istore_3
    //   3498: aload_0
    //   3499: getfield 15	com/tencent/mobileqq/secspy/SecSpyFileManager$2:this$0	Lcom/tencent/mobileqq/secspy/SecSpyFileManager;
    //   3502: lload 13
    //   3504: iconst_m1
    //   3505: iconst_1
    //   3506: anewarray 4	java/lang/Object
    //   3509: dup
    //   3510: iconst_0
    //   3511: aload 17
    //   3513: invokevirtual 372	java/lang/Exception:getMessage	()Ljava/lang/String;
    //   3516: aastore
    //   3517: invokevirtual 113	com/tencent/mobileqq/secspy/SecSpyFileManager:a	(JI[Ljava/lang/Object;)V
    //   3520: iload 7
    //   3522: istore 6
    //   3524: goto -3144 -> 380
    //   3527: iload 8
    //   3529: istore 4
    //   3531: iload 9
    //   3533: istore 5
    //   3535: iload 10
    //   3537: istore_3
    //   3538: aload_0
    //   3539: getfield 15	com/tencent/mobileqq/secspy/SecSpyFileManager$2:this$0	Lcom/tencent/mobileqq/secspy/SecSpyFileManager;
    //   3542: lload 13
    //   3544: iconst_m1
    //   3545: iconst_1
    //   3546: anewarray 4	java/lang/Object
    //   3549: dup
    //   3550: iconst_0
    //   3551: ldc_w 377
    //   3554: aastore
    //   3555: invokevirtual 113	com/tencent/mobileqq/secspy/SecSpyFileManager:a	(JI[Ljava/lang/Object;)V
    //   3558: iload 7
    //   3560: istore 6
    //   3562: goto -3182 -> 380
    //   3565: iload 8
    //   3567: istore 4
    //   3569: iload 9
    //   3571: istore 5
    //   3573: iload 10
    //   3575: istore_3
    //   3576: new 211	org/json/JSONObject
    //   3579: dup
    //   3580: aload 18
    //   3582: invokespecial 215	org/json/JSONObject:<init>	(Ljava/lang/String;)V
    //   3585: ldc_w 364
    //   3588: invokevirtual 340	org/json/JSONObject:optJSONArray	(Ljava/lang/String;)Lorg/json/JSONArray;
    //   3591: astore 17
    //   3593: aload 17
    //   3595: ifnull +103 -> 3698
    //   3598: iload 8
    //   3600: istore 4
    //   3602: iload 9
    //   3604: istore 5
    //   3606: iload 10
    //   3608: istore_3
    //   3609: aload_0
    //   3610: getfield 15	com/tencent/mobileqq/secspy/SecSpyFileManager$2:this$0	Lcom/tencent/mobileqq/secspy/SecSpyFileManager;
    //   3613: aload 17
    //   3615: invokevirtual 348	com/tencent/mobileqq/secspy/SecSpyFileManager:a	(Lorg/json/JSONArray;)Ljava/util/List;
    //   3618: astore 17
    //   3620: iload 8
    //   3622: istore 4
    //   3624: iload 10
    //   3626: istore_3
    //   3627: aload_0
    //   3628: getfield 15	com/tencent/mobileqq/secspy/SecSpyFileManager$2:this$0	Lcom/tencent/mobileqq/secspy/SecSpyFileManager;
    //   3631: getfield 185	com/tencent/mobileqq/secspy/SecSpyFileManager:jdField_a_of_type_ComTencentMobileqqUnifiedebugUnifiedDebugManager	Lcom/tencent/mobileqq/unifiedebug/UnifiedDebugManager;
    //   3634: aload_0
    //   3635: getfield 15	com/tencent/mobileqq/secspy/SecSpyFileManager$2:this$0	Lcom/tencent/mobileqq/secspy/SecSpyFileManager;
    //   3638: getfield 188	com/tencent/mobileqq/secspy/SecSpyFileManager:jdField_a_of_type_ComTencentMobileqqAppQQAppInterface	Lcom/tencent/mobileqq/app/QQAppInterface;
    //   3641: invokevirtual 194	com/tencent/mobileqq/app/QQAppInterface:getApplication	()Lmqq/app/MobileQQ;
    //   3644: aload 17
    //   3646: invokevirtual 380	com/tencent/mobileqq/unifiedebug/UnifiedDebugManager:a	(Landroid/content/Context;Ljava/util/List;)V
    //   3649: iload 7
    //   3651: istore 6
    //   3653: goto -3273 -> 380
    //   3656: astore 17
    //   3658: iload 8
    //   3660: istore 4
    //   3662: iload 9
    //   3664: istore 5
    //   3666: iload 10
    //   3668: istore_3
    //   3669: aload_0
    //   3670: getfield 15	com/tencent/mobileqq/secspy/SecSpyFileManager$2:this$0	Lcom/tencent/mobileqq/secspy/SecSpyFileManager;
    //   3673: lload 13
    //   3675: iconst_m1
    //   3676: iconst_1
    //   3677: anewarray 4	java/lang/Object
    //   3680: dup
    //   3681: iconst_0
    //   3682: aload 17
    //   3684: invokevirtual 372	java/lang/Exception:getMessage	()Ljava/lang/String;
    //   3687: aastore
    //   3688: invokevirtual 113	com/tencent/mobileqq/secspy/SecSpyFileManager:a	(JI[Ljava/lang/Object;)V
    //   3691: iload 7
    //   3693: istore 6
    //   3695: goto -3315 -> 380
    //   3698: iload 8
    //   3700: istore 4
    //   3702: iload 9
    //   3704: istore 5
    //   3706: iload 10
    //   3708: istore_3
    //   3709: aload_0
    //   3710: getfield 15	com/tencent/mobileqq/secspy/SecSpyFileManager$2:this$0	Lcom/tencent/mobileqq/secspy/SecSpyFileManager;
    //   3713: lload 13
    //   3715: iconst_m1
    //   3716: iconst_1
    //   3717: anewarray 4	java/lang/Object
    //   3720: dup
    //   3721: iconst_0
    //   3722: ldc_w 377
    //   3725: aastore
    //   3726: invokevirtual 113	com/tencent/mobileqq/secspy/SecSpyFileManager:a	(JI[Ljava/lang/Object;)V
    //   3729: iload 7
    //   3731: istore 6
    //   3733: goto -3353 -> 380
    //   3736: iload 8
    //   3738: istore 4
    //   3740: iload 10
    //   3742: istore_3
    //   3743: aload_0
    //   3744: getfield 15	com/tencent/mobileqq/secspy/SecSpyFileManager$2:this$0	Lcom/tencent/mobileqq/secspy/SecSpyFileManager;
    //   3747: getfield 185	com/tencent/mobileqq/secspy/SecSpyFileManager:jdField_a_of_type_ComTencentMobileqqUnifiedebugUnifiedDebugManager	Lcom/tencent/mobileqq/unifiedebug/UnifiedDebugManager;
    //   3750: aload_0
    //   3751: getfield 15	com/tencent/mobileqq/secspy/SecSpyFileManager$2:this$0	Lcom/tencent/mobileqq/secspy/SecSpyFileManager;
    //   3754: getfield 188	com/tencent/mobileqq/secspy/SecSpyFileManager:jdField_a_of_type_ComTencentMobileqqAppQQAppInterface	Lcom/tencent/mobileqq/app/QQAppInterface;
    //   3757: invokevirtual 194	com/tencent/mobileqq/app/QQAppInterface:getApplication	()Lmqq/app/MobileQQ;
    //   3760: invokevirtual 383	com/tencent/mobileqq/unifiedebug/UnifiedDebugManager:a	(Landroid/content/Context;)Ljava/util/Set;
    //   3763: astore 17
    //   3765: iload 8
    //   3767: istore 4
    //   3769: iload 10
    //   3771: istore_3
    //   3772: new 211	org/json/JSONObject
    //   3775: dup
    //   3776: invokespecial 362	org/json/JSONObject:<init>	()V
    //   3779: astore 18
    //   3781: iload 8
    //   3783: istore 4
    //   3785: iload 10
    //   3787: istore_3
    //   3788: aload 18
    //   3790: ldc_w 385
    //   3793: aload_0
    //   3794: getfield 15	com/tencent/mobileqq/secspy/SecSpyFileManager$2:this$0	Lcom/tencent/mobileqq/secspy/SecSpyFileManager;
    //   3797: aload 17
    //   3799: invokevirtual 367	com/tencent/mobileqq/secspy/SecSpyFileManager:a	(Ljava/util/Collection;)Lorg/json/JSONArray;
    //   3802: invokevirtual 371	org/json/JSONObject:put	(Ljava/lang/String;Ljava/lang/Object;)Lorg/json/JSONObject;
    //   3805: pop
    //   3806: iload 8
    //   3808: istore 4
    //   3810: iload 10
    //   3812: istore_3
    //   3813: aload_0
    //   3814: getfield 15	com/tencent/mobileqq/secspy/SecSpyFileManager$2:this$0	Lcom/tencent/mobileqq/secspy/SecSpyFileManager;
    //   3817: lload 13
    //   3819: aload 18
    //   3821: invokevirtual 207	com/tencent/mobileqq/secspy/SecSpyFileManager:a	(JLorg/json/JSONObject;)V
    //   3824: iload 7
    //   3826: istore 6
    //   3828: goto -3448 -> 380
    //   3831: astore 17
    //   3833: iload 8
    //   3835: istore 4
    //   3837: iload 9
    //   3839: istore 5
    //   3841: iload 10
    //   3843: istore_3
    //   3844: aload_0
    //   3845: getfield 15	com/tencent/mobileqq/secspy/SecSpyFileManager$2:this$0	Lcom/tencent/mobileqq/secspy/SecSpyFileManager;
    //   3848: lload 13
    //   3850: iconst_m1
    //   3851: iconst_1
    //   3852: anewarray 4	java/lang/Object
    //   3855: dup
    //   3856: iconst_0
    //   3857: aload 17
    //   3859: invokevirtual 372	java/lang/Exception:getMessage	()Ljava/lang/String;
    //   3862: aastore
    //   3863: invokevirtual 113	com/tencent/mobileqq/secspy/SecSpyFileManager:a	(JI[Ljava/lang/Object;)V
    //   3866: iload 7
    //   3868: istore 6
    //   3870: goto -3490 -> 380
    //   3873: iload 8
    //   3875: istore 4
    //   3877: iload 9
    //   3879: istore 5
    //   3881: iload 10
    //   3883: istore_3
    //   3884: new 211	org/json/JSONObject
    //   3887: dup
    //   3888: aload 18
    //   3890: invokespecial 215	org/json/JSONObject:<init>	(Ljava/lang/String;)V
    //   3893: ldc_w 387
    //   3896: invokevirtual 322	org/json/JSONObject:optString	(Ljava/lang/String;)Ljava/lang/String;
    //   3899: astore 18
    //   3901: iload 8
    //   3903: istore 4
    //   3905: iload 9
    //   3907: istore 5
    //   3909: iload 10
    //   3911: istore_3
    //   3912: aload 18
    //   3914: invokestatic 148	android/text/TextUtils:isEmpty	(Ljava/lang/CharSequence;)Z
    //   3917: istore 6
    //   3919: iload 6
    //   3921: ifne +399 -> 4320
    //   3924: iload 8
    //   3926: istore 4
    //   3928: iload 9
    //   3930: istore 5
    //   3932: iload 10
    //   3934: istore_3
    //   3935: aload_0
    //   3936: getfield 15	com/tencent/mobileqq/secspy/SecSpyFileManager$2:this$0	Lcom/tencent/mobileqq/secspy/SecSpyFileManager;
    //   3939: getfield 185	com/tencent/mobileqq/secspy/SecSpyFileManager:jdField_a_of_type_ComTencentMobileqqUnifiedebugUnifiedDebugManager	Lcom/tencent/mobileqq/unifiedebug/UnifiedDebugManager;
    //   3942: aload_0
    //   3943: getfield 15	com/tencent/mobileqq/secspy/SecSpyFileManager$2:this$0	Lcom/tencent/mobileqq/secspy/SecSpyFileManager;
    //   3946: getfield 188	com/tencent/mobileqq/secspy/SecSpyFileManager:jdField_a_of_type_ComTencentMobileqqAppQQAppInterface	Lcom/tencent/mobileqq/app/QQAppInterface;
    //   3949: invokevirtual 194	com/tencent/mobileqq/app/QQAppInterface:getApplication	()Lmqq/app/MobileQQ;
    //   3952: aload 18
    //   3954: invokevirtual 390	com/tencent/mobileqq/unifiedebug/UnifiedDebugManager:a	(Landroid/content/Context;Ljava/lang/String;)Ljava/util/List;
    //   3957: astore 19
    //   3959: iload 8
    //   3961: istore 4
    //   3963: iload 9
    //   3965: istore 5
    //   3967: iload 10
    //   3969: istore_3
    //   3970: new 211	org/json/JSONObject
    //   3973: dup
    //   3974: invokespecial 362	org/json/JSONObject:<init>	()V
    //   3977: astore 17
    //   3979: iload 8
    //   3981: istore 4
    //   3983: iload 9
    //   3985: istore 5
    //   3987: iload 10
    //   3989: istore_3
    //   3990: aload 17
    //   3992: ldc_w 387
    //   3995: aload 18
    //   3997: invokevirtual 371	org/json/JSONObject:put	(Ljava/lang/String;Ljava/lang/Object;)Lorg/json/JSONObject;
    //   4000: pop
    //   4001: iload 8
    //   4003: istore 4
    //   4005: iload 9
    //   4007: istore 5
    //   4009: iload 10
    //   4011: istore_3
    //   4012: new 342	org/json/JSONArray
    //   4015: dup
    //   4016: invokespecial 391	org/json/JSONArray:<init>	()V
    //   4019: astore 18
    //   4021: iload 8
    //   4023: istore 4
    //   4025: iload 9
    //   4027: istore 5
    //   4029: iload 10
    //   4031: istore_3
    //   4032: aload 19
    //   4034: invokeinterface 397 1 0
    //   4039: astore 19
    //   4041: iload 8
    //   4043: istore 4
    //   4045: iload 9
    //   4047: istore 5
    //   4049: iload 10
    //   4051: istore_3
    //   4052: aload 19
    //   4054: invokeinterface 402 1 0
    //   4059: ifeq +210 -> 4269
    //   4062: iload 8
    //   4064: istore 4
    //   4066: iload 9
    //   4068: istore 5
    //   4070: iload 10
    //   4072: istore_3
    //   4073: aload 19
    //   4075: invokeinterface 406 1 0
    //   4080: checkcast 408	java/util/Map
    //   4083: astore 20
    //   4085: iload 8
    //   4087: istore 4
    //   4089: iload 9
    //   4091: istore 5
    //   4093: iload 10
    //   4095: istore_3
    //   4096: new 211	org/json/JSONObject
    //   4099: dup
    //   4100: invokespecial 362	org/json/JSONObject:<init>	()V
    //   4103: astore 21
    //   4105: iload 8
    //   4107: istore 4
    //   4109: iload 9
    //   4111: istore 5
    //   4113: iload 10
    //   4115: istore_3
    //   4116: aload 20
    //   4118: invokeinterface 412 1 0
    //   4123: invokeinterface 415 1 0
    //   4128: astore 22
    //   4130: iload 8
    //   4132: istore 4
    //   4134: iload 9
    //   4136: istore 5
    //   4138: iload 10
    //   4140: istore_3
    //   4141: aload 22
    //   4143: invokeinterface 402 1 0
    //   4148: ifeq +99 -> 4247
    //   4151: iload 8
    //   4153: istore 4
    //   4155: iload 9
    //   4157: istore 5
    //   4159: iload 10
    //   4161: istore_3
    //   4162: aload 22
    //   4164: invokeinterface 406 1 0
    //   4169: checkcast 68	java/lang/String
    //   4172: astore 23
    //   4174: iload 8
    //   4176: istore 4
    //   4178: iload 9
    //   4180: istore 5
    //   4182: iload 10
    //   4184: istore_3
    //   4185: aload 21
    //   4187: aload 23
    //   4189: aload 20
    //   4191: aload 23
    //   4193: invokeinterface 418 2 0
    //   4198: invokevirtual 371	org/json/JSONObject:put	(Ljava/lang/String;Ljava/lang/Object;)Lorg/json/JSONObject;
    //   4201: pop
    //   4202: goto -72 -> 4130
    //   4205: astore 17
    //   4207: iload 8
    //   4209: istore 4
    //   4211: iload 9
    //   4213: istore 5
    //   4215: iload 10
    //   4217: istore_3
    //   4218: aload_0
    //   4219: getfield 15	com/tencent/mobileqq/secspy/SecSpyFileManager$2:this$0	Lcom/tencent/mobileqq/secspy/SecSpyFileManager;
    //   4222: lload 13
    //   4224: iconst_m1
    //   4225: iconst_1
    //   4226: anewarray 4	java/lang/Object
    //   4229: dup
    //   4230: iconst_0
    //   4231: aload 17
    //   4233: invokevirtual 419	android/database/sqlite/SQLiteException:getMessage	()Ljava/lang/String;
    //   4236: aastore
    //   4237: invokevirtual 113	com/tencent/mobileqq/secspy/SecSpyFileManager:a	(JI[Ljava/lang/Object;)V
    //   4240: iload 7
    //   4242: istore 6
    //   4244: goto -3864 -> 380
    //   4247: iload 8
    //   4249: istore 4
    //   4251: iload 9
    //   4253: istore 5
    //   4255: iload 10
    //   4257: istore_3
    //   4258: aload 18
    //   4260: aload 21
    //   4262: invokevirtual 422	org/json/JSONArray:put	(Ljava/lang/Object;)Lorg/json/JSONArray;
    //   4265: pop
    //   4266: goto -225 -> 4041
    //   4269: iload 8
    //   4271: istore 4
    //   4273: iload 9
    //   4275: istore 5
    //   4277: iload 10
    //   4279: istore_3
    //   4280: aload 17
    //   4282: ldc_w 424
    //   4285: aload 18
    //   4287: invokevirtual 371	org/json/JSONObject:put	(Ljava/lang/String;Ljava/lang/Object;)Lorg/json/JSONObject;
    //   4290: pop
    //   4291: iload 8
    //   4293: istore 4
    //   4295: iload 9
    //   4297: istore 5
    //   4299: iload 10
    //   4301: istore_3
    //   4302: aload_0
    //   4303: getfield 15	com/tencent/mobileqq/secspy/SecSpyFileManager$2:this$0	Lcom/tencent/mobileqq/secspy/SecSpyFileManager;
    //   4306: lload 13
    //   4308: aload 17
    //   4310: invokevirtual 207	com/tencent/mobileqq/secspy/SecSpyFileManager:a	(JLorg/json/JSONObject;)V
    //   4313: iload 7
    //   4315: istore 6
    //   4317: goto -3937 -> 380
    //   4320: iload 8
    //   4322: istore 4
    //   4324: iload 9
    //   4326: istore 5
    //   4328: iload 10
    //   4330: istore_3
    //   4331: aload_0
    //   4332: getfield 15	com/tencent/mobileqq/secspy/SecSpyFileManager$2:this$0	Lcom/tencent/mobileqq/secspy/SecSpyFileManager;
    //   4335: lload 13
    //   4337: iconst_m1
    //   4338: iconst_1
    //   4339: anewarray 4	java/lang/Object
    //   4342: dup
    //   4343: iconst_0
    //   4344: ldc_w 426
    //   4347: aastore
    //   4348: invokevirtual 113	com/tencent/mobileqq/secspy/SecSpyFileManager:a	(JI[Ljava/lang/Object;)V
    //   4351: iload 7
    //   4353: istore 6
    //   4355: goto -3975 -> 380
    //   4358: iload 8
    //   4360: istore 4
    //   4362: iload 9
    //   4364: istore 5
    //   4366: iload 10
    //   4368: istore_3
    //   4369: new 211	org/json/JSONObject
    //   4372: dup
    //   4373: aload 18
    //   4375: invokespecial 215	org/json/JSONObject:<init>	(Ljava/lang/String;)V
    //   4378: astore 18
    //   4380: iload 8
    //   4382: istore 4
    //   4384: iload 9
    //   4386: istore 5
    //   4388: iload 10
    //   4390: istore_3
    //   4391: aload 18
    //   4393: ldc_w 387
    //   4396: invokevirtual 322	org/json/JSONObject:optString	(Ljava/lang/String;)Ljava/lang/String;
    //   4399: astore 17
    //   4401: iload 8
    //   4403: istore 4
    //   4405: iload 9
    //   4407: istore 5
    //   4409: iload 10
    //   4411: istore_3
    //   4412: aload 18
    //   4414: ldc_w 424
    //   4417: invokevirtual 340	org/json/JSONObject:optJSONArray	(Ljava/lang/String;)Lorg/json/JSONArray;
    //   4420: astore 18
    //   4422: iload 8
    //   4424: istore 4
    //   4426: iload 9
    //   4428: istore 5
    //   4430: iload 10
    //   4432: istore_3
    //   4433: aload 17
    //   4435: invokestatic 148	android/text/TextUtils:isEmpty	(Ljava/lang/CharSequence;)Z
    //   4438: ifne +169 -> 4607
    //   4441: aload 18
    //   4443: ifnull +126 -> 4569
    //   4446: iload 8
    //   4448: istore 4
    //   4450: iload 9
    //   4452: istore 5
    //   4454: iload 10
    //   4456: istore_3
    //   4457: aload_0
    //   4458: getfield 15	com/tencent/mobileqq/secspy/SecSpyFileManager$2:this$0	Lcom/tencent/mobileqq/secspy/SecSpyFileManager;
    //   4461: aload 18
    //   4463: invokevirtual 348	com/tencent/mobileqq/secspy/SecSpyFileManager:a	(Lorg/json/JSONArray;)Ljava/util/List;
    //   4466: astore 18
    //   4468: iload 8
    //   4470: istore 4
    //   4472: iload 10
    //   4474: istore_3
    //   4475: aload_0
    //   4476: getfield 15	com/tencent/mobileqq/secspy/SecSpyFileManager$2:this$0	Lcom/tencent/mobileqq/secspy/SecSpyFileManager;
    //   4479: getfield 185	com/tencent/mobileqq/secspy/SecSpyFileManager:jdField_a_of_type_ComTencentMobileqqUnifiedebugUnifiedDebugManager	Lcom/tencent/mobileqq/unifiedebug/UnifiedDebugManager;
    //   4482: aload_0
    //   4483: getfield 15	com/tencent/mobileqq/secspy/SecSpyFileManager$2:this$0	Lcom/tencent/mobileqq/secspy/SecSpyFileManager;
    //   4486: getfield 188	com/tencent/mobileqq/secspy/SecSpyFileManager:jdField_a_of_type_ComTencentMobileqqAppQQAppInterface	Lcom/tencent/mobileqq/app/QQAppInterface;
    //   4489: invokevirtual 194	com/tencent/mobileqq/app/QQAppInterface:getApplication	()Lmqq/app/MobileQQ;
    //   4492: aload 17
    //   4494: aload 18
    //   4496: invokevirtual 429	com/tencent/mobileqq/unifiedebug/UnifiedDebugManager:a	(Landroid/content/Context;Ljava/lang/String;Ljava/util/List;)V
    //   4499: iload 8
    //   4501: istore 4
    //   4503: iload 10
    //   4505: istore_3
    //   4506: aload_0
    //   4507: getfield 15	com/tencent/mobileqq/secspy/SecSpyFileManager$2:this$0	Lcom/tencent/mobileqq/secspy/SecSpyFileManager;
    //   4510: lload 13
    //   4512: iconst_0
    //   4513: iconst_0
    //   4514: anewarray 4	java/lang/Object
    //   4517: invokevirtual 113	com/tencent/mobileqq/secspy/SecSpyFileManager:a	(JI[Ljava/lang/Object;)V
    //   4520: iload 7
    //   4522: istore 6
    //   4524: goto -4144 -> 380
    //   4527: astore 17
    //   4529: iload 8
    //   4531: istore 4
    //   4533: iload 9
    //   4535: istore 5
    //   4537: iload 10
    //   4539: istore_3
    //   4540: aload_0
    //   4541: getfield 15	com/tencent/mobileqq/secspy/SecSpyFileManager$2:this$0	Lcom/tencent/mobileqq/secspy/SecSpyFileManager;
    //   4544: lload 13
    //   4546: iconst_m1
    //   4547: iconst_1
    //   4548: anewarray 4	java/lang/Object
    //   4551: dup
    //   4552: iconst_0
    //   4553: aload 17
    //   4555: invokevirtual 372	java/lang/Exception:getMessage	()Ljava/lang/String;
    //   4558: aastore
    //   4559: invokevirtual 113	com/tencent/mobileqq/secspy/SecSpyFileManager:a	(JI[Ljava/lang/Object;)V
    //   4562: iload 7
    //   4564: istore 6
    //   4566: goto -4186 -> 380
    //   4569: iload 8
    //   4571: istore 4
    //   4573: iload 9
    //   4575: istore 5
    //   4577: iload 10
    //   4579: istore_3
    //   4580: aload_0
    //   4581: getfield 15	com/tencent/mobileqq/secspy/SecSpyFileManager$2:this$0	Lcom/tencent/mobileqq/secspy/SecSpyFileManager;
    //   4584: lload 13
    //   4586: iconst_m1
    //   4587: iconst_1
    //   4588: anewarray 4	java/lang/Object
    //   4591: dup
    //   4592: iconst_0
    //   4593: ldc_w 431
    //   4596: aastore
    //   4597: invokevirtual 113	com/tencent/mobileqq/secspy/SecSpyFileManager:a	(JI[Ljava/lang/Object;)V
    //   4600: iload 7
    //   4602: istore 6
    //   4604: goto -4224 -> 380
    //   4607: iload 8
    //   4609: istore 4
    //   4611: iload 9
    //   4613: istore 5
    //   4615: iload 10
    //   4617: istore_3
    //   4618: aload_0
    //   4619: getfield 15	com/tencent/mobileqq/secspy/SecSpyFileManager$2:this$0	Lcom/tencent/mobileqq/secspy/SecSpyFileManager;
    //   4622: lload 13
    //   4624: iconst_m1
    //   4625: iconst_1
    //   4626: anewarray 4	java/lang/Object
    //   4629: dup
    //   4630: iconst_0
    //   4631: ldc_w 426
    //   4634: aastore
    //   4635: invokevirtual 113	com/tencent/mobileqq/secspy/SecSpyFileManager:a	(JI[Ljava/lang/Object;)V
    //   4638: iload 7
    //   4640: istore 6
    //   4642: goto -4262 -> 380
    //   4645: iload 8
    //   4647: istore 4
    //   4649: iload 10
    //   4651: istore_3
    //   4652: aload_0
    //   4653: getfield 15	com/tencent/mobileqq/secspy/SecSpyFileManager$2:this$0	Lcom/tencent/mobileqq/secspy/SecSpyFileManager;
    //   4656: getfield 185	com/tencent/mobileqq/secspy/SecSpyFileManager:jdField_a_of_type_ComTencentMobileqqUnifiedebugUnifiedDebugManager	Lcom/tencent/mobileqq/unifiedebug/UnifiedDebugManager;
    //   4659: aload_0
    //   4660: getfield 15	com/tencent/mobileqq/secspy/SecSpyFileManager$2:this$0	Lcom/tencent/mobileqq/secspy/SecSpyFileManager;
    //   4663: getfield 188	com/tencent/mobileqq/secspy/SecSpyFileManager:jdField_a_of_type_ComTencentMobileqqAppQQAppInterface	Lcom/tencent/mobileqq/app/QQAppInterface;
    //   4666: invokevirtual 194	com/tencent/mobileqq/app/QQAppInterface:getApplication	()Lmqq/app/MobileQQ;
    //   4669: invokevirtual 434	com/tencent/mobileqq/unifiedebug/UnifiedDebugManager:b	(Landroid/content/Context;)Ljava/util/Set;
    //   4672: astore 17
    //   4674: iload 8
    //   4676: istore 4
    //   4678: iload 10
    //   4680: istore_3
    //   4681: new 211	org/json/JSONObject
    //   4684: dup
    //   4685: invokespecial 362	org/json/JSONObject:<init>	()V
    //   4688: astore 18
    //   4690: iload 8
    //   4692: istore 4
    //   4694: iload 10
    //   4696: istore_3
    //   4697: aload 18
    //   4699: ldc_w 385
    //   4702: aload_0
    //   4703: getfield 15	com/tencent/mobileqq/secspy/SecSpyFileManager$2:this$0	Lcom/tencent/mobileqq/secspy/SecSpyFileManager;
    //   4706: aload 17
    //   4708: invokevirtual 367	com/tencent/mobileqq/secspy/SecSpyFileManager:a	(Ljava/util/Collection;)Lorg/json/JSONArray;
    //   4711: invokevirtual 371	org/json/JSONObject:put	(Ljava/lang/String;Ljava/lang/Object;)Lorg/json/JSONObject;
    //   4714: pop
    //   4715: iload 8
    //   4717: istore 4
    //   4719: iload 10
    //   4721: istore_3
    //   4722: aload_0
    //   4723: getfield 15	com/tencent/mobileqq/secspy/SecSpyFileManager$2:this$0	Lcom/tencent/mobileqq/secspy/SecSpyFileManager;
    //   4726: lload 13
    //   4728: aload 18
    //   4730: invokevirtual 207	com/tencent/mobileqq/secspy/SecSpyFileManager:a	(JLorg/json/JSONObject;)V
    //   4733: iload 7
    //   4735: istore 6
    //   4737: goto -4357 -> 380
    //   4740: astore 17
    //   4742: iload 8
    //   4744: istore 4
    //   4746: iload 9
    //   4748: istore 5
    //   4750: iload 10
    //   4752: istore_3
    //   4753: aload_0
    //   4754: getfield 15	com/tencent/mobileqq/secspy/SecSpyFileManager$2:this$0	Lcom/tencent/mobileqq/secspy/SecSpyFileManager;
    //   4757: lload 13
    //   4759: iconst_m1
    //   4760: iconst_1
    //   4761: anewarray 4	java/lang/Object
    //   4764: dup
    //   4765: iconst_0
    //   4766: aload 17
    //   4768: invokevirtual 372	java/lang/Exception:getMessage	()Ljava/lang/String;
    //   4771: aastore
    //   4772: invokevirtual 113	com/tencent/mobileqq/secspy/SecSpyFileManager:a	(JI[Ljava/lang/Object;)V
    //   4775: iload 7
    //   4777: istore 6
    //   4779: goto -4399 -> 380
    //   4782: iload 8
    //   4784: istore 4
    //   4786: iload 9
    //   4788: istore 5
    //   4790: iload 10
    //   4792: istore_3
    //   4793: new 211	org/json/JSONObject
    //   4796: dup
    //   4797: aload 18
    //   4799: invokespecial 215	org/json/JSONObject:<init>	(Ljava/lang/String;)V
    //   4802: ldc_w 387
    //   4805: invokevirtual 322	org/json/JSONObject:optString	(Ljava/lang/String;)Ljava/lang/String;
    //   4808: astore 18
    //   4810: iload 8
    //   4812: istore 4
    //   4814: iload 9
    //   4816: istore 5
    //   4818: iload 10
    //   4820: istore_3
    //   4821: aload 18
    //   4823: invokestatic 148	android/text/TextUtils:isEmpty	(Ljava/lang/CharSequence;)Z
    //   4826: istore 6
    //   4828: iload 6
    //   4830: ifne +171 -> 5001
    //   4833: iload 8
    //   4835: istore 4
    //   4837: iload 10
    //   4839: istore_3
    //   4840: aload_0
    //   4841: getfield 15	com/tencent/mobileqq/secspy/SecSpyFileManager$2:this$0	Lcom/tencent/mobileqq/secspy/SecSpyFileManager;
    //   4844: getfield 185	com/tencent/mobileqq/secspy/SecSpyFileManager:jdField_a_of_type_ComTencentMobileqqUnifiedebugUnifiedDebugManager	Lcom/tencent/mobileqq/unifiedebug/UnifiedDebugManager;
    //   4847: aload_0
    //   4848: getfield 15	com/tencent/mobileqq/secspy/SecSpyFileManager$2:this$0	Lcom/tencent/mobileqq/secspy/SecSpyFileManager;
    //   4851: getfield 188	com/tencent/mobileqq/secspy/SecSpyFileManager:jdField_a_of_type_ComTencentMobileqqAppQQAppInterface	Lcom/tencent/mobileqq/app/QQAppInterface;
    //   4854: invokevirtual 194	com/tencent/mobileqq/app/QQAppInterface:getApplication	()Lmqq/app/MobileQQ;
    //   4857: aload 18
    //   4859: invokevirtual 437	com/tencent/mobileqq/unifiedebug/UnifiedDebugManager:a	(Landroid/content/Context;Ljava/lang/String;)Ljava/lang/String;
    //   4862: astore 19
    //   4864: iload 8
    //   4866: istore 4
    //   4868: iload 10
    //   4870: istore_3
    //   4871: aload 19
    //   4873: invokestatic 148	android/text/TextUtils:isEmpty	(Ljava/lang/CharSequence;)Z
    //   4876: ifne +73 -> 4949
    //   4879: iload 8
    //   4881: istore 4
    //   4883: iload 10
    //   4885: istore_3
    //   4886: aload_0
    //   4887: getfield 15	com/tencent/mobileqq/secspy/SecSpyFileManager$2:this$0	Lcom/tencent/mobileqq/secspy/SecSpyFileManager;
    //   4890: aload 19
    //   4892: lload 13
    //   4894: aload 17
    //   4896: iconst_1
    //   4897: invokevirtual 313	com/tencent/mobileqq/secspy/SecSpyFileManager:a	(Ljava/lang/String;JLjava/lang/String;Z)V
    //   4900: iload 7
    //   4902: istore 6
    //   4904: goto -4524 -> 380
    //   4907: astore 17
    //   4909: iload 8
    //   4911: istore 4
    //   4913: iload 9
    //   4915: istore 5
    //   4917: iload 10
    //   4919: istore_3
    //   4920: aload_0
    //   4921: getfield 15	com/tencent/mobileqq/secspy/SecSpyFileManager$2:this$0	Lcom/tencent/mobileqq/secspy/SecSpyFileManager;
    //   4924: lload 13
    //   4926: iconst_m1
    //   4927: iconst_1
    //   4928: anewarray 4	java/lang/Object
    //   4931: dup
    //   4932: iconst_0
    //   4933: aload 17
    //   4935: invokevirtual 372	java/lang/Exception:getMessage	()Ljava/lang/String;
    //   4938: aastore
    //   4939: invokevirtual 113	com/tencent/mobileqq/secspy/SecSpyFileManager:a	(JI[Ljava/lang/Object;)V
    //   4942: iload 7
    //   4944: istore 6
    //   4946: goto -4566 -> 380
    //   4949: iload 8
    //   4951: istore 4
    //   4953: iload 10
    //   4955: istore_3
    //   4956: aload_0
    //   4957: getfield 15	com/tencent/mobileqq/secspy/SecSpyFileManager$2:this$0	Lcom/tencent/mobileqq/secspy/SecSpyFileManager;
    //   4960: lload 13
    //   4962: iconst_m1
    //   4963: iconst_1
    //   4964: anewarray 4	java/lang/Object
    //   4967: dup
    //   4968: iconst_0
    //   4969: new 79	java/lang/StringBuilder
    //   4972: dup
    //   4973: invokespecial 80	java/lang/StringBuilder:<init>	()V
    //   4976: ldc_w 439
    //   4979: invokevirtual 86	java/lang/StringBuilder:append	(Ljava/lang/String;)Ljava/lang/StringBuilder;
    //   4982: aload 18
    //   4984: invokevirtual 86	java/lang/StringBuilder:append	(Ljava/lang/String;)Ljava/lang/StringBuilder;
    //   4987: invokevirtual 102	java/lang/StringBuilder:toString	()Ljava/lang/String;
    //   4990: aastore
    //   4991: invokevirtual 113	com/tencent/mobileqq/secspy/SecSpyFileManager:a	(JI[Ljava/lang/Object;)V
    //   4994: iload 7
    //   4996: istore 6
    //   4998: goto -4618 -> 380
    //   5001: iload 8
    //   5003: istore 4
    //   5005: iload 9
    //   5007: istore 5
    //   5009: iload 10
    //   5011: istore_3
    //   5012: aload_0
    //   5013: getfield 15	com/tencent/mobileqq/secspy/SecSpyFileManager$2:this$0	Lcom/tencent/mobileqq/secspy/SecSpyFileManager;
    //   5016: lload 13
    //   5018: iconst_m1
    //   5019: iconst_1
    //   5020: anewarray 4	java/lang/Object
    //   5023: dup
    //   5024: iconst_0
    //   5025: ldc_w 426
    //   5028: aastore
    //   5029: invokevirtual 113	com/tencent/mobileqq/secspy/SecSpyFileManager:a	(JI[Ljava/lang/Object;)V
    //   5032: iload 7
    //   5034: istore 6
    //   5036: goto -4656 -> 380
    //   5039: iload 8
    //   5041: istore 4
    //   5043: iload 9
    //   5045: istore 5
    //   5047: iload 10
    //   5049: istore_3
    //   5050: new 211	org/json/JSONObject
    //   5053: dup
    //   5054: aload 18
    //   5056: invokespecial 215	org/json/JSONObject:<init>	(Ljava/lang/String;)V
    //   5059: astore 18
    //   5061: iload 8
    //   5063: istore 4
    //   5065: iload 9
    //   5067: istore 5
    //   5069: iload 10
    //   5071: istore_3
    //   5072: aload 18
    //   5074: ldc_w 387
    //   5077: invokevirtual 322	org/json/JSONObject:optString	(Ljava/lang/String;)Ljava/lang/String;
    //   5080: astore 17
    //   5082: iload 8
    //   5084: istore 4
    //   5086: iload 9
    //   5088: istore 5
    //   5090: iload 10
    //   5092: istore_3
    //   5093: aload 18
    //   5095: ldc_w 441
    //   5098: invokevirtual 340	org/json/JSONObject:optJSONArray	(Ljava/lang/String;)Lorg/json/JSONArray;
    //   5101: astore 18
    //   5103: iload 8
    //   5105: istore 4
    //   5107: iload 9
    //   5109: istore 5
    //   5111: iload 10
    //   5113: istore_3
    //   5114: aload 17
    //   5116: invokestatic 148	android/text/TextUtils:isEmpty	(Ljava/lang/CharSequence;)Z
    //   5119: ifne +169 -> 5288
    //   5122: aload 18
    //   5124: ifnull +126 -> 5250
    //   5127: iload 8
    //   5129: istore 4
    //   5131: iload 9
    //   5133: istore 5
    //   5135: iload 10
    //   5137: istore_3
    //   5138: aload_0
    //   5139: getfield 15	com/tencent/mobileqq/secspy/SecSpyFileManager$2:this$0	Lcom/tencent/mobileqq/secspy/SecSpyFileManager;
    //   5142: aload 18
    //   5144: invokevirtual 348	com/tencent/mobileqq/secspy/SecSpyFileManager:a	(Lorg/json/JSONArray;)Ljava/util/List;
    //   5147: astore 18
    //   5149: iload 8
    //   5151: istore 4
    //   5153: iload 10
    //   5155: istore_3
    //   5156: aload_0
    //   5157: getfield 15	com/tencent/mobileqq/secspy/SecSpyFileManager$2:this$0	Lcom/tencent/mobileqq/secspy/SecSpyFileManager;
    //   5160: getfield 185	com/tencent/mobileqq/secspy/SecSpyFileManager:jdField_a_of_type_ComTencentMobileqqUnifiedebugUnifiedDebugManager	Lcom/tencent/mobileqq/unifiedebug/UnifiedDebugManager;
    //   5163: aload_0
    //   5164: getfield 15	com/tencent/mobileqq/secspy/SecSpyFileManager$2:this$0	Lcom/tencent/mobileqq/secspy/SecSpyFileManager;
    //   5167: getfield 188	com/tencent/mobileqq/secspy/SecSpyFileManager:jdField_a_of_type_ComTencentMobileqqAppQQAppInterface	Lcom/tencent/mobileqq/app/QQAppInterface;
    //   5170: invokevirtual 194	com/tencent/mobileqq/app/QQAppInterface:getApplication	()Lmqq/app/MobileQQ;
    //   5173: aload 17
    //   5175: aload 18
    //   5177: invokevirtual 443	com/tencent/mobileqq/unifiedebug/UnifiedDebugManager:b	(Landroid/content/Context;Ljava/lang/String;Ljava/util/List;)V
    //   5180: iload 8
    //   5182: istore 4
    //   5184: iload 10
    //   5186: istore_3
    //   5187: aload_0
    //   5188: getfield 15	com/tencent/mobileqq/secspy/SecSpyFileManager$2:this$0	Lcom/tencent/mobileqq/secspy/SecSpyFileManager;
    //   5191: lload 13
    //   5193: iconst_0
    //   5194: iconst_0
    //   5195: anewarray 4	java/lang/Object
    //   5198: invokevirtual 113	com/tencent/mobileqq/secspy/SecSpyFileManager:a	(JI[Ljava/lang/Object;)V
    //   5201: iload 7
    //   5203: istore 6
    //   5205: goto -4825 -> 380
    //   5208: astore 17
    //   5210: iload 8
    //   5212: istore 4
    //   5214: iload 9
    //   5216: istore 5
    //   5218: iload 10
    //   5220: istore_3
    //   5221: aload_0
    //   5222: getfield 15	com/tencent/mobileqq/secspy/SecSpyFileManager$2:this$0	Lcom/tencent/mobileqq/secspy/SecSpyFileManager;
    //   5225: lload 13
    //   5227: iconst_m1
    //   5228: iconst_1
    //   5229: anewarray 4	java/lang/Object
    //   5232: dup
    //   5233: iconst_0
    //   5234: aload 17
    //   5236: invokevirtual 372	java/lang/Exception:getMessage	()Ljava/lang/String;
    //   5239: aastore
    //   5240: invokevirtual 113	com/tencent/mobileqq/secspy/SecSpyFileManager:a	(JI[Ljava/lang/Object;)V
    //   5243: iload 7
    //   5245: istore 6
    //   5247: goto -4867 -> 380
    //   5250: iload 8
    //   5252: istore 4
    //   5254: iload 9
    //   5256: istore 5
    //   5258: iload 10
    //   5260: istore_3
    //   5261: aload_0
    //   5262: getfield 15	com/tencent/mobileqq/secspy/SecSpyFileManager$2:this$0	Lcom/tencent/mobileqq/secspy/SecSpyFileManager;
    //   5265: lload 13
    //   5267: iconst_m1
    //   5268: iconst_1
    //   5269: anewarray 4	java/lang/Object
    //   5272: dup
    //   5273: iconst_0
    //   5274: ldc_w 445
    //   5277: aastore
    //   5278: invokevirtual 113	com/tencent/mobileqq/secspy/SecSpyFileManager:a	(JI[Ljava/lang/Object;)V
    //   5281: iload 7
    //   5283: istore 6
    //   5285: goto -4905 -> 380
    //   5288: iload 8
    //   5290: istore 4
    //   5292: iload 9
    //   5294: istore 5
    //   5296: iload 10
    //   5298: istore_3
    //   5299: aload_0
    //   5300: getfield 15	com/tencent/mobileqq/secspy/SecSpyFileManager$2:this$0	Lcom/tencent/mobileqq/secspy/SecSpyFileManager;
    //   5303: lload 13
    //   5305: iconst_m1
    //   5306: iconst_1
    //   5307: anewarray 4	java/lang/Object
    //   5310: dup
    //   5311: iconst_0
    //   5312: ldc_w 426
    //   5315: aastore
    //   5316: invokevirtual 113	com/tencent/mobileqq/secspy/SecSpyFileManager:a	(JI[Ljava/lang/Object;)V
    //   5319: iload 7
    //   5321: istore 6
    //   5323: goto -4943 -> 380
    //   5326: iload 8
    //   5328: istore 4
    //   5330: iload 9
    //   5332: istore 5
    //   5334: iload 10
    //   5336: istore_3
    //   5337: new 211	org/json/JSONObject
    //   5340: dup
    //   5341: aload 18
    //   5343: invokespecial 215	org/json/JSONObject:<init>	(Ljava/lang/String;)V
    //   5346: astore 19
    //   5348: iload 8
    //   5350: istore 4
    //   5352: iload 9
    //   5354: istore 5
    //   5356: iload 10
    //   5358: istore_3
    //   5359: aload 19
    //   5361: ldc_w 447
    //   5364: ldc2_w 448
    //   5367: invokevirtual 453	org/json/JSONObject:optLong	(Ljava/lang/String;J)J
    //   5370: lstore 11
    //   5372: iload 8
    //   5374: istore 4
    //   5376: iload 9
    //   5378: istore 5
    //   5380: iload 10
    //   5382: istore_3
    //   5383: aload 19
    //   5385: ldc_w 455
    //   5388: iconst_5
    //   5389: invokevirtual 459	org/json/JSONObject:optInt	(Ljava/lang/String;I)I
    //   5392: istore_2
    //   5393: lload 11
    //   5395: lconst_0
    //   5396: lcmp
    //   5397: ifle +48 -> 5445
    //   5400: iload 8
    //   5402: istore 4
    //   5404: iload 9
    //   5406: istore 5
    //   5408: iload 10
    //   5410: istore_3
    //   5411: aload_0
    //   5412: getfield 15	com/tencent/mobileqq/secspy/SecSpyFileManager$2:this$0	Lcom/tencent/mobileqq/secspy/SecSpyFileManager;
    //   5415: getfield 185	com/tencent/mobileqq/secspy/SecSpyFileManager:jdField_a_of_type_ComTencentMobileqqUnifiedebugUnifiedDebugManager	Lcom/tencent/mobileqq/unifiedebug/UnifiedDebugManager;
    //   5418: aload_0
    //   5419: getfield 15	com/tencent/mobileqq/secspy/SecSpyFileManager$2:this$0	Lcom/tencent/mobileqq/secspy/SecSpyFileManager;
    //   5422: getfield 188	com/tencent/mobileqq/secspy/SecSpyFileManager:jdField_a_of_type_ComTencentMobileqqAppQQAppInterface	Lcom/tencent/mobileqq/app/QQAppInterface;
    //   5425: invokevirtual 194	com/tencent/mobileqq/app/QQAppInterface:getApplication	()Lmqq/app/MobileQQ;
    //   5428: lload 11
    //   5430: lload 13
    //   5432: aload 17
    //   5434: iload_2
    //   5435: invokevirtual 462	com/tencent/mobileqq/unifiedebug/UnifiedDebugManager:a	(Landroid/content/Context;JJLjava/lang/String;I)V
    //   5438: iload 7
    //   5440: istore 6
    //   5442: goto -5062 -> 380
    //   5445: iload 8
    //   5447: istore 4
    //   5449: iload 9
    //   5451: istore 5
    //   5453: iload 10
    //   5455: istore_3
    //   5456: aload 19
    //   5458: ldc_w 464
    //   5461: invokevirtual 322	org/json/JSONObject:optString	(Ljava/lang/String;)Ljava/lang/String;
    //   5464: astore 18
    //   5466: iload 8
    //   5468: istore 4
    //   5470: iload 9
    //   5472: istore 5
    //   5474: iload 10
    //   5476: istore_3
    //   5477: aload 19
    //   5479: ldc_w 466
    //   5482: ldc2_w 448
    //   5485: invokevirtual 453	org/json/JSONObject:optLong	(Ljava/lang/String;J)J
    //   5488: lstore 11
    //   5490: iload 8
    //   5492: istore 4
    //   5494: iload 9
    //   5496: istore 5
    //   5498: iload 10
    //   5500: istore_3
    //   5501: aload 18
    //   5503: invokestatic 148	android/text/TextUtils:isEmpty	(Ljava/lang/CharSequence;)Z
    //   5506: ifne +159 -> 5665
    //   5509: iload 8
    //   5511: istore 4
    //   5513: iload 9
    //   5515: istore 5
    //   5517: iload 10
    //   5519: istore_3
    //   5520: aload 18
    //   5522: invokestatic 472	android/net/Uri:parse	(Ljava/lang/String;)Landroid/net/Uri;
    //   5525: astore 19
    //   5527: iload 8
    //   5529: istore 4
    //   5531: iload 9
    //   5533: istore 5
    //   5535: iload 10
    //   5537: istore_3
    //   5538: ldc_w 474
    //   5541: aload 19
    //   5543: invokevirtual 477	android/net/Uri:getScheme	()Ljava/lang/String;
    //   5546: invokevirtual 481	java/lang/String:equals	(Ljava/lang/Object;)Z
    //   5549: ifne +1420 -> 6969
    //   5552: iload 8
    //   5554: istore 4
    //   5556: iload 9
    //   5558: istore 5
    //   5560: iload 10
    //   5562: istore_3
    //   5563: ldc_w 483
    //   5566: aload 19
    //   5568: invokevirtual 477	android/net/Uri:getScheme	()Ljava/lang/String;
    //   5571: invokevirtual 481	java/lang/String:equals	(Ljava/lang/Object;)Z
    //   5574: ifeq +53 -> 5627
    //   5577: goto +1392 -> 6969
    //   5580: iload 8
    //   5582: istore 4
    //   5584: iload 9
    //   5586: istore 5
    //   5588: iload 10
    //   5590: istore_3
    //   5591: aload_0
    //   5592: getfield 15	com/tencent/mobileqq/secspy/SecSpyFileManager$2:this$0	Lcom/tencent/mobileqq/secspy/SecSpyFileManager;
    //   5595: getfield 185	com/tencent/mobileqq/secspy/SecSpyFileManager:jdField_a_of_type_ComTencentMobileqqUnifiedebugUnifiedDebugManager	Lcom/tencent/mobileqq/unifiedebug/UnifiedDebugManager;
    //   5598: aload_0
    //   5599: getfield 15	com/tencent/mobileqq/secspy/SecSpyFileManager$2:this$0	Lcom/tencent/mobileqq/secspy/SecSpyFileManager;
    //   5602: getfield 188	com/tencent/mobileqq/secspy/SecSpyFileManager:jdField_a_of_type_ComTencentMobileqqAppQQAppInterface	Lcom/tencent/mobileqq/app/QQAppInterface;
    //   5605: invokevirtual 194	com/tencent/mobileqq/app/QQAppInterface:getApplication	()Lmqq/app/MobileQQ;
    //   5608: aload 18
    //   5610: iload_2
    //   5611: lload 11
    //   5613: lload 13
    //   5615: aload 17
    //   5617: invokevirtual 486	com/tencent/mobileqq/unifiedebug/UnifiedDebugManager:a	(Landroid/content/Context;Ljava/lang/String;IJJLjava/lang/String;)V
    //   5620: iload 7
    //   5622: istore 6
    //   5624: goto -5244 -> 380
    //   5627: iload 8
    //   5629: istore 4
    //   5631: iload 9
    //   5633: istore 5
    //   5635: iload 10
    //   5637: istore_3
    //   5638: aload_0
    //   5639: getfield 15	com/tencent/mobileqq/secspy/SecSpyFileManager$2:this$0	Lcom/tencent/mobileqq/secspy/SecSpyFileManager;
    //   5642: lload 13
    //   5644: iconst_m1
    //   5645: iconst_1
    //   5646: anewarray 4	java/lang/Object
    //   5649: dup
    //   5650: iconst_0
    //   5651: ldc_w 488
    //   5654: aastore
    //   5655: invokevirtual 113	com/tencent/mobileqq/secspy/SecSpyFileManager:a	(JI[Ljava/lang/Object;)V
    //   5658: iload 7
    //   5660: istore 6
    //   5662: goto -5282 -> 380
    //   5665: iload 8
    //   5667: istore 4
    //   5669: iload 9
    //   5671: istore 5
    //   5673: iload 10
    //   5675: istore_3
    //   5676: aload_0
    //   5677: getfield 15	com/tencent/mobileqq/secspy/SecSpyFileManager$2:this$0	Lcom/tencent/mobileqq/secspy/SecSpyFileManager;
    //   5680: lload 13
    //   5682: iconst_m1
    //   5683: iconst_1
    //   5684: anewarray 4	java/lang/Object
    //   5687: dup
    //   5688: iconst_0
    //   5689: ldc_w 490
    //   5692: aastore
    //   5693: invokevirtual 113	com/tencent/mobileqq/secspy/SecSpyFileManager:a	(JI[Ljava/lang/Object;)V
    //   5696: iload 7
    //   5698: istore 6
    //   5700: goto -5320 -> 380
    //   5703: iload 8
    //   5705: istore 4
    //   5707: iload 9
    //   5709: istore 5
    //   5711: iload 10
    //   5713: istore_3
    //   5714: aload_0
    //   5715: getfield 15	com/tencent/mobileqq/secspy/SecSpyFileManager$2:this$0	Lcom/tencent/mobileqq/secspy/SecSpyFileManager;
    //   5718: getfield 188	com/tencent/mobileqq/secspy/SecSpyFileManager:jdField_a_of_type_ComTencentMobileqqAppQQAppInterface	Lcom/tencent/mobileqq/app/QQAppInterface;
    //   5721: invokevirtual 194	com/tencent/mobileqq/app/QQAppInterface:getApplication	()Lmqq/app/MobileQQ;
    //   5724: invokestatic 266	com/tencent/smtt/sdk/QbSdk:getTbsVersion	(Landroid/content/Context;)I
    //   5727: ifgt +41 -> 5768
    //   5730: iload 8
    //   5732: istore 4
    //   5734: iload 9
    //   5736: istore 5
    //   5738: iload 10
    //   5740: istore_3
    //   5741: aload_0
    //   5742: getfield 15	com/tencent/mobileqq/secspy/SecSpyFileManager$2:this$0	Lcom/tencent/mobileqq/secspy/SecSpyFileManager;
    //   5745: lload 13
    //   5747: iconst_m1
    //   5748: iconst_1
    //   5749: anewarray 4	java/lang/Object
    //   5752: dup
    //   5753: iconst_0
    //   5754: ldc_w 492
    //   5757: aastore
    //   5758: invokevirtual 113	com/tencent/mobileqq/secspy/SecSpyFileManager:a	(JI[Ljava/lang/Object;)V
    //   5761: iload 7
    //   5763: istore 6
    //   5765: goto -5385 -> 380
    //   5768: iload 8
    //   5770: istore 4
    //   5772: iload 9
    //   5774: istore 5
    //   5776: iload 10
    //   5778: istore_3
    //   5779: new 211	org/json/JSONObject
    //   5782: dup
    //   5783: aload 18
    //   5785: invokespecial 215	org/json/JSONObject:<init>	(Ljava/lang/String;)V
    //   5788: astore 18
    //   5790: iload 8
    //   5792: istore 4
    //   5794: iload 9
    //   5796: istore 5
    //   5798: iload 10
    //   5800: istore_3
    //   5801: aload 18
    //   5803: ldc_w 387
    //   5806: invokevirtual 495	org/json/JSONObject:getString	(Ljava/lang/String;)Ljava/lang/String;
    //   5809: astore 19
    //   5811: iload 8
    //   5813: istore 4
    //   5815: iload 9
    //   5817: istore 5
    //   5819: iload 10
    //   5821: istore_3
    //   5822: aload 19
    //   5824: invokestatic 148	android/text/TextUtils:isEmpty	(Ljava/lang/CharSequence;)Z
    //   5827: ifne +529 -> 6356
    //   5830: iload 8
    //   5832: istore 4
    //   5834: iload 9
    //   5836: istore 5
    //   5838: iload 10
    //   5840: istore_3
    //   5841: aload 18
    //   5843: ldc_w 497
    //   5846: invokevirtual 501	org/json/JSONObject:getInt	(Ljava/lang/String;)I
    //   5849: istore_2
    //   5850: iload 8
    //   5852: istore 4
    //   5854: iload 9
    //   5856: istore 5
    //   5858: iload 10
    //   5860: istore_3
    //   5861: aload_0
    //   5862: getfield 15	com/tencent/mobileqq/secspy/SecSpyFileManager$2:this$0	Lcom/tencent/mobileqq/secspy/SecSpyFileManager;
    //   5865: getfield 188	com/tencent/mobileqq/secspy/SecSpyFileManager:jdField_a_of_type_ComTencentMobileqqAppQQAppInterface	Lcom/tencent/mobileqq/app/QQAppInterface;
    //   5868: invokevirtual 194	com/tencent/mobileqq/app/QQAppInterface:getApplication	()Lmqq/app/MobileQQ;
    //   5871: invokestatic 504	com/tencent/mobileqq/unifiedebug/UnifiedDebugManager:a	(Landroid/content/Context;)Z
    //   5874: ifne +50 -> 5924
    //   5877: iload 8
    //   5879: istore 4
    //   5881: iload 9
    //   5883: istore 5
    //   5885: iload 10
    //   5887: istore_3
    //   5888: aload_0
    //   5889: getfield 15	com/tencent/mobileqq/secspy/SecSpyFileManager$2:this$0	Lcom/tencent/mobileqq/secspy/SecSpyFileManager;
    //   5892: getfield 185	com/tencent/mobileqq/secspy/SecSpyFileManager:jdField_a_of_type_ComTencentMobileqqUnifiedebugUnifiedDebugManager	Lcom/tencent/mobileqq/unifiedebug/UnifiedDebugManager;
    //   5895: astore 20
    //   5897: iload 8
    //   5899: istore 4
    //   5901: iload 9
    //   5903: istore 5
    //   5905: iload 10
    //   5907: istore_3
    //   5908: aload_0
    //   5909: getfield 15	com/tencent/mobileqq/secspy/SecSpyFileManager$2:this$0	Lcom/tencent/mobileqq/secspy/SecSpyFileManager;
    //   5912: getfield 188	com/tencent/mobileqq/secspy/SecSpyFileManager:jdField_a_of_type_ComTencentMobileqqAppQQAppInterface	Lcom/tencent/mobileqq/app/QQAppInterface;
    //   5915: invokevirtual 194	com/tencent/mobileqq/app/QQAppInterface:getApplication	()Lmqq/app/MobileQQ;
    //   5918: aload 19
    //   5920: iload_2
    //   5921: invokestatic 507	com/tencent/mobileqq/unifiedebug/UnifiedDebugManager:a	(Landroid/app/Application;Ljava/lang/String;I)V
    //   5924: iload 8
    //   5926: istore 4
    //   5928: iload 9
    //   5930: istore 5
    //   5932: iload 10
    //   5934: istore_3
    //   5935: aload_0
    //   5936: getfield 15	com/tencent/mobileqq/secspy/SecSpyFileManager$2:this$0	Lcom/tencent/mobileqq/secspy/SecSpyFileManager;
    //   5939: getfield 185	com/tencent/mobileqq/secspy/SecSpyFileManager:jdField_a_of_type_ComTencentMobileqqUnifiedebugUnifiedDebugManager	Lcom/tencent/mobileqq/unifiedebug/UnifiedDebugManager;
    //   5942: invokevirtual 510	com/tencent/mobileqq/unifiedebug/UnifiedDebugManager:a	()Landroid/os/Handler;
    //   5945: aload_0
    //   5946: getfield 15	com/tencent/mobileqq/secspy/SecSpyFileManager$2:this$0	Lcom/tencent/mobileqq/secspy/SecSpyFileManager;
    //   5949: invokestatic 513	com/tencent/mobileqq/secspy/SecSpyFileManager:a	(Lcom/tencent/mobileqq/secspy/SecSpyFileManager;)Ljava/lang/Runnable;
    //   5952: invokevirtual 519	android/os/Handler:removeCallbacks	(Ljava/lang/Runnable;)V
    //   5955: iload 8
    //   5957: istore 4
    //   5959: iload 9
    //   5961: istore 5
    //   5963: iload 10
    //   5965: istore_3
    //   5966: aload 18
    //   5968: ldc_w 521
    //   5971: invokevirtual 229	org/json/JSONObject:getLong	(Ljava/lang/String;)J
    //   5974: lstore 11
    //   5976: iload 8
    //   5978: istore 4
    //   5980: iload 9
    //   5982: istore 5
    //   5984: iload 10
    //   5986: istore_3
    //   5987: aload_0
    //   5988: getfield 15	com/tencent/mobileqq/secspy/SecSpyFileManager$2:this$0	Lcom/tencent/mobileqq/secspy/SecSpyFileManager;
    //   5991: getfield 185	com/tencent/mobileqq/secspy/SecSpyFileManager:jdField_a_of_type_ComTencentMobileqqUnifiedebugUnifiedDebugManager	Lcom/tencent/mobileqq/unifiedebug/UnifiedDebugManager;
    //   5994: invokevirtual 510	com/tencent/mobileqq/unifiedebug/UnifiedDebugManager:a	()Landroid/os/Handler;
    //   5997: aload_0
    //   5998: getfield 15	com/tencent/mobileqq/secspy/SecSpyFileManager$2:this$0	Lcom/tencent/mobileqq/secspy/SecSpyFileManager;
    //   6001: invokestatic 513	com/tencent/mobileqq/secspy/SecSpyFileManager:a	(Lcom/tencent/mobileqq/secspy/SecSpyFileManager;)Ljava/lang/Runnable;
    //   6004: lload 11
    //   6006: ldc2_w 119
    //   6009: lmul
    //   6010: invokevirtual 525	android/os/Handler:postDelayed	(Ljava/lang/Runnable;J)Z
    //   6013: pop
    //   6014: iload 8
    //   6016: istore 4
    //   6018: iload 9
    //   6020: istore 5
    //   6022: iload 10
    //   6024: istore_3
    //   6025: aload 18
    //   6027: ldc_w 464
    //   6030: invokevirtual 528	org/json/JSONObject:has	(Ljava/lang/String;)Z
    //   6033: ifeq +291 -> 6324
    //   6036: iload 8
    //   6038: istore 4
    //   6040: iload 9
    //   6042: istore 5
    //   6044: iload 10
    //   6046: istore_3
    //   6047: aload 18
    //   6049: ldc_w 464
    //   6052: invokevirtual 322	org/json/JSONObject:optString	(Ljava/lang/String;)Ljava/lang/String;
    //   6055: astore 19
    //   6057: iload 8
    //   6059: istore 4
    //   6061: iload 9
    //   6063: istore 5
    //   6065: iload 10
    //   6067: istore_3
    //   6068: aload 19
    //   6070: invokestatic 148	android/text/TextUtils:isEmpty	(Ljava/lang/CharSequence;)Z
    //   6073: ifne +213 -> 6286
    //   6076: iload 8
    //   6078: istore 4
    //   6080: iload 9
    //   6082: istore 5
    //   6084: iload 10
    //   6086: istore_3
    //   6087: aload 19
    //   6089: invokestatic 472	android/net/Uri:parse	(Ljava/lang/String;)Landroid/net/Uri;
    //   6092: astore 20
    //   6094: iload 8
    //   6096: istore 4
    //   6098: iload 9
    //   6100: istore 5
    //   6102: iload 10
    //   6104: istore_3
    //   6105: ldc_w 474
    //   6108: aload 20
    //   6110: invokevirtual 477	android/net/Uri:getScheme	()Ljava/lang/String;
    //   6113: invokevirtual 481	java/lang/String:equals	(Ljava/lang/Object;)Z
    //   6116: ifne +28 -> 6144
    //   6119: iload 8
    //   6121: istore 4
    //   6123: iload 9
    //   6125: istore 5
    //   6127: iload 10
    //   6129: istore_3
    //   6130: ldc_w 483
    //   6133: aload 20
    //   6135: invokevirtual 477	android/net/Uri:getScheme	()Ljava/lang/String;
    //   6138: invokevirtual 481	java/lang/String:equals	(Ljava/lang/Object;)Z
    //   6141: ifeq +107 -> 6248
    //   6144: iload 8
    //   6146: istore 4
    //   6148: iload 9
    //   6150: istore 5
    //   6152: iload 10
    //   6154: istore_3
    //   6155: aload 18
    //   6157: ldc_w 530
    //   6160: ldc2_w 448
    //   6163: invokevirtual 453	org/json/JSONObject:optLong	(Ljava/lang/String;J)J
    //   6166: lstore 11
    //   6168: lload 11
    //   6170: lconst_0
    //   6171: lcmp
    //   6172: ifgt +823 -> 6995
    //   6175: ldc2_w 531
    //   6178: lstore 11
    //   6180: iload 8
    //   6182: istore 4
    //   6184: iload 9
    //   6186: istore 5
    //   6188: iload 10
    //   6190: istore_3
    //   6191: aload 18
    //   6193: ldc_w 455
    //   6196: iconst_5
    //   6197: invokevirtual 459	org/json/JSONObject:optInt	(Ljava/lang/String;I)I
    //   6200: istore_2
    //   6201: iload 8
    //   6203: istore 4
    //   6205: iload 9
    //   6207: istore 5
    //   6209: iload 10
    //   6211: istore_3
    //   6212: aload_0
    //   6213: getfield 15	com/tencent/mobileqq/secspy/SecSpyFileManager$2:this$0	Lcom/tencent/mobileqq/secspy/SecSpyFileManager;
    //   6216: getfield 185	com/tencent/mobileqq/secspy/SecSpyFileManager:jdField_a_of_type_ComTencentMobileqqUnifiedebugUnifiedDebugManager	Lcom/tencent/mobileqq/unifiedebug/UnifiedDebugManager;
    //   6219: aload_0
    //   6220: getfield 15	com/tencent/mobileqq/secspy/SecSpyFileManager$2:this$0	Lcom/tencent/mobileqq/secspy/SecSpyFileManager;
    //   6223: getfield 188	com/tencent/mobileqq/secspy/SecSpyFileManager:jdField_a_of_type_ComTencentMobileqqAppQQAppInterface	Lcom/tencent/mobileqq/app/QQAppInterface;
    //   6226: invokevirtual 194	com/tencent/mobileqq/app/QQAppInterface:getApplication	()Lmqq/app/MobileQQ;
    //   6229: aload 19
    //   6231: iload_2
    //   6232: lload 11
    //   6234: lload 13
    //   6236: aload 17
    //   6238: invokevirtual 535	com/tencent/mobileqq/unifiedebug/UnifiedDebugManager:c	(Landroid/content/Context;Ljava/lang/String;IJJLjava/lang/String;)V
    //   6241: iload 7
    //   6243: istore 6
    //   6245: goto -5865 -> 380
    //   6248: iload 8
    //   6250: istore 4
    //   6252: iload 9
    //   6254: istore 5
    //   6256: iload 10
    //   6258: istore_3
    //   6259: aload_0
    //   6260: getfield 15	com/tencent/mobileqq/secspy/SecSpyFileManager$2:this$0	Lcom/tencent/mobileqq/secspy/SecSpyFileManager;
    //   6263: lload 13
    //   6265: iconst_m1
    //   6266: iconst_1
    //   6267: anewarray 4	java/lang/Object
    //   6270: dup
    //   6271: iconst_0
    //   6272: ldc_w 488
    //   6275: aastore
    //   6276: invokevirtual 113	com/tencent/mobileqq/secspy/SecSpyFileManager:a	(JI[Ljava/lang/Object;)V
    //   6279: iload 7
    //   6281: istore 6
    //   6283: goto -5903 -> 380
    //   6286: iload 8
    //   6288: istore 4
    //   6290: iload 9
    //   6292: istore 5
    //   6294: iload 10
    //   6296: istore_3
    //   6297: aload_0
    //   6298: getfield 15	com/tencent/mobileqq/secspy/SecSpyFileManager$2:this$0	Lcom/tencent/mobileqq/secspy/SecSpyFileManager;
    //   6301: lload 13
    //   6303: iconst_m1
    //   6304: iconst_1
    //   6305: anewarray 4	java/lang/Object
    //   6308: dup
    //   6309: iconst_0
    //   6310: ldc_w 490
    //   6313: aastore
    //   6314: invokevirtual 113	com/tencent/mobileqq/secspy/SecSpyFileManager:a	(JI[Ljava/lang/Object;)V
    //   6317: iload 7
    //   6319: istore 6
    //   6321: goto -5941 -> 380
    //   6324: iload 8
    //   6326: istore 4
    //   6328: iload 9
    //   6330: istore 5
    //   6332: iload 10
    //   6334: istore_3
    //   6335: aload_0
    //   6336: getfield 15	com/tencent/mobileqq/secspy/SecSpyFileManager$2:this$0	Lcom/tencent/mobileqq/secspy/SecSpyFileManager;
    //   6339: lload 13
    //   6341: iconst_0
    //   6342: iconst_0
    //   6343: anewarray 4	java/lang/Object
    //   6346: invokevirtual 113	com/tencent/mobileqq/secspy/SecSpyFileManager:a	(JI[Ljava/lang/Object;)V
    //   6349: iload 7
    //   6351: istore 6
    //   6353: goto -5973 -> 380
    //   6356: iload 8
    //   6358: istore 4
    //   6360: iload 9
    //   6362: istore 5
    //   6364: iload 10
    //   6366: istore_3
    //   6367: aload_0
    //   6368: getfield 15	com/tencent/mobileqq/secspy/SecSpyFileManager$2:this$0	Lcom/tencent/mobileqq/secspy/SecSpyFileManager;
    //   6371: lload 13
    //   6373: iconst_m1
    //   6374: iconst_1
    //   6375: anewarray 4	java/lang/Object
    //   6378: dup
    //   6379: iconst_0
    //   6380: ldc_w 426
    //   6383: aastore
    //   6384: invokevirtual 113	com/tencent/mobileqq/secspy/SecSpyFileManager:a	(JI[Ljava/lang/Object;)V
    //   6387: iload 7
    //   6389: istore 6
    //   6391: goto -6011 -> 380
    //   6394: iload 8
    //   6396: istore 4
    //   6398: iload 9
    //   6400: istore 5
    //   6402: iload 10
    //   6404: istore_3
    //   6405: aload_0
    //   6406: getfield 15	com/tencent/mobileqq/secspy/SecSpyFileManager$2:this$0	Lcom/tencent/mobileqq/secspy/SecSpyFileManager;
    //   6409: getfield 188	com/tencent/mobileqq/secspy/SecSpyFileManager:jdField_a_of_type_ComTencentMobileqqAppQQAppInterface	Lcom/tencent/mobileqq/app/QQAppInterface;
    //   6412: invokevirtual 194	com/tencent/mobileqq/app/QQAppInterface:getApplication	()Lmqq/app/MobileQQ;
    //   6415: invokestatic 538	com/tencent/mobileqq/unifiedebug/UnifiedDebugManager:a	(Landroid/app/Application;)V
    //   6418: iload 8
    //   6420: istore 4
    //   6422: iload 9
    //   6424: istore 5
    //   6426: iload 10
    //   6428: istore_3
    //   6429: aload_0
    //   6430: getfield 15	com/tencent/mobileqq/secspy/SecSpyFileManager$2:this$0	Lcom/tencent/mobileqq/secspy/SecSpyFileManager;
    //   6433: getfield 185	com/tencent/mobileqq/secspy/SecSpyFileManager:jdField_a_of_type_ComTencentMobileqqUnifiedebugUnifiedDebugManager	Lcom/tencent/mobileqq/unifiedebug/UnifiedDebugManager;
    //   6436: invokevirtual 510	com/tencent/mobileqq/unifiedebug/UnifiedDebugManager:a	()Landroid/os/Handler;
    //   6439: aload_0
    //   6440: getfield 15	com/tencent/mobileqq/secspy/SecSpyFileManager$2:this$0	Lcom/tencent/mobileqq/secspy/SecSpyFileManager;
    //   6443: invokestatic 513	com/tencent/mobileqq/secspy/SecSpyFileManager:a	(Lcom/tencent/mobileqq/secspy/SecSpyFileManager;)Ljava/lang/Runnable;
    //   6446: invokevirtual 519	android/os/Handler:removeCallbacks	(Ljava/lang/Runnable;)V
    //   6449: iload 8
    //   6451: istore 4
    //   6453: iload 9
    //   6455: istore 5
    //   6457: iload 10
    //   6459: istore_3
    //   6460: aload_0
    //   6461: getfield 15	com/tencent/mobileqq/secspy/SecSpyFileManager$2:this$0	Lcom/tencent/mobileqq/secspy/SecSpyFileManager;
    //   6464: lload 13
    //   6466: iconst_0
    //   6467: iconst_0
    //   6468: anewarray 4	java/lang/Object
    //   6471: invokevirtual 113	com/tencent/mobileqq/secspy/SecSpyFileManager:a	(JI[Ljava/lang/Object;)V
    //   6474: iload 7
    //   6476: istore 6
    //   6478: goto -6098 -> 380
    //   6481: iload 8
    //   6483: istore 4
    //   6485: iload 9
    //   6487: istore 5
    //   6489: iload 10
    //   6491: istore_3
    //   6492: new 211	org/json/JSONObject
    //   6495: dup
    //   6496: aload 18
    //   6498: invokespecial 215	org/json/JSONObject:<init>	(Ljava/lang/String;)V
    //   6501: ldc_w 464
    //   6504: invokevirtual 495	org/json/JSONObject:getString	(Ljava/lang/String;)Ljava/lang/String;
    //   6507: astore 17
    //   6509: iload 8
    //   6511: istore 4
    //   6513: iload 9
    //   6515: istore 5
    //   6517: iload 10
    //   6519: istore_3
    //   6520: aload 17
    //   6522: invokestatic 148	android/text/TextUtils:isEmpty	(Ljava/lang/CharSequence;)Z
    //   6525: istore 6
    //   6527: iload 6
    //   6529: ifne +91 -> 6620
    //   6532: iload 8
    //   6534: istore 4
    //   6536: iload 9
    //   6538: istore 5
    //   6540: iload 10
    //   6542: istore_3
    //   6543: aload_0
    //   6544: getfield 15	com/tencent/mobileqq/secspy/SecSpyFileManager$2:this$0	Lcom/tencent/mobileqq/secspy/SecSpyFileManager;
    //   6547: getfield 185	com/tencent/mobileqq/secspy/SecSpyFileManager:jdField_a_of_type_ComTencentMobileqqUnifiedebugUnifiedDebugManager	Lcom/tencent/mobileqq/unifiedebug/UnifiedDebugManager;
    //   6550: aload_0
    //   6551: getfield 15	com/tencent/mobileqq/secspy/SecSpyFileManager$2:this$0	Lcom/tencent/mobileqq/secspy/SecSpyFileManager;
    //   6554: getfield 188	com/tencent/mobileqq/secspy/SecSpyFileManager:jdField_a_of_type_ComTencentMobileqqAppQQAppInterface	Lcom/tencent/mobileqq/app/QQAppInterface;
    //   6557: lload 13
    //   6559: aload 17
    //   6561: aload_0
    //   6562: getfield 15	com/tencent/mobileqq/secspy/SecSpyFileManager$2:this$0	Lcom/tencent/mobileqq/secspy/SecSpyFileManager;
    //   6565: getfield 285	com/tencent/mobileqq/secspy/SecSpyFileManager:jdField_a_of_type_AndroidOsHandler	Landroid/os/Handler;
    //   6568: invokevirtual 541	com/tencent/mobileqq/unifiedebug/UnifiedDebugManager:a	(Lcom/tencent/mobileqq/app/QQAppInterface;JLjava/lang/String;Landroid/os/Handler;)V
    //   6571: iload 7
    //   6573: istore 6
    //   6575: goto -6195 -> 380
    //   6578: astore 17
    //   6580: iload 8
    //   6582: istore 4
    //   6584: iload 9
    //   6586: istore 5
    //   6588: iload 10
    //   6590: istore_3
    //   6591: aload_0
    //   6592: getfield 15	com/tencent/mobileqq/secspy/SecSpyFileManager$2:this$0	Lcom/tencent/mobileqq/secspy/SecSpyFileManager;
    //   6595: lload 13
    //   6597: iconst_m1
    //   6598: iconst_1
    //   6599: anewarray 4	java/lang/Object
    //   6602: dup
    //   6603: iconst_0
    //   6604: aload 17
    //   6606: invokevirtual 542	java/io/IOException:getMessage	()Ljava/lang/String;
    //   6609: aastore
    //   6610: invokevirtual 113	com/tencent/mobileqq/secspy/SecSpyFileManager:a	(JI[Ljava/lang/Object;)V
    //   6613: iload 7
    //   6615: istore 6
    //   6617: goto -6237 -> 380
    //   6620: iload 8
    //   6622: istore 4
    //   6624: iload 9
    //   6626: istore 5
    //   6628: iload 10
    //   6630: istore_3
    //   6631: aload_0
    //   6632: getfield 15	com/tencent/mobileqq/secspy/SecSpyFileManager$2:this$0	Lcom/tencent/mobileqq/secspy/SecSpyFileManager;
    //   6635: lload 13
    //   6637: iconst_m1
    //   6638: iconst_1
    //   6639: anewarray 4	java/lang/Object
    //   6642: dup
    //   6643: iconst_0
    //   6644: ldc_w 426
    //   6647: aastore
    //   6648: invokevirtual 113	com/tencent/mobileqq/secspy/SecSpyFileManager:a	(JI[Ljava/lang/Object;)V
    //   6651: iload 7
    //   6653: istore 6
    //   6655: goto -6275 -> 380
    //   6658: iload 8
    //   6660: istore 4
    //   6662: iload 9
    //   6664: istore 5
    //   6666: iload 10
    //   6668: istore_3
    //   6669: new 211	org/json/JSONObject
    //   6672: dup
    //   6673: aload 18
    //   6675: invokespecial 215	org/json/JSONObject:<init>	(Ljava/lang/String;)V
    //   6678: ldc_w 464
    //   6681: invokevirtual 322	org/json/JSONObject:optString	(Ljava/lang/String;)Ljava/lang/String;
    //   6684: astore 18
    //   6686: iload 8
    //   6688: istore 4
    //   6690: iload 9
    //   6692: istore 5
    //   6694: iload 10
    //   6696: istore_3
    //   6697: aload 18
    //   6699: invokestatic 148	android/text/TextUtils:isEmpty	(Ljava/lang/CharSequence;)Z
    //   6702: istore 6
    //   6704: iload 6
    //   6706: ifne +103 -> 6809
    //   6709: iload 8
    //   6711: istore 4
    //   6713: iload 10
    //   6715: istore_3
    //   6716: aload_0
    //   6717: getfield 15	com/tencent/mobileqq/secspy/SecSpyFileManager$2:this$0	Lcom/tencent/mobileqq/secspy/SecSpyFileManager;
    //   6720: getfield 185	com/tencent/mobileqq/secspy/SecSpyFileManager:jdField_a_of_type_ComTencentMobileqqUnifiedebugUnifiedDebugManager	Lcom/tencent/mobileqq/unifiedebug/UnifiedDebugManager;
    //   6723: aload_0
    //   6724: getfield 15	com/tencent/mobileqq/secspy/SecSpyFileManager$2:this$0	Lcom/tencent/mobileqq/secspy/SecSpyFileManager;
    //   6727: getfield 188	com/tencent/mobileqq/secspy/SecSpyFileManager:jdField_a_of_type_ComTencentMobileqqAppQQAppInterface	Lcom/tencent/mobileqq/app/QQAppInterface;
    //   6730: lload 13
    //   6732: aload 18
    //   6734: invokevirtual 545	com/tencent/mobileqq/unifiedebug/UnifiedDebugManager:a	(Lcom/tencent/mobileqq/app/QQAppInterface;JLjava/lang/String;)Ljava/lang/String;
    //   6737: astore 18
    //   6739: iload 8
    //   6741: istore 4
    //   6743: iload 10
    //   6745: istore_3
    //   6746: aload_0
    //   6747: getfield 15	com/tencent/mobileqq/secspy/SecSpyFileManager$2:this$0	Lcom/tencent/mobileqq/secspy/SecSpyFileManager;
    //   6750: aload 18
    //   6752: lload 13
    //   6754: aload 17
    //   6756: iconst_1
    //   6757: invokevirtual 313	com/tencent/mobileqq/secspy/SecSpyFileManager:a	(Ljava/lang/String;JLjava/lang/String;Z)V
    //   6760: iload 7
    //   6762: istore 6
    //   6764: goto -6384 -> 380
    //   6767: astore 17
    //   6769: iload 8
    //   6771: istore 4
    //   6773: iload 9
    //   6775: istore 5
    //   6777: iload 10
    //   6779: istore_3
    //   6780: aload_0
    //   6781: getfield 15	com/tencent/mobileqq/secspy/SecSpyFileManager$2:this$0	Lcom/tencent/mobileqq/secspy/SecSpyFileManager;
    //   6784: lload 13
    //   6786: iconst_m1
    //   6787: iconst_1
    //   6788: anewarray 4	java/lang/Object
    //   6791: dup
    //   6792: iconst_0
    //   6793: aload 17
    //   6795: invokevirtual 372	java/lang/Exception:getMessage	()Ljava/lang/String;
    //   6798: aastore
    //   6799: invokevirtual 113	com/tencent/mobileqq/secspy/SecSpyFileManager:a	(JI[Ljava/lang/Object;)V
    //   6802: iload 7
    //   6804: istore 6
    //   6806: goto -6426 -> 380
    //   6809: iload 8
    //   6811: istore 4
    //   6813: iload 9
    //   6815: istore 5
    //   6817: iload 10
    //   6819: istore_3
    //   6820: aload_0
    //   6821: getfield 15	com/tencent/mobileqq/secspy/SecSpyFileManager$2:this$0	Lcom/tencent/mobileqq/secspy/SecSpyFileManager;
    //   6824: lload 13
    //   6826: iconst_m1
    //   6827: iconst_1
    //   6828: anewarray 4	java/lang/Object
    //   6831: dup
    //   6832: iconst_0
    //   6833: ldc_w 426
    //   6836: aastore
    //   6837: invokevirtual 113	com/tencent/mobileqq/secspy/SecSpyFileManager:a	(JI[Ljava/lang/Object;)V
    //   6840: iload 7
    //   6842: istore 6
    //   6844: goto -6464 -> 380
    //   6847: iload 8
    //   6849: istore 4
    //   6851: iload 9
    //   6853: istore 5
    //   6855: iload 10
    //   6857: istore_3
    //   6858: aconst_null
    //   6859: aload_0
    //   6860: getfield 15	com/tencent/mobileqq/secspy/SecSpyFileManager$2:this$0	Lcom/tencent/mobileqq/secspy/SecSpyFileManager;
    //   6863: getfield 188	com/tencent/mobileqq/secspy/SecSpyFileManager:jdField_a_of_type_ComTencentMobileqqAppQQAppInterface	Lcom/tencent/mobileqq/app/QQAppInterface;
    //   6866: invokestatic 550	com/tencent/mobileqq/activity/QQSettingMsgHistoryActivity:a	(Landroid/app/Activity;Lcom/tencent/mobileqq/app/QQAppInterface;)V
    //   6869: iload 8
    //   6871: istore 4
    //   6873: iload 9
    //   6875: istore 5
    //   6877: iload 10
    //   6879: istore_3
    //   6880: aload_0
    //   6881: getfield 15	com/tencent/mobileqq/secspy/SecSpyFileManager$2:this$0	Lcom/tencent/mobileqq/secspy/SecSpyFileManager;
    //   6884: lload 13
    //   6886: iconst_0
    //   6887: iconst_0
    //   6888: anewarray 4	java/lang/Object
    //   6891: invokevirtual 113	com/tencent/mobileqq/secspy/SecSpyFileManager:a	(JI[Ljava/lang/Object;)V
    //   6894: iload 7
    //   6896: istore 6
    //   6898: goto -6518 -> 380
    //   6901: astore 17
    //   6903: aload 17
    //   6905: invokevirtual 553	java/lang/InterruptedException:printStackTrace	()V
    //   6908: goto -6468 -> 440
    //   6911: astore 17
    //   6913: aload 17
    //   6915: invokevirtual 553	java/lang/InterruptedException:printStackTrace	()V
    //   6918: goto -6276 -> 642
    //   6921: astore 17
    //   6923: aload 17
    //   6925: invokevirtual 553	java/lang/InterruptedException:printStackTrace	()V
    //   6928: goto -6091 -> 837
    //   6931: astore 18
    //   6933: aload 18
    //   6935: invokevirtual 553	java/lang/InterruptedException:printStackTrace	()V
    //   6938: goto -5449 -> 1489
    //   6941: astore 17
    //   6943: iconst_1
    //   6944: istore_3
    //   6945: goto -5515 -> 1430
    //   6948: astore 17
    //   6950: iconst_1
    //   6951: istore 5
    //   6953: goto -6198 -> 755
    //   6956: astore 17
    //   6958: iconst_1
    //   6959: istore 4
    //   6961: goto -6401 -> 560
    //   6964: iconst_0
    //   6965: istore_3
    //   6966: goto -5898 -> 1068
    //   6969: lload 11
    //   6971: lconst_0
    //   6972: lcmp
    //   6973: ifgt +11 -> 6984
    //   6976: ldc2_w 531
    //   6979: lstore 11
    //   6981: goto -1401 -> 5580
    //   6984: lload 11
    //   6986: ldc2_w 119
    //   6989: lmul
    //   6990: lstore 11
    //   6992: goto -1412 -> 5580
    //   6995: ldc2_w 119
    //   6998: lload 11
    //   7000: lmul
    //   7001: lstore 11
    //   7003: goto -823 -> 6180
    // Local variable table:
    //   start	length	slot	name	signature
    //   0	7006	0	this	2
    //   22	1412	1	i	int
    //   5392	840	2	j	int
    //   90	6876	3	bool1	boolean
    //   82	6878	4	bool2	boolean
    //   86	6866	5	bool3	boolean
    //   378	6519	6	bool4	boolean
    //   10	6885	7	bool5	boolean
    //   1	6869	8	bool6	boolean
    //   4	6870	9	bool7	boolean
    //   7	6871	10	bool8	boolean
    //   2024	4978	11	l1	long
    //   33	6852	13	l2	long
    //   2045	27	15	l3	long
    //   78	432	17	str1	java.lang.String
    //   558	147	17	localInvalidProtocolBufferMicroException1	com.tencent.mobileqq.pb.InvalidProtocolBufferMicroException
    //   753	20	17	localException1	java.lang.Exception
    //   898	441	17	localObject1	Object
    //   1428	79	17	localObject2	Object
    //   1540	562	17	localTerminalInfo	com.tencent.mobileqq.unifiedebug.UnifiedDebugManager.TerminalInfo
    //   2114	27	17	localJSONException1	org.json.JSONException
    //   2182	160	17	localObject3	Object
    //   2353	383	17	localJSONException2	org.json.JSONException
    //   2862	434	17	localObject4	Object
    //   3329	144	17	localException2	java.lang.Exception
    //   3485	27	17	localException3	java.lang.Exception
    //   3591	54	17	localObject5	Object
    //   3656	27	17	localException4	java.lang.Exception
    //   3763	35	17	localSet1	java.util.Set
    //   3831	27	17	localException5	java.lang.Exception
    //   3977	14	17	localJSONObject1	org.json.JSONObject
    //   4205	104	17	localSQLiteException	android.database.sqlite.SQLiteException
    //   4399	94	17	str2	java.lang.String
    //   4527	27	17	localException6	java.lang.Exception
    //   4672	35	17	localSet2	java.util.Set
    //   4740	155	17	localException7	java.lang.Exception
    //   4907	27	17	localException8	java.lang.Exception
    //   5080	94	17	str3	java.lang.String
    //   5208	1029	17	localException9	java.lang.Exception
    //   6507	53	17	str4	java.lang.String
    //   6578	177	17	localIOException	java.io.IOException
    //   6767	27	17	localException10	java.lang.Exception
    //   6901	3	17	localInterruptedException1	java.lang.InterruptedException
    //   6911	3	17	localInterruptedException2	java.lang.InterruptedException
    //   6921	3	17	localInterruptedException3	java.lang.InterruptedException
    //   6941	1	17	localObject6	Object
    //   6948	1	17	localException11	java.lang.Exception
    //   6956	1	17	localInvalidProtocolBufferMicroException2	com.tencent.mobileqq.pb.InvalidProtocolBufferMicroException
    //   49	6702	18	localObject7	Object
    //   6931	3	18	localInterruptedException4	java.lang.InterruptedException
    //   1760	4470	19	localObject8	Object
    //   2600	3534	20	localObject9	Object
    //   4103	158	21	localJSONObject2	org.json.JSONObject
    //   4128	35	22	localIterator	java.util.Iterator
    //   4172	20	23	str5	java.lang.String
    // Exception table:
    //   from	to	target	type
    //   91	146	558	com/tencent/mobileqq/pb/InvalidProtocolBufferMicroException
    //   157	171	558	com/tencent/mobileqq/pb/InvalidProtocolBufferMicroException
    //   476	490	558	com/tencent/mobileqq/pb/InvalidProtocolBufferMicroException
    //   501	517	558	com/tencent/mobileqq/pb/InvalidProtocolBufferMicroException
    //   537	551	558	com/tencent/mobileqq/pb/InvalidProtocolBufferMicroException
    //   671	685	558	com/tencent/mobileqq/pb/InvalidProtocolBufferMicroException
    //   696	712	558	com/tencent/mobileqq/pb/InvalidProtocolBufferMicroException
    //   732	746	558	com/tencent/mobileqq/pb/InvalidProtocolBufferMicroException
    //   870	878	558	com/tencent/mobileqq/pb/InvalidProtocolBufferMicroException
    //   889	900	558	com/tencent/mobileqq/pb/InvalidProtocolBufferMicroException
    //   916	924	558	com/tencent/mobileqq/pb/InvalidProtocolBufferMicroException
    //   935	943	558	com/tencent/mobileqq/pb/InvalidProtocolBufferMicroException
    //   954	960	558	com/tencent/mobileqq/pb/InvalidProtocolBufferMicroException
    //   971	997	558	com/tencent/mobileqq/pb/InvalidProtocolBufferMicroException
    //   1008	1014	558	com/tencent/mobileqq/pb/InvalidProtocolBufferMicroException
    //   1025	1031	558	com/tencent/mobileqq/pb/InvalidProtocolBufferMicroException
    //   1089	1103	558	com/tencent/mobileqq/pb/InvalidProtocolBufferMicroException
    //   1114	1130	558	com/tencent/mobileqq/pb/InvalidProtocolBufferMicroException
    //   1145	1153	558	com/tencent/mobileqq/pb/InvalidProtocolBufferMicroException
    //   1168	1176	558	com/tencent/mobileqq/pb/InvalidProtocolBufferMicroException
    //   1187	1193	558	com/tencent/mobileqq/pb/InvalidProtocolBufferMicroException
    //   1204	1240	558	com/tencent/mobileqq/pb/InvalidProtocolBufferMicroException
    //   1251	1262	558	com/tencent/mobileqq/pb/InvalidProtocolBufferMicroException
    //   1273	1284	558	com/tencent/mobileqq/pb/InvalidProtocolBufferMicroException
    //   1317	1325	558	com/tencent/mobileqq/pb/InvalidProtocolBufferMicroException
    //   1336	1344	558	com/tencent/mobileqq/pb/InvalidProtocolBufferMicroException
    //   1367	1381	558	com/tencent/mobileqq/pb/InvalidProtocolBufferMicroException
    //   1396	1402	558	com/tencent/mobileqq/pb/InvalidProtocolBufferMicroException
    //   1413	1421	558	com/tencent/mobileqq/pb/InvalidProtocolBufferMicroException
    //   1520	1542	558	com/tencent/mobileqq/pb/InvalidProtocolBufferMicroException
    //   1553	1567	558	com/tencent/mobileqq/pb/InvalidProtocolBufferMicroException
    //   1582	1588	558	com/tencent/mobileqq/pb/InvalidProtocolBufferMicroException
    //   1599	1631	558	com/tencent/mobileqq/pb/InvalidProtocolBufferMicroException
    //   1649	1660	558	com/tencent/mobileqq/pb/InvalidProtocolBufferMicroException
    //   1671	1682	558	com/tencent/mobileqq/pb/InvalidProtocolBufferMicroException
    //   1693	1713	558	com/tencent/mobileqq/pb/InvalidProtocolBufferMicroException
    //   1724	1740	558	com/tencent/mobileqq/pb/InvalidProtocolBufferMicroException
    //   1751	1762	558	com/tencent/mobileqq/pb/InvalidProtocolBufferMicroException
    //   1773	1789	558	com/tencent/mobileqq/pb/InvalidProtocolBufferMicroException
    //   1800	1819	558	com/tencent/mobileqq/pb/InvalidProtocolBufferMicroException
    //   1830	1841	558	com/tencent/mobileqq/pb/InvalidProtocolBufferMicroException
    //   1852	1871	558	com/tencent/mobileqq/pb/InvalidProtocolBufferMicroException
    //   1882	1910	558	com/tencent/mobileqq/pb/InvalidProtocolBufferMicroException
    //   1921	1932	558	com/tencent/mobileqq/pb/InvalidProtocolBufferMicroException
    //   1943	1958	558	com/tencent/mobileqq/pb/InvalidProtocolBufferMicroException
    //   1976	1999	558	com/tencent/mobileqq/pb/InvalidProtocolBufferMicroException
    //   2017	2026	558	com/tencent/mobileqq/pb/InvalidProtocolBufferMicroException
    //   2037	2047	558	com/tencent/mobileqq/pb/InvalidProtocolBufferMicroException
    //   2058	2082	558	com/tencent/mobileqq/pb/InvalidProtocolBufferMicroException
    //   2093	2107	558	com/tencent/mobileqq/pb/InvalidProtocolBufferMicroException
    //   2127	2149	558	com/tencent/mobileqq/pb/InvalidProtocolBufferMicroException
    //   2167	2184	558	com/tencent/mobileqq/pb/InvalidProtocolBufferMicroException
    //   2195	2203	558	com/tencent/mobileqq/pb/InvalidProtocolBufferMicroException
    //   2214	2228	558	com/tencent/mobileqq/pb/InvalidProtocolBufferMicroException
    //   2239	2250	558	com/tencent/mobileqq/pb/InvalidProtocolBufferMicroException
    //   2266	2274	558	com/tencent/mobileqq/pb/InvalidProtocolBufferMicroException
    //   2285	2292	558	com/tencent/mobileqq/pb/InvalidProtocolBufferMicroException
    //   2308	2324	558	com/tencent/mobileqq/pb/InvalidProtocolBufferMicroException
    //   2335	2346	558	com/tencent/mobileqq/pb/InvalidProtocolBufferMicroException
    //   2366	2388	558	com/tencent/mobileqq/pb/InvalidProtocolBufferMicroException
    //   2406	2444	558	com/tencent/mobileqq/pb/InvalidProtocolBufferMicroException
    //   2462	2482	558	com/tencent/mobileqq/pb/InvalidProtocolBufferMicroException
    //   2500	2511	558	com/tencent/mobileqq/pb/InvalidProtocolBufferMicroException
    //   2522	2532	558	com/tencent/mobileqq/pb/InvalidProtocolBufferMicroException
    //   2543	2553	558	com/tencent/mobileqq/pb/InvalidProtocolBufferMicroException
    //   2569	2577	558	com/tencent/mobileqq/pb/InvalidProtocolBufferMicroException
    //   2588	2602	558	com/tencent/mobileqq/pb/InvalidProtocolBufferMicroException
    //   2613	2624	558	com/tencent/mobileqq/pb/InvalidProtocolBufferMicroException
    //   2640	2648	558	com/tencent/mobileqq/pb/InvalidProtocolBufferMicroException
    //   2659	2667	558	com/tencent/mobileqq/pb/InvalidProtocolBufferMicroException
    //   2678	2689	558	com/tencent/mobileqq/pb/InvalidProtocolBufferMicroException
    //   2700	2716	558	com/tencent/mobileqq/pb/InvalidProtocolBufferMicroException
    //   2727	2741	558	com/tencent/mobileqq/pb/InvalidProtocolBufferMicroException
    //   2759	2797	558	com/tencent/mobileqq/pb/InvalidProtocolBufferMicroException
    //   2815	2835	558	com/tencent/mobileqq/pb/InvalidProtocolBufferMicroException
    //   2853	2864	558	com/tencent/mobileqq/pb/InvalidProtocolBufferMicroException
    //   2875	2885	558	com/tencent/mobileqq/pb/InvalidProtocolBufferMicroException
    //   2896	2906	558	com/tencent/mobileqq/pb/InvalidProtocolBufferMicroException
    //   2922	2930	558	com/tencent/mobileqq/pb/InvalidProtocolBufferMicroException
    //   2941	2955	558	com/tencent/mobileqq/pb/InvalidProtocolBufferMicroException
    //   2966	2977	558	com/tencent/mobileqq/pb/InvalidProtocolBufferMicroException
    //   2993	3001	558	com/tencent/mobileqq/pb/InvalidProtocolBufferMicroException
    //   3012	3020	558	com/tencent/mobileqq/pb/InvalidProtocolBufferMicroException
    //   3031	3042	558	com/tencent/mobileqq/pb/InvalidProtocolBufferMicroException
    //   3053	3070	558	com/tencent/mobileqq/pb/InvalidProtocolBufferMicroException
    //   3081	3095	558	com/tencent/mobileqq/pb/InvalidProtocolBufferMicroException
    //   3113	3133	558	com/tencent/mobileqq/pb/InvalidProtocolBufferMicroException
    //   3151	3189	558	com/tencent/mobileqq/pb/InvalidProtocolBufferMicroException
    //   3207	3227	558	com/tencent/mobileqq/pb/InvalidProtocolBufferMicroException
    //   3241	3263	558	com/tencent/mobileqq/pb/InvalidProtocolBufferMicroException
    //   3270	3279	558	com/tencent/mobileqq/pb/InvalidProtocolBufferMicroException
    //   3286	3304	558	com/tencent/mobileqq/pb/InvalidProtocolBufferMicroException
    //   3311	3322	558	com/tencent/mobileqq/pb/InvalidProtocolBufferMicroException
    //   3342	3364	558	com/tencent/mobileqq/pb/InvalidProtocolBufferMicroException
    //   3382	3399	558	com/tencent/mobileqq/pb/InvalidProtocolBufferMicroException
    //   3415	3426	558	com/tencent/mobileqq/pb/InvalidProtocolBufferMicroException
    //   3433	3457	558	com/tencent/mobileqq/pb/InvalidProtocolBufferMicroException
    //   3464	3478	558	com/tencent/mobileqq/pb/InvalidProtocolBufferMicroException
    //   3498	3520	558	com/tencent/mobileqq/pb/InvalidProtocolBufferMicroException
    //   3538	3558	558	com/tencent/mobileqq/pb/InvalidProtocolBufferMicroException
    //   3576	3593	558	com/tencent/mobileqq/pb/InvalidProtocolBufferMicroException
    //   3609	3620	558	com/tencent/mobileqq/pb/InvalidProtocolBufferMicroException
    //   3627	3649	558	com/tencent/mobileqq/pb/InvalidProtocolBufferMicroException
    //   3669	3691	558	com/tencent/mobileqq/pb/InvalidProtocolBufferMicroException
    //   3709	3729	558	com/tencent/mobileqq/pb/InvalidProtocolBufferMicroException
    //   3743	3765	558	com/tencent/mobileqq/pb/InvalidProtocolBufferMicroException
    //   3772	3781	558	com/tencent/mobileqq/pb/InvalidProtocolBufferMicroException
    //   3788	3806	558	com/tencent/mobileqq/pb/InvalidProtocolBufferMicroException
    //   3813	3824	558	com/tencent/mobileqq/pb/InvalidProtocolBufferMicroException
    //   3844	3866	558	com/tencent/mobileqq/pb/InvalidProtocolBufferMicroException
    //   3884	3901	558	com/tencent/mobileqq/pb/InvalidProtocolBufferMicroException
    //   3912	3919	558	com/tencent/mobileqq/pb/InvalidProtocolBufferMicroException
    //   3935	3959	558	com/tencent/mobileqq/pb/InvalidProtocolBufferMicroException
    //   3970	3979	558	com/tencent/mobileqq/pb/InvalidProtocolBufferMicroException
    //   3990	4001	558	com/tencent/mobileqq/pb/InvalidProtocolBufferMicroException
    //   4012	4021	558	com/tencent/mobileqq/pb/InvalidProtocolBufferMicroException
    //   4032	4041	558	com/tencent/mobileqq/pb/InvalidProtocolBufferMicroException
    //   4052	4062	558	com/tencent/mobileqq/pb/InvalidProtocolBufferMicroException
    //   4073	4085	558	com/tencent/mobileqq/pb/InvalidProtocolBufferMicroException
    //   4096	4105	558	com/tencent/mobileqq/pb/InvalidProtocolBufferMicroException
    //   4116	4130	558	com/tencent/mobileqq/pb/InvalidProtocolBufferMicroException
    //   4141	4151	558	com/tencent/mobileqq/pb/InvalidProtocolBufferMicroException
    //   4162	4174	558	com/tencent/mobileqq/pb/InvalidProtocolBufferMicroException
    //   4185	4202	558	com/tencent/mobileqq/pb/InvalidProtocolBufferMicroException
    //   4218	4240	558	com/tencent/mobileqq/pb/InvalidProtocolBufferMicroException
    //   4258	4266	558	com/tencent/mobileqq/pb/InvalidProtocolBufferMicroException
    //   4280	4291	558	com/tencent/mobileqq/pb/InvalidProtocolBufferMicroException
    //   4302	4313	558	com/tencent/mobileqq/pb/InvalidProtocolBufferMicroException
    //   4331	4351	558	com/tencent/mobileqq/pb/InvalidProtocolBufferMicroException
    //   4369	4380	558	com/tencent/mobileqq/pb/InvalidProtocolBufferMicroException
    //   4391	4401	558	com/tencent/mobileqq/pb/InvalidProtocolBufferMicroException
    //   4412	4422	558	com/tencent/mobileqq/pb/InvalidProtocolBufferMicroException
    //   4433	4441	558	com/tencent/mobileqq/pb/InvalidProtocolBufferMicroException
    //   4457	4468	558	com/tencent/mobileqq/pb/InvalidProtocolBufferMicroException
    //   4475	4499	558	com/tencent/mobileqq/pb/InvalidProtocolBufferMicroException
    //   4506	4520	558	com/tencent/mobileqq/pb/InvalidProtocolBufferMicroException
    //   4540	4562	558	com/tencent/mobileqq/pb/InvalidProtocolBufferMicroException
    //   4580	4600	558	com/tencent/mobileqq/pb/InvalidProtocolBufferMicroException
    //   4618	4638	558	com/tencent/mobileqq/pb/InvalidProtocolBufferMicroException
    //   4652	4674	558	com/tencent/mobileqq/pb/InvalidProtocolBufferMicroException
    //   4681	4690	558	com/tencent/mobileqq/pb/InvalidProtocolBufferMicroException
    //   4697	4715	558	com/tencent/mobileqq/pb/InvalidProtocolBufferMicroException
    //   4722	4733	558	com/tencent/mobileqq/pb/InvalidProtocolBufferMicroException
    //   4753	4775	558	com/tencent/mobileqq/pb/InvalidProtocolBufferMicroException
    //   4793	4810	558	com/tencent/mobileqq/pb/InvalidProtocolBufferMicroException
    //   4821	4828	558	com/tencent/mobileqq/pb/InvalidProtocolBufferMicroException
    //   4840	4864	558	com/tencent/mobileqq/pb/InvalidProtocolBufferMicroException
    //   4871	4879	558	com/tencent/mobileqq/pb/InvalidProtocolBufferMicroException
    //   4886	4900	558	com/tencent/mobileqq/pb/InvalidProtocolBufferMicroException
    //   4920	4942	558	com/tencent/mobileqq/pb/InvalidProtocolBufferMicroException
    //   4956	4994	558	com/tencent/mobileqq/pb/InvalidProtocolBufferMicroException
    //   5012	5032	558	com/tencent/mobileqq/pb/InvalidProtocolBufferMicroException
    //   5050	5061	558	com/tencent/mobileqq/pb/InvalidProtocolBufferMicroException
    //   5072	5082	558	com/tencent/mobileqq/pb/InvalidProtocolBufferMicroException
    //   5093	5103	558	com/tencent/mobileqq/pb/InvalidProtocolBufferMicroException
    //   5114	5122	558	com/tencent/mobileqq/pb/InvalidProtocolBufferMicroException
    //   5138	5149	558	com/tencent/mobileqq/pb/InvalidProtocolBufferMicroException
    //   5156	5180	558	com/tencent/mobileqq/pb/InvalidProtocolBufferMicroException
    //   5187	5201	558	com/tencent/mobileqq/pb/InvalidProtocolBufferMicroException
    //   5221	5243	558	com/tencent/mobileqq/pb/InvalidProtocolBufferMicroException
    //   5261	5281	558	com/tencent/mobileqq/pb/InvalidProtocolBufferMicroException
    //   5299	5319	558	com/tencent/mobileqq/pb/InvalidProtocolBufferMicroException
    //   5337	5348	558	com/tencent/mobileqq/pb/InvalidProtocolBufferMicroException
    //   5359	5372	558	com/tencent/mobileqq/pb/InvalidProtocolBufferMicroException
    //   5383	5393	558	com/tencent/mobileqq/pb/InvalidProtocolBufferMicroException
    //   5411	5438	558	com/tencent/mobileqq/pb/InvalidProtocolBufferMicroException
    //   5456	5466	558	com/tencent/mobileqq/pb/InvalidProtocolBufferMicroException
    //   5477	5490	558	com/tencent/mobileqq/pb/InvalidProtocolBufferMicroException
    //   5501	5509	558	com/tencent/mobileqq/pb/InvalidProtocolBufferMicroException
    //   5520	5527	558	com/tencent/mobileqq/pb/InvalidProtocolBufferMicroException
    //   5538	5552	558	com/tencent/mobileqq/pb/InvalidProtocolBufferMicroException
    //   5563	5577	558	com/tencent/mobileqq/pb/InvalidProtocolBufferMicroException
    //   5591	5620	558	com/tencent/mobileqq/pb/InvalidProtocolBufferMicroException
    //   5638	5658	558	com/tencent/mobileqq/pb/InvalidProtocolBufferMicroException
    //   5676	5696	558	com/tencent/mobileqq/pb/InvalidProtocolBufferMicroException
    //   5714	5730	558	com/tencent/mobileqq/pb/InvalidProtocolBufferMicroException
    //   5741	5761	558	com/tencent/mobileqq/pb/InvalidProtocolBufferMicroException
    //   5779	5790	558	com/tencent/mobileqq/pb/InvalidProtocolBufferMicroException
    //   5801	5811	558	com/tencent/mobileqq/pb/InvalidProtocolBufferMicroException
    //   5822	5830	558	com/tencent/mobileqq/pb/InvalidProtocolBufferMicroException
    //   5841	5850	558	com/tencent/mobileqq/pb/InvalidProtocolBufferMicroException
    //   5861	5877	558	com/tencent/mobileqq/pb/InvalidProtocolBufferMicroException
    //   5888	5897	558	com/tencent/mobileqq/pb/InvalidProtocolBufferMicroException
    //   5908	5924	558	com/tencent/mobileqq/pb/InvalidProtocolBufferMicroException
    //   5935	5955	558	com/tencent/mobileqq/pb/InvalidProtocolBufferMicroException
    //   5966	5976	558	com/tencent/mobileqq/pb/InvalidProtocolBufferMicroException
    //   5987	6014	558	com/tencent/mobileqq/pb/InvalidProtocolBufferMicroException
    //   6025	6036	558	com/tencent/mobileqq/pb/InvalidProtocolBufferMicroException
    //   6047	6057	558	com/tencent/mobileqq/pb/InvalidProtocolBufferMicroException
    //   6068	6076	558	com/tencent/mobileqq/pb/InvalidProtocolBufferMicroException
    //   6087	6094	558	com/tencent/mobileqq/pb/InvalidProtocolBufferMicroException
    //   6105	6119	558	com/tencent/mobileqq/pb/InvalidProtocolBufferMicroException
    //   6130	6144	558	com/tencent/mobileqq/pb/InvalidProtocolBufferMicroException
    //   6155	6168	558	com/tencent/mobileqq/pb/InvalidProtocolBufferMicroException
    //   6191	6201	558	com/tencent/mobileqq/pb/InvalidProtocolBufferMicroException
    //   6212	6241	558	com/tencent/mobileqq/pb/InvalidProtocolBufferMicroException
    //   6259	6279	558	com/tencent/mobileqq/pb/InvalidProtocolBufferMicroException
    //   6297	6317	558	com/tencent/mobileqq/pb/InvalidProtocolBufferMicroException
    //   6335	6349	558	com/tencent/mobileqq/pb/InvalidProtocolBufferMicroException
    //   6367	6387	558	com/tencent/mobileqq/pb/InvalidProtocolBufferMicroException
    //   6405	6418	558	com/tencent/mobileqq/pb/InvalidProtocolBufferMicroException
    //   6429	6449	558	com/tencent/mobileqq/pb/InvalidProtocolBufferMicroException
    //   6460	6474	558	com/tencent/mobileqq/pb/InvalidProtocolBufferMicroException
    //   6492	6509	558	com/tencent/mobileqq/pb/InvalidProtocolBufferMicroException
    //   6520	6527	558	com/tencent/mobileqq/pb/InvalidProtocolBufferMicroException
    //   6543	6571	558	com/tencent/mobileqq/pb/InvalidProtocolBufferMicroException
    //   6591	6613	558	com/tencent/mobileqq/pb/InvalidProtocolBufferMicroException
    //   6631	6651	558	com/tencent/mobileqq/pb/InvalidProtocolBufferMicroException
    //   6669	6686	558	com/tencent/mobileqq/pb/InvalidProtocolBufferMicroException
    //   6697	6704	558	com/tencent/mobileqq/pb/InvalidProtocolBufferMicroException
    //   6716	6739	558	com/tencent/mobileqq/pb/InvalidProtocolBufferMicroException
    //   6746	6760	558	com/tencent/mobileqq/pb/InvalidProtocolBufferMicroException
    //   6780	6802	558	com/tencent/mobileqq/pb/InvalidProtocolBufferMicroException
    //   6820	6840	558	com/tencent/mobileqq/pb/InvalidProtocolBufferMicroException
    //   6858	6869	558	com/tencent/mobileqq/pb/InvalidProtocolBufferMicroException
    //   6880	6894	558	com/tencent/mobileqq/pb/InvalidProtocolBufferMicroException
    //   91	146	753	java/lang/Exception
    //   157	171	753	java/lang/Exception
    //   476	490	753	java/lang/Exception
    //   501	517	753	java/lang/Exception
    //   537	551	753	java/lang/Exception
    //   671	685	753	java/lang/Exception
    //   696	712	753	java/lang/Exception
    //   732	746	753	java/lang/Exception
    //   870	878	753	java/lang/Exception
    //   889	900	753	java/lang/Exception
    //   916	924	753	java/lang/Exception
    //   935	943	753	java/lang/Exception
    //   954	960	753	java/lang/Exception
    //   971	997	753	java/lang/Exception
    //   1008	1014	753	java/lang/Exception
    //   1025	1031	753	java/lang/Exception
    //   1089	1103	753	java/lang/Exception
    //   1114	1130	753	java/lang/Exception
    //   1145	1153	753	java/lang/Exception
    //   1168	1176	753	java/lang/Exception
    //   1187	1193	753	java/lang/Exception
    //   1204	1240	753	java/lang/Exception
    //   1251	1262	753	java/lang/Exception
    //   1273	1284	753	java/lang/Exception
    //   1317	1325	753	java/lang/Exception
    //   1336	1344	753	java/lang/Exception
    //   1367	1381	753	java/lang/Exception
    //   1396	1402	753	java/lang/Exception
    //   1413	1421	753	java/lang/Exception
    //   1520	1542	753	java/lang/Exception
    //   1553	1567	753	java/lang/Exception
    //   1582	1588	753	java/lang/Exception
    //   1599	1631	753	java/lang/Exception
    //   1649	1660	753	java/lang/Exception
    //   1671	1682	753	java/lang/Exception
    //   1693	1713	753	java/lang/Exception
    //   1724	1740	753	java/lang/Exception
    //   1751	1762	753	java/lang/Exception
    //   1773	1789	753	java/lang/Exception
    //   1800	1819	753	java/lang/Exception
    //   1830	1841	753	java/lang/Exception
    //   1852	1871	753	java/lang/Exception
    //   1882	1910	753	java/lang/Exception
    //   1921	1932	753	java/lang/Exception
    //   1943	1958	753	java/lang/Exception
    //   1976	1999	753	java/lang/Exception
    //   2017	2026	753	java/lang/Exception
    //   2037	2047	753	java/lang/Exception
    //   2058	2082	753	java/lang/Exception
    //   2093	2107	753	java/lang/Exception
    //   2127	2149	753	java/lang/Exception
    //   2167	2184	753	java/lang/Exception
    //   2195	2203	753	java/lang/Exception
    //   2214	2228	753	java/lang/Exception
    //   2239	2250	753	java/lang/Exception
    //   2266	2274	753	java/lang/Exception
    //   2285	2292	753	java/lang/Exception
    //   2308	2324	753	java/lang/Exception
    //   2335	2346	753	java/lang/Exception
    //   2366	2388	753	java/lang/Exception
    //   2406	2444	753	java/lang/Exception
    //   2462	2482	753	java/lang/Exception
    //   2500	2511	753	java/lang/Exception
    //   2522	2532	753	java/lang/Exception
    //   2543	2553	753	java/lang/Exception
    //   2569	2577	753	java/lang/Exception
    //   2588	2602	753	java/lang/Exception
    //   2613	2624	753	java/lang/Exception
    //   2640	2648	753	java/lang/Exception
    //   2659	2667	753	java/lang/Exception
    //   2678	2689	753	java/lang/Exception
    //   2700	2716	753	java/lang/Exception
    //   2727	2741	753	java/lang/Exception
    //   2759	2797	753	java/lang/Exception
    //   2815	2835	753	java/lang/Exception
    //   2853	2864	753	java/lang/Exception
    //   2875	2885	753	java/lang/Exception
    //   2896	2906	753	java/lang/Exception
    //   2922	2930	753	java/lang/Exception
    //   2941	2955	753	java/lang/Exception
    //   2966	2977	753	java/lang/Exception
    //   2993	3001	753	java/lang/Exception
    //   3012	3020	753	java/lang/Exception
    //   3031	3042	753	java/lang/Exception
    //   3053	3070	753	java/lang/Exception
    //   3081	3095	753	java/lang/Exception
    //   3113	3133	753	java/lang/Exception
    //   3151	3189	753	java/lang/Exception
    //   3207	3227	753	java/lang/Exception
    //   3342	3364	753	java/lang/Exception
    //   3382	3399	753	java/lang/Exception
    //   3415	3426	753	java/lang/Exception
    //   3498	3520	753	java/lang/Exception
    //   3538	3558	753	java/lang/Exception
    //   3576	3593	753	java/lang/Exception
    //   3609	3620	753	java/lang/Exception
    //   3669	3691	753	java/lang/Exception
    //   3709	3729	753	java/lang/Exception
    //   3844	3866	753	java/lang/Exception
    //   3884	3901	753	java/lang/Exception
    //   3912	3919	753	java/lang/Exception
    //   3935	3959	753	java/lang/Exception
    //   3970	3979	753	java/lang/Exception
    //   3990	4001	753	java/lang/Exception
    //   4012	4021	753	java/lang/Exception
    //   4032	4041	753	java/lang/Exception
    //   4052	4062	753	java/lang/Exception
    //   4073	4085	753	java/lang/Exception
    //   4096	4105	753	java/lang/Exception
    //   4116	4130	753	java/lang/Exception
    //   4141	4151	753	java/lang/Exception
    //   4162	4174	753	java/lang/Exception
    //   4185	4202	753	java/lang/Exception
    //   4218	4240	753	java/lang/Exception
    //   4258	4266	753	java/lang/Exception
    //   4280	4291	753	java/lang/Exception
    //   4302	4313	753	java/lang/Exception
    //   4331	4351	753	java/lang/Exception
    //   4369	4380	753	java/lang/Exception
    //   4391	4401	753	java/lang/Exception
    //   4412	4422	753	java/lang/Exception
    //   4433	4441	753	java/lang/Exception
    //   4457	4468	753	java/lang/Exception
    //   4540	4562	753	java/lang/Exception
    //   4580	4600	753	java/lang/Exception
    //   4618	4638	753	java/lang/Exception
    //   4753	4775	753	java/lang/Exception
    //   4793	4810	753	java/lang/Exception
    //   4821	4828	753	java/lang/Exception
    //   4920	4942	753	java/lang/Exception
    //   5012	5032	753	java/lang/Exception
    //   5050	5061	753	java/lang/Exception
    //   5072	5082	753	java/lang/Exception
    //   5093	5103	753	java/lang/Exception
    //   5114	5122	753	java/lang/Exception
    //   5138	5149	753	java/lang/Exception
    //   5221	5243	753	java/lang/Exception
    //   5261	5281	753	java/lang/Exception
    //   5299	5319	753	java/lang/Exception
    //   5337	5348	753	java/lang/Exception
    //   5359	5372	753	java/lang/Exception
    //   5383	5393	753	java/lang/Exception
    //   5411	5438	753	java/lang/Exception
    //   5456	5466	753	java/lang/Exception
    //   5477	5490	753	java/lang/Exception
    //   5501	5509	753	java/lang/Exception
    //   5520	5527	753	java/lang/Exception
    //   5538	5552	753	java/lang/Exception
    //   5563	5577	753	java/lang/Exception
    //   5591	5620	753	java/lang/Exception
    //   5638	5658	753	java/lang/Exception
    //   5676	5696	753	java/lang/Exception
    //   5714	5730	753	java/lang/Exception
    //   5741	5761	753	java/lang/Exception
    //   5779	5790	753	java/lang/Exception
    //   5801	5811	753	java/lang/Exception
    //   5822	5830	753	java/lang/Exception
    //   5841	5850	753	java/lang/Exception
    //   5861	5877	753	java/lang/Exception
    //   5888	5897	753	java/lang/Exception
    //   5908	5924	753	java/lang/Exception
    //   5935	5955	753	java/lang/Exception
    //   5966	5976	753	java/lang/Exception
    //   5987	6014	753	java/lang/Exception
    //   6025	6036	753	java/lang/Exception
    //   6047	6057	753	java/lang/Exception
    //   6068	6076	753	java/lang/Exception
    //   6087	6094	753	java/lang/Exception
    //   6105	6119	753	java/lang/Exception
    //   6130	6144	753	java/lang/Exception
    //   6155	6168	753	java/lang/Exception
    //   6191	6201	753	java/lang/Exception
    //   6212	6241	753	java/lang/Exception
    //   6259	6279	753	java/lang/Exception
    //   6297	6317	753	java/lang/Exception
    //   6335	6349	753	java/lang/Exception
    //   6367	6387	753	java/lang/Exception
    //   6405	6418	753	java/lang/Exception
    //   6429	6449	753	java/lang/Exception
    //   6460	6474	753	java/lang/Exception
    //   6492	6509	753	java/lang/Exception
    //   6520	6527	753	java/lang/Exception
    //   6543	6571	753	java/lang/Exception
    //   6591	6613	753	java/lang/Exception
    //   6631	6651	753	java/lang/Exception
    //   6669	6686	753	java/lang/Exception
    //   6697	6704	753	java/lang/Exception
    //   6780	6802	753	java/lang/Exception
    //   6820	6840	753	java/lang/Exception
    //   6858	6869	753	java/lang/Exception
    //   6880	6894	753	java/lang/Exception
    //   91	146	1428	finally
    //   157	171	1428	finally
    //   476	490	1428	finally
    //   501	517	1428	finally
    //   537	551	1428	finally
    //   563	569	1428	finally
    //   572	582	1428	finally
    //   671	685	1428	finally
    //   696	712	1428	finally
    //   732	746	1428	finally
    //   758	764	1428	finally
    //   767	777	1428	finally
    //   870	878	1428	finally
    //   889	900	1428	finally
    //   916	924	1428	finally
    //   935	943	1428	finally
    //   954	960	1428	finally
    //   971	997	1428	finally
    //   1008	1014	1428	finally
    //   1025	1031	1428	finally
    //   1089	1103	1428	finally
    //   1114	1130	1428	finally
    //   1145	1153	1428	finally
    //   1168	1176	1428	finally
    //   1187	1193	1428	finally
    //   1204	1240	1428	finally
    //   1251	1262	1428	finally
    //   1273	1284	1428	finally
    //   1317	1325	1428	finally
    //   1336	1344	1428	finally
    //   1367	1381	1428	finally
    //   1396	1402	1428	finally
    //   1413	1421	1428	finally
    //   1520	1542	1428	finally
    //   1553	1567	1428	finally
    //   1582	1588	1428	finally
    //   1599	1631	1428	finally
    //   1649	1660	1428	finally
    //   1671	1682	1428	finally
    //   1693	1713	1428	finally
    //   1724	1740	1428	finally
    //   1751	1762	1428	finally
    //   1773	1789	1428	finally
    //   1800	1819	1428	finally
    //   1830	1841	1428	finally
    //   1852	1871	1428	finally
    //   1882	1910	1428	finally
    //   1921	1932	1428	finally
    //   1943	1958	1428	finally
    //   1976	1999	1428	finally
    //   2017	2026	1428	finally
    //   2037	2047	1428	finally
    //   2058	2082	1428	finally
    //   2093	2107	1428	finally
    //   2127	2149	1428	finally
    //   2167	2184	1428	finally
    //   2195	2203	1428	finally
    //   2214	2228	1428	finally
    //   2239	2250	1428	finally
    //   2266	2274	1428	finally
    //   2285	2292	1428	finally
    //   2308	2324	1428	finally
    //   2335	2346	1428	finally
    //   2366	2388	1428	finally
    //   2406	2444	1428	finally
    //   2462	2482	1428	finally
    //   2500	2511	1428	finally
    //   2522	2532	1428	finally
    //   2543	2553	1428	finally
    //   2569	2577	1428	finally
    //   2588	2602	1428	finally
    //   2613	2624	1428	finally
    //   2640	2648	1428	finally
    //   2659	2667	1428	finally
    //   2678	2689	1428	finally
    //   2700	2716	1428	finally
    //   2727	2741	1428	finally
    //   2759	2797	1428	finally
    //   2815	2835	1428	finally
    //   2853	2864	1428	finally
    //   2875	2885	1428	finally
    //   2896	2906	1428	finally
    //   2922	2930	1428	finally
    //   2941	2955	1428	finally
    //   2966	2977	1428	finally
    //   2993	3001	1428	finally
    //   3012	3020	1428	finally
    //   3031	3042	1428	finally
    //   3053	3070	1428	finally
    //   3081	3095	1428	finally
    //   3113	3133	1428	finally
    //   3151	3189	1428	finally
    //   3207	3227	1428	finally
    //   3241	3263	1428	finally
    //   3270	3279	1428	finally
    //   3286	3304	1428	finally
    //   3311	3322	1428	finally
    //   3342	3364	1428	finally
    //   3382	3399	1428	finally
    //   3415	3426	1428	finally
    //   3433	3457	1428	finally
    //   3464	3478	1428	finally
    //   3498	3520	1428	finally
    //   3538	3558	1428	finally
    //   3576	3593	1428	finally
    //   3609	3620	1428	finally
    //   3627	3649	1428	finally
    //   3669	3691	1428	finally
    //   3709	3729	1428	finally
    //   3743	3765	1428	finally
    //   3772	3781	1428	finally
    //   3788	3806	1428	finally
    //   3813	3824	1428	finally
    //   3844	3866	1428	finally
    //   3884	3901	1428	finally
    //   3912	3919	1428	finally
    //   3935	3959	1428	finally
    //   3970	3979	1428	finally
    //   3990	4001	1428	finally
    //   4012	4021	1428	finally
    //   4032	4041	1428	finally
    //   4052	4062	1428	finally
    //   4073	4085	1428	finally
    //   4096	4105	1428	finally
    //   4116	4130	1428	finally
    //   4141	4151	1428	finally
    //   4162	4174	1428	finally
    //   4185	4202	1428	finally
    //   4218	4240	1428	finally
    //   4258	4266	1428	finally
    //   4280	4291	1428	finally
    //   4302	4313	1428	finally
    //   4331	4351	1428	finally
    //   4369	4380	1428	finally
    //   4391	4401	1428	finally
    //   4412	4422	1428	finally
    //   4433	4441	1428	finally
    //   4457	4468	1428	finally
    //   4475	4499	1428	finally
    //   4506	4520	1428	finally
    //   4540	4562	1428	finally
    //   4580	4600	1428	finally
    //   4618	4638	1428	finally
    //   4652	4674	1428	finally
    //   4681	4690	1428	finally
    //   4697	4715	1428	finally
    //   4722	4733	1428	finally
    //   4753	4775	1428	finally
    //   4793	4810	1428	finally
    //   4821	4828	1428	finally
    //   4840	4864	1428	finally
    //   4871	4879	1428	finally
    //   4886	4900	1428	finally
    //   4920	4942	1428	finally
    //   4956	4994	1428	finally
    //   5012	5032	1428	finally
    //   5050	5061	1428	finally
    //   5072	5082	1428	finally
    //   5093	5103	1428	finally
    //   5114	5122	1428	finally
    //   5138	5149	1428	finally
    //   5156	5180	1428	finally
    //   5187	5201	1428	finally
    //   5221	5243	1428	finally
    //   5261	5281	1428	finally
    //   5299	5319	1428	finally
    //   5337	5348	1428	finally
    //   5359	5372	1428	finally
    //   5383	5393	1428	finally
    //   5411	5438	1428	finally
    //   5456	5466	1428	finally
    //   5477	5490	1428	finally
    //   5501	5509	1428	finally
    //   5520	5527	1428	finally
    //   5538	5552	1428	finally
    //   5563	5577	1428	finally
    //   5591	5620	1428	finally
    //   5638	5658	1428	finally
    //   5676	5696	1428	finally
    //   5714	5730	1428	finally
    //   5741	5761	1428	finally
    //   5779	5790	1428	finally
    //   5801	5811	1428	finally
    //   5822	5830	1428	finally
    //   5841	5850	1428	finally
    //   5861	5877	1428	finally
    //   5888	5897	1428	finally
    //   5908	5924	1428	finally
    //   5935	5955	1428	finally
    //   5966	5976	1428	finally
    //   5987	6014	1428	finally
    //   6025	6036	1428	finally
    //   6047	6057	1428	finally
    //   6068	6076	1428	finally
    //   6087	6094	1428	finally
    //   6105	6119	1428	finally
    //   6130	6144	1428	finally
    //   6155	6168	1428	finally
    //   6191	6201	1428	finally
    //   6212	6241	1428	finally
    //   6259	6279	1428	finally
    //   6297	6317	1428	finally
    //   6335	6349	1428	finally
    //   6367	6387	1428	finally
    //   6405	6418	1428	finally
    //   6429	6449	1428	finally
    //   6460	6474	1428	finally
    //   6492	6509	1428	finally
    //   6520	6527	1428	finally
    //   6543	6571	1428	finally
    //   6591	6613	1428	finally
    //   6631	6651	1428	finally
    //   6669	6686	1428	finally
    //   6697	6704	1428	finally
    //   6716	6739	1428	finally
    //   6746	6760	1428	finally
    //   6780	6802	1428	finally
    //   6820	6840	1428	finally
    //   6858	6869	1428	finally
    //   6880	6894	1428	finally
    //   2017	2026	2114	org/json/JSONException
    //   2037	2047	2114	org/json/JSONException
    //   2058	2082	2114	org/json/JSONException
    //   2093	2107	2114	org/json/JSONException
    //   2308	2324	2353	org/json/JSONException
    //   2335	2346	2353	org/json/JSONException
    //   3241	3263	3329	java/lang/Exception
    //   3270	3279	3329	java/lang/Exception
    //   3286	3304	3329	java/lang/Exception
    //   3311	3322	3329	java/lang/Exception
    //   3433	3457	3485	java/lang/Exception
    //   3464	3478	3485	java/lang/Exception
    //   3627	3649	3656	java/lang/Exception
    //   3743	3765	3831	java/lang/Exception
    //   3772	3781	3831	java/lang/Exception
    //   3788	3806	3831	java/lang/Exception
    //   3813	3824	3831	java/lang/Exception
    //   3935	3959	4205	android/database/sqlite/SQLiteException
    //   3970	3979	4205	android/database/sqlite/SQLiteException
    //   3990	4001	4205	android/database/sqlite/SQLiteException
    //   4012	4021	4205	android/database/sqlite/SQLiteException
    //   4032	4041	4205	android/database/sqlite/SQLiteException
    //   4052	4062	4205	android/database/sqlite/SQLiteException
    //   4073	4085	4205	android/database/sqlite/SQLiteException
    //   4096	4105	4205	android/database/sqlite/SQLiteException
    //   4116	4130	4205	android/database/sqlite/SQLiteException
    //   4141	4151	4205	android/database/sqlite/SQLiteException
    //   4162	4174	4205	android/database/sqlite/SQLiteException
    //   4185	4202	4205	android/database/sqlite/SQLiteException
    //   4258	4266	4205	android/database/sqlite/SQLiteException
    //   4280	4291	4205	android/database/sqlite/SQLiteException
    //   4302	4313	4205	android/database/sqlite/SQLiteException
    //   4475	4499	4527	java/lang/Exception
    //   4506	4520	4527	java/lang/Exception
    //   4652	4674	4740	java/lang/Exception
    //   4681	4690	4740	java/lang/Exception
    //   4697	4715	4740	java/lang/Exception
    //   4722	4733	4740	java/lang/Exception
    //   4840	4864	4907	java/lang/Exception
    //   4871	4879	4907	java/lang/Exception
    //   4886	4900	4907	java/lang/Exception
    //   4956	4994	4907	java/lang/Exception
    //   5156	5180	5208	java/lang/Exception
    //   5187	5201	5208	java/lang/Exception
    //   6543	6571	6578	java/io/IOException
    //   6716	6739	6767	java/lang/Exception
    //   6746	6760	6767	java/lang/Exception
    //   434	440	6901	java/lang/InterruptedException
    //   636	642	6911	java/lang/InterruptedException
    //   831	837	6921	java/lang/InterruptedException
    //   1483	1489	6931	java/lang/InterruptedException
    //   1034	1048	6941	finally
    //   1051	1065	6941	finally
    //   1034	1048	6948	java/lang/Exception
    //   1051	1065	6948	java/lang/Exception
    //   1034	1048	6956	com/tencent/mobileqq/pb/InvalidProtocolBufferMicroException
    //   1051	1065	6956	com/tencent/mobileqq/pb/InvalidProtocolBufferMicroException
  }
}


/* Location:           L:\local\mybackup\temp\qq_apk\com.tencent.mobileqq\classes10.jar
 * Qualified Name:     com.tencent.mobileqq.secspy.SecSpyFileManager.2
 * JD-Core Version:    0.7.0.1
 */