package com.tencent.mm.console;

final class Shell$2$2
  implements Runnable
{
  Shell$2$2(Shell.2 param2, String paramString) {}
  
  /* Error */
  public final void run()
  {
    // Byte code:
    //   0: sipush 16109
    //   3: invokestatic 38	com/tencent/matrix/trace/core/AppMethodBeat:i	(I)V
    //   6: invokestatic 44	com/tencent/mm/kernel/g:RL	()Lcom/tencent/mm/kernel/e;
    //   9: getfield 50	com/tencent/mm/kernel/e:eHS	Lcom/tencent/mm/cg/h;
    //   12: invokevirtual 56	com/tencent/mm/cg/h:dzV	()Lcom/tencent/wcdb/database/SQLiteDatabase;
    //   15: astore 6
    //   17: invokestatic 62	java/lang/System:currentTimeMillis	()J
    //   20: lstore_1
    //   21: new 64	java/io/BufferedReader
    //   24: dup
    //   25: new 66	java/io/FileReader
    //   28: dup
    //   29: aload_0
    //   30: getfield 21	com/tencent/mm/console/Shell$2$2:euq	Ljava/lang/String;
    //   33: invokespecial 69	java/io/FileReader:<init>	(Ljava/lang/String;)V
    //   36: invokespecial 72	java/io/BufferedReader:<init>	(Ljava/io/Reader;)V
    //   39: astore_3
    //   40: aload_3
    //   41: astore 4
    //   43: ldc 74
    //   45: new 76	java/lang/StringBuilder
    //   48: dup
    //   49: ldc 78
    //   51: invokespecial 79	java/lang/StringBuilder:<init>	(Ljava/lang/String;)V
    //   54: aload_0
    //   55: getfield 21	com/tencent/mm/console/Shell$2$2:euq	Ljava/lang/String;
    //   58: invokevirtual 83	java/lang/StringBuilder:append	(Ljava/lang/String;)Ljava/lang/StringBuilder;
    //   61: invokevirtual 87	java/lang/StringBuilder:toString	()Ljava/lang/String;
    //   64: invokestatic 92	com/tencent/mm/sdk/platformtools/ab:i	(Ljava/lang/String;Ljava/lang/String;)V
    //   67: aload_3
    //   68: astore 4
    //   70: aload_3
    //   71: invokevirtual 95	java/io/BufferedReader:readLine	()Ljava/lang/String;
    //   74: astore 5
    //   76: aload 5
    //   78: ifnull +73 -> 151
    //   81: aload_3
    //   82: astore 4
    //   84: aload 6
    //   86: aload 5
    //   88: invokevirtual 100	com/tencent/wcdb/database/SQLiteDatabase:execSQL	(Ljava/lang/String;)V
    //   91: goto -24 -> 67
    //   94: astore 4
    //   96: aload_3
    //   97: astore 4
    //   99: ldc 74
    //   101: new 76	java/lang/StringBuilder
    //   104: dup
    //   105: ldc 102
    //   107: invokespecial 79	java/lang/StringBuilder:<init>	(Ljava/lang/String;)V
    //   110: aload_0
    //   111: getfield 21	com/tencent/mm/console/Shell$2$2:euq	Ljava/lang/String;
    //   114: invokevirtual 83	java/lang/StringBuilder:append	(Ljava/lang/String;)Ljava/lang/StringBuilder;
    //   117: invokevirtual 87	java/lang/StringBuilder:toString	()Ljava/lang/String;
    //   120: invokestatic 105	com/tencent/mm/sdk/platformtools/ab:e	(Ljava/lang/String;Ljava/lang/String;)V
    //   123: aload_3
    //   124: ifnull +7 -> 131
    //   127: aload_3
    //   128: invokevirtual 108	java/io/BufferedReader:close	()V
    //   131: aload 6
    //   133: invokevirtual 112	com/tencent/wcdb/database/SQLiteDatabase:inTransaction	()Z
    //   136: ifeq +160 -> 296
    //   139: aload 6
    //   141: invokevirtual 115	com/tencent/wcdb/database/SQLiteDatabase:endTransaction	()V
    //   144: sipush 16109
    //   147: invokestatic 118	com/tencent/matrix/trace/core/AppMethodBeat:o	(I)V
    //   150: return
    //   151: aload_3
    //   152: astore 4
    //   154: ldc 74
    //   156: ldc 120
    //   158: iconst_1
    //   159: anewarray 4	java/lang/Object
    //   162: dup
    //   163: iconst_0
    //   164: invokestatic 62	java/lang/System:currentTimeMillis	()J
    //   167: lload_1
    //   168: lsub
    //   169: invokestatic 126	java/lang/Long:valueOf	(J)Ljava/lang/Long;
    //   172: aastore
    //   173: invokestatic 129	com/tencent/mm/sdk/platformtools/ab:i	(Ljava/lang/String;Ljava/lang/String;[Ljava/lang/Object;)V
    //   176: aload_3
    //   177: invokevirtual 108	java/io/BufferedReader:close	()V
    //   180: aload 6
    //   182: invokevirtual 112	com/tencent/wcdb/database/SQLiteDatabase:inTransaction	()Z
    //   185: ifeq +111 -> 296
    //   188: aload 6
    //   190: invokevirtual 115	com/tencent/wcdb/database/SQLiteDatabase:endTransaction	()V
    //   193: sipush 16109
    //   196: invokestatic 118	com/tencent/matrix/trace/core/AppMethodBeat:o	(I)V
    //   199: return
    //   200: astore 4
    //   202: aconst_null
    //   203: astore_3
    //   204: ldc 74
    //   206: aload 4
    //   208: new 76	java/lang/StringBuilder
    //   211: dup
    //   212: ldc 131
    //   214: invokespecial 79	java/lang/StringBuilder:<init>	(Ljava/lang/String;)V
    //   217: aload_0
    //   218: getfield 21	com/tencent/mm/console/Shell$2$2:euq	Ljava/lang/String;
    //   221: invokevirtual 83	java/lang/StringBuilder:append	(Ljava/lang/String;)Ljava/lang/StringBuilder;
    //   224: invokevirtual 87	java/lang/StringBuilder:toString	()Ljava/lang/String;
    //   227: iconst_0
    //   228: anewarray 4	java/lang/Object
    //   231: invokestatic 135	com/tencent/mm/sdk/platformtools/ab:printErrStackTrace	(Ljava/lang/String;Ljava/lang/Throwable;Ljava/lang/String;[Ljava/lang/Object;)V
    //   234: aload_3
    //   235: ifnull +7 -> 242
    //   238: aload_3
    //   239: invokevirtual 108	java/io/BufferedReader:close	()V
    //   242: aload 6
    //   244: invokevirtual 112	com/tencent/wcdb/database/SQLiteDatabase:inTransaction	()Z
    //   247: ifeq +49 -> 296
    //   250: aload 6
    //   252: invokevirtual 115	com/tencent/wcdb/database/SQLiteDatabase:endTransaction	()V
    //   255: sipush 16109
    //   258: invokestatic 118	com/tencent/matrix/trace/core/AppMethodBeat:o	(I)V
    //   261: return
    //   262: astore 4
    //   264: aconst_null
    //   265: astore_3
    //   266: aload_3
    //   267: ifnull +7 -> 274
    //   270: aload_3
    //   271: invokevirtual 108	java/io/BufferedReader:close	()V
    //   274: aload 6
    //   276: invokevirtual 112	com/tencent/wcdb/database/SQLiteDatabase:inTransaction	()Z
    //   279: ifeq +8 -> 287
    //   282: aload 6
    //   284: invokevirtual 115	com/tencent/wcdb/database/SQLiteDatabase:endTransaction	()V
    //   287: sipush 16109
    //   290: invokestatic 118	com/tencent/matrix/trace/core/AppMethodBeat:o	(I)V
    //   293: aload 4
    //   295: athrow
    //   296: sipush 16109
    //   299: invokestatic 118	com/tencent/matrix/trace/core/AppMethodBeat:o	(I)V
    //   302: return
    //   303: astore_3
    //   304: goto -124 -> 180
    //   307: astore_3
    //   308: goto -177 -> 131
    //   311: astore_3
    //   312: goto -70 -> 242
    //   315: astore_3
    //   316: goto -42 -> 274
    //   319: astore_3
    //   320: aload 4
    //   322: astore 5
    //   324: aload_3
    //   325: astore 4
    //   327: aload 5
    //   329: astore_3
    //   330: goto -64 -> 266
    //   333: astore 4
    //   335: goto -69 -> 266
    //   338: astore 4
    //   340: goto -136 -> 204
    //   343: astore_3
    //   344: aconst_null
    //   345: astore_3
    //   346: goto -250 -> 96
    // Local variable table:
    //   start	length	slot	name	signature
    //   0	349	0	this	2
    //   20	148	1	l	long
    //   39	232	3	localBufferedReader1	java.io.BufferedReader
    //   303	1	3	localIOException1	java.io.IOException
    //   307	1	3	localIOException2	java.io.IOException
    //   311	1	3	localIOException3	java.io.IOException
    //   315	1	3	localIOException4	java.io.IOException
    //   319	6	3	localObject1	Object
    //   329	1	3	localObject2	Object
    //   343	1	3	localFileNotFoundException1	java.io.FileNotFoundException
    //   345	1	3	localObject3	Object
    //   41	42	4	localBufferedReader2	java.io.BufferedReader
    //   94	1	4	localFileNotFoundException2	java.io.FileNotFoundException
    //   97	56	4	localBufferedReader3	java.io.BufferedReader
    //   200	7	4	localException1	java.lang.Exception
    //   262	59	4	localObject4	Object
    //   325	1	4	localObject5	Object
    //   333	1	4	localObject6	Object
    //   338	1	4	localException2	java.lang.Exception
    //   74	254	5	localObject7	Object
    //   15	268	6	localSQLiteDatabase	com.tencent.wcdb.database.SQLiteDatabase
    // Exception table:
    //   from	to	target	type
    //   43	67	94	java/io/FileNotFoundException
    //   70	76	94	java/io/FileNotFoundException
    //   84	91	94	java/io/FileNotFoundException
    //   154	176	94	java/io/FileNotFoundException
    //   17	40	200	java/lang/Exception
    //   17	40	262	finally
    //   176	180	303	java/io/IOException
    //   127	131	307	java/io/IOException
    //   238	242	311	java/io/IOException
    //   270	274	315	java/io/IOException
    //   43	67	319	finally
    //   70	76	319	finally
    //   84	91	319	finally
    //   99	123	319	finally
    //   154	176	319	finally
    //   204	234	333	finally
    //   43	67	338	java/lang/Exception
    //   70	76	338	java/lang/Exception
    //   84	91	338	java/lang/Exception
    //   154	176	338	java/lang/Exception
    //   17	40	343	java/io/FileNotFoundException
  }
}


/* Location:           L:\local\mybackup\temp\qq_apk\com.tencent.mm\classes8.jar
 * Qualified Name:     com.tencent.mm.console.Shell.2.2
 * JD-Core Version:    0.7.0.1
 */