package com.tencent.mobileqq.cmshow.engine.resource;

class AbsApolloResManager$16
  implements Runnable
{
  AbsApolloResManager$16(AbsApolloResManager paramAbsApolloResManager) {}
  
  /* Error */
  public void run()
  {
    // Byte code:
    //   0: aload_0
    //   1: getfield 12	com/tencent/mobileqq/cmshow/engine/resource/AbsApolloResManager$16:this$0	Lcom/tencent/mobileqq/cmshow/engine/resource/AbsApolloResManager;
    //   4: getfield 31	com/tencent/mobileqq/cmshow/engine/resource/AbsApolloResManager:b	Lorg/json/JSONObject;
    //   7: ifnonnull +4 -> 11
    //   10: return
    //   11: aload_0
    //   12: getfield 12	com/tencent/mobileqq/cmshow/engine/resource/AbsApolloResManager$16:this$0	Lcom/tencent/mobileqq/cmshow/engine/resource/AbsApolloResManager;
    //   15: invokestatic 34	com/tencent/mobileqq/cmshow/engine/resource/AbsApolloResManager:b	(Lcom/tencent/mobileqq/cmshow/engine/resource/AbsApolloResManager;)Lcom/tencent/common/app/AppInterface;
    //   18: astore_1
    //   19: aconst_null
    //   20: astore_3
    //   21: aconst_null
    //   22: astore 4
    //   24: aconst_null
    //   25: astore 5
    //   27: aconst_null
    //   28: astore_2
    //   29: aload_1
    //   30: ifnull +11 -> 41
    //   33: aload_1
    //   34: invokevirtual 40	mqq/app/AppRuntime:getApp	()Lcom/tencent/qphone/base/util/BaseApplication;
    //   37: astore_1
    //   38: goto +5 -> 43
    //   41: aconst_null
    //   42: astore_1
    //   43: aload_1
    //   44: ifnonnull +12 -> 56
    //   47: ldc 42
    //   49: iconst_1
    //   50: ldc 44
    //   52: invokestatic 50	com/tencent/qphone/base/util/QLog:e	(Ljava/lang/String;ILjava/lang/String;)V
    //   55: return
    //   56: new 52	java/io/File
    //   59: dup
    //   60: ldc 54
    //   62: invokespecial 57	java/io/File:<init>	(Ljava/lang/String;)V
    //   65: astore_1
    //   66: aload_1
    //   67: invokevirtual 61	java/io/File:mkdirs	()Z
    //   70: pop
    //   71: new 52	java/io/File
    //   74: dup
    //   75: aload_1
    //   76: ldc 63
    //   78: invokespecial 66	java/io/File:<init>	(Ljava/io/File;Ljava/lang/String;)V
    //   81: astore 8
    //   83: aload 8
    //   85: invokevirtual 69	java/io/File:exists	()Z
    //   88: ifeq +9 -> 97
    //   91: aload 8
    //   93: invokevirtual 72	java/io/File:delete	()Z
    //   96: pop
    //   97: aload_2
    //   98: astore_1
    //   99: aload_0
    //   100: getfield 12	com/tencent/mobileqq/cmshow/engine/resource/AbsApolloResManager$16:this$0	Lcom/tencent/mobileqq/cmshow/engine/resource/AbsApolloResManager;
    //   103: getfield 31	com/tencent/mobileqq/cmshow/engine/resource/AbsApolloResManager:b	Lorg/json/JSONObject;
    //   106: astore 6
    //   108: aload_2
    //   109: astore_1
    //   110: aload 6
    //   112: monitorenter
    //   113: aload_0
    //   114: getfield 12	com/tencent/mobileqq/cmshow/engine/resource/AbsApolloResManager$16:this$0	Lcom/tencent/mobileqq/cmshow/engine/resource/AbsApolloResManager;
    //   117: getfield 31	com/tencent/mobileqq/cmshow/engine/resource/AbsApolloResManager:b	Lorg/json/JSONObject;
    //   120: invokevirtual 78	org/json/JSONObject:toString	()Ljava/lang/String;
    //   123: astore 7
    //   125: aload 6
    //   127: monitorexit
    //   128: aload_2
    //   129: astore_1
    //   130: aload 7
    //   132: invokestatic 84	android/text/TextUtils:isEmpty	(Ljava/lang/CharSequence;)Z
    //   135: ifeq +4 -> 139
    //   138: return
    //   139: aload_2
    //   140: astore_1
    //   141: new 86	java/io/FileOutputStream
    //   144: dup
    //   145: aload 8
    //   147: invokespecial 89	java/io/FileOutputStream:<init>	(Ljava/io/File;)V
    //   150: astore_2
    //   151: aload_2
    //   152: aload 7
    //   154: invokevirtual 95	java/lang/String:getBytes	()[B
    //   157: invokevirtual 99	java/io/FileOutputStream:write	([B)V
    //   160: aload_2
    //   161: invokevirtual 102	java/io/FileOutputStream:flush	()V
    //   164: aload_2
    //   165: invokevirtual 105	java/io/FileOutputStream:close	()V
    //   168: return
    //   169: astore_3
    //   170: aload_2
    //   171: astore_1
    //   172: aload_3
    //   173: astore_2
    //   174: goto +129 -> 303
    //   177: astore_3
    //   178: goto +30 -> 208
    //   181: astore_3
    //   182: goto +55 -> 237
    //   185: astore_3
    //   186: goto +80 -> 266
    //   189: astore 7
    //   191: aload 6
    //   193: monitorexit
    //   194: aload_2
    //   195: astore_1
    //   196: aload 7
    //   198: athrow
    //   199: astore_2
    //   200: goto +103 -> 303
    //   203: astore_1
    //   204: aload_3
    //   205: astore_2
    //   206: aload_1
    //   207: astore_3
    //   208: aload_2
    //   209: astore_1
    //   210: ldc 42
    //   212: iconst_1
    //   213: aload_3
    //   214: invokevirtual 108	java/lang/Exception:getMessage	()Ljava/lang/String;
    //   217: invokestatic 50	com/tencent/qphone/base/util/QLog:e	(Ljava/lang/String;ILjava/lang/String;)V
    //   220: aload_2
    //   221: ifnull +81 -> 302
    //   224: aload_2
    //   225: invokevirtual 102	java/io/FileOutputStream:flush	()V
    //   228: aload_2
    //   229: invokevirtual 105	java/io/FileOutputStream:close	()V
    //   232: return
    //   233: astore_3
    //   234: aload 4
    //   236: astore_2
    //   237: aload_2
    //   238: astore_1
    //   239: ldc 42
    //   241: iconst_1
    //   242: aload_3
    //   243: invokevirtual 109	java/lang/OutOfMemoryError:getMessage	()Ljava/lang/String;
    //   246: invokestatic 50	com/tencent/qphone/base/util/QLog:e	(Ljava/lang/String;ILjava/lang/String;)V
    //   249: aload_2
    //   250: ifnull +52 -> 302
    //   253: aload_2
    //   254: invokevirtual 102	java/io/FileOutputStream:flush	()V
    //   257: aload_2
    //   258: invokevirtual 105	java/io/FileOutputStream:close	()V
    //   261: return
    //   262: astore_3
    //   263: aload 5
    //   265: astore_2
    //   266: aload_2
    //   267: astore_1
    //   268: ldc 42
    //   270: iconst_1
    //   271: aload_3
    //   272: invokevirtual 110	java/io/FileNotFoundException:getMessage	()Ljava/lang/String;
    //   275: invokestatic 50	com/tencent/qphone/base/util/QLog:e	(Ljava/lang/String;ILjava/lang/String;)V
    //   278: aload_2
    //   279: ifnull +23 -> 302
    //   282: aload_2
    //   283: invokevirtual 102	java/io/FileOutputStream:flush	()V
    //   286: aload_2
    //   287: invokevirtual 105	java/io/FileOutputStream:close	()V
    //   290: return
    //   291: astore_1
    //   292: ldc 42
    //   294: iconst_1
    //   295: aload_1
    //   296: invokevirtual 111	java/io/IOException:getMessage	()Ljava/lang/String;
    //   299: invokestatic 50	com/tencent/qphone/base/util/QLog:e	(Ljava/lang/String;ILjava/lang/String;)V
    //   302: return
    //   303: aload_1
    //   304: ifnull +25 -> 329
    //   307: aload_1
    //   308: invokevirtual 102	java/io/FileOutputStream:flush	()V
    //   311: aload_1
    //   312: invokevirtual 105	java/io/FileOutputStream:close	()V
    //   315: goto +14 -> 329
    //   318: astore_1
    //   319: ldc 42
    //   321: iconst_1
    //   322: aload_1
    //   323: invokevirtual 111	java/io/IOException:getMessage	()Ljava/lang/String;
    //   326: invokestatic 50	com/tencent/qphone/base/util/QLog:e	(Ljava/lang/String;ILjava/lang/String;)V
    //   329: aload_2
    //   330: athrow
    // Local variable table:
    //   start	length	slot	name	signature
    //   0	331	0	this	16
    //   18	178	1	localObject1	Object
    //   203	4	1	localException1	java.lang.Exception
    //   209	59	1	localObject2	Object
    //   291	21	1	localIOException1	java.io.IOException
    //   318	5	1	localIOException2	java.io.IOException
    //   28	167	2	localObject3	Object
    //   199	1	2	localObject4	Object
    //   205	125	2	localObject5	Object
    //   20	1	3	localObject6	Object
    //   169	4	3	localObject7	Object
    //   177	1	3	localException2	java.lang.Exception
    //   181	1	3	localOutOfMemoryError1	java.lang.OutOfMemoryError
    //   185	20	3	localFileNotFoundException1	java.io.FileNotFoundException
    //   207	7	3	localException3	java.lang.Exception
    //   233	10	3	localOutOfMemoryError2	java.lang.OutOfMemoryError
    //   262	10	3	localFileNotFoundException2	java.io.FileNotFoundException
    //   22	213	4	localObject8	Object
    //   25	239	5	localObject9	Object
    //   106	86	6	localJSONObject	org.json.JSONObject
    //   123	30	7	str	java.lang.String
    //   189	8	7	localObject10	Object
    //   81	65	8	localFile	java.io.File
    // Exception table:
    //   from	to	target	type
    //   151	160	169	finally
    //   151	160	177	java/lang/Exception
    //   151	160	181	java/lang/OutOfMemoryError
    //   151	160	185	java/io/FileNotFoundException
    //   113	128	189	finally
    //   191	194	189	finally
    //   99	108	199	finally
    //   110	113	199	finally
    //   130	138	199	finally
    //   141	151	199	finally
    //   196	199	199	finally
    //   210	220	199	finally
    //   239	249	199	finally
    //   268	278	199	finally
    //   99	108	203	java/lang/Exception
    //   110	113	203	java/lang/Exception
    //   130	138	203	java/lang/Exception
    //   141	151	203	java/lang/Exception
    //   196	199	203	java/lang/Exception
    //   99	108	233	java/lang/OutOfMemoryError
    //   110	113	233	java/lang/OutOfMemoryError
    //   130	138	233	java/lang/OutOfMemoryError
    //   141	151	233	java/lang/OutOfMemoryError
    //   196	199	233	java/lang/OutOfMemoryError
    //   99	108	262	java/io/FileNotFoundException
    //   110	113	262	java/io/FileNotFoundException
    //   130	138	262	java/io/FileNotFoundException
    //   141	151	262	java/io/FileNotFoundException
    //   196	199	262	java/io/FileNotFoundException
    //   160	168	291	java/io/IOException
    //   224	232	291	java/io/IOException
    //   253	261	291	java/io/IOException
    //   282	290	291	java/io/IOException
    //   307	315	318	java/io/IOException
  }
}


/* Location:           L:\local\mybackup\temp\qq_apk\com.tencent.mobileqq\classes21.jar
 * Qualified Name:     com.tencent.mobileqq.cmshow.engine.resource.AbsApolloResManager.16
 * JD-Core Version:    0.7.0.1
 */