package midas.x;

import com.tencent.midas.comm.APLog;
import org.json.JSONException;
import org.json.JSONObject;

public class cv
  extends bw
{
  private String m = "";
  private String n = "";
  private String o = "";
  private String p = "";
  private String q = "";
  private String r = "";
  private String s = "";
  
  public cv(kl paramkl)
  {
    super(paramkl);
  }
  
  private void t(JSONObject paramJSONObject)
  {
    for (;;)
    {
      try
      {
        paramJSONObject = paramJSONObject.getJSONObject("user_info");
        String str2 = paramJSONObject.getString("uin");
        String str1 = paramJSONObject.getString("uin_type");
        int i = paramJSONObject.getInt("uin_len");
        int j = paramJSONObject.getInt("codeindex");
        if ((!str2.equals("")) && (j < h.length))
        {
          paramJSONObject = fx.b(str2, h[j]);
          if (paramJSONObject.length() >= i)
          {
            paramJSONObject = paramJSONObject.substring(0, i);
            this.g.d.k = paramJSONObject;
          }
        }
        else
        {
          this.g.d.l = str1;
          return;
        }
      }
      catch (JSONException paramJSONObject)
      {
        paramJSONObject.printStackTrace();
        return;
      }
      paramJSONObject = "";
    }
  }
  
  private void u(JSONObject paramJSONObject)
  {
    try
    {
      if (paramJSONObject.has("sp_forbid_channel_list")) {
        o.a().a(paramJSONObject.getString("sp_forbid_channel_list"));
      }
      int j = 0;
      int i = 0;
      if (paramJSONObject.has("mp_info"))
      {
        paramJSONObject = paramJSONObject.getJSONObject("mp_info");
        if (paramJSONObject.has("gold_mpinfo"))
        {
          ac.a().a(paramJSONObject.toString());
          i = 1;
        }
        else
        {
          o.a().i();
        }
        g(paramJSONObject);
      }
      else
      {
        APLog.i("mpInfo", "has not mp_info");
        o.a().i();
        i = j;
      }
      boolean bool = o.a().e();
      o.a().a(true);
      if (!o.a().b()) {
        o.a().a("");
      }
      o.a().a(bool);
      if (i == 0)
      {
        ac.a().a(null);
        return;
      }
    }
    catch (Exception paramJSONObject)
    {
      APLog.e("APMobileBuyGoodsAns mpInfo crash=", paramJSONObject.toString());
    }
  }
  
  /* Error */
  protected boolean a(jo paramjo)
  {
    // Byte code:
    //   0: aload_1
    //   1: getfield 172	midas/x/jo:b	Ljava/lang/String;
    //   4: astore_3
    //   5: new 174	java/lang/StringBuilder
    //   8: dup
    //   9: invokespecial 176	java/lang/StringBuilder:<init>	()V
    //   12: astore 4
    //   14: aload 4
    //   16: ldc 178
    //   18: invokevirtual 182	java/lang/StringBuilder:append	(Ljava/lang/String;)Ljava/lang/StringBuilder;
    //   21: pop
    //   22: aload 4
    //   24: aload_3
    //   25: invokevirtual 182	java/lang/StringBuilder:append	(Ljava/lang/String;)Ljava/lang/StringBuilder;
    //   28: pop
    //   29: ldc 184
    //   31: aload 4
    //   33: invokevirtual 185	java/lang/StringBuilder:toString	()Ljava/lang/String;
    //   36: invokestatic 153	com/tencent/midas/comm/APLog:i	(Ljava/lang/String;Ljava/lang/String;)V
    //   39: invokestatic 190	midas/x/ed:b	()Lmidas/x/ed;
    //   42: invokevirtual 193	midas/x/ed:n	()Lmidas/x/ec;
    //   45: ifnull +1011 -> 1056
    //   48: invokestatic 190	midas/x/ed:b	()Lmidas/x/ed;
    //   51: invokevirtual 193	midas/x/ed:n	()Lmidas/x/ec;
    //   54: getfield 196	midas/x/ec:a	Lcom/pay/api/request/APBaseRequest;
    //   57: instanceof 198
    //   60: ifne +6 -> 66
    //   63: goto +993 -> 1056
    //   66: aload_0
    //   67: invokestatic 190	midas/x/ed:b	()Lmidas/x/ed;
    //   70: invokevirtual 193	midas/x/ed:n	()Lmidas/x/ec;
    //   73: putfield 89	midas/x/cv:g	Lmidas/x/ec;
    //   76: new 41	org/json/JSONObject
    //   79: dup
    //   80: aload_3
    //   81: invokespecial 200	org/json/JSONObject:<init>	(Ljava/lang/String;)V
    //   84: astore 4
    //   86: aload_0
    //   87: aload 4
    //   89: ldc 202
    //   91: invokevirtual 51	org/json/JSONObject:getString	(Ljava/lang/String;)Ljava/lang/String;
    //   94: invokestatic 207	java/lang/Integer:parseInt	(Ljava/lang/String;)I
    //   97: putfield 210	midas/x/cv:i	I
    //   100: aload_0
    //   101: aload 4
    //   103: ldc 212
    //   105: invokevirtual 51	org/json/JSONObject:getString	(Ljava/lang/String;)Ljava/lang/String;
    //   108: putfield 215	midas/x/cv:j	Ljava/lang/String;
    //   111: aload_0
    //   112: getfield 210	midas/x/cv:i	I
    //   115: ifne +751 -> 866
    //   118: aload 4
    //   120: ldc 217
    //   122: invokevirtual 45	org/json/JSONObject:getJSONObject	(Ljava/lang/String;)Lorg/json/JSONObject;
    //   125: astore 5
    //   127: aload_0
    //   128: getfield 89	midas/x/cv:g	Lmidas/x/ec;
    //   131: getfield 220	midas/x/ec:b	Lmidas/x/ek;
    //   134: aload 5
    //   136: ldc 222
    //   138: invokevirtual 51	org/json/JSONObject:getString	(Ljava/lang/String;)Ljava/lang/String;
    //   141: putfield 226	midas/x/ek:a	Ljava/lang/String;
    //   144: aload_0
    //   145: getfield 89	midas/x/cv:g	Lmidas/x/ec;
    //   148: getfield 220	midas/x/ec:b	Lmidas/x/ek;
    //   151: aload 5
    //   153: ldc 228
    //   155: invokevirtual 51	org/json/JSONObject:getString	(Ljava/lang/String;)Ljava/lang/String;
    //   158: putfield 229	midas/x/ek:b	Ljava/lang/String;
    //   161: aload_0
    //   162: getfield 89	midas/x/cv:g	Lmidas/x/ec;
    //   165: getfield 220	midas/x/ec:b	Lmidas/x/ek;
    //   168: checkcast 231	midas/x/em
    //   171: astore 7
    //   173: aload_0
    //   174: aload 5
    //   176: ldc 233
    //   178: invokevirtual 51	org/json/JSONObject:getString	(Ljava/lang/String;)Ljava/lang/String;
    //   181: putfield 28	midas/x/cv:q	Ljava/lang/String;
    //   184: invokestatic 238	midas/x/a:c	()Z
    //   187: ifeq +9 -> 196
    //   190: aload_0
    //   191: ldc 240
    //   193: putfield 28	midas/x/cv:q	Ljava/lang/String;
    //   196: aload_0
    //   197: getfield 28	midas/x/cv:q	Ljava/lang/String;
    //   200: ldc 242
    //   202: invokevirtual 67	java/lang/String:equals	(Ljava/lang/Object;)Z
    //   205: ifeq +17 -> 222
    //   208: aload_0
    //   209: getfield 89	midas/x/cv:g	Lmidas/x/ec;
    //   212: getfield 196	midas/x/ec:a	Lcom/pay/api/request/APBaseRequest;
    //   215: iconst_1
    //   216: putfield 248	com/pay/api/request/APBaseRequest:isCanChange	Z
    //   219: goto +28 -> 247
    //   222: aload_0
    //   223: getfield 89	midas/x/cv:g	Lmidas/x/ec;
    //   226: getfield 196	midas/x/ec:a	Lcom/pay/api/request/APBaseRequest;
    //   229: iconst_0
    //   230: putfield 248	com/pay/api/request/APBaseRequest:isCanChange	Z
    //   233: goto +14 -> 247
    //   236: aload_0
    //   237: getfield 89	midas/x/cv:g	Lmidas/x/ec;
    //   240: getfield 196	midas/x/ec:a	Lcom/pay/api/request/APBaseRequest;
    //   243: iconst_1
    //   244: putfield 248	com/pay/api/request/APBaseRequest:isCanChange	Z
    //   247: aload 5
    //   249: ldc 250
    //   251: invokevirtual 116	org/json/JSONObject:has	(Ljava/lang/String;)Z
    //   254: ifeq +9 -> 263
    //   257: aload_0
    //   258: aload 5
    //   260: invokevirtual 252	midas/x/cv:a	(Lorg/json/JSONObject;)V
    //   263: aload_0
    //   264: invokevirtual 255	midas/x/cv:V	()Ljava/lang/String;
    //   267: astore 6
    //   269: aload 6
    //   271: invokestatic 261	android/text/TextUtils:isEmpty	(Ljava/lang/CharSequence;)Z
    //   274: ifeq +12 -> 286
    //   277: ldc_w 263
    //   280: ldc_w 265
    //   283: invokestatic 167	com/tencent/midas/comm/APLog:e	(Ljava/lang/String;Ljava/lang/String;)V
    //   286: aload_0
    //   287: aload 5
    //   289: invokevirtual 267	midas/x/cv:b	(Lorg/json/JSONObject;)V
    //   292: aload_0
    //   293: aload 5
    //   295: ldc_w 269
    //   298: aload 6
    //   300: invokestatic 274	midas/x/eb:d	(Lorg/json/JSONObject;Ljava/lang/String;Ljava/lang/String;)Ljava/lang/String;
    //   303: putfield 20	midas/x/cv:m	Ljava/lang/String;
    //   306: aload_0
    //   307: aload 5
    //   309: ldc_w 276
    //   312: aload 6
    //   314: invokestatic 274	midas/x/eb:d	(Lorg/json/JSONObject;Ljava/lang/String;Ljava/lang/String;)Ljava/lang/String;
    //   317: putfield 22	midas/x/cv:n	Ljava/lang/String;
    //   320: goto +15 -> 335
    //   323: aload_0
    //   324: ldc 18
    //   326: putfield 20	midas/x/cv:m	Ljava/lang/String;
    //   329: aload_0
    //   330: ldc 18
    //   332: putfield 22	midas/x/cv:n	Ljava/lang/String;
    //   335: aload 7
    //   337: aload_0
    //   338: getfield 20	midas/x/cv:m	Ljava/lang/String;
    //   341: putfield 278	midas/x/em:e	Ljava/lang/String;
    //   344: aload 7
    //   346: aload_0
    //   347: getfield 22	midas/x/cv:n	Ljava/lang/String;
    //   350: putfield 281	midas/x/em:f	Ljava/lang/String;
    //   353: aload_0
    //   354: aload 5
    //   356: ldc_w 283
    //   359: aload 6
    //   361: invokestatic 274	midas/x/eb:d	(Lorg/json/JSONObject;Ljava/lang/String;Ljava/lang/String;)Ljava/lang/String;
    //   364: putfield 24	midas/x/cv:o	Ljava/lang/String;
    //   367: goto +9 -> 376
    //   370: aload_0
    //   371: ldc 18
    //   373: putfield 24	midas/x/cv:o	Ljava/lang/String;
    //   376: aload_0
    //   377: getfield 89	midas/x/cv:g	Lmidas/x/ec;
    //   380: getfield 95	midas/x/ec:d	Lmidas/x/eq;
    //   383: aload_0
    //   384: getfield 24	midas/x/cv:o	Ljava/lang/String;
    //   387: invokevirtual 286	java/lang/String:toLowerCase	()Ljava/lang/String;
    //   390: putfield 287	midas/x/eq:a	Ljava/lang/String;
    //   393: aload 5
    //   395: ldc_w 289
    //   398: invokevirtual 51	org/json/JSONObject:getString	(Ljava/lang/String;)Ljava/lang/String;
    //   401: astore_3
    //   402: goto +6 -> 408
    //   405: ldc 18
    //   407: astore_3
    //   408: aload_0
    //   409: getfield 89	midas/x/cv:g	Lmidas/x/ec;
    //   412: getfield 292	midas/x/ec:e	Lmidas/x/er;
    //   415: aload_3
    //   416: putfield 295	midas/x/er:j	Ljava/lang/String;
    //   419: aload_0
    //   420: getfield 89	midas/x/cv:g	Lmidas/x/ec;
    //   423: getfield 292	midas/x/ec:e	Lmidas/x/er;
    //   426: aload_3
    //   427: putfield 296	midas/x/er:k	Ljava/lang/String;
    //   430: aload 5
    //   432: ldc_w 298
    //   435: aload 6
    //   437: invokestatic 274	midas/x/eb:d	(Lorg/json/JSONObject;Ljava/lang/String;Ljava/lang/String;)Ljava/lang/String;
    //   440: ldc 240
    //   442: invokevirtual 67	java/lang/String:equals	(Ljava/lang/Object;)Z
    //   445: ifeq +17 -> 462
    //   448: aload_0
    //   449: getfield 89	midas/x/cv:g	Lmidas/x/ec;
    //   452: getfield 95	midas/x/ec:d	Lmidas/x/eq;
    //   455: iconst_1
    //   456: putfield 300	midas/x/eq:d	Z
    //   459: goto +14 -> 473
    //   462: aload_0
    //   463: getfield 89	midas/x/cv:g	Lmidas/x/ec;
    //   466: getfield 95	midas/x/ec:d	Lmidas/x/eq;
    //   469: iconst_0
    //   470: putfield 300	midas/x/eq:d	Z
    //   473: aload_0
    //   474: aload 5
    //   476: ldc_w 302
    //   479: invokevirtual 51	org/json/JSONObject:getString	(Ljava/lang/String;)Ljava/lang/String;
    //   482: putfield 30	midas/x/cv:r	Ljava/lang/String;
    //   485: goto +9 -> 494
    //   488: aload_0
    //   489: ldc 18
    //   491: putfield 30	midas/x/cv:r	Ljava/lang/String;
    //   494: aload_0
    //   495: getfield 89	midas/x/cv:g	Lmidas/x/ec;
    //   498: getfield 292	midas/x/ec:e	Lmidas/x/er;
    //   501: aload_0
    //   502: getfield 30	midas/x/cv:r	Ljava/lang/String;
    //   505: putfield 304	midas/x/er:g	Ljava/lang/String;
    //   508: aload_0
    //   509: getfield 89	midas/x/cv:g	Lmidas/x/ec;
    //   512: getfield 196	midas/x/ec:a	Lcom/pay/api/request/APBaseRequest;
    //   515: aload_0
    //   516: getfield 30	midas/x/cv:r	Ljava/lang/String;
    //   519: putfield 307	com/pay/api/request/APBaseRequest:saveValue	Ljava/lang/String;
    //   522: aload 7
    //   524: aload 5
    //   526: ldc_w 309
    //   529: invokevirtual 59	org/json/JSONObject:getInt	(Ljava/lang/String;)I
    //   532: putfield 310	midas/x/em:i	I
    //   535: aload 5
    //   537: ldc_w 312
    //   540: aload 6
    //   542: invokestatic 274	midas/x/eb:d	(Lorg/json/JSONObject;Ljava/lang/String;Ljava/lang/String;)Ljava/lang/String;
    //   545: ldc 240
    //   547: invokevirtual 67	java/lang/String:equals	(Ljava/lang/Object;)Z
    //   550: ifeq +17 -> 567
    //   553: aload_0
    //   554: getfield 89	midas/x/cv:g	Lmidas/x/ec;
    //   557: getfield 95	midas/x/ec:d	Lmidas/x/eq;
    //   560: iconst_1
    //   561: putfield 314	midas/x/eq:c	Z
    //   564: goto +14 -> 578
    //   567: aload_0
    //   568: getfield 89	midas/x/cv:g	Lmidas/x/ec;
    //   571: getfield 95	midas/x/ec:d	Lmidas/x/eq;
    //   574: iconst_0
    //   575: putfield 314	midas/x/eq:c	Z
    //   578: aload 5
    //   580: ldc_w 316
    //   583: aload 6
    //   585: invokestatic 274	midas/x/eb:d	(Lorg/json/JSONObject;Ljava/lang/String;Ljava/lang/String;)Ljava/lang/String;
    //   588: ldc 240
    //   590: invokevirtual 67	java/lang/String:equals	(Ljava/lang/Object;)Z
    //   593: ifeq +17 -> 610
    //   596: aload_0
    //   597: getfield 89	midas/x/cv:g	Lmidas/x/ec;
    //   600: getfield 95	midas/x/ec:d	Lmidas/x/eq;
    //   603: iconst_1
    //   604: putfield 318	midas/x/eq:e	Z
    //   607: goto +14 -> 621
    //   610: aload_0
    //   611: getfield 89	midas/x/cv:g	Lmidas/x/ec;
    //   614: getfield 95	midas/x/ec:d	Lmidas/x/eq;
    //   617: iconst_0
    //   618: putfield 318	midas/x/eq:e	Z
    //   621: new 174	java/lang/StringBuilder
    //   624: dup
    //   625: invokespecial 176	java/lang/StringBuilder:<init>	()V
    //   628: astore_3
    //   629: aload_3
    //   630: ldc_w 320
    //   633: invokevirtual 182	java/lang/StringBuilder:append	(Ljava/lang/String;)Ljava/lang/StringBuilder;
    //   636: pop
    //   637: aload_3
    //   638: aload_0
    //   639: getfield 89	midas/x/cv:g	Lmidas/x/ec;
    //   642: getfield 95	midas/x/ec:d	Lmidas/x/eq;
    //   645: getfield 318	midas/x/eq:e	Z
    //   648: invokevirtual 323	java/lang/StringBuilder:append	(Z)Ljava/lang/StringBuilder;
    //   651: pop
    //   652: ldc_w 325
    //   655: aload_3
    //   656: invokevirtual 185	java/lang/StringBuilder:toString	()Ljava/lang/String;
    //   659: invokestatic 328	com/tencent/midas/comm/APLog:w	(Ljava/lang/String;Ljava/lang/String;)V
    //   662: aload 5
    //   664: ldc_w 330
    //   667: aload 6
    //   669: invokestatic 333	midas/x/eb:c	(Lorg/json/JSONObject;Ljava/lang/String;Ljava/lang/String;)I
    //   672: istore_2
    //   673: aload_0
    //   674: getfield 89	midas/x/cv:g	Lmidas/x/ec;
    //   677: getfield 95	midas/x/ec:d	Lmidas/x/eq;
    //   680: iload_2
    //   681: putfield 335	midas/x/eq:g	I
    //   684: aload 5
    //   686: ldc_w 337
    //   689: invokevirtual 116	org/json/JSONObject:has	(Ljava/lang/String;)Z
    //   692: ifeq +9 -> 701
    //   695: aload_0
    //   696: aload 5
    //   698: invokevirtual 339	midas/x/cv:e	(Lorg/json/JSONObject;)V
    //   701: new 174	java/lang/StringBuilder
    //   704: dup
    //   705: invokespecial 176	java/lang/StringBuilder:<init>	()V
    //   708: astore_3
    //   709: aload_3
    //   710: ldc_w 341
    //   713: invokevirtual 182	java/lang/StringBuilder:append	(Ljava/lang/String;)Ljava/lang/StringBuilder;
    //   716: pop
    //   717: aload_3
    //   718: aload_0
    //   719: getfield 89	midas/x/cv:g	Lmidas/x/ec;
    //   722: getfield 95	midas/x/ec:d	Lmidas/x/eq;
    //   725: getfield 342	midas/x/eq:m	Ljava/lang/String;
    //   728: invokevirtual 182	java/lang/StringBuilder:append	(Ljava/lang/String;)Ljava/lang/StringBuilder;
    //   731: pop
    //   732: ldc_w 344
    //   735: aload_3
    //   736: invokevirtual 185	java/lang/StringBuilder:toString	()Ljava/lang/String;
    //   739: invokestatic 328	com/tencent/midas/comm/APLog:w	(Ljava/lang/String;Ljava/lang/String;)V
    //   742: aload 5
    //   744: ldc_w 346
    //   747: invokevirtual 116	org/json/JSONObject:has	(Ljava/lang/String;)Z
    //   750: ifeq +9 -> 759
    //   753: aload_0
    //   754: aload 5
    //   756: invokevirtual 348	midas/x/cv:d	(Lorg/json/JSONObject;)V
    //   759: aload 5
    //   761: ldc_w 350
    //   764: invokevirtual 116	org/json/JSONObject:has	(Ljava/lang/String;)Z
    //   767: ifeq +25 -> 792
    //   770: aload 5
    //   772: ldc_w 350
    //   775: invokevirtual 59	org/json/JSONObject:getInt	(Ljava/lang/String;)I
    //   778: iconst_1
    //   779: if_icmpne +13 -> 792
    //   782: invokestatic 355	midas/x/fp:a	()Lmidas/x/fp;
    //   785: iconst_1
    //   786: invokevirtual 357	midas/x/fp:i	(Z)V
    //   789: goto +10 -> 799
    //   792: invokestatic 355	midas/x/fp:a	()Lmidas/x/fp;
    //   795: iconst_0
    //   796: invokevirtual 357	midas/x/fp:i	(Z)V
    //   799: aload 5
    //   801: ldc_w 359
    //   804: aload 6
    //   806: invokestatic 333	midas/x/eb:c	(Lorg/json/JSONObject;Ljava/lang/String;Ljava/lang/String;)I
    //   809: istore_2
    //   810: aload_0
    //   811: getfield 89	midas/x/cv:g	Lmidas/x/ec;
    //   814: getfield 95	midas/x/ec:d	Lmidas/x/eq;
    //   817: iload_2
    //   818: putfield 361	midas/x/eq:h	I
    //   821: aload_0
    //   822: aload 5
    //   824: invokevirtual 363	midas/x/cv:o	(Lorg/json/JSONObject;)V
    //   827: aload_0
    //   828: aload 5
    //   830: invokevirtual 365	midas/x/cv:p	(Lorg/json/JSONObject;)V
    //   833: aload_0
    //   834: aload 5
    //   836: invokespecial 367	midas/x/cv:u	(Lorg/json/JSONObject;)V
    //   839: aload_0
    //   840: aload 5
    //   842: invokevirtual 369	midas/x/cv:r	(Lorg/json/JSONObject;)V
    //   845: aload_0
    //   846: aload 5
    //   848: invokevirtual 371	midas/x/cv:s	(Lorg/json/JSONObject;)V
    //   851: aload_0
    //   852: aload 5
    //   854: invokevirtual 373	midas/x/cv:q	(Lorg/json/JSONObject;)V
    //   857: aload_0
    //   858: aload 5
    //   860: invokevirtual 375	midas/x/cv:h	(Lorg/json/JSONObject;)V
    //   863: goto +77 -> 940
    //   866: aload 4
    //   868: ldc_w 377
    //   871: invokevirtual 51	org/json/JSONObject:getString	(Ljava/lang/String;)Ljava/lang/String;
    //   874: invokevirtual 378	java/lang/String:toString	()Ljava/lang/String;
    //   877: astore_3
    //   878: aload_3
    //   879: ldc 18
    //   881: invokevirtual 67	java/lang/String:equals	(Ljava/lang/Object;)Z
    //   884: ifne +56 -> 940
    //   887: new 174	java/lang/StringBuilder
    //   890: dup
    //   891: invokespecial 176	java/lang/StringBuilder:<init>	()V
    //   894: astore 5
    //   896: aload 5
    //   898: aload_0
    //   899: getfield 215	midas/x/cv:j	Ljava/lang/String;
    //   902: invokevirtual 182	java/lang/StringBuilder:append	(Ljava/lang/String;)Ljava/lang/StringBuilder;
    //   905: pop
    //   906: aload 5
    //   908: ldc_w 380
    //   911: invokevirtual 182	java/lang/StringBuilder:append	(Ljava/lang/String;)Ljava/lang/StringBuilder;
    //   914: pop
    //   915: aload 5
    //   917: aload_3
    //   918: invokevirtual 182	java/lang/StringBuilder:append	(Ljava/lang/String;)Ljava/lang/StringBuilder;
    //   921: pop
    //   922: aload 5
    //   924: ldc_w 382
    //   927: invokevirtual 182	java/lang/StringBuilder:append	(Ljava/lang/String;)Ljava/lang/StringBuilder;
    //   930: pop
    //   931: aload_0
    //   932: aload 5
    //   934: invokevirtual 185	java/lang/StringBuilder:toString	()Ljava/lang/String;
    //   937: putfield 215	midas/x/cv:j	Ljava/lang/String;
    //   940: aload 4
    //   942: ldc 217
    //   944: invokevirtual 116	org/json/JSONObject:has	(Ljava/lang/String;)Z
    //   947: ifeq +103 -> 1050
    //   950: aload 4
    //   952: ldc 217
    //   954: invokevirtual 45	org/json/JSONObject:getJSONObject	(Ljava/lang/String;)Lorg/json/JSONObject;
    //   957: astore_3
    //   958: aload_0
    //   959: aload_3
    //   960: invokevirtual 384	midas/x/cv:i	(Lorg/json/JSONObject;)V
    //   963: aload_0
    //   964: aload_3
    //   965: invokespecial 386	midas/x/cv:t	(Lorg/json/JSONObject;)V
    //   968: aload_0
    //   969: aload_3
    //   970: invokevirtual 388	midas/x/cv:j	(Lorg/json/JSONObject;)V
    //   973: aload_0
    //   974: aload_3
    //   975: invokevirtual 390	midas/x/cv:k	(Lorg/json/JSONObject;)V
    //   978: aload_0
    //   979: aload_3
    //   980: invokevirtual 392	midas/x/cv:n	(Lorg/json/JSONObject;)V
    //   983: aload_0
    //   984: aload_3
    //   985: invokevirtual 394	midas/x/cv:l	(Lorg/json/JSONObject;)V
    //   988: aload_0
    //   989: aload_3
    //   990: invokevirtual 396	midas/x/cv:m	(Lorg/json/JSONObject;)V
    //   993: goto +57 -> 1050
    //   996: astore_3
    //   997: aload_3
    //   998: invokevirtual 107	org/json/JSONException:printStackTrace	()V
    //   1001: new 174	java/lang/StringBuilder
    //   1004: dup
    //   1005: invokespecial 176	java/lang/StringBuilder:<init>	()V
    //   1008: astore 4
    //   1010: aload 4
    //   1012: ldc_w 398
    //   1015: invokevirtual 182	java/lang/StringBuilder:append	(Ljava/lang/String;)Ljava/lang/StringBuilder;
    //   1018: pop
    //   1019: aload 4
    //   1021: sipush 20003
    //   1024: invokestatic 403	midas/x/bq:a	(I)Ljava/lang/String;
    //   1027: invokevirtual 182	java/lang/StringBuilder:append	(Ljava/lang/String;)Ljava/lang/StringBuilder;
    //   1030: pop
    //   1031: aload_0
    //   1032: aload 4
    //   1034: invokevirtual 185	java/lang/StringBuilder:toString	()Ljava/lang/String;
    //   1037: putfield 215	midas/x/cv:j	Ljava/lang/String;
    //   1040: ldc_w 405
    //   1043: aload_3
    //   1044: invokevirtual 408	org/json/JSONException:getMessage	()Ljava/lang/String;
    //   1047: invokestatic 328	com/tencent/midas/comm/APLog:w	(Ljava/lang/String;Ljava/lang/String;)V
    //   1050: aload_0
    //   1051: aload_1
    //   1052: invokespecial 410	midas/x/bw:a	(Lmidas/x/jo;)Z
    //   1055: ireturn
    //   1056: aload_0
    //   1057: aload_1
    //   1058: invokespecial 410	midas/x/bw:a	(Lmidas/x/jo;)Z
    //   1061: ireturn
    //   1062: astore_3
    //   1063: goto -827 -> 236
    //   1066: astore_3
    //   1067: goto -744 -> 323
    //   1070: astore_3
    //   1071: goto -701 -> 370
    //   1074: astore_3
    //   1075: goto -670 -> 405
    //   1078: astore_3
    //   1079: goto -591 -> 488
    //   1082: astore_3
    //   1083: goto -548 -> 535
    // Local variable table:
    //   start	length	slot	name	signature
    //   0	1086	0	this	cv
    //   0	1086	1	paramjo	jo
    //   672	146	2	i	int
    //   4	986	3	localObject1	java.lang.Object
    //   996	48	3	localJSONException	JSONException
    //   1062	1	3	localException1	Exception
    //   1066	1	3	localException2	Exception
    //   1070	1	3	localException3	Exception
    //   1074	1	3	localException4	Exception
    //   1078	1	3	localException5	Exception
    //   1082	1	3	localException6	Exception
    //   12	1021	4	localObject2	java.lang.Object
    //   125	808	5	localObject3	java.lang.Object
    //   267	538	6	str	String
    //   171	352	7	localem	em
    // Exception table:
    //   from	to	target	type
    //   76	173	996	org/json/JSONException
    //   173	196	996	org/json/JSONException
    //   196	219	996	org/json/JSONException
    //   222	233	996	org/json/JSONException
    //   236	247	996	org/json/JSONException
    //   247	263	996	org/json/JSONException
    //   263	286	996	org/json/JSONException
    //   286	292	996	org/json/JSONException
    //   292	320	996	org/json/JSONException
    //   323	335	996	org/json/JSONException
    //   335	353	996	org/json/JSONException
    //   353	367	996	org/json/JSONException
    //   370	376	996	org/json/JSONException
    //   376	393	996	org/json/JSONException
    //   393	402	996	org/json/JSONException
    //   408	459	996	org/json/JSONException
    //   462	473	996	org/json/JSONException
    //   473	485	996	org/json/JSONException
    //   488	494	996	org/json/JSONException
    //   494	522	996	org/json/JSONException
    //   522	535	996	org/json/JSONException
    //   535	564	996	org/json/JSONException
    //   567	578	996	org/json/JSONException
    //   578	607	996	org/json/JSONException
    //   610	621	996	org/json/JSONException
    //   621	701	996	org/json/JSONException
    //   701	759	996	org/json/JSONException
    //   759	789	996	org/json/JSONException
    //   792	799	996	org/json/JSONException
    //   799	863	996	org/json/JSONException
    //   866	940	996	org/json/JSONException
    //   940	993	996	org/json/JSONException
    //   173	196	1062	java/lang/Exception
    //   196	219	1062	java/lang/Exception
    //   222	233	1062	java/lang/Exception
    //   292	320	1066	java/lang/Exception
    //   353	367	1070	java/lang/Exception
    //   393	402	1074	java/lang/Exception
    //   473	485	1078	java/lang/Exception
    //   522	535	1082	java/lang/Exception
  }
  
  public String e()
  {
    return this.f;
  }
}


/* Location:           L:\local\mybackup\temp\qq_apk\com.tencent.mm\assets\MidasPay_zip\MidasPay_1.7.1f_171060_ba4e988cc9e36ab96c2103acb9510bd4.jar\classes.jar
 * Qualified Name:     midas.x.cv
 * JD-Core Version:    0.7.0.1
 */