package com.tencent.tencentmap.mapsdk.a;

final class tn$1
  extends Thread
{
  tn$1(tn paramtn) {}
  
  /* Error */
  public final void run()
  {
    // Byte code:
    //   0: new 21	java/lang/StringBuilder
    //   3: dup
    //   4: invokespecial 22	java/lang/StringBuilder:<init>	()V
    //   7: getstatic 26	com/tencent/tencentmap/mapsdk/a/tn:c	I
    //   10: invokestatic 32	java/lang/Integer:toString	(I)Ljava/lang/String;
    //   13: invokevirtual 36	java/lang/StringBuilder:append	(Ljava/lang/String;)Ljava/lang/StringBuilder;
    //   16: ldc 38
    //   18: invokevirtual 36	java/lang/StringBuilder:append	(Ljava/lang/String;)Ljava/lang/StringBuilder;
    //   21: getstatic 41	com/tencent/tencentmap/mapsdk/a/tn:d	I
    //   24: invokestatic 32	java/lang/Integer:toString	(I)Ljava/lang/String;
    //   27: invokevirtual 36	java/lang/StringBuilder:append	(Ljava/lang/String;)Ljava/lang/StringBuilder;
    //   30: invokevirtual 44	java/lang/StringBuilder:toString	()Ljava/lang/String;
    //   33: astore_2
    //   34: new 21	java/lang/StringBuilder
    //   37: dup
    //   38: invokespecial 22	java/lang/StringBuilder:<init>	()V
    //   41: getstatic 46	com/tencent/tencentmap/mapsdk/a/tn:a	I
    //   44: invokestatic 32	java/lang/Integer:toString	(I)Ljava/lang/String;
    //   47: invokevirtual 36	java/lang/StringBuilder:append	(Ljava/lang/String;)Ljava/lang/StringBuilder;
    //   50: ldc 38
    //   52: invokevirtual 36	java/lang/StringBuilder:append	(Ljava/lang/String;)Ljava/lang/StringBuilder;
    //   55: getstatic 49	com/tencent/tencentmap/mapsdk/a/tn:b	I
    //   58: invokestatic 32	java/lang/Integer:toString	(I)Ljava/lang/String;
    //   61: invokevirtual 36	java/lang/StringBuilder:append	(Ljava/lang/String;)Ljava/lang/StringBuilder;
    //   64: invokevirtual 44	java/lang/StringBuilder:toString	()Ljava/lang/String;
    //   67: astore_3
    //   68: new 21	java/lang/StringBuilder
    //   71: dup
    //   72: invokespecial 22	java/lang/StringBuilder:<init>	()V
    //   75: getstatic 52	com/tencent/tencentmap/mapsdk/a/tn:e	I
    //   78: invokestatic 32	java/lang/Integer:toString	(I)Ljava/lang/String;
    //   81: invokevirtual 36	java/lang/StringBuilder:append	(Ljava/lang/String;)Ljava/lang/StringBuilder;
    //   84: ldc 38
    //   86: invokevirtual 36	java/lang/StringBuilder:append	(Ljava/lang/String;)Ljava/lang/StringBuilder;
    //   89: iconst_0
    //   90: invokestatic 32	java/lang/Integer:toString	(I)Ljava/lang/String;
    //   93: invokevirtual 36	java/lang/StringBuilder:append	(Ljava/lang/String;)Ljava/lang/StringBuilder;
    //   96: invokevirtual 44	java/lang/StringBuilder:toString	()Ljava/lang/String;
    //   99: astore 4
    //   101: new 21	java/lang/StringBuilder
    //   104: dup
    //   105: invokespecial 22	java/lang/StringBuilder:<init>	()V
    //   108: getstatic 55	com/tencent/tencentmap/mapsdk/a/tn:f	I
    //   111: invokestatic 32	java/lang/Integer:toString	(I)Ljava/lang/String;
    //   114: invokevirtual 36	java/lang/StringBuilder:append	(Ljava/lang/String;)Ljava/lang/StringBuilder;
    //   117: ldc 38
    //   119: invokevirtual 36	java/lang/StringBuilder:append	(Ljava/lang/String;)Ljava/lang/StringBuilder;
    //   122: iconst_0
    //   123: invokestatic 32	java/lang/Integer:toString	(I)Ljava/lang/String;
    //   126: invokevirtual 36	java/lang/StringBuilder:append	(Ljava/lang/String;)Ljava/lang/StringBuilder;
    //   129: invokevirtual 44	java/lang/StringBuilder:toString	()Ljava/lang/String;
    //   132: astore 5
    //   134: new 21	java/lang/StringBuilder
    //   137: dup
    //   138: ldc 57
    //   140: invokespecial 60	java/lang/StringBuilder:<init>	(Ljava/lang/String;)V
    //   143: astore 6
    //   145: aload_0
    //   146: getfield 12	com/tencent/tencentmap/mapsdk/a/tn$1:a	Lcom/tencent/tencentmap/mapsdk/a/tn;
    //   149: invokestatic 63	com/tencent/tencentmap/mapsdk/a/tn:a	(Lcom/tencent/tencentmap/mapsdk/a/tn;)Lcom/tencent/tencentmap/mapsdk/a/sm;
    //   152: ifnull +217 -> 369
    //   155: aload_0
    //   156: getfield 12	com/tencent/tencentmap/mapsdk/a/tn$1:a	Lcom/tencent/tencentmap/mapsdk/a/tn;
    //   159: invokestatic 63	com/tencent/tencentmap/mapsdk/a/tn:a	(Lcom/tencent/tencentmap/mapsdk/a/tn;)Lcom/tencent/tencentmap/mapsdk/a/sm;
    //   162: invokevirtual 67	com/tencent/tencentmap/mapsdk/a/sm:b	()Ljava/lang/String;
    //   165: ifnonnull +133 -> 298
    //   168: goto +201 -> 369
    //   171: new 69	java/net/URL
    //   174: dup
    //   175: aload 6
    //   177: aload_1
    //   178: invokevirtual 36	java/lang/StringBuilder:append	(Ljava/lang/String;)Ljava/lang/StringBuilder;
    //   181: ldc 71
    //   183: invokevirtual 36	java/lang/StringBuilder:append	(Ljava/lang/String;)Ljava/lang/StringBuilder;
    //   186: aload_2
    //   187: invokevirtual 36	java/lang/StringBuilder:append	(Ljava/lang/String;)Ljava/lang/StringBuilder;
    //   190: ldc 73
    //   192: invokevirtual 36	java/lang/StringBuilder:append	(Ljava/lang/String;)Ljava/lang/StringBuilder;
    //   195: aload_3
    //   196: invokevirtual 36	java/lang/StringBuilder:append	(Ljava/lang/String;)Ljava/lang/StringBuilder;
    //   199: ldc 75
    //   201: invokevirtual 36	java/lang/StringBuilder:append	(Ljava/lang/String;)Ljava/lang/StringBuilder;
    //   204: aload 4
    //   206: invokevirtual 36	java/lang/StringBuilder:append	(Ljava/lang/String;)Ljava/lang/StringBuilder;
    //   209: ldc 77
    //   211: invokevirtual 36	java/lang/StringBuilder:append	(Ljava/lang/String;)Ljava/lang/StringBuilder;
    //   214: aload 5
    //   216: invokevirtual 36	java/lang/StringBuilder:append	(Ljava/lang/String;)Ljava/lang/StringBuilder;
    //   219: invokevirtual 44	java/lang/StringBuilder:toString	()Ljava/lang/String;
    //   222: invokespecial 78	java/net/URL:<init>	(Ljava/lang/String;)V
    //   225: invokevirtual 82	java/net/URL:openConnection	()Ljava/net/URLConnection;
    //   228: checkcast 84	java/net/HttpURLConnection
    //   231: astore_1
    //   232: aload_1
    //   233: ldc 86
    //   235: invokevirtual 89	java/net/HttpURLConnection:setRequestMethod	(Ljava/lang/String;)V
    //   238: aload_1
    //   239: invokevirtual 92	java/net/HttpURLConnection:connect	()V
    //   242: aload_1
    //   243: invokevirtual 96	java/net/HttpURLConnection:getResponseCode	()I
    //   246: sipush 200
    //   249: if_icmpne +40 -> 289
    //   252: aload_1
    //   253: invokevirtual 100	java/net/HttpURLConnection:getInputStream	()Ljava/io/InputStream;
    //   256: pop
    //   257: iconst_0
    //   258: putstatic 26	com/tencent/tencentmap/mapsdk/a/tn:c	I
    //   261: iconst_0
    //   262: putstatic 41	com/tencent/tencentmap/mapsdk/a/tn:d	I
    //   265: iconst_0
    //   266: putstatic 46	com/tencent/tencentmap/mapsdk/a/tn:a	I
    //   269: iconst_0
    //   270: putstatic 49	com/tencent/tencentmap/mapsdk/a/tn:b	I
    //   273: iconst_0
    //   274: putstatic 52	com/tencent/tencentmap/mapsdk/a/tn:e	I
    //   277: iconst_0
    //   278: putstatic 55	com/tencent/tencentmap/mapsdk/a/tn:f	I
    //   281: iconst_0
    //   282: putstatic 103	com/tencent/tencentmap/mapsdk/a/tn:g	I
    //   285: iconst_0
    //   286: putstatic 49	com/tencent/tencentmap/mapsdk/a/tn:b	I
    //   289: aload_1
    //   290: ifnull +7 -> 297
    //   293: aload_1
    //   294: invokevirtual 106	java/net/HttpURLConnection:disconnect	()V
    //   297: return
    //   298: new 21	java/lang/StringBuilder
    //   301: dup
    //   302: invokespecial 22	java/lang/StringBuilder:<init>	()V
    //   305: aload_0
    //   306: getfield 12	com/tencent/tencentmap/mapsdk/a/tn$1:a	Lcom/tencent/tencentmap/mapsdk/a/tn;
    //   309: invokestatic 63	com/tencent/tencentmap/mapsdk/a/tn:a	(Lcom/tencent/tencentmap/mapsdk/a/tn;)Lcom/tencent/tencentmap/mapsdk/a/sm;
    //   312: invokevirtual 67	com/tencent/tencentmap/mapsdk/a/sm:b	()Ljava/lang/String;
    //   315: invokevirtual 36	java/lang/StringBuilder:append	(Ljava/lang/String;)Ljava/lang/StringBuilder;
    //   318: ldc 108
    //   320: invokevirtual 36	java/lang/StringBuilder:append	(Ljava/lang/String;)Ljava/lang/StringBuilder;
    //   323: invokevirtual 44	java/lang/StringBuilder:toString	()Ljava/lang/String;
    //   326: astore_1
    //   327: goto -156 -> 171
    //   330: astore_1
    //   331: aconst_null
    //   332: astore_1
    //   333: aload_1
    //   334: ifnull -37 -> 297
    //   337: aload_1
    //   338: invokevirtual 106	java/net/HttpURLConnection:disconnect	()V
    //   341: return
    //   342: astore_1
    //   343: aconst_null
    //   344: astore_2
    //   345: aload_2
    //   346: ifnull +7 -> 353
    //   349: aload_2
    //   350: invokevirtual 106	java/net/HttpURLConnection:disconnect	()V
    //   353: aload_1
    //   354: athrow
    //   355: astore_2
    //   356: aload_1
    //   357: astore_3
    //   358: aload_2
    //   359: astore_1
    //   360: aload_3
    //   361: astore_2
    //   362: goto -17 -> 345
    //   365: astore_2
    //   366: goto -33 -> 333
    //   369: ldc 110
    //   371: astore_1
    //   372: goto -201 -> 171
    // Local variable table:
    //   start	length	slot	name	signature
    //   0	375	0	this	1
    //   177	150	1	localObject1	java.lang.Object
    //   330	1	1	localException1	java.lang.Exception
    //   332	6	1	localObject2	java.lang.Object
    //   342	15	1	localObject3	java.lang.Object
    //   359	13	1	localObject4	java.lang.Object
    //   33	317	2	str1	java.lang.String
    //   355	4	2	localObject5	java.lang.Object
    //   361	1	2	localObject6	java.lang.Object
    //   365	1	2	localException2	java.lang.Exception
    //   67	294	3	localObject7	java.lang.Object
    //   99	106	4	str2	java.lang.String
    //   132	83	5	str3	java.lang.String
    //   143	33	6	localStringBuilder	java.lang.StringBuilder
    // Exception table:
    //   from	to	target	type
    //   0	168	330	java/lang/Exception
    //   171	232	330	java/lang/Exception
    //   298	327	330	java/lang/Exception
    //   0	168	342	finally
    //   171	232	342	finally
    //   298	327	342	finally
    //   232	289	355	finally
    //   232	289	365	java/lang/Exception
  }
}


/* Location:           L:\local\mybackup\temp\qq_apk\com.tencent.mm\classes6.jar
 * Qualified Name:     com.tencent.tencentmap.mapsdk.a.tn.1
 * JD-Core Version:    0.7.0.1
 */