package com.tencent.qmsp.sdk.d;

public class a
{
  /* Error */
  public static java.lang.String a(java.lang.String paramString)
  {
    // Byte code:
    //   0: ldc 16
    //   2: invokestatic 22	java/security/MessageDigest:getInstance	(Ljava/lang/String;)Ljava/security/MessageDigest;
    //   5: astore 8
    //   7: new 24	java/io/FileInputStream
    //   10: dup
    //   11: aload_0
    //   12: invokespecial 28	java/io/FileInputStream:<init>	(Ljava/lang/String;)V
    //   15: astore 7
    //   17: new 30	java/io/File
    //   20: dup
    //   21: aload_0
    //   22: invokespecial 31	java/io/File:<init>	(Ljava/lang/String;)V
    //   25: invokevirtual 35	java/io/File:length	()J
    //   28: lstore 5
    //   30: lload 5
    //   32: lstore_3
    //   33: lload 5
    //   35: ldc2_w 36
    //   38: lcmp
    //   39: ifle +7 -> 46
    //   42: ldc2_w 36
    //   45: lstore_3
    //   46: sipush 4096
    //   49: newarray byte
    //   51: astore_0
    //   52: lload_3
    //   53: lconst_0
    //   54: lcmp
    //   55: ifle +43 -> 98
    //   58: aload 7
    //   60: aload_0
    //   61: invokevirtual 41	java/io/FileInputStream:read	([B)I
    //   64: istore_2
    //   65: iload_2
    //   66: iconst_m1
    //   67: if_icmpeq +31 -> 98
    //   70: iload_2
    //   71: istore_1
    //   72: iload_2
    //   73: i2l
    //   74: lload_3
    //   75: lcmp
    //   76: ifle +6 -> 82
    //   79: lload_3
    //   80: l2i
    //   81: istore_1
    //   82: lload_3
    //   83: iload_1
    //   84: i2l
    //   85: lsub
    //   86: lstore_3
    //   87: aload 8
    //   89: aload_0
    //   90: iconst_0
    //   91: iload_1
    //   92: invokevirtual 45	java/security/MessageDigest:update	([BII)V
    //   95: goto -43 -> 52
    //   98: aload 7
    //   100: invokevirtual 49	java/io/FileInputStream:close	()V
    //   103: aload 8
    //   105: invokevirtual 53	java/security/MessageDigest:digest	()[B
    //   108: invokestatic 58	com/tencent/qmsp/sdk/f/e:a	([B)Ljava/lang/String;
    //   111: astore_0
    //   112: aload 7
    //   114: invokevirtual 49	java/io/FileInputStream:close	()V
    //   117: aload_0
    //   118: areturn
    //   119: astore 8
    //   121: goto +23 -> 144
    //   124: astore 8
    //   126: goto +34 -> 160
    //   129: astore 8
    //   131: goto +45 -> 176
    //   134: astore 8
    //   136: goto +56 -> 192
    //   139: astore 8
    //   141: aconst_null
    //   142: astore 7
    //   144: aload 7
    //   146: astore_0
    //   147: aload 8
    //   149: invokevirtual 63	java/lang/Throwable:printStackTrace	()V
    //   152: aload 7
    //   154: ifnull +56 -> 210
    //   157: goto +48 -> 205
    //   160: aload 7
    //   162: astore_0
    //   163: aload 8
    //   165: invokevirtual 64	java/io/IOException:printStackTrace	()V
    //   168: aload 7
    //   170: ifnull +40 -> 210
    //   173: goto +32 -> 205
    //   176: aload 7
    //   178: astore_0
    //   179: aload 8
    //   181: invokevirtual 65	java/io/FileNotFoundException:printStackTrace	()V
    //   184: aload 7
    //   186: ifnull +24 -> 210
    //   189: goto +16 -> 205
    //   192: aload 7
    //   194: astore_0
    //   195: aload 8
    //   197: invokevirtual 66	java/security/NoSuchAlgorithmException:printStackTrace	()V
    //   200: aload 7
    //   202: ifnull +8 -> 210
    //   205: aload 7
    //   207: invokevirtual 49	java/io/FileInputStream:close	()V
    //   210: aconst_null
    //   211: areturn
    //   212: astore 7
    //   214: aload_0
    //   215: ifnull +7 -> 222
    //   218: aload_0
    //   219: invokevirtual 49	java/io/FileInputStream:close	()V
    //   222: goto +6 -> 228
    //   225: aload 7
    //   227: athrow
    //   228: goto -3 -> 225
    //   231: astore 7
    //   233: aload_0
    //   234: areturn
    //   235: astore_0
    //   236: aconst_null
    //   237: areturn
    //   238: astore_0
    //   239: goto -17 -> 222
    //   242: astore 8
    //   244: aconst_null
    //   245: astore 7
    //   247: goto -87 -> 160
    //   250: astore 8
    //   252: aconst_null
    //   253: astore 7
    //   255: goto -79 -> 176
    //   258: astore 8
    //   260: aconst_null
    //   261: astore 7
    //   263: goto -71 -> 192
    // Local variable table:
    //   start	length	slot	name	signature
    //   0	266	0	paramString	java.lang.String
    //   71	21	1	i	int
    //   64	9	2	j	int
    //   32	55	3	l1	long
    //   28	6	5	l2	long
    //   15	191	7	localFileInputStream	java.io.FileInputStream
    //   212	14	7	localObject1	Object
    //   231	1	7	localException	java.lang.Exception
    //   245	17	7	localObject2	Object
    //   5	99	8	localMessageDigest	java.security.MessageDigest
    //   119	1	8	localObject3	Object
    //   124	1	8	localIOException1	java.io.IOException
    //   129	1	8	localFileNotFoundException1	java.io.FileNotFoundException
    //   134	1	8	localNoSuchAlgorithmException1	java.security.NoSuchAlgorithmException
    //   139	57	8	localObject4	Object
    //   242	1	8	localIOException2	java.io.IOException
    //   250	1	8	localFileNotFoundException2	java.io.FileNotFoundException
    //   258	1	8	localNoSuchAlgorithmException2	java.security.NoSuchAlgorithmException
    // Exception table:
    //   from	to	target	type
    //   17	30	119	finally
    //   46	52	119	finally
    //   58	65	119	finally
    //   87	95	119	finally
    //   98	112	119	finally
    //   17	30	124	java/io/IOException
    //   46	52	124	java/io/IOException
    //   58	65	124	java/io/IOException
    //   87	95	124	java/io/IOException
    //   98	112	124	java/io/IOException
    //   17	30	129	java/io/FileNotFoundException
    //   46	52	129	java/io/FileNotFoundException
    //   58	65	129	java/io/FileNotFoundException
    //   87	95	129	java/io/FileNotFoundException
    //   98	112	129	java/io/FileNotFoundException
    //   17	30	134	java/security/NoSuchAlgorithmException
    //   46	52	134	java/security/NoSuchAlgorithmException
    //   58	65	134	java/security/NoSuchAlgorithmException
    //   87	95	134	java/security/NoSuchAlgorithmException
    //   98	112	134	java/security/NoSuchAlgorithmException
    //   0	17	139	finally
    //   147	152	212	finally
    //   163	168	212	finally
    //   179	184	212	finally
    //   195	200	212	finally
    //   112	117	231	java/lang/Exception
    //   205	210	235	java/lang/Exception
    //   218	222	238	java/lang/Exception
    //   0	17	242	java/io/IOException
    //   0	17	250	java/io/FileNotFoundException
    //   0	17	258	java/security/NoSuchAlgorithmException
  }
}


/* Location:           L:\local\mybackup\temp\qq_apk\com.tencent.mobileqq\classes13.jar
 * Qualified Name:     com.tencent.qmsp.sdk.d.a
 * JD-Core Version:    0.7.0.1
 */