package com.tencent.mm.protocal;

import android.os.Binder;
import android.os.IBinder;
import android.os.IInterface;
import android.os.Parcel;

public abstract interface h
  extends IInterface
{
  public abstract int CK();
  
  public abstract byte[] Dj();
  
  public abstract byte[] KM();
  
  public abstract byte[] KO();
  
  public abstract int Lf();
  
  public abstract String Lg();
  
  public abstract int Lh();
  
  public abstract byte[] Li();
  
  public abstract String Lj();
  
  public abstract String Lk();
  
  public abstract int Ll();
  
  public abstract String Lm();
  
  public abstract boolean a(int paramInt, byte[] paramArrayOfByte1, byte[] paramArrayOfByte2);
  
  public abstract int getCmdId();
  
  public abstract void ij(int paramInt);
  
  public abstract void ky(String paramString);
  
  public static abstract class a
    extends Binder
    implements h
  {
    public a()
    {
      attachInterface(this, "com.tencent.mm.protocal.IMMBaseResp_AIDL");
    }
    
    public static h L(IBinder paramIBinder)
    {
      if (paramIBinder == null) {
        return null;
      }
      IInterface localIInterface = paramIBinder.queryLocalInterface("com.tencent.mm.protocal.IMMBaseResp_AIDL");
      if ((localIInterface != null) && ((localIInterface instanceof h))) {
        return (h)localIInterface;
      }
      return new a(paramIBinder);
    }
    
    public IBinder asBinder()
    {
      return this;
    }
    
    public boolean onTransact(int paramInt1, Parcel paramParcel1, Parcel paramParcel2, int paramInt2)
    {
      switch (paramInt1)
      {
      default: 
        return super.onTransact(paramInt1, paramParcel1, paramParcel2, paramInt2);
      case 1598968902: 
        paramParcel2.writeString("com.tencent.mm.protocal.IMMBaseResp_AIDL");
        return true;
      case 1: 
        paramParcel1.enforceInterface("com.tencent.mm.protocal.IMMBaseResp_AIDL");
        boolean bool = a(paramParcel1.readInt(), paramParcel1.createByteArray(), paramParcel1.createByteArray());
        paramParcel2.writeNoException();
        if (bool) {}
        for (paramInt1 = 1;; paramInt1 = 0)
        {
          paramParcel2.writeInt(paramInt1);
          return true;
        }
      case 2: 
        paramParcel1.enforceInterface("com.tencent.mm.protocal.IMMBaseResp_AIDL");
        paramParcel1 = KM();
        paramParcel2.writeNoException();
        paramParcel2.writeByteArray(paramParcel1);
        return true;
      case 3: 
        paramParcel1.enforceInterface("com.tencent.mm.protocal.IMMBaseResp_AIDL");
        ij(paramParcel1.readInt());
        paramParcel2.writeNoException();
        return true;
      case 4: 
        paramParcel1.enforceInterface("com.tencent.mm.protocal.IMMBaseResp_AIDL");
        paramInt1 = Lh();
        paramParcel2.writeNoException();
        paramParcel2.writeInt(paramInt1);
        return true;
      case 5: 
        paramParcel1.enforceInterface("com.tencent.mm.protocal.IMMBaseResp_AIDL");
        paramInt1 = Lf();
        paramParcel2.writeNoException();
        paramParcel2.writeInt(paramInt1);
        return true;
      case 6: 
        paramParcel1.enforceInterface("com.tencent.mm.protocal.IMMBaseResp_AIDL");
        paramParcel1 = Lg();
        paramParcel2.writeNoException();
        paramParcel2.writeString(paramParcel1);
        return true;
      case 7: 
        paramParcel1.enforceInterface("com.tencent.mm.protocal.IMMBaseResp_AIDL");
        ky(paramParcel1.readString());
        paramParcel2.writeNoException();
        return true;
      case 8: 
        paramParcel1.enforceInterface("com.tencent.mm.protocal.IMMBaseResp_AIDL");
        paramParcel1 = Dj();
        paramParcel2.writeNoException();
        paramParcel2.writeByteArray(paramParcel1);
        return true;
      case 9: 
        paramParcel1.enforceInterface("com.tencent.mm.protocal.IMMBaseResp_AIDL");
        paramParcel1 = Li();
        paramParcel2.writeNoException();
        paramParcel2.writeByteArray(paramParcel1);
        return true;
      case 10: 
        paramParcel1.enforceInterface("com.tencent.mm.protocal.IMMBaseResp_AIDL");
        paramParcel1 = KO();
        paramParcel2.writeNoException();
        paramParcel2.writeByteArray(paramParcel1);
        return true;
      case 11: 
        paramParcel1.enforceInterface("com.tencent.mm.protocal.IMMBaseResp_AIDL");
        paramInt1 = CK();
        paramParcel2.writeNoException();
        paramParcel2.writeInt(paramInt1);
        return true;
      case 12: 
        paramParcel1.enforceInterface("com.tencent.mm.protocal.IMMBaseResp_AIDL");
        paramParcel1 = Lm();
        paramParcel2.writeNoException();
        paramParcel2.writeString(paramParcel1);
        return true;
      case 13: 
        paramParcel1.enforceInterface("com.tencent.mm.protocal.IMMBaseResp_AIDL");
        paramInt1 = getCmdId();
        paramParcel2.writeNoException();
        paramParcel2.writeInt(paramInt1);
        return true;
      case 14: 
        paramParcel1.enforceInterface("com.tencent.mm.protocal.IMMBaseResp_AIDL");
        paramParcel1 = Lj();
        paramParcel2.writeNoException();
        paramParcel2.writeString(paramParcel1);
        return true;
      case 15: 
        paramParcel1.enforceInterface("com.tencent.mm.protocal.IMMBaseResp_AIDL");
        paramParcel1 = Lk();
        paramParcel2.writeNoException();
        paramParcel2.writeString(paramParcel1);
        return true;
      }
      paramParcel1.enforceInterface("com.tencent.mm.protocal.IMMBaseResp_AIDL");
      paramInt1 = Ll();
      paramParcel2.writeNoException();
      paramParcel2.writeInt(paramInt1);
      return true;
    }
    
    private static final class a
      implements h
    {
      private IBinder mRemote;
      
      a(IBinder paramIBinder)
      {
        this.mRemote = paramIBinder;
      }
      
      public final int CK()
      {
        Parcel localParcel1 = Parcel.obtain();
        Parcel localParcel2 = Parcel.obtain();
        try
        {
          localParcel1.writeInterfaceToken("com.tencent.mm.protocal.IMMBaseResp_AIDL");
          this.mRemote.transact(11, localParcel1, localParcel2, 0);
          localParcel2.readException();
          int i = localParcel2.readInt();
          return i;
        }
        finally
        {
          localParcel2.recycle();
          localParcel1.recycle();
        }
      }
      
      public final byte[] Dj()
      {
        Parcel localParcel1 = Parcel.obtain();
        Parcel localParcel2 = Parcel.obtain();
        try
        {
          localParcel1.writeInterfaceToken("com.tencent.mm.protocal.IMMBaseResp_AIDL");
          this.mRemote.transact(8, localParcel1, localParcel2, 0);
          localParcel2.readException();
          byte[] arrayOfByte = localParcel2.createByteArray();
          return arrayOfByte;
        }
        finally
        {
          localParcel2.recycle();
          localParcel1.recycle();
        }
      }
      
      public final byte[] KM()
      {
        Parcel localParcel1 = Parcel.obtain();
        Parcel localParcel2 = Parcel.obtain();
        try
        {
          localParcel1.writeInterfaceToken("com.tencent.mm.protocal.IMMBaseResp_AIDL");
          this.mRemote.transact(2, localParcel1, localParcel2, 0);
          localParcel2.readException();
          byte[] arrayOfByte = localParcel2.createByteArray();
          return arrayOfByte;
        }
        finally
        {
          localParcel2.recycle();
          localParcel1.recycle();
        }
      }
      
      public final byte[] KO()
      {
        Parcel localParcel1 = Parcel.obtain();
        Parcel localParcel2 = Parcel.obtain();
        try
        {
          localParcel1.writeInterfaceToken("com.tencent.mm.protocal.IMMBaseResp_AIDL");
          this.mRemote.transact(10, localParcel1, localParcel2, 0);
          localParcel2.readException();
          byte[] arrayOfByte = localParcel2.createByteArray();
          return arrayOfByte;
        }
        finally
        {
          localParcel2.recycle();
          localParcel1.recycle();
        }
      }
      
      public final int Lf()
      {
        Parcel localParcel1 = Parcel.obtain();
        Parcel localParcel2 = Parcel.obtain();
        try
        {
          localParcel1.writeInterfaceToken("com.tencent.mm.protocal.IMMBaseResp_AIDL");
          this.mRemote.transact(5, localParcel1, localParcel2, 0);
          localParcel2.readException();
          int i = localParcel2.readInt();
          return i;
        }
        finally
        {
          localParcel2.recycle();
          localParcel1.recycle();
        }
      }
      
      public final String Lg()
      {
        Parcel localParcel1 = Parcel.obtain();
        Parcel localParcel2 = Parcel.obtain();
        try
        {
          localParcel1.writeInterfaceToken("com.tencent.mm.protocal.IMMBaseResp_AIDL");
          this.mRemote.transact(6, localParcel1, localParcel2, 0);
          localParcel2.readException();
          String str = localParcel2.readString();
          return str;
        }
        finally
        {
          localParcel2.recycle();
          localParcel1.recycle();
        }
      }
      
      public final int Lh()
      {
        Parcel localParcel1 = Parcel.obtain();
        Parcel localParcel2 = Parcel.obtain();
        try
        {
          localParcel1.writeInterfaceToken("com.tencent.mm.protocal.IMMBaseResp_AIDL");
          this.mRemote.transact(4, localParcel1, localParcel2, 0);
          localParcel2.readException();
          int i = localParcel2.readInt();
          return i;
        }
        finally
        {
          localParcel2.recycle();
          localParcel1.recycle();
        }
      }
      
      public final byte[] Li()
      {
        Parcel localParcel1 = Parcel.obtain();
        Parcel localParcel2 = Parcel.obtain();
        try
        {
          localParcel1.writeInterfaceToken("com.tencent.mm.protocal.IMMBaseResp_AIDL");
          this.mRemote.transact(9, localParcel1, localParcel2, 0);
          localParcel2.readException();
          byte[] arrayOfByte = localParcel2.createByteArray();
          return arrayOfByte;
        }
        finally
        {
          localParcel2.recycle();
          localParcel1.recycle();
        }
      }
      
      public final String Lj()
      {
        Parcel localParcel1 = Parcel.obtain();
        Parcel localParcel2 = Parcel.obtain();
        try
        {
          localParcel1.writeInterfaceToken("com.tencent.mm.protocal.IMMBaseResp_AIDL");
          this.mRemote.transact(14, localParcel1, localParcel2, 0);
          localParcel2.readException();
          String str = localParcel2.readString();
          return str;
        }
        finally
        {
          localParcel2.recycle();
          localParcel1.recycle();
        }
      }
      
      public final String Lk()
      {
        Parcel localParcel1 = Parcel.obtain();
        Parcel localParcel2 = Parcel.obtain();
        try
        {
          localParcel1.writeInterfaceToken("com.tencent.mm.protocal.IMMBaseResp_AIDL");
          this.mRemote.transact(15, localParcel1, localParcel2, 0);
          localParcel2.readException();
          String str = localParcel2.readString();
          return str;
        }
        finally
        {
          localParcel2.recycle();
          localParcel1.recycle();
        }
      }
      
      public final int Ll()
      {
        Parcel localParcel1 = Parcel.obtain();
        Parcel localParcel2 = Parcel.obtain();
        try
        {
          localParcel1.writeInterfaceToken("com.tencent.mm.protocal.IMMBaseResp_AIDL");
          this.mRemote.transact(16, localParcel1, localParcel2, 0);
          localParcel2.readException();
          int i = localParcel2.readInt();
          return i;
        }
        finally
        {
          localParcel2.recycle();
          localParcel1.recycle();
        }
      }
      
      public final String Lm()
      {
        Parcel localParcel1 = Parcel.obtain();
        Parcel localParcel2 = Parcel.obtain();
        try
        {
          localParcel1.writeInterfaceToken("com.tencent.mm.protocal.IMMBaseResp_AIDL");
          this.mRemote.transact(12, localParcel1, localParcel2, 0);
          localParcel2.readException();
          String str = localParcel2.readString();
          return str;
        }
        finally
        {
          localParcel2.recycle();
          localParcel1.recycle();
        }
      }
      
      /* Error */
      public final boolean a(int paramInt, byte[] paramArrayOfByte1, byte[] paramArrayOfByte2)
      {
        // Byte code:
        //   0: iconst_1
        //   1: istore 4
        //   3: invokestatic 27	android/os/Parcel:obtain	()Landroid/os/Parcel;
        //   6: astore 5
        //   8: invokestatic 27	android/os/Parcel:obtain	()Landroid/os/Parcel;
        //   11: astore 6
        //   13: aload 5
        //   15: ldc 29
        //   17: invokevirtual 33	android/os/Parcel:writeInterfaceToken	(Ljava/lang/String;)V
        //   20: aload 5
        //   22: iload_1
        //   23: invokevirtual 72	android/os/Parcel:writeInt	(I)V
        //   26: aload 5
        //   28: aload_2
        //   29: invokevirtual 76	android/os/Parcel:writeByteArray	([B)V
        //   32: aload 5
        //   34: aload_3
        //   35: invokevirtual 76	android/os/Parcel:writeByteArray	([B)V
        //   38: aload_0
        //   39: getfield 18	com/tencent/mm/protocal/h$a$a:mRemote	Landroid/os/IBinder;
        //   42: iconst_1
        //   43: aload 5
        //   45: aload 6
        //   47: iconst_0
        //   48: invokeinterface 39 5 0
        //   53: pop
        //   54: aload 6
        //   56: invokevirtual 42	android/os/Parcel:readException	()V
        //   59: aload 6
        //   61: invokevirtual 45	android/os/Parcel:readInt	()I
        //   64: istore_1
        //   65: iload_1
        //   66: ifeq +16 -> 82
        //   69: aload 6
        //   71: invokevirtual 48	android/os/Parcel:recycle	()V
        //   74: aload 5
        //   76: invokevirtual 48	android/os/Parcel:recycle	()V
        //   79: iload 4
        //   81: ireturn
        //   82: iconst_0
        //   83: istore 4
        //   85: goto -16 -> 69
        //   88: astore_2
        //   89: aload 6
        //   91: invokevirtual 48	android/os/Parcel:recycle	()V
        //   94: aload 5
        //   96: invokevirtual 48	android/os/Parcel:recycle	()V
        //   99: aload_2
        //   100: athrow
        // Local variable table:
        //   start	length	slot	name	signature
        //   0	101	0	this	a
        //   0	101	1	paramInt	int
        //   0	101	2	paramArrayOfByte1	byte[]
        //   0	101	3	paramArrayOfByte2	byte[]
        //   1	83	4	bool	boolean
        //   6	89	5	localParcel1	Parcel
        //   11	79	6	localParcel2	Parcel
        // Exception table:
        //   from	to	target	type
        //   13	65	88	finally
      }
      
      public final IBinder asBinder()
      {
        return this.mRemote;
      }
      
      public final int getCmdId()
      {
        Parcel localParcel1 = Parcel.obtain();
        Parcel localParcel2 = Parcel.obtain();
        try
        {
          localParcel1.writeInterfaceToken("com.tencent.mm.protocal.IMMBaseResp_AIDL");
          this.mRemote.transact(13, localParcel1, localParcel2, 0);
          localParcel2.readException();
          int i = localParcel2.readInt();
          return i;
        }
        finally
        {
          localParcel2.recycle();
          localParcel1.recycle();
        }
      }
      
      public final void ij(int paramInt)
      {
        Parcel localParcel1 = Parcel.obtain();
        Parcel localParcel2 = Parcel.obtain();
        try
        {
          localParcel1.writeInterfaceToken("com.tencent.mm.protocal.IMMBaseResp_AIDL");
          localParcel1.writeInt(paramInt);
          this.mRemote.transact(3, localParcel1, localParcel2, 0);
          localParcel2.readException();
          return;
        }
        finally
        {
          localParcel2.recycle();
          localParcel1.recycle();
        }
      }
      
      public final void ky(String paramString)
      {
        Parcel localParcel1 = Parcel.obtain();
        Parcel localParcel2 = Parcel.obtain();
        try
        {
          localParcel1.writeInterfaceToken("com.tencent.mm.protocal.IMMBaseResp_AIDL");
          localParcel1.writeString(paramString);
          this.mRemote.transact(7, localParcel1, localParcel2, 0);
          localParcel2.readException();
          return;
        }
        finally
        {
          localParcel2.recycle();
          localParcel1.recycle();
        }
      }
    }
  }
}


/* Location:           L:\local\mybackup\temp\qq_apk\com.tencent.mm\classes.jar
 * Qualified Name:     com.tencent.mm.protocal.h
 * JD-Core Version:    0.7.0.1
 */