package android.support.v4.os;

import android.os.Binder;
import android.os.Bundle;
import android.os.IBinder;
import android.os.IInterface;
import android.os.Parcel;
import android.os.Parcelable.Creator;

public abstract interface IResultReceiver
  extends IInterface
{
  public abstract void send(int paramInt, Bundle paramBundle);
  
  public static abstract class Stub
    extends Binder
    implements IResultReceiver
  {
    private static final String DESCRIPTOR = "android.support.v4.os.IResultReceiver";
    static final int TRANSACTION_send = 1;
    
    public Stub()
    {
      attachInterface(this, "android.support.v4.os.IResultReceiver");
    }
    
    public static IResultReceiver asInterface(IBinder paramIBinder)
    {
      if (paramIBinder == null) {
        return null;
      }
      IInterface localIInterface = paramIBinder.queryLocalInterface("android.support.v4.os.IResultReceiver");
      if ((localIInterface != null) && ((localIInterface instanceof IResultReceiver))) {
        return (IResultReceiver)localIInterface;
      }
      return new Proxy(paramIBinder);
    }
    
    public IBinder asBinder()
    {
      return this;
    }
    
    public boolean onTransact(int paramInt1, Parcel paramParcel1, Parcel paramParcel2, int paramInt2)
    {
      switch (paramInt1)
      {
      default: 
        return super.onTransact(paramInt1, paramParcel1, paramParcel2, paramInt2);
      case 1598968902: 
        paramParcel2.writeString("android.support.v4.os.IResultReceiver");
        return true;
      }
      paramParcel1.enforceInterface("android.support.v4.os.IResultReceiver");
      paramInt1 = paramParcel1.readInt();
      if (paramParcel1.readInt() != 0) {}
      for (paramParcel1 = (Bundle)Bundle.CREATOR.createFromParcel(paramParcel1);; paramParcel1 = null)
      {
        send(paramInt1, paramParcel1);
        return true;
      }
    }
    
    private static class Proxy
      implements IResultReceiver
    {
      private IBinder mRemote;
      
      Proxy(IBinder paramIBinder)
      {
        this.mRemote = paramIBinder;
      }
      
      public IBinder asBinder()
      {
        return this.mRemote;
      }
      
      public String getInterfaceDescriptor()
      {
        return "android.support.v4.os.IResultReceiver";
      }
      
      /* Error */
      public void send(int paramInt, Bundle paramBundle)
      {
        // Byte code:
        //   0: invokestatic 34	android/os/Parcel:obtain	()Landroid/os/Parcel;
        //   3: astore_3
        //   4: aload_3
        //   5: ldc 26
        //   7: invokevirtual 38	android/os/Parcel:writeInterfaceToken	(Ljava/lang/String;)V
        //   10: aload_3
        //   11: iload_1
        //   12: invokevirtual 42	android/os/Parcel:writeInt	(I)V
        //   15: aload_2
        //   16: ifnull +33 -> 49
        //   19: aload_3
        //   20: iconst_1
        //   21: invokevirtual 42	android/os/Parcel:writeInt	(I)V
        //   24: aload_2
        //   25: aload_3
        //   26: iconst_0
        //   27: invokevirtual 48	android/os/Bundle:writeToParcel	(Landroid/os/Parcel;I)V
        //   30: aload_0
        //   31: getfield 19	android/support/v4/os/IResultReceiver$Stub$Proxy:mRemote	Landroid/os/IBinder;
        //   34: iconst_1
        //   35: aload_3
        //   36: aconst_null
        //   37: iconst_1
        //   38: invokeinterface 54 5 0
        //   43: pop
        //   44: aload_3
        //   45: invokevirtual 57	android/os/Parcel:recycle	()V
        //   48: return
        //   49: aload_3
        //   50: iconst_0
        //   51: invokevirtual 42	android/os/Parcel:writeInt	(I)V
        //   54: goto -24 -> 30
        //   57: astore_2
        //   58: aload_3
        //   59: invokevirtual 57	android/os/Parcel:recycle	()V
        //   62: aload_2
        //   63: athrow
        // Local variable table:
        //   start	length	slot	name	signature
        //   0	64	0	this	Proxy
        //   0	64	1	paramInt	int
        //   0	64	2	paramBundle	Bundle
        //   3	56	3	localParcel	Parcel
        // Exception table:
        //   from	to	target	type
        //   4	15	57	finally
        //   19	30	57	finally
        //   30	44	57	finally
        //   49	54	57	finally
      }
    }
  }
}


/* Location:           L:\local\mybackup\temp\qq_apk\com.tencent.token\classes.jar
 * Qualified Name:     android.support.v4.os.IResultReceiver
 * JD-Core Version:    0.7.0.1
 */