package com.tencent.TMG.logger;

import java.net.HttpURLConnection;
import java.util.Map;

final class IMFunc$1
  implements Runnable
{
  IMFunc$1(HttpURLConnection paramHttpURLConnection, byte[] paramArrayOfByte, Map paramMap, IMFunc.RequestListener paramRequestListener) {}
  
  /* Error */
  public void run()
  {
    // Byte code:
    //   0: aload_0
    //   1: getfield 18	com/tencent/TMG/logger/IMFunc$1:val$http	Ljava/net/HttpURLConnection;
    //   4: ldc 33
    //   6: invokevirtual 39	java/net/HttpURLConnection:setRequestMethod	(Ljava/lang/String;)V
    //   9: aload_0
    //   10: getfield 18	com/tencent/TMG/logger/IMFunc$1:val$http	Ljava/net/HttpURLConnection;
    //   13: iconst_1
    //   14: invokevirtual 43	java/net/HttpURLConnection:setDoOutput	(Z)V
    //   17: aload_0
    //   18: getfield 18	com/tencent/TMG/logger/IMFunc$1:val$http	Ljava/net/HttpURLConnection;
    //   21: ldc 45
    //   23: ldc 47
    //   25: invokevirtual 51	java/net/HttpURLConnection:setRequestProperty	(Ljava/lang/String;Ljava/lang/String;)V
    //   28: aload_0
    //   29: getfield 18	com/tencent/TMG/logger/IMFunc$1:val$http	Ljava/net/HttpURLConnection;
    //   32: ldc 53
    //   34: aload_0
    //   35: getfield 20	com/tencent/TMG/logger/IMFunc$1:val$req	[B
    //   38: arraylength
    //   39: invokestatic 59	java/lang/String:valueOf	(I)Ljava/lang/String;
    //   42: invokevirtual 51	java/net/HttpURLConnection:setRequestProperty	(Ljava/lang/String;Ljava/lang/String;)V
    //   45: aload_0
    //   46: getfield 22	com/tencent/TMG/logger/IMFunc$1:val$proMaps	Ljava/util/Map;
    //   49: invokeinterface 65 1 0
    //   54: invokeinterface 71 1 0
    //   59: astore_2
    //   60: aload_2
    //   61: invokeinterface 77 1 0
    //   66: ifeq +76 -> 142
    //   69: aload_2
    //   70: invokeinterface 81 1 0
    //   75: checkcast 83	java/util/Map$Entry
    //   78: astore_3
    //   79: aload_0
    //   80: getfield 18	com/tencent/TMG/logger/IMFunc$1:val$http	Ljava/net/HttpURLConnection;
    //   83: aload_3
    //   84: invokeinterface 86 1 0
    //   89: checkcast 55	java/lang/String
    //   92: aload_3
    //   93: invokeinterface 89 1 0
    //   98: checkcast 55	java/lang/String
    //   101: invokevirtual 51	java/net/HttpURLConnection:setRequestProperty	(Ljava/lang/String;Ljava/lang/String;)V
    //   104: goto -44 -> 60
    //   107: astore_2
    //   108: aload_2
    //   109: invokevirtual 92	java/lang/Throwable:printStackTrace	()V
    //   112: aload_2
    //   113: invokevirtual 96	java/lang/Throwable:toString	()Ljava/lang/String;
    //   116: astore_2
    //   117: aload_0
    //   118: getfield 24	com/tencent/TMG/logger/IMFunc$1:val$listener	Lcom/tencent/TMG/logger/IMFunc$RequestListener;
    //   121: ifnull +13 -> 134
    //   124: aload_0
    //   125: getfield 24	com/tencent/TMG/logger/IMFunc$1:val$listener	Lcom/tencent/TMG/logger/IMFunc$RequestListener;
    //   128: aload_2
    //   129: invokeinterface 101 2 0
    //   134: aload_0
    //   135: getfield 18	com/tencent/TMG/logger/IMFunc$1:val$http	Ljava/net/HttpURLConnection;
    //   138: invokevirtual 104	java/net/HttpURLConnection:disconnect	()V
    //   141: return
    //   142: aload_0
    //   143: getfield 18	com/tencent/TMG/logger/IMFunc$1:val$http	Ljava/net/HttpURLConnection;
    //   146: invokevirtual 108	java/net/HttpURLConnection:getOutputStream	()Ljava/io/OutputStream;
    //   149: aload_0
    //   150: getfield 20	com/tencent/TMG/logger/IMFunc$1:val$req	[B
    //   153: invokevirtual 114	java/io/OutputStream:write	([B)V
    //   156: new 116	java/io/BufferedInputStream
    //   159: dup
    //   160: aload_0
    //   161: getfield 18	com/tencent/TMG/logger/IMFunc$1:val$http	Ljava/net/HttpURLConnection;
    //   164: invokevirtual 120	java/net/HttpURLConnection:getInputStream	()Ljava/io/InputStream;
    //   167: invokespecial 123	java/io/BufferedInputStream:<init>	(Ljava/io/InputStream;)V
    //   170: astore_2
    //   171: new 125	java/io/ByteArrayOutputStream
    //   174: dup
    //   175: sipush 10240
    //   178: invokespecial 128	java/io/ByteArrayOutputStream:<init>	(I)V
    //   181: astore_3
    //   182: sipush 10240
    //   185: newarray byte
    //   187: astore 4
    //   189: aload_2
    //   190: aload 4
    //   192: invokevirtual 134	java/io/InputStream:read	([B)I
    //   195: istore_1
    //   196: iload_1
    //   197: ifge +33 -> 230
    //   200: aload_3
    //   201: invokevirtual 138	java/io/ByteArrayOutputStream:toByteArray	()[B
    //   204: astore_2
    //   205: aload_0
    //   206: getfield 24	com/tencent/TMG/logger/IMFunc$1:val$listener	Lcom/tencent/TMG/logger/IMFunc$RequestListener;
    //   209: ifnull +13 -> 222
    //   212: aload_0
    //   213: getfield 24	com/tencent/TMG/logger/IMFunc$1:val$listener	Lcom/tencent/TMG/logger/IMFunc$RequestListener;
    //   216: aload_2
    //   217: invokeinterface 141 2 0
    //   222: aload_0
    //   223: getfield 18	com/tencent/TMG/logger/IMFunc$1:val$http	Ljava/net/HttpURLConnection;
    //   226: invokevirtual 104	java/net/HttpURLConnection:disconnect	()V
    //   229: return
    //   230: aload_3
    //   231: aload 4
    //   233: iconst_0
    //   234: iload_1
    //   235: invokevirtual 144	java/io/ByteArrayOutputStream:write	([BII)V
    //   238: goto -49 -> 189
    //   241: astore_2
    //   242: aload_0
    //   243: getfield 18	com/tencent/TMG/logger/IMFunc$1:val$http	Ljava/net/HttpURLConnection;
    //   246: invokevirtual 104	java/net/HttpURLConnection:disconnect	()V
    //   249: aload_2
    //   250: athrow
    // Local variable table:
    //   start	length	slot	name	signature
    //   0	251	0	this	1
    //   195	40	1	i	int
    //   59	11	2	localIterator	java.util.Iterator
    //   107	6	2	localThrowable	java.lang.Throwable
    //   116	101	2	localObject1	Object
    //   241	9	2	localObject2	Object
    //   78	153	3	localObject3	Object
    //   187	45	4	arrayOfByte	byte[]
    // Exception table:
    //   from	to	target	type
    //   0	60	107	java/lang/Throwable
    //   60	104	107	java/lang/Throwable
    //   142	189	107	java/lang/Throwable
    //   189	196	107	java/lang/Throwable
    //   200	222	107	java/lang/Throwable
    //   230	238	107	java/lang/Throwable
    //   0	60	241	finally
    //   60	104	241	finally
    //   108	134	241	finally
    //   142	189	241	finally
    //   189	196	241	finally
    //   200	222	241	finally
    //   230	238	241	finally
  }
}


/* Location:           L:\local\mybackup\temp\qq_apk\com.tencent.mobileqq\classes6.jar
 * Qualified Name:     com.tencent.TMG.logger.IMFunc.1
 * JD-Core Version:    0.7.0.1
 */