package com.tencent.mm.plugin.expt.hellhound.core.a.a;

import android.os.Message;
import com.tencent.e.i;
import com.tencent.matrix.trace.core.AppMethodBeat;
import com.tencent.mm.plugin.report.service.g;
import com.tencent.mm.sdk.platformtools.ad;
import com.tencent.mm.sdk.platformtools.ap;

public final class e
{
  private ap qQX;
  public d qQY;
  b qQZ;
  private final com.tencent.e.i.h qRa;
  
  e()
  {
    AppMethodBeat.i(121873);
    this.qRa = new com.tencent.e.i.h()
    {
      public final String getKey()
      {
        return "hellhound-receive";
      }
      
      public final void run()
      {
        AppMethodBeat.i(121871);
        for (;;)
        {
          try
          {
            a locala = e.this.qQZ.cnL();
            if (locala == null)
            {
              ad.e("HABBYGE-MALI.MsgQ", "MsgQ, mReceiver, localMsg == null");
              continue;
              continue;
            }
          }
          catch (Exception localException)
          {
            ad.printErrStackTrace("HABBYGE-MALI.MsgQ", localException, "MsgQ, mReceiver: %s", new Object[] { localException.getMessage() });
            g.yhR.idkeyStat(932L, 113L, 1L, false);
          }
          if (e.this.qQY != null) {
            e.this.qQY.a(localException);
          }
        }
      }
    };
    this.qQZ = new b();
    if (com.tencent.mm.plugin.expt.hellhound.core.b.cnC()) {
      com.tencent.mm.plugin.expt.hellhound.core.a.b.p("key_hellhound_msgQ", new byte[0]);
    }
    this.qQX = new a("hellhound_msgq");
    this.qQX.setLogging(false);
    com.tencent.e.h.LTJ.aU(this.qRa);
    AppMethodBeat.o(121873);
  }
  
  final void b(a parama)
  {
    AppMethodBeat.i(121874);
    Message localMessage = this.qQX.obtainMessage();
    localMessage.what = 0;
    localMessage.obj = parama;
    this.qQX.sendMessage(localMessage);
    AppMethodBeat.o(121874);
  }
  
  final class a
    extends ap
  {
    a(String paramString)
    {
      super();
    }
    
    /* Error */
    public final void handleMessage(Message paramMessage)
    {
      // Byte code:
      //   0: ldc 22
      //   2: invokestatic 28	com/tencent/matrix/trace/core/AppMethodBeat:i	(I)V
      //   5: aload_1
      //   6: ifnull +10 -> 16
      //   9: aload_1
      //   10: getfield 34	android/os/Message:what	I
      //   13: ifeq +9 -> 22
      //   16: ldc 22
      //   18: invokestatic 37	com/tencent/matrix/trace/core/AppMethodBeat:o	(I)V
      //   21: return
      //   22: aload_1
      //   23: getfield 41	android/os/Message:obj	Ljava/lang/Object;
      //   26: checkcast 43	com/tencent/mm/plugin/expt/hellhound/core/a/a/a
      //   29: astore 5
      //   31: aload_0
      //   32: getfield 13	com/tencent/mm/plugin/expt/hellhound/core/a/a/e$a:qRb	Lcom/tencent/mm/plugin/expt/hellhound/core/a/a/e;
      //   35: getfield 47	com/tencent/mm/plugin/expt/hellhound/core/a/a/e:qQZ	Lcom/tencent/mm/plugin/expt/hellhound/core/a/a/b;
      //   38: astore 6
      //   40: aload 5
      //   42: ifnull +3694 -> 3736
      //   45: aload 6
      //   47: getfield 53	com/tencent/mm/plugin/expt/hellhound/core/a/a/b:cPz	Ljava/util/concurrent/locks/ReentrantLock;
      //   50: astore 4
      //   52: aload 4
      //   54: invokevirtual 59	java/util/concurrent/locks/ReentrantLock:lockInterruptibly	()V
      //   57: invokestatic 63	com/tencent/mm/plugin/expt/hellhound/core/a/a/b:cnM	()I
      //   60: bipush 10
      //   62: if_icmpne +50 -> 112
      //   65: aload 6
      //   67: getfield 67	com/tencent/mm/plugin/expt/hellhound/core/a/a/b:qQU	Ljava/util/concurrent/locks/Condition;
      //   70: invokeinterface 72 1 0
      //   75: goto -18 -> 57
      //   78: astore_1
      //   79: aload 4
      //   81: invokevirtual 75	java/util/concurrent/locks/ReentrantLock:unlock	()V
      //   84: ldc 22
      //   86: invokestatic 37	com/tencent/matrix/trace/core/AppMethodBeat:o	(I)V
      //   89: aload_1
      //   90: athrow
      //   91: astore_1
      //   92: getstatic 81	com/tencent/mm/plugin/report/service/g:yhR	Lcom/tencent/mm/plugin/report/service/g;
      //   95: ldc2_w 82
      //   98: ldc2_w 84
      //   101: lconst_1
      //   102: iconst_0
      //   103: invokevirtual 89	com/tencent/mm/plugin/report/service/g:idkeyStat	(JJJZ)V
      //   106: ldc 22
      //   108: invokestatic 37	com/tencent/matrix/trace/core/AppMethodBeat:o	(I)V
      //   111: return
      //   112: invokestatic 93	com/tencent/mm/plugin/expt/hellhound/core/a/a/b:cnN	()Lcom/tencent/mm/protocal/protobuf/boa;
      //   115: astore_1
      //   116: aload_1
      //   117: ifnonnull +3625 -> 3742
      //   120: new 95	com/tencent/mm/protocal/protobuf/boa
      //   123: dup
      //   124: invokespecial 97	com/tencent/mm/protocal/protobuf/boa:<init>	()V
      //   127: astore_1
      //   128: aload_1
      //   129: getfield 101	com/tencent/mm/protocal/protobuf/boa:GIH	Ljava/util/LinkedList;
      //   132: astore 7
      //   134: aload 5
      //   136: ifnonnull +66 -> 202
      //   139: aconst_null
      //   140: astore_3
      //   141: aload 7
      //   143: aload_3
      //   144: invokevirtual 107	java/util/LinkedList:offerLast	(Ljava/lang/Object;)Z
      //   147: istore_2
      //   148: ldc 109
      //   150: ldc 111
      //   152: iconst_2
      //   153: anewarray 113	java/lang/Object
      //   156: dup
      //   157: iconst_0
      //   158: aload 5
      //   160: getfield 116	com/tencent/mm/plugin/expt/hellhound/core/a/a/a:msgType	I
      //   163: invokestatic 122	java/lang/Integer:valueOf	(I)Ljava/lang/Integer;
      //   166: aastore
      //   167: dup
      //   168: iconst_1
      //   169: iload_2
      //   170: invokestatic 127	java/lang/Boolean:valueOf	(Z)Ljava/lang/Boolean;
      //   173: aastore
      //   174: invokestatic 132	com/tencent/mm/sdk/platformtools/ad:i	(Ljava/lang/String;Ljava/lang/String;[Ljava/lang/Object;)V
      //   177: aload_1
      //   178: invokestatic 135	com/tencent/mm/plugin/expt/hellhound/core/a/a/b:a	(Lcom/tencent/mm/protocal/protobuf/boa;)V
      //   181: aload 6
      //   183: getfield 138	com/tencent/mm/plugin/expt/hellhound/core/a/a/b:qQT	Ljava/util/concurrent/locks/Condition;
      //   186: invokeinterface 141 1 0
      //   191: aload 4
      //   193: invokevirtual 75	java/util/concurrent/locks/ReentrantLock:unlock	()V
      //   196: ldc 22
      //   198: invokestatic 37	com/tencent/matrix/trace/core/AppMethodBeat:o	(I)V
      //   201: return
      //   202: new 143	com/tencent/mm/protocal/protobuf/bnz
      //   205: dup
      //   206: invokespecial 144	com/tencent/mm/protocal/protobuf/bnz:<init>	()V
      //   209: astore_3
      //   210: aload 5
      //   212: getfield 116	com/tencent/mm/plugin/expt/hellhound/core/a/a/a:msgType	I
      //   215: lookupswitch	default:+3530->3745, 1:+1799->2014, 2:+1799->2014, 3:+1799->2014, 4:+1799->2014, 5:+1826->2041, 6:+1962->2177, 100:+761->976, 101:+971->1186, 102:+1037->1252, 200:+1121->1336, 201:+1206->1421, 202:+1291->1506, 203:+1380->1595, 204:+1483->1698, 205:+1550->1765, 206:+1653->1868, 207:+1720->1935, 208:+2284->2499, 209:+2399->2614, 210:+2409->2624, 211:+2309->2524, 212:+2334->2549, 213:+2359->2574, 214:+2369->2584, 215:+2379->2594, 216:+2389->2604, 217:+2209->2424, 218:+2259->2474, 219:+2234->2449, 220:+3442->3657, 221:+3467->3682, 222:+1358->1573, 300:+1799->2014, 301:+1799->2014, 400:+2072->2287, 401:+2072->2287, 402:+2072->2287, 403:+2072->2287, 500:+2099->2314, 501:+2121->2336, 502:+2143->2358, 503:+2187->2402, 504:+2165->2380, 600:+1787->2002, 700:+2434->2649, 701:+2444->2659, 702:+2454->2669, 703:+2464->2679, 704:+2474->2689, 705:+2716->2931, 706:+2958->3173, 707:+3200->3415, 708:+2496->2711, 709:+2738->2953, 710:+2980->3195, 711:+3222->3437, 712:+2518->2733, 713:+2760->2975, 714:+3002->3217, 715:+3244->3459, 716:+2672->2887, 717:+2914->3129, 718:+3156->3371, 719:+3398->3613, 720:+2694->2909, 721:+2936->3151, 722:+3178->3393, 723:+3420->3635, 724:+2540->2755, 725:+2782->2997, 726:+3024->3239, 727:+3266->3481, 728:+2584->2799, 729:+2826->3041, 730:+3068->3283, 731:+3310->3525, 732:+2606->2821, 733:+2848->3063, 734:+3090->3305, 735:+3332->3547, 736:+2628->2843, 737:+2870->3085, 738:+3112->3327, 739:+3354->3569, 740:+2650->2865, 741:+2892->3107, 742:+3134->3349, 743:+3376->3591, 744:+2562->2777, 745:+2804->3019, 746:+3046->3261, 747:+3288->3503, 800:+3477->3692, 801:+3499->3714
      //   977: iconst_2
      //   978: getfield 147	com/tencent/mm/plugin/expt/hellhound/core/a/a/a:qQS	Ljava/lang/Object;
      //   981: checkcast 149	com/tencent/mm/protocal/protobuf/dic
      //   984: astore 8
      //   986: aload_3
      //   987: new 151	com/tencent/mm/protocal/protobuf/dno
      //   990: dup
      //   991: invokespecial 152	com/tencent/mm/protocal/protobuf/dno:<init>	()V
      //   994: putfield 156	com/tencent/mm/protocal/protobuf/bnz:GIy	Lcom/tencent/mm/protocal/protobuf/dno;
      //   997: aload 8
      //   999: getfield 157	com/tencent/mm/protocal/protobuf/dic:GIy	Lcom/tencent/mm/protocal/protobuf/dno;
      //   1002: ifnull +48 -> 1050
      //   1005: aload_3
      //   1006: getfield 156	com/tencent/mm/protocal/protobuf/bnz:GIy	Lcom/tencent/mm/protocal/protobuf/dno;
      //   1009: aload 8
      //   1011: getfield 157	com/tencent/mm/protocal/protobuf/dic:GIy	Lcom/tencent/mm/protocal/protobuf/dno;
      //   1014: getfield 161	com/tencent/mm/protocal/protobuf/dno:activityName	Ljava/lang/String;
      //   1017: putfield 161	com/tencent/mm/protocal/protobuf/dno:activityName	Ljava/lang/String;
      //   1020: aload_3
      //   1021: getfield 156	com/tencent/mm/protocal/protobuf/bnz:GIy	Lcom/tencent/mm/protocal/protobuf/dno;
      //   1024: aload 8
      //   1026: getfield 157	com/tencent/mm/protocal/protobuf/dic:GIy	Lcom/tencent/mm/protocal/protobuf/dno;
      //   1029: getfield 164	com/tencent/mm/protocal/protobuf/dno:aHQ	I
      //   1032: putfield 164	com/tencent/mm/protocal/protobuf/dno:aHQ	I
      //   1035: aload_3
      //   1036: getfield 156	com/tencent/mm/protocal/protobuf/bnz:GIy	Lcom/tencent/mm/protocal/protobuf/dno;
      //   1039: aload 8
      //   1041: getfield 157	com/tencent/mm/protocal/protobuf/dic:GIy	Lcom/tencent/mm/protocal/protobuf/dno;
      //   1044: getfield 168	com/tencent/mm/protocal/protobuf/dno:timestamp	J
      //   1047: putfield 168	com/tencent/mm/protocal/protobuf/dno:timestamp	J
      //   1050: aload_3
      //   1051: new 151	com/tencent/mm/protocal/protobuf/dno
      //   1054: dup
      //   1055: invokespecial 152	com/tencent/mm/protocal/protobuf/dno:<init>	()V
      //   1058: putfield 171	com/tencent/mm/protocal/protobuf/bnz:GIz	Lcom/tencent/mm/protocal/protobuf/dno;
      //   1061: aload 8
      //   1063: getfield 172	com/tencent/mm/protocal/protobuf/dic:GIz	Lcom/tencent/mm/protocal/protobuf/dno;
      //   1066: ifnull +48 -> 1114
      //   1069: aload_3
      //   1070: getfield 171	com/tencent/mm/protocal/protobuf/bnz:GIz	Lcom/tencent/mm/protocal/protobuf/dno;
      //   1073: aload 8
      //   1075: getfield 172	com/tencent/mm/protocal/protobuf/dic:GIz	Lcom/tencent/mm/protocal/protobuf/dno;
      //   1078: getfield 161	com/tencent/mm/protocal/protobuf/dno:activityName	Ljava/lang/String;
      //   1081: putfield 161	com/tencent/mm/protocal/protobuf/dno:activityName	Ljava/lang/String;
      //   1084: aload_3
      //   1085: getfield 171	com/tencent/mm/protocal/protobuf/bnz:GIz	Lcom/tencent/mm/protocal/protobuf/dno;
      //   1088: aload 8
      //   1090: getfield 172	com/tencent/mm/protocal/protobuf/dic:GIz	Lcom/tencent/mm/protocal/protobuf/dno;
      //   1093: getfield 164	com/tencent/mm/protocal/protobuf/dno:aHQ	I
      //   1096: putfield 164	com/tencent/mm/protocal/protobuf/dno:aHQ	I
      //   1099: aload_3
      //   1100: getfield 171	com/tencent/mm/protocal/protobuf/bnz:GIz	Lcom/tencent/mm/protocal/protobuf/dno;
      //   1103: aload 8
      //   1105: getfield 172	com/tencent/mm/protocal/protobuf/dic:GIz	Lcom/tencent/mm/protocal/protobuf/dno;
      //   1108: getfield 168	com/tencent/mm/protocal/protobuf/dno:timestamp	J
      //   1111: putfield 168	com/tencent/mm/protocal/protobuf/dno:timestamp	J
      //   1114: aload_3
      //   1115: aload 8
      //   1117: getfield 176	com/tencent/mm/protocal/protobuf/dic:Grz	Z
      //   1120: putfield 177	com/tencent/mm/protocal/protobuf/bnz:Grz	Z
      //   1123: aload_3
      //   1124: aload 8
      //   1126: getfield 180	com/tencent/mm/protocal/protobuf/dic:Grw	Ljava/lang/String;
      //   1129: putfield 181	com/tencent/mm/protocal/protobuf/bnz:Grw	Ljava/lang/String;
      //   1132: aload_3
      //   1133: aload 8
      //   1135: getfield 184	com/tencent/mm/protocal/protobuf/dic:flags	I
      //   1138: putfield 185	com/tencent/mm/protocal/protobuf/bnz:flags	I
      //   1141: aload_3
      //   1142: aload 8
      //   1144: getfield 188	com/tencent/mm/protocal/protobuf/dic:Gry	Ljava/lang/String;
      //   1147: putfield 189	com/tencent/mm/protocal/protobuf/bnz:Gry	Ljava/lang/String;
      //   1150: aload_3
      //   1151: aload 8
      //   1153: getfield 192	com/tencent/mm/protocal/protobuf/dic:GIA	Ljava/lang/String;
      //   1156: putfield 193	com/tencent/mm/protocal/protobuf/bnz:GIA	Ljava/lang/String;
      //   1159: aload_3
      //   1160: aload 8
      //   1162: getfield 196	com/tencent/mm/protocal/protobuf/dic:GIB	Ljava/lang/String;
      //   1165: putfield 197	com/tencent/mm/protocal/protobuf/bnz:GIB	Ljava/lang/String;
      //   1168: aload_3
      //   1169: aload 8
      //   1171: getfield 198	com/tencent/mm/protocal/protobuf/dic:timestamp	J
      //   1174: putfield 199	com/tencent/mm/protocal/protobuf/bnz:timestamp	J
      //   1177: aload_3
      //   1178: bipush 100
      //   1180: putfield 200	com/tencent/mm/protocal/protobuf/bnz:msgType	I
      //   1183: goto +2562 -> 3745
      //   1186: aload 5
      //   1188: getfield 147	com/tencent/mm/plugin/expt/hellhound/core/a/a/a:qQS	Ljava/lang/Object;
      //   1191: checkcast 151	com/tencent/mm/protocal/protobuf/dno
      //   1194: astore 8
      //   1196: aload_3
      //   1197: new 151	com/tencent/mm/protocal/protobuf/dno
      //   1200: dup
      //   1201: invokespecial 152	com/tencent/mm/protocal/protobuf/dno:<init>	()V
      //   1204: putfield 171	com/tencent/mm/protocal/protobuf/bnz:GIz	Lcom/tencent/mm/protocal/protobuf/dno;
      //   1207: aload_3
      //   1208: getfield 171	com/tencent/mm/protocal/protobuf/bnz:GIz	Lcom/tencent/mm/protocal/protobuf/dno;
      //   1211: aload 8
      //   1213: getfield 161	com/tencent/mm/protocal/protobuf/dno:activityName	Ljava/lang/String;
      //   1216: putfield 161	com/tencent/mm/protocal/protobuf/dno:activityName	Ljava/lang/String;
      //   1219: aload_3
      //   1220: getfield 171	com/tencent/mm/protocal/protobuf/bnz:GIz	Lcom/tencent/mm/protocal/protobuf/dno;
      //   1223: aload 8
      //   1225: getfield 164	com/tencent/mm/protocal/protobuf/dno:aHQ	I
      //   1228: putfield 164	com/tencent/mm/protocal/protobuf/dno:aHQ	I
      //   1231: aload_3
      //   1232: getfield 171	com/tencent/mm/protocal/protobuf/bnz:GIz	Lcom/tencent/mm/protocal/protobuf/dno;
      //   1235: aload 8
      //   1237: getfield 168	com/tencent/mm/protocal/protobuf/dno:timestamp	J
      //   1240: putfield 168	com/tencent/mm/protocal/protobuf/dno:timestamp	J
      //   1243: aload_3
      //   1244: bipush 101
      //   1246: putfield 200	com/tencent/mm/protocal/protobuf/bnz:msgType	I
      //   1249: goto +2496 -> 3745
      //   1252: aload 5
      //   1254: getfield 147	com/tencent/mm/plugin/expt/hellhound/core/a/a/a:qQS	Ljava/lang/Object;
      //   1257: checkcast 202	com/tencent/mm/protocal/protobuf/cbm
      //   1260: astore 8
      //   1262: aload_3
      //   1263: new 151	com/tencent/mm/protocal/protobuf/dno
      //   1266: dup
      //   1267: invokespecial 152	com/tencent/mm/protocal/protobuf/dno:<init>	()V
      //   1270: putfield 171	com/tencent/mm/protocal/protobuf/bnz:GIz	Lcom/tencent/mm/protocal/protobuf/dno;
      //   1273: aload_3
      //   1274: getfield 171	com/tencent/mm/protocal/protobuf/bnz:GIz	Lcom/tencent/mm/protocal/protobuf/dno;
      //   1277: aload 8
      //   1279: getfield 205	com/tencent/mm/protocal/protobuf/cbm:Grv	Lcom/tencent/mm/protocal/protobuf/dno;
      //   1282: getfield 161	com/tencent/mm/protocal/protobuf/dno:activityName	Ljava/lang/String;
      //   1285: putfield 161	com/tencent/mm/protocal/protobuf/dno:activityName	Ljava/lang/String;
      //   1288: aload_3
      //   1289: getfield 171	com/tencent/mm/protocal/protobuf/bnz:GIz	Lcom/tencent/mm/protocal/protobuf/dno;
      //   1292: aload 8
      //   1294: getfield 205	com/tencent/mm/protocal/protobuf/cbm:Grv	Lcom/tencent/mm/protocal/protobuf/dno;
      //   1297: getfield 164	com/tencent/mm/protocal/protobuf/dno:aHQ	I
      //   1300: putfield 164	com/tencent/mm/protocal/protobuf/dno:aHQ	I
      //   1303: aload_3
      //   1304: getfield 171	com/tencent/mm/protocal/protobuf/bnz:GIz	Lcom/tencent/mm/protocal/protobuf/dno;
      //   1307: aload 8
      //   1309: getfield 205	com/tencent/mm/protocal/protobuf/cbm:Grv	Lcom/tencent/mm/protocal/protobuf/dno;
      //   1312: getfield 168	com/tencent/mm/protocal/protobuf/dno:timestamp	J
      //   1315: putfield 168	com/tencent/mm/protocal/protobuf/dno:timestamp	J
      //   1318: aload_3
      //   1319: aload 8
      //   1321: getfield 208	com/tencent/mm/protocal/protobuf/cbm:GID	Z
      //   1324: putfield 209	com/tencent/mm/protocal/protobuf/bnz:GID	Z
      //   1327: aload_3
      //   1328: bipush 102
      //   1330: putfield 200	com/tencent/mm/protocal/protobuf/bnz:msgType	I
      //   1333: goto +2412 -> 3745
      //   1336: aload 5
      //   1338: getfield 147	com/tencent/mm/plugin/expt/hellhound/core/a/a/a:qQS	Ljava/lang/Object;
      //   1341: checkcast 211	com/tencent/mm/protocal/protobuf/cdx
      //   1344: astore 8
      //   1346: aload_3
      //   1347: new 151	com/tencent/mm/protocal/protobuf/dno
      //   1350: dup
      //   1351: invokespecial 152	com/tencent/mm/protocal/protobuf/dno:<init>	()V
      //   1354: putfield 171	com/tencent/mm/protocal/protobuf/bnz:GIz	Lcom/tencent/mm/protocal/protobuf/dno;
      //   1357: aload_3
      //   1358: getfield 171	com/tencent/mm/protocal/protobuf/bnz:GIz	Lcom/tencent/mm/protocal/protobuf/dno;
      //   1361: aload 8
      //   1363: getfield 212	com/tencent/mm/protocal/protobuf/cdx:Grv	Lcom/tencent/mm/protocal/protobuf/dno;
      //   1366: getfield 161	com/tencent/mm/protocal/protobuf/dno:activityName	Ljava/lang/String;
      //   1369: putfield 161	com/tencent/mm/protocal/protobuf/dno:activityName	Ljava/lang/String;
      //   1372: aload_3
      //   1373: getfield 171	com/tencent/mm/protocal/protobuf/bnz:GIz	Lcom/tencent/mm/protocal/protobuf/dno;
      //   1376: aload 8
      //   1378: getfield 212	com/tencent/mm/protocal/protobuf/cdx:Grv	Lcom/tencent/mm/protocal/protobuf/dno;
      //   1381: getfield 164	com/tencent/mm/protocal/protobuf/dno:aHQ	I
      //   1384: putfield 164	com/tencent/mm/protocal/protobuf/dno:aHQ	I
      //   1387: aload_3
      //   1388: getfield 171	com/tencent/mm/protocal/protobuf/bnz:GIz	Lcom/tencent/mm/protocal/protobuf/dno;
      //   1391: aload 8
      //   1393: getfield 212	com/tencent/mm/protocal/protobuf/cdx:Grv	Lcom/tencent/mm/protocal/protobuf/dno;
      //   1396: getfield 168	com/tencent/mm/protocal/protobuf/dno:timestamp	J
      //   1399: putfield 168	com/tencent/mm/protocal/protobuf/dno:timestamp	J
      //   1402: aload_3
      //   1403: aload 8
      //   1405: getfield 213	com/tencent/mm/protocal/protobuf/cdx:flags	I
      //   1408: putfield 185	com/tencent/mm/protocal/protobuf/bnz:flags	I
      //   1411: aload_3
      //   1412: sipush 200
      //   1415: putfield 200	com/tencent/mm/protocal/protobuf/bnz:msgType	I
      //   1418: goto +2327 -> 3745
      //   1421: aload 5
      //   1423: getfield 147	com/tencent/mm/plugin/expt/hellhound/core/a/a/a:qQS	Ljava/lang/Object;
      //   1426: checkcast 211	com/tencent/mm/protocal/protobuf/cdx
      //   1429: astore 8
      //   1431: aload_3
      //   1432: new 151	com/tencent/mm/protocal/protobuf/dno
      //   1435: dup
      //   1436: invokespecial 152	com/tencent/mm/protocal/protobuf/dno:<init>	()V
      //   1439: putfield 171	com/tencent/mm/protocal/protobuf/bnz:GIz	Lcom/tencent/mm/protocal/protobuf/dno;
      //   1442: aload_3
      //   1443: getfield 171	com/tencent/mm/protocal/protobuf/bnz:GIz	Lcom/tencent/mm/protocal/protobuf/dno;
      //   1446: aload 8
      //   1448: getfield 212	com/tencent/mm/protocal/protobuf/cdx:Grv	Lcom/tencent/mm/protocal/protobuf/dno;
      //   1451: getfield 161	com/tencent/mm/protocal/protobuf/dno:activityName	Ljava/lang/String;
      //   1454: putfield 161	com/tencent/mm/protocal/protobuf/dno:activityName	Ljava/lang/String;
      //   1457: aload_3
      //   1458: getfield 171	com/tencent/mm/protocal/protobuf/bnz:GIz	Lcom/tencent/mm/protocal/protobuf/dno;
      //   1461: aload 8
      //   1463: getfield 212	com/tencent/mm/protocal/protobuf/cdx:Grv	Lcom/tencent/mm/protocal/protobuf/dno;
      //   1466: getfield 164	com/tencent/mm/protocal/protobuf/dno:aHQ	I
      //   1469: putfield 164	com/tencent/mm/protocal/protobuf/dno:aHQ	I
      //   1472: aload_3
      //   1473: getfield 171	com/tencent/mm/protocal/protobuf/bnz:GIz	Lcom/tencent/mm/protocal/protobuf/dno;
      //   1476: aload 8
      //   1478: getfield 212	com/tencent/mm/protocal/protobuf/cdx:Grv	Lcom/tencent/mm/protocal/protobuf/dno;
      //   1481: getfield 168	com/tencent/mm/protocal/protobuf/dno:timestamp	J
      //   1484: putfield 168	com/tencent/mm/protocal/protobuf/dno:timestamp	J
      //   1487: aload_3
      //   1488: aload 8
      //   1490: getfield 213	com/tencent/mm/protocal/protobuf/cdx:flags	I
      //   1493: putfield 185	com/tencent/mm/protocal/protobuf/bnz:flags	I
      //   1496: aload_3
      //   1497: sipush 201
      //   1500: putfield 200	com/tencent/mm/protocal/protobuf/bnz:msgType	I
      //   1503: goto +2242 -> 3745
      //   1506: aload 5
      //   1508: getfield 147	com/tencent/mm/plugin/expt/hellhound/core/a/a/a:qQS	Ljava/lang/Object;
      //   1511: checkcast 151	com/tencent/mm/protocal/protobuf/dno
      //   1514: astore 8
      //   1516: aload_3
      //   1517: new 151	com/tencent/mm/protocal/protobuf/dno
      //   1520: dup
      //   1521: invokespecial 152	com/tencent/mm/protocal/protobuf/dno:<init>	()V
      //   1524: putfield 171	com/tencent/mm/protocal/protobuf/bnz:GIz	Lcom/tencent/mm/protocal/protobuf/dno;
      //   1527: aload_3
      //   1528: getfield 171	com/tencent/mm/protocal/protobuf/bnz:GIz	Lcom/tencent/mm/protocal/protobuf/dno;
      //   1531: aload 8
      //   1533: getfield 161	com/tencent/mm/protocal/protobuf/dno:activityName	Ljava/lang/String;
      //   1536: putfield 161	com/tencent/mm/protocal/protobuf/dno:activityName	Ljava/lang/String;
      //   1539: aload_3
      //   1540: getfield 171	com/tencent/mm/protocal/protobuf/bnz:GIz	Lcom/tencent/mm/protocal/protobuf/dno;
      //   1543: aload 8
      //   1545: getfield 164	com/tencent/mm/protocal/protobuf/dno:aHQ	I
      //   1548: putfield 164	com/tencent/mm/protocal/protobuf/dno:aHQ	I
      //   1551: aload_3
      //   1552: getfield 171	com/tencent/mm/protocal/protobuf/bnz:GIz	Lcom/tencent/mm/protocal/protobuf/dno;
      //   1555: aload 8
      //   1557: getfield 168	com/tencent/mm/protocal/protobuf/dno:timestamp	J
      //   1560: putfield 168	com/tencent/mm/protocal/protobuf/dno:timestamp	J
      //   1563: aload_3
      //   1564: sipush 202
      //   1567: putfield 200	com/tencent/mm/protocal/protobuf/bnz:msgType	I
      //   1570: goto +2175 -> 3745
      //   1573: aload_3
      //   1574: aload 5
      //   1576: getfield 147	com/tencent/mm/plugin/expt/hellhound/core/a/a/a:qQS	Ljava/lang/Object;
      //   1579: checkcast 215	java/lang/String
      //   1582: putfield 189	com/tencent/mm/protocal/protobuf/bnz:Gry	Ljava/lang/String;
      //   1585: aload_3
      //   1586: sipush 222
      //   1589: putfield 200	com/tencent/mm/protocal/protobuf/bnz:msgType	I
      //   1592: goto +2153 -> 3745
      //   1595: aload 5
      //   1597: getfield 147	com/tencent/mm/plugin/expt/hellhound/core/a/a/a:qQS	Ljava/lang/Object;
      //   1600: checkcast 217	com/tencent/mm/protocal/protobuf/cdy
      //   1603: astore 8
      //   1605: aload_3
      //   1606: new 151	com/tencent/mm/protocal/protobuf/dno
      //   1609: dup
      //   1610: invokespecial 152	com/tencent/mm/protocal/protobuf/dno:<init>	()V
      //   1613: putfield 171	com/tencent/mm/protocal/protobuf/bnz:GIz	Lcom/tencent/mm/protocal/protobuf/dno;
      //   1616: aload_3
      //   1617: getfield 171	com/tencent/mm/protocal/protobuf/bnz:GIz	Lcom/tencent/mm/protocal/protobuf/dno;
      //   1620: aload 8
      //   1622: getfield 218	com/tencent/mm/protocal/protobuf/cdy:Grv	Lcom/tencent/mm/protocal/protobuf/dno;
      //   1625: getfield 161	com/tencent/mm/protocal/protobuf/dno:activityName	Ljava/lang/String;
      //   1628: putfield 161	com/tencent/mm/protocal/protobuf/dno:activityName	Ljava/lang/String;
      //   1631: aload_3
      //   1632: getfield 171	com/tencent/mm/protocal/protobuf/bnz:GIz	Lcom/tencent/mm/protocal/protobuf/dno;
      //   1635: aload 8
      //   1637: getfield 218	com/tencent/mm/protocal/protobuf/cdy:Grv	Lcom/tencent/mm/protocal/protobuf/dno;
      //   1640: getfield 164	com/tencent/mm/protocal/protobuf/dno:aHQ	I
      //   1643: putfield 164	com/tencent/mm/protocal/protobuf/dno:aHQ	I
      //   1646: aload_3
      //   1647: getfield 171	com/tencent/mm/protocal/protobuf/bnz:GIz	Lcom/tencent/mm/protocal/protobuf/dno;
      //   1650: aload 8
      //   1652: getfield 218	com/tencent/mm/protocal/protobuf/cdy:Grv	Lcom/tencent/mm/protocal/protobuf/dno;
      //   1655: getfield 168	com/tencent/mm/protocal/protobuf/dno:timestamp	J
      //   1658: putfield 168	com/tencent/mm/protocal/protobuf/dno:timestamp	J
      //   1661: aload_3
      //   1662: aload 8
      //   1664: getfield 219	com/tencent/mm/protocal/protobuf/cdy:Grz	Z
      //   1667: putfield 177	com/tencent/mm/protocal/protobuf/bnz:Grz	Z
      //   1670: aload_3
      //   1671: aload 8
      //   1673: getfield 222	com/tencent/mm/protocal/protobuf/cdy:GIC	Z
      //   1676: putfield 223	com/tencent/mm/protocal/protobuf/bnz:GIC	Z
      //   1679: aload_3
      //   1680: aload 8
      //   1682: getfield 224	com/tencent/mm/protocal/protobuf/cdy:Grw	Ljava/lang/String;
      //   1685: putfield 181	com/tencent/mm/protocal/protobuf/bnz:Grw	Ljava/lang/String;
      //   1688: aload_3
      //   1689: sipush 203
      //   1692: putfield 200	com/tencent/mm/protocal/protobuf/bnz:msgType	I
      //   1695: goto +2050 -> 3745
      //   1698: aload 5
      //   1700: getfield 147	com/tencent/mm/plugin/expt/hellhound/core/a/a/a:qQS	Ljava/lang/Object;
      //   1703: checkcast 151	com/tencent/mm/protocal/protobuf/dno
      //   1706: astore 8
      //   1708: aload_3
      //   1709: new 151	com/tencent/mm/protocal/protobuf/dno
      //   1712: dup
      //   1713: invokespecial 152	com/tencent/mm/protocal/protobuf/dno:<init>	()V
      //   1716: putfield 171	com/tencent/mm/protocal/protobuf/bnz:GIz	Lcom/tencent/mm/protocal/protobuf/dno;
      //   1719: aload_3
      //   1720: getfield 171	com/tencent/mm/protocal/protobuf/bnz:GIz	Lcom/tencent/mm/protocal/protobuf/dno;
      //   1723: aload 8
      //   1725: getfield 161	com/tencent/mm/protocal/protobuf/dno:activityName	Ljava/lang/String;
      //   1728: putfield 161	com/tencent/mm/protocal/protobuf/dno:activityName	Ljava/lang/String;
      //   1731: aload_3
      //   1732: getfield 171	com/tencent/mm/protocal/protobuf/bnz:GIz	Lcom/tencent/mm/protocal/protobuf/dno;
      //   1735: aload 8
      //   1737: getfield 164	com/tencent/mm/protocal/protobuf/dno:aHQ	I
      //   1740: putfield 164	com/tencent/mm/protocal/protobuf/dno:aHQ	I
      //   1743: aload_3
      //   1744: getfield 171	com/tencent/mm/protocal/protobuf/bnz:GIz	Lcom/tencent/mm/protocal/protobuf/dno;
      //   1747: aload 8
      //   1749: getfield 168	com/tencent/mm/protocal/protobuf/dno:timestamp	J
      //   1752: putfield 168	com/tencent/mm/protocal/protobuf/dno:timestamp	J
      //   1755: aload_3
      //   1756: sipush 204
      //   1759: putfield 200	com/tencent/mm/protocal/protobuf/bnz:msgType	I
      //   1762: goto +1983 -> 3745
      //   1765: aload 5
      //   1767: getfield 147	com/tencent/mm/plugin/expt/hellhound/core/a/a/a:qQS	Ljava/lang/Object;
      //   1770: checkcast 217	com/tencent/mm/protocal/protobuf/cdy
      //   1773: astore 8
      //   1775: aload_3
      //   1776: new 151	com/tencent/mm/protocal/protobuf/dno
      //   1779: dup
      //   1780: invokespecial 152	com/tencent/mm/protocal/protobuf/dno:<init>	()V
      //   1783: putfield 171	com/tencent/mm/protocal/protobuf/bnz:GIz	Lcom/tencent/mm/protocal/protobuf/dno;
      //   1786: aload_3
      //   1787: getfield 171	com/tencent/mm/protocal/protobuf/bnz:GIz	Lcom/tencent/mm/protocal/protobuf/dno;
      //   1790: aload 8
      //   1792: getfield 218	com/tencent/mm/protocal/protobuf/cdy:Grv	Lcom/tencent/mm/protocal/protobuf/dno;
      //   1795: getfield 161	com/tencent/mm/protocal/protobuf/dno:activityName	Ljava/lang/String;
      //   1798: putfield 161	com/tencent/mm/protocal/protobuf/dno:activityName	Ljava/lang/String;
      //   1801: aload_3
      //   1802: getfield 171	com/tencent/mm/protocal/protobuf/bnz:GIz	Lcom/tencent/mm/protocal/protobuf/dno;
      //   1805: aload 8
      //   1807: getfield 218	com/tencent/mm/protocal/protobuf/cdy:Grv	Lcom/tencent/mm/protocal/protobuf/dno;
      //   1810: getfield 164	com/tencent/mm/protocal/protobuf/dno:aHQ	I
      //   1813: putfield 164	com/tencent/mm/protocal/protobuf/dno:aHQ	I
      //   1816: aload_3
      //   1817: getfield 171	com/tencent/mm/protocal/protobuf/bnz:GIz	Lcom/tencent/mm/protocal/protobuf/dno;
      //   1820: aload 8
      //   1822: getfield 218	com/tencent/mm/protocal/protobuf/cdy:Grv	Lcom/tencent/mm/protocal/protobuf/dno;
      //   1825: getfield 168	com/tencent/mm/protocal/protobuf/dno:timestamp	J
      //   1828: putfield 168	com/tencent/mm/protocal/protobuf/dno:timestamp	J
      //   1831: aload_3
      //   1832: aload 8
      //   1834: getfield 219	com/tencent/mm/protocal/protobuf/cdy:Grz	Z
      //   1837: putfield 177	com/tencent/mm/protocal/protobuf/bnz:Grz	Z
      //   1840: aload_3
      //   1841: aload 8
      //   1843: getfield 222	com/tencent/mm/protocal/protobuf/cdy:GIC	Z
      //   1846: putfield 223	com/tencent/mm/protocal/protobuf/bnz:GIC	Z
      //   1849: aload_3
      //   1850: aload 8
      //   1852: getfield 224	com/tencent/mm/protocal/protobuf/cdy:Grw	Ljava/lang/String;
      //   1855: putfield 181	com/tencent/mm/protocal/protobuf/bnz:Grw	Ljava/lang/String;
      //   1858: aload_3
      //   1859: sipush 205
      //   1862: putfield 200	com/tencent/mm/protocal/protobuf/bnz:msgType	I
      //   1865: goto +1880 -> 3745
      //   1868: aload 5
      //   1870: getfield 147	com/tencent/mm/plugin/expt/hellhound/core/a/a/a:qQS	Ljava/lang/Object;
      //   1873: checkcast 151	com/tencent/mm/protocal/protobuf/dno
      //   1876: astore 8
      //   1878: aload_3
      //   1879: new 151	com/tencent/mm/protocal/protobuf/dno
      //   1882: dup
      //   1883: invokespecial 152	com/tencent/mm/protocal/protobuf/dno:<init>	()V
      //   1886: putfield 171	com/tencent/mm/protocal/protobuf/bnz:GIz	Lcom/tencent/mm/protocal/protobuf/dno;
      //   1889: aload_3
      //   1890: getfield 171	com/tencent/mm/protocal/protobuf/bnz:GIz	Lcom/tencent/mm/protocal/protobuf/dno;
      //   1893: aload 8
      //   1895: getfield 161	com/tencent/mm/protocal/protobuf/dno:activityName	Ljava/lang/String;
      //   1898: putfield 161	com/tencent/mm/protocal/protobuf/dno:activityName	Ljava/lang/String;
      //   1901: aload_3
      //   1902: getfield 171	com/tencent/mm/protocal/protobuf/bnz:GIz	Lcom/tencent/mm/protocal/protobuf/dno;
      //   1905: aload 8
      //   1907: getfield 164	com/tencent/mm/protocal/protobuf/dno:aHQ	I
      //   1910: putfield 164	com/tencent/mm/protocal/protobuf/dno:aHQ	I
      //   1913: aload_3
      //   1914: getfield 171	com/tencent/mm/protocal/protobuf/bnz:GIz	Lcom/tencent/mm/protocal/protobuf/dno;
      //   1917: aload 8
      //   1919: getfield 168	com/tencent/mm/protocal/protobuf/dno:timestamp	J
      //   1922: putfield 168	com/tencent/mm/protocal/protobuf/dno:timestamp	J
      //   1925: aload_3
      //   1926: sipush 206
      //   1929: putfield 200	com/tencent/mm/protocal/protobuf/bnz:msgType	I
      //   1932: goto +1813 -> 3745
      //   1935: aload 5
      //   1937: getfield 147	com/tencent/mm/plugin/expt/hellhound/core/a/a/a:qQS	Ljava/lang/Object;
      //   1940: checkcast 151	com/tencent/mm/protocal/protobuf/dno
      //   1943: astore 8
      //   1945: aload_3
      //   1946: new 151	com/tencent/mm/protocal/protobuf/dno
      //   1949: dup
      //   1950: invokespecial 152	com/tencent/mm/protocal/protobuf/dno:<init>	()V
      //   1953: putfield 171	com/tencent/mm/protocal/protobuf/bnz:GIz	Lcom/tencent/mm/protocal/protobuf/dno;
      //   1956: aload_3
      //   1957: getfield 171	com/tencent/mm/protocal/protobuf/bnz:GIz	Lcom/tencent/mm/protocal/protobuf/dno;
      //   1960: aload 8
      //   1962: getfield 161	com/tencent/mm/protocal/protobuf/dno:activityName	Ljava/lang/String;
      //   1965: putfield 161	com/tencent/mm/protocal/protobuf/dno:activityName	Ljava/lang/String;
      //   1968: aload_3
      //   1969: getfield 171	com/tencent/mm/protocal/protobuf/bnz:GIz	Lcom/tencent/mm/protocal/protobuf/dno;
      //   1972: aload 8
      //   1974: getfield 164	com/tencent/mm/protocal/protobuf/dno:aHQ	I
      //   1977: putfield 164	com/tencent/mm/protocal/protobuf/dno:aHQ	I
      //   1980: aload_3
      //   1981: getfield 171	com/tencent/mm/protocal/protobuf/bnz:GIz	Lcom/tencent/mm/protocal/protobuf/dno;
      //   1984: aload 8
      //   1986: getfield 168	com/tencent/mm/protocal/protobuf/dno:timestamp	J
      //   1989: putfield 168	com/tencent/mm/protocal/protobuf/dno:timestamp	J
      //   1992: aload_3
      //   1993: sipush 207
      //   1996: putfield 200	com/tencent/mm/protocal/protobuf/bnz:msgType	I
      //   1999: goto +1746 -> 3745
      //   2002: aload_3
      //   2003: aload 5
      //   2005: getfield 116	com/tencent/mm/plugin/expt/hellhound/core/a/a/a:msgType	I
      //   2008: putfield 200	com/tencent/mm/protocal/protobuf/bnz:msgType	I
      //   2011: goto +1734 -> 3745
      //   2014: aload_3
      //   2015: aload 5
      //   2017: getfield 147	com/tencent/mm/plugin/expt/hellhound/core/a/a/a:qQS	Ljava/lang/Object;
      //   2020: checkcast 226	java/lang/Long
      //   2023: invokevirtual 230	java/lang/Long:longValue	()J
      //   2026: putfield 199	com/tencent/mm/protocal/protobuf/bnz:timestamp	J
      //   2029: aload_3
      //   2030: aload 5
      //   2032: getfield 116	com/tencent/mm/plugin/expt/hellhound/core/a/a/a:msgType	I
      //   2035: putfield 200	com/tencent/mm/protocal/protobuf/bnz:msgType	I
      //   2038: goto +1707 -> 3745
      //   2041: aload 5
      //   2043: getfield 147	com/tencent/mm/plugin/expt/hellhound/core/a/a/a:qQS	Ljava/lang/Object;
      //   2046: checkcast 232	com/tencent/mm/protocal/protobuf/atl
      //   2049: astore 8
      //   2051: aload_3
      //   2052: new 151	com/tencent/mm/protocal/protobuf/dno
      //   2055: dup
      //   2056: invokespecial 152	com/tencent/mm/protocal/protobuf/dno:<init>	()V
      //   2059: putfield 171	com/tencent/mm/protocal/protobuf/bnz:GIz	Lcom/tencent/mm/protocal/protobuf/dno;
      //   2062: aload 8
      //   2064: getfield 233	com/tencent/mm/protocal/protobuf/atl:Grv	Lcom/tencent/mm/protocal/protobuf/dno;
      //   2067: ifnull +48 -> 2115
      //   2070: aload_3
      //   2071: getfield 171	com/tencent/mm/protocal/protobuf/bnz:GIz	Lcom/tencent/mm/protocal/protobuf/dno;
      //   2074: aload 8
      //   2076: getfield 233	com/tencent/mm/protocal/protobuf/atl:Grv	Lcom/tencent/mm/protocal/protobuf/dno;
      //   2079: getfield 161	com/tencent/mm/protocal/protobuf/dno:activityName	Ljava/lang/String;
      //   2082: putfield 161	com/tencent/mm/protocal/protobuf/dno:activityName	Ljava/lang/String;
      //   2085: aload_3
      //   2086: getfield 171	com/tencent/mm/protocal/protobuf/bnz:GIz	Lcom/tencent/mm/protocal/protobuf/dno;
      //   2089: aload 8
      //   2091: getfield 233	com/tencent/mm/protocal/protobuf/atl:Grv	Lcom/tencent/mm/protocal/protobuf/dno;
      //   2094: getfield 164	com/tencent/mm/protocal/protobuf/dno:aHQ	I
      //   2097: putfield 164	com/tencent/mm/protocal/protobuf/dno:aHQ	I
      //   2100: aload_3
      //   2101: getfield 171	com/tencent/mm/protocal/protobuf/bnz:GIz	Lcom/tencent/mm/protocal/protobuf/dno;
      //   2104: aload 8
      //   2106: getfield 233	com/tencent/mm/protocal/protobuf/atl:Grv	Lcom/tencent/mm/protocal/protobuf/dno;
      //   2109: getfield 168	com/tencent/mm/protocal/protobuf/dno:timestamp	J
      //   2112: putfield 168	com/tencent/mm/protocal/protobuf/dno:timestamp	J
      //   2115: aload_3
      //   2116: aload 8
      //   2118: getfield 234	com/tencent/mm/protocal/protobuf/atl:Gry	Ljava/lang/String;
      //   2121: putfield 189	com/tencent/mm/protocal/protobuf/bnz:Gry	Ljava/lang/String;
      //   2124: aload_3
      //   2125: aload 8
      //   2127: getfield 235	com/tencent/mm/protocal/protobuf/atl:Grz	Z
      //   2130: putfield 177	com/tencent/mm/protocal/protobuf/bnz:Grz	Z
      //   2133: aload_3
      //   2134: aload 8
      //   2136: getfield 236	com/tencent/mm/protocal/protobuf/atl:Grw	Ljava/lang/String;
      //   2139: putfield 181	com/tencent/mm/protocal/protobuf/bnz:Grw	Ljava/lang/String;
      //   2142: aload_3
      //   2143: aload 8
      //   2145: getfield 239	com/tencent/mm/protocal/protobuf/atl:Grx	I
      //   2148: putfield 240	com/tencent/mm/protocal/protobuf/bnz:Grx	I
      //   2151: aload_3
      //   2152: aload 8
      //   2154: getfield 243	com/tencent/mm/protocal/protobuf/atl:GrA	Z
      //   2157: putfield 244	com/tencent/mm/protocal/protobuf/bnz:GrA	Z
      //   2160: aload_3
      //   2161: aload 8
      //   2163: getfield 245	com/tencent/mm/protocal/protobuf/atl:timestamp	J
      //   2166: putfield 199	com/tencent/mm/protocal/protobuf/bnz:timestamp	J
      //   2169: aload_3
      //   2170: iconst_5
      //   2171: putfield 200	com/tencent/mm/protocal/protobuf/bnz:msgType	I
      //   2174: goto +1571 -> 3745
      //   2177: aload 5
      //   2179: getfield 147	com/tencent/mm/plugin/expt/hellhound/core/a/a/a:qQS	Ljava/lang/Object;
      //   2182: checkcast 247	com/tencent/mm/protocal/protobuf/atk
      //   2185: astore 8
      //   2187: aload_3
      //   2188: new 151	com/tencent/mm/protocal/protobuf/dno
      //   2191: dup
      //   2192: invokespecial 152	com/tencent/mm/protocal/protobuf/dno:<init>	()V
      //   2195: putfield 171	com/tencent/mm/protocal/protobuf/bnz:GIz	Lcom/tencent/mm/protocal/protobuf/dno;
      //   2198: aload 8
      //   2200: getfield 248	com/tencent/mm/protocal/protobuf/atk:Grv	Lcom/tencent/mm/protocal/protobuf/dno;
      //   2203: ifnull +48 -> 2251
      //   2206: aload_3
      //   2207: getfield 171	com/tencent/mm/protocal/protobuf/bnz:GIz	Lcom/tencent/mm/protocal/protobuf/dno;
      //   2210: aload 8
      //   2212: getfield 248	com/tencent/mm/protocal/protobuf/atk:Grv	Lcom/tencent/mm/protocal/protobuf/dno;
      //   2215: getfield 161	com/tencent/mm/protocal/protobuf/dno:activityName	Ljava/lang/String;
      //   2218: putfield 161	com/tencent/mm/protocal/protobuf/dno:activityName	Ljava/lang/String;
      //   2221: aload_3
      //   2222: getfield 171	com/tencent/mm/protocal/protobuf/bnz:GIz	Lcom/tencent/mm/protocal/protobuf/dno;
      //   2225: aload 8
      //   2227: getfield 248	com/tencent/mm/protocal/protobuf/atk:Grv	Lcom/tencent/mm/protocal/protobuf/dno;
      //   2230: getfield 164	com/tencent/mm/protocal/protobuf/dno:aHQ	I
      //   2233: putfield 164	com/tencent/mm/protocal/protobuf/dno:aHQ	I
      //   2236: aload_3
      //   2237: getfield 171	com/tencent/mm/protocal/protobuf/bnz:GIz	Lcom/tencent/mm/protocal/protobuf/dno;
      //   2240: aload 8
      //   2242: getfield 248	com/tencent/mm/protocal/protobuf/atk:Grv	Lcom/tencent/mm/protocal/protobuf/dno;
      //   2245: getfield 168	com/tencent/mm/protocal/protobuf/dno:timestamp	J
      //   2248: putfield 168	com/tencent/mm/protocal/protobuf/dno:timestamp	J
      //   2251: aload_3
      //   2252: aload 8
      //   2254: getfield 249	com/tencent/mm/protocal/protobuf/atk:Grw	Ljava/lang/String;
      //   2257: putfield 181	com/tencent/mm/protocal/protobuf/bnz:Grw	Ljava/lang/String;
      //   2260: aload_3
      //   2261: aload 8
      //   2263: getfield 250	com/tencent/mm/protocal/protobuf/atk:Grx	I
      //   2266: putfield 240	com/tencent/mm/protocal/protobuf/bnz:Grx	I
      //   2269: aload_3
      //   2270: aload 8
      //   2272: getfield 251	com/tencent/mm/protocal/protobuf/atk:timestamp	J
      //   2275: putfield 199	com/tencent/mm/protocal/protobuf/bnz:timestamp	J
      //   2278: aload_3
      //   2279: bipush 6
      //   2281: putfield 200	com/tencent/mm/protocal/protobuf/bnz:msgType	I
      //   2284: goto +1461 -> 3745
      //   2287: aload_3
      //   2288: aload 5
      //   2290: getfield 147	com/tencent/mm/plugin/expt/hellhound/core/a/a/a:qQS	Ljava/lang/Object;
      //   2293: checkcast 118	java/lang/Integer
      //   2296: invokevirtual 254	java/lang/Integer:intValue	()I
      //   2299: putfield 185	com/tencent/mm/protocal/protobuf/bnz:flags	I
      //   2302: aload_3
      //   2303: aload 5
      //   2305: getfield 116	com/tencent/mm/plugin/expt/hellhound/core/a/a/a:msgType	I
      //   2308: putfield 200	com/tencent/mm/protocal/protobuf/bnz:msgType	I
      //   2311: goto +1434 -> 3745
      //   2314: aload_3
      //   2315: aload 5
      //   2317: getfield 147	com/tencent/mm/plugin/expt/hellhound/core/a/a/a:qQS	Ljava/lang/Object;
      //   2320: checkcast 256	com/tencent/mm/protocal/protobuf/bod
      //   2323: putfield 260	com/tencent/mm/protocal/protobuf/bnz:GIE	Lcom/tencent/mm/protocal/protobuf/bod;
      //   2326: aload_3
      //   2327: sipush 500
      //   2330: putfield 200	com/tencent/mm/protocal/protobuf/bnz:msgType	I
      //   2333: goto +1412 -> 3745
      //   2336: aload_3
      //   2337: aload 5
      //   2339: getfield 147	com/tencent/mm/plugin/expt/hellhound/core/a/a/a:qQS	Ljava/lang/Object;
      //   2342: checkcast 215	java/lang/String
      //   2345: putfield 193	com/tencent/mm/protocal/protobuf/bnz:GIA	Ljava/lang/String;
      //   2348: aload_3
      //   2349: sipush 501
      //   2352: putfield 200	com/tencent/mm/protocal/protobuf/bnz:msgType	I
      //   2355: goto +1390 -> 3745
      //   2358: aload_3
      //   2359: aload 5
      //   2361: getfield 147	com/tencent/mm/plugin/expt/hellhound/core/a/a/a:qQS	Ljava/lang/Object;
      //   2364: checkcast 256	com/tencent/mm/protocal/protobuf/bod
      //   2367: putfield 260	com/tencent/mm/protocal/protobuf/bnz:GIE	Lcom/tencent/mm/protocal/protobuf/bod;
      //   2370: aload_3
      //   2371: sipush 502
      //   2374: putfield 200	com/tencent/mm/protocal/protobuf/bnz:msgType	I
      //   2377: goto +1368 -> 3745
      //   2380: aload_3
      //   2381: aload 5
      //   2383: getfield 147	com/tencent/mm/plugin/expt/hellhound/core/a/a/a:qQS	Ljava/lang/Object;
      //   2386: checkcast 215	java/lang/String
      //   2389: putfield 193	com/tencent/mm/protocal/protobuf/bnz:GIA	Ljava/lang/String;
      //   2392: aload_3
      //   2393: sipush 504
      //   2396: putfield 200	com/tencent/mm/protocal/protobuf/bnz:msgType	I
      //   2399: goto +1346 -> 3745
      //   2402: aload_3
      //   2403: aload 5
      //   2405: getfield 147	com/tencent/mm/plugin/expt/hellhound/core/a/a/a:qQS	Ljava/lang/Object;
      //   2408: checkcast 215	java/lang/String
      //   2411: putfield 193	com/tencent/mm/protocal/protobuf/bnz:GIA	Ljava/lang/String;
      //   2414: aload_3
      //   2415: sipush 503
      //   2418: putfield 200	com/tencent/mm/protocal/protobuf/bnz:msgType	I
      //   2421: goto +1324 -> 3745
      //   2424: aload_3
      //   2425: aload 5
      //   2427: getfield 147	com/tencent/mm/plugin/expt/hellhound/core/a/a/a:qQS	Ljava/lang/Object;
      //   2430: checkcast 226	java/lang/Long
      //   2433: invokevirtual 230	java/lang/Long:longValue	()J
      //   2436: putfield 199	com/tencent/mm/protocal/protobuf/bnz:timestamp	J
      //   2439: aload_3
      //   2440: sipush 217
      //   2443: putfield 200	com/tencent/mm/protocal/protobuf/bnz:msgType	I
      //   2446: goto +1299 -> 3745
      //   2449: aload_3
      //   2450: aload 5
      //   2452: getfield 147	com/tencent/mm/plugin/expt/hellhound/core/a/a/a:qQS	Ljava/lang/Object;
      //   2455: checkcast 226	java/lang/Long
      //   2458: invokevirtual 230	java/lang/Long:longValue	()J
      //   2461: putfield 199	com/tencent/mm/protocal/protobuf/bnz:timestamp	J
      //   2464: aload_3
      //   2465: sipush 219
      //   2468: putfield 200	com/tencent/mm/protocal/protobuf/bnz:msgType	I
      //   2471: goto +1274 -> 3745
      //   2474: aload_3
      //   2475: aload 5
      //   2477: getfield 147	com/tencent/mm/plugin/expt/hellhound/core/a/a/a:qQS	Ljava/lang/Object;
      //   2480: checkcast 226	java/lang/Long
      //   2483: invokevirtual 230	java/lang/Long:longValue	()J
      //   2486: putfield 199	com/tencent/mm/protocal/protobuf/bnz:timestamp	J
      //   2489: aload_3
      //   2490: sipush 218
      //   2493: putfield 200	com/tencent/mm/protocal/protobuf/bnz:msgType	I
      //   2496: goto +1249 -> 3745
      //   2499: aload_3
      //   2500: aload 5
      //   2502: getfield 147	com/tencent/mm/plugin/expt/hellhound/core/a/a/a:qQS	Ljava/lang/Object;
      //   2505: checkcast 226	java/lang/Long
      //   2508: invokevirtual 230	java/lang/Long:longValue	()J
      //   2511: putfield 199	com/tencent/mm/protocal/protobuf/bnz:timestamp	J
      //   2514: aload_3
      //   2515: sipush 208
      //   2518: putfield 200	com/tencent/mm/protocal/protobuf/bnz:msgType	I
      //   2521: goto +1224 -> 3745
      //   2524: aload_3
      //   2525: aload 5
      //   2527: getfield 147	com/tencent/mm/plugin/expt/hellhound/core/a/a/a:qQS	Ljava/lang/Object;
      //   2530: checkcast 226	java/lang/Long
      //   2533: invokevirtual 230	java/lang/Long:longValue	()J
      //   2536: putfield 199	com/tencent/mm/protocal/protobuf/bnz:timestamp	J
      //   2539: aload_3
      //   2540: sipush 211
      //   2543: putfield 200	com/tencent/mm/protocal/protobuf/bnz:msgType	I
      //   2546: goto +1199 -> 3745
      //   2549: aload_3
      //   2550: aload 5
      //   2552: getfield 147	com/tencent/mm/plugin/expt/hellhound/core/a/a/a:qQS	Ljava/lang/Object;
      //   2555: checkcast 226	java/lang/Long
      //   2558: invokevirtual 230	java/lang/Long:longValue	()J
      //   2561: putfield 199	com/tencent/mm/protocal/protobuf/bnz:timestamp	J
      //   2564: aload_3
      //   2565: sipush 212
      //   2568: putfield 200	com/tencent/mm/protocal/protobuf/bnz:msgType	I
      //   2571: goto +1174 -> 3745
      //   2574: aload_3
      //   2575: sipush 213
      //   2578: putfield 200	com/tencent/mm/protocal/protobuf/bnz:msgType	I
      //   2581: goto +1164 -> 3745
      //   2584: aload_3
      //   2585: sipush 214
      //   2588: putfield 200	com/tencent/mm/protocal/protobuf/bnz:msgType	I
      //   2591: goto +1154 -> 3745
      //   2594: aload_3
      //   2595: sipush 215
      //   2598: putfield 200	com/tencent/mm/protocal/protobuf/bnz:msgType	I
      //   2601: goto +1144 -> 3745
      //   2604: aload_3
      //   2605: sipush 216
      //   2608: putfield 200	com/tencent/mm/protocal/protobuf/bnz:msgType	I
      //   2611: goto +1134 -> 3745
      //   2614: aload_3
      //   2615: sipush 209
      //   2618: putfield 200	com/tencent/mm/protocal/protobuf/bnz:msgType	I
      //   2621: goto +1124 -> 3745
      //   2624: aload_3
      //   2625: aload 5
      //   2627: getfield 147	com/tencent/mm/plugin/expt/hellhound/core/a/a/a:qQS	Ljava/lang/Object;
      //   2630: checkcast 262	com/tencent/mm/protocal/protobuf/asx
      //   2633: getfield 265	com/tencent/mm/protocal/protobuf/asx:type	I
      //   2636: putfield 185	com/tencent/mm/protocal/protobuf/bnz:flags	I
      //   2639: aload_3
      //   2640: sipush 210
      //   2643: putfield 200	com/tencent/mm/protocal/protobuf/bnz:msgType	I
      //   2646: goto +1099 -> 3745
      //   2649: aload_3
      //   2650: sipush 700
      //   2653: putfield 200	com/tencent/mm/protocal/protobuf/bnz:msgType	I
      //   2656: goto +1089 -> 3745
      //   2659: aload_3
      //   2660: sipush 701
      //   2663: putfield 200	com/tencent/mm/protocal/protobuf/bnz:msgType	I
      //   2666: goto +1079 -> 3745
      //   2669: aload_3
      //   2670: sipush 702
      //   2673: putfield 200	com/tencent/mm/protocal/protobuf/bnz:msgType	I
      //   2676: goto +1069 -> 3745
      //   2679: aload_3
      //   2680: sipush 703
      //   2683: putfield 200	com/tencent/mm/protocal/protobuf/bnz:msgType	I
      //   2686: goto +1059 -> 3745
      //   2689: aload_3
      //   2690: aload 5
      //   2692: getfield 147	com/tencent/mm/plugin/expt/hellhound/core/a/a/a:qQS	Ljava/lang/Object;
      //   2695: checkcast 215	java/lang/String
      //   2698: putfield 193	com/tencent/mm/protocal/protobuf/bnz:GIA	Ljava/lang/String;
      //   2701: aload_3
      //   2702: sipush 704
      //   2705: putfield 200	com/tencent/mm/protocal/protobuf/bnz:msgType	I
      //   2708: goto +1037 -> 3745
      //   2711: aload_3
      //   2712: aload 5
      //   2714: getfield 147	com/tencent/mm/plugin/expt/hellhound/core/a/a/a:qQS	Ljava/lang/Object;
      //   2717: checkcast 215	java/lang/String
      //   2720: putfield 193	com/tencent/mm/protocal/protobuf/bnz:GIA	Ljava/lang/String;
      //   2723: aload_3
      //   2724: sipush 708
      //   2727: putfield 200	com/tencent/mm/protocal/protobuf/bnz:msgType	I
      //   2730: goto +1015 -> 3745
      //   2733: aload_3
      //   2734: aload 5
      //   2736: getfield 147	com/tencent/mm/plugin/expt/hellhound/core/a/a/a:qQS	Ljava/lang/Object;
      //   2739: checkcast 215	java/lang/String
      //   2742: putfield 193	com/tencent/mm/protocal/protobuf/bnz:GIA	Ljava/lang/String;
      //   2745: aload_3
      //   2746: sipush 712
      //   2749: putfield 200	com/tencent/mm/protocal/protobuf/bnz:msgType	I
      //   2752: goto +993 -> 3745
      //   2755: aload_3
      //   2756: aload 5
      //   2758: getfield 147	com/tencent/mm/plugin/expt/hellhound/core/a/a/a:qQS	Ljava/lang/Object;
      //   2761: checkcast 215	java/lang/String
      //   2764: putfield 193	com/tencent/mm/protocal/protobuf/bnz:GIA	Ljava/lang/String;
      //   2767: aload_3
      //   2768: sipush 724
      //   2771: putfield 200	com/tencent/mm/protocal/protobuf/bnz:msgType	I
      //   2774: goto +971 -> 3745
      //   2777: aload_3
      //   2778: aload 5
      //   2780: getfield 147	com/tencent/mm/plugin/expt/hellhound/core/a/a/a:qQS	Ljava/lang/Object;
      //   2783: checkcast 215	java/lang/String
      //   2786: putfield 193	com/tencent/mm/protocal/protobuf/bnz:GIA	Ljava/lang/String;
      //   2789: aload_3
      //   2790: sipush 744
      //   2793: putfield 200	com/tencent/mm/protocal/protobuf/bnz:msgType	I
      //   2796: goto +949 -> 3745
      //   2799: aload_3
      //   2800: aload 5
      //   2802: getfield 147	com/tencent/mm/plugin/expt/hellhound/core/a/a/a:qQS	Ljava/lang/Object;
      //   2805: checkcast 215	java/lang/String
      //   2808: putfield 193	com/tencent/mm/protocal/protobuf/bnz:GIA	Ljava/lang/String;
      //   2811: aload_3
      //   2812: sipush 728
      //   2815: putfield 200	com/tencent/mm/protocal/protobuf/bnz:msgType	I
      //   2818: goto +927 -> 3745
      //   2821: aload_3
      //   2822: aload 5
      //   2824: getfield 147	com/tencent/mm/plugin/expt/hellhound/core/a/a/a:qQS	Ljava/lang/Object;
      //   2827: checkcast 215	java/lang/String
      //   2830: putfield 193	com/tencent/mm/protocal/protobuf/bnz:GIA	Ljava/lang/String;
      //   2833: aload_3
      //   2834: sipush 732
      //   2837: putfield 200	com/tencent/mm/protocal/protobuf/bnz:msgType	I
      //   2840: goto +905 -> 3745
      //   2843: aload_3
      //   2844: aload 5
      //   2846: getfield 147	com/tencent/mm/plugin/expt/hellhound/core/a/a/a:qQS	Ljava/lang/Object;
      //   2849: checkcast 215	java/lang/String
      //   2852: putfield 193	com/tencent/mm/protocal/protobuf/bnz:GIA	Ljava/lang/String;
      //   2855: aload_3
      //   2856: sipush 736
      //   2859: putfield 200	com/tencent/mm/protocal/protobuf/bnz:msgType	I
      //   2862: goto +883 -> 3745
      //   2865: aload_3
      //   2866: aload 5
      //   2868: getfield 147	com/tencent/mm/plugin/expt/hellhound/core/a/a/a:qQS	Ljava/lang/Object;
      //   2871: checkcast 215	java/lang/String
      //   2874: putfield 193	com/tencent/mm/protocal/protobuf/bnz:GIA	Ljava/lang/String;
      //   2877: aload_3
      //   2878: sipush 740
      //   2881: putfield 200	com/tencent/mm/protocal/protobuf/bnz:msgType	I
      //   2884: goto +861 -> 3745
      //   2887: aload_3
      //   2888: aload 5
      //   2890: getfield 147	com/tencent/mm/plugin/expt/hellhound/core/a/a/a:qQS	Ljava/lang/Object;
      //   2893: checkcast 215	java/lang/String
      //   2896: putfield 193	com/tencent/mm/protocal/protobuf/bnz:GIA	Ljava/lang/String;
      //   2899: aload_3
      //   2900: sipush 716
      //   2903: putfield 200	com/tencent/mm/protocal/protobuf/bnz:msgType	I
      //   2906: goto +839 -> 3745
      //   2909: aload_3
      //   2910: aload 5
      //   2912: getfield 147	com/tencent/mm/plugin/expt/hellhound/core/a/a/a:qQS	Ljava/lang/Object;
      //   2915: checkcast 215	java/lang/String
      //   2918: putfield 193	com/tencent/mm/protocal/protobuf/bnz:GIA	Ljava/lang/String;
      //   2921: aload_3
      //   2922: sipush 720
      //   2925: putfield 200	com/tencent/mm/protocal/protobuf/bnz:msgType	I
      //   2928: goto +817 -> 3745
      //   2931: aload_3
      //   2932: aload 5
      //   2934: getfield 147	com/tencent/mm/plugin/expt/hellhound/core/a/a/a:qQS	Ljava/lang/Object;
      //   2937: checkcast 215	java/lang/String
      //   2940: putfield 193	com/tencent/mm/protocal/protobuf/bnz:GIA	Ljava/lang/String;
      //   2943: aload_3
      //   2944: sipush 705
      //   2947: putfield 200	com/tencent/mm/protocal/protobuf/bnz:msgType	I
      //   2950: goto +795 -> 3745
      //   2953: aload_3
      //   2954: aload 5
      //   2956: getfield 147	com/tencent/mm/plugin/expt/hellhound/core/a/a/a:qQS	Ljava/lang/Object;
      //   2959: checkcast 215	java/lang/String
      //   2962: putfield 193	com/tencent/mm/protocal/protobuf/bnz:GIA	Ljava/lang/String;
      //   2965: aload_3
      //   2966: sipush 709
      //   2969: putfield 200	com/tencent/mm/protocal/protobuf/bnz:msgType	I
      //   2972: goto +773 -> 3745
      //   2975: aload_3
      //   2976: aload 5
      //   2978: getfield 147	com/tencent/mm/plugin/expt/hellhound/core/a/a/a:qQS	Ljava/lang/Object;
      //   2981: checkcast 215	java/lang/String
      //   2984: putfield 193	com/tencent/mm/protocal/protobuf/bnz:GIA	Ljava/lang/String;
      //   2987: aload_3
      //   2988: sipush 713
      //   2991: putfield 200	com/tencent/mm/protocal/protobuf/bnz:msgType	I
      //   2994: goto +751 -> 3745
      //   2997: aload_3
      //   2998: aload 5
      //   3000: getfield 147	com/tencent/mm/plugin/expt/hellhound/core/a/a/a:qQS	Ljava/lang/Object;
      //   3003: checkcast 215	java/lang/String
      //   3006: putfield 193	com/tencent/mm/protocal/protobuf/bnz:GIA	Ljava/lang/String;
      //   3009: aload_3
      //   3010: sipush 725
      //   3013: putfield 200	com/tencent/mm/protocal/protobuf/bnz:msgType	I
      //   3016: goto +729 -> 3745
      //   3019: aload_3
      //   3020: aload 5
      //   3022: getfield 147	com/tencent/mm/plugin/expt/hellhound/core/a/a/a:qQS	Ljava/lang/Object;
      //   3025: checkcast 215	java/lang/String
      //   3028: putfield 193	com/tencent/mm/protocal/protobuf/bnz:GIA	Ljava/lang/String;
      //   3031: aload_3
      //   3032: sipush 745
      //   3035: putfield 200	com/tencent/mm/protocal/protobuf/bnz:msgType	I
      //   3038: goto +707 -> 3745
      //   3041: aload_3
      //   3042: aload 5
      //   3044: getfield 147	com/tencent/mm/plugin/expt/hellhound/core/a/a/a:qQS	Ljava/lang/Object;
      //   3047: checkcast 215	java/lang/String
      //   3050: putfield 193	com/tencent/mm/protocal/protobuf/bnz:GIA	Ljava/lang/String;
      //   3053: aload_3
      //   3054: sipush 729
      //   3057: putfield 200	com/tencent/mm/protocal/protobuf/bnz:msgType	I
      //   3060: goto +685 -> 3745
      //   3063: aload_3
      //   3064: aload 5
      //   3066: getfield 147	com/tencent/mm/plugin/expt/hellhound/core/a/a/a:qQS	Ljava/lang/Object;
      //   3069: checkcast 215	java/lang/String
      //   3072: putfield 193	com/tencent/mm/protocal/protobuf/bnz:GIA	Ljava/lang/String;
      //   3075: aload_3
      //   3076: sipush 733
      //   3079: putfield 200	com/tencent/mm/protocal/protobuf/bnz:msgType	I
      //   3082: goto +663 -> 3745
      //   3085: aload_3
      //   3086: aload 5
      //   3088: getfield 147	com/tencent/mm/plugin/expt/hellhound/core/a/a/a:qQS	Ljava/lang/Object;
      //   3091: checkcast 215	java/lang/String
      //   3094: putfield 193	com/tencent/mm/protocal/protobuf/bnz:GIA	Ljava/lang/String;
      //   3097: aload_3
      //   3098: sipush 737
      //   3101: putfield 200	com/tencent/mm/protocal/protobuf/bnz:msgType	I
      //   3104: goto +641 -> 3745
      //   3107: aload_3
      //   3108: aload 5
      //   3110: getfield 147	com/tencent/mm/plugin/expt/hellhound/core/a/a/a:qQS	Ljava/lang/Object;
      //   3113: checkcast 215	java/lang/String
      //   3116: putfield 193	com/tencent/mm/protocal/protobuf/bnz:GIA	Ljava/lang/String;
      //   3119: aload_3
      //   3120: sipush 741
      //   3123: putfield 200	com/tencent/mm/protocal/protobuf/bnz:msgType	I
      //   3126: goto +619 -> 3745
      //   3129: aload_3
      //   3130: aload 5
      //   3132: getfield 147	com/tencent/mm/plugin/expt/hellhound/core/a/a/a:qQS	Ljava/lang/Object;
      //   3135: checkcast 215	java/lang/String
      //   3138: putfield 193	com/tencent/mm/protocal/protobuf/bnz:GIA	Ljava/lang/String;
      //   3141: aload_3
      //   3142: sipush 717
      //   3145: putfield 200	com/tencent/mm/protocal/protobuf/bnz:msgType	I
      //   3148: goto +597 -> 3745
      //   3151: aload_3
      //   3152: aload 5
      //   3154: getfield 147	com/tencent/mm/plugin/expt/hellhound/core/a/a/a:qQS	Ljava/lang/Object;
      //   3157: checkcast 215	java/lang/String
      //   3160: putfield 193	com/tencent/mm/protocal/protobuf/bnz:GIA	Ljava/lang/String;
      //   3163: aload_3
      //   3164: sipush 721
      //   3167: putfield 200	com/tencent/mm/protocal/protobuf/bnz:msgType	I
      //   3170: goto +575 -> 3745
      //   3173: aload_3
      //   3174: aload 5
      //   3176: getfield 147	com/tencent/mm/plugin/expt/hellhound/core/a/a/a:qQS	Ljava/lang/Object;
      //   3179: checkcast 215	java/lang/String
      //   3182: putfield 193	com/tencent/mm/protocal/protobuf/bnz:GIA	Ljava/lang/String;
      //   3185: aload_3
      //   3186: sipush 706
      //   3189: putfield 200	com/tencent/mm/protocal/protobuf/bnz:msgType	I
      //   3192: goto +553 -> 3745
      //   3195: aload_3
      //   3196: aload 5
      //   3198: getfield 147	com/tencent/mm/plugin/expt/hellhound/core/a/a/a:qQS	Ljava/lang/Object;
      //   3201: checkcast 215	java/lang/String
      //   3204: putfield 193	com/tencent/mm/protocal/protobuf/bnz:GIA	Ljava/lang/String;
      //   3207: aload_3
      //   3208: sipush 710
      //   3211: putfield 200	com/tencent/mm/protocal/protobuf/bnz:msgType	I
      //   3214: goto +531 -> 3745
      //   3217: aload_3
      //   3218: aload 5
      //   3220: getfield 147	com/tencent/mm/plugin/expt/hellhound/core/a/a/a:qQS	Ljava/lang/Object;
      //   3223: checkcast 215	java/lang/String
      //   3226: putfield 193	com/tencent/mm/protocal/protobuf/bnz:GIA	Ljava/lang/String;
      //   3229: aload_3
      //   3230: sipush 714
      //   3233: putfield 200	com/tencent/mm/protocal/protobuf/bnz:msgType	I
      //   3236: goto +509 -> 3745
      //   3239: aload_3
      //   3240: aload 5
      //   3242: getfield 147	com/tencent/mm/plugin/expt/hellhound/core/a/a/a:qQS	Ljava/lang/Object;
      //   3245: checkcast 215	java/lang/String
      //   3248: putfield 193	com/tencent/mm/protocal/protobuf/bnz:GIA	Ljava/lang/String;
      //   3251: aload_3
      //   3252: sipush 726
      //   3255: putfield 200	com/tencent/mm/protocal/protobuf/bnz:msgType	I
      //   3258: goto +487 -> 3745
      //   3261: aload_3
      //   3262: aload 5
      //   3264: getfield 147	com/tencent/mm/plugin/expt/hellhound/core/a/a/a:qQS	Ljava/lang/Object;
      //   3267: checkcast 215	java/lang/String
      //   3270: putfield 193	com/tencent/mm/protocal/protobuf/bnz:GIA	Ljava/lang/String;
      //   3273: aload_3
      //   3274: sipush 746
      //   3277: putfield 200	com/tencent/mm/protocal/protobuf/bnz:msgType	I
      //   3280: goto +465 -> 3745
      //   3283: aload_3
      //   3284: aload 5
      //   3286: getfield 147	com/tencent/mm/plugin/expt/hellhound/core/a/a/a:qQS	Ljava/lang/Object;
      //   3289: checkcast 215	java/lang/String
      //   3292: putfield 193	com/tencent/mm/protocal/protobuf/bnz:GIA	Ljava/lang/String;
      //   3295: aload_3
      //   3296: sipush 730
      //   3299: putfield 200	com/tencent/mm/protocal/protobuf/bnz:msgType	I
      //   3302: goto +443 -> 3745
      //   3305: aload_3
      //   3306: aload 5
      //   3308: getfield 147	com/tencent/mm/plugin/expt/hellhound/core/a/a/a:qQS	Ljava/lang/Object;
      //   3311: checkcast 215	java/lang/String
      //   3314: putfield 193	com/tencent/mm/protocal/protobuf/bnz:GIA	Ljava/lang/String;
      //   3317: aload_3
      //   3318: sipush 734
      //   3321: putfield 200	com/tencent/mm/protocal/protobuf/bnz:msgType	I
      //   3324: goto +421 -> 3745
      //   3327: aload_3
      //   3328: aload 5
      //   3330: getfield 147	com/tencent/mm/plugin/expt/hellhound/core/a/a/a:qQS	Ljava/lang/Object;
      //   3333: checkcast 215	java/lang/String
      //   3336: putfield 193	com/tencent/mm/protocal/protobuf/bnz:GIA	Ljava/lang/String;
      //   3339: aload_3
      //   3340: sipush 738
      //   3343: putfield 200	com/tencent/mm/protocal/protobuf/bnz:msgType	I
      //   3346: goto +399 -> 3745
      //   3349: aload_3
      //   3350: aload 5
      //   3352: getfield 147	com/tencent/mm/plugin/expt/hellhound/core/a/a/a:qQS	Ljava/lang/Object;
      //   3355: checkcast 215	java/lang/String
      //   3358: putfield 193	com/tencent/mm/protocal/protobuf/bnz:GIA	Ljava/lang/String;
      //   3361: aload_3
      //   3362: sipush 742
      //   3365: putfield 200	com/tencent/mm/protocal/protobuf/bnz:msgType	I
      //   3368: goto +377 -> 3745
      //   3371: aload_3
      //   3372: aload 5
      //   3374: getfield 147	com/tencent/mm/plugin/expt/hellhound/core/a/a/a:qQS	Ljava/lang/Object;
      //   3377: checkcast 215	java/lang/String
      //   3380: putfield 193	com/tencent/mm/protocal/protobuf/bnz:GIA	Ljava/lang/String;
      //   3383: aload_3
      //   3384: sipush 718
      //   3387: putfield 200	com/tencent/mm/protocal/protobuf/bnz:msgType	I
      //   3390: goto +355 -> 3745
      //   3393: aload_3
      //   3394: aload 5
      //   3396: getfield 147	com/tencent/mm/plugin/expt/hellhound/core/a/a/a:qQS	Ljava/lang/Object;
      //   3399: checkcast 215	java/lang/String
      //   3402: putfield 193	com/tencent/mm/protocal/protobuf/bnz:GIA	Ljava/lang/String;
      //   3405: aload_3
      //   3406: sipush 722
      //   3409: putfield 200	com/tencent/mm/protocal/protobuf/bnz:msgType	I
      //   3412: goto +333 -> 3745
      //   3415: aload_3
      //   3416: aload 5
      //   3418: getfield 147	com/tencent/mm/plugin/expt/hellhound/core/a/a/a:qQS	Ljava/lang/Object;
      //   3421: checkcast 215	java/lang/String
      //   3424: putfield 193	com/tencent/mm/protocal/protobuf/bnz:GIA	Ljava/lang/String;
      //   3427: aload_3
      //   3428: sipush 707
      //   3431: putfield 200	com/tencent/mm/protocal/protobuf/bnz:msgType	I
      //   3434: goto +311 -> 3745
      //   3437: aload_3
      //   3438: aload 5
      //   3440: getfield 147	com/tencent/mm/plugin/expt/hellhound/core/a/a/a:qQS	Ljava/lang/Object;
      //   3443: checkcast 215	java/lang/String
      //   3446: putfield 193	com/tencent/mm/protocal/protobuf/bnz:GIA	Ljava/lang/String;
      //   3449: aload_3
      //   3450: sipush 711
      //   3453: putfield 200	com/tencent/mm/protocal/protobuf/bnz:msgType	I
      //   3456: goto +289 -> 3745
      //   3459: aload_3
      //   3460: aload 5
      //   3462: getfield 147	com/tencent/mm/plugin/expt/hellhound/core/a/a/a:qQS	Ljava/lang/Object;
      //   3465: checkcast 215	java/lang/String
      //   3468: putfield 193	com/tencent/mm/protocal/protobuf/bnz:GIA	Ljava/lang/String;
      //   3471: aload_3
      //   3472: sipush 715
      //   3475: putfield 200	com/tencent/mm/protocal/protobuf/bnz:msgType	I
      //   3478: goto +267 -> 3745
      //   3481: aload_3
      //   3482: aload 5
      //   3484: getfield 147	com/tencent/mm/plugin/expt/hellhound/core/a/a/a:qQS	Ljava/lang/Object;
      //   3487: checkcast 215	java/lang/String
      //   3490: putfield 193	com/tencent/mm/protocal/protobuf/bnz:GIA	Ljava/lang/String;
      //   3493: aload_3
      //   3494: sipush 727
      //   3497: putfield 200	com/tencent/mm/protocal/protobuf/bnz:msgType	I
      //   3500: goto +245 -> 3745
      //   3503: aload_3
      //   3504: aload 5
      //   3506: getfield 147	com/tencent/mm/plugin/expt/hellhound/core/a/a/a:qQS	Ljava/lang/Object;
      //   3509: checkcast 215	java/lang/String
      //   3512: putfield 193	com/tencent/mm/protocal/protobuf/bnz:GIA	Ljava/lang/String;
      //   3515: aload_3
      //   3516: sipush 747
      //   3519: putfield 200	com/tencent/mm/protocal/protobuf/bnz:msgType	I
      //   3522: goto +223 -> 3745
      //   3525: aload_3
      //   3526: aload 5
      //   3528: getfield 147	com/tencent/mm/plugin/expt/hellhound/core/a/a/a:qQS	Ljava/lang/Object;
      //   3531: checkcast 215	java/lang/String
      //   3534: putfield 193	com/tencent/mm/protocal/protobuf/bnz:GIA	Ljava/lang/String;
      //   3537: aload_3
      //   3538: sipush 731
      //   3541: putfield 200	com/tencent/mm/protocal/protobuf/bnz:msgType	I
      //   3544: goto +201 -> 3745
      //   3547: aload_3
      //   3548: aload 5
      //   3550: getfield 147	com/tencent/mm/plugin/expt/hellhound/core/a/a/a:qQS	Ljava/lang/Object;
      //   3553: checkcast 215	java/lang/String
      //   3556: putfield 193	com/tencent/mm/protocal/protobuf/bnz:GIA	Ljava/lang/String;
      //   3559: aload_3
      //   3560: sipush 735
      //   3563: putfield 200	com/tencent/mm/protocal/protobuf/bnz:msgType	I
      //   3566: goto +179 -> 3745
      //   3569: aload_3
      //   3570: aload 5
      //   3572: getfield 147	com/tencent/mm/plugin/expt/hellhound/core/a/a/a:qQS	Ljava/lang/Object;
      //   3575: checkcast 215	java/lang/String
      //   3578: putfield 193	com/tencent/mm/protocal/protobuf/bnz:GIA	Ljava/lang/String;
      //   3581: aload_3
      //   3582: sipush 739
      //   3585: putfield 200	com/tencent/mm/protocal/protobuf/bnz:msgType	I
      //   3588: goto +157 -> 3745
      //   3591: aload_3
      //   3592: aload 5
      //   3594: getfield 147	com/tencent/mm/plugin/expt/hellhound/core/a/a/a:qQS	Ljava/lang/Object;
      //   3597: checkcast 215	java/lang/String
      //   3600: putfield 193	com/tencent/mm/protocal/protobuf/bnz:GIA	Ljava/lang/String;
      //   3603: aload_3
      //   3604: sipush 743
      //   3607: putfield 200	com/tencent/mm/protocal/protobuf/bnz:msgType	I
      //   3610: goto +135 -> 3745
      //   3613: aload_3
      //   3614: aload 5
      //   3616: getfield 147	com/tencent/mm/plugin/expt/hellhound/core/a/a/a:qQS	Ljava/lang/Object;
      //   3619: checkcast 215	java/lang/String
      //   3622: putfield 193	com/tencent/mm/protocal/protobuf/bnz:GIA	Ljava/lang/String;
      //   3625: aload_3
      //   3626: sipush 719
      //   3629: putfield 200	com/tencent/mm/protocal/protobuf/bnz:msgType	I
      //   3632: goto +113 -> 3745
      //   3635: aload_3
      //   3636: aload 5
      //   3638: getfield 147	com/tencent/mm/plugin/expt/hellhound/core/a/a/a:qQS	Ljava/lang/Object;
      //   3641: checkcast 215	java/lang/String
      //   3644: putfield 193	com/tencent/mm/protocal/protobuf/bnz:GIA	Ljava/lang/String;
      //   3647: aload_3
      //   3648: sipush 723
      //   3651: putfield 200	com/tencent/mm/protocal/protobuf/bnz:msgType	I
      //   3654: goto +91 -> 3745
      //   3657: aload_3
      //   3658: aload 5
      //   3660: getfield 147	com/tencent/mm/plugin/expt/hellhound/core/a/a/a:qQS	Ljava/lang/Object;
      //   3663: checkcast 226	java/lang/Long
      //   3666: invokevirtual 230	java/lang/Long:longValue	()J
      //   3669: putfield 199	com/tencent/mm/protocal/protobuf/bnz:timestamp	J
      //   3672: aload_3
      //   3673: sipush 220
      //   3676: putfield 200	com/tencent/mm/protocal/protobuf/bnz:msgType	I
      //   3679: goto +66 -> 3745
      //   3682: aload_3
      //   3683: sipush 221
      //   3686: putfield 200	com/tencent/mm/protocal/protobuf/bnz:msgType	I
      //   3689: goto +56 -> 3745
      //   3692: aload_3
      //   3693: aload 5
      //   3695: getfield 147	com/tencent/mm/plugin/expt/hellhound/core/a/a/a:qQS	Ljava/lang/Object;
      //   3698: checkcast 267	com/tencent/mm/protocal/protobuf/dwc
      //   3701: putfield 271	com/tencent/mm/protocal/protobuf/bnz:GIF	Lcom/tencent/mm/protocal/protobuf/dwc;
      //   3704: aload_3
      //   3705: sipush 800
      //   3708: putfield 200	com/tencent/mm/protocal/protobuf/bnz:msgType	I
      //   3711: goto +34 -> 3745
      //   3714: aload_3
      //   3715: aload 5
      //   3717: getfield 147	com/tencent/mm/plugin/expt/hellhound/core/a/a/a:qQS	Ljava/lang/Object;
      //   3720: checkcast 273	com/tencent/mm/protocal/protobuf/bch
      //   3723: putfield 277	com/tencent/mm/protocal/protobuf/bnz:GIG	Lcom/tencent/mm/protocal/protobuf/bch;
      //   3726: aload_3
      //   3727: sipush 801
      //   3730: putfield 200	com/tencent/mm/protocal/protobuf/bnz:msgType	I
      //   3733: goto +12 -> 3745
      //   3736: ldc 22
      //   3738: invokestatic 37	com/tencent/matrix/trace/core/AppMethodBeat:o	(I)V
      //   3741: return
      //   3742: goto -3614 -> 128
      //   3745: goto -3604 -> 141
      // Local variable table:
      //   start	length	slot	name	signature
      //   0	3748	0	this	a
      //   0	3748	1	paramMessage	Message
      //   147	23	2	bool	boolean
      //   140	3587	3	localObject1	Object
      //   50	142	4	localReentrantLock	java.util.concurrent.locks.ReentrantLock
      //   29	3687	5	locala	a
      //   38	144	6	localb	b
      //   132	10	7	localLinkedList	java.util.LinkedList
      //   984	1287	8	localObject2	Object
      // Exception table:
      //   from	to	target	type
      //   57	75	78	finally
      //   112	116	78	finally
      //   120	128	78	finally
      //   128	134	78	finally
      //   141	191	78	finally
      //   202	976	78	finally
      //   976	1050	78	finally
      //   1050	1114	78	finally
      //   1114	1183	78	finally
      //   1186	1249	78	finally
      //   1252	1333	78	finally
      //   1336	1418	78	finally
      //   1421	1503	78	finally
      //   1506	1570	78	finally
      //   1573	1592	78	finally
      //   1595	1695	78	finally
      //   1698	1762	78	finally
      //   1765	1865	78	finally
      //   1868	1932	78	finally
      //   1935	1999	78	finally
      //   2002	2011	78	finally
      //   2014	2038	78	finally
      //   2041	2115	78	finally
      //   2115	2174	78	finally
      //   2177	2251	78	finally
      //   2251	2284	78	finally
      //   2287	2311	78	finally
      //   2314	2333	78	finally
      //   2336	2355	78	finally
      //   2358	2377	78	finally
      //   2380	2399	78	finally
      //   2402	2421	78	finally
      //   2424	2446	78	finally
      //   2449	2471	78	finally
      //   2474	2496	78	finally
      //   2499	2521	78	finally
      //   2524	2546	78	finally
      //   2549	2571	78	finally
      //   2574	2581	78	finally
      //   2584	2591	78	finally
      //   2594	2601	78	finally
      //   2604	2611	78	finally
      //   2614	2621	78	finally
      //   2624	2646	78	finally
      //   2649	2656	78	finally
      //   2659	2666	78	finally
      //   2669	2676	78	finally
      //   2679	2686	78	finally
      //   2689	2708	78	finally
      //   2711	2730	78	finally
      //   2733	2752	78	finally
      //   2755	2774	78	finally
      //   2777	2796	78	finally
      //   2799	2818	78	finally
      //   2821	2840	78	finally
      //   2843	2862	78	finally
      //   2865	2884	78	finally
      //   2887	2906	78	finally
      //   2909	2928	78	finally
      //   2931	2950	78	finally
      //   2953	2972	78	finally
      //   2975	2994	78	finally
      //   2997	3016	78	finally
      //   3019	3038	78	finally
      //   3041	3060	78	finally
      //   3063	3082	78	finally
      //   3085	3104	78	finally
      //   3107	3126	78	finally
      //   3129	3148	78	finally
      //   3151	3170	78	finally
      //   3173	3192	78	finally
      //   3195	3214	78	finally
      //   3217	3236	78	finally
      //   3239	3258	78	finally
      //   3261	3280	78	finally
      //   3283	3302	78	finally
      //   3305	3324	78	finally
      //   3327	3346	78	finally
      //   3349	3368	78	finally
      //   3371	3390	78	finally
      //   3393	3412	78	finally
      //   3415	3434	78	finally
      //   3437	3456	78	finally
      //   3459	3478	78	finally
      //   3481	3500	78	finally
      //   3503	3522	78	finally
      //   3525	3544	78	finally
      //   3547	3566	78	finally
      //   3569	3588	78	finally
      //   3591	3610	78	finally
      //   3613	3632	78	finally
      //   3635	3654	78	finally
      //   3657	3679	78	finally
      //   3682	3689	78	finally
      //   3692	3711	78	finally
      //   3714	3733	78	finally
      //   22	40	91	java/lang/Exception
      //   45	57	91	java/lang/Exception
      //   79	91	91	java/lang/Exception
      //   191	201	91	java/lang/Exception
    }
  }
}


/* Location:           L:\local\mybackup\temp\qq_apk\com.tencent.mm\classes6.jar
 * Qualified Name:     com.tencent.mm.plugin.expt.hellhound.core.a.a.e
 * JD-Core Version:    0.7.0.1
 */