package com.tencent.mobileqq.qwallet.report.impl;

class VACDReportServiceImpl$2
  implements Runnable
{
  VACDReportServiceImpl$2(VACDReportServiceImpl paramVACDReportServiceImpl, boolean paramBoolean) {}
  
  /* Error */
  public void run()
  {
    // Byte code:
    //   0: invokestatic 29	com/tencent/qphone/base/util/QLog:isColorLevel	()Z
    //   3: ifeq +31 -> 34
    //   6: ldc 31
    //   8: iconst_2
    //   9: new 33	java/lang/StringBuilder
    //   12: dup
    //   13: invokespecial 34	java/lang/StringBuilder:<init>	()V
    //   16: ldc 36
    //   18: invokevirtual 40	java/lang/StringBuilder:append	(Ljava/lang/String;)Ljava/lang/StringBuilder;
    //   21: aload_0
    //   22: getfield 16	com/tencent/mobileqq/qwallet/report/impl/VACDReportServiceImpl$2:a	Z
    //   25: invokevirtual 43	java/lang/StringBuilder:append	(Z)Ljava/lang/StringBuilder;
    //   28: invokevirtual 47	java/lang/StringBuilder:toString	()Ljava/lang/String;
    //   31: invokestatic 51	com/tencent/qphone/base/util/QLog:d	(Ljava/lang/String;ILjava/lang/String;)V
    //   34: invokestatic 57	com/tencent/mobileqq/qwallet/report/impl/VACDReportServiceImpl:access$000	()[B
    //   37: astore 13
    //   39: aload 13
    //   41: monitorenter
    //   42: aload_0
    //   43: getfield 14	com/tencent/mobileqq/qwallet/report/impl/VACDReportServiceImpl$2:this$0	Lcom/tencent/mobileqq/qwallet/report/impl/VACDReportServiceImpl;
    //   46: invokestatic 61	com/tencent/mobileqq/qwallet/report/impl/VACDReportServiceImpl:access$100	(Lcom/tencent/mobileqq/qwallet/report/impl/VACDReportServiceImpl;)Ljava/util/Map;
    //   49: invokeinterface 66 1 0
    //   54: ifeq +168 -> 222
    //   57: aload 13
    //   59: monitorexit
    //   60: aload_0
    //   61: getfield 14	com/tencent/mobileqq/qwallet/report/impl/VACDReportServiceImpl$2:this$0	Lcom/tencent/mobileqq/qwallet/report/impl/VACDReportServiceImpl;
    //   64: invokestatic 70	com/tencent/mobileqq/qwallet/report/impl/VACDReportServiceImpl:access$400	(Lcom/tencent/mobileqq/qwallet/report/impl/VACDReportServiceImpl;)Z
    //   67: ifeq +112 -> 179
    //   70: aload_0
    //   71: getfield 16	com/tencent/mobileqq/qwallet/report/impl/VACDReportServiceImpl$2:a	Z
    //   74: ifne +105 -> 179
    //   77: invokestatic 76	com/tencent/mobileqq/msf/core/NetConnInfoCenter:getServerTimeMillis	()J
    //   80: lstore_1
    //   81: lload_1
    //   82: aload_0
    //   83: getfield 14	com/tencent/mobileqq/qwallet/report/impl/VACDReportServiceImpl$2:this$0	Lcom/tencent/mobileqq/qwallet/report/impl/VACDReportServiceImpl;
    //   86: getfield 80	com/tencent/mobileqq/qwallet/report/impl/VACDReportServiceImpl:mLastReportTime	J
    //   89: lcmp
    //   90: ifle +73 -> 163
    //   93: lload_1
    //   94: aload_0
    //   95: getfield 14	com/tencent/mobileqq/qwallet/report/impl/VACDReportServiceImpl$2:this$0	Lcom/tencent/mobileqq/qwallet/report/impl/VACDReportServiceImpl;
    //   98: getfield 80	com/tencent/mobileqq/qwallet/report/impl/VACDReportServiceImpl:mLastReportTime	J
    //   101: lsub
    //   102: ldc2_w 81
    //   105: lcmp
    //   106: ifle +57 -> 163
    //   109: invokestatic 29	com/tencent/qphone/base/util/QLog:isColorLevel	()Z
    //   112: ifeq +43 -> 155
    //   115: ldc 31
    //   117: iconst_2
    //   118: new 33	java/lang/StringBuilder
    //   121: dup
    //   122: invokespecial 34	java/lang/StringBuilder:<init>	()V
    //   125: ldc 84
    //   127: invokevirtual 40	java/lang/StringBuilder:append	(Ljava/lang/String;)Ljava/lang/StringBuilder;
    //   130: lload_1
    //   131: invokevirtual 87	java/lang/StringBuilder:append	(J)Ljava/lang/StringBuilder;
    //   134: ldc 89
    //   136: invokevirtual 40	java/lang/StringBuilder:append	(Ljava/lang/String;)Ljava/lang/StringBuilder;
    //   139: aload_0
    //   140: getfield 14	com/tencent/mobileqq/qwallet/report/impl/VACDReportServiceImpl$2:this$0	Lcom/tencent/mobileqq/qwallet/report/impl/VACDReportServiceImpl;
    //   143: getfield 80	com/tencent/mobileqq/qwallet/report/impl/VACDReportServiceImpl:mLastReportTime	J
    //   146: invokevirtual 87	java/lang/StringBuilder:append	(J)Ljava/lang/StringBuilder;
    //   149: invokevirtual 47	java/lang/StringBuilder:toString	()Ljava/lang/String;
    //   152: invokestatic 92	com/tencent/qphone/base/util/QLog:i	(Ljava/lang/String;ILjava/lang/String;)V
    //   155: aload_0
    //   156: getfield 14	com/tencent/mobileqq/qwallet/report/impl/VACDReportServiceImpl$2:this$0	Lcom/tencent/mobileqq/qwallet/report/impl/VACDReportServiceImpl;
    //   159: invokevirtual 95	com/tencent/mobileqq/qwallet/report/impl/VACDReportServiceImpl:onDestroy	()V
    //   162: return
    //   163: aload_0
    //   164: getfield 14	com/tencent/mobileqq/qwallet/report/impl/VACDReportServiceImpl$2:this$0	Lcom/tencent/mobileqq/qwallet/report/impl/VACDReportServiceImpl;
    //   167: invokestatic 99	com/tencent/mobileqq/qwallet/report/impl/VACDReportServiceImpl:access$500	(Lcom/tencent/mobileqq/qwallet/report/impl/VACDReportServiceImpl;)Landroid/os/Handler;
    //   170: aload_0
    //   171: ldc2_w 100
    //   174: invokevirtual 107	android/os/Handler:postDelayed	(Ljava/lang/Runnable;J)Z
    //   177: pop
    //   178: return
    //   179: invokestatic 29	com/tencent/qphone/base/util/QLog:isColorLevel	()Z
    //   182: ifeq +11 -> 193
    //   185: ldc 31
    //   187: iconst_2
    //   188: ldc 109
    //   190: invokestatic 51	com/tencent/qphone/base/util/QLog:d	(Ljava/lang/String;ILjava/lang/String;)V
    //   193: aload_0
    //   194: getfield 16	com/tencent/mobileqq/qwallet/report/impl/VACDReportServiceImpl$2:a	Z
    //   197: ifeq -35 -> 162
    //   200: invokestatic 29	com/tencent/qphone/base/util/QLog:isColorLevel	()Z
    //   203: ifeq +11 -> 214
    //   206: ldc 31
    //   208: iconst_2
    //   209: ldc 111
    //   211: invokestatic 92	com/tencent/qphone/base/util/QLog:i	(Ljava/lang/String;ILjava/lang/String;)V
    //   214: aload_0
    //   215: getfield 14	com/tencent/mobileqq/qwallet/report/impl/VACDReportServiceImpl$2:this$0	Lcom/tencent/mobileqq/qwallet/report/impl/VACDReportServiceImpl;
    //   218: invokevirtual 95	com/tencent/mobileqq/qwallet/report/impl/VACDReportServiceImpl:onDestroy	()V
    //   221: return
    //   222: invokestatic 76	com/tencent/mobileqq/msf/core/NetConnInfoCenter:getServerTimeMillis	()J
    //   225: lstore 7
    //   227: new 113	java/util/ArrayList
    //   230: dup
    //   231: iconst_1
    //   232: invokespecial 116	java/util/ArrayList:<init>	(I)V
    //   235: astore 14
    //   237: aload_0
    //   238: getfield 14	com/tencent/mobileqq/qwallet/report/impl/VACDReportServiceImpl$2:this$0	Lcom/tencent/mobileqq/qwallet/report/impl/VACDReportServiceImpl;
    //   241: invokestatic 61	com/tencent/mobileqq/qwallet/report/impl/VACDReportServiceImpl:access$100	(Lcom/tencent/mobileqq/qwallet/report/impl/VACDReportServiceImpl;)Ljava/util/Map;
    //   244: invokeinterface 120 1 0
    //   249: invokeinterface 126 1 0
    //   254: astore 15
    //   256: aload 15
    //   258: invokeinterface 131 1 0
    //   263: ifeq +808 -> 1071
    //   266: aload 15
    //   268: invokeinterface 135 1 0
    //   273: checkcast 137	java/util/Map$Entry
    //   276: invokeinterface 140 1 0
    //   281: checkcast 142	VACDReport/ReportInfo
    //   284: astore 16
    //   286: aload 16
    //   288: ifnull -32 -> 256
    //   291: aload 16
    //   293: getfield 146	VACDReport/ReportInfo:header	LVACDReport/ReportHeader;
    //   296: ifnull +196 -> 492
    //   299: aload 16
    //   301: getfield 150	VACDReport/ReportInfo:body	LVACDReport/ReportBody;
    //   304: ifnonnull +188 -> 492
    //   307: aload 16
    //   309: getfield 146	VACDReport/ReportInfo:header	LVACDReport/ReportHeader;
    //   312: getfield 155	VACDReport/ReportHeader:seqno	J
    //   315: lstore_1
    //   316: lload 7
    //   318: aload 16
    //   320: getfield 146	VACDReport/ReportInfo:header	LVACDReport/ReportHeader;
    //   323: getfield 158	VACDReport/ReportHeader:createTime	J
    //   326: lsub
    //   327: invokestatic 164	java/lang/Math:abs	(J)J
    //   330: lstore_3
    //   331: lload_1
    //   332: lconst_0
    //   333: lcmp
    //   334: iflt +281 -> 615
    //   337: lload_3
    //   338: ldc2_w 165
    //   341: lcmp
    //   342: iflt +273 -> 615
    //   345: aload 14
    //   347: lload_1
    //   348: invokestatic 172	java/lang/Long:valueOf	(J)Ljava/lang/Long;
    //   351: invokeinterface 178 2 0
    //   356: ifne -100 -> 256
    //   359: aload 14
    //   361: lload_1
    //   362: invokestatic 172	java/lang/Long:valueOf	(J)Ljava/lang/Long;
    //   365: invokeinterface 181 2 0
    //   370: pop
    //   371: goto -115 -> 256
    //   374: astore 11
    //   376: aload 13
    //   378: monitorexit
    //   379: aload 11
    //   381: athrow
    //   382: astore 11
    //   384: aload 11
    //   386: invokevirtual 184	java/lang/Throwable:printStackTrace	()V
    //   389: aload_0
    //   390: getfield 14	com/tencent/mobileqq/qwallet/report/impl/VACDReportServiceImpl$2:this$0	Lcom/tencent/mobileqq/qwallet/report/impl/VACDReportServiceImpl;
    //   393: invokestatic 70	com/tencent/mobileqq/qwallet/report/impl/VACDReportServiceImpl:access$400	(Lcom/tencent/mobileqq/qwallet/report/impl/VACDReportServiceImpl;)Z
    //   396: ifeq +886 -> 1282
    //   399: aload_0
    //   400: getfield 16	com/tencent/mobileqq/qwallet/report/impl/VACDReportServiceImpl$2:a	Z
    //   403: ifne +879 -> 1282
    //   406: invokestatic 76	com/tencent/mobileqq/msf/core/NetConnInfoCenter:getServerTimeMillis	()J
    //   409: lstore_1
    //   410: lload_1
    //   411: aload_0
    //   412: getfield 14	com/tencent/mobileqq/qwallet/report/impl/VACDReportServiceImpl$2:this$0	Lcom/tencent/mobileqq/qwallet/report/impl/VACDReportServiceImpl;
    //   415: getfield 80	com/tencent/mobileqq/qwallet/report/impl/VACDReportServiceImpl:mLastReportTime	J
    //   418: lcmp
    //   419: ifle +847 -> 1266
    //   422: lload_1
    //   423: aload_0
    //   424: getfield 14	com/tencent/mobileqq/qwallet/report/impl/VACDReportServiceImpl$2:this$0	Lcom/tencent/mobileqq/qwallet/report/impl/VACDReportServiceImpl;
    //   427: getfield 80	com/tencent/mobileqq/qwallet/report/impl/VACDReportServiceImpl:mLastReportTime	J
    //   430: lsub
    //   431: ldc2_w 81
    //   434: lcmp
    //   435: ifle +831 -> 1266
    //   438: invokestatic 29	com/tencent/qphone/base/util/QLog:isColorLevel	()Z
    //   441: ifeq +43 -> 484
    //   444: ldc 31
    //   446: iconst_2
    //   447: new 33	java/lang/StringBuilder
    //   450: dup
    //   451: invokespecial 34	java/lang/StringBuilder:<init>	()V
    //   454: ldc 84
    //   456: invokevirtual 40	java/lang/StringBuilder:append	(Ljava/lang/String;)Ljava/lang/StringBuilder;
    //   459: lload_1
    //   460: invokevirtual 87	java/lang/StringBuilder:append	(J)Ljava/lang/StringBuilder;
    //   463: ldc 89
    //   465: invokevirtual 40	java/lang/StringBuilder:append	(Ljava/lang/String;)Ljava/lang/StringBuilder;
    //   468: aload_0
    //   469: getfield 14	com/tencent/mobileqq/qwallet/report/impl/VACDReportServiceImpl$2:this$0	Lcom/tencent/mobileqq/qwallet/report/impl/VACDReportServiceImpl;
    //   472: getfield 80	com/tencent/mobileqq/qwallet/report/impl/VACDReportServiceImpl:mLastReportTime	J
    //   475: invokevirtual 87	java/lang/StringBuilder:append	(J)Ljava/lang/StringBuilder;
    //   478: invokevirtual 47	java/lang/StringBuilder:toString	()Ljava/lang/String;
    //   481: invokestatic 92	com/tencent/qphone/base/util/QLog:i	(Ljava/lang/String;ILjava/lang/String;)V
    //   484: aload_0
    //   485: getfield 14	com/tencent/mobileqq/qwallet/report/impl/VACDReportServiceImpl$2:this$0	Lcom/tencent/mobileqq/qwallet/report/impl/VACDReportServiceImpl;
    //   488: invokevirtual 95	com/tencent/mobileqq/qwallet/report/impl/VACDReportServiceImpl:onDestroy	()V
    //   491: return
    //   492: aload 16
    //   494: getfield 146	VACDReport/ReportInfo:header	LVACDReport/ReportHeader;
    //   497: ifnonnull +80 -> 577
    //   500: aload 16
    //   502: getfield 150	VACDReport/ReportInfo:body	LVACDReport/ReportBody;
    //   505: ifnull +72 -> 577
    //   508: invokestatic 76	com/tencent/mobileqq/msf/core/NetConnInfoCenter:getServerTimeMillis	()J
    //   511: aload 16
    //   513: getfield 150	VACDReport/ReportInfo:body	LVACDReport/ReportBody;
    //   516: getfield 189	VACDReport/ReportBody:startTime	J
    //   519: lsub
    //   520: invokestatic 164	java/lang/Math:abs	(J)J
    //   523: lstore_1
    //   524: aload 16
    //   526: getfield 150	VACDReport/ReportInfo:body	LVACDReport/ReportBody;
    //   529: getfield 193	VACDReport/ReportBody:reportItems	Ljava/util/ArrayList;
    //   532: ifnull +963 -> 1495
    //   535: aload 16
    //   537: getfield 150	VACDReport/ReportInfo:body	LVACDReport/ReportBody;
    //   540: getfield 193	VACDReport/ReportBody:reportItems	Ljava/util/ArrayList;
    //   543: invokevirtual 197	java/util/ArrayList:size	()I
    //   546: ifle +949 -> 1495
    //   549: aload 16
    //   551: getfield 150	VACDReport/ReportInfo:body	LVACDReport/ReportBody;
    //   554: getfield 193	VACDReport/ReportBody:reportItems	Ljava/util/ArrayList;
    //   557: iconst_0
    //   558: invokevirtual 201	java/util/ArrayList:get	(I)Ljava/lang/Object;
    //   561: checkcast 203	VACDReport/ReportItem
    //   564: getfield 204	VACDReport/ReportItem:seqno	J
    //   567: lstore 5
    //   569: lload_1
    //   570: lstore_3
    //   571: lload 5
    //   573: lstore_1
    //   574: goto -243 -> 331
    //   577: aload 16
    //   579: getfield 146	VACDReport/ReportInfo:header	LVACDReport/ReportHeader;
    //   582: ifnonnull +11 -> 593
    //   585: aload 16
    //   587: getfield 150	VACDReport/ReportInfo:body	LVACDReport/ReportBody;
    //   590: ifnull -334 -> 256
    //   593: lload 7
    //   595: aload 16
    //   597: getfield 146	VACDReport/ReportInfo:header	LVACDReport/ReportHeader;
    //   600: getfield 158	VACDReport/ReportHeader:createTime	J
    //   603: lsub
    //   604: invokestatic 164	java/lang/Math:abs	(J)J
    //   607: lstore_3
    //   608: ldc2_w 205
    //   611: lstore_1
    //   612: goto -281 -> 331
    //   615: lload_1
    //   616: ldc2_w 205
    //   619: lcmp
    //   620: ifne -364 -> 256
    //   623: aload 16
    //   625: getfield 146	VACDReport/ReportInfo:header	LVACDReport/ReportHeader;
    //   628: ifnull -372 -> 256
    //   631: aload 16
    //   633: getfield 150	VACDReport/ReportInfo:body	LVACDReport/ReportBody;
    //   636: ifnull -380 -> 256
    //   639: aload 16
    //   641: getfield 146	VACDReport/ReportInfo:header	LVACDReport/ReportHeader;
    //   644: getfield 209	VACDReport/ReportHeader:totalTime	J
    //   647: lconst_0
    //   648: lcmp
    //   649: ifge -393 -> 256
    //   652: iconst_0
    //   653: istore 10
    //   655: aconst_null
    //   656: astore 12
    //   658: aload 12
    //   660: astore 11
    //   662: iload 10
    //   664: istore 9
    //   666: aload 16
    //   668: getfield 150	VACDReport/ReportInfo:body	LVACDReport/ReportBody;
    //   671: getfield 193	VACDReport/ReportBody:reportItems	Ljava/util/ArrayList;
    //   674: ifnull +72 -> 746
    //   677: aload 12
    //   679: astore 11
    //   681: iload 10
    //   683: istore 9
    //   685: aload 16
    //   687: getfield 150	VACDReport/ReportInfo:body	LVACDReport/ReportBody;
    //   690: getfield 193	VACDReport/ReportBody:reportItems	Ljava/util/ArrayList;
    //   693: invokevirtual 197	java/util/ArrayList:size	()I
    //   696: ifle +50 -> 746
    //   699: aload 16
    //   701: getfield 150	VACDReport/ReportInfo:body	LVACDReport/ReportBody;
    //   704: getfield 193	VACDReport/ReportBody:reportItems	Ljava/util/ArrayList;
    //   707: invokestatic 215	java/util/Collections:sort	(Ljava/util/List;)V
    //   710: aload 16
    //   712: getfield 150	VACDReport/ReportInfo:body	LVACDReport/ReportBody;
    //   715: getfield 193	VACDReport/ReportBody:reportItems	Ljava/util/ArrayList;
    //   718: aload 16
    //   720: getfield 150	VACDReport/ReportInfo:body	LVACDReport/ReportBody;
    //   723: getfield 193	VACDReport/ReportBody:reportItems	Ljava/util/ArrayList;
    //   726: invokevirtual 197	java/util/ArrayList:size	()I
    //   729: iconst_1
    //   730: isub
    //   731: invokevirtual 201	java/util/ArrayList:get	(I)Ljava/lang/Object;
    //   734: checkcast 203	VACDReport/ReportItem
    //   737: astore 11
    //   739: aload 11
    //   741: getfield 218	VACDReport/ReportItem:isNormalEnd	Z
    //   744: istore 9
    //   746: iload 9
    //   748: ifeq +121 -> 869
    //   751: aload 16
    //   753: getfield 146	VACDReport/ReportInfo:header	LVACDReport/ReportHeader;
    //   756: aload 11
    //   758: getfield 219	VACDReport/ReportItem:createTime	J
    //   761: aload 16
    //   763: getfield 146	VACDReport/ReportInfo:header	LVACDReport/ReportHeader;
    //   766: getfield 158	VACDReport/ReportHeader:createTime	J
    //   769: lsub
    //   770: invokestatic 164	java/lang/Math:abs	(J)J
    //   773: putfield 209	VACDReport/ReportHeader:totalTime	J
    //   776: aload 16
    //   778: getfield 150	VACDReport/ReportInfo:body	LVACDReport/ReportBody;
    //   781: aload 16
    //   783: getfield 146	VACDReport/ReportInfo:header	LVACDReport/ReportHeader;
    //   786: getfield 209	VACDReport/ReportHeader:totalTime	J
    //   789: putfield 220	VACDReport/ReportBody:totalTime	J
    //   792: invokestatic 29	com/tencent/qphone/base/util/QLog:isColorLevel	()Z
    //   795: ifeq -539 -> 256
    //   798: aload 16
    //   800: getfield 146	VACDReport/ReportInfo:header	LVACDReport/ReportHeader;
    //   803: getfield 209	VACDReport/ReportHeader:totalTime	J
    //   806: lconst_0
    //   807: lcmp
    //   808: iflt -552 -> 256
    //   811: ldc 31
    //   813: iconst_2
    //   814: new 33	java/lang/StringBuilder
    //   817: dup
    //   818: invokespecial 34	java/lang/StringBuilder:<init>	()V
    //   821: ldc 222
    //   823: invokevirtual 40	java/lang/StringBuilder:append	(Ljava/lang/String;)Ljava/lang/StringBuilder;
    //   826: aload 16
    //   828: getfield 146	VACDReport/ReportInfo:header	LVACDReport/ReportHeader;
    //   831: getfield 155	VACDReport/ReportHeader:seqno	J
    //   834: invokevirtual 87	java/lang/StringBuilder:append	(J)Ljava/lang/StringBuilder;
    //   837: ldc 224
    //   839: invokevirtual 40	java/lang/StringBuilder:append	(Ljava/lang/String;)Ljava/lang/StringBuilder;
    //   842: lload_3
    //   843: ldc2_w 225
    //   846: ldiv
    //   847: invokevirtual 87	java/lang/StringBuilder:append	(J)Ljava/lang/StringBuilder;
    //   850: ldc 228
    //   852: invokevirtual 40	java/lang/StringBuilder:append	(Ljava/lang/String;)Ljava/lang/StringBuilder;
    //   855: iload 9
    //   857: invokevirtual 43	java/lang/StringBuilder:append	(Z)Ljava/lang/StringBuilder;
    //   860: invokevirtual 47	java/lang/StringBuilder:toString	()Ljava/lang/String;
    //   863: invokestatic 51	com/tencent/qphone/base/util/QLog:d	(Ljava/lang/String;ILjava/lang/String;)V
    //   866: goto -610 -> 256
    //   869: getstatic 233	com/tencent/mobileqq/qwallet/report/VACDConstants:a	Ljava/util/Set;
    //   872: aload 16
    //   874: getfield 146	VACDReport/ReportInfo:header	LVACDReport/ReportHeader;
    //   877: getfield 237	VACDReport/ReportHeader:sModule	Ljava/lang/String;
    //   880: invokeinterface 238 2 0
    //   885: ifeq +46 -> 931
    //   888: aload 14
    //   890: aload 16
    //   892: getfield 146	VACDReport/ReportInfo:header	LVACDReport/ReportHeader;
    //   895: getfield 155	VACDReport/ReportHeader:seqno	J
    //   898: invokestatic 172	java/lang/Long:valueOf	(J)Ljava/lang/Long;
    //   901: invokeinterface 178 2 0
    //   906: ifne -650 -> 256
    //   909: aload 14
    //   911: aload 16
    //   913: getfield 146	VACDReport/ReportInfo:header	LVACDReport/ReportHeader;
    //   916: getfield 155	VACDReport/ReportHeader:seqno	J
    //   919: invokestatic 172	java/lang/Long:valueOf	(J)Ljava/lang/Long;
    //   922: invokeinterface 181 2 0
    //   927: pop
    //   928: goto -672 -> 256
    //   931: lload_3
    //   932: ldc2_w 165
    //   935: lcmp
    //   936: iflt -144 -> 792
    //   939: aload 11
    //   941: ifnull +105 -> 1046
    //   944: aload 16
    //   946: getfield 146	VACDReport/ReportInfo:header	LVACDReport/ReportHeader;
    //   949: aload 11
    //   951: getfield 219	VACDReport/ReportItem:createTime	J
    //   954: aload 16
    //   956: getfield 146	VACDReport/ReportInfo:header	LVACDReport/ReportHeader;
    //   959: getfield 158	VACDReport/ReportHeader:createTime	J
    //   962: lsub
    //   963: invokestatic 164	java/lang/Math:abs	(J)J
    //   966: putfield 209	VACDReport/ReportHeader:totalTime	J
    //   969: aload 16
    //   971: getfield 150	VACDReport/ReportInfo:body	LVACDReport/ReportBody;
    //   974: aload 16
    //   976: getfield 146	VACDReport/ReportInfo:header	LVACDReport/ReportHeader;
    //   979: getfield 209	VACDReport/ReportHeader:totalTime	J
    //   982: putfield 220	VACDReport/ReportBody:totalTime	J
    //   985: new 203	VACDReport/ReportItem
    //   988: dup
    //   989: invokespecial 239	VACDReport/ReportItem:<init>	()V
    //   992: astore 11
    //   994: aload 11
    //   996: ldc 241
    //   998: putfield 244	VACDReport/ReportItem:step	Ljava/lang/String;
    //   1001: aload 11
    //   1003: ldc 246
    //   1005: putfield 249	VACDReport/ReportItem:params	Ljava/lang/String;
    //   1008: aload 11
    //   1010: lload 7
    //   1012: putfield 219	VACDReport/ReportItem:createTime	J
    //   1015: aload 11
    //   1017: ldc 250
    //   1019: putfield 253	VACDReport/ReportItem:result	I
    //   1022: aload 11
    //   1024: ldc 255
    //   1026: putfield 258	VACDReport/ReportItem:failReason	Ljava/lang/String;
    //   1029: aload 16
    //   1031: getfield 150	VACDReport/ReportInfo:body	LVACDReport/ReportBody;
    //   1034: getfield 193	VACDReport/ReportBody:reportItems	Ljava/util/ArrayList;
    //   1037: aload 11
    //   1039: invokevirtual 259	java/util/ArrayList:add	(Ljava/lang/Object;)Z
    //   1042: pop
    //   1043: goto -251 -> 792
    //   1046: aload 16
    //   1048: getfield 146	VACDReport/ReportInfo:header	LVACDReport/ReportHeader;
    //   1051: lload 7
    //   1053: aload 16
    //   1055: getfield 146	VACDReport/ReportInfo:header	LVACDReport/ReportHeader;
    //   1058: getfield 158	VACDReport/ReportHeader:createTime	J
    //   1061: lsub
    //   1062: invokestatic 164	java/lang/Math:abs	(J)J
    //   1065: putfield 209	VACDReport/ReportHeader:totalTime	J
    //   1068: goto -99 -> 969
    //   1071: aload_0
    //   1072: getfield 14	com/tencent/mobileqq/qwallet/report/impl/VACDReportServiceImpl$2:this$0	Lcom/tencent/mobileqq/qwallet/report/impl/VACDReportServiceImpl;
    //   1075: iconst_3
    //   1076: invokestatic 263	com/tencent/mobileqq/qwallet/report/impl/VACDReportServiceImpl:access$300	(Lcom/tencent/mobileqq/qwallet/report/impl/VACDReportServiceImpl;I)V
    //   1079: aload 14
    //   1081: invokeinterface 264 1 0
    //   1086: ifne +15 -> 1101
    //   1089: aload_0
    //   1090: getfield 14	com/tencent/mobileqq/qwallet/report/impl/VACDReportServiceImpl$2:this$0	Lcom/tencent/mobileqq/qwallet/report/impl/VACDReportServiceImpl;
    //   1093: invokestatic 268	com/tencent/mobileqq/qwallet/report/impl/VACDReportServiceImpl:access$200	(Lcom/tencent/mobileqq/qwallet/report/impl/VACDReportServiceImpl;)Lcom/tencent/mobileqq/qwallet/report/impl/VACDReportDBHelper;
    //   1096: aload 14
    //   1098: invokevirtual 272	com/tencent/mobileqq/qwallet/report/impl/VACDReportDBHelper:a	(Ljava/util/List;)V
    //   1101: aload 13
    //   1103: monitorexit
    //   1104: aload_0
    //   1105: getfield 14	com/tencent/mobileqq/qwallet/report/impl/VACDReportServiceImpl$2:this$0	Lcom/tencent/mobileqq/qwallet/report/impl/VACDReportServiceImpl;
    //   1108: invokestatic 70	com/tencent/mobileqq/qwallet/report/impl/VACDReportServiceImpl:access$400	(Lcom/tencent/mobileqq/qwallet/report/impl/VACDReportServiceImpl;)Z
    //   1111: ifeq +112 -> 1223
    //   1114: aload_0
    //   1115: getfield 16	com/tencent/mobileqq/qwallet/report/impl/VACDReportServiceImpl$2:a	Z
    //   1118: ifne +105 -> 1223
    //   1121: invokestatic 76	com/tencent/mobileqq/msf/core/NetConnInfoCenter:getServerTimeMillis	()J
    //   1124: lstore_1
    //   1125: lload_1
    //   1126: aload_0
    //   1127: getfield 14	com/tencent/mobileqq/qwallet/report/impl/VACDReportServiceImpl$2:this$0	Lcom/tencent/mobileqq/qwallet/report/impl/VACDReportServiceImpl;
    //   1130: getfield 80	com/tencent/mobileqq/qwallet/report/impl/VACDReportServiceImpl:mLastReportTime	J
    //   1133: lcmp
    //   1134: ifle +73 -> 1207
    //   1137: lload_1
    //   1138: aload_0
    //   1139: getfield 14	com/tencent/mobileqq/qwallet/report/impl/VACDReportServiceImpl$2:this$0	Lcom/tencent/mobileqq/qwallet/report/impl/VACDReportServiceImpl;
    //   1142: getfield 80	com/tencent/mobileqq/qwallet/report/impl/VACDReportServiceImpl:mLastReportTime	J
    //   1145: lsub
    //   1146: ldc2_w 81
    //   1149: lcmp
    //   1150: ifle +57 -> 1207
    //   1153: invokestatic 29	com/tencent/qphone/base/util/QLog:isColorLevel	()Z
    //   1156: ifeq +43 -> 1199
    //   1159: ldc 31
    //   1161: iconst_2
    //   1162: new 33	java/lang/StringBuilder
    //   1165: dup
    //   1166: invokespecial 34	java/lang/StringBuilder:<init>	()V
    //   1169: ldc 84
    //   1171: invokevirtual 40	java/lang/StringBuilder:append	(Ljava/lang/String;)Ljava/lang/StringBuilder;
    //   1174: lload_1
    //   1175: invokevirtual 87	java/lang/StringBuilder:append	(J)Ljava/lang/StringBuilder;
    //   1178: ldc 89
    //   1180: invokevirtual 40	java/lang/StringBuilder:append	(Ljava/lang/String;)Ljava/lang/StringBuilder;
    //   1183: aload_0
    //   1184: getfield 14	com/tencent/mobileqq/qwallet/report/impl/VACDReportServiceImpl$2:this$0	Lcom/tencent/mobileqq/qwallet/report/impl/VACDReportServiceImpl;
    //   1187: getfield 80	com/tencent/mobileqq/qwallet/report/impl/VACDReportServiceImpl:mLastReportTime	J
    //   1190: invokevirtual 87	java/lang/StringBuilder:append	(J)Ljava/lang/StringBuilder;
    //   1193: invokevirtual 47	java/lang/StringBuilder:toString	()Ljava/lang/String;
    //   1196: invokestatic 92	com/tencent/qphone/base/util/QLog:i	(Ljava/lang/String;ILjava/lang/String;)V
    //   1199: aload_0
    //   1200: getfield 14	com/tencent/mobileqq/qwallet/report/impl/VACDReportServiceImpl$2:this$0	Lcom/tencent/mobileqq/qwallet/report/impl/VACDReportServiceImpl;
    //   1203: invokevirtual 95	com/tencent/mobileqq/qwallet/report/impl/VACDReportServiceImpl:onDestroy	()V
    //   1206: return
    //   1207: aload_0
    //   1208: getfield 14	com/tencent/mobileqq/qwallet/report/impl/VACDReportServiceImpl$2:this$0	Lcom/tencent/mobileqq/qwallet/report/impl/VACDReportServiceImpl;
    //   1211: invokestatic 99	com/tencent/mobileqq/qwallet/report/impl/VACDReportServiceImpl:access$500	(Lcom/tencent/mobileqq/qwallet/report/impl/VACDReportServiceImpl;)Landroid/os/Handler;
    //   1214: aload_0
    //   1215: ldc2_w 100
    //   1218: invokevirtual 107	android/os/Handler:postDelayed	(Ljava/lang/Runnable;J)Z
    //   1221: pop
    //   1222: return
    //   1223: invokestatic 29	com/tencent/qphone/base/util/QLog:isColorLevel	()Z
    //   1226: ifeq +11 -> 1237
    //   1229: ldc 31
    //   1231: iconst_2
    //   1232: ldc 109
    //   1234: invokestatic 51	com/tencent/qphone/base/util/QLog:d	(Ljava/lang/String;ILjava/lang/String;)V
    //   1237: aload_0
    //   1238: getfield 16	com/tencent/mobileqq/qwallet/report/impl/VACDReportServiceImpl$2:a	Z
    //   1241: ifeq -1079 -> 162
    //   1244: invokestatic 29	com/tencent/qphone/base/util/QLog:isColorLevel	()Z
    //   1247: ifeq +11 -> 1258
    //   1250: ldc 31
    //   1252: iconst_2
    //   1253: ldc 111
    //   1255: invokestatic 92	com/tencent/qphone/base/util/QLog:i	(Ljava/lang/String;ILjava/lang/String;)V
    //   1258: aload_0
    //   1259: getfield 14	com/tencent/mobileqq/qwallet/report/impl/VACDReportServiceImpl$2:this$0	Lcom/tencent/mobileqq/qwallet/report/impl/VACDReportServiceImpl;
    //   1262: invokevirtual 95	com/tencent/mobileqq/qwallet/report/impl/VACDReportServiceImpl:onDestroy	()V
    //   1265: return
    //   1266: aload_0
    //   1267: getfield 14	com/tencent/mobileqq/qwallet/report/impl/VACDReportServiceImpl$2:this$0	Lcom/tencent/mobileqq/qwallet/report/impl/VACDReportServiceImpl;
    //   1270: invokestatic 99	com/tencent/mobileqq/qwallet/report/impl/VACDReportServiceImpl:access$500	(Lcom/tencent/mobileqq/qwallet/report/impl/VACDReportServiceImpl;)Landroid/os/Handler;
    //   1273: aload_0
    //   1274: ldc2_w 100
    //   1277: invokevirtual 107	android/os/Handler:postDelayed	(Ljava/lang/Runnable;J)Z
    //   1280: pop
    //   1281: return
    //   1282: invokestatic 29	com/tencent/qphone/base/util/QLog:isColorLevel	()Z
    //   1285: ifeq +11 -> 1296
    //   1288: ldc 31
    //   1290: iconst_2
    //   1291: ldc 109
    //   1293: invokestatic 51	com/tencent/qphone/base/util/QLog:d	(Ljava/lang/String;ILjava/lang/String;)V
    //   1296: aload_0
    //   1297: getfield 16	com/tencent/mobileqq/qwallet/report/impl/VACDReportServiceImpl$2:a	Z
    //   1300: ifeq -1138 -> 162
    //   1303: invokestatic 29	com/tencent/qphone/base/util/QLog:isColorLevel	()Z
    //   1306: ifeq +11 -> 1317
    //   1309: ldc 31
    //   1311: iconst_2
    //   1312: ldc 111
    //   1314: invokestatic 92	com/tencent/qphone/base/util/QLog:i	(Ljava/lang/String;ILjava/lang/String;)V
    //   1317: aload_0
    //   1318: getfield 14	com/tencent/mobileqq/qwallet/report/impl/VACDReportServiceImpl$2:this$0	Lcom/tencent/mobileqq/qwallet/report/impl/VACDReportServiceImpl;
    //   1321: invokevirtual 95	com/tencent/mobileqq/qwallet/report/impl/VACDReportServiceImpl:onDestroy	()V
    //   1324: return
    //   1325: astore 11
    //   1327: aload_0
    //   1328: getfield 14	com/tencent/mobileqq/qwallet/report/impl/VACDReportServiceImpl$2:this$0	Lcom/tencent/mobileqq/qwallet/report/impl/VACDReportServiceImpl;
    //   1331: invokestatic 70	com/tencent/mobileqq/qwallet/report/impl/VACDReportServiceImpl:access$400	(Lcom/tencent/mobileqq/qwallet/report/impl/VACDReportServiceImpl;)Z
    //   1334: ifeq +116 -> 1450
    //   1337: aload_0
    //   1338: getfield 16	com/tencent/mobileqq/qwallet/report/impl/VACDReportServiceImpl$2:a	Z
    //   1341: ifne +109 -> 1450
    //   1344: invokestatic 76	com/tencent/mobileqq/msf/core/NetConnInfoCenter:getServerTimeMillis	()J
    //   1347: lstore_1
    //   1348: lload_1
    //   1349: aload_0
    //   1350: getfield 14	com/tencent/mobileqq/qwallet/report/impl/VACDReportServiceImpl$2:this$0	Lcom/tencent/mobileqq/qwallet/report/impl/VACDReportServiceImpl;
    //   1353: getfield 80	com/tencent/mobileqq/qwallet/report/impl/VACDReportServiceImpl:mLastReportTime	J
    //   1356: lcmp
    //   1357: ifle +75 -> 1432
    //   1360: lload_1
    //   1361: aload_0
    //   1362: getfield 14	com/tencent/mobileqq/qwallet/report/impl/VACDReportServiceImpl$2:this$0	Lcom/tencent/mobileqq/qwallet/report/impl/VACDReportServiceImpl;
    //   1365: getfield 80	com/tencent/mobileqq/qwallet/report/impl/VACDReportServiceImpl:mLastReportTime	J
    //   1368: lsub
    //   1369: ldc2_w 81
    //   1372: lcmp
    //   1373: ifle +59 -> 1432
    //   1376: invokestatic 29	com/tencent/qphone/base/util/QLog:isColorLevel	()Z
    //   1379: ifeq +43 -> 1422
    //   1382: ldc 31
    //   1384: iconst_2
    //   1385: new 33	java/lang/StringBuilder
    //   1388: dup
    //   1389: invokespecial 34	java/lang/StringBuilder:<init>	()V
    //   1392: ldc 84
    //   1394: invokevirtual 40	java/lang/StringBuilder:append	(Ljava/lang/String;)Ljava/lang/StringBuilder;
    //   1397: lload_1
    //   1398: invokevirtual 87	java/lang/StringBuilder:append	(J)Ljava/lang/StringBuilder;
    //   1401: ldc 89
    //   1403: invokevirtual 40	java/lang/StringBuilder:append	(Ljava/lang/String;)Ljava/lang/StringBuilder;
    //   1406: aload_0
    //   1407: getfield 14	com/tencent/mobileqq/qwallet/report/impl/VACDReportServiceImpl$2:this$0	Lcom/tencent/mobileqq/qwallet/report/impl/VACDReportServiceImpl;
    //   1410: getfield 80	com/tencent/mobileqq/qwallet/report/impl/VACDReportServiceImpl:mLastReportTime	J
    //   1413: invokevirtual 87	java/lang/StringBuilder:append	(J)Ljava/lang/StringBuilder;
    //   1416: invokevirtual 47	java/lang/StringBuilder:toString	()Ljava/lang/String;
    //   1419: invokestatic 92	com/tencent/qphone/base/util/QLog:i	(Ljava/lang/String;ILjava/lang/String;)V
    //   1422: aload_0
    //   1423: getfield 14	com/tencent/mobileqq/qwallet/report/impl/VACDReportServiceImpl$2:this$0	Lcom/tencent/mobileqq/qwallet/report/impl/VACDReportServiceImpl;
    //   1426: invokevirtual 95	com/tencent/mobileqq/qwallet/report/impl/VACDReportServiceImpl:onDestroy	()V
    //   1429: aload 11
    //   1431: athrow
    //   1432: aload_0
    //   1433: getfield 14	com/tencent/mobileqq/qwallet/report/impl/VACDReportServiceImpl$2:this$0	Lcom/tencent/mobileqq/qwallet/report/impl/VACDReportServiceImpl;
    //   1436: invokestatic 99	com/tencent/mobileqq/qwallet/report/impl/VACDReportServiceImpl:access$500	(Lcom/tencent/mobileqq/qwallet/report/impl/VACDReportServiceImpl;)Landroid/os/Handler;
    //   1439: aload_0
    //   1440: ldc2_w 100
    //   1443: invokevirtual 107	android/os/Handler:postDelayed	(Ljava/lang/Runnable;J)Z
    //   1446: pop
    //   1447: goto -18 -> 1429
    //   1450: invokestatic 29	com/tencent/qphone/base/util/QLog:isColorLevel	()Z
    //   1453: ifeq +11 -> 1464
    //   1456: ldc 31
    //   1458: iconst_2
    //   1459: ldc 109
    //   1461: invokestatic 51	com/tencent/qphone/base/util/QLog:d	(Ljava/lang/String;ILjava/lang/String;)V
    //   1464: aload_0
    //   1465: getfield 16	com/tencent/mobileqq/qwallet/report/impl/VACDReportServiceImpl$2:a	Z
    //   1468: ifeq -39 -> 1429
    //   1471: invokestatic 29	com/tencent/qphone/base/util/QLog:isColorLevel	()Z
    //   1474: ifeq +11 -> 1485
    //   1477: ldc 31
    //   1479: iconst_2
    //   1480: ldc 111
    //   1482: invokestatic 92	com/tencent/qphone/base/util/QLog:i	(Ljava/lang/String;ILjava/lang/String;)V
    //   1485: aload_0
    //   1486: getfield 14	com/tencent/mobileqq/qwallet/report/impl/VACDReportServiceImpl$2:this$0	Lcom/tencent/mobileqq/qwallet/report/impl/VACDReportServiceImpl;
    //   1489: invokevirtual 95	com/tencent/mobileqq/qwallet/report/impl/VACDReportServiceImpl:onDestroy	()V
    //   1492: goto -63 -> 1429
    //   1495: ldc2_w 205
    //   1498: lstore 5
    //   1500: lload_1
    //   1501: lstore_3
    //   1502: lload 5
    //   1504: lstore_1
    //   1505: goto -1174 -> 331
    // Local variable table:
    //   start	length	slot	name	signature
    //   0	1508	0	this	2
    //   80	1425	1	l1	long
    //   330	1172	3	l2	long
    //   567	936	5	l3	long
    //   225	827	7	l4	long
    //   664	192	9	bool1	boolean
    //   653	29	10	bool2	boolean
    //   374	6	11	localObject1	Object
    //   382	3	11	localThrowable	java.lang.Throwable
    //   660	378	11	localObject2	Object
    //   1325	105	11	localObject3	Object
    //   656	22	12	localObject4	Object
    //   235	862	14	localArrayList	java.util.ArrayList
    //   254	13	15	localIterator	java.util.Iterator
    //   284	770	16	localReportInfo	VACDReport.ReportInfo
    // Exception table:
    //   from	to	target	type
    //   42	60	374	finally
    //   222	256	374	finally
    //   256	286	374	finally
    //   291	331	374	finally
    //   345	371	374	finally
    //   376	379	374	finally
    //   492	569	374	finally
    //   577	593	374	finally
    //   593	608	374	finally
    //   623	652	374	finally
    //   666	677	374	finally
    //   685	746	374	finally
    //   751	792	374	finally
    //   792	866	374	finally
    //   869	928	374	finally
    //   944	969	374	finally
    //   969	1043	374	finally
    //   1046	1068	374	finally
    //   1071	1101	374	finally
    //   1101	1104	374	finally
    //   34	42	382	java/lang/Throwable
    //   379	382	382	java/lang/Throwable
    //   34	42	1325	finally
    //   379	382	1325	finally
    //   384	389	1325	finally
  }
}


/* Location:           L:\local\mybackup\temp\qq_apk\com.tencent.mobileqq\classes9.jar
 * Qualified Name:     com.tencent.mobileqq.qwallet.report.impl.VACDReportServiceImpl.2
 * JD-Core Version:    0.7.0.1
 */