package com.tencent.luggage.wxa.oa;

import android.webkit.URLUtil;
import com.tencent.luggage.wxa.ba.e;
import com.tencent.luggage.wxa.nz.j;
import com.tencent.luggage.wxa.qz.af;
import com.tencent.luggage.wxa.qz.r;
import com.tencent.luggage.wxa.qz.x;
import com.tencent.luggage.wxa.rc.d;
import com.tencent.luggage.wxa.rc.d.a;
import com.tencent.luggage.wxa.rz.f;
import com.tencent.luggage.wxa.rz.g;
import com.tencent.mars.cdn.CronetLogic;
import com.tencent.mars.cdn.CronetLogic.CronetHttpsCreateResult;
import com.tencent.mars.cdn.CronetLogic.CronetRequestParams;
import com.tencent.mars.cdn.CronetLogic.CronetTaskCallback;
import java.io.IOException;
import java.io.InputStream;
import java.net.HttpURLConnection;
import java.util.ArrayList;
import java.util.Map;
import javax.net.ssl.SSLContext;
import org.json.JSONObject;

public class b
  implements Runnable
{
  com.tencent.luggage.wxa.jx.c a;
  private int b = 15;
  private final a c;
  private volatile boolean d = false;
  private volatile boolean e = false;
  private String f;
  private String g;
  private String h;
  private String i = "unknow";
  private Map<String, String> j;
  private int k = 60000;
  private SSLContext l;
  private ArrayList<String> m;
  private volatile int n;
  private long o;
  private String p;
  private HttpURLConnection q;
  private String r;
  private long s;
  private String t;
  private final String u;
  private boolean v = false;
  private boolean w = false;
  private boolean x = false;
  private boolean y = false;
  private boolean z = true;
  
  public b(com.tencent.luggage.wxa.jx.c paramc, String paramString1, String paramString2, String paramString3, String paramString4, boolean paramBoolean1, boolean paramBoolean2, boolean paramBoolean3, boolean paramBoolean4, boolean paramBoolean5, a parama)
  {
    this.a = paramc;
    this.f = paramString1;
    this.g = paramString2;
    this.h = paramString3;
    this.c = parama;
    this.s = System.currentTimeMillis();
    this.u = paramString4;
    this.v = paramBoolean1;
    this.w = paramBoolean2;
    this.x = paramBoolean3;
    this.y = paramBoolean4;
    this.z = paramBoolean5;
  }
  
  private String a(String paramString1, String paramString2)
  {
    paramString1 = d.a.a(paramString1);
    if (paramString1 == null) {
      return d.b(paramString2);
    }
    if (paramString1.a.contains("application/octet-stream"))
    {
      paramString2 = d.b(paramString2);
      if (af.c(paramString2)) {
        return paramString1.a;
      }
      return paramString2;
    }
    return paramString1.a;
  }
  
  private void a(long paramLong1, long paramLong2)
  {
    if ((paramLong1 > 0L) && (paramLong2 > 0L))
    {
      int i1 = 34;
      double d1 = paramLong1;
      double d2 = paramLong2;
      Double.isNaN(d1);
      Double.isNaN(d2);
      d1 = d1 / d2 * 0.9765625D;
      if (x.f(r.a())) {
        i1 = 30;
      } else if (x.i(r.a())) {
        i1 = 31;
      } else if (x.g(r.a())) {
        i1 = 32;
      } else if (x.j(r.a())) {
        i1 = 33;
      }
      ((com.tencent.luggage.wxa.ot.c)e.b(com.tencent.luggage.wxa.ot.c.class)).a(437L, i1, d1, false);
      com.tencent.luggage.wxa.qz.o.d("MicroMsg.AppBrandDownloadWorker", "reportSpeed len:%d, time:%d, speed:%f, key:%d", new Object[] { Long.valueOf(paramLong1), Long.valueOf(paramLong2), Double.valueOf(d1), Integer.valueOf(i1) });
      return;
    }
    com.tencent.luggage.wxa.qz.o.d("MicroMsg.AppBrandDownloadWorker", "reportSpeed len:%d, time:%d return", new Object[] { Long.valueOf(paramLong1), Long.valueOf(paramLong2) });
  }
  
  private void b(long paramLong1, long paramLong2)
  {
    if ((paramLong1 > 0L) && (paramLong2 > 0L))
    {
      int i1 = 34;
      double d1 = paramLong1;
      double d2 = paramLong2;
      Double.isNaN(d1);
      Double.isNaN(d2);
      d1 = d1 / d2 * 0.9765625D;
      if (x.f(r.a())) {
        i1 = 30;
      } else if (x.i(r.a())) {
        i1 = 31;
      } else if (x.g(r.a())) {
        i1 = 32;
      } else if (x.j(r.a())) {
        i1 = 33;
      }
      ((com.tencent.luggage.wxa.ot.c)e.b(com.tencent.luggage.wxa.ot.c.class)).a(1197L, i1, d1, false);
      com.tencent.luggage.wxa.qz.o.d("MicroMsg.AppBrandDownloadWorker", "reportCronetSpeed len:%d, time:%d, speed:%f, key:%d", new Object[] { Long.valueOf(paramLong1), Long.valueOf(paramLong2), Double.valueOf(d1), Integer.valueOf(i1) });
      return;
    }
    com.tencent.luggage.wxa.qz.o.d("MicroMsg.AppBrandDownloadWorker", "reportCronetSpeed len:%d, time:%d return", new Object[] { Long.valueOf(paramLong1), Long.valueOf(paramLong2) });
  }
  
  private void c(int paramInt)
  {
    int i1;
    if ((paramInt >= 100) && (paramInt < 200)) {
      i1 = 20;
    } else if (200 == paramInt) {
      i1 = 21;
    } else if ((paramInt > 200) && (paramInt < 300)) {
      i1 = 22;
    } else if (302 == paramInt) {
      i1 = 23;
    } else if ((paramInt >= 300) && (paramInt < 400)) {
      i1 = 24;
    } else if (404 == paramInt) {
      i1 = 25;
    } else if ((paramInt >= 400) && (paramInt < 500)) {
      i1 = 26;
    } else if (paramInt >= 500) {
      i1 = 27;
    } else {
      i1 = 28;
    }
    ((com.tencent.luggage.wxa.ot.c)e.b(com.tencent.luggage.wxa.ot.c.class)).a(437L, i1, 1L, false);
    com.tencent.luggage.wxa.qz.o.d("MicroMsg.AppBrandDownloadWorker", "reportStatusCode:%d, key:%d", new Object[] { Integer.valueOf(paramInt), Integer.valueOf(i1) });
  }
  
  private void d(int paramInt)
  {
    int i1;
    if ((paramInt >= 100) && (paramInt < 200)) {
      i1 = 20;
    } else if (200 == paramInt) {
      i1 = 21;
    } else if ((paramInt > 200) && (paramInt < 300)) {
      i1 = 22;
    } else if (302 == paramInt) {
      i1 = 23;
    } else if ((paramInt >= 300) && (paramInt < 400)) {
      i1 = 24;
    } else if (404 == paramInt) {
      i1 = 25;
    } else if ((paramInt >= 400) && (paramInt < 500)) {
      i1 = 26;
    } else if (paramInt >= 500) {
      i1 = 27;
    } else {
      i1 = 28;
    }
    ((com.tencent.luggage.wxa.ot.c)e.b(com.tencent.luggage.wxa.ot.c.class)).a(1197L, i1, 1L, false);
    com.tencent.luggage.wxa.qz.o.d("MicroMsg.AppBrandDownloadWorker", "reportCronetStatusCode:%d, key:%d", new Object[] { Integer.valueOf(paramInt), Integer.valueOf(i1) });
  }
  
  private void f()
  {
    long l1 = System.currentTimeMillis();
    Object localObject2 = new b.a(this);
    if (!this.d)
    {
      this.c.a(this.g, this.f, "force stop");
      if (af.c(this.h))
      {
        ((com.tencent.luggage.wxa.nz.o)e.b(com.tencent.luggage.wxa.nz.o.class)).a(this.a.getAppId(), d(), "GET", a(), 0L, 0L, 0, 2, e(), this.g, this.i);
        return;
      }
      ((com.tencent.luggage.wxa.nz.o)e.b(com.tencent.luggage.wxa.nz.o.class)).a(this.a.getAppId(), d(), "GET", a(), 0L, 0L, 0, 2, e(), this.h, this.i);
      return;
    }
    this.o = System.currentTimeMillis();
    this.c.a(this.g, this.f);
    ((com.tencent.luggage.wxa.ot.c)e.b(com.tencent.luggage.wxa.ot.c.class)).a(1197L, 0L, 1L, false);
    com.tencent.luggage.wxa.qz.o.d("MicroMsg.AppBrandDownloadWorker", "downloadCronetFile prepare to start download taskid is %s, usehttp2 is %b, usequic is %b, usecache is %b, url is %s, filename is %s", new Object[] { this.p, Boolean.valueOf(this.w), Boolean.valueOf(this.x), Boolean.valueOf(this.y), this.f, this.g });
    Object localObject1 = new b.1(this);
    localObject2 = new b.2(this, (com.tencent.luggage.wxa.sj.b)localObject1, (b.a)localObject2, l1);
    CronetLogic.CronetRequestParams localCronetRequestParams = new CronetLogic.CronetRequestParams();
    localCronetRequestParams.url = this.f;
    localCronetRequestParams.taskId = this.p;
    localCronetRequestParams.followRedirect = false;
    localCronetRequestParams.savePath = this.g;
    localCronetRequestParams.method = "GET";
    localCronetRequestParams.needWirteCache = true;
    localCronetRequestParams.useHttp2 = this.w;
    localCronetRequestParams.useQuic = this.x;
    localCronetRequestParams.useMemoryCache = this.y;
    Object localObject3 = this.j;
    if (!((Map)localObject3).containsKey("Accept-Encoding")) {
      ((Map)localObject3).put("Accept-Encoding", "gzip,compress,br,deflate");
    } else {
      com.tencent.luggage.wxa.qz.o.d("MicroMsg.AppBrandDownloadWorker", "startCronetHttpsRequest Accept-Encoding:%s", new Object[] { ((Map)localObject3).get("Accept-Encoding") });
    }
    ((Map)localObject3).put("User-Agent", this.u);
    localCronetRequestParams.makeRequestHeader((Map)localObject3);
    localObject3 = j.a(j.a((Map)localObject3), 1);
    this.c.a((JSONObject)localObject3);
    localCronetRequestParams.taskType = 2;
    f.a.b((Runnable)localObject1, this.k);
    com.tencent.luggage.wxa.qz.o.d("MicroMsg.AppBrandDownloadWorker", "startCronetHttpsRequest taskId:%s", new Object[] { localCronetRequestParams.taskId });
    localObject1 = CronetLogic.startCronetDownloadTask(localCronetRequestParams, (CronetLogic.CronetTaskCallback)localObject2);
    com.tencent.luggage.wxa.qz.o.d("MicroMsg.AppBrandDownloadWorker", "startCronetHttpsRequest createRet is %d, taskId %s,CronetRequestId:%s", new Object[] { Integer.valueOf(((CronetLogic.CronetHttpsCreateResult)localObject1).createRet), this.p, ((CronetLogic.CronetHttpsCreateResult)localObject1).taskId });
    if ((localObject1 != null) && (((CronetLogic.CronetHttpsCreateResult)localObject1).createRet != 0))
    {
      ((com.tencent.luggage.wxa.ot.c)e.b(com.tencent.luggage.wxa.ot.c.class)).a(1197L, 1L, 1L, false);
      return;
    }
    this.r = ((CronetLogic.CronetHttpsCreateResult)localObject1).taskId;
    ((com.tencent.luggage.wxa.ot.c)e.b(com.tencent.luggage.wxa.ot.c.class)).a(1197L, 2L, 1L, false);
  }
  
  /* Error */
  private void g()
  {
    // Byte code:
    //   0: ldc_w 381
    //   3: astore 13
    //   5: ldc_w 383
    //   8: astore 17
    //   10: invokestatic 88	java/lang/System:currentTimeMillis	()J
    //   13: lstore 5
    //   15: aload_0
    //   16: getfield 53	com/tencent/luggage/wxa/oa/b:d	Z
    //   19: ifne +130 -> 149
    //   22: aload_0
    //   23: getfield 82	com/tencent/luggage/wxa/oa/b:c	Lcom/tencent/luggage/wxa/oa/a;
    //   26: aload_0
    //   27: getfield 78	com/tencent/luggage/wxa/oa/b:g	Ljava/lang/String;
    //   30: aload_0
    //   31: getfield 76	com/tencent/luggage/wxa/oa/b:f	Ljava/lang/String;
    //   34: ldc 216
    //   36: invokeinterface 221 4 0
    //   41: aload_0
    //   42: getfield 80	com/tencent/luggage/wxa/oa/b:h	Ljava/lang/String;
    //   45: invokestatic 124	com/tencent/luggage/wxa/qz/af:c	(Ljava/lang/String;)Z
    //   48: ifeq +52 -> 100
    //   51: ldc 223
    //   53: invokestatic 156	com/tencent/luggage/wxa/ba/e:b	(Ljava/lang/Class;)Lcom/tencent/luggage/wxa/ba/d;
    //   56: checkcast 223	com/tencent/luggage/wxa/nz/o
    //   59: aload_0
    //   60: getfield 74	com/tencent/luggage/wxa/oa/b:a	Lcom/tencent/luggage/wxa/jx/c;
    //   63: invokeinterface 229 1 0
    //   68: aload_0
    //   69: invokevirtual 231	com/tencent/luggage/wxa/oa/b:d	()Ljava/lang/String;
    //   72: ldc 233
    //   74: aload_0
    //   75: invokevirtual 235	com/tencent/luggage/wxa/oa/b:a	()Ljava/lang/String;
    //   78: lconst_0
    //   79: lconst_0
    //   80: iconst_0
    //   81: iconst_2
    //   82: aload_0
    //   83: invokevirtual 238	com/tencent/luggage/wxa/oa/b:e	()I
    //   86: aload_0
    //   87: getfield 78	com/tencent/luggage/wxa/oa/b:g	Ljava/lang/String;
    //   90: aload_0
    //   91: getfield 59	com/tencent/luggage/wxa/oa/b:i	Ljava/lang/String;
    //   94: invokeinterface 241 14 0
    //   99: return
    //   100: ldc 223
    //   102: invokestatic 156	com/tencent/luggage/wxa/ba/e:b	(Ljava/lang/Class;)Lcom/tencent/luggage/wxa/ba/d;
    //   105: checkcast 223	com/tencent/luggage/wxa/nz/o
    //   108: aload_0
    //   109: getfield 74	com/tencent/luggage/wxa/oa/b:a	Lcom/tencent/luggage/wxa/jx/c;
    //   112: invokeinterface 229 1 0
    //   117: aload_0
    //   118: invokevirtual 231	com/tencent/luggage/wxa/oa/b:d	()Ljava/lang/String;
    //   121: ldc 233
    //   123: aload_0
    //   124: invokevirtual 235	com/tencent/luggage/wxa/oa/b:a	()Ljava/lang/String;
    //   127: lconst_0
    //   128: lconst_0
    //   129: iconst_0
    //   130: iconst_2
    //   131: aload_0
    //   132: invokevirtual 238	com/tencent/luggage/wxa/oa/b:e	()I
    //   135: aload_0
    //   136: getfield 80	com/tencent/luggage/wxa/oa/b:h	Ljava/lang/String;
    //   139: aload_0
    //   140: getfield 59	com/tencent/luggage/wxa/oa/b:i	Ljava/lang/String;
    //   143: invokeinterface 241 14 0
    //   148: return
    //   149: aload_0
    //   150: invokestatic 88	java/lang/System:currentTimeMillis	()J
    //   153: putfield 243	com/tencent/luggage/wxa/oa/b:o	J
    //   156: aload_0
    //   157: getfield 82	com/tencent/luggage/wxa/oa/b:c	Lcom/tencent/luggage/wxa/oa/a;
    //   160: aload_0
    //   161: getfield 78	com/tencent/luggage/wxa/oa/b:g	Ljava/lang/String;
    //   164: aload_0
    //   165: getfield 76	com/tencent/luggage/wxa/oa/b:f	Ljava/lang/String;
    //   168: invokeinterface 246 3 0
    //   173: ldc 151
    //   175: invokestatic 156	com/tencent/luggage/wxa/ba/e:b	(Ljava/lang/Class;)Lcom/tencent/luggage/wxa/ba/d;
    //   178: checkcast 151	com/tencent/luggage/wxa/ot/c
    //   181: ldc2_w 157
    //   184: lconst_0
    //   185: lconst_1
    //   186: iconst_0
    //   187: invokeinterface 161 8 0
    //   192: new 385	java/net/URL
    //   195: dup
    //   196: aload_0
    //   197: getfield 76	com/tencent/luggage/wxa/oa/b:f	Ljava/lang/String;
    //   200: invokespecial 388	java/net/URL:<init>	(Ljava/lang/String;)V
    //   203: astore 14
    //   205: ldc 163
    //   207: ldc_w 390
    //   210: iconst_3
    //   211: anewarray 4	java/lang/Object
    //   214: dup
    //   215: iconst_0
    //   216: aload_0
    //   217: getfield 250	com/tencent/luggage/wxa/oa/b:p	Ljava/lang/String;
    //   220: aastore
    //   221: dup
    //   222: iconst_1
    //   223: aload_0
    //   224: getfield 76	com/tencent/luggage/wxa/oa/b:f	Ljava/lang/String;
    //   227: aastore
    //   228: dup
    //   229: iconst_2
    //   230: aload_0
    //   231: getfield 78	com/tencent/luggage/wxa/oa/b:g	Ljava/lang/String;
    //   234: aastore
    //   235: invokestatic 184	com/tencent/luggage/wxa/qz/o:d	(Ljava/lang/String;Ljava/lang/String;[Ljava/lang/Object;)V
    //   238: aload_0
    //   239: aload 14
    //   241: invokevirtual 394	java/net/URL:openConnection	()Ljava/net/URLConnection;
    //   244: checkcast 396	java/net/HttpURLConnection
    //   247: putfield 398	com/tencent/luggage/wxa/oa/b:q	Ljava/net/HttpURLConnection;
    //   250: aload_0
    //   251: getfield 398	com/tencent/luggage/wxa/oa/b:q	Ljava/net/HttpURLConnection;
    //   254: instanceof 400
    //   257: istore 11
    //   259: iload 11
    //   261: ifeq +71 -> 332
    //   264: aload_0
    //   265: getfield 402	com/tencent/luggage/wxa/oa/b:l	Ljavax/net/ssl/SSLContext;
    //   268: ifnull +64 -> 332
    //   271: aload_0
    //   272: getfield 398	com/tencent/luggage/wxa/oa/b:q	Ljava/net/HttpURLConnection;
    //   275: checkcast 400	javax/net/ssl/HttpsURLConnection
    //   278: aload_0
    //   279: getfield 402	com/tencent/luggage/wxa/oa/b:l	Ljavax/net/ssl/SSLContext;
    //   282: invokevirtual 408	javax/net/ssl/SSLContext:getSocketFactory	()Ljavax/net/ssl/SSLSocketFactory;
    //   285: invokevirtual 412	javax/net/ssl/HttpsURLConnection:setSSLSocketFactory	(Ljavax/net/ssl/SSLSocketFactory;)V
    //   288: aload_0
    //   289: getfield 398	com/tencent/luggage/wxa/oa/b:q	Ljava/net/HttpURLConnection;
    //   292: aload_0
    //   293: getfield 414	com/tencent/luggage/wxa/oa/b:m	Ljava/util/ArrayList;
    //   296: invokestatic 417	com/tencent/luggage/wxa/nz/j:a	(Ljava/net/HttpURLConnection;Ljava/util/ArrayList;)V
    //   299: goto +33 -> 332
    //   302: astore 12
    //   304: goto +5880 -> 6184
    //   307: astore 20
    //   309: goto +5903 -> 6212
    //   312: astore 20
    //   314: goto +6845 -> 7159
    //   317: astore 20
    //   319: goto +7594 -> 7913
    //   322: astore 20
    //   324: goto +8343 -> 8667
    //   327: astore 20
    //   329: goto +9092 -> 9421
    //   332: aload_0
    //   333: getfield 398	com/tencent/luggage/wxa/oa/b:q	Ljava/net/HttpURLConnection;
    //   336: iconst_1
    //   337: invokevirtual 421	java/net/HttpURLConnection:setDoInput	(Z)V
    //   340: aload_0
    //   341: getfield 398	com/tencent/luggage/wxa/oa/b:q	Ljava/net/HttpURLConnection;
    //   344: aload_0
    //   345: getfield 62	com/tencent/luggage/wxa/oa/b:k	I
    //   348: invokevirtual 424	java/net/HttpURLConnection:setConnectTimeout	(I)V
    //   351: aload_0
    //   352: getfield 398	com/tencent/luggage/wxa/oa/b:q	Ljava/net/HttpURLConnection;
    //   355: aload_0
    //   356: getfield 62	com/tencent/luggage/wxa/oa/b:k	I
    //   359: invokevirtual 427	java/net/HttpURLConnection:setReadTimeout	(I)V
    //   362: aload_0
    //   363: getfield 398	com/tencent/luggage/wxa/oa/b:q	Ljava/net/HttpURLConnection;
    //   366: iconst_0
    //   367: invokevirtual 430	java/net/HttpURLConnection:setInstanceFollowRedirects	(Z)V
    //   370: aload_0
    //   371: getfield 398	com/tencent/luggage/wxa/oa/b:q	Ljava/net/HttpURLConnection;
    //   374: ldc_w 297
    //   377: ldc_w 432
    //   380: invokevirtual 435	java/net/HttpURLConnection:setRequestProperty	(Ljava/lang/String;Ljava/lang/String;)V
    //   383: aload_0
    //   384: getfield 295	com/tencent/luggage/wxa/oa/b:j	Ljava/util/Map;
    //   387: astore 12
    //   389: lload 5
    //   391: lstore 7
    //   393: aload 12
    //   395: ifnull +131 -> 526
    //   398: ldc 163
    //   400: ldc_w 437
    //   403: iconst_1
    //   404: anewarray 4	java/lang/Object
    //   407: dup
    //   408: iconst_0
    //   409: aload 14
    //   411: aastore
    //   412: invokestatic 184	com/tencent/luggage/wxa/qz/o:d	(Ljava/lang/String;Ljava/lang/String;[Ljava/lang/Object;)V
    //   415: aload_0
    //   416: getfield 295	com/tencent/luggage/wxa/oa/b:j	Ljava/util/Map;
    //   419: invokeinterface 441 1 0
    //   424: invokeinterface 447 1 0
    //   429: astore 12
    //   431: lload 5
    //   433: lstore 7
    //   435: aload 12
    //   437: invokeinterface 453 1 0
    //   442: ifeq +84 -> 526
    //   445: aload 12
    //   447: invokeinterface 457 1 0
    //   452: checkcast 459	java/util/Map$Entry
    //   455: astore 15
    //   457: aload_0
    //   458: getfield 398	com/tencent/luggage/wxa/oa/b:q	Ljava/net/HttpURLConnection;
    //   461: aload 15
    //   463: invokeinterface 462 1 0
    //   468: checkcast 115	java/lang/String
    //   471: aload 15
    //   473: invokeinterface 465 1 0
    //   478: checkcast 115	java/lang/String
    //   481: invokevirtual 435	java/net/HttpURLConnection:setRequestProperty	(Ljava/lang/String;Ljava/lang/String;)V
    //   484: ldc 163
    //   486: ldc_w 467
    //   489: iconst_3
    //   490: anewarray 4	java/lang/Object
    //   493: dup
    //   494: iconst_0
    //   495: aload_0
    //   496: getfield 78	com/tencent/luggage/wxa/oa/b:g	Ljava/lang/String;
    //   499: aastore
    //   500: dup
    //   501: iconst_1
    //   502: aload 15
    //   504: invokeinterface 462 1 0
    //   509: aastore
    //   510: dup
    //   511: iconst_2
    //   512: aload 15
    //   514: invokeinterface 465 1 0
    //   519: aastore
    //   520: invokestatic 184	com/tencent/luggage/wxa/qz/o:d	(Ljava/lang/String;Ljava/lang/String;[Ljava/lang/Object;)V
    //   523: goto -92 -> 431
    //   526: aload_0
    //   527: getfield 398	com/tencent/luggage/wxa/oa/b:q	Ljava/net/HttpURLConnection;
    //   530: ldc_w 317
    //   533: aload_0
    //   534: getfield 92	com/tencent/luggage/wxa/oa/b:u	Ljava/lang/String;
    //   537: invokevirtual 435	java/net/HttpURLConnection:setRequestProperty	(Ljava/lang/String;Ljava/lang/String;)V
    //   540: aload_0
    //   541: getfield 398	com/tencent/luggage/wxa/oa/b:q	Ljava/net/HttpURLConnection;
    //   544: invokestatic 470	com/tencent/luggage/wxa/nz/j:c	(Ljava/net/HttpURLConnection;)Lorg/json/JSONObject;
    //   547: astore 12
    //   549: aload_0
    //   550: getfield 82	com/tencent/luggage/wxa/oa/b:c	Lcom/tencent/luggage/wxa/oa/a;
    //   553: aload 12
    //   555: invokeinterface 332 2 0
    //   560: aload_0
    //   561: getfield 398	com/tencent/luggage/wxa/oa/b:q	Ljava/net/HttpURLConnection;
    //   564: invokevirtual 473	java/net/HttpURLConnection:getContentLength	()I
    //   567: i2l
    //   568: lstore 9
    //   570: aload_0
    //   571: aload_0
    //   572: aload_0
    //   573: getfield 398	com/tencent/luggage/wxa/oa/b:q	Ljava/net/HttpURLConnection;
    //   576: ldc_w 475
    //   579: invokevirtual 478	java/net/HttpURLConnection:getHeaderField	(Ljava/lang/String;)Ljava/lang/String;
    //   582: aload 14
    //   584: invokevirtual 481	java/net/URL:toString	()Ljava/lang/String;
    //   587: invokespecial 99	com/tencent/luggage/wxa/oa/b:a	(Ljava/lang/String;Ljava/lang/String;)Ljava/lang/String;
    //   590: putfield 59	com/tencent/luggage/wxa/oa/b:i	Ljava/lang/String;
    //   593: aload_0
    //   594: getfield 398	com/tencent/luggage/wxa/oa/b:q	Ljava/net/HttpURLConnection;
    //   597: invokevirtual 484	java/net/HttpURLConnection:getResponseCode	()I
    //   600: istore_1
    //   601: lload 9
    //   603: lconst_0
    //   604: lcmp
    //   605: ifle +201 -> 806
    //   608: ldc 151
    //   610: invokestatic 156	com/tencent/luggage/wxa/ba/e:b	(Ljava/lang/Class;)Lcom/tencent/luggage/wxa/ba/d;
    //   613: checkcast 151	com/tencent/luggage/wxa/ot/c
    //   616: ldc2_w 157
    //   619: ldc2_w 485
    //   622: lload 9
    //   624: iconst_0
    //   625: invokeinterface 161 8 0
    //   630: goto +176 -> 806
    //   633: astore 12
    //   635: ldc_w 381
    //   638: astore 14
    //   640: ldc_w 383
    //   643: astore 18
    //   645: iload_1
    //   646: istore_2
    //   647: aconst_null
    //   648: astore 13
    //   650: iconst_0
    //   651: istore_1
    //   652: aconst_null
    //   653: astore 15
    //   655: lconst_0
    //   656: lstore 5
    //   658: goto +9539 -> 10197
    //   661: astore 20
    //   663: ldc_w 381
    //   666: astore 17
    //   668: ldc_w 383
    //   671: astore 18
    //   673: aconst_null
    //   674: astore 16
    //   676: iconst_0
    //   677: istore_3
    //   678: aconst_null
    //   679: astore 19
    //   681: lconst_0
    //   682: lstore 7
    //   684: iload_1
    //   685: istore 4
    //   687: goto +5549 -> 6236
    //   690: astore 20
    //   692: ldc_w 381
    //   695: astore 17
    //   697: ldc_w 383
    //   700: astore 18
    //   702: aconst_null
    //   703: astore 16
    //   705: iconst_0
    //   706: istore_3
    //   707: aconst_null
    //   708: astore 19
    //   710: lconst_0
    //   711: lstore 7
    //   713: iload_1
    //   714: istore 4
    //   716: goto +6467 -> 7183
    //   719: astore 20
    //   721: ldc_w 381
    //   724: astore 17
    //   726: ldc_w 383
    //   729: astore 18
    //   731: aconst_null
    //   732: astore 16
    //   734: iconst_0
    //   735: istore_3
    //   736: aconst_null
    //   737: astore 19
    //   739: lconst_0
    //   740: lstore 7
    //   742: iload_1
    //   743: istore 4
    //   745: goto +7192 -> 7937
    //   748: astore 20
    //   750: ldc_w 381
    //   753: astore 17
    //   755: ldc_w 383
    //   758: astore 18
    //   760: aconst_null
    //   761: astore 16
    //   763: iconst_0
    //   764: istore_3
    //   765: aconst_null
    //   766: astore 19
    //   768: lconst_0
    //   769: lstore 7
    //   771: iload_1
    //   772: istore 4
    //   774: goto +7917 -> 8691
    //   777: astore 20
    //   779: ldc_w 381
    //   782: astore 17
    //   784: ldc_w 383
    //   787: astore 18
    //   789: aconst_null
    //   790: astore 16
    //   792: iconst_0
    //   793: istore_3
    //   794: aconst_null
    //   795: astore 19
    //   797: lconst_0
    //   798: lstore 7
    //   800: iload_1
    //   801: istore 4
    //   803: goto +8642 -> 9445
    //   806: aload_0
    //   807: getfield 398	com/tencent/luggage/wxa/oa/b:q	Ljava/net/HttpURLConnection;
    //   810: invokestatic 488	com/tencent/luggage/wxa/nz/j:b	(Ljava/net/HttpURLConnection;)Lorg/json/JSONObject;
    //   813: astore 12
    //   815: aload_0
    //   816: iload_1
    //   817: invokespecial 490	com/tencent/luggage/wxa/oa/b:c	(I)V
    //   820: aload_0
    //   821: getfield 82	com/tencent/luggage/wxa/oa/b:c	Lcom/tencent/luggage/wxa/oa/a;
    //   824: aload 12
    //   826: invokeinterface 332 2 0
    //   831: iload_1
    //   832: sipush 200
    //   835: if_icmpeq +634 -> 1469
    //   838: ldc 163
    //   840: ldc_w 492
    //   843: iconst_4
    //   844: anewarray 4	java/lang/Object
    //   847: dup
    //   848: iconst_0
    //   849: iload_1
    //   850: invokestatic 179	java/lang/Integer:valueOf	(I)Ljava/lang/Integer;
    //   853: aastore
    //   854: dup
    //   855: iconst_1
    //   856: aload_0
    //   857: getfield 250	com/tencent/luggage/wxa/oa/b:p	Ljava/lang/String;
    //   860: aastore
    //   861: dup
    //   862: iconst_2
    //   863: aload_0
    //   864: getfield 76	com/tencent/luggage/wxa/oa/b:f	Ljava/lang/String;
    //   867: aastore
    //   868: dup
    //   869: iconst_3
    //   870: aload_0
    //   871: getfield 78	com/tencent/luggage/wxa/oa/b:g	Ljava/lang/String;
    //   874: aastore
    //   875: invokestatic 494	com/tencent/luggage/wxa/qz/o:b	(Ljava/lang/String;Ljava/lang/String;[Ljava/lang/Object;)V
    //   878: iload_1
    //   879: invokestatic 497	com/tencent/luggage/wxa/nz/j:b	(I)Z
    //   882: ifeq +587 -> 1469
    //   885: aload_0
    //   886: getfield 398	com/tencent/luggage/wxa/oa/b:q	Ljava/net/HttpURLConnection;
    //   889: invokestatic 500	com/tencent/luggage/wxa/nz/j:a	(Ljava/net/HttpURLConnection;)Ljava/lang/String;
    //   892: astore 12
    //   894: aload 12
    //   896: invokestatic 505	android/text/TextUtils:isEmpty	(Ljava/lang/CharSequence;)Z
    //   899: ifne +570 -> 1469
    //   902: aload_0
    //   903: getfield 51	com/tencent/luggage/wxa/oa/b:b	I
    //   906: istore_2
    //   907: aload_0
    //   908: iload_2
    //   909: iconst_1
    //   910: isub
    //   911: putfield 51	com/tencent/luggage/wxa/oa/b:b	I
    //   914: iload_2
    //   915: ifgt +249 -> 1164
    //   918: ldc 163
    //   920: ldc_w 507
    //   923: iconst_1
    //   924: anewarray 4	java/lang/Object
    //   927: dup
    //   928: iconst_0
    //   929: bipush 15
    //   931: invokestatic 179	java/lang/Integer:valueOf	(I)Ljava/lang/Integer;
    //   934: aastore
    //   935: invokestatic 509	com/tencent/luggage/wxa/qz/o:c	(Ljava/lang/String;Ljava/lang/String;[Ljava/lang/Object;)V
    //   938: aload_0
    //   939: getfield 82	com/tencent/luggage/wxa/oa/b:c	Lcom/tencent/luggage/wxa/oa/a;
    //   942: aload_0
    //   943: getfield 78	com/tencent/luggage/wxa/oa/b:g	Ljava/lang/String;
    //   946: aload_0
    //   947: getfield 59	com/tencent/luggage/wxa/oa/b:i	Ljava/lang/String;
    //   950: aload_0
    //   951: getfield 76	com/tencent/luggage/wxa/oa/b:f	Ljava/lang/String;
    //   954: iload_1
    //   955: lconst_0
    //   956: aconst_null
    //   957: invokeinterface 512 8 0
    //   962: aload_0
    //   963: getfield 80	com/tencent/luggage/wxa/oa/b:h	Ljava/lang/String;
    //   966: invokestatic 124	com/tencent/luggage/wxa/qz/af:c	(Ljava/lang/String;)Z
    //   969: ifeq +54 -> 1023
    //   972: ldc 223
    //   974: invokestatic 156	com/tencent/luggage/wxa/ba/e:b	(Ljava/lang/Class;)Lcom/tencent/luggage/wxa/ba/d;
    //   977: checkcast 223	com/tencent/luggage/wxa/nz/o
    //   980: aload_0
    //   981: getfield 74	com/tencent/luggage/wxa/oa/b:a	Lcom/tencent/luggage/wxa/jx/c;
    //   984: invokeinterface 229 1 0
    //   989: aload_0
    //   990: invokevirtual 231	com/tencent/luggage/wxa/oa/b:d	()Ljava/lang/String;
    //   993: ldc 233
    //   995: aload_0
    //   996: invokevirtual 235	com/tencent/luggage/wxa/oa/b:a	()Ljava/lang/String;
    //   999: lconst_0
    //   1000: lconst_0
    //   1001: iload_1
    //   1002: iconst_1
    //   1003: aload_0
    //   1004: invokevirtual 238	com/tencent/luggage/wxa/oa/b:e	()I
    //   1007: aload_0
    //   1008: getfield 78	com/tencent/luggage/wxa/oa/b:g	Ljava/lang/String;
    //   1011: aload_0
    //   1012: getfield 59	com/tencent/luggage/wxa/oa/b:i	Ljava/lang/String;
    //   1015: invokeinterface 241 14 0
    //   1020: goto +51 -> 1071
    //   1023: ldc 223
    //   1025: invokestatic 156	com/tencent/luggage/wxa/ba/e:b	(Ljava/lang/Class;)Lcom/tencent/luggage/wxa/ba/d;
    //   1028: checkcast 223	com/tencent/luggage/wxa/nz/o
    //   1031: aload_0
    //   1032: getfield 74	com/tencent/luggage/wxa/oa/b:a	Lcom/tencent/luggage/wxa/jx/c;
    //   1035: invokeinterface 229 1 0
    //   1040: aload_0
    //   1041: invokevirtual 231	com/tencent/luggage/wxa/oa/b:d	()Ljava/lang/String;
    //   1044: ldc 233
    //   1046: aload_0
    //   1047: invokevirtual 235	com/tencent/luggage/wxa/oa/b:a	()Ljava/lang/String;
    //   1050: lconst_0
    //   1051: lconst_0
    //   1052: iload_1
    //   1053: iconst_1
    //   1054: aload_0
    //   1055: invokevirtual 238	com/tencent/luggage/wxa/oa/b:e	()I
    //   1058: aload_0
    //   1059: getfield 80	com/tencent/luggage/wxa/oa/b:h	Ljava/lang/String;
    //   1062: aload_0
    //   1063: getfield 59	com/tencent/luggage/wxa/oa/b:i	Ljava/lang/String;
    //   1066: invokeinterface 241 14 0
    //   1071: ldc 151
    //   1073: invokestatic 156	com/tencent/luggage/wxa/ba/e:b	(Ljava/lang/Class;)Lcom/tencent/luggage/wxa/ba/d;
    //   1076: checkcast 151	com/tencent/luggage/wxa/ot/c
    //   1079: ldc2_w 157
    //   1082: ldc2_w 513
    //   1085: lconst_1
    //   1086: iconst_0
    //   1087: invokeinterface 161 8 0
    //   1092: ldc 151
    //   1094: invokestatic 156	com/tencent/luggage/wxa/ba/e:b	(Ljava/lang/Class;)Lcom/tencent/luggage/wxa/ba/d;
    //   1097: checkcast 151	com/tencent/luggage/wxa/ot/c
    //   1100: ldc2_w 157
    //   1103: ldc2_w 515
    //   1106: invokestatic 88	java/lang/System:currentTimeMillis	()J
    //   1109: aload_0
    //   1110: getfield 243	com/tencent/luggage/wxa/oa/b:o	J
    //   1113: lsub
    //   1114: iconst_0
    //   1115: invokeinterface 161 8 0
    //   1120: aload_0
    //   1121: invokevirtual 518	com/tencent/luggage/wxa/oa/b:b	()V
    //   1124: aload_0
    //   1125: getfield 82	com/tencent/luggage/wxa/oa/b:c	Lcom/tencent/luggage/wxa/oa/a;
    //   1128: aload_0
    //   1129: invokevirtual 520	com/tencent/luggage/wxa/oa/b:c	()Ljava/lang/String;
    //   1132: invokeinterface 522 2 0
    //   1137: ldc 163
    //   1139: ldc_w 524
    //   1142: iconst_2
    //   1143: anewarray 4	java/lang/Object
    //   1146: dup
    //   1147: iconst_0
    //   1148: aload_0
    //   1149: getfield 250	com/tencent/luggage/wxa/oa/b:p	Ljava/lang/String;
    //   1152: aastore
    //   1153: dup
    //   1154: iconst_1
    //   1155: aload_0
    //   1156: getfield 76	com/tencent/luggage/wxa/oa/b:f	Ljava/lang/String;
    //   1159: aastore
    //   1160: invokestatic 184	com/tencent/luggage/wxa/qz/o:d	(Ljava/lang/String;Ljava/lang/String;[Ljava/lang/Object;)V
    //   1163: return
    //   1164: ldc 163
    //   1166: ldc_w 526
    //   1169: iconst_3
    //   1170: anewarray 4	java/lang/Object
    //   1173: dup
    //   1174: iconst_0
    //   1175: aload_0
    //   1176: getfield 51	com/tencent/luggage/wxa/oa/b:b	I
    //   1179: invokestatic 179	java/lang/Integer:valueOf	(I)Ljava/lang/Integer;
    //   1182: aastore
    //   1183: dup
    //   1184: iconst_1
    //   1185: aload_0
    //   1186: getfield 76	com/tencent/luggage/wxa/oa/b:f	Ljava/lang/String;
    //   1189: aastore
    //   1190: dup
    //   1191: iconst_2
    //   1192: aload 12
    //   1194: aastore
    //   1195: invokestatic 184	com/tencent/luggage/wxa/qz/o:d	(Ljava/lang/String;Ljava/lang/String;[Ljava/lang/Object;)V
    //   1198: aload_0
    //   1199: aload 12
    //   1201: putfield 76	com/tencent/luggage/wxa/oa/b:f	Ljava/lang/String;
    //   1204: aload_0
    //   1205: invokevirtual 529	com/tencent/luggage/wxa/oa/b:run	()V
    //   1208: aload_0
    //   1209: getfield 80	com/tencent/luggage/wxa/oa/b:h	Ljava/lang/String;
    //   1212: invokestatic 124	com/tencent/luggage/wxa/qz/af:c	(Ljava/lang/String;)Z
    //   1215: ifeq +54 -> 1269
    //   1218: ldc 223
    //   1220: invokestatic 156	com/tencent/luggage/wxa/ba/e:b	(Ljava/lang/Class;)Lcom/tencent/luggage/wxa/ba/d;
    //   1223: checkcast 223	com/tencent/luggage/wxa/nz/o
    //   1226: aload_0
    //   1227: getfield 74	com/tencent/luggage/wxa/oa/b:a	Lcom/tencent/luggage/wxa/jx/c;
    //   1230: invokeinterface 229 1 0
    //   1235: aload_0
    //   1236: invokevirtual 231	com/tencent/luggage/wxa/oa/b:d	()Ljava/lang/String;
    //   1239: ldc 233
    //   1241: aload_0
    //   1242: invokevirtual 235	com/tencent/luggage/wxa/oa/b:a	()Ljava/lang/String;
    //   1245: lconst_0
    //   1246: lconst_0
    //   1247: iload_1
    //   1248: iconst_2
    //   1249: aload_0
    //   1250: invokevirtual 238	com/tencent/luggage/wxa/oa/b:e	()I
    //   1253: aload_0
    //   1254: getfield 78	com/tencent/luggage/wxa/oa/b:g	Ljava/lang/String;
    //   1257: aload_0
    //   1258: getfield 59	com/tencent/luggage/wxa/oa/b:i	Ljava/lang/String;
    //   1261: invokeinterface 241 14 0
    //   1266: goto +51 -> 1317
    //   1269: ldc 223
    //   1271: invokestatic 156	com/tencent/luggage/wxa/ba/e:b	(Ljava/lang/Class;)Lcom/tencent/luggage/wxa/ba/d;
    //   1274: checkcast 223	com/tencent/luggage/wxa/nz/o
    //   1277: aload_0
    //   1278: getfield 74	com/tencent/luggage/wxa/oa/b:a	Lcom/tencent/luggage/wxa/jx/c;
    //   1281: invokeinterface 229 1 0
    //   1286: aload_0
    //   1287: invokevirtual 231	com/tencent/luggage/wxa/oa/b:d	()Ljava/lang/String;
    //   1290: ldc 233
    //   1292: aload_0
    //   1293: invokevirtual 235	com/tencent/luggage/wxa/oa/b:a	()Ljava/lang/String;
    //   1296: lconst_0
    //   1297: lconst_0
    //   1298: iload_1
    //   1299: iconst_2
    //   1300: aload_0
    //   1301: invokevirtual 238	com/tencent/luggage/wxa/oa/b:e	()I
    //   1304: aload_0
    //   1305: getfield 80	com/tencent/luggage/wxa/oa/b:h	Ljava/lang/String;
    //   1308: aload_0
    //   1309: getfield 59	com/tencent/luggage/wxa/oa/b:i	Ljava/lang/String;
    //   1312: invokeinterface 241 14 0
    //   1317: ldc 151
    //   1319: invokestatic 156	com/tencent/luggage/wxa/ba/e:b	(Ljava/lang/Class;)Lcom/tencent/luggage/wxa/ba/d;
    //   1322: checkcast 151	com/tencent/luggage/wxa/ot/c
    //   1325: ldc2_w 157
    //   1328: ldc2_w 530
    //   1331: lconst_1
    //   1332: iconst_0
    //   1333: invokeinterface 161 8 0
    //   1338: ldc 151
    //   1340: invokestatic 156	com/tencent/luggage/wxa/ba/e:b	(Ljava/lang/Class;)Lcom/tencent/luggage/wxa/ba/d;
    //   1343: checkcast 151	com/tencent/luggage/wxa/ot/c
    //   1346: ldc2_w 157
    //   1349: ldc2_w 532
    //   1352: invokestatic 88	java/lang/System:currentTimeMillis	()J
    //   1355: aload_0
    //   1356: getfield 243	com/tencent/luggage/wxa/oa/b:o	J
    //   1359: lsub
    //   1360: iconst_0
    //   1361: invokeinterface 161 8 0
    //   1366: invokestatic 138	com/tencent/luggage/wxa/qz/r:a	()Landroid/content/Context;
    //   1369: invokestatic 536	com/tencent/luggage/wxa/qz/x:d	(Landroid/content/Context;)I
    //   1372: istore_1
    //   1373: iload_1
    //   1374: iconst_m1
    //   1375: if_icmpne +24 -> 1399
    //   1378: ldc 151
    //   1380: invokestatic 156	com/tencent/luggage/wxa/ba/e:b	(Ljava/lang/Class;)Lcom/tencent/luggage/wxa/ba/d;
    //   1383: checkcast 151	com/tencent/luggage/wxa/ot/c
    //   1386: ldc2_w 157
    //   1389: ldc2_w 537
    //   1392: lconst_1
    //   1393: iconst_0
    //   1394: invokeinterface 161 8 0
    //   1399: ldc 163
    //   1401: ldc_w 540
    //   1404: iconst_2
    //   1405: anewarray 4	java/lang/Object
    //   1408: dup
    //   1409: iconst_0
    //   1410: aload_0
    //   1411: getfield 250	com/tencent/luggage/wxa/oa/b:p	Ljava/lang/String;
    //   1414: aastore
    //   1415: dup
    //   1416: iconst_1
    //   1417: iload_1
    //   1418: invokestatic 179	java/lang/Integer:valueOf	(I)Ljava/lang/Integer;
    //   1421: aastore
    //   1422: invokestatic 184	com/tencent/luggage/wxa/qz/o:d	(Ljava/lang/String;Ljava/lang/String;[Ljava/lang/Object;)V
    //   1425: aload_0
    //   1426: invokevirtual 518	com/tencent/luggage/wxa/oa/b:b	()V
    //   1429: aload_0
    //   1430: getfield 82	com/tencent/luggage/wxa/oa/b:c	Lcom/tencent/luggage/wxa/oa/a;
    //   1433: aload_0
    //   1434: invokevirtual 520	com/tencent/luggage/wxa/oa/b:c	()Ljava/lang/String;
    //   1437: invokeinterface 522 2 0
    //   1442: ldc 163
    //   1444: ldc_w 524
    //   1447: iconst_2
    //   1448: anewarray 4	java/lang/Object
    //   1451: dup
    //   1452: iconst_0
    //   1453: aload_0
    //   1454: getfield 250	com/tencent/luggage/wxa/oa/b:p	Ljava/lang/String;
    //   1457: aastore
    //   1458: dup
    //   1459: iconst_1
    //   1460: aload_0
    //   1461: getfield 76	com/tencent/luggage/wxa/oa/b:f	Ljava/lang/String;
    //   1464: aastore
    //   1465: invokestatic 184	com/tencent/luggage/wxa/qz/o:d	(Ljava/lang/String;Ljava/lang/String;[Ljava/lang/Object;)V
    //   1468: return
    //   1469: aload_0
    //   1470: getfield 398	com/tencent/luggage/wxa/oa/b:q	Ljava/net/HttpURLConnection;
    //   1473: invokevirtual 473	java/net/HttpURLConnection:getContentLength	()I
    //   1476: istore_2
    //   1477: iload_2
    //   1478: ifle +322 -> 1800
    //   1481: aload_0
    //   1482: getfield 542	com/tencent/luggage/wxa/oa/b:n	I
    //   1485: ifle +315 -> 1800
    //   1488: iload_2
    //   1489: aload_0
    //   1490: getfield 542	com/tencent/luggage/wxa/oa/b:n	I
    //   1493: ldc_w 543
    //   1496: imul
    //   1497: if_icmplt +303 -> 1800
    //   1500: ldc 163
    //   1502: ldc_w 545
    //   1505: iconst_1
    //   1506: anewarray 4	java/lang/Object
    //   1509: dup
    //   1510: iconst_0
    //   1511: iload_2
    //   1512: invokestatic 179	java/lang/Integer:valueOf	(I)Ljava/lang/Integer;
    //   1515: aastore
    //   1516: invokestatic 184	com/tencent/luggage/wxa/qz/o:d	(Ljava/lang/String;Ljava/lang/String;[Ljava/lang/Object;)V
    //   1519: aload_0
    //   1520: getfield 82	com/tencent/luggage/wxa/oa/b:c	Lcom/tencent/luggage/wxa/oa/a;
    //   1523: aload_0
    //   1524: getfield 78	com/tencent/luggage/wxa/oa/b:g	Ljava/lang/String;
    //   1527: aload_0
    //   1528: getfield 76	com/tencent/luggage/wxa/oa/b:f	Ljava/lang/String;
    //   1531: ldc_w 547
    //   1534: invokeinterface 221 4 0
    //   1539: aload_0
    //   1540: getfield 80	com/tencent/luggage/wxa/oa/b:h	Ljava/lang/String;
    //   1543: invokestatic 124	com/tencent/luggage/wxa/qz/af:c	(Ljava/lang/String;)Z
    //   1546: ifeq +54 -> 1600
    //   1549: ldc 223
    //   1551: invokestatic 156	com/tencent/luggage/wxa/ba/e:b	(Ljava/lang/Class;)Lcom/tencent/luggage/wxa/ba/d;
    //   1554: checkcast 223	com/tencent/luggage/wxa/nz/o
    //   1557: aload_0
    //   1558: getfield 74	com/tencent/luggage/wxa/oa/b:a	Lcom/tencent/luggage/wxa/jx/c;
    //   1561: invokeinterface 229 1 0
    //   1566: aload_0
    //   1567: invokevirtual 231	com/tencent/luggage/wxa/oa/b:d	()Ljava/lang/String;
    //   1570: ldc 233
    //   1572: aload_0
    //   1573: invokevirtual 235	com/tencent/luggage/wxa/oa/b:a	()Ljava/lang/String;
    //   1576: lconst_0
    //   1577: lconst_0
    //   1578: iload_1
    //   1579: iconst_2
    //   1580: aload_0
    //   1581: invokevirtual 238	com/tencent/luggage/wxa/oa/b:e	()I
    //   1584: aload_0
    //   1585: getfield 78	com/tencent/luggage/wxa/oa/b:g	Ljava/lang/String;
    //   1588: aload_0
    //   1589: getfield 59	com/tencent/luggage/wxa/oa/b:i	Ljava/lang/String;
    //   1592: invokeinterface 241 14 0
    //   1597: goto +51 -> 1648
    //   1600: ldc 223
    //   1602: invokestatic 156	com/tencent/luggage/wxa/ba/e:b	(Ljava/lang/Class;)Lcom/tencent/luggage/wxa/ba/d;
    //   1605: checkcast 223	com/tencent/luggage/wxa/nz/o
    //   1608: aload_0
    //   1609: getfield 74	com/tencent/luggage/wxa/oa/b:a	Lcom/tencent/luggage/wxa/jx/c;
    //   1612: invokeinterface 229 1 0
    //   1617: aload_0
    //   1618: invokevirtual 231	com/tencent/luggage/wxa/oa/b:d	()Ljava/lang/String;
    //   1621: ldc 233
    //   1623: aload_0
    //   1624: invokevirtual 235	com/tencent/luggage/wxa/oa/b:a	()Ljava/lang/String;
    //   1627: lconst_0
    //   1628: lconst_0
    //   1629: iload_1
    //   1630: iconst_2
    //   1631: aload_0
    //   1632: invokevirtual 238	com/tencent/luggage/wxa/oa/b:e	()I
    //   1635: aload_0
    //   1636: getfield 80	com/tencent/luggage/wxa/oa/b:h	Ljava/lang/String;
    //   1639: aload_0
    //   1640: getfield 59	com/tencent/luggage/wxa/oa/b:i	Ljava/lang/String;
    //   1643: invokeinterface 241 14 0
    //   1648: ldc 151
    //   1650: invokestatic 156	com/tencent/luggage/wxa/ba/e:b	(Ljava/lang/Class;)Lcom/tencent/luggage/wxa/ba/d;
    //   1653: checkcast 151	com/tencent/luggage/wxa/ot/c
    //   1656: ldc2_w 157
    //   1659: ldc2_w 530
    //   1662: lconst_1
    //   1663: iconst_0
    //   1664: invokeinterface 161 8 0
    //   1669: ldc 151
    //   1671: invokestatic 156	com/tencent/luggage/wxa/ba/e:b	(Ljava/lang/Class;)Lcom/tencent/luggage/wxa/ba/d;
    //   1674: checkcast 151	com/tencent/luggage/wxa/ot/c
    //   1677: ldc2_w 157
    //   1680: ldc2_w 532
    //   1683: invokestatic 88	java/lang/System:currentTimeMillis	()J
    //   1686: aload_0
    //   1687: getfield 243	com/tencent/luggage/wxa/oa/b:o	J
    //   1690: lsub
    //   1691: iconst_0
    //   1692: invokeinterface 161 8 0
    //   1697: invokestatic 138	com/tencent/luggage/wxa/qz/r:a	()Landroid/content/Context;
    //   1700: invokestatic 536	com/tencent/luggage/wxa/qz/x:d	(Landroid/content/Context;)I
    //   1703: istore_1
    //   1704: iload_1
    //   1705: iconst_m1
    //   1706: if_icmpne +24 -> 1730
    //   1709: ldc 151
    //   1711: invokestatic 156	com/tencent/luggage/wxa/ba/e:b	(Ljava/lang/Class;)Lcom/tencent/luggage/wxa/ba/d;
    //   1714: checkcast 151	com/tencent/luggage/wxa/ot/c
    //   1717: ldc2_w 157
    //   1720: ldc2_w 537
    //   1723: lconst_1
    //   1724: iconst_0
    //   1725: invokeinterface 161 8 0
    //   1730: ldc 163
    //   1732: ldc_w 540
    //   1735: iconst_2
    //   1736: anewarray 4	java/lang/Object
    //   1739: dup
    //   1740: iconst_0
    //   1741: aload_0
    //   1742: getfield 250	com/tencent/luggage/wxa/oa/b:p	Ljava/lang/String;
    //   1745: aastore
    //   1746: dup
    //   1747: iconst_1
    //   1748: iload_1
    //   1749: invokestatic 179	java/lang/Integer:valueOf	(I)Ljava/lang/Integer;
    //   1752: aastore
    //   1753: invokestatic 184	com/tencent/luggage/wxa/qz/o:d	(Ljava/lang/String;Ljava/lang/String;[Ljava/lang/Object;)V
    //   1756: aload_0
    //   1757: invokevirtual 518	com/tencent/luggage/wxa/oa/b:b	()V
    //   1760: aload_0
    //   1761: getfield 82	com/tencent/luggage/wxa/oa/b:c	Lcom/tencent/luggage/wxa/oa/a;
    //   1764: aload_0
    //   1765: invokevirtual 520	com/tencent/luggage/wxa/oa/b:c	()Ljava/lang/String;
    //   1768: invokeinterface 522 2 0
    //   1773: ldc 163
    //   1775: ldc_w 524
    //   1778: iconst_2
    //   1779: anewarray 4	java/lang/Object
    //   1782: dup
    //   1783: iconst_0
    //   1784: aload_0
    //   1785: getfield 250	com/tencent/luggage/wxa/oa/b:p	Ljava/lang/String;
    //   1788: aastore
    //   1789: dup
    //   1790: iconst_1
    //   1791: aload_0
    //   1792: getfield 76	com/tencent/luggage/wxa/oa/b:f	Ljava/lang/String;
    //   1795: aastore
    //   1796: invokestatic 184	com/tencent/luggage/wxa/qz/o:d	(Ljava/lang/String;Ljava/lang/String;[Ljava/lang/Object;)V
    //   1799: return
    //   1800: ldc_w 432
    //   1803: aload_0
    //   1804: getfield 398	com/tencent/luggage/wxa/oa/b:q	Ljava/net/HttpURLConnection;
    //   1807: invokevirtual 550	java/net/HttpURLConnection:getContentEncoding	()Ljava/lang/String;
    //   1810: invokevirtual 553	java/lang/String:equals	(Ljava/lang/Object;)Z
    //   1813: ifeq +22 -> 1835
    //   1816: new 555	java/util/zip/GZIPInputStream
    //   1819: dup
    //   1820: aload_0
    //   1821: getfield 398	com/tencent/luggage/wxa/oa/b:q	Ljava/net/HttpURLConnection;
    //   1824: invokevirtual 559	java/net/HttpURLConnection:getInputStream	()Ljava/io/InputStream;
    //   1827: invokespecial 562	java/util/zip/GZIPInputStream:<init>	(Ljava/io/InputStream;)V
    //   1830: astore 12
    //   1832: goto +59 -> 1891
    //   1835: ldc_w 564
    //   1838: aload_0
    //   1839: getfield 398	com/tencent/luggage/wxa/oa/b:q	Ljava/net/HttpURLConnection;
    //   1842: invokevirtual 550	java/net/HttpURLConnection:getContentEncoding	()Ljava/lang/String;
    //   1845: invokevirtual 553	java/lang/String:equals	(Ljava/lang/Object;)Z
    //   1848: ifeq +34 -> 1882
    //   1851: aload_0
    //   1852: getfield 398	com/tencent/luggage/wxa/oa/b:q	Ljava/net/HttpURLConnection;
    //   1855: invokevirtual 559	java/net/HttpURLConnection:getInputStream	()Ljava/io/InputStream;
    //   1858: astore 12
    //   1860: new 566	java/util/zip/InflaterInputStream
    //   1863: dup
    //   1864: aload 12
    //   1866: new 568	java/util/zip/Inflater
    //   1869: dup
    //   1870: iconst_1
    //   1871: invokespecial 570	java/util/zip/Inflater:<init>	(Z)V
    //   1874: invokespecial 573	java/util/zip/InflaterInputStream:<init>	(Ljava/io/InputStream;Ljava/util/zip/Inflater;)V
    //   1877: astore 12
    //   1879: goto +12 -> 1891
    //   1882: aload_0
    //   1883: getfield 398	com/tencent/luggage/wxa/oa/b:q	Ljava/net/HttpURLConnection;
    //   1886: invokevirtual 559	java/net/HttpURLConnection:getInputStream	()Ljava/io/InputStream;
    //   1889: astore 12
    //   1891: aload 12
    //   1893: astore 14
    //   1895: goto +88 -> 1983
    //   1898: astore 12
    //   1900: goto +5 -> 1905
    //   1903: astore 12
    //   1905: ldc 163
    //   1907: aload 12
    //   1909: ldc_w 575
    //   1912: iconst_0
    //   1913: anewarray 4	java/lang/Object
    //   1916: invokestatic 578	com/tencent/luggage/wxa/qz/o:a	(Ljava/lang/String;Ljava/lang/Throwable;Ljava/lang/String;[Ljava/lang/Object;)V
    //   1919: ldc_w 432
    //   1922: aload_0
    //   1923: getfield 398	com/tencent/luggage/wxa/oa/b:q	Ljava/net/HttpURLConnection;
    //   1926: invokevirtual 550	java/net/HttpURLConnection:getContentEncoding	()Ljava/lang/String;
    //   1929: invokevirtual 553	java/lang/String:equals	(Ljava/lang/Object;)Z
    //   1932: ifeq +22 -> 1954
    //   1935: new 555	java/util/zip/GZIPInputStream
    //   1938: dup
    //   1939: aload_0
    //   1940: getfield 398	com/tencent/luggage/wxa/oa/b:q	Ljava/net/HttpURLConnection;
    //   1943: invokevirtual 581	java/net/HttpURLConnection:getErrorStream	()Ljava/io/InputStream;
    //   1946: invokespecial 562	java/util/zip/GZIPInputStream:<init>	(Ljava/io/InputStream;)V
    //   1949: astore 14
    //   1951: goto +32 -> 1983
    //   1954: aload_0
    //   1955: getfield 398	com/tencent/luggage/wxa/oa/b:q	Ljava/net/HttpURLConnection;
    //   1958: invokevirtual 581	java/net/HttpURLConnection:getErrorStream	()Ljava/io/InputStream;
    //   1961: astore 14
    //   1963: goto +20 -> 1983
    //   1966: ldc 163
    //   1968: aload 12
    //   1970: ldc_w 583
    //   1973: iconst_0
    //   1974: anewarray 4	java/lang/Object
    //   1977: invokestatic 578	com/tencent/luggage/wxa/qz/o:a	(Ljava/lang/String;Ljava/lang/Throwable;Ljava/lang/String;[Ljava/lang/Object;)V
    //   1980: aconst_null
    //   1981: astore 14
    //   1983: new 585	com/tencent/luggage/wxa/rt/i
    //   1986: dup
    //   1987: aload_0
    //   1988: getfield 78	com/tencent/luggage/wxa/oa/b:g	Ljava/lang/String;
    //   1991: invokespecial 586	com/tencent/luggage/wxa/rt/i:<init>	(Ljava/lang/String;)V
    //   1994: astore 18
    //   1996: aload 18
    //   1998: invokevirtual 588	com/tencent/luggage/wxa/rt/i:j	()Z
    //   2001: istore 11
    //   2003: iload 11
    //   2005: ifeq +584 -> 2589
    //   2008: ldc 163
    //   2010: ldc_w 590
    //   2013: iconst_2
    //   2014: anewarray 4	java/lang/Object
    //   2017: dup
    //   2018: iconst_0
    //   2019: aload_0
    //   2020: getfield 250	com/tencent/luggage/wxa/oa/b:p	Ljava/lang/String;
    //   2023: aastore
    //   2024: dup
    //   2025: iconst_1
    //   2026: aload_0
    //   2027: getfield 78	com/tencent/luggage/wxa/oa/b:g	Ljava/lang/String;
    //   2030: aastore
    //   2031: invokestatic 184	com/tencent/luggage/wxa/qz/o:d	(Ljava/lang/String;Ljava/lang/String;[Ljava/lang/Object;)V
    //   2034: aload 18
    //   2036: invokevirtual 592	com/tencent/luggage/wxa/rt/i:w	()Z
    //   2039: ifne +550 -> 2589
    //   2042: ldc 163
    //   2044: ldc_w 594
    //   2047: iconst_1
    //   2048: anewarray 4	java/lang/Object
    //   2051: dup
    //   2052: iconst_0
    //   2053: aload_0
    //   2054: getfield 78	com/tencent/luggage/wxa/oa/b:g	Ljava/lang/String;
    //   2057: aastore
    //   2058: invokestatic 494	com/tencent/luggage/wxa/qz/o:b	(Ljava/lang/String;Ljava/lang/String;[Ljava/lang/Object;)V
    //   2061: aload_0
    //   2062: getfield 82	com/tencent/luggage/wxa/oa/b:c	Lcom/tencent/luggage/wxa/oa/a;
    //   2065: aload_0
    //   2066: getfield 78	com/tencent/luggage/wxa/oa/b:g	Ljava/lang/String;
    //   2069: aload_0
    //   2070: getfield 76	com/tencent/luggage/wxa/oa/b:f	Ljava/lang/String;
    //   2073: ldc_w 596
    //   2076: invokeinterface 221 4 0
    //   2081: aload_0
    //   2082: getfield 80	com/tencent/luggage/wxa/oa/b:h	Ljava/lang/String;
    //   2085: invokestatic 124	com/tencent/luggage/wxa/qz/af:c	(Ljava/lang/String;)Z
    //   2088: ifeq +54 -> 2142
    //   2091: ldc 223
    //   2093: invokestatic 156	com/tencent/luggage/wxa/ba/e:b	(Ljava/lang/Class;)Lcom/tencent/luggage/wxa/ba/d;
    //   2096: checkcast 223	com/tencent/luggage/wxa/nz/o
    //   2099: aload_0
    //   2100: getfield 74	com/tencent/luggage/wxa/oa/b:a	Lcom/tencent/luggage/wxa/jx/c;
    //   2103: invokeinterface 229 1 0
    //   2108: aload_0
    //   2109: invokevirtual 231	com/tencent/luggage/wxa/oa/b:d	()Ljava/lang/String;
    //   2112: ldc 233
    //   2114: aload_0
    //   2115: invokevirtual 235	com/tencent/luggage/wxa/oa/b:a	()Ljava/lang/String;
    //   2118: lconst_0
    //   2119: lconst_0
    //   2120: iload_1
    //   2121: iconst_2
    //   2122: aload_0
    //   2123: invokevirtual 238	com/tencent/luggage/wxa/oa/b:e	()I
    //   2126: aload_0
    //   2127: getfield 78	com/tencent/luggage/wxa/oa/b:g	Ljava/lang/String;
    //   2130: aload_0
    //   2131: getfield 59	com/tencent/luggage/wxa/oa/b:i	Ljava/lang/String;
    //   2134: invokeinterface 241 14 0
    //   2139: goto +51 -> 2190
    //   2142: ldc 223
    //   2144: invokestatic 156	com/tencent/luggage/wxa/ba/e:b	(Ljava/lang/Class;)Lcom/tencent/luggage/wxa/ba/d;
    //   2147: checkcast 223	com/tencent/luggage/wxa/nz/o
    //   2150: aload_0
    //   2151: getfield 74	com/tencent/luggage/wxa/oa/b:a	Lcom/tencent/luggage/wxa/jx/c;
    //   2154: invokeinterface 229 1 0
    //   2159: aload_0
    //   2160: invokevirtual 231	com/tencent/luggage/wxa/oa/b:d	()Ljava/lang/String;
    //   2163: ldc 233
    //   2165: aload_0
    //   2166: invokevirtual 235	com/tencent/luggage/wxa/oa/b:a	()Ljava/lang/String;
    //   2169: lconst_0
    //   2170: lconst_0
    //   2171: iload_1
    //   2172: iconst_2
    //   2173: aload_0
    //   2174: invokevirtual 238	com/tencent/luggage/wxa/oa/b:e	()I
    //   2177: aload_0
    //   2178: getfield 80	com/tencent/luggage/wxa/oa/b:h	Ljava/lang/String;
    //   2181: aload_0
    //   2182: getfield 59	com/tencent/luggage/wxa/oa/b:i	Ljava/lang/String;
    //   2185: invokeinterface 241 14 0
    //   2190: ldc 151
    //   2192: invokestatic 156	com/tencent/luggage/wxa/ba/e:b	(Ljava/lang/Class;)Lcom/tencent/luggage/wxa/ba/d;
    //   2195: checkcast 151	com/tencent/luggage/wxa/ot/c
    //   2198: ldc2_w 157
    //   2201: ldc2_w 530
    //   2204: lconst_1
    //   2205: iconst_0
    //   2206: invokeinterface 161 8 0
    //   2211: ldc 151
    //   2213: invokestatic 156	com/tencent/luggage/wxa/ba/e:b	(Ljava/lang/Class;)Lcom/tencent/luggage/wxa/ba/d;
    //   2216: checkcast 151	com/tencent/luggage/wxa/ot/c
    //   2219: ldc2_w 157
    //   2222: ldc2_w 532
    //   2225: invokestatic 88	java/lang/System:currentTimeMillis	()J
    //   2228: aload_0
    //   2229: getfield 243	com/tencent/luggage/wxa/oa/b:o	J
    //   2232: lsub
    //   2233: iconst_0
    //   2234: invokeinterface 161 8 0
    //   2239: invokestatic 138	com/tencent/luggage/wxa/qz/r:a	()Landroid/content/Context;
    //   2242: invokestatic 536	com/tencent/luggage/wxa/qz/x:d	(Landroid/content/Context;)I
    //   2245: istore_1
    //   2246: iload_1
    //   2247: iconst_m1
    //   2248: if_icmpne +24 -> 2272
    //   2251: ldc 151
    //   2253: invokestatic 156	com/tencent/luggage/wxa/ba/e:b	(Ljava/lang/Class;)Lcom/tencent/luggage/wxa/ba/d;
    //   2256: checkcast 151	com/tencent/luggage/wxa/ot/c
    //   2259: ldc2_w 157
    //   2262: ldc2_w 537
    //   2265: lconst_1
    //   2266: iconst_0
    //   2267: invokeinterface 161 8 0
    //   2272: ldc 163
    //   2274: ldc_w 540
    //   2277: iconst_2
    //   2278: anewarray 4	java/lang/Object
    //   2281: dup
    //   2282: iconst_0
    //   2283: aload_0
    //   2284: getfield 250	com/tencent/luggage/wxa/oa/b:p	Ljava/lang/String;
    //   2287: aastore
    //   2288: dup
    //   2289: iconst_1
    //   2290: iload_1
    //   2291: invokestatic 179	java/lang/Integer:valueOf	(I)Ljava/lang/Integer;
    //   2294: aastore
    //   2295: invokestatic 184	com/tencent/luggage/wxa/qz/o:d	(Ljava/lang/String;Ljava/lang/String;[Ljava/lang/Object;)V
    //   2298: aload 14
    //   2300: ifnull +107 -> 2407
    //   2303: aload 14
    //   2305: invokevirtual 601	java/io/InputStream:close	()V
    //   2308: goto +99 -> 2407
    //   2311: astore 12
    //   2313: ldc 163
    //   2315: aload 12
    //   2317: ldc_w 381
    //   2320: iconst_2
    //   2321: anewarray 4	java/lang/Object
    //   2324: dup
    //   2325: iconst_0
    //   2326: aload_0
    //   2327: getfield 76	com/tencent/luggage/wxa/oa/b:f	Ljava/lang/String;
    //   2330: aastore
    //   2331: dup
    //   2332: iconst_1
    //   2333: aload_0
    //   2334: getfield 78	com/tencent/luggage/wxa/oa/b:g	Ljava/lang/String;
    //   2337: aastore
    //   2338: invokestatic 578	com/tencent/luggage/wxa/qz/o:a	(Ljava/lang/String;Ljava/lang/Throwable;Ljava/lang/String;[Ljava/lang/Object;)V
    //   2341: goto +66 -> 2407
    //   2344: astore 12
    //   2346: ldc 163
    //   2348: aload 12
    //   2350: ldc_w 383
    //   2353: iconst_2
    //   2354: anewarray 4	java/lang/Object
    //   2357: dup
    //   2358: iconst_0
    //   2359: aload_0
    //   2360: getfield 76	com/tencent/luggage/wxa/oa/b:f	Ljava/lang/String;
    //   2363: aastore
    //   2364: dup
    //   2365: iconst_1
    //   2366: aload_0
    //   2367: getfield 78	com/tencent/luggage/wxa/oa/b:g	Ljava/lang/String;
    //   2370: aastore
    //   2371: invokestatic 578	com/tencent/luggage/wxa/qz/o:a	(Ljava/lang/String;Ljava/lang/Throwable;Ljava/lang/String;[Ljava/lang/Object;)V
    //   2374: goto +33 -> 2407
    //   2377: astore 12
    //   2379: ldc 163
    //   2381: aload 12
    //   2383: ldc_w 603
    //   2386: iconst_2
    //   2387: anewarray 4	java/lang/Object
    //   2390: dup
    //   2391: iconst_0
    //   2392: aload_0
    //   2393: getfield 76	com/tencent/luggage/wxa/oa/b:f	Ljava/lang/String;
    //   2396: aastore
    //   2397: dup
    //   2398: iconst_1
    //   2399: aload_0
    //   2400: getfield 78	com/tencent/luggage/wxa/oa/b:g	Ljava/lang/String;
    //   2403: aastore
    //   2404: invokestatic 578	com/tencent/luggage/wxa/qz/o:a	(Ljava/lang/String;Ljava/lang/Throwable;Ljava/lang/String;[Ljava/lang/Object;)V
    //   2407: aload_0
    //   2408: invokevirtual 518	com/tencent/luggage/wxa/oa/b:b	()V
    //   2411: aload_0
    //   2412: getfield 82	com/tencent/luggage/wxa/oa/b:c	Lcom/tencent/luggage/wxa/oa/a;
    //   2415: aload_0
    //   2416: invokevirtual 520	com/tencent/luggage/wxa/oa/b:c	()Ljava/lang/String;
    //   2419: invokeinterface 522 2 0
    //   2424: ldc 163
    //   2426: ldc_w 524
    //   2429: iconst_2
    //   2430: anewarray 4	java/lang/Object
    //   2433: dup
    //   2434: iconst_0
    //   2435: aload_0
    //   2436: getfield 250	com/tencent/luggage/wxa/oa/b:p	Ljava/lang/String;
    //   2439: aastore
    //   2440: dup
    //   2441: iconst_1
    //   2442: aload_0
    //   2443: getfield 76	com/tencent/luggage/wxa/oa/b:f	Ljava/lang/String;
    //   2446: aastore
    //   2447: invokestatic 184	com/tencent/luggage/wxa/qz/o:d	(Ljava/lang/String;Ljava/lang/String;[Ljava/lang/Object;)V
    //   2450: return
    //   2451: astore 17
    //   2453: ldc_w 381
    //   2456: astore 16
    //   2458: ldc_w 383
    //   2461: astore 18
    //   2463: aconst_null
    //   2464: astore 15
    //   2466: lconst_0
    //   2467: lstore 5
    //   2469: iconst_0
    //   2470: istore_2
    //   2471: goto +3307 -> 5778
    //   2474: astore 15
    //   2476: ldc_w 381
    //   2479: astore 13
    //   2481: ldc_w 383
    //   2484: astore 12
    //   2486: aconst_null
    //   2487: astore 16
    //   2489: iconst_0
    //   2490: istore_3
    //   2491: lconst_0
    //   2492: lstore 7
    //   2494: goto +3325 -> 5819
    //   2497: astore 15
    //   2499: ldc_w 381
    //   2502: astore 13
    //   2504: ldc_w 383
    //   2507: astore 12
    //   2509: aconst_null
    //   2510: astore 16
    //   2512: iconst_0
    //   2513: istore_3
    //   2514: lconst_0
    //   2515: lstore 7
    //   2517: goto +3344 -> 5861
    //   2520: astore 15
    //   2522: ldc_w 381
    //   2525: astore 13
    //   2527: ldc_w 383
    //   2530: astore 12
    //   2532: aconst_null
    //   2533: astore 16
    //   2535: iconst_0
    //   2536: istore_3
    //   2537: lconst_0
    //   2538: lstore 7
    //   2540: goto +3363 -> 5903
    //   2543: astore 15
    //   2545: ldc_w 381
    //   2548: astore 13
    //   2550: ldc_w 383
    //   2553: astore 12
    //   2555: aconst_null
    //   2556: astore 16
    //   2558: iconst_0
    //   2559: istore_3
    //   2560: lconst_0
    //   2561: lstore 7
    //   2563: goto +3382 -> 5945
    //   2566: astore 15
    //   2568: ldc_w 381
    //   2571: astore 13
    //   2573: ldc_w 383
    //   2576: astore 12
    //   2578: aconst_null
    //   2579: astore 16
    //   2581: iconst_0
    //   2582: istore_3
    //   2583: lconst_0
    //   2584: lstore 7
    //   2586: goto +3401 -> 5987
    //   2589: aload 18
    //   2591: invokevirtual 606	com/tencent/luggage/wxa/rt/i:g	()Lcom/tencent/luggage/wxa/rt/i;
    //   2594: invokevirtual 588	com/tencent/luggage/wxa/rt/i:j	()Z
    //   2597: istore 11
    //   2599: iload 11
    //   2601: ifne +449 -> 3050
    //   2604: ldc 163
    //   2606: ldc_w 608
    //   2609: iconst_2
    //   2610: anewarray 4	java/lang/Object
    //   2613: dup
    //   2614: iconst_0
    //   2615: aload_0
    //   2616: getfield 250	com/tencent/luggage/wxa/oa/b:p	Ljava/lang/String;
    //   2619: aastore
    //   2620: dup
    //   2621: iconst_1
    //   2622: aload_0
    //   2623: getfield 78	com/tencent/luggage/wxa/oa/b:g	Ljava/lang/String;
    //   2626: aastore
    //   2627: invokestatic 184	com/tencent/luggage/wxa/qz/o:d	(Ljava/lang/String;Ljava/lang/String;[Ljava/lang/Object;)V
    //   2630: aload 18
    //   2632: invokevirtual 606	com/tencent/luggage/wxa/rt/i:g	()Lcom/tencent/luggage/wxa/rt/i;
    //   2635: invokevirtual 610	com/tencent/luggage/wxa/rt/i:u	()Z
    //   2638: ifne +412 -> 3050
    //   2641: ldc 163
    //   2643: ldc_w 612
    //   2646: iconst_1
    //   2647: anewarray 4	java/lang/Object
    //   2650: dup
    //   2651: iconst_0
    //   2652: aload_0
    //   2653: getfield 78	com/tencent/luggage/wxa/oa/b:g	Ljava/lang/String;
    //   2656: aastore
    //   2657: invokestatic 494	com/tencent/luggage/wxa/qz/o:b	(Ljava/lang/String;Ljava/lang/String;[Ljava/lang/Object;)V
    //   2660: aload_0
    //   2661: getfield 82	com/tencent/luggage/wxa/oa/b:c	Lcom/tencent/luggage/wxa/oa/a;
    //   2664: aload_0
    //   2665: getfield 78	com/tencent/luggage/wxa/oa/b:g	Ljava/lang/String;
    //   2668: aload_0
    //   2669: getfield 76	com/tencent/luggage/wxa/oa/b:f	Ljava/lang/String;
    //   2672: ldc_w 614
    //   2675: invokeinterface 221 4 0
    //   2680: aload_0
    //   2681: getfield 80	com/tencent/luggage/wxa/oa/b:h	Ljava/lang/String;
    //   2684: invokestatic 124	com/tencent/luggage/wxa/qz/af:c	(Ljava/lang/String;)Z
    //   2687: ifeq +54 -> 2741
    //   2690: ldc 223
    //   2692: invokestatic 156	com/tencent/luggage/wxa/ba/e:b	(Ljava/lang/Class;)Lcom/tencent/luggage/wxa/ba/d;
    //   2695: checkcast 223	com/tencent/luggage/wxa/nz/o
    //   2698: aload_0
    //   2699: getfield 74	com/tencent/luggage/wxa/oa/b:a	Lcom/tencent/luggage/wxa/jx/c;
    //   2702: invokeinterface 229 1 0
    //   2707: aload_0
    //   2708: invokevirtual 231	com/tencent/luggage/wxa/oa/b:d	()Ljava/lang/String;
    //   2711: ldc 233
    //   2713: aload_0
    //   2714: invokevirtual 235	com/tencent/luggage/wxa/oa/b:a	()Ljava/lang/String;
    //   2717: lconst_0
    //   2718: lconst_0
    //   2719: iload_1
    //   2720: iconst_2
    //   2721: aload_0
    //   2722: invokevirtual 238	com/tencent/luggage/wxa/oa/b:e	()I
    //   2725: aload_0
    //   2726: getfield 78	com/tencent/luggage/wxa/oa/b:g	Ljava/lang/String;
    //   2729: aload_0
    //   2730: getfield 59	com/tencent/luggage/wxa/oa/b:i	Ljava/lang/String;
    //   2733: invokeinterface 241 14 0
    //   2738: goto +51 -> 2789
    //   2741: ldc 223
    //   2743: invokestatic 156	com/tencent/luggage/wxa/ba/e:b	(Ljava/lang/Class;)Lcom/tencent/luggage/wxa/ba/d;
    //   2746: checkcast 223	com/tencent/luggage/wxa/nz/o
    //   2749: aload_0
    //   2750: getfield 74	com/tencent/luggage/wxa/oa/b:a	Lcom/tencent/luggage/wxa/jx/c;
    //   2753: invokeinterface 229 1 0
    //   2758: aload_0
    //   2759: invokevirtual 231	com/tencent/luggage/wxa/oa/b:d	()Ljava/lang/String;
    //   2762: ldc 233
    //   2764: aload_0
    //   2765: invokevirtual 235	com/tencent/luggage/wxa/oa/b:a	()Ljava/lang/String;
    //   2768: lconst_0
    //   2769: lconst_0
    //   2770: iload_1
    //   2771: iconst_2
    //   2772: aload_0
    //   2773: invokevirtual 238	com/tencent/luggage/wxa/oa/b:e	()I
    //   2776: aload_0
    //   2777: getfield 80	com/tencent/luggage/wxa/oa/b:h	Ljava/lang/String;
    //   2780: aload_0
    //   2781: getfield 59	com/tencent/luggage/wxa/oa/b:i	Ljava/lang/String;
    //   2784: invokeinterface 241 14 0
    //   2789: ldc 151
    //   2791: invokestatic 156	com/tencent/luggage/wxa/ba/e:b	(Ljava/lang/Class;)Lcom/tencent/luggage/wxa/ba/d;
    //   2794: checkcast 151	com/tencent/luggage/wxa/ot/c
    //   2797: ldc2_w 157
    //   2800: ldc2_w 530
    //   2803: lconst_1
    //   2804: iconst_0
    //   2805: invokeinterface 161 8 0
    //   2810: ldc 151
    //   2812: invokestatic 156	com/tencent/luggage/wxa/ba/e:b	(Ljava/lang/Class;)Lcom/tencent/luggage/wxa/ba/d;
    //   2815: checkcast 151	com/tencent/luggage/wxa/ot/c
    //   2818: ldc2_w 157
    //   2821: ldc2_w 532
    //   2824: invokestatic 88	java/lang/System:currentTimeMillis	()J
    //   2827: aload_0
    //   2828: getfield 243	com/tencent/luggage/wxa/oa/b:o	J
    //   2831: lsub
    //   2832: iconst_0
    //   2833: invokeinterface 161 8 0
    //   2838: invokestatic 138	com/tencent/luggage/wxa/qz/r:a	()Landroid/content/Context;
    //   2841: invokestatic 536	com/tencent/luggage/wxa/qz/x:d	(Landroid/content/Context;)I
    //   2844: istore_1
    //   2845: iload_1
    //   2846: iconst_m1
    //   2847: if_icmpne +24 -> 2871
    //   2850: ldc 151
    //   2852: invokestatic 156	com/tencent/luggage/wxa/ba/e:b	(Ljava/lang/Class;)Lcom/tencent/luggage/wxa/ba/d;
    //   2855: checkcast 151	com/tencent/luggage/wxa/ot/c
    //   2858: ldc2_w 157
    //   2861: ldc2_w 537
    //   2864: lconst_1
    //   2865: iconst_0
    //   2866: invokeinterface 161 8 0
    //   2871: ldc 163
    //   2873: ldc_w 540
    //   2876: iconst_2
    //   2877: anewarray 4	java/lang/Object
    //   2880: dup
    //   2881: iconst_0
    //   2882: aload_0
    //   2883: getfield 250	com/tencent/luggage/wxa/oa/b:p	Ljava/lang/String;
    //   2886: aastore
    //   2887: dup
    //   2888: iconst_1
    //   2889: iload_1
    //   2890: invokestatic 179	java/lang/Integer:valueOf	(I)Ljava/lang/Integer;
    //   2893: aastore
    //   2894: invokestatic 184	com/tencent/luggage/wxa/qz/o:d	(Ljava/lang/String;Ljava/lang/String;[Ljava/lang/Object;)V
    //   2897: aload 14
    //   2899: ifnull +107 -> 3006
    //   2902: aload 14
    //   2904: invokevirtual 601	java/io/InputStream:close	()V
    //   2907: goto +99 -> 3006
    //   2910: astore 12
    //   2912: ldc 163
    //   2914: aload 12
    //   2916: ldc_w 381
    //   2919: iconst_2
    //   2920: anewarray 4	java/lang/Object
    //   2923: dup
    //   2924: iconst_0
    //   2925: aload_0
    //   2926: getfield 76	com/tencent/luggage/wxa/oa/b:f	Ljava/lang/String;
    //   2929: aastore
    //   2930: dup
    //   2931: iconst_1
    //   2932: aload_0
    //   2933: getfield 78	com/tencent/luggage/wxa/oa/b:g	Ljava/lang/String;
    //   2936: aastore
    //   2937: invokestatic 578	com/tencent/luggage/wxa/qz/o:a	(Ljava/lang/String;Ljava/lang/Throwable;Ljava/lang/String;[Ljava/lang/Object;)V
    //   2940: goto +66 -> 3006
    //   2943: astore 12
    //   2945: ldc 163
    //   2947: aload 12
    //   2949: ldc_w 383
    //   2952: iconst_2
    //   2953: anewarray 4	java/lang/Object
    //   2956: dup
    //   2957: iconst_0
    //   2958: aload_0
    //   2959: getfield 76	com/tencent/luggage/wxa/oa/b:f	Ljava/lang/String;
    //   2962: aastore
    //   2963: dup
    //   2964: iconst_1
    //   2965: aload_0
    //   2966: getfield 78	com/tencent/luggage/wxa/oa/b:g	Ljava/lang/String;
    //   2969: aastore
    //   2970: invokestatic 578	com/tencent/luggage/wxa/qz/o:a	(Ljava/lang/String;Ljava/lang/Throwable;Ljava/lang/String;[Ljava/lang/Object;)V
    //   2973: goto +33 -> 3006
    //   2976: astore 12
    //   2978: ldc 163
    //   2980: aload 12
    //   2982: ldc_w 603
    //   2985: iconst_2
    //   2986: anewarray 4	java/lang/Object
    //   2989: dup
    //   2990: iconst_0
    //   2991: aload_0
    //   2992: getfield 76	com/tencent/luggage/wxa/oa/b:f	Ljava/lang/String;
    //   2995: aastore
    //   2996: dup
    //   2997: iconst_1
    //   2998: aload_0
    //   2999: getfield 78	com/tencent/luggage/wxa/oa/b:g	Ljava/lang/String;
    //   3002: aastore
    //   3003: invokestatic 578	com/tencent/luggage/wxa/qz/o:a	(Ljava/lang/String;Ljava/lang/Throwable;Ljava/lang/String;[Ljava/lang/Object;)V
    //   3006: aload_0
    //   3007: invokevirtual 518	com/tencent/luggage/wxa/oa/b:b	()V
    //   3010: aload_0
    //   3011: getfield 82	com/tencent/luggage/wxa/oa/b:c	Lcom/tencent/luggage/wxa/oa/a;
    //   3014: aload_0
    //   3015: invokevirtual 520	com/tencent/luggage/wxa/oa/b:c	()Ljava/lang/String;
    //   3018: invokeinterface 522 2 0
    //   3023: ldc 163
    //   3025: ldc_w 524
    //   3028: iconst_2
    //   3029: anewarray 4	java/lang/Object
    //   3032: dup
    //   3033: iconst_0
    //   3034: aload_0
    //   3035: getfield 250	com/tencent/luggage/wxa/oa/b:p	Ljava/lang/String;
    //   3038: aastore
    //   3039: dup
    //   3040: iconst_1
    //   3041: aload_0
    //   3042: getfield 76	com/tencent/luggage/wxa/oa/b:f	Ljava/lang/String;
    //   3045: aastore
    //   3046: invokestatic 184	com/tencent/luggage/wxa/qz/o:d	(Ljava/lang/String;Ljava/lang/String;[Ljava/lang/Object;)V
    //   3049: return
    //   3050: aload 14
    //   3052: ifnull +1707 -> 4759
    //   3055: aload 18
    //   3057: invokestatic 619	com/tencent/luggage/wxa/rt/k:b	(Lcom/tencent/luggage/wxa/rt/i;)Ljava/io/OutputStream;
    //   3060: astore 15
    //   3062: iload_2
    //   3063: i2l
    //   3064: lstore 5
    //   3066: lload 5
    //   3068: invokestatic 622	com/tencent/luggage/wxa/nz/j:a	(J)I
    //   3071: newarray byte
    //   3073: astore 16
    //   3075: lconst_0
    //   3076: lstore 5
    //   3078: iconst_m1
    //   3079: istore_2
    //   3080: aload 17
    //   3082: astore 12
    //   3084: aload 14
    //   3086: aload 16
    //   3088: invokevirtual 626	java/io/InputStream:read	([B)I
    //   3091: istore_3
    //   3092: iload_3
    //   3093: iconst_m1
    //   3094: if_icmpeq +1300 -> 4394
    //   3097: aload_0
    //   3098: getfield 53	com/tencent/luggage/wxa/oa/b:d	Z
    //   3101: ifeq +1293 -> 4394
    //   3104: aload_0
    //   3105: getfield 74	com/tencent/luggage/wxa/oa/b:a	Lcom/tencent/luggage/wxa/jx/c;
    //   3108: invokestatic 629	com/tencent/luggage/wxa/nz/j:a	(Lcom/tencent/luggage/wxa/jx/c;)Z
    //   3111: istore 11
    //   3113: iload 11
    //   3115: ifeq +516 -> 3631
    //   3118: aload_0
    //   3119: getfield 82	com/tencent/luggage/wxa/oa/b:c	Lcom/tencent/luggage/wxa/oa/a;
    //   3122: astore 16
    //   3124: aload_0
    //   3125: getfield 78	com/tencent/luggage/wxa/oa/b:g	Ljava/lang/String;
    //   3128: astore 17
    //   3130: aload_0
    //   3131: getfield 76	com/tencent/luggage/wxa/oa/b:f	Ljava/lang/String;
    //   3134: astore 18
    //   3136: aload 16
    //   3138: aload 17
    //   3140: aload 18
    //   3142: ldc_w 631
    //   3145: invokeinterface 221 4 0
    //   3150: aload_0
    //   3151: getfield 80	com/tencent/luggage/wxa/oa/b:h	Ljava/lang/String;
    //   3154: invokestatic 124	com/tencent/luggage/wxa/qz/af:c	(Ljava/lang/String;)Z
    //   3157: ifeq +55 -> 3212
    //   3160: ldc 223
    //   3162: invokestatic 156	com/tencent/luggage/wxa/ba/e:b	(Ljava/lang/Class;)Lcom/tencent/luggage/wxa/ba/d;
    //   3165: checkcast 223	com/tencent/luggage/wxa/nz/o
    //   3168: aload_0
    //   3169: getfield 74	com/tencent/luggage/wxa/oa/b:a	Lcom/tencent/luggage/wxa/jx/c;
    //   3172: invokeinterface 229 1 0
    //   3177: aload_0
    //   3178: invokevirtual 231	com/tencent/luggage/wxa/oa/b:d	()Ljava/lang/String;
    //   3181: ldc 233
    //   3183: aload_0
    //   3184: invokevirtual 235	com/tencent/luggage/wxa/oa/b:a	()Ljava/lang/String;
    //   3187: lconst_0
    //   3188: lload 5
    //   3190: iload_1
    //   3191: iconst_2
    //   3192: aload_0
    //   3193: invokevirtual 238	com/tencent/luggage/wxa/oa/b:e	()I
    //   3196: aload_0
    //   3197: getfield 78	com/tencent/luggage/wxa/oa/b:g	Ljava/lang/String;
    //   3200: aload_0
    //   3201: getfield 59	com/tencent/luggage/wxa/oa/b:i	Ljava/lang/String;
    //   3204: invokeinterface 241 14 0
    //   3209: goto +52 -> 3261
    //   3212: ldc 223
    //   3214: invokestatic 156	com/tencent/luggage/wxa/ba/e:b	(Ljava/lang/Class;)Lcom/tencent/luggage/wxa/ba/d;
    //   3217: checkcast 223	com/tencent/luggage/wxa/nz/o
    //   3220: aload_0
    //   3221: getfield 74	com/tencent/luggage/wxa/oa/b:a	Lcom/tencent/luggage/wxa/jx/c;
    //   3224: invokeinterface 229 1 0
    //   3229: aload_0
    //   3230: invokevirtual 231	com/tencent/luggage/wxa/oa/b:d	()Ljava/lang/String;
    //   3233: ldc 233
    //   3235: aload_0
    //   3236: invokevirtual 235	com/tencent/luggage/wxa/oa/b:a	()Ljava/lang/String;
    //   3239: lconst_0
    //   3240: lload 5
    //   3242: iload_1
    //   3243: iconst_2
    //   3244: aload_0
    //   3245: invokevirtual 238	com/tencent/luggage/wxa/oa/b:e	()I
    //   3248: aload_0
    //   3249: getfield 80	com/tencent/luggage/wxa/oa/b:h	Ljava/lang/String;
    //   3252: aload_0
    //   3253: getfield 59	com/tencent/luggage/wxa/oa/b:i	Ljava/lang/String;
    //   3256: invokeinterface 241 14 0
    //   3261: ldc 151
    //   3263: invokestatic 156	com/tencent/luggage/wxa/ba/e:b	(Ljava/lang/Class;)Lcom/tencent/luggage/wxa/ba/d;
    //   3266: checkcast 151	com/tencent/luggage/wxa/ot/c
    //   3269: ldc2_w 157
    //   3272: ldc2_w 530
    //   3275: lconst_1
    //   3276: iconst_0
    //   3277: invokeinterface 161 8 0
    //   3282: ldc 151
    //   3284: invokestatic 156	com/tencent/luggage/wxa/ba/e:b	(Ljava/lang/Class;)Lcom/tencent/luggage/wxa/ba/d;
    //   3287: checkcast 151	com/tencent/luggage/wxa/ot/c
    //   3290: ldc2_w 157
    //   3293: ldc2_w 532
    //   3296: invokestatic 88	java/lang/System:currentTimeMillis	()J
    //   3299: aload_0
    //   3300: getfield 243	com/tencent/luggage/wxa/oa/b:o	J
    //   3303: lsub
    //   3304: iconst_0
    //   3305: invokeinterface 161 8 0
    //   3310: invokestatic 138	com/tencent/luggage/wxa/qz/r:a	()Landroid/content/Context;
    //   3313: invokestatic 536	com/tencent/luggage/wxa/qz/x:d	(Landroid/content/Context;)I
    //   3316: istore_1
    //   3317: iload_1
    //   3318: iconst_m1
    //   3319: if_icmpne +24 -> 3343
    //   3322: ldc 151
    //   3324: invokestatic 156	com/tencent/luggage/wxa/ba/e:b	(Ljava/lang/Class;)Lcom/tencent/luggage/wxa/ba/d;
    //   3327: checkcast 151	com/tencent/luggage/wxa/ot/c
    //   3330: ldc2_w 157
    //   3333: ldc2_w 537
    //   3336: lconst_1
    //   3337: iconst_0
    //   3338: invokeinterface 161 8 0
    //   3343: ldc 163
    //   3345: ldc_w 540
    //   3348: iconst_2
    //   3349: anewarray 4	java/lang/Object
    //   3352: dup
    //   3353: iconst_0
    //   3354: aload_0
    //   3355: getfield 250	com/tencent/luggage/wxa/oa/b:p	Ljava/lang/String;
    //   3358: aastore
    //   3359: dup
    //   3360: iconst_1
    //   3361: iload_1
    //   3362: invokestatic 179	java/lang/Integer:valueOf	(I)Ljava/lang/Integer;
    //   3365: aastore
    //   3366: invokestatic 184	com/tencent/luggage/wxa/qz/o:d	(Ljava/lang/String;Ljava/lang/String;[Ljava/lang/Object;)V
    //   3369: aload 15
    //   3371: ifnull +41 -> 3412
    //   3374: aload 15
    //   3376: invokevirtual 634	java/io/OutputStream:close	()V
    //   3379: goto +33 -> 3412
    //   3382: astore 15
    //   3384: ldc 163
    //   3386: aload 15
    //   3388: ldc_w 603
    //   3391: iconst_2
    //   3392: anewarray 4	java/lang/Object
    //   3395: dup
    //   3396: iconst_0
    //   3397: aload_0
    //   3398: getfield 76	com/tencent/luggage/wxa/oa/b:f	Ljava/lang/String;
    //   3401: aastore
    //   3402: dup
    //   3403: iconst_1
    //   3404: aload_0
    //   3405: getfield 78	com/tencent/luggage/wxa/oa/b:g	Ljava/lang/String;
    //   3408: aastore
    //   3409: invokestatic 578	com/tencent/luggage/wxa/qz/o:a	(Ljava/lang/String;Ljava/lang/Throwable;Ljava/lang/String;[Ljava/lang/Object;)V
    //   3412: aload 14
    //   3414: ifnull +105 -> 3519
    //   3417: aload 14
    //   3419: invokevirtual 601	java/io/InputStream:close	()V
    //   3422: goto +97 -> 3519
    //   3425: astore 12
    //   3427: ldc 163
    //   3429: aload 12
    //   3431: aload 13
    //   3433: iconst_2
    //   3434: anewarray 4	java/lang/Object
    //   3437: dup
    //   3438: iconst_0
    //   3439: aload_0
    //   3440: getfield 76	com/tencent/luggage/wxa/oa/b:f	Ljava/lang/String;
    //   3443: aastore
    //   3444: dup
    //   3445: iconst_1
    //   3446: aload_0
    //   3447: getfield 78	com/tencent/luggage/wxa/oa/b:g	Ljava/lang/String;
    //   3450: aastore
    //   3451: invokestatic 578	com/tencent/luggage/wxa/qz/o:a	(Ljava/lang/String;Ljava/lang/Throwable;Ljava/lang/String;[Ljava/lang/Object;)V
    //   3454: goto +65 -> 3519
    //   3457: astore 13
    //   3459: ldc 163
    //   3461: aload 13
    //   3463: aload 12
    //   3465: iconst_2
    //   3466: anewarray 4	java/lang/Object
    //   3469: dup
    //   3470: iconst_0
    //   3471: aload_0
    //   3472: getfield 76	com/tencent/luggage/wxa/oa/b:f	Ljava/lang/String;
    //   3475: aastore
    //   3476: dup
    //   3477: iconst_1
    //   3478: aload_0
    //   3479: getfield 78	com/tencent/luggage/wxa/oa/b:g	Ljava/lang/String;
    //   3482: aastore
    //   3483: invokestatic 578	com/tencent/luggage/wxa/qz/o:a	(Ljava/lang/String;Ljava/lang/Throwable;Ljava/lang/String;[Ljava/lang/Object;)V
    //   3486: goto +33 -> 3519
    //   3489: astore 12
    //   3491: ldc 163
    //   3493: aload 12
    //   3495: ldc_w 603
    //   3498: iconst_2
    //   3499: anewarray 4	java/lang/Object
    //   3502: dup
    //   3503: iconst_0
    //   3504: aload_0
    //   3505: getfield 76	com/tencent/luggage/wxa/oa/b:f	Ljava/lang/String;
    //   3508: aastore
    //   3509: dup
    //   3510: iconst_1
    //   3511: aload_0
    //   3512: getfield 78	com/tencent/luggage/wxa/oa/b:g	Ljava/lang/String;
    //   3515: aastore
    //   3516: invokestatic 578	com/tencent/luggage/wxa/qz/o:a	(Ljava/lang/String;Ljava/lang/Throwable;Ljava/lang/String;[Ljava/lang/Object;)V
    //   3519: aload_0
    //   3520: invokevirtual 518	com/tencent/luggage/wxa/oa/b:b	()V
    //   3523: aload_0
    //   3524: getfield 82	com/tencent/luggage/wxa/oa/b:c	Lcom/tencent/luggage/wxa/oa/a;
    //   3527: aload_0
    //   3528: invokevirtual 520	com/tencent/luggage/wxa/oa/b:c	()Ljava/lang/String;
    //   3531: invokeinterface 522 2 0
    //   3536: ldc 163
    //   3538: ldc_w 524
    //   3541: iconst_2
    //   3542: anewarray 4	java/lang/Object
    //   3545: dup
    //   3546: iconst_0
    //   3547: aload_0
    //   3548: getfield 250	com/tencent/luggage/wxa/oa/b:p	Ljava/lang/String;
    //   3551: aastore
    //   3552: dup
    //   3553: iconst_1
    //   3554: aload_0
    //   3555: getfield 76	com/tencent/luggage/wxa/oa/b:f	Ljava/lang/String;
    //   3558: aastore
    //   3559: invokestatic 184	com/tencent/luggage/wxa/qz/o:d	(Ljava/lang/String;Ljava/lang/String;[Ljava/lang/Object;)V
    //   3562: return
    //   3563: astore 17
    //   3565: goto +30 -> 3595
    //   3568: astore 16
    //   3570: goto +38 -> 3608
    //   3573: astore 16
    //   3575: goto +38 -> 3613
    //   3578: astore 16
    //   3580: goto +38 -> 3618
    //   3583: astore 16
    //   3585: goto +38 -> 3623
    //   3588: astore 16
    //   3590: goto +38 -> 3628
    //   3593: astore 17
    //   3595: aload 13
    //   3597: astore 16
    //   3599: aload 12
    //   3601: astore 18
    //   3603: goto -1134 -> 2469
    //   3606: astore 16
    //   3608: goto +855 -> 4463
    //   3611: astore 16
    //   3613: goto +871 -> 4484
    //   3616: astore 16
    //   3618: goto +887 -> 4505
    //   3621: astore 16
    //   3623: goto +903 -> 4526
    //   3626: astore 16
    //   3628: goto +919 -> 4547
    //   3631: aload 15
    //   3633: aload 16
    //   3635: iconst_0
    //   3636: iload_3
    //   3637: invokevirtual 638	java/io/OutputStream:write	([BII)V
    //   3640: lload 5
    //   3642: iload_3
    //   3643: i2l
    //   3644: ladd
    //   3645: lstore 5
    //   3647: lload 9
    //   3649: lconst_0
    //   3650: lcmp
    //   3651: ifle +209 -> 3860
    //   3654: aload_0
    //   3655: getfield 53	com/tencent/luggage/wxa/oa/b:d	Z
    //   3658: ifeq +202 -> 3860
    //   3661: ldc2_w 639
    //   3664: lload 5
    //   3666: lmul
    //   3667: lload 9
    //   3669: ldiv
    //   3670: l2i
    //   3671: istore_3
    //   3672: iload_2
    //   3673: iload_3
    //   3674: if_icmpeq +7121 -> 10795
    //   3677: aload_0
    //   3678: getfield 82	com/tencent/luggage/wxa/oa/b:c	Lcom/tencent/luggage/wxa/oa/a;
    //   3681: aload_0
    //   3682: getfield 78	com/tencent/luggage/wxa/oa/b:g	Ljava/lang/String;
    //   3685: aload_0
    //   3686: getfield 76	com/tencent/luggage/wxa/oa/b:f	Ljava/lang/String;
    //   3689: iload_3
    //   3690: lload 5
    //   3692: lload 9
    //   3694: invokeinterface 643 8 0
    //   3699: iload_3
    //   3700: istore_2
    //   3701: goto +3 -> 3704
    //   3704: ldc 163
    //   3706: ldc_w 645
    //   3709: iconst_3
    //   3710: anewarray 4	java/lang/Object
    //   3713: dup
    //   3714: iconst_0
    //   3715: lload 5
    //   3717: invokestatic 171	java/lang/Long:valueOf	(J)Ljava/lang/Long;
    //   3720: aastore
    //   3721: dup
    //   3722: iconst_1
    //   3723: lload 9
    //   3725: invokestatic 171	java/lang/Long:valueOf	(J)Ljava/lang/Long;
    //   3728: aastore
    //   3729: dup
    //   3730: iconst_2
    //   3731: iload_3
    //   3732: invokestatic 179	java/lang/Integer:valueOf	(I)Ljava/lang/Integer;
    //   3735: aastore
    //   3736: invokestatic 647	com/tencent/luggage/wxa/qz/o:f	(Ljava/lang/String;Ljava/lang/String;[Ljava/lang/Object;)V
    //   3739: goto +121 -> 3860
    //   3742: astore 17
    //   3744: aload 13
    //   3746: astore 16
    //   3748: aload 12
    //   3750: astore 18
    //   3752: goto +1876 -> 5628
    //   3755: astore 16
    //   3757: aload 12
    //   3759: astore 18
    //   3761: aload 16
    //   3763: astore 12
    //   3765: aload 13
    //   3767: astore 17
    //   3769: lload 5
    //   3771: lstore 7
    //   3773: goto +826 -> 4599
    //   3776: astore 16
    //   3778: aload 12
    //   3780: astore 18
    //   3782: aload 16
    //   3784: astore 12
    //   3786: aload 13
    //   3788: astore 17
    //   3790: lload 5
    //   3792: lstore 7
    //   3794: goto +840 -> 4634
    //   3797: astore 16
    //   3799: aload 12
    //   3801: astore 18
    //   3803: aload 16
    //   3805: astore 12
    //   3807: aload 13
    //   3809: astore 17
    //   3811: lload 5
    //   3813: lstore 7
    //   3815: goto +854 -> 4669
    //   3818: astore 16
    //   3820: aload 12
    //   3822: astore 18
    //   3824: aload 16
    //   3826: astore 12
    //   3828: aload 13
    //   3830: astore 17
    //   3832: lload 5
    //   3834: lstore 7
    //   3836: goto +868 -> 4704
    //   3839: astore 16
    //   3841: aload 12
    //   3843: astore 18
    //   3845: aload 16
    //   3847: astore 12
    //   3849: aload 13
    //   3851: astore 17
    //   3853: lload 5
    //   3855: lstore 7
    //   3857: goto +882 -> 4739
    //   3860: lload 5
    //   3862: lconst_0
    //   3863: lcmp
    //   3864: ifle +527 -> 4391
    //   3867: aload_0
    //   3868: getfield 542	com/tencent/luggage/wxa/oa/b:n	I
    //   3871: ifle +520 -> 4391
    //   3874: lload 5
    //   3876: aload_0
    //   3877: getfield 542	com/tencent/luggage/wxa/oa/b:n	I
    //   3880: i2l
    //   3881: ldc2_w 648
    //   3884: lmul
    //   3885: lcmp
    //   3886: iflt +505 -> 4391
    //   3889: ldc 163
    //   3891: ldc_w 651
    //   3894: iconst_1
    //   3895: anewarray 4	java/lang/Object
    //   3898: dup
    //   3899: iconst_0
    //   3900: lload 5
    //   3902: invokestatic 171	java/lang/Long:valueOf	(J)Ljava/lang/Long;
    //   3905: aastore
    //   3906: invokestatic 184	com/tencent/luggage/wxa/qz/o:d	(Ljava/lang/String;Ljava/lang/String;[Ljava/lang/Object;)V
    //   3909: aload_0
    //   3910: getfield 82	com/tencent/luggage/wxa/oa/b:c	Lcom/tencent/luggage/wxa/oa/a;
    //   3913: aload_0
    //   3914: getfield 78	com/tencent/luggage/wxa/oa/b:g	Ljava/lang/String;
    //   3917: aload_0
    //   3918: getfield 76	com/tencent/luggage/wxa/oa/b:f	Ljava/lang/String;
    //   3921: ldc_w 547
    //   3924: invokeinterface 221 4 0
    //   3929: aload 15
    //   3931: invokestatic 654	com/tencent/luggage/wxa/qz/af:a	(Ljava/io/Closeable;)V
    //   3934: aload 14
    //   3936: invokestatic 654	com/tencent/luggage/wxa/qz/af:a	(Ljava/io/Closeable;)V
    //   3939: aload 18
    //   3941: invokevirtual 656	com/tencent/luggage/wxa/rt/i:l	()Ljava/lang/String;
    //   3944: invokestatic 658	com/tencent/luggage/wxa/rt/k:i	(Ljava/lang/String;)Z
    //   3947: pop
    //   3948: aload_0
    //   3949: getfield 80	com/tencent/luggage/wxa/oa/b:h	Ljava/lang/String;
    //   3952: invokestatic 124	com/tencent/luggage/wxa/qz/af:c	(Ljava/lang/String;)Z
    //   3955: ifeq +55 -> 4010
    //   3958: ldc 223
    //   3960: invokestatic 156	com/tencent/luggage/wxa/ba/e:b	(Ljava/lang/Class;)Lcom/tencent/luggage/wxa/ba/d;
    //   3963: checkcast 223	com/tencent/luggage/wxa/nz/o
    //   3966: aload_0
    //   3967: getfield 74	com/tencent/luggage/wxa/oa/b:a	Lcom/tencent/luggage/wxa/jx/c;
    //   3970: invokeinterface 229 1 0
    //   3975: aload_0
    //   3976: invokevirtual 231	com/tencent/luggage/wxa/oa/b:d	()Ljava/lang/String;
    //   3979: ldc 233
    //   3981: aload_0
    //   3982: invokevirtual 235	com/tencent/luggage/wxa/oa/b:a	()Ljava/lang/String;
    //   3985: lconst_0
    //   3986: lload 5
    //   3988: iload_1
    //   3989: iconst_2
    //   3990: aload_0
    //   3991: invokevirtual 238	com/tencent/luggage/wxa/oa/b:e	()I
    //   3994: aload_0
    //   3995: getfield 78	com/tencent/luggage/wxa/oa/b:g	Ljava/lang/String;
    //   3998: aload_0
    //   3999: getfield 59	com/tencent/luggage/wxa/oa/b:i	Ljava/lang/String;
    //   4002: invokeinterface 241 14 0
    //   4007: goto +52 -> 4059
    //   4010: ldc 223
    //   4012: invokestatic 156	com/tencent/luggage/wxa/ba/e:b	(Ljava/lang/Class;)Lcom/tencent/luggage/wxa/ba/d;
    //   4015: checkcast 223	com/tencent/luggage/wxa/nz/o
    //   4018: aload_0
    //   4019: getfield 74	com/tencent/luggage/wxa/oa/b:a	Lcom/tencent/luggage/wxa/jx/c;
    //   4022: invokeinterface 229 1 0
    //   4027: aload_0
    //   4028: invokevirtual 231	com/tencent/luggage/wxa/oa/b:d	()Ljava/lang/String;
    //   4031: ldc 233
    //   4033: aload_0
    //   4034: invokevirtual 235	com/tencent/luggage/wxa/oa/b:a	()Ljava/lang/String;
    //   4037: lconst_0
    //   4038: lload 5
    //   4040: iload_1
    //   4041: iconst_2
    //   4042: aload_0
    //   4043: invokevirtual 238	com/tencent/luggage/wxa/oa/b:e	()I
    //   4046: aload_0
    //   4047: getfield 80	com/tencent/luggage/wxa/oa/b:h	Ljava/lang/String;
    //   4050: aload_0
    //   4051: getfield 59	com/tencent/luggage/wxa/oa/b:i	Ljava/lang/String;
    //   4054: invokeinterface 241 14 0
    //   4059: ldc 151
    //   4061: invokestatic 156	com/tencent/luggage/wxa/ba/e:b	(Ljava/lang/Class;)Lcom/tencent/luggage/wxa/ba/d;
    //   4064: checkcast 151	com/tencent/luggage/wxa/ot/c
    //   4067: ldc2_w 157
    //   4070: ldc2_w 530
    //   4073: lconst_1
    //   4074: iconst_0
    //   4075: invokeinterface 161 8 0
    //   4080: ldc 151
    //   4082: invokestatic 156	com/tencent/luggage/wxa/ba/e:b	(Ljava/lang/Class;)Lcom/tencent/luggage/wxa/ba/d;
    //   4085: checkcast 151	com/tencent/luggage/wxa/ot/c
    //   4088: ldc2_w 157
    //   4091: ldc2_w 532
    //   4094: invokestatic 88	java/lang/System:currentTimeMillis	()J
    //   4097: aload_0
    //   4098: getfield 243	com/tencent/luggage/wxa/oa/b:o	J
    //   4101: lsub
    //   4102: iconst_0
    //   4103: invokeinterface 161 8 0
    //   4108: invokestatic 138	com/tencent/luggage/wxa/qz/r:a	()Landroid/content/Context;
    //   4111: invokestatic 536	com/tencent/luggage/wxa/qz/x:d	(Landroid/content/Context;)I
    //   4114: istore_1
    //   4115: iload_1
    //   4116: iconst_m1
    //   4117: if_icmpne +24 -> 4141
    //   4120: ldc 151
    //   4122: invokestatic 156	com/tencent/luggage/wxa/ba/e:b	(Ljava/lang/Class;)Lcom/tencent/luggage/wxa/ba/d;
    //   4125: checkcast 151	com/tencent/luggage/wxa/ot/c
    //   4128: ldc2_w 157
    //   4131: ldc2_w 537
    //   4134: lconst_1
    //   4135: iconst_0
    //   4136: invokeinterface 161 8 0
    //   4141: ldc 163
    //   4143: ldc_w 540
    //   4146: iconst_2
    //   4147: anewarray 4	java/lang/Object
    //   4150: dup
    //   4151: iconst_0
    //   4152: aload_0
    //   4153: getfield 250	com/tencent/luggage/wxa/oa/b:p	Ljava/lang/String;
    //   4156: aastore
    //   4157: dup
    //   4158: iconst_1
    //   4159: iload_1
    //   4160: invokestatic 179	java/lang/Integer:valueOf	(I)Ljava/lang/Integer;
    //   4163: aastore
    //   4164: invokestatic 184	com/tencent/luggage/wxa/qz/o:d	(Ljava/lang/String;Ljava/lang/String;[Ljava/lang/Object;)V
    //   4167: aload 15
    //   4169: ifnull +41 -> 4210
    //   4172: aload 15
    //   4174: invokevirtual 634	java/io/OutputStream:close	()V
    //   4177: goto +33 -> 4210
    //   4180: astore 15
    //   4182: ldc 163
    //   4184: aload 15
    //   4186: ldc_w 603
    //   4189: iconst_2
    //   4190: anewarray 4	java/lang/Object
    //   4193: dup
    //   4194: iconst_0
    //   4195: aload_0
    //   4196: getfield 76	com/tencent/luggage/wxa/oa/b:f	Ljava/lang/String;
    //   4199: aastore
    //   4200: dup
    //   4201: iconst_1
    //   4202: aload_0
    //   4203: getfield 78	com/tencent/luggage/wxa/oa/b:g	Ljava/lang/String;
    //   4206: aastore
    //   4207: invokestatic 578	com/tencent/luggage/wxa/qz/o:a	(Ljava/lang/String;Ljava/lang/Throwable;Ljava/lang/String;[Ljava/lang/Object;)V
    //   4210: aload 14
    //   4212: ifnull +105 -> 4317
    //   4215: aload 14
    //   4217: invokevirtual 601	java/io/InputStream:close	()V
    //   4220: goto +97 -> 4317
    //   4223: astore 12
    //   4225: ldc 163
    //   4227: aload 12
    //   4229: aload 13
    //   4231: iconst_2
    //   4232: anewarray 4	java/lang/Object
    //   4235: dup
    //   4236: iconst_0
    //   4237: aload_0
    //   4238: getfield 76	com/tencent/luggage/wxa/oa/b:f	Ljava/lang/String;
    //   4241: aastore
    //   4242: dup
    //   4243: iconst_1
    //   4244: aload_0
    //   4245: getfield 78	com/tencent/luggage/wxa/oa/b:g	Ljava/lang/String;
    //   4248: aastore
    //   4249: invokestatic 578	com/tencent/luggage/wxa/qz/o:a	(Ljava/lang/String;Ljava/lang/Throwable;Ljava/lang/String;[Ljava/lang/Object;)V
    //   4252: goto +65 -> 4317
    //   4255: astore 13
    //   4257: ldc 163
    //   4259: aload 13
    //   4261: aload 12
    //   4263: iconst_2
    //   4264: anewarray 4	java/lang/Object
    //   4267: dup
    //   4268: iconst_0
    //   4269: aload_0
    //   4270: getfield 76	com/tencent/luggage/wxa/oa/b:f	Ljava/lang/String;
    //   4273: aastore
    //   4274: dup
    //   4275: iconst_1
    //   4276: aload_0
    //   4277: getfield 78	com/tencent/luggage/wxa/oa/b:g	Ljava/lang/String;
    //   4280: aastore
    //   4281: invokestatic 578	com/tencent/luggage/wxa/qz/o:a	(Ljava/lang/String;Ljava/lang/Throwable;Ljava/lang/String;[Ljava/lang/Object;)V
    //   4284: goto +33 -> 4317
    //   4287: astore 12
    //   4289: ldc 163
    //   4291: aload 12
    //   4293: ldc_w 603
    //   4296: iconst_2
    //   4297: anewarray 4	java/lang/Object
    //   4300: dup
    //   4301: iconst_0
    //   4302: aload_0
    //   4303: getfield 76	com/tencent/luggage/wxa/oa/b:f	Ljava/lang/String;
    //   4306: aastore
    //   4307: dup
    //   4308: iconst_1
    //   4309: aload_0
    //   4310: getfield 78	com/tencent/luggage/wxa/oa/b:g	Ljava/lang/String;
    //   4313: aastore
    //   4314: invokestatic 578	com/tencent/luggage/wxa/qz/o:a	(Ljava/lang/String;Ljava/lang/Throwable;Ljava/lang/String;[Ljava/lang/Object;)V
    //   4317: aload_0
    //   4318: invokevirtual 518	com/tencent/luggage/wxa/oa/b:b	()V
    //   4321: aload_0
    //   4322: getfield 82	com/tencent/luggage/wxa/oa/b:c	Lcom/tencent/luggage/wxa/oa/a;
    //   4325: aload_0
    //   4326: invokevirtual 520	com/tencent/luggage/wxa/oa/b:c	()Ljava/lang/String;
    //   4329: invokeinterface 522 2 0
    //   4334: ldc 163
    //   4336: ldc_w 524
    //   4339: iconst_2
    //   4340: anewarray 4	java/lang/Object
    //   4343: dup
    //   4344: iconst_0
    //   4345: aload_0
    //   4346: getfield 250	com/tencent/luggage/wxa/oa/b:p	Ljava/lang/String;
    //   4349: aastore
    //   4350: dup
    //   4351: iconst_1
    //   4352: aload_0
    //   4353: getfield 76	com/tencent/luggage/wxa/oa/b:f	Ljava/lang/String;
    //   4356: aastore
    //   4357: invokestatic 184	com/tencent/luggage/wxa/qz/o:d	(Ljava/lang/String;Ljava/lang/String;[Ljava/lang/Object;)V
    //   4360: return
    //   4361: astore 17
    //   4363: goto +87 -> 4450
    //   4366: astore 16
    //   4368: goto +95 -> 4463
    //   4371: astore 16
    //   4373: goto +111 -> 4484
    //   4376: astore 16
    //   4378: goto +127 -> 4505
    //   4381: astore 16
    //   4383: goto +143 -> 4526
    //   4386: astore 16
    //   4388: goto +159 -> 4547
    //   4391: goto -1307 -> 3084
    //   4394: aload 13
    //   4396: astore 17
    //   4398: aload 12
    //   4400: astore 16
    //   4402: aload 15
    //   4404: invokevirtual 661	java/io/OutputStream:flush	()V
    //   4407: aload 17
    //   4409: astore 13
    //   4411: aload 16
    //   4413: astore 12
    //   4415: goto +360 -> 4775
    //   4418: astore 17
    //   4420: goto +30 -> 4450
    //   4423: astore 16
    //   4425: goto +38 -> 4463
    //   4428: astore 16
    //   4430: goto +54 -> 4484
    //   4433: astore 16
    //   4435: goto +70 -> 4505
    //   4438: astore 16
    //   4440: goto +86 -> 4526
    //   4443: astore 16
    //   4445: goto +102 -> 4547
    //   4448: astore 17
    //   4450: aload 13
    //   4452: astore 16
    //   4454: aload 12
    //   4456: astore 18
    //   4458: goto +1170 -> 5628
    //   4461: astore 16
    //   4463: aload 12
    //   4465: astore 18
    //   4467: aload 16
    //   4469: astore 12
    //   4471: aload 13
    //   4473: astore 17
    //   4475: lload 5
    //   4477: lstore 7
    //   4479: goto +120 -> 4599
    //   4482: astore 16
    //   4484: aload 12
    //   4486: astore 18
    //   4488: aload 16
    //   4490: astore 12
    //   4492: aload 13
    //   4494: astore 17
    //   4496: lload 5
    //   4498: lstore 7
    //   4500: goto +134 -> 4634
    //   4503: astore 16
    //   4505: aload 12
    //   4507: astore 18
    //   4509: aload 16
    //   4511: astore 12
    //   4513: aload 13
    //   4515: astore 17
    //   4517: lload 5
    //   4519: lstore 7
    //   4521: goto +148 -> 4669
    //   4524: astore 16
    //   4526: aload 12
    //   4528: astore 18
    //   4530: aload 16
    //   4532: astore 12
    //   4534: aload 13
    //   4536: astore 17
    //   4538: lload 5
    //   4540: lstore 7
    //   4542: goto +162 -> 4704
    //   4545: astore 16
    //   4547: aload 12
    //   4549: astore 18
    //   4551: aload 16
    //   4553: astore 12
    //   4555: aload 13
    //   4557: astore 17
    //   4559: lload 5
    //   4561: lstore 7
    //   4563: goto +176 -> 4739
    //   4566: astore 17
    //   4568: ldc_w 381
    //   4571: astore 13
    //   4573: ldc_w 383
    //   4576: astore 12
    //   4578: lconst_0
    //   4579: lstore 5
    //   4581: goto +1039 -> 5620
    //   4584: astore 12
    //   4586: ldc_w 381
    //   4589: astore 17
    //   4591: ldc_w 383
    //   4594: astore 18
    //   4596: lconst_0
    //   4597: lstore 7
    //   4599: iconst_0
    //   4600: istore_3
    //   4601: aload 12
    //   4603: astore 20
    //   4605: aload 15
    //   4607: astore 16
    //   4609: aload 14
    //   4611: astore 19
    //   4613: iload_1
    //   4614: istore 4
    //   4616: goto +1620 -> 6236
    //   4619: astore 12
    //   4621: ldc_w 381
    //   4624: astore 17
    //   4626: ldc_w 383
    //   4629: astore 18
    //   4631: lconst_0
    //   4632: lstore 7
    //   4634: iconst_0
    //   4635: istore_3
    //   4636: aload 12
    //   4638: astore 20
    //   4640: aload 15
    //   4642: astore 16
    //   4644: aload 14
    //   4646: astore 19
    //   4648: iload_1
    //   4649: istore 4
    //   4651: goto +2532 -> 7183
    //   4654: astore 12
    //   4656: ldc_w 381
    //   4659: astore 17
    //   4661: ldc_w 383
    //   4664: astore 18
    //   4666: lconst_0
    //   4667: lstore 7
    //   4669: iconst_0
    //   4670: istore_3
    //   4671: aload 12
    //   4673: astore 20
    //   4675: aload 15
    //   4677: astore 16
    //   4679: aload 14
    //   4681: astore 19
    //   4683: iload_1
    //   4684: istore 4
    //   4686: goto +3251 -> 7937
    //   4689: astore 12
    //   4691: ldc_w 381
    //   4694: astore 17
    //   4696: ldc_w 383
    //   4699: astore 18
    //   4701: lconst_0
    //   4702: lstore 7
    //   4704: iconst_0
    //   4705: istore_3
    //   4706: aload 12
    //   4708: astore 20
    //   4710: aload 15
    //   4712: astore 16
    //   4714: aload 14
    //   4716: astore 19
    //   4718: iload_1
    //   4719: istore 4
    //   4721: goto +3970 -> 8691
    //   4724: astore 12
    //   4726: ldc_w 381
    //   4729: astore 17
    //   4731: ldc_w 383
    //   4734: astore 18
    //   4736: lconst_0
    //   4737: lstore 7
    //   4739: iconst_0
    //   4740: istore_3
    //   4741: aload 12
    //   4743: astore 20
    //   4745: aload 15
    //   4747: astore 16
    //   4749: aload 14
    //   4751: astore 19
    //   4753: iload_1
    //   4754: istore 4
    //   4756: goto +4689 -> 9445
    //   4759: ldc_w 381
    //   4762: astore 13
    //   4764: ldc_w 383
    //   4767: astore 12
    //   4769: lconst_0
    //   4770: lstore 5
    //   4772: aconst_null
    //   4773: astore 15
    //   4775: aload_0
    //   4776: getfield 53	com/tencent/luggage/wxa/oa/b:d	Z
    //   4779: ifeq +47 -> 4826
    //   4782: aload_0
    //   4783: getfield 82	com/tencent/luggage/wxa/oa/b:c	Lcom/tencent/luggage/wxa/oa/a;
    //   4786: aload_0
    //   4787: getfield 78	com/tencent/luggage/wxa/oa/b:g	Ljava/lang/String;
    //   4790: aload_0
    //   4791: getfield 59	com/tencent/luggage/wxa/oa/b:i	Ljava/lang/String;
    //   4794: aload_0
    //   4795: getfield 76	com/tencent/luggage/wxa/oa/b:f	Ljava/lang/String;
    //   4798: iload_1
    //   4799: lload 5
    //   4801: aconst_null
    //   4802: invokeinterface 512 8 0
    //   4807: aload_0
    //   4808: lload 9
    //   4810: invokestatic 88	java/lang/System:currentTimeMillis	()J
    //   4813: aload_0
    //   4814: getfield 243	com/tencent/luggage/wxa/oa/b:o	J
    //   4817: lsub
    //   4818: invokespecial 663	com/tencent/luggage/wxa/oa/b:a	(JJ)V
    //   4821: iconst_1
    //   4822: istore_2
    //   4823: goto +24 -> 4847
    //   4826: aload_0
    //   4827: getfield 82	com/tencent/luggage/wxa/oa/b:c	Lcom/tencent/luggage/wxa/oa/a;
    //   4830: aload_0
    //   4831: getfield 78	com/tencent/luggage/wxa/oa/b:g	Ljava/lang/String;
    //   4834: aload_0
    //   4835: getfield 76	com/tencent/luggage/wxa/oa/b:f	Ljava/lang/String;
    //   4838: ldc 216
    //   4840: invokeinterface 221 4 0
    //   4845: iconst_0
    //   4846: istore_2
    //   4847: ldc 163
    //   4849: ldc_w 665
    //   4852: iconst_3
    //   4853: anewarray 4	java/lang/Object
    //   4856: dup
    //   4857: iconst_0
    //   4858: aload_0
    //   4859: getfield 250	com/tencent/luggage/wxa/oa/b:p	Ljava/lang/String;
    //   4862: aastore
    //   4863: dup
    //   4864: iconst_1
    //   4865: aload_0
    //   4866: getfield 78	com/tencent/luggage/wxa/oa/b:g	Ljava/lang/String;
    //   4869: aastore
    //   4870: dup
    //   4871: iconst_2
    //   4872: aload_0
    //   4873: getfield 76	com/tencent/luggage/wxa/oa/b:f	Ljava/lang/String;
    //   4876: aastore
    //   4877: invokestatic 184	com/tencent/luggage/wxa/qz/o:d	(Ljava/lang/String;Ljava/lang/String;[Ljava/lang/Object;)V
    //   4880: aload_0
    //   4881: getfield 398	com/tencent/luggage/wxa/oa/b:q	Ljava/net/HttpURLConnection;
    //   4884: invokevirtual 559	java/net/HttpURLConnection:getInputStream	()Ljava/io/InputStream;
    //   4887: invokevirtual 601	java/io/InputStream:close	()V
    //   4890: goto +15 -> 4905
    //   4893: astore 16
    //   4895: ldc 163
    //   4897: aload 16
    //   4899: invokevirtual 668	java/io/IOException:getMessage	()Ljava/lang/String;
    //   4902: invokestatic 670	com/tencent/luggage/wxa/qz/o:b	(Ljava/lang/String;Ljava/lang/String;)V
    //   4905: aload_0
    //   4906: getfield 398	com/tencent/luggage/wxa/oa/b:q	Ljava/net/HttpURLConnection;
    //   4909: invokevirtual 673	java/net/HttpURLConnection:disconnect	()V
    //   4912: invokestatic 88	java/lang/System:currentTimeMillis	()J
    //   4915: lload 7
    //   4917: lsub
    //   4918: lstore 7
    //   4920: new 675	java/lang/StringBuilder
    //   4923: dup
    //   4924: invokespecial 676	java/lang/StringBuilder:<init>	()V
    //   4927: astore 16
    //   4929: aload 16
    //   4931: ldc_w 678
    //   4934: invokevirtual 682	java/lang/StringBuilder:append	(Ljava/lang/String;)Ljava/lang/StringBuilder;
    //   4937: pop
    //   4938: aload 16
    //   4940: lload 7
    //   4942: invokevirtual 685	java/lang/StringBuilder:append	(J)Ljava/lang/StringBuilder;
    //   4945: pop
    //   4946: ldc_w 687
    //   4949: aload 16
    //   4951: invokevirtual 688	java/lang/StringBuilder:toString	()Ljava/lang/String;
    //   4954: invokestatic 690	com/tencent/luggage/wxa/qz/o:d	(Ljava/lang/String;Ljava/lang/String;)V
    //   4957: ldc 151
    //   4959: invokestatic 156	com/tencent/luggage/wxa/ba/e:b	(Ljava/lang/Class;)Lcom/tencent/luggage/wxa/ba/d;
    //   4962: checkcast 151	com/tencent/luggage/wxa/ot/c
    //   4965: ldc2_w 691
    //   4968: ldc2_w 693
    //   4971: lload 7
    //   4973: iconst_0
    //   4974: invokeinterface 161 8 0
    //   4979: ldc 151
    //   4981: invokestatic 156	com/tencent/luggage/wxa/ba/e:b	(Ljava/lang/Class;)Lcom/tencent/luggage/wxa/ba/d;
    //   4984: checkcast 151	com/tencent/luggage/wxa/ot/c
    //   4987: ldc2_w 691
    //   4990: ldc2_w 639
    //   4993: lconst_1
    //   4994: iconst_0
    //   4995: invokeinterface 161 8 0
    //   5000: iload_2
    //   5001: ifeq +166 -> 5167
    //   5004: aload_0
    //   5005: getfield 80	com/tencent/luggage/wxa/oa/b:h	Ljava/lang/String;
    //   5008: invokestatic 124	com/tencent/luggage/wxa/qz/af:c	(Ljava/lang/String;)Z
    //   5011: ifeq +55 -> 5066
    //   5014: ldc 223
    //   5016: invokestatic 156	com/tencent/luggage/wxa/ba/e:b	(Ljava/lang/Class;)Lcom/tencent/luggage/wxa/ba/d;
    //   5019: checkcast 223	com/tencent/luggage/wxa/nz/o
    //   5022: aload_0
    //   5023: getfield 74	com/tencent/luggage/wxa/oa/b:a	Lcom/tencent/luggage/wxa/jx/c;
    //   5026: invokeinterface 229 1 0
    //   5031: aload_0
    //   5032: invokevirtual 231	com/tencent/luggage/wxa/oa/b:d	()Ljava/lang/String;
    //   5035: ldc 233
    //   5037: aload_0
    //   5038: invokevirtual 235	com/tencent/luggage/wxa/oa/b:a	()Ljava/lang/String;
    //   5041: lconst_0
    //   5042: lload 5
    //   5044: iload_1
    //   5045: iconst_1
    //   5046: aload_0
    //   5047: invokevirtual 238	com/tencent/luggage/wxa/oa/b:e	()I
    //   5050: aload_0
    //   5051: getfield 78	com/tencent/luggage/wxa/oa/b:g	Ljava/lang/String;
    //   5054: aload_0
    //   5055: getfield 59	com/tencent/luggage/wxa/oa/b:i	Ljava/lang/String;
    //   5058: invokeinterface 241 14 0
    //   5063: goto +52 -> 5115
    //   5066: ldc 223
    //   5068: invokestatic 156	com/tencent/luggage/wxa/ba/e:b	(Ljava/lang/Class;)Lcom/tencent/luggage/wxa/ba/d;
    //   5071: checkcast 223	com/tencent/luggage/wxa/nz/o
    //   5074: aload_0
    //   5075: getfield 74	com/tencent/luggage/wxa/oa/b:a	Lcom/tencent/luggage/wxa/jx/c;
    //   5078: invokeinterface 229 1 0
    //   5083: aload_0
    //   5084: invokevirtual 231	com/tencent/luggage/wxa/oa/b:d	()Ljava/lang/String;
    //   5087: ldc 233
    //   5089: aload_0
    //   5090: invokevirtual 235	com/tencent/luggage/wxa/oa/b:a	()Ljava/lang/String;
    //   5093: lconst_0
    //   5094: lload 5
    //   5096: iload_1
    //   5097: iconst_1
    //   5098: aload_0
    //   5099: invokevirtual 238	com/tencent/luggage/wxa/oa/b:e	()I
    //   5102: aload_0
    //   5103: getfield 80	com/tencent/luggage/wxa/oa/b:h	Ljava/lang/String;
    //   5106: aload_0
    //   5107: getfield 59	com/tencent/luggage/wxa/oa/b:i	Ljava/lang/String;
    //   5110: invokeinterface 241 14 0
    //   5115: ldc 151
    //   5117: invokestatic 156	com/tencent/luggage/wxa/ba/e:b	(Ljava/lang/Class;)Lcom/tencent/luggage/wxa/ba/d;
    //   5120: checkcast 151	com/tencent/luggage/wxa/ot/c
    //   5123: ldc2_w 157
    //   5126: ldc2_w 513
    //   5129: lconst_1
    //   5130: iconst_0
    //   5131: invokeinterface 161 8 0
    //   5136: ldc 151
    //   5138: invokestatic 156	com/tencent/luggage/wxa/ba/e:b	(Ljava/lang/Class;)Lcom/tencent/luggage/wxa/ba/d;
    //   5141: checkcast 151	com/tencent/luggage/wxa/ot/c
    //   5144: ldc2_w 157
    //   5147: ldc2_w 515
    //   5150: invokestatic 88	java/lang/System:currentTimeMillis	()J
    //   5153: aload_0
    //   5154: getfield 243	com/tencent/luggage/wxa/oa/b:o	J
    //   5157: lsub
    //   5158: iconst_0
    //   5159: invokeinterface 161 8 0
    //   5164: goto +222 -> 5386
    //   5167: aload_0
    //   5168: getfield 80	com/tencent/luggage/wxa/oa/b:h	Ljava/lang/String;
    //   5171: invokestatic 124	com/tencent/luggage/wxa/qz/af:c	(Ljava/lang/String;)Z
    //   5174: ifeq +55 -> 5229
    //   5177: ldc 223
    //   5179: invokestatic 156	com/tencent/luggage/wxa/ba/e:b	(Ljava/lang/Class;)Lcom/tencent/luggage/wxa/ba/d;
    //   5182: checkcast 223	com/tencent/luggage/wxa/nz/o
    //   5185: aload_0
    //   5186: getfield 74	com/tencent/luggage/wxa/oa/b:a	Lcom/tencent/luggage/wxa/jx/c;
    //   5189: invokeinterface 229 1 0
    //   5194: aload_0
    //   5195: invokevirtual 231	com/tencent/luggage/wxa/oa/b:d	()Ljava/lang/String;
    //   5198: ldc 233
    //   5200: aload_0
    //   5201: invokevirtual 235	com/tencent/luggage/wxa/oa/b:a	()Ljava/lang/String;
    //   5204: lconst_0
    //   5205: lload 5
    //   5207: iload_1
    //   5208: iconst_2
    //   5209: aload_0
    //   5210: invokevirtual 238	com/tencent/luggage/wxa/oa/b:e	()I
    //   5213: aload_0
    //   5214: getfield 78	com/tencent/luggage/wxa/oa/b:g	Ljava/lang/String;
    //   5217: aload_0
    //   5218: getfield 59	com/tencent/luggage/wxa/oa/b:i	Ljava/lang/String;
    //   5221: invokeinterface 241 14 0
    //   5226: goto +52 -> 5278
    //   5229: ldc 223
    //   5231: invokestatic 156	com/tencent/luggage/wxa/ba/e:b	(Ljava/lang/Class;)Lcom/tencent/luggage/wxa/ba/d;
    //   5234: checkcast 223	com/tencent/luggage/wxa/nz/o
    //   5237: aload_0
    //   5238: getfield 74	com/tencent/luggage/wxa/oa/b:a	Lcom/tencent/luggage/wxa/jx/c;
    //   5241: invokeinterface 229 1 0
    //   5246: aload_0
    //   5247: invokevirtual 231	com/tencent/luggage/wxa/oa/b:d	()Ljava/lang/String;
    //   5250: ldc 233
    //   5252: aload_0
    //   5253: invokevirtual 235	com/tencent/luggage/wxa/oa/b:a	()Ljava/lang/String;
    //   5256: lconst_0
    //   5257: lload 5
    //   5259: iload_1
    //   5260: iconst_2
    //   5261: aload_0
    //   5262: invokevirtual 238	com/tencent/luggage/wxa/oa/b:e	()I
    //   5265: aload_0
    //   5266: getfield 80	com/tencent/luggage/wxa/oa/b:h	Ljava/lang/String;
    //   5269: aload_0
    //   5270: getfield 59	com/tencent/luggage/wxa/oa/b:i	Ljava/lang/String;
    //   5273: invokeinterface 241 14 0
    //   5278: ldc 151
    //   5280: invokestatic 156	com/tencent/luggage/wxa/ba/e:b	(Ljava/lang/Class;)Lcom/tencent/luggage/wxa/ba/d;
    //   5283: checkcast 151	com/tencent/luggage/wxa/ot/c
    //   5286: ldc2_w 157
    //   5289: ldc2_w 530
    //   5292: lconst_1
    //   5293: iconst_0
    //   5294: invokeinterface 161 8 0
    //   5299: ldc 151
    //   5301: invokestatic 156	com/tencent/luggage/wxa/ba/e:b	(Ljava/lang/Class;)Lcom/tencent/luggage/wxa/ba/d;
    //   5304: checkcast 151	com/tencent/luggage/wxa/ot/c
    //   5307: ldc2_w 157
    //   5310: ldc2_w 532
    //   5313: invokestatic 88	java/lang/System:currentTimeMillis	()J
    //   5316: aload_0
    //   5317: getfield 243	com/tencent/luggage/wxa/oa/b:o	J
    //   5320: lsub
    //   5321: iconst_0
    //   5322: invokeinterface 161 8 0
    //   5327: invokestatic 138	com/tencent/luggage/wxa/qz/r:a	()Landroid/content/Context;
    //   5330: invokestatic 536	com/tencent/luggage/wxa/qz/x:d	(Landroid/content/Context;)I
    //   5333: istore_1
    //   5334: iload_1
    //   5335: iconst_m1
    //   5336: if_icmpne +24 -> 5360
    //   5339: ldc 151
    //   5341: invokestatic 156	com/tencent/luggage/wxa/ba/e:b	(Ljava/lang/Class;)Lcom/tencent/luggage/wxa/ba/d;
    //   5344: checkcast 151	com/tencent/luggage/wxa/ot/c
    //   5347: ldc2_w 157
    //   5350: ldc2_w 537
    //   5353: lconst_1
    //   5354: iconst_0
    //   5355: invokeinterface 161 8 0
    //   5360: ldc 163
    //   5362: ldc_w 540
    //   5365: iconst_2
    //   5366: anewarray 4	java/lang/Object
    //   5369: dup
    //   5370: iconst_0
    //   5371: aload_0
    //   5372: getfield 250	com/tencent/luggage/wxa/oa/b:p	Ljava/lang/String;
    //   5375: aastore
    //   5376: dup
    //   5377: iconst_1
    //   5378: iload_1
    //   5379: invokestatic 179	java/lang/Integer:valueOf	(I)Ljava/lang/Integer;
    //   5382: aastore
    //   5383: invokestatic 184	com/tencent/luggage/wxa/qz/o:d	(Ljava/lang/String;Ljava/lang/String;[Ljava/lang/Object;)V
    //   5386: aload 15
    //   5388: ifnull +41 -> 5429
    //   5391: aload 15
    //   5393: invokevirtual 634	java/io/OutputStream:close	()V
    //   5396: goto +33 -> 5429
    //   5399: astore 15
    //   5401: ldc 163
    //   5403: aload 15
    //   5405: ldc_w 603
    //   5408: iconst_2
    //   5409: anewarray 4	java/lang/Object
    //   5412: dup
    //   5413: iconst_0
    //   5414: aload_0
    //   5415: getfield 76	com/tencent/luggage/wxa/oa/b:f	Ljava/lang/String;
    //   5418: aastore
    //   5419: dup
    //   5420: iconst_1
    //   5421: aload_0
    //   5422: getfield 78	com/tencent/luggage/wxa/oa/b:g	Ljava/lang/String;
    //   5425: aastore
    //   5426: invokestatic 578	com/tencent/luggage/wxa/qz/o:a	(Ljava/lang/String;Ljava/lang/Throwable;Ljava/lang/String;[Ljava/lang/Object;)V
    //   5429: aload 14
    //   5431: ifnull +105 -> 5536
    //   5434: aload 14
    //   5436: invokevirtual 601	java/io/InputStream:close	()V
    //   5439: goto +97 -> 5536
    //   5442: astore 12
    //   5444: ldc 163
    //   5446: aload 12
    //   5448: aload 13
    //   5450: iconst_2
    //   5451: anewarray 4	java/lang/Object
    //   5454: dup
    //   5455: iconst_0
    //   5456: aload_0
    //   5457: getfield 76	com/tencent/luggage/wxa/oa/b:f	Ljava/lang/String;
    //   5460: aastore
    //   5461: dup
    //   5462: iconst_1
    //   5463: aload_0
    //   5464: getfield 78	com/tencent/luggage/wxa/oa/b:g	Ljava/lang/String;
    //   5467: aastore
    //   5468: invokestatic 578	com/tencent/luggage/wxa/qz/o:a	(Ljava/lang/String;Ljava/lang/Throwable;Ljava/lang/String;[Ljava/lang/Object;)V
    //   5471: goto +65 -> 5536
    //   5474: astore 13
    //   5476: ldc 163
    //   5478: aload 13
    //   5480: aload 12
    //   5482: iconst_2
    //   5483: anewarray 4	java/lang/Object
    //   5486: dup
    //   5487: iconst_0
    //   5488: aload_0
    //   5489: getfield 76	com/tencent/luggage/wxa/oa/b:f	Ljava/lang/String;
    //   5492: aastore
    //   5493: dup
    //   5494: iconst_1
    //   5495: aload_0
    //   5496: getfield 78	com/tencent/luggage/wxa/oa/b:g	Ljava/lang/String;
    //   5499: aastore
    //   5500: invokestatic 578	com/tencent/luggage/wxa/qz/o:a	(Ljava/lang/String;Ljava/lang/Throwable;Ljava/lang/String;[Ljava/lang/Object;)V
    //   5503: goto +33 -> 5536
    //   5506: astore 12
    //   5508: ldc 163
    //   5510: aload 12
    //   5512: ldc_w 603
    //   5515: iconst_2
    //   5516: anewarray 4	java/lang/Object
    //   5519: dup
    //   5520: iconst_0
    //   5521: aload_0
    //   5522: getfield 76	com/tencent/luggage/wxa/oa/b:f	Ljava/lang/String;
    //   5525: aastore
    //   5526: dup
    //   5527: iconst_1
    //   5528: aload_0
    //   5529: getfield 78	com/tencent/luggage/wxa/oa/b:g	Ljava/lang/String;
    //   5532: aastore
    //   5533: invokestatic 578	com/tencent/luggage/wxa/qz/o:a	(Ljava/lang/String;Ljava/lang/Throwable;Ljava/lang/String;[Ljava/lang/Object;)V
    //   5536: aload_0
    //   5537: invokevirtual 518	com/tencent/luggage/wxa/oa/b:b	()V
    //   5540: aload_0
    //   5541: getfield 82	com/tencent/luggage/wxa/oa/b:c	Lcom/tencent/luggage/wxa/oa/a;
    //   5544: aload_0
    //   5545: invokevirtual 520	com/tencent/luggage/wxa/oa/b:c	()Ljava/lang/String;
    //   5548: invokeinterface 522 2 0
    //   5553: ldc 163
    //   5555: ldc_w 524
    //   5558: iconst_2
    //   5559: anewarray 4	java/lang/Object
    //   5562: dup
    //   5563: iconst_0
    //   5564: aload_0
    //   5565: getfield 250	com/tencent/luggage/wxa/oa/b:p	Ljava/lang/String;
    //   5568: aastore
    //   5569: dup
    //   5570: iconst_1
    //   5571: aload_0
    //   5572: getfield 76	com/tencent/luggage/wxa/oa/b:f	Ljava/lang/String;
    //   5575: aastore
    //   5576: invokestatic 184	com/tencent/luggage/wxa/qz/o:d	(Ljava/lang/String;Ljava/lang/String;[Ljava/lang/Object;)V
    //   5579: return
    //   5580: astore 17
    //   5582: aload 13
    //   5584: astore 16
    //   5586: aload 12
    //   5588: astore 18
    //   5590: goto +188 -> 5778
    //   5593: astore 16
    //   5595: goto +42 -> 5637
    //   5598: astore 16
    //   5600: goto +62 -> 5662
    //   5603: astore 16
    //   5605: goto +82 -> 5687
    //   5608: astore 16
    //   5610: goto +102 -> 5712
    //   5613: astore 16
    //   5615: goto +122 -> 5737
    //   5618: astore 17
    //   5620: aload 12
    //   5622: astore 18
    //   5624: aload 13
    //   5626: astore 16
    //   5628: iconst_0
    //   5629: istore_2
    //   5630: goto +148 -> 5778
    //   5633: astore 16
    //   5635: iconst_0
    //   5636: istore_2
    //   5637: aload 15
    //   5639: astore 17
    //   5641: aload 16
    //   5643: astore 15
    //   5645: aload 17
    //   5647: astore 16
    //   5649: iload_2
    //   5650: istore_3
    //   5651: lload 5
    //   5653: lstore 7
    //   5655: goto +164 -> 5819
    //   5658: astore 16
    //   5660: iconst_0
    //   5661: istore_2
    //   5662: aload 15
    //   5664: astore 17
    //   5666: aload 16
    //   5668: astore 15
    //   5670: aload 17
    //   5672: astore 16
    //   5674: iload_2
    //   5675: istore_3
    //   5676: lload 5
    //   5678: lstore 7
    //   5680: goto +181 -> 5861
    //   5683: astore 16
    //   5685: iconst_0
    //   5686: istore_2
    //   5687: aload 15
    //   5689: astore 17
    //   5691: aload 16
    //   5693: astore 15
    //   5695: aload 17
    //   5697: astore 16
    //   5699: iload_2
    //   5700: istore_3
    //   5701: lload 5
    //   5703: lstore 7
    //   5705: goto +198 -> 5903
    //   5708: astore 16
    //   5710: iconst_0
    //   5711: istore_2
    //   5712: aload 15
    //   5714: astore 17
    //   5716: aload 16
    //   5718: astore 15
    //   5720: aload 17
    //   5722: astore 16
    //   5724: iload_2
    //   5725: istore_3
    //   5726: lload 5
    //   5728: lstore 7
    //   5730: goto +215 -> 5945
    //   5733: astore 16
    //   5735: iconst_0
    //   5736: istore_2
    //   5737: aload 15
    //   5739: astore 17
    //   5741: aload 16
    //   5743: astore 15
    //   5745: aload 17
    //   5747: astore 16
    //   5749: iload_2
    //   5750: istore_3
    //   5751: lload 5
    //   5753: lstore 7
    //   5755: goto +232 -> 5987
    //   5758: astore 17
    //   5760: ldc_w 381
    //   5763: astore 16
    //   5765: ldc_w 383
    //   5768: astore 18
    //   5770: lconst_0
    //   5771: lstore 5
    //   5773: iconst_0
    //   5774: istore_2
    //   5775: aconst_null
    //   5776: astore 15
    //   5778: iload_1
    //   5779: istore_3
    //   5780: aload 14
    //   5782: astore 13
    //   5784: aload 17
    //   5786: astore 12
    //   5788: aload 16
    //   5790: astore 14
    //   5792: iload_2
    //   5793: istore_1
    //   5794: iload_3
    //   5795: istore_2
    //   5796: goto +4401 -> 10197
    //   5799: astore 15
    //   5801: ldc_w 381
    //   5804: astore 13
    //   5806: ldc_w 383
    //   5809: astore 12
    //   5811: lconst_0
    //   5812: lstore 7
    //   5814: aconst_null
    //   5815: astore 16
    //   5817: iconst_0
    //   5818: istore_3
    //   5819: aload 15
    //   5821: astore 20
    //   5823: aload 13
    //   5825: astore 17
    //   5827: aload 12
    //   5829: astore 18
    //   5831: aload 14
    //   5833: astore 19
    //   5835: iload_1
    //   5836: istore 4
    //   5838: goto +398 -> 6236
    //   5841: astore 15
    //   5843: ldc_w 381
    //   5846: astore 13
    //   5848: ldc_w 383
    //   5851: astore 12
    //   5853: lconst_0
    //   5854: lstore 7
    //   5856: aconst_null
    //   5857: astore 16
    //   5859: iconst_0
    //   5860: istore_3
    //   5861: aload 15
    //   5863: astore 20
    //   5865: aload 13
    //   5867: astore 17
    //   5869: aload 12
    //   5871: astore 18
    //   5873: aload 14
    //   5875: astore 19
    //   5877: iload_1
    //   5878: istore 4
    //   5880: goto +1303 -> 7183
    //   5883: astore 15
    //   5885: ldc_w 381
    //   5888: astore 13
    //   5890: ldc_w 383
    //   5893: astore 12
    //   5895: lconst_0
    //   5896: lstore 7
    //   5898: aconst_null
    //   5899: astore 16
    //   5901: iconst_0
    //   5902: istore_3
    //   5903: aload 15
    //   5905: astore 20
    //   5907: aload 13
    //   5909: astore 17
    //   5911: aload 12
    //   5913: astore 18
    //   5915: aload 14
    //   5917: astore 19
    //   5919: iload_1
    //   5920: istore 4
    //   5922: goto +2015 -> 7937
    //   5925: astore 15
    //   5927: ldc_w 381
    //   5930: astore 13
    //   5932: ldc_w 383
    //   5935: astore 12
    //   5937: lconst_0
    //   5938: lstore 7
    //   5940: aconst_null
    //   5941: astore 16
    //   5943: iconst_0
    //   5944: istore_3
    //   5945: aload 15
    //   5947: astore 20
    //   5949: aload 13
    //   5951: astore 17
    //   5953: aload 12
    //   5955: astore 18
    //   5957: aload 14
    //   5959: astore 19
    //   5961: iload_1
    //   5962: istore 4
    //   5964: goto +2727 -> 8691
    //   5967: astore 15
    //   5969: ldc_w 381
    //   5972: astore 13
    //   5974: ldc_w 383
    //   5977: astore 12
    //   5979: lconst_0
    //   5980: lstore 7
    //   5982: aconst_null
    //   5983: astore 16
    //   5985: iconst_0
    //   5986: istore_3
    //   5987: aload 15
    //   5989: astore 20
    //   5991: aload 13
    //   5993: astore 17
    //   5995: aload 12
    //   5997: astore 18
    //   5999: aload 14
    //   6001: astore 19
    //   6003: iload_1
    //   6004: istore 4
    //   6006: goto +3439 -> 9445
    //   6009: astore 12
    //   6011: ldc_w 381
    //   6014: astore 14
    //   6016: ldc_w 383
    //   6019: astore 18
    //   6021: iload_1
    //   6022: istore_2
    //   6023: lconst_0
    //   6024: lstore 5
    //   6026: aconst_null
    //   6027: astore 13
    //   6029: iconst_0
    //   6030: istore_1
    //   6031: aconst_null
    //   6032: astore 15
    //   6034: goto +4163 -> 10197
    //   6037: astore 20
    //   6039: ldc_w 381
    //   6042: astore 17
    //   6044: ldc_w 383
    //   6047: astore 18
    //   6049: lconst_0
    //   6050: lstore 7
    //   6052: aconst_null
    //   6053: astore 16
    //   6055: iconst_0
    //   6056: istore_3
    //   6057: aconst_null
    //   6058: astore 19
    //   6060: iload_1
    //   6061: istore 4
    //   6063: goto +173 -> 6236
    //   6066: astore 20
    //   6068: ldc_w 381
    //   6071: astore 17
    //   6073: ldc_w 383
    //   6076: astore 18
    //   6078: lconst_0
    //   6079: lstore 7
    //   6081: aconst_null
    //   6082: astore 16
    //   6084: iconst_0
    //   6085: istore_3
    //   6086: aconst_null
    //   6087: astore 19
    //   6089: iload_1
    //   6090: istore 4
    //   6092: goto +1091 -> 7183
    //   6095: astore 20
    //   6097: ldc_w 381
    //   6100: astore 17
    //   6102: ldc_w 383
    //   6105: astore 18
    //   6107: lconst_0
    //   6108: lstore 7
    //   6110: aconst_null
    //   6111: astore 16
    //   6113: iconst_0
    //   6114: istore_3
    //   6115: aconst_null
    //   6116: astore 19
    //   6118: iload_1
    //   6119: istore 4
    //   6121: goto +1816 -> 7937
    //   6124: astore 20
    //   6126: ldc_w 381
    //   6129: astore 17
    //   6131: ldc_w 383
    //   6134: astore 18
    //   6136: lconst_0
    //   6137: lstore 7
    //   6139: aconst_null
    //   6140: astore 16
    //   6142: iconst_0
    //   6143: istore_3
    //   6144: aconst_null
    //   6145: astore 19
    //   6147: iload_1
    //   6148: istore 4
    //   6150: goto +2541 -> 8691
    //   6153: astore 20
    //   6155: ldc_w 381
    //   6158: astore 17
    //   6160: ldc_w 383
    //   6163: astore 18
    //   6165: lconst_0
    //   6166: lstore 7
    //   6168: aconst_null
    //   6169: astore 16
    //   6171: iconst_0
    //   6172: istore_3
    //   6173: aconst_null
    //   6174: astore 19
    //   6176: iload_1
    //   6177: istore 4
    //   6179: goto +3266 -> 9445
    //   6182: astore 12
    //   6184: lconst_0
    //   6185: lstore 5
    //   6187: aconst_null
    //   6188: astore 15
    //   6190: ldc_w 383
    //   6193: astore 18
    //   6195: iconst_0
    //   6196: istore_1
    //   6197: ldc_w 381
    //   6200: astore 14
    //   6202: aconst_null
    //   6203: astore 13
    //   6205: iconst_0
    //   6206: istore_2
    //   6207: goto +3990 -> 10197
    //   6210: astore 20
    //   6212: lconst_0
    //   6213: lstore 7
    //   6215: aconst_null
    //   6216: astore 19
    //   6218: ldc_w 383
    //   6221: astore 18
    //   6223: iconst_0
    //   6224: istore_3
    //   6225: ldc_w 381
    //   6228: astore 17
    //   6230: aconst_null
    //   6231: astore 16
    //   6233: iconst_0
    //   6234: istore 4
    //   6236: aload 16
    //   6238: astore 14
    //   6240: aload 17
    //   6242: astore 12
    //   6244: iload_3
    //   6245: istore_1
    //   6246: aload 18
    //   6248: astore 13
    //   6250: aload 19
    //   6252: astore 15
    //   6254: lload 7
    //   6256: lstore 5
    //   6258: iload 4
    //   6260: istore_2
    //   6261: ldc 151
    //   6263: invokestatic 156	com/tencent/luggage/wxa/ba/e:b	(Ljava/lang/Class;)Lcom/tencent/luggage/wxa/ba/d;
    //   6266: checkcast 151	com/tencent/luggage/wxa/ot/c
    //   6269: ldc2_w 157
    //   6272: ldc2_w 695
    //   6275: lconst_1
    //   6276: iconst_0
    //   6277: invokeinterface 161 8 0
    //   6282: aload 16
    //   6284: astore 14
    //   6286: aload 17
    //   6288: astore 12
    //   6290: iload_3
    //   6291: istore_1
    //   6292: aload 18
    //   6294: astore 13
    //   6296: aload 19
    //   6298: astore 15
    //   6300: lload 7
    //   6302: lstore 5
    //   6304: iload 4
    //   6306: istore_2
    //   6307: ldc 163
    //   6309: aload 20
    //   6311: ldc_w 698
    //   6314: iconst_2
    //   6315: anewarray 4	java/lang/Object
    //   6318: dup
    //   6319: iconst_0
    //   6320: aload_0
    //   6321: getfield 76	com/tencent/luggage/wxa/oa/b:f	Ljava/lang/String;
    //   6324: aastore
    //   6325: dup
    //   6326: iconst_1
    //   6327: aload_0
    //   6328: getfield 78	com/tencent/luggage/wxa/oa/b:g	Ljava/lang/String;
    //   6331: aastore
    //   6332: invokestatic 578	com/tencent/luggage/wxa/qz/o:a	(Ljava/lang/String;Ljava/lang/Throwable;Ljava/lang/String;[Ljava/lang/Object;)V
    //   6335: aload 16
    //   6337: astore 14
    //   6339: aload 17
    //   6341: astore 12
    //   6343: iload_3
    //   6344: istore_1
    //   6345: aload 18
    //   6347: astore 13
    //   6349: aload 19
    //   6351: astore 15
    //   6353: lload 7
    //   6355: lstore 5
    //   6357: iload 4
    //   6359: istore_2
    //   6360: aload_0
    //   6361: getfield 82	com/tencent/luggage/wxa/oa/b:c	Lcom/tencent/luggage/wxa/oa/a;
    //   6364: astore 21
    //   6366: aload 16
    //   6368: astore 14
    //   6370: aload 17
    //   6372: astore 12
    //   6374: iload_3
    //   6375: istore_1
    //   6376: aload 18
    //   6378: astore 13
    //   6380: aload 19
    //   6382: astore 15
    //   6384: lload 7
    //   6386: lstore 5
    //   6388: iload 4
    //   6390: istore_2
    //   6391: aload_0
    //   6392: getfield 78	com/tencent/luggage/wxa/oa/b:g	Ljava/lang/String;
    //   6395: astore 22
    //   6397: aload 16
    //   6399: astore 14
    //   6401: aload 17
    //   6403: astore 12
    //   6405: iload_3
    //   6406: istore_1
    //   6407: aload 18
    //   6409: astore 13
    //   6411: aload 19
    //   6413: astore 15
    //   6415: lload 7
    //   6417: lstore 5
    //   6419: iload 4
    //   6421: istore_2
    //   6422: aload_0
    //   6423: getfield 76	com/tencent/luggage/wxa/oa/b:f	Ljava/lang/String;
    //   6426: astore 23
    //   6428: aload 16
    //   6430: astore 14
    //   6432: aload 17
    //   6434: astore 12
    //   6436: iload_3
    //   6437: istore_1
    //   6438: aload 18
    //   6440: astore 13
    //   6442: aload 19
    //   6444: astore 15
    //   6446: lload 7
    //   6448: lstore 5
    //   6450: iload 4
    //   6452: istore_2
    //   6453: new 675	java/lang/StringBuilder
    //   6456: dup
    //   6457: invokespecial 676	java/lang/StringBuilder:<init>	()V
    //   6460: astore 24
    //   6462: aload 16
    //   6464: astore 14
    //   6466: aload 17
    //   6468: astore 12
    //   6470: iload_3
    //   6471: istore_1
    //   6472: aload 18
    //   6474: astore 13
    //   6476: aload 19
    //   6478: astore 15
    //   6480: lload 7
    //   6482: lstore 5
    //   6484: iload 4
    //   6486: istore_2
    //   6487: aload 24
    //   6489: ldc_w 700
    //   6492: invokevirtual 682	java/lang/StringBuilder:append	(Ljava/lang/String;)Ljava/lang/StringBuilder;
    //   6495: pop
    //   6496: aload 16
    //   6498: astore 14
    //   6500: aload 17
    //   6502: astore 12
    //   6504: iload_3
    //   6505: istore_1
    //   6506: aload 18
    //   6508: astore 13
    //   6510: aload 19
    //   6512: astore 15
    //   6514: lload 7
    //   6516: lstore 5
    //   6518: iload 4
    //   6520: istore_2
    //   6521: aload 24
    //   6523: aload 20
    //   6525: invokevirtual 701	java/lang/Exception:getMessage	()Ljava/lang/String;
    //   6528: invokevirtual 682	java/lang/StringBuilder:append	(Ljava/lang/String;)Ljava/lang/StringBuilder;
    //   6531: pop
    //   6532: aload 16
    //   6534: astore 14
    //   6536: aload 17
    //   6538: astore 12
    //   6540: iload_3
    //   6541: istore_1
    //   6542: aload 18
    //   6544: astore 13
    //   6546: aload 19
    //   6548: astore 15
    //   6550: lload 7
    //   6552: lstore 5
    //   6554: iload 4
    //   6556: istore_2
    //   6557: aload 21
    //   6559: aload 22
    //   6561: aload 23
    //   6563: aload 24
    //   6565: invokevirtual 688	java/lang/StringBuilder:toString	()Ljava/lang/String;
    //   6568: invokeinterface 221 4 0
    //   6573: iload_3
    //   6574: ifeq +168 -> 6742
    //   6577: aload_0
    //   6578: getfield 80	com/tencent/luggage/wxa/oa/b:h	Ljava/lang/String;
    //   6581: invokestatic 124	com/tencent/luggage/wxa/qz/af:c	(Ljava/lang/String;)Z
    //   6584: ifeq +56 -> 6640
    //   6587: ldc 223
    //   6589: invokestatic 156	com/tencent/luggage/wxa/ba/e:b	(Ljava/lang/Class;)Lcom/tencent/luggage/wxa/ba/d;
    //   6592: checkcast 223	com/tencent/luggage/wxa/nz/o
    //   6595: aload_0
    //   6596: getfield 74	com/tencent/luggage/wxa/oa/b:a	Lcom/tencent/luggage/wxa/jx/c;
    //   6599: invokeinterface 229 1 0
    //   6604: aload_0
    //   6605: invokevirtual 231	com/tencent/luggage/wxa/oa/b:d	()Ljava/lang/String;
    //   6608: ldc 233
    //   6610: aload_0
    //   6611: invokevirtual 235	com/tencent/luggage/wxa/oa/b:a	()Ljava/lang/String;
    //   6614: lconst_0
    //   6615: lload 7
    //   6617: iload 4
    //   6619: iconst_1
    //   6620: aload_0
    //   6621: invokevirtual 238	com/tencent/luggage/wxa/oa/b:e	()I
    //   6624: aload_0
    //   6625: getfield 78	com/tencent/luggage/wxa/oa/b:g	Ljava/lang/String;
    //   6628: aload_0
    //   6629: getfield 59	com/tencent/luggage/wxa/oa/b:i	Ljava/lang/String;
    //   6632: invokeinterface 241 14 0
    //   6637: goto +53 -> 6690
    //   6640: ldc 223
    //   6642: invokestatic 156	com/tencent/luggage/wxa/ba/e:b	(Ljava/lang/Class;)Lcom/tencent/luggage/wxa/ba/d;
    //   6645: checkcast 223	com/tencent/luggage/wxa/nz/o
    //   6648: aload_0
    //   6649: getfield 74	com/tencent/luggage/wxa/oa/b:a	Lcom/tencent/luggage/wxa/jx/c;
    //   6652: invokeinterface 229 1 0
    //   6657: aload_0
    //   6658: invokevirtual 231	com/tencent/luggage/wxa/oa/b:d	()Ljava/lang/String;
    //   6661: ldc 233
    //   6663: aload_0
    //   6664: invokevirtual 235	com/tencent/luggage/wxa/oa/b:a	()Ljava/lang/String;
    //   6667: lconst_0
    //   6668: lload 7
    //   6670: iload 4
    //   6672: iconst_1
    //   6673: aload_0
    //   6674: invokevirtual 238	com/tencent/luggage/wxa/oa/b:e	()I
    //   6677: aload_0
    //   6678: getfield 80	com/tencent/luggage/wxa/oa/b:h	Ljava/lang/String;
    //   6681: aload_0
    //   6682: getfield 59	com/tencent/luggage/wxa/oa/b:i	Ljava/lang/String;
    //   6685: invokeinterface 241 14 0
    //   6690: ldc 151
    //   6692: invokestatic 156	com/tencent/luggage/wxa/ba/e:b	(Ljava/lang/Class;)Lcom/tencent/luggage/wxa/ba/d;
    //   6695: checkcast 151	com/tencent/luggage/wxa/ot/c
    //   6698: ldc2_w 157
    //   6701: ldc2_w 513
    //   6704: lconst_1
    //   6705: iconst_0
    //   6706: invokeinterface 161 8 0
    //   6711: ldc 151
    //   6713: invokestatic 156	com/tencent/luggage/wxa/ba/e:b	(Ljava/lang/Class;)Lcom/tencent/luggage/wxa/ba/d;
    //   6716: checkcast 151	com/tencent/luggage/wxa/ot/c
    //   6719: ldc2_w 157
    //   6722: ldc2_w 515
    //   6725: invokestatic 88	java/lang/System:currentTimeMillis	()J
    //   6728: aload_0
    //   6729: getfield 243	com/tencent/luggage/wxa/oa/b:o	J
    //   6732: lsub
    //   6733: iconst_0
    //   6734: invokeinterface 161 8 0
    //   6739: goto +224 -> 6963
    //   6742: aload_0
    //   6743: getfield 80	com/tencent/luggage/wxa/oa/b:h	Ljava/lang/String;
    //   6746: invokestatic 124	com/tencent/luggage/wxa/qz/af:c	(Ljava/lang/String;)Z
    //   6749: ifeq +56 -> 6805
    //   6752: ldc 223
    //   6754: invokestatic 156	com/tencent/luggage/wxa/ba/e:b	(Ljava/lang/Class;)Lcom/tencent/luggage/wxa/ba/d;
    //   6757: checkcast 223	com/tencent/luggage/wxa/nz/o
    //   6760: aload_0
    //   6761: getfield 74	com/tencent/luggage/wxa/oa/b:a	Lcom/tencent/luggage/wxa/jx/c;
    //   6764: invokeinterface 229 1 0
    //   6769: aload_0
    //   6770: invokevirtual 231	com/tencent/luggage/wxa/oa/b:d	()Ljava/lang/String;
    //   6773: ldc 233
    //   6775: aload_0
    //   6776: invokevirtual 235	com/tencent/luggage/wxa/oa/b:a	()Ljava/lang/String;
    //   6779: lconst_0
    //   6780: lload 7
    //   6782: iload 4
    //   6784: iconst_2
    //   6785: aload_0
    //   6786: invokevirtual 238	com/tencent/luggage/wxa/oa/b:e	()I
    //   6789: aload_0
    //   6790: getfield 78	com/tencent/luggage/wxa/oa/b:g	Ljava/lang/String;
    //   6793: aload_0
    //   6794: getfield 59	com/tencent/luggage/wxa/oa/b:i	Ljava/lang/String;
    //   6797: invokeinterface 241 14 0
    //   6802: goto +53 -> 6855
    //   6805: ldc 223
    //   6807: invokestatic 156	com/tencent/luggage/wxa/ba/e:b	(Ljava/lang/Class;)Lcom/tencent/luggage/wxa/ba/d;
    //   6810: checkcast 223	com/tencent/luggage/wxa/nz/o
    //   6813: aload_0
    //   6814: getfield 74	com/tencent/luggage/wxa/oa/b:a	Lcom/tencent/luggage/wxa/jx/c;
    //   6817: invokeinterface 229 1 0
    //   6822: aload_0
    //   6823: invokevirtual 231	com/tencent/luggage/wxa/oa/b:d	()Ljava/lang/String;
    //   6826: ldc 233
    //   6828: aload_0
    //   6829: invokevirtual 235	com/tencent/luggage/wxa/oa/b:a	()Ljava/lang/String;
    //   6832: lconst_0
    //   6833: lload 7
    //   6835: iload 4
    //   6837: iconst_2
    //   6838: aload_0
    //   6839: invokevirtual 238	com/tencent/luggage/wxa/oa/b:e	()I
    //   6842: aload_0
    //   6843: getfield 80	com/tencent/luggage/wxa/oa/b:h	Ljava/lang/String;
    //   6846: aload_0
    //   6847: getfield 59	com/tencent/luggage/wxa/oa/b:i	Ljava/lang/String;
    //   6850: invokeinterface 241 14 0
    //   6855: ldc 151
    //   6857: invokestatic 156	com/tencent/luggage/wxa/ba/e:b	(Ljava/lang/Class;)Lcom/tencent/luggage/wxa/ba/d;
    //   6860: checkcast 151	com/tencent/luggage/wxa/ot/c
    //   6863: ldc2_w 157
    //   6866: ldc2_w 530
    //   6869: lconst_1
    //   6870: iconst_0
    //   6871: invokeinterface 161 8 0
    //   6876: ldc 151
    //   6878: invokestatic 156	com/tencent/luggage/wxa/ba/e:b	(Ljava/lang/Class;)Lcom/tencent/luggage/wxa/ba/d;
    //   6881: checkcast 151	com/tencent/luggage/wxa/ot/c
    //   6884: ldc2_w 157
    //   6887: ldc2_w 532
    //   6890: invokestatic 88	java/lang/System:currentTimeMillis	()J
    //   6893: aload_0
    //   6894: getfield 243	com/tencent/luggage/wxa/oa/b:o	J
    //   6897: lsub
    //   6898: iconst_0
    //   6899: invokeinterface 161 8 0
    //   6904: invokestatic 138	com/tencent/luggage/wxa/qz/r:a	()Landroid/content/Context;
    //   6907: invokestatic 536	com/tencent/luggage/wxa/qz/x:d	(Landroid/content/Context;)I
    //   6910: istore_1
    //   6911: iload_1
    //   6912: iconst_m1
    //   6913: if_icmpne +24 -> 6937
    //   6916: ldc 151
    //   6918: invokestatic 156	com/tencent/luggage/wxa/ba/e:b	(Ljava/lang/Class;)Lcom/tencent/luggage/wxa/ba/d;
    //   6921: checkcast 151	com/tencent/luggage/wxa/ot/c
    //   6924: ldc2_w 157
    //   6927: ldc2_w 537
    //   6930: lconst_1
    //   6931: iconst_0
    //   6932: invokeinterface 161 8 0
    //   6937: ldc 163
    //   6939: ldc_w 540
    //   6942: iconst_2
    //   6943: anewarray 4	java/lang/Object
    //   6946: dup
    //   6947: iconst_0
    //   6948: aload_0
    //   6949: getfield 250	com/tencent/luggage/wxa/oa/b:p	Ljava/lang/String;
    //   6952: aastore
    //   6953: dup
    //   6954: iconst_1
    //   6955: iload_1
    //   6956: invokestatic 179	java/lang/Integer:valueOf	(I)Ljava/lang/Integer;
    //   6959: aastore
    //   6960: invokestatic 184	com/tencent/luggage/wxa/qz/o:d	(Ljava/lang/String;Ljava/lang/String;[Ljava/lang/Object;)V
    //   6963: aload 16
    //   6965: ifnull +41 -> 7006
    //   6968: aload 16
    //   6970: invokevirtual 634	java/io/OutputStream:close	()V
    //   6973: goto +33 -> 7006
    //   6976: astore 12
    //   6978: ldc 163
    //   6980: aload 12
    //   6982: ldc_w 603
    //   6985: iconst_2
    //   6986: anewarray 4	java/lang/Object
    //   6989: dup
    //   6990: iconst_0
    //   6991: aload_0
    //   6992: getfield 76	com/tencent/luggage/wxa/oa/b:f	Ljava/lang/String;
    //   6995: aastore
    //   6996: dup
    //   6997: iconst_1
    //   6998: aload_0
    //   6999: getfield 78	com/tencent/luggage/wxa/oa/b:g	Ljava/lang/String;
    //   7002: aastore
    //   7003: invokestatic 578	com/tencent/luggage/wxa/qz/o:a	(Ljava/lang/String;Ljava/lang/Throwable;Ljava/lang/String;[Ljava/lang/Object;)V
    //   7006: aload 19
    //   7008: ifnull +105 -> 7113
    //   7011: aload 19
    //   7013: invokevirtual 601	java/io/InputStream:close	()V
    //   7016: goto +97 -> 7113
    //   7019: astore 12
    //   7021: ldc 163
    //   7023: aload 12
    //   7025: aload 17
    //   7027: iconst_2
    //   7028: anewarray 4	java/lang/Object
    //   7031: dup
    //   7032: iconst_0
    //   7033: aload_0
    //   7034: getfield 76	com/tencent/luggage/wxa/oa/b:f	Ljava/lang/String;
    //   7037: aastore
    //   7038: dup
    //   7039: iconst_1
    //   7040: aload_0
    //   7041: getfield 78	com/tencent/luggage/wxa/oa/b:g	Ljava/lang/String;
    //   7044: aastore
    //   7045: invokestatic 578	com/tencent/luggage/wxa/qz/o:a	(Ljava/lang/String;Ljava/lang/Throwable;Ljava/lang/String;[Ljava/lang/Object;)V
    //   7048: goto +65 -> 7113
    //   7051: astore 12
    //   7053: ldc 163
    //   7055: aload 12
    //   7057: aload 18
    //   7059: iconst_2
    //   7060: anewarray 4	java/lang/Object
    //   7063: dup
    //   7064: iconst_0
    //   7065: aload_0
    //   7066: getfield 76	com/tencent/luggage/wxa/oa/b:f	Ljava/lang/String;
    //   7069: aastore
    //   7070: dup
    //   7071: iconst_1
    //   7072: aload_0
    //   7073: getfield 78	com/tencent/luggage/wxa/oa/b:g	Ljava/lang/String;
    //   7076: aastore
    //   7077: invokestatic 578	com/tencent/luggage/wxa/qz/o:a	(Ljava/lang/String;Ljava/lang/Throwable;Ljava/lang/String;[Ljava/lang/Object;)V
    //   7080: goto +33 -> 7113
    //   7083: astore 12
    //   7085: ldc 163
    //   7087: aload 12
    //   7089: ldc_w 603
    //   7092: iconst_2
    //   7093: anewarray 4	java/lang/Object
    //   7096: dup
    //   7097: iconst_0
    //   7098: aload_0
    //   7099: getfield 76	com/tencent/luggage/wxa/oa/b:f	Ljava/lang/String;
    //   7102: aastore
    //   7103: dup
    //   7104: iconst_1
    //   7105: aload_0
    //   7106: getfield 78	com/tencent/luggage/wxa/oa/b:g	Ljava/lang/String;
    //   7109: aastore
    //   7110: invokestatic 578	com/tencent/luggage/wxa/qz/o:a	(Ljava/lang/String;Ljava/lang/Throwable;Ljava/lang/String;[Ljava/lang/Object;)V
    //   7113: aload_0
    //   7114: invokevirtual 518	com/tencent/luggage/wxa/oa/b:b	()V
    //   7117: aload_0
    //   7118: getfield 82	com/tencent/luggage/wxa/oa/b:c	Lcom/tencent/luggage/wxa/oa/a;
    //   7121: aload_0
    //   7122: invokevirtual 520	com/tencent/luggage/wxa/oa/b:c	()Ljava/lang/String;
    //   7125: invokeinterface 522 2 0
    //   7130: ldc 163
    //   7132: ldc_w 524
    //   7135: iconst_2
    //   7136: anewarray 4	java/lang/Object
    //   7139: dup
    //   7140: iconst_0
    //   7141: aload_0
    //   7142: getfield 250	com/tencent/luggage/wxa/oa/b:p	Ljava/lang/String;
    //   7145: aastore
    //   7146: dup
    //   7147: iconst_1
    //   7148: aload_0
    //   7149: getfield 76	com/tencent/luggage/wxa/oa/b:f	Ljava/lang/String;
    //   7152: aastore
    //   7153: invokestatic 184	com/tencent/luggage/wxa/qz/o:d	(Ljava/lang/String;Ljava/lang/String;[Ljava/lang/Object;)V
    //   7156: return
    //   7157: astore 20
    //   7159: lconst_0
    //   7160: lstore 7
    //   7162: aconst_null
    //   7163: astore 19
    //   7165: ldc_w 383
    //   7168: astore 18
    //   7170: iconst_0
    //   7171: istore_3
    //   7172: ldc_w 381
    //   7175: astore 17
    //   7177: aconst_null
    //   7178: astore 16
    //   7180: iconst_0
    //   7181: istore 4
    //   7183: aload 16
    //   7185: astore 14
    //   7187: aload 17
    //   7189: astore 12
    //   7191: iload_3
    //   7192: istore_1
    //   7193: aload 18
    //   7195: astore 13
    //   7197: aload 19
    //   7199: astore 15
    //   7201: lload 7
    //   7203: lstore 5
    //   7205: iload 4
    //   7207: istore_2
    //   7208: ldc 151
    //   7210: invokestatic 156	com/tencent/luggage/wxa/ba/e:b	(Ljava/lang/Class;)Lcom/tencent/luggage/wxa/ba/d;
    //   7213: checkcast 151	com/tencent/luggage/wxa/ot/c
    //   7216: ldc2_w 157
    //   7219: ldc2_w 702
    //   7222: lconst_1
    //   7223: iconst_0
    //   7224: invokeinterface 161 8 0
    //   7229: aload 16
    //   7231: astore 14
    //   7233: aload 17
    //   7235: astore 12
    //   7237: iload_3
    //   7238: istore_1
    //   7239: aload 18
    //   7241: astore 13
    //   7243: aload 19
    //   7245: astore 15
    //   7247: lload 7
    //   7249: lstore 5
    //   7251: iload 4
    //   7253: istore_2
    //   7254: ldc 163
    //   7256: aload 20
    //   7258: ldc_w 705
    //   7261: iconst_2
    //   7262: anewarray 4	java/lang/Object
    //   7265: dup
    //   7266: iconst_0
    //   7267: aload_0
    //   7268: getfield 76	com/tencent/luggage/wxa/oa/b:f	Ljava/lang/String;
    //   7271: aastore
    //   7272: dup
    //   7273: iconst_1
    //   7274: aload_0
    //   7275: getfield 78	com/tencent/luggage/wxa/oa/b:g	Ljava/lang/String;
    //   7278: aastore
    //   7279: invokestatic 578	com/tencent/luggage/wxa/qz/o:a	(Ljava/lang/String;Ljava/lang/Throwable;Ljava/lang/String;[Ljava/lang/Object;)V
    //   7282: aload 16
    //   7284: astore 14
    //   7286: aload 17
    //   7288: astore 12
    //   7290: iload_3
    //   7291: istore_1
    //   7292: aload 18
    //   7294: astore 13
    //   7296: aload 19
    //   7298: astore 15
    //   7300: lload 7
    //   7302: lstore 5
    //   7304: iload 4
    //   7306: istore_2
    //   7307: aload_0
    //   7308: getfield 82	com/tencent/luggage/wxa/oa/b:c	Lcom/tencent/luggage/wxa/oa/a;
    //   7311: aload_0
    //   7312: getfield 78	com/tencent/luggage/wxa/oa/b:g	Ljava/lang/String;
    //   7315: aload_0
    //   7316: getfield 76	com/tencent/luggage/wxa/oa/b:f	Ljava/lang/String;
    //   7319: ldc_w 707
    //   7322: invokeinterface 221 4 0
    //   7327: iload_3
    //   7328: ifeq +168 -> 7496
    //   7331: aload_0
    //   7332: getfield 80	com/tencent/luggage/wxa/oa/b:h	Ljava/lang/String;
    //   7335: invokestatic 124	com/tencent/luggage/wxa/qz/af:c	(Ljava/lang/String;)Z
    //   7338: ifeq +56 -> 7394
    //   7341: ldc 223
    //   7343: invokestatic 156	com/tencent/luggage/wxa/ba/e:b	(Ljava/lang/Class;)Lcom/tencent/luggage/wxa/ba/d;
    //   7346: checkcast 223	com/tencent/luggage/wxa/nz/o
    //   7349: aload_0
    //   7350: getfield 74	com/tencent/luggage/wxa/oa/b:a	Lcom/tencent/luggage/wxa/jx/c;
    //   7353: invokeinterface 229 1 0
    //   7358: aload_0
    //   7359: invokevirtual 231	com/tencent/luggage/wxa/oa/b:d	()Ljava/lang/String;
    //   7362: ldc 233
    //   7364: aload_0
    //   7365: invokevirtual 235	com/tencent/luggage/wxa/oa/b:a	()Ljava/lang/String;
    //   7368: lconst_0
    //   7369: lload 7
    //   7371: iload 4
    //   7373: iconst_1
    //   7374: aload_0
    //   7375: invokevirtual 238	com/tencent/luggage/wxa/oa/b:e	()I
    //   7378: aload_0
    //   7379: getfield 78	com/tencent/luggage/wxa/oa/b:g	Ljava/lang/String;
    //   7382: aload_0
    //   7383: getfield 59	com/tencent/luggage/wxa/oa/b:i	Ljava/lang/String;
    //   7386: invokeinterface 241 14 0
    //   7391: goto +53 -> 7444
    //   7394: ldc 223
    //   7396: invokestatic 156	com/tencent/luggage/wxa/ba/e:b	(Ljava/lang/Class;)Lcom/tencent/luggage/wxa/ba/d;
    //   7399: checkcast 223	com/tencent/luggage/wxa/nz/o
    //   7402: aload_0
    //   7403: getfield 74	com/tencent/luggage/wxa/oa/b:a	Lcom/tencent/luggage/wxa/jx/c;
    //   7406: invokeinterface 229 1 0
    //   7411: aload_0
    //   7412: invokevirtual 231	com/tencent/luggage/wxa/oa/b:d	()Ljava/lang/String;
    //   7415: ldc 233
    //   7417: aload_0
    //   7418: invokevirtual 235	com/tencent/luggage/wxa/oa/b:a	()Ljava/lang/String;
    //   7421: lconst_0
    //   7422: lload 7
    //   7424: iload 4
    //   7426: iconst_1
    //   7427: aload_0
    //   7428: invokevirtual 238	com/tencent/luggage/wxa/oa/b:e	()I
    //   7431: aload_0
    //   7432: getfield 80	com/tencent/luggage/wxa/oa/b:h	Ljava/lang/String;
    //   7435: aload_0
    //   7436: getfield 59	com/tencent/luggage/wxa/oa/b:i	Ljava/lang/String;
    //   7439: invokeinterface 241 14 0
    //   7444: ldc 151
    //   7446: invokestatic 156	com/tencent/luggage/wxa/ba/e:b	(Ljava/lang/Class;)Lcom/tencent/luggage/wxa/ba/d;
    //   7449: checkcast 151	com/tencent/luggage/wxa/ot/c
    //   7452: ldc2_w 157
    //   7455: ldc2_w 513
    //   7458: lconst_1
    //   7459: iconst_0
    //   7460: invokeinterface 161 8 0
    //   7465: ldc 151
    //   7467: invokestatic 156	com/tencent/luggage/wxa/ba/e:b	(Ljava/lang/Class;)Lcom/tencent/luggage/wxa/ba/d;
    //   7470: checkcast 151	com/tencent/luggage/wxa/ot/c
    //   7473: ldc2_w 157
    //   7476: ldc2_w 515
    //   7479: invokestatic 88	java/lang/System:currentTimeMillis	()J
    //   7482: aload_0
    //   7483: getfield 243	com/tencent/luggage/wxa/oa/b:o	J
    //   7486: lsub
    //   7487: iconst_0
    //   7488: invokeinterface 161 8 0
    //   7493: goto +224 -> 7717
    //   7496: aload_0
    //   7497: getfield 80	com/tencent/luggage/wxa/oa/b:h	Ljava/lang/String;
    //   7500: invokestatic 124	com/tencent/luggage/wxa/qz/af:c	(Ljava/lang/String;)Z
    //   7503: ifeq +56 -> 7559
    //   7506: ldc 223
    //   7508: invokestatic 156	com/tencent/luggage/wxa/ba/e:b	(Ljava/lang/Class;)Lcom/tencent/luggage/wxa/ba/d;
    //   7511: checkcast 223	com/tencent/luggage/wxa/nz/o
    //   7514: aload_0
    //   7515: getfield 74	com/tencent/luggage/wxa/oa/b:a	Lcom/tencent/luggage/wxa/jx/c;
    //   7518: invokeinterface 229 1 0
    //   7523: aload_0
    //   7524: invokevirtual 231	com/tencent/luggage/wxa/oa/b:d	()Ljava/lang/String;
    //   7527: ldc 233
    //   7529: aload_0
    //   7530: invokevirtual 235	com/tencent/luggage/wxa/oa/b:a	()Ljava/lang/String;
    //   7533: lconst_0
    //   7534: lload 7
    //   7536: iload 4
    //   7538: iconst_2
    //   7539: aload_0
    //   7540: invokevirtual 238	com/tencent/luggage/wxa/oa/b:e	()I
    //   7543: aload_0
    //   7544: getfield 78	com/tencent/luggage/wxa/oa/b:g	Ljava/lang/String;
    //   7547: aload_0
    //   7548: getfield 59	com/tencent/luggage/wxa/oa/b:i	Ljava/lang/String;
    //   7551: invokeinterface 241 14 0
    //   7556: goto +53 -> 7609
    //   7559: ldc 223
    //   7561: invokestatic 156	com/tencent/luggage/wxa/ba/e:b	(Ljava/lang/Class;)Lcom/tencent/luggage/wxa/ba/d;
    //   7564: checkcast 223	com/tencent/luggage/wxa/nz/o
    //   7567: aload_0
    //   7568: getfield 74	com/tencent/luggage/wxa/oa/b:a	Lcom/tencent/luggage/wxa/jx/c;
    //   7571: invokeinterface 229 1 0
    //   7576: aload_0
    //   7577: invokevirtual 231	com/tencent/luggage/wxa/oa/b:d	()Ljava/lang/String;
    //   7580: ldc 233
    //   7582: aload_0
    //   7583: invokevirtual 235	com/tencent/luggage/wxa/oa/b:a	()Ljava/lang/String;
    //   7586: lconst_0
    //   7587: lload 7
    //   7589: iload 4
    //   7591: iconst_2
    //   7592: aload_0
    //   7593: invokevirtual 238	com/tencent/luggage/wxa/oa/b:e	()I
    //   7596: aload_0
    //   7597: getfield 80	com/tencent/luggage/wxa/oa/b:h	Ljava/lang/String;
    //   7600: aload_0
    //   7601: getfield 59	com/tencent/luggage/wxa/oa/b:i	Ljava/lang/String;
    //   7604: invokeinterface 241 14 0
    //   7609: ldc 151
    //   7611: invokestatic 156	com/tencent/luggage/wxa/ba/e:b	(Ljava/lang/Class;)Lcom/tencent/luggage/wxa/ba/d;
    //   7614: checkcast 151	com/tencent/luggage/wxa/ot/c
    //   7617: ldc2_w 157
    //   7620: ldc2_w 530
    //   7623: lconst_1
    //   7624: iconst_0
    //   7625: invokeinterface 161 8 0
    //   7630: ldc 151
    //   7632: invokestatic 156	com/tencent/luggage/wxa/ba/e:b	(Ljava/lang/Class;)Lcom/tencent/luggage/wxa/ba/d;
    //   7635: checkcast 151	com/tencent/luggage/wxa/ot/c
    //   7638: ldc2_w 157
    //   7641: ldc2_w 532
    //   7644: invokestatic 88	java/lang/System:currentTimeMillis	()J
    //   7647: aload_0
    //   7648: getfield 243	com/tencent/luggage/wxa/oa/b:o	J
    //   7651: lsub
    //   7652: iconst_0
    //   7653: invokeinterface 161 8 0
    //   7658: invokestatic 138	com/tencent/luggage/wxa/qz/r:a	()Landroid/content/Context;
    //   7661: invokestatic 536	com/tencent/luggage/wxa/qz/x:d	(Landroid/content/Context;)I
    //   7664: istore_1
    //   7665: iload_1
    //   7666: iconst_m1
    //   7667: if_icmpne +24 -> 7691
    //   7670: ldc 151
    //   7672: invokestatic 156	com/tencent/luggage/wxa/ba/e:b	(Ljava/lang/Class;)Lcom/tencent/luggage/wxa/ba/d;
    //   7675: checkcast 151	com/tencent/luggage/wxa/ot/c
    //   7678: ldc2_w 157
    //   7681: ldc2_w 537
    //   7684: lconst_1
    //   7685: iconst_0
    //   7686: invokeinterface 161 8 0
    //   7691: ldc 163
    //   7693: ldc_w 540
    //   7696: iconst_2
    //   7697: anewarray 4	java/lang/Object
    //   7700: dup
    //   7701: iconst_0
    //   7702: aload_0
    //   7703: getfield 250	com/tencent/luggage/wxa/oa/b:p	Ljava/lang/String;
    //   7706: aastore
    //   7707: dup
    //   7708: iconst_1
    //   7709: iload_1
    //   7710: invokestatic 179	java/lang/Integer:valueOf	(I)Ljava/lang/Integer;
    //   7713: aastore
    //   7714: invokestatic 184	com/tencent/luggage/wxa/qz/o:d	(Ljava/lang/String;Ljava/lang/String;[Ljava/lang/Object;)V
    //   7717: aload 16
    //   7719: ifnull +41 -> 7760
    //   7722: aload 16
    //   7724: invokevirtual 634	java/io/OutputStream:close	()V
    //   7727: goto +33 -> 7760
    //   7730: astore 12
    //   7732: ldc 163
    //   7734: aload 12
    //   7736: ldc_w 603
    //   7739: iconst_2
    //   7740: anewarray 4	java/lang/Object
    //   7743: dup
    //   7744: iconst_0
    //   7745: aload_0
    //   7746: getfield 76	com/tencent/luggage/wxa/oa/b:f	Ljava/lang/String;
    //   7749: aastore
    //   7750: dup
    //   7751: iconst_1
    //   7752: aload_0
    //   7753: getfield 78	com/tencent/luggage/wxa/oa/b:g	Ljava/lang/String;
    //   7756: aastore
    //   7757: invokestatic 578	com/tencent/luggage/wxa/qz/o:a	(Ljava/lang/String;Ljava/lang/Throwable;Ljava/lang/String;[Ljava/lang/Object;)V
    //   7760: aload 19
    //   7762: ifnull +105 -> 7867
    //   7765: aload 19
    //   7767: invokevirtual 601	java/io/InputStream:close	()V
    //   7770: goto +97 -> 7867
    //   7773: astore 12
    //   7775: ldc 163
    //   7777: aload 12
    //   7779: aload 17
    //   7781: iconst_2
    //   7782: anewarray 4	java/lang/Object
    //   7785: dup
    //   7786: iconst_0
    //   7787: aload_0
    //   7788: getfield 76	com/tencent/luggage/wxa/oa/b:f	Ljava/lang/String;
    //   7791: aastore
    //   7792: dup
    //   7793: iconst_1
    //   7794: aload_0
    //   7795: getfield 78	com/tencent/luggage/wxa/oa/b:g	Ljava/lang/String;
    //   7798: aastore
    //   7799: invokestatic 578	com/tencent/luggage/wxa/qz/o:a	(Ljava/lang/String;Ljava/lang/Throwable;Ljava/lang/String;[Ljava/lang/Object;)V
    //   7802: goto +65 -> 7867
    //   7805: astore 12
    //   7807: ldc 163
    //   7809: aload 12
    //   7811: aload 18
    //   7813: iconst_2
    //   7814: anewarray 4	java/lang/Object
    //   7817: dup
    //   7818: iconst_0
    //   7819: aload_0
    //   7820: getfield 76	com/tencent/luggage/wxa/oa/b:f	Ljava/lang/String;
    //   7823: aastore
    //   7824: dup
    //   7825: iconst_1
    //   7826: aload_0
    //   7827: getfield 78	com/tencent/luggage/wxa/oa/b:g	Ljava/lang/String;
    //   7830: aastore
    //   7831: invokestatic 578	com/tencent/luggage/wxa/qz/o:a	(Ljava/lang/String;Ljava/lang/Throwable;Ljava/lang/String;[Ljava/lang/Object;)V
    //   7834: goto +33 -> 7867
    //   7837: astore 12
    //   7839: ldc 163
    //   7841: aload 12
    //   7843: ldc_w 603
    //   7846: iconst_2
    //   7847: anewarray 4	java/lang/Object
    //   7850: dup
    //   7851: iconst_0
    //   7852: aload_0
    //   7853: getfield 76	com/tencent/luggage/wxa/oa/b:f	Ljava/lang/String;
    //   7856: aastore
    //   7857: dup
    //   7858: iconst_1
    //   7859: aload_0
    //   7860: getfield 78	com/tencent/luggage/wxa/oa/b:g	Ljava/lang/String;
    //   7863: aastore
    //   7864: invokestatic 578	com/tencent/luggage/wxa/qz/o:a	(Ljava/lang/String;Ljava/lang/Throwable;Ljava/lang/String;[Ljava/lang/Object;)V
    //   7867: aload_0
    //   7868: invokevirtual 518	com/tencent/luggage/wxa/oa/b:b	()V
    //   7871: aload_0
    //   7872: getfield 82	com/tencent/luggage/wxa/oa/b:c	Lcom/tencent/luggage/wxa/oa/a;
    //   7875: aload_0
    //   7876: invokevirtual 520	com/tencent/luggage/wxa/oa/b:c	()Ljava/lang/String;
    //   7879: invokeinterface 522 2 0
    //   7884: ldc 163
    //   7886: ldc_w 524
    //   7889: iconst_2
    //   7890: anewarray 4	java/lang/Object
    //   7893: dup
    //   7894: iconst_0
    //   7895: aload_0
    //   7896: getfield 250	com/tencent/luggage/wxa/oa/b:p	Ljava/lang/String;
    //   7899: aastore
    //   7900: dup
    //   7901: iconst_1
    //   7902: aload_0
    //   7903: getfield 76	com/tencent/luggage/wxa/oa/b:f	Ljava/lang/String;
    //   7906: aastore
    //   7907: invokestatic 184	com/tencent/luggage/wxa/qz/o:d	(Ljava/lang/String;Ljava/lang/String;[Ljava/lang/Object;)V
    //   7910: return
    //   7911: astore 20
    //   7913: lconst_0
    //   7914: lstore 7
    //   7916: aconst_null
    //   7917: astore 19
    //   7919: ldc_w 383
    //   7922: astore 18
    //   7924: iconst_0
    //   7925: istore_3
    //   7926: ldc_w 381
    //   7929: astore 17
    //   7931: aconst_null
    //   7932: astore 16
    //   7934: iconst_0
    //   7935: istore 4
    //   7937: aload 16
    //   7939: astore 14
    //   7941: aload 17
    //   7943: astore 12
    //   7945: iload_3
    //   7946: istore_1
    //   7947: aload 18
    //   7949: astore 13
    //   7951: aload 19
    //   7953: astore 15
    //   7955: lload 7
    //   7957: lstore 5
    //   7959: iload 4
    //   7961: istore_2
    //   7962: ldc 151
    //   7964: invokestatic 156	com/tencent/luggage/wxa/ba/e:b	(Ljava/lang/Class;)Lcom/tencent/luggage/wxa/ba/d;
    //   7967: checkcast 151	com/tencent/luggage/wxa/ot/c
    //   7970: ldc2_w 157
    //   7973: ldc2_w 362
    //   7976: lconst_1
    //   7977: iconst_0
    //   7978: invokeinterface 161 8 0
    //   7983: aload 16
    //   7985: astore 14
    //   7987: aload 17
    //   7989: astore 12
    //   7991: iload_3
    //   7992: istore_1
    //   7993: aload 18
    //   7995: astore 13
    //   7997: aload 19
    //   7999: astore 15
    //   8001: lload 7
    //   8003: lstore 5
    //   8005: iload 4
    //   8007: istore_2
    //   8008: ldc 163
    //   8010: aload 20
    //   8012: ldc_w 709
    //   8015: iconst_2
    //   8016: anewarray 4	java/lang/Object
    //   8019: dup
    //   8020: iconst_0
    //   8021: aload_0
    //   8022: getfield 76	com/tencent/luggage/wxa/oa/b:f	Ljava/lang/String;
    //   8025: aastore
    //   8026: dup
    //   8027: iconst_1
    //   8028: aload_0
    //   8029: getfield 78	com/tencent/luggage/wxa/oa/b:g	Ljava/lang/String;
    //   8032: aastore
    //   8033: invokestatic 578	com/tencent/luggage/wxa/qz/o:a	(Ljava/lang/String;Ljava/lang/Throwable;Ljava/lang/String;[Ljava/lang/Object;)V
    //   8036: aload 16
    //   8038: astore 14
    //   8040: aload 17
    //   8042: astore 12
    //   8044: iload_3
    //   8045: istore_1
    //   8046: aload 18
    //   8048: astore 13
    //   8050: aload 19
    //   8052: astore 15
    //   8054: lload 7
    //   8056: lstore 5
    //   8058: iload 4
    //   8060: istore_2
    //   8061: aload_0
    //   8062: getfield 82	com/tencent/luggage/wxa/oa/b:c	Lcom/tencent/luggage/wxa/oa/a;
    //   8065: aload_0
    //   8066: getfield 78	com/tencent/luggage/wxa/oa/b:g	Ljava/lang/String;
    //   8069: aload_0
    //   8070: getfield 76	com/tencent/luggage/wxa/oa/b:f	Ljava/lang/String;
    //   8073: ldc_w 711
    //   8076: invokeinterface 221 4 0
    //   8081: iload_3
    //   8082: ifeq +168 -> 8250
    //   8085: aload_0
    //   8086: getfield 80	com/tencent/luggage/wxa/oa/b:h	Ljava/lang/String;
    //   8089: invokestatic 124	com/tencent/luggage/wxa/qz/af:c	(Ljava/lang/String;)Z
    //   8092: ifeq +56 -> 8148
    //   8095: ldc 223
    //   8097: invokestatic 156	com/tencent/luggage/wxa/ba/e:b	(Ljava/lang/Class;)Lcom/tencent/luggage/wxa/ba/d;
    //   8100: checkcast 223	com/tencent/luggage/wxa/nz/o
    //   8103: aload_0
    //   8104: getfield 74	com/tencent/luggage/wxa/oa/b:a	Lcom/tencent/luggage/wxa/jx/c;
    //   8107: invokeinterface 229 1 0
    //   8112: aload_0
    //   8113: invokevirtual 231	com/tencent/luggage/wxa/oa/b:d	()Ljava/lang/String;
    //   8116: ldc 233
    //   8118: aload_0
    //   8119: invokevirtual 235	com/tencent/luggage/wxa/oa/b:a	()Ljava/lang/String;
    //   8122: lconst_0
    //   8123: lload 7
    //   8125: iload 4
    //   8127: iconst_1
    //   8128: aload_0
    //   8129: invokevirtual 238	com/tencent/luggage/wxa/oa/b:e	()I
    //   8132: aload_0
    //   8133: getfield 78	com/tencent/luggage/wxa/oa/b:g	Ljava/lang/String;
    //   8136: aload_0
    //   8137: getfield 59	com/tencent/luggage/wxa/oa/b:i	Ljava/lang/String;
    //   8140: invokeinterface 241 14 0
    //   8145: goto +53 -> 8198
    //   8148: ldc 223
    //   8150: invokestatic 156	com/tencent/luggage/wxa/ba/e:b	(Ljava/lang/Class;)Lcom/tencent/luggage/wxa/ba/d;
    //   8153: checkcast 223	com/tencent/luggage/wxa/nz/o
    //   8156: aload_0
    //   8157: getfield 74	com/tencent/luggage/wxa/oa/b:a	Lcom/tencent/luggage/wxa/jx/c;
    //   8160: invokeinterface 229 1 0
    //   8165: aload_0
    //   8166: invokevirtual 231	com/tencent/luggage/wxa/oa/b:d	()Ljava/lang/String;
    //   8169: ldc 233
    //   8171: aload_0
    //   8172: invokevirtual 235	com/tencent/luggage/wxa/oa/b:a	()Ljava/lang/String;
    //   8175: lconst_0
    //   8176: lload 7
    //   8178: iload 4
    //   8180: iconst_1
    //   8181: aload_0
    //   8182: invokevirtual 238	com/tencent/luggage/wxa/oa/b:e	()I
    //   8185: aload_0
    //   8186: getfield 80	com/tencent/luggage/wxa/oa/b:h	Ljava/lang/String;
    //   8189: aload_0
    //   8190: getfield 59	com/tencent/luggage/wxa/oa/b:i	Ljava/lang/String;
    //   8193: invokeinterface 241 14 0
    //   8198: ldc 151
    //   8200: invokestatic 156	com/tencent/luggage/wxa/ba/e:b	(Ljava/lang/Class;)Lcom/tencent/luggage/wxa/ba/d;
    //   8203: checkcast 151	com/tencent/luggage/wxa/ot/c
    //   8206: ldc2_w 157
    //   8209: ldc2_w 513
    //   8212: lconst_1
    //   8213: iconst_0
    //   8214: invokeinterface 161 8 0
    //   8219: ldc 151
    //   8221: invokestatic 156	com/tencent/luggage/wxa/ba/e:b	(Ljava/lang/Class;)Lcom/tencent/luggage/wxa/ba/d;
    //   8224: checkcast 151	com/tencent/luggage/wxa/ot/c
    //   8227: ldc2_w 157
    //   8230: ldc2_w 515
    //   8233: invokestatic 88	java/lang/System:currentTimeMillis	()J
    //   8236: aload_0
    //   8237: getfield 243	com/tencent/luggage/wxa/oa/b:o	J
    //   8240: lsub
    //   8241: iconst_0
    //   8242: invokeinterface 161 8 0
    //   8247: goto +224 -> 8471
    //   8250: aload_0
    //   8251: getfield 80	com/tencent/luggage/wxa/oa/b:h	Ljava/lang/String;
    //   8254: invokestatic 124	com/tencent/luggage/wxa/qz/af:c	(Ljava/lang/String;)Z
    //   8257: ifeq +56 -> 8313
    //   8260: ldc 223
    //   8262: invokestatic 156	com/tencent/luggage/wxa/ba/e:b	(Ljava/lang/Class;)Lcom/tencent/luggage/wxa/ba/d;
    //   8265: checkcast 223	com/tencent/luggage/wxa/nz/o
    //   8268: aload_0
    //   8269: getfield 74	com/tencent/luggage/wxa/oa/b:a	Lcom/tencent/luggage/wxa/jx/c;
    //   8272: invokeinterface 229 1 0
    //   8277: aload_0
    //   8278: invokevirtual 231	com/tencent/luggage/wxa/oa/b:d	()Ljava/lang/String;
    //   8281: ldc 233
    //   8283: aload_0
    //   8284: invokevirtual 235	com/tencent/luggage/wxa/oa/b:a	()Ljava/lang/String;
    //   8287: lconst_0
    //   8288: lload 7
    //   8290: iload 4
    //   8292: iconst_2
    //   8293: aload_0
    //   8294: invokevirtual 238	com/tencent/luggage/wxa/oa/b:e	()I
    //   8297: aload_0
    //   8298: getfield 78	com/tencent/luggage/wxa/oa/b:g	Ljava/lang/String;
    //   8301: aload_0
    //   8302: getfield 59	com/tencent/luggage/wxa/oa/b:i	Ljava/lang/String;
    //   8305: invokeinterface 241 14 0
    //   8310: goto +53 -> 8363
    //   8313: ldc 223
    //   8315: invokestatic 156	com/tencent/luggage/wxa/ba/e:b	(Ljava/lang/Class;)Lcom/tencent/luggage/wxa/ba/d;
    //   8318: checkcast 223	com/tencent/luggage/wxa/nz/o
    //   8321: aload_0
    //   8322: getfield 74	com/tencent/luggage/wxa/oa/b:a	Lcom/tencent/luggage/wxa/jx/c;
    //   8325: invokeinterface 229 1 0
    //   8330: aload_0
    //   8331: invokevirtual 231	com/tencent/luggage/wxa/oa/b:d	()Ljava/lang/String;
    //   8334: ldc 233
    //   8336: aload_0
    //   8337: invokevirtual 235	com/tencent/luggage/wxa/oa/b:a	()Ljava/lang/String;
    //   8340: lconst_0
    //   8341: lload 7
    //   8343: iload 4
    //   8345: iconst_2
    //   8346: aload_0
    //   8347: invokevirtual 238	com/tencent/luggage/wxa/oa/b:e	()I
    //   8350: aload_0
    //   8351: getfield 80	com/tencent/luggage/wxa/oa/b:h	Ljava/lang/String;
    //   8354: aload_0
    //   8355: getfield 59	com/tencent/luggage/wxa/oa/b:i	Ljava/lang/String;
    //   8358: invokeinterface 241 14 0
    //   8363: ldc 151
    //   8365: invokestatic 156	com/tencent/luggage/wxa/ba/e:b	(Ljava/lang/Class;)Lcom/tencent/luggage/wxa/ba/d;
    //   8368: checkcast 151	com/tencent/luggage/wxa/ot/c
    //   8371: ldc2_w 157
    //   8374: ldc2_w 530
    //   8377: lconst_1
    //   8378: iconst_0
    //   8379: invokeinterface 161 8 0
    //   8384: ldc 151
    //   8386: invokestatic 156	com/tencent/luggage/wxa/ba/e:b	(Ljava/lang/Class;)Lcom/tencent/luggage/wxa/ba/d;
    //   8389: checkcast 151	com/tencent/luggage/wxa/ot/c
    //   8392: ldc2_w 157
    //   8395: ldc2_w 532
    //   8398: invokestatic 88	java/lang/System:currentTimeMillis	()J
    //   8401: aload_0
    //   8402: getfield 243	com/tencent/luggage/wxa/oa/b:o	J
    //   8405: lsub
    //   8406: iconst_0
    //   8407: invokeinterface 161 8 0
    //   8412: invokestatic 138	com/tencent/luggage/wxa/qz/r:a	()Landroid/content/Context;
    //   8415: invokestatic 536	com/tencent/luggage/wxa/qz/x:d	(Landroid/content/Context;)I
    //   8418: istore_1
    //   8419: iload_1
    //   8420: iconst_m1
    //   8421: if_icmpne +24 -> 8445
    //   8424: ldc 151
    //   8426: invokestatic 156	com/tencent/luggage/wxa/ba/e:b	(Ljava/lang/Class;)Lcom/tencent/luggage/wxa/ba/d;
    //   8429: checkcast 151	com/tencent/luggage/wxa/ot/c
    //   8432: ldc2_w 157
    //   8435: ldc2_w 537
    //   8438: lconst_1
    //   8439: iconst_0
    //   8440: invokeinterface 161 8 0
    //   8445: ldc 163
    //   8447: ldc_w 540
    //   8450: iconst_2
    //   8451: anewarray 4	java/lang/Object
    //   8454: dup
    //   8455: iconst_0
    //   8456: aload_0
    //   8457: getfield 250	com/tencent/luggage/wxa/oa/b:p	Ljava/lang/String;
    //   8460: aastore
    //   8461: dup
    //   8462: iconst_1
    //   8463: iload_1
    //   8464: invokestatic 179	java/lang/Integer:valueOf	(I)Ljava/lang/Integer;
    //   8467: aastore
    //   8468: invokestatic 184	com/tencent/luggage/wxa/qz/o:d	(Ljava/lang/String;Ljava/lang/String;[Ljava/lang/Object;)V
    //   8471: aload 16
    //   8473: ifnull +41 -> 8514
    //   8476: aload 16
    //   8478: invokevirtual 634	java/io/OutputStream:close	()V
    //   8481: goto +33 -> 8514
    //   8484: astore 12
    //   8486: ldc 163
    //   8488: aload 12
    //   8490: ldc_w 603
    //   8493: iconst_2
    //   8494: anewarray 4	java/lang/Object
    //   8497: dup
    //   8498: iconst_0
    //   8499: aload_0
    //   8500: getfield 76	com/tencent/luggage/wxa/oa/b:f	Ljava/lang/String;
    //   8503: aastore
    //   8504: dup
    //   8505: iconst_1
    //   8506: aload_0
    //   8507: getfield 78	com/tencent/luggage/wxa/oa/b:g	Ljava/lang/String;
    //   8510: aastore
    //   8511: invokestatic 578	com/tencent/luggage/wxa/qz/o:a	(Ljava/lang/String;Ljava/lang/Throwable;Ljava/lang/String;[Ljava/lang/Object;)V
    //   8514: aload 19
    //   8516: ifnull +105 -> 8621
    //   8519: aload 19
    //   8521: invokevirtual 601	java/io/InputStream:close	()V
    //   8524: goto +97 -> 8621
    //   8527: astore 12
    //   8529: ldc 163
    //   8531: aload 12
    //   8533: aload 17
    //   8535: iconst_2
    //   8536: anewarray 4	java/lang/Object
    //   8539: dup
    //   8540: iconst_0
    //   8541: aload_0
    //   8542: getfield 76	com/tencent/luggage/wxa/oa/b:f	Ljava/lang/String;
    //   8545: aastore
    //   8546: dup
    //   8547: iconst_1
    //   8548: aload_0
    //   8549: getfield 78	com/tencent/luggage/wxa/oa/b:g	Ljava/lang/String;
    //   8552: aastore
    //   8553: invokestatic 578	com/tencent/luggage/wxa/qz/o:a	(Ljava/lang/String;Ljava/lang/Throwable;Ljava/lang/String;[Ljava/lang/Object;)V
    //   8556: goto +65 -> 8621
    //   8559: astore 12
    //   8561: ldc 163
    //   8563: aload 12
    //   8565: aload 18
    //   8567: iconst_2
    //   8568: anewarray 4	java/lang/Object
    //   8571: dup
    //   8572: iconst_0
    //   8573: aload_0
    //   8574: getfield 76	com/tencent/luggage/wxa/oa/b:f	Ljava/lang/String;
    //   8577: aastore
    //   8578: dup
    //   8579: iconst_1
    //   8580: aload_0
    //   8581: getfield 78	com/tencent/luggage/wxa/oa/b:g	Ljava/lang/String;
    //   8584: aastore
    //   8585: invokestatic 578	com/tencent/luggage/wxa/qz/o:a	(Ljava/lang/String;Ljava/lang/Throwable;Ljava/lang/String;[Ljava/lang/Object;)V
    //   8588: goto +33 -> 8621
    //   8591: astore 12
    //   8593: ldc 163
    //   8595: aload 12
    //   8597: ldc_w 603
    //   8600: iconst_2
    //   8601: anewarray 4	java/lang/Object
    //   8604: dup
    //   8605: iconst_0
    //   8606: aload_0
    //   8607: getfield 76	com/tencent/luggage/wxa/oa/b:f	Ljava/lang/String;
    //   8610: aastore
    //   8611: dup
    //   8612: iconst_1
    //   8613: aload_0
    //   8614: getfield 78	com/tencent/luggage/wxa/oa/b:g	Ljava/lang/String;
    //   8617: aastore
    //   8618: invokestatic 578	com/tencent/luggage/wxa/qz/o:a	(Ljava/lang/String;Ljava/lang/Throwable;Ljava/lang/String;[Ljava/lang/Object;)V
    //   8621: aload_0
    //   8622: invokevirtual 518	com/tencent/luggage/wxa/oa/b:b	()V
    //   8625: aload_0
    //   8626: getfield 82	com/tencent/luggage/wxa/oa/b:c	Lcom/tencent/luggage/wxa/oa/a;
    //   8629: aload_0
    //   8630: invokevirtual 520	com/tencent/luggage/wxa/oa/b:c	()Ljava/lang/String;
    //   8633: invokeinterface 522 2 0
    //   8638: ldc 163
    //   8640: ldc_w 524
    //   8643: iconst_2
    //   8644: anewarray 4	java/lang/Object
    //   8647: dup
    //   8648: iconst_0
    //   8649: aload_0
    //   8650: getfield 250	com/tencent/luggage/wxa/oa/b:p	Ljava/lang/String;
    //   8653: aastore
    //   8654: dup
    //   8655: iconst_1
    //   8656: aload_0
    //   8657: getfield 76	com/tencent/luggage/wxa/oa/b:f	Ljava/lang/String;
    //   8660: aastore
    //   8661: invokestatic 184	com/tencent/luggage/wxa/qz/o:d	(Ljava/lang/String;Ljava/lang/String;[Ljava/lang/Object;)V
    //   8664: return
    //   8665: astore 20
    //   8667: lconst_0
    //   8668: lstore 7
    //   8670: aconst_null
    //   8671: astore 19
    //   8673: ldc_w 383
    //   8676: astore 18
    //   8678: iconst_0
    //   8679: istore_3
    //   8680: ldc_w 381
    //   8683: astore 17
    //   8685: aconst_null
    //   8686: astore 16
    //   8688: iconst_0
    //   8689: istore 4
    //   8691: aload 16
    //   8693: astore 14
    //   8695: aload 17
    //   8697: astore 12
    //   8699: iload_3
    //   8700: istore_1
    //   8701: aload 18
    //   8703: astore 13
    //   8705: aload 19
    //   8707: astore 15
    //   8709: lload 7
    //   8711: lstore 5
    //   8713: iload 4
    //   8715: istore_2
    //   8716: ldc 151
    //   8718: invokestatic 156	com/tencent/luggage/wxa/ba/e:b	(Ljava/lang/Class;)Lcom/tencent/luggage/wxa/ba/d;
    //   8721: checkcast 151	com/tencent/luggage/wxa/ot/c
    //   8724: ldc2_w 157
    //   8727: ldc2_w 712
    //   8730: lconst_1
    //   8731: iconst_0
    //   8732: invokeinterface 161 8 0
    //   8737: aload 16
    //   8739: astore 14
    //   8741: aload 17
    //   8743: astore 12
    //   8745: iload_3
    //   8746: istore_1
    //   8747: aload 18
    //   8749: astore 13
    //   8751: aload 19
    //   8753: astore 15
    //   8755: lload 7
    //   8757: lstore 5
    //   8759: iload 4
    //   8761: istore_2
    //   8762: ldc 163
    //   8764: aload 20
    //   8766: ldc_w 715
    //   8769: iconst_2
    //   8770: anewarray 4	java/lang/Object
    //   8773: dup
    //   8774: iconst_0
    //   8775: aload_0
    //   8776: getfield 76	com/tencent/luggage/wxa/oa/b:f	Ljava/lang/String;
    //   8779: aastore
    //   8780: dup
    //   8781: iconst_1
    //   8782: aload_0
    //   8783: getfield 78	com/tencent/luggage/wxa/oa/b:g	Ljava/lang/String;
    //   8786: aastore
    //   8787: invokestatic 578	com/tencent/luggage/wxa/qz/o:a	(Ljava/lang/String;Ljava/lang/Throwable;Ljava/lang/String;[Ljava/lang/Object;)V
    //   8790: aload 16
    //   8792: astore 14
    //   8794: aload 17
    //   8796: astore 12
    //   8798: iload_3
    //   8799: istore_1
    //   8800: aload 18
    //   8802: astore 13
    //   8804: aload 19
    //   8806: astore 15
    //   8808: lload 7
    //   8810: lstore 5
    //   8812: iload 4
    //   8814: istore_2
    //   8815: aload_0
    //   8816: getfield 82	com/tencent/luggage/wxa/oa/b:c	Lcom/tencent/luggage/wxa/oa/a;
    //   8819: aload_0
    //   8820: getfield 78	com/tencent/luggage/wxa/oa/b:g	Ljava/lang/String;
    //   8823: aload_0
    //   8824: getfield 76	com/tencent/luggage/wxa/oa/b:f	Ljava/lang/String;
    //   8827: ldc_w 717
    //   8830: invokeinterface 221 4 0
    //   8835: iload_3
    //   8836: ifeq +168 -> 9004
    //   8839: aload_0
    //   8840: getfield 80	com/tencent/luggage/wxa/oa/b:h	Ljava/lang/String;
    //   8843: invokestatic 124	com/tencent/luggage/wxa/qz/af:c	(Ljava/lang/String;)Z
    //   8846: ifeq +56 -> 8902
    //   8849: ldc 223
    //   8851: invokestatic 156	com/tencent/luggage/wxa/ba/e:b	(Ljava/lang/Class;)Lcom/tencent/luggage/wxa/ba/d;
    //   8854: checkcast 223	com/tencent/luggage/wxa/nz/o
    //   8857: aload_0
    //   8858: getfield 74	com/tencent/luggage/wxa/oa/b:a	Lcom/tencent/luggage/wxa/jx/c;
    //   8861: invokeinterface 229 1 0
    //   8866: aload_0
    //   8867: invokevirtual 231	com/tencent/luggage/wxa/oa/b:d	()Ljava/lang/String;
    //   8870: ldc 233
    //   8872: aload_0
    //   8873: invokevirtual 235	com/tencent/luggage/wxa/oa/b:a	()Ljava/lang/String;
    //   8876: lconst_0
    //   8877: lload 7
    //   8879: iload 4
    //   8881: iconst_1
    //   8882: aload_0
    //   8883: invokevirtual 238	com/tencent/luggage/wxa/oa/b:e	()I
    //   8886: aload_0
    //   8887: getfield 78	com/tencent/luggage/wxa/oa/b:g	Ljava/lang/String;
    //   8890: aload_0
    //   8891: getfield 59	com/tencent/luggage/wxa/oa/b:i	Ljava/lang/String;
    //   8894: invokeinterface 241 14 0
    //   8899: goto +53 -> 8952
    //   8902: ldc 223
    //   8904: invokestatic 156	com/tencent/luggage/wxa/ba/e:b	(Ljava/lang/Class;)Lcom/tencent/luggage/wxa/ba/d;
    //   8907: checkcast 223	com/tencent/luggage/wxa/nz/o
    //   8910: aload_0
    //   8911: getfield 74	com/tencent/luggage/wxa/oa/b:a	Lcom/tencent/luggage/wxa/jx/c;
    //   8914: invokeinterface 229 1 0
    //   8919: aload_0
    //   8920: invokevirtual 231	com/tencent/luggage/wxa/oa/b:d	()Ljava/lang/String;
    //   8923: ldc 233
    //   8925: aload_0
    //   8926: invokevirtual 235	com/tencent/luggage/wxa/oa/b:a	()Ljava/lang/String;
    //   8929: lconst_0
    //   8930: lload 7
    //   8932: iload 4
    //   8934: iconst_1
    //   8935: aload_0
    //   8936: invokevirtual 238	com/tencent/luggage/wxa/oa/b:e	()I
    //   8939: aload_0
    //   8940: getfield 80	com/tencent/luggage/wxa/oa/b:h	Ljava/lang/String;
    //   8943: aload_0
    //   8944: getfield 59	com/tencent/luggage/wxa/oa/b:i	Ljava/lang/String;
    //   8947: invokeinterface 241 14 0
    //   8952: ldc 151
    //   8954: invokestatic 156	com/tencent/luggage/wxa/ba/e:b	(Ljava/lang/Class;)Lcom/tencent/luggage/wxa/ba/d;
    //   8957: checkcast 151	com/tencent/luggage/wxa/ot/c
    //   8960: ldc2_w 157
    //   8963: ldc2_w 513
    //   8966: lconst_1
    //   8967: iconst_0
    //   8968: invokeinterface 161 8 0
    //   8973: ldc 151
    //   8975: invokestatic 156	com/tencent/luggage/wxa/ba/e:b	(Ljava/lang/Class;)Lcom/tencent/luggage/wxa/ba/d;
    //   8978: checkcast 151	com/tencent/luggage/wxa/ot/c
    //   8981: ldc2_w 157
    //   8984: ldc2_w 515
    //   8987: invokestatic 88	java/lang/System:currentTimeMillis	()J
    //   8990: aload_0
    //   8991: getfield 243	com/tencent/luggage/wxa/oa/b:o	J
    //   8994: lsub
    //   8995: iconst_0
    //   8996: invokeinterface 161 8 0
    //   9001: goto +224 -> 9225
    //   9004: aload_0
    //   9005: getfield 80	com/tencent/luggage/wxa/oa/b:h	Ljava/lang/String;
    //   9008: invokestatic 124	com/tencent/luggage/wxa/qz/af:c	(Ljava/lang/String;)Z
    //   9011: ifeq +56 -> 9067
    //   9014: ldc 223
    //   9016: invokestatic 156	com/tencent/luggage/wxa/ba/e:b	(Ljava/lang/Class;)Lcom/tencent/luggage/wxa/ba/d;
    //   9019: checkcast 223	com/tencent/luggage/wxa/nz/o
    //   9022: aload_0
    //   9023: getfield 74	com/tencent/luggage/wxa/oa/b:a	Lcom/tencent/luggage/wxa/jx/c;
    //   9026: invokeinterface 229 1 0
    //   9031: aload_0
    //   9032: invokevirtual 231	com/tencent/luggage/wxa/oa/b:d	()Ljava/lang/String;
    //   9035: ldc 233
    //   9037: aload_0
    //   9038: invokevirtual 235	com/tencent/luggage/wxa/oa/b:a	()Ljava/lang/String;
    //   9041: lconst_0
    //   9042: lload 7
    //   9044: iload 4
    //   9046: iconst_2
    //   9047: aload_0
    //   9048: invokevirtual 238	com/tencent/luggage/wxa/oa/b:e	()I
    //   9051: aload_0
    //   9052: getfield 78	com/tencent/luggage/wxa/oa/b:g	Ljava/lang/String;
    //   9055: aload_0
    //   9056: getfield 59	com/tencent/luggage/wxa/oa/b:i	Ljava/lang/String;
    //   9059: invokeinterface 241 14 0
    //   9064: goto +53 -> 9117
    //   9067: ldc 223
    //   9069: invokestatic 156	com/tencent/luggage/wxa/ba/e:b	(Ljava/lang/Class;)Lcom/tencent/luggage/wxa/ba/d;
    //   9072: checkcast 223	com/tencent/luggage/wxa/nz/o
    //   9075: aload_0
    //   9076: getfield 74	com/tencent/luggage/wxa/oa/b:a	Lcom/tencent/luggage/wxa/jx/c;
    //   9079: invokeinterface 229 1 0
    //   9084: aload_0
    //   9085: invokevirtual 231	com/tencent/luggage/wxa/oa/b:d	()Ljava/lang/String;
    //   9088: ldc 233
    //   9090: aload_0
    //   9091: invokevirtual 235	com/tencent/luggage/wxa/oa/b:a	()Ljava/lang/String;
    //   9094: lconst_0
    //   9095: lload 7
    //   9097: iload 4
    //   9099: iconst_2
    //   9100: aload_0
    //   9101: invokevirtual 238	com/tencent/luggage/wxa/oa/b:e	()I
    //   9104: aload_0
    //   9105: getfield 80	com/tencent/luggage/wxa/oa/b:h	Ljava/lang/String;
    //   9108: aload_0
    //   9109: getfield 59	com/tencent/luggage/wxa/oa/b:i	Ljava/lang/String;
    //   9112: invokeinterface 241 14 0
    //   9117: ldc 151
    //   9119: invokestatic 156	com/tencent/luggage/wxa/ba/e:b	(Ljava/lang/Class;)Lcom/tencent/luggage/wxa/ba/d;
    //   9122: checkcast 151	com/tencent/luggage/wxa/ot/c
    //   9125: ldc2_w 157
    //   9128: ldc2_w 530
    //   9131: lconst_1
    //   9132: iconst_0
    //   9133: invokeinterface 161 8 0
    //   9138: ldc 151
    //   9140: invokestatic 156	com/tencent/luggage/wxa/ba/e:b	(Ljava/lang/Class;)Lcom/tencent/luggage/wxa/ba/d;
    //   9143: checkcast 151	com/tencent/luggage/wxa/ot/c
    //   9146: ldc2_w 157
    //   9149: ldc2_w 532
    //   9152: invokestatic 88	java/lang/System:currentTimeMillis	()J
    //   9155: aload_0
    //   9156: getfield 243	com/tencent/luggage/wxa/oa/b:o	J
    //   9159: lsub
    //   9160: iconst_0
    //   9161: invokeinterface 161 8 0
    //   9166: invokestatic 138	com/tencent/luggage/wxa/qz/r:a	()Landroid/content/Context;
    //   9169: invokestatic 536	com/tencent/luggage/wxa/qz/x:d	(Landroid/content/Context;)I
    //   9172: istore_1
    //   9173: iload_1
    //   9174: iconst_m1
    //   9175: if_icmpne +24 -> 9199
    //   9178: ldc 151
    //   9180: invokestatic 156	com/tencent/luggage/wxa/ba/e:b	(Ljava/lang/Class;)Lcom/tencent/luggage/wxa/ba/d;
    //   9183: checkcast 151	com/tencent/luggage/wxa/ot/c
    //   9186: ldc2_w 157
    //   9189: ldc2_w 537
    //   9192: lconst_1
    //   9193: iconst_0
    //   9194: invokeinterface 161 8 0
    //   9199: ldc 163
    //   9201: ldc_w 540
    //   9204: iconst_2
    //   9205: anewarray 4	java/lang/Object
    //   9208: dup
    //   9209: iconst_0
    //   9210: aload_0
    //   9211: getfield 250	com/tencent/luggage/wxa/oa/b:p	Ljava/lang/String;
    //   9214: aastore
    //   9215: dup
    //   9216: iconst_1
    //   9217: iload_1
    //   9218: invokestatic 179	java/lang/Integer:valueOf	(I)Ljava/lang/Integer;
    //   9221: aastore
    //   9222: invokestatic 184	com/tencent/luggage/wxa/qz/o:d	(Ljava/lang/String;Ljava/lang/String;[Ljava/lang/Object;)V
    //   9225: aload 16
    //   9227: ifnull +41 -> 9268
    //   9230: aload 16
    //   9232: invokevirtual 634	java/io/OutputStream:close	()V
    //   9235: goto +33 -> 9268
    //   9238: astore 12
    //   9240: ldc 163
    //   9242: aload 12
    //   9244: ldc_w 603
    //   9247: iconst_2
    //   9248: anewarray 4	java/lang/Object
    //   9251: dup
    //   9252: iconst_0
    //   9253: aload_0
    //   9254: getfield 76	com/tencent/luggage/wxa/oa/b:f	Ljava/lang/String;
    //   9257: aastore
    //   9258: dup
    //   9259: iconst_1
    //   9260: aload_0
    //   9261: getfield 78	com/tencent/luggage/wxa/oa/b:g	Ljava/lang/String;
    //   9264: aastore
    //   9265: invokestatic 578	com/tencent/luggage/wxa/qz/o:a	(Ljava/lang/String;Ljava/lang/Throwable;Ljava/lang/String;[Ljava/lang/Object;)V
    //   9268: aload 19
    //   9270: ifnull +105 -> 9375
    //   9273: aload 19
    //   9275: invokevirtual 601	java/io/InputStream:close	()V
    //   9278: goto +97 -> 9375
    //   9281: astore 12
    //   9283: ldc 163
    //   9285: aload 12
    //   9287: aload 17
    //   9289: iconst_2
    //   9290: anewarray 4	java/lang/Object
    //   9293: dup
    //   9294: iconst_0
    //   9295: aload_0
    //   9296: getfield 76	com/tencent/luggage/wxa/oa/b:f	Ljava/lang/String;
    //   9299: aastore
    //   9300: dup
    //   9301: iconst_1
    //   9302: aload_0
    //   9303: getfield 78	com/tencent/luggage/wxa/oa/b:g	Ljava/lang/String;
    //   9306: aastore
    //   9307: invokestatic 578	com/tencent/luggage/wxa/qz/o:a	(Ljava/lang/String;Ljava/lang/Throwable;Ljava/lang/String;[Ljava/lang/Object;)V
    //   9310: goto +65 -> 9375
    //   9313: astore 12
    //   9315: ldc 163
    //   9317: aload 12
    //   9319: aload 18
    //   9321: iconst_2
    //   9322: anewarray 4	java/lang/Object
    //   9325: dup
    //   9326: iconst_0
    //   9327: aload_0
    //   9328: getfield 76	com/tencent/luggage/wxa/oa/b:f	Ljava/lang/String;
    //   9331: aastore
    //   9332: dup
    //   9333: iconst_1
    //   9334: aload_0
    //   9335: getfield 78	com/tencent/luggage/wxa/oa/b:g	Ljava/lang/String;
    //   9338: aastore
    //   9339: invokestatic 578	com/tencent/luggage/wxa/qz/o:a	(Ljava/lang/String;Ljava/lang/Throwable;Ljava/lang/String;[Ljava/lang/Object;)V
    //   9342: goto +33 -> 9375
    //   9345: astore 12
    //   9347: ldc 163
    //   9349: aload 12
    //   9351: ldc_w 603
    //   9354: iconst_2
    //   9355: anewarray 4	java/lang/Object
    //   9358: dup
    //   9359: iconst_0
    //   9360: aload_0
    //   9361: getfield 76	com/tencent/luggage/wxa/oa/b:f	Ljava/lang/String;
    //   9364: aastore
    //   9365: dup
    //   9366: iconst_1
    //   9367: aload_0
    //   9368: getfield 78	com/tencent/luggage/wxa/oa/b:g	Ljava/lang/String;
    //   9371: aastore
    //   9372: invokestatic 578	com/tencent/luggage/wxa/qz/o:a	(Ljava/lang/String;Ljava/lang/Throwable;Ljava/lang/String;[Ljava/lang/Object;)V
    //   9375: aload_0
    //   9376: invokevirtual 518	com/tencent/luggage/wxa/oa/b:b	()V
    //   9379: aload_0
    //   9380: getfield 82	com/tencent/luggage/wxa/oa/b:c	Lcom/tencent/luggage/wxa/oa/a;
    //   9383: aload_0
    //   9384: invokevirtual 520	com/tencent/luggage/wxa/oa/b:c	()Ljava/lang/String;
    //   9387: invokeinterface 522 2 0
    //   9392: ldc 163
    //   9394: ldc_w 524
    //   9397: iconst_2
    //   9398: anewarray 4	java/lang/Object
    //   9401: dup
    //   9402: iconst_0
    //   9403: aload_0
    //   9404: getfield 250	com/tencent/luggage/wxa/oa/b:p	Ljava/lang/String;
    //   9407: aastore
    //   9408: dup
    //   9409: iconst_1
    //   9410: aload_0
    //   9411: getfield 76	com/tencent/luggage/wxa/oa/b:f	Ljava/lang/String;
    //   9414: aastore
    //   9415: invokestatic 184	com/tencent/luggage/wxa/qz/o:d	(Ljava/lang/String;Ljava/lang/String;[Ljava/lang/Object;)V
    //   9418: return
    //   9419: astore 20
    //   9421: lconst_0
    //   9422: lstore 7
    //   9424: aconst_null
    //   9425: astore 19
    //   9427: ldc_w 383
    //   9430: astore 18
    //   9432: iconst_0
    //   9433: istore_3
    //   9434: ldc_w 381
    //   9437: astore 17
    //   9439: aconst_null
    //   9440: astore 16
    //   9442: iconst_0
    //   9443: istore 4
    //   9445: aload 16
    //   9447: astore 14
    //   9449: aload 17
    //   9451: astore 12
    //   9453: iload_3
    //   9454: istore_1
    //   9455: aload 18
    //   9457: astore 13
    //   9459: aload 19
    //   9461: astore 15
    //   9463: lload 7
    //   9465: lstore 5
    //   9467: iload 4
    //   9469: istore_2
    //   9470: ldc 151
    //   9472: invokestatic 156	com/tencent/luggage/wxa/ba/e:b	(Ljava/lang/Class;)Lcom/tencent/luggage/wxa/ba/d;
    //   9475: checkcast 151	com/tencent/luggage/wxa/ot/c
    //   9478: ldc2_w 157
    //   9481: lconst_1
    //   9482: lconst_1
    //   9483: iconst_0
    //   9484: invokeinterface 161 8 0
    //   9489: aload 16
    //   9491: astore 14
    //   9493: aload 17
    //   9495: astore 12
    //   9497: iload_3
    //   9498: istore_1
    //   9499: aload 18
    //   9501: astore 13
    //   9503: aload 19
    //   9505: astore 15
    //   9507: lload 7
    //   9509: lstore 5
    //   9511: iload 4
    //   9513: istore_2
    //   9514: ldc 163
    //   9516: aload 20
    //   9518: ldc_w 719
    //   9521: iconst_2
    //   9522: anewarray 4	java/lang/Object
    //   9525: dup
    //   9526: iconst_0
    //   9527: aload_0
    //   9528: getfield 76	com/tencent/luggage/wxa/oa/b:f	Ljava/lang/String;
    //   9531: aastore
    //   9532: dup
    //   9533: iconst_1
    //   9534: aload_0
    //   9535: getfield 78	com/tencent/luggage/wxa/oa/b:g	Ljava/lang/String;
    //   9538: aastore
    //   9539: invokestatic 578	com/tencent/luggage/wxa/qz/o:a	(Ljava/lang/String;Ljava/lang/Throwable;Ljava/lang/String;[Ljava/lang/Object;)V
    //   9542: aload 16
    //   9544: astore 14
    //   9546: aload 17
    //   9548: astore 12
    //   9550: iload_3
    //   9551: istore_1
    //   9552: aload 18
    //   9554: astore 13
    //   9556: aload 19
    //   9558: astore 15
    //   9560: lload 7
    //   9562: lstore 5
    //   9564: iload 4
    //   9566: istore_2
    //   9567: aload_0
    //   9568: getfield 82	com/tencent/luggage/wxa/oa/b:c	Lcom/tencent/luggage/wxa/oa/a;
    //   9571: aload_0
    //   9572: getfield 78	com/tencent/luggage/wxa/oa/b:g	Ljava/lang/String;
    //   9575: aload_0
    //   9576: getfield 76	com/tencent/luggage/wxa/oa/b:f	Ljava/lang/String;
    //   9579: ldc_w 721
    //   9582: invokeinterface 221 4 0
    //   9587: iload_3
    //   9588: ifeq +168 -> 9756
    //   9591: aload_0
    //   9592: getfield 80	com/tencent/luggage/wxa/oa/b:h	Ljava/lang/String;
    //   9595: invokestatic 124	com/tencent/luggage/wxa/qz/af:c	(Ljava/lang/String;)Z
    //   9598: ifeq +56 -> 9654
    //   9601: ldc 223
    //   9603: invokestatic 156	com/tencent/luggage/wxa/ba/e:b	(Ljava/lang/Class;)Lcom/tencent/luggage/wxa/ba/d;
    //   9606: checkcast 223	com/tencent/luggage/wxa/nz/o
    //   9609: aload_0
    //   9610: getfield 74	com/tencent/luggage/wxa/oa/b:a	Lcom/tencent/luggage/wxa/jx/c;
    //   9613: invokeinterface 229 1 0
    //   9618: aload_0
    //   9619: invokevirtual 231	com/tencent/luggage/wxa/oa/b:d	()Ljava/lang/String;
    //   9622: ldc 233
    //   9624: aload_0
    //   9625: invokevirtual 235	com/tencent/luggage/wxa/oa/b:a	()Ljava/lang/String;
    //   9628: lconst_0
    //   9629: lload 7
    //   9631: iload 4
    //   9633: iconst_1
    //   9634: aload_0
    //   9635: invokevirtual 238	com/tencent/luggage/wxa/oa/b:e	()I
    //   9638: aload_0
    //   9639: getfield 78	com/tencent/luggage/wxa/oa/b:g	Ljava/lang/String;
    //   9642: aload_0
    //   9643: getfield 59	com/tencent/luggage/wxa/oa/b:i	Ljava/lang/String;
    //   9646: invokeinterface 241 14 0
    //   9651: goto +53 -> 9704
    //   9654: ldc 223
    //   9656: invokestatic 156	com/tencent/luggage/wxa/ba/e:b	(Ljava/lang/Class;)Lcom/tencent/luggage/wxa/ba/d;
    //   9659: checkcast 223	com/tencent/luggage/wxa/nz/o
    //   9662: aload_0
    //   9663: getfield 74	com/tencent/luggage/wxa/oa/b:a	Lcom/tencent/luggage/wxa/jx/c;
    //   9666: invokeinterface 229 1 0
    //   9671: aload_0
    //   9672: invokevirtual 231	com/tencent/luggage/wxa/oa/b:d	()Ljava/lang/String;
    //   9675: ldc 233
    //   9677: aload_0
    //   9678: invokevirtual 235	com/tencent/luggage/wxa/oa/b:a	()Ljava/lang/String;
    //   9681: lconst_0
    //   9682: lload 7
    //   9684: iload 4
    //   9686: iconst_1
    //   9687: aload_0
    //   9688: invokevirtual 238	com/tencent/luggage/wxa/oa/b:e	()I
    //   9691: aload_0
    //   9692: getfield 80	com/tencent/luggage/wxa/oa/b:h	Ljava/lang/String;
    //   9695: aload_0
    //   9696: getfield 59	com/tencent/luggage/wxa/oa/b:i	Ljava/lang/String;
    //   9699: invokeinterface 241 14 0
    //   9704: ldc 151
    //   9706: invokestatic 156	com/tencent/luggage/wxa/ba/e:b	(Ljava/lang/Class;)Lcom/tencent/luggage/wxa/ba/d;
    //   9709: checkcast 151	com/tencent/luggage/wxa/ot/c
    //   9712: ldc2_w 157
    //   9715: ldc2_w 513
    //   9718: lconst_1
    //   9719: iconst_0
    //   9720: invokeinterface 161 8 0
    //   9725: ldc 151
    //   9727: invokestatic 156	com/tencent/luggage/wxa/ba/e:b	(Ljava/lang/Class;)Lcom/tencent/luggage/wxa/ba/d;
    //   9730: checkcast 151	com/tencent/luggage/wxa/ot/c
    //   9733: ldc2_w 157
    //   9736: ldc2_w 515
    //   9739: invokestatic 88	java/lang/System:currentTimeMillis	()J
    //   9742: aload_0
    //   9743: getfield 243	com/tencent/luggage/wxa/oa/b:o	J
    //   9746: lsub
    //   9747: iconst_0
    //   9748: invokeinterface 161 8 0
    //   9753: goto +224 -> 9977
    //   9756: aload_0
    //   9757: getfield 80	com/tencent/luggage/wxa/oa/b:h	Ljava/lang/String;
    //   9760: invokestatic 124	com/tencent/luggage/wxa/qz/af:c	(Ljava/lang/String;)Z
    //   9763: ifeq +56 -> 9819
    //   9766: ldc 223
    //   9768: invokestatic 156	com/tencent/luggage/wxa/ba/e:b	(Ljava/lang/Class;)Lcom/tencent/luggage/wxa/ba/d;
    //   9771: checkcast 223	com/tencent/luggage/wxa/nz/o
    //   9774: aload_0
    //   9775: getfield 74	com/tencent/luggage/wxa/oa/b:a	Lcom/tencent/luggage/wxa/jx/c;
    //   9778: invokeinterface 229 1 0
    //   9783: aload_0
    //   9784: invokevirtual 231	com/tencent/luggage/wxa/oa/b:d	()Ljava/lang/String;
    //   9787: ldc 233
    //   9789: aload_0
    //   9790: invokevirtual 235	com/tencent/luggage/wxa/oa/b:a	()Ljava/lang/String;
    //   9793: lconst_0
    //   9794: lload 7
    //   9796: iload 4
    //   9798: iconst_2
    //   9799: aload_0
    //   9800: invokevirtual 238	com/tencent/luggage/wxa/oa/b:e	()I
    //   9803: aload_0
    //   9804: getfield 78	com/tencent/luggage/wxa/oa/b:g	Ljava/lang/String;
    //   9807: aload_0
    //   9808: getfield 59	com/tencent/luggage/wxa/oa/b:i	Ljava/lang/String;
    //   9811: invokeinterface 241 14 0
    //   9816: goto +53 -> 9869
    //   9819: ldc 223
    //   9821: invokestatic 156	com/tencent/luggage/wxa/ba/e:b	(Ljava/lang/Class;)Lcom/tencent/luggage/wxa/ba/d;
    //   9824: checkcast 223	com/tencent/luggage/wxa/nz/o
    //   9827: aload_0
    //   9828: getfield 74	com/tencent/luggage/wxa/oa/b:a	Lcom/tencent/luggage/wxa/jx/c;
    //   9831: invokeinterface 229 1 0
    //   9836: aload_0
    //   9837: invokevirtual 231	com/tencent/luggage/wxa/oa/b:d	()Ljava/lang/String;
    //   9840: ldc 233
    //   9842: aload_0
    //   9843: invokevirtual 235	com/tencent/luggage/wxa/oa/b:a	()Ljava/lang/String;
    //   9846: lconst_0
    //   9847: lload 7
    //   9849: iload 4
    //   9851: iconst_2
    //   9852: aload_0
    //   9853: invokevirtual 238	com/tencent/luggage/wxa/oa/b:e	()I
    //   9856: aload_0
    //   9857: getfield 80	com/tencent/luggage/wxa/oa/b:h	Ljava/lang/String;
    //   9860: aload_0
    //   9861: getfield 59	com/tencent/luggage/wxa/oa/b:i	Ljava/lang/String;
    //   9864: invokeinterface 241 14 0
    //   9869: ldc 151
    //   9871: invokestatic 156	com/tencent/luggage/wxa/ba/e:b	(Ljava/lang/Class;)Lcom/tencent/luggage/wxa/ba/d;
    //   9874: checkcast 151	com/tencent/luggage/wxa/ot/c
    //   9877: ldc2_w 157
    //   9880: ldc2_w 530
    //   9883: lconst_1
    //   9884: iconst_0
    //   9885: invokeinterface 161 8 0
    //   9890: ldc 151
    //   9892: invokestatic 156	com/tencent/luggage/wxa/ba/e:b	(Ljava/lang/Class;)Lcom/tencent/luggage/wxa/ba/d;
    //   9895: checkcast 151	com/tencent/luggage/wxa/ot/c
    //   9898: ldc2_w 157
    //   9901: ldc2_w 532
    //   9904: invokestatic 88	java/lang/System:currentTimeMillis	()J
    //   9907: aload_0
    //   9908: getfield 243	com/tencent/luggage/wxa/oa/b:o	J
    //   9911: lsub
    //   9912: iconst_0
    //   9913: invokeinterface 161 8 0
    //   9918: invokestatic 138	com/tencent/luggage/wxa/qz/r:a	()Landroid/content/Context;
    //   9921: invokestatic 536	com/tencent/luggage/wxa/qz/x:d	(Landroid/content/Context;)I
    //   9924: istore_1
    //   9925: iload_1
    //   9926: iconst_m1
    //   9927: if_icmpne +24 -> 9951
    //   9930: ldc 151
    //   9932: invokestatic 156	com/tencent/luggage/wxa/ba/e:b	(Ljava/lang/Class;)Lcom/tencent/luggage/wxa/ba/d;
    //   9935: checkcast 151	com/tencent/luggage/wxa/ot/c
    //   9938: ldc2_w 157
    //   9941: ldc2_w 537
    //   9944: lconst_1
    //   9945: iconst_0
    //   9946: invokeinterface 161 8 0
    //   9951: ldc 163
    //   9953: ldc_w 540
    //   9956: iconst_2
    //   9957: anewarray 4	java/lang/Object
    //   9960: dup
    //   9961: iconst_0
    //   9962: aload_0
    //   9963: getfield 250	com/tencent/luggage/wxa/oa/b:p	Ljava/lang/String;
    //   9966: aastore
    //   9967: dup
    //   9968: iconst_1
    //   9969: iload_1
    //   9970: invokestatic 179	java/lang/Integer:valueOf	(I)Ljava/lang/Integer;
    //   9973: aastore
    //   9974: invokestatic 184	com/tencent/luggage/wxa/qz/o:d	(Ljava/lang/String;Ljava/lang/String;[Ljava/lang/Object;)V
    //   9977: aload 16
    //   9979: ifnull +41 -> 10020
    //   9982: aload 16
    //   9984: invokevirtual 634	java/io/OutputStream:close	()V
    //   9987: goto +33 -> 10020
    //   9990: astore 12
    //   9992: ldc 163
    //   9994: aload 12
    //   9996: ldc_w 603
    //   9999: iconst_2
    //   10000: anewarray 4	java/lang/Object
    //   10003: dup
    //   10004: iconst_0
    //   10005: aload_0
    //   10006: getfield 76	com/tencent/luggage/wxa/oa/b:f	Ljava/lang/String;
    //   10009: aastore
    //   10010: dup
    //   10011: iconst_1
    //   10012: aload_0
    //   10013: getfield 78	com/tencent/luggage/wxa/oa/b:g	Ljava/lang/String;
    //   10016: aastore
    //   10017: invokestatic 578	com/tencent/luggage/wxa/qz/o:a	(Ljava/lang/String;Ljava/lang/Throwable;Ljava/lang/String;[Ljava/lang/Object;)V
    //   10020: aload 19
    //   10022: ifnull +105 -> 10127
    //   10025: aload 19
    //   10027: invokevirtual 601	java/io/InputStream:close	()V
    //   10030: goto +97 -> 10127
    //   10033: astore 12
    //   10035: ldc 163
    //   10037: aload 12
    //   10039: aload 17
    //   10041: iconst_2
    //   10042: anewarray 4	java/lang/Object
    //   10045: dup
    //   10046: iconst_0
    //   10047: aload_0
    //   10048: getfield 76	com/tencent/luggage/wxa/oa/b:f	Ljava/lang/String;
    //   10051: aastore
    //   10052: dup
    //   10053: iconst_1
    //   10054: aload_0
    //   10055: getfield 78	com/tencent/luggage/wxa/oa/b:g	Ljava/lang/String;
    //   10058: aastore
    //   10059: invokestatic 578	com/tencent/luggage/wxa/qz/o:a	(Ljava/lang/String;Ljava/lang/Throwable;Ljava/lang/String;[Ljava/lang/Object;)V
    //   10062: goto +65 -> 10127
    //   10065: astore 12
    //   10067: ldc 163
    //   10069: aload 12
    //   10071: aload 18
    //   10073: iconst_2
    //   10074: anewarray 4	java/lang/Object
    //   10077: dup
    //   10078: iconst_0
    //   10079: aload_0
    //   10080: getfield 76	com/tencent/luggage/wxa/oa/b:f	Ljava/lang/String;
    //   10083: aastore
    //   10084: dup
    //   10085: iconst_1
    //   10086: aload_0
    //   10087: getfield 78	com/tencent/luggage/wxa/oa/b:g	Ljava/lang/String;
    //   10090: aastore
    //   10091: invokestatic 578	com/tencent/luggage/wxa/qz/o:a	(Ljava/lang/String;Ljava/lang/Throwable;Ljava/lang/String;[Ljava/lang/Object;)V
    //   10094: goto +33 -> 10127
    //   10097: astore 12
    //   10099: ldc 163
    //   10101: aload 12
    //   10103: ldc_w 603
    //   10106: iconst_2
    //   10107: anewarray 4	java/lang/Object
    //   10110: dup
    //   10111: iconst_0
    //   10112: aload_0
    //   10113: getfield 76	com/tencent/luggage/wxa/oa/b:f	Ljava/lang/String;
    //   10116: aastore
    //   10117: dup
    //   10118: iconst_1
    //   10119: aload_0
    //   10120: getfield 78	com/tencent/luggage/wxa/oa/b:g	Ljava/lang/String;
    //   10123: aastore
    //   10124: invokestatic 578	com/tencent/luggage/wxa/qz/o:a	(Ljava/lang/String;Ljava/lang/Throwable;Ljava/lang/String;[Ljava/lang/Object;)V
    //   10127: aload_0
    //   10128: invokevirtual 518	com/tencent/luggage/wxa/oa/b:b	()V
    //   10131: aload_0
    //   10132: getfield 82	com/tencent/luggage/wxa/oa/b:c	Lcom/tencent/luggage/wxa/oa/a;
    //   10135: aload_0
    //   10136: invokevirtual 520	com/tencent/luggage/wxa/oa/b:c	()Ljava/lang/String;
    //   10139: invokeinterface 522 2 0
    //   10144: ldc 163
    //   10146: ldc_w 524
    //   10149: iconst_2
    //   10150: anewarray 4	java/lang/Object
    //   10153: dup
    //   10154: iconst_0
    //   10155: aload_0
    //   10156: getfield 250	com/tencent/luggage/wxa/oa/b:p	Ljava/lang/String;
    //   10159: aastore
    //   10160: dup
    //   10161: iconst_1
    //   10162: aload_0
    //   10163: getfield 76	com/tencent/luggage/wxa/oa/b:f	Ljava/lang/String;
    //   10166: aastore
    //   10167: invokestatic 184	com/tencent/luggage/wxa/qz/o:d	(Ljava/lang/String;Ljava/lang/String;[Ljava/lang/Object;)V
    //   10170: return
    //   10171: astore 16
    //   10173: aload 15
    //   10175: astore 17
    //   10177: aload 14
    //   10179: astore 15
    //   10181: aload 13
    //   10183: astore 18
    //   10185: aload 12
    //   10187: astore 14
    //   10189: aload 17
    //   10191: astore 13
    //   10193: aload 16
    //   10195: astore 12
    //   10197: iload_1
    //   10198: ifeq +166 -> 10364
    //   10201: aload_0
    //   10202: getfield 80	com/tencent/luggage/wxa/oa/b:h	Ljava/lang/String;
    //   10205: invokestatic 124	com/tencent/luggage/wxa/qz/af:c	(Ljava/lang/String;)Z
    //   10208: ifeq +55 -> 10263
    //   10211: ldc 223
    //   10213: invokestatic 156	com/tencent/luggage/wxa/ba/e:b	(Ljava/lang/Class;)Lcom/tencent/luggage/wxa/ba/d;
    //   10216: checkcast 223	com/tencent/luggage/wxa/nz/o
    //   10219: aload_0
    //   10220: getfield 74	com/tencent/luggage/wxa/oa/b:a	Lcom/tencent/luggage/wxa/jx/c;
    //   10223: invokeinterface 229 1 0
    //   10228: aload_0
    //   10229: invokevirtual 231	com/tencent/luggage/wxa/oa/b:d	()Ljava/lang/String;
    //   10232: ldc 233
    //   10234: aload_0
    //   10235: invokevirtual 235	com/tencent/luggage/wxa/oa/b:a	()Ljava/lang/String;
    //   10238: lconst_0
    //   10239: lload 5
    //   10241: iload_2
    //   10242: iconst_1
    //   10243: aload_0
    //   10244: invokevirtual 238	com/tencent/luggage/wxa/oa/b:e	()I
    //   10247: aload_0
    //   10248: getfield 78	com/tencent/luggage/wxa/oa/b:g	Ljava/lang/String;
    //   10251: aload_0
    //   10252: getfield 59	com/tencent/luggage/wxa/oa/b:i	Ljava/lang/String;
    //   10255: invokeinterface 241 14 0
    //   10260: goto +52 -> 10312
    //   10263: ldc 223
    //   10265: invokestatic 156	com/tencent/luggage/wxa/ba/e:b	(Ljava/lang/Class;)Lcom/tencent/luggage/wxa/ba/d;
    //   10268: checkcast 223	com/tencent/luggage/wxa/nz/o
    //   10271: aload_0
    //   10272: getfield 74	com/tencent/luggage/wxa/oa/b:a	Lcom/tencent/luggage/wxa/jx/c;
    //   10275: invokeinterface 229 1 0
    //   10280: aload_0
    //   10281: invokevirtual 231	com/tencent/luggage/wxa/oa/b:d	()Ljava/lang/String;
    //   10284: ldc 233
    //   10286: aload_0
    //   10287: invokevirtual 235	com/tencent/luggage/wxa/oa/b:a	()Ljava/lang/String;
    //   10290: lconst_0
    //   10291: lload 5
    //   10293: iload_2
    //   10294: iconst_1
    //   10295: aload_0
    //   10296: invokevirtual 238	com/tencent/luggage/wxa/oa/b:e	()I
    //   10299: aload_0
    //   10300: getfield 80	com/tencent/luggage/wxa/oa/b:h	Ljava/lang/String;
    //   10303: aload_0
    //   10304: getfield 59	com/tencent/luggage/wxa/oa/b:i	Ljava/lang/String;
    //   10307: invokeinterface 241 14 0
    //   10312: ldc 151
    //   10314: invokestatic 156	com/tencent/luggage/wxa/ba/e:b	(Ljava/lang/Class;)Lcom/tencent/luggage/wxa/ba/d;
    //   10317: checkcast 151	com/tencent/luggage/wxa/ot/c
    //   10320: ldc2_w 157
    //   10323: ldc2_w 513
    //   10326: lconst_1
    //   10327: iconst_0
    //   10328: invokeinterface 161 8 0
    //   10333: ldc 151
    //   10335: invokestatic 156	com/tencent/luggage/wxa/ba/e:b	(Ljava/lang/Class;)Lcom/tencent/luggage/wxa/ba/d;
    //   10338: checkcast 151	com/tencent/luggage/wxa/ot/c
    //   10341: ldc2_w 157
    //   10344: ldc2_w 515
    //   10347: invokestatic 88	java/lang/System:currentTimeMillis	()J
    //   10350: aload_0
    //   10351: getfield 243	com/tencent/luggage/wxa/oa/b:o	J
    //   10354: lsub
    //   10355: iconst_0
    //   10356: invokeinterface 161 8 0
    //   10361: goto +222 -> 10583
    //   10364: aload_0
    //   10365: getfield 80	com/tencent/luggage/wxa/oa/b:h	Ljava/lang/String;
    //   10368: invokestatic 124	com/tencent/luggage/wxa/qz/af:c	(Ljava/lang/String;)Z
    //   10371: ifeq +55 -> 10426
    //   10374: ldc 223
    //   10376: invokestatic 156	com/tencent/luggage/wxa/ba/e:b	(Ljava/lang/Class;)Lcom/tencent/luggage/wxa/ba/d;
    //   10379: checkcast 223	com/tencent/luggage/wxa/nz/o
    //   10382: aload_0
    //   10383: getfield 74	com/tencent/luggage/wxa/oa/b:a	Lcom/tencent/luggage/wxa/jx/c;
    //   10386: invokeinterface 229 1 0
    //   10391: aload_0
    //   10392: invokevirtual 231	com/tencent/luggage/wxa/oa/b:d	()Ljava/lang/String;
    //   10395: ldc 233
    //   10397: aload_0
    //   10398: invokevirtual 235	com/tencent/luggage/wxa/oa/b:a	()Ljava/lang/String;
    //   10401: lconst_0
    //   10402: lload 5
    //   10404: iload_2
    //   10405: iconst_2
    //   10406: aload_0
    //   10407: invokevirtual 238	com/tencent/luggage/wxa/oa/b:e	()I
    //   10410: aload_0
    //   10411: getfield 78	com/tencent/luggage/wxa/oa/b:g	Ljava/lang/String;
    //   10414: aload_0
    //   10415: getfield 59	com/tencent/luggage/wxa/oa/b:i	Ljava/lang/String;
    //   10418: invokeinterface 241 14 0
    //   10423: goto +52 -> 10475
    //   10426: ldc 223
    //   10428: invokestatic 156	com/tencent/luggage/wxa/ba/e:b	(Ljava/lang/Class;)Lcom/tencent/luggage/wxa/ba/d;
    //   10431: checkcast 223	com/tencent/luggage/wxa/nz/o
    //   10434: aload_0
    //   10435: getfield 74	com/tencent/luggage/wxa/oa/b:a	Lcom/tencent/luggage/wxa/jx/c;
    //   10438: invokeinterface 229 1 0
    //   10443: aload_0
    //   10444: invokevirtual 231	com/tencent/luggage/wxa/oa/b:d	()Ljava/lang/String;
    //   10447: ldc 233
    //   10449: aload_0
    //   10450: invokevirtual 235	com/tencent/luggage/wxa/oa/b:a	()Ljava/lang/String;
    //   10453: lconst_0
    //   10454: lload 5
    //   10456: iload_2
    //   10457: iconst_2
    //   10458: aload_0
    //   10459: invokevirtual 238	com/tencent/luggage/wxa/oa/b:e	()I
    //   10462: aload_0
    //   10463: getfield 80	com/tencent/luggage/wxa/oa/b:h	Ljava/lang/String;
    //   10466: aload_0
    //   10467: getfield 59	com/tencent/luggage/wxa/oa/b:i	Ljava/lang/String;
    //   10470: invokeinterface 241 14 0
    //   10475: ldc 151
    //   10477: invokestatic 156	com/tencent/luggage/wxa/ba/e:b	(Ljava/lang/Class;)Lcom/tencent/luggage/wxa/ba/d;
    //   10480: checkcast 151	com/tencent/luggage/wxa/ot/c
    //   10483: ldc2_w 157
    //   10486: ldc2_w 530
    //   10489: lconst_1
    //   10490: iconst_0
    //   10491: invokeinterface 161 8 0
    //   10496: ldc 151
    //   10498: invokestatic 156	com/tencent/luggage/wxa/ba/e:b	(Ljava/lang/Class;)Lcom/tencent/luggage/wxa/ba/d;
    //   10501: checkcast 151	com/tencent/luggage/wxa/ot/c
    //   10504: ldc2_w 157
    //   10507: ldc2_w 532
    //   10510: invokestatic 88	java/lang/System:currentTimeMillis	()J
    //   10513: aload_0
    //   10514: getfield 243	com/tencent/luggage/wxa/oa/b:o	J
    //   10517: lsub
    //   10518: iconst_0
    //   10519: invokeinterface 161 8 0
    //   10524: invokestatic 138	com/tencent/luggage/wxa/qz/r:a	()Landroid/content/Context;
    //   10527: invokestatic 536	com/tencent/luggage/wxa/qz/x:d	(Landroid/content/Context;)I
    //   10530: istore_1
    //   10531: iload_1
    //   10532: iconst_m1
    //   10533: if_icmpne +24 -> 10557
    //   10536: ldc 151
    //   10538: invokestatic 156	com/tencent/luggage/wxa/ba/e:b	(Ljava/lang/Class;)Lcom/tencent/luggage/wxa/ba/d;
    //   10541: checkcast 151	com/tencent/luggage/wxa/ot/c
    //   10544: ldc2_w 157
    //   10547: ldc2_w 537
    //   10550: lconst_1
    //   10551: iconst_0
    //   10552: invokeinterface 161 8 0
    //   10557: ldc 163
    //   10559: ldc_w 540
    //   10562: iconst_2
    //   10563: anewarray 4	java/lang/Object
    //   10566: dup
    //   10567: iconst_0
    //   10568: aload_0
    //   10569: getfield 250	com/tencent/luggage/wxa/oa/b:p	Ljava/lang/String;
    //   10572: aastore
    //   10573: dup
    //   10574: iconst_1
    //   10575: iload_1
    //   10576: invokestatic 179	java/lang/Integer:valueOf	(I)Ljava/lang/Integer;
    //   10579: aastore
    //   10580: invokestatic 184	com/tencent/luggage/wxa/qz/o:d	(Ljava/lang/String;Ljava/lang/String;[Ljava/lang/Object;)V
    //   10583: aload 15
    //   10585: ifnull +41 -> 10626
    //   10588: aload 15
    //   10590: invokevirtual 634	java/io/OutputStream:close	()V
    //   10593: goto +33 -> 10626
    //   10596: astore 15
    //   10598: ldc 163
    //   10600: aload 15
    //   10602: ldc_w 603
    //   10605: iconst_2
    //   10606: anewarray 4	java/lang/Object
    //   10609: dup
    //   10610: iconst_0
    //   10611: aload_0
    //   10612: getfield 76	com/tencent/luggage/wxa/oa/b:f	Ljava/lang/String;
    //   10615: aastore
    //   10616: dup
    //   10617: iconst_1
    //   10618: aload_0
    //   10619: getfield 78	com/tencent/luggage/wxa/oa/b:g	Ljava/lang/String;
    //   10622: aastore
    //   10623: invokestatic 578	com/tencent/luggage/wxa/qz/o:a	(Ljava/lang/String;Ljava/lang/Throwable;Ljava/lang/String;[Ljava/lang/Object;)V
    //   10626: aload 13
    //   10628: ifnull +105 -> 10733
    //   10631: aload 13
    //   10633: invokevirtual 601	java/io/InputStream:close	()V
    //   10636: goto +97 -> 10733
    //   10639: astore 13
    //   10641: ldc 163
    //   10643: aload 13
    //   10645: aload 14
    //   10647: iconst_2
    //   10648: anewarray 4	java/lang/Object
    //   10651: dup
    //   10652: iconst_0
    //   10653: aload_0
    //   10654: getfield 76	com/tencent/luggage/wxa/oa/b:f	Ljava/lang/String;
    //   10657: aastore
    //   10658: dup
    //   10659: iconst_1
    //   10660: aload_0
    //   10661: getfield 78	com/tencent/luggage/wxa/oa/b:g	Ljava/lang/String;
    //   10664: aastore
    //   10665: invokestatic 578	com/tencent/luggage/wxa/qz/o:a	(Ljava/lang/String;Ljava/lang/Throwable;Ljava/lang/String;[Ljava/lang/Object;)V
    //   10668: goto +65 -> 10733
    //   10671: astore 13
    //   10673: ldc 163
    //   10675: aload 13
    //   10677: aload 18
    //   10679: iconst_2
    //   10680: anewarray 4	java/lang/Object
    //   10683: dup
    //   10684: iconst_0
    //   10685: aload_0
    //   10686: getfield 76	com/tencent/luggage/wxa/oa/b:f	Ljava/lang/String;
    //   10689: aastore
    //   10690: dup
    //   10691: iconst_1
    //   10692: aload_0
    //   10693: getfield 78	com/tencent/luggage/wxa/oa/b:g	Ljava/lang/String;
    //   10696: aastore
    //   10697: invokestatic 578	com/tencent/luggage/wxa/qz/o:a	(Ljava/lang/String;Ljava/lang/Throwable;Ljava/lang/String;[Ljava/lang/Object;)V
    //   10700: goto +33 -> 10733
    //   10703: astore 13
    //   10705: ldc 163
    //   10707: aload 13
    //   10709: ldc_w 603
    //   10712: iconst_2
    //   10713: anewarray 4	java/lang/Object
    //   10716: dup
    //   10717: iconst_0
    //   10718: aload_0
    //   10719: getfield 76	com/tencent/luggage/wxa/oa/b:f	Ljava/lang/String;
    //   10722: aastore
    //   10723: dup
    //   10724: iconst_1
    //   10725: aload_0
    //   10726: getfield 78	com/tencent/luggage/wxa/oa/b:g	Ljava/lang/String;
    //   10729: aastore
    //   10730: invokestatic 578	com/tencent/luggage/wxa/qz/o:a	(Ljava/lang/String;Ljava/lang/Throwable;Ljava/lang/String;[Ljava/lang/Object;)V
    //   10733: aload_0
    //   10734: invokevirtual 518	com/tencent/luggage/wxa/oa/b:b	()V
    //   10737: aload_0
    //   10738: getfield 82	com/tencent/luggage/wxa/oa/b:c	Lcom/tencent/luggage/wxa/oa/a;
    //   10741: aload_0
    //   10742: invokevirtual 520	com/tencent/luggage/wxa/oa/b:c	()Ljava/lang/String;
    //   10745: invokeinterface 522 2 0
    //   10750: ldc 163
    //   10752: ldc_w 524
    //   10755: iconst_2
    //   10756: anewarray 4	java/lang/Object
    //   10759: dup
    //   10760: iconst_0
    //   10761: aload_0
    //   10762: getfield 250	com/tencent/luggage/wxa/oa/b:p	Ljava/lang/String;
    //   10765: aastore
    //   10766: dup
    //   10767: iconst_1
    //   10768: aload_0
    //   10769: getfield 76	com/tencent/luggage/wxa/oa/b:f	Ljava/lang/String;
    //   10772: aastore
    //   10773: invokestatic 184	com/tencent/luggage/wxa/qz/o:d	(Ljava/lang/String;Ljava/lang/String;[Ljava/lang/Object;)V
    //   10776: goto +6 -> 10782
    //   10779: aload 12
    //   10781: athrow
    //   10782: goto -3 -> 10779
    //   10785: astore 14
    //   10787: goto -8821 -> 1966
    //   10790: astore 12
    //   10792: goto -8887 -> 1905
    //   10795: goto -7091 -> 3704
    // Local variable table:
    //   start	length	slot	name	signature
    //   0	10798	0	this	b
    //   600	9976	1	i1	int
    //   646	9811	2	i2	int
    //   677	8911	3	i3	int
    //   685	9165	4	i4	int
    //   13	10442	5	l1	long
    //   391	9457	7	l2	long
    //   568	4241	9	l3	long
    //   257	2857	11	bool	boolean
    //   302	1	12	localObject1	Object
    //   387	167	12	localObject2	Object
    //   633	1	12	localObject3	Object
    //   813	1079	12	localObject4	Object
    //   1898	1	12	localException1	Exception
    //   1903	66	12	localException2	Exception
    //   2311	5	12	localThrowable1	java.lang.Throwable
    //   2344	5	12	localArrayIndexOutOfBoundsException1	java.lang.ArrayIndexOutOfBoundsException
    //   2377	5	12	localIOException1	IOException
    //   2484	93	12	str1	String
    //   2910	5	12	localThrowable2	java.lang.Throwable
    //   2943	5	12	localArrayIndexOutOfBoundsException2	java.lang.ArrayIndexOutOfBoundsException
    //   2976	5	12	localIOException2	IOException
    //   3082	1	12	localObject5	Object
    //   3425	39	12	localThrowable3	java.lang.Throwable
    //   3489	269	12	localIOException3	IOException
    //   3763	85	12	localObject6	Object
    //   4223	39	12	localThrowable4	java.lang.Throwable
    //   4287	112	12	localIOException4	IOException
    //   4413	164	12	localObject7	Object
    //   4584	18	12	localException3	Exception
    //   4619	18	12	localSocketTimeoutException1	java.net.SocketTimeoutException
    //   4654	18	12	localSSLHandshakeException1	javax.net.ssl.SSLHandshakeException
    //   4689	18	12	localFileNotFoundException1	java.io.FileNotFoundException
    //   4724	18	12	localUnsupportedEncodingException1	java.io.UnsupportedEncodingException
    //   4767	1	12	str2	String
    //   5442	39	12	localThrowable5	java.lang.Throwable
    //   5506	115	12	localIOException5	IOException
    //   5786	210	12	localObject8	Object
    //   6009	1	12	localObject9	Object
    //   6182	1	12	localObject10	Object
    //   6242	297	12	localObject11	Object
    //   6976	5	12	localIOException6	IOException
    //   7019	5	12	localThrowable6	java.lang.Throwable
    //   7051	5	12	localArrayIndexOutOfBoundsException3	java.lang.ArrayIndexOutOfBoundsException
    //   7083	5	12	localIOException7	IOException
    //   7189	100	12	localObject12	Object
    //   7730	5	12	localIOException8	IOException
    //   7773	5	12	localThrowable7	java.lang.Throwable
    //   7805	5	12	localArrayIndexOutOfBoundsException4	java.lang.ArrayIndexOutOfBoundsException
    //   7837	5	12	localIOException9	IOException
    //   7943	100	12	localObject13	Object
    //   8484	5	12	localIOException10	IOException
    //   8527	5	12	localThrowable8	java.lang.Throwable
    //   8559	5	12	localArrayIndexOutOfBoundsException5	java.lang.ArrayIndexOutOfBoundsException
    //   8591	5	12	localIOException11	IOException
    //   8697	100	12	localObject14	Object
    //   9238	5	12	localIOException12	IOException
    //   9281	5	12	localThrowable9	java.lang.Throwable
    //   9313	5	12	localArrayIndexOutOfBoundsException6	java.lang.ArrayIndexOutOfBoundsException
    //   9345	5	12	localIOException13	IOException
    //   9451	98	12	localObject15	Object
    //   9990	5	12	localIOException14	IOException
    //   10033	5	12	localThrowable10	java.lang.Throwable
    //   10065	5	12	localArrayIndexOutOfBoundsException7	java.lang.ArrayIndexOutOfBoundsException
    //   10097	89	12	localIOException15	IOException
    //   10195	585	12	localObject16	Object
    //   3	3429	13	str3	String
    //   3457	773	13	localArrayIndexOutOfBoundsException8	java.lang.ArrayIndexOutOfBoundsException
    //   4255	140	13	localArrayIndexOutOfBoundsException9	java.lang.ArrayIndexOutOfBoundsException
    //   4409	1040	13	localObject17	Object
    //   5474	151	13	localArrayIndexOutOfBoundsException10	java.lang.ArrayIndexOutOfBoundsException
    //   5782	4850	13	localObject18	Object
    //   10639	5	13	localThrowable11	java.lang.Throwable
    //   10671	5	13	localArrayIndexOutOfBoundsException11	java.lang.ArrayIndexOutOfBoundsException
    //   10703	5	13	localIOException16	IOException
    //   203	10443	14	localObject19	Object
    //   10785	1	14	localException4	Exception
    //   455	2010	15	localEntry	java.util.Map.Entry
    //   2474	1	15	localException5	Exception
    //   2497	1	15	localSocketTimeoutException2	java.net.SocketTimeoutException
    //   2520	1	15	localSSLHandshakeException2	javax.net.ssl.SSLHandshakeException
    //   2543	1	15	localFileNotFoundException2	java.io.FileNotFoundException
    //   2566	1	15	localUnsupportedEncodingException2	java.io.UnsupportedEncodingException
    //   3060	315	15	localOutputStream	java.io.OutputStream
    //   3382	791	15	localIOException17	IOException
    //   4180	566	15	localIOException18	IOException
    //   4773	619	15	localObject20	Object
    //   5399	239	15	localIOException19	IOException
    //   5643	134	15	localObject21	Object
    //   5799	21	15	localException6	Exception
    //   5841	21	15	localSocketTimeoutException3	java.net.SocketTimeoutException
    //   5883	21	15	localSSLHandshakeException3	javax.net.ssl.SSLHandshakeException
    //   5925	21	15	localFileNotFoundException3	java.io.FileNotFoundException
    //   5967	21	15	localUnsupportedEncodingException3	java.io.UnsupportedEncodingException
    //   6032	4557	15	localObject22	Object
    //   10596	5	15	localIOException20	IOException
    //   674	2463	16	localObject23	Object
    //   3568	1	16	localException7	Exception
    //   3573	1	16	localSocketTimeoutException4	java.net.SocketTimeoutException
    //   3578	1	16	localSSLHandshakeException4	javax.net.ssl.SSLHandshakeException
    //   3583	1	16	localFileNotFoundException4	java.io.FileNotFoundException
    //   3588	1	16	localUnsupportedEncodingException4	java.io.UnsupportedEncodingException
    //   3597	1	16	localArrayIndexOutOfBoundsException12	java.lang.ArrayIndexOutOfBoundsException
    //   3606	1	16	localException8	Exception
    //   3611	1	16	localSocketTimeoutException5	java.net.SocketTimeoutException
    //   3616	1	16	localSSLHandshakeException5	javax.net.ssl.SSLHandshakeException
    //   3621	1	16	localFileNotFoundException5	java.io.FileNotFoundException
    //   3626	8	16	localUnsupportedEncodingException5	java.io.UnsupportedEncodingException
    //   3746	1	16	localArrayIndexOutOfBoundsException13	java.lang.ArrayIndexOutOfBoundsException
    //   3755	7	16	localException9	Exception
    //   3776	7	16	localSocketTimeoutException6	java.net.SocketTimeoutException
    //   3797	7	16	localSSLHandshakeException6	javax.net.ssl.SSLHandshakeException
    //   3818	7	16	localFileNotFoundException6	java.io.FileNotFoundException
    //   3839	7	16	localUnsupportedEncodingException6	java.io.UnsupportedEncodingException
    //   4366	1	16	localException10	Exception
    //   4371	1	16	localSocketTimeoutException7	java.net.SocketTimeoutException
    //   4376	1	16	localSSLHandshakeException7	javax.net.ssl.SSLHandshakeException
    //   4381	1	16	localFileNotFoundException7	java.io.FileNotFoundException
    //   4386	1	16	localUnsupportedEncodingException7	java.io.UnsupportedEncodingException
    //   4400	12	16	localIOException21	IOException
    //   4423	1	16	localException11	Exception
    //   4428	1	16	localSocketTimeoutException8	java.net.SocketTimeoutException
    //   4433	1	16	localSSLHandshakeException8	javax.net.ssl.SSLHandshakeException
    //   4438	1	16	localFileNotFoundException8	java.io.FileNotFoundException
    //   4443	1	16	localUnsupportedEncodingException8	java.io.UnsupportedEncodingException
    //   4452	1	16	localObject24	Object
    //   4461	7	16	localException12	Exception
    //   4482	7	16	localSocketTimeoutException9	java.net.SocketTimeoutException
    //   4503	7	16	localSSLHandshakeException9	javax.net.ssl.SSLHandshakeException
    //   4524	7	16	localFileNotFoundException9	java.io.FileNotFoundException
    //   4545	7	16	localUnsupportedEncodingException9	java.io.UnsupportedEncodingException
    //   4607	141	16	localIOException22	IOException
    //   4893	5	16	localIOException23	IOException
    //   4927	658	16	localObject25	Object
    //   5593	1	16	localException13	Exception
    //   5598	1	16	localSocketTimeoutException10	java.net.SocketTimeoutException
    //   5603	1	16	localSSLHandshakeException10	javax.net.ssl.SSLHandshakeException
    //   5608	1	16	localFileNotFoundException10	java.io.FileNotFoundException
    //   5613	1	16	localUnsupportedEncodingException10	java.io.UnsupportedEncodingException
    //   5626	1	16	localArrayIndexOutOfBoundsException14	java.lang.ArrayIndexOutOfBoundsException
    //   5633	9	16	localException14	Exception
    //   5647	1	16	localObject26	Object
    //   5658	9	16	localSocketTimeoutException11	java.net.SocketTimeoutException
    //   5672	1	16	localObject27	Object
    //   5683	9	16	localSSLHandshakeException11	javax.net.ssl.SSLHandshakeException
    //   5697	1	16	localObject28	Object
    //   5708	9	16	localFileNotFoundException11	java.io.FileNotFoundException
    //   5722	1	16	localObject29	Object
    //   5733	9	16	localUnsupportedEncodingException11	java.io.UnsupportedEncodingException
    //   5747	4236	16	localObject30	Object
    //   10171	23	16	localObject31	Object
    //   8	775	17	str4	String
    //   2451	630	17	localObject32	Object
    //   3128	11	17	str5	String
    //   3563	1	17	localObject33	Object
    //   3593	1	17	localObject34	Object
    //   3742	1	17	localObject35	Object
    //   3767	85	17	localArrayIndexOutOfBoundsException15	java.lang.ArrayIndexOutOfBoundsException
    //   4361	1	17	localObject36	Object
    //   4396	12	17	localArrayIndexOutOfBoundsException16	java.lang.ArrayIndexOutOfBoundsException
    //   4418	1	17	localObject37	Object
    //   4448	1	17	localObject38	Object
    //   4473	85	17	localObject39	Object
    //   4566	1	17	localObject40	Object
    //   4589	141	17	str6	String
    //   5580	1	17	localObject41	Object
    //   5618	1	17	localObject42	Object
    //   5639	107	17	localObject43	Object
    //   5758	27	17	localObject44	Object
    //   5825	4365	17	localObject45	Object
    //   643	10035	18	localObject46	Object
    //   679	9347	19	localObject47	Object
    //   307	1	20	localException15	Exception
    //   312	1	20	localSocketTimeoutException12	java.net.SocketTimeoutException
    //   317	1	20	localSSLHandshakeException12	javax.net.ssl.SSLHandshakeException
    //   322	1	20	localFileNotFoundException12	java.io.FileNotFoundException
    //   327	1	20	localUnsupportedEncodingException12	java.io.UnsupportedEncodingException
    //   661	1	20	localException16	Exception
    //   690	1	20	localSocketTimeoutException13	java.net.SocketTimeoutException
    //   719	1	20	localSSLHandshakeException13	javax.net.ssl.SSLHandshakeException
    //   748	1	20	localFileNotFoundException13	java.io.FileNotFoundException
    //   777	1	20	localUnsupportedEncodingException13	java.io.UnsupportedEncodingException
    //   4603	1387	20	localObject48	Object
    //   6037	1	20	localException17	Exception
    //   6066	1	20	localSocketTimeoutException14	java.net.SocketTimeoutException
    //   6095	1	20	localSSLHandshakeException14	javax.net.ssl.SSLHandshakeException
    //   6124	1	20	localFileNotFoundException14	java.io.FileNotFoundException
    //   6153	1	20	localUnsupportedEncodingException14	java.io.UnsupportedEncodingException
    //   6210	314	20	localException18	Exception
    //   7157	100	20	localSocketTimeoutException15	java.net.SocketTimeoutException
    //   7911	100	20	localSSLHandshakeException15	javax.net.ssl.SSLHandshakeException
    //   8665	100	20	localFileNotFoundException15	java.io.FileNotFoundException
    //   9419	98	20	localUnsupportedEncodingException15	java.io.UnsupportedEncodingException
    //   6364	194	21	locala	a
    //   6395	165	22	str7	String
    //   6426	136	23	str8	String
    //   6460	104	24	localStringBuilder	java.lang.StringBuilder
    // Exception table:
    //   from	to	target	type
    //   264	299	302	finally
    //   398	431	302	finally
    //   435	523	302	finally
    //   264	299	307	java/lang/Exception
    //   398	431	307	java/lang/Exception
    //   435	523	307	java/lang/Exception
    //   264	299	312	java/net/SocketTimeoutException
    //   398	431	312	java/net/SocketTimeoutException
    //   435	523	312	java/net/SocketTimeoutException
    //   264	299	317	javax/net/ssl/SSLHandshakeException
    //   398	431	317	javax/net/ssl/SSLHandshakeException
    //   435	523	317	javax/net/ssl/SSLHandshakeException
    //   264	299	322	java/io/FileNotFoundException
    //   398	431	322	java/io/FileNotFoundException
    //   435	523	322	java/io/FileNotFoundException
    //   264	299	327	java/io/UnsupportedEncodingException
    //   398	431	327	java/io/UnsupportedEncodingException
    //   435	523	327	java/io/UnsupportedEncodingException
    //   608	630	633	finally
    //   838	914	633	finally
    //   918	962	633	finally
    //   1164	1208	633	finally
    //   1481	1539	633	finally
    //   1800	1832	633	finally
    //   1835	1860	633	finally
    //   1860	1879	633	finally
    //   1882	1891	633	finally
    //   1919	1951	633	finally
    //   1954	1963	633	finally
    //   608	630	661	java/lang/Exception
    //   838	914	661	java/lang/Exception
    //   918	962	661	java/lang/Exception
    //   1164	1208	661	java/lang/Exception
    //   1481	1539	661	java/lang/Exception
    //   608	630	690	java/net/SocketTimeoutException
    //   838	914	690	java/net/SocketTimeoutException
    //   918	962	690	java/net/SocketTimeoutException
    //   1164	1208	690	java/net/SocketTimeoutException
    //   1481	1539	690	java/net/SocketTimeoutException
    //   1800	1832	690	java/net/SocketTimeoutException
    //   1835	1860	690	java/net/SocketTimeoutException
    //   1860	1879	690	java/net/SocketTimeoutException
    //   1882	1891	690	java/net/SocketTimeoutException
    //   1919	1951	690	java/net/SocketTimeoutException
    //   1954	1963	690	java/net/SocketTimeoutException
    //   608	630	719	javax/net/ssl/SSLHandshakeException
    //   838	914	719	javax/net/ssl/SSLHandshakeException
    //   918	962	719	javax/net/ssl/SSLHandshakeException
    //   1164	1208	719	javax/net/ssl/SSLHandshakeException
    //   1481	1539	719	javax/net/ssl/SSLHandshakeException
    //   1800	1832	719	javax/net/ssl/SSLHandshakeException
    //   1835	1860	719	javax/net/ssl/SSLHandshakeException
    //   1860	1879	719	javax/net/ssl/SSLHandshakeException
    //   1882	1891	719	javax/net/ssl/SSLHandshakeException
    //   1919	1951	719	javax/net/ssl/SSLHandshakeException
    //   1954	1963	719	javax/net/ssl/SSLHandshakeException
    //   608	630	748	java/io/FileNotFoundException
    //   838	914	748	java/io/FileNotFoundException
    //   918	962	748	java/io/FileNotFoundException
    //   1164	1208	748	java/io/FileNotFoundException
    //   1481	1539	748	java/io/FileNotFoundException
    //   1800	1832	748	java/io/FileNotFoundException
    //   1835	1860	748	java/io/FileNotFoundException
    //   1860	1879	748	java/io/FileNotFoundException
    //   1882	1891	748	java/io/FileNotFoundException
    //   1919	1951	748	java/io/FileNotFoundException
    //   1954	1963	748	java/io/FileNotFoundException
    //   608	630	777	java/io/UnsupportedEncodingException
    //   838	914	777	java/io/UnsupportedEncodingException
    //   918	962	777	java/io/UnsupportedEncodingException
    //   1164	1208	777	java/io/UnsupportedEncodingException
    //   1481	1539	777	java/io/UnsupportedEncodingException
    //   1800	1832	777	java/io/UnsupportedEncodingException
    //   1835	1860	777	java/io/UnsupportedEncodingException
    //   1860	1879	777	java/io/UnsupportedEncodingException
    //   1882	1891	777	java/io/UnsupportedEncodingException
    //   1919	1951	777	java/io/UnsupportedEncodingException
    //   1954	1963	777	java/io/UnsupportedEncodingException
    //   1860	1879	1898	java/lang/Exception
    //   1882	1891	1898	java/lang/Exception
    //   1800	1832	1903	java/lang/Exception
    //   1835	1860	1903	java/lang/Exception
    //   2303	2308	2311	java/lang/Throwable
    //   2303	2308	2344	java/lang/ArrayIndexOutOfBoundsException
    //   2303	2308	2377	java/io/IOException
    //   2008	2081	2451	finally
    //   2604	2680	2451	finally
    //   2008	2081	2474	java/lang/Exception
    //   2604	2680	2474	java/lang/Exception
    //   2008	2081	2497	java/net/SocketTimeoutException
    //   2604	2680	2497	java/net/SocketTimeoutException
    //   2008	2081	2520	javax/net/ssl/SSLHandshakeException
    //   2604	2680	2520	javax/net/ssl/SSLHandshakeException
    //   2008	2081	2543	java/io/FileNotFoundException
    //   2604	2680	2543	java/io/FileNotFoundException
    //   2008	2081	2566	java/io/UnsupportedEncodingException
    //   2604	2680	2566	java/io/UnsupportedEncodingException
    //   2902	2907	2910	java/lang/Throwable
    //   2902	2907	2943	java/lang/ArrayIndexOutOfBoundsException
    //   2902	2907	2976	java/io/IOException
    //   3374	3379	3382	java/io/IOException
    //   3417	3422	3425	java/lang/Throwable
    //   3417	3422	3457	java/lang/ArrayIndexOutOfBoundsException
    //   3417	3422	3489	java/io/IOException
    //   3136	3150	3563	finally
    //   3136	3150	3568	java/lang/Exception
    //   3136	3150	3573	java/net/SocketTimeoutException
    //   3136	3150	3578	javax/net/ssl/SSLHandshakeException
    //   3136	3150	3583	java/io/FileNotFoundException
    //   3136	3150	3588	java/io/UnsupportedEncodingException
    //   3118	3136	3593	finally
    //   3118	3136	3606	java/lang/Exception
    //   3118	3136	3611	java/net/SocketTimeoutException
    //   3118	3136	3616	javax/net/ssl/SSLHandshakeException
    //   3118	3136	3621	java/io/FileNotFoundException
    //   3118	3136	3626	java/io/UnsupportedEncodingException
    //   3654	3672	3742	finally
    //   3677	3699	3742	finally
    //   3704	3739	3742	finally
    //   3654	3672	3755	java/lang/Exception
    //   3677	3699	3755	java/lang/Exception
    //   3704	3739	3755	java/lang/Exception
    //   3654	3672	3776	java/net/SocketTimeoutException
    //   3677	3699	3776	java/net/SocketTimeoutException
    //   3704	3739	3776	java/net/SocketTimeoutException
    //   3654	3672	3797	javax/net/ssl/SSLHandshakeException
    //   3677	3699	3797	javax/net/ssl/SSLHandshakeException
    //   3704	3739	3797	javax/net/ssl/SSLHandshakeException
    //   3654	3672	3818	java/io/FileNotFoundException
    //   3677	3699	3818	java/io/FileNotFoundException
    //   3704	3739	3818	java/io/FileNotFoundException
    //   3654	3672	3839	java/io/UnsupportedEncodingException
    //   3677	3699	3839	java/io/UnsupportedEncodingException
    //   3704	3739	3839	java/io/UnsupportedEncodingException
    //   4172	4177	4180	java/io/IOException
    //   4215	4220	4223	java/lang/Throwable
    //   4215	4220	4255	java/lang/ArrayIndexOutOfBoundsException
    //   4215	4220	4287	java/io/IOException
    //   3867	3948	4361	finally
    //   3867	3948	4366	java/lang/Exception
    //   3867	3948	4371	java/net/SocketTimeoutException
    //   3867	3948	4376	javax/net/ssl/SSLHandshakeException
    //   3867	3948	4381	java/io/FileNotFoundException
    //   3867	3948	4386	java/io/UnsupportedEncodingException
    //   4402	4407	4418	finally
    //   4402	4407	4423	java/lang/Exception
    //   4402	4407	4428	java/net/SocketTimeoutException
    //   4402	4407	4433	javax/net/ssl/SSLHandshakeException
    //   4402	4407	4438	java/io/FileNotFoundException
    //   4402	4407	4443	java/io/UnsupportedEncodingException
    //   3084	3092	4448	finally
    //   3097	3113	4448	finally
    //   3631	3640	4448	finally
    //   3084	3092	4461	java/lang/Exception
    //   3097	3113	4461	java/lang/Exception
    //   3631	3640	4461	java/lang/Exception
    //   3084	3092	4482	java/net/SocketTimeoutException
    //   3097	3113	4482	java/net/SocketTimeoutException
    //   3631	3640	4482	java/net/SocketTimeoutException
    //   3084	3092	4503	javax/net/ssl/SSLHandshakeException
    //   3097	3113	4503	javax/net/ssl/SSLHandshakeException
    //   3631	3640	4503	javax/net/ssl/SSLHandshakeException
    //   3084	3092	4524	java/io/FileNotFoundException
    //   3097	3113	4524	java/io/FileNotFoundException
    //   3631	3640	4524	java/io/FileNotFoundException
    //   3084	3092	4545	java/io/UnsupportedEncodingException
    //   3097	3113	4545	java/io/UnsupportedEncodingException
    //   3631	3640	4545	java/io/UnsupportedEncodingException
    //   3066	3075	4566	finally
    //   3066	3075	4584	java/lang/Exception
    //   3066	3075	4619	java/net/SocketTimeoutException
    //   3066	3075	4654	javax/net/ssl/SSLHandshakeException
    //   3066	3075	4689	java/io/FileNotFoundException
    //   3066	3075	4724	java/io/UnsupportedEncodingException
    //   4880	4890	4893	java/io/IOException
    //   5391	5396	5399	java/io/IOException
    //   5434	5439	5442	java/lang/Throwable
    //   5434	5439	5474	java/lang/ArrayIndexOutOfBoundsException
    //   5434	5439	5506	java/io/IOException
    //   4847	4880	5580	finally
    //   4880	4890	5580	finally
    //   4895	4905	5580	finally
    //   4905	5000	5580	finally
    //   4847	4880	5593	java/lang/Exception
    //   4880	4890	5593	java/lang/Exception
    //   4895	4905	5593	java/lang/Exception
    //   4905	5000	5593	java/lang/Exception
    //   4847	4880	5598	java/net/SocketTimeoutException
    //   4880	4890	5598	java/net/SocketTimeoutException
    //   4895	4905	5598	java/net/SocketTimeoutException
    //   4905	5000	5598	java/net/SocketTimeoutException
    //   4847	4880	5603	javax/net/ssl/SSLHandshakeException
    //   4880	4890	5603	javax/net/ssl/SSLHandshakeException
    //   4895	4905	5603	javax/net/ssl/SSLHandshakeException
    //   4905	5000	5603	javax/net/ssl/SSLHandshakeException
    //   4847	4880	5608	java/io/FileNotFoundException
    //   4880	4890	5608	java/io/FileNotFoundException
    //   4895	4905	5608	java/io/FileNotFoundException
    //   4905	5000	5608	java/io/FileNotFoundException
    //   4847	4880	5613	java/io/UnsupportedEncodingException
    //   4880	4890	5613	java/io/UnsupportedEncodingException
    //   4895	4905	5613	java/io/UnsupportedEncodingException
    //   4905	5000	5613	java/io/UnsupportedEncodingException
    //   4775	4821	5618	finally
    //   4826	4845	5618	finally
    //   4775	4821	5633	java/lang/Exception
    //   4826	4845	5633	java/lang/Exception
    //   4775	4821	5658	java/net/SocketTimeoutException
    //   4826	4845	5658	java/net/SocketTimeoutException
    //   4775	4821	5683	javax/net/ssl/SSLHandshakeException
    //   4826	4845	5683	javax/net/ssl/SSLHandshakeException
    //   4775	4821	5708	java/io/FileNotFoundException
    //   4826	4845	5708	java/io/FileNotFoundException
    //   4775	4821	5733	java/io/UnsupportedEncodingException
    //   4826	4845	5733	java/io/UnsupportedEncodingException
    //   1983	2003	5758	finally
    //   2589	2599	5758	finally
    //   3055	3062	5758	finally
    //   1983	2003	5799	java/lang/Exception
    //   2589	2599	5799	java/lang/Exception
    //   3055	3062	5799	java/lang/Exception
    //   1983	2003	5841	java/net/SocketTimeoutException
    //   2589	2599	5841	java/net/SocketTimeoutException
    //   3055	3062	5841	java/net/SocketTimeoutException
    //   1983	2003	5883	javax/net/ssl/SSLHandshakeException
    //   2589	2599	5883	javax/net/ssl/SSLHandshakeException
    //   3055	3062	5883	javax/net/ssl/SSLHandshakeException
    //   1983	2003	5925	java/io/FileNotFoundException
    //   2589	2599	5925	java/io/FileNotFoundException
    //   3055	3062	5925	java/io/FileNotFoundException
    //   1983	2003	5967	java/io/UnsupportedEncodingException
    //   2589	2599	5967	java/io/UnsupportedEncodingException
    //   3055	3062	5967	java/io/UnsupportedEncodingException
    //   806	831	6009	finally
    //   1469	1477	6009	finally
    //   1905	1919	6009	finally
    //   1966	1980	6009	finally
    //   806	831	6037	java/lang/Exception
    //   1469	1477	6037	java/lang/Exception
    //   1905	1919	6037	java/lang/Exception
    //   1966	1980	6037	java/lang/Exception
    //   806	831	6066	java/net/SocketTimeoutException
    //   1469	1477	6066	java/net/SocketTimeoutException
    //   1905	1919	6066	java/net/SocketTimeoutException
    //   1966	1980	6066	java/net/SocketTimeoutException
    //   806	831	6095	javax/net/ssl/SSLHandshakeException
    //   1469	1477	6095	javax/net/ssl/SSLHandshakeException
    //   1905	1919	6095	javax/net/ssl/SSLHandshakeException
    //   1966	1980	6095	javax/net/ssl/SSLHandshakeException
    //   806	831	6124	java/io/FileNotFoundException
    //   1469	1477	6124	java/io/FileNotFoundException
    //   1905	1919	6124	java/io/FileNotFoundException
    //   1966	1980	6124	java/io/FileNotFoundException
    //   806	831	6153	java/io/UnsupportedEncodingException
    //   1469	1477	6153	java/io/UnsupportedEncodingException
    //   1905	1919	6153	java/io/UnsupportedEncodingException
    //   1966	1980	6153	java/io/UnsupportedEncodingException
    //   173	259	6182	finally
    //   332	389	6182	finally
    //   526	601	6182	finally
    //   173	259	6210	java/lang/Exception
    //   332	389	6210	java/lang/Exception
    //   526	601	6210	java/lang/Exception
    //   6968	6973	6976	java/io/IOException
    //   7011	7016	7019	java/lang/Throwable
    //   7011	7016	7051	java/lang/ArrayIndexOutOfBoundsException
    //   7011	7016	7083	java/io/IOException
    //   173	259	7157	java/net/SocketTimeoutException
    //   332	389	7157	java/net/SocketTimeoutException
    //   526	601	7157	java/net/SocketTimeoutException
    //   7722	7727	7730	java/io/IOException
    //   7765	7770	7773	java/lang/Throwable
    //   7765	7770	7805	java/lang/ArrayIndexOutOfBoundsException
    //   7765	7770	7837	java/io/IOException
    //   173	259	7911	javax/net/ssl/SSLHandshakeException
    //   332	389	7911	javax/net/ssl/SSLHandshakeException
    //   526	601	7911	javax/net/ssl/SSLHandshakeException
    //   8476	8481	8484	java/io/IOException
    //   8519	8524	8527	java/lang/Throwable
    //   8519	8524	8559	java/lang/ArrayIndexOutOfBoundsException
    //   8519	8524	8591	java/io/IOException
    //   173	259	8665	java/io/FileNotFoundException
    //   332	389	8665	java/io/FileNotFoundException
    //   526	601	8665	java/io/FileNotFoundException
    //   9230	9235	9238	java/io/IOException
    //   9273	9278	9281	java/lang/Throwable
    //   9273	9278	9313	java/lang/ArrayIndexOutOfBoundsException
    //   9273	9278	9345	java/io/IOException
    //   173	259	9419	java/io/UnsupportedEncodingException
    //   332	389	9419	java/io/UnsupportedEncodingException
    //   526	601	9419	java/io/UnsupportedEncodingException
    //   9982	9987	9990	java/io/IOException
    //   10025	10030	10033	java/lang/Throwable
    //   10025	10030	10065	java/lang/ArrayIndexOutOfBoundsException
    //   10025	10030	10097	java/io/IOException
    //   6261	6282	10171	finally
    //   6307	6335	10171	finally
    //   6360	6366	10171	finally
    //   6391	6397	10171	finally
    //   6422	6428	10171	finally
    //   6453	6462	10171	finally
    //   6487	6496	10171	finally
    //   6521	6532	10171	finally
    //   6557	6573	10171	finally
    //   7208	7229	10171	finally
    //   7254	7282	10171	finally
    //   7307	7327	10171	finally
    //   7962	7983	10171	finally
    //   8008	8036	10171	finally
    //   8061	8081	10171	finally
    //   8716	8737	10171	finally
    //   8762	8790	10171	finally
    //   8815	8835	10171	finally
    //   9470	9489	10171	finally
    //   9514	9542	10171	finally
    //   9567	9587	10171	finally
    //   10588	10593	10596	java/io/IOException
    //   10631	10636	10639	java/lang/Throwable
    //   10631	10636	10671	java/lang/ArrayIndexOutOfBoundsException
    //   10631	10636	10703	java/io/IOException
    //   1919	1951	10785	java/lang/Exception
    //   1954	1963	10785	java/lang/Exception
  }
  
  public String a()
  {
    return this.f;
  }
  
  public void a(int paramInt)
  {
    this.k = paramInt;
  }
  
  public void a(String paramString)
  {
    this.p = paramString;
  }
  
  public void a(ArrayList<String> paramArrayList)
  {
    this.m = paramArrayList;
  }
  
  public void a(Map<String, String> paramMap)
  {
    this.j = paramMap;
  }
  
  public void a(SSLContext paramSSLContext)
  {
    this.l = paramSSLContext;
  }
  
  public void a(boolean paramBoolean)
  {
    this.d = paramBoolean;
  }
  
  public void b()
  {
    this.d = false;
    HttpURLConnection localHttpURLConnection = this.q;
    if (localHttpURLConnection != null)
    {
      try
      {
        localHttpURLConnection.getInputStream().close();
      }
      catch (Exception localException)
      {
        break label48;
      }
      catch (IOException localIOException)
      {
        com.tencent.luggage.wxa.qz.o.b("MicroMsg.AppBrandDownloadWorker", localIOException.getMessage());
      }
      this.q.disconnect();
      break label61;
      label48:
      com.tencent.luggage.wxa.qz.o.a("MicroMsg.AppBrandDownloadWorker", localIOException, "abortTask Exception", new Object[0]);
    }
    label61:
    if (!af.c(this.r)) {
      CronetLogic.cancelCronetTask(this.r);
    }
  }
  
  public void b(int paramInt)
  {
    this.n = paramInt;
  }
  
  public void b(String paramString)
  {
    this.t = paramString;
  }
  
  public String c()
  {
    return this.p;
  }
  
  public String d()
  {
    return this.t;
  }
  
  public int e()
  {
    return (int)(System.currentTimeMillis() - this.s);
  }
  
  public void run()
  {
    if ((!URLUtil.isHttpsUrl(this.f)) && (!URLUtil.isHttpUrl(this.f)))
    {
      this.c.a(this.g, this.f, "downloadFile protocol must be http or https");
      return;
    }
    ArrayList localArrayList = this.m;
    if ((localArrayList != null) && (!j.a(localArrayList, this.f)))
    {
      this.c.a(this.g, this.f, "url not in domain list");
      com.tencent.luggage.wxa.qz.o.d("MicroMsg.AppBrandDownloadWorker", "not in domain url %s", new Object[] { this.f });
      return;
    }
    if (this.v)
    {
      f();
      return;
    }
    g();
  }
}


/* Location:           L:\local\mybackup\temp\qq_apk\com.tencent.mobileqq\classes5.jar
 * Qualified Name:     com.tencent.luggage.wxa.oa.b
 * JD-Core Version:    0.7.0.1
 */