package com.tencent.tmassistantsdk.network;

class GetHttpRequest$1
  implements Runnable
{
  GetHttpRequest$1(GetHttpRequest paramGetHttpRequest, String paramString) {}
  
  /* Error */
  public void run()
  {
    // Byte code:
    //   0: ldc 35
    //   2: invokestatic 41	com/tencent/matrix/trace/core/AppMethodBeat:i	(I)V
    //   5: aload_0
    //   6: getfield 21	com/tencent/tmassistantsdk/network/GetHttpRequest$1:val$param	Ljava/lang/String;
    //   9: astore_1
    //   10: aload_0
    //   11: getfield 19	com/tencent/tmassistantsdk/network/GetHttpRequest$1:this$0	Lcom/tencent/tmassistantsdk/network/GetHttpRequest;
    //   14: new 43	org/apache/http/client/methods/HttpGet
    //   17: dup
    //   18: invokespecial 44	org/apache/http/client/methods/HttpGet:<init>	()V
    //   21: putfield 48	com/tencent/tmassistantsdk/network/GetHttpRequest:mHttpGet	Lorg/apache/http/client/methods/HttpGet;
    //   24: ldc 50
    //   26: aload_1
    //   27: invokestatic 56	java/lang/String:valueOf	(Ljava/lang/Object;)Ljava/lang/String;
    //   30: invokevirtual 60	java/lang/String:concat	(Ljava/lang/String;)Ljava/lang/String;
    //   33: astore_1
    //   34: aload_0
    //   35: getfield 19	com/tencent/tmassistantsdk/network/GetHttpRequest$1:this$0	Lcom/tencent/tmassistantsdk/network/GetHttpRequest;
    //   38: getfield 48	com/tencent/tmassistantsdk/network/GetHttpRequest:mHttpGet	Lorg/apache/http/client/methods/HttpGet;
    //   41: new 62	java/net/URI
    //   44: dup
    //   45: aload_1
    //   46: invokespecial 65	java/net/URI:<init>	(Ljava/lang/String;)V
    //   49: invokevirtual 69	org/apache/http/client/methods/HttpGet:setURI	(Ljava/net/URI;)V
    //   52: invokestatic 75	com/tencent/tmassistantsdk/downloadservice/HttpClientUtil:createHttpClient	()Lorg/apache/http/client/HttpClient;
    //   55: astore_2
    //   56: aload_2
    //   57: astore_1
    //   58: aload_2
    //   59: invokestatic 79	com/tencent/tmassistantsdk/downloadservice/HttpClientUtil:setProxy	(Lorg/apache/http/client/HttpClient;)V
    //   62: aload_2
    //   63: astore_1
    //   64: aload_2
    //   65: aload_0
    //   66: getfield 19	com/tencent/tmassistantsdk/network/GetHttpRequest$1:this$0	Lcom/tencent/tmassistantsdk/network/GetHttpRequest;
    //   69: getfield 48	com/tencent/tmassistantsdk/network/GetHttpRequest:mHttpGet	Lorg/apache/http/client/methods/HttpGet;
    //   72: invokeinterface 85 2 0
    //   77: astore_3
    //   78: aload_3
    //   79: ifnull +237 -> 316
    //   82: aload_2
    //   83: astore_1
    //   84: aload_3
    //   85: invokeinterface 91 1 0
    //   90: invokeinterface 97 1 0
    //   95: sipush 200
    //   98: if_icmpne +218 -> 316
    //   101: aload_2
    //   102: astore_1
    //   103: aload_3
    //   104: invokeinterface 101 1 0
    //   109: astore_3
    //   110: aload_3
    //   111: ifnull +205 -> 316
    //   114: aload_2
    //   115: astore_1
    //   116: aload_3
    //   117: invokestatic 107	org/apache/http/util/EntityUtils:toByteArray	(Lorg/apache/http/HttpEntity;)[B
    //   120: astore_3
    //   121: aload_3
    //   122: ifnull +143 -> 265
    //   125: aload_2
    //   126: astore_1
    //   127: aload_3
    //   128: arraylength
    //   129: ifle +136 -> 265
    //   132: aload_2
    //   133: astore_1
    //   134: new 52	java/lang/String
    //   137: dup
    //   138: aload_3
    //   139: ldc 109
    //   141: invokespecial 112	java/lang/String:<init>	([BLjava/lang/String;)V
    //   144: astore_3
    //   145: aload_2
    //   146: astore_1
    //   147: aload_3
    //   148: invokestatic 118	android/text/TextUtils:isEmpty	(Ljava/lang/CharSequence;)Z
    //   151: ifne +63 -> 214
    //   154: aload_2
    //   155: astore_1
    //   156: new 120	org/json/JSONObject
    //   159: dup
    //   160: aload_3
    //   161: invokespecial 121	org/json/JSONObject:<init>	(Ljava/lang/String;)V
    //   164: astore_3
    //   165: aload_2
    //   166: astore_1
    //   167: ldc 123
    //   169: ldc 125
    //   171: invokestatic 130	com/tencent/tmassistantsdk/util/TMLog:i	(Ljava/lang/String;Ljava/lang/String;)V
    //   174: aload_2
    //   175: astore_1
    //   176: aload_0
    //   177: getfield 19	com/tencent/tmassistantsdk/network/GetHttpRequest$1:this$0	Lcom/tencent/tmassistantsdk/network/GetHttpRequest;
    //   180: aload_3
    //   181: iconst_0
    //   182: invokevirtual 134	com/tencent/tmassistantsdk/network/GetHttpRequest:onFinished	(Lorg/json/JSONObject;I)V
    //   185: aload_0
    //   186: getfield 19	com/tencent/tmassistantsdk/network/GetHttpRequest$1:this$0	Lcom/tencent/tmassistantsdk/network/GetHttpRequest;
    //   189: aconst_null
    //   190: putfield 48	com/tencent/tmassistantsdk/network/GetHttpRequest:mHttpGet	Lorg/apache/http/client/methods/HttpGet;
    //   193: aload_2
    //   194: ifnull +14 -> 208
    //   197: aload_2
    //   198: invokeinterface 138 1 0
    //   203: invokeinterface 143 1 0
    //   208: ldc 35
    //   210: invokestatic 146	com/tencent/matrix/trace/core/AppMethodBeat:o	(I)V
    //   213: return
    //   214: aload_2
    //   215: astore_1
    //   216: ldc 123
    //   218: ldc 148
    //   220: invokestatic 130	com/tencent/tmassistantsdk/util/TMLog:i	(Ljava/lang/String;Ljava/lang/String;)V
    //   223: aload_2
    //   224: astore_1
    //   225: aload_0
    //   226: getfield 19	com/tencent/tmassistantsdk/network/GetHttpRequest$1:this$0	Lcom/tencent/tmassistantsdk/network/GetHttpRequest;
    //   229: aconst_null
    //   230: sipush 606
    //   233: invokevirtual 134	com/tencent/tmassistantsdk/network/GetHttpRequest:onFinished	(Lorg/json/JSONObject;I)V
    //   236: aload_0
    //   237: getfield 19	com/tencent/tmassistantsdk/network/GetHttpRequest$1:this$0	Lcom/tencent/tmassistantsdk/network/GetHttpRequest;
    //   240: aconst_null
    //   241: putfield 48	com/tencent/tmassistantsdk/network/GetHttpRequest:mHttpGet	Lorg/apache/http/client/methods/HttpGet;
    //   244: aload_2
    //   245: ifnull +14 -> 259
    //   248: aload_2
    //   249: invokeinterface 138 1 0
    //   254: invokeinterface 143 1 0
    //   259: ldc 35
    //   261: invokestatic 146	com/tencent/matrix/trace/core/AppMethodBeat:o	(I)V
    //   264: return
    //   265: aload_2
    //   266: astore_1
    //   267: ldc 123
    //   269: ldc 150
    //   271: invokestatic 130	com/tencent/tmassistantsdk/util/TMLog:i	(Ljava/lang/String;Ljava/lang/String;)V
    //   274: aload_2
    //   275: astore_1
    //   276: aload_0
    //   277: getfield 19	com/tencent/tmassistantsdk/network/GetHttpRequest$1:this$0	Lcom/tencent/tmassistantsdk/network/GetHttpRequest;
    //   280: aconst_null
    //   281: sipush 704
    //   284: invokevirtual 134	com/tencent/tmassistantsdk/network/GetHttpRequest:onFinished	(Lorg/json/JSONObject;I)V
    //   287: aload_0
    //   288: getfield 19	com/tencent/tmassistantsdk/network/GetHttpRequest$1:this$0	Lcom/tencent/tmassistantsdk/network/GetHttpRequest;
    //   291: aconst_null
    //   292: putfield 48	com/tencent/tmassistantsdk/network/GetHttpRequest:mHttpGet	Lorg/apache/http/client/methods/HttpGet;
    //   295: aload_2
    //   296: ifnull +14 -> 310
    //   299: aload_2
    //   300: invokeinterface 138 1 0
    //   305: invokeinterface 143 1 0
    //   310: ldc 35
    //   312: invokestatic 146	com/tencent/matrix/trace/core/AppMethodBeat:o	(I)V
    //   315: return
    //   316: aload_2
    //   317: astore_1
    //   318: aload_0
    //   319: getfield 19	com/tencent/tmassistantsdk/network/GetHttpRequest$1:this$0	Lcom/tencent/tmassistantsdk/network/GetHttpRequest;
    //   322: aconst_null
    //   323: sipush 704
    //   326: invokevirtual 134	com/tencent/tmassistantsdk/network/GetHttpRequest:onFinished	(Lorg/json/JSONObject;I)V
    //   329: aload_0
    //   330: getfield 19	com/tencent/tmassistantsdk/network/GetHttpRequest$1:this$0	Lcom/tencent/tmassistantsdk/network/GetHttpRequest;
    //   333: aconst_null
    //   334: putfield 48	com/tencent/tmassistantsdk/network/GetHttpRequest:mHttpGet	Lorg/apache/http/client/methods/HttpGet;
    //   337: aload_2
    //   338: ifnull +287 -> 625
    //   341: aload_2
    //   342: invokeinterface 138 1 0
    //   347: invokeinterface 143 1 0
    //   352: ldc 35
    //   354: invokestatic 146	com/tencent/matrix/trace/core/AppMethodBeat:o	(I)V
    //   357: return
    //   358: astore_3
    //   359: aconst_null
    //   360: astore_2
    //   361: aload_2
    //   362: astore_1
    //   363: ldc 123
    //   365: aload_3
    //   366: ldc 152
    //   368: iconst_0
    //   369: anewarray 4	java/lang/Object
    //   372: invokestatic 158	com/tencent/mm/sdk/platformtools/ab:printErrStackTrace	(Ljava/lang/String;Ljava/lang/Throwable;Ljava/lang/String;[Ljava/lang/Object;)V
    //   375: aload_2
    //   376: astore_1
    //   377: aload_0
    //   378: getfield 19	com/tencent/tmassistantsdk/network/GetHttpRequest$1:this$0	Lcom/tencent/tmassistantsdk/network/GetHttpRequest;
    //   381: aconst_null
    //   382: sipush 601
    //   385: invokevirtual 134	com/tencent/tmassistantsdk/network/GetHttpRequest:onFinished	(Lorg/json/JSONObject;I)V
    //   388: aload_0
    //   389: getfield 19	com/tencent/tmassistantsdk/network/GetHttpRequest$1:this$0	Lcom/tencent/tmassistantsdk/network/GetHttpRequest;
    //   392: aconst_null
    //   393: putfield 48	com/tencent/tmassistantsdk/network/GetHttpRequest:mHttpGet	Lorg/apache/http/client/methods/HttpGet;
    //   396: aload_2
    //   397: ifnull +228 -> 625
    //   400: aload_2
    //   401: invokeinterface 138 1 0
    //   406: invokeinterface 143 1 0
    //   411: ldc 35
    //   413: invokestatic 146	com/tencent/matrix/trace/core/AppMethodBeat:o	(I)V
    //   416: return
    //   417: astore_3
    //   418: aconst_null
    //   419: astore_2
    //   420: aload_2
    //   421: astore_1
    //   422: ldc 123
    //   424: aload_3
    //   425: ldc 152
    //   427: iconst_0
    //   428: anewarray 4	java/lang/Object
    //   431: invokestatic 158	com/tencent/mm/sdk/platformtools/ab:printErrStackTrace	(Ljava/lang/String;Ljava/lang/Throwable;Ljava/lang/String;[Ljava/lang/Object;)V
    //   434: aload_2
    //   435: astore_1
    //   436: aload_0
    //   437: getfield 19	com/tencent/tmassistantsdk/network/GetHttpRequest$1:this$0	Lcom/tencent/tmassistantsdk/network/GetHttpRequest;
    //   440: aconst_null
    //   441: iconst_1
    //   442: invokevirtual 134	com/tencent/tmassistantsdk/network/GetHttpRequest:onFinished	(Lorg/json/JSONObject;I)V
    //   445: aload_0
    //   446: getfield 19	com/tencent/tmassistantsdk/network/GetHttpRequest$1:this$0	Lcom/tencent/tmassistantsdk/network/GetHttpRequest;
    //   449: aconst_null
    //   450: putfield 48	com/tencent/tmassistantsdk/network/GetHttpRequest:mHttpGet	Lorg/apache/http/client/methods/HttpGet;
    //   453: aload_2
    //   454: ifnull +171 -> 625
    //   457: aload_2
    //   458: invokeinterface 138 1 0
    //   463: invokeinterface 143 1 0
    //   468: ldc 35
    //   470: invokestatic 146	com/tencent/matrix/trace/core/AppMethodBeat:o	(I)V
    //   473: return
    //   474: astore_3
    //   475: aconst_null
    //   476: astore_2
    //   477: aload_2
    //   478: astore_1
    //   479: ldc 123
    //   481: aload_3
    //   482: ldc 152
    //   484: iconst_0
    //   485: anewarray 4	java/lang/Object
    //   488: invokestatic 158	com/tencent/mm/sdk/platformtools/ab:printErrStackTrace	(Ljava/lang/String;Ljava/lang/Throwable;Ljava/lang/String;[Ljava/lang/Object;)V
    //   491: aload_2
    //   492: astore_1
    //   493: aload_0
    //   494: getfield 19	com/tencent/tmassistantsdk/network/GetHttpRequest$1:this$0	Lcom/tencent/tmassistantsdk/network/GetHttpRequest;
    //   497: aconst_null
    //   498: sipush 602
    //   501: invokevirtual 134	com/tencent/tmassistantsdk/network/GetHttpRequest:onFinished	(Lorg/json/JSONObject;I)V
    //   504: aload_0
    //   505: getfield 19	com/tencent/tmassistantsdk/network/GetHttpRequest$1:this$0	Lcom/tencent/tmassistantsdk/network/GetHttpRequest;
    //   508: aconst_null
    //   509: putfield 48	com/tencent/tmassistantsdk/network/GetHttpRequest:mHttpGet	Lorg/apache/http/client/methods/HttpGet;
    //   512: aload_2
    //   513: ifnull +112 -> 625
    //   516: aload_2
    //   517: invokeinterface 138 1 0
    //   522: invokeinterface 143 1 0
    //   527: ldc 35
    //   529: invokestatic 146	com/tencent/matrix/trace/core/AppMethodBeat:o	(I)V
    //   532: return
    //   533: astore_3
    //   534: aconst_null
    //   535: astore_2
    //   536: aload_2
    //   537: astore_1
    //   538: ldc 123
    //   540: aload_3
    //   541: ldc 152
    //   543: iconst_0
    //   544: anewarray 4	java/lang/Object
    //   547: invokestatic 158	com/tencent/mm/sdk/platformtools/ab:printErrStackTrace	(Ljava/lang/String;Ljava/lang/Throwable;Ljava/lang/String;[Ljava/lang/Object;)V
    //   550: aload_2
    //   551: astore_1
    //   552: aload_0
    //   553: getfield 19	com/tencent/tmassistantsdk/network/GetHttpRequest$1:this$0	Lcom/tencent/tmassistantsdk/network/GetHttpRequest;
    //   556: aconst_null
    //   557: sipush 604
    //   560: invokevirtual 134	com/tencent/tmassistantsdk/network/GetHttpRequest:onFinished	(Lorg/json/JSONObject;I)V
    //   563: aload_0
    //   564: getfield 19	com/tencent/tmassistantsdk/network/GetHttpRequest$1:this$0	Lcom/tencent/tmassistantsdk/network/GetHttpRequest;
    //   567: aconst_null
    //   568: putfield 48	com/tencent/tmassistantsdk/network/GetHttpRequest:mHttpGet	Lorg/apache/http/client/methods/HttpGet;
    //   571: aload_2
    //   572: ifnull +53 -> 625
    //   575: aload_2
    //   576: invokeinterface 138 1 0
    //   581: invokeinterface 143 1 0
    //   586: ldc 35
    //   588: invokestatic 146	com/tencent/matrix/trace/core/AppMethodBeat:o	(I)V
    //   591: return
    //   592: astore_2
    //   593: aconst_null
    //   594: astore_1
    //   595: aload_0
    //   596: getfield 19	com/tencent/tmassistantsdk/network/GetHttpRequest$1:this$0	Lcom/tencent/tmassistantsdk/network/GetHttpRequest;
    //   599: aconst_null
    //   600: putfield 48	com/tencent/tmassistantsdk/network/GetHttpRequest:mHttpGet	Lorg/apache/http/client/methods/HttpGet;
    //   603: aload_1
    //   604: ifnull +14 -> 618
    //   607: aload_1
    //   608: invokeinterface 138 1 0
    //   613: invokeinterface 143 1 0
    //   618: ldc 35
    //   620: invokestatic 146	com/tencent/matrix/trace/core/AppMethodBeat:o	(I)V
    //   623: aload_2
    //   624: athrow
    //   625: ldc 35
    //   627: invokestatic 146	com/tencent/matrix/trace/core/AppMethodBeat:o	(I)V
    //   630: return
    //   631: astore_2
    //   632: goto -37 -> 595
    //   635: astore_3
    //   636: goto -100 -> 536
    //   639: astore_3
    //   640: goto -163 -> 477
    //   643: astore_3
    //   644: goto -224 -> 420
    //   647: astore_3
    //   648: goto -287 -> 361
    // Local variable table:
    //   start	length	slot	name	signature
    //   0	651	0	this	1
    //   9	599	1	localObject1	Object
    //   55	521	2	localHttpClient	org.apache.http.client.HttpClient
    //   592	32	2	localObject2	Object
    //   631	1	2	localObject3	Object
    //   77	104	3	localObject4	Object
    //   358	8	3	localConnectTimeoutException1	org.apache.http.conn.ConnectTimeoutException
    //   417	8	3	localConnectException1	java.net.ConnectException
    //   474	8	3	localSocketTimeoutException1	java.net.SocketTimeoutException
    //   533	8	3	localException1	java.lang.Exception
    //   635	1	3	localException2	java.lang.Exception
    //   639	1	3	localSocketTimeoutException2	java.net.SocketTimeoutException
    //   643	1	3	localConnectException2	java.net.ConnectException
    //   647	1	3	localConnectTimeoutException2	org.apache.http.conn.ConnectTimeoutException
    // Exception table:
    //   from	to	target	type
    //   10	56	358	org/apache/http/conn/ConnectTimeoutException
    //   10	56	417	java/net/ConnectException
    //   10	56	474	java/net/SocketTimeoutException
    //   10	56	533	java/lang/Exception
    //   10	56	592	finally
    //   58	62	631	finally
    //   64	78	631	finally
    //   84	101	631	finally
    //   103	110	631	finally
    //   116	121	631	finally
    //   127	132	631	finally
    //   134	145	631	finally
    //   147	154	631	finally
    //   156	165	631	finally
    //   167	174	631	finally
    //   176	185	631	finally
    //   216	223	631	finally
    //   225	236	631	finally
    //   267	274	631	finally
    //   276	287	631	finally
    //   318	329	631	finally
    //   363	375	631	finally
    //   377	388	631	finally
    //   422	434	631	finally
    //   436	445	631	finally
    //   479	491	631	finally
    //   493	504	631	finally
    //   538	550	631	finally
    //   552	563	631	finally
    //   58	62	635	java/lang/Exception
    //   64	78	635	java/lang/Exception
    //   84	101	635	java/lang/Exception
    //   103	110	635	java/lang/Exception
    //   116	121	635	java/lang/Exception
    //   127	132	635	java/lang/Exception
    //   134	145	635	java/lang/Exception
    //   147	154	635	java/lang/Exception
    //   156	165	635	java/lang/Exception
    //   167	174	635	java/lang/Exception
    //   176	185	635	java/lang/Exception
    //   216	223	635	java/lang/Exception
    //   225	236	635	java/lang/Exception
    //   267	274	635	java/lang/Exception
    //   276	287	635	java/lang/Exception
    //   318	329	635	java/lang/Exception
    //   58	62	639	java/net/SocketTimeoutException
    //   64	78	639	java/net/SocketTimeoutException
    //   84	101	639	java/net/SocketTimeoutException
    //   103	110	639	java/net/SocketTimeoutException
    //   116	121	639	java/net/SocketTimeoutException
    //   127	132	639	java/net/SocketTimeoutException
    //   134	145	639	java/net/SocketTimeoutException
    //   147	154	639	java/net/SocketTimeoutException
    //   156	165	639	java/net/SocketTimeoutException
    //   167	174	639	java/net/SocketTimeoutException
    //   176	185	639	java/net/SocketTimeoutException
    //   216	223	639	java/net/SocketTimeoutException
    //   225	236	639	java/net/SocketTimeoutException
    //   267	274	639	java/net/SocketTimeoutException
    //   276	287	639	java/net/SocketTimeoutException
    //   318	329	639	java/net/SocketTimeoutException
    //   58	62	643	java/net/ConnectException
    //   64	78	643	java/net/ConnectException
    //   84	101	643	java/net/ConnectException
    //   103	110	643	java/net/ConnectException
    //   116	121	643	java/net/ConnectException
    //   127	132	643	java/net/ConnectException
    //   134	145	643	java/net/ConnectException
    //   147	154	643	java/net/ConnectException
    //   156	165	643	java/net/ConnectException
    //   167	174	643	java/net/ConnectException
    //   176	185	643	java/net/ConnectException
    //   216	223	643	java/net/ConnectException
    //   225	236	643	java/net/ConnectException
    //   267	274	643	java/net/ConnectException
    //   276	287	643	java/net/ConnectException
    //   318	329	643	java/net/ConnectException
    //   58	62	647	org/apache/http/conn/ConnectTimeoutException
    //   64	78	647	org/apache/http/conn/ConnectTimeoutException
    //   84	101	647	org/apache/http/conn/ConnectTimeoutException
    //   103	110	647	org/apache/http/conn/ConnectTimeoutException
    //   116	121	647	org/apache/http/conn/ConnectTimeoutException
    //   127	132	647	org/apache/http/conn/ConnectTimeoutException
    //   134	145	647	org/apache/http/conn/ConnectTimeoutException
    //   147	154	647	org/apache/http/conn/ConnectTimeoutException
    //   156	165	647	org/apache/http/conn/ConnectTimeoutException
    //   167	174	647	org/apache/http/conn/ConnectTimeoutException
    //   176	185	647	org/apache/http/conn/ConnectTimeoutException
    //   216	223	647	org/apache/http/conn/ConnectTimeoutException
    //   225	236	647	org/apache/http/conn/ConnectTimeoutException
    //   267	274	647	org/apache/http/conn/ConnectTimeoutException
    //   276	287	647	org/apache/http/conn/ConnectTimeoutException
    //   318	329	647	org/apache/http/conn/ConnectTimeoutException
  }
}


/* Location:           L:\local\mybackup\temp\qq_apk\com.tencent.mm\classes5.jar
 * Qualified Name:     com.tencent.tmassistantsdk.network.GetHttpRequest.1
 * JD-Core Version:    0.7.0.1
 */