package com.tencent.luggage.wxa.nz;

import com.tencent.luggage.wxa.qz.af;

public class g$b
  implements Runnable
{
  private h b;
  
  public g$b(g paramg, h paramh)
  {
    this.b = paramh;
  }
  
  private String a(String paramString1, String paramString2)
  {
    String str = paramString1;
    if (af.c(paramString1)) {
      str = paramString2;
    }
    return str;
  }
  
  /* Error */
  private void a(h paramh)
  {
    // Byte code:
    //   0: aload_1
    //   1: invokevirtual 49	com/tencent/luggage/wxa/nz/h:b	()Ljava/lang/String;
    //   4: astore 29
    //   6: aload 29
    //   8: astore 26
    //   10: aload_1
    //   11: invokevirtual 51	com/tencent/luggage/wxa/nz/h:a	()Ljava/lang/String;
    //   14: astore 30
    //   16: aload_1
    //   17: invokevirtual 54	com/tencent/luggage/wxa/nz/h:d	()Ljava/lang/String;
    //   20: astore 46
    //   22: aload_0
    //   23: aload_1
    //   24: invokevirtual 57	com/tencent/luggage/wxa/nz/h:f	()Ljava/lang/String;
    //   27: ldc 59
    //   29: invokespecial 61	com/tencent/luggage/wxa/nz/g$b:a	(Ljava/lang/String;Ljava/lang/String;)Ljava/lang/String;
    //   32: astore 28
    //   34: aload_1
    //   35: invokevirtual 64	com/tencent/luggage/wxa/nz/h:e	()Ljava/lang/String;
    //   38: astore 38
    //   40: ldc 66
    //   42: astore 25
    //   44: ldc 68
    //   46: ldc 70
    //   48: iconst_1
    //   49: anewarray 4	java/lang/Object
    //   52: dup
    //   53: iconst_0
    //   54: aload 38
    //   56: aastore
    //   57: invokestatic 75	com/tencent/luggage/wxa/qz/o:f	(Ljava/lang/String;Ljava/lang/String;[Ljava/lang/Object;)V
    //   60: aload_1
    //   61: invokevirtual 79	com/tencent/luggage/wxa/nz/h:g	()Ljava/util/Map;
    //   64: astore 40
    //   66: aload_1
    //   67: invokevirtual 82	com/tencent/luggage/wxa/nz/h:h	()Ljava/util/Map;
    //   70: astore 39
    //   72: ldc 84
    //   74: astore 24
    //   76: aload_1
    //   77: invokevirtual 87	com/tencent/luggage/wxa/nz/h:c	()Lcom/tencent/luggage/wxa/nz/g$a;
    //   80: astore 21
    //   82: ldc 89
    //   84: astore 23
    //   86: aload_1
    //   87: invokevirtual 93	com/tencent/luggage/wxa/nz/h:j	()Ljava/util/ArrayList;
    //   90: astore 44
    //   92: aload 44
    //   94: ifnull +94 -> 188
    //   97: aload 44
    //   99: aload 26
    //   101: invokestatic 98	com/tencent/luggage/wxa/nz/j:a	(Ljava/util/ArrayList;Ljava/lang/String;)Z
    //   104: ifne +84 -> 188
    //   107: aload_0
    //   108: getfield 14	com/tencent/luggage/wxa/nz/g$b:a	Lcom/tencent/luggage/wxa/nz/g;
    //   111: aload 21
    //   113: iconst_m1
    //   114: ldc 100
    //   116: aload_1
    //   117: invokevirtual 103	com/tencent/luggage/wxa/nz/h:l	()Ljava/lang/String;
    //   120: aconst_null
    //   121: invokestatic 108	com/tencent/luggage/wxa/nz/g:a	(Lcom/tencent/luggage/wxa/nz/g;Lcom/tencent/luggage/wxa/nz/g$a;ILjava/lang/String;Ljava/lang/String;Ljava/net/HttpURLConnection;)V
    //   124: ldc 110
    //   126: invokestatic 115	com/tencent/luggage/wxa/ba/e:b	(Ljava/lang/Class;)Lcom/tencent/luggage/wxa/ba/d;
    //   129: checkcast 110	com/tencent/luggage/wxa/nz/o
    //   132: aload_0
    //   133: getfield 14	com/tencent/luggage/wxa/nz/g$b:a	Lcom/tencent/luggage/wxa/nz/g;
    //   136: invokestatic 118	com/tencent/luggage/wxa/nz/g:a	(Lcom/tencent/luggage/wxa/nz/g;)Lcom/tencent/luggage/wxa/jx/c;
    //   139: invokeinterface 123 1 0
    //   144: aload_1
    //   145: invokevirtual 126	com/tencent/luggage/wxa/nz/h:n	()Ljava/lang/String;
    //   148: ldc 128
    //   150: aload_1
    //   151: invokevirtual 49	com/tencent/luggage/wxa/nz/h:b	()Ljava/lang/String;
    //   154: lconst_0
    //   155: iconst_0
    //   156: i2l
    //   157: iconst_0
    //   158: iconst_2
    //   159: aload_1
    //   160: invokevirtual 132	com/tencent/luggage/wxa/nz/h:o	()I
    //   163: aconst_null
    //   164: aload 28
    //   166: invokeinterface 135 14 0
    //   171: ldc 68
    //   173: ldc 137
    //   175: iconst_1
    //   176: anewarray 4	java/lang/Object
    //   179: dup
    //   180: iconst_0
    //   181: aload 26
    //   183: aastore
    //   184: invokestatic 139	com/tencent/luggage/wxa/qz/o:d	(Ljava/lang/String;Ljava/lang/String;[Ljava/lang/Object;)V
    //   187: return
    //   188: aload_1
    //   189: getfield 142	com/tencent/luggage/wxa/nz/h:a	Z
    //   192: ifne +75 -> 267
    //   195: aload_0
    //   196: getfield 14	com/tencent/luggage/wxa/nz/g$b:a	Lcom/tencent/luggage/wxa/nz/g;
    //   199: aload 21
    //   201: iconst_m1
    //   202: ldc 144
    //   204: aload_1
    //   205: invokevirtual 103	com/tencent/luggage/wxa/nz/h:l	()Ljava/lang/String;
    //   208: aconst_null
    //   209: invokestatic 108	com/tencent/luggage/wxa/nz/g:a	(Lcom/tencent/luggage/wxa/nz/g;Lcom/tencent/luggage/wxa/nz/g$a;ILjava/lang/String;Ljava/lang/String;Ljava/net/HttpURLConnection;)V
    //   212: ldc 110
    //   214: invokestatic 115	com/tencent/luggage/wxa/ba/e:b	(Ljava/lang/Class;)Lcom/tencent/luggage/wxa/ba/d;
    //   217: checkcast 110	com/tencent/luggage/wxa/nz/o
    //   220: aload_0
    //   221: getfield 14	com/tencent/luggage/wxa/nz/g$b:a	Lcom/tencent/luggage/wxa/nz/g;
    //   224: invokestatic 118	com/tencent/luggage/wxa/nz/g:a	(Lcom/tencent/luggage/wxa/nz/g;)Lcom/tencent/luggage/wxa/jx/c;
    //   227: invokeinterface 123 1 0
    //   232: aload_1
    //   233: invokevirtual 126	com/tencent/luggage/wxa/nz/h:n	()Ljava/lang/String;
    //   236: ldc 128
    //   238: aload_1
    //   239: invokevirtual 49	com/tencent/luggage/wxa/nz/h:b	()Ljava/lang/String;
    //   242: lconst_0
    //   243: iconst_0
    //   244: i2l
    //   245: iconst_0
    //   246: iconst_2
    //   247: aload_1
    //   248: invokevirtual 132	com/tencent/luggage/wxa/nz/h:o	()I
    //   251: aconst_null
    //   252: aload 28
    //   254: invokeinterface 135 14 0
    //   259: ldc 68
    //   261: ldc 146
    //   263: invokestatic 149	com/tencent/luggage/wxa/qz/o:b	(Ljava/lang/String;Ljava/lang/String;)V
    //   266: return
    //   267: aload_1
    //   268: invokevirtual 49	com/tencent/luggage/wxa/nz/h:b	()Ljava/lang/String;
    //   271: invokestatic 154	android/webkit/URLUtil:isHttpsUrl	(Ljava/lang/String;)Z
    //   274: istore 11
    //   276: lconst_0
    //   277: lstore 12
    //   279: iload 11
    //   281: ifne +78 -> 359
    //   284: aload_1
    //   285: invokevirtual 49	com/tencent/luggage/wxa/nz/h:b	()Ljava/lang/String;
    //   288: invokestatic 157	android/webkit/URLUtil:isHttpUrl	(Ljava/lang/String;)Z
    //   291: ifne +68 -> 359
    //   294: aload_0
    //   295: getfield 14	com/tencent/luggage/wxa/nz/g$b:a	Lcom/tencent/luggage/wxa/nz/g;
    //   298: aload 21
    //   300: iconst_m1
    //   301: ldc 159
    //   303: aload_1
    //   304: invokevirtual 103	com/tencent/luggage/wxa/nz/h:l	()Ljava/lang/String;
    //   307: aconst_null
    //   308: invokestatic 108	com/tencent/luggage/wxa/nz/g:a	(Lcom/tencent/luggage/wxa/nz/g;Lcom/tencent/luggage/wxa/nz/g$a;ILjava/lang/String;Ljava/lang/String;Ljava/net/HttpURLConnection;)V
    //   311: ldc 110
    //   313: invokestatic 115	com/tencent/luggage/wxa/ba/e:b	(Ljava/lang/Class;)Lcom/tencent/luggage/wxa/ba/d;
    //   316: checkcast 110	com/tencent/luggage/wxa/nz/o
    //   319: aload_0
    //   320: getfield 14	com/tencent/luggage/wxa/nz/g$b:a	Lcom/tencent/luggage/wxa/nz/g;
    //   323: invokestatic 118	com/tencent/luggage/wxa/nz/g:a	(Lcom/tencent/luggage/wxa/nz/g;)Lcom/tencent/luggage/wxa/jx/c;
    //   326: invokeinterface 123 1 0
    //   331: aload_1
    //   332: invokevirtual 126	com/tencent/luggage/wxa/nz/h:n	()Ljava/lang/String;
    //   335: ldc 128
    //   337: aload_1
    //   338: invokevirtual 49	com/tencent/luggage/wxa/nz/h:b	()Ljava/lang/String;
    //   341: lconst_0
    //   342: iconst_0
    //   343: i2l
    //   344: iconst_0
    //   345: iconst_2
    //   346: aload_1
    //   347: invokevirtual 132	com/tencent/luggage/wxa/nz/h:o	()I
    //   350: aconst_null
    //   351: aload 28
    //   353: invokeinterface 135 14 0
    //   358: return
    //   359: invokestatic 165	java/lang/System:currentTimeMillis	()J
    //   362: invokestatic 171	java/lang/Long:toString	(J)Ljava/lang/String;
    //   365: astore 42
    //   367: aconst_null
    //   368: astore 41
    //   370: aload 28
    //   372: astore 27
    //   374: ldc 173
    //   376: invokestatic 115	com/tencent/luggage/wxa/ba/e:b	(Ljava/lang/Class;)Lcom/tencent/luggage/wxa/ba/d;
    //   379: checkcast 173	com/tencent/luggage/wxa/ot/c
    //   382: ldc2_w 174
    //   385: lconst_0
    //   386: lconst_1
    //   387: iconst_0
    //   388: invokeinterface 178 8 0
    //   393: new 180	com/tencent/luggage/wxa/rt/i
    //   396: dup
    //   397: aload 30
    //   399: invokespecial 183	com/tencent/luggage/wxa/rt/i:<init>	(Ljava/lang/String;)V
    //   402: astore 43
    //   404: aload 30
    //   406: astore 22
    //   408: aload 43
    //   410: invokestatic 188	com/tencent/luggage/wxa/rt/k:a	(Lcom/tencent/luggage/wxa/rt/i;)Ljava/io/InputStream;
    //   413: astore 20
    //   415: new 190	java/net/URL
    //   418: dup
    //   419: aload 26
    //   421: invokespecial 191	java/net/URL:<init>	(Ljava/lang/String;)V
    //   424: astore 37
    //   426: aload 37
    //   428: invokevirtual 195	java/net/URL:openConnection	()Ljava/net/URLConnection;
    //   431: astore 29
    //   433: aload 29
    //   435: checkcast 197	java/net/HttpURLConnection
    //   438: astore 29
    //   440: aload_1
    //   441: invokevirtual 103	com/tencent/luggage/wxa/nz/h:l	()Ljava/lang/String;
    //   444: invokestatic 27	com/tencent/luggage/wxa/qz/af:c	(Ljava/lang/String;)Z
    //   447: istore 11
    //   449: iload 11
    //   451: ifne +343 -> 794
    //   454: aload_1
    //   455: aload 29
    //   457: invokevirtual 200	com/tencent/luggage/wxa/nz/h:a	(Ljava/net/HttpURLConnection;)V
    //   460: goto +334 -> 794
    //   463: astore 29
    //   465: aload 26
    //   467: astore 31
    //   469: lconst_0
    //   470: lstore 12
    //   472: aconst_null
    //   473: astore 26
    //   475: aload 26
    //   477: astore 28
    //   479: aload 23
    //   481: astore 21
    //   483: aload 20
    //   485: astore 30
    //   487: iconst_0
    //   488: istore_2
    //   489: iconst_0
    //   490: istore_3
    //   491: aload 29
    //   493: astore 20
    //   495: aload 25
    //   497: astore 32
    //   499: aload 24
    //   501: astore 29
    //   503: aload 31
    //   505: astore 23
    //   507: goto +10399 -> 10906
    //   510: astore 22
    //   512: aload 26
    //   514: astore 28
    //   516: ldc 202
    //   518: astore 33
    //   520: aload 20
    //   522: astore 26
    //   524: aload 30
    //   526: astore 25
    //   528: aload 29
    //   530: astore 24
    //   532: aconst_null
    //   533: astore 23
    //   535: ldc 84
    //   537: astore 31
    //   539: ldc 89
    //   541: astore 29
    //   543: ldc 66
    //   545: astore 32
    //   547: aload 22
    //   549: astore 20
    //   551: aload 29
    //   553: astore 22
    //   555: aload 33
    //   557: astore 29
    //   559: goto +7364 -> 7923
    //   562: astore 38
    //   564: aconst_null
    //   565: astore 31
    //   567: aload 31
    //   569: astore 37
    //   571: iconst_0
    //   572: istore 4
    //   574: iconst_0
    //   575: istore 5
    //   577: aload 25
    //   579: astore 30
    //   581: aload 21
    //   583: astore 39
    //   585: aload 23
    //   587: astore 33
    //   589: aload 24
    //   591: astore 32
    //   593: aload 29
    //   595: astore 40
    //   597: lload 12
    //   599: lstore 14
    //   601: aload 27
    //   603: astore 35
    //   605: aload 22
    //   607: astore 29
    //   609: aload 20
    //   611: astore 36
    //   613: aload 26
    //   615: astore 34
    //   617: goto +7927 -> 8544
    //   620: astore 38
    //   622: aconst_null
    //   623: astore 31
    //   625: aload 31
    //   627: astore 37
    //   629: iconst_0
    //   630: istore 4
    //   632: iconst_0
    //   633: istore 5
    //   635: aload 25
    //   637: astore 30
    //   639: aload 21
    //   641: astore 39
    //   643: aload 23
    //   645: astore 33
    //   647: aload 24
    //   649: astore 32
    //   651: aload 29
    //   653: astore 40
    //   655: lload 12
    //   657: lstore 14
    //   659: aload 27
    //   661: astore 35
    //   663: aload 22
    //   665: astore 29
    //   667: aload 20
    //   669: astore 36
    //   671: aload 26
    //   673: astore 34
    //   675: goto +8468 -> 9143
    //   678: astore 38
    //   680: aconst_null
    //   681: astore 31
    //   683: aload 31
    //   685: astore 37
    //   687: iconst_0
    //   688: istore 4
    //   690: iconst_0
    //   691: istore 5
    //   693: aload 25
    //   695: astore 30
    //   697: aload 21
    //   699: astore 39
    //   701: aload 23
    //   703: astore 33
    //   705: aload 24
    //   707: astore 32
    //   709: aload 29
    //   711: astore 40
    //   713: lload 12
    //   715: lstore 14
    //   717: aload 27
    //   719: astore 35
    //   721: aload 22
    //   723: astore 29
    //   725: aload 20
    //   727: astore 36
    //   729: aload 26
    //   731: astore 34
    //   733: goto +9009 -> 9742
    //   736: astore 38
    //   738: aconst_null
    //   739: astore 31
    //   741: aload 31
    //   743: astore 35
    //   745: iconst_0
    //   746: istore 4
    //   748: iconst_0
    //   749: istore 5
    //   751: aload 25
    //   753: astore 34
    //   755: aload 21
    //   757: astore 39
    //   759: aload 23
    //   761: astore 33
    //   763: aload 24
    //   765: astore 32
    //   767: aload 29
    //   769: astore 40
    //   771: lload 12
    //   773: lstore 14
    //   775: aload 27
    //   777: astore 36
    //   779: aload 22
    //   781: astore 29
    //   783: aload 20
    //   785: astore 37
    //   787: aload 26
    //   789: astore 30
    //   791: goto +9583 -> 10374
    //   794: aload 29
    //   796: instanceof 204
    //   799: istore 11
    //   801: iload 11
    //   803: ifeq +337 -> 1140
    //   806: aload 26
    //   808: astore 36
    //   810: aload 26
    //   812: astore 31
    //   814: aload 26
    //   816: astore 32
    //   818: aload 26
    //   820: astore 33
    //   822: aload 26
    //   824: astore 34
    //   826: aload 26
    //   828: astore 35
    //   830: aload_0
    //   831: getfield 14	com/tencent/luggage/wxa/nz/g$b:a	Lcom/tencent/luggage/wxa/nz/g;
    //   834: invokestatic 207	com/tencent/luggage/wxa/nz/g:b	(Lcom/tencent/luggage/wxa/nz/g;)Ljavax/net/ssl/SSLContext;
    //   837: ifnull +303 -> 1140
    //   840: aload 26
    //   842: astore 36
    //   844: aload 26
    //   846: astore 31
    //   848: aload 26
    //   850: astore 32
    //   852: aload 26
    //   854: astore 33
    //   856: aload 26
    //   858: astore 34
    //   860: aload 26
    //   862: astore 35
    //   864: aload 29
    //   866: checkcast 204	javax/net/ssl/HttpsURLConnection
    //   869: aload_0
    //   870: getfield 14	com/tencent/luggage/wxa/nz/g$b:a	Lcom/tencent/luggage/wxa/nz/g;
    //   873: invokestatic 207	com/tencent/luggage/wxa/nz/g:b	(Lcom/tencent/luggage/wxa/nz/g;)Ljavax/net/ssl/SSLContext;
    //   876: invokevirtual 213	javax/net/ssl/SSLContext:getSocketFactory	()Ljavax/net/ssl/SSLSocketFactory;
    //   879: invokevirtual 217	javax/net/ssl/HttpsURLConnection:setSSLSocketFactory	(Ljavax/net/ssl/SSLSocketFactory;)V
    //   882: aload 26
    //   884: astore 36
    //   886: aload 26
    //   888: astore 31
    //   890: aload 26
    //   892: astore 32
    //   894: aload 26
    //   896: astore 33
    //   898: aload 26
    //   900: astore 34
    //   902: aload 26
    //   904: astore 35
    //   906: aload 29
    //   908: aload 44
    //   910: invokestatic 220	com/tencent/luggage/wxa/nz/j:a	(Ljava/net/HttpURLConnection;Ljava/util/ArrayList;)V
    //   913: goto +227 -> 1140
    //   916: astore 21
    //   918: lconst_0
    //   919: lstore 12
    //   921: aconst_null
    //   922: astore 28
    //   924: aload 23
    //   926: astore 26
    //   928: aload 20
    //   930: astore 23
    //   932: aload 21
    //   934: astore 20
    //   936: aload 25
    //   938: astore 32
    //   940: aload 26
    //   942: astore 21
    //   944: aload 24
    //   946: astore 31
    //   948: aload 36
    //   950: astore 24
    //   952: goto +6909 -> 7861
    //   955: astore 22
    //   957: aload 31
    //   959: astore 26
    //   961: goto -449 -> 512
    //   964: astore 28
    //   966: aload 32
    //   968: astore 26
    //   970: aconst_null
    //   971: astore 30
    //   973: aload 25
    //   975: astore 32
    //   977: aload 24
    //   979: astore 31
    //   981: aload 22
    //   983: astore 24
    //   985: aload 20
    //   987: astore 25
    //   989: aload 28
    //   991: astore 20
    //   993: aload 23
    //   995: astore 22
    //   997: aload 30
    //   999: astore 28
    //   1001: aload 29
    //   1003: astore 23
    //   1005: goto +7464 -> 8469
    //   1008: astore 28
    //   1010: aload 33
    //   1012: astore 26
    //   1014: aconst_null
    //   1015: astore 30
    //   1017: aload 25
    //   1019: astore 32
    //   1021: aload 24
    //   1023: astore 31
    //   1025: aload 22
    //   1027: astore 24
    //   1029: aload 20
    //   1031: astore 25
    //   1033: aload 28
    //   1035: astore 20
    //   1037: aload 23
    //   1039: astore 22
    //   1041: aload 30
    //   1043: astore 28
    //   1045: aload 29
    //   1047: astore 23
    //   1049: goto +8019 -> 9068
    //   1052: astore 28
    //   1054: aload 34
    //   1056: astore 26
    //   1058: aconst_null
    //   1059: astore 30
    //   1061: aload 25
    //   1063: astore 32
    //   1065: aload 24
    //   1067: astore 31
    //   1069: aload 22
    //   1071: astore 24
    //   1073: aload 20
    //   1075: astore 25
    //   1077: aload 28
    //   1079: astore 20
    //   1081: aload 23
    //   1083: astore 22
    //   1085: aload 30
    //   1087: astore 28
    //   1089: aload 29
    //   1091: astore 23
    //   1093: goto +8574 -> 9667
    //   1096: astore 28
    //   1098: aload 35
    //   1100: astore 26
    //   1102: aconst_null
    //   1103: astore 30
    //   1105: aload 25
    //   1107: astore 32
    //   1109: aload 24
    //   1111: astore 31
    //   1113: aload 22
    //   1115: astore 24
    //   1117: aload 20
    //   1119: astore 25
    //   1121: aload 28
    //   1123: astore 20
    //   1125: aload 23
    //   1127: astore 22
    //   1129: aload 30
    //   1131: astore 28
    //   1133: aload 29
    //   1135: astore 23
    //   1137: goto +9162 -> 10299
    //   1140: aload 29
    //   1142: iconst_1
    //   1143: invokevirtual 224	java/net/HttpURLConnection:setDoInput	(Z)V
    //   1146: aload 29
    //   1148: iconst_1
    //   1149: invokevirtual 227	java/net/HttpURLConnection:setDoOutput	(Z)V
    //   1152: aload 29
    //   1154: iconst_0
    //   1155: invokevirtual 230	java/net/HttpURLConnection:setUseCaches	(Z)V
    //   1158: aload 29
    //   1160: aload_1
    //   1161: invokevirtual 233	com/tencent/luggage/wxa/nz/h:i	()I
    //   1164: invokevirtual 237	java/net/HttpURLConnection:setConnectTimeout	(I)V
    //   1167: aload 29
    //   1169: aload_1
    //   1170: invokevirtual 233	com/tencent/luggage/wxa/nz/h:i	()I
    //   1173: invokevirtual 240	java/net/HttpURLConnection:setReadTimeout	(I)V
    //   1176: aload 29
    //   1178: ldc 128
    //   1180: invokevirtual 243	java/net/HttpURLConnection:setRequestMethod	(Ljava/lang/String;)V
    //   1183: aload 29
    //   1185: ldc 245
    //   1187: ldc 247
    //   1189: invokevirtual 250	java/net/HttpURLConnection:setRequestProperty	(Ljava/lang/String;Ljava/lang/String;)V
    //   1192: aload 29
    //   1194: ldc 252
    //   1196: ldc 254
    //   1198: invokevirtual 250	java/net/HttpURLConnection:setRequestProperty	(Ljava/lang/String;Ljava/lang/String;)V
    //   1201: ldc 68
    //   1203: ldc_w 256
    //   1206: iconst_2
    //   1207: anewarray 4	java/lang/Object
    //   1210: dup
    //   1211: iconst_0
    //   1212: aload 43
    //   1214: invokevirtual 257	com/tencent/luggage/wxa/rt/i:l	()Ljava/lang/String;
    //   1217: aastore
    //   1218: dup
    //   1219: iconst_1
    //   1220: aload 43
    //   1222: invokevirtual 260	com/tencent/luggage/wxa/rt/i:q	()J
    //   1225: invokestatic 264	java/lang/Long:valueOf	(J)Ljava/lang/Long;
    //   1228: aastore
    //   1229: invokestatic 139	com/tencent/luggage/wxa/qz/o:d	(Ljava/lang/String;Ljava/lang/String;[Ljava/lang/Object;)V
    //   1232: aload 29
    //   1234: iconst_0
    //   1235: invokevirtual 267	java/net/HttpURLConnection:setInstanceFollowRedirects	(Z)V
    //   1238: aload 39
    //   1240: ifnull +426 -> 1666
    //   1243: aload 26
    //   1245: astore 36
    //   1247: aload 26
    //   1249: astore 31
    //   1251: aload 26
    //   1253: astore 32
    //   1255: aload 26
    //   1257: astore 33
    //   1259: aload 26
    //   1261: astore 34
    //   1263: aload 26
    //   1265: astore 35
    //   1267: ldc 68
    //   1269: ldc_w 269
    //   1272: iconst_1
    //   1273: anewarray 4	java/lang/Object
    //   1276: dup
    //   1277: iconst_0
    //   1278: aload 26
    //   1280: aastore
    //   1281: invokestatic 139	com/tencent/luggage/wxa/qz/o:d	(Ljava/lang/String;Ljava/lang/String;[Ljava/lang/Object;)V
    //   1284: aload 26
    //   1286: astore 36
    //   1288: aload 26
    //   1290: astore 31
    //   1292: aload 26
    //   1294: astore 32
    //   1296: aload 26
    //   1298: astore 33
    //   1300: aload 26
    //   1302: astore 34
    //   1304: aload 26
    //   1306: astore 35
    //   1308: aload 39
    //   1310: invokeinterface 275 1 0
    //   1315: invokeinterface 281 1 0
    //   1320: astore 39
    //   1322: aload 26
    //   1324: astore 36
    //   1326: aload 26
    //   1328: astore 31
    //   1330: aload 26
    //   1332: astore 32
    //   1334: aload 26
    //   1336: astore 33
    //   1338: aload 26
    //   1340: astore 34
    //   1342: aload 26
    //   1344: astore 35
    //   1346: aload 39
    //   1348: invokeinterface 287 1 0
    //   1353: ifeq +313 -> 1666
    //   1356: aload 26
    //   1358: astore 36
    //   1360: aload 26
    //   1362: astore 31
    //   1364: aload 26
    //   1366: astore 32
    //   1368: aload 26
    //   1370: astore 33
    //   1372: aload 26
    //   1374: astore 34
    //   1376: aload 26
    //   1378: astore 35
    //   1380: aload 39
    //   1382: invokeinterface 291 1 0
    //   1387: checkcast 293	java/util/Map$Entry
    //   1390: astore 44
    //   1392: aload 26
    //   1394: astore 36
    //   1396: aload 26
    //   1398: astore 31
    //   1400: aload 26
    //   1402: astore 32
    //   1404: aload 26
    //   1406: astore 33
    //   1408: aload 26
    //   1410: astore 34
    //   1412: aload 26
    //   1414: astore 35
    //   1416: ldc 68
    //   1418: ldc_w 295
    //   1421: iconst_3
    //   1422: anewarray 4	java/lang/Object
    //   1425: dup
    //   1426: iconst_0
    //   1427: aload 26
    //   1429: aastore
    //   1430: dup
    //   1431: iconst_1
    //   1432: aload 44
    //   1434: invokeinterface 298 1 0
    //   1439: aastore
    //   1440: dup
    //   1441: iconst_2
    //   1442: aload 44
    //   1444: invokeinterface 301 1 0
    //   1449: aastore
    //   1450: invokestatic 139	com/tencent/luggage/wxa/qz/o:d	(Ljava/lang/String;Ljava/lang/String;[Ljava/lang/Object;)V
    //   1453: aload 26
    //   1455: astore 36
    //   1457: aload 26
    //   1459: astore 31
    //   1461: aload 26
    //   1463: astore 32
    //   1465: aload 26
    //   1467: astore 33
    //   1469: aload 26
    //   1471: astore 34
    //   1473: aload 26
    //   1475: astore 35
    //   1477: aload 44
    //   1479: invokeinterface 298 1 0
    //   1484: checkcast 303	java/lang/String
    //   1487: invokestatic 27	com/tencent/luggage/wxa/qz/af:c	(Ljava/lang/String;)Z
    //   1490: ifne -168 -> 1322
    //   1493: aload 26
    //   1495: astore 36
    //   1497: aload 26
    //   1499: astore 31
    //   1501: aload 26
    //   1503: astore 32
    //   1505: aload 26
    //   1507: astore 33
    //   1509: aload 26
    //   1511: astore 34
    //   1513: aload 26
    //   1515: astore 35
    //   1517: aload 44
    //   1519: invokeinterface 301 1 0
    //   1524: checkcast 303	java/lang/String
    //   1527: invokestatic 27	com/tencent/luggage/wxa/qz/af:c	(Ljava/lang/String;)Z
    //   1530: ifne -208 -> 1322
    //   1533: aload 26
    //   1535: astore 36
    //   1537: aload 26
    //   1539: astore 31
    //   1541: aload 26
    //   1543: astore 32
    //   1545: aload 26
    //   1547: astore 33
    //   1549: aload 26
    //   1551: astore 34
    //   1553: aload 26
    //   1555: astore 35
    //   1557: aload 44
    //   1559: invokeinterface 298 1 0
    //   1564: checkcast 303	java/lang/String
    //   1567: invokevirtual 306	java/lang/String:toLowerCase	()Ljava/lang/String;
    //   1570: ldc_w 308
    //   1573: invokevirtual 312	java/lang/String:contains	(Ljava/lang/CharSequence;)Z
    //   1576: ifeq +38 -> 1614
    //   1579: aload 26
    //   1581: astore 36
    //   1583: aload 26
    //   1585: astore 31
    //   1587: aload 26
    //   1589: astore 32
    //   1591: aload 26
    //   1593: astore 33
    //   1595: aload 26
    //   1597: astore 34
    //   1599: aload 26
    //   1601: astore 35
    //   1603: ldc 68
    //   1605: ldc_w 314
    //   1608: invokestatic 149	com/tencent/luggage/wxa/qz/o:b	(Ljava/lang/String;Ljava/lang/String;)V
    //   1611: goto -289 -> 1322
    //   1614: aload 26
    //   1616: astore 36
    //   1618: aload 26
    //   1620: astore 31
    //   1622: aload 26
    //   1624: astore 32
    //   1626: aload 26
    //   1628: astore 33
    //   1630: aload 26
    //   1632: astore 34
    //   1634: aload 26
    //   1636: astore 35
    //   1638: aload 29
    //   1640: aload 44
    //   1642: invokeinterface 298 1 0
    //   1647: checkcast 303	java/lang/String
    //   1650: aload 44
    //   1652: invokeinterface 301 1 0
    //   1657: checkcast 303	java/lang/String
    //   1660: invokevirtual 250	java/net/HttpURLConnection:setRequestProperty	(Ljava/lang/String;Ljava/lang/String;)V
    //   1663: goto -341 -> 1322
    //   1666: aload 29
    //   1668: ldc_w 316
    //   1671: aload_0
    //   1672: getfield 14	com/tencent/luggage/wxa/nz/g$b:a	Lcom/tencent/luggage/wxa/nz/g;
    //   1675: invokestatic 319	com/tencent/luggage/wxa/nz/g:c	(Lcom/tencent/luggage/wxa/nz/g;)Ljava/lang/String;
    //   1678: invokevirtual 250	java/net/HttpURLConnection:setRequestProperty	(Ljava/lang/String;Ljava/lang/String;)V
    //   1681: aload 43
    //   1683: invokevirtual 260	com/tencent/luggage/wxa/rt/i:q	()J
    //   1686: lstore 14
    //   1688: new 321	java/lang/StringBuilder
    //   1691: dup
    //   1692: invokespecial 322	java/lang/StringBuilder:<init>	()V
    //   1695: astore 45
    //   1697: new 321	java/lang/StringBuilder
    //   1700: dup
    //   1701: invokespecial 322	java/lang/StringBuilder:<init>	()V
    //   1704: astore 44
    //   1706: aload 40
    //   1708: ifnull +998 -> 2706
    //   1711: aload 26
    //   1713: astore 36
    //   1715: aload 26
    //   1717: astore 31
    //   1719: aload 26
    //   1721: astore 32
    //   1723: aload 26
    //   1725: astore 33
    //   1727: aload 26
    //   1729: astore 34
    //   1731: aload 26
    //   1733: astore 35
    //   1735: new 321	java/lang/StringBuilder
    //   1738: dup
    //   1739: invokespecial 322	java/lang/StringBuilder:<init>	()V
    //   1742: astore 39
    //   1744: aload 26
    //   1746: astore 36
    //   1748: aload 26
    //   1750: astore 31
    //   1752: aload 26
    //   1754: astore 32
    //   1756: aload 26
    //   1758: astore 33
    //   1760: aload 26
    //   1762: astore 34
    //   1764: aload 26
    //   1766: astore 35
    //   1768: aload 39
    //   1770: ldc_w 324
    //   1773: invokevirtual 328	java/lang/StringBuilder:append	(Ljava/lang/String;)Ljava/lang/StringBuilder;
    //   1776: pop
    //   1777: aload 26
    //   1779: astore 36
    //   1781: aload 26
    //   1783: astore 31
    //   1785: aload 26
    //   1787: astore 32
    //   1789: aload 26
    //   1791: astore 33
    //   1793: aload 26
    //   1795: astore 34
    //   1797: aload 26
    //   1799: astore 35
    //   1801: aload 39
    //   1803: aload 42
    //   1805: invokevirtual 328	java/lang/StringBuilder:append	(Ljava/lang/String;)Ljava/lang/StringBuilder;
    //   1808: pop
    //   1809: aload 26
    //   1811: astore 36
    //   1813: aload 26
    //   1815: astore 31
    //   1817: aload 26
    //   1819: astore 32
    //   1821: aload 26
    //   1823: astore 33
    //   1825: aload 26
    //   1827: astore 34
    //   1829: aload 26
    //   1831: astore 35
    //   1833: aload 29
    //   1835: ldc_w 330
    //   1838: aload 39
    //   1840: invokevirtual 332	java/lang/StringBuilder:toString	()Ljava/lang/String;
    //   1843: invokevirtual 250	java/net/HttpURLConnection:setRequestProperty	(Ljava/lang/String;Ljava/lang/String;)V
    //   1846: aload 26
    //   1848: astore 36
    //   1850: aload 26
    //   1852: astore 31
    //   1854: aload 26
    //   1856: astore 32
    //   1858: aload 26
    //   1860: astore 33
    //   1862: aload 26
    //   1864: astore 34
    //   1866: aload 26
    //   1868: astore 35
    //   1870: aload 40
    //   1872: invokeinterface 335 1 0
    //   1877: invokeinterface 281 1 0
    //   1882: astore 39
    //   1884: aload 26
    //   1886: astore 36
    //   1888: aload 26
    //   1890: astore 31
    //   1892: aload 26
    //   1894: astore 32
    //   1896: aload 26
    //   1898: astore 33
    //   1900: aload 26
    //   1902: astore 34
    //   1904: aload 26
    //   1906: astore 35
    //   1908: aload 39
    //   1910: invokeinterface 287 1 0
    //   1915: ifeq +229 -> 2144
    //   1918: aload 26
    //   1920: astore 36
    //   1922: aload 26
    //   1924: astore 31
    //   1926: aload 26
    //   1928: astore 32
    //   1930: aload 26
    //   1932: astore 33
    //   1934: aload 26
    //   1936: astore 34
    //   1938: aload 26
    //   1940: astore 35
    //   1942: aload 39
    //   1944: invokeinterface 291 1 0
    //   1949: checkcast 303	java/lang/String
    //   1952: astore 47
    //   1954: aload 26
    //   1956: astore 36
    //   1958: aload 26
    //   1960: astore 31
    //   1962: aload 26
    //   1964: astore 32
    //   1966: aload 26
    //   1968: astore 33
    //   1970: aload 26
    //   1972: astore 34
    //   1974: aload 26
    //   1976: astore 35
    //   1978: aload 40
    //   1980: aload 47
    //   1982: invokeinterface 339 2 0
    //   1987: checkcast 303	java/lang/String
    //   1990: astore 48
    //   1992: ldc 68
    //   1994: ldc_w 341
    //   1997: iconst_2
    //   1998: anewarray 4	java/lang/Object
    //   2001: dup
    //   2002: iconst_0
    //   2003: aload 47
    //   2005: aastore
    //   2006: dup
    //   2007: iconst_1
    //   2008: aload 48
    //   2010: aastore
    //   2011: invokestatic 139	com/tencent/luggage/wxa/qz/o:d	(Ljava/lang/String;Ljava/lang/String;[Ljava/lang/Object;)V
    //   2014: new 321	java/lang/StringBuilder
    //   2017: dup
    //   2018: invokespecial 322	java/lang/StringBuilder:<init>	()V
    //   2021: astore 31
    //   2023: aload 31
    //   2025: ldc_w 343
    //   2028: invokevirtual 328	java/lang/StringBuilder:append	(Ljava/lang/String;)Ljava/lang/StringBuilder;
    //   2031: pop
    //   2032: aload 31
    //   2034: aload 42
    //   2036: invokevirtual 328	java/lang/StringBuilder:append	(Ljava/lang/String;)Ljava/lang/StringBuilder;
    //   2039: pop
    //   2040: aload 31
    //   2042: ldc_w 345
    //   2045: invokevirtual 328	java/lang/StringBuilder:append	(Ljava/lang/String;)Ljava/lang/StringBuilder;
    //   2048: pop
    //   2049: aload 45
    //   2051: aload 31
    //   2053: invokevirtual 332	java/lang/StringBuilder:toString	()Ljava/lang/String;
    //   2056: invokevirtual 328	java/lang/StringBuilder:append	(Ljava/lang/String;)Ljava/lang/StringBuilder;
    //   2059: pop
    //   2060: new 321	java/lang/StringBuilder
    //   2063: dup
    //   2064: invokespecial 322	java/lang/StringBuilder:<init>	()V
    //   2067: astore 31
    //   2069: aload 31
    //   2071: ldc_w 347
    //   2074: invokevirtual 328	java/lang/StringBuilder:append	(Ljava/lang/String;)Ljava/lang/StringBuilder;
    //   2077: pop
    //   2078: aload 31
    //   2080: aload 47
    //   2082: invokevirtual 328	java/lang/StringBuilder:append	(Ljava/lang/String;)Ljava/lang/StringBuilder;
    //   2085: pop
    //   2086: aload 31
    //   2088: ldc_w 349
    //   2091: invokevirtual 328	java/lang/StringBuilder:append	(Ljava/lang/String;)Ljava/lang/StringBuilder;
    //   2094: pop
    //   2095: aload 45
    //   2097: aload 31
    //   2099: invokevirtual 332	java/lang/StringBuilder:toString	()Ljava/lang/String;
    //   2102: invokevirtual 328	java/lang/StringBuilder:append	(Ljava/lang/String;)Ljava/lang/StringBuilder;
    //   2105: pop
    //   2106: aload 45
    //   2108: ldc_w 345
    //   2111: invokevirtual 328	java/lang/StringBuilder:append	(Ljava/lang/String;)Ljava/lang/StringBuilder;
    //   2114: pop
    //   2115: aload 45
    //   2117: ldc_w 345
    //   2120: invokevirtual 328	java/lang/StringBuilder:append	(Ljava/lang/String;)Ljava/lang/StringBuilder;
    //   2123: pop
    //   2124: aload 45
    //   2126: aload 48
    //   2128: invokevirtual 328	java/lang/StringBuilder:append	(Ljava/lang/String;)Ljava/lang/StringBuilder;
    //   2131: pop
    //   2132: aload 45
    //   2134: ldc_w 345
    //   2137: invokevirtual 328	java/lang/StringBuilder:append	(Ljava/lang/String;)Ljava/lang/StringBuilder;
    //   2140: pop
    //   2141: goto -257 -> 1884
    //   2144: aload 26
    //   2146: astore 31
    //   2148: new 321	java/lang/StringBuilder
    //   2151: dup
    //   2152: invokespecial 322	java/lang/StringBuilder:<init>	()V
    //   2155: astore 32
    //   2157: aload 32
    //   2159: ldc_w 343
    //   2162: invokevirtual 328	java/lang/StringBuilder:append	(Ljava/lang/String;)Ljava/lang/StringBuilder;
    //   2165: pop
    //   2166: aload 32
    //   2168: aload 42
    //   2170: invokevirtual 328	java/lang/StringBuilder:append	(Ljava/lang/String;)Ljava/lang/StringBuilder;
    //   2173: pop
    //   2174: aload 32
    //   2176: ldc_w 345
    //   2179: invokevirtual 328	java/lang/StringBuilder:append	(Ljava/lang/String;)Ljava/lang/StringBuilder;
    //   2182: pop
    //   2183: aload 45
    //   2185: aload 32
    //   2187: invokevirtual 332	java/lang/StringBuilder:toString	()Ljava/lang/String;
    //   2190: invokevirtual 328	java/lang/StringBuilder:append	(Ljava/lang/String;)Ljava/lang/StringBuilder;
    //   2193: pop
    //   2194: new 321	java/lang/StringBuilder
    //   2197: dup
    //   2198: invokespecial 322	java/lang/StringBuilder:<init>	()V
    //   2201: astore 32
    //   2203: aload 32
    //   2205: ldc_w 347
    //   2208: invokevirtual 328	java/lang/StringBuilder:append	(Ljava/lang/String;)Ljava/lang/StringBuilder;
    //   2211: pop
    //   2212: aload 32
    //   2214: aload 46
    //   2216: invokevirtual 328	java/lang/StringBuilder:append	(Ljava/lang/String;)Ljava/lang/StringBuilder;
    //   2219: pop
    //   2220: aload 32
    //   2222: ldc_w 351
    //   2225: invokevirtual 328	java/lang/StringBuilder:append	(Ljava/lang/String;)Ljava/lang/StringBuilder;
    //   2228: pop
    //   2229: aload 32
    //   2231: aload 38
    //   2233: invokevirtual 328	java/lang/StringBuilder:append	(Ljava/lang/String;)Ljava/lang/StringBuilder;
    //   2236: pop
    //   2237: aload 32
    //   2239: ldc_w 349
    //   2242: invokevirtual 328	java/lang/StringBuilder:append	(Ljava/lang/String;)Ljava/lang/StringBuilder;
    //   2245: pop
    //   2246: aload 32
    //   2248: ldc_w 345
    //   2251: invokevirtual 328	java/lang/StringBuilder:append	(Ljava/lang/String;)Ljava/lang/StringBuilder;
    //   2254: pop
    //   2255: aload 45
    //   2257: aload 32
    //   2259: invokevirtual 332	java/lang/StringBuilder:toString	()Ljava/lang/String;
    //   2262: invokevirtual 328	java/lang/StringBuilder:append	(Ljava/lang/String;)Ljava/lang/StringBuilder;
    //   2265: pop
    //   2266: new 321	java/lang/StringBuilder
    //   2269: dup
    //   2270: invokespecial 322	java/lang/StringBuilder:<init>	()V
    //   2273: astore 39
    //   2275: aload 39
    //   2277: ldc_w 353
    //   2280: invokevirtual 328	java/lang/StringBuilder:append	(Ljava/lang/String;)Ljava/lang/StringBuilder;
    //   2283: pop
    //   2284: aload 31
    //   2286: astore 26
    //   2288: aload 31
    //   2290: astore 32
    //   2292: aload 31
    //   2294: astore 33
    //   2296: aload 31
    //   2298: astore 34
    //   2300: aload 31
    //   2302: astore 35
    //   2304: aload 31
    //   2306: astore 36
    //   2308: aload 39
    //   2310: aload 27
    //   2312: invokevirtual 328	java/lang/StringBuilder:append	(Ljava/lang/String;)Ljava/lang/StringBuilder;
    //   2315: pop
    //   2316: aload 31
    //   2318: astore 26
    //   2320: aload 31
    //   2322: astore 32
    //   2324: aload 31
    //   2326: astore 33
    //   2328: aload 31
    //   2330: astore 34
    //   2332: aload 31
    //   2334: astore 35
    //   2336: aload 31
    //   2338: astore 36
    //   2340: aload 45
    //   2342: aload 39
    //   2344: invokevirtual 332	java/lang/StringBuilder:toString	()Ljava/lang/String;
    //   2347: invokevirtual 328	java/lang/StringBuilder:append	(Ljava/lang/String;)Ljava/lang/StringBuilder;
    //   2350: pop
    //   2351: aload 31
    //   2353: astore 26
    //   2355: aload 31
    //   2357: astore 32
    //   2359: aload 31
    //   2361: astore 33
    //   2363: aload 31
    //   2365: astore 34
    //   2367: aload 31
    //   2369: astore 35
    //   2371: aload 31
    //   2373: astore 36
    //   2375: aload 45
    //   2377: ldc_w 345
    //   2380: invokevirtual 328	java/lang/StringBuilder:append	(Ljava/lang/String;)Ljava/lang/StringBuilder;
    //   2383: pop
    //   2384: aload 31
    //   2386: astore 26
    //   2388: aload 31
    //   2390: astore 32
    //   2392: aload 31
    //   2394: astore 33
    //   2396: aload 31
    //   2398: astore 34
    //   2400: aload 31
    //   2402: astore 35
    //   2404: aload 31
    //   2406: astore 36
    //   2408: aload 45
    //   2410: ldc_w 345
    //   2413: invokevirtual 328	java/lang/StringBuilder:append	(Ljava/lang/String;)Ljava/lang/StringBuilder;
    //   2416: pop
    //   2417: aload 31
    //   2419: astore 26
    //   2421: aload 31
    //   2423: astore 32
    //   2425: aload 31
    //   2427: astore 33
    //   2429: aload 31
    //   2431: astore 34
    //   2433: aload 31
    //   2435: astore 35
    //   2437: aload 31
    //   2439: astore 36
    //   2441: new 321	java/lang/StringBuilder
    //   2444: dup
    //   2445: invokespecial 322	java/lang/StringBuilder:<init>	()V
    //   2448: astore 27
    //   2450: aload 31
    //   2452: astore 26
    //   2454: aload 31
    //   2456: astore 32
    //   2458: aload 31
    //   2460: astore 33
    //   2462: aload 31
    //   2464: astore 34
    //   2466: aload 31
    //   2468: astore 35
    //   2470: aload 31
    //   2472: astore 36
    //   2474: aload 27
    //   2476: ldc_w 345
    //   2479: invokevirtual 328	java/lang/StringBuilder:append	(Ljava/lang/String;)Ljava/lang/StringBuilder;
    //   2482: pop
    //   2483: aload 31
    //   2485: astore 26
    //   2487: aload 31
    //   2489: astore 32
    //   2491: aload 31
    //   2493: astore 33
    //   2495: aload 31
    //   2497: astore 34
    //   2499: aload 31
    //   2501: astore 35
    //   2503: aload 31
    //   2505: astore 36
    //   2507: aload 27
    //   2509: ldc_w 343
    //   2512: invokevirtual 328	java/lang/StringBuilder:append	(Ljava/lang/String;)Ljava/lang/StringBuilder;
    //   2515: pop
    //   2516: aload 31
    //   2518: astore 26
    //   2520: aload 31
    //   2522: astore 32
    //   2524: aload 31
    //   2526: astore 33
    //   2528: aload 31
    //   2530: astore 34
    //   2532: aload 31
    //   2534: astore 35
    //   2536: aload 31
    //   2538: astore 36
    //   2540: aload 27
    //   2542: aload 42
    //   2544: invokevirtual 328	java/lang/StringBuilder:append	(Ljava/lang/String;)Ljava/lang/StringBuilder;
    //   2547: pop
    //   2548: aload 31
    //   2550: astore 26
    //   2552: aload 31
    //   2554: astore 32
    //   2556: aload 31
    //   2558: astore 33
    //   2560: aload 31
    //   2562: astore 34
    //   2564: aload 31
    //   2566: astore 35
    //   2568: aload 31
    //   2570: astore 36
    //   2572: aload 27
    //   2574: ldc_w 343
    //   2577: invokevirtual 328	java/lang/StringBuilder:append	(Ljava/lang/String;)Ljava/lang/StringBuilder;
    //   2580: pop
    //   2581: aload 31
    //   2583: astore 26
    //   2585: aload 31
    //   2587: astore 32
    //   2589: aload 31
    //   2591: astore 33
    //   2593: aload 31
    //   2595: astore 34
    //   2597: aload 31
    //   2599: astore 35
    //   2601: aload 31
    //   2603: astore 36
    //   2605: aload 27
    //   2607: ldc_w 345
    //   2610: invokevirtual 328	java/lang/StringBuilder:append	(Ljava/lang/String;)Ljava/lang/StringBuilder;
    //   2613: pop
    //   2614: aload 31
    //   2616: astore 26
    //   2618: aload 31
    //   2620: astore 32
    //   2622: aload 31
    //   2624: astore 33
    //   2626: aload 31
    //   2628: astore 34
    //   2630: aload 31
    //   2632: astore 35
    //   2634: aload 31
    //   2636: astore 36
    //   2638: aload 44
    //   2640: aload 27
    //   2642: invokevirtual 332	java/lang/StringBuilder:toString	()Ljava/lang/String;
    //   2645: invokevirtual 328	java/lang/StringBuilder:append	(Ljava/lang/String;)Ljava/lang/StringBuilder;
    //   2648: pop
    //   2649: aload 31
    //   2651: astore 27
    //   2653: goto +57 -> 2710
    //   2656: astore 21
    //   2658: goto +8559 -> 11217
    //   2661: astore 22
    //   2663: aload 26
    //   2665: astore 32
    //   2667: goto +8597 -> 11264
    //   2670: aload 26
    //   2672: astore 33
    //   2674: astore 26
    //   2676: goto +8601 -> 11277
    //   2679: aload 26
    //   2681: astore 34
    //   2683: astore 26
    //   2685: goto +8636 -> 11321
    //   2688: aload 26
    //   2690: astore 35
    //   2692: astore 26
    //   2694: goto +8671 -> 11365
    //   2697: aload 26
    //   2699: astore 36
    //   2701: astore 26
    //   2703: goto +8706 -> 11409
    //   2706: aload 26
    //   2708: astore 27
    //   2710: aload 28
    //   2712: astore 31
    //   2714: aload 45
    //   2716: invokevirtual 332	java/lang/StringBuilder:toString	()Ljava/lang/String;
    //   2719: astore 26
    //   2721: ldc_w 355
    //   2724: astore 42
    //   2726: aload 26
    //   2728: aload 42
    //   2730: invokevirtual 359	java/lang/String:getBytes	(Ljava/lang/String;)[B
    //   2733: astore 26
    //   2735: aload 44
    //   2737: invokevirtual 332	java/lang/StringBuilder:toString	()Ljava/lang/String;
    //   2740: aload 42
    //   2742: invokevirtual 359	java/lang/String:getBytes	(Ljava/lang/String;)[B
    //   2745: astore 40
    //   2747: aload 26
    //   2749: astore 39
    //   2751: aload 26
    //   2753: ifnonnull +35 -> 2788
    //   2756: aload 27
    //   2758: astore 26
    //   2760: aload 27
    //   2762: astore 32
    //   2764: aload 27
    //   2766: astore 33
    //   2768: aload 27
    //   2770: astore 34
    //   2772: aload 27
    //   2774: astore 35
    //   2776: aload 27
    //   2778: astore 36
    //   2780: iconst_0
    //   2781: newarray byte
    //   2783: astore 39
    //   2785: goto +3 -> 2788
    //   2788: aload 40
    //   2790: astore 36
    //   2792: aload 40
    //   2794: ifnonnull +36 -> 2830
    //   2797: aload 27
    //   2799: astore 26
    //   2801: aload 27
    //   2803: astore 32
    //   2805: aload 27
    //   2807: astore 33
    //   2809: aload 27
    //   2811: astore 34
    //   2813: aload 27
    //   2815: astore 35
    //   2817: aload 27
    //   2819: astore 36
    //   2821: iconst_0
    //   2822: newarray byte
    //   2824: astore 40
    //   2826: aload 40
    //   2828: astore 36
    //   2830: lload 14
    //   2832: aload 39
    //   2834: arraylength
    //   2835: i2l
    //   2836: ladd
    //   2837: aload 36
    //   2839: arraylength
    //   2840: i2l
    //   2841: ladd
    //   2842: lstore 14
    //   2844: ldc 68
    //   2846: ldc_w 361
    //   2849: iconst_1
    //   2850: anewarray 4	java/lang/Object
    //   2853: dup
    //   2854: iconst_0
    //   2855: lload 14
    //   2857: invokestatic 264	java/lang/Long:valueOf	(J)Ljava/lang/Long;
    //   2860: aastore
    //   2861: invokestatic 139	com/tencent/luggage/wxa/qz/o:d	(Ljava/lang/String;Ljava/lang/String;[Ljava/lang/Object;)V
    //   2864: new 321	java/lang/StringBuilder
    //   2867: dup
    //   2868: invokespecial 322	java/lang/StringBuilder:<init>	()V
    //   2871: astore 26
    //   2873: aload 26
    //   2875: lload 14
    //   2877: invokevirtual 364	java/lang/StringBuilder:append	(J)Ljava/lang/StringBuilder;
    //   2880: pop
    //   2881: ldc 202
    //   2883: astore 34
    //   2885: aload 26
    //   2887: aload 34
    //   2889: invokevirtual 328	java/lang/StringBuilder:append	(Ljava/lang/String;)Ljava/lang/StringBuilder;
    //   2892: pop
    //   2893: aload 29
    //   2895: ldc_w 366
    //   2898: aload 26
    //   2900: invokevirtual 332	java/lang/StringBuilder:toString	()Ljava/lang/String;
    //   2903: invokevirtual 250	java/net/HttpURLConnection:setRequestProperty	(Ljava/lang/String;Ljava/lang/String;)V
    //   2906: aload 29
    //   2908: invokestatic 369	com/tencent/luggage/wxa/nz/j:c	(Ljava/net/HttpURLConnection;)Lorg/json/JSONObject;
    //   2911: astore 26
    //   2913: aload 21
    //   2915: astore 32
    //   2917: aload 32
    //   2919: aload 26
    //   2921: invokeinterface 374 2 0
    //   2926: new 376	java/io/DataOutputStream
    //   2929: dup
    //   2930: aload 29
    //   2932: invokevirtual 380	java/net/HttpURLConnection:getOutputStream	()Ljava/io/OutputStream;
    //   2935: invokespecial 383	java/io/DataOutputStream:<init>	(Ljava/io/OutputStream;)V
    //   2938: astore 28
    //   2940: aload 28
    //   2942: aload 39
    //   2944: invokevirtual 387	java/io/DataOutputStream:write	([B)V
    //   2947: lload 14
    //   2949: invokestatic 390	com/tencent/luggage/wxa/nz/j:a	(J)I
    //   2952: newarray byte
    //   2954: astore 39
    //   2956: aload 43
    //   2958: invokevirtual 260	com/tencent/luggage/wxa/rt/i:q	()J
    //   2961: lstore 16
    //   2963: aload 38
    //   2965: astore 40
    //   2967: aload 20
    //   2969: astore 21
    //   2971: iconst_m1
    //   2972: istore_2
    //   2973: aload 22
    //   2975: astore 26
    //   2977: aload 23
    //   2979: astore 20
    //   2981: aload 37
    //   2983: astore 38
    //   2985: aload 29
    //   2987: astore 23
    //   2989: aload 21
    //   2991: astore 22
    //   2993: aload 32
    //   2995: astore 21
    //   2997: aload 31
    //   2999: astore 29
    //   3001: aload 42
    //   3003: astore 37
    //   3005: aload 22
    //   3007: aload 39
    //   3009: invokevirtual 396	java/io/InputStream:read	([B)I
    //   3012: istore_3
    //   3013: iload_3
    //   3014: iconst_m1
    //   3015: if_icmpeq +1015 -> 4030
    //   3018: aload_1
    //   3019: getfield 142	com/tencent/luggage/wxa/nz/h:a	Z
    //   3022: ifeq +1008 -> 4030
    //   3025: aload_0
    //   3026: getfield 14	com/tencent/luggage/wxa/nz/g$b:a	Lcom/tencent/luggage/wxa/nz/g;
    //   3029: invokestatic 118	com/tencent/luggage/wxa/nz/g:a	(Lcom/tencent/luggage/wxa/nz/g;)Lcom/tencent/luggage/wxa/jx/c;
    //   3032: invokestatic 399	com/tencent/luggage/wxa/nz/j:a	(Lcom/tencent/luggage/wxa/jx/c;)Z
    //   3035: istore 11
    //   3037: iload 11
    //   3039: ifeq +450 -> 3489
    //   3042: aload_0
    //   3043: getfield 14	com/tencent/luggage/wxa/nz/g$b:a	Lcom/tencent/luggage/wxa/nz/g;
    //   3046: aload 21
    //   3048: iconst_m1
    //   3049: ldc_w 401
    //   3052: aload_1
    //   3053: invokevirtual 103	com/tencent/luggage/wxa/nz/h:l	()Ljava/lang/String;
    //   3056: aload 23
    //   3058: invokestatic 108	com/tencent/luggage/wxa/nz/g:a	(Lcom/tencent/luggage/wxa/nz/g;Lcom/tencent/luggage/wxa/nz/g$a;ILjava/lang/String;Ljava/lang/String;Ljava/net/HttpURLConnection;)V
    //   3061: ldc 110
    //   3063: invokestatic 115	com/tencent/luggage/wxa/ba/e:b	(Ljava/lang/Class;)Lcom/tencent/luggage/wxa/ba/d;
    //   3066: checkcast 110	com/tencent/luggage/wxa/nz/o
    //   3069: aload_0
    //   3070: getfield 14	com/tencent/luggage/wxa/nz/g$b:a	Lcom/tencent/luggage/wxa/nz/g;
    //   3073: invokestatic 118	com/tencent/luggage/wxa/nz/g:a	(Lcom/tencent/luggage/wxa/nz/g;)Lcom/tencent/luggage/wxa/jx/c;
    //   3076: invokeinterface 123 1 0
    //   3081: aload_1
    //   3082: invokevirtual 126	com/tencent/luggage/wxa/nz/h:n	()Ljava/lang/String;
    //   3085: ldc 128
    //   3087: aload_1
    //   3088: invokevirtual 49	com/tencent/luggage/wxa/nz/h:b	()Ljava/lang/String;
    //   3091: lload 12
    //   3093: iconst_0
    //   3094: i2l
    //   3095: iconst_0
    //   3096: iconst_2
    //   3097: aload_1
    //   3098: invokevirtual 132	com/tencent/luggage/wxa/nz/h:o	()I
    //   3101: aconst_null
    //   3102: aload 29
    //   3104: invokeinterface 135 14 0
    //   3109: invokestatic 406	com/tencent/luggage/wxa/qz/r:a	()Landroid/content/Context;
    //   3112: invokestatic 411	com/tencent/luggage/wxa/qz/x:d	(Landroid/content/Context;)I
    //   3115: istore_2
    //   3116: iload_2
    //   3117: iconst_m1
    //   3118: if_icmpne +24 -> 3142
    //   3121: ldc 173
    //   3123: invokestatic 115	com/tencent/luggage/wxa/ba/e:b	(Ljava/lang/Class;)Lcom/tencent/luggage/wxa/ba/d;
    //   3126: checkcast 173	com/tencent/luggage/wxa/ot/c
    //   3129: ldc2_w 174
    //   3132: ldc2_w 412
    //   3135: lconst_1
    //   3136: iconst_0
    //   3137: invokeinterface 178 8 0
    //   3142: ldc 68
    //   3144: aload 20
    //   3146: iconst_1
    //   3147: anewarray 4	java/lang/Object
    //   3150: dup
    //   3151: iconst_0
    //   3152: iload_2
    //   3153: invokestatic 418	java/lang/Integer:valueOf	(I)Ljava/lang/Integer;
    //   3156: aastore
    //   3157: invokestatic 139	com/tencent/luggage/wxa/qz/o:d	(Ljava/lang/String;Ljava/lang/String;[Ljava/lang/Object;)V
    //   3160: aload_1
    //   3161: iconst_0
    //   3162: putfield 142	com/tencent/luggage/wxa/nz/h:a	Z
    //   3165: aload 22
    //   3167: ifnull +36 -> 3203
    //   3170: aload 22
    //   3172: invokevirtual 421	java/io/InputStream:close	()V
    //   3175: goto +28 -> 3203
    //   3178: astore 20
    //   3180: ldc 68
    //   3182: aload 20
    //   3184: aload 24
    //   3186: iconst_2
    //   3187: anewarray 4	java/lang/Object
    //   3190: dup
    //   3191: iconst_0
    //   3192: aload 27
    //   3194: aastore
    //   3195: dup
    //   3196: iconst_1
    //   3197: aload 26
    //   3199: aastore
    //   3200: invokestatic 424	com/tencent/luggage/wxa/qz/o:a	(Ljava/lang/String;Ljava/lang/Throwable;Ljava/lang/String;[Ljava/lang/Object;)V
    //   3203: aload 28
    //   3205: invokevirtual 425	java/io/DataOutputStream:close	()V
    //   3208: goto +28 -> 3236
    //   3211: astore 20
    //   3213: ldc 68
    //   3215: aload 20
    //   3217: aload 25
    //   3219: iconst_2
    //   3220: anewarray 4	java/lang/Object
    //   3223: dup
    //   3224: iconst_0
    //   3225: aload 27
    //   3227: aastore
    //   3228: dup
    //   3229: iconst_1
    //   3230: aload 26
    //   3232: aastore
    //   3233: invokestatic 424	com/tencent/luggage/wxa/qz/o:a	(Ljava/lang/String;Ljava/lang/Throwable;Ljava/lang/String;[Ljava/lang/Object;)V
    //   3236: aload_0
    //   3237: getfield 14	com/tencent/luggage/wxa/nz/g$b:a	Lcom/tencent/luggage/wxa/nz/g;
    //   3240: getfield 428	com/tencent/luggage/wxa/nz/g:a	Ljava/util/ArrayList;
    //   3243: aload_1
    //   3244: invokevirtual 103	com/tencent/luggage/wxa/nz/h:l	()Ljava/lang/String;
    //   3247: invokevirtual 434	java/util/ArrayList:remove	(Ljava/lang/Object;)Z
    //   3250: pop
    //   3251: return
    //   3252: astore 21
    //   3254: aload 29
    //   3256: astore 23
    //   3258: aconst_null
    //   3259: astore 33
    //   3261: aload 25
    //   3263: astore 32
    //   3265: aload 24
    //   3267: astore 29
    //   3269: aload 20
    //   3271: astore 31
    //   3273: aload 26
    //   3275: astore 25
    //   3277: aload 27
    //   3279: astore 24
    //   3281: iconst_0
    //   3282: istore_3
    //   3283: aload 22
    //   3285: astore 30
    //   3287: iconst_0
    //   3288: istore_2
    //   3289: aload 21
    //   3291: astore 20
    //   3293: aload 33
    //   3295: astore 26
    //   3297: aload 31
    //   3299: astore 21
    //   3301: aload 23
    //   3303: astore 27
    //   3305: aload 25
    //   3307: astore 22
    //   3309: aload 24
    //   3311: astore 23
    //   3313: goto +7593 -> 10906
    //   3316: astore 30
    //   3318: aload 29
    //   3320: astore 33
    //   3322: aload 34
    //   3324: astore 36
    //   3326: aload 20
    //   3328: astore 29
    //   3330: aload 26
    //   3332: astore 34
    //   3334: aload 27
    //   3336: astore 35
    //   3338: aload 22
    //   3340: astore 20
    //   3342: aload 30
    //   3344: astore 22
    //   3346: aload 21
    //   3348: astore 26
    //   3350: aload 29
    //   3352: astore 27
    //   3354: aload 24
    //   3356: astore 31
    //   3358: aload 23
    //   3360: astore 29
    //   3362: aload 20
    //   3364: astore 30
    //   3366: goto +4601 -> 7967
    //   3369: astore 30
    //   3371: aconst_null
    //   3372: astore 31
    //   3374: aload 20
    //   3376: astore 33
    //   3378: iconst_0
    //   3379: istore_3
    //   3380: aload 30
    //   3382: astore 20
    //   3384: aload 29
    //   3386: astore 35
    //   3388: aload 22
    //   3390: astore 36
    //   3392: aload 27
    //   3394: astore 34
    //   3396: goto +5110 -> 8506
    //   3399: astore 30
    //   3401: aconst_null
    //   3402: astore 31
    //   3404: aload 20
    //   3406: astore 33
    //   3408: iconst_0
    //   3409: istore_3
    //   3410: aload 30
    //   3412: astore 20
    //   3414: aload 29
    //   3416: astore 35
    //   3418: aload 22
    //   3420: astore 36
    //   3422: aload 27
    //   3424: astore 34
    //   3426: goto +5679 -> 9105
    //   3429: astore 30
    //   3431: aconst_null
    //   3432: astore 31
    //   3434: aload 20
    //   3436: astore 33
    //   3438: iconst_0
    //   3439: istore_3
    //   3440: aload 30
    //   3442: astore 20
    //   3444: aload 29
    //   3446: astore 35
    //   3448: aload 22
    //   3450: astore 36
    //   3452: aload 27
    //   3454: astore 34
    //   3456: goto +6248 -> 9704
    //   3459: astore 30
    //   3461: aconst_null
    //   3462: astore 31
    //   3464: aload 20
    //   3466: astore 33
    //   3468: iconst_0
    //   3469: istore_3
    //   3470: aload 30
    //   3472: astore 20
    //   3474: aload 29
    //   3476: astore 36
    //   3478: aload 22
    //   3480: astore 37
    //   3482: aload 27
    //   3484: astore 30
    //   3486: goto +6850 -> 10336
    //   3489: aload 29
    //   3491: astore 30
    //   3493: aload 25
    //   3495: astore 32
    //   3497: aload 24
    //   3499: astore 31
    //   3501: aload 20
    //   3503: astore 33
    //   3505: lload 12
    //   3507: lstore 14
    //   3509: aload 28
    //   3511: aload 39
    //   3513: iconst_0
    //   3514: iload_3
    //   3515: invokevirtual 437	java/io/DataOutputStream:write	([BII)V
    //   3518: aload 23
    //   3520: astore 35
    //   3522: lload 12
    //   3524: iload_3
    //   3525: i2l
    //   3526: ladd
    //   3527: lstore 12
    //   3529: lload 16
    //   3531: lconst_0
    //   3532: lcmp
    //   3533: ifle +138 -> 3671
    //   3536: lload 12
    //   3538: lstore 14
    //   3540: aload_1
    //   3541: getfield 142	com/tencent/luggage/wxa/nz/h:a	Z
    //   3544: ifeq +127 -> 3671
    //   3547: lload 12
    //   3549: lstore 14
    //   3551: ldc2_w 438
    //   3554: lload 12
    //   3556: lmul
    //   3557: lload 16
    //   3559: ldiv
    //   3560: lstore 18
    //   3562: lload 18
    //   3564: l2i
    //   3565: istore_3
    //   3566: iload_2
    //   3567: iload_3
    //   3568: if_icmpeq +8045 -> 11613
    //   3571: aload 21
    //   3573: aload 40
    //   3575: aload 27
    //   3577: iload_3
    //   3578: lload 12
    //   3580: lload 16
    //   3582: invokeinterface 442 8 0
    //   3587: iload_3
    //   3588: istore_2
    //   3589: goto +3 -> 3592
    //   3592: ldc 68
    //   3594: ldc_w 444
    //   3597: iconst_3
    //   3598: anewarray 4	java/lang/Object
    //   3601: dup
    //   3602: iconst_0
    //   3603: lload 12
    //   3605: invokestatic 264	java/lang/Long:valueOf	(J)Ljava/lang/Long;
    //   3608: aastore
    //   3609: dup
    //   3610: iconst_1
    //   3611: lload 16
    //   3613: invokestatic 264	java/lang/Long:valueOf	(J)Ljava/lang/Long;
    //   3616: aastore
    //   3617: dup
    //   3618: iconst_2
    //   3619: iload_3
    //   3620: invokestatic 418	java/lang/Integer:valueOf	(I)Ljava/lang/Integer;
    //   3623: aastore
    //   3624: invokestatic 75	com/tencent/luggage/wxa/qz/o:f	(Ljava/lang/String;Ljava/lang/String;[Ljava/lang/Object;)V
    //   3627: goto +44 -> 3671
    //   3630: astore 23
    //   3632: goto +163 -> 3795
    //   3635: astore 30
    //   3637: aload 35
    //   3639: astore 23
    //   3641: goto +211 -> 3852
    //   3644: astore 30
    //   3646: aload 35
    //   3648: astore 23
    //   3650: goto +247 -> 3897
    //   3653: astore 30
    //   3655: aload 35
    //   3657: astore 23
    //   3659: goto +283 -> 3942
    //   3662: astore 30
    //   3664: aload 35
    //   3666: astore 23
    //   3668: goto +319 -> 3987
    //   3671: aload 33
    //   3673: astore 20
    //   3675: aload 32
    //   3677: astore 25
    //   3679: aload 31
    //   3681: astore 24
    //   3683: aload 30
    //   3685: astore 29
    //   3687: goto -682 -> 3005
    //   3690: astore 20
    //   3692: lload 14
    //   3694: lstore 12
    //   3696: aload 27
    //   3698: astore 24
    //   3700: aload 22
    //   3702: astore 23
    //   3704: aload 26
    //   3706: astore 22
    //   3708: aload 33
    //   3710: astore 21
    //   3712: aload 30
    //   3714: astore 27
    //   3716: goto +4145 -> 7861
    //   3719: astore 30
    //   3721: goto +66 -> 3787
    //   3724: astore 30
    //   3726: goto +126 -> 3852
    //   3729: astore 30
    //   3731: goto +166 -> 3897
    //   3734: astore 30
    //   3736: goto +206 -> 3942
    //   3739: astore 30
    //   3741: goto +246 -> 3987
    //   3744: astore 21
    //   3746: aload 24
    //   3748: astore 31
    //   3750: aload 27
    //   3752: astore 24
    //   3754: aload 22
    //   3756: astore 23
    //   3758: aload 21
    //   3760: astore 22
    //   3762: aload 20
    //   3764: astore 21
    //   3766: aload 22
    //   3768: astore 20
    //   3770: aload 25
    //   3772: astore 32
    //   3774: aload 29
    //   3776: astore 27
    //   3778: aload 26
    //   3780: astore 22
    //   3782: goto +4079 -> 7861
    //   3785: astore 30
    //   3787: aload 23
    //   3789: astore 35
    //   3791: aload 30
    //   3793: astore 23
    //   3795: aload 27
    //   3797: astore 30
    //   3799: aload 22
    //   3801: astore 33
    //   3803: aload 29
    //   3805: astore 27
    //   3807: aload 20
    //   3809: astore 22
    //   3811: aload 25
    //   3813: astore 32
    //   3815: aload 23
    //   3817: astore 20
    //   3819: aload 24
    //   3821: astore 31
    //   3823: aload 28
    //   3825: astore 23
    //   3827: aload 35
    //   3829: astore 24
    //   3831: aload 26
    //   3833: astore 25
    //   3835: aload 33
    //   3837: astore 26
    //   3839: aload 30
    //   3841: astore 28
    //   3843: aload 34
    //   3845: astore 29
    //   3847: goto +4076 -> 7923
    //   3850: astore 30
    //   3852: aload 27
    //   3854: astore 33
    //   3856: aload 22
    //   3858: astore 34
    //   3860: aload 29
    //   3862: astore 27
    //   3864: aload 20
    //   3866: astore 22
    //   3868: aload 30
    //   3870: astore 20
    //   3872: aload 25
    //   3874: astore 32
    //   3876: aload 24
    //   3878: astore 31
    //   3880: aload 26
    //   3882: astore 24
    //   3884: aload 34
    //   3886: astore 25
    //   3888: aload 33
    //   3890: astore 26
    //   3892: goto +4577 -> 8469
    //   3895: astore 30
    //   3897: aload 27
    //   3899: astore 33
    //   3901: aload 22
    //   3903: astore 34
    //   3905: aload 29
    //   3907: astore 27
    //   3909: aload 20
    //   3911: astore 22
    //   3913: aload 30
    //   3915: astore 20
    //   3917: aload 25
    //   3919: astore 32
    //   3921: aload 24
    //   3923: astore 31
    //   3925: aload 26
    //   3927: astore 24
    //   3929: aload 34
    //   3931: astore 25
    //   3933: aload 33
    //   3935: astore 26
    //   3937: goto +5131 -> 9068
    //   3940: astore 30
    //   3942: aload 27
    //   3944: astore 33
    //   3946: aload 22
    //   3948: astore 34
    //   3950: aload 29
    //   3952: astore 27
    //   3954: aload 20
    //   3956: astore 22
    //   3958: aload 30
    //   3960: astore 20
    //   3962: aload 25
    //   3964: astore 32
    //   3966: aload 24
    //   3968: astore 31
    //   3970: aload 26
    //   3972: astore 24
    //   3974: aload 34
    //   3976: astore 25
    //   3978: aload 33
    //   3980: astore 26
    //   3982: goto +5685 -> 9667
    //   3985: astore 30
    //   3987: aload 27
    //   3989: astore 33
    //   3991: aload 22
    //   3993: astore 34
    //   3995: aload 29
    //   3997: astore 27
    //   3999: aload 20
    //   4001: astore 22
    //   4003: aload 30
    //   4005: astore 20
    //   4007: aload 25
    //   4009: astore 32
    //   4011: aload 24
    //   4013: astore 31
    //   4015: aload 26
    //   4017: astore 24
    //   4019: aload 34
    //   4021: astore 25
    //   4023: aload 33
    //   4025: astore 26
    //   4027: goto +6272 -> 10299
    //   4030: aload 23
    //   4032: astore 30
    //   4034: aload 28
    //   4036: aload 36
    //   4038: invokevirtual 387	java/io/DataOutputStream:write	([B)V
    //   4041: aload 28
    //   4043: invokevirtual 447	java/io/DataOutputStream:flush	()V
    //   4046: aload 30
    //   4048: invokevirtual 450	java/net/HttpURLConnection:getResponseCode	()I
    //   4051: istore 10
    //   4053: iload 10
    //   4055: istore_3
    //   4056: aload 30
    //   4058: invokestatic 452	com/tencent/luggage/wxa/nz/j:b	(Ljava/net/HttpURLConnection;)Lorg/json/JSONObject;
    //   4061: astore 31
    //   4063: aload 21
    //   4065: astore 32
    //   4067: aload 32
    //   4069: aload 31
    //   4071: invokeinterface 374 2 0
    //   4076: sipush 200
    //   4079: iload_3
    //   4080: if_icmpeq +725 -> 4805
    //   4083: ldc 68
    //   4085: ldc_w 454
    //   4088: iconst_3
    //   4089: anewarray 4	java/lang/Object
    //   4092: dup
    //   4093: iconst_0
    //   4094: iload_3
    //   4095: invokestatic 418	java/lang/Integer:valueOf	(I)Ljava/lang/Integer;
    //   4098: aastore
    //   4099: dup
    //   4100: iconst_1
    //   4101: aload 27
    //   4103: aastore
    //   4104: dup
    //   4105: iconst_2
    //   4106: aload 26
    //   4108: aastore
    //   4109: invokestatic 456	com/tencent/luggage/wxa/qz/o:b	(Ljava/lang/String;Ljava/lang/String;[Ljava/lang/Object;)V
    //   4112: iload_3
    //   4113: invokestatic 459	com/tencent/luggage/wxa/nz/j:b	(I)Z
    //   4116: ifeq +689 -> 4805
    //   4119: aload 30
    //   4121: invokestatic 462	com/tencent/luggage/wxa/nz/j:a	(Ljava/net/HttpURLConnection;)Ljava/lang/String;
    //   4124: astore 33
    //   4126: aload_1
    //   4127: invokevirtual 465	com/tencent/luggage/wxa/nz/h:k	()I
    //   4130: istore_2
    //   4131: aload 33
    //   4133: invokestatic 470	android/text/TextUtils:isEmpty	(Ljava/lang/CharSequence;)Z
    //   4136: istore 11
    //   4138: iload 11
    //   4140: ifne +665 -> 4805
    //   4143: iload_2
    //   4144: ifgt +340 -> 4484
    //   4147: ldc 68
    //   4149: ldc_w 472
    //   4152: iconst_1
    //   4153: anewarray 4	java/lang/Object
    //   4156: dup
    //   4157: iconst_0
    //   4158: bipush 15
    //   4160: invokestatic 418	java/lang/Integer:valueOf	(I)Ljava/lang/Integer;
    //   4163: aastore
    //   4164: invokestatic 474	com/tencent/luggage/wxa/qz/o:c	(Ljava/lang/String;Ljava/lang/String;[Ljava/lang/Object;)V
    //   4167: aload_0
    //   4168: getfield 14	com/tencent/luggage/wxa/nz/g$b:a	Lcom/tencent/luggage/wxa/nz/g;
    //   4171: aload 32
    //   4173: iconst_0
    //   4174: ldc_w 476
    //   4177: iload_3
    //   4178: aload_1
    //   4179: invokevirtual 103	com/tencent/luggage/wxa/nz/h:l	()Ljava/lang/String;
    //   4182: aload 30
    //   4184: invokestatic 479	com/tencent/luggage/wxa/nz/g:a	(Lcom/tencent/luggage/wxa/nz/g;Lcom/tencent/luggage/wxa/nz/g$a;ILjava/lang/String;ILjava/lang/String;Ljava/net/HttpURLConnection;)V
    //   4187: ldc 110
    //   4189: invokestatic 115	com/tencent/luggage/wxa/ba/e:b	(Ljava/lang/Class;)Lcom/tencent/luggage/wxa/ba/d;
    //   4192: checkcast 110	com/tencent/luggage/wxa/nz/o
    //   4195: aload_0
    //   4196: getfield 14	com/tencent/luggage/wxa/nz/g$b:a	Lcom/tencent/luggage/wxa/nz/g;
    //   4199: invokestatic 118	com/tencent/luggage/wxa/nz/g:a	(Lcom/tencent/luggage/wxa/nz/g;)Lcom/tencent/luggage/wxa/jx/c;
    //   4202: invokeinterface 123 1 0
    //   4207: aload_1
    //   4208: invokevirtual 126	com/tencent/luggage/wxa/nz/h:n	()Ljava/lang/String;
    //   4211: ldc 128
    //   4213: aload_1
    //   4214: invokevirtual 49	com/tencent/luggage/wxa/nz/h:b	()Ljava/lang/String;
    //   4217: lload 12
    //   4219: iconst_0
    //   4220: i2l
    //   4221: iload_3
    //   4222: iconst_1
    //   4223: aload_1
    //   4224: invokevirtual 132	com/tencent/luggage/wxa/nz/h:o	()I
    //   4227: aconst_null
    //   4228: aload 29
    //   4230: invokeinterface 135 14 0
    //   4235: aload_1
    //   4236: iconst_0
    //   4237: putfield 142	com/tencent/luggage/wxa/nz/h:a	Z
    //   4240: aload 22
    //   4242: ifnull +36 -> 4278
    //   4245: aload 22
    //   4247: invokevirtual 421	java/io/InputStream:close	()V
    //   4250: goto +28 -> 4278
    //   4253: astore 20
    //   4255: ldc 68
    //   4257: aload 20
    //   4259: aload 24
    //   4261: iconst_2
    //   4262: anewarray 4	java/lang/Object
    //   4265: dup
    //   4266: iconst_0
    //   4267: aload 27
    //   4269: aastore
    //   4270: dup
    //   4271: iconst_1
    //   4272: aload 26
    //   4274: aastore
    //   4275: invokestatic 424	com/tencent/luggage/wxa/qz/o:a	(Ljava/lang/String;Ljava/lang/Throwable;Ljava/lang/String;[Ljava/lang/Object;)V
    //   4278: aload 28
    //   4280: invokevirtual 425	java/io/DataOutputStream:close	()V
    //   4283: goto +28 -> 4311
    //   4286: astore 20
    //   4288: ldc 68
    //   4290: aload 20
    //   4292: aload 25
    //   4294: iconst_2
    //   4295: anewarray 4	java/lang/Object
    //   4298: dup
    //   4299: iconst_0
    //   4300: aload 27
    //   4302: aastore
    //   4303: dup
    //   4304: iconst_1
    //   4305: aload 26
    //   4307: aastore
    //   4308: invokestatic 424	com/tencent/luggage/wxa/qz/o:a	(Ljava/lang/String;Ljava/lang/Throwable;Ljava/lang/String;[Ljava/lang/Object;)V
    //   4311: aload_0
    //   4312: getfield 14	com/tencent/luggage/wxa/nz/g$b:a	Lcom/tencent/luggage/wxa/nz/g;
    //   4315: getfield 428	com/tencent/luggage/wxa/nz/g:a	Ljava/util/ArrayList;
    //   4318: aload_1
    //   4319: invokevirtual 103	com/tencent/luggage/wxa/nz/h:l	()Ljava/lang/String;
    //   4322: invokevirtual 434	java/util/ArrayList:remove	(Ljava/lang/Object;)Z
    //   4325: pop
    //   4326: return
    //   4327: astore 21
    //   4329: aconst_null
    //   4330: astore 31
    //   4332: goto +1646 -> 5978
    //   4335: astore 31
    //   4337: goto +1668 -> 6005
    //   4340: astore 21
    //   4342: aconst_null
    //   4343: astore 31
    //   4345: aload 30
    //   4347: astore 23
    //   4349: aload 20
    //   4351: astore 33
    //   4353: aload 21
    //   4355: astore 20
    //   4357: aload 32
    //   4359: astore 21
    //   4361: aload 29
    //   4363: astore 35
    //   4365: aload 22
    //   4367: astore 36
    //   4369: aload 27
    //   4371: astore 34
    //   4373: goto +4133 -> 8506
    //   4376: astore 21
    //   4378: aconst_null
    //   4379: astore 31
    //   4381: aload 30
    //   4383: astore 23
    //   4385: aload 20
    //   4387: astore 33
    //   4389: aload 21
    //   4391: astore 20
    //   4393: aload 32
    //   4395: astore 21
    //   4397: aload 29
    //   4399: astore 35
    //   4401: aload 22
    //   4403: astore 36
    //   4405: aload 27
    //   4407: astore 34
    //   4409: goto +4696 -> 9105
    //   4412: astore 21
    //   4414: aconst_null
    //   4415: astore 31
    //   4417: aload 30
    //   4419: astore 23
    //   4421: aload 20
    //   4423: astore 33
    //   4425: aload 21
    //   4427: astore 20
    //   4429: aload 32
    //   4431: astore 21
    //   4433: aload 29
    //   4435: astore 35
    //   4437: aload 22
    //   4439: astore 36
    //   4441: aload 27
    //   4443: astore 34
    //   4445: goto +5259 -> 9704
    //   4448: astore 21
    //   4450: aconst_null
    //   4451: astore 31
    //   4453: aload 30
    //   4455: astore 23
    //   4457: aload 20
    //   4459: astore 33
    //   4461: aload 21
    //   4463: astore 20
    //   4465: aload 32
    //   4467: astore 21
    //   4469: aload 29
    //   4471: astore 36
    //   4473: aload 22
    //   4475: astore 37
    //   4477: aload 27
    //   4479: astore 30
    //   4481: goto +5855 -> 10336
    //   4484: aload_1
    //   4485: astore 31
    //   4487: ldc 68
    //   4489: ldc_w 481
    //   4492: iconst_3
    //   4493: anewarray 4	java/lang/Object
    //   4496: dup
    //   4497: iconst_0
    //   4498: iload_2
    //   4499: invokestatic 418	java/lang/Integer:valueOf	(I)Ljava/lang/Integer;
    //   4502: aastore
    //   4503: dup
    //   4504: iconst_1
    //   4505: aload_1
    //   4506: invokevirtual 49	com/tencent/luggage/wxa/nz/h:b	()Ljava/lang/String;
    //   4509: aastore
    //   4510: dup
    //   4511: iconst_2
    //   4512: aload 33
    //   4514: aastore
    //   4515: invokestatic 139	com/tencent/luggage/wxa/qz/o:d	(Ljava/lang/String;Ljava/lang/String;[Ljava/lang/Object;)V
    //   4518: aload 31
    //   4520: aload 33
    //   4522: invokevirtual 483	com/tencent/luggage/wxa/nz/h:a	(Ljava/lang/String;)V
    //   4525: aload 31
    //   4527: iload_2
    //   4528: iconst_1
    //   4529: isub
    //   4530: invokevirtual 485	com/tencent/luggage/wxa/nz/h:a	(I)V
    //   4533: aload_0
    //   4534: aload_1
    //   4535: invokespecial 487	com/tencent/luggage/wxa/nz/g$b:a	(Lcom/tencent/luggage/wxa/nz/h;)V
    //   4538: ldc 110
    //   4540: invokestatic 115	com/tencent/luggage/wxa/ba/e:b	(Ljava/lang/Class;)Lcom/tencent/luggage/wxa/ba/d;
    //   4543: checkcast 110	com/tencent/luggage/wxa/nz/o
    //   4546: aload_0
    //   4547: getfield 14	com/tencent/luggage/wxa/nz/g$b:a	Lcom/tencent/luggage/wxa/nz/g;
    //   4550: invokestatic 118	com/tencent/luggage/wxa/nz/g:a	(Lcom/tencent/luggage/wxa/nz/g;)Lcom/tencent/luggage/wxa/jx/c;
    //   4553: invokeinterface 123 1 0
    //   4558: aload_1
    //   4559: invokevirtual 126	com/tencent/luggage/wxa/nz/h:n	()Ljava/lang/String;
    //   4562: ldc 128
    //   4564: aload_1
    //   4565: invokevirtual 49	com/tencent/luggage/wxa/nz/h:b	()Ljava/lang/String;
    //   4568: lload 12
    //   4570: iconst_0
    //   4571: i2l
    //   4572: iload_3
    //   4573: iconst_2
    //   4574: aload_1
    //   4575: invokevirtual 132	com/tencent/luggage/wxa/nz/h:o	()I
    //   4578: aconst_null
    //   4579: aload 29
    //   4581: invokeinterface 135 14 0
    //   4586: invokestatic 406	com/tencent/luggage/wxa/qz/r:a	()Landroid/content/Context;
    //   4589: invokestatic 411	com/tencent/luggage/wxa/qz/x:d	(Landroid/content/Context;)I
    //   4592: istore_2
    //   4593: iload_2
    //   4594: iconst_m1
    //   4595: if_icmpne +24 -> 4619
    //   4598: ldc 173
    //   4600: invokestatic 115	com/tencent/luggage/wxa/ba/e:b	(Ljava/lang/Class;)Lcom/tencent/luggage/wxa/ba/d;
    //   4603: checkcast 173	com/tencent/luggage/wxa/ot/c
    //   4606: ldc2_w 174
    //   4609: ldc2_w 412
    //   4612: lconst_1
    //   4613: iconst_0
    //   4614: invokeinterface 178 8 0
    //   4619: ldc 68
    //   4621: aload 20
    //   4623: iconst_1
    //   4624: anewarray 4	java/lang/Object
    //   4627: dup
    //   4628: iconst_0
    //   4629: iload_2
    //   4630: invokestatic 418	java/lang/Integer:valueOf	(I)Ljava/lang/Integer;
    //   4633: aastore
    //   4634: invokestatic 139	com/tencent/luggage/wxa/qz/o:d	(Ljava/lang/String;Ljava/lang/String;[Ljava/lang/Object;)V
    //   4637: aload 31
    //   4639: iconst_0
    //   4640: putfield 142	com/tencent/luggage/wxa/nz/h:a	Z
    //   4643: aload 22
    //   4645: ifnull +36 -> 4681
    //   4648: aload 22
    //   4650: invokevirtual 421	java/io/InputStream:close	()V
    //   4653: goto +28 -> 4681
    //   4656: astore 20
    //   4658: ldc 68
    //   4660: aload 20
    //   4662: aload 24
    //   4664: iconst_2
    //   4665: anewarray 4	java/lang/Object
    //   4668: dup
    //   4669: iconst_0
    //   4670: aload 27
    //   4672: aastore
    //   4673: dup
    //   4674: iconst_1
    //   4675: aload 26
    //   4677: aastore
    //   4678: invokestatic 424	com/tencent/luggage/wxa/qz/o:a	(Ljava/lang/String;Ljava/lang/Throwable;Ljava/lang/String;[Ljava/lang/Object;)V
    //   4681: aload 28
    //   4683: invokevirtual 425	java/io/DataOutputStream:close	()V
    //   4686: goto +28 -> 4714
    //   4689: astore 20
    //   4691: ldc 68
    //   4693: aload 20
    //   4695: aload 25
    //   4697: iconst_2
    //   4698: anewarray 4	java/lang/Object
    //   4701: dup
    //   4702: iconst_0
    //   4703: aload 27
    //   4705: aastore
    //   4706: dup
    //   4707: iconst_1
    //   4708: aload 26
    //   4710: aastore
    //   4711: invokestatic 424	com/tencent/luggage/wxa/qz/o:a	(Ljava/lang/String;Ljava/lang/Throwable;Ljava/lang/String;[Ljava/lang/Object;)V
    //   4714: aload_0
    //   4715: getfield 14	com/tencent/luggage/wxa/nz/g$b:a	Lcom/tencent/luggage/wxa/nz/g;
    //   4718: getfield 428	com/tencent/luggage/wxa/nz/g:a	Ljava/util/ArrayList;
    //   4721: aload_1
    //   4722: invokevirtual 103	com/tencent/luggage/wxa/nz/h:l	()Ljava/lang/String;
    //   4725: invokevirtual 434	java/util/ArrayList:remove	(Ljava/lang/Object;)Z
    //   4728: pop
    //   4729: return
    //   4730: astore 21
    //   4732: goto +30 -> 4762
    //   4735: astore 30
    //   4737: goto +33 -> 4770
    //   4740: astore 23
    //   4742: goto +33 -> 4775
    //   4745: astore 23
    //   4747: goto +36 -> 4783
    //   4750: astore 23
    //   4752: goto +39 -> 4791
    //   4755: astore 23
    //   4757: goto +42 -> 4799
    //   4760: astore 21
    //   4762: aconst_null
    //   4763: astore 31
    //   4765: goto +1213 -> 5978
    //   4768: astore 30
    //   4770: goto +1231 -> 6001
    //   4773: astore 23
    //   4775: aconst_null
    //   4776: astore 31
    //   4778: goto +1295 -> 6073
    //   4781: astore 23
    //   4783: aconst_null
    //   4784: astore 31
    //   4786: goto +1319 -> 6105
    //   4789: astore 23
    //   4791: aconst_null
    //   4792: astore 31
    //   4794: goto +1343 -> 6137
    //   4797: astore 23
    //   4799: aconst_null
    //   4800: astore 31
    //   4802: goto +1367 -> 6169
    //   4805: aload_1
    //   4806: astore 36
    //   4808: aload 20
    //   4810: astore 33
    //   4812: ldc 68
    //   4814: ldc_w 489
    //   4817: iconst_1
    //   4818: anewarray 4	java/lang/Object
    //   4821: dup
    //   4822: iconst_0
    //   4823: aload 27
    //   4825: aastore
    //   4826: invokestatic 139	com/tencent/luggage/wxa/qz/o:d	(Ljava/lang/String;Ljava/lang/String;[Ljava/lang/Object;)V
    //   4829: aload 30
    //   4831: invokevirtual 492	java/net/HttpURLConnection:getContentEncoding	()Ljava/lang/String;
    //   4834: astore 31
    //   4836: ldc 254
    //   4838: aload 31
    //   4840: invokevirtual 495	java/lang/String:equals	(Ljava/lang/Object;)Z
    //   4843: ifeq +20 -> 4863
    //   4846: new 497	java/util/zip/GZIPInputStream
    //   4849: dup
    //   4850: aload 30
    //   4852: invokevirtual 501	java/net/HttpURLConnection:getInputStream	()Ljava/io/InputStream;
    //   4855: invokespecial 504	java/util/zip/GZIPInputStream:<init>	(Ljava/io/InputStream;)V
    //   4858: astore 31
    //   4860: goto +10 -> 4870
    //   4863: aload 30
    //   4865: invokevirtual 501	java/net/HttpURLConnection:getInputStream	()Ljava/io/InputStream;
    //   4868: astore 31
    //   4870: goto +118 -> 4988
    //   4873: astore 31
    //   4875: goto +30 -> 4905
    //   4878: astore 21
    //   4880: goto -118 -> 4762
    //   4883: astore 23
    //   4885: goto -110 -> 4775
    //   4888: astore 23
    //   4890: goto -107 -> 4783
    //   4893: astore 23
    //   4895: goto -104 -> 4791
    //   4898: astore 23
    //   4900: goto -101 -> 4799
    //   4903: astore 31
    //   4905: ldc 68
    //   4907: aload 31
    //   4909: ldc_w 506
    //   4912: iconst_0
    //   4913: anewarray 4	java/lang/Object
    //   4916: invokestatic 424	com/tencent/luggage/wxa/qz/o:a	(Ljava/lang/String;Ljava/lang/Throwable;Ljava/lang/String;[Ljava/lang/Object;)V
    //   4919: ldc 254
    //   4921: aload 30
    //   4923: invokevirtual 492	java/net/HttpURLConnection:getContentEncoding	()Ljava/lang/String;
    //   4926: invokevirtual 495	java/lang/String:equals	(Ljava/lang/Object;)Z
    //   4929: ifeq +24 -> 4953
    //   4932: new 497	java/util/zip/GZIPInputStream
    //   4935: dup
    //   4936: aload 30
    //   4938: invokevirtual 509	java/net/HttpURLConnection:getErrorStream	()Ljava/io/InputStream;
    //   4941: invokespecial 504	java/util/zip/GZIPInputStream:<init>	(Ljava/io/InputStream;)V
    //   4944: astore 35
    //   4946: aload 35
    //   4948: astore 31
    //   4950: goto -80 -> 4870
    //   4953: aload 30
    //   4955: invokevirtual 509	java/net/HttpURLConnection:getErrorStream	()Ljava/io/InputStream;
    //   4958: astore 35
    //   4960: aload 35
    //   4962: astore 31
    //   4964: goto -94 -> 4870
    //   4967: ldc 68
    //   4969: aload 31
    //   4971: ldc_w 511
    //   4974: iconst_0
    //   4975: anewarray 4	java/lang/Object
    //   4978: invokestatic 424	com/tencent/luggage/wxa/qz/o:a	(Ljava/lang/String;Ljava/lang/Throwable;Ljava/lang/String;[Ljava/lang/Object;)V
    //   4981: aload 41
    //   4983: astore 31
    //   4985: goto -115 -> 4870
    //   4988: aload 31
    //   4990: ifnull +162 -> 5152
    //   4993: new 513	java/io/BufferedReader
    //   4996: dup
    //   4997: new 515	java/io/InputStreamReader
    //   5000: dup
    //   5001: aload 31
    //   5003: invokespecial 516	java/io/InputStreamReader:<init>	(Ljava/io/InputStream;)V
    //   5006: invokespecial 519	java/io/BufferedReader:<init>	(Ljava/io/Reader;)V
    //   5009: astore 35
    //   5011: new 321	java/lang/StringBuilder
    //   5014: dup
    //   5015: invokespecial 322	java/lang/StringBuilder:<init>	()V
    //   5018: astore 39
    //   5020: aload 35
    //   5022: invokevirtual 522	java/io/BufferedReader:readLine	()Ljava/lang/String;
    //   5025: astore 40
    //   5027: aload 40
    //   5029: ifnull +22 -> 5051
    //   5032: aload 36
    //   5034: getfield 142	com/tencent/luggage/wxa/nz/h:a	Z
    //   5037: ifeq +14 -> 5051
    //   5040: aload 39
    //   5042: aload 40
    //   5044: invokevirtual 328	java/lang/StringBuilder:append	(Ljava/lang/String;)Ljava/lang/StringBuilder;
    //   5047: pop
    //   5048: goto -28 -> 5020
    //   5051: aload 39
    //   5053: invokevirtual 332	java/lang/StringBuilder:toString	()Ljava/lang/String;
    //   5056: astore 35
    //   5058: aload 35
    //   5060: aload 37
    //   5062: invokestatic 528	java/nio/charset/Charset:forName	(Ljava/lang/String;)Ljava/nio/charset/Charset;
    //   5065: invokevirtual 531	java/lang/String:getBytes	(Ljava/nio/charset/Charset;)[B
    //   5068: arraylength
    //   5069: istore_2
    //   5070: iload_2
    //   5071: istore 4
    //   5073: iload_2
    //   5074: istore 5
    //   5076: iload_2
    //   5077: istore 6
    //   5079: iload_2
    //   5080: istore 7
    //   5082: iload_2
    //   5083: istore 8
    //   5085: iload_2
    //   5086: istore 9
    //   5088: ldc 68
    //   5090: ldc_w 533
    //   5093: iconst_3
    //   5094: anewarray 4	java/lang/Object
    //   5097: dup
    //   5098: iconst_0
    //   5099: aload 38
    //   5101: aastore
    //   5102: dup
    //   5103: iconst_1
    //   5104: aload 35
    //   5106: aastore
    //   5107: dup
    //   5108: iconst_2
    //   5109: iload_3
    //   5110: invokestatic 418	java/lang/Integer:valueOf	(I)Ljava/lang/Integer;
    //   5113: aastore
    //   5114: invokestatic 139	com/tencent/luggage/wxa/qz/o:d	(Ljava/lang/String;Ljava/lang/String;[Ljava/lang/Object;)V
    //   5117: goto +41 -> 5158
    //   5120: astore 21
    //   5122: goto -357 -> 4765
    //   5125: astore 30
    //   5127: iconst_0
    //   5128: istore_2
    //   5129: goto +570 -> 5699
    //   5132: astore 23
    //   5134: goto -356 -> 4778
    //   5137: astore 23
    //   5139: goto -353 -> 4786
    //   5142: astore 23
    //   5144: goto -350 -> 4794
    //   5147: astore 23
    //   5149: goto -347 -> 4802
    //   5152: aload 34
    //   5154: astore 35
    //   5156: iconst_0
    //   5157: istore_2
    //   5158: aload 36
    //   5160: getfield 142	com/tencent/luggage/wxa/nz/h:a	Z
    //   5163: istore 11
    //   5165: iload 11
    //   5167: ifeq +142 -> 5309
    //   5170: iload_2
    //   5171: istore 4
    //   5173: iload_2
    //   5174: istore 5
    //   5176: iload_2
    //   5177: istore 6
    //   5179: iload_2
    //   5180: istore 7
    //   5182: iload_2
    //   5183: istore 8
    //   5185: iload_2
    //   5186: istore 9
    //   5188: aload_0
    //   5189: getfield 14	com/tencent/luggage/wxa/nz/g$b:a	Lcom/tencent/luggage/wxa/nz/g;
    //   5192: aload 32
    //   5194: iconst_0
    //   5195: aload 35
    //   5197: iload_3
    //   5198: aload_1
    //   5199: invokevirtual 103	com/tencent/luggage/wxa/nz/h:l	()Ljava/lang/String;
    //   5202: aload 30
    //   5204: invokestatic 479	com/tencent/luggage/wxa/nz/g:a	(Lcom/tencent/luggage/wxa/nz/g;Lcom/tencent/luggage/wxa/nz/g$a;ILjava/lang/String;ILjava/lang/String;Ljava/net/HttpURLConnection;)V
    //   5207: iload_2
    //   5208: istore 4
    //   5210: iload_2
    //   5211: istore 5
    //   5213: iload_2
    //   5214: istore 6
    //   5216: iload_2
    //   5217: istore 7
    //   5219: iload_2
    //   5220: istore 8
    //   5222: iload_2
    //   5223: istore 9
    //   5225: ldc 68
    //   5227: ldc_w 535
    //   5230: iconst_2
    //   5231: anewarray 4	java/lang/Object
    //   5234: dup
    //   5235: iconst_0
    //   5236: aload 27
    //   5238: aastore
    //   5239: dup
    //   5240: iconst_1
    //   5241: aload 26
    //   5243: aastore
    //   5244: invokestatic 139	com/tencent/luggage/wxa/qz/o:d	(Ljava/lang/String;Ljava/lang/String;[Ljava/lang/Object;)V
    //   5247: iconst_1
    //   5248: istore 4
    //   5250: goto +88 -> 5338
    //   5253: astore 20
    //   5255: iload 4
    //   5257: istore_2
    //   5258: aload 29
    //   5260: astore 36
    //   5262: aload 27
    //   5264: astore 23
    //   5266: goto +5612 -> 10878
    //   5269: astore 30
    //   5271: iload 5
    //   5273: istore_2
    //   5274: goto +425 -> 5699
    //   5277: astore 38
    //   5279: iload 6
    //   5281: istore_2
    //   5282: goto +434 -> 5716
    //   5285: astore 38
    //   5287: iload 7
    //   5289: istore_2
    //   5290: goto +477 -> 5767
    //   5293: astore 38
    //   5295: iload 8
    //   5297: istore_2
    //   5298: goto +520 -> 5818
    //   5301: astore 38
    //   5303: iload 9
    //   5305: istore_2
    //   5306: goto +563 -> 5869
    //   5309: aload_0
    //   5310: getfield 14	com/tencent/luggage/wxa/nz/g$b:a	Lcom/tencent/luggage/wxa/nz/g;
    //   5313: aload 32
    //   5315: iconst_m1
    //   5316: ldc 144
    //   5318: iload_3
    //   5319: aload_1
    //   5320: invokevirtual 103	com/tencent/luggage/wxa/nz/h:l	()Ljava/lang/String;
    //   5323: aload 30
    //   5325: invokestatic 479	com/tencent/luggage/wxa/nz/g:a	(Lcom/tencent/luggage/wxa/nz/g;Lcom/tencent/luggage/wxa/nz/g$a;ILjava/lang/String;ILjava/lang/String;Ljava/net/HttpURLConnection;)V
    //   5328: ldc 68
    //   5330: ldc 146
    //   5332: invokestatic 149	com/tencent/luggage/wxa/qz/o:b	(Ljava/lang/String;Ljava/lang/String;)V
    //   5335: iconst_0
    //   5336: istore 4
    //   5338: iload 4
    //   5340: ifeq +54 -> 5394
    //   5343: ldc 110
    //   5345: invokestatic 115	com/tencent/luggage/wxa/ba/e:b	(Ljava/lang/Class;)Lcom/tencent/luggage/wxa/ba/d;
    //   5348: checkcast 110	com/tencent/luggage/wxa/nz/o
    //   5351: aload_0
    //   5352: getfield 14	com/tencent/luggage/wxa/nz/g$b:a	Lcom/tencent/luggage/wxa/nz/g;
    //   5355: invokestatic 118	com/tencent/luggage/wxa/nz/g:a	(Lcom/tencent/luggage/wxa/nz/g;)Lcom/tencent/luggage/wxa/jx/c;
    //   5358: invokeinterface 123 1 0
    //   5363: aload_1
    //   5364: invokevirtual 126	com/tencent/luggage/wxa/nz/h:n	()Ljava/lang/String;
    //   5367: ldc 128
    //   5369: aload_1
    //   5370: invokevirtual 49	com/tencent/luggage/wxa/nz/h:b	()Ljava/lang/String;
    //   5373: lload 12
    //   5375: iload_2
    //   5376: i2l
    //   5377: iload_3
    //   5378: iconst_1
    //   5379: aload_1
    //   5380: invokevirtual 132	com/tencent/luggage/wxa/nz/h:o	()I
    //   5383: aconst_null
    //   5384: aload 29
    //   5386: invokeinterface 135 14 0
    //   5391: goto +102 -> 5493
    //   5394: ldc 110
    //   5396: invokestatic 115	com/tencent/luggage/wxa/ba/e:b	(Ljava/lang/Class;)Lcom/tencent/luggage/wxa/ba/d;
    //   5399: checkcast 110	com/tencent/luggage/wxa/nz/o
    //   5402: aload_0
    //   5403: getfield 14	com/tencent/luggage/wxa/nz/g$b:a	Lcom/tencent/luggage/wxa/nz/g;
    //   5406: invokestatic 118	com/tencent/luggage/wxa/nz/g:a	(Lcom/tencent/luggage/wxa/nz/g;)Lcom/tencent/luggage/wxa/jx/c;
    //   5409: invokeinterface 123 1 0
    //   5414: aload_1
    //   5415: invokevirtual 126	com/tencent/luggage/wxa/nz/h:n	()Ljava/lang/String;
    //   5418: ldc 128
    //   5420: aload_1
    //   5421: invokevirtual 49	com/tencent/luggage/wxa/nz/h:b	()Ljava/lang/String;
    //   5424: lload 12
    //   5426: iload_2
    //   5427: i2l
    //   5428: iload_3
    //   5429: iconst_2
    //   5430: aload_1
    //   5431: invokevirtual 132	com/tencent/luggage/wxa/nz/h:o	()I
    //   5434: aconst_null
    //   5435: aload 29
    //   5437: invokeinterface 135 14 0
    //   5442: invokestatic 406	com/tencent/luggage/wxa/qz/r:a	()Landroid/content/Context;
    //   5445: invokestatic 411	com/tencent/luggage/wxa/qz/x:d	(Landroid/content/Context;)I
    //   5448: istore_2
    //   5449: iload_2
    //   5450: iconst_m1
    //   5451: if_icmpne +24 -> 5475
    //   5454: ldc 173
    //   5456: invokestatic 115	com/tencent/luggage/wxa/ba/e:b	(Ljava/lang/Class;)Lcom/tencent/luggage/wxa/ba/d;
    //   5459: checkcast 173	com/tencent/luggage/wxa/ot/c
    //   5462: ldc2_w 174
    //   5465: ldc2_w 412
    //   5468: lconst_1
    //   5469: iconst_0
    //   5470: invokeinterface 178 8 0
    //   5475: ldc 68
    //   5477: aload 33
    //   5479: iconst_1
    //   5480: anewarray 4	java/lang/Object
    //   5483: dup
    //   5484: iconst_0
    //   5485: iload_2
    //   5486: invokestatic 418	java/lang/Integer:valueOf	(I)Ljava/lang/Integer;
    //   5489: aastore
    //   5490: invokestatic 139	com/tencent/luggage/wxa/qz/o:d	(Ljava/lang/String;Ljava/lang/String;[Ljava/lang/Object;)V
    //   5493: aload 36
    //   5495: iconst_0
    //   5496: putfield 142	com/tencent/luggage/wxa/nz/h:a	Z
    //   5499: aload 22
    //   5501: ifnull +36 -> 5537
    //   5504: aload 22
    //   5506: invokevirtual 421	java/io/InputStream:close	()V
    //   5509: goto +28 -> 5537
    //   5512: astore 20
    //   5514: ldc 68
    //   5516: aload 20
    //   5518: aload 24
    //   5520: iconst_2
    //   5521: anewarray 4	java/lang/Object
    //   5524: dup
    //   5525: iconst_0
    //   5526: aload 27
    //   5528: aastore
    //   5529: dup
    //   5530: iconst_1
    //   5531: aload 26
    //   5533: aastore
    //   5534: invokestatic 424	com/tencent/luggage/wxa/qz/o:a	(Ljava/lang/String;Ljava/lang/Throwable;Ljava/lang/String;[Ljava/lang/Object;)V
    //   5537: aload 31
    //   5539: ifnull +94 -> 5633
    //   5542: aload 31
    //   5544: invokevirtual 421	java/io/InputStream:close	()V
    //   5547: goto +86 -> 5633
    //   5550: astore 20
    //   5552: ldc 68
    //   5554: aload 20
    //   5556: ldc_w 537
    //   5559: iconst_2
    //   5560: anewarray 4	java/lang/Object
    //   5563: dup
    //   5564: iconst_0
    //   5565: aload 27
    //   5567: aastore
    //   5568: dup
    //   5569: iconst_1
    //   5570: aload 26
    //   5572: aastore
    //   5573: invokestatic 424	com/tencent/luggage/wxa/qz/o:a	(Ljava/lang/String;Ljava/lang/Throwable;Ljava/lang/String;[Ljava/lang/Object;)V
    //   5576: goto +57 -> 5633
    //   5579: astore 20
    //   5581: ldc 68
    //   5583: aload 20
    //   5585: ldc_w 539
    //   5588: iconst_2
    //   5589: anewarray 4	java/lang/Object
    //   5592: dup
    //   5593: iconst_0
    //   5594: aload 27
    //   5596: aastore
    //   5597: dup
    //   5598: iconst_1
    //   5599: aload 26
    //   5601: aastore
    //   5602: invokestatic 424	com/tencent/luggage/wxa/qz/o:a	(Ljava/lang/String;Ljava/lang/Throwable;Ljava/lang/String;[Ljava/lang/Object;)V
    //   5605: goto +28 -> 5633
    //   5608: astore 20
    //   5610: ldc 68
    //   5612: aload 20
    //   5614: aload 25
    //   5616: iconst_2
    //   5617: anewarray 4	java/lang/Object
    //   5620: dup
    //   5621: iconst_0
    //   5622: aload 27
    //   5624: aastore
    //   5625: dup
    //   5626: iconst_1
    //   5627: aload 26
    //   5629: aastore
    //   5630: invokestatic 424	com/tencent/luggage/wxa/qz/o:a	(Ljava/lang/String;Ljava/lang/Throwable;Ljava/lang/String;[Ljava/lang/Object;)V
    //   5633: aload 28
    //   5635: invokevirtual 425	java/io/DataOutputStream:close	()V
    //   5638: goto +5127 -> 10765
    //   5641: astore 20
    //   5643: ldc 68
    //   5645: aload 20
    //   5647: aload 25
    //   5649: iconst_2
    //   5650: anewarray 4	java/lang/Object
    //   5653: dup
    //   5654: iconst_0
    //   5655: aload 27
    //   5657: aastore
    //   5658: dup
    //   5659: iconst_1
    //   5660: aload 26
    //   5662: aastore
    //   5663: invokestatic 424	com/tencent/luggage/wxa/qz/o:a	(Ljava/lang/String;Ljava/lang/Throwable;Ljava/lang/String;[Ljava/lang/Object;)V
    //   5666: goto +5099 -> 10765
    //   5669: astore 23
    //   5671: aload 25
    //   5673: astore 20
    //   5675: aload 31
    //   5677: astore 21
    //   5679: iload_2
    //   5680: istore 4
    //   5682: aload 29
    //   5684: astore 25
    //   5686: aload 22
    //   5688: astore 29
    //   5690: aload 27
    //   5692: astore 30
    //   5694: goto +5153 -> 10847
    //   5697: astore 30
    //   5699: aload 31
    //   5701: astore 32
    //   5703: aload 30
    //   5705: astore 31
    //   5707: aload 32
    //   5709: astore 30
    //   5711: goto +299 -> 6010
    //   5714: astore 38
    //   5716: aload 30
    //   5718: astore 40
    //   5720: aload 25
    //   5722: astore 30
    //   5724: iload_3
    //   5725: istore 4
    //   5727: aload 32
    //   5729: astore 39
    //   5731: aload 28
    //   5733: astore 37
    //   5735: aload 24
    //   5737: astore 32
    //   5739: iload_2
    //   5740: istore 5
    //   5742: lload 12
    //   5744: lstore 14
    //   5746: aload 29
    //   5748: astore 35
    //   5750: aload 26
    //   5752: astore 29
    //   5754: aload 22
    //   5756: astore 36
    //   5758: aload 27
    //   5760: astore 34
    //   5762: goto +2782 -> 8544
    //   5765: astore 38
    //   5767: aload 30
    //   5769: astore 40
    //   5771: aload 25
    //   5773: astore 30
    //   5775: iload_3
    //   5776: istore 4
    //   5778: aload 32
    //   5780: astore 39
    //   5782: aload 28
    //   5784: astore 37
    //   5786: aload 24
    //   5788: astore 32
    //   5790: iload_2
    //   5791: istore 5
    //   5793: lload 12
    //   5795: lstore 14
    //   5797: aload 29
    //   5799: astore 35
    //   5801: aload 26
    //   5803: astore 29
    //   5805: aload 22
    //   5807: astore 36
    //   5809: aload 27
    //   5811: astore 34
    //   5813: goto +3330 -> 9143
    //   5816: astore 38
    //   5818: aload 30
    //   5820: astore 40
    //   5822: aload 25
    //   5824: astore 30
    //   5826: iload_3
    //   5827: istore 4
    //   5829: aload 32
    //   5831: astore 39
    //   5833: aload 28
    //   5835: astore 37
    //   5837: aload 24
    //   5839: astore 32
    //   5841: iload_2
    //   5842: istore 5
    //   5844: lload 12
    //   5846: lstore 14
    //   5848: aload 29
    //   5850: astore 35
    //   5852: aload 26
    //   5854: astore 29
    //   5856: aload 22
    //   5858: astore 36
    //   5860: aload 27
    //   5862: astore 34
    //   5864: goto +3878 -> 9742
    //   5867: astore 38
    //   5869: aload 25
    //   5871: astore 34
    //   5873: iload_3
    //   5874: istore 4
    //   5876: aload 32
    //   5878: astore 39
    //   5880: aload 28
    //   5882: astore 35
    //   5884: aload 24
    //   5886: astore 32
    //   5888: iload_2
    //   5889: istore 5
    //   5891: aload 30
    //   5893: astore 40
    //   5895: lload 12
    //   5897: lstore 14
    //   5899: aload 29
    //   5901: astore 36
    //   5903: aload 26
    //   5905: astore 29
    //   5907: aload 22
    //   5909: astore 37
    //   5911: aload 27
    //   5913: astore 30
    //   5915: goto +4459 -> 10374
    //   5918: astore 21
    //   5920: goto +55 -> 5975
    //   5923: astore 30
    //   5925: goto +76 -> 6001
    //   5928: astore 23
    //   5930: goto +140 -> 6070
    //   5933: astore 23
    //   5935: goto +167 -> 6102
    //   5938: astore 23
    //   5940: goto +194 -> 6134
    //   5943: astore 23
    //   5945: goto +221 -> 6166
    //   5948: astore 30
    //   5950: goto +51 -> 6001
    //   5953: astore 23
    //   5955: goto +115 -> 6070
    //   5958: astore 23
    //   5960: goto +142 -> 6102
    //   5963: astore 23
    //   5965: goto +169 -> 6134
    //   5968: astore 23
    //   5970: goto +196 -> 6166
    //   5973: astore 21
    //   5975: aconst_null
    //   5976: astore 31
    //   5978: aload 20
    //   5980: astore 33
    //   5982: iconst_0
    //   5983: istore_2
    //   5984: aload 21
    //   5986: astore 20
    //   5988: aload 29
    //   5990: astore 36
    //   5992: aload 27
    //   5994: astore 23
    //   5996: goto +4882 -> 10878
    //   5999: astore 30
    //   6001: aload 30
    //   6003: astore 31
    //   6005: aconst_null
    //   6006: astore 30
    //   6008: iconst_0
    //   6009: istore_2
    //   6010: aload 28
    //   6012: astore 33
    //   6014: iload 10
    //   6016: istore_3
    //   6017: aload 31
    //   6019: astore 32
    //   6021: aload 21
    //   6023: astore 35
    //   6025: aload 20
    //   6027: astore 21
    //   6029: aload 30
    //   6031: astore 28
    //   6033: aload 24
    //   6035: astore 31
    //   6037: aload 33
    //   6039: astore 20
    //   6041: aload 23
    //   6043: astore 36
    //   6045: aload 29
    //   6047: astore 33
    //   6049: aload 26
    //   6051: astore 24
    //   6053: aload 22
    //   6055: astore 30
    //   6057: aload 27
    //   6059: astore 23
    //   6061: aload 34
    //   6063: astore 37
    //   6065: goto +1945 -> 8010
    //   6068: astore 23
    //   6070: aconst_null
    //   6071: astore 31
    //   6073: aload 20
    //   6075: astore 33
    //   6077: aload 23
    //   6079: astore 20
    //   6081: aload 30
    //   6083: astore 23
    //   6085: aload 29
    //   6087: astore 35
    //   6089: aload 22
    //   6091: astore 36
    //   6093: aload 27
    //   6095: astore 34
    //   6097: goto +2409 -> 8506
    //   6100: astore 23
    //   6102: aconst_null
    //   6103: astore 31
    //   6105: aload 20
    //   6107: astore 33
    //   6109: aload 23
    //   6111: astore 20
    //   6113: aload 30
    //   6115: astore 23
    //   6117: aload 29
    //   6119: astore 35
    //   6121: aload 22
    //   6123: astore 36
    //   6125: aload 27
    //   6127: astore 34
    //   6129: goto +2976 -> 9105
    //   6132: astore 23
    //   6134: aconst_null
    //   6135: astore 31
    //   6137: aload 20
    //   6139: astore 33
    //   6141: aload 23
    //   6143: astore 20
    //   6145: aload 30
    //   6147: astore 23
    //   6149: aload 29
    //   6151: astore 35
    //   6153: aload 22
    //   6155: astore 36
    //   6157: aload 27
    //   6159: astore 34
    //   6161: goto +3543 -> 9704
    //   6164: astore 23
    //   6166: aconst_null
    //   6167: astore 31
    //   6169: aload 20
    //   6171: astore 33
    //   6173: aload 23
    //   6175: astore 20
    //   6177: aload 30
    //   6179: astore 23
    //   6181: aload 29
    //   6183: astore 36
    //   6185: aload 22
    //   6187: astore 37
    //   6189: aload 27
    //   6191: astore 30
    //   6193: goto +4143 -> 10336
    //   6196: astore 23
    //   6198: aload 20
    //   6200: astore 21
    //   6202: aload 23
    //   6204: astore 20
    //   6206: aload 25
    //   6208: astore 32
    //   6210: aload 22
    //   6212: astore 23
    //   6214: aload 27
    //   6216: astore 25
    //   6218: goto +496 -> 6714
    //   6221: astore 31
    //   6223: aload 20
    //   6225: astore 23
    //   6227: aload 21
    //   6229: astore 32
    //   6231: aload 31
    //   6233: astore 20
    //   6235: aload 25
    //   6237: astore 21
    //   6239: aload 24
    //   6241: astore 31
    //   6243: aload 26
    //   6245: astore 25
    //   6247: goto +536 -> 6783
    //   6250: astore 31
    //   6252: aload 20
    //   6254: astore 23
    //   6256: aload 21
    //   6258: astore 32
    //   6260: aload 31
    //   6262: astore 20
    //   6264: aload 25
    //   6266: astore 21
    //   6268: aload 23
    //   6270: astore 25
    //   6272: aload 24
    //   6274: astore 31
    //   6276: aload 26
    //   6278: astore 23
    //   6280: aload 27
    //   6282: astore 26
    //   6284: goto +584 -> 6868
    //   6287: astore 31
    //   6289: aload 20
    //   6291: astore 23
    //   6293: aload 21
    //   6295: astore 32
    //   6297: aload 31
    //   6299: astore 20
    //   6301: aload 25
    //   6303: astore 21
    //   6305: aload 23
    //   6307: astore 25
    //   6309: aload 24
    //   6311: astore 31
    //   6313: aload 26
    //   6315: astore 23
    //   6317: aload 27
    //   6319: astore 26
    //   6321: goto +624 -> 6945
    //   6324: astore 31
    //   6326: aload 20
    //   6328: astore 23
    //   6330: aload 21
    //   6332: astore 32
    //   6334: aload 31
    //   6336: astore 20
    //   6338: aload 25
    //   6340: astore 21
    //   6342: aload 23
    //   6344: astore 25
    //   6346: aload 24
    //   6348: astore 31
    //   6350: aload 26
    //   6352: astore 23
    //   6354: aload 27
    //   6356: astore 26
    //   6358: goto +664 -> 7022
    //   6361: astore 31
    //   6363: aload 20
    //   6365: astore 23
    //   6367: aload 21
    //   6369: astore 32
    //   6371: aload 31
    //   6373: astore 20
    //   6375: aload 25
    //   6377: astore 21
    //   6379: aload 23
    //   6381: astore 25
    //   6383: aload 24
    //   6385: astore 31
    //   6387: aload 26
    //   6389: astore 23
    //   6391: aload 27
    //   6393: astore 26
    //   6395: goto +704 -> 7099
    //   6398: astore 23
    //   6400: aload 25
    //   6402: astore 32
    //   6404: aload 20
    //   6406: astore 21
    //   6408: aload 27
    //   6410: astore 25
    //   6412: aload 23
    //   6414: astore 20
    //   6416: aload 22
    //   6418: astore 23
    //   6420: goto +294 -> 6714
    //   6423: astore 33
    //   6425: aload 29
    //   6427: astore 30
    //   6429: aload 21
    //   6431: astore 29
    //   6433: aload 25
    //   6435: astore 21
    //   6437: aload 24
    //   6439: astore 31
    //   6441: aload 20
    //   6443: astore 32
    //   6445: aload 26
    //   6447: astore 25
    //   6449: aload 33
    //   6451: astore 20
    //   6453: aload 29
    //   6455: astore 24
    //   6457: aload 32
    //   6459: astore 26
    //   6461: aload 23
    //   6463: astore 29
    //   6465: aload 30
    //   6467: astore 23
    //   6469: goto +298 -> 6767
    //   6472: astore 33
    //   6474: aload 29
    //   6476: astore 31
    //   6478: aload 21
    //   6480: astore 29
    //   6482: aload 25
    //   6484: astore 21
    //   6486: aload 24
    //   6488: astore 32
    //   6490: aload 20
    //   6492: astore 25
    //   6494: aload 26
    //   6496: astore 30
    //   6498: aload 27
    //   6500: astore 26
    //   6502: aload 33
    //   6504: astore 20
    //   6506: aload 29
    //   6508: astore 24
    //   6510: aload 32
    //   6512: astore 27
    //   6514: aload 23
    //   6516: astore 29
    //   6518: aload 30
    //   6520: astore 23
    //   6522: goto +330 -> 6852
    //   6525: astore 33
    //   6527: aload 29
    //   6529: astore 31
    //   6531: aload 21
    //   6533: astore 29
    //   6535: aload 25
    //   6537: astore 21
    //   6539: aload 24
    //   6541: astore 32
    //   6543: aload 20
    //   6545: astore 25
    //   6547: aload 26
    //   6549: astore 30
    //   6551: aload 27
    //   6553: astore 26
    //   6555: aload 33
    //   6557: astore 20
    //   6559: aload 29
    //   6561: astore 24
    //   6563: aload 32
    //   6565: astore 27
    //   6567: aload 23
    //   6569: astore 29
    //   6571: aload 30
    //   6573: astore 23
    //   6575: goto +354 -> 6929
    //   6578: astore 33
    //   6580: aload 29
    //   6582: astore 31
    //   6584: aload 21
    //   6586: astore 29
    //   6588: aload 25
    //   6590: astore 21
    //   6592: aload 24
    //   6594: astore 32
    //   6596: aload 20
    //   6598: astore 25
    //   6600: aload 26
    //   6602: astore 30
    //   6604: aload 27
    //   6606: astore 26
    //   6608: aload 33
    //   6610: astore 20
    //   6612: aload 29
    //   6614: astore 24
    //   6616: aload 32
    //   6618: astore 27
    //   6620: aload 23
    //   6622: astore 29
    //   6624: aload 30
    //   6626: astore 23
    //   6628: goto +378 -> 7006
    //   6631: astore 33
    //   6633: aload 29
    //   6635: astore 31
    //   6637: aload 21
    //   6639: astore 29
    //   6641: aload 25
    //   6643: astore 21
    //   6645: aload 24
    //   6647: astore 32
    //   6649: aload 20
    //   6651: astore 25
    //   6653: aload 26
    //   6655: astore 30
    //   6657: aload 27
    //   6659: astore 26
    //   6661: aload 33
    //   6663: astore 20
    //   6665: aload 29
    //   6667: astore 24
    //   6669: aload 32
    //   6671: astore 27
    //   6673: aload 23
    //   6675: astore 29
    //   6677: aload 30
    //   6679: astore 23
    //   6681: goto +402 -> 7083
    //   6684: astore 30
    //   6686: aload 31
    //   6688: astore 29
    //   6690: aload 25
    //   6692: astore 32
    //   6694: aload 23
    //   6696: astore 21
    //   6698: aload 27
    //   6700: astore 25
    //   6702: aload 20
    //   6704: astore 23
    //   6706: aload 22
    //   6708: astore 26
    //   6710: aload 30
    //   6712: astore 20
    //   6714: aload 24
    //   6716: astore 31
    //   6718: aload 29
    //   6720: astore 27
    //   6722: aload 26
    //   6724: astore 22
    //   6726: aload 25
    //   6728: astore 24
    //   6730: goto +1131 -> 7861
    //   6733: astore 30
    //   6735: aload 25
    //   6737: astore 21
    //   6739: aload 23
    //   6741: astore 26
    //   6743: aload 22
    //   6745: astore 25
    //   6747: aload 20
    //   6749: astore 22
    //   6751: aload 31
    //   6753: astore 23
    //   6755: aload 24
    //   6757: astore 31
    //   6759: aload 32
    //   6761: astore 24
    //   6763: aload 30
    //   6765: astore 20
    //   6767: aload 29
    //   6769: astore 30
    //   6771: aload 23
    //   6773: astore 29
    //   6775: aload 26
    //   6777: astore 23
    //   6779: aload 24
    //   6781: astore 32
    //   6783: aload 21
    //   6785: astore 35
    //   6787: aload 32
    //   6789: astore 21
    //   6791: aload 23
    //   6793: astore 24
    //   6795: aload 28
    //   6797: astore 23
    //   6799: aload 29
    //   6801: astore 33
    //   6803: aload 22
    //   6805: astore 26
    //   6807: aload 27
    //   6809: astore 28
    //   6811: aload 34
    //   6813: astore 29
    //   6815: goto +498 -> 7313
    //   6818: astore 30
    //   6820: aload 25
    //   6822: astore 21
    //   6824: aload 23
    //   6826: astore 25
    //   6828: aload 22
    //   6830: astore 23
    //   6832: aload 27
    //   6834: astore 26
    //   6836: aload 20
    //   6838: astore 22
    //   6840: aload 24
    //   6842: astore 27
    //   6844: aload 32
    //   6846: astore 24
    //   6848: aload 30
    //   6850: astore 20
    //   6852: aload 29
    //   6854: astore 30
    //   6856: aload 31
    //   6858: astore 29
    //   6860: aload 27
    //   6862: astore 31
    //   6864: aload 24
    //   6866: astore 32
    //   6868: aload 21
    //   6870: astore 34
    //   6872: aload 32
    //   6874: astore 21
    //   6876: aload 25
    //   6878: astore 33
    //   6880: aload 29
    //   6882: astore 27
    //   6884: aload 23
    //   6886: astore 24
    //   6888: aload 22
    //   6890: astore 25
    //   6892: goto +473 -> 7365
    //   6895: astore 30
    //   6897: aload 25
    //   6899: astore 21
    //   6901: aload 23
    //   6903: astore 25
    //   6905: aload 22
    //   6907: astore 23
    //   6909: aload 27
    //   6911: astore 26
    //   6913: aload 20
    //   6915: astore 22
    //   6917: aload 24
    //   6919: astore 27
    //   6921: aload 32
    //   6923: astore 24
    //   6925: aload 30
    //   6927: astore 20
    //   6929: aload 29
    //   6931: astore 30
    //   6933: aload 31
    //   6935: astore 29
    //   6937: aload 27
    //   6939: astore 31
    //   6941: aload 24
    //   6943: astore 32
    //   6945: aload 21
    //   6947: astore 34
    //   6949: aload 32
    //   6951: astore 21
    //   6953: aload 25
    //   6955: astore 33
    //   6957: aload 29
    //   6959: astore 27
    //   6961: aload 23
    //   6963: astore 24
    //   6965: aload 22
    //   6967: astore 25
    //   6969: goto +444 -> 7413
    //   6972: astore 30
    //   6974: aload 25
    //   6976: astore 21
    //   6978: aload 23
    //   6980: astore 25
    //   6982: aload 22
    //   6984: astore 23
    //   6986: aload 27
    //   6988: astore 26
    //   6990: aload 20
    //   6992: astore 22
    //   6994: aload 24
    //   6996: astore 27
    //   6998: aload 32
    //   7000: astore 24
    //   7002: aload 30
    //   7004: astore 20
    //   7006: aload 29
    //   7008: astore 30
    //   7010: aload 31
    //   7012: astore 29
    //   7014: aload 27
    //   7016: astore 31
    //   7018: aload 24
    //   7020: astore 32
    //   7022: aload 21
    //   7024: astore 34
    //   7026: aload 32
    //   7028: astore 21
    //   7030: aload 25
    //   7032: astore 33
    //   7034: aload 29
    //   7036: astore 27
    //   7038: aload 23
    //   7040: astore 24
    //   7042: aload 22
    //   7044: astore 25
    //   7046: goto +415 -> 7461
    //   7049: astore 30
    //   7051: aload 25
    //   7053: astore 21
    //   7055: aload 23
    //   7057: astore 25
    //   7059: aload 22
    //   7061: astore 23
    //   7063: aload 27
    //   7065: astore 26
    //   7067: aload 20
    //   7069: astore 22
    //   7071: aload 24
    //   7073: astore 27
    //   7075: aload 32
    //   7077: astore 24
    //   7079: aload 30
    //   7081: astore 20
    //   7083: aload 29
    //   7085: astore 30
    //   7087: aload 31
    //   7089: astore 29
    //   7091: aload 27
    //   7093: astore 31
    //   7095: aload 24
    //   7097: astore 32
    //   7099: aload 21
    //   7101: astore 34
    //   7103: aload 32
    //   7105: astore 21
    //   7107: aload 25
    //   7109: astore 33
    //   7111: aload 29
    //   7113: astore 27
    //   7115: aload 23
    //   7117: astore 24
    //   7119: aload 22
    //   7121: astore 25
    //   7123: goto +386 -> 7509
    //   7126: astore 22
    //   7128: goto +43 -> 7171
    //   7131: astore 22
    //   7133: goto +51 -> 7184
    //   7136: astore 22
    //   7138: goto +59 -> 7197
    //   7141: astore 22
    //   7143: goto +67 -> 7210
    //   7146: astore 22
    //   7148: goto +75 -> 7223
    //   7151: astore 22
    //   7153: goto +18 -> 7171
    //   7156: astore 21
    //   7158: aload 27
    //   7160: astore 24
    //   7162: aload 31
    //   7164: astore 27
    //   7166: goto +364 -> 7530
    //   7169: astore 22
    //   7171: aload 27
    //   7173: astore 28
    //   7175: aload 31
    //   7177: astore 27
    //   7179: goto +91 -> 7270
    //   7182: astore 22
    //   7184: aload 27
    //   7186: astore 26
    //   7188: aload 31
    //   7190: astore 27
    //   7192: goto +142 -> 7334
    //   7195: astore 22
    //   7197: aload 27
    //   7199: astore 26
    //   7201: aload 31
    //   7203: astore 27
    //   7205: goto +177 -> 7382
    //   7208: astore 22
    //   7210: aload 27
    //   7212: astore 26
    //   7214: aload 31
    //   7216: astore 27
    //   7218: goto +212 -> 7430
    //   7221: astore 22
    //   7223: aload 27
    //   7225: astore 26
    //   7227: aload 31
    //   7229: astore 27
    //   7231: goto +247 -> 7478
    //   7234: astore 21
    //   7236: goto +290 -> 7526
    //   7239: astore 22
    //   7241: goto +25 -> 7266
    //   7244: astore 22
    //   7246: goto +88 -> 7334
    //   7249: astore 22
    //   7251: goto +131 -> 7382
    //   7254: astore 22
    //   7256: goto +174 -> 7430
    //   7259: astore 22
    //   7261: goto +217 -> 7478
    //   7264: astore 22
    //   7266: aload 26
    //   7268: astore 28
    //   7270: ldc 202
    //   7272: astore 32
    //   7274: aload 20
    //   7276: astore 26
    //   7278: aload 30
    //   7280: astore 25
    //   7282: ldc 84
    //   7284: astore 31
    //   7286: ldc 89
    //   7288: astore 24
    //   7290: ldc 66
    //   7292: astore 35
    //   7294: aload 29
    //   7296: astore 30
    //   7298: aload 22
    //   7300: astore 20
    //   7302: aconst_null
    //   7303: astore 23
    //   7305: aload 32
    //   7307: astore 29
    //   7309: aload 27
    //   7311: astore 33
    //   7313: aload 35
    //   7315: astore 32
    //   7317: aload 24
    //   7319: astore 22
    //   7321: aload 30
    //   7323: astore 24
    //   7325: aload 33
    //   7327: astore 27
    //   7329: goto +594 -> 7923
    //   7332: astore 22
    //   7334: aload 20
    //   7336: astore 25
    //   7338: aload 30
    //   7340: astore 24
    //   7342: ldc 84
    //   7344: astore 31
    //   7346: ldc 89
    //   7348: astore 33
    //   7350: ldc 66
    //   7352: astore 34
    //   7354: aload 22
    //   7356: astore 20
    //   7358: aconst_null
    //   7359: astore 28
    //   7361: aload 29
    //   7363: astore 30
    //   7365: aload 30
    //   7367: astore 23
    //   7369: aload 34
    //   7371: astore 32
    //   7373: aload 33
    //   7375: astore 22
    //   7377: goto +1092 -> 8469
    //   7380: astore 22
    //   7382: aload 20
    //   7384: astore 25
    //   7386: aload 30
    //   7388: astore 24
    //   7390: ldc 84
    //   7392: astore 31
    //   7394: ldc 89
    //   7396: astore 33
    //   7398: ldc 66
    //   7400: astore 34
    //   7402: aload 22
    //   7404: astore 20
    //   7406: aconst_null
    //   7407: astore 28
    //   7409: aload 29
    //   7411: astore 30
    //   7413: aload 30
    //   7415: astore 23
    //   7417: aload 34
    //   7419: astore 32
    //   7421: aload 33
    //   7423: astore 22
    //   7425: goto +1643 -> 9068
    //   7428: astore 22
    //   7430: aload 20
    //   7432: astore 25
    //   7434: aload 30
    //   7436: astore 24
    //   7438: ldc 84
    //   7440: astore 31
    //   7442: ldc 89
    //   7444: astore 33
    //   7446: ldc 66
    //   7448: astore 34
    //   7450: aload 22
    //   7452: astore 20
    //   7454: aconst_null
    //   7455: astore 28
    //   7457: aload 29
    //   7459: astore 30
    //   7461: aload 30
    //   7463: astore 23
    //   7465: aload 34
    //   7467: astore 32
    //   7469: aload 33
    //   7471: astore 22
    //   7473: goto +2194 -> 9667
    //   7476: astore 22
    //   7478: aload 20
    //   7480: astore 25
    //   7482: aload 30
    //   7484: astore 24
    //   7486: ldc 84
    //   7488: astore 31
    //   7490: ldc 89
    //   7492: astore 33
    //   7494: ldc 66
    //   7496: astore 34
    //   7498: aload 22
    //   7500: astore 20
    //   7502: aconst_null
    //   7503: astore 28
    //   7505: aload 29
    //   7507: astore 30
    //   7509: aload 30
    //   7511: astore 23
    //   7513: aload 34
    //   7515: astore 32
    //   7517: aload 33
    //   7519: astore 22
    //   7521: goto +2778 -> 10299
    //   7524: astore 21
    //   7526: aload 26
    //   7528: astore 24
    //   7530: aload 20
    //   7532: astore 23
    //   7534: aload 30
    //   7536: astore 22
    //   7538: ldc 84
    //   7540: astore 31
    //   7542: ldc 89
    //   7544: astore 25
    //   7546: ldc 66
    //   7548: astore 32
    //   7550: aload 21
    //   7552: astore 20
    //   7554: lconst_0
    //   7555: lstore 12
    //   7557: aconst_null
    //   7558: astore 28
    //   7560: aload 25
    //   7562: astore 21
    //   7564: goto +297 -> 7861
    //   7567: astore 30
    //   7569: aload 26
    //   7571: astore 28
    //   7573: ldc 202
    //   7575: astore 29
    //   7577: aload 25
    //   7579: astore 32
    //   7581: aload 22
    //   7583: astore 25
    //   7585: aload 20
    //   7587: astore 26
    //   7589: aload 30
    //   7591: astore 20
    //   7593: aconst_null
    //   7594: astore 30
    //   7596: aconst_null
    //   7597: astore 33
    //   7599: aload 23
    //   7601: astore 22
    //   7603: aload 24
    //   7605: astore 31
    //   7607: aload 33
    //   7609: astore 23
    //   7611: aload 30
    //   7613: astore 24
    //   7615: goto +308 -> 7923
    //   7618: astore 28
    //   7620: aload 25
    //   7622: astore 32
    //   7624: aload 24
    //   7626: astore 31
    //   7628: aload 22
    //   7630: astore 24
    //   7632: aload 20
    //   7634: astore 25
    //   7636: aload 28
    //   7638: astore 20
    //   7640: aconst_null
    //   7641: astore 29
    //   7643: aconst_null
    //   7644: astore 28
    //   7646: aload 23
    //   7648: astore 22
    //   7650: aload 29
    //   7652: astore 23
    //   7654: goto +815 -> 8469
    //   7657: astore 28
    //   7659: aload 25
    //   7661: astore 32
    //   7663: aload 24
    //   7665: astore 31
    //   7667: aload 22
    //   7669: astore 24
    //   7671: aload 20
    //   7673: astore 25
    //   7675: aload 28
    //   7677: astore 20
    //   7679: aconst_null
    //   7680: astore 29
    //   7682: aconst_null
    //   7683: astore 28
    //   7685: aload 23
    //   7687: astore 22
    //   7689: aload 29
    //   7691: astore 23
    //   7693: goto +1375 -> 9068
    //   7696: astore 28
    //   7698: aload 25
    //   7700: astore 32
    //   7702: aload 24
    //   7704: astore 31
    //   7706: aload 22
    //   7708: astore 24
    //   7710: aload 20
    //   7712: astore 25
    //   7714: aload 28
    //   7716: astore 20
    //   7718: aconst_null
    //   7719: astore 29
    //   7721: aconst_null
    //   7722: astore 28
    //   7724: aload 23
    //   7726: astore 22
    //   7728: aload 29
    //   7730: astore 23
    //   7732: goto +1935 -> 9667
    //   7735: astore 28
    //   7737: aload 25
    //   7739: astore 32
    //   7741: aload 24
    //   7743: astore 31
    //   7745: aload 22
    //   7747: astore 24
    //   7749: aload 20
    //   7751: astore 25
    //   7753: aload 28
    //   7755: astore 20
    //   7757: aconst_null
    //   7758: astore 29
    //   7760: aconst_null
    //   7761: astore 28
    //   7763: aload 23
    //   7765: astore 22
    //   7767: aload 29
    //   7769: astore 23
    //   7771: goto +2528 -> 10299
    //   7774: astore 20
    //   7776: goto +55 -> 7831
    //   7779: astore 20
    //   7781: goto +104 -> 7885
    //   7784: astore 20
    //   7786: goto +653 -> 8439
    //   7789: astore 20
    //   7791: goto +1247 -> 9038
    //   7794: astore 20
    //   7796: goto +1841 -> 9637
    //   7799: astore 20
    //   7801: goto +2468 -> 10269
    //   7804: astore 20
    //   7806: goto +25 -> 7831
    //   7809: astore 20
    //   7811: goto +628 -> 8439
    //   7814: astore 20
    //   7816: goto +1222 -> 9038
    //   7819: astore 20
    //   7821: goto +1816 -> 9637
    //   7824: astore 20
    //   7826: goto +2443 -> 10269
    //   7829: astore 20
    //   7831: aload 29
    //   7833: astore 24
    //   7835: aload 30
    //   7837: astore 22
    //   7839: ldc 84
    //   7841: astore 31
    //   7843: ldc 89
    //   7845: astore 21
    //   7847: ldc 66
    //   7849: astore 32
    //   7851: lconst_0
    //   7852: lstore 12
    //   7854: aconst_null
    //   7855: astore 28
    //   7857: aload 28
    //   7859: astore 23
    //   7861: aconst_null
    //   7862: astore 26
    //   7864: iconst_0
    //   7865: istore_2
    //   7866: iconst_0
    //   7867: istore_3
    //   7868: aload 31
    //   7870: astore 29
    //   7872: aload 23
    //   7874: astore 30
    //   7876: aload 24
    //   7878: astore 23
    //   7880: goto +3026 -> 10906
    //   7883: astore 20
    //   7885: ldc 202
    //   7887: astore 33
    //   7889: aload 29
    //   7891: astore 28
    //   7893: aload 30
    //   7895: astore 25
    //   7897: ldc 84
    //   7899: astore 31
    //   7901: ldc 89
    //   7903: astore 22
    //   7905: ldc 66
    //   7907: astore 32
    //   7909: aconst_null
    //   7910: astore 24
    //   7912: aconst_null
    //   7913: astore 23
    //   7915: aload 23
    //   7917: astore 26
    //   7919: aload 33
    //   7921: astore 29
    //   7923: aload 29
    //   7925: astore 36
    //   7927: aload 28
    //   7929: astore 35
    //   7931: aload 26
    //   7933: astore 30
    //   7935: aload 25
    //   7937: astore 34
    //   7939: aload 27
    //   7941: astore 33
    //   7943: aload 24
    //   7945: astore 29
    //   7947: aload 23
    //   7949: astore 28
    //   7951: aload 22
    //   7953: astore 27
    //   7955: aload 21
    //   7957: astore 26
    //   7959: aload 20
    //   7961: astore 22
    //   7963: aload 32
    //   7965: astore 25
    //   7967: aconst_null
    //   7968: astore 21
    //   7970: iconst_0
    //   7971: istore_3
    //   7972: iconst_0
    //   7973: istore_2
    //   7974: aload 36
    //   7976: astore 37
    //   7978: aload 35
    //   7980: astore 23
    //   7982: aload 34
    //   7984: astore 24
    //   7986: aload 29
    //   7988: astore 36
    //   7990: aload 28
    //   7992: astore 20
    //   7994: aload 21
    //   7996: astore 28
    //   7998: aload 27
    //   8000: astore 21
    //   8002: aload 26
    //   8004: astore 35
    //   8006: aload 22
    //   8008: astore 32
    //   8010: ldc 173
    //   8012: invokestatic 115	com/tencent/luggage/wxa/ba/e:b	(Ljava/lang/Class;)Lcom/tencent/luggage/wxa/ba/d;
    //   8015: checkcast 173	com/tencent/luggage/wxa/ot/c
    //   8018: ldc2_w 174
    //   8021: ldc2_w 540
    //   8024: lconst_1
    //   8025: iconst_0
    //   8026: invokeinterface 178 8 0
    //   8031: aload 20
    //   8033: astore 22
    //   8035: ldc 68
    //   8037: aload 32
    //   8039: aload 31
    //   8041: iconst_2
    //   8042: anewarray 4	java/lang/Object
    //   8045: dup
    //   8046: iconst_0
    //   8047: aload 23
    //   8049: aastore
    //   8050: dup
    //   8051: iconst_1
    //   8052: aload 24
    //   8054: aastore
    //   8055: invokestatic 424	com/tencent/luggage/wxa/qz/o:a	(Ljava/lang/String;Ljava/lang/Throwable;Ljava/lang/String;[Ljava/lang/Object;)V
    //   8058: aload_0
    //   8059: getfield 14	com/tencent/luggage/wxa/nz/g$b:a	Lcom/tencent/luggage/wxa/nz/g;
    //   8062: astore 26
    //   8064: new 321	java/lang/StringBuilder
    //   8067: dup
    //   8068: invokespecial 322	java/lang/StringBuilder:<init>	()V
    //   8071: astore 27
    //   8073: aload 27
    //   8075: aload 37
    //   8077: invokevirtual 328	java/lang/StringBuilder:append	(Ljava/lang/String;)Ljava/lang/StringBuilder;
    //   8080: pop
    //   8081: aload 27
    //   8083: aload 32
    //   8085: invokevirtual 544	java/lang/Exception:getMessage	()Ljava/lang/String;
    //   8088: invokevirtual 328	java/lang/StringBuilder:append	(Ljava/lang/String;)Ljava/lang/StringBuilder;
    //   8091: pop
    //   8092: aload 26
    //   8094: aload 35
    //   8096: iconst_m1
    //   8097: aload 27
    //   8099: invokevirtual 332	java/lang/StringBuilder:toString	()Ljava/lang/String;
    //   8102: iload_3
    //   8103: aload_1
    //   8104: invokevirtual 103	com/tencent/luggage/wxa/nz/h:l	()Ljava/lang/String;
    //   8107: aload 36
    //   8109: invokestatic 479	com/tencent/luggage/wxa/nz/g:a	(Lcom/tencent/luggage/wxa/nz/g;Lcom/tencent/luggage/wxa/nz/g$a;ILjava/lang/String;ILjava/lang/String;Ljava/net/HttpURLConnection;)V
    //   8112: ldc 110
    //   8114: invokestatic 115	com/tencent/luggage/wxa/ba/e:b	(Ljava/lang/Class;)Lcom/tencent/luggage/wxa/ba/d;
    //   8117: checkcast 110	com/tencent/luggage/wxa/nz/o
    //   8120: aload_0
    //   8121: getfield 14	com/tencent/luggage/wxa/nz/g$b:a	Lcom/tencent/luggage/wxa/nz/g;
    //   8124: invokestatic 118	com/tencent/luggage/wxa/nz/g:a	(Lcom/tencent/luggage/wxa/nz/g;)Lcom/tencent/luggage/wxa/jx/c;
    //   8127: invokeinterface 123 1 0
    //   8132: aload_1
    //   8133: invokevirtual 126	com/tencent/luggage/wxa/nz/h:n	()Ljava/lang/String;
    //   8136: ldc 128
    //   8138: aload_1
    //   8139: invokevirtual 49	com/tencent/luggage/wxa/nz/h:b	()Ljava/lang/String;
    //   8142: lload 12
    //   8144: iload_2
    //   8145: i2l
    //   8146: iload_3
    //   8147: iconst_2
    //   8148: aload_1
    //   8149: invokevirtual 132	com/tencent/luggage/wxa/nz/h:o	()I
    //   8152: aconst_null
    //   8153: aload 33
    //   8155: invokeinterface 135 14 0
    //   8160: invokestatic 406	com/tencent/luggage/wxa/qz/r:a	()Landroid/content/Context;
    //   8163: invokestatic 411	com/tencent/luggage/wxa/qz/x:d	(Landroid/content/Context;)I
    //   8166: istore_2
    //   8167: iload_2
    //   8168: iconst_m1
    //   8169: if_icmpne +24 -> 8193
    //   8172: ldc 173
    //   8174: invokestatic 115	com/tencent/luggage/wxa/ba/e:b	(Ljava/lang/Class;)Lcom/tencent/luggage/wxa/ba/d;
    //   8177: checkcast 173	com/tencent/luggage/wxa/ot/c
    //   8180: ldc2_w 174
    //   8183: ldc2_w 412
    //   8186: lconst_1
    //   8187: iconst_0
    //   8188: invokeinterface 178 8 0
    //   8193: ldc 68
    //   8195: aload 21
    //   8197: iconst_1
    //   8198: anewarray 4	java/lang/Object
    //   8201: dup
    //   8202: iconst_0
    //   8203: iload_2
    //   8204: invokestatic 418	java/lang/Integer:valueOf	(I)Ljava/lang/Integer;
    //   8207: aastore
    //   8208: invokestatic 139	com/tencent/luggage/wxa/qz/o:d	(Ljava/lang/String;Ljava/lang/String;[Ljava/lang/Object;)V
    //   8211: aload_1
    //   8212: iconst_0
    //   8213: putfield 142	com/tencent/luggage/wxa/nz/h:a	Z
    //   8216: aload 30
    //   8218: ifnull +36 -> 8254
    //   8221: aload 30
    //   8223: invokevirtual 421	java/io/InputStream:close	()V
    //   8226: goto +28 -> 8254
    //   8229: astore 20
    //   8231: ldc 68
    //   8233: aload 20
    //   8235: aload 31
    //   8237: iconst_2
    //   8238: anewarray 4	java/lang/Object
    //   8241: dup
    //   8242: iconst_0
    //   8243: aload 23
    //   8245: aastore
    //   8246: dup
    //   8247: iconst_1
    //   8248: aload 24
    //   8250: aastore
    //   8251: invokestatic 424	com/tencent/luggage/wxa/qz/o:a	(Ljava/lang/String;Ljava/lang/Throwable;Ljava/lang/String;[Ljava/lang/Object;)V
    //   8254: aload 28
    //   8256: ifnull +97 -> 8353
    //   8259: aload 28
    //   8261: invokevirtual 421	java/io/InputStream:close	()V
    //   8264: goto +89 -> 8353
    //   8267: astore 20
    //   8269: ldc 68
    //   8271: aload 20
    //   8273: ldc_w 537
    //   8276: iconst_2
    //   8277: anewarray 4	java/lang/Object
    //   8280: dup
    //   8281: iconst_0
    //   8282: aload 23
    //   8284: aastore
    //   8285: dup
    //   8286: iconst_1
    //   8287: aload 24
    //   8289: aastore
    //   8290: invokestatic 424	com/tencent/luggage/wxa/qz/o:a	(Ljava/lang/String;Ljava/lang/Throwable;Ljava/lang/String;[Ljava/lang/Object;)V
    //   8293: goto +60 -> 8353
    //   8296: astore 20
    //   8298: ldc 68
    //   8300: aload 20
    //   8302: ldc_w 539
    //   8305: iconst_2
    //   8306: anewarray 4	java/lang/Object
    //   8309: dup
    //   8310: iconst_0
    //   8311: aload 23
    //   8313: aastore
    //   8314: dup
    //   8315: iconst_1
    //   8316: aload 24
    //   8318: aastore
    //   8319: invokestatic 424	com/tencent/luggage/wxa/qz/o:a	(Ljava/lang/String;Ljava/lang/Throwable;Ljava/lang/String;[Ljava/lang/Object;)V
    //   8322: goto +31 -> 8353
    //   8325: astore 20
    //   8327: ldc 68
    //   8329: aload 20
    //   8331: aload 25
    //   8333: iconst_2
    //   8334: anewarray 4	java/lang/Object
    //   8337: dup
    //   8338: iconst_0
    //   8339: aload 23
    //   8341: aastore
    //   8342: dup
    //   8343: iconst_1
    //   8344: aload 24
    //   8346: aastore
    //   8347: invokestatic 424	com/tencent/luggage/wxa/qz/o:a	(Ljava/lang/String;Ljava/lang/Throwable;Ljava/lang/String;[Ljava/lang/Object;)V
    //   8350: goto +3 -> 8353
    //   8353: aload 22
    //   8355: ifnull +2410 -> 10765
    //   8358: aload 22
    //   8360: invokevirtual 425	java/io/DataOutputStream:close	()V
    //   8363: goto +2402 -> 10765
    //   8366: astore 20
    //   8368: ldc 68
    //   8370: aload 20
    //   8372: aload 25
    //   8374: iconst_2
    //   8375: anewarray 4	java/lang/Object
    //   8378: dup
    //   8379: iconst_0
    //   8380: aload 23
    //   8382: aastore
    //   8383: dup
    //   8384: iconst_1
    //   8385: aload 24
    //   8387: aastore
    //   8388: invokestatic 424	com/tencent/luggage/wxa/qz/o:a	(Ljava/lang/String;Ljava/lang/Throwable;Ljava/lang/String;[Ljava/lang/Object;)V
    //   8391: goto +2374 -> 10765
    //   8394: astore 22
    //   8396: goto +10 -> 8406
    //   8399: astore 22
    //   8401: goto +5 -> 8406
    //   8404: astore 22
    //   8406: aload 28
    //   8408: astore 26
    //   8410: aload 20
    //   8412: astore 28
    //   8414: aload 22
    //   8416: astore 20
    //   8418: aload 25
    //   8420: astore 32
    //   8422: aload 31
    //   8424: astore 29
    //   8426: aload 33
    //   8428: astore 27
    //   8430: aload 24
    //   8432: astore 22
    //   8434: goto +2472 -> 10906
    //   8437: astore 20
    //   8439: aload 29
    //   8441: astore 26
    //   8443: aload 30
    //   8445: astore 24
    //   8447: ldc 84
    //   8449: astore 31
    //   8451: ldc 89
    //   8453: astore 22
    //   8455: ldc 66
    //   8457: astore 32
    //   8459: aconst_null
    //   8460: astore 23
    //   8462: aconst_null
    //   8463: astore 28
    //   8465: aload 28
    //   8467: astore 25
    //   8469: aconst_null
    //   8470: astore 29
    //   8472: iconst_0
    //   8473: istore_3
    //   8474: aload 26
    //   8476: astore 34
    //   8478: aload 25
    //   8480: astore 36
    //   8482: aload 24
    //   8484: astore 26
    //   8486: aload 27
    //   8488: astore 35
    //   8490: aload 31
    //   8492: astore 24
    //   8494: aload 22
    //   8496: astore 33
    //   8498: aload 29
    //   8500: astore 31
    //   8502: aload 32
    //   8504: astore 25
    //   8506: iconst_0
    //   8507: istore 5
    //   8509: aload 26
    //   8511: astore 29
    //   8513: lload 12
    //   8515: lstore 14
    //   8517: aload 23
    //   8519: astore 40
    //   8521: aload 24
    //   8523: astore 32
    //   8525: aload 28
    //   8527: astore 37
    //   8529: aload 21
    //   8531: astore 39
    //   8533: iload_3
    //   8534: istore 4
    //   8536: aload 25
    //   8538: astore 30
    //   8540: aload 20
    //   8542: astore 38
    //   8544: aload 30
    //   8546: astore 20
    //   8548: iload 4
    //   8550: istore_2
    //   8551: aload 31
    //   8553: astore 21
    //   8555: aload 33
    //   8557: astore 22
    //   8559: aload 37
    //   8561: astore 23
    //   8563: aload 32
    //   8565: astore 24
    //   8567: iload 5
    //   8569: istore_3
    //   8570: lload 14
    //   8572: lstore 12
    //   8574: aload 35
    //   8576: astore 25
    //   8578: aload 29
    //   8580: astore 26
    //   8582: aload 36
    //   8584: astore 27
    //   8586: aload 34
    //   8588: astore 28
    //   8590: ldc 173
    //   8592: invokestatic 115	com/tencent/luggage/wxa/ba/e:b	(Ljava/lang/Class;)Lcom/tencent/luggage/wxa/ba/d;
    //   8595: checkcast 173	com/tencent/luggage/wxa/ot/c
    //   8598: ldc2_w 174
    //   8601: ldc2_w 545
    //   8604: lconst_1
    //   8605: iconst_0
    //   8606: invokeinterface 178 8 0
    //   8611: aload 30
    //   8613: astore 41
    //   8615: iload 4
    //   8617: istore_3
    //   8618: aload 31
    //   8620: astore 28
    //   8622: aload 33
    //   8624: astore 27
    //   8626: aload 32
    //   8628: astore 24
    //   8630: iload 5
    //   8632: istore_2
    //   8633: lload 14
    //   8635: lstore 12
    //   8637: aload 35
    //   8639: astore 21
    //   8641: aload 37
    //   8643: astore 25
    //   8645: aload 29
    //   8647: astore 26
    //   8649: aload 36
    //   8651: astore 22
    //   8653: aload 41
    //   8655: astore 20
    //   8657: aload 34
    //   8659: astore 23
    //   8661: ldc 68
    //   8663: aload 38
    //   8665: ldc_w 548
    //   8668: iconst_2
    //   8669: anewarray 4	java/lang/Object
    //   8672: dup
    //   8673: iconst_0
    //   8674: aload 34
    //   8676: aastore
    //   8677: dup
    //   8678: iconst_1
    //   8679: aload 29
    //   8681: aastore
    //   8682: invokestatic 424	com/tencent/luggage/wxa/qz/o:a	(Ljava/lang/String;Ljava/lang/Throwable;Ljava/lang/String;[Ljava/lang/Object;)V
    //   8685: iload 4
    //   8687: istore_3
    //   8688: aload 31
    //   8690: astore 28
    //   8692: aload 33
    //   8694: astore 27
    //   8696: aload 32
    //   8698: astore 24
    //   8700: iload 5
    //   8702: istore_2
    //   8703: lload 14
    //   8705: lstore 12
    //   8707: aload 35
    //   8709: astore 21
    //   8711: aload 37
    //   8713: astore 25
    //   8715: aload 29
    //   8717: astore 26
    //   8719: aload 36
    //   8721: astore 22
    //   8723: aload 41
    //   8725: astore 20
    //   8727: aload 34
    //   8729: astore 23
    //   8731: aload_0
    //   8732: getfield 14	com/tencent/luggage/wxa/nz/g$b:a	Lcom/tencent/luggage/wxa/nz/g;
    //   8735: aload 39
    //   8737: iconst_m1
    //   8738: ldc_w 550
    //   8741: iload 4
    //   8743: aload_1
    //   8744: invokevirtual 103	com/tencent/luggage/wxa/nz/h:l	()Ljava/lang/String;
    //   8747: aload 40
    //   8749: invokestatic 479	com/tencent/luggage/wxa/nz/g:a	(Lcom/tencent/luggage/wxa/nz/g;Lcom/tencent/luggage/wxa/nz/g$a;ILjava/lang/String;ILjava/lang/String;Ljava/net/HttpURLConnection;)V
    //   8752: ldc 110
    //   8754: invokestatic 115	com/tencent/luggage/wxa/ba/e:b	(Ljava/lang/Class;)Lcom/tencent/luggage/wxa/ba/d;
    //   8757: checkcast 110	com/tencent/luggage/wxa/nz/o
    //   8760: aload_0
    //   8761: getfield 14	com/tencent/luggage/wxa/nz/g$b:a	Lcom/tencent/luggage/wxa/nz/g;
    //   8764: invokestatic 118	com/tencent/luggage/wxa/nz/g:a	(Lcom/tencent/luggage/wxa/nz/g;)Lcom/tencent/luggage/wxa/jx/c;
    //   8767: invokeinterface 123 1 0
    //   8772: aload_1
    //   8773: invokevirtual 126	com/tencent/luggage/wxa/nz/h:n	()Ljava/lang/String;
    //   8776: ldc 128
    //   8778: aload_1
    //   8779: invokevirtual 49	com/tencent/luggage/wxa/nz/h:b	()Ljava/lang/String;
    //   8782: lload 14
    //   8784: iload 5
    //   8786: i2l
    //   8787: iload 4
    //   8789: iconst_2
    //   8790: aload_1
    //   8791: invokevirtual 132	com/tencent/luggage/wxa/nz/h:o	()I
    //   8794: aconst_null
    //   8795: aload 35
    //   8797: invokeinterface 135 14 0
    //   8802: invokestatic 406	com/tencent/luggage/wxa/qz/r:a	()Landroid/content/Context;
    //   8805: invokestatic 411	com/tencent/luggage/wxa/qz/x:d	(Landroid/content/Context;)I
    //   8808: istore_2
    //   8809: iload_2
    //   8810: iconst_m1
    //   8811: if_icmpne +24 -> 8835
    //   8814: ldc 173
    //   8816: invokestatic 115	com/tencent/luggage/wxa/ba/e:b	(Ljava/lang/Class;)Lcom/tencent/luggage/wxa/ba/d;
    //   8819: checkcast 173	com/tencent/luggage/wxa/ot/c
    //   8822: ldc2_w 174
    //   8825: ldc2_w 412
    //   8828: lconst_1
    //   8829: iconst_0
    //   8830: invokeinterface 178 8 0
    //   8835: ldc 68
    //   8837: aload 33
    //   8839: iconst_1
    //   8840: anewarray 4	java/lang/Object
    //   8843: dup
    //   8844: iconst_0
    //   8845: iload_2
    //   8846: invokestatic 418	java/lang/Integer:valueOf	(I)Ljava/lang/Integer;
    //   8849: aastore
    //   8850: invokestatic 139	com/tencent/luggage/wxa/qz/o:d	(Ljava/lang/String;Ljava/lang/String;[Ljava/lang/Object;)V
    //   8853: aload_1
    //   8854: iconst_0
    //   8855: putfield 142	com/tencent/luggage/wxa/nz/h:a	Z
    //   8858: aload 36
    //   8860: ifnull +36 -> 8896
    //   8863: aload 36
    //   8865: invokevirtual 421	java/io/InputStream:close	()V
    //   8868: goto +28 -> 8896
    //   8871: astore 20
    //   8873: ldc 68
    //   8875: aload 20
    //   8877: aload 32
    //   8879: iconst_2
    //   8880: anewarray 4	java/lang/Object
    //   8883: dup
    //   8884: iconst_0
    //   8885: aload 34
    //   8887: aastore
    //   8888: dup
    //   8889: iconst_1
    //   8890: aload 29
    //   8892: aastore
    //   8893: invokestatic 424	com/tencent/luggage/wxa/qz/o:a	(Ljava/lang/String;Ljava/lang/Throwable;Ljava/lang/String;[Ljava/lang/Object;)V
    //   8896: aload 31
    //   8898: ifnull +97 -> 8995
    //   8901: aload 31
    //   8903: invokevirtual 421	java/io/InputStream:close	()V
    //   8906: goto +89 -> 8995
    //   8909: astore 20
    //   8911: ldc 68
    //   8913: aload 20
    //   8915: ldc_w 537
    //   8918: iconst_2
    //   8919: anewarray 4	java/lang/Object
    //   8922: dup
    //   8923: iconst_0
    //   8924: aload 34
    //   8926: aastore
    //   8927: dup
    //   8928: iconst_1
    //   8929: aload 29
    //   8931: aastore
    //   8932: invokestatic 424	com/tencent/luggage/wxa/qz/o:a	(Ljava/lang/String;Ljava/lang/Throwable;Ljava/lang/String;[Ljava/lang/Object;)V
    //   8935: goto +60 -> 8995
    //   8938: astore 20
    //   8940: ldc 68
    //   8942: aload 20
    //   8944: ldc_w 539
    //   8947: iconst_2
    //   8948: anewarray 4	java/lang/Object
    //   8951: dup
    //   8952: iconst_0
    //   8953: aload 34
    //   8955: aastore
    //   8956: dup
    //   8957: iconst_1
    //   8958: aload 29
    //   8960: aastore
    //   8961: invokestatic 424	com/tencent/luggage/wxa/qz/o:a	(Ljava/lang/String;Ljava/lang/Throwable;Ljava/lang/String;[Ljava/lang/Object;)V
    //   8964: goto +31 -> 8995
    //   8967: astore 20
    //   8969: ldc 68
    //   8971: aload 20
    //   8973: aload 41
    //   8975: iconst_2
    //   8976: anewarray 4	java/lang/Object
    //   8979: dup
    //   8980: iconst_0
    //   8981: aload 34
    //   8983: aastore
    //   8984: dup
    //   8985: iconst_1
    //   8986: aload 29
    //   8988: aastore
    //   8989: invokestatic 424	com/tencent/luggage/wxa/qz/o:a	(Ljava/lang/String;Ljava/lang/Throwable;Ljava/lang/String;[Ljava/lang/Object;)V
    //   8992: goto +3 -> 8995
    //   8995: aload 37
    //   8997: ifnull +1768 -> 10765
    //   9000: aload 37
    //   9002: invokevirtual 425	java/io/DataOutputStream:close	()V
    //   9005: goto +1760 -> 10765
    //   9008: astore 20
    //   9010: ldc 68
    //   9012: aload 20
    //   9014: aload 30
    //   9016: iconst_2
    //   9017: anewarray 4	java/lang/Object
    //   9020: dup
    //   9021: iconst_0
    //   9022: aload 34
    //   9024: aastore
    //   9025: dup
    //   9026: iconst_1
    //   9027: aload 29
    //   9029: aastore
    //   9030: invokestatic 424	com/tencent/luggage/wxa/qz/o:a	(Ljava/lang/String;Ljava/lang/Throwable;Ljava/lang/String;[Ljava/lang/Object;)V
    //   9033: goto +1732 -> 10765
    //   9036: astore 20
    //   9038: aload 29
    //   9040: astore 26
    //   9042: aload 30
    //   9044: astore 24
    //   9046: ldc 84
    //   9048: astore 31
    //   9050: ldc 89
    //   9052: astore 22
    //   9054: ldc 66
    //   9056: astore 32
    //   9058: aconst_null
    //   9059: astore 23
    //   9061: aconst_null
    //   9062: astore 28
    //   9064: aload 28
    //   9066: astore 25
    //   9068: aconst_null
    //   9069: astore 29
    //   9071: iconst_0
    //   9072: istore_3
    //   9073: aload 26
    //   9075: astore 34
    //   9077: aload 25
    //   9079: astore 36
    //   9081: aload 24
    //   9083: astore 26
    //   9085: aload 27
    //   9087: astore 35
    //   9089: aload 31
    //   9091: astore 24
    //   9093: aload 22
    //   9095: astore 33
    //   9097: aload 29
    //   9099: astore 31
    //   9101: aload 32
    //   9103: astore 25
    //   9105: iconst_0
    //   9106: istore 5
    //   9108: aload 26
    //   9110: astore 29
    //   9112: lload 12
    //   9114: lstore 14
    //   9116: aload 23
    //   9118: astore 40
    //   9120: aload 24
    //   9122: astore 32
    //   9124: aload 28
    //   9126: astore 37
    //   9128: aload 21
    //   9130: astore 39
    //   9132: iload_3
    //   9133: istore 4
    //   9135: aload 25
    //   9137: astore 30
    //   9139: aload 20
    //   9141: astore 38
    //   9143: aload 30
    //   9145: astore 20
    //   9147: iload 4
    //   9149: istore_2
    //   9150: aload 31
    //   9152: astore 21
    //   9154: aload 33
    //   9156: astore 22
    //   9158: aload 37
    //   9160: astore 23
    //   9162: aload 32
    //   9164: astore 24
    //   9166: iload 5
    //   9168: istore_3
    //   9169: lload 14
    //   9171: lstore 12
    //   9173: aload 35
    //   9175: astore 25
    //   9177: aload 29
    //   9179: astore 26
    //   9181: aload 36
    //   9183: astore 27
    //   9185: aload 34
    //   9187: astore 28
    //   9189: ldc 173
    //   9191: invokestatic 115	com/tencent/luggage/wxa/ba/e:b	(Ljava/lang/Class;)Lcom/tencent/luggage/wxa/ba/d;
    //   9194: checkcast 173	com/tencent/luggage/wxa/ot/c
    //   9197: ldc2_w 174
    //   9200: ldc2_w 551
    //   9203: lconst_1
    //   9204: iconst_0
    //   9205: invokeinterface 178 8 0
    //   9210: aload 30
    //   9212: astore 41
    //   9214: iload 4
    //   9216: istore_3
    //   9217: aload 31
    //   9219: astore 28
    //   9221: aload 33
    //   9223: astore 27
    //   9225: aload 32
    //   9227: astore 24
    //   9229: iload 5
    //   9231: istore_2
    //   9232: lload 14
    //   9234: lstore 12
    //   9236: aload 35
    //   9238: astore 21
    //   9240: aload 37
    //   9242: astore 25
    //   9244: aload 29
    //   9246: astore 26
    //   9248: aload 36
    //   9250: astore 22
    //   9252: aload 41
    //   9254: astore 20
    //   9256: aload 34
    //   9258: astore 23
    //   9260: ldc 68
    //   9262: aload 38
    //   9264: ldc_w 554
    //   9267: iconst_2
    //   9268: anewarray 4	java/lang/Object
    //   9271: dup
    //   9272: iconst_0
    //   9273: aload 34
    //   9275: aastore
    //   9276: dup
    //   9277: iconst_1
    //   9278: aload 29
    //   9280: aastore
    //   9281: invokestatic 424	com/tencent/luggage/wxa/qz/o:a	(Ljava/lang/String;Ljava/lang/Throwable;Ljava/lang/String;[Ljava/lang/Object;)V
    //   9284: iload 4
    //   9286: istore_3
    //   9287: aload 31
    //   9289: astore 28
    //   9291: aload 33
    //   9293: astore 27
    //   9295: aload 32
    //   9297: astore 24
    //   9299: iload 5
    //   9301: istore_2
    //   9302: lload 14
    //   9304: lstore 12
    //   9306: aload 35
    //   9308: astore 21
    //   9310: aload 37
    //   9312: astore 25
    //   9314: aload 29
    //   9316: astore 26
    //   9318: aload 36
    //   9320: astore 22
    //   9322: aload 41
    //   9324: astore 20
    //   9326: aload 34
    //   9328: astore 23
    //   9330: aload_0
    //   9331: getfield 14	com/tencent/luggage/wxa/nz/g$b:a	Lcom/tencent/luggage/wxa/nz/g;
    //   9334: aload 39
    //   9336: iconst_m1
    //   9337: ldc_w 556
    //   9340: iload 4
    //   9342: aload_1
    //   9343: invokevirtual 103	com/tencent/luggage/wxa/nz/h:l	()Ljava/lang/String;
    //   9346: aload 40
    //   9348: invokestatic 479	com/tencent/luggage/wxa/nz/g:a	(Lcom/tencent/luggage/wxa/nz/g;Lcom/tencent/luggage/wxa/nz/g$a;ILjava/lang/String;ILjava/lang/String;Ljava/net/HttpURLConnection;)V
    //   9351: ldc 110
    //   9353: invokestatic 115	com/tencent/luggage/wxa/ba/e:b	(Ljava/lang/Class;)Lcom/tencent/luggage/wxa/ba/d;
    //   9356: checkcast 110	com/tencent/luggage/wxa/nz/o
    //   9359: aload_0
    //   9360: getfield 14	com/tencent/luggage/wxa/nz/g$b:a	Lcom/tencent/luggage/wxa/nz/g;
    //   9363: invokestatic 118	com/tencent/luggage/wxa/nz/g:a	(Lcom/tencent/luggage/wxa/nz/g;)Lcom/tencent/luggage/wxa/jx/c;
    //   9366: invokeinterface 123 1 0
    //   9371: aload_1
    //   9372: invokevirtual 126	com/tencent/luggage/wxa/nz/h:n	()Ljava/lang/String;
    //   9375: ldc 128
    //   9377: aload_1
    //   9378: invokevirtual 49	com/tencent/luggage/wxa/nz/h:b	()Ljava/lang/String;
    //   9381: lload 14
    //   9383: iload 5
    //   9385: i2l
    //   9386: iload 4
    //   9388: iconst_2
    //   9389: aload_1
    //   9390: invokevirtual 132	com/tencent/luggage/wxa/nz/h:o	()I
    //   9393: aconst_null
    //   9394: aload 35
    //   9396: invokeinterface 135 14 0
    //   9401: invokestatic 406	com/tencent/luggage/wxa/qz/r:a	()Landroid/content/Context;
    //   9404: invokestatic 411	com/tencent/luggage/wxa/qz/x:d	(Landroid/content/Context;)I
    //   9407: istore_2
    //   9408: iload_2
    //   9409: iconst_m1
    //   9410: if_icmpne +24 -> 9434
    //   9413: ldc 173
    //   9415: invokestatic 115	com/tencent/luggage/wxa/ba/e:b	(Ljava/lang/Class;)Lcom/tencent/luggage/wxa/ba/d;
    //   9418: checkcast 173	com/tencent/luggage/wxa/ot/c
    //   9421: ldc2_w 174
    //   9424: ldc2_w 412
    //   9427: lconst_1
    //   9428: iconst_0
    //   9429: invokeinterface 178 8 0
    //   9434: ldc 68
    //   9436: aload 33
    //   9438: iconst_1
    //   9439: anewarray 4	java/lang/Object
    //   9442: dup
    //   9443: iconst_0
    //   9444: iload_2
    //   9445: invokestatic 418	java/lang/Integer:valueOf	(I)Ljava/lang/Integer;
    //   9448: aastore
    //   9449: invokestatic 139	com/tencent/luggage/wxa/qz/o:d	(Ljava/lang/String;Ljava/lang/String;[Ljava/lang/Object;)V
    //   9452: aload_1
    //   9453: iconst_0
    //   9454: putfield 142	com/tencent/luggage/wxa/nz/h:a	Z
    //   9457: aload 36
    //   9459: ifnull +36 -> 9495
    //   9462: aload 36
    //   9464: invokevirtual 421	java/io/InputStream:close	()V
    //   9467: goto +28 -> 9495
    //   9470: astore 20
    //   9472: ldc 68
    //   9474: aload 20
    //   9476: aload 32
    //   9478: iconst_2
    //   9479: anewarray 4	java/lang/Object
    //   9482: dup
    //   9483: iconst_0
    //   9484: aload 34
    //   9486: aastore
    //   9487: dup
    //   9488: iconst_1
    //   9489: aload 29
    //   9491: aastore
    //   9492: invokestatic 424	com/tencent/luggage/wxa/qz/o:a	(Ljava/lang/String;Ljava/lang/Throwable;Ljava/lang/String;[Ljava/lang/Object;)V
    //   9495: aload 31
    //   9497: ifnull +97 -> 9594
    //   9500: aload 31
    //   9502: invokevirtual 421	java/io/InputStream:close	()V
    //   9505: goto +89 -> 9594
    //   9508: astore 20
    //   9510: ldc 68
    //   9512: aload 20
    //   9514: ldc_w 537
    //   9517: iconst_2
    //   9518: anewarray 4	java/lang/Object
    //   9521: dup
    //   9522: iconst_0
    //   9523: aload 34
    //   9525: aastore
    //   9526: dup
    //   9527: iconst_1
    //   9528: aload 29
    //   9530: aastore
    //   9531: invokestatic 424	com/tencent/luggage/wxa/qz/o:a	(Ljava/lang/String;Ljava/lang/Throwable;Ljava/lang/String;[Ljava/lang/Object;)V
    //   9534: goto +60 -> 9594
    //   9537: astore 20
    //   9539: ldc 68
    //   9541: aload 20
    //   9543: ldc_w 539
    //   9546: iconst_2
    //   9547: anewarray 4	java/lang/Object
    //   9550: dup
    //   9551: iconst_0
    //   9552: aload 34
    //   9554: aastore
    //   9555: dup
    //   9556: iconst_1
    //   9557: aload 29
    //   9559: aastore
    //   9560: invokestatic 424	com/tencent/luggage/wxa/qz/o:a	(Ljava/lang/String;Ljava/lang/Throwable;Ljava/lang/String;[Ljava/lang/Object;)V
    //   9563: goto +31 -> 9594
    //   9566: astore 20
    //   9568: ldc 68
    //   9570: aload 20
    //   9572: aload 41
    //   9574: iconst_2
    //   9575: anewarray 4	java/lang/Object
    //   9578: dup
    //   9579: iconst_0
    //   9580: aload 34
    //   9582: aastore
    //   9583: dup
    //   9584: iconst_1
    //   9585: aload 29
    //   9587: aastore
    //   9588: invokestatic 424	com/tencent/luggage/wxa/qz/o:a	(Ljava/lang/String;Ljava/lang/Throwable;Ljava/lang/String;[Ljava/lang/Object;)V
    //   9591: goto +3 -> 9594
    //   9594: aload 37
    //   9596: ifnull +1169 -> 10765
    //   9599: aload 37
    //   9601: invokevirtual 425	java/io/DataOutputStream:close	()V
    //   9604: goto +1161 -> 10765
    //   9607: astore 20
    //   9609: ldc 68
    //   9611: aload 20
    //   9613: aload 30
    //   9615: iconst_2
    //   9616: anewarray 4	java/lang/Object
    //   9619: dup
    //   9620: iconst_0
    //   9621: aload 34
    //   9623: aastore
    //   9624: dup
    //   9625: iconst_1
    //   9626: aload 29
    //   9628: aastore
    //   9629: invokestatic 424	com/tencent/luggage/wxa/qz/o:a	(Ljava/lang/String;Ljava/lang/Throwable;Ljava/lang/String;[Ljava/lang/Object;)V
    //   9632: goto +1133 -> 10765
    //   9635: astore 20
    //   9637: aload 29
    //   9639: astore 26
    //   9641: aload 30
    //   9643: astore 24
    //   9645: ldc 84
    //   9647: astore 31
    //   9649: ldc 89
    //   9651: astore 22
    //   9653: ldc 66
    //   9655: astore 32
    //   9657: aconst_null
    //   9658: astore 23
    //   9660: aconst_null
    //   9661: astore 28
    //   9663: aload 28
    //   9665: astore 25
    //   9667: aconst_null
    //   9668: astore 29
    //   9670: iconst_0
    //   9671: istore_3
    //   9672: aload 26
    //   9674: astore 34
    //   9676: aload 25
    //   9678: astore 36
    //   9680: aload 24
    //   9682: astore 26
    //   9684: aload 27
    //   9686: astore 35
    //   9688: aload 31
    //   9690: astore 24
    //   9692: aload 22
    //   9694: astore 33
    //   9696: aload 29
    //   9698: astore 31
    //   9700: aload 32
    //   9702: astore 25
    //   9704: iconst_0
    //   9705: istore 5
    //   9707: aload 26
    //   9709: astore 29
    //   9711: lload 12
    //   9713: lstore 14
    //   9715: aload 23
    //   9717: astore 40
    //   9719: aload 24
    //   9721: astore 32
    //   9723: aload 28
    //   9725: astore 37
    //   9727: aload 21
    //   9729: astore 39
    //   9731: iload_3
    //   9732: istore 4
    //   9734: aload 25
    //   9736: astore 30
    //   9738: aload 20
    //   9740: astore 38
    //   9742: aload 30
    //   9744: astore 20
    //   9746: iload 4
    //   9748: istore_2
    //   9749: aload 31
    //   9751: astore 21
    //   9753: aload 33
    //   9755: astore 22
    //   9757: aload 37
    //   9759: astore 23
    //   9761: aload 32
    //   9763: astore 24
    //   9765: iload 5
    //   9767: istore_3
    //   9768: lload 14
    //   9770: lstore 12
    //   9772: aload 35
    //   9774: astore 25
    //   9776: aload 29
    //   9778: astore 26
    //   9780: aload 36
    //   9782: astore 27
    //   9784: aload 34
    //   9786: astore 28
    //   9788: ldc 173
    //   9790: invokestatic 115	com/tencent/luggage/wxa/ba/e:b	(Ljava/lang/Class;)Lcom/tencent/luggage/wxa/ba/d;
    //   9793: checkcast 173	com/tencent/luggage/wxa/ot/c
    //   9796: ldc2_w 174
    //   9799: ldc2_w 557
    //   9802: lconst_1
    //   9803: iconst_0
    //   9804: invokeinterface 178 8 0
    //   9809: aload 30
    //   9811: astore 41
    //   9813: iload 4
    //   9815: istore_3
    //   9816: aload 31
    //   9818: astore 28
    //   9820: aload 33
    //   9822: astore 27
    //   9824: aload 32
    //   9826: astore 24
    //   9828: iload 5
    //   9830: istore_2
    //   9831: lload 14
    //   9833: lstore 12
    //   9835: aload 35
    //   9837: astore 21
    //   9839: aload 37
    //   9841: astore 25
    //   9843: aload 29
    //   9845: astore 26
    //   9847: aload 36
    //   9849: astore 22
    //   9851: aload 41
    //   9853: astore 20
    //   9855: aload 34
    //   9857: astore 23
    //   9859: ldc 68
    //   9861: aload 38
    //   9863: ldc_w 560
    //   9866: iconst_2
    //   9867: anewarray 4	java/lang/Object
    //   9870: dup
    //   9871: iconst_0
    //   9872: aload 34
    //   9874: aastore
    //   9875: dup
    //   9876: iconst_1
    //   9877: aload 29
    //   9879: aastore
    //   9880: invokestatic 424	com/tencent/luggage/wxa/qz/o:a	(Ljava/lang/String;Ljava/lang/Throwable;Ljava/lang/String;[Ljava/lang/Object;)V
    //   9883: iload 4
    //   9885: istore_3
    //   9886: aload 31
    //   9888: astore 28
    //   9890: aload 33
    //   9892: astore 27
    //   9894: aload 32
    //   9896: astore 24
    //   9898: iload 5
    //   9900: istore_2
    //   9901: lload 14
    //   9903: lstore 12
    //   9905: aload 35
    //   9907: astore 21
    //   9909: aload 37
    //   9911: astore 25
    //   9913: aload 29
    //   9915: astore 26
    //   9917: aload 36
    //   9919: astore 22
    //   9921: aload 41
    //   9923: astore 20
    //   9925: aload 34
    //   9927: astore 23
    //   9929: aload_0
    //   9930: getfield 14	com/tencent/luggage/wxa/nz/g$b:a	Lcom/tencent/luggage/wxa/nz/g;
    //   9933: aload 39
    //   9935: iconst_m1
    //   9936: ldc_w 562
    //   9939: iload 4
    //   9941: aload_1
    //   9942: invokevirtual 103	com/tencent/luggage/wxa/nz/h:l	()Ljava/lang/String;
    //   9945: aload 40
    //   9947: invokestatic 479	com/tencent/luggage/wxa/nz/g:a	(Lcom/tencent/luggage/wxa/nz/g;Lcom/tencent/luggage/wxa/nz/g$a;ILjava/lang/String;ILjava/lang/String;Ljava/net/HttpURLConnection;)V
    //   9950: ldc 110
    //   9952: invokestatic 115	com/tencent/luggage/wxa/ba/e:b	(Ljava/lang/Class;)Lcom/tencent/luggage/wxa/ba/d;
    //   9955: checkcast 110	com/tencent/luggage/wxa/nz/o
    //   9958: aload_0
    //   9959: getfield 14	com/tencent/luggage/wxa/nz/g$b:a	Lcom/tencent/luggage/wxa/nz/g;
    //   9962: invokestatic 118	com/tencent/luggage/wxa/nz/g:a	(Lcom/tencent/luggage/wxa/nz/g;)Lcom/tencent/luggage/wxa/jx/c;
    //   9965: invokeinterface 123 1 0
    //   9970: aload_1
    //   9971: invokevirtual 126	com/tencent/luggage/wxa/nz/h:n	()Ljava/lang/String;
    //   9974: ldc 128
    //   9976: aload_1
    //   9977: invokevirtual 49	com/tencent/luggage/wxa/nz/h:b	()Ljava/lang/String;
    //   9980: lload 14
    //   9982: iload 5
    //   9984: i2l
    //   9985: iload 4
    //   9987: iconst_2
    //   9988: aload_1
    //   9989: invokevirtual 132	com/tencent/luggage/wxa/nz/h:o	()I
    //   9992: aconst_null
    //   9993: aload 35
    //   9995: invokeinterface 135 14 0
    //   10000: invokestatic 406	com/tencent/luggage/wxa/qz/r:a	()Landroid/content/Context;
    //   10003: invokestatic 411	com/tencent/luggage/wxa/qz/x:d	(Landroid/content/Context;)I
    //   10006: istore_2
    //   10007: iload_2
    //   10008: iconst_m1
    //   10009: if_icmpne +24 -> 10033
    //   10012: ldc 173
    //   10014: invokestatic 115	com/tencent/luggage/wxa/ba/e:b	(Ljava/lang/Class;)Lcom/tencent/luggage/wxa/ba/d;
    //   10017: checkcast 173	com/tencent/luggage/wxa/ot/c
    //   10020: ldc2_w 174
    //   10023: ldc2_w 412
    //   10026: lconst_1
    //   10027: iconst_0
    //   10028: invokeinterface 178 8 0
    //   10033: ldc 68
    //   10035: aload 33
    //   10037: iconst_1
    //   10038: anewarray 4	java/lang/Object
    //   10041: dup
    //   10042: iconst_0
    //   10043: iload_2
    //   10044: invokestatic 418	java/lang/Integer:valueOf	(I)Ljava/lang/Integer;
    //   10047: aastore
    //   10048: invokestatic 139	com/tencent/luggage/wxa/qz/o:d	(Ljava/lang/String;Ljava/lang/String;[Ljava/lang/Object;)V
    //   10051: aload_1
    //   10052: iconst_0
    //   10053: putfield 142	com/tencent/luggage/wxa/nz/h:a	Z
    //   10056: aload 36
    //   10058: ifnull +36 -> 10094
    //   10061: aload 36
    //   10063: invokevirtual 421	java/io/InputStream:close	()V
    //   10066: goto +28 -> 10094
    //   10069: astore 20
    //   10071: ldc 68
    //   10073: aload 20
    //   10075: aload 32
    //   10077: iconst_2
    //   10078: anewarray 4	java/lang/Object
    //   10081: dup
    //   10082: iconst_0
    //   10083: aload 34
    //   10085: aastore
    //   10086: dup
    //   10087: iconst_1
    //   10088: aload 29
    //   10090: aastore
    //   10091: invokestatic 424	com/tencent/luggage/wxa/qz/o:a	(Ljava/lang/String;Ljava/lang/Throwable;Ljava/lang/String;[Ljava/lang/Object;)V
    //   10094: aload 31
    //   10096: ifnull +97 -> 10193
    //   10099: aload 31
    //   10101: invokevirtual 421	java/io/InputStream:close	()V
    //   10104: goto +89 -> 10193
    //   10107: astore 20
    //   10109: ldc 68
    //   10111: aload 20
    //   10113: ldc_w 537
    //   10116: iconst_2
    //   10117: anewarray 4	java/lang/Object
    //   10120: dup
    //   10121: iconst_0
    //   10122: aload 34
    //   10124: aastore
    //   10125: dup
    //   10126: iconst_1
    //   10127: aload 29
    //   10129: aastore
    //   10130: invokestatic 424	com/tencent/luggage/wxa/qz/o:a	(Ljava/lang/String;Ljava/lang/Throwable;Ljava/lang/String;[Ljava/lang/Object;)V
    //   10133: goto +60 -> 10193
    //   10136: astore 20
    //   10138: ldc 68
    //   10140: aload 20
    //   10142: ldc_w 539
    //   10145: iconst_2
    //   10146: anewarray 4	java/lang/Object
    //   10149: dup
    //   10150: iconst_0
    //   10151: aload 34
    //   10153: aastore
    //   10154: dup
    //   10155: iconst_1
    //   10156: aload 29
    //   10158: aastore
    //   10159: invokestatic 424	com/tencent/luggage/wxa/qz/o:a	(Ljava/lang/String;Ljava/lang/Throwable;Ljava/lang/String;[Ljava/lang/Object;)V
    //   10162: goto +31 -> 10193
    //   10165: astore 20
    //   10167: ldc 68
    //   10169: aload 20
    //   10171: aload 41
    //   10173: iconst_2
    //   10174: anewarray 4	java/lang/Object
    //   10177: dup
    //   10178: iconst_0
    //   10179: aload 34
    //   10181: aastore
    //   10182: dup
    //   10183: iconst_1
    //   10184: aload 29
    //   10186: aastore
    //   10187: invokestatic 424	com/tencent/luggage/wxa/qz/o:a	(Ljava/lang/String;Ljava/lang/Throwable;Ljava/lang/String;[Ljava/lang/Object;)V
    //   10190: goto +3 -> 10193
    //   10193: aload 37
    //   10195: ifnull +570 -> 10765
    //   10198: aload 37
    //   10200: invokevirtual 425	java/io/DataOutputStream:close	()V
    //   10203: goto +562 -> 10765
    //   10206: astore 20
    //   10208: ldc 68
    //   10210: aload 20
    //   10212: aload 30
    //   10214: iconst_2
    //   10215: anewarray 4	java/lang/Object
    //   10218: dup
    //   10219: iconst_0
    //   10220: aload 34
    //   10222: aastore
    //   10223: dup
    //   10224: iconst_1
    //   10225: aload 29
    //   10227: aastore
    //   10228: invokestatic 424	com/tencent/luggage/wxa/qz/o:a	(Ljava/lang/String;Ljava/lang/Throwable;Ljava/lang/String;[Ljava/lang/Object;)V
    //   10231: goto +534 -> 10765
    //   10234: astore 30
    //   10236: aload 25
    //   10238: astore 29
    //   10240: aload 20
    //   10242: astore 25
    //   10244: aload 30
    //   10246: astore 20
    //   10248: aload 28
    //   10250: astore 31
    //   10252: aload 27
    //   10254: astore 33
    //   10256: aload 29
    //   10258: astore 28
    //   10260: aload 21
    //   10262: astore 36
    //   10264: goto +614 -> 10878
    //   10267: astore 20
    //   10269: aload 29
    //   10271: astore 26
    //   10273: aload 30
    //   10275: astore 24
    //   10277: ldc 84
    //   10279: astore 31
    //   10281: ldc 89
    //   10283: astore 22
    //   10285: ldc 66
    //   10287: astore 32
    //   10289: aconst_null
    //   10290: astore 23
    //   10292: aconst_null
    //   10293: astore 28
    //   10295: aload 28
    //   10297: astore 25
    //   10299: aconst_null
    //   10300: astore 29
    //   10302: iconst_0
    //   10303: istore_3
    //   10304: aload 26
    //   10306: astore 30
    //   10308: aload 25
    //   10310: astore 37
    //   10312: aload 24
    //   10314: astore 26
    //   10316: aload 27
    //   10318: astore 36
    //   10320: aload 31
    //   10322: astore 24
    //   10324: aload 22
    //   10326: astore 33
    //   10328: aload 29
    //   10330: astore 31
    //   10332: aload 32
    //   10334: astore 25
    //   10336: iconst_0
    //   10337: istore 5
    //   10339: aload 26
    //   10341: astore 29
    //   10343: lload 12
    //   10345: lstore 14
    //   10347: aload 23
    //   10349: astore 40
    //   10351: aload 24
    //   10353: astore 32
    //   10355: aload 28
    //   10357: astore 35
    //   10359: aload 21
    //   10361: astore 39
    //   10363: iload_3
    //   10364: istore 4
    //   10366: aload 25
    //   10368: astore 34
    //   10370: aload 20
    //   10372: astore 38
    //   10374: aload 34
    //   10376: astore 20
    //   10378: iload 4
    //   10380: istore_2
    //   10381: aload 31
    //   10383: astore 21
    //   10385: aload 33
    //   10387: astore 22
    //   10389: aload 35
    //   10391: astore 23
    //   10393: aload 32
    //   10395: astore 24
    //   10397: iload 5
    //   10399: istore_3
    //   10400: lload 14
    //   10402: lstore 12
    //   10404: aload 36
    //   10406: astore 25
    //   10408: aload 29
    //   10410: astore 26
    //   10412: aload 37
    //   10414: astore 27
    //   10416: aload 30
    //   10418: astore 28
    //   10420: ldc 173
    //   10422: invokestatic 115	com/tencent/luggage/wxa/ba/e:b	(Ljava/lang/Class;)Lcom/tencent/luggage/wxa/ba/d;
    //   10425: checkcast 173	com/tencent/luggage/wxa/ot/c
    //   10428: ldc2_w 174
    //   10431: lconst_1
    //   10432: lconst_1
    //   10433: iconst_0
    //   10434: invokeinterface 178 8 0
    //   10439: ldc 68
    //   10441: aload 38
    //   10443: ldc_w 564
    //   10446: iconst_2
    //   10447: anewarray 4	java/lang/Object
    //   10450: dup
    //   10451: iconst_0
    //   10452: aload 30
    //   10454: aastore
    //   10455: dup
    //   10456: iconst_1
    //   10457: aload 29
    //   10459: aastore
    //   10460: invokestatic 424	com/tencent/luggage/wxa/qz/o:a	(Ljava/lang/String;Ljava/lang/Throwable;Ljava/lang/String;[Ljava/lang/Object;)V
    //   10463: aload_0
    //   10464: getfield 14	com/tencent/luggage/wxa/nz/g$b:a	Lcom/tencent/luggage/wxa/nz/g;
    //   10467: aload 39
    //   10469: iconst_m1
    //   10470: ldc_w 566
    //   10473: iload 4
    //   10475: aload_1
    //   10476: invokevirtual 103	com/tencent/luggage/wxa/nz/h:l	()Ljava/lang/String;
    //   10479: aload 40
    //   10481: invokestatic 479	com/tencent/luggage/wxa/nz/g:a	(Lcom/tencent/luggage/wxa/nz/g;Lcom/tencent/luggage/wxa/nz/g$a;ILjava/lang/String;ILjava/lang/String;Ljava/net/HttpURLConnection;)V
    //   10484: ldc 110
    //   10486: invokestatic 115	com/tencent/luggage/wxa/ba/e:b	(Ljava/lang/Class;)Lcom/tencent/luggage/wxa/ba/d;
    //   10489: checkcast 110	com/tencent/luggage/wxa/nz/o
    //   10492: aload_0
    //   10493: getfield 14	com/tencent/luggage/wxa/nz/g$b:a	Lcom/tencent/luggage/wxa/nz/g;
    //   10496: invokestatic 118	com/tencent/luggage/wxa/nz/g:a	(Lcom/tencent/luggage/wxa/nz/g;)Lcom/tencent/luggage/wxa/jx/c;
    //   10499: invokeinterface 123 1 0
    //   10504: aload_1
    //   10505: invokevirtual 126	com/tencent/luggage/wxa/nz/h:n	()Ljava/lang/String;
    //   10508: ldc 128
    //   10510: aload_1
    //   10511: invokevirtual 49	com/tencent/luggage/wxa/nz/h:b	()Ljava/lang/String;
    //   10514: lload 14
    //   10516: iload 5
    //   10518: i2l
    //   10519: iload 4
    //   10521: iconst_2
    //   10522: aload_1
    //   10523: invokevirtual 132	com/tencent/luggage/wxa/nz/h:o	()I
    //   10526: aconst_null
    //   10527: aload 36
    //   10529: invokeinterface 135 14 0
    //   10534: invokestatic 406	com/tencent/luggage/wxa/qz/r:a	()Landroid/content/Context;
    //   10537: invokestatic 411	com/tencent/luggage/wxa/qz/x:d	(Landroid/content/Context;)I
    //   10540: istore_2
    //   10541: iload_2
    //   10542: iconst_m1
    //   10543: if_icmpne +24 -> 10567
    //   10546: ldc 173
    //   10548: invokestatic 115	com/tencent/luggage/wxa/ba/e:b	(Ljava/lang/Class;)Lcom/tencent/luggage/wxa/ba/d;
    //   10551: checkcast 173	com/tencent/luggage/wxa/ot/c
    //   10554: ldc2_w 174
    //   10557: ldc2_w 412
    //   10560: lconst_1
    //   10561: iconst_0
    //   10562: invokeinterface 178 8 0
    //   10567: ldc 68
    //   10569: aload 33
    //   10571: iconst_1
    //   10572: anewarray 4	java/lang/Object
    //   10575: dup
    //   10576: iconst_0
    //   10577: iload_2
    //   10578: invokestatic 418	java/lang/Integer:valueOf	(I)Ljava/lang/Integer;
    //   10581: aastore
    //   10582: invokestatic 139	com/tencent/luggage/wxa/qz/o:d	(Ljava/lang/String;Ljava/lang/String;[Ljava/lang/Object;)V
    //   10585: aload_1
    //   10586: iconst_0
    //   10587: putfield 142	com/tencent/luggage/wxa/nz/h:a	Z
    //   10590: aload 37
    //   10592: ifnull +36 -> 10628
    //   10595: aload 37
    //   10597: invokevirtual 421	java/io/InputStream:close	()V
    //   10600: goto +28 -> 10628
    //   10603: astore 20
    //   10605: ldc 68
    //   10607: aload 20
    //   10609: aload 32
    //   10611: iconst_2
    //   10612: anewarray 4	java/lang/Object
    //   10615: dup
    //   10616: iconst_0
    //   10617: aload 30
    //   10619: aastore
    //   10620: dup
    //   10621: iconst_1
    //   10622: aload 29
    //   10624: aastore
    //   10625: invokestatic 424	com/tencent/luggage/wxa/qz/o:a	(Ljava/lang/String;Ljava/lang/Throwable;Ljava/lang/String;[Ljava/lang/Object;)V
    //   10628: aload 31
    //   10630: ifnull +97 -> 10727
    //   10633: aload 31
    //   10635: invokevirtual 421	java/io/InputStream:close	()V
    //   10638: goto +89 -> 10727
    //   10641: astore 20
    //   10643: ldc 68
    //   10645: aload 20
    //   10647: ldc_w 537
    //   10650: iconst_2
    //   10651: anewarray 4	java/lang/Object
    //   10654: dup
    //   10655: iconst_0
    //   10656: aload 30
    //   10658: aastore
    //   10659: dup
    //   10660: iconst_1
    //   10661: aload 29
    //   10663: aastore
    //   10664: invokestatic 424	com/tencent/luggage/wxa/qz/o:a	(Ljava/lang/String;Ljava/lang/Throwable;Ljava/lang/String;[Ljava/lang/Object;)V
    //   10667: goto +60 -> 10727
    //   10670: astore 20
    //   10672: ldc 68
    //   10674: aload 20
    //   10676: ldc_w 539
    //   10679: iconst_2
    //   10680: anewarray 4	java/lang/Object
    //   10683: dup
    //   10684: iconst_0
    //   10685: aload 30
    //   10687: aastore
    //   10688: dup
    //   10689: iconst_1
    //   10690: aload 29
    //   10692: aastore
    //   10693: invokestatic 424	com/tencent/luggage/wxa/qz/o:a	(Ljava/lang/String;Ljava/lang/Throwable;Ljava/lang/String;[Ljava/lang/Object;)V
    //   10696: goto +31 -> 10727
    //   10699: astore 20
    //   10701: ldc 68
    //   10703: aload 20
    //   10705: aload 34
    //   10707: iconst_2
    //   10708: anewarray 4	java/lang/Object
    //   10711: dup
    //   10712: iconst_0
    //   10713: aload 30
    //   10715: aastore
    //   10716: dup
    //   10717: iconst_1
    //   10718: aload 29
    //   10720: aastore
    //   10721: invokestatic 424	com/tencent/luggage/wxa/qz/o:a	(Ljava/lang/String;Ljava/lang/Throwable;Ljava/lang/String;[Ljava/lang/Object;)V
    //   10724: goto +3 -> 10727
    //   10727: aload 35
    //   10729: ifnull +36 -> 10765
    //   10732: aload 35
    //   10734: invokevirtual 425	java/io/DataOutputStream:close	()V
    //   10737: goto +28 -> 10765
    //   10740: astore 20
    //   10742: ldc 68
    //   10744: aload 20
    //   10746: aload 34
    //   10748: iconst_2
    //   10749: anewarray 4	java/lang/Object
    //   10752: dup
    //   10753: iconst_0
    //   10754: aload 30
    //   10756: aastore
    //   10757: dup
    //   10758: iconst_1
    //   10759: aload 29
    //   10761: aastore
    //   10762: invokestatic 424	com/tencent/luggage/wxa/qz/o:a	(Ljava/lang/String;Ljava/lang/Throwable;Ljava/lang/String;[Ljava/lang/Object;)V
    //   10765: aload_0
    //   10766: getfield 14	com/tencent/luggage/wxa/nz/g$b:a	Lcom/tencent/luggage/wxa/nz/g;
    //   10769: getfield 428	com/tencent/luggage/wxa/nz/g:a	Ljava/util/ArrayList;
    //   10772: aload_1
    //   10773: invokevirtual 103	com/tencent/luggage/wxa/nz/h:l	()Ljava/lang/String;
    //   10776: invokevirtual 434	java/util/ArrayList:remove	(Ljava/lang/Object;)Z
    //   10779: pop
    //   10780: return
    //   10781: astore 20
    //   10783: aload 34
    //   10785: astore 25
    //   10787: lload 14
    //   10789: lstore 12
    //   10791: aload 35
    //   10793: astore 28
    //   10795: iload 4
    //   10797: istore_3
    //   10798: aload 32
    //   10800: astore 24
    //   10802: iload 5
    //   10804: istore_2
    //   10805: aload 29
    //   10807: astore 26
    //   10809: aload 37
    //   10811: astore 22
    //   10813: aload 30
    //   10815: astore 23
    //   10817: goto +61 -> 10878
    //   10820: astore 31
    //   10822: aload 28
    //   10824: astore 30
    //   10826: aload 27
    //   10828: astore 29
    //   10830: iload_3
    //   10831: istore 4
    //   10833: aload 23
    //   10835: astore 28
    //   10837: aload 22
    //   10839: astore 33
    //   10841: iload_2
    //   10842: istore_3
    //   10843: aload 31
    //   10845: astore 23
    //   10847: aload 23
    //   10849: astore 27
    //   10851: aload 30
    //   10853: astore 23
    //   10855: aload 29
    //   10857: astore 22
    //   10859: aload 25
    //   10861: astore 36
    //   10863: iload 4
    //   10865: istore_2
    //   10866: aload 21
    //   10868: astore 31
    //   10870: aload 20
    //   10872: astore 25
    //   10874: aload 27
    //   10876: astore 20
    //   10878: aload 22
    //   10880: astore 30
    //   10882: aload 26
    //   10884: astore 22
    //   10886: aload 36
    //   10888: astore 27
    //   10890: aload 24
    //   10892: astore 29
    //   10894: aload 33
    //   10896: astore 21
    //   10898: aload 31
    //   10900: astore 26
    //   10902: aload 25
    //   10904: astore 32
    //   10906: ldc 110
    //   10908: invokestatic 115	com/tencent/luggage/wxa/ba/e:b	(Ljava/lang/Class;)Lcom/tencent/luggage/wxa/ba/d;
    //   10911: checkcast 110	com/tencent/luggage/wxa/nz/o
    //   10914: aload_0
    //   10915: getfield 14	com/tencent/luggage/wxa/nz/g$b:a	Lcom/tencent/luggage/wxa/nz/g;
    //   10918: invokestatic 118	com/tencent/luggage/wxa/nz/g:a	(Lcom/tencent/luggage/wxa/nz/g;)Lcom/tencent/luggage/wxa/jx/c;
    //   10921: invokeinterface 123 1 0
    //   10926: aload_1
    //   10927: invokevirtual 126	com/tencent/luggage/wxa/nz/h:n	()Ljava/lang/String;
    //   10930: ldc 128
    //   10932: aload_1
    //   10933: invokevirtual 49	com/tencent/luggage/wxa/nz/h:b	()Ljava/lang/String;
    //   10936: lload 12
    //   10938: iload_2
    //   10939: i2l
    //   10940: iload_3
    //   10941: iconst_2
    //   10942: aload_1
    //   10943: invokevirtual 132	com/tencent/luggage/wxa/nz/h:o	()I
    //   10946: aconst_null
    //   10947: aload 27
    //   10949: invokeinterface 135 14 0
    //   10954: invokestatic 406	com/tencent/luggage/wxa/qz/r:a	()Landroid/content/Context;
    //   10957: invokestatic 411	com/tencent/luggage/wxa/qz/x:d	(Landroid/content/Context;)I
    //   10960: istore_2
    //   10961: iload_2
    //   10962: iconst_m1
    //   10963: if_icmpne +24 -> 10987
    //   10966: ldc 173
    //   10968: invokestatic 115	com/tencent/luggage/wxa/ba/e:b	(Ljava/lang/Class;)Lcom/tencent/luggage/wxa/ba/d;
    //   10971: checkcast 173	com/tencent/luggage/wxa/ot/c
    //   10974: ldc2_w 174
    //   10977: ldc2_w 412
    //   10980: lconst_1
    //   10981: iconst_0
    //   10982: invokeinterface 178 8 0
    //   10987: ldc 68
    //   10989: aload 21
    //   10991: iconst_1
    //   10992: anewarray 4	java/lang/Object
    //   10995: dup
    //   10996: iconst_0
    //   10997: iload_2
    //   10998: invokestatic 418	java/lang/Integer:valueOf	(I)Ljava/lang/Integer;
    //   11001: aastore
    //   11002: invokestatic 139	com/tencent/luggage/wxa/qz/o:d	(Ljava/lang/String;Ljava/lang/String;[Ljava/lang/Object;)V
    //   11005: aload_1
    //   11006: iconst_0
    //   11007: putfield 142	com/tencent/luggage/wxa/nz/h:a	Z
    //   11010: aload 30
    //   11012: ifnull +36 -> 11048
    //   11015: aload 30
    //   11017: invokevirtual 421	java/io/InputStream:close	()V
    //   11020: goto +28 -> 11048
    //   11023: astore 21
    //   11025: ldc 68
    //   11027: aload 21
    //   11029: aload 29
    //   11031: iconst_2
    //   11032: anewarray 4	java/lang/Object
    //   11035: dup
    //   11036: iconst_0
    //   11037: aload 23
    //   11039: aastore
    //   11040: dup
    //   11041: iconst_1
    //   11042: aload 22
    //   11044: aastore
    //   11045: invokestatic 424	com/tencent/luggage/wxa/qz/o:a	(Ljava/lang/String;Ljava/lang/Throwable;Ljava/lang/String;[Ljava/lang/Object;)V
    //   11048: aload 26
    //   11050: ifnull +94 -> 11144
    //   11053: aload 26
    //   11055: invokevirtual 421	java/io/InputStream:close	()V
    //   11058: goto +86 -> 11144
    //   11061: astore 21
    //   11063: ldc 68
    //   11065: aload 21
    //   11067: ldc_w 537
    //   11070: iconst_2
    //   11071: anewarray 4	java/lang/Object
    //   11074: dup
    //   11075: iconst_0
    //   11076: aload 23
    //   11078: aastore
    //   11079: dup
    //   11080: iconst_1
    //   11081: aload 22
    //   11083: aastore
    //   11084: invokestatic 424	com/tencent/luggage/wxa/qz/o:a	(Ljava/lang/String;Ljava/lang/Throwable;Ljava/lang/String;[Ljava/lang/Object;)V
    //   11087: goto +57 -> 11144
    //   11090: astore 21
    //   11092: ldc 68
    //   11094: aload 21
    //   11096: ldc_w 539
    //   11099: iconst_2
    //   11100: anewarray 4	java/lang/Object
    //   11103: dup
    //   11104: iconst_0
    //   11105: aload 23
    //   11107: aastore
    //   11108: dup
    //   11109: iconst_1
    //   11110: aload 22
    //   11112: aastore
    //   11113: invokestatic 424	com/tencent/luggage/wxa/qz/o:a	(Ljava/lang/String;Ljava/lang/Throwable;Ljava/lang/String;[Ljava/lang/Object;)V
    //   11116: goto +28 -> 11144
    //   11119: astore 21
    //   11121: ldc 68
    //   11123: aload 21
    //   11125: aload 32
    //   11127: iconst_2
    //   11128: anewarray 4	java/lang/Object
    //   11131: dup
    //   11132: iconst_0
    //   11133: aload 23
    //   11135: aastore
    //   11136: dup
    //   11137: iconst_1
    //   11138: aload 22
    //   11140: aastore
    //   11141: invokestatic 424	com/tencent/luggage/wxa/qz/o:a	(Ljava/lang/String;Ljava/lang/Throwable;Ljava/lang/String;[Ljava/lang/Object;)V
    //   11144: aload 28
    //   11146: ifnull +36 -> 11182
    //   11149: aload 28
    //   11151: invokevirtual 425	java/io/DataOutputStream:close	()V
    //   11154: goto +28 -> 11182
    //   11157: astore 21
    //   11159: ldc 68
    //   11161: aload 21
    //   11163: aload 32
    //   11165: iconst_2
    //   11166: anewarray 4	java/lang/Object
    //   11169: dup
    //   11170: iconst_0
    //   11171: aload 23
    //   11173: aastore
    //   11174: dup
    //   11175: iconst_1
    //   11176: aload 22
    //   11178: aastore
    //   11179: invokestatic 424	com/tencent/luggage/wxa/qz/o:a	(Ljava/lang/String;Ljava/lang/Throwable;Ljava/lang/String;[Ljava/lang/Object;)V
    //   11182: aload_0
    //   11183: getfield 14	com/tencent/luggage/wxa/nz/g$b:a	Lcom/tencent/luggage/wxa/nz/g;
    //   11186: getfield 428	com/tencent/luggage/wxa/nz/g:a	Ljava/util/ArrayList;
    //   11189: aload_1
    //   11190: invokevirtual 103	com/tencent/luggage/wxa/nz/h:l	()Ljava/lang/String;
    //   11193: invokevirtual 434	java/util/ArrayList:remove	(Ljava/lang/Object;)Z
    //   11196: pop
    //   11197: goto +6 -> 11203
    //   11200: aload 20
    //   11202: athrow
    //   11203: goto -3 -> 11200
    //   11206: astore 35
    //   11208: goto -6241 -> 4967
    //   11211: astore 21
    //   11213: aload 28
    //   11215: astore 27
    //   11217: lconst_0
    //   11218: lstore 12
    //   11220: aconst_null
    //   11221: astore 29
    //   11223: aload 23
    //   11225: astore 28
    //   11227: aload 20
    //   11229: astore 23
    //   11231: aload 21
    //   11233: astore 20
    //   11235: aload 25
    //   11237: astore 32
    //   11239: aload 28
    //   11241: astore 21
    //   11243: aload 29
    //   11245: astore 28
    //   11247: aload 24
    //   11249: astore 31
    //   11251: aload 26
    //   11253: astore 24
    //   11255: goto -3394 -> 7861
    //   11258: astore 22
    //   11260: aload 28
    //   11262: astore 27
    //   11264: aload 32
    //   11266: astore 28
    //   11268: goto -10752 -> 516
    //   11271: astore 26
    //   11273: aload 28
    //   11275: astore 27
    //   11277: aconst_null
    //   11278: astore 28
    //   11280: aload 25
    //   11282: astore 32
    //   11284: aload 24
    //   11286: astore 31
    //   11288: aload 22
    //   11290: astore 24
    //   11292: aload 20
    //   11294: astore 25
    //   11296: aload 26
    //   11298: astore 20
    //   11300: aload 23
    //   11302: astore 22
    //   11304: aload 29
    //   11306: astore 23
    //   11308: aload 33
    //   11310: astore 26
    //   11312: goto -2843 -> 8469
    //   11315: astore 26
    //   11317: aload 28
    //   11319: astore 27
    //   11321: aconst_null
    //   11322: astore 28
    //   11324: aload 25
    //   11326: astore 32
    //   11328: aload 24
    //   11330: astore 31
    //   11332: aload 22
    //   11334: astore 24
    //   11336: aload 20
    //   11338: astore 25
    //   11340: aload 26
    //   11342: astore 20
    //   11344: aload 23
    //   11346: astore 22
    //   11348: aload 29
    //   11350: astore 23
    //   11352: aload 34
    //   11354: astore 26
    //   11356: goto -2288 -> 9068
    //   11359: astore 26
    //   11361: aload 28
    //   11363: astore 27
    //   11365: aconst_null
    //   11366: astore 28
    //   11368: aload 25
    //   11370: astore 32
    //   11372: aload 24
    //   11374: astore 31
    //   11376: aload 22
    //   11378: astore 24
    //   11380: aload 20
    //   11382: astore 25
    //   11384: aload 26
    //   11386: astore 20
    //   11388: aload 23
    //   11390: astore 22
    //   11392: aload 29
    //   11394: astore 23
    //   11396: aload 35
    //   11398: astore 26
    //   11400: goto -1733 -> 9667
    //   11403: astore 26
    //   11405: aload 28
    //   11407: astore 27
    //   11409: aconst_null
    //   11410: astore 28
    //   11412: aload 25
    //   11414: astore 32
    //   11416: aload 24
    //   11418: astore 31
    //   11420: aload 22
    //   11422: astore 24
    //   11424: aload 20
    //   11426: astore 25
    //   11428: aload 26
    //   11430: astore 20
    //   11432: aload 23
    //   11434: astore 22
    //   11436: aload 29
    //   11438: astore 23
    //   11440: aload 36
    //   11442: astore 26
    //   11444: goto -1145 -> 10299
    //   11447: astore 20
    //   11449: goto -7753 -> 3696
    //   11452: aload 34
    //   11454: astore 29
    //   11456: aload 27
    //   11458: astore 34
    //   11460: aload 22
    //   11462: astore 35
    //   11464: aload 26
    //   11466: astore 25
    //   11468: astore 20
    //   11470: aload 23
    //   11472: astore 24
    //   11474: aload 33
    //   11476: astore 22
    //   11478: aload 28
    //   11480: astore 23
    //   11482: aload 30
    //   11484: astore 27
    //   11486: aload 35
    //   11488: astore 26
    //   11490: aload 34
    //   11492: astore 28
    //   11494: goto -3571 -> 7923
    //   11497: aload 27
    //   11499: astore 29
    //   11501: aload 22
    //   11503: astore 25
    //   11505: aload 26
    //   11507: astore 24
    //   11509: astore 20
    //   11511: aload 33
    //   11513: astore 22
    //   11515: aload 30
    //   11517: astore 27
    //   11519: aload 29
    //   11521: astore 26
    //   11523: goto -3054 -> 8469
    //   11526: aload 27
    //   11528: astore 29
    //   11530: aload 22
    //   11532: astore 25
    //   11534: aload 26
    //   11536: astore 24
    //   11538: astore 20
    //   11540: aload 33
    //   11542: astore 22
    //   11544: aload 30
    //   11546: astore 27
    //   11548: aload 29
    //   11550: astore 26
    //   11552: goto -2484 -> 9068
    //   11555: aload 27
    //   11557: astore 29
    //   11559: aload 22
    //   11561: astore 25
    //   11563: aload 26
    //   11565: astore 24
    //   11567: astore 20
    //   11569: aload 33
    //   11571: astore 22
    //   11573: aload 30
    //   11575: astore 27
    //   11577: aload 29
    //   11579: astore 26
    //   11581: goto -1914 -> 9667
    //   11584: aload 27
    //   11586: astore 29
    //   11588: aload 22
    //   11590: astore 25
    //   11592: aload 26
    //   11594: astore 24
    //   11596: astore 20
    //   11598: aload 33
    //   11600: astore 22
    //   11602: aload 30
    //   11604: astore 27
    //   11606: aload 29
    //   11608: astore 26
    //   11610: goto -1311 -> 10299
    //   11613: goto -8021 -> 3592
    // Local variable table:
    //   start	length	slot	name	signature
    //   0	11616	0	this	b
    //   0	11616	1	paramh	h
    //   488	10510	2	i	int
    //   490	10451	3	j	int
    //   572	10292	4	k	int
    //   575	10228	5	m	int
    //   5077	203	6	n	int
    //   5080	208	7	i1	int
    //   5083	213	8	i2	int
    //   5086	218	9	i3	int
    //   4051	1964	10	i4	int
    //   274	4892	11	bool	boolean
    //   277	10942	12	l1	long
    //   599	10189	14	l2	long
    //   2961	651	16	l3	long
    //   3560	3	18	l4	long
    //   413	2732	20	localObject1	Object
    //   3178	5	20	localException1	java.lang.Exception
    //   3211	59	20	localIOException1	java.io.IOException
    //   3291	383	20	localObject2	Object
    //   3690	73	20	localObject3	Object
    //   3768	238	20	localObject4	Object
    //   4253	5	20	localException2	java.lang.Exception
    //   4286	64	20	localIOException2	java.io.IOException
    //   4355	267	20	localObject5	Object
    //   4656	5	20	localException3	java.lang.Exception
    //   4689	120	20	localIOException3	java.io.IOException
    //   5253	1	20	localObject6	Object
    //   5512	5	20	localException4	java.lang.Exception
    //   5550	5	20	localThrowable1	java.lang.Throwable
    //   5579	5	20	localArrayIndexOutOfBoundsException1	java.lang.ArrayIndexOutOfBoundsException
    //   5608	5	20	localIOException4	java.io.IOException
    //   5641	5	20	localIOException5	java.io.IOException
    //   5673	2083	20	localObject7	Object
    //   7774	1	20	localObject8	Object
    //   7779	1	20	localException5	java.lang.Exception
    //   7784	1	20	localSocketTimeoutException1	java.net.SocketTimeoutException
    //   7789	1	20	localSSLHandshakeException1	javax.net.ssl.SSLHandshakeException
    //   7794	1	20	localFileNotFoundException1	java.io.FileNotFoundException
    //   7799	1	20	localUnsupportedEncodingException1	java.io.UnsupportedEncodingException
    //   7804	1	20	localObject9	Object
    //   7809	1	20	localSocketTimeoutException2	java.net.SocketTimeoutException
    //   7814	1	20	localSSLHandshakeException2	javax.net.ssl.SSLHandshakeException
    //   7819	1	20	localFileNotFoundException2	java.io.FileNotFoundException
    //   7824	1	20	localUnsupportedEncodingException2	java.io.UnsupportedEncodingException
    //   7829	1	20	localObject10	Object
    //   7883	77	20	localException6	java.lang.Exception
    //   7992	40	20	localObject11	Object
    //   8229	5	20	localException7	java.lang.Exception
    //   8267	5	20	localThrowable2	java.lang.Throwable
    //   8296	5	20	localArrayIndexOutOfBoundsException2	java.lang.ArrayIndexOutOfBoundsException
    //   8325	5	20	localIOException6	java.io.IOException
    //   8366	45	20	localIOException7	java.io.IOException
    //   8416	1	20	localObject12	Object
    //   8437	104	20	localSocketTimeoutException3	java.net.SocketTimeoutException
    //   8546	180	20	localObject13	Object
    //   8871	5	20	localException8	java.lang.Exception
    //   8909	5	20	localThrowable3	java.lang.Throwable
    //   8938	5	20	localArrayIndexOutOfBoundsException3	java.lang.ArrayIndexOutOfBoundsException
    //   8967	5	20	localIOException8	java.io.IOException
    //   9008	5	20	localIOException9	java.io.IOException
    //   9036	104	20	localSSLHandshakeException3	javax.net.ssl.SSLHandshakeException
    //   9145	180	20	localObject14	Object
    //   9470	5	20	localException9	java.lang.Exception
    //   9508	5	20	localThrowable4	java.lang.Throwable
    //   9537	5	20	localArrayIndexOutOfBoundsException4	java.lang.ArrayIndexOutOfBoundsException
    //   9566	5	20	localIOException10	java.io.IOException
    //   9607	5	20	localIOException11	java.io.IOException
    //   9635	104	20	localFileNotFoundException3	java.io.FileNotFoundException
    //   9744	180	20	localObject15	Object
    //   10069	5	20	localException10	java.lang.Exception
    //   10107	5	20	localThrowable5	java.lang.Throwable
    //   10136	5	20	localArrayIndexOutOfBoundsException5	java.lang.ArrayIndexOutOfBoundsException
    //   10165	5	20	localIOException12	java.io.IOException
    //   10206	35	20	localIOException13	java.io.IOException
    //   10246	1	20	localObject16	Object
    //   10267	104	20	localUnsupportedEncodingException3	java.io.UnsupportedEncodingException
    //   10376	1	20	localObject17	Object
    //   10603	5	20	localException11	java.lang.Exception
    //   10641	5	20	localThrowable6	java.lang.Throwable
    //   10670	5	20	localArrayIndexOutOfBoundsException6	java.lang.ArrayIndexOutOfBoundsException
    //   10699	5	20	localIOException14	java.io.IOException
    //   10740	5	20	localIOException15	java.io.IOException
    //   10781	90	20	localObject18	Object
    //   10876	555	20	localObject19	Object
    //   11447	1	20	localObject20	Object
    //   11468	1	20	localException12	java.lang.Exception
    //   11509	1	20	localSocketTimeoutException4	java.net.SocketTimeoutException
    //   11538	1	20	localSSLHandshakeException4	javax.net.ssl.SSLHandshakeException
    //   11567	1	20	localFileNotFoundException4	java.io.FileNotFoundException
    //   11596	1	20	localUnsupportedEncodingException4	java.io.UnsupportedEncodingException
    //   80	676	21	localObject21	Object
    //   916	17	21	localObject22	Object
    //   942	1	21	localObject23	Object
    //   2656	258	21	localObject24	Object
    //   2969	78	21	localObject25	Object
    //   3252	38	21	localObject26	Object
    //   3299	412	21	localObject27	Object
    //   3744	15	21	localObject28	Object
    //   3764	300	21	localObject29	Object
    //   4327	1	21	localObject30	Object
    //   4340	14	21	localSocketTimeoutException5	java.net.SocketTimeoutException
    //   4359	1	21	localObject31	Object
    //   4376	14	21	localSSLHandshakeException5	javax.net.ssl.SSLHandshakeException
    //   4395	1	21	localObject32	Object
    //   4412	14	21	localFileNotFoundException5	java.io.FileNotFoundException
    //   4431	1	21	localObject33	Object
    //   4448	14	21	localUnsupportedEncodingException5	java.io.UnsupportedEncodingException
    //   4467	1	21	localObject34	Object
    //   4730	1	21	localObject35	Object
    //   4760	1	21	localObject36	Object
    //   4878	1	21	localObject37	Object
    //   5120	1	21	localObject38	Object
    //   5677	1	21	localObject39	Object
    //   5918	1	21	localObject40	Object
    //   5973	49	21	localObject41	Object
    //   6027	1079	21	localObject42	Object
    //   7156	1	21	localObject43	Object
    //   7234	1	21	localObject44	Object
    //   7524	27	21	localObject45	Object
    //   7562	3428	21	localObject46	Object
    //   11023	5	21	localException13	java.lang.Exception
    //   11061	5	21	localThrowable7	java.lang.Throwable
    //   11090	5	21	localArrayIndexOutOfBoundsException7	java.lang.ArrayIndexOutOfBoundsException
    //   11119	5	21	localIOException16	java.io.IOException
    //   11157	5	21	localIOException17	java.io.IOException
    //   11211	21	21	localObject47	Object
    //   11241	1	21	localObject48	Object
    //   406	1	22	localObject49	Object
    //   510	38	22	localException14	java.lang.Exception
    //   553	227	22	localObject50	Object
    //   955	27	22	localException15	java.lang.Exception
    //   995	133	22	localObject51	Object
    //   2661	313	22	localException16	java.lang.Exception
    //   2991	4129	22	localObject52	Object
    //   7126	1	22	localException17	java.lang.Exception
    //   7131	1	22	localSocketTimeoutException6	java.net.SocketTimeoutException
    //   7136	1	22	localSSLHandshakeException6	javax.net.ssl.SSLHandshakeException
    //   7141	1	22	localFileNotFoundException6	java.io.FileNotFoundException
    //   7146	1	22	localUnsupportedEncodingException6	java.io.UnsupportedEncodingException
    //   7151	1	22	localException18	java.lang.Exception
    //   7169	1	22	localException19	java.lang.Exception
    //   7182	1	22	localSocketTimeoutException7	java.net.SocketTimeoutException
    //   7195	1	22	localSSLHandshakeException7	javax.net.ssl.SSLHandshakeException
    //   7208	1	22	localFileNotFoundException7	java.io.FileNotFoundException
    //   7221	1	22	localUnsupportedEncodingException7	java.io.UnsupportedEncodingException
    //   7239	1	22	localException20	java.lang.Exception
    //   7244	1	22	localSocketTimeoutException8	java.net.SocketTimeoutException
    //   7249	1	22	localSSLHandshakeException8	javax.net.ssl.SSLHandshakeException
    //   7254	1	22	localFileNotFoundException8	java.io.FileNotFoundException
    //   7259	1	22	localUnsupportedEncodingException8	java.io.UnsupportedEncodingException
    //   7264	35	22	localException21	java.lang.Exception
    //   7319	1	22	localObject53	Object
    //   7332	23	22	localSocketTimeoutException9	java.net.SocketTimeoutException
    //   7375	1	22	localObject54	Object
    //   7380	23	22	localSSLHandshakeException9	javax.net.ssl.SSLHandshakeException
    //   7423	1	22	localObject55	Object
    //   7428	23	22	localFileNotFoundException9	java.io.FileNotFoundException
    //   7471	1	22	localObject56	Object
    //   7476	23	22	localUnsupportedEncodingException9	java.io.UnsupportedEncodingException
    //   7519	840	22	localObject57	Object
    //   8394	1	22	localObject58	Object
    //   8399	1	22	localObject59	Object
    //   8404	11	22	localObject60	Object
    //   8432	2745	22	localObject61	Object
    //   11258	31	22	localException22	java.lang.Exception
    //   11302	299	22	localObject62	Object
    //   84	3435	23	localObject63	Object
    //   3630	1	23	localException23	java.lang.Exception
    //   3639	817	23	localObject64	Object
    //   4740	1	23	localSocketTimeoutException10	java.net.SocketTimeoutException
    //   4745	1	23	localSSLHandshakeException10	javax.net.ssl.SSLHandshakeException
    //   4750	1	23	localFileNotFoundException10	java.io.FileNotFoundException
    //   4755	1	23	localUnsupportedEncodingException10	java.io.UnsupportedEncodingException
    //   4773	1	23	localSocketTimeoutException11	java.net.SocketTimeoutException
    //   4781	1	23	localSSLHandshakeException11	javax.net.ssl.SSLHandshakeException
    //   4789	1	23	localFileNotFoundException11	java.io.FileNotFoundException
    //   4797	1	23	localUnsupportedEncodingException11	java.io.UnsupportedEncodingException
    //   4883	1	23	localSocketTimeoutException12	java.net.SocketTimeoutException
    //   4888	1	23	localSSLHandshakeException12	javax.net.ssl.SSLHandshakeException
    //   4893	1	23	localFileNotFoundException12	java.io.FileNotFoundException
    //   4898	1	23	localUnsupportedEncodingException12	java.io.UnsupportedEncodingException
    //   5132	1	23	localSocketTimeoutException13	java.net.SocketTimeoutException
    //   5137	1	23	localSSLHandshakeException13	javax.net.ssl.SSLHandshakeException
    //   5142	1	23	localFileNotFoundException13	java.io.FileNotFoundException
    //   5147	1	23	localUnsupportedEncodingException13	java.io.UnsupportedEncodingException
    //   5264	1	23	localObject65	Object
    //   5669	1	23	localObject66	Object
    //   5928	1	23	localSocketTimeoutException14	java.net.SocketTimeoutException
    //   5933	1	23	localSSLHandshakeException14	javax.net.ssl.SSLHandshakeException
    //   5938	1	23	localFileNotFoundException14	java.io.FileNotFoundException
    //   5943	1	23	localUnsupportedEncodingException14	java.io.UnsupportedEncodingException
    //   5953	1	23	localSocketTimeoutException15	java.net.SocketTimeoutException
    //   5958	1	23	localSSLHandshakeException15	javax.net.ssl.SSLHandshakeException
    //   5963	1	23	localFileNotFoundException15	java.io.FileNotFoundException
    //   5968	1	23	localUnsupportedEncodingException15	java.io.UnsupportedEncodingException
    //   5994	66	23	localObject67	Object
    //   6068	10	23	localSocketTimeoutException16	java.net.SocketTimeoutException
    //   6083	1	23	localObject68	Object
    //   6100	10	23	localSSLHandshakeException16	javax.net.ssl.SSLHandshakeException
    //   6115	1	23	localObject69	Object
    //   6132	10	23	localFileNotFoundException16	java.io.FileNotFoundException
    //   6147	1	23	localObject70	Object
    //   6164	10	23	localUnsupportedEncodingException16	java.io.UnsupportedEncodingException
    //   6179	1	23	localObject71	Object
    //   6196	7	23	localObject72	Object
    //   6212	178	23	localObject73	Object
    //   6398	15	23	localObject74	Object
    //   6418	5063	23	localObject75	Object
    //   74	11521	24	localObject76	Object
    //   42	11549	25	localObject77	Object
    //   8	2663	26	localObject78	Object
    //   2674	6	26	localSocketTimeoutException17	java.net.SocketTimeoutException
    //   2683	6	26	localSSLHandshakeException17	javax.net.ssl.SSLHandshakeException
    //   2692	6	26	localFileNotFoundException17	java.io.FileNotFoundException
    //   2701	6	26	localUnsupportedEncodingException17	java.io.UnsupportedEncodingException
    //   2719	8533	26	localObject79	Object
    //   11271	26	26	localSocketTimeoutException18	java.net.SocketTimeoutException
    //   11310	1	26	localObject80	Object
    //   11315	26	26	localSSLHandshakeException18	javax.net.ssl.SSLHandshakeException
    //   11354	1	26	localObject81	Object
    //   11359	26	26	localFileNotFoundException18	java.io.FileNotFoundException
    //   11398	1	26	localObject82	Object
    //   11403	26	26	localUnsupportedEncodingException18	java.io.UnsupportedEncodingException
    //   11442	167	26	localObject83	Object
    //   372	11233	27	localObject84	Object
    //   32	891	28	localObject85	Object
    //   964	26	28	localSocketTimeoutException19	java.net.SocketTimeoutException
    //   999	1	28	localObject86	Object
    //   1008	26	28	localSSLHandshakeException19	javax.net.ssl.SSLHandshakeException
    //   1043	1	28	localObject87	Object
    //   1052	26	28	localFileNotFoundException19	java.io.FileNotFoundException
    //   1087	1	28	localObject88	Object
    //   1096	26	28	localUnsupportedEncodingException19	java.io.UnsupportedEncodingException
    //   1131	6441	28	localObject89	Object
    //   7618	19	28	localSocketTimeoutException20	java.net.SocketTimeoutException
    //   7644	1	28	localObject90	Object
    //   7657	19	28	localSSLHandshakeException20	javax.net.ssl.SSLHandshakeException
    //   7683	1	28	localObject91	Object
    //   7696	19	28	localFileNotFoundException20	java.io.FileNotFoundException
    //   7722	1	28	localObject92	Object
    //   7735	19	28	localUnsupportedEncodingException20	java.io.UnsupportedEncodingException
    //   7761	3732	28	localObject93	Object
    //   4	452	29	localObject94	Object
    //   463	29	29	localObject95	Object
    //   501	11106	29	localObject96	Object
    //   14	3272	30	localObject97	Object
    //   3316	27	30	localException24	java.lang.Exception
    //   3364	1	30	localObject98	Object
    //   3369	12	30	localSocketTimeoutException21	java.net.SocketTimeoutException
    //   3399	12	30	localSSLHandshakeException21	javax.net.ssl.SSLHandshakeException
    //   3429	12	30	localFileNotFoundException21	java.io.FileNotFoundException
    //   3459	12	30	localUnsupportedEncodingException21	java.io.UnsupportedEncodingException
    //   3484	8	30	localObject99	Object
    //   3635	1	30	localSocketTimeoutException22	java.net.SocketTimeoutException
    //   3644	1	30	localSSLHandshakeException22	javax.net.ssl.SSLHandshakeException
    //   3653	1	30	localFileNotFoundException22	java.io.FileNotFoundException
    //   3662	51	30	localUnsupportedEncodingException22	java.io.UnsupportedEncodingException
    //   3719	1	30	localException25	java.lang.Exception
    //   3724	1	30	localSocketTimeoutException23	java.net.SocketTimeoutException
    //   3729	1	30	localSSLHandshakeException23	javax.net.ssl.SSLHandshakeException
    //   3734	1	30	localFileNotFoundException23	java.io.FileNotFoundException
    //   3739	1	30	localUnsupportedEncodingException23	java.io.UnsupportedEncodingException
    //   3785	7	30	localException26	java.lang.Exception
    //   3797	43	30	localObject100	Object
    //   3850	19	30	localSocketTimeoutException24	java.net.SocketTimeoutException
    //   3895	19	30	localSSLHandshakeException24	javax.net.ssl.SSLHandshakeException
    //   3940	19	30	localFileNotFoundException24	java.io.FileNotFoundException
    //   3985	19	30	localUnsupportedEncodingException24	java.io.UnsupportedEncodingException
    //   4032	448	30	localObject101	Object
    //   4735	1	30	localException27	java.lang.Exception
    //   4768	186	30	localException28	java.lang.Exception
    //   5125	78	30	localException29	java.lang.Exception
    //   5269	55	30	localException30	java.lang.Exception
    //   5692	1	30	localObject102	Object
    //   5697	7	30	localException31	java.lang.Exception
    //   5709	205	30	localObject103	Object
    //   5923	1	30	localException32	java.lang.Exception
    //   5948	1	30	localException33	java.lang.Exception
    //   5999	3	30	localException34	java.lang.Exception
    //   6006	672	30	localObject104	Object
    //   6684	27	30	localObject105	Object
    //   6733	31	30	localException35	java.lang.Exception
    //   6769	1	30	localObject106	Object
    //   6818	31	30	localSocketTimeoutException25	java.net.SocketTimeoutException
    //   6854	1	30	localObject107	Object
    //   6895	31	30	localSSLHandshakeException25	javax.net.ssl.SSLHandshakeException
    //   6931	1	30	localObject108	Object
    //   6972	31	30	localFileNotFoundException25	java.io.FileNotFoundException
    //   7008	1	30	localObject109	Object
    //   7049	31	30	localUnsupportedEncodingException25	java.io.UnsupportedEncodingException
    //   7085	450	30	localObject110	Object
    //   7567	23	30	localException36	java.lang.Exception
    //   7594	2619	30	localObject111	Object
    //   10234	40	30	localObject112	Object
    //   10306	1297	30	localObject113	Object
    //   467	3864	31	localObject114	Object
    //   4335	1	31	localException37	java.lang.Exception
    //   4343	526	31	localObject115	Object
    //   4873	1	31	localException38	java.lang.Exception
    //   4903	5	31	localException39	java.lang.Exception
    //   4948	1220	31	localObject116	Object
    //   6221	11	31	localException40	java.lang.Exception
    //   6241	1	31	localObject117	Object
    //   6250	11	31	localSocketTimeoutException26	java.net.SocketTimeoutException
    //   6274	1	31	localObject118	Object
    //   6287	11	31	localSSLHandshakeException26	javax.net.ssl.SSLHandshakeException
    //   6311	1	31	localObject119	Object
    //   6324	11	31	localFileNotFoundException26	java.io.FileNotFoundException
    //   6348	1	31	localObject120	Object
    //   6361	11	31	localUnsupportedEncodingException26	java.io.UnsupportedEncodingException
    //   6385	4249	31	localObject121	Object
    //   10820	24	31	localObject122	Object
    //   10868	551	31	localObject123	Object
    //   497	10918	32	localObject124	Object
    //   518	5654	33	localObject125	Object
    //   6423	27	33	localException41	java.lang.Exception
    //   6472	31	33	localSocketTimeoutException27	java.net.SocketTimeoutException
    //   6525	31	33	localSSLHandshakeException27	javax.net.ssl.SSLHandshakeException
    //   6578	31	33	localFileNotFoundException27	java.io.FileNotFoundException
    //   6631	31	33	localUnsupportedEncodingException27	java.io.UnsupportedEncodingException
    //   6801	4798	33	localObject126	Object
    //   615	10876	34	localObject127	Object
    //   603	10189	35	localObject128	Object
    //   11206	191	35	localException42	java.lang.Exception
    //   11462	25	35	localObject129	Object
    //   611	10830	36	localObject130	Object
    //   424	10386	37	localObject131	Object
    //   38	17	38	str1	String
    //   562	1	38	localSocketTimeoutException28	java.net.SocketTimeoutException
    //   620	1	38	localSSLHandshakeException28	javax.net.ssl.SSLHandshakeException
    //   678	1	38	localFileNotFoundException28	java.io.FileNotFoundException
    //   736	2228	38	localUnsupportedEncodingException28	java.io.UnsupportedEncodingException
    //   2983	2117	38	localObject132	Object
    //   5277	1	38	localSocketTimeoutException29	java.net.SocketTimeoutException
    //   5285	1	38	localSSLHandshakeException29	javax.net.ssl.SSLHandshakeException
    //   5293	1	38	localFileNotFoundException29	java.io.FileNotFoundException
    //   5301	1	38	localUnsupportedEncodingException29	java.io.UnsupportedEncodingException
    //   5714	1	38	localSocketTimeoutException30	java.net.SocketTimeoutException
    //   5765	1	38	localSSLHandshakeException30	javax.net.ssl.SSLHandshakeException
    //   5816	1	38	localFileNotFoundException30	java.io.FileNotFoundException
    //   5867	1	38	localUnsupportedEncodingException30	java.io.UnsupportedEncodingException
    //   8542	1900	38	localObject133	Object
    //   70	10398	39	localObject134	Object
    //   64	10416	40	localObject135	Object
    //   368	9804	41	localObject136	Object
    //   365	2637	42	str2	String
    //   402	2555	43	locali	com.tencent.luggage.wxa.rt.i
    //   90	2646	44	localObject137	Object
    //   1695	1020	45	localStringBuilder	java.lang.StringBuilder
    //   20	2195	46	str3	String
    //   1952	129	47	str4	String
    //   1990	137	48	str5	String
    // Exception table:
    //   from	to	target	type
    //   454	460	463	finally
    //   454	460	510	java/lang/Exception
    //   454	460	562	java/net/SocketTimeoutException
    //   454	460	620	javax/net/ssl/SSLHandshakeException
    //   454	460	678	java/io/FileNotFoundException
    //   454	460	736	java/io/UnsupportedEncodingException
    //   830	840	916	finally
    //   864	882	916	finally
    //   906	913	916	finally
    //   1267	1284	916	finally
    //   1308	1322	916	finally
    //   1346	1356	916	finally
    //   1380	1392	916	finally
    //   1416	1453	916	finally
    //   1477	1493	916	finally
    //   1517	1533	916	finally
    //   1557	1579	916	finally
    //   1603	1611	916	finally
    //   1638	1663	916	finally
    //   1735	1744	916	finally
    //   1768	1777	916	finally
    //   1801	1809	916	finally
    //   1833	1846	916	finally
    //   1870	1884	916	finally
    //   1908	1918	916	finally
    //   1942	1954	916	finally
    //   1978	1992	916	finally
    //   830	840	955	java/lang/Exception
    //   864	882	955	java/lang/Exception
    //   906	913	955	java/lang/Exception
    //   1267	1284	955	java/lang/Exception
    //   1308	1322	955	java/lang/Exception
    //   1346	1356	955	java/lang/Exception
    //   1380	1392	955	java/lang/Exception
    //   1416	1453	955	java/lang/Exception
    //   1477	1493	955	java/lang/Exception
    //   1517	1533	955	java/lang/Exception
    //   1557	1579	955	java/lang/Exception
    //   1603	1611	955	java/lang/Exception
    //   1638	1663	955	java/lang/Exception
    //   1735	1744	955	java/lang/Exception
    //   1768	1777	955	java/lang/Exception
    //   1801	1809	955	java/lang/Exception
    //   1833	1846	955	java/lang/Exception
    //   1870	1884	955	java/lang/Exception
    //   1908	1918	955	java/lang/Exception
    //   1942	1954	955	java/lang/Exception
    //   1978	1992	955	java/lang/Exception
    //   830	840	964	java/net/SocketTimeoutException
    //   864	882	964	java/net/SocketTimeoutException
    //   906	913	964	java/net/SocketTimeoutException
    //   1267	1284	964	java/net/SocketTimeoutException
    //   1308	1322	964	java/net/SocketTimeoutException
    //   1346	1356	964	java/net/SocketTimeoutException
    //   1380	1392	964	java/net/SocketTimeoutException
    //   1416	1453	964	java/net/SocketTimeoutException
    //   1477	1493	964	java/net/SocketTimeoutException
    //   1517	1533	964	java/net/SocketTimeoutException
    //   1557	1579	964	java/net/SocketTimeoutException
    //   1603	1611	964	java/net/SocketTimeoutException
    //   1638	1663	964	java/net/SocketTimeoutException
    //   1735	1744	964	java/net/SocketTimeoutException
    //   1768	1777	964	java/net/SocketTimeoutException
    //   1801	1809	964	java/net/SocketTimeoutException
    //   1833	1846	964	java/net/SocketTimeoutException
    //   1870	1884	964	java/net/SocketTimeoutException
    //   1908	1918	964	java/net/SocketTimeoutException
    //   1942	1954	964	java/net/SocketTimeoutException
    //   1978	1992	964	java/net/SocketTimeoutException
    //   830	840	1008	javax/net/ssl/SSLHandshakeException
    //   864	882	1008	javax/net/ssl/SSLHandshakeException
    //   906	913	1008	javax/net/ssl/SSLHandshakeException
    //   1267	1284	1008	javax/net/ssl/SSLHandshakeException
    //   1308	1322	1008	javax/net/ssl/SSLHandshakeException
    //   1346	1356	1008	javax/net/ssl/SSLHandshakeException
    //   1380	1392	1008	javax/net/ssl/SSLHandshakeException
    //   1416	1453	1008	javax/net/ssl/SSLHandshakeException
    //   1477	1493	1008	javax/net/ssl/SSLHandshakeException
    //   1517	1533	1008	javax/net/ssl/SSLHandshakeException
    //   1557	1579	1008	javax/net/ssl/SSLHandshakeException
    //   1603	1611	1008	javax/net/ssl/SSLHandshakeException
    //   1638	1663	1008	javax/net/ssl/SSLHandshakeException
    //   1735	1744	1008	javax/net/ssl/SSLHandshakeException
    //   1768	1777	1008	javax/net/ssl/SSLHandshakeException
    //   1801	1809	1008	javax/net/ssl/SSLHandshakeException
    //   1833	1846	1008	javax/net/ssl/SSLHandshakeException
    //   1870	1884	1008	javax/net/ssl/SSLHandshakeException
    //   1908	1918	1008	javax/net/ssl/SSLHandshakeException
    //   1942	1954	1008	javax/net/ssl/SSLHandshakeException
    //   1978	1992	1008	javax/net/ssl/SSLHandshakeException
    //   830	840	1052	java/io/FileNotFoundException
    //   864	882	1052	java/io/FileNotFoundException
    //   906	913	1052	java/io/FileNotFoundException
    //   1267	1284	1052	java/io/FileNotFoundException
    //   1308	1322	1052	java/io/FileNotFoundException
    //   1346	1356	1052	java/io/FileNotFoundException
    //   1380	1392	1052	java/io/FileNotFoundException
    //   1416	1453	1052	java/io/FileNotFoundException
    //   1477	1493	1052	java/io/FileNotFoundException
    //   1517	1533	1052	java/io/FileNotFoundException
    //   1557	1579	1052	java/io/FileNotFoundException
    //   1603	1611	1052	java/io/FileNotFoundException
    //   1638	1663	1052	java/io/FileNotFoundException
    //   1735	1744	1052	java/io/FileNotFoundException
    //   1768	1777	1052	java/io/FileNotFoundException
    //   1801	1809	1052	java/io/FileNotFoundException
    //   1833	1846	1052	java/io/FileNotFoundException
    //   1870	1884	1052	java/io/FileNotFoundException
    //   1908	1918	1052	java/io/FileNotFoundException
    //   1942	1954	1052	java/io/FileNotFoundException
    //   1978	1992	1052	java/io/FileNotFoundException
    //   830	840	1096	java/io/UnsupportedEncodingException
    //   864	882	1096	java/io/UnsupportedEncodingException
    //   906	913	1096	java/io/UnsupportedEncodingException
    //   1267	1284	1096	java/io/UnsupportedEncodingException
    //   1308	1322	1096	java/io/UnsupportedEncodingException
    //   1346	1356	1096	java/io/UnsupportedEncodingException
    //   1380	1392	1096	java/io/UnsupportedEncodingException
    //   1416	1453	1096	java/io/UnsupportedEncodingException
    //   1477	1493	1096	java/io/UnsupportedEncodingException
    //   1517	1533	1096	java/io/UnsupportedEncodingException
    //   1557	1579	1096	java/io/UnsupportedEncodingException
    //   1603	1611	1096	java/io/UnsupportedEncodingException
    //   1638	1663	1096	java/io/UnsupportedEncodingException
    //   1735	1744	1096	java/io/UnsupportedEncodingException
    //   1768	1777	1096	java/io/UnsupportedEncodingException
    //   1801	1809	1096	java/io/UnsupportedEncodingException
    //   1833	1846	1096	java/io/UnsupportedEncodingException
    //   1870	1884	1096	java/io/UnsupportedEncodingException
    //   1908	1918	1096	java/io/UnsupportedEncodingException
    //   1942	1954	1096	java/io/UnsupportedEncodingException
    //   1978	1992	1096	java/io/UnsupportedEncodingException
    //   1992	2141	2656	finally
    //   2148	2284	2656	finally
    //   1992	2141	2661	java/lang/Exception
    //   2148	2284	2661	java/lang/Exception
    //   1992	2141	2670	java/net/SocketTimeoutException
    //   2148	2284	2670	java/net/SocketTimeoutException
    //   1992	2141	2679	javax/net/ssl/SSLHandshakeException
    //   2148	2284	2679	javax/net/ssl/SSLHandshakeException
    //   1992	2141	2688	java/io/FileNotFoundException
    //   2148	2284	2688	java/io/FileNotFoundException
    //   1992	2141	2697	java/io/UnsupportedEncodingException
    //   2148	2284	2697	java/io/UnsupportedEncodingException
    //   3170	3175	3178	java/lang/Exception
    //   3203	3208	3211	java/io/IOException
    //   3042	3061	3252	finally
    //   3042	3061	3316	java/lang/Exception
    //   3042	3061	3369	java/net/SocketTimeoutException
    //   3042	3061	3399	javax/net/ssl/SSLHandshakeException
    //   3042	3061	3429	java/io/FileNotFoundException
    //   3042	3061	3459	java/io/UnsupportedEncodingException
    //   3540	3547	3630	java/lang/Exception
    //   3551	3562	3630	java/lang/Exception
    //   3540	3547	3635	java/net/SocketTimeoutException
    //   3551	3562	3635	java/net/SocketTimeoutException
    //   3540	3547	3644	javax/net/ssl/SSLHandshakeException
    //   3551	3562	3644	javax/net/ssl/SSLHandshakeException
    //   3540	3547	3653	java/io/FileNotFoundException
    //   3551	3562	3653	java/io/FileNotFoundException
    //   3540	3547	3662	java/io/UnsupportedEncodingException
    //   3551	3562	3662	java/io/UnsupportedEncodingException
    //   3509	3518	3690	finally
    //   3540	3547	3690	finally
    //   3551	3562	3690	finally
    //   3509	3518	3719	java/lang/Exception
    //   3509	3518	3724	java/net/SocketTimeoutException
    //   3509	3518	3729	javax/net/ssl/SSLHandshakeException
    //   3509	3518	3734	java/io/FileNotFoundException
    //   3509	3518	3739	java/io/UnsupportedEncodingException
    //   3018	3037	3744	finally
    //   3018	3037	3785	java/lang/Exception
    //   3018	3037	3850	java/net/SocketTimeoutException
    //   3018	3037	3895	javax/net/ssl/SSLHandshakeException
    //   3018	3037	3940	java/io/FileNotFoundException
    //   3018	3037	3985	java/io/UnsupportedEncodingException
    //   4245	4250	4253	java/lang/Exception
    //   4278	4283	4286	java/io/IOException
    //   4147	4187	4327	finally
    //   4147	4187	4335	java/lang/Exception
    //   4147	4187	4340	java/net/SocketTimeoutException
    //   4147	4187	4376	javax/net/ssl/SSLHandshakeException
    //   4147	4187	4412	java/io/FileNotFoundException
    //   4147	4187	4448	java/io/UnsupportedEncodingException
    //   4648	4653	4656	java/lang/Exception
    //   4681	4686	4689	java/io/IOException
    //   4487	4538	4730	finally
    //   4487	4538	4735	java/lang/Exception
    //   4487	4538	4740	java/net/SocketTimeoutException
    //   4487	4538	4745	javax/net/ssl/SSLHandshakeException
    //   4487	4538	4750	java/io/FileNotFoundException
    //   4487	4538	4755	java/io/UnsupportedEncodingException
    //   4083	4138	4760	finally
    //   4083	4138	4768	java/lang/Exception
    //   4083	4138	4773	java/net/SocketTimeoutException
    //   4083	4138	4781	javax/net/ssl/SSLHandshakeException
    //   4083	4138	4789	java/io/FileNotFoundException
    //   4083	4138	4797	java/io/UnsupportedEncodingException
    //   4836	4860	4873	java/lang/Exception
    //   4863	4870	4873	java/lang/Exception
    //   4829	4836	4878	finally
    //   4836	4860	4878	finally
    //   4863	4870	4878	finally
    //   4919	4946	4878	finally
    //   4953	4960	4878	finally
    //   4829	4836	4883	java/net/SocketTimeoutException
    //   4836	4860	4883	java/net/SocketTimeoutException
    //   4863	4870	4883	java/net/SocketTimeoutException
    //   4919	4946	4883	java/net/SocketTimeoutException
    //   4953	4960	4883	java/net/SocketTimeoutException
    //   4829	4836	4888	javax/net/ssl/SSLHandshakeException
    //   4836	4860	4888	javax/net/ssl/SSLHandshakeException
    //   4863	4870	4888	javax/net/ssl/SSLHandshakeException
    //   4919	4946	4888	javax/net/ssl/SSLHandshakeException
    //   4953	4960	4888	javax/net/ssl/SSLHandshakeException
    //   4829	4836	4893	java/io/FileNotFoundException
    //   4836	4860	4893	java/io/FileNotFoundException
    //   4863	4870	4893	java/io/FileNotFoundException
    //   4919	4946	4893	java/io/FileNotFoundException
    //   4953	4960	4893	java/io/FileNotFoundException
    //   4829	4836	4898	java/io/UnsupportedEncodingException
    //   4836	4860	4898	java/io/UnsupportedEncodingException
    //   4863	4870	4898	java/io/UnsupportedEncodingException
    //   4919	4946	4898	java/io/UnsupportedEncodingException
    //   4953	4960	4898	java/io/UnsupportedEncodingException
    //   4829	4836	4903	java/lang/Exception
    //   4993	5020	5120	finally
    //   5020	5027	5120	finally
    //   5032	5048	5120	finally
    //   5051	5070	5120	finally
    //   4993	5020	5125	java/lang/Exception
    //   5020	5027	5125	java/lang/Exception
    //   5032	5048	5125	java/lang/Exception
    //   5051	5070	5125	java/lang/Exception
    //   4993	5020	5132	java/net/SocketTimeoutException
    //   5020	5027	5132	java/net/SocketTimeoutException
    //   5032	5048	5132	java/net/SocketTimeoutException
    //   5051	5070	5132	java/net/SocketTimeoutException
    //   4993	5020	5137	javax/net/ssl/SSLHandshakeException
    //   5020	5027	5137	javax/net/ssl/SSLHandshakeException
    //   5032	5048	5137	javax/net/ssl/SSLHandshakeException
    //   5051	5070	5137	javax/net/ssl/SSLHandshakeException
    //   4993	5020	5142	java/io/FileNotFoundException
    //   5020	5027	5142	java/io/FileNotFoundException
    //   5032	5048	5142	java/io/FileNotFoundException
    //   5051	5070	5142	java/io/FileNotFoundException
    //   4993	5020	5147	java/io/UnsupportedEncodingException
    //   5020	5027	5147	java/io/UnsupportedEncodingException
    //   5032	5048	5147	java/io/UnsupportedEncodingException
    //   5051	5070	5147	java/io/UnsupportedEncodingException
    //   5088	5117	5253	finally
    //   5188	5207	5253	finally
    //   5225	5247	5253	finally
    //   5088	5117	5269	java/lang/Exception
    //   5188	5207	5269	java/lang/Exception
    //   5225	5247	5269	java/lang/Exception
    //   5088	5117	5277	java/net/SocketTimeoutException
    //   5188	5207	5277	java/net/SocketTimeoutException
    //   5225	5247	5277	java/net/SocketTimeoutException
    //   5088	5117	5285	javax/net/ssl/SSLHandshakeException
    //   5188	5207	5285	javax/net/ssl/SSLHandshakeException
    //   5225	5247	5285	javax/net/ssl/SSLHandshakeException
    //   5088	5117	5293	java/io/FileNotFoundException
    //   5188	5207	5293	java/io/FileNotFoundException
    //   5225	5247	5293	java/io/FileNotFoundException
    //   5088	5117	5301	java/io/UnsupportedEncodingException
    //   5188	5207	5301	java/io/UnsupportedEncodingException
    //   5225	5247	5301	java/io/UnsupportedEncodingException
    //   5504	5509	5512	java/lang/Exception
    //   5542	5547	5550	java/lang/Throwable
    //   5542	5547	5579	java/lang/ArrayIndexOutOfBoundsException
    //   5542	5547	5608	java/io/IOException
    //   5633	5638	5641	java/io/IOException
    //   5158	5165	5669	finally
    //   5309	5335	5669	finally
    //   5158	5165	5697	java/lang/Exception
    //   5309	5335	5697	java/lang/Exception
    //   5158	5165	5714	java/net/SocketTimeoutException
    //   5309	5335	5714	java/net/SocketTimeoutException
    //   5158	5165	5765	javax/net/ssl/SSLHandshakeException
    //   5309	5335	5765	javax/net/ssl/SSLHandshakeException
    //   5158	5165	5816	java/io/FileNotFoundException
    //   5309	5335	5816	java/io/FileNotFoundException
    //   5158	5165	5867	java/io/UnsupportedEncodingException
    //   5309	5335	5867	java/io/UnsupportedEncodingException
    //   4812	4829	5918	finally
    //   4905	4919	5918	finally
    //   4967	4981	5918	finally
    //   4812	4829	5923	java/lang/Exception
    //   4905	4919	5923	java/lang/Exception
    //   4967	4981	5923	java/lang/Exception
    //   4812	4829	5928	java/net/SocketTimeoutException
    //   4905	4919	5928	java/net/SocketTimeoutException
    //   4967	4981	5928	java/net/SocketTimeoutException
    //   4812	4829	5933	javax/net/ssl/SSLHandshakeException
    //   4905	4919	5933	javax/net/ssl/SSLHandshakeException
    //   4967	4981	5933	javax/net/ssl/SSLHandshakeException
    //   4812	4829	5938	java/io/FileNotFoundException
    //   4905	4919	5938	java/io/FileNotFoundException
    //   4967	4981	5938	java/io/FileNotFoundException
    //   4812	4829	5943	java/io/UnsupportedEncodingException
    //   4905	4919	5943	java/io/UnsupportedEncodingException
    //   4967	4981	5943	java/io/UnsupportedEncodingException
    //   4067	4076	5948	java/lang/Exception
    //   4067	4076	5953	java/net/SocketTimeoutException
    //   4067	4076	5958	javax/net/ssl/SSLHandshakeException
    //   4067	4076	5963	java/io/FileNotFoundException
    //   4067	4076	5968	java/io/UnsupportedEncodingException
    //   4056	4063	5973	finally
    //   4067	4076	5973	finally
    //   4056	4063	5999	java/lang/Exception
    //   4056	4063	6068	java/net/SocketTimeoutException
    //   4056	4063	6100	javax/net/ssl/SSLHandshakeException
    //   4056	4063	6132	java/io/FileNotFoundException
    //   4056	4063	6164	java/io/UnsupportedEncodingException
    //   4034	4053	6196	finally
    //   4034	4053	6221	java/lang/Exception
    //   4034	4053	6250	java/net/SocketTimeoutException
    //   4034	4053	6287	javax/net/ssl/SSLHandshakeException
    //   4034	4053	6324	java/io/FileNotFoundException
    //   4034	4053	6361	java/io/UnsupportedEncodingException
    //   3005	3013	6398	finally
    //   3005	3013	6423	java/lang/Exception
    //   3005	3013	6472	java/net/SocketTimeoutException
    //   3005	3013	6525	javax/net/ssl/SSLHandshakeException
    //   3005	3013	6578	java/io/FileNotFoundException
    //   3005	3013	6631	java/io/UnsupportedEncodingException
    //   2940	2963	6684	finally
    //   2940	2963	6733	java/lang/Exception
    //   2940	2963	6818	java/net/SocketTimeoutException
    //   2940	2963	6895	javax/net/ssl/SSLHandshakeException
    //   2940	2963	6972	java/io/FileNotFoundException
    //   2940	2963	7049	java/io/UnsupportedEncodingException
    //   2917	2940	7126	java/lang/Exception
    //   2917	2940	7131	java/net/SocketTimeoutException
    //   2917	2940	7136	javax/net/ssl/SSLHandshakeException
    //   2917	2940	7141	java/io/FileNotFoundException
    //   2917	2940	7146	java/io/UnsupportedEncodingException
    //   2885	2913	7151	java/lang/Exception
    //   2714	2721	7156	finally
    //   2726	2747	7156	finally
    //   2830	2881	7156	finally
    //   2885	2913	7156	finally
    //   2917	2940	7156	finally
    //   2714	2721	7169	java/lang/Exception
    //   2726	2747	7169	java/lang/Exception
    //   2830	2881	7169	java/lang/Exception
    //   2714	2721	7182	java/net/SocketTimeoutException
    //   2726	2747	7182	java/net/SocketTimeoutException
    //   2830	2881	7182	java/net/SocketTimeoutException
    //   2885	2913	7182	java/net/SocketTimeoutException
    //   2714	2721	7195	javax/net/ssl/SSLHandshakeException
    //   2726	2747	7195	javax/net/ssl/SSLHandshakeException
    //   2830	2881	7195	javax/net/ssl/SSLHandshakeException
    //   2885	2913	7195	javax/net/ssl/SSLHandshakeException
    //   2714	2721	7208	java/io/FileNotFoundException
    //   2726	2747	7208	java/io/FileNotFoundException
    //   2830	2881	7208	java/io/FileNotFoundException
    //   2885	2913	7208	java/io/FileNotFoundException
    //   2714	2721	7221	java/io/UnsupportedEncodingException
    //   2726	2747	7221	java/io/UnsupportedEncodingException
    //   2830	2881	7221	java/io/UnsupportedEncodingException
    //   2885	2913	7221	java/io/UnsupportedEncodingException
    //   794	801	7234	finally
    //   1140	1238	7234	finally
    //   1666	1706	7234	finally
    //   794	801	7239	java/lang/Exception
    //   1140	1238	7239	java/lang/Exception
    //   1666	1706	7239	java/lang/Exception
    //   794	801	7244	java/net/SocketTimeoutException
    //   1140	1238	7244	java/net/SocketTimeoutException
    //   1666	1706	7244	java/net/SocketTimeoutException
    //   794	801	7249	javax/net/ssl/SSLHandshakeException
    //   1140	1238	7249	javax/net/ssl/SSLHandshakeException
    //   1666	1706	7249	javax/net/ssl/SSLHandshakeException
    //   794	801	7254	java/io/FileNotFoundException
    //   1140	1238	7254	java/io/FileNotFoundException
    //   1666	1706	7254	java/io/FileNotFoundException
    //   794	801	7259	java/io/UnsupportedEncodingException
    //   1140	1238	7259	java/io/UnsupportedEncodingException
    //   1666	1706	7259	java/io/UnsupportedEncodingException
    //   440	449	7264	java/lang/Exception
    //   440	449	7332	java/net/SocketTimeoutException
    //   440	449	7380	javax/net/ssl/SSLHandshakeException
    //   440	449	7428	java/io/FileNotFoundException
    //   440	449	7476	java/io/UnsupportedEncodingException
    //   415	433	7524	finally
    //   433	440	7524	finally
    //   440	449	7524	finally
    //   415	433	7567	java/lang/Exception
    //   433	440	7567	java/lang/Exception
    //   415	433	7618	java/net/SocketTimeoutException
    //   433	440	7618	java/net/SocketTimeoutException
    //   415	433	7657	javax/net/ssl/SSLHandshakeException
    //   433	440	7657	javax/net/ssl/SSLHandshakeException
    //   415	433	7696	java/io/FileNotFoundException
    //   433	440	7696	java/io/FileNotFoundException
    //   415	433	7735	java/io/UnsupportedEncodingException
    //   433	440	7735	java/io/UnsupportedEncodingException
    //   408	415	7774	finally
    //   408	415	7779	java/lang/Exception
    //   408	415	7784	java/net/SocketTimeoutException
    //   408	415	7789	javax/net/ssl/SSLHandshakeException
    //   408	415	7794	java/io/FileNotFoundException
    //   408	415	7799	java/io/UnsupportedEncodingException
    //   393	404	7804	finally
    //   393	404	7809	java/net/SocketTimeoutException
    //   393	404	7814	javax/net/ssl/SSLHandshakeException
    //   393	404	7819	java/io/FileNotFoundException
    //   393	404	7824	java/io/UnsupportedEncodingException
    //   374	393	7829	finally
    //   374	393	7883	java/lang/Exception
    //   393	404	7883	java/lang/Exception
    //   8221	8226	8229	java/lang/Exception
    //   8259	8264	8267	java/lang/Throwable
    //   8259	8264	8296	java/lang/ArrayIndexOutOfBoundsException
    //   8259	8264	8325	java/io/IOException
    //   8358	8363	8366	java/io/IOException
    //   8073	8112	8394	finally
    //   8035	8073	8399	finally
    //   8010	8031	8404	finally
    //   374	393	8437	java/net/SocketTimeoutException
    //   8863	8868	8871	java/lang/Exception
    //   8901	8906	8909	java/lang/Throwable
    //   8901	8906	8938	java/lang/ArrayIndexOutOfBoundsException
    //   8901	8906	8967	java/io/IOException
    //   9000	9005	9008	java/io/IOException
    //   374	393	9036	javax/net/ssl/SSLHandshakeException
    //   9462	9467	9470	java/lang/Exception
    //   9500	9505	9508	java/lang/Throwable
    //   9500	9505	9537	java/lang/ArrayIndexOutOfBoundsException
    //   9500	9505	9566	java/io/IOException
    //   9599	9604	9607	java/io/IOException
    //   374	393	9635	java/io/FileNotFoundException
    //   10061	10066	10069	java/lang/Exception
    //   10099	10104	10107	java/lang/Throwable
    //   10099	10104	10136	java/lang/ArrayIndexOutOfBoundsException
    //   10099	10104	10165	java/io/IOException
    //   10198	10203	10206	java/io/IOException
    //   8661	8685	10234	finally
    //   8731	8752	10234	finally
    //   9260	9284	10234	finally
    //   9330	9351	10234	finally
    //   9859	9883	10234	finally
    //   9929	9950	10234	finally
    //   374	393	10267	java/io/UnsupportedEncodingException
    //   10595	10600	10603	java/lang/Exception
    //   10633	10638	10641	java/lang/Throwable
    //   10633	10638	10670	java/lang/ArrayIndexOutOfBoundsException
    //   10633	10638	10699	java/io/IOException
    //   10732	10737	10740	java/io/IOException
    //   10439	10484	10781	finally
    //   8590	8611	10820	finally
    //   9189	9210	10820	finally
    //   9788	9809	10820	finally
    //   10420	10439	10820	finally
    //   11015	11020	11023	java/lang/Exception
    //   11053	11058	11061	java/lang/Throwable
    //   11053	11058	11090	java/lang/ArrayIndexOutOfBoundsException
    //   11053	11058	11119	java/io/IOException
    //   11149	11154	11157	java/io/IOException
    //   4919	4946	11206	java/lang/Exception
    //   4953	4960	11206	java/lang/Exception
    //   2308	2316	11211	finally
    //   2340	2351	11211	finally
    //   2375	2384	11211	finally
    //   2408	2417	11211	finally
    //   2441	2450	11211	finally
    //   2474	2483	11211	finally
    //   2507	2516	11211	finally
    //   2540	2548	11211	finally
    //   2572	2581	11211	finally
    //   2605	2614	11211	finally
    //   2638	2649	11211	finally
    //   2780	2785	11211	finally
    //   2821	2826	11211	finally
    //   2308	2316	11258	java/lang/Exception
    //   2340	2351	11258	java/lang/Exception
    //   2375	2384	11258	java/lang/Exception
    //   2408	2417	11258	java/lang/Exception
    //   2441	2450	11258	java/lang/Exception
    //   2474	2483	11258	java/lang/Exception
    //   2507	2516	11258	java/lang/Exception
    //   2540	2548	11258	java/lang/Exception
    //   2572	2581	11258	java/lang/Exception
    //   2605	2614	11258	java/lang/Exception
    //   2638	2649	11258	java/lang/Exception
    //   2780	2785	11258	java/lang/Exception
    //   2821	2826	11258	java/lang/Exception
    //   2308	2316	11271	java/net/SocketTimeoutException
    //   2340	2351	11271	java/net/SocketTimeoutException
    //   2375	2384	11271	java/net/SocketTimeoutException
    //   2408	2417	11271	java/net/SocketTimeoutException
    //   2441	2450	11271	java/net/SocketTimeoutException
    //   2474	2483	11271	java/net/SocketTimeoutException
    //   2507	2516	11271	java/net/SocketTimeoutException
    //   2540	2548	11271	java/net/SocketTimeoutException
    //   2572	2581	11271	java/net/SocketTimeoutException
    //   2605	2614	11271	java/net/SocketTimeoutException
    //   2638	2649	11271	java/net/SocketTimeoutException
    //   2780	2785	11271	java/net/SocketTimeoutException
    //   2821	2826	11271	java/net/SocketTimeoutException
    //   2308	2316	11315	javax/net/ssl/SSLHandshakeException
    //   2340	2351	11315	javax/net/ssl/SSLHandshakeException
    //   2375	2384	11315	javax/net/ssl/SSLHandshakeException
    //   2408	2417	11315	javax/net/ssl/SSLHandshakeException
    //   2441	2450	11315	javax/net/ssl/SSLHandshakeException
    //   2474	2483	11315	javax/net/ssl/SSLHandshakeException
    //   2507	2516	11315	javax/net/ssl/SSLHandshakeException
    //   2540	2548	11315	javax/net/ssl/SSLHandshakeException
    //   2572	2581	11315	javax/net/ssl/SSLHandshakeException
    //   2605	2614	11315	javax/net/ssl/SSLHandshakeException
    //   2638	2649	11315	javax/net/ssl/SSLHandshakeException
    //   2780	2785	11315	javax/net/ssl/SSLHandshakeException
    //   2821	2826	11315	javax/net/ssl/SSLHandshakeException
    //   2308	2316	11359	java/io/FileNotFoundException
    //   2340	2351	11359	java/io/FileNotFoundException
    //   2375	2384	11359	java/io/FileNotFoundException
    //   2408	2417	11359	java/io/FileNotFoundException
    //   2441	2450	11359	java/io/FileNotFoundException
    //   2474	2483	11359	java/io/FileNotFoundException
    //   2507	2516	11359	java/io/FileNotFoundException
    //   2540	2548	11359	java/io/FileNotFoundException
    //   2572	2581	11359	java/io/FileNotFoundException
    //   2605	2614	11359	java/io/FileNotFoundException
    //   2638	2649	11359	java/io/FileNotFoundException
    //   2780	2785	11359	java/io/FileNotFoundException
    //   2821	2826	11359	java/io/FileNotFoundException
    //   2308	2316	11403	java/io/UnsupportedEncodingException
    //   2340	2351	11403	java/io/UnsupportedEncodingException
    //   2375	2384	11403	java/io/UnsupportedEncodingException
    //   2408	2417	11403	java/io/UnsupportedEncodingException
    //   2441	2450	11403	java/io/UnsupportedEncodingException
    //   2474	2483	11403	java/io/UnsupportedEncodingException
    //   2507	2516	11403	java/io/UnsupportedEncodingException
    //   2540	2548	11403	java/io/UnsupportedEncodingException
    //   2572	2581	11403	java/io/UnsupportedEncodingException
    //   2605	2614	11403	java/io/UnsupportedEncodingException
    //   2638	2649	11403	java/io/UnsupportedEncodingException
    //   2780	2785	11403	java/io/UnsupportedEncodingException
    //   2821	2826	11403	java/io/UnsupportedEncodingException
    //   3571	3587	11447	finally
    //   3592	3627	11447	finally
    //   3571	3587	11452	java/lang/Exception
    //   3592	3627	11452	java/lang/Exception
    //   3571	3587	11497	java/net/SocketTimeoutException
    //   3592	3627	11497	java/net/SocketTimeoutException
    //   3571	3587	11526	javax/net/ssl/SSLHandshakeException
    //   3592	3627	11526	javax/net/ssl/SSLHandshakeException
    //   3571	3587	11555	java/io/FileNotFoundException
    //   3592	3627	11555	java/io/FileNotFoundException
    //   3571	3587	11584	java/io/UnsupportedEncodingException
    //   3592	3627	11584	java/io/UnsupportedEncodingException
  }
  
  public void run()
  {
    a(this.b);
  }
}


/* Location:           L:\local\mybackup\temp\qq_apk\com.tencent.mobileqq\classes5.jar
 * Qualified Name:     com.tencent.luggage.wxa.nz.g.b
 * JD-Core Version:    0.7.0.1
 */