import android.graphics.Bitmap;
import com.tencent.biz.webviewplugin.Share;

public class bpc
  extends Thread
{
  public bpc(Share paramShare, String paramString, boolean paramBoolean, Bitmap paramBitmap, int paramInt) {}
  
  /* Error */
  public void run()
  {
    // Byte code:
    //   0: aconst_null
    //   1: astore 30
    //   3: aconst_null
    //   4: astore 31
    //   6: aconst_null
    //   7: astore 32
    //   9: aconst_null
    //   10: astore 33
    //   12: aconst_null
    //   13: astore 29
    //   15: aconst_null
    //   16: astore 34
    //   18: ldc 37
    //   20: iconst_2
    //   21: anewarray 39	java/lang/Object
    //   24: dup
    //   25: iconst_0
    //   26: aload_0
    //   27: getfield 14	bpc:jdField_a_of_type_ComTencentBizWebviewpluginShare	Lcom/tencent/biz/webviewplugin/Share;
    //   30: getfield 44	com/tencent/biz/webviewplugin/Share:k	Ljava/lang/String;
    //   33: aastore
    //   34: dup
    //   35: iconst_1
    //   36: aload_0
    //   37: getfield 16	bpc:jdField_a_of_type_JavaLangString	Ljava/lang/String;
    //   40: invokestatic 50	java/net/URLEncoder:encode	(Ljava/lang/String;)Ljava/lang/String;
    //   43: aastore
    //   44: invokestatic 56	java/lang/String:format	(Ljava/lang/String;[Ljava/lang/Object;)Ljava/lang/String;
    //   47: astore 35
    //   49: ldc 58
    //   51: astore 6
    //   53: ldc 58
    //   55: astore 8
    //   57: ldc 58
    //   59: astore 7
    //   61: ldc 58
    //   63: astore 5
    //   65: aload 8
    //   67: astore 10
    //   69: aload 6
    //   71: astore 14
    //   73: aload 5
    //   75: astore 19
    //   77: aload 7
    //   79: astore 24
    //   81: aload 8
    //   83: astore 11
    //   85: aload 6
    //   87: astore 15
    //   89: aload 5
    //   91: astore 20
    //   93: aload 7
    //   95: astore 25
    //   97: aload 8
    //   99: astore 12
    //   101: aload 6
    //   103: astore 16
    //   105: aload 5
    //   107: astore 21
    //   109: aload 7
    //   111: astore 26
    //   113: aload 8
    //   115: astore 17
    //   117: aload 6
    //   119: astore 22
    //   121: aload 5
    //   123: astore 27
    //   125: aload 7
    //   127: astore 28
    //   129: aload 8
    //   131: astore 9
    //   133: aload 6
    //   135: astore 13
    //   137: aload 5
    //   139: astore 18
    //   141: aload 7
    //   143: astore 23
    //   145: new 60	org/json/JSONObject
    //   148: dup
    //   149: invokestatic 66	com/tencent/qphone/base/util/BaseApplication:getContext	()Landroid/content/Context;
    //   152: aload 35
    //   154: ldc 68
    //   156: aconst_null
    //   157: aconst_null
    //   158: invokestatic 73	com/tencent/biz/common/util/HttpUtil:a	(Landroid/content/Context;Ljava/lang/String;Ljava/lang/String;Landroid/os/Bundle;Landroid/os/Bundle;)Ljava/lang/String;
    //   161: invokespecial 76	org/json/JSONObject:<init>	(Ljava/lang/String;)V
    //   164: astore 35
    //   166: aload 8
    //   168: astore 10
    //   170: aload 6
    //   172: astore 14
    //   174: aload 5
    //   176: astore 19
    //   178: aload 7
    //   180: astore 24
    //   182: aload 8
    //   184: astore 11
    //   186: aload 6
    //   188: astore 15
    //   190: aload 5
    //   192: astore 20
    //   194: aload 7
    //   196: astore 25
    //   198: aload 8
    //   200: astore 12
    //   202: aload 6
    //   204: astore 16
    //   206: aload 5
    //   208: astore 21
    //   210: aload 7
    //   212: astore 26
    //   214: aload 8
    //   216: astore 17
    //   218: aload 6
    //   220: astore 22
    //   222: aload 5
    //   224: astore 27
    //   226: aload 7
    //   228: astore 28
    //   230: aload 8
    //   232: astore 9
    //   234: aload 6
    //   236: astore 13
    //   238: aload 5
    //   240: astore 18
    //   242: aload 7
    //   244: astore 23
    //   246: aload 35
    //   248: ldc 78
    //   250: invokevirtual 81	org/json/JSONObject:optString	(Ljava/lang/String;)Ljava/lang/String;
    //   253: astore 5
    //   255: aload 8
    //   257: astore 10
    //   259: aload 6
    //   261: astore 14
    //   263: aload 5
    //   265: astore 19
    //   267: aload 7
    //   269: astore 24
    //   271: aload 8
    //   273: astore 11
    //   275: aload 6
    //   277: astore 15
    //   279: aload 5
    //   281: astore 20
    //   283: aload 7
    //   285: astore 25
    //   287: aload 8
    //   289: astore 12
    //   291: aload 6
    //   293: astore 16
    //   295: aload 5
    //   297: astore 21
    //   299: aload 7
    //   301: astore 26
    //   303: aload 8
    //   305: astore 17
    //   307: aload 6
    //   309: astore 22
    //   311: aload 5
    //   313: astore 27
    //   315: aload 7
    //   317: astore 28
    //   319: aload 8
    //   321: astore 9
    //   323: aload 6
    //   325: astore 13
    //   327: aload 5
    //   329: astore 18
    //   331: aload 7
    //   333: astore 23
    //   335: aload 35
    //   337: ldc 83
    //   339: invokevirtual 86	org/json/JSONObject:getString	(Ljava/lang/String;)Ljava/lang/String;
    //   342: astore 6
    //   344: aload 8
    //   346: astore 10
    //   348: aload 6
    //   350: astore 14
    //   352: aload 5
    //   354: astore 19
    //   356: aload 7
    //   358: astore 24
    //   360: aload 8
    //   362: astore 11
    //   364: aload 6
    //   366: astore 15
    //   368: aload 5
    //   370: astore 20
    //   372: aload 7
    //   374: astore 25
    //   376: aload 8
    //   378: astore 12
    //   380: aload 6
    //   382: astore 16
    //   384: aload 5
    //   386: astore 21
    //   388: aload 7
    //   390: astore 26
    //   392: aload 8
    //   394: astore 17
    //   396: aload 6
    //   398: astore 22
    //   400: aload 5
    //   402: astore 27
    //   404: aload 7
    //   406: astore 28
    //   408: aload 8
    //   410: astore 9
    //   412: aload 6
    //   414: astore 13
    //   416: aload 5
    //   418: astore 18
    //   420: aload 7
    //   422: astore 23
    //   424: aload 35
    //   426: ldc 88
    //   428: invokevirtual 86	org/json/JSONObject:getString	(Ljava/lang/String;)Ljava/lang/String;
    //   431: astore 8
    //   433: aload 8
    //   435: astore 10
    //   437: aload 6
    //   439: astore 14
    //   441: aload 5
    //   443: astore 19
    //   445: aload 7
    //   447: astore 24
    //   449: aload 8
    //   451: astore 11
    //   453: aload 6
    //   455: astore 15
    //   457: aload 5
    //   459: astore 20
    //   461: aload 7
    //   463: astore 25
    //   465: aload 8
    //   467: astore 12
    //   469: aload 6
    //   471: astore 16
    //   473: aload 5
    //   475: astore 21
    //   477: aload 7
    //   479: astore 26
    //   481: aload 8
    //   483: astore 17
    //   485: aload 6
    //   487: astore 22
    //   489: aload 5
    //   491: astore 27
    //   493: aload 7
    //   495: astore 28
    //   497: aload 8
    //   499: astore 9
    //   501: aload 6
    //   503: astore 13
    //   505: aload 5
    //   507: astore 18
    //   509: aload 7
    //   511: astore 23
    //   513: aload 35
    //   515: ldc 90
    //   517: invokevirtual 86	org/json/JSONObject:getString	(Ljava/lang/String;)Ljava/lang/String;
    //   520: astore 7
    //   522: aload 8
    //   524: astore 10
    //   526: aload 6
    //   528: astore 14
    //   530: aload 5
    //   532: astore 19
    //   534: aload 7
    //   536: astore 24
    //   538: aload 8
    //   540: astore 11
    //   542: aload 6
    //   544: astore 15
    //   546: aload 5
    //   548: astore 20
    //   550: aload 7
    //   552: astore 25
    //   554: aload 8
    //   556: astore 12
    //   558: aload 6
    //   560: astore 16
    //   562: aload 5
    //   564: astore 21
    //   566: aload 7
    //   568: astore 26
    //   570: aload 8
    //   572: astore 17
    //   574: aload 6
    //   576: astore 22
    //   578: aload 5
    //   580: astore 27
    //   582: aload 7
    //   584: astore 28
    //   586: aload 8
    //   588: astore 9
    //   590: aload 6
    //   592: astore 13
    //   594: aload 5
    //   596: astore 18
    //   598: aload 7
    //   600: astore 23
    //   602: aload_0
    //   603: getfield 18	bpc:jdField_a_of_type_Boolean	Z
    //   606: ifeq +752 -> 1358
    //   609: aload 8
    //   611: astore 10
    //   613: aload 6
    //   615: astore 14
    //   617: aload 5
    //   619: astore 19
    //   621: aload 7
    //   623: astore 24
    //   625: aload 8
    //   627: astore 11
    //   629: aload 6
    //   631: astore 15
    //   633: aload 5
    //   635: astore 20
    //   637: aload 7
    //   639: astore 25
    //   641: aload 8
    //   643: astore 12
    //   645: aload 6
    //   647: astore 16
    //   649: aload 5
    //   651: astore 21
    //   653: aload 7
    //   655: astore 26
    //   657: aload 8
    //   659: astore 17
    //   661: aload 6
    //   663: astore 22
    //   665: aload 5
    //   667: astore 27
    //   669: aload 7
    //   671: astore 28
    //   673: aload 8
    //   675: astore 9
    //   677: aload 6
    //   679: astore 13
    //   681: aload 5
    //   683: astore 18
    //   685: aload 7
    //   687: astore 23
    //   689: aload_0
    //   690: getfield 20	bpc:jdField_a_of_type_AndroidGraphicsBitmap	Landroid/graphics/Bitmap;
    //   693: ifnonnull +665 -> 1358
    //   696: aload 8
    //   698: astore 10
    //   700: aload 6
    //   702: astore 14
    //   704: aload 5
    //   706: astore 19
    //   708: aload 7
    //   710: astore 24
    //   712: aload 8
    //   714: astore 11
    //   716: aload 6
    //   718: astore 15
    //   720: aload 5
    //   722: astore 20
    //   724: aload 7
    //   726: astore 25
    //   728: aload 8
    //   730: astore 12
    //   732: aload 6
    //   734: astore 16
    //   736: aload 5
    //   738: astore 21
    //   740: aload 7
    //   742: astore 26
    //   744: aload 8
    //   746: astore 17
    //   748: aload 6
    //   750: astore 22
    //   752: aload 5
    //   754: astore 27
    //   756: aload 7
    //   758: astore 28
    //   760: aload 8
    //   762: astore 9
    //   764: aload 6
    //   766: astore 13
    //   768: aload 5
    //   770: astore 18
    //   772: aload 7
    //   774: astore 23
    //   776: aload 7
    //   778: invokestatic 96	android/text/TextUtils:isEmpty	(Ljava/lang/CharSequence;)Z
    //   781: ifne +577 -> 1358
    //   784: aload 8
    //   786: astore 10
    //   788: aload 6
    //   790: astore 14
    //   792: aload 5
    //   794: astore 19
    //   796: aload 7
    //   798: astore 24
    //   800: aload 8
    //   802: astore 11
    //   804: aload 6
    //   806: astore 15
    //   808: aload 5
    //   810: astore 20
    //   812: aload 7
    //   814: astore 25
    //   816: aload 8
    //   818: astore 12
    //   820: aload 6
    //   822: astore 16
    //   824: aload 5
    //   826: astore 21
    //   828: aload 7
    //   830: astore 26
    //   832: aload 8
    //   834: astore 17
    //   836: aload 6
    //   838: astore 22
    //   840: aload 5
    //   842: astore 27
    //   844: aload 7
    //   846: astore 28
    //   848: aload 8
    //   850: astore 9
    //   852: aload 6
    //   854: astore 13
    //   856: aload 5
    //   858: astore 18
    //   860: aload 7
    //   862: astore 23
    //   864: invokestatic 66	com/tencent/qphone/base/util/BaseApplication:getContext	()Landroid/content/Context;
    //   867: aload 7
    //   869: ldc 68
    //   871: aconst_null
    //   872: aconst_null
    //   873: invokestatic 99	com/tencent/biz/common/util/HttpUtil:a	(Landroid/content/Context;Ljava/lang/String;Ljava/lang/String;Landroid/os/Bundle;Landroid/os/Bundle;)[B
    //   876: astore 35
    //   878: aload 8
    //   880: astore 10
    //   882: aload 6
    //   884: astore 14
    //   886: aload 5
    //   888: astore 19
    //   890: aload 7
    //   892: astore 24
    //   894: aload 8
    //   896: astore 11
    //   898: aload 6
    //   900: astore 15
    //   902: aload 5
    //   904: astore 20
    //   906: aload 7
    //   908: astore 25
    //   910: aload 8
    //   912: astore 12
    //   914: aload 6
    //   916: astore 16
    //   918: aload 5
    //   920: astore 21
    //   922: aload 7
    //   924: astore 26
    //   926: aload 8
    //   928: astore 17
    //   930: aload 6
    //   932: astore 22
    //   934: aload 5
    //   936: astore 27
    //   938: aload 7
    //   940: astore 28
    //   942: aload 8
    //   944: astore 9
    //   946: aload 6
    //   948: astore 13
    //   950: aload 5
    //   952: astore 18
    //   954: aload 7
    //   956: astore 23
    //   958: aload 35
    //   960: iconst_0
    //   961: aload 35
    //   963: arraylength
    //   964: invokestatic 105	android/graphics/BitmapFactory:decodeByteArray	([BII)Landroid/graphics/Bitmap;
    //   967: astore 35
    //   969: aload 35
    //   971: astore 9
    //   973: aload 9
    //   975: astore 10
    //   977: aload 9
    //   979: ifnull +299 -> 1278
    //   982: aload 9
    //   984: astore 11
    //   986: aload 8
    //   988: astore 15
    //   990: aload 6
    //   992: astore 14
    //   994: aload 5
    //   996: astore 13
    //   998: aload 7
    //   1000: astore 12
    //   1002: aload 9
    //   1004: astore 16
    //   1006: aload 9
    //   1008: astore 17
    //   1010: aload 9
    //   1012: astore 18
    //   1014: aload 9
    //   1016: astore 19
    //   1018: aload 9
    //   1020: invokevirtual 111	android/graphics/Bitmap:getWidth	()I
    //   1023: istore_3
    //   1024: aload 9
    //   1026: astore 11
    //   1028: aload 8
    //   1030: astore 15
    //   1032: aload 6
    //   1034: astore 14
    //   1036: aload 5
    //   1038: astore 13
    //   1040: aload 7
    //   1042: astore 12
    //   1044: aload 9
    //   1046: astore 16
    //   1048: aload 9
    //   1050: astore 17
    //   1052: aload 9
    //   1054: astore 18
    //   1056: aload 9
    //   1058: astore 19
    //   1060: aload 9
    //   1062: invokevirtual 114	android/graphics/Bitmap:getHeight	()I
    //   1065: istore 4
    //   1067: aload 9
    //   1069: astore 10
    //   1071: iload_3
    //   1072: iload 4
    //   1074: imul
    //   1075: sipush 8000
    //   1078: if_icmple +148 -> 1226
    //   1081: aload 9
    //   1083: astore 11
    //   1085: aload 8
    //   1087: astore 15
    //   1089: aload 6
    //   1091: astore 14
    //   1093: aload 5
    //   1095: astore 13
    //   1097: aload 7
    //   1099: astore 12
    //   1101: aload 9
    //   1103: astore 16
    //   1105: aload 9
    //   1107: astore 17
    //   1109: aload 9
    //   1111: astore 18
    //   1113: aload 9
    //   1115: astore 19
    //   1117: ldc2_w 115
    //   1120: iload_3
    //   1121: iload 4
    //   1123: imul
    //   1124: i2d
    //   1125: ddiv
    //   1126: invokestatic 122	java/lang/Math:sqrt	(D)D
    //   1129: dstore_1
    //   1130: aload 9
    //   1132: astore 11
    //   1134: aload 8
    //   1136: astore 15
    //   1138: aload 6
    //   1140: astore 14
    //   1142: aload 5
    //   1144: astore 13
    //   1146: aload 7
    //   1148: astore 12
    //   1150: aload 9
    //   1152: astore 16
    //   1154: aload 9
    //   1156: astore 17
    //   1158: aload 9
    //   1160: astore 18
    //   1162: aload 9
    //   1164: astore 19
    //   1166: aload 9
    //   1168: iload_3
    //   1169: i2d
    //   1170: dload_1
    //   1171: dmul
    //   1172: d2i
    //   1173: iload 4
    //   1175: i2d
    //   1176: dload_1
    //   1177: dmul
    //   1178: d2i
    //   1179: iconst_1
    //   1180: invokestatic 126	android/graphics/Bitmap:createScaledBitmap	(Landroid/graphics/Bitmap;IIZ)Landroid/graphics/Bitmap;
    //   1183: astore 10
    //   1185: aload 9
    //   1187: astore 11
    //   1189: aload 8
    //   1191: astore 15
    //   1193: aload 6
    //   1195: astore 14
    //   1197: aload 5
    //   1199: astore 13
    //   1201: aload 7
    //   1203: astore 12
    //   1205: aload 9
    //   1207: astore 16
    //   1209: aload 9
    //   1211: astore 17
    //   1213: aload 9
    //   1215: astore 18
    //   1217: aload 9
    //   1219: astore 19
    //   1221: aload 9
    //   1223: invokevirtual 129	android/graphics/Bitmap:recycle	()V
    //   1226: aload 10
    //   1228: astore 11
    //   1230: aload 8
    //   1232: astore 15
    //   1234: aload 6
    //   1236: astore 14
    //   1238: aload 5
    //   1240: astore 13
    //   1242: aload 7
    //   1244: astore 12
    //   1246: aload 10
    //   1248: astore 16
    //   1250: aload 10
    //   1252: astore 17
    //   1254: aload 10
    //   1256: astore 18
    //   1258: aload 10
    //   1260: astore 19
    //   1262: aload_0
    //   1263: getfield 14	bpc:jdField_a_of_type_ComTencentBizWebviewpluginShare	Lcom/tencent/biz/webviewplugin/Share;
    //   1266: new 131	java/lang/ref/WeakReference
    //   1269: dup
    //   1270: aload 10
    //   1272: invokespecial 134	java/lang/ref/WeakReference:<init>	(Ljava/lang/Object;)V
    //   1275: putfield 137	com/tencent/biz/webviewplugin/Share:jdField_a_of_type_JavaLangRefWeakReference	Ljava/lang/ref/WeakReference;
    //   1278: aload 6
    //   1280: astore 9
    //   1282: aload 6
    //   1284: invokestatic 96	android/text/TextUtils:isEmpty	(Ljava/lang/CharSequence;)Z
    //   1287: ifeq +9 -> 1296
    //   1290: aload_0
    //   1291: getfield 16	bpc:jdField_a_of_type_JavaLangString	Ljava/lang/String;
    //   1294: astore 9
    //   1296: aload 5
    //   1298: astore 6
    //   1300: aload 5
    //   1302: invokestatic 96	android/text/TextUtils:isEmpty	(Ljava/lang/CharSequence;)Z
    //   1305: ifeq +9 -> 1314
    //   1308: aload_0
    //   1309: getfield 16	bpc:jdField_a_of_type_JavaLangString	Ljava/lang/String;
    //   1312: astore 6
    //   1314: aload 34
    //   1316: astore 5
    //   1318: aload_0
    //   1319: getfield 18	bpc:jdField_a_of_type_Boolean	Z
    //   1322: ifeq +7 -> 1329
    //   1325: aload 10
    //   1327: astore 5
    //   1329: aload_0
    //   1330: getfield 14	bpc:jdField_a_of_type_ComTencentBizWebviewpluginShare	Lcom/tencent/biz/webviewplugin/Share;
    //   1333: getfield 140	com/tencent/biz/webviewplugin/Share:jdField_a_of_type_ComTencentMobileqqActivityQQBrowserActivity	Lcom/tencent/mobileqq/activity/QQBrowserActivity;
    //   1336: new 142	bpd
    //   1339: dup
    //   1340: aload_0
    //   1341: aload 8
    //   1343: aload 9
    //   1345: aload 6
    //   1347: aload 7
    //   1349: aload 5
    //   1351: invokespecial 145	bpd:<init>	(Lbpc;Ljava/lang/String;Ljava/lang/String;Ljava/lang/String;Ljava/lang/String;Landroid/graphics/Bitmap;)V
    //   1354: invokevirtual 151	com/tencent/mobileqq/activity/QQBrowserActivity:runOnUiThread	(Ljava/lang/Runnable;)V
    //   1357: return
    //   1358: aload 8
    //   1360: astore 10
    //   1362: aload 6
    //   1364: astore 14
    //   1366: aload 5
    //   1368: astore 19
    //   1370: aload 7
    //   1372: astore 24
    //   1374: aload 8
    //   1376: astore 11
    //   1378: aload 6
    //   1380: astore 15
    //   1382: aload 5
    //   1384: astore 20
    //   1386: aload 7
    //   1388: astore 25
    //   1390: aload 8
    //   1392: astore 12
    //   1394: aload 6
    //   1396: astore 16
    //   1398: aload 5
    //   1400: astore 21
    //   1402: aload 7
    //   1404: astore 26
    //   1406: aload 8
    //   1408: astore 17
    //   1410: aload 6
    //   1412: astore 22
    //   1414: aload 5
    //   1416: astore 27
    //   1418: aload 7
    //   1420: astore 28
    //   1422: aload 8
    //   1424: astore 9
    //   1426: aload 6
    //   1428: astore 13
    //   1430: aload 5
    //   1432: astore 18
    //   1434: aload 7
    //   1436: astore 23
    //   1438: aload_0
    //   1439: getfield 20	bpc:jdField_a_of_type_AndroidGraphicsBitmap	Landroid/graphics/Bitmap;
    //   1442: astore 35
    //   1444: aload 35
    //   1446: astore 10
    //   1448: goto -170 -> 1278
    //   1451: astore 9
    //   1453: aconst_null
    //   1454: astore 11
    //   1456: aload 24
    //   1458: astore 7
    //   1460: aload 19
    //   1462: astore 5
    //   1464: aload 14
    //   1466: astore 6
    //   1468: aload 10
    //   1470: astore 8
    //   1472: aload 9
    //   1474: astore 10
    //   1476: aload 11
    //   1478: astore 9
    //   1480: aload 9
    //   1482: astore 11
    //   1484: aload 8
    //   1486: astore 15
    //   1488: aload 6
    //   1490: astore 14
    //   1492: aload 5
    //   1494: astore 13
    //   1496: aload 7
    //   1498: astore 12
    //   1500: aload 10
    //   1502: invokevirtual 154	java/lang/IllegalArgumentException:printStackTrace	()V
    //   1505: aload 6
    //   1507: astore 10
    //   1509: aload 6
    //   1511: invokestatic 96	android/text/TextUtils:isEmpty	(Ljava/lang/CharSequence;)Z
    //   1514: ifeq +9 -> 1523
    //   1517: aload_0
    //   1518: getfield 16	bpc:jdField_a_of_type_JavaLangString	Ljava/lang/String;
    //   1521: astore 10
    //   1523: aload 5
    //   1525: astore 6
    //   1527: aload 5
    //   1529: invokestatic 96	android/text/TextUtils:isEmpty	(Ljava/lang/CharSequence;)Z
    //   1532: ifeq +9 -> 1541
    //   1535: aload_0
    //   1536: getfield 16	bpc:jdField_a_of_type_JavaLangString	Ljava/lang/String;
    //   1539: astore 6
    //   1541: aload 30
    //   1543: astore 5
    //   1545: aload_0
    //   1546: getfield 18	bpc:jdField_a_of_type_Boolean	Z
    //   1549: ifeq +7 -> 1556
    //   1552: aload 9
    //   1554: astore 5
    //   1556: aload_0
    //   1557: getfield 14	bpc:jdField_a_of_type_ComTencentBizWebviewpluginShare	Lcom/tencent/biz/webviewplugin/Share;
    //   1560: getfield 140	com/tencent/biz/webviewplugin/Share:jdField_a_of_type_ComTencentMobileqqActivityQQBrowserActivity	Lcom/tencent/mobileqq/activity/QQBrowserActivity;
    //   1563: new 142	bpd
    //   1566: dup
    //   1567: aload_0
    //   1568: aload 8
    //   1570: aload 10
    //   1572: aload 6
    //   1574: aload 7
    //   1576: aload 5
    //   1578: invokespecial 145	bpd:<init>	(Lbpc;Ljava/lang/String;Ljava/lang/String;Ljava/lang/String;Ljava/lang/String;Landroid/graphics/Bitmap;)V
    //   1581: invokevirtual 151	com/tencent/mobileqq/activity/QQBrowserActivity:runOnUiThread	(Ljava/lang/Runnable;)V
    //   1584: return
    //   1585: astore 10
    //   1587: aconst_null
    //   1588: astore 9
    //   1590: aload 25
    //   1592: astore 7
    //   1594: aload 20
    //   1596: astore 5
    //   1598: aload 15
    //   1600: astore 6
    //   1602: aload 11
    //   1604: astore 8
    //   1606: aload 9
    //   1608: astore 11
    //   1610: aload 8
    //   1612: astore 15
    //   1614: aload 6
    //   1616: astore 14
    //   1618: aload 5
    //   1620: astore 13
    //   1622: aload 7
    //   1624: astore 12
    //   1626: aload 10
    //   1628: invokevirtual 155	java/io/IOException:printStackTrace	()V
    //   1631: aload 6
    //   1633: astore 10
    //   1635: aload 6
    //   1637: invokestatic 96	android/text/TextUtils:isEmpty	(Ljava/lang/CharSequence;)Z
    //   1640: ifeq +9 -> 1649
    //   1643: aload_0
    //   1644: getfield 16	bpc:jdField_a_of_type_JavaLangString	Ljava/lang/String;
    //   1647: astore 10
    //   1649: aload 5
    //   1651: astore 6
    //   1653: aload 5
    //   1655: invokestatic 96	android/text/TextUtils:isEmpty	(Ljava/lang/CharSequence;)Z
    //   1658: ifeq +9 -> 1667
    //   1661: aload_0
    //   1662: getfield 16	bpc:jdField_a_of_type_JavaLangString	Ljava/lang/String;
    //   1665: astore 6
    //   1667: aload 31
    //   1669: astore 5
    //   1671: aload_0
    //   1672: getfield 18	bpc:jdField_a_of_type_Boolean	Z
    //   1675: ifeq +7 -> 1682
    //   1678: aload 9
    //   1680: astore 5
    //   1682: aload_0
    //   1683: getfield 14	bpc:jdField_a_of_type_ComTencentBizWebviewpluginShare	Lcom/tencent/biz/webviewplugin/Share;
    //   1686: getfield 140	com/tencent/biz/webviewplugin/Share:jdField_a_of_type_ComTencentMobileqqActivityQQBrowserActivity	Lcom/tencent/mobileqq/activity/QQBrowserActivity;
    //   1689: new 142	bpd
    //   1692: dup
    //   1693: aload_0
    //   1694: aload 8
    //   1696: aload 10
    //   1698: aload 6
    //   1700: aload 7
    //   1702: aload 5
    //   1704: invokespecial 145	bpd:<init>	(Lbpc;Ljava/lang/String;Ljava/lang/String;Ljava/lang/String;Ljava/lang/String;Landroid/graphics/Bitmap;)V
    //   1707: invokevirtual 151	com/tencent/mobileqq/activity/QQBrowserActivity:runOnUiThread	(Ljava/lang/Runnable;)V
    //   1710: return
    //   1711: astore 10
    //   1713: aconst_null
    //   1714: astore 9
    //   1716: aload 26
    //   1718: astore 7
    //   1720: aload 21
    //   1722: astore 5
    //   1724: aload 16
    //   1726: astore 6
    //   1728: aload 12
    //   1730: astore 8
    //   1732: aload 9
    //   1734: astore 11
    //   1736: aload 8
    //   1738: astore 15
    //   1740: aload 6
    //   1742: astore 14
    //   1744: aload 5
    //   1746: astore 13
    //   1748: aload 7
    //   1750: astore 12
    //   1752: aload 10
    //   1754: invokevirtual 156	org/json/JSONException:printStackTrace	()V
    //   1757: aload 6
    //   1759: astore 10
    //   1761: aload 6
    //   1763: invokestatic 96	android/text/TextUtils:isEmpty	(Ljava/lang/CharSequence;)Z
    //   1766: ifeq +9 -> 1775
    //   1769: aload_0
    //   1770: getfield 16	bpc:jdField_a_of_type_JavaLangString	Ljava/lang/String;
    //   1773: astore 10
    //   1775: aload 5
    //   1777: astore 6
    //   1779: aload 5
    //   1781: invokestatic 96	android/text/TextUtils:isEmpty	(Ljava/lang/CharSequence;)Z
    //   1784: ifeq +9 -> 1793
    //   1787: aload_0
    //   1788: getfield 16	bpc:jdField_a_of_type_JavaLangString	Ljava/lang/String;
    //   1791: astore 6
    //   1793: aload 32
    //   1795: astore 5
    //   1797: aload_0
    //   1798: getfield 18	bpc:jdField_a_of_type_Boolean	Z
    //   1801: ifeq +7 -> 1808
    //   1804: aload 9
    //   1806: astore 5
    //   1808: aload_0
    //   1809: getfield 14	bpc:jdField_a_of_type_ComTencentBizWebviewpluginShare	Lcom/tencent/biz/webviewplugin/Share;
    //   1812: getfield 140	com/tencent/biz/webviewplugin/Share:jdField_a_of_type_ComTencentMobileqqActivityQQBrowserActivity	Lcom/tencent/mobileqq/activity/QQBrowserActivity;
    //   1815: new 142	bpd
    //   1818: dup
    //   1819: aload_0
    //   1820: aload 8
    //   1822: aload 10
    //   1824: aload 6
    //   1826: aload 7
    //   1828: aload 5
    //   1830: invokespecial 145	bpd:<init>	(Lbpc;Ljava/lang/String;Ljava/lang/String;Ljava/lang/String;Ljava/lang/String;Landroid/graphics/Bitmap;)V
    //   1833: invokevirtual 151	com/tencent/mobileqq/activity/QQBrowserActivity:runOnUiThread	(Ljava/lang/Runnable;)V
    //   1836: return
    //   1837: astore 5
    //   1839: aconst_null
    //   1840: astore 16
    //   1842: aload 28
    //   1844: astore 7
    //   1846: aload 27
    //   1848: astore 5
    //   1850: aload 22
    //   1852: astore 6
    //   1854: aload 17
    //   1856: astore 8
    //   1858: aload 6
    //   1860: astore 9
    //   1862: aload 6
    //   1864: invokestatic 96	android/text/TextUtils:isEmpty	(Ljava/lang/CharSequence;)Z
    //   1867: ifeq +9 -> 1876
    //   1870: aload_0
    //   1871: getfield 16	bpc:jdField_a_of_type_JavaLangString	Ljava/lang/String;
    //   1874: astore 9
    //   1876: aload 5
    //   1878: astore 6
    //   1880: aload 5
    //   1882: invokestatic 96	android/text/TextUtils:isEmpty	(Ljava/lang/CharSequence;)Z
    //   1885: ifeq +9 -> 1894
    //   1888: aload_0
    //   1889: getfield 16	bpc:jdField_a_of_type_JavaLangString	Ljava/lang/String;
    //   1892: astore 6
    //   1894: aload 33
    //   1896: astore 5
    //   1898: aload_0
    //   1899: getfield 18	bpc:jdField_a_of_type_Boolean	Z
    //   1902: ifeq +7 -> 1909
    //   1905: aload 16
    //   1907: astore 5
    //   1909: aload_0
    //   1910: getfield 14	bpc:jdField_a_of_type_ComTencentBizWebviewpluginShare	Lcom/tencent/biz/webviewplugin/Share;
    //   1913: getfield 140	com/tencent/biz/webviewplugin/Share:jdField_a_of_type_ComTencentMobileqqActivityQQBrowserActivity	Lcom/tencent/mobileqq/activity/QQBrowserActivity;
    //   1916: new 142	bpd
    //   1919: dup
    //   1920: aload_0
    //   1921: aload 8
    //   1923: aload 9
    //   1925: aload 6
    //   1927: aload 7
    //   1929: aload 5
    //   1931: invokespecial 145	bpd:<init>	(Lbpc;Ljava/lang/String;Ljava/lang/String;Ljava/lang/String;Ljava/lang/String;Landroid/graphics/Bitmap;)V
    //   1934: invokevirtual 151	com/tencent/mobileqq/activity/QQBrowserActivity:runOnUiThread	(Ljava/lang/Runnable;)V
    //   1937: return
    //   1938: astore 5
    //   1940: aconst_null
    //   1941: astore 11
    //   1943: aload 23
    //   1945: astore 12
    //   1947: aload 13
    //   1949: astore 14
    //   1951: aload 14
    //   1953: astore 6
    //   1955: aload 14
    //   1957: invokestatic 96	android/text/TextUtils:isEmpty	(Ljava/lang/CharSequence;)Z
    //   1960: ifeq +9 -> 1969
    //   1963: aload_0
    //   1964: getfield 16	bpc:jdField_a_of_type_JavaLangString	Ljava/lang/String;
    //   1967: astore 6
    //   1969: aload 18
    //   1971: astore 7
    //   1973: aload 18
    //   1975: invokestatic 96	android/text/TextUtils:isEmpty	(Ljava/lang/CharSequence;)Z
    //   1978: ifeq +9 -> 1987
    //   1981: aload_0
    //   1982: getfield 16	bpc:jdField_a_of_type_JavaLangString	Ljava/lang/String;
    //   1985: astore 7
    //   1987: aload 29
    //   1989: astore 8
    //   1991: aload_0
    //   1992: getfield 18	bpc:jdField_a_of_type_Boolean	Z
    //   1995: ifeq +7 -> 2002
    //   1998: aload 11
    //   2000: astore 8
    //   2002: aload_0
    //   2003: getfield 14	bpc:jdField_a_of_type_ComTencentBizWebviewpluginShare	Lcom/tencent/biz/webviewplugin/Share;
    //   2006: getfield 140	com/tencent/biz/webviewplugin/Share:jdField_a_of_type_ComTencentMobileqqActivityQQBrowserActivity	Lcom/tencent/mobileqq/activity/QQBrowserActivity;
    //   2009: new 142	bpd
    //   2012: dup
    //   2013: aload_0
    //   2014: aload 9
    //   2016: aload 6
    //   2018: aload 7
    //   2020: aload 12
    //   2022: aload 8
    //   2024: invokespecial 145	bpd:<init>	(Lbpc;Ljava/lang/String;Ljava/lang/String;Ljava/lang/String;Ljava/lang/String;Landroid/graphics/Bitmap;)V
    //   2027: invokevirtual 151	com/tencent/mobileqq/activity/QQBrowserActivity:runOnUiThread	(Ljava/lang/Runnable;)V
    //   2030: aload 5
    //   2032: athrow
    //   2033: astore 5
    //   2035: aload 15
    //   2037: astore 9
    //   2039: aload 13
    //   2041: astore 18
    //   2043: goto -92 -> 1951
    //   2046: astore 9
    //   2048: goto -190 -> 1858
    //   2051: astore 10
    //   2053: aload 17
    //   2055: astore 9
    //   2057: goto -325 -> 1732
    //   2060: astore 10
    //   2062: aload 18
    //   2064: astore 9
    //   2066: goto -460 -> 1606
    //   2069: astore 10
    //   2071: aload 19
    //   2073: astore 9
    //   2075: goto -595 -> 1480
    // Local variable table:
    //   start	length	slot	name	signature
    //   0	2078	0	this	bpc
    //   1129	48	1	d	double
    //   1023	146	3	i	int
    //   1065	109	4	j	int
    //   63	1766	5	localObject1	java.lang.Object
    //   1837	1	5	localOutOfMemoryError1	java.lang.OutOfMemoryError
    //   1848	82	5	localObject2	java.lang.Object
    //   1938	93	5	localObject3	java.lang.Object
    //   2033	1	5	localObject4	java.lang.Object
    //   51	1966	6	localObject5	java.lang.Object
    //   59	1960	7	localObject6	java.lang.Object
    //   55	1968	8	localObject7	java.lang.Object
    //   131	1294	9	localObject8	java.lang.Object
    //   1451	22	9	localIllegalArgumentException1	java.lang.IllegalArgumentException
    //   1478	560	9	localObject9	java.lang.Object
    //   2046	1	9	localOutOfMemoryError2	java.lang.OutOfMemoryError
    //   2055	19	9	localObject10	java.lang.Object
    //   67	1504	10	localObject11	java.lang.Object
    //   1585	42	10	localIOException1	java.io.IOException
    //   1633	64	10	localObject12	java.lang.Object
    //   1711	42	10	localJSONException1	org.json.JSONException
    //   1759	64	10	localObject13	java.lang.Object
    //   2051	1	10	localJSONException2	org.json.JSONException
    //   2060	1	10	localIOException2	java.io.IOException
    //   2069	1	10	localIllegalArgumentException2	java.lang.IllegalArgumentException
    //   83	1916	11	localObject14	java.lang.Object
    //   99	1922	12	localObject15	java.lang.Object
    //   135	1905	13	localObject16	java.lang.Object
    //   71	1885	14	localObject17	java.lang.Object
    //   87	1949	15	localObject18	java.lang.Object
    //   103	1803	16	localObject19	java.lang.Object
    //   115	1939	17	localObject20	java.lang.Object
    //   139	1924	18	localObject21	java.lang.Object
    //   75	1997	19	localObject22	java.lang.Object
    //   91	1504	20	localObject23	java.lang.Object
    //   107	1614	21	localObject24	java.lang.Object
    //   119	1732	22	localObject25	java.lang.Object
    //   143	1801	23	localObject26	java.lang.Object
    //   79	1378	24	localObject27	java.lang.Object
    //   95	1496	25	localObject28	java.lang.Object
    //   111	1606	26	localObject29	java.lang.Object
    //   123	1724	27	localObject30	java.lang.Object
    //   127	1716	28	localObject31	java.lang.Object
    //   13	1975	29	localObject32	java.lang.Object
    //   1	1541	30	localObject33	java.lang.Object
    //   4	1664	31	localObject34	java.lang.Object
    //   7	1787	32	localObject35	java.lang.Object
    //   10	1885	33	localObject36	java.lang.Object
    //   16	1299	34	localObject37	java.lang.Object
    //   47	1398	35	localObject38	java.lang.Object
    // Exception table:
    //   from	to	target	type
    //   145	166	1451	java/lang/IllegalArgumentException
    //   246	255	1451	java/lang/IllegalArgumentException
    //   335	344	1451	java/lang/IllegalArgumentException
    //   424	433	1451	java/lang/IllegalArgumentException
    //   513	522	1451	java/lang/IllegalArgumentException
    //   602	609	1451	java/lang/IllegalArgumentException
    //   689	696	1451	java/lang/IllegalArgumentException
    //   776	784	1451	java/lang/IllegalArgumentException
    //   864	878	1451	java/lang/IllegalArgumentException
    //   958	969	1451	java/lang/IllegalArgumentException
    //   1438	1444	1451	java/lang/IllegalArgumentException
    //   145	166	1585	java/io/IOException
    //   246	255	1585	java/io/IOException
    //   335	344	1585	java/io/IOException
    //   424	433	1585	java/io/IOException
    //   513	522	1585	java/io/IOException
    //   602	609	1585	java/io/IOException
    //   689	696	1585	java/io/IOException
    //   776	784	1585	java/io/IOException
    //   864	878	1585	java/io/IOException
    //   958	969	1585	java/io/IOException
    //   1438	1444	1585	java/io/IOException
    //   145	166	1711	org/json/JSONException
    //   246	255	1711	org/json/JSONException
    //   335	344	1711	org/json/JSONException
    //   424	433	1711	org/json/JSONException
    //   513	522	1711	org/json/JSONException
    //   602	609	1711	org/json/JSONException
    //   689	696	1711	org/json/JSONException
    //   776	784	1711	org/json/JSONException
    //   864	878	1711	org/json/JSONException
    //   958	969	1711	org/json/JSONException
    //   1438	1444	1711	org/json/JSONException
    //   145	166	1837	java/lang/OutOfMemoryError
    //   246	255	1837	java/lang/OutOfMemoryError
    //   335	344	1837	java/lang/OutOfMemoryError
    //   424	433	1837	java/lang/OutOfMemoryError
    //   513	522	1837	java/lang/OutOfMemoryError
    //   602	609	1837	java/lang/OutOfMemoryError
    //   689	696	1837	java/lang/OutOfMemoryError
    //   776	784	1837	java/lang/OutOfMemoryError
    //   864	878	1837	java/lang/OutOfMemoryError
    //   958	969	1837	java/lang/OutOfMemoryError
    //   1438	1444	1837	java/lang/OutOfMemoryError
    //   145	166	1938	finally
    //   246	255	1938	finally
    //   335	344	1938	finally
    //   424	433	1938	finally
    //   513	522	1938	finally
    //   602	609	1938	finally
    //   689	696	1938	finally
    //   776	784	1938	finally
    //   864	878	1938	finally
    //   958	969	1938	finally
    //   1438	1444	1938	finally
    //   1018	1024	2033	finally
    //   1060	1067	2033	finally
    //   1117	1130	2033	finally
    //   1166	1185	2033	finally
    //   1221	1226	2033	finally
    //   1262	1278	2033	finally
    //   1500	1505	2033	finally
    //   1626	1631	2033	finally
    //   1752	1757	2033	finally
    //   1018	1024	2046	java/lang/OutOfMemoryError
    //   1060	1067	2046	java/lang/OutOfMemoryError
    //   1117	1130	2046	java/lang/OutOfMemoryError
    //   1166	1185	2046	java/lang/OutOfMemoryError
    //   1221	1226	2046	java/lang/OutOfMemoryError
    //   1262	1278	2046	java/lang/OutOfMemoryError
    //   1018	1024	2051	org/json/JSONException
    //   1060	1067	2051	org/json/JSONException
    //   1117	1130	2051	org/json/JSONException
    //   1166	1185	2051	org/json/JSONException
    //   1221	1226	2051	org/json/JSONException
    //   1262	1278	2051	org/json/JSONException
    //   1018	1024	2060	java/io/IOException
    //   1060	1067	2060	java/io/IOException
    //   1117	1130	2060	java/io/IOException
    //   1166	1185	2060	java/io/IOException
    //   1221	1226	2060	java/io/IOException
    //   1262	1278	2060	java/io/IOException
    //   1018	1024	2069	java/lang/IllegalArgumentException
    //   1060	1067	2069	java/lang/IllegalArgumentException
    //   1117	1130	2069	java/lang/IllegalArgumentException
    //   1166	1185	2069	java/lang/IllegalArgumentException
    //   1221	1226	2069	java/lang/IllegalArgumentException
    //   1262	1278	2069	java/lang/IllegalArgumentException
  }
}


/* Location:           L:\local\mybackup\temp\qq_apk\com.tencent.mobileqqi\classes3.jar
 * Qualified Name:     bpc
 * JD-Core Version:    0.7.0.1
 */