package a.j.b.a.c.e.b;

import a.j.b.a.c.e.a.a;
import a.j.b.a.c.e.a.aa;
import a.j.b.a.c.e.a.ae;
import a.j.b.a.c.e.a.c;
import a.j.b.a.c.e.a.e;
import a.j.b.a.c.e.a.o;
import a.j.b.a.c.e.a.s;
import a.j.b.a.c.e.a.u;
import a.j.b.a.c.g.d;
import a.j.b.a.c.g.f;
import a.j.b.a.c.g.g;
import a.j.b.a.c.g.i;
import a.j.b.a.c.g.i.a;
import a.j.b.a.c.g.i.f;
import a.j.b.a.c.g.s;
import a.j.b.a.c.g.z.a;
import com.tencent.matrix.trace.core.AppMethodBeat;
import java.util.Collections;
import java.util.List;

public final class b
{
  public static final i.f<a.e, b.c> Cpn;
  public static final i.f<a.o, b.c> Cpo;
  public static final i.f<a.o, Integer> Cpp;
  public static final i.f<a.u, b.e> Cpq;
  public static final i.f<a.u, Integer> Cpr;
  public static final i.f<a.aa, List<a.a>> Cps;
  public static final i.f<a.aa, Boolean> Cpt;
  public static final i.f<a.ae, List<a.a>> Cpu;
  public static final i.f<a.c, Integer> Cpv;
  public static final i.f<a.c, List<a.u>> Cpw;
  public static final i.f<a.c, Integer> Cpx;
  public static final i.f<a.s, Integer> Cpy;
  public static final i.f<a.s, List<a.u>> Cpz;
  
  static
  {
    AppMethodBeat.i(121297);
    Cpn = i.a(a.e.eib(), b.c.elp(), b.c.elp(), 100, z.a.CsP, b.c.class);
    Cpo = i.a(a.o.eiJ(), b.c.elp(), b.c.elp(), 100, z.a.CsP, b.c.class);
    Cpp = i.a(a.o.eiJ(), Integer.valueOf(0), null, 101, z.a.CsJ, Integer.class);
    Cpq = i.a(a.u.eiX(), b.e.elu(), b.e.elu(), 100, z.a.CsP, b.e.class);
    Cpr = i.a(a.u.eiX(), Integer.valueOf(0), null, 101, z.a.CsJ, Integer.class);
    Cps = i.a(a.aa.ejw(), a.a.egW(), 100, z.a.CsP, a.a.class);
    Cpt = i.a(a.aa.ejw(), Boolean.FALSE, null, 101, z.a.CsM, Boolean.class);
    Cpu = i.a(a.ae.ekd(), a.a.egW(), 100, z.a.CsP, a.a.class);
    Cpv = i.a(a.c.ehH(), Integer.valueOf(0), null, 101, z.a.CsJ, Integer.class);
    Cpw = i.a(a.c.ehH(), a.u.eiX(), 102, z.a.CsP, a.u.class);
    Cpx = i.a(a.c.ehH(), Integer.valueOf(0), null, 103, z.a.CsJ, Integer.class);
    Cpy = i.a(a.s.eiT(), Integer.valueOf(0), null, 101, z.a.CsJ, Integer.class);
    Cpz = i.a(a.s.eiT(), a.u.eiX(), 102, z.a.CsP, a.u.class);
    AppMethodBeat.o(121297);
  }
  
  public static void a(g paramg)
  {
    AppMethodBeat.i(121296);
    paramg.a(Cpn);
    paramg.a(Cpo);
    paramg.a(Cpp);
    paramg.a(Cpq);
    paramg.a(Cpr);
    paramg.a(Cps);
    paramg.a(Cpt);
    paramg.a(Cpu);
    paramg.a(Cpv);
    paramg.a(Cpw);
    paramg.a(Cpx);
    paramg.a(Cpy);
    paramg.a(Cpz);
    AppMethodBeat.o(121296);
  }
  
  public static final class g$b
    extends i
    implements b.g.c
  {
    public static s<b> Ckq;
    private static final b CpM;
    private final d Ckp;
    private int Ckr;
    private byte Cku = -1;
    private int Ckv = -1;
    public int CpN;
    public int CpO;
    private Object CpP;
    public b.g.b.b CpQ;
    public List<Integer> CpR;
    private int CpS = -1;
    public List<Integer> CpT;
    private int CpU = -1;
    
    static
    {
      AppMethodBeat.i(121287);
      Ckq = new b.g.b.1();
      b localb = new b();
      CpM = localb;
      localb.egZ();
      AppMethodBeat.o(121287);
    }
    
    private g$b()
    {
      this.Ckp = d.Cre;
    }
    
    /* Error */
    private g$b(a.j.b.a.c.g.e parame, g paramg)
    {
      // Byte code:
      //   0: aload_0
      //   1: invokespecial 64	a/j/b/a/c/g/i:<init>	()V
      //   4: ldc 85
      //   6: invokestatic 46	com/tencent/matrix/trace/core/AppMethodBeat:i	(I)V
      //   9: aload_0
      //   10: iconst_m1
      //   11: putfield 66	a/j/b/a/c/e/b/b$g$b:CpS	I
      //   14: aload_0
      //   15: iconst_m1
      //   16: putfield 68	a/j/b/a/c/e/b/b$g$b:CpU	I
      //   19: aload_0
      //   20: iconst_m1
      //   21: putfield 70	a/j/b/a/c/e/b/b$g$b:Cku	B
      //   24: aload_0
      //   25: iconst_m1
      //   26: putfield 72	a/j/b/a/c/e/b/b$g$b:Ckv	I
      //   29: aload_0
      //   30: invokespecial 59	a/j/b/a/c/e/b/b$g$b:egZ	()V
      //   33: iconst_0
      //   34: istore_3
      //   35: invokestatic 89	a/j/b/a/c/g/d:emp	()La/j/b/a/c/g/d$b;
      //   38: astore 10
      //   40: aload 10
      //   42: iconst_1
      //   43: invokestatic 95	a/j/b/a/c/g/f:e	(Ljava/io/OutputStream;I)La/j/b/a/c/g/f;
      //   46: astore 11
      //   48: iconst_0
      //   49: istore 8
      //   51: iload 8
      //   53: ifne +952 -> 1005
      //   56: iload_3
      //   57: istore 5
      //   59: iload_3
      //   60: istore 4
      //   62: iload_3
      //   63: istore 6
      //   65: aload_1
      //   66: invokevirtual 101	a/j/b/a/c/g/e:sk	()I
      //   69: istore 7
      //   71: iload 7
      //   73: lookupswitch	default:+1056->1129, 0:+1059->1132, 8:+111->184, 16:+243->316, 24:+323->396, 32:+432->505, 34:+505->578, 40:+656->729, 42:+729->802, 50:+880->953
      //   157: istore 5
      //   159: iload_3
      //   160: istore 4
      //   162: iload_3
      //   163: istore 6
      //   165: aload_0
      //   166: aload_1
      //   167: aload 11
      //   169: aload_2
      //   170: iload 7
      //   172: invokevirtual 105	a/j/b/a/c/e/b/b$g$b:a	(La/j/b/a/c/g/e;La/j/b/a/c/g/f;La/j/b/a/c/g/g;I)Z
      //   175: ifne -124 -> 51
      //   178: iconst_1
      //   179: istore 8
      //   181: goto -130 -> 51
      //   184: iload_3
      //   185: istore 5
      //   187: iload_3
      //   188: istore 4
      //   190: iload_3
      //   191: istore 6
      //   193: aload_0
      //   194: aload_0
      //   195: getfield 107	a/j/b/a/c/e/b/b$g$b:Ckr	I
      //   198: iconst_1
      //   199: ior
      //   200: putfield 107	a/j/b/a/c/e/b/b$g$b:Ckr	I
      //   203: iload_3
      //   204: istore 5
      //   206: iload_3
      //   207: istore 4
      //   209: iload_3
      //   210: istore 6
      //   212: aload_0
      //   213: aload_1
      //   214: invokevirtual 110	a/j/b/a/c/g/e:sl	()I
      //   217: putfield 112	a/j/b/a/c/e/b/b$g$b:CpN	I
      //   220: goto -169 -> 51
      //   223: astore_1
      //   224: iload 5
      //   226: istore 4
      //   228: aload_1
      //   229: aload_0
      //   230: putfield 116	a/j/b/a/c/g/k:CrM	La/j/b/a/c/g/q;
      //   233: iload 5
      //   235: istore 4
      //   237: ldc 85
      //   239: invokestatic 62	com/tencent/matrix/trace/core/AppMethodBeat:o	(I)V
      //   242: iload 5
      //   244: istore 4
      //   246: aload_1
      //   247: athrow
      //   248: astore_1
      //   249: iload 4
      //   251: bipush 16
      //   253: iand
      //   254: bipush 16
      //   256: if_icmpne +14 -> 270
      //   259: aload_0
      //   260: aload_0
      //   261: getfield 118	a/j/b/a/c/e/b/b$g$b:CpR	Ljava/util/List;
      //   264: invokestatic 124	java/util/Collections:unmodifiableList	(Ljava/util/List;)Ljava/util/List;
      //   267: putfield 118	a/j/b/a/c/e/b/b$g$b:CpR	Ljava/util/List;
      //   270: iload 4
      //   272: bipush 32
      //   274: iand
      //   275: bipush 32
      //   277: if_icmpne +14 -> 291
      //   280: aload_0
      //   281: aload_0
      //   282: getfield 126	a/j/b/a/c/e/b/b$g$b:CpT	Ljava/util/List;
      //   285: invokestatic 124	java/util/Collections:unmodifiableList	(Ljava/util/List;)Ljava/util/List;
      //   288: putfield 126	a/j/b/a/c/e/b/b$g$b:CpT	Ljava/util/List;
      //   291: aload 11
      //   293: invokevirtual 129	a/j/b/a/c/g/f:flush	()V
      //   296: aload_0
      //   297: aload 10
      //   299: invokevirtual 135	a/j/b/a/c/g/d$b:emt	()La/j/b/a/c/g/d;
      //   302: putfield 79	a/j/b/a/c/e/b/b$g$b:Ckp	La/j/b/a/c/g/d;
      //   305: aload_0
      //   306: invokevirtual 138	a/j/b/a/c/e/b/b$g$b:emL	()V
      //   309: ldc 85
      //   311: invokestatic 62	com/tencent/matrix/trace/core/AppMethodBeat:o	(I)V
      //   314: aload_1
      //   315: athrow
      //   316: iload_3
      //   317: istore 5
      //   319: iload_3
      //   320: istore 4
      //   322: iload_3
      //   323: istore 6
      //   325: aload_0
      //   326: aload_0
      //   327: getfield 107	a/j/b/a/c/e/b/b$g$b:Ckr	I
      //   330: iconst_2
      //   331: ior
      //   332: putfield 107	a/j/b/a/c/e/b/b$g$b:Ckr	I
      //   335: iload_3
      //   336: istore 5
      //   338: iload_3
      //   339: istore 4
      //   341: iload_3
      //   342: istore 6
      //   344: aload_0
      //   345: aload_1
      //   346: invokevirtual 110	a/j/b/a/c/g/e:sl	()I
      //   349: putfield 140	a/j/b/a/c/e/b/b$g$b:CpO	I
      //   352: goto -301 -> 51
      //   355: astore_1
      //   356: iload 6
      //   358: istore 4
      //   360: new 82	a/j/b/a/c/g/k
      //   363: dup
      //   364: aload_1
      //   365: invokevirtual 144	java/io/IOException:getMessage	()Ljava/lang/String;
      //   368: invokespecial 147	a/j/b/a/c/g/k:<init>	(Ljava/lang/String;)V
      //   371: astore_1
      //   372: iload 6
      //   374: istore 4
      //   376: aload_1
      //   377: aload_0
      //   378: putfield 116	a/j/b/a/c/g/k:CrM	La/j/b/a/c/g/q;
      //   381: iload 6
      //   383: istore 4
      //   385: ldc 85
      //   387: invokestatic 62	com/tencent/matrix/trace/core/AppMethodBeat:o	(I)V
      //   390: iload 6
      //   392: istore 4
      //   394: aload_1
      //   395: athrow
      //   396: iload_3
      //   397: istore 5
      //   399: iload_3
      //   400: istore 4
      //   402: iload_3
      //   403: istore 6
      //   405: aload_1
      //   406: invokevirtual 110	a/j/b/a/c/g/e:sl	()I
      //   409: istore 9
      //   411: iload_3
      //   412: istore 5
      //   414: iload_3
      //   415: istore 4
      //   417: iload_3
      //   418: istore 6
      //   420: iload 9
      //   422: invokestatic 151	a/j/b/a/c/e/b/b$g$b$b:Vz	(I)La/j/b/a/c/e/b/b$g$b$b;
      //   425: astore 12
      //   427: aload 12
      //   429: ifnonnull +38 -> 467
      //   432: iload_3
      //   433: istore 5
      //   435: iload_3
      //   436: istore 4
      //   438: iload_3
      //   439: istore 6
      //   441: aload 11
      //   443: iload 7
      //   445: invokevirtual 154	a/j/b/a/c/g/f:eX	(I)V
      //   448: iload_3
      //   449: istore 5
      //   451: iload_3
      //   452: istore 4
      //   454: iload_3
      //   455: istore 6
      //   457: aload 11
      //   459: iload 9
      //   461: invokevirtual 154	a/j/b/a/c/g/f:eX	(I)V
      //   464: goto -413 -> 51
      //   467: iload_3
      //   468: istore 5
      //   470: iload_3
      //   471: istore 4
      //   473: iload_3
      //   474: istore 6
      //   476: aload_0
      //   477: aload_0
      //   478: getfield 107	a/j/b/a/c/e/b/b$g$b:Ckr	I
      //   481: bipush 8
      //   483: ior
      //   484: putfield 107	a/j/b/a/c/e/b/b$g$b:Ckr	I
      //   487: iload_3
      //   488: istore 5
      //   490: iload_3
      //   491: istore 4
      //   493: iload_3
      //   494: istore 6
      //   496: aload_0
      //   497: aload 12
      //   499: putfield 156	a/j/b/a/c/e/b/b$g$b:CpQ	La/j/b/a/c/e/b/b$g$b$b;
      //   502: goto -451 -> 51
      //   505: iload_3
      //   506: istore 7
      //   508: iload_3
      //   509: bipush 16
      //   511: iand
      //   512: bipush 16
      //   514: if_icmpeq +29 -> 543
      //   517: iload_3
      //   518: istore 5
      //   520: iload_3
      //   521: istore 4
      //   523: iload_3
      //   524: istore 6
      //   526: aload_0
      //   527: new 158	java/util/ArrayList
      //   530: dup
      //   531: invokespecial 159	java/util/ArrayList:<init>	()V
      //   534: putfield 118	a/j/b/a/c/e/b/b$g$b:CpR	Ljava/util/List;
      //   537: iload_3
      //   538: bipush 16
      //   540: ior
      //   541: istore 7
      //   543: iload 7
      //   545: istore 5
      //   547: iload 7
      //   549: istore 4
      //   551: iload 7
      //   553: istore 6
      //   555: aload_0
      //   556: getfield 118	a/j/b/a/c/e/b/b$g$b:CpR	Ljava/util/List;
      //   559: aload_1
      //   560: invokevirtual 110	a/j/b/a/c/g/e:sl	()I
      //   563: invokestatic 165	java/lang/Integer:valueOf	(I)Ljava/lang/Integer;
      //   566: invokeinterface 171 2 0
      //   571: pop
      //   572: iload 7
      //   574: istore_3
      //   575: goto -524 -> 51
      //   578: iload_3
      //   579: istore 5
      //   581: iload_3
      //   582: istore 4
      //   584: iload_3
      //   585: istore 6
      //   587: aload_1
      //   588: aload_1
      //   589: invokevirtual 110	a/j/b/a/c/g/e:sl	()I
      //   592: invokevirtual 175	a/j/b/a/c/g/e:eP	(I)I
      //   595: istore 9
      //   597: iload_3
      //   598: istore 7
      //   600: iload_3
      //   601: bipush 16
      //   603: iand
      //   604: bipush 16
      //   606: if_icmpeq +48 -> 654
      //   609: iload_3
      //   610: istore 5
      //   612: iload_3
      //   613: istore 4
      //   615: iload_3
      //   616: istore 6
      //   618: iload_3
      //   619: istore 7
      //   621: aload_1
      //   622: invokevirtual 178	a/j/b/a/c/g/e:so	()I
      //   625: ifle +29 -> 654
      //   628: iload_3
      //   629: istore 5
      //   631: iload_3
      //   632: istore 4
      //   634: iload_3
      //   635: istore 6
      //   637: aload_0
      //   638: new 158	java/util/ArrayList
      //   641: dup
      //   642: invokespecial 159	java/util/ArrayList:<init>	()V
      //   645: putfield 118	a/j/b/a/c/e/b/b$g$b:CpR	Ljava/util/List;
      //   648: iload_3
      //   649: bipush 16
      //   651: ior
      //   652: istore 7
      //   654: iload 7
      //   656: istore 5
      //   658: iload 7
      //   660: istore 4
      //   662: iload 7
      //   664: istore 6
      //   666: aload_1
      //   667: invokevirtual 178	a/j/b/a/c/g/e:so	()I
      //   670: ifle +35 -> 705
      //   673: iload 7
      //   675: istore 5
      //   677: iload 7
      //   679: istore 4
      //   681: iload 7
      //   683: istore 6
      //   685: aload_0
      //   686: getfield 118	a/j/b/a/c/e/b/b$g$b:CpR	Ljava/util/List;
      //   689: aload_1
      //   690: invokevirtual 110	a/j/b/a/c/g/e:sl	()I
      //   693: invokestatic 165	java/lang/Integer:valueOf	(I)Ljava/lang/Integer;
      //   696: invokeinterface 171 2 0
      //   701: pop
      //   702: goto -48 -> 654
      //   705: iload 7
      //   707: istore 5
      //   709: iload 7
      //   711: istore 4
      //   713: iload 7
      //   715: istore 6
      //   717: aload_1
      //   718: iload 9
      //   720: invokevirtual 181	a/j/b/a/c/g/e:eQ	(I)V
      //   723: iload 7
      //   725: istore_3
      //   726: goto -675 -> 51
      //   729: iload_3
      //   730: istore 7
      //   732: iload_3
      //   733: bipush 32
      //   735: iand
      //   736: bipush 32
      //   738: if_icmpeq +29 -> 767
      //   741: iload_3
      //   742: istore 5
      //   744: iload_3
      //   745: istore 4
      //   747: iload_3
      //   748: istore 6
      //   750: aload_0
      //   751: new 158	java/util/ArrayList
      //   754: dup
      //   755: invokespecial 159	java/util/ArrayList:<init>	()V
      //   758: putfield 126	a/j/b/a/c/e/b/b$g$b:CpT	Ljava/util/List;
      //   761: iload_3
      //   762: bipush 32
      //   764: ior
      //   765: istore 7
      //   767: iload 7
      //   769: istore 5
      //   771: iload 7
      //   773: istore 4
      //   775: iload 7
      //   777: istore 6
      //   779: aload_0
      //   780: getfield 126	a/j/b/a/c/e/b/b$g$b:CpT	Ljava/util/List;
      //   783: aload_1
      //   784: invokevirtual 110	a/j/b/a/c/g/e:sl	()I
      //   787: invokestatic 165	java/lang/Integer:valueOf	(I)Ljava/lang/Integer;
      //   790: invokeinterface 171 2 0
      //   795: pop
      //   796: iload 7
      //   798: istore_3
      //   799: goto -748 -> 51
      //   802: iload_3
      //   803: istore 5
      //   805: iload_3
      //   806: istore 4
      //   808: iload_3
      //   809: istore 6
      //   811: aload_1
      //   812: aload_1
      //   813: invokevirtual 110	a/j/b/a/c/g/e:sl	()I
      //   816: invokevirtual 175	a/j/b/a/c/g/e:eP	(I)I
      //   819: istore 9
      //   821: iload_3
      //   822: istore 7
      //   824: iload_3
      //   825: bipush 32
      //   827: iand
      //   828: bipush 32
      //   830: if_icmpeq +48 -> 878
      //   833: iload_3
      //   834: istore 5
      //   836: iload_3
      //   837: istore 4
      //   839: iload_3
      //   840: istore 6
      //   842: iload_3
      //   843: istore 7
      //   845: aload_1
      //   846: invokevirtual 178	a/j/b/a/c/g/e:so	()I
      //   849: ifle +29 -> 878
      //   852: iload_3
      //   853: istore 5
      //   855: iload_3
      //   856: istore 4
      //   858: iload_3
      //   859: istore 6
      //   861: aload_0
      //   862: new 158	java/util/ArrayList
      //   865: dup
      //   866: invokespecial 159	java/util/ArrayList:<init>	()V
      //   869: putfield 126	a/j/b/a/c/e/b/b$g$b:CpT	Ljava/util/List;
      //   872: iload_3
      //   873: bipush 32
      //   875: ior
      //   876: istore 7
      //   878: iload 7
      //   880: istore 5
      //   882: iload 7
      //   884: istore 4
      //   886: iload 7
      //   888: istore 6
      //   890: aload_1
      //   891: invokevirtual 178	a/j/b/a/c/g/e:so	()I
      //   894: ifle +35 -> 929
      //   897: iload 7
      //   899: istore 5
      //   901: iload 7
      //   903: istore 4
      //   905: iload 7
      //   907: istore 6
      //   909: aload_0
      //   910: getfield 126	a/j/b/a/c/e/b/b$g$b:CpT	Ljava/util/List;
      //   913: aload_1
      //   914: invokevirtual 110	a/j/b/a/c/g/e:sl	()I
      //   917: invokestatic 165	java/lang/Integer:valueOf	(I)Ljava/lang/Integer;
      //   920: invokeinterface 171 2 0
      //   925: pop
      //   926: goto -48 -> 878
      //   929: iload 7
      //   931: istore 5
      //   933: iload 7
      //   935: istore 4
      //   937: iload 7
      //   939: istore 6
      //   941: aload_1
      //   942: iload 9
      //   944: invokevirtual 181	a/j/b/a/c/g/e:eQ	(I)V
      //   947: iload 7
      //   949: istore_3
      //   950: goto -899 -> 51
      //   953: iload_3
      //   954: istore 5
      //   956: iload_3
      //   957: istore 4
      //   959: iload_3
      //   960: istore 6
      //   962: aload_1
      //   963: invokevirtual 184	a/j/b/a/c/g/e:emv	()La/j/b/a/c/g/d;
      //   966: astore 12
      //   968: iload_3
      //   969: istore 5
      //   971: iload_3
      //   972: istore 4
      //   974: iload_3
      //   975: istore 6
      //   977: aload_0
      //   978: aload_0
      //   979: getfield 107	a/j/b/a/c/e/b/b$g$b:Ckr	I
      //   982: iconst_4
      //   983: ior
      //   984: putfield 107	a/j/b/a/c/e/b/b$g$b:Ckr	I
      //   987: iload_3
      //   988: istore 5
      //   990: iload_3
      //   991: istore 4
      //   993: iload_3
      //   994: istore 6
      //   996: aload_0
      //   997: aload 12
      //   999: putfield 186	a/j/b/a/c/e/b/b$g$b:CpP	Ljava/lang/Object;
      //   1002: goto -951 -> 51
      //   1005: iload_3
      //   1006: bipush 16
      //   1008: iand
      //   1009: bipush 16
      //   1011: if_icmpne +14 -> 1025
      //   1014: aload_0
      //   1015: aload_0
      //   1016: getfield 118	a/j/b/a/c/e/b/b$g$b:CpR	Ljava/util/List;
      //   1019: invokestatic 124	java/util/Collections:unmodifiableList	(Ljava/util/List;)Ljava/util/List;
      //   1022: putfield 118	a/j/b/a/c/e/b/b$g$b:CpR	Ljava/util/List;
      //   1025: iload_3
      //   1026: bipush 32
      //   1028: iand
      //   1029: bipush 32
      //   1031: if_icmpne +14 -> 1045
      //   1034: aload_0
      //   1035: aload_0
      //   1036: getfield 126	a/j/b/a/c/e/b/b$g$b:CpT	Ljava/util/List;
      //   1039: invokestatic 124	java/util/Collections:unmodifiableList	(Ljava/util/List;)Ljava/util/List;
      //   1042: putfield 126	a/j/b/a/c/e/b/b$g$b:CpT	Ljava/util/List;
      //   1045: aload 11
      //   1047: invokevirtual 129	a/j/b/a/c/g/f:flush	()V
      //   1050: aload_0
      //   1051: aload 10
      //   1053: invokevirtual 135	a/j/b/a/c/g/d$b:emt	()La/j/b/a/c/g/d;
      //   1056: putfield 79	a/j/b/a/c/e/b/b$g$b:Ckp	La/j/b/a/c/g/d;
      //   1059: aload_0
      //   1060: invokevirtual 138	a/j/b/a/c/e/b/b$g$b:emL	()V
      //   1063: ldc 85
      //   1065: invokestatic 62	com/tencent/matrix/trace/core/AppMethodBeat:o	(I)V
      //   1068: return
      //   1069: astore_1
      //   1070: aload_0
      //   1071: aload 10
      //   1073: invokevirtual 135	a/j/b/a/c/g/d$b:emt	()La/j/b/a/c/g/d;
      //   1076: putfield 79	a/j/b/a/c/e/b/b$g$b:Ckp	La/j/b/a/c/g/d;
      //   1079: goto -20 -> 1059
      //   1082: astore_1
      //   1083: aload_0
      //   1084: aload 10
      //   1086: invokevirtual 135	a/j/b/a/c/g/d$b:emt	()La/j/b/a/c/g/d;
      //   1089: putfield 79	a/j/b/a/c/e/b/b$g$b:Ckp	La/j/b/a/c/g/d;
      //   1092: ldc 85
      //   1094: invokestatic 62	com/tencent/matrix/trace/core/AppMethodBeat:o	(I)V
      //   1097: aload_1
      //   1098: athrow
      //   1099: astore_2
      //   1100: aload_0
      //   1101: aload 10
      //   1103: invokevirtual 135	a/j/b/a/c/g/d$b:emt	()La/j/b/a/c/g/d;
      //   1106: putfield 79	a/j/b/a/c/e/b/b$g$b:Ckp	La/j/b/a/c/g/d;
      //   1109: goto -804 -> 305
      //   1112: astore_1
      //   1113: aload_0
      //   1114: aload 10
      //   1116: invokevirtual 135	a/j/b/a/c/g/d$b:emt	()La/j/b/a/c/g/d;
      //   1119: putfield 79	a/j/b/a/c/e/b/b$g$b:Ckp	La/j/b/a/c/g/d;
      //   1122: ldc 85
      //   1124: invokestatic 62	com/tencent/matrix/trace/core/AppMethodBeat:o	(I)V
      //   1127: aload_1
      //   1128: athrow
      //   1129: goto -973 -> 156
      //   1132: iconst_1
      //   1133: istore 8
      //   1135: goto -1084 -> 51
      // Local variable table:
      //   start	length	slot	name	signature
      //   0	1138	0	this	b
      //   0	1138	1	parame	a.j.b.a.c.g.e
      //   0	1138	2	paramg	g
      //   34	995	3	i	int
      //   60	932	4	j	int
      //   57	932	5	k	int
      //   63	932	6	m	int
      //   69	879	7	n	int
      //   49	1085	8	i1	int
      //   409	534	9	i2	int
      //   38	1077	10	localb	a.j.b.a.c.g.d.b
      //   46	1000	11	localf	f
      //   425	573	12	localObject	Object
      // Exception table:
      //   from	to	target	type
      //   65	71	223	a/j/b/a/c/g/k
      //   165	178	223	a/j/b/a/c/g/k
      //   193	203	223	a/j/b/a/c/g/k
      //   212	220	223	a/j/b/a/c/g/k
      //   325	335	223	a/j/b/a/c/g/k
      //   344	352	223	a/j/b/a/c/g/k
      //   405	411	223	a/j/b/a/c/g/k
      //   420	427	223	a/j/b/a/c/g/k
      //   441	448	223	a/j/b/a/c/g/k
      //   457	464	223	a/j/b/a/c/g/k
      //   476	487	223	a/j/b/a/c/g/k
      //   496	502	223	a/j/b/a/c/g/k
      //   526	537	223	a/j/b/a/c/g/k
      //   555	572	223	a/j/b/a/c/g/k
      //   587	597	223	a/j/b/a/c/g/k
      //   621	628	223	a/j/b/a/c/g/k
      //   637	648	223	a/j/b/a/c/g/k
      //   666	673	223	a/j/b/a/c/g/k
      //   685	702	223	a/j/b/a/c/g/k
      //   717	723	223	a/j/b/a/c/g/k
      //   750	761	223	a/j/b/a/c/g/k
      //   779	796	223	a/j/b/a/c/g/k
      //   811	821	223	a/j/b/a/c/g/k
      //   845	852	223	a/j/b/a/c/g/k
      //   861	872	223	a/j/b/a/c/g/k
      //   890	897	223	a/j/b/a/c/g/k
      //   909	926	223	a/j/b/a/c/g/k
      //   941	947	223	a/j/b/a/c/g/k
      //   962	968	223	a/j/b/a/c/g/k
      //   977	987	223	a/j/b/a/c/g/k
      //   996	1002	223	a/j/b/a/c/g/k
      //   65	71	248	finally
      //   165	178	248	finally
      //   193	203	248	finally
      //   212	220	248	finally
      //   228	233	248	finally
      //   237	242	248	finally
      //   246	248	248	finally
      //   325	335	248	finally
      //   344	352	248	finally
      //   360	372	248	finally
      //   376	381	248	finally
      //   385	390	248	finally
      //   394	396	248	finally
      //   405	411	248	finally
      //   420	427	248	finally
      //   441	448	248	finally
      //   457	464	248	finally
      //   476	487	248	finally
      //   496	502	248	finally
      //   526	537	248	finally
      //   555	572	248	finally
      //   587	597	248	finally
      //   621	628	248	finally
      //   637	648	248	finally
      //   666	673	248	finally
      //   685	702	248	finally
      //   717	723	248	finally
      //   750	761	248	finally
      //   779	796	248	finally
      //   811	821	248	finally
      //   845	852	248	finally
      //   861	872	248	finally
      //   890	897	248	finally
      //   909	926	248	finally
      //   941	947	248	finally
      //   962	968	248	finally
      //   977	987	248	finally
      //   996	1002	248	finally
      //   65	71	355	java/io/IOException
      //   165	178	355	java/io/IOException
      //   193	203	355	java/io/IOException
      //   212	220	355	java/io/IOException
      //   325	335	355	java/io/IOException
      //   344	352	355	java/io/IOException
      //   405	411	355	java/io/IOException
      //   420	427	355	java/io/IOException
      //   441	448	355	java/io/IOException
      //   457	464	355	java/io/IOException
      //   476	487	355	java/io/IOException
      //   496	502	355	java/io/IOException
      //   526	537	355	java/io/IOException
      //   555	572	355	java/io/IOException
      //   587	597	355	java/io/IOException
      //   621	628	355	java/io/IOException
      //   637	648	355	java/io/IOException
      //   666	673	355	java/io/IOException
      //   685	702	355	java/io/IOException
      //   717	723	355	java/io/IOException
      //   750	761	355	java/io/IOException
      //   779	796	355	java/io/IOException
      //   811	821	355	java/io/IOException
      //   845	852	355	java/io/IOException
      //   861	872	355	java/io/IOException
      //   890	897	355	java/io/IOException
      //   909	926	355	java/io/IOException
      //   941	947	355	java/io/IOException
      //   962	968	355	java/io/IOException
      //   977	987	355	java/io/IOException
      //   996	1002	355	java/io/IOException
      //   1045	1050	1069	java/io/IOException
      //   1045	1050	1082	finally
      //   291	296	1099	java/io/IOException
      //   291	296	1112	finally
    }
    
    private g$b(i.a parama)
    {
      super();
      this.Ckp = parama.Ckp;
    }
    
    private void egZ()
    {
      AppMethodBeat.i(121282);
      this.CpN = 1;
      this.CpO = 0;
      this.CpP = "";
      this.CpQ = b.g.b.b.CpV;
      this.CpR = Collections.emptyList();
      this.CpT = Collections.emptyList();
      AppMethodBeat.o(121282);
    }
    
    public static b elI()
    {
      return CpM;
    }
    
    private d elM()
    {
      AppMethodBeat.i(121279);
      Object localObject = this.CpP;
      if ((localObject instanceof String))
      {
        localObject = d.ayY((String)localObject);
        this.CpP = localObject;
        AppMethodBeat.o(121279);
        return localObject;
      }
      localObject = (d)localObject;
      AppMethodBeat.o(121279);
      return localObject;
    }
    
    public final void a(f paramf)
    {
      int j = 0;
      AppMethodBeat.i(121283);
      sy();
      if ((this.Ckr & 0x1) == 1) {
        paramf.bj(1, this.CpN);
      }
      if ((this.Ckr & 0x2) == 2) {
        paramf.bj(2, this.CpO);
      }
      if ((this.Ckr & 0x8) == 8) {
        paramf.iG(3, this.CpQ.value);
      }
      if (this.CpR.size() > 0)
      {
        paramf.eX(34);
        paramf.eX(this.CpS);
      }
      int i = 0;
      while (i < this.CpR.size())
      {
        paramf.VG(((Integer)this.CpR.get(i)).intValue());
        i += 1;
      }
      i = j;
      if (this.CpT.size() > 0)
      {
        paramf.eX(42);
        paramf.eX(this.CpU);
        i = j;
      }
      while (i < this.CpT.size())
      {
        paramf.VG(((Integer)this.CpT.get(i)).intValue());
        i += 1;
      }
      if ((this.Ckr & 0x4) == 4) {
        paramf.a(6, elM());
      }
      paramf.d(this.Ckp);
      AppMethodBeat.o(121283);
    }
    
    public final s<b> egX()
    {
      return Ckq;
    }
    
    public final boolean elJ()
    {
      return (this.Ckr & 0x1) == 1;
    }
    
    public final boolean elK()
    {
      return (this.Ckr & 0x2) == 2;
    }
    
    public final boolean elL()
    {
      return (this.Ckr & 0x4) == 4;
    }
    
    public final boolean elN()
    {
      return (this.Ckr & 0x8) == 8;
    }
    
    public final int elO()
    {
      AppMethodBeat.i(121280);
      int i = this.CpR.size();
      AppMethodBeat.o(121280);
      return i;
    }
    
    public final int elP()
    {
      AppMethodBeat.i(121281);
      int i = this.CpT.size();
      AppMethodBeat.o(121281);
      return i;
    }
    
    public final String getString()
    {
      AppMethodBeat.i(121278);
      Object localObject = this.CpP;
      if ((localObject instanceof String))
      {
        localObject = (String)localObject;
        AppMethodBeat.o(121278);
        return localObject;
      }
      localObject = (d)localObject;
      String str = ((d)localObject).dqj();
      if (((d)localObject).emn()) {
        this.CpP = str;
      }
      AppMethodBeat.o(121278);
      return str;
    }
    
    public final boolean isInitialized()
    {
      int i = this.Cku;
      if (i == 1) {
        return true;
      }
      if (i == 0) {
        return false;
      }
      this.Cku = 1;
      return true;
    }
    
    public final int sy()
    {
      AppMethodBeat.i(121284);
      int i = this.Ckv;
      if (i != -1)
      {
        AppMethodBeat.o(121284);
        return i;
      }
      if ((this.Ckr & 0x1) == 1) {}
      for (i = f.bl(1, this.CpN) + 0;; i = 0)
      {
        int j = i;
        if ((this.Ckr & 0x2) == 2) {
          j = i + f.bl(2, this.CpO);
        }
        if ((this.Ckr & 0x8) == 8) {}
        for (i = j + f.iH(3, this.CpQ.value);; i = j)
        {
          int k = 0;
          j = 0;
          while (k < this.CpR.size())
          {
            j += f.eU(((Integer)this.CpR.get(k)).intValue());
            k += 1;
          }
          i += j;
          if (!this.CpR.isEmpty()) {
            i = i + 1 + f.eU(j);
          }
          for (;;)
          {
            this.CpS = j;
            k = 0;
            int m;
            for (j = 0; k < this.CpT.size(); j = m + j)
            {
              m = f.eU(((Integer)this.CpT.get(k)).intValue());
              k += 1;
            }
            k = i + j;
            i = k;
            if (!this.CpT.isEmpty()) {
              i = k + 1 + f.eU(j);
            }
            this.CpU = j;
            j = i;
            if ((this.Ckr & 0x4) == 4) {
              j = i + f.b(6, elM());
            }
            i = j + this.Ckp.size();
            this.Ckv = i;
            AppMethodBeat.o(121284);
            return i;
          }
        }
      }
    }
  }
}


/* Location:           L:\local\mybackup\temp\qq_apk\com.tencent.mm\classes3.jar
 * Qualified Name:     a.j.b.a.c.e.b.b
 * JD-Core Version:    0.7.0.1
 */