package kotlin.l.b.a.b.e;

import com.tencent.matrix.trace.core.AppMethodBeat;
import java.io.InputStream;
import java.util.ArrayList;
import java.util.Collections;
import java.util.List;
import kotlin.l.b.a.b.h.b;
import kotlin.l.b.a.b.h.d;
import kotlin.l.b.a.b.h.f;
import kotlin.l.b.a.b.h.g;
import kotlin.l.b.a.b.h.i.a;
import kotlin.l.b.a.b.h.i.b;
import kotlin.l.b.a.b.h.i.c;
import kotlin.l.b.a.b.h.i.c.a;
import kotlin.l.b.a.b.h.k.a;
import kotlin.l.b.a.b.h.k.b;
import kotlin.l.b.a.b.h.r;
import kotlin.l.b.a.b.h.t;

public final class a$b
  extends i.c<b>
  implements e
{
  private static final b aiYG;
  public static t<b> aiYa;
  private final d aiXZ;
  public int aiYH;
  public int aiYI;
  public List<a.r> aiYJ;
  public List<a.p> aiYK;
  public List<Integer> aiYL;
  private int aiYM = -1;
  public List<Integer> aiYN;
  private int aiYO = -1;
  public List<a.c> aiYP;
  public List<a.h> aiYQ;
  public List<a.m> aiYR;
  public List<a.q> aiYS;
  public List<a.f> aiYT;
  public List<Integer> aiYU;
  private int aiYV = -1;
  public int aiYW;
  public a.p aiYX;
  public int aiYY;
  public a.s aiYZ;
  public int aiYq;
  public List<Integer> aiZa;
  public a.v aiZb;
  private int bitField0_;
  private int dRJ = -1;
  private byte memoizedIsInitialized = -1;
  
  static
  {
    AppMethodBeat.i(58434);
    aiYa = new b() {};
    b localb = new b();
    aiYG = localb;
    localb.ktf();
    AppMethodBeat.o(58434);
  }
  
  private a$b()
  {
    this.aiXZ = d.ajeU;
  }
  
  /* Error */
  private a$b(kotlin.l.b.a.b.h.e parame, g paramg)
  {
    // Byte code:
    //   0: aload_0
    //   1: invokespecial 90	kotlin/l/b/a/b/h/i$c:<init>	()V
    //   4: ldc 113
    //   6: invokestatic 74	com/tencent/matrix/trace/core/AppMethodBeat:i	(I)V
    //   9: aload_0
    //   10: iconst_m1
    //   11: putfield 92	kotlin/l/b/a/b/e/a$b:aiYM	I
    //   14: aload_0
    //   15: iconst_m1
    //   16: putfield 94	kotlin/l/b/a/b/e/a$b:aiYO	I
    //   19: aload_0
    //   20: iconst_m1
    //   21: putfield 96	kotlin/l/b/a/b/e/a$b:aiYV	I
    //   24: aload_0
    //   25: iconst_m1
    //   26: putfield 98	kotlin/l/b/a/b/e/a$b:memoizedIsInitialized	B
    //   29: aload_0
    //   30: iconst_m1
    //   31: putfield 100	kotlin/l/b/a/b/e/a$b:dRJ	I
    //   34: aload_0
    //   35: invokespecial 85	kotlin/l/b/a/b/e/a$b:ktf	()V
    //   38: iconst_0
    //   39: istore_3
    //   40: invokestatic 117	kotlin/l/b/a/b/h/d:kya	()Lkotlin/l/b/a/b/h/d$b;
    //   43: astore 11
    //   45: aload 11
    //   47: iconst_1
    //   48: invokestatic 122	kotlin/l/b/a/b/h/f:i	(Ljava/io/OutputStream;I)Lkotlin/l/b/a/b/h/f;
    //   51: astore 12
    //   53: iconst_0
    //   54: istore 8
    //   56: iload 8
    //   58: ifne +2604 -> 2662
    //   61: iload_3
    //   62: istore 5
    //   64: iload_3
    //   65: istore 4
    //   67: iload_3
    //   68: istore 6
    //   70: aload_1
    //   71: invokevirtual 128	kotlin/l/b/a/b/h/e:aac	()I
    //   74: istore 7
    //   76: iload 7
    //   78: lookupswitch	default:+2918->2996, 0:+2921->2999, 8:+230->308, 16:+563->641, 18:+677->755, 24:+828->906, 32:+867->945, 42:+906->984, 50:+980->1058, 56:+1054->1132, 58:+1127->1205, 66:+1278->1356, 74:+1355->1433, 82:+1432->1510, 90:+1509->1587, 106:+1586->1664, 128:+1663->1741, 130:+1739->1817, 136:+1893->1971, 146:+1933->2011, 152:+2061->2139, 242:+2101->2179, 248:+2229->2307, 250:+2302->2380, 258:+2453->2531
    //   281: istore 5
    //   283: iload_3
    //   284: istore 4
    //   286: iload_3
    //   287: istore 6
    //   289: aload_0
    //   290: aload_1
    //   291: aload 12
    //   293: aload_2
    //   294: iload 7
    //   296: invokevirtual 131	kotlin/l/b/a/b/e/a$b:a	(Lkotlin/l/b/a/b/h/e;Lkotlin/l/b/a/b/h/f;Lkotlin/l/b/a/b/h/g;I)Z
    //   299: ifne -243 -> 56
    //   302: iconst_1
    //   303: istore 8
    //   305: goto -249 -> 56
    //   308: iload_3
    //   309: istore 5
    //   311: iload_3
    //   312: istore 4
    //   314: iload_3
    //   315: istore 6
    //   317: aload_0
    //   318: aload_0
    //   319: getfield 133	kotlin/l/b/a/b/e/a$b:bitField0_	I
    //   322: iconst_1
    //   323: ior
    //   324: putfield 133	kotlin/l/b/a/b/e/a$b:bitField0_	I
    //   327: iload_3
    //   328: istore 5
    //   330: iload_3
    //   331: istore 4
    //   333: iload_3
    //   334: istore 6
    //   336: aload_0
    //   337: aload_1
    //   338: invokevirtual 136	kotlin/l/b/a/b/h/e:aar	()I
    //   341: putfield 138	kotlin/l/b/a/b/e/a$b:aiYq	I
    //   344: goto -288 -> 56
    //   347: astore_1
    //   348: iload 5
    //   350: istore 4
    //   352: aload_1
    //   353: aload_0
    //   354: putfield 142	kotlin/l/b/a/b/h/l:ajfp	Lkotlin/l/b/a/b/h/r;
    //   357: iload 5
    //   359: istore 4
    //   361: ldc 113
    //   363: invokestatic 88	com/tencent/matrix/trace/core/AppMethodBeat:o	(I)V
    //   366: iload 5
    //   368: istore 4
    //   370: aload_1
    //   371: athrow
    //   372: astore_1
    //   373: iload 4
    //   375: bipush 32
    //   377: iand
    //   378: bipush 32
    //   380: if_icmpne +14 -> 394
    //   383: aload_0
    //   384: aload_0
    //   385: getfield 144	kotlin/l/b/a/b/e/a$b:aiYL	Ljava/util/List;
    //   388: invokestatic 150	java/util/Collections:unmodifiableList	(Ljava/util/List;)Ljava/util/List;
    //   391: putfield 144	kotlin/l/b/a/b/e/a$b:aiYL	Ljava/util/List;
    //   394: iload 4
    //   396: bipush 8
    //   398: iand
    //   399: bipush 8
    //   401: if_icmpne +14 -> 415
    //   404: aload_0
    //   405: aload_0
    //   406: getfield 152	kotlin/l/b/a/b/e/a$b:aiYJ	Ljava/util/List;
    //   409: invokestatic 150	java/util/Collections:unmodifiableList	(Ljava/util/List;)Ljava/util/List;
    //   412: putfield 152	kotlin/l/b/a/b/e/a$b:aiYJ	Ljava/util/List;
    //   415: iload 4
    //   417: bipush 16
    //   419: iand
    //   420: bipush 16
    //   422: if_icmpne +14 -> 436
    //   425: aload_0
    //   426: aload_0
    //   427: getfield 154	kotlin/l/b/a/b/e/a$b:aiYK	Ljava/util/List;
    //   430: invokestatic 150	java/util/Collections:unmodifiableList	(Ljava/util/List;)Ljava/util/List;
    //   433: putfield 154	kotlin/l/b/a/b/e/a$b:aiYK	Ljava/util/List;
    //   436: iload 4
    //   438: bipush 64
    //   440: iand
    //   441: bipush 64
    //   443: if_icmpne +14 -> 457
    //   446: aload_0
    //   447: aload_0
    //   448: getfield 156	kotlin/l/b/a/b/e/a$b:aiYN	Ljava/util/List;
    //   451: invokestatic 150	java/util/Collections:unmodifiableList	(Ljava/util/List;)Ljava/util/List;
    //   454: putfield 156	kotlin/l/b/a/b/e/a$b:aiYN	Ljava/util/List;
    //   457: iload 4
    //   459: sipush 128
    //   462: iand
    //   463: sipush 128
    //   466: if_icmpne +14 -> 480
    //   469: aload_0
    //   470: aload_0
    //   471: getfield 158	kotlin/l/b/a/b/e/a$b:aiYP	Ljava/util/List;
    //   474: invokestatic 150	java/util/Collections:unmodifiableList	(Ljava/util/List;)Ljava/util/List;
    //   477: putfield 158	kotlin/l/b/a/b/e/a$b:aiYP	Ljava/util/List;
    //   480: iload 4
    //   482: sipush 256
    //   485: iand
    //   486: sipush 256
    //   489: if_icmpne +14 -> 503
    //   492: aload_0
    //   493: aload_0
    //   494: getfield 160	kotlin/l/b/a/b/e/a$b:aiYQ	Ljava/util/List;
    //   497: invokestatic 150	java/util/Collections:unmodifiableList	(Ljava/util/List;)Ljava/util/List;
    //   500: putfield 160	kotlin/l/b/a/b/e/a$b:aiYQ	Ljava/util/List;
    //   503: iload 4
    //   505: sipush 512
    //   508: iand
    //   509: sipush 512
    //   512: if_icmpne +14 -> 526
    //   515: aload_0
    //   516: aload_0
    //   517: getfield 162	kotlin/l/b/a/b/e/a$b:aiYR	Ljava/util/List;
    //   520: invokestatic 150	java/util/Collections:unmodifiableList	(Ljava/util/List;)Ljava/util/List;
    //   523: putfield 162	kotlin/l/b/a/b/e/a$b:aiYR	Ljava/util/List;
    //   526: iload 4
    //   528: sipush 1024
    //   531: iand
    //   532: sipush 1024
    //   535: if_icmpne +14 -> 549
    //   538: aload_0
    //   539: aload_0
    //   540: getfield 164	kotlin/l/b/a/b/e/a$b:aiYS	Ljava/util/List;
    //   543: invokestatic 150	java/util/Collections:unmodifiableList	(Ljava/util/List;)Ljava/util/List;
    //   546: putfield 164	kotlin/l/b/a/b/e/a$b:aiYS	Ljava/util/List;
    //   549: iload 4
    //   551: sipush 2048
    //   554: iand
    //   555: sipush 2048
    //   558: if_icmpne +14 -> 572
    //   561: aload_0
    //   562: aload_0
    //   563: getfield 166	kotlin/l/b/a/b/e/a$b:aiYT	Ljava/util/List;
    //   566: invokestatic 150	java/util/Collections:unmodifiableList	(Ljava/util/List;)Ljava/util/List;
    //   569: putfield 166	kotlin/l/b/a/b/e/a$b:aiYT	Ljava/util/List;
    //   572: iload 4
    //   574: sipush 4096
    //   577: iand
    //   578: sipush 4096
    //   581: if_icmpne +14 -> 595
    //   584: aload_0
    //   585: aload_0
    //   586: getfield 168	kotlin/l/b/a/b/e/a$b:aiYU	Ljava/util/List;
    //   589: invokestatic 150	java/util/Collections:unmodifiableList	(Ljava/util/List;)Ljava/util/List;
    //   592: putfield 168	kotlin/l/b/a/b/e/a$b:aiYU	Ljava/util/List;
    //   595: iload 4
    //   597: ldc 169
    //   599: iand
    //   600: ldc 169
    //   602: if_icmpne +14 -> 616
    //   605: aload_0
    //   606: aload_0
    //   607: getfield 171	kotlin/l/b/a/b/e/a$b:aiZa	Ljava/util/List;
    //   610: invokestatic 150	java/util/Collections:unmodifiableList	(Ljava/util/List;)Ljava/util/List;
    //   613: putfield 171	kotlin/l/b/a/b/e/a$b:aiZa	Ljava/util/List;
    //   616: aload 12
    //   618: invokevirtual 174	kotlin/l/b/a/b/h/f:flush	()V
    //   621: aload_0
    //   622: aload 11
    //   624: invokevirtual 180	kotlin/l/b/a/b/h/d$b:kyc	()Lkotlin/l/b/a/b/h/d;
    //   627: putfield 107	kotlin/l/b/a/b/e/a$b:aiXZ	Lkotlin/l/b/a/b/h/d;
    //   630: aload_0
    //   631: invokevirtual 183	kotlin/l/b/a/b/e/a$b:makeExtensionsImmutable	()V
    //   634: ldc 113
    //   636: invokestatic 88	com/tencent/matrix/trace/core/AppMethodBeat:o	(I)V
    //   639: aload_1
    //   640: athrow
    //   641: iload_3
    //   642: istore 7
    //   644: iload_3
    //   645: bipush 32
    //   647: iand
    //   648: bipush 32
    //   650: if_icmpeq +29 -> 679
    //   653: iload_3
    //   654: istore 5
    //   656: iload_3
    //   657: istore 4
    //   659: iload_3
    //   660: istore 6
    //   662: aload_0
    //   663: new 185	java/util/ArrayList
    //   666: dup
    //   667: invokespecial 186	java/util/ArrayList:<init>	()V
    //   670: putfield 144	kotlin/l/b/a/b/e/a$b:aiYL	Ljava/util/List;
    //   673: iload_3
    //   674: bipush 32
    //   676: ior
    //   677: istore 7
    //   679: iload 7
    //   681: istore 5
    //   683: iload 7
    //   685: istore 4
    //   687: iload 7
    //   689: istore 6
    //   691: aload_0
    //   692: getfield 144	kotlin/l/b/a/b/e/a$b:aiYL	Ljava/util/List;
    //   695: aload_1
    //   696: invokevirtual 136	kotlin/l/b/a/b/h/e:aar	()I
    //   699: invokestatic 192	java/lang/Integer:valueOf	(I)Ljava/lang/Integer;
    //   702: invokeinterface 198 2 0
    //   707: pop
    //   708: iload 7
    //   710: istore_3
    //   711: goto -655 -> 56
    //   714: astore_1
    //   715: iload 6
    //   717: istore 4
    //   719: new 110	kotlin/l/b/a/b/h/l
    //   722: dup
    //   723: aload_1
    //   724: invokevirtual 202	java/io/IOException:getMessage	()Ljava/lang/String;
    //   727: invokespecial 205	kotlin/l/b/a/b/h/l:<init>	(Ljava/lang/String;)V
    //   730: astore_1
    //   731: iload 6
    //   733: istore 4
    //   735: aload_1
    //   736: aload_0
    //   737: putfield 142	kotlin/l/b/a/b/h/l:ajfp	Lkotlin/l/b/a/b/h/r;
    //   740: iload 6
    //   742: istore 4
    //   744: ldc 113
    //   746: invokestatic 88	com/tencent/matrix/trace/core/AppMethodBeat:o	(I)V
    //   749: iload 6
    //   751: istore 4
    //   753: aload_1
    //   754: athrow
    //   755: iload_3
    //   756: istore 5
    //   758: iload_3
    //   759: istore 4
    //   761: iload_3
    //   762: istore 6
    //   764: aload_1
    //   765: aload_1
    //   766: invokevirtual 136	kotlin/l/b/a/b/h/e:aar	()I
    //   769: invokevirtual 209	kotlin/l/b/a/b/h/e:jO	(I)I
    //   772: istore 9
    //   774: iload_3
    //   775: istore 7
    //   777: iload_3
    //   778: bipush 32
    //   780: iand
    //   781: bipush 32
    //   783: if_icmpeq +48 -> 831
    //   786: iload_3
    //   787: istore 5
    //   789: iload_3
    //   790: istore 4
    //   792: iload_3
    //   793: istore 6
    //   795: iload_3
    //   796: istore 7
    //   798: aload_1
    //   799: invokevirtual 212	kotlin/l/b/a/b/h/e:aat	()I
    //   802: ifle +29 -> 831
    //   805: iload_3
    //   806: istore 5
    //   808: iload_3
    //   809: istore 4
    //   811: iload_3
    //   812: istore 6
    //   814: aload_0
    //   815: new 185	java/util/ArrayList
    //   818: dup
    //   819: invokespecial 186	java/util/ArrayList:<init>	()V
    //   822: putfield 144	kotlin/l/b/a/b/e/a$b:aiYL	Ljava/util/List;
    //   825: iload_3
    //   826: bipush 32
    //   828: ior
    //   829: istore 7
    //   831: iload 7
    //   833: istore 5
    //   835: iload 7
    //   837: istore 4
    //   839: iload 7
    //   841: istore 6
    //   843: aload_1
    //   844: invokevirtual 212	kotlin/l/b/a/b/h/e:aat	()I
    //   847: ifle +35 -> 882
    //   850: iload 7
    //   852: istore 5
    //   854: iload 7
    //   856: istore 4
    //   858: iload 7
    //   860: istore 6
    //   862: aload_0
    //   863: getfield 144	kotlin/l/b/a/b/e/a$b:aiYL	Ljava/util/List;
    //   866: aload_1
    //   867: invokevirtual 136	kotlin/l/b/a/b/h/e:aar	()I
    //   870: invokestatic 192	java/lang/Integer:valueOf	(I)Ljava/lang/Integer;
    //   873: invokeinterface 198 2 0
    //   878: pop
    //   879: goto -48 -> 831
    //   882: iload 7
    //   884: istore 5
    //   886: iload 7
    //   888: istore 4
    //   890: iload 7
    //   892: istore 6
    //   894: aload_1
    //   895: iload 9
    //   897: invokevirtual 215	kotlin/l/b/a/b/h/e:jP	(I)V
    //   900: iload 7
    //   902: istore_3
    //   903: goto -847 -> 56
    //   906: iload_3
    //   907: istore 5
    //   909: iload_3
    //   910: istore 4
    //   912: iload_3
    //   913: istore 6
    //   915: aload_0
    //   916: aload_0
    //   917: getfield 133	kotlin/l/b/a/b/e/a$b:bitField0_	I
    //   920: iconst_2
    //   921: ior
    //   922: putfield 133	kotlin/l/b/a/b/e/a$b:bitField0_	I
    //   925: iload_3
    //   926: istore 5
    //   928: iload_3
    //   929: istore 4
    //   931: iload_3
    //   932: istore 6
    //   934: aload_0
    //   935: aload_1
    //   936: invokevirtual 136	kotlin/l/b/a/b/h/e:aar	()I
    //   939: putfield 217	kotlin/l/b/a/b/e/a$b:aiYH	I
    //   942: goto -886 -> 56
    //   945: iload_3
    //   946: istore 5
    //   948: iload_3
    //   949: istore 4
    //   951: iload_3
    //   952: istore 6
    //   954: aload_0
    //   955: aload_0
    //   956: getfield 133	kotlin/l/b/a/b/e/a$b:bitField0_	I
    //   959: iconst_4
    //   960: ior
    //   961: putfield 133	kotlin/l/b/a/b/e/a$b:bitField0_	I
    //   964: iload_3
    //   965: istore 5
    //   967: iload_3
    //   968: istore 4
    //   970: iload_3
    //   971: istore 6
    //   973: aload_0
    //   974: aload_1
    //   975: invokevirtual 136	kotlin/l/b/a/b/h/e:aar	()I
    //   978: putfield 219	kotlin/l/b/a/b/e/a$b:aiYI	I
    //   981: goto -925 -> 56
    //   984: iload_3
    //   985: istore 7
    //   987: iload_3
    //   988: bipush 8
    //   990: iand
    //   991: bipush 8
    //   993: if_icmpeq +29 -> 1022
    //   996: iload_3
    //   997: istore 5
    //   999: iload_3
    //   1000: istore 4
    //   1002: iload_3
    //   1003: istore 6
    //   1005: aload_0
    //   1006: new 185	java/util/ArrayList
    //   1009: dup
    //   1010: invokespecial 186	java/util/ArrayList:<init>	()V
    //   1013: putfield 152	kotlin/l/b/a/b/e/a$b:aiYJ	Ljava/util/List;
    //   1016: iload_3
    //   1017: bipush 8
    //   1019: ior
    //   1020: istore 7
    //   1022: iload 7
    //   1024: istore 5
    //   1026: iload 7
    //   1028: istore 4
    //   1030: iload 7
    //   1032: istore 6
    //   1034: aload_0
    //   1035: getfield 152	kotlin/l/b/a/b/e/a$b:aiYJ	Ljava/util/List;
    //   1038: aload_1
    //   1039: getstatic 222	kotlin/l/b/a/b/e/a$r:aiYa	Lkotlin/l/b/a/b/h/t;
    //   1042: aload_2
    //   1043: invokevirtual 225	kotlin/l/b/a/b/h/e:a	(Lkotlin/l/b/a/b/h/t;Lkotlin/l/b/a/b/h/g;)Lkotlin/l/b/a/b/h/r;
    //   1046: invokeinterface 198 2 0
    //   1051: pop
    //   1052: iload 7
    //   1054: istore_3
    //   1055: goto -999 -> 56
    //   1058: iload_3
    //   1059: istore 7
    //   1061: iload_3
    //   1062: bipush 16
    //   1064: iand
    //   1065: bipush 16
    //   1067: if_icmpeq +29 -> 1096
    //   1070: iload_3
    //   1071: istore 5
    //   1073: iload_3
    //   1074: istore 4
    //   1076: iload_3
    //   1077: istore 6
    //   1079: aload_0
    //   1080: new 185	java/util/ArrayList
    //   1083: dup
    //   1084: invokespecial 186	java/util/ArrayList:<init>	()V
    //   1087: putfield 154	kotlin/l/b/a/b/e/a$b:aiYK	Ljava/util/List;
    //   1090: iload_3
    //   1091: bipush 16
    //   1093: ior
    //   1094: istore 7
    //   1096: iload 7
    //   1098: istore 5
    //   1100: iload 7
    //   1102: istore 4
    //   1104: iload 7
    //   1106: istore 6
    //   1108: aload_0
    //   1109: getfield 154	kotlin/l/b/a/b/e/a$b:aiYK	Ljava/util/List;
    //   1112: aload_1
    //   1113: getstatic 228	kotlin/l/b/a/b/e/a$p:aiYa	Lkotlin/l/b/a/b/h/t;
    //   1116: aload_2
    //   1117: invokevirtual 225	kotlin/l/b/a/b/h/e:a	(Lkotlin/l/b/a/b/h/t;Lkotlin/l/b/a/b/h/g;)Lkotlin/l/b/a/b/h/r;
    //   1120: invokeinterface 198 2 0
    //   1125: pop
    //   1126: iload 7
    //   1128: istore_3
    //   1129: goto -1073 -> 56
    //   1132: iload_3
    //   1133: istore 7
    //   1135: iload_3
    //   1136: bipush 64
    //   1138: iand
    //   1139: bipush 64
    //   1141: if_icmpeq +29 -> 1170
    //   1144: iload_3
    //   1145: istore 5
    //   1147: iload_3
    //   1148: istore 4
    //   1150: iload_3
    //   1151: istore 6
    //   1153: aload_0
    //   1154: new 185	java/util/ArrayList
    //   1157: dup
    //   1158: invokespecial 186	java/util/ArrayList:<init>	()V
    //   1161: putfield 156	kotlin/l/b/a/b/e/a$b:aiYN	Ljava/util/List;
    //   1164: iload_3
    //   1165: bipush 64
    //   1167: ior
    //   1168: istore 7
    //   1170: iload 7
    //   1172: istore 5
    //   1174: iload 7
    //   1176: istore 4
    //   1178: iload 7
    //   1180: istore 6
    //   1182: aload_0
    //   1183: getfield 156	kotlin/l/b/a/b/e/a$b:aiYN	Ljava/util/List;
    //   1186: aload_1
    //   1187: invokevirtual 136	kotlin/l/b/a/b/h/e:aar	()I
    //   1190: invokestatic 192	java/lang/Integer:valueOf	(I)Ljava/lang/Integer;
    //   1193: invokeinterface 198 2 0
    //   1198: pop
    //   1199: iload 7
    //   1201: istore_3
    //   1202: goto -1146 -> 56
    //   1205: iload_3
    //   1206: istore 5
    //   1208: iload_3
    //   1209: istore 4
    //   1211: iload_3
    //   1212: istore 6
    //   1214: aload_1
    //   1215: aload_1
    //   1216: invokevirtual 136	kotlin/l/b/a/b/h/e:aar	()I
    //   1219: invokevirtual 209	kotlin/l/b/a/b/h/e:jO	(I)I
    //   1222: istore 9
    //   1224: iload_3
    //   1225: istore 7
    //   1227: iload_3
    //   1228: bipush 64
    //   1230: iand
    //   1231: bipush 64
    //   1233: if_icmpeq +48 -> 1281
    //   1236: iload_3
    //   1237: istore 5
    //   1239: iload_3
    //   1240: istore 4
    //   1242: iload_3
    //   1243: istore 6
    //   1245: iload_3
    //   1246: istore 7
    //   1248: aload_1
    //   1249: invokevirtual 212	kotlin/l/b/a/b/h/e:aat	()I
    //   1252: ifle +29 -> 1281
    //   1255: iload_3
    //   1256: istore 5
    //   1258: iload_3
    //   1259: istore 4
    //   1261: iload_3
    //   1262: istore 6
    //   1264: aload_0
    //   1265: new 185	java/util/ArrayList
    //   1268: dup
    //   1269: invokespecial 186	java/util/ArrayList:<init>	()V
    //   1272: putfield 156	kotlin/l/b/a/b/e/a$b:aiYN	Ljava/util/List;
    //   1275: iload_3
    //   1276: bipush 64
    //   1278: ior
    //   1279: istore 7
    //   1281: iload 7
    //   1283: istore 5
    //   1285: iload 7
    //   1287: istore 4
    //   1289: iload 7
    //   1291: istore 6
    //   1293: aload_1
    //   1294: invokevirtual 212	kotlin/l/b/a/b/h/e:aat	()I
    //   1297: ifle +35 -> 1332
    //   1300: iload 7
    //   1302: istore 5
    //   1304: iload 7
    //   1306: istore 4
    //   1308: iload 7
    //   1310: istore 6
    //   1312: aload_0
    //   1313: getfield 156	kotlin/l/b/a/b/e/a$b:aiYN	Ljava/util/List;
    //   1316: aload_1
    //   1317: invokevirtual 136	kotlin/l/b/a/b/h/e:aar	()I
    //   1320: invokestatic 192	java/lang/Integer:valueOf	(I)Ljava/lang/Integer;
    //   1323: invokeinterface 198 2 0
    //   1328: pop
    //   1329: goto -48 -> 1281
    //   1332: iload 7
    //   1334: istore 5
    //   1336: iload 7
    //   1338: istore 4
    //   1340: iload 7
    //   1342: istore 6
    //   1344: aload_1
    //   1345: iload 9
    //   1347: invokevirtual 215	kotlin/l/b/a/b/h/e:jP	(I)V
    //   1350: iload 7
    //   1352: istore_3
    //   1353: goto -1297 -> 56
    //   1356: iload_3
    //   1357: istore 7
    //   1359: iload_3
    //   1360: sipush 128
    //   1363: iand
    //   1364: sipush 128
    //   1367: if_icmpeq +30 -> 1397
    //   1370: iload_3
    //   1371: istore 5
    //   1373: iload_3
    //   1374: istore 4
    //   1376: iload_3
    //   1377: istore 6
    //   1379: aload_0
    //   1380: new 185	java/util/ArrayList
    //   1383: dup
    //   1384: invokespecial 186	java/util/ArrayList:<init>	()V
    //   1387: putfield 158	kotlin/l/b/a/b/e/a$b:aiYP	Ljava/util/List;
    //   1390: iload_3
    //   1391: sipush 128
    //   1394: ior
    //   1395: istore 7
    //   1397: iload 7
    //   1399: istore 5
    //   1401: iload 7
    //   1403: istore 4
    //   1405: iload 7
    //   1407: istore 6
    //   1409: aload_0
    //   1410: getfield 158	kotlin/l/b/a/b/e/a$b:aiYP	Ljava/util/List;
    //   1413: aload_1
    //   1414: getstatic 231	kotlin/l/b/a/b/e/a$c:aiYa	Lkotlin/l/b/a/b/h/t;
    //   1417: aload_2
    //   1418: invokevirtual 225	kotlin/l/b/a/b/h/e:a	(Lkotlin/l/b/a/b/h/t;Lkotlin/l/b/a/b/h/g;)Lkotlin/l/b/a/b/h/r;
    //   1421: invokeinterface 198 2 0
    //   1426: pop
    //   1427: iload 7
    //   1429: istore_3
    //   1430: goto -1374 -> 56
    //   1433: iload_3
    //   1434: istore 7
    //   1436: iload_3
    //   1437: sipush 256
    //   1440: iand
    //   1441: sipush 256
    //   1444: if_icmpeq +30 -> 1474
    //   1447: iload_3
    //   1448: istore 5
    //   1450: iload_3
    //   1451: istore 4
    //   1453: iload_3
    //   1454: istore 6
    //   1456: aload_0
    //   1457: new 185	java/util/ArrayList
    //   1460: dup
    //   1461: invokespecial 186	java/util/ArrayList:<init>	()V
    //   1464: putfield 160	kotlin/l/b/a/b/e/a$b:aiYQ	Ljava/util/List;
    //   1467: iload_3
    //   1468: sipush 256
    //   1471: ior
    //   1472: istore 7
    //   1474: iload 7
    //   1476: istore 5
    //   1478: iload 7
    //   1480: istore 4
    //   1482: iload 7
    //   1484: istore 6
    //   1486: aload_0
    //   1487: getfield 160	kotlin/l/b/a/b/e/a$b:aiYQ	Ljava/util/List;
    //   1490: aload_1
    //   1491: getstatic 234	kotlin/l/b/a/b/e/a$h:aiYa	Lkotlin/l/b/a/b/h/t;
    //   1494: aload_2
    //   1495: invokevirtual 225	kotlin/l/b/a/b/h/e:a	(Lkotlin/l/b/a/b/h/t;Lkotlin/l/b/a/b/h/g;)Lkotlin/l/b/a/b/h/r;
    //   1498: invokeinterface 198 2 0
    //   1503: pop
    //   1504: iload 7
    //   1506: istore_3
    //   1507: goto -1451 -> 56
    //   1510: iload_3
    //   1511: istore 7
    //   1513: iload_3
    //   1514: sipush 512
    //   1517: iand
    //   1518: sipush 512
    //   1521: if_icmpeq +30 -> 1551
    //   1524: iload_3
    //   1525: istore 5
    //   1527: iload_3
    //   1528: istore 4
    //   1530: iload_3
    //   1531: istore 6
    //   1533: aload_0
    //   1534: new 185	java/util/ArrayList
    //   1537: dup
    //   1538: invokespecial 186	java/util/ArrayList:<init>	()V
    //   1541: putfield 162	kotlin/l/b/a/b/e/a$b:aiYR	Ljava/util/List;
    //   1544: iload_3
    //   1545: sipush 512
    //   1548: ior
    //   1549: istore 7
    //   1551: iload 7
    //   1553: istore 5
    //   1555: iload 7
    //   1557: istore 4
    //   1559: iload 7
    //   1561: istore 6
    //   1563: aload_0
    //   1564: getfield 162	kotlin/l/b/a/b/e/a$b:aiYR	Ljava/util/List;
    //   1567: aload_1
    //   1568: getstatic 237	kotlin/l/b/a/b/e/a$m:aiYa	Lkotlin/l/b/a/b/h/t;
    //   1571: aload_2
    //   1572: invokevirtual 225	kotlin/l/b/a/b/h/e:a	(Lkotlin/l/b/a/b/h/t;Lkotlin/l/b/a/b/h/g;)Lkotlin/l/b/a/b/h/r;
    //   1575: invokeinterface 198 2 0
    //   1580: pop
    //   1581: iload 7
    //   1583: istore_3
    //   1584: goto -1528 -> 56
    //   1587: iload_3
    //   1588: istore 7
    //   1590: iload_3
    //   1591: sipush 1024
    //   1594: iand
    //   1595: sipush 1024
    //   1598: if_icmpeq +30 -> 1628
    //   1601: iload_3
    //   1602: istore 5
    //   1604: iload_3
    //   1605: istore 4
    //   1607: iload_3
    //   1608: istore 6
    //   1610: aload_0
    //   1611: new 185	java/util/ArrayList
    //   1614: dup
    //   1615: invokespecial 186	java/util/ArrayList:<init>	()V
    //   1618: putfield 164	kotlin/l/b/a/b/e/a$b:aiYS	Ljava/util/List;
    //   1621: iload_3
    //   1622: sipush 1024
    //   1625: ior
    //   1626: istore 7
    //   1628: iload 7
    //   1630: istore 5
    //   1632: iload 7
    //   1634: istore 4
    //   1636: iload 7
    //   1638: istore 6
    //   1640: aload_0
    //   1641: getfield 164	kotlin/l/b/a/b/e/a$b:aiYS	Ljava/util/List;
    //   1644: aload_1
    //   1645: getstatic 240	kotlin/l/b/a/b/e/a$q:aiYa	Lkotlin/l/b/a/b/h/t;
    //   1648: aload_2
    //   1649: invokevirtual 225	kotlin/l/b/a/b/h/e:a	(Lkotlin/l/b/a/b/h/t;Lkotlin/l/b/a/b/h/g;)Lkotlin/l/b/a/b/h/r;
    //   1652: invokeinterface 198 2 0
    //   1657: pop
    //   1658: iload 7
    //   1660: istore_3
    //   1661: goto -1605 -> 56
    //   1664: iload_3
    //   1665: istore 7
    //   1667: iload_3
    //   1668: sipush 2048
    //   1671: iand
    //   1672: sipush 2048
    //   1675: if_icmpeq +30 -> 1705
    //   1678: iload_3
    //   1679: istore 5
    //   1681: iload_3
    //   1682: istore 4
    //   1684: iload_3
    //   1685: istore 6
    //   1687: aload_0
    //   1688: new 185	java/util/ArrayList
    //   1691: dup
    //   1692: invokespecial 186	java/util/ArrayList:<init>	()V
    //   1695: putfield 166	kotlin/l/b/a/b/e/a$b:aiYT	Ljava/util/List;
    //   1698: iload_3
    //   1699: sipush 2048
    //   1702: ior
    //   1703: istore 7
    //   1705: iload 7
    //   1707: istore 5
    //   1709: iload 7
    //   1711: istore 4
    //   1713: iload 7
    //   1715: istore 6
    //   1717: aload_0
    //   1718: getfield 166	kotlin/l/b/a/b/e/a$b:aiYT	Ljava/util/List;
    //   1721: aload_1
    //   1722: getstatic 243	kotlin/l/b/a/b/e/a$f:aiYa	Lkotlin/l/b/a/b/h/t;
    //   1725: aload_2
    //   1726: invokevirtual 225	kotlin/l/b/a/b/h/e:a	(Lkotlin/l/b/a/b/h/t;Lkotlin/l/b/a/b/h/g;)Lkotlin/l/b/a/b/h/r;
    //   1729: invokeinterface 198 2 0
    //   1734: pop
    //   1735: iload 7
    //   1737: istore_3
    //   1738: goto -1682 -> 56
    //   1741: iload_3
    //   1742: istore 7
    //   1744: iload_3
    //   1745: sipush 4096
    //   1748: iand
    //   1749: sipush 4096
    //   1752: if_icmpeq +30 -> 1782
    //   1755: iload_3
    //   1756: istore 5
    //   1758: iload_3
    //   1759: istore 4
    //   1761: iload_3
    //   1762: istore 6
    //   1764: aload_0
    //   1765: new 185	java/util/ArrayList
    //   1768: dup
    //   1769: invokespecial 186	java/util/ArrayList:<init>	()V
    //   1772: putfield 168	kotlin/l/b/a/b/e/a$b:aiYU	Ljava/util/List;
    //   1775: iload_3
    //   1776: sipush 4096
    //   1779: ior
    //   1780: istore 7
    //   1782: iload 7
    //   1784: istore 5
    //   1786: iload 7
    //   1788: istore 4
    //   1790: iload 7
    //   1792: istore 6
    //   1794: aload_0
    //   1795: getfield 168	kotlin/l/b/a/b/e/a$b:aiYU	Ljava/util/List;
    //   1798: aload_1
    //   1799: invokevirtual 136	kotlin/l/b/a/b/h/e:aar	()I
    //   1802: invokestatic 192	java/lang/Integer:valueOf	(I)Ljava/lang/Integer;
    //   1805: invokeinterface 198 2 0
    //   1810: pop
    //   1811: iload 7
    //   1813: istore_3
    //   1814: goto -1758 -> 56
    //   1817: iload_3
    //   1818: istore 5
    //   1820: iload_3
    //   1821: istore 4
    //   1823: iload_3
    //   1824: istore 6
    //   1826: aload_1
    //   1827: aload_1
    //   1828: invokevirtual 136	kotlin/l/b/a/b/h/e:aar	()I
    //   1831: invokevirtual 209	kotlin/l/b/a/b/h/e:jO	(I)I
    //   1834: istore 9
    //   1836: iload_3
    //   1837: istore 7
    //   1839: iload_3
    //   1840: sipush 4096
    //   1843: iand
    //   1844: sipush 4096
    //   1847: if_icmpeq +49 -> 1896
    //   1850: iload_3
    //   1851: istore 5
    //   1853: iload_3
    //   1854: istore 4
    //   1856: iload_3
    //   1857: istore 6
    //   1859: iload_3
    //   1860: istore 7
    //   1862: aload_1
    //   1863: invokevirtual 212	kotlin/l/b/a/b/h/e:aat	()I
    //   1866: ifle +30 -> 1896
    //   1869: iload_3
    //   1870: istore 5
    //   1872: iload_3
    //   1873: istore 4
    //   1875: iload_3
    //   1876: istore 6
    //   1878: aload_0
    //   1879: new 185	java/util/ArrayList
    //   1882: dup
    //   1883: invokespecial 186	java/util/ArrayList:<init>	()V
    //   1886: putfield 168	kotlin/l/b/a/b/e/a$b:aiYU	Ljava/util/List;
    //   1889: iload_3
    //   1890: sipush 4096
    //   1893: ior
    //   1894: istore 7
    //   1896: iload 7
    //   1898: istore 5
    //   1900: iload 7
    //   1902: istore 4
    //   1904: iload 7
    //   1906: istore 6
    //   1908: aload_1
    //   1909: invokevirtual 212	kotlin/l/b/a/b/h/e:aat	()I
    //   1912: ifle +35 -> 1947
    //   1915: iload 7
    //   1917: istore 5
    //   1919: iload 7
    //   1921: istore 4
    //   1923: iload 7
    //   1925: istore 6
    //   1927: aload_0
    //   1928: getfield 168	kotlin/l/b/a/b/e/a$b:aiYU	Ljava/util/List;
    //   1931: aload_1
    //   1932: invokevirtual 136	kotlin/l/b/a/b/h/e:aar	()I
    //   1935: invokestatic 192	java/lang/Integer:valueOf	(I)Ljava/lang/Integer;
    //   1938: invokeinterface 198 2 0
    //   1943: pop
    //   1944: goto -48 -> 1896
    //   1947: iload 7
    //   1949: istore 5
    //   1951: iload 7
    //   1953: istore 4
    //   1955: iload 7
    //   1957: istore 6
    //   1959: aload_1
    //   1960: iload 9
    //   1962: invokevirtual 215	kotlin/l/b/a/b/h/e:jP	(I)V
    //   1965: iload 7
    //   1967: istore_3
    //   1968: goto -1912 -> 56
    //   1971: iload_3
    //   1972: istore 5
    //   1974: iload_3
    //   1975: istore 4
    //   1977: iload_3
    //   1978: istore 6
    //   1980: aload_0
    //   1981: aload_0
    //   1982: getfield 133	kotlin/l/b/a/b/e/a$b:bitField0_	I
    //   1985: bipush 8
    //   1987: ior
    //   1988: putfield 133	kotlin/l/b/a/b/e/a$b:bitField0_	I
    //   1991: iload_3
    //   1992: istore 5
    //   1994: iload_3
    //   1995: istore 4
    //   1997: iload_3
    //   1998: istore 6
    //   2000: aload_0
    //   2001: aload_1
    //   2002: invokevirtual 136	kotlin/l/b/a/b/h/e:aar	()I
    //   2005: putfield 245	kotlin/l/b/a/b/e/a$b:aiYW	I
    //   2008: goto -1952 -> 56
    //   2011: iload_3
    //   2012: istore 5
    //   2014: iload_3
    //   2015: istore 4
    //   2017: iload_3
    //   2018: istore 6
    //   2020: aload_0
    //   2021: getfield 133	kotlin/l/b/a/b/e/a$b:bitField0_	I
    //   2024: bipush 16
    //   2026: iand
    //   2027: bipush 16
    //   2029: if_icmpne +961 -> 2990
    //   2032: iload_3
    //   2033: istore 5
    //   2035: iload_3
    //   2036: istore 4
    //   2038: iload_3
    //   2039: istore 6
    //   2041: aload_0
    //   2042: getfield 247	kotlin/l/b/a/b/e/a$b:aiYX	Lkotlin/l/b/a/b/e/a$p;
    //   2045: invokestatic 251	kotlin/l/b/a/b/e/a$p:g	(Lkotlin/l/b/a/b/e/a$p;)Lkotlin/l/b/a/b/e/a$p$b;
    //   2048: astore 10
    //   2050: iload_3
    //   2051: istore 5
    //   2053: iload_3
    //   2054: istore 4
    //   2056: iload_3
    //   2057: istore 6
    //   2059: aload_0
    //   2060: aload_1
    //   2061: getstatic 228	kotlin/l/b/a/b/e/a$p:aiYa	Lkotlin/l/b/a/b/h/t;
    //   2064: aload_2
    //   2065: invokevirtual 225	kotlin/l/b/a/b/h/e:a	(Lkotlin/l/b/a/b/h/t;Lkotlin/l/b/a/b/h/g;)Lkotlin/l/b/a/b/h/r;
    //   2068: checkcast 227	kotlin/l/b/a/b/e/a$p
    //   2071: putfield 247	kotlin/l/b/a/b/e/a$b:aiYX	Lkotlin/l/b/a/b/e/a$p;
    //   2074: aload 10
    //   2076: ifnull +40 -> 2116
    //   2079: iload_3
    //   2080: istore 5
    //   2082: iload_3
    //   2083: istore 4
    //   2085: iload_3
    //   2086: istore 6
    //   2088: aload 10
    //   2090: aload_0
    //   2091: getfield 247	kotlin/l/b/a/b/e/a$b:aiYX	Lkotlin/l/b/a/b/e/a$p;
    //   2094: invokevirtual 256	kotlin/l/b/a/b/e/a$p$b:k	(Lkotlin/l/b/a/b/e/a$p;)Lkotlin/l/b/a/b/e/a$p$b;
    //   2097: pop
    //   2098: iload_3
    //   2099: istore 5
    //   2101: iload_3
    //   2102: istore 4
    //   2104: iload_3
    //   2105: istore 6
    //   2107: aload_0
    //   2108: aload 10
    //   2110: invokevirtual 260	kotlin/l/b/a/b/e/a$p$b:kwd	()Lkotlin/l/b/a/b/e/a$p;
    //   2113: putfield 247	kotlin/l/b/a/b/e/a$b:aiYX	Lkotlin/l/b/a/b/e/a$p;
    //   2116: iload_3
    //   2117: istore 5
    //   2119: iload_3
    //   2120: istore 4
    //   2122: iload_3
    //   2123: istore 6
    //   2125: aload_0
    //   2126: aload_0
    //   2127: getfield 133	kotlin/l/b/a/b/e/a$b:bitField0_	I
    //   2130: bipush 16
    //   2132: ior
    //   2133: putfield 133	kotlin/l/b/a/b/e/a$b:bitField0_	I
    //   2136: goto -2080 -> 56
    //   2139: iload_3
    //   2140: istore 5
    //   2142: iload_3
    //   2143: istore 4
    //   2145: iload_3
    //   2146: istore 6
    //   2148: aload_0
    //   2149: aload_0
    //   2150: getfield 133	kotlin/l/b/a/b/e/a$b:bitField0_	I
    //   2153: bipush 32
    //   2155: ior
    //   2156: putfield 133	kotlin/l/b/a/b/e/a$b:bitField0_	I
    //   2159: iload_3
    //   2160: istore 5
    //   2162: iload_3
    //   2163: istore 4
    //   2165: iload_3
    //   2166: istore 6
    //   2168: aload_0
    //   2169: aload_1
    //   2170: invokevirtual 136	kotlin/l/b/a/b/h/e:aar	()I
    //   2173: putfield 262	kotlin/l/b/a/b/e/a$b:aiYY	I
    //   2176: goto -2120 -> 56
    //   2179: iload_3
    //   2180: istore 5
    //   2182: iload_3
    //   2183: istore 4
    //   2185: iload_3
    //   2186: istore 6
    //   2188: aload_0
    //   2189: getfield 133	kotlin/l/b/a/b/e/a$b:bitField0_	I
    //   2192: bipush 64
    //   2194: iand
    //   2195: bipush 64
    //   2197: if_icmpne +787 -> 2984
    //   2200: iload_3
    //   2201: istore 5
    //   2203: iload_3
    //   2204: istore 4
    //   2206: iload_3
    //   2207: istore 6
    //   2209: aload_0
    //   2210: getfield 264	kotlin/l/b/a/b/e/a$b:aiYZ	Lkotlin/l/b/a/b/e/a$s;
    //   2213: invokestatic 270	kotlin/l/b/a/b/e/a$s:d	(Lkotlin/l/b/a/b/e/a$s;)Lkotlin/l/b/a/b/e/a$s$a;
    //   2216: astore 10
    //   2218: iload_3
    //   2219: istore 5
    //   2221: iload_3
    //   2222: istore 4
    //   2224: iload_3
    //   2225: istore 6
    //   2227: aload_0
    //   2228: aload_1
    //   2229: getstatic 271	kotlin/l/b/a/b/e/a$s:aiYa	Lkotlin/l/b/a/b/h/t;
    //   2232: aload_2
    //   2233: invokevirtual 225	kotlin/l/b/a/b/h/e:a	(Lkotlin/l/b/a/b/h/t;Lkotlin/l/b/a/b/h/g;)Lkotlin/l/b/a/b/h/r;
    //   2236: checkcast 266	kotlin/l/b/a/b/e/a$s
    //   2239: putfield 264	kotlin/l/b/a/b/e/a$b:aiYZ	Lkotlin/l/b/a/b/e/a$s;
    //   2242: aload 10
    //   2244: ifnull +40 -> 2284
    //   2247: iload_3
    //   2248: istore 5
    //   2250: iload_3
    //   2251: istore 4
    //   2253: iload_3
    //   2254: istore 6
    //   2256: aload 10
    //   2258: aload_0
    //   2259: getfield 264	kotlin/l/b/a/b/e/a$b:aiYZ	Lkotlin/l/b/a/b/e/a$s;
    //   2262: invokevirtual 275	kotlin/l/b/a/b/e/a$s$a:g	(Lkotlin/l/b/a/b/e/a$s;)Lkotlin/l/b/a/b/e/a$s$a;
    //   2265: pop
    //   2266: iload_3
    //   2267: istore 5
    //   2269: iload_3
    //   2270: istore 4
    //   2272: iload_3
    //   2273: istore 6
    //   2275: aload_0
    //   2276: aload 10
    //   2278: invokevirtual 279	kotlin/l/b/a/b/e/a$s$a:kwz	()Lkotlin/l/b/a/b/e/a$s;
    //   2281: putfield 264	kotlin/l/b/a/b/e/a$b:aiYZ	Lkotlin/l/b/a/b/e/a$s;
    //   2284: iload_3
    //   2285: istore 5
    //   2287: iload_3
    //   2288: istore 4
    //   2290: iload_3
    //   2291: istore 6
    //   2293: aload_0
    //   2294: aload_0
    //   2295: getfield 133	kotlin/l/b/a/b/e/a$b:bitField0_	I
    //   2298: bipush 64
    //   2300: ior
    //   2301: putfield 133	kotlin/l/b/a/b/e/a$b:bitField0_	I
    //   2304: goto -2248 -> 56
    //   2307: iload_3
    //   2308: istore 7
    //   2310: iload_3
    //   2311: ldc 169
    //   2313: iand
    //   2314: ldc 169
    //   2316: if_icmpeq +29 -> 2345
    //   2319: iload_3
    //   2320: istore 5
    //   2322: iload_3
    //   2323: istore 4
    //   2325: iload_3
    //   2326: istore 6
    //   2328: aload_0
    //   2329: new 185	java/util/ArrayList
    //   2332: dup
    //   2333: invokespecial 186	java/util/ArrayList:<init>	()V
    //   2336: putfield 171	kotlin/l/b/a/b/e/a$b:aiZa	Ljava/util/List;
    //   2339: iload_3
    //   2340: ldc 169
    //   2342: ior
    //   2343: istore 7
    //   2345: iload 7
    //   2347: istore 5
    //   2349: iload 7
    //   2351: istore 4
    //   2353: iload 7
    //   2355: istore 6
    //   2357: aload_0
    //   2358: getfield 171	kotlin/l/b/a/b/e/a$b:aiZa	Ljava/util/List;
    //   2361: aload_1
    //   2362: invokevirtual 136	kotlin/l/b/a/b/h/e:aar	()I
    //   2365: invokestatic 192	java/lang/Integer:valueOf	(I)Ljava/lang/Integer;
    //   2368: invokeinterface 198 2 0
    //   2373: pop
    //   2374: iload 7
    //   2376: istore_3
    //   2377: goto -2321 -> 56
    //   2380: iload_3
    //   2381: istore 5
    //   2383: iload_3
    //   2384: istore 4
    //   2386: iload_3
    //   2387: istore 6
    //   2389: aload_1
    //   2390: aload_1
    //   2391: invokevirtual 136	kotlin/l/b/a/b/h/e:aar	()I
    //   2394: invokevirtual 209	kotlin/l/b/a/b/h/e:jO	(I)I
    //   2397: istore 9
    //   2399: iload_3
    //   2400: istore 7
    //   2402: iload_3
    //   2403: ldc 169
    //   2405: iand
    //   2406: ldc 169
    //   2408: if_icmpeq +48 -> 2456
    //   2411: iload_3
    //   2412: istore 5
    //   2414: iload_3
    //   2415: istore 4
    //   2417: iload_3
    //   2418: istore 6
    //   2420: iload_3
    //   2421: istore 7
    //   2423: aload_1
    //   2424: invokevirtual 212	kotlin/l/b/a/b/h/e:aat	()I
    //   2427: ifle +29 -> 2456
    //   2430: iload_3
    //   2431: istore 5
    //   2433: iload_3
    //   2434: istore 4
    //   2436: iload_3
    //   2437: istore 6
    //   2439: aload_0
    //   2440: new 185	java/util/ArrayList
    //   2443: dup
    //   2444: invokespecial 186	java/util/ArrayList:<init>	()V
    //   2447: putfield 171	kotlin/l/b/a/b/e/a$b:aiZa	Ljava/util/List;
    //   2450: iload_3
    //   2451: ldc 169
    //   2453: ior
    //   2454: istore 7
    //   2456: iload 7
    //   2458: istore 5
    //   2460: iload 7
    //   2462: istore 4
    //   2464: iload 7
    //   2466: istore 6
    //   2468: aload_1
    //   2469: invokevirtual 212	kotlin/l/b/a/b/h/e:aat	()I
    //   2472: ifle +35 -> 2507
    //   2475: iload 7
    //   2477: istore 5
    //   2479: iload 7
    //   2481: istore 4
    //   2483: iload 7
    //   2485: istore 6
    //   2487: aload_0
    //   2488: getfield 171	kotlin/l/b/a/b/e/a$b:aiZa	Ljava/util/List;
    //   2491: aload_1
    //   2492: invokevirtual 136	kotlin/l/b/a/b/h/e:aar	()I
    //   2495: invokestatic 192	java/lang/Integer:valueOf	(I)Ljava/lang/Integer;
    //   2498: invokeinterface 198 2 0
    //   2503: pop
    //   2504: goto -48 -> 2456
    //   2507: iload 7
    //   2509: istore 5
    //   2511: iload 7
    //   2513: istore 4
    //   2515: iload 7
    //   2517: istore 6
    //   2519: aload_1
    //   2520: iload 9
    //   2522: invokevirtual 215	kotlin/l/b/a/b/h/e:jP	(I)V
    //   2525: iload 7
    //   2527: istore_3
    //   2528: goto -2472 -> 56
    //   2531: iload_3
    //   2532: istore 5
    //   2534: iload_3
    //   2535: istore 4
    //   2537: iload_3
    //   2538: istore 6
    //   2540: aload_0
    //   2541: getfield 133	kotlin/l/b/a/b/e/a$b:bitField0_	I
    //   2544: sipush 128
    //   2547: iand
    //   2548: sipush 128
    //   2551: if_icmpne +427 -> 2978
    //   2554: iload_3
    //   2555: istore 5
    //   2557: iload_3
    //   2558: istore 4
    //   2560: iload_3
    //   2561: istore 6
    //   2563: aload_0
    //   2564: getfield 281	kotlin/l/b/a/b/e/a$b:aiZb	Lkotlin/l/b/a/b/e/a$v;
    //   2567: invokestatic 287	kotlin/l/b/a/b/e/a$v:c	(Lkotlin/l/b/a/b/e/a$v;)Lkotlin/l/b/a/b/e/a$v$a;
    //   2570: astore 10
    //   2572: iload_3
    //   2573: istore 5
    //   2575: iload_3
    //   2576: istore 4
    //   2578: iload_3
    //   2579: istore 6
    //   2581: aload_0
    //   2582: aload_1
    //   2583: getstatic 288	kotlin/l/b/a/b/e/a$v:aiYa	Lkotlin/l/b/a/b/h/t;
    //   2586: aload_2
    //   2587: invokevirtual 225	kotlin/l/b/a/b/h/e:a	(Lkotlin/l/b/a/b/h/t;Lkotlin/l/b/a/b/h/g;)Lkotlin/l/b/a/b/h/r;
    //   2590: checkcast 283	kotlin/l/b/a/b/e/a$v
    //   2593: putfield 281	kotlin/l/b/a/b/e/a$b:aiZb	Lkotlin/l/b/a/b/e/a$v;
    //   2596: aload 10
    //   2598: ifnull +40 -> 2638
    //   2601: iload_3
    //   2602: istore 5
    //   2604: iload_3
    //   2605: istore 4
    //   2607: iload_3
    //   2608: istore 6
    //   2610: aload 10
    //   2612: aload_0
    //   2613: getfield 281	kotlin/l/b/a/b/e/a$b:aiZb	Lkotlin/l/b/a/b/e/a$v;
    //   2616: invokevirtual 293	kotlin/l/b/a/b/e/a$v$a:f	(Lkotlin/l/b/a/b/e/a$v;)Lkotlin/l/b/a/b/e/a$v$a;
    //   2619: pop
    //   2620: iload_3
    //   2621: istore 5
    //   2623: iload_3
    //   2624: istore 4
    //   2626: iload_3
    //   2627: istore 6
    //   2629: aload_0
    //   2630: aload 10
    //   2632: invokevirtual 297	kotlin/l/b/a/b/e/a$v$a:kwT	()Lkotlin/l/b/a/b/e/a$v;
    //   2635: putfield 281	kotlin/l/b/a/b/e/a$b:aiZb	Lkotlin/l/b/a/b/e/a$v;
    //   2638: iload_3
    //   2639: istore 5
    //   2641: iload_3
    //   2642: istore 4
    //   2644: iload_3
    //   2645: istore 6
    //   2647: aload_0
    //   2648: aload_0
    //   2649: getfield 133	kotlin/l/b/a/b/e/a$b:bitField0_	I
    //   2652: sipush 128
    //   2655: ior
    //   2656: putfield 133	kotlin/l/b/a/b/e/a$b:bitField0_	I
    //   2659: goto -2603 -> 56
    //   2662: iload_3
    //   2663: bipush 32
    //   2665: iand
    //   2666: bipush 32
    //   2668: if_icmpne +14 -> 2682
    //   2671: aload_0
    //   2672: aload_0
    //   2673: getfield 144	kotlin/l/b/a/b/e/a$b:aiYL	Ljava/util/List;
    //   2676: invokestatic 150	java/util/Collections:unmodifiableList	(Ljava/util/List;)Ljava/util/List;
    //   2679: putfield 144	kotlin/l/b/a/b/e/a$b:aiYL	Ljava/util/List;
    //   2682: iload_3
    //   2683: bipush 8
    //   2685: iand
    //   2686: bipush 8
    //   2688: if_icmpne +14 -> 2702
    //   2691: aload_0
    //   2692: aload_0
    //   2693: getfield 152	kotlin/l/b/a/b/e/a$b:aiYJ	Ljava/util/List;
    //   2696: invokestatic 150	java/util/Collections:unmodifiableList	(Ljava/util/List;)Ljava/util/List;
    //   2699: putfield 152	kotlin/l/b/a/b/e/a$b:aiYJ	Ljava/util/List;
    //   2702: iload_3
    //   2703: bipush 16
    //   2705: iand
    //   2706: bipush 16
    //   2708: if_icmpne +14 -> 2722
    //   2711: aload_0
    //   2712: aload_0
    //   2713: getfield 154	kotlin/l/b/a/b/e/a$b:aiYK	Ljava/util/List;
    //   2716: invokestatic 150	java/util/Collections:unmodifiableList	(Ljava/util/List;)Ljava/util/List;
    //   2719: putfield 154	kotlin/l/b/a/b/e/a$b:aiYK	Ljava/util/List;
    //   2722: iload_3
    //   2723: bipush 64
    //   2725: iand
    //   2726: bipush 64
    //   2728: if_icmpne +14 -> 2742
    //   2731: aload_0
    //   2732: aload_0
    //   2733: getfield 156	kotlin/l/b/a/b/e/a$b:aiYN	Ljava/util/List;
    //   2736: invokestatic 150	java/util/Collections:unmodifiableList	(Ljava/util/List;)Ljava/util/List;
    //   2739: putfield 156	kotlin/l/b/a/b/e/a$b:aiYN	Ljava/util/List;
    //   2742: iload_3
    //   2743: sipush 128
    //   2746: iand
    //   2747: sipush 128
    //   2750: if_icmpne +14 -> 2764
    //   2753: aload_0
    //   2754: aload_0
    //   2755: getfield 158	kotlin/l/b/a/b/e/a$b:aiYP	Ljava/util/List;
    //   2758: invokestatic 150	java/util/Collections:unmodifiableList	(Ljava/util/List;)Ljava/util/List;
    //   2761: putfield 158	kotlin/l/b/a/b/e/a$b:aiYP	Ljava/util/List;
    //   2764: iload_3
    //   2765: sipush 256
    //   2768: iand
    //   2769: sipush 256
    //   2772: if_icmpne +14 -> 2786
    //   2775: aload_0
    //   2776: aload_0
    //   2777: getfield 160	kotlin/l/b/a/b/e/a$b:aiYQ	Ljava/util/List;
    //   2780: invokestatic 150	java/util/Collections:unmodifiableList	(Ljava/util/List;)Ljava/util/List;
    //   2783: putfield 160	kotlin/l/b/a/b/e/a$b:aiYQ	Ljava/util/List;
    //   2786: iload_3
    //   2787: sipush 512
    //   2790: iand
    //   2791: sipush 512
    //   2794: if_icmpne +14 -> 2808
    //   2797: aload_0
    //   2798: aload_0
    //   2799: getfield 162	kotlin/l/b/a/b/e/a$b:aiYR	Ljava/util/List;
    //   2802: invokestatic 150	java/util/Collections:unmodifiableList	(Ljava/util/List;)Ljava/util/List;
    //   2805: putfield 162	kotlin/l/b/a/b/e/a$b:aiYR	Ljava/util/List;
    //   2808: iload_3
    //   2809: sipush 1024
    //   2812: iand
    //   2813: sipush 1024
    //   2816: if_icmpne +14 -> 2830
    //   2819: aload_0
    //   2820: aload_0
    //   2821: getfield 164	kotlin/l/b/a/b/e/a$b:aiYS	Ljava/util/List;
    //   2824: invokestatic 150	java/util/Collections:unmodifiableList	(Ljava/util/List;)Ljava/util/List;
    //   2827: putfield 164	kotlin/l/b/a/b/e/a$b:aiYS	Ljava/util/List;
    //   2830: iload_3
    //   2831: sipush 2048
    //   2834: iand
    //   2835: sipush 2048
    //   2838: if_icmpne +14 -> 2852
    //   2841: aload_0
    //   2842: aload_0
    //   2843: getfield 166	kotlin/l/b/a/b/e/a$b:aiYT	Ljava/util/List;
    //   2846: invokestatic 150	java/util/Collections:unmodifiableList	(Ljava/util/List;)Ljava/util/List;
    //   2849: putfield 166	kotlin/l/b/a/b/e/a$b:aiYT	Ljava/util/List;
    //   2852: iload_3
    //   2853: sipush 4096
    //   2856: iand
    //   2857: sipush 4096
    //   2860: if_icmpne +14 -> 2874
    //   2863: aload_0
    //   2864: aload_0
    //   2865: getfield 168	kotlin/l/b/a/b/e/a$b:aiYU	Ljava/util/List;
    //   2868: invokestatic 150	java/util/Collections:unmodifiableList	(Ljava/util/List;)Ljava/util/List;
    //   2871: putfield 168	kotlin/l/b/a/b/e/a$b:aiYU	Ljava/util/List;
    //   2874: iload_3
    //   2875: ldc 169
    //   2877: iand
    //   2878: ldc 169
    //   2880: if_icmpne +14 -> 2894
    //   2883: aload_0
    //   2884: aload_0
    //   2885: getfield 171	kotlin/l/b/a/b/e/a$b:aiZa	Ljava/util/List;
    //   2888: invokestatic 150	java/util/Collections:unmodifiableList	(Ljava/util/List;)Ljava/util/List;
    //   2891: putfield 171	kotlin/l/b/a/b/e/a$b:aiZa	Ljava/util/List;
    //   2894: aload 12
    //   2896: invokevirtual 174	kotlin/l/b/a/b/h/f:flush	()V
    //   2899: aload_0
    //   2900: aload 11
    //   2902: invokevirtual 180	kotlin/l/b/a/b/h/d$b:kyc	()Lkotlin/l/b/a/b/h/d;
    //   2905: putfield 107	kotlin/l/b/a/b/e/a$b:aiXZ	Lkotlin/l/b/a/b/h/d;
    //   2908: aload_0
    //   2909: invokevirtual 183	kotlin/l/b/a/b/e/a$b:makeExtensionsImmutable	()V
    //   2912: ldc 113
    //   2914: invokestatic 88	com/tencent/matrix/trace/core/AppMethodBeat:o	(I)V
    //   2917: return
    //   2918: astore_1
    //   2919: aload_0
    //   2920: aload 11
    //   2922: invokevirtual 180	kotlin/l/b/a/b/h/d$b:kyc	()Lkotlin/l/b/a/b/h/d;
    //   2925: putfield 107	kotlin/l/b/a/b/e/a$b:aiXZ	Lkotlin/l/b/a/b/h/d;
    //   2928: goto -20 -> 2908
    //   2931: astore_1
    //   2932: aload_0
    //   2933: aload 11
    //   2935: invokevirtual 180	kotlin/l/b/a/b/h/d$b:kyc	()Lkotlin/l/b/a/b/h/d;
    //   2938: putfield 107	kotlin/l/b/a/b/e/a$b:aiXZ	Lkotlin/l/b/a/b/h/d;
    //   2941: ldc 113
    //   2943: invokestatic 88	com/tencent/matrix/trace/core/AppMethodBeat:o	(I)V
    //   2946: aload_1
    //   2947: athrow
    //   2948: astore_2
    //   2949: aload_0
    //   2950: aload 11
    //   2952: invokevirtual 180	kotlin/l/b/a/b/h/d$b:kyc	()Lkotlin/l/b/a/b/h/d;
    //   2955: putfield 107	kotlin/l/b/a/b/e/a$b:aiXZ	Lkotlin/l/b/a/b/h/d;
    //   2958: goto -2328 -> 630
    //   2961: astore_1
    //   2962: aload_0
    //   2963: aload 11
    //   2965: invokevirtual 180	kotlin/l/b/a/b/h/d$b:kyc	()Lkotlin/l/b/a/b/h/d;
    //   2968: putfield 107	kotlin/l/b/a/b/e/a$b:aiXZ	Lkotlin/l/b/a/b/h/d;
    //   2971: ldc 113
    //   2973: invokestatic 88	com/tencent/matrix/trace/core/AppMethodBeat:o	(I)V
    //   2976: aload_1
    //   2977: athrow
    //   2978: aconst_null
    //   2979: astore 10
    //   2981: goto -409 -> 2572
    //   2984: aconst_null
    //   2985: astore 10
    //   2987: goto -769 -> 2218
    //   2990: aconst_null
    //   2991: astore 10
    //   2993: goto -943 -> 2050
    //   2996: goto -2716 -> 280
    //   2999: iconst_1
    //   3000: istore 8
    //   3002: goto -2946 -> 56
    // Local variable table:
    //   start	length	slot	name	signature
    //   0	3005	0	this	b
    //   0	3005	1	parame	kotlin.l.b.a.b.h.e
    //   0	3005	2	paramg	g
    //   39	2839	3	i	int
    //   65	2578	4	j	int
    //   62	2578	5	k	int
    //   68	2578	6	m	int
    //   74	2452	7	n	int
    //   54	2947	8	i1	int
    //   772	1749	9	i2	int
    //   2048	944	10	localObject	Object
    //   43	2921	11	localb	kotlin.l.b.a.b.h.d.b
    //   51	2844	12	localf	f
    // Exception table:
    //   from	to	target	type
    //   70	76	347	kotlin/l/b/a/b/h/l
    //   289	302	347	kotlin/l/b/a/b/h/l
    //   317	327	347	kotlin/l/b/a/b/h/l
    //   336	344	347	kotlin/l/b/a/b/h/l
    //   662	673	347	kotlin/l/b/a/b/h/l
    //   691	708	347	kotlin/l/b/a/b/h/l
    //   764	774	347	kotlin/l/b/a/b/h/l
    //   798	805	347	kotlin/l/b/a/b/h/l
    //   814	825	347	kotlin/l/b/a/b/h/l
    //   843	850	347	kotlin/l/b/a/b/h/l
    //   862	879	347	kotlin/l/b/a/b/h/l
    //   894	900	347	kotlin/l/b/a/b/h/l
    //   915	925	347	kotlin/l/b/a/b/h/l
    //   934	942	347	kotlin/l/b/a/b/h/l
    //   954	964	347	kotlin/l/b/a/b/h/l
    //   973	981	347	kotlin/l/b/a/b/h/l
    //   1005	1016	347	kotlin/l/b/a/b/h/l
    //   1034	1052	347	kotlin/l/b/a/b/h/l
    //   1079	1090	347	kotlin/l/b/a/b/h/l
    //   1108	1126	347	kotlin/l/b/a/b/h/l
    //   1153	1164	347	kotlin/l/b/a/b/h/l
    //   1182	1199	347	kotlin/l/b/a/b/h/l
    //   1214	1224	347	kotlin/l/b/a/b/h/l
    //   1248	1255	347	kotlin/l/b/a/b/h/l
    //   1264	1275	347	kotlin/l/b/a/b/h/l
    //   1293	1300	347	kotlin/l/b/a/b/h/l
    //   1312	1329	347	kotlin/l/b/a/b/h/l
    //   1344	1350	347	kotlin/l/b/a/b/h/l
    //   1379	1390	347	kotlin/l/b/a/b/h/l
    //   1409	1427	347	kotlin/l/b/a/b/h/l
    //   1456	1467	347	kotlin/l/b/a/b/h/l
    //   1486	1504	347	kotlin/l/b/a/b/h/l
    //   1533	1544	347	kotlin/l/b/a/b/h/l
    //   1563	1581	347	kotlin/l/b/a/b/h/l
    //   1610	1621	347	kotlin/l/b/a/b/h/l
    //   1640	1658	347	kotlin/l/b/a/b/h/l
    //   1687	1698	347	kotlin/l/b/a/b/h/l
    //   1717	1735	347	kotlin/l/b/a/b/h/l
    //   1764	1775	347	kotlin/l/b/a/b/h/l
    //   1794	1811	347	kotlin/l/b/a/b/h/l
    //   1826	1836	347	kotlin/l/b/a/b/h/l
    //   1862	1869	347	kotlin/l/b/a/b/h/l
    //   1878	1889	347	kotlin/l/b/a/b/h/l
    //   1908	1915	347	kotlin/l/b/a/b/h/l
    //   1927	1944	347	kotlin/l/b/a/b/h/l
    //   1959	1965	347	kotlin/l/b/a/b/h/l
    //   1980	1991	347	kotlin/l/b/a/b/h/l
    //   2000	2008	347	kotlin/l/b/a/b/h/l
    //   2020	2032	347	kotlin/l/b/a/b/h/l
    //   2041	2050	347	kotlin/l/b/a/b/h/l
    //   2059	2074	347	kotlin/l/b/a/b/h/l
    //   2088	2098	347	kotlin/l/b/a/b/h/l
    //   2107	2116	347	kotlin/l/b/a/b/h/l
    //   2125	2136	347	kotlin/l/b/a/b/h/l
    //   2148	2159	347	kotlin/l/b/a/b/h/l
    //   2168	2176	347	kotlin/l/b/a/b/h/l
    //   2188	2200	347	kotlin/l/b/a/b/h/l
    //   2209	2218	347	kotlin/l/b/a/b/h/l
    //   2227	2242	347	kotlin/l/b/a/b/h/l
    //   2256	2266	347	kotlin/l/b/a/b/h/l
    //   2275	2284	347	kotlin/l/b/a/b/h/l
    //   2293	2304	347	kotlin/l/b/a/b/h/l
    //   2328	2339	347	kotlin/l/b/a/b/h/l
    //   2357	2374	347	kotlin/l/b/a/b/h/l
    //   2389	2399	347	kotlin/l/b/a/b/h/l
    //   2423	2430	347	kotlin/l/b/a/b/h/l
    //   2439	2450	347	kotlin/l/b/a/b/h/l
    //   2468	2475	347	kotlin/l/b/a/b/h/l
    //   2487	2504	347	kotlin/l/b/a/b/h/l
    //   2519	2525	347	kotlin/l/b/a/b/h/l
    //   2540	2554	347	kotlin/l/b/a/b/h/l
    //   2563	2572	347	kotlin/l/b/a/b/h/l
    //   2581	2596	347	kotlin/l/b/a/b/h/l
    //   2610	2620	347	kotlin/l/b/a/b/h/l
    //   2629	2638	347	kotlin/l/b/a/b/h/l
    //   2647	2659	347	kotlin/l/b/a/b/h/l
    //   70	76	372	finally
    //   289	302	372	finally
    //   317	327	372	finally
    //   336	344	372	finally
    //   352	357	372	finally
    //   361	366	372	finally
    //   370	372	372	finally
    //   662	673	372	finally
    //   691	708	372	finally
    //   719	731	372	finally
    //   735	740	372	finally
    //   744	749	372	finally
    //   753	755	372	finally
    //   764	774	372	finally
    //   798	805	372	finally
    //   814	825	372	finally
    //   843	850	372	finally
    //   862	879	372	finally
    //   894	900	372	finally
    //   915	925	372	finally
    //   934	942	372	finally
    //   954	964	372	finally
    //   973	981	372	finally
    //   1005	1016	372	finally
    //   1034	1052	372	finally
    //   1079	1090	372	finally
    //   1108	1126	372	finally
    //   1153	1164	372	finally
    //   1182	1199	372	finally
    //   1214	1224	372	finally
    //   1248	1255	372	finally
    //   1264	1275	372	finally
    //   1293	1300	372	finally
    //   1312	1329	372	finally
    //   1344	1350	372	finally
    //   1379	1390	372	finally
    //   1409	1427	372	finally
    //   1456	1467	372	finally
    //   1486	1504	372	finally
    //   1533	1544	372	finally
    //   1563	1581	372	finally
    //   1610	1621	372	finally
    //   1640	1658	372	finally
    //   1687	1698	372	finally
    //   1717	1735	372	finally
    //   1764	1775	372	finally
    //   1794	1811	372	finally
    //   1826	1836	372	finally
    //   1862	1869	372	finally
    //   1878	1889	372	finally
    //   1908	1915	372	finally
    //   1927	1944	372	finally
    //   1959	1965	372	finally
    //   1980	1991	372	finally
    //   2000	2008	372	finally
    //   2020	2032	372	finally
    //   2041	2050	372	finally
    //   2059	2074	372	finally
    //   2088	2098	372	finally
    //   2107	2116	372	finally
    //   2125	2136	372	finally
    //   2148	2159	372	finally
    //   2168	2176	372	finally
    //   2188	2200	372	finally
    //   2209	2218	372	finally
    //   2227	2242	372	finally
    //   2256	2266	372	finally
    //   2275	2284	372	finally
    //   2293	2304	372	finally
    //   2328	2339	372	finally
    //   2357	2374	372	finally
    //   2389	2399	372	finally
    //   2423	2430	372	finally
    //   2439	2450	372	finally
    //   2468	2475	372	finally
    //   2487	2504	372	finally
    //   2519	2525	372	finally
    //   2540	2554	372	finally
    //   2563	2572	372	finally
    //   2581	2596	372	finally
    //   2610	2620	372	finally
    //   2629	2638	372	finally
    //   2647	2659	372	finally
    //   70	76	714	java/io/IOException
    //   289	302	714	java/io/IOException
    //   317	327	714	java/io/IOException
    //   336	344	714	java/io/IOException
    //   662	673	714	java/io/IOException
    //   691	708	714	java/io/IOException
    //   764	774	714	java/io/IOException
    //   798	805	714	java/io/IOException
    //   814	825	714	java/io/IOException
    //   843	850	714	java/io/IOException
    //   862	879	714	java/io/IOException
    //   894	900	714	java/io/IOException
    //   915	925	714	java/io/IOException
    //   934	942	714	java/io/IOException
    //   954	964	714	java/io/IOException
    //   973	981	714	java/io/IOException
    //   1005	1016	714	java/io/IOException
    //   1034	1052	714	java/io/IOException
    //   1079	1090	714	java/io/IOException
    //   1108	1126	714	java/io/IOException
    //   1153	1164	714	java/io/IOException
    //   1182	1199	714	java/io/IOException
    //   1214	1224	714	java/io/IOException
    //   1248	1255	714	java/io/IOException
    //   1264	1275	714	java/io/IOException
    //   1293	1300	714	java/io/IOException
    //   1312	1329	714	java/io/IOException
    //   1344	1350	714	java/io/IOException
    //   1379	1390	714	java/io/IOException
    //   1409	1427	714	java/io/IOException
    //   1456	1467	714	java/io/IOException
    //   1486	1504	714	java/io/IOException
    //   1533	1544	714	java/io/IOException
    //   1563	1581	714	java/io/IOException
    //   1610	1621	714	java/io/IOException
    //   1640	1658	714	java/io/IOException
    //   1687	1698	714	java/io/IOException
    //   1717	1735	714	java/io/IOException
    //   1764	1775	714	java/io/IOException
    //   1794	1811	714	java/io/IOException
    //   1826	1836	714	java/io/IOException
    //   1862	1869	714	java/io/IOException
    //   1878	1889	714	java/io/IOException
    //   1908	1915	714	java/io/IOException
    //   1927	1944	714	java/io/IOException
    //   1959	1965	714	java/io/IOException
    //   1980	1991	714	java/io/IOException
    //   2000	2008	714	java/io/IOException
    //   2020	2032	714	java/io/IOException
    //   2041	2050	714	java/io/IOException
    //   2059	2074	714	java/io/IOException
    //   2088	2098	714	java/io/IOException
    //   2107	2116	714	java/io/IOException
    //   2125	2136	714	java/io/IOException
    //   2148	2159	714	java/io/IOException
    //   2168	2176	714	java/io/IOException
    //   2188	2200	714	java/io/IOException
    //   2209	2218	714	java/io/IOException
    //   2227	2242	714	java/io/IOException
    //   2256	2266	714	java/io/IOException
    //   2275	2284	714	java/io/IOException
    //   2293	2304	714	java/io/IOException
    //   2328	2339	714	java/io/IOException
    //   2357	2374	714	java/io/IOException
    //   2389	2399	714	java/io/IOException
    //   2423	2430	714	java/io/IOException
    //   2439	2450	714	java/io/IOException
    //   2468	2475	714	java/io/IOException
    //   2487	2504	714	java/io/IOException
    //   2519	2525	714	java/io/IOException
    //   2540	2554	714	java/io/IOException
    //   2563	2572	714	java/io/IOException
    //   2581	2596	714	java/io/IOException
    //   2610	2620	714	java/io/IOException
    //   2629	2638	714	java/io/IOException
    //   2647	2659	714	java/io/IOException
    //   2894	2899	2918	java/io/IOException
    //   2894	2899	2931	finally
    //   616	621	2948	java/io/IOException
    //   616	621	2961	finally
  }
  
  private a$b(i.b<b, ?> paramb)
  {
    super(paramb);
    this.aiXZ = paramb.aiXZ;
  }
  
  public static b a(InputStream paramInputStream, g paramg)
  {
    AppMethodBeat.i(58431);
    paramInputStream = (b)aiYa.j(paramInputStream, paramg);
    AppMethodBeat.o(58431);
    return paramInputStream;
  }
  
  public static b ktK()
  {
    return aiYG;
  }
  
  private void ktf()
  {
    AppMethodBeat.i(58427);
    this.aiYq = 6;
    this.aiYH = 0;
    this.aiYI = 0;
    this.aiYJ = Collections.emptyList();
    this.aiYK = Collections.emptyList();
    this.aiYL = Collections.emptyList();
    this.aiYN = Collections.emptyList();
    this.aiYP = Collections.emptyList();
    this.aiYQ = Collections.emptyList();
    this.aiYR = Collections.emptyList();
    this.aiYS = Collections.emptyList();
    this.aiYT = Collections.emptyList();
    this.aiYU = Collections.emptyList();
    this.aiYW = 0;
    this.aiYX = a.p.kvH();
    this.aiYY = 0;
    this.aiYZ = a.s.kww();
    this.aiZa = Collections.emptyList();
    this.aiZb = a.v.kwR();
    AppMethodBeat.o(58427);
  }
  
  public final void a(f paramf)
  {
    int j = 0;
    AppMethodBeat.i(58429);
    getSerializedSize();
    i.c.a locala = kym();
    if ((this.bitField0_ & 0x1) == 1) {
      paramf.cF(1, this.aiYq);
    }
    if (this.aiYL.size() > 0)
    {
      paramf.lI(18);
      paramf.lI(this.aiYM);
    }
    int i = 0;
    while (i < this.aiYL.size())
    {
      paramf.kd(((Integer)this.aiYL.get(i)).intValue());
      i += 1;
    }
    if ((this.bitField0_ & 0x2) == 2) {
      paramf.cF(3, this.aiYH);
    }
    if ((this.bitField0_ & 0x4) == 4) {
      paramf.cF(4, this.aiYI);
    }
    i = 0;
    while (i < this.aiYJ.size())
    {
      paramf.a(5, (r)this.aiYJ.get(i));
      i += 1;
    }
    i = 0;
    while (i < this.aiYK.size())
    {
      paramf.a(6, (r)this.aiYK.get(i));
      i += 1;
    }
    if (this.aiYN.size() > 0)
    {
      paramf.lI(58);
      paramf.lI(this.aiYO);
    }
    i = 0;
    while (i < this.aiYN.size())
    {
      paramf.kd(((Integer)this.aiYN.get(i)).intValue());
      i += 1;
    }
    i = 0;
    while (i < this.aiYP.size())
    {
      paramf.a(8, (r)this.aiYP.get(i));
      i += 1;
    }
    i = 0;
    while (i < this.aiYQ.size())
    {
      paramf.a(9, (r)this.aiYQ.get(i));
      i += 1;
    }
    i = 0;
    while (i < this.aiYR.size())
    {
      paramf.a(10, (r)this.aiYR.get(i));
      i += 1;
    }
    i = 0;
    while (i < this.aiYS.size())
    {
      paramf.a(11, (r)this.aiYS.get(i));
      i += 1;
    }
    i = 0;
    while (i < this.aiYT.size())
    {
      paramf.a(13, (r)this.aiYT.get(i));
      i += 1;
    }
    if (this.aiYU.size() > 0)
    {
      paramf.lI(130);
      paramf.lI(this.aiYV);
    }
    i = 0;
    while (i < this.aiYU.size())
    {
      paramf.kd(((Integer)this.aiYU.get(i)).intValue());
      i += 1;
    }
    if ((this.bitField0_ & 0x8) == 8) {
      paramf.cF(17, this.aiYW);
    }
    if ((this.bitField0_ & 0x10) == 16) {
      paramf.a(18, this.aiYX);
    }
    if ((this.bitField0_ & 0x20) == 32) {
      paramf.cF(19, this.aiYY);
    }
    i = j;
    if ((this.bitField0_ & 0x40) == 64)
    {
      paramf.a(30, this.aiYZ);
      i = j;
    }
    while (i < this.aiZa.size())
    {
      paramf.cF(31, ((Integer)this.aiZa.get(i)).intValue());
      i += 1;
    }
    if ((this.bitField0_ & 0x80) == 128) {
      paramf.a(32, this.aiZb);
    }
    locala.b(19000, paramf);
    paramf.e(this.aiXZ);
    AppMethodBeat.o(58429);
  }
  
  public final int getSerializedSize()
  {
    AppMethodBeat.i(58430);
    int i = this.dRJ;
    if (i != -1)
    {
      AppMethodBeat.o(58430);
      return i;
    }
    if ((this.bitField0_ & 0x1) == 1) {}
    for (i = f.cJ(1, this.aiYq) + 0;; i = 0)
    {
      int k = 0;
      int j = 0;
      while (k < this.aiYL.size())
      {
        j += f.kp(((Integer)this.aiYL.get(k)).intValue());
        k += 1;
      }
      k = i + j;
      i = k;
      if (!this.aiYL.isEmpty()) {
        i = k + 1 + f.kp(j);
      }
      this.aiYM = j;
      j = i;
      if ((this.bitField0_ & 0x2) == 2) {
        j = i + f.cJ(3, this.aiYH);
      }
      i = j;
      if ((this.bitField0_ & 0x4) == 4) {
        i = j + f.cJ(4, this.aiYI);
      }
      j = 0;
      while (j < this.aiYJ.size())
      {
        i += f.c(5, (r)this.aiYJ.get(j));
        j += 1;
      }
      j = 0;
      while (j < this.aiYK.size())
      {
        i += f.c(6, (r)this.aiYK.get(j));
        j += 1;
      }
      k = 0;
      j = 0;
      while (k < this.aiYN.size())
      {
        j += f.kp(((Integer)this.aiYN.get(k)).intValue());
        k += 1;
      }
      k = i + j;
      i = k;
      if (!this.aiYN.isEmpty()) {
        i = k + 1 + f.kp(j);
      }
      this.aiYO = j;
      j = 0;
      while (j < this.aiYP.size())
      {
        i += f.c(8, (r)this.aiYP.get(j));
        j += 1;
      }
      j = 0;
      while (j < this.aiYQ.size())
      {
        i += f.c(9, (r)this.aiYQ.get(j));
        j += 1;
      }
      j = 0;
      while (j < this.aiYR.size())
      {
        i += f.c(10, (r)this.aiYR.get(j));
        j += 1;
      }
      j = 0;
      while (j < this.aiYS.size())
      {
        i += f.c(11, (r)this.aiYS.get(j));
        j += 1;
      }
      j = 0;
      while (j < this.aiYT.size())
      {
        i += f.c(13, (r)this.aiYT.get(j));
        j += 1;
      }
      k = 0;
      j = 0;
      while (k < this.aiYU.size())
      {
        j += f.kp(((Integer)this.aiYU.get(k)).intValue());
        k += 1;
      }
      k = i + j;
      i = k;
      if (!this.aiYU.isEmpty()) {
        i = k + 2 + f.kp(j);
      }
      this.aiYV = j;
      j = i;
      if ((this.bitField0_ & 0x8) == 8) {
        j = i + f.cJ(17, this.aiYW);
      }
      i = j;
      if ((this.bitField0_ & 0x10) == 16) {
        i = j + f.c(18, this.aiYX);
      }
      j = i;
      if ((this.bitField0_ & 0x20) == 32) {
        j = i + f.cJ(19, this.aiYY);
      }
      if ((this.bitField0_ & 0x40) == 64) {}
      for (i = j + f.c(30, this.aiYZ);; i = j)
      {
        k = 0;
        int m;
        for (j = 0; k < this.aiZa.size(); j = m + j)
        {
          m = f.kp(((Integer)this.aiZa.get(k)).intValue());
          k += 1;
        }
        j = i + j + this.aiZa.size() * 2;
        i = j;
        if ((this.bitField0_ & 0x80) == 128) {
          i = j + f.c(32, this.aiZb);
        }
        i = i + aie() + this.aiXZ.size();
        this.dRJ = i;
        AppMethodBeat.o(58430);
        return i;
      }
    }
  }
  
  public final boolean isInitialized()
  {
    AppMethodBeat.i(58428);
    int i = this.memoizedIsInitialized;
    if (i == 1)
    {
      AppMethodBeat.o(58428);
      return true;
    }
    if (i == 0)
    {
      AppMethodBeat.o(58428);
      return false;
    }
    if (!ktL())
    {
      this.memoizedIsInitialized = 0;
      AppMethodBeat.o(58428);
      return false;
    }
    i = 0;
    while (i < this.aiYJ.size())
    {
      if (!((a.r)this.aiYJ.get(i)).isInitialized())
      {
        this.memoizedIsInitialized = 0;
        AppMethodBeat.o(58428);
        return false;
      }
      i += 1;
    }
    i = 0;
    while (i < this.aiYK.size())
    {
      if (!((a.p)this.aiYK.get(i)).isInitialized())
      {
        this.memoizedIsInitialized = 0;
        AppMethodBeat.o(58428);
        return false;
      }
      i += 1;
    }
    i = 0;
    while (i < this.aiYP.size())
    {
      if (!((a.c)this.aiYP.get(i)).isInitialized())
      {
        this.memoizedIsInitialized = 0;
        AppMethodBeat.o(58428);
        return false;
      }
      i += 1;
    }
    i = 0;
    while (i < this.aiYQ.size())
    {
      if (!((a.h)this.aiYQ.get(i)).isInitialized())
      {
        this.memoizedIsInitialized = 0;
        AppMethodBeat.o(58428);
        return false;
      }
      i += 1;
    }
    i = 0;
    while (i < this.aiYR.size())
    {
      if (!((a.m)this.aiYR.get(i)).isInitialized())
      {
        this.memoizedIsInitialized = 0;
        AppMethodBeat.o(58428);
        return false;
      }
      i += 1;
    }
    i = 0;
    while (i < this.aiYS.size())
    {
      if (!((a.q)this.aiYS.get(i)).isInitialized())
      {
        this.memoizedIsInitialized = 0;
        AppMethodBeat.o(58428);
        return false;
      }
      i += 1;
    }
    i = 0;
    while (i < this.aiYT.size())
    {
      if (!((a.f)this.aiYT.get(i)).isInitialized())
      {
        this.memoizedIsInitialized = 0;
        AppMethodBeat.o(58428);
        return false;
      }
      i += 1;
    }
    if ((ktO()) && (!this.aiYX.isInitialized()))
    {
      this.memoizedIsInitialized = 0;
      AppMethodBeat.o(58428);
      return false;
    }
    if ((ktQ()) && (!this.aiYZ.isInitialized()))
    {
      this.memoizedIsInitialized = 0;
      AppMethodBeat.o(58428);
      return false;
    }
    if (!aic())
    {
      this.memoizedIsInitialized = 0;
      AppMethodBeat.o(58428);
      return false;
    }
    this.memoizedIsInitialized = 1;
    AppMethodBeat.o(58428);
    return true;
  }
  
  public final boolean ktB()
  {
    return (this.bitField0_ & 0x1) == 1;
  }
  
  public final boolean ktL()
  {
    return (this.bitField0_ & 0x2) == 2;
  }
  
  public final boolean ktM()
  {
    return (this.bitField0_ & 0x4) == 4;
  }
  
  public final boolean ktN()
  {
    return (this.bitField0_ & 0x8) == 8;
  }
  
  public final boolean ktO()
  {
    return (this.bitField0_ & 0x10) == 16;
  }
  
  public final boolean ktP()
  {
    return (this.bitField0_ & 0x20) == 32;
  }
  
  public final boolean ktQ()
  {
    return (this.bitField0_ & 0x40) == 64;
  }
  
  public final boolean ktR()
  {
    return (this.bitField0_ & 0x80) == 128;
  }
  
  public static final class a
    extends i.b<a.b, a>
    implements e
  {
    private int aiYH;
    private int aiYI;
    private List<a.r> aiYJ;
    private List<a.p> aiYK;
    private List<Integer> aiYL;
    private List<Integer> aiYN;
    private List<a.c> aiYP;
    private List<a.h> aiYQ;
    private List<a.m> aiYR;
    private List<a.q> aiYS;
    private List<a.f> aiYT;
    private List<Integer> aiYU;
    private int aiYW;
    private a.p aiYX;
    private int aiYY;
    private a.s aiYZ;
    private int aiYq;
    private List<Integer> aiZa;
    private a.v aiZb;
    private int bitField0_;
    
    private a()
    {
      AppMethodBeat.i(58392);
      this.aiYq = 6;
      this.aiYJ = Collections.emptyList();
      this.aiYK = Collections.emptyList();
      this.aiYL = Collections.emptyList();
      this.aiYN = Collections.emptyList();
      this.aiYP = Collections.emptyList();
      this.aiYQ = Collections.emptyList();
      this.aiYR = Collections.emptyList();
      this.aiYS = Collections.emptyList();
      this.aiYT = Collections.emptyList();
      this.aiYU = Collections.emptyList();
      this.aiYX = a.p.kvH();
      this.aiYZ = a.s.kww();
      this.aiZa = Collections.emptyList();
      this.aiZb = a.v.kwR();
      AppMethodBeat.o(58392);
    }
    
    private a a(a.p paramp)
    {
      AppMethodBeat.i(191541);
      if (((this.bitField0_ & 0x4000) == 16384) && (this.aiYX != a.p.kvH())) {}
      for (this.aiYX = a.p.g(this.aiYX).k(paramp).kwd();; this.aiYX = paramp)
      {
        this.bitField0_ |= 0x4000;
        AppMethodBeat.o(191541);
        return this;
      }
    }
    
    private a a(a.s params)
    {
      AppMethodBeat.i(58408);
      if (((this.bitField0_ & 0x10000) == 65536) && (this.aiYZ != a.s.kww())) {}
      for (this.aiYZ = a.s.d(this.aiYZ).g(params).kwz();; this.aiYZ = params)
      {
        this.bitField0_ |= 0x10000;
        AppMethodBeat.o(58408);
        return this;
      }
    }
    
    private a a(a.v paramv)
    {
      AppMethodBeat.i(58410);
      if (((this.bitField0_ & 0x40000) == 262144) && (this.aiZb != a.v.kwR())) {}
      for (this.aiZb = a.v.c(this.aiZb).f(paramv).kwT();; this.aiZb = paramv)
      {
        this.bitField0_ |= 0x40000;
        AppMethodBeat.o(58410);
        return this;
      }
    }
    
    private a aKL(int paramInt)
    {
      this.bitField0_ |= 0x1;
      this.aiYq = paramInt;
      return this;
    }
    
    private a aKM(int paramInt)
    {
      this.bitField0_ |= 0x2;
      this.aiYH = paramInt;
      return this;
    }
    
    private a aKN(int paramInt)
    {
      this.bitField0_ |= 0x4;
      this.aiYI = paramInt;
      return this;
    }
    
    private a aKO(int paramInt)
    {
      this.bitField0_ |= 0x2000;
      this.aiYW = paramInt;
      return this;
    }
    
    private a aKP(int paramInt)
    {
      this.bitField0_ |= 0x8000;
      this.aiYY = paramInt;
      return this;
    }
    
    /* Error */
    private a g(kotlin.l.b.a.b.h.e parame, g paramg)
    {
      // Byte code:
      //   0: ldc 179
      //   2: invokestatic 57	com/tencent/matrix/trace/core/AppMethodBeat:i	(I)V
      //   5: aconst_null
      //   6: astore_3
      //   7: getstatic 183	kotlin/l/b/a/b/e/a$b:aiYa	Lkotlin/l/b/a/b/h/t;
      //   10: aload_1
      //   11: aload_2
      //   12: invokeinterface 188 3 0
      //   17: checkcast 9	kotlin/l/b/a/b/e/a$b
      //   20: astore_1
      //   21: aload_1
      //   22: ifnull +9 -> 31
      //   25: aload_0
      //   26: aload_1
      //   27: invokevirtual 192	kotlin/l/b/a/b/e/a$b$a:m	(Lkotlin/l/b/a/b/e/a$b;)Lkotlin/l/b/a/b/e/a$b$a;
      //   30: pop
      //   31: ldc 179
      //   33: invokestatic 114	com/tencent/matrix/trace/core/AppMethodBeat:o	(I)V
      //   36: aload_0
      //   37: areturn
      //   38: astore_1
      //   39: aload_1
      //   40: getfield 196	kotlin/l/b/a/b/h/l:ajfp	Lkotlin/l/b/a/b/h/r;
      //   43: checkcast 9	kotlin/l/b/a/b/e/a$b
      //   46: astore_2
      //   47: ldc 179
      //   49: invokestatic 114	com/tencent/matrix/trace/core/AppMethodBeat:o	(I)V
      //   52: aload_1
      //   53: athrow
      //   54: astore_1
      //   55: aload_2
      //   56: ifnull +9 -> 65
      //   59: aload_0
      //   60: aload_2
      //   61: invokevirtual 192	kotlin/l/b/a/b/e/a$b$a:m	(Lkotlin/l/b/a/b/e/a$b;)Lkotlin/l/b/a/b/e/a$b$a;
      //   64: pop
      //   65: ldc 179
      //   67: invokestatic 114	com/tencent/matrix/trace/core/AppMethodBeat:o	(I)V
      //   70: aload_1
      //   71: athrow
      //   72: astore_1
      //   73: aload_3
      //   74: astore_2
      //   75: goto -20 -> 55
      // Local variable table:
      //   start	length	slot	name	signature
      //   0	78	0	this	a
      //   0	78	1	parame	kotlin.l.b.a.b.h.e
      //   0	78	2	paramg	g
      //   6	68	3	localObject	Object
      // Exception table:
      //   from	to	target	type
      //   7	21	38	kotlin/l/b/a/b/h/l
      //   47	54	54	finally
      //   7	21	72	finally
      //   39	47	72	finally
    }
    
    private a ktS()
    {
      AppMethodBeat.i(58393);
      a locala = new a().m(ktT());
      AppMethodBeat.o(58393);
      return locala;
    }
    
    private a.b ktT()
    {
      int j = 1;
      AppMethodBeat.i(58394);
      a.b localb = new a.b(this, (byte)0);
      int k = this.bitField0_;
      if ((k & 0x1) == 1) {}
      for (;;)
      {
        a.b.a(localb, this.aiYq);
        int i = j;
        if ((k & 0x2) == 2) {
          i = j | 0x2;
        }
        a.b.b(localb, this.aiYH);
        j = i;
        if ((k & 0x4) == 4) {
          j = i | 0x4;
        }
        a.b.c(localb, this.aiYI);
        if ((this.bitField0_ & 0x8) == 8)
        {
          this.aiYJ = Collections.unmodifiableList(this.aiYJ);
          this.bitField0_ &= 0xFFFFFFF7;
        }
        a.b.a(localb, this.aiYJ);
        if ((this.bitField0_ & 0x10) == 16)
        {
          this.aiYK = Collections.unmodifiableList(this.aiYK);
          this.bitField0_ &= 0xFFFFFFEF;
        }
        a.b.b(localb, this.aiYK);
        if ((this.bitField0_ & 0x20) == 32)
        {
          this.aiYL = Collections.unmodifiableList(this.aiYL);
          this.bitField0_ &= 0xFFFFFFDF;
        }
        a.b.c(localb, this.aiYL);
        if ((this.bitField0_ & 0x40) == 64)
        {
          this.aiYN = Collections.unmodifiableList(this.aiYN);
          this.bitField0_ &= 0xFFFFFFBF;
        }
        a.b.d(localb, this.aiYN);
        if ((this.bitField0_ & 0x80) == 128)
        {
          this.aiYP = Collections.unmodifiableList(this.aiYP);
          this.bitField0_ &= 0xFFFFFF7F;
        }
        a.b.e(localb, this.aiYP);
        if ((this.bitField0_ & 0x100) == 256)
        {
          this.aiYQ = Collections.unmodifiableList(this.aiYQ);
          this.bitField0_ &= 0xFFFFFEFF;
        }
        a.b.f(localb, this.aiYQ);
        if ((this.bitField0_ & 0x200) == 512)
        {
          this.aiYR = Collections.unmodifiableList(this.aiYR);
          this.bitField0_ &= 0xFFFFFDFF;
        }
        a.b.g(localb, this.aiYR);
        if ((this.bitField0_ & 0x400) == 1024)
        {
          this.aiYS = Collections.unmodifiableList(this.aiYS);
          this.bitField0_ &= 0xFFFFFBFF;
        }
        a.b.h(localb, this.aiYS);
        if ((this.bitField0_ & 0x800) == 2048)
        {
          this.aiYT = Collections.unmodifiableList(this.aiYT);
          this.bitField0_ &= 0xFFFFF7FF;
        }
        a.b.i(localb, this.aiYT);
        if ((this.bitField0_ & 0x1000) == 4096)
        {
          this.aiYU = Collections.unmodifiableList(this.aiYU);
          this.bitField0_ &= 0xFFFFEFFF;
        }
        a.b.j(localb, this.aiYU);
        i = j;
        if ((k & 0x2000) == 8192) {
          i = j | 0x8;
        }
        a.b.d(localb, this.aiYW);
        j = i;
        if ((k & 0x4000) == 16384) {
          j = i | 0x10;
        }
        a.b.a(localb, this.aiYX);
        i = j;
        if ((k & 0x8000) == 32768) {
          i = j | 0x20;
        }
        a.b.e(localb, this.aiYY);
        j = i;
        if ((k & 0x10000) == 65536) {
          j = i | 0x40;
        }
        a.b.a(localb, this.aiYZ);
        if ((this.bitField0_ & 0x20000) == 131072)
        {
          this.aiZa = Collections.unmodifiableList(this.aiZa);
          this.bitField0_ &= 0xFFFDFFFF;
        }
        a.b.k(localb, this.aiZa);
        i = j;
        if ((0x40000 & k) == 262144) {
          i = j | 0x80;
        }
        a.b.a(localb, this.aiZb);
        a.b.f(localb, i);
        AppMethodBeat.o(58394);
        return localb;
        j = 0;
      }
    }
    
    private void ktU()
    {
      AppMethodBeat.i(58398);
      if ((this.bitField0_ & 0x8) != 8)
      {
        this.aiYJ = new ArrayList(this.aiYJ);
        this.bitField0_ |= 0x8;
      }
      AppMethodBeat.o(58398);
    }
    
    private void ktV()
    {
      AppMethodBeat.i(58399);
      if ((this.bitField0_ & 0x10) != 16)
      {
        this.aiYK = new ArrayList(this.aiYK);
        this.bitField0_ |= 0x10;
      }
      AppMethodBeat.o(58399);
    }
    
    private void ktW()
    {
      AppMethodBeat.i(58400);
      if ((this.bitField0_ & 0x20) != 32)
      {
        this.aiYL = new ArrayList(this.aiYL);
        this.bitField0_ |= 0x20;
      }
      AppMethodBeat.o(58400);
    }
    
    private void ktX()
    {
      AppMethodBeat.i(58401);
      if ((this.bitField0_ & 0x40) != 64)
      {
        this.aiYN = new ArrayList(this.aiYN);
        this.bitField0_ |= 0x40;
      }
      AppMethodBeat.o(58401);
    }
    
    private void ktY()
    {
      AppMethodBeat.i(58402);
      if ((this.bitField0_ & 0x80) != 128)
      {
        this.aiYP = new ArrayList(this.aiYP);
        this.bitField0_ |= 0x80;
      }
      AppMethodBeat.o(58402);
    }
    
    private void ktZ()
    {
      AppMethodBeat.i(58403);
      if ((this.bitField0_ & 0x100) != 256)
      {
        this.aiYQ = new ArrayList(this.aiYQ);
        this.bitField0_ |= 0x100;
      }
      AppMethodBeat.o(58403);
    }
    
    private void kua()
    {
      AppMethodBeat.i(58404);
      if ((this.bitField0_ & 0x200) != 512)
      {
        this.aiYR = new ArrayList(this.aiYR);
        this.bitField0_ |= 0x200;
      }
      AppMethodBeat.o(58404);
    }
    
    private void kub()
    {
      AppMethodBeat.i(58405);
      if ((this.bitField0_ & 0x400) != 1024)
      {
        this.aiYS = new ArrayList(this.aiYS);
        this.bitField0_ |= 0x400;
      }
      AppMethodBeat.o(58405);
    }
    
    private void kuc()
    {
      AppMethodBeat.i(58406);
      if ((this.bitField0_ & 0x800) != 2048)
      {
        this.aiYT = new ArrayList(this.aiYT);
        this.bitField0_ |= 0x800;
      }
      AppMethodBeat.o(58406);
    }
    
    private void kud()
    {
      AppMethodBeat.i(58407);
      if ((this.bitField0_ & 0x1000) != 4096)
      {
        this.aiYU = new ArrayList(this.aiYU);
        this.bitField0_ |= 0x1000;
      }
      AppMethodBeat.o(58407);
    }
    
    private void kue()
    {
      AppMethodBeat.i(58409);
      if ((this.bitField0_ & 0x20000) != 131072)
      {
        this.aiZa = new ArrayList(this.aiZa);
        this.bitField0_ |= 0x20000;
      }
      AppMethodBeat.o(58409);
    }
    
    public final boolean isInitialized()
    {
      AppMethodBeat.i(58396);
      if ((this.bitField0_ & 0x2) == 2) {}
      for (int i = 1; i == 0; i = 0)
      {
        AppMethodBeat.o(58396);
        return false;
      }
      i = 0;
      while (i < this.aiYJ.size())
      {
        if (!((a.r)this.aiYJ.get(i)).isInitialized())
        {
          AppMethodBeat.o(58396);
          return false;
        }
        i += 1;
      }
      i = 0;
      while (i < this.aiYK.size())
      {
        if (!((a.p)this.aiYK.get(i)).isInitialized())
        {
          AppMethodBeat.o(58396);
          return false;
        }
        i += 1;
      }
      i = 0;
      while (i < this.aiYP.size())
      {
        if (!((a.c)this.aiYP.get(i)).isInitialized())
        {
          AppMethodBeat.o(58396);
          return false;
        }
        i += 1;
      }
      i = 0;
      while (i < this.aiYQ.size())
      {
        if (!((a.h)this.aiYQ.get(i)).isInitialized())
        {
          AppMethodBeat.o(58396);
          return false;
        }
        i += 1;
      }
      i = 0;
      while (i < this.aiYR.size())
      {
        if (!((a.m)this.aiYR.get(i)).isInitialized())
        {
          AppMethodBeat.o(58396);
          return false;
        }
        i += 1;
      }
      i = 0;
      while (i < this.aiYS.size())
      {
        if (!((a.q)this.aiYS.get(i)).isInitialized())
        {
          AppMethodBeat.o(58396);
          return false;
        }
        i += 1;
      }
      i = 0;
      while (i < this.aiYT.size())
      {
        if (!((a.f)this.aiYT.get(i)).isInitialized())
        {
          AppMethodBeat.o(58396);
          return false;
        }
        i += 1;
      }
      if ((this.bitField0_ & 0x4000) == 16384) {}
      for (i = 1; (i != 0) && (!this.aiYX.isInitialized()); i = 0)
      {
        AppMethodBeat.o(58396);
        return false;
      }
      if ((this.bitField0_ & 0x10000) == 65536) {}
      for (i = 1; (i != 0) && (!this.aiYZ.isInitialized()); i = 0)
      {
        AppMethodBeat.o(58396);
        return false;
      }
      if (!aic())
      {
        AppMethodBeat.o(58396);
        return false;
      }
      AppMethodBeat.o(58396);
      return true;
    }
    
    public final a m(a.b paramb)
    {
      AppMethodBeat.i(58395);
      if (paramb == a.b.ktK())
      {
        AppMethodBeat.o(58395);
        return this;
      }
      if (paramb.ktB()) {
        aKL(paramb.aiYq);
      }
      if (paramb.ktL()) {
        aKM(paramb.aiYH);
      }
      if (paramb.ktM()) {
        aKN(paramb.aiYI);
      }
      if (!a.b.a(paramb).isEmpty())
      {
        if (this.aiYJ.isEmpty())
        {
          this.aiYJ = a.b.a(paramb);
          this.bitField0_ &= 0xFFFFFFF7;
        }
      }
      else
      {
        if (!a.b.b(paramb).isEmpty())
        {
          if (!this.aiYK.isEmpty()) {
            break label677;
          }
          this.aiYK = a.b.b(paramb);
          this.bitField0_ &= 0xFFFFFFEF;
        }
        label155:
        if (!a.b.c(paramb).isEmpty())
        {
          if (!this.aiYL.isEmpty()) {
            break label698;
          }
          this.aiYL = a.b.c(paramb);
          this.bitField0_ &= 0xFFFFFFDF;
        }
        label198:
        if (!a.b.d(paramb).isEmpty())
        {
          if (!this.aiYN.isEmpty()) {
            break label719;
          }
          this.aiYN = a.b.d(paramb);
          this.bitField0_ &= 0xFFFFFFBF;
        }
        label241:
        if (!a.b.e(paramb).isEmpty())
        {
          if (!this.aiYP.isEmpty()) {
            break label740;
          }
          this.aiYP = a.b.e(paramb);
          this.bitField0_ &= 0xFFFFFF7F;
        }
        label285:
        if (!a.b.f(paramb).isEmpty())
        {
          if (!this.aiYQ.isEmpty()) {
            break label761;
          }
          this.aiYQ = a.b.f(paramb);
          this.bitField0_ &= 0xFFFFFEFF;
        }
        label329:
        if (!a.b.g(paramb).isEmpty())
        {
          if (!this.aiYR.isEmpty()) {
            break label782;
          }
          this.aiYR = a.b.g(paramb);
          this.bitField0_ &= 0xFFFFFDFF;
        }
        label373:
        if (!a.b.h(paramb).isEmpty())
        {
          if (!this.aiYS.isEmpty()) {
            break label803;
          }
          this.aiYS = a.b.h(paramb);
          this.bitField0_ &= 0xFFFFFBFF;
        }
        label417:
        if (!a.b.i(paramb).isEmpty())
        {
          if (!this.aiYT.isEmpty()) {
            break label824;
          }
          this.aiYT = a.b.i(paramb);
          this.bitField0_ &= 0xFFFFF7FF;
        }
        label461:
        if (!a.b.j(paramb).isEmpty())
        {
          if (!this.aiYU.isEmpty()) {
            break label845;
          }
          this.aiYU = a.b.j(paramb);
          this.bitField0_ &= 0xFFFFEFFF;
        }
        label505:
        if (paramb.ktN()) {
          aKO(paramb.aiYW);
        }
        if (paramb.ktO()) {
          a(paramb.aiYX);
        }
        if (paramb.ktP()) {
          aKP(paramb.aiYY);
        }
        if (paramb.ktQ()) {
          a(paramb.aiYZ);
        }
        if (!a.b.k(paramb).isEmpty())
        {
          if (!this.aiZa.isEmpty()) {
            break label866;
          }
          this.aiZa = a.b.k(paramb);
          this.bitField0_ &= 0xFFFDFFFF;
        }
      }
      for (;;)
      {
        if (paramb.ktR()) {
          a(paramb.aiZb);
        }
        a(paramb);
        this.aiXZ = this.aiXZ.a(a.b.l(paramb));
        AppMethodBeat.o(58395);
        return this;
        ktU();
        this.aiYJ.addAll(a.b.a(paramb));
        break;
        label677:
        ktV();
        this.aiYK.addAll(a.b.b(paramb));
        break label155;
        label698:
        ktW();
        this.aiYL.addAll(a.b.c(paramb));
        break label198;
        label719:
        ktX();
        this.aiYN.addAll(a.b.d(paramb));
        break label241;
        label740:
        ktY();
        this.aiYP.addAll(a.b.e(paramb));
        break label285;
        label761:
        ktZ();
        this.aiYQ.addAll(a.b.f(paramb));
        break label329;
        label782:
        kua();
        this.aiYR.addAll(a.b.g(paramb));
        break label373;
        label803:
        kub();
        this.aiYS.addAll(a.b.h(paramb));
        break label417;
        label824:
        kuc();
        this.aiYT.addAll(a.b.i(paramb));
        break label461;
        label845:
        kud();
        this.aiYU.addAll(a.b.j(paramb));
        break label505;
        label866:
        kue();
        this.aiZa.addAll(a.b.k(paramb));
      }
    }
  }
  
  public static enum b
    implements k.a
  {
    private static k.b<b> aiYE;
    private final int value;
    
    static
    {
      AppMethodBeat.i(58425);
      aiZc = new b("CLASS", 0, 0);
      aiZd = new b("INTERFACE", 1, 1);
      aiZe = new b("ENUM_CLASS", 2, 2);
      aiZf = new b("ENUM_ENTRY", 3, 3);
      aiZg = new b("ANNOTATION_CLASS", 4, 4);
      aiZh = new b("OBJECT", 5, 5);
      aiZi = new b("COMPANION_OBJECT", 6, 6);
      aiZj = new b[] { aiZc, aiZd, aiZe, aiZf, aiZg, aiZh, aiZi };
      aiYE = new k.b() {};
      AppMethodBeat.o(58425);
    }
    
    private b(int paramInt)
    {
      this.value = paramInt;
    }
    
    public static b aKQ(int paramInt)
    {
      switch (paramInt)
      {
      default: 
        return null;
      case 0: 
        return aiZc;
      case 1: 
        return aiZd;
      case 2: 
        return aiZe;
      case 3: 
        return aiZf;
      case 4: 
        return aiZg;
      case 5: 
        return aiZh;
      }
      return aiZi;
    }
    
    public final int getNumber()
    {
      return this.value;
    }
  }
}


/* Location:           L:\local\mybackup\temp\qq_apk\com.tencent.mm\classes11.jar
 * Qualified Name:     kotlin.l.b.a.b.e.a.b
 * JD-Core Version:    0.7.0.1
 */