package com.tencent.mobileqq.msf.core.net;

class v
  extends Thread
{
  v(n paramn) {}
  
  /* Error */
  public void run()
  {
    // Byte code:
    //   0: aload_0
    //   1: getfield 10	com/tencent/mobileqq/msf/core/net/v:a	Lcom/tencent/mobileqq/msf/core/net/n;
    //   4: iconst_0
    //   5: invokestatic 22	com/tencent/mobileqq/msf/core/net/n:a	(Lcom/tencent/mobileqq/msf/core/net/n;I)I
    //   8: pop
    //   9: aload_0
    //   10: getfield 10	com/tencent/mobileqq/msf/core/net/v:a	Lcom/tencent/mobileqq/msf/core/net/n;
    //   13: iconst_0
    //   14: invokestatic 26	com/tencent/mobileqq/msf/core/net/n:c	(Lcom/tencent/mobileqq/msf/core/net/n;Z)Z
    //   17: pop
    //   18: ldc 28
    //   20: invokevirtual 34	java/lang/String:getBytes	()[B
    //   23: astore 8
    //   25: sipush 128
    //   28: newarray byte
    //   30: astore 9
    //   32: aconst_null
    //   33: astore 7
    //   35: aconst_null
    //   36: astore 6
    //   38: aload 6
    //   40: astore 5
    //   42: new 36	java/net/URL
    //   45: dup
    //   46: ldc 38
    //   48: invokespecial 41	java/net/URL:<init>	(Ljava/lang/String;)V
    //   51: astore 10
    //   53: aload 6
    //   55: astore 5
    //   57: invokestatic 47	java/lang/System:currentTimeMillis	()J
    //   60: lstore_3
    //   61: aload 6
    //   63: astore 5
    //   65: invokestatic 53	com/tencent/qphone/base/util/QLog:isColorLevel	()Z
    //   68: ifeq +15 -> 83
    //   71: aload 6
    //   73: astore 5
    //   75: ldc 55
    //   77: iconst_2
    //   78: ldc 57
    //   80: invokestatic 61	com/tencent/qphone/base/util/QLog:d	(Ljava/lang/String;ILjava/lang/String;)V
    //   83: aload 6
    //   85: astore 5
    //   87: aload 10
    //   89: invokevirtual 65	java/net/URL:openConnection	()Ljava/net/URLConnection;
    //   92: checkcast 67	java/net/HttpURLConnection
    //   95: astore 6
    //   97: aload 6
    //   99: iconst_1
    //   100: invokevirtual 71	java/net/HttpURLConnection:setDoOutput	(Z)V
    //   103: aload 6
    //   105: ldc 73
    //   107: invokevirtual 76	java/net/HttpURLConnection:setRequestMethod	(Ljava/lang/String;)V
    //   110: aload 6
    //   112: sipush 10000
    //   115: invokevirtual 80	java/net/HttpURLConnection:setConnectTimeout	(I)V
    //   118: aload 6
    //   120: sipush 10000
    //   123: invokevirtual 83	java/net/HttpURLConnection:setReadTimeout	(I)V
    //   126: aload 6
    //   128: invokevirtual 87	java/net/HttpURLConnection:getOutputStream	()Ljava/io/OutputStream;
    //   131: aload 8
    //   133: invokevirtual 93	java/io/OutputStream:write	([B)V
    //   136: aload 6
    //   138: invokevirtual 87	java/net/HttpURLConnection:getOutputStream	()Ljava/io/OutputStream;
    //   141: invokevirtual 96	java/io/OutputStream:flush	()V
    //   144: aload 6
    //   146: invokevirtual 87	java/net/HttpURLConnection:getOutputStream	()Ljava/io/OutputStream;
    //   149: invokevirtual 99	java/io/OutputStream:close	()V
    //   152: aload 6
    //   154: invokevirtual 103	java/net/HttpURLConnection:getInputStream	()Ljava/io/InputStream;
    //   157: aload 9
    //   159: invokevirtual 109	java/io/InputStream:read	([B)I
    //   162: istore_1
    //   163: aload 6
    //   165: invokevirtual 113	java/net/HttpURLConnection:getResponseCode	()I
    //   168: istore_2
    //   169: iload_2
    //   170: sipush 200
    //   173: if_icmpne +112 -> 285
    //   176: aload 10
    //   178: invokevirtual 117	java/net/URL:getHost	()Ljava/lang/String;
    //   181: aload 6
    //   183: invokevirtual 121	java/net/HttpURLConnection:getURL	()Ljava/net/URL;
    //   186: invokevirtual 117	java/net/URL:getHost	()Ljava/lang/String;
    //   189: invokevirtual 125	java/lang/String:equals	(Ljava/lang/Object;)Z
    //   192: ifeq +93 -> 285
    //   195: new 127	java/lang/StringBuilder
    //   198: dup
    //   199: invokespecial 128	java/lang/StringBuilder:<init>	()V
    //   202: astore 5
    //   204: aload 5
    //   206: ldc 130
    //   208: invokevirtual 134	java/lang/StringBuilder:append	(Ljava/lang/String;)Ljava/lang/StringBuilder;
    //   211: pop
    //   212: aload 5
    //   214: iload_2
    //   215: invokevirtual 137	java/lang/StringBuilder:append	(I)Ljava/lang/StringBuilder;
    //   218: pop
    //   219: aload 5
    //   221: ldc 139
    //   223: invokevirtual 134	java/lang/StringBuilder:append	(Ljava/lang/String;)Ljava/lang/StringBuilder;
    //   226: pop
    //   227: aload 5
    //   229: invokestatic 47	java/lang/System:currentTimeMillis	()J
    //   232: lload_3
    //   233: lsub
    //   234: invokevirtual 142	java/lang/StringBuilder:append	(J)Ljava/lang/StringBuilder;
    //   237: pop
    //   238: aload 5
    //   240: ldc 144
    //   242: invokevirtual 134	java/lang/StringBuilder:append	(Ljava/lang/String;)Ljava/lang/StringBuilder;
    //   245: pop
    //   246: aload 5
    //   248: iload_1
    //   249: invokevirtual 137	java/lang/StringBuilder:append	(I)Ljava/lang/StringBuilder;
    //   252: pop
    //   253: ldc 55
    //   255: iconst_1
    //   256: aload 5
    //   258: invokevirtual 147	java/lang/StringBuilder:toString	()Ljava/lang/String;
    //   261: invokestatic 61	com/tencent/qphone/base/util/QLog:d	(Ljava/lang/String;ILjava/lang/String;)V
    //   264: aload_0
    //   265: getfield 10	com/tencent/mobileqq/msf/core/net/v:a	Lcom/tencent/mobileqq/msf/core/net/n;
    //   268: iload_2
    //   269: invokestatic 22	com/tencent/mobileqq/msf/core/net/n:a	(Lcom/tencent/mobileqq/msf/core/net/n;I)I
    //   272: pop
    //   273: aload_0
    //   274: getfield 10	com/tencent/mobileqq/msf/core/net/v:a	Lcom/tencent/mobileqq/msf/core/net/n;
    //   277: iconst_1
    //   278: invokestatic 26	com/tencent/mobileqq/msf/core/net/n:c	(Lcom/tencent/mobileqq/msf/core/net/n;Z)Z
    //   281: pop
    //   282: goto +83 -> 365
    //   285: new 127	java/lang/StringBuilder
    //   288: dup
    //   289: invokespecial 128	java/lang/StringBuilder:<init>	()V
    //   292: astore 5
    //   294: aload 5
    //   296: ldc 149
    //   298: invokevirtual 134	java/lang/StringBuilder:append	(Ljava/lang/String;)Ljava/lang/StringBuilder;
    //   301: pop
    //   302: aload 5
    //   304: iload_2
    //   305: invokevirtual 137	java/lang/StringBuilder:append	(I)Ljava/lang/StringBuilder;
    //   308: pop
    //   309: aload 5
    //   311: invokevirtual 147	java/lang/StringBuilder:toString	()Ljava/lang/String;
    //   314: pop
    //   315: new 127	java/lang/StringBuilder
    //   318: dup
    //   319: invokespecial 128	java/lang/StringBuilder:<init>	()V
    //   322: astore 5
    //   324: aload 5
    //   326: ldc 151
    //   328: invokevirtual 134	java/lang/StringBuilder:append	(Ljava/lang/String;)Ljava/lang/StringBuilder;
    //   331: pop
    //   332: aload 5
    //   334: iload_2
    //   335: invokevirtual 137	java/lang/StringBuilder:append	(I)Ljava/lang/StringBuilder;
    //   338: pop
    //   339: aload 5
    //   341: ldc 144
    //   343: invokevirtual 134	java/lang/StringBuilder:append	(Ljava/lang/String;)Ljava/lang/StringBuilder;
    //   346: pop
    //   347: aload 5
    //   349: iload_1
    //   350: invokevirtual 137	java/lang/StringBuilder:append	(I)Ljava/lang/StringBuilder;
    //   353: pop
    //   354: ldc 55
    //   356: iconst_1
    //   357: aload 5
    //   359: invokevirtual 147	java/lang/StringBuilder:toString	()Ljava/lang/String;
    //   362: invokestatic 61	com/tencent/qphone/base/util/QLog:d	(Ljava/lang/String;ILjava/lang/String;)V
    //   365: aload 6
    //   367: ifnull +145 -> 512
    //   370: aload 6
    //   372: invokevirtual 154	java/net/HttpURLConnection:disconnect	()V
    //   375: goto +137 -> 512
    //   378: astore 5
    //   380: goto +144 -> 524
    //   383: astore 7
    //   385: goto +26 -> 411
    //   388: astore 7
    //   390: aload 5
    //   392: astore 6
    //   394: aload 7
    //   396: astore 5
    //   398: goto +126 -> 524
    //   401: astore 5
    //   403: aload 7
    //   405: astore 6
    //   407: aload 5
    //   409: astore 7
    //   411: aload 6
    //   413: astore 5
    //   415: aload 7
    //   417: invokevirtual 155	java/lang/Throwable:toString	()Ljava/lang/String;
    //   420: astore 8
    //   422: aload 6
    //   424: astore 5
    //   426: aload_0
    //   427: getfield 10	com/tencent/mobileqq/msf/core/net/v:a	Lcom/tencent/mobileqq/msf/core/net/n;
    //   430: iconst_0
    //   431: invokestatic 22	com/tencent/mobileqq/msf/core/net/n:a	(Lcom/tencent/mobileqq/msf/core/net/n;I)I
    //   434: pop
    //   435: aload 6
    //   437: astore 5
    //   439: aload_0
    //   440: getfield 10	com/tencent/mobileqq/msf/core/net/v:a	Lcom/tencent/mobileqq/msf/core/net/n;
    //   443: iconst_0
    //   444: invokestatic 26	com/tencent/mobileqq/msf/core/net/n:c	(Lcom/tencent/mobileqq/msf/core/net/n;Z)Z
    //   447: pop
    //   448: aload 6
    //   450: astore 5
    //   452: new 127	java/lang/StringBuilder
    //   455: dup
    //   456: invokespecial 128	java/lang/StringBuilder:<init>	()V
    //   459: astore 9
    //   461: aload 6
    //   463: astore 5
    //   465: aload 9
    //   467: ldc 157
    //   469: invokevirtual 134	java/lang/StringBuilder:append	(Ljava/lang/String;)Ljava/lang/StringBuilder;
    //   472: pop
    //   473: aload 6
    //   475: astore 5
    //   477: aload 9
    //   479: aload 8
    //   481: invokevirtual 134	java/lang/StringBuilder:append	(Ljava/lang/String;)Ljava/lang/StringBuilder;
    //   484: pop
    //   485: aload 6
    //   487: astore 5
    //   489: ldc 55
    //   491: iconst_1
    //   492: aload 9
    //   494: invokevirtual 147	java/lang/StringBuilder:toString	()Ljava/lang/String;
    //   497: aload 7
    //   499: invokestatic 160	com/tencent/qphone/base/util/QLog:d	(Ljava/lang/String;ILjava/lang/String;Ljava/lang/Throwable;)V
    //   502: aload 6
    //   504: ifnull +8 -> 512
    //   507: aload 6
    //   509: invokevirtual 154	java/net/HttpURLConnection:disconnect	()V
    //   512: aload_0
    //   513: getfield 10	com/tencent/mobileqq/msf/core/net/v:a	Lcom/tencent/mobileqq/msf/core/net/n;
    //   516: invokestatic 47	java/lang/System:currentTimeMillis	()J
    //   519: invokestatic 164	com/tencent/mobileqq/msf/core/net/n:b	(Lcom/tencent/mobileqq/msf/core/net/n;J)J
    //   522: pop2
    //   523: return
    //   524: aload 6
    //   526: ifnull +8 -> 534
    //   529: aload 6
    //   531: invokevirtual 154	java/net/HttpURLConnection:disconnect	()V
    //   534: aload_0
    //   535: getfield 10	com/tencent/mobileqq/msf/core/net/v:a	Lcom/tencent/mobileqq/msf/core/net/n;
    //   538: invokestatic 47	java/lang/System:currentTimeMillis	()J
    //   541: invokestatic 164	com/tencent/mobileqq/msf/core/net/n:b	(Lcom/tencent/mobileqq/msf/core/net/n;J)J
    //   544: pop2
    //   545: aload 5
    //   547: athrow
    // Local variable table:
    //   start	length	slot	name	signature
    //   0	548	0	this	v
    //   162	188	1	i	int
    //   168	167	2	j	int
    //   60	173	3	l	long
    //   40	318	5	localObject1	java.lang.Object
    //   378	13	5	localObject2	java.lang.Object
    //   396	1	5	localObject3	java.lang.Object
    //   401	7	5	localThrowable1	java.lang.Throwable
    //   413	133	5	localObject4	java.lang.Object
    //   36	494	6	localObject5	java.lang.Object
    //   33	1	7	localObject6	java.lang.Object
    //   383	1	7	localThrowable2	java.lang.Throwable
    //   388	16	7	localObject7	java.lang.Object
    //   409	89	7	localObject8	java.lang.Object
    //   23	457	8	localObject9	java.lang.Object
    //   30	463	9	localObject10	java.lang.Object
    //   51	126	10	localURL	java.net.URL
    // Exception table:
    //   from	to	target	type
    //   97	169	378	finally
    //   176	282	378	finally
    //   285	365	378	finally
    //   97	169	383	java/lang/Throwable
    //   176	282	383	java/lang/Throwable
    //   285	365	383	java/lang/Throwable
    //   42	53	388	finally
    //   57	61	388	finally
    //   65	71	388	finally
    //   75	83	388	finally
    //   87	97	388	finally
    //   415	422	388	finally
    //   426	435	388	finally
    //   439	448	388	finally
    //   452	461	388	finally
    //   465	473	388	finally
    //   477	485	388	finally
    //   489	502	388	finally
    //   42	53	401	java/lang/Throwable
    //   57	61	401	java/lang/Throwable
    //   65	71	401	java/lang/Throwable
    //   75	83	401	java/lang/Throwable
    //   87	97	401	java/lang/Throwable
  }
}


/* Location:           L:\local\mybackup\temp\qq_apk\com.tencent.mobileqq\classes7.jar
 * Qualified Name:     com.tencent.mobileqq.msf.core.net.v
 * JD-Core Version:    0.7.0.1
 */