package com.tencent.biz.pubaccount.readinjoy.comment;

import mqq.observer.BusinessObserver;

final class NativeCommentServlet$1
  implements BusinessObserver
{
  /* Error */
  public void onReceive(int paramInt, boolean paramBoolean, android.os.Bundle paramBundle)
  {
    // Byte code:
    //   0: iconst_0
    //   1: istore 5
    //   3: iconst_0
    //   4: istore_1
    //   5: iload_2
    //   6: ifeq +279 -> 285
    //   9: aload_3
    //   10: ldc 16
    //   12: invokevirtual 22	android/os/Bundle:getByteArray	(Ljava/lang/String;)[B
    //   15: astore_3
    //   16: aload_3
    //   17: ifnull +268 -> 285
    //   20: new 24	com/tencent/mobileqq/WebSsoBody$WebSsoResponseBody
    //   23: dup
    //   24: invokespecial 28	com/tencent/mobileqq/WebSsoBody$WebSsoResponseBody:<init>	()V
    //   27: astore 6
    //   29: aload 6
    //   31: aload_3
    //   32: invokevirtual 32	com/tencent/mobileqq/WebSsoBody$WebSsoResponseBody:mergeFrom	([B)Lcom/tencent/mobileqq/pb/MessageMicro;
    //   35: pop
    //   36: aload 6
    //   38: getfield 36	com/tencent/mobileqq/WebSsoBody$WebSsoResponseBody:ret	Lcom/tencent/mobileqq/pb/PBUInt32Field;
    //   41: invokevirtual 42	com/tencent/mobileqq/pb/PBUInt32Field:get	()I
    //   44: istore 4
    //   46: iload 4
    //   48: istore_1
    //   49: iload 5
    //   51: istore 4
    //   53: aload 6
    //   55: getfield 45	com/tencent/mobileqq/WebSsoBody$WebSsoResponseBody:data	Lcom/tencent/mobileqq/pb/PBStringField;
    //   58: invokevirtual 50	com/tencent/mobileqq/pb/PBStringField:get	()Ljava/lang/String;
    //   61: astore_3
    //   62: iload 5
    //   64: istore 4
    //   66: invokestatic 56	com/tencent/qphone/base/util/QLog:isColorLevel	()Z
    //   69: ifeq +44 -> 113
    //   72: iload 5
    //   74: istore 4
    //   76: ldc 58
    //   78: iconst_2
    //   79: new 60	java/lang/StringBuilder
    //   82: dup
    //   83: invokespecial 61	java/lang/StringBuilder:<init>	()V
    //   86: ldc 63
    //   88: invokevirtual 67	java/lang/StringBuilder:append	(Ljava/lang/String;)Ljava/lang/StringBuilder;
    //   91: aload_0
    //   92: getfield 69	com/tencent/biz/pubaccount/readinjoy/comment/NativeCommentServlet$1:jdField_a_of_type_JavaLangString	Ljava/lang/String;
    //   95: invokevirtual 67	java/lang/StringBuilder:append	(Ljava/lang/String;)Ljava/lang/StringBuilder;
    //   98: ldc 71
    //   100: invokevirtual 67	java/lang/StringBuilder:append	(Ljava/lang/String;)Ljava/lang/StringBuilder;
    //   103: aload_3
    //   104: invokevirtual 67	java/lang/StringBuilder:append	(Ljava/lang/String;)Ljava/lang/StringBuilder;
    //   107: invokevirtual 74	java/lang/StringBuilder:toString	()Ljava/lang/String;
    //   110: invokestatic 78	com/tencent/qphone/base/util/QLog:d	(Ljava/lang/String;ILjava/lang/String;)V
    //   113: aconst_null
    //   114: astore 6
    //   116: iload 5
    //   118: istore 4
    //   120: aload_3
    //   121: invokestatic 84	android/text/TextUtils:isEmpty	(Ljava/lang/CharSequence;)Z
    //   124: ifne +17 -> 141
    //   127: iload 5
    //   129: istore 4
    //   131: new 86	org/json/JSONObject
    //   134: dup
    //   135: aload_3
    //   136: invokespecial 89	org/json/JSONObject:<init>	(Ljava/lang/String;)V
    //   139: astore 6
    //   141: iload_1
    //   142: ifeq +48 -> 190
    //   145: aload 6
    //   147: ifnull +15 -> 162
    //   150: iload 5
    //   152: istore 4
    //   154: aload 6
    //   156: ldc 91
    //   158: invokevirtual 95	org/json/JSONObject:optString	(Ljava/lang/String;)Ljava/lang/String;
    //   161: astore_3
    //   162: iconst_0
    //   163: istore 4
    //   165: iload_1
    //   166: istore 5
    //   168: iload 4
    //   170: ifne +19 -> 189
    //   173: aload_0
    //   174: getfield 97	com/tencent/biz/pubaccount/readinjoy/comment/NativeCommentServlet$1:jdField_a_of_type_ComTencentBizPubaccountReadinjoyCommentNativeCommentServlet$CommentObserver	Lcom/tencent/biz/pubaccount/readinjoy/comment/NativeCommentServlet$CommentObserver;
    //   177: aload_0
    //   178: getfield 99	com/tencent/biz/pubaccount/readinjoy/comment/NativeCommentServlet$1:jdField_a_of_type_ComTencentBizPubaccountReadinjoyStructArticleInfo	Lcom/tencent/biz/pubaccount/readinjoy/struct/ArticleInfo;
    //   181: iload 5
    //   183: aload_3
    //   184: invokeinterface 104 4 0
    //   189: return
    //   190: iconst_1
    //   191: istore 4
    //   193: aload_0
    //   194: getfield 97	com/tencent/biz/pubaccount/readinjoy/comment/NativeCommentServlet$1:jdField_a_of_type_ComTencentBizPubaccountReadinjoyCommentNativeCommentServlet$CommentObserver	Lcom/tencent/biz/pubaccount/readinjoy/comment/NativeCommentServlet$CommentObserver;
    //   197: aload_0
    //   198: getfield 99	com/tencent/biz/pubaccount/readinjoy/comment/NativeCommentServlet$1:jdField_a_of_type_ComTencentBizPubaccountReadinjoyStructArticleInfo	Lcom/tencent/biz/pubaccount/readinjoy/struct/ArticleInfo;
    //   201: aload 6
    //   203: aload_3
    //   204: invokeinterface 107 4 0
    //   209: ldc 109
    //   211: astore_3
    //   212: iconst_1
    //   213: istore 4
    //   215: goto -50 -> 165
    //   218: astore_3
    //   219: iconst_m1
    //   220: istore 5
    //   222: aload_3
    //   223: invokevirtual 112	java/lang/Exception:getLocalizedMessage	()Ljava/lang/String;
    //   226: astore 6
    //   228: aload_3
    //   229: invokevirtual 115	java/lang/Exception:printStackTrace	()V
    //   232: invokestatic 56	com/tencent/qphone/base/util/QLog:isColorLevel	()Z
    //   235: ifeq +31 -> 266
    //   238: ldc 58
    //   240: iconst_2
    //   241: new 60	java/lang/StringBuilder
    //   244: dup
    //   245: invokespecial 61	java/lang/StringBuilder:<init>	()V
    //   248: ldc 117
    //   250: invokevirtual 67	java/lang/StringBuilder:append	(Ljava/lang/String;)Ljava/lang/StringBuilder;
    //   253: aload_3
    //   254: invokevirtual 112	java/lang/Exception:getLocalizedMessage	()Ljava/lang/String;
    //   257: invokevirtual 67	java/lang/StringBuilder:append	(Ljava/lang/String;)Ljava/lang/StringBuilder;
    //   260: invokevirtual 74	java/lang/StringBuilder:toString	()Ljava/lang/String;
    //   263: invokestatic 78	com/tencent/qphone/base/util/QLog:d	(Ljava/lang/String;ILjava/lang/String;)V
    //   266: aload 6
    //   268: astore_3
    //   269: iload_1
    //   270: istore 4
    //   272: goto -104 -> 168
    //   275: astore_3
    //   276: iload_1
    //   277: istore 5
    //   279: iload 4
    //   281: istore_1
    //   282: goto -60 -> 222
    //   285: iconst_0
    //   286: istore 4
    //   288: ldc 109
    //   290: astore_3
    //   291: iconst_m1
    //   292: istore_1
    //   293: goto -128 -> 165
    // Local variable table:
    //   start	length	slot	name	signature
    //   0	296	0	this	1
    //   0	296	1	paramInt	int
    //   0	296	2	paramBoolean	boolean
    //   0	296	3	paramBundle	android.os.Bundle
    //   44	243	4	i	int
    //   1	277	5	j	int
    //   27	240	6	localObject	Object
    // Exception table:
    //   from	to	target	type
    //   9	16	218	java/lang/Exception
    //   20	46	218	java/lang/Exception
    //   53	62	275	java/lang/Exception
    //   66	72	275	java/lang/Exception
    //   76	113	275	java/lang/Exception
    //   120	127	275	java/lang/Exception
    //   131	141	275	java/lang/Exception
    //   154	162	275	java/lang/Exception
    //   193	209	275	java/lang/Exception
  }
}


/* Location:           L:\local\mybackup\temp\qq_apk\com.tencent.mobileqq\classes3.jar
 * Qualified Name:     com.tencent.biz.pubaccount.readinjoy.comment.NativeCommentServlet.1
 * JD-Core Version:    0.7.0.1
 */