package com.tencent.mobileqq.activity;

import android.app.Activity;
import com.tencent.mobileqq.app.QQAppInterface;
import com.tencent.mobileqq.widget.QQProgressDialog;

final class DiscussionInfoCardActivity$16
  implements Runnable
{
  DiscussionInfoCardActivity$16(long paramLong, QQAppInterface paramQQAppInterface, String paramString1, String paramString2, String paramString3, String paramString4, Activity paramActivity, int paramInt, QQProgressDialog paramQQProgressDialog) {}
  
  /* Error */
  public void run()
  {
    // Byte code:
    //   0: aconst_null
    //   1: astore 7
    //   3: iconst_0
    //   4: istore_2
    //   5: lconst_1
    //   6: aload_0
    //   7: getfield 20	com/tencent/mobileqq/activity/DiscussionInfoCardActivity$16:jdField_a_of_type_Long	J
    //   10: lcmp
    //   11: ifne +627 -> 638
    //   14: invokestatic 48	com/tencent/mobileqq/util/SystemUtil:a	()Z
    //   17: ifeq +388 -> 405
    //   20: getstatic 53	com/tencent/mobileqq/app/AppConstants:PATH_HEAD_HD	Ljava/lang/String;
    //   23: astore 4
    //   25: new 55	java/lang/StringBuilder
    //   28: dup
    //   29: invokespecial 56	java/lang/StringBuilder:<init>	()V
    //   32: aload 4
    //   34: invokevirtual 60	java/lang/StringBuilder:append	(Ljava/lang/String;)Ljava/lang/StringBuilder;
    //   37: ldc 62
    //   39: invokevirtual 60	java/lang/StringBuilder:append	(Ljava/lang/String;)Ljava/lang/StringBuilder;
    //   42: invokevirtual 66	java/lang/StringBuilder:toString	()Ljava/lang/String;
    //   45: astore 4
    //   47: new 68	java/io/File
    //   50: dup
    //   51: aload 4
    //   53: invokespecial 71	java/io/File:<init>	(Ljava/lang/String;)V
    //   56: astore 5
    //   58: aload 5
    //   60: invokevirtual 74	java/io/File:exists	()Z
    //   63: ifeq +349 -> 412
    //   66: iconst_1
    //   67: istore_1
    //   68: iload_1
    //   69: ifne +792 -> 861
    //   72: ldc 76
    //   74: astore 5
    //   76: new 78	com/tencent/mobileqq/structmsg/AbsShareMsg$Builder
    //   79: dup
    //   80: ldc 80
    //   82: invokespecial 83	com/tencent/mobileqq/structmsg/AbsShareMsg$Builder:<init>	(Ljava/lang/Class;)V
    //   85: bipush 15
    //   87: invokevirtual 86	com/tencent/mobileqq/structmsg/AbsShareMsg$Builder:c	(I)Lcom/tencent/mobileqq/structmsg/AbsShareMsg$Builder;
    //   90: new 55	java/lang/StringBuilder
    //   93: dup
    //   94: invokespecial 56	java/lang/StringBuilder:<init>	()V
    //   97: ldc 87
    //   99: invokestatic 92	com/tencent/mobileqq/app/HardCodeUtil:a	(I)Ljava/lang/String;
    //   102: invokevirtual 60	java/lang/StringBuilder:append	(Ljava/lang/String;)Ljava/lang/StringBuilder;
    //   105: aload_0
    //   106: getfield 28	com/tencent/mobileqq/activity/DiscussionInfoCardActivity$16:c	Ljava/lang/String;
    //   109: invokevirtual 60	java/lang/StringBuilder:append	(Ljava/lang/String;)Ljava/lang/StringBuilder;
    //   112: invokevirtual 66	java/lang/StringBuilder:toString	()Ljava/lang/String;
    //   115: invokevirtual 95	com/tencent/mobileqq/structmsg/AbsShareMsg$Builder:a	(Ljava/lang/String;)Lcom/tencent/mobileqq/structmsg/AbsShareMsg$Builder;
    //   118: aload_0
    //   119: getfield 30	com/tencent/mobileqq/activity/DiscussionInfoCardActivity$16:d	Ljava/lang/String;
    //   122: invokevirtual 98	com/tencent/mobileqq/structmsg/AbsShareMsg$Builder:e	(Ljava/lang/String;)Lcom/tencent/mobileqq/structmsg/AbsShareMsg$Builder;
    //   125: invokevirtual 101	com/tencent/mobileqq/structmsg/AbsShareMsg$Builder:a	()Lcom/tencent/mobileqq/structmsg/AbsShareMsg;
    //   128: astore 8
    //   130: aload_0
    //   131: getfield 22	com/tencent/mobileqq/activity/DiscussionInfoCardActivity$16:jdField_a_of_type_ComTencentMobileqqAppQQAppInterface	Lcom/tencent/mobileqq/app/QQAppInterface;
    //   134: getstatic 106	com/tencent/mobileqq/app/QQManagerFactory:FRIENDS_MANAGER	I
    //   137: invokevirtual 112	com/tencent/mobileqq/app/QQAppInterface:getManager	(I)Lmqq/manager/Manager;
    //   140: checkcast 114	com/tencent/mobileqq/app/FriendsManager
    //   143: astore 9
    //   145: aload_0
    //   146: getfield 22	com/tencent/mobileqq/activity/DiscussionInfoCardActivity$16:jdField_a_of_type_ComTencentMobileqqAppQQAppInterface	Lcom/tencent/mobileqq/app/QQAppInterface;
    //   149: getstatic 117	com/tencent/mobileqq/app/QQManagerFactory:DISCUSSION_MANAGER	I
    //   152: invokevirtual 112	com/tencent/mobileqq/app/QQAppInterface:getManager	(I)Lmqq/manager/Manager;
    //   155: checkcast 119	com/tencent/mobileqq/app/DiscussionManager
    //   158: astore 10
    //   160: aload 7
    //   162: astore 4
    //   164: aload 9
    //   166: ifnull +55 -> 221
    //   169: aload 10
    //   171: aload_0
    //   172: getfield 24	com/tencent/mobileqq/activity/DiscussionInfoCardActivity$16:jdField_a_of_type_JavaLangString	Ljava/lang/String;
    //   175: invokevirtual 122	com/tencent/mobileqq/app/DiscussionManager:a	(Ljava/lang/String;)Lcom/tencent/mobileqq/data/DiscussionInfo;
    //   178: astore 6
    //   180: aload 7
    //   182: astore 4
    //   184: aload 6
    //   186: ifnull +35 -> 221
    //   189: aload 10
    //   191: aload_0
    //   192: getfield 24	com/tencent/mobileqq/activity/DiscussionInfoCardActivity$16:jdField_a_of_type_JavaLangString	Ljava/lang/String;
    //   195: aload 6
    //   197: getfield 127	com/tencent/mobileqq/data/DiscussionInfo:ownerUin	Ljava/lang/String;
    //   200: invokevirtual 130	com/tencent/mobileqq/app/DiscussionManager:a	(Ljava/lang/String;Ljava/lang/String;)Lcom/tencent/mobileqq/data/DiscussionMemberInfo;
    //   203: astore 4
    //   205: aload 4
    //   207: ifnull +556 -> 763
    //   210: aload 4
    //   212: aload_0
    //   213: getfield 22	com/tencent/mobileqq/activity/DiscussionInfoCardActivity$16:jdField_a_of_type_ComTencentMobileqqAppQQAppInterface	Lcom/tencent/mobileqq/app/QQAppInterface;
    //   216: invokestatic 135	com/tencent/mobileqq/utils/ContactUtils:a	(Lcom/tencent/mobileqq/data/DiscussionMemberInfo;Lcom/tencent/mobileqq/app/QQAppInterface;)Ljava/lang/String;
    //   219: astore 4
    //   221: aload 4
    //   223: astore 6
    //   225: aload 4
    //   227: invokestatic 141	android/text/TextUtils:isEmpty	(Ljava/lang/CharSequence;)Z
    //   230: ifeq +10 -> 240
    //   233: ldc 142
    //   235: invokestatic 92	com/tencent/mobileqq/app/HardCodeUtil:a	(I)Ljava/lang/String;
    //   238: astore 6
    //   240: new 144	com/tencent/mobileqq/structmsg/view/StructMsgItemLayoutDefault
    //   243: dup
    //   244: invokespecial 145	com/tencent/mobileqq/structmsg/view/StructMsgItemLayoutDefault:<init>	()V
    //   247: astore 4
    //   249: aload 4
    //   251: iconst_1
    //   252: invokevirtual 150	com/tencent/mobileqq/structmsg/AbsStructMsgItem:b	(I)V
    //   255: aload 4
    //   257: aload_0
    //   258: getfield 32	com/tencent/mobileqq/activity/DiscussionInfoCardActivity$16:jdField_a_of_type_AndroidAppActivity	Landroid/app/Activity;
    //   261: ldc 151
    //   263: invokevirtual 156	android/app/Activity:getString	(I)Ljava/lang/String;
    //   266: invokevirtual 158	com/tencent/mobileqq/structmsg/AbsStructMsgItem:a	(Ljava/lang/String;)V
    //   269: iconst_2
    //   270: invokestatic 163	com/tencent/mobileqq/structmsg/StructMsgElementFactory:a	(I)Lcom/tencent/mobileqq/structmsg/AbsStructMsgItem;
    //   273: astore 7
    //   275: aload 7
    //   277: aload 5
    //   279: aload_0
    //   280: getfield 22	com/tencent/mobileqq/activity/DiscussionInfoCardActivity$16:jdField_a_of_type_ComTencentMobileqqAppQQAppInterface	Lcom/tencent/mobileqq/app/QQAppInterface;
    //   283: aload_0
    //   284: getfield 28	com/tencent/mobileqq/activity/DiscussionInfoCardActivity$16:c	Ljava/lang/String;
    //   287: aload_0
    //   288: getfield 24	com/tencent/mobileqq/activity/DiscussionInfoCardActivity$16:jdField_a_of_type_JavaLangString	Ljava/lang/String;
    //   291: invokestatic 168	com/tencent/mobileqq/activity/aio/ForwardUtils:a	(Lcom/tencent/mobileqq/app/QQAppInterface;Ljava/lang/String;Ljava/lang/String;)Ljava/lang/String;
    //   294: new 55	java/lang/StringBuilder
    //   297: dup
    //   298: invokespecial 56	java/lang/StringBuilder:<init>	()V
    //   301: ldc 169
    //   303: invokestatic 92	com/tencent/mobileqq/app/HardCodeUtil:a	(I)Ljava/lang/String;
    //   306: invokevirtual 60	java/lang/StringBuilder:append	(Ljava/lang/String;)Ljava/lang/StringBuilder;
    //   309: aload 6
    //   311: invokevirtual 60	java/lang/StringBuilder:append	(Ljava/lang/String;)Ljava/lang/StringBuilder;
    //   314: invokevirtual 66	java/lang/StringBuilder:toString	()Ljava/lang/String;
    //   317: iconst_1
    //   318: invokevirtual 172	com/tencent/mobileqq/structmsg/AbsStructMsgItem:a	(Ljava/lang/String;Ljava/lang/String;Ljava/lang/String;I)V
    //   321: aload 8
    //   323: aload 4
    //   325: invokevirtual 178	com/tencent/mobileqq/structmsg/AbsShareMsg:addItem	(Lcom/tencent/mobileqq/structmsg/AbsStructMsgElement;)V
    //   328: aload 8
    //   330: aload 7
    //   332: invokevirtual 178	com/tencent/mobileqq/structmsg/AbsShareMsg:addItem	(Lcom/tencent/mobileqq/structmsg/AbsStructMsgElement;)V
    //   335: new 180	android/content/Intent
    //   338: dup
    //   339: invokespecial 181	android/content/Intent:<init>	()V
    //   342: astore 4
    //   344: aload 4
    //   346: ldc 183
    //   348: bipush 253
    //   350: invokevirtual 187	android/content/Intent:putExtra	(Ljava/lang/String;I)Landroid/content/Intent;
    //   353: pop
    //   354: aload 4
    //   356: ldc 189
    //   358: aload 8
    //   360: invokevirtual 193	com/tencent/mobileqq/structmsg/AbsShareMsg:getBytes	()[B
    //   363: invokevirtual 196	android/content/Intent:putExtra	(Ljava/lang/String;[B)Landroid/content/Intent;
    //   366: pop
    //   367: aload_0
    //   368: getfield 32	com/tencent/mobileqq/activity/DiscussionInfoCardActivity$16:jdField_a_of_type_AndroidAppActivity	Landroid/app/Activity;
    //   371: aload 4
    //   373: aload_0
    //   374: getfield 34	com/tencent/mobileqq/activity/DiscussionInfoCardActivity$16:jdField_a_of_type_Int	I
    //   377: invokestatic 201	com/tencent/mobileqq/forward/ForwardBaseOption:a	(Landroid/app/Activity;Landroid/content/Intent;I)V
    //   380: aload_0
    //   381: getfield 36	com/tencent/mobileqq/activity/DiscussionInfoCardActivity$16:jdField_a_of_type_ComTencentMobileqqWidgetQQProgressDialog	Lcom/tencent/mobileqq/widget/QQProgressDialog;
    //   384: ifnull +20 -> 404
    //   387: aload_0
    //   388: getfield 36	com/tencent/mobileqq/activity/DiscussionInfoCardActivity$16:jdField_a_of_type_ComTencentMobileqqWidgetQQProgressDialog	Lcom/tencent/mobileqq/widget/QQProgressDialog;
    //   391: invokevirtual 206	com/tencent/mobileqq/widget/QQProgressDialog:isShowing	()Z
    //   394: ifeq +10 -> 404
    //   397: aload_0
    //   398: getfield 36	com/tencent/mobileqq/activity/DiscussionInfoCardActivity$16:jdField_a_of_type_ComTencentMobileqqWidgetQQProgressDialog	Lcom/tencent/mobileqq/widget/QQProgressDialog;
    //   401: invokevirtual 209	com/tencent/mobileqq/widget/QQProgressDialog:dismiss	()V
    //   404: return
    //   405: ldc 211
    //   407: astore 4
    //   409: goto -384 -> 25
    //   412: aload 5
    //   414: invokevirtual 214	java/io/File:createNewFile	()Z
    //   417: pop
    //   418: new 216	java/io/BufferedOutputStream
    //   421: dup
    //   422: new 218	java/io/FileOutputStream
    //   425: dup
    //   426: aload 5
    //   428: invokespecial 221	java/io/FileOutputStream:<init>	(Ljava/io/File;)V
    //   431: sipush 8192
    //   434: invokespecial 224	java/io/BufferedOutputStream:<init>	(Ljava/io/OutputStream;I)V
    //   437: astore 6
    //   439: invokestatic 229	com/tencent/mobileqq/utils/ImageUtil:b	()Landroid/graphics/drawable/Drawable;
    //   442: checkcast 231	android/graphics/drawable/BitmapDrawable
    //   445: invokevirtual 235	android/graphics/drawable/BitmapDrawable:getBitmap	()Landroid/graphics/Bitmap;
    //   448: getstatic 241	android/graphics/Bitmap$CompressFormat:PNG	Landroid/graphics/Bitmap$CompressFormat;
    //   451: bipush 100
    //   453: aload 6
    //   455: invokevirtual 247	android/graphics/Bitmap:compress	(Landroid/graphics/Bitmap$CompressFormat;ILjava/io/OutputStream;)Z
    //   458: istore_3
    //   459: iload_3
    //   460: ifeq +424 -> 884
    //   463: iconst_1
    //   464: istore_2
    //   465: aload 4
    //   467: astore 5
    //   469: aload 5
    //   471: astore 4
    //   473: iload_2
    //   474: istore_1
    //   475: aload 6
    //   477: ifnull -409 -> 68
    //   480: aload 6
    //   482: invokevirtual 252	java/io/OutputStream:close	()V
    //   485: aload 5
    //   487: astore 4
    //   489: iload_2
    //   490: istore_1
    //   491: goto -423 -> 68
    //   494: astore 6
    //   496: aload 5
    //   498: astore 4
    //   500: iload_2
    //   501: istore_1
    //   502: invokestatic 257	com/tencent/qphone/base/util/QLog:isColorLevel	()Z
    //   505: ifeq -437 -> 68
    //   508: ldc_w 259
    //   511: iconst_2
    //   512: aload 6
    //   514: invokevirtual 262	java/io/IOException:getMessage	()Ljava/lang/String;
    //   517: aload 6
    //   519: invokestatic 265	com/tencent/qphone/base/util/QLog:d	(Ljava/lang/String;ILjava/lang/String;Ljava/lang/Throwable;)V
    //   522: aload 5
    //   524: astore 4
    //   526: iload_2
    //   527: istore_1
    //   528: goto -460 -> 68
    //   531: astore 5
    //   533: aconst_null
    //   534: astore 4
    //   536: invokestatic 257	com/tencent/qphone/base/util/QLog:isColorLevel	()Z
    //   539: ifeq +8 -> 547
    //   542: aload 5
    //   544: invokevirtual 268	java/io/IOException:printStackTrace	()V
    //   547: aload 4
    //   549: ifnull +327 -> 876
    //   552: aload 4
    //   554: invokevirtual 252	java/io/OutputStream:close	()V
    //   557: aconst_null
    //   558: astore 4
    //   560: iconst_0
    //   561: istore_1
    //   562: goto -494 -> 68
    //   565: astore 4
    //   567: invokestatic 257	com/tencent/qphone/base/util/QLog:isColorLevel	()Z
    //   570: ifeq +17 -> 587
    //   573: ldc_w 259
    //   576: iconst_2
    //   577: aload 4
    //   579: invokevirtual 262	java/io/IOException:getMessage	()Ljava/lang/String;
    //   582: aload 4
    //   584: invokestatic 265	com/tencent/qphone/base/util/QLog:d	(Ljava/lang/String;ILjava/lang/String;Ljava/lang/Throwable;)V
    //   587: aconst_null
    //   588: astore 4
    //   590: iconst_0
    //   591: istore_1
    //   592: goto -524 -> 68
    //   595: astore 4
    //   597: aconst_null
    //   598: astore 5
    //   600: aload 5
    //   602: ifnull +8 -> 610
    //   605: aload 5
    //   607: invokevirtual 252	java/io/OutputStream:close	()V
    //   610: aload 4
    //   612: athrow
    //   613: astore 5
    //   615: invokestatic 257	com/tencent/qphone/base/util/QLog:isColorLevel	()Z
    //   618: ifeq -8 -> 610
    //   621: ldc_w 259
    //   624: iconst_2
    //   625: aload 5
    //   627: invokevirtual 262	java/io/IOException:getMessage	()Ljava/lang/String;
    //   630: aload 5
    //   632: invokestatic 265	com/tencent/qphone/base/util/QLog:d	(Ljava/lang/String;ILjava/lang/String;Ljava/lang/Throwable;)V
    //   635: goto -25 -> 610
    //   638: new 270	java/util/ArrayList
    //   641: dup
    //   642: invokespecial 271	java/util/ArrayList:<init>	()V
    //   645: astore 4
    //   647: aload 4
    //   649: aload_0
    //   650: getfield 22	com/tencent/mobileqq/activity/DiscussionInfoCardActivity$16:jdField_a_of_type_ComTencentMobileqqAppQQAppInterface	Lcom/tencent/mobileqq/app/QQAppInterface;
    //   653: bipush 101
    //   655: aload_0
    //   656: getfield 24	com/tencent/mobileqq/activity/DiscussionInfoCardActivity$16:jdField_a_of_type_JavaLangString	Ljava/lang/String;
    //   659: iconst_0
    //   660: invokevirtual 275	com/tencent/mobileqq/app/QQAppInterface:getCustomFaceFilePath	(ILjava/lang/String;I)Ljava/lang/String;
    //   663: invokevirtual 279	java/util/ArrayList:add	(Ljava/lang/Object;)Z
    //   666: pop
    //   667: aload 4
    //   669: aload_0
    //   670: getfield 22	com/tencent/mobileqq/activity/DiscussionInfoCardActivity$16:jdField_a_of_type_ComTencentMobileqqAppQQAppInterface	Lcom/tencent/mobileqq/app/QQAppInterface;
    //   673: invokevirtual 282	com/tencent/mobileqq/app/QQAppInterface:getCurrentAccountUin	()Ljava/lang/String;
    //   676: aload_0
    //   677: getfield 26	com/tencent/mobileqq/activity/DiscussionInfoCardActivity$16:b	Ljava/lang/String;
    //   680: ldc_w 284
    //   683: invokestatic 290	cooperation/qzone/QZoneShareManager:batchUploadImages	(Ljava/util/ArrayList;Ljava/lang/String;Ljava/lang/String;Ljava/lang/String;)Ljava/util/ArrayList;
    //   686: astore 4
    //   688: aload 4
    //   690: ifnull +178 -> 868
    //   693: aload 4
    //   695: invokevirtual 294	java/util/ArrayList:size	()I
    //   698: ifle +170 -> 868
    //   701: aload 4
    //   703: iconst_0
    //   704: invokevirtual 298	java/util/ArrayList:get	(I)Ljava/lang/Object;
    //   707: checkcast 300	java/lang/String
    //   710: astore 5
    //   712: aload 5
    //   714: astore 4
    //   716: iload_2
    //   717: istore_1
    //   718: aload 5
    //   720: invokestatic 141	android/text/TextUtils:isEmpty	(Ljava/lang/CharSequence;)Z
    //   723: ifne -655 -> 68
    //   726: aload 5
    //   728: ldc_w 302
    //   731: invokevirtual 306	java/lang/String:startsWith	(Ljava/lang/String;)Z
    //   734: ifne +20 -> 754
    //   737: aload 5
    //   739: astore 4
    //   741: iload_2
    //   742: istore_1
    //   743: aload 5
    //   745: ldc_w 308
    //   748: invokevirtual 306	java/lang/String:startsWith	(Ljava/lang/String;)Z
    //   751: ifeq -683 -> 68
    //   754: iconst_1
    //   755: istore_1
    //   756: aload 5
    //   758: astore 4
    //   760: goto -692 -> 68
    //   763: aload 9
    //   765: aload 6
    //   767: getfield 127	com/tencent/mobileqq/data/DiscussionInfo:ownerUin	Ljava/lang/String;
    //   770: invokevirtual 310	com/tencent/mobileqq/app/FriendsManager:b	(Ljava/lang/String;)Z
    //   773: ifeq +20 -> 793
    //   776: aload_0
    //   777: getfield 22	com/tencent/mobileqq/activity/DiscussionInfoCardActivity$16:jdField_a_of_type_ComTencentMobileqqAppQQAppInterface	Lcom/tencent/mobileqq/app/QQAppInterface;
    //   780: aload 6
    //   782: getfield 127	com/tencent/mobileqq/data/DiscussionInfo:ownerUin	Ljava/lang/String;
    //   785: invokestatic 314	com/tencent/mobileqq/utils/ContactUtils:j	(Lcom/tencent/mobileqq/app/QQAppInterface;Ljava/lang/String;)Ljava/lang/String;
    //   788: astore 4
    //   790: goto -569 -> 221
    //   793: aload 9
    //   795: aload 6
    //   797: getfield 127	com/tencent/mobileqq/data/DiscussionInfo:ownerUin	Ljava/lang/String;
    //   800: invokevirtual 317	com/tencent/mobileqq/app/FriendsManager:e	(Ljava/lang/String;)Lcom/tencent/mobileqq/data/Friends;
    //   803: astore 4
    //   805: aload 4
    //   807: ifnull +13 -> 820
    //   810: aload 4
    //   812: getfield 322	com/tencent/mobileqq/data/Friends:name	Ljava/lang/String;
    //   815: astore 4
    //   817: goto -596 -> 221
    //   820: aload 6
    //   822: getfield 127	com/tencent/mobileqq/data/DiscussionInfo:ownerUin	Ljava/lang/String;
    //   825: astore 4
    //   827: goto -606 -> 221
    //   830: astore 4
    //   832: aload 6
    //   834: astore 5
    //   836: goto -236 -> 600
    //   839: astore 6
    //   841: aload 4
    //   843: astore 5
    //   845: aload 6
    //   847: astore 4
    //   849: goto -249 -> 600
    //   852: astore 5
    //   854: aload 6
    //   856: astore 4
    //   858: goto -322 -> 536
    //   861: aload 4
    //   863: astore 5
    //   865: goto -789 -> 76
    //   868: aconst_null
    //   869: astore 4
    //   871: iload_2
    //   872: istore_1
    //   873: goto -805 -> 68
    //   876: aconst_null
    //   877: astore 4
    //   879: iconst_0
    //   880: istore_1
    //   881: goto -813 -> 68
    //   884: aconst_null
    //   885: astore 5
    //   887: iconst_0
    //   888: istore_2
    //   889: goto -420 -> 469
    // Local variable table:
    //   start	length	slot	name	signature
    //   0	892	0	this	16
    //   67	814	1	i	int
    //   4	885	2	j	int
    //   458	2	3	bool	boolean
    //   23	536	4	localObject1	Object
    //   565	18	4	localIOException1	java.io.IOException
    //   588	1	4	localObject2	Object
    //   595	16	4	localObject3	Object
    //   645	181	4	localObject4	Object
    //   830	12	4	localObject5	Object
    //   847	31	4	localObject6	Object
    //   56	467	5	localObject7	Object
    //   531	12	5	localIOException2	java.io.IOException
    //   598	8	5	localObject8	Object
    //   613	18	5	localIOException3	java.io.IOException
    //   710	134	5	localObject9	Object
    //   852	1	5	localIOException4	java.io.IOException
    //   863	23	5	localObject10	Object
    //   178	303	6	localObject11	Object
    //   494	339	6	localIOException5	java.io.IOException
    //   839	16	6	localObject12	Object
    //   1	330	7	localAbsStructMsgItem	com.tencent.mobileqq.structmsg.AbsStructMsgItem
    //   128	231	8	localAbsShareMsg	com.tencent.mobileqq.structmsg.AbsShareMsg
    //   143	651	9	localFriendsManager	com.tencent.mobileqq.app.FriendsManager
    //   158	32	10	localDiscussionManager	com.tencent.mobileqq.app.DiscussionManager
    // Exception table:
    //   from	to	target	type
    //   480	485	494	java/io/IOException
    //   412	439	531	java/io/IOException
    //   552	557	565	java/io/IOException
    //   412	439	595	finally
    //   605	610	613	java/io/IOException
    //   439	459	830	finally
    //   536	547	839	finally
    //   439	459	852	java/io/IOException
  }
}


/* Location:           L:\local\mybackup\temp\qq_apk\com.tencent.mobileqq\classes6.jar
 * Qualified Name:     com.tencent.mobileqq.activity.DiscussionInfoCardActivity.16
 * JD-Core Version:    0.7.0.1
 */