package c.t.m.g;

final class cb
  implements Runnable
{
  cb(bu parambu) {}
  
  /* Error */
  public final void run()
  {
    // Byte code:
    //   0: iconst_0
    //   1: istore_1
    //   2: iconst_0
    //   3: istore 5
    //   5: iconst_0
    //   6: istore 4
    //   8: invokestatic 25	android/os/SystemClock:elapsedRealtime	()J
    //   11: lstore 6
    //   13: iload 4
    //   15: istore_2
    //   16: iload 5
    //   18: istore_3
    //   19: new 27	c/t/m/g/bm
    //   22: dup
    //   23: invokespecial 28	c/t/m/g/bm:<init>	()V
    //   26: astore 9
    //   28: iload 4
    //   30: istore_2
    //   31: iload 5
    //   33: istore_3
    //   34: aload_0
    //   35: getfield 12	c/t/m/g/cb:a	Lc/t/m/g/bu;
    //   38: invokestatic 34	c/t/m/g/bu:d	(Lc/t/m/g/bu;)Ljava/util/Map;
    //   41: invokeinterface 40 1 0
    //   46: invokeinterface 46 1 0
    //   51: astore 10
    //   53: iload 4
    //   55: istore_2
    //   56: iload 5
    //   58: istore_3
    //   59: aload 10
    //   61: invokeinterface 52 1 0
    //   66: ifeq +80 -> 146
    //   69: iload 4
    //   71: istore_2
    //   72: iload 5
    //   74: istore_3
    //   75: aload 10
    //   77: invokeinterface 56 1 0
    //   82: checkcast 58	c/t/m/g/bq
    //   85: aload 9
    //   87: invokevirtual 61	c/t/m/g/bq:a	(Lc/t/m/g/bm;)V
    //   90: goto -37 -> 53
    //   93: astore 9
    //   95: aload_0
    //   96: getfield 12	c/t/m/g/cb:a	Lc/t/m/g/bu;
    //   99: invokestatic 67	c/t/m/g/x:b	()Ljava/lang/String;
    //   102: invokestatic 70	c/t/m/g/bu:a	(Lc/t/m/g/bu;Ljava/lang/String;)Lc/t/m/g/bu$a;
    //   105: astore 9
    //   107: aload 9
    //   109: invokestatic 25	android/os/SystemClock:elapsedRealtime	()J
    //   112: putfield 75	c/t/m/g/bu$a:a	J
    //   115: aload 9
    //   117: iload_2
    //   118: putfield 78	c/t/m/g/bu$a:b	I
    //   121: aload_0
    //   122: getfield 12	c/t/m/g/cb:a	Lc/t/m/g/bu;
    //   125: invokestatic 81	c/t/m/g/bu:e	(Lc/t/m/g/bu;)V
    //   128: aload_0
    //   129: getfield 12	c/t/m/g/cb:a	Lc/t/m/g/bu;
    //   132: invokestatic 85	c/t/m/g/bu:c	(Lc/t/m/g/bu;)Landroid/os/Handler;
    //   135: aload_0
    //   136: getfield 12	c/t/m/g/cb:a	Lc/t/m/g/bu;
    //   139: invokestatic 88	c/t/m/g/bu:b	(Lc/t/m/g/bu;)Ljava/lang/Runnable;
    //   142: invokevirtual 94	android/os/Handler:removeCallbacks	(Ljava/lang/Runnable;)V
    //   145: return
    //   146: iload 4
    //   148: istore_2
    //   149: iload 5
    //   151: istore_3
    //   152: aload 9
    //   154: invokevirtual 97	c/t/m/g/bm:a	()[B
    //   157: astore 9
    //   159: iload 4
    //   161: istore_2
    //   162: iload 5
    //   164: istore_3
    //   165: aload 9
    //   167: invokestatic 102	c/t/m/g/cm:a	([B)Z
    //   170: ifne +254 -> 424
    //   173: iload 4
    //   175: istore_2
    //   176: iload 5
    //   178: istore_3
    //   179: invokestatic 104	c/t/m/g/cm:d	()Ljava/lang/String;
    //   182: astore 10
    //   184: iload 4
    //   186: istore_2
    //   187: iload 5
    //   189: istore_3
    //   190: invokestatic 109	c/t/m/g/cf:d	()Lc/t/m/g/cf;
    //   193: invokevirtual 112	c/t/m/g/cf:e	()Lc/t/m/g/w;
    //   196: pop
    //   197: iload 4
    //   199: istore_2
    //   200: iload 5
    //   202: istore_3
    //   203: ldc 114
    //   205: aconst_null
    //   206: aload 9
    //   208: sipush 15000
    //   211: aload 10
    //   213: invokestatic 119	c/t/m/g/ak:a	(Ljava/lang/String;Ljava/util/Map;[BILjava/lang/String;)Lc/t/m/g/ak;
    //   216: astore 9
    //   218: iload 4
    //   220: istore_2
    //   221: iload 5
    //   223: istore_3
    //   224: aload 9
    //   226: invokestatic 123	c/t/m/g/bu:f	()I
    //   229: putfield 126	c/t/m/g/ak:o	I
    //   232: iload 4
    //   234: istore_2
    //   235: iload 5
    //   237: istore_3
    //   238: aload 9
    //   240: ldc 128
    //   242: putfield 132	c/t/m/g/ak:p	Ljava/lang/String;
    //   245: iload 4
    //   247: istore_2
    //   248: iload 5
    //   250: istore_3
    //   251: aload 9
    //   253: invokevirtual 135	c/t/m/g/ak:a	()Lc/t/m/g/an;
    //   256: astore 10
    //   258: iload 4
    //   260: istore_2
    //   261: iload 5
    //   263: istore_3
    //   264: aload 10
    //   266: getfield 139	c/t/m/g/an:a	I
    //   269: istore_1
    //   270: iload_1
    //   271: istore_2
    //   272: iload_1
    //   273: istore_3
    //   274: aload 10
    //   276: getfield 139	c/t/m/g/an:a	I
    //   279: ifne +120 -> 399
    //   282: iload_1
    //   283: istore_2
    //   284: iload_1
    //   285: istore_3
    //   286: aload 10
    //   288: getfield 141	c/t/m/g/an:c	I
    //   291: sipush 200
    //   294: if_icmpne +105 -> 399
    //   297: iload_1
    //   298: istore_2
    //   299: iload_1
    //   300: istore_3
    //   301: aload 10
    //   303: getfield 144	c/t/m/g/an:d	[B
    //   306: invokestatic 102	c/t/m/g/cm:a	([B)Z
    //   309: istore 8
    //   311: iload 8
    //   313: ifne +86 -> 399
    //   316: iload_1
    //   317: istore_3
    //   318: new 146	org/json/JSONObject
    //   321: dup
    //   322: new 148	java/lang/String
    //   325: dup
    //   326: aload 10
    //   328: getfield 144	c/t/m/g/an:d	[B
    //   331: invokespecial 151	java/lang/String:<init>	([B)V
    //   334: invokespecial 154	org/json/JSONObject:<init>	(Ljava/lang/String;)V
    //   337: astore 10
    //   339: iload_1
    //   340: istore_3
    //   341: invokestatic 156	c/t/m/g/x:e	()V
    //   344: iload_1
    //   345: istore_3
    //   346: aload_0
    //   347: getfield 12	c/t/m/g/cb:a	Lc/t/m/g/bu;
    //   350: invokestatic 34	c/t/m/g/bu:d	(Lc/t/m/g/bu;)Ljava/util/Map;
    //   353: invokeinterface 40 1 0
    //   358: invokeinterface 46 1 0
    //   363: astore 11
    //   365: iload_1
    //   366: istore_3
    //   367: aload 11
    //   369: invokeinterface 52 1 0
    //   374: ifeq +25 -> 399
    //   377: iload_1
    //   378: istore_3
    //   379: aload 11
    //   381: invokeinterface 56 1 0
    //   386: checkcast 58	c/t/m/g/bq
    //   389: aload 10
    //   391: invokevirtual 159	c/t/m/g/bq:a	(Lorg/json/JSONObject;)V
    //   394: goto -29 -> 365
    //   397: astore 10
    //   399: iload_1
    //   400: istore_2
    //   401: iload_1
    //   402: istore_3
    //   403: aload 9
    //   405: invokestatic 25	android/os/SystemClock:elapsedRealtime	()J
    //   408: lload 6
    //   410: lsub
    //   411: putfield 162	c/t/m/g/ak:k	J
    //   414: iload_1
    //   415: istore_2
    //   416: iload_1
    //   417: istore_3
    //   418: aload 9
    //   420: iconst_0
    //   421: invokevirtual 165	c/t/m/g/ak:a	(Z)V
    //   424: aload_0
    //   425: getfield 12	c/t/m/g/cb:a	Lc/t/m/g/bu;
    //   428: invokestatic 67	c/t/m/g/x:b	()Ljava/lang/String;
    //   431: invokestatic 70	c/t/m/g/bu:a	(Lc/t/m/g/bu;Ljava/lang/String;)Lc/t/m/g/bu$a;
    //   434: astore 9
    //   436: aload 9
    //   438: invokestatic 25	android/os/SystemClock:elapsedRealtime	()J
    //   441: putfield 75	c/t/m/g/bu$a:a	J
    //   444: aload 9
    //   446: iload_1
    //   447: putfield 78	c/t/m/g/bu$a:b	I
    //   450: aload_0
    //   451: getfield 12	c/t/m/g/cb:a	Lc/t/m/g/bu;
    //   454: invokestatic 81	c/t/m/g/bu:e	(Lc/t/m/g/bu;)V
    //   457: aload_0
    //   458: getfield 12	c/t/m/g/cb:a	Lc/t/m/g/bu;
    //   461: invokestatic 85	c/t/m/g/bu:c	(Lc/t/m/g/bu;)Landroid/os/Handler;
    //   464: aload_0
    //   465: getfield 12	c/t/m/g/cb:a	Lc/t/m/g/bu;
    //   468: invokestatic 88	c/t/m/g/bu:b	(Lc/t/m/g/bu;)Ljava/lang/Runnable;
    //   471: invokevirtual 94	android/os/Handler:removeCallbacks	(Ljava/lang/Runnable;)V
    //   474: return
    //   475: astore 9
    //   477: aload_0
    //   478: getfield 12	c/t/m/g/cb:a	Lc/t/m/g/bu;
    //   481: invokestatic 67	c/t/m/g/x:b	()Ljava/lang/String;
    //   484: invokestatic 70	c/t/m/g/bu:a	(Lc/t/m/g/bu;Ljava/lang/String;)Lc/t/m/g/bu$a;
    //   487: astore 10
    //   489: aload 10
    //   491: invokestatic 25	android/os/SystemClock:elapsedRealtime	()J
    //   494: putfield 75	c/t/m/g/bu$a:a	J
    //   497: aload 10
    //   499: iload_3
    //   500: putfield 78	c/t/m/g/bu$a:b	I
    //   503: aload_0
    //   504: getfield 12	c/t/m/g/cb:a	Lc/t/m/g/bu;
    //   507: invokestatic 81	c/t/m/g/bu:e	(Lc/t/m/g/bu;)V
    //   510: aload_0
    //   511: getfield 12	c/t/m/g/cb:a	Lc/t/m/g/bu;
    //   514: invokestatic 85	c/t/m/g/bu:c	(Lc/t/m/g/bu;)Landroid/os/Handler;
    //   517: aload_0
    //   518: getfield 12	c/t/m/g/cb:a	Lc/t/m/g/bu;
    //   521: invokestatic 88	c/t/m/g/bu:b	(Lc/t/m/g/bu;)Ljava/lang/Runnable;
    //   524: invokevirtual 94	android/os/Handler:removeCallbacks	(Ljava/lang/Runnable;)V
    //   527: aload 9
    //   529: athrow
    // Local variable table:
    //   start	length	slot	name	signature
    //   0	530	0	this	cb
    //   1	446	1	i	int
    //   15	401	2	j	int
    //   18	482	3	k	int
    //   6	253	4	m	int
    //   3	259	5	n	int
    //   11	398	6	l	long
    //   309	3	8	bool	boolean
    //   26	60	9	localbm	bm
    //   93	1	9	localThrowable1	java.lang.Throwable
    //   105	340	9	localObject1	Object
    //   475	53	9	localObject2	Object
    //   51	339	10	localObject3	Object
    //   397	1	10	localThrowable2	java.lang.Throwable
    //   487	11	10	locala	bu.a
    //   363	17	11	localIterator	java.util.Iterator
    // Exception table:
    //   from	to	target	type
    //   19	28	93	java/lang/Throwable
    //   34	53	93	java/lang/Throwable
    //   59	69	93	java/lang/Throwable
    //   75	90	93	java/lang/Throwable
    //   152	159	93	java/lang/Throwable
    //   165	173	93	java/lang/Throwable
    //   179	184	93	java/lang/Throwable
    //   190	197	93	java/lang/Throwable
    //   203	218	93	java/lang/Throwable
    //   224	232	93	java/lang/Throwable
    //   238	245	93	java/lang/Throwable
    //   251	258	93	java/lang/Throwable
    //   264	270	93	java/lang/Throwable
    //   274	282	93	java/lang/Throwable
    //   286	297	93	java/lang/Throwable
    //   301	311	93	java/lang/Throwable
    //   403	414	93	java/lang/Throwable
    //   418	424	93	java/lang/Throwable
    //   318	339	397	java/lang/Throwable
    //   341	344	397	java/lang/Throwable
    //   346	365	397	java/lang/Throwable
    //   367	377	397	java/lang/Throwable
    //   379	394	397	java/lang/Throwable
    //   19	28	475	finally
    //   34	53	475	finally
    //   59	69	475	finally
    //   75	90	475	finally
    //   152	159	475	finally
    //   165	173	475	finally
    //   179	184	475	finally
    //   190	197	475	finally
    //   203	218	475	finally
    //   224	232	475	finally
    //   238	245	475	finally
    //   251	258	475	finally
    //   264	270	475	finally
    //   274	282	475	finally
    //   286	297	475	finally
    //   301	311	475	finally
    //   318	339	475	finally
    //   341	344	475	finally
    //   346	365	475	finally
    //   367	377	475	finally
    //   379	394	475	finally
    //   403	414	475	finally
    //   418	424	475	finally
  }
}


/* Location:           L:\local\mybackup\temp\qq_apk\com.tencent.mm\classes6.jar
 * Qualified Name:     c.t.m.g.cb
 * JD-Core Version:    0.7.0.1
 */