package com.tencent.mm.plugin.expt.ui;

import android.view.View.OnClickListener;

final class ExptDebugUI$7
  implements View.OnClickListener
{
  ExptDebugUI$7(ExptDebugUI paramExptDebugUI) {}
  
  /* Error */
  public final void onClick(android.view.View paramView)
  {
    // Byte code:
    //   0: ldc 25
    //   2: invokestatic 31	com/tencent/matrix/trace/core/AppMethodBeat:i	(I)V
    //   5: new 33	com/tencent/mm/hellhoundlib/b/b
    //   8: dup
    //   9: invokespecial 34	com/tencent/mm/hellhoundlib/b/b:<init>	()V
    //   12: astore_3
    //   13: aload_3
    //   14: aload_1
    //   15: invokevirtual 38	com/tencent/mm/hellhoundlib/b/b:cH	(Ljava/lang/Object;)V
    //   18: ldc 39
    //   20: ldc 40
    //   22: ldc 41
    //   24: ldc 42
    //   26: aload_0
    //   27: aload_3
    //   28: invokevirtual 46	com/tencent/mm/hellhoundlib/b/b:aYj	()[Ljava/lang/Object;
    //   31: invokestatic 52	com/tencent/mm/hellhoundlib/a/a:c	(Ljava/lang/String;Ljava/lang/String;Ljava/lang/String;Ljava/lang/String;Ljava/lang/Object;[Ljava/lang/Object;)V
    //   34: invokestatic 58	com/tencent/mm/plugin/expt/model/a:dMQ	()Lcom/tencent/mm/plugin/expt/model/a;
    //   37: invokevirtual 62	com/tencent/mm/plugin/expt/model/a:dMS	()Ljava/util/ArrayList;
    //   40: astore 5
    //   42: new 64	java/lang/StringBuilder
    //   45: dup
    //   46: invokespecial 65	java/lang/StringBuilder:<init>	()V
    //   49: invokestatic 71	com/tencent/mm/loader/i/b:bmz	()Ljava/lang/String;
    //   52: invokevirtual 75	java/lang/StringBuilder:append	(Ljava/lang/String;)Ljava/lang/StringBuilder;
    //   55: ldc 77
    //   57: invokevirtual 75	java/lang/StringBuilder:append	(Ljava/lang/String;)Ljava/lang/StringBuilder;
    //   60: invokestatic 83	com/tencent/mm/sdk/platformtools/Util:nowSecond	()J
    //   63: invokevirtual 86	java/lang/StringBuilder:append	(J)Ljava/lang/StringBuilder;
    //   66: ldc 88
    //   68: invokevirtual 75	java/lang/StringBuilder:append	(Ljava/lang/String;)Ljava/lang/StringBuilder;
    //   71: invokevirtual 91	java/lang/StringBuilder:toString	()Ljava/lang/String;
    //   74: astore 4
    //   76: aload 4
    //   78: invokestatic 97	com/tencent/mm/vfs/y:ZC	(Ljava/lang/String;)Z
    //   81: ifeq +9 -> 90
    //   84: aload 4
    //   86: invokestatic 100	com/tencent/mm/vfs/y:deleteFile	(Ljava/lang/String;)Z
    //   89: pop
    //   90: aload 4
    //   92: invokestatic 103	com/tencent/mm/vfs/y:bEp	(Ljava/lang/String;)Z
    //   95: ifeq +78 -> 173
    //   98: aconst_null
    //   99: astore_3
    //   100: aload 4
    //   102: iconst_0
    //   103: invokestatic 107	com/tencent/mm/vfs/y:ev	(Ljava/lang/String;Z)Ljava/io/OutputStream;
    //   106: astore_1
    //   107: aload 5
    //   109: invokevirtual 113	java/util/ArrayList:iterator	()Ljava/util/Iterator;
    //   112: astore_3
    //   113: aload_3
    //   114: invokeinterface 119 1 0
    //   119: ifeq +152 -> 271
    //   122: aload_3
    //   123: invokeinterface 123 1 0
    //   128: checkcast 125	java/lang/Integer
    //   131: invokevirtual 129	java/lang/Integer:intValue	()I
    //   134: istore_2
    //   135: aload_1
    //   136: new 64	java/lang/StringBuilder
    //   139: dup
    //   140: invokespecial 65	java/lang/StringBuilder:<init>	()V
    //   143: iload_2
    //   144: invokevirtual 132	java/lang/StringBuilder:append	(I)Ljava/lang/StringBuilder;
    //   147: ldc 134
    //   149: invokevirtual 75	java/lang/StringBuilder:append	(Ljava/lang/String;)Ljava/lang/StringBuilder;
    //   152: invokevirtual 91	java/lang/StringBuilder:toString	()Ljava/lang/String;
    //   155: invokevirtual 140	java/lang/String:getBytes	()[B
    //   158: invokevirtual 146	java/io/OutputStream:write	([B)V
    //   161: goto -48 -> 113
    //   164: astore_3
    //   165: aload_1
    //   166: ifnull +7 -> 173
    //   169: aload_1
    //   170: invokevirtual 149	java/io/OutputStream:close	()V
    //   173: aload_0
    //   174: getfield 14	com/tencent/mm/plugin/expt/ui/ExptDebugUI$7:zNN	Lcom/tencent/mm/plugin/expt/ui/ExptDebugUI;
    //   177: invokestatic 153	com/tencent/mm/plugin/expt/ui/ExptDebugUI:e	(Lcom/tencent/mm/plugin/expt/ui/ExptDebugUI;)Landroid/widget/TextView;
    //   180: ldc 155
    //   182: aload 4
    //   184: invokestatic 159	java/lang/String:valueOf	(Ljava/lang/Object;)Ljava/lang/String;
    //   187: invokevirtual 163	java/lang/String:concat	(Ljava/lang/String;)Ljava/lang/String;
    //   190: invokevirtual 169	android/widget/TextView:setText	(Ljava/lang/CharSequence;)V
    //   193: invokestatic 175	com/tencent/mm/sdk/platformtools/MMApplicationContext:getContext	()Landroid/content/Context;
    //   196: ldc 177
    //   198: aload 4
    //   200: invokestatic 182	com/tencent/mm/sdk/platformtools/ClipboardHelper:setText	(Landroid/content/Context;Ljava/lang/CharSequence;Ljava/lang/CharSequence;)V
    //   203: aload_0
    //   204: getfield 14	com/tencent/mm/plugin/expt/ui/ExptDebugUI$7:zNN	Lcom/tencent/mm/plugin/expt/ui/ExptDebugUI;
    //   207: invokevirtual 185	com/tencent/mm/plugin/expt/ui/ExptDebugUI:getContext	()Landroidx/appcompat/app/AppCompatActivity;
    //   210: new 64	java/lang/StringBuilder
    //   213: dup
    //   214: invokespecial 65	java/lang/StringBuilder:<init>	()V
    //   217: aload_0
    //   218: getfield 14	com/tencent/mm/plugin/expt/ui/ExptDebugUI$7:zNN	Lcom/tencent/mm/plugin/expt/ui/ExptDebugUI;
    //   221: invokevirtual 185	com/tencent/mm/plugin/expt/ui/ExptDebugUI:getContext	()Landroidx/appcompat/app/AppCompatActivity;
    //   224: getstatic 191	com/tencent/mm/plugin/expt/b$e:app_copy_ok	I
    //   227: invokevirtual 197	androidx/appcompat/app/AppCompatActivity:getString	(I)Ljava/lang/String;
    //   230: invokevirtual 75	java/lang/StringBuilder:append	(Ljava/lang/String;)Ljava/lang/StringBuilder;
    //   233: ldc 199
    //   235: invokevirtual 75	java/lang/StringBuilder:append	(Ljava/lang/String;)Ljava/lang/StringBuilder;
    //   238: aload 4
    //   240: invokevirtual 75	java/lang/StringBuilder:append	(Ljava/lang/String;)Ljava/lang/StringBuilder;
    //   243: invokevirtual 91	java/lang/StringBuilder:toString	()Ljava/lang/String;
    //   246: iconst_0
    //   247: invokestatic 205	android/widget/Toast:makeText	(Landroid/content/Context;Ljava/lang/CharSequence;I)Landroid/widget/Toast;
    //   250: invokevirtual 208	android/widget/Toast:show	()V
    //   253: aload_0
    //   254: ldc 39
    //   256: ldc 40
    //   258: ldc 41
    //   260: ldc 42
    //   262: invokestatic 212	com/tencent/mm/hellhoundlib/a/a:a	(Ljava/lang/Object;Ljava/lang/String;Ljava/lang/String;Ljava/lang/String;Ljava/lang/String;)V
    //   265: ldc 25
    //   267: invokestatic 215	com/tencent/matrix/trace/core/AppMethodBeat:o	(I)V
    //   270: return
    //   271: aload_1
    //   272: invokevirtual 218	java/io/OutputStream:flush	()V
    //   275: aload_1
    //   276: ifnull -103 -> 173
    //   279: aload_1
    //   280: invokevirtual 149	java/io/OutputStream:close	()V
    //   283: goto -110 -> 173
    //   286: astore_1
    //   287: goto -114 -> 173
    //   290: astore_1
    //   291: aconst_null
    //   292: astore_3
    //   293: aload_3
    //   294: ifnull +7 -> 301
    //   297: aload_3
    //   298: invokevirtual 149	java/io/OutputStream:close	()V
    //   301: ldc 25
    //   303: invokestatic 215	com/tencent/matrix/trace/core/AppMethodBeat:o	(I)V
    //   306: aload_1
    //   307: athrow
    //   308: astore_1
    //   309: aload_0
    //   310: getfield 14	com/tencent/mm/plugin/expt/ui/ExptDebugUI$7:zNN	Lcom/tencent/mm/plugin/expt/ui/ExptDebugUI;
    //   313: invokevirtual 185	com/tencent/mm/plugin/expt/ui/ExptDebugUI:getContext	()Landroidx/appcompat/app/AppCompatActivity;
    //   316: ldc 220
    //   318: iconst_0
    //   319: invokestatic 205	android/widget/Toast:makeText	(Landroid/content/Context;Ljava/lang/CharSequence;I)Landroid/widget/Toast;
    //   322: invokevirtual 208	android/widget/Toast:show	()V
    //   325: goto -72 -> 253
    //   328: astore_1
    //   329: goto -156 -> 173
    //   332: astore_3
    //   333: goto -32 -> 301
    //   336: astore_3
    //   337: aload_1
    //   338: astore 4
    //   340: aload_3
    //   341: astore_1
    //   342: aload 4
    //   344: astore_3
    //   345: goto -52 -> 293
    //   348: astore_1
    //   349: aload_3
    //   350: astore_1
    //   351: goto -186 -> 165
    // Local variable table:
    //   start	length	slot	name	signature
    //   0	354	0	this	7
    //   0	354	1	paramView	android.view.View
    //   134	10	2	i	int
    //   12	111	3	localObject1	Object
    //   164	1	3	localException	java.lang.Exception
    //   292	6	3	localObject2	Object
    //   332	1	3	localIOException	java.io.IOException
    //   336	5	3	localObject3	Object
    //   344	6	3	localObject4	Object
    //   74	269	4	localObject5	Object
    //   40	68	5	localArrayList	java.util.ArrayList
    // Exception table:
    //   from	to	target	type
    //   107	113	164	java/lang/Exception
    //   113	161	164	java/lang/Exception
    //   271	275	164	java/lang/Exception
    //   279	283	286	java/io/IOException
    //   100	107	290	finally
    //   193	253	308	java/lang/Exception
    //   169	173	328	java/io/IOException
    //   297	301	332	java/io/IOException
    //   107	113	336	finally
    //   113	161	336	finally
    //   271	275	336	finally
    //   100	107	348	java/lang/Exception
  }
}


/* Location:           L:\local\mybackup\temp\qq_apk\com.tencent.mm\classes4.jar
 * Qualified Name:     com.tencent.mm.plugin.expt.ui.ExptDebugUI.7
 * JD-Core Version:    0.7.0.1
 */