package com.tencent.mobileqq.theme.diy;

import android.graphics.drawable.Drawable;

class ThemeDIYActivity$13
  implements Runnable
{
  ThemeDIYActivity$13(ThemeDIYActivity paramThemeDIYActivity, Drawable paramDrawable, ResData paramResData, int paramInt, boolean paramBoolean) {}
  
  /* Error */
  public void run()
  {
    // Byte code:
    //   0: aload_0
    //   1: getfield 22	com/tencent/mobileqq/theme/diy/ThemeDIYActivity$13:val$orgDrawable	Landroid/graphics/drawable/Drawable;
    //   4: astore 5
    //   6: aload 5
    //   8: ifnonnull +157 -> 165
    //   11: aload_0
    //   12: getfield 24	com/tencent/mobileqq/theme/diy/ThemeDIYActivity$13:val$resData	Lcom/tencent/mobileqq/theme/diy/ResData;
    //   15: ifnonnull +12 -> 27
    //   18: ldc 39
    //   20: iconst_1
    //   21: ldc 41
    //   23: invokestatic 47	com/tencent/qphone/base/util/QLog:e	(Ljava/lang/String;ILjava/lang/String;)V
    //   26: return
    //   27: ldc 49
    //   29: aload_0
    //   30: getfield 24	com/tencent/mobileqq/theme/diy/ThemeDIYActivity$13:val$resData	Lcom/tencent/mobileqq/theme/diy/ResData;
    //   33: getfield 55	com/tencent/mobileqq/theme/diy/ResData:id	Ljava/lang/String;
    //   36: invokevirtual 61	java/lang/String:equals	(Ljava/lang/Object;)Z
    //   39: ifeq +103 -> 142
    //   42: aload_0
    //   43: getfield 20	com/tencent/mobileqq/theme/diy/ThemeDIYActivity$13:this$0	Lcom/tencent/mobileqq/theme/diy/ThemeDIYActivity;
    //   46: getfield 67	com/tencent/mobileqq/theme/diy/ThemeDIYActivity:mContext	Landroid/content/Context;
    //   49: aload_0
    //   50: getfield 24	com/tencent/mobileqq/theme/diy/ThemeDIYActivity$13:val$resData	Lcom/tencent/mobileqq/theme/diy/ResData;
    //   53: aload_0
    //   54: getfield 20	com/tencent/mobileqq/theme/diy/ThemeDIYActivity$13:this$0	Lcom/tencent/mobileqq/theme/diy/ThemeDIYActivity;
    //   57: getfield 71	com/tencent/mobileqq/theme/diy/ThemeDIYActivity:mPageView	Lcom/tencent/mobileqq/theme/diy/PageView;
    //   60: getfield 76	com/tencent/mobileqq/theme/diy/PageView:picw	I
    //   63: i2d
    //   64: ldc2_w 77
    //   67: dmul
    //   68: d2i
    //   69: aload_0
    //   70: getfield 20	com/tencent/mobileqq/theme/diy/ThemeDIYActivity$13:this$0	Lcom/tencent/mobileqq/theme/diy/ThemeDIYActivity;
    //   73: getfield 71	com/tencent/mobileqq/theme/diy/ThemeDIYActivity:mPageView	Lcom/tencent/mobileqq/theme/diy/PageView;
    //   76: getfield 81	com/tencent/mobileqq/theme/diy/PageView:pich	I
    //   79: i2d
    //   80: ldc2_w 77
    //   83: dmul
    //   84: d2i
    //   85: iconst_m1
    //   86: iconst_1
    //   87: invokestatic 87	com/tencent/mobileqq/theme/diy/DIYThemeUtils:getDIYDrawable	(Landroid/content/Context;Lcom/tencent/mobileqq/theme/diy/ResData;IIIZ)Landroid/graphics/drawable/Drawable;
    //   90: astore 5
    //   92: aload 5
    //   94: astore 4
    //   96: aload 5
    //   98: ifnonnull +89 -> 187
    //   101: ldc 39
    //   103: iconst_1
    //   104: ldc 89
    //   106: invokestatic 47	com/tencent/qphone/base/util/QLog:e	(Ljava/lang/String;ILjava/lang/String;)V
    //   109: return
    //   110: astore 4
    //   112: ldc 39
    //   114: iconst_2
    //   115: new 91	java/lang/StringBuilder
    //   118: dup
    //   119: invokespecial 92	java/lang/StringBuilder:<init>	()V
    //   122: ldc 94
    //   124: invokevirtual 98	java/lang/StringBuilder:append	(Ljava/lang/String;)Ljava/lang/StringBuilder;
    //   127: aload 4
    //   129: invokevirtual 102	java/lang/Exception:getMessage	()Ljava/lang/String;
    //   132: invokevirtual 98	java/lang/StringBuilder:append	(Ljava/lang/String;)Ljava/lang/StringBuilder;
    //   135: invokevirtual 105	java/lang/StringBuilder:toString	()Ljava/lang/String;
    //   138: invokestatic 108	com/tencent/qphone/base/util/QLog:d	(Ljava/lang/String;ILjava/lang/String;)V
    //   141: return
    //   142: aload_0
    //   143: getfield 20	com/tencent/mobileqq/theme/diy/ThemeDIYActivity$13:this$0	Lcom/tencent/mobileqq/theme/diy/ThemeDIYActivity;
    //   146: getfield 67	com/tencent/mobileqq/theme/diy/ThemeDIYActivity:mContext	Landroid/content/Context;
    //   149: aload_0
    //   150: getfield 24	com/tencent/mobileqq/theme/diy/ThemeDIYActivity$13:val$resData	Lcom/tencent/mobileqq/theme/diy/ResData;
    //   153: iconst_0
    //   154: iconst_0
    //   155: iconst_m1
    //   156: iconst_1
    //   157: invokestatic 87	com/tencent/mobileqq/theme/diy/DIYThemeUtils:getDIYDrawable	(Landroid/content/Context;Lcom/tencent/mobileqq/theme/diy/ResData;IIIZ)Landroid/graphics/drawable/Drawable;
    //   160: astore 5
    //   162: goto -70 -> 92
    //   165: aload 5
    //   167: astore 4
    //   169: aload_0
    //   170: getfield 26	com/tencent/mobileqq/theme/diy/ThemeDIYActivity$13:val$cloneType	I
    //   173: iconst_1
    //   174: if_icmpne +13 -> 187
    //   177: aload 5
    //   179: invokevirtual 114	android/graphics/drawable/Drawable:getConstantState	()Landroid/graphics/drawable/Drawable$ConstantState;
    //   182: invokevirtual 120	android/graphics/drawable/Drawable$ConstantState:newDrawable	()Landroid/graphics/drawable/Drawable;
    //   185: astore 4
    //   187: aload_0
    //   188: getfield 28	com/tencent/mobileqq/theme/diy/ThemeDIYActivity$13:val$needBlur	Z
    //   191: ifeq +323 -> 514
    //   194: aload_0
    //   195: getfield 20	com/tencent/mobileqq/theme/diy/ThemeDIYActivity$13:this$0	Lcom/tencent/mobileqq/theme/diy/ThemeDIYActivity;
    //   198: getfield 71	com/tencent/mobileqq/theme/diy/ThemeDIYActivity:mPageView	Lcom/tencent/mobileqq/theme/diy/PageView;
    //   201: getfield 76	com/tencent/mobileqq/theme/diy/PageView:picw	I
    //   204: i2d
    //   205: ldc2_w 77
    //   208: dmul
    //   209: d2i
    //   210: istore_2
    //   211: aload_0
    //   212: getfield 20	com/tencent/mobileqq/theme/diy/ThemeDIYActivity$13:this$0	Lcom/tencent/mobileqq/theme/diy/ThemeDIYActivity;
    //   215: getfield 71	com/tencent/mobileqq/theme/diy/ThemeDIYActivity:mPageView	Lcom/tencent/mobileqq/theme/diy/PageView;
    //   218: getfield 81	com/tencent/mobileqq/theme/diy/PageView:pich	I
    //   221: istore_1
    //   222: iload_1
    //   223: i2d
    //   224: ldc2_w 77
    //   227: dmul
    //   228: d2i
    //   229: istore_3
    //   230: iload_2
    //   231: ifle +9 -> 240
    //   234: iload_3
    //   235: istore_1
    //   236: iload_3
    //   237: ifgt +10 -> 247
    //   240: bipush 100
    //   242: istore_2
    //   243: sipush 150
    //   246: istore_1
    //   247: aload 4
    //   249: invokevirtual 124	android/graphics/drawable/Drawable:getOpacity	()I
    //   252: iconst_m1
    //   253: if_icmpeq +187 -> 440
    //   256: getstatic 130	android/graphics/Bitmap$Config:ARGB_8888	Landroid/graphics/Bitmap$Config;
    //   259: astore 5
    //   261: iload_2
    //   262: iload_1
    //   263: aload 5
    //   265: invokestatic 136	android/graphics/Bitmap:createBitmap	(IILandroid/graphics/Bitmap$Config;)Landroid/graphics/Bitmap;
    //   268: astore 5
    //   270: new 138	android/graphics/Canvas
    //   273: dup
    //   274: aload 5
    //   276: invokespecial 141	android/graphics/Canvas:<init>	(Landroid/graphics/Bitmap;)V
    //   279: astore 6
    //   281: aload 4
    //   283: iconst_0
    //   284: iconst_0
    //   285: iload_2
    //   286: iload_1
    //   287: invokevirtual 145	android/graphics/drawable/Drawable:setBounds	(IIII)V
    //   290: aload 4
    //   292: aload 6
    //   294: invokevirtual 149	android/graphics/drawable/Drawable:draw	(Landroid/graphics/Canvas;)V
    //   297: aload 5
    //   299: ifnull +224 -> 523
    //   302: aload 5
    //   304: invokevirtual 153	android/graphics/Bitmap:isMutable	()Z
    //   307: ifne +216 -> 523
    //   310: aload 5
    //   312: ifnull +205 -> 517
    //   315: aload 5
    //   317: invokevirtual 156	android/graphics/Bitmap:isRecycled	()Z
    //   320: ifne +197 -> 517
    //   323: aload 5
    //   325: aload 5
    //   327: invokevirtual 159	android/graphics/Bitmap:getWidth	()I
    //   330: iconst_2
    //   331: idiv
    //   332: aload 5
    //   334: invokevirtual 162	android/graphics/Bitmap:getHeight	()I
    //   337: iconst_2
    //   338: idiv
    //   339: iconst_1
    //   340: invokestatic 166	android/graphics/Bitmap:createScaledBitmap	(Landroid/graphics/Bitmap;IIZ)Landroid/graphics/Bitmap;
    //   343: astore 6
    //   345: aload 5
    //   347: invokevirtual 169	android/graphics/Bitmap:recycle	()V
    //   350: aload 6
    //   352: astore 5
    //   354: aload 5
    //   356: ifnull +150 -> 506
    //   359: aload 5
    //   361: bipush 8
    //   363: invokestatic 175	aqmp:fastblur	(Landroid/graphics/Bitmap;I)V
    //   366: new 177	android/graphics/drawable/BitmapDrawable
    //   369: dup
    //   370: aload 5
    //   372: invokespecial 178	android/graphics/drawable/BitmapDrawable:<init>	(Landroid/graphics/Bitmap;)V
    //   375: astore 4
    //   377: aload_0
    //   378: getfield 20	com/tencent/mobileqq/theme/diy/ThemeDIYActivity$13:this$0	Lcom/tencent/mobileqq/theme/diy/ThemeDIYActivity;
    //   381: getfield 182	com/tencent/mobileqq/theme/diy/ThemeDIYActivity:mHandler	Landroid/os/Handler;
    //   384: aload_0
    //   385: getfield 20	com/tencent/mobileqq/theme/diy/ThemeDIYActivity$13:this$0	Lcom/tencent/mobileqq/theme/diy/ThemeDIYActivity;
    //   388: getfield 182	com/tencent/mobileqq/theme/diy/ThemeDIYActivity:mHandler	Landroid/os/Handler;
    //   391: bipush 20
    //   393: aload_0
    //   394: getfield 26	com/tencent/mobileqq/theme/diy/ThemeDIYActivity$13:val$cloneType	I
    //   397: iconst_0
    //   398: aload 4
    //   400: invokestatic 188	android/os/Message:obtain	(Landroid/os/Handler;IIILjava/lang/Object;)Landroid/os/Message;
    //   403: invokevirtual 194	android/os/Handler:sendMessage	(Landroid/os/Message;)Z
    //   406: pop
    //   407: return
    //   408: astore 4
    //   410: ldc 39
    //   412: iconst_2
    //   413: new 91	java/lang/StringBuilder
    //   416: dup
    //   417: invokespecial 92	java/lang/StringBuilder:<init>	()V
    //   420: ldc 94
    //   422: invokevirtual 98	java/lang/StringBuilder:append	(Ljava/lang/String;)Ljava/lang/StringBuilder;
    //   425: aload 4
    //   427: invokevirtual 195	java/lang/OutOfMemoryError:getMessage	()Ljava/lang/String;
    //   430: invokevirtual 98	java/lang/StringBuilder:append	(Ljava/lang/String;)Ljava/lang/StringBuilder;
    //   433: invokevirtual 105	java/lang/StringBuilder:toString	()Ljava/lang/String;
    //   436: invokestatic 108	com/tencent/qphone/base/util/QLog:d	(Ljava/lang/String;ILjava/lang/String;)V
    //   439: return
    //   440: getstatic 198	android/graphics/Bitmap$Config:RGB_565	Landroid/graphics/Bitmap$Config;
    //   443: astore 5
    //   445: goto -184 -> 261
    //   448: astore 4
    //   450: ldc 39
    //   452: iconst_1
    //   453: new 91	java/lang/StringBuilder
    //   456: dup
    //   457: invokespecial 92	java/lang/StringBuilder:<init>	()V
    //   460: ldc 200
    //   462: invokevirtual 98	java/lang/StringBuilder:append	(Ljava/lang/String;)Ljava/lang/StringBuilder;
    //   465: aload 4
    //   467: invokevirtual 203	java/lang/StringBuilder:append	(Ljava/lang/Object;)Ljava/lang/StringBuilder;
    //   470: invokevirtual 105	java/lang/StringBuilder:toString	()Ljava/lang/String;
    //   473: invokestatic 47	com/tencent/qphone/base/util/QLog:e	(Ljava/lang/String;ILjava/lang/String;)V
    //   476: return
    //   477: astore 4
    //   479: ldc 39
    //   481: iconst_1
    //   482: new 91	java/lang/StringBuilder
    //   485: dup
    //   486: invokespecial 92	java/lang/StringBuilder:<init>	()V
    //   489: ldc 205
    //   491: invokevirtual 98	java/lang/StringBuilder:append	(Ljava/lang/String;)Ljava/lang/StringBuilder;
    //   494: aload 4
    //   496: invokevirtual 203	java/lang/StringBuilder:append	(Ljava/lang/Object;)Ljava/lang/StringBuilder;
    //   499: invokevirtual 105	java/lang/StringBuilder:toString	()Ljava/lang/String;
    //   502: invokestatic 47	com/tencent/qphone/base/util/QLog:e	(Ljava/lang/String;ILjava/lang/String;)V
    //   505: return
    //   506: ldc 39
    //   508: iconst_1
    //   509: ldc 207
    //   511: invokestatic 47	com/tencent/qphone/base/util/QLog:e	(Ljava/lang/String;ILjava/lang/String;)V
    //   514: goto -137 -> 377
    //   517: aconst_null
    //   518: astore 5
    //   520: goto -166 -> 354
    //   523: goto -169 -> 354
    // Local variable table:
    //   start	length	slot	name	signature
    //   0	526	0	this	13
    //   221	66	1	i	int
    //   210	76	2	j	int
    //   229	8	3	k	int
    //   94	1	4	localObject1	Object
    //   110	18	4	localException1	java.lang.Exception
    //   167	232	4	localObject2	Object
    //   408	18	4	localOutOfMemoryError1	java.lang.OutOfMemoryError
    //   448	18	4	localOutOfMemoryError2	java.lang.OutOfMemoryError
    //   477	18	4	localException2	java.lang.Exception
    //   4	515	5	localObject3	Object
    //   279	72	6	localObject4	Object
    // Exception table:
    //   from	to	target	type
    //   0	6	110	java/lang/Exception
    //   11	26	110	java/lang/Exception
    //   27	92	110	java/lang/Exception
    //   101	109	110	java/lang/Exception
    //   142	162	110	java/lang/Exception
    //   169	187	110	java/lang/Exception
    //   187	222	110	java/lang/Exception
    //   302	310	110	java/lang/Exception
    //   315	350	110	java/lang/Exception
    //   359	377	110	java/lang/Exception
    //   377	407	110	java/lang/Exception
    //   450	476	110	java/lang/Exception
    //   479	505	110	java/lang/Exception
    //   506	514	110	java/lang/Exception
    //   0	6	408	java/lang/OutOfMemoryError
    //   11	26	408	java/lang/OutOfMemoryError
    //   27	92	408	java/lang/OutOfMemoryError
    //   101	109	408	java/lang/OutOfMemoryError
    //   142	162	408	java/lang/OutOfMemoryError
    //   169	187	408	java/lang/OutOfMemoryError
    //   187	222	408	java/lang/OutOfMemoryError
    //   302	310	408	java/lang/OutOfMemoryError
    //   315	350	408	java/lang/OutOfMemoryError
    //   359	377	408	java/lang/OutOfMemoryError
    //   377	407	408	java/lang/OutOfMemoryError
    //   450	476	408	java/lang/OutOfMemoryError
    //   479	505	408	java/lang/OutOfMemoryError
    //   506	514	408	java/lang/OutOfMemoryError
    //   247	261	448	java/lang/OutOfMemoryError
    //   261	297	448	java/lang/OutOfMemoryError
    //   440	445	448	java/lang/OutOfMemoryError
    //   247	261	477	java/lang/Exception
    //   261	297	477	java/lang/Exception
    //   440	445	477	java/lang/Exception
  }
}


/* Location:           L:\local\mybackup\temp\qq_apk\com.tencent.tim\classes9.jar
 * Qualified Name:     com.tencent.mobileqq.theme.diy.ThemeDIYActivity.13
 * JD-Core Version:    0.7.0.1
 */