package com.tencent.mm.plugin.sns.storage.AdLandingPagesStorage;

public final class f
  extends b
{
  private a JLv;
  
  public f(String paramString1, String paramString2, boolean paramBoolean, int paramInt1, int paramInt2, a parama)
  {
    this.url = paramString1;
    this.filePath = paramString2;
    this.KxW = paramBoolean;
    this.KxX = paramInt1;
    this.scene = paramInt2;
    this.JLv = parama;
  }
  
  /* Error */
  private String fSp()
  {
    // Byte code:
    //   0: ldc 44
    //   2: invokestatic 50	com/tencent/matrix/trace/core/AppMethodBeat:i	(I)V
    //   5: aload_0
    //   6: getfield 21	com/tencent/mm/plugin/sns/storage/AdLandingPagesStorage/f:filePath	Ljava/lang/String;
    //   9: invokestatic 56	com/tencent/mm/vfs/u:agG	(Ljava/lang/String;)Z
    //   12: ifeq +10 -> 22
    //   15: ldc 44
    //   17: invokestatic 59	com/tencent/matrix/trace/core/AppMethodBeat:o	(I)V
    //   20: aconst_null
    //   21: areturn
    //   22: invokestatic 65	com/tencent/mm/sdk/platformtools/MMApplicationContext:getContext	()Landroid/content/Context;
    //   25: invokestatic 71	com/tencent/mm/sdk/platformtools/NetStatusUtil:getFormatedNetType	(Landroid/content/Context;)Ljava/lang/String;
    //   28: astore 24
    //   30: ldc 73
    //   32: new 75	java/lang/StringBuilder
    //   35: dup
    //   36: ldc 77
    //   38: invokespecial 80	java/lang/StringBuilder:<init>	(Ljava/lang/String;)V
    //   41: aload 24
    //   43: invokevirtual 84	java/lang/StringBuilder:append	(Ljava/lang/String;)Ljava/lang/StringBuilder;
    //   46: ldc 86
    //   48: invokevirtual 84	java/lang/StringBuilder:append	(Ljava/lang/String;)Ljava/lang/StringBuilder;
    //   51: aload_0
    //   52: getfield 18	com/tencent/mm/plugin/sns/storage/AdLandingPagesStorage/f:url	Ljava/lang/String;
    //   55: invokevirtual 84	java/lang/StringBuilder:append	(Ljava/lang/String;)Ljava/lang/StringBuilder;
    //   58: invokevirtual 89	java/lang/StringBuilder:toString	()Ljava/lang/String;
    //   61: invokestatic 94	com/tencent/mm/sdk/platformtools/Log:i	(Ljava/lang/String;Ljava/lang/String;)V
    //   64: invokestatic 100	com/tencent/mm/sdk/platformtools/Util:nowMilliSecond	()J
    //   67: lstore 11
    //   69: iconst_0
    //   70: istore_1
    //   71: iconst_0
    //   72: istore 6
    //   74: iconst_0
    //   75: istore 10
    //   77: iconst_0
    //   78: istore_3
    //   79: iconst_0
    //   80: istore 5
    //   82: iconst_0
    //   83: istore_2
    //   84: iconst_0
    //   85: istore 8
    //   87: iconst_0
    //   88: istore 9
    //   90: iconst_0
    //   91: istore 7
    //   93: aload_0
    //   94: getfield 21	com/tencent/mm/plugin/sns/storage/AdLandingPagesStorage/f:filePath	Ljava/lang/String;
    //   97: iconst_0
    //   98: aload_0
    //   99: getfield 21	com/tencent/mm/plugin/sns/storage/AdLandingPagesStorage/f:filePath	Ljava/lang/String;
    //   102: ldc 102
    //   104: invokevirtual 108	java/lang/String:lastIndexOf	(Ljava/lang/String;)I
    //   107: invokevirtual 112	java/lang/String:substring	(II)Ljava/lang/String;
    //   110: invokestatic 115	com/tencent/mm/vfs/u:bBD	(Ljava/lang/String;)Z
    //   113: pop
    //   114: aconst_null
    //   115: astore 15
    //   117: aconst_null
    //   118: astore 18
    //   120: aconst_null
    //   121: astore 22
    //   123: aconst_null
    //   124: astore 23
    //   126: aconst_null
    //   127: astore 14
    //   129: aconst_null
    //   130: astore 19
    //   132: aconst_null
    //   133: astore 20
    //   135: aconst_null
    //   136: astore 16
    //   138: aconst_null
    //   139: astore 13
    //   141: aconst_null
    //   142: astore 21
    //   144: aload_0
    //   145: getfield 34	com/tencent/mm/plugin/sns/storage/AdLandingPagesStorage/f:JLv	Lcom/tencent/mm/plugin/sns/storage/AdLandingPagesStorage/f$a;
    //   148: invokeinterface 118 1 0
    //   153: new 120	java/net/URL
    //   156: dup
    //   157: aload_0
    //   158: getfield 18	com/tencent/mm/plugin/sns/storage/AdLandingPagesStorage/f:url	Ljava/lang/String;
    //   161: invokespecial 121	java/net/URL:<init>	(Ljava/lang/String;)V
    //   164: invokevirtual 125	java/net/URL:openConnection	()Ljava/net/URLConnection;
    //   167: checkcast 127	java/net/HttpURLConnection
    //   170: astore 17
    //   172: aload 19
    //   174: astore 15
    //   176: aload 18
    //   178: astore 13
    //   180: iload 8
    //   182: istore 4
    //   184: iload 6
    //   186: istore_2
    //   187: aload 20
    //   189: astore 16
    //   191: aload 22
    //   193: astore 14
    //   195: iload 9
    //   197: istore 5
    //   199: iload 10
    //   201: istore_3
    //   202: aload 17
    //   204: sipush 10000
    //   207: invokevirtual 130	java/net/HttpURLConnection:setConnectTimeout	(I)V
    //   210: aload 19
    //   212: astore 15
    //   214: aload 18
    //   216: astore 13
    //   218: iload 8
    //   220: istore 4
    //   222: iload 6
    //   224: istore_2
    //   225: aload 20
    //   227: astore 16
    //   229: aload 22
    //   231: astore 14
    //   233: iload 9
    //   235: istore 5
    //   237: iload 10
    //   239: istore_3
    //   240: aload 17
    //   242: sipush 10000
    //   245: invokevirtual 133	java/net/HttpURLConnection:setReadTimeout	(I)V
    //   248: aload 19
    //   250: astore 15
    //   252: aload 18
    //   254: astore 13
    //   256: iload 8
    //   258: istore 4
    //   260: iload 6
    //   262: istore_2
    //   263: aload 20
    //   265: astore 16
    //   267: aload 22
    //   269: astore 14
    //   271: iload 9
    //   273: istore 5
    //   275: iload 10
    //   277: istore_3
    //   278: aload 17
    //   280: invokevirtual 136	java/net/HttpURLConnection:connect	()V
    //   283: aload 19
    //   285: astore 15
    //   287: aload 18
    //   289: astore 13
    //   291: iload 8
    //   293: istore 4
    //   295: iload 6
    //   297: istore_2
    //   298: aload 20
    //   300: astore 16
    //   302: aload 22
    //   304: astore 14
    //   306: iload 9
    //   308: istore 5
    //   310: iload 10
    //   312: istore_3
    //   313: aload 17
    //   315: invokevirtual 140	java/net/HttpURLConnection:getResponseCode	()I
    //   318: istore 6
    //   320: iload 6
    //   322: sipush 200
    //   325: if_icmpeq +411 -> 736
    //   328: aload 19
    //   330: astore 15
    //   332: aload 18
    //   334: astore 13
    //   336: iload 8
    //   338: istore 4
    //   340: iload 6
    //   342: istore_2
    //   343: aload 20
    //   345: astore 16
    //   347: aload 22
    //   349: astore 14
    //   351: iload 9
    //   353: istore 5
    //   355: iload 6
    //   357: istore_3
    //   358: new 75	java/lang/StringBuilder
    //   361: dup
    //   362: ldc 142
    //   364: invokespecial 80	java/lang/StringBuilder:<init>	(Ljava/lang/String;)V
    //   367: aload 17
    //   369: invokevirtual 140	java/net/HttpURLConnection:getResponseCode	()I
    //   372: invokevirtual 145	java/lang/StringBuilder:append	(I)Ljava/lang/StringBuilder;
    //   375: ldc 147
    //   377: invokevirtual 84	java/lang/StringBuilder:append	(Ljava/lang/String;)Ljava/lang/StringBuilder;
    //   380: aload 24
    //   382: invokevirtual 84	java/lang/StringBuilder:append	(Ljava/lang/String;)Ljava/lang/StringBuilder;
    //   385: ldc 149
    //   387: invokevirtual 84	java/lang/StringBuilder:append	(Ljava/lang/String;)Ljava/lang/StringBuilder;
    //   390: aload 17
    //   392: invokevirtual 152	java/net/HttpURLConnection:getResponseMessage	()Ljava/lang/String;
    //   395: invokevirtual 84	java/lang/StringBuilder:append	(Ljava/lang/String;)Ljava/lang/StringBuilder;
    //   398: invokevirtual 89	java/lang/StringBuilder:toString	()Ljava/lang/String;
    //   401: astore 18
    //   403: aload 17
    //   405: invokevirtual 156	java/net/HttpURLConnection:getInputStream	()Ljava/io/InputStream;
    //   408: invokevirtual 161	java/io/InputStream:close	()V
    //   411: aload 17
    //   413: ifnull +8 -> 421
    //   416: aload 17
    //   418: invokevirtual 164	java/net/HttpURLConnection:disconnect	()V
    //   421: aload_0
    //   422: getfield 18	com/tencent/mm/plugin/sns/storage/AdLandingPagesStorage/f:url	Ljava/lang/String;
    //   425: invokestatic 170	com/tencent/mm/sdk/platformtools/MD5Util:getMD5String	(Ljava/lang/String;)Ljava/lang/String;
    //   428: astore 14
    //   430: aload_0
    //   431: invokespecial 173	com/tencent/mm/plugin/sns/storage/AdLandingPagesStorage/f:getMediaType	()I
    //   434: istore_1
    //   435: lload 11
    //   437: invokestatic 177	com/tencent/mm/sdk/platformtools/Util:milliSecondsToNow	(J)J
    //   440: l2i
    //   441: istore_2
    //   442: new 179	com/tencent/mm/modelsns/n
    //   445: dup
    //   446: invokespecial 180	com/tencent/mm/modelsns/n:<init>	()V
    //   449: astore 13
    //   451: aload 13
    //   453: ldc 182
    //   455: new 75	java/lang/StringBuilder
    //   458: dup
    //   459: invokespecial 183	java/lang/StringBuilder:<init>	()V
    //   462: aload 14
    //   464: invokevirtual 84	java/lang/StringBuilder:append	(Ljava/lang/String;)Ljava/lang/StringBuilder;
    //   467: ldc 185
    //   469: invokevirtual 84	java/lang/StringBuilder:append	(Ljava/lang/String;)Ljava/lang/StringBuilder;
    //   472: invokevirtual 89	java/lang/StringBuilder:toString	()Ljava/lang/String;
    //   475: invokevirtual 189	com/tencent/mm/modelsns/n:m	(Ljava/lang/String;Ljava/lang/Object;)V
    //   478: aload 13
    //   480: ldc 191
    //   482: new 75	java/lang/StringBuilder
    //   485: dup
    //   486: invokespecial 183	java/lang/StringBuilder:<init>	()V
    //   489: iload_1
    //   490: invokevirtual 145	java/lang/StringBuilder:append	(I)Ljava/lang/StringBuilder;
    //   493: ldc 185
    //   495: invokevirtual 84	java/lang/StringBuilder:append	(Ljava/lang/String;)Ljava/lang/StringBuilder;
    //   498: invokevirtual 89	java/lang/StringBuilder:toString	()Ljava/lang/String;
    //   501: invokevirtual 189	com/tencent/mm/modelsns/n:m	(Ljava/lang/String;Ljava/lang/Object;)V
    //   504: new 75	java/lang/StringBuilder
    //   507: dup
    //   508: invokespecial 183	java/lang/StringBuilder:<init>	()V
    //   511: astore 14
    //   513: aload_0
    //   514: getfield 25	com/tencent/mm/plugin/sns/storage/AdLandingPagesStorage/f:KxW	Z
    //   517: ifeq +214 -> 731
    //   520: iconst_1
    //   521: istore_1
    //   522: aload 13
    //   524: ldc 193
    //   526: aload 14
    //   528: iload_1
    //   529: invokevirtual 145	java/lang/StringBuilder:append	(I)Ljava/lang/StringBuilder;
    //   532: ldc 185
    //   534: invokevirtual 84	java/lang/StringBuilder:append	(Ljava/lang/String;)Ljava/lang/StringBuilder;
    //   537: invokevirtual 89	java/lang/StringBuilder:toString	()Ljava/lang/String;
    //   540: invokevirtual 189	com/tencent/mm/modelsns/n:m	(Ljava/lang/String;Ljava/lang/Object;)V
    //   543: aload 13
    //   545: ldc 195
    //   547: new 75	java/lang/StringBuilder
    //   550: dup
    //   551: invokespecial 183	java/lang/StringBuilder:<init>	()V
    //   554: iload_2
    //   555: invokevirtual 145	java/lang/StringBuilder:append	(I)Ljava/lang/StringBuilder;
    //   558: ldc 185
    //   560: invokevirtual 84	java/lang/StringBuilder:append	(Ljava/lang/String;)Ljava/lang/StringBuilder;
    //   563: invokevirtual 89	java/lang/StringBuilder:toString	()Ljava/lang/String;
    //   566: invokevirtual 189	com/tencent/mm/modelsns/n:m	(Ljava/lang/String;Ljava/lang/Object;)V
    //   569: aload 13
    //   571: ldc 197
    //   573: new 75	java/lang/StringBuilder
    //   576: dup
    //   577: invokespecial 183	java/lang/StringBuilder:<init>	()V
    //   580: iload 6
    //   582: invokevirtual 145	java/lang/StringBuilder:append	(I)Ljava/lang/StringBuilder;
    //   585: ldc 185
    //   587: invokevirtual 84	java/lang/StringBuilder:append	(Ljava/lang/String;)Ljava/lang/StringBuilder;
    //   590: invokevirtual 89	java/lang/StringBuilder:toString	()Ljava/lang/String;
    //   593: invokevirtual 189	com/tencent/mm/modelsns/n:m	(Ljava/lang/String;Ljava/lang/Object;)V
    //   596: aload 13
    //   598: ldc 199
    //   600: new 75	java/lang/StringBuilder
    //   603: dup
    //   604: invokespecial 183	java/lang/StringBuilder:<init>	()V
    //   607: aload_0
    //   608: getfield 32	com/tencent/mm/plugin/sns/storage/AdLandingPagesStorage/f:scene	I
    //   611: invokevirtual 145	java/lang/StringBuilder:append	(I)Ljava/lang/StringBuilder;
    //   614: ldc 185
    //   616: invokevirtual 84	java/lang/StringBuilder:append	(Ljava/lang/String;)Ljava/lang/StringBuilder;
    //   619: invokevirtual 89	java/lang/StringBuilder:toString	()Ljava/lang/String;
    //   622: invokevirtual 189	com/tencent/mm/modelsns/n:m	(Ljava/lang/String;Ljava/lang/Object;)V
    //   625: aload 13
    //   627: ldc 201
    //   629: ldc 203
    //   631: invokevirtual 189	com/tencent/mm/modelsns/n:m	(Ljava/lang/String;Ljava/lang/Object;)V
    //   634: aload 13
    //   636: ldc 205
    //   638: new 75	java/lang/StringBuilder
    //   641: dup
    //   642: invokespecial 183	java/lang/StringBuilder:<init>	()V
    //   645: lload 11
    //   647: ldc2_w 206
    //   650: ldiv
    //   651: invokevirtual 210	java/lang/StringBuilder:append	(J)Ljava/lang/StringBuilder;
    //   654: ldc 185
    //   656: invokevirtual 84	java/lang/StringBuilder:append	(Ljava/lang/String;)Ljava/lang/StringBuilder;
    //   659: invokevirtual 89	java/lang/StringBuilder:toString	()Ljava/lang/String;
    //   662: invokevirtual 189	com/tencent/mm/modelsns/n:m	(Ljava/lang/String;Ljava/lang/Object;)V
    //   665: ldc 73
    //   667: new 75	java/lang/StringBuilder
    //   670: dup
    //   671: ldc 212
    //   673: invokespecial 80	java/lang/StringBuilder:<init>	(Ljava/lang/String;)V
    //   676: aload 13
    //   678: invokevirtual 215	com/tencent/mm/modelsns/n:agI	()Ljava/lang/String;
    //   681: invokevirtual 84	java/lang/StringBuilder:append	(Ljava/lang/String;)Ljava/lang/StringBuilder;
    //   684: invokevirtual 89	java/lang/StringBuilder:toString	()Ljava/lang/String;
    //   687: invokestatic 94	com/tencent/mm/sdk/platformtools/Log:i	(Ljava/lang/String;Ljava/lang/String;)V
    //   690: getstatic 221	com/tencent/mm/plugin/report/service/h:IzE	Lcom/tencent/mm/plugin/report/service/h;
    //   693: sipush 13572
    //   696: iconst_1
    //   697: anewarray 223	java/lang/Object
    //   700: dup
    //   701: iconst_0
    //   702: aload 13
    //   704: aastore
    //   705: invokevirtual 226	com/tencent/mm/plugin/report/service/h:a	(I[Ljava/lang/Object;)V
    //   708: ldc 44
    //   710: invokestatic 59	com/tencent/matrix/trace/core/AppMethodBeat:o	(I)V
    //   713: aload 18
    //   715: areturn
    //   716: astore 13
    //   718: ldc 73
    //   720: aload 13
    //   722: invokevirtual 229	java/lang/Exception:getMessage	()Ljava/lang/String;
    //   725: invokestatic 232	com/tencent/mm/sdk/platformtools/Log:e	(Ljava/lang/String;Ljava/lang/String;)V
    //   728: goto -317 -> 411
    //   731: iconst_0
    //   732: istore_1
    //   733: goto -211 -> 522
    //   736: aload 19
    //   738: astore 15
    //   740: aload 18
    //   742: astore 13
    //   744: iload 8
    //   746: istore 4
    //   748: iload 6
    //   750: istore_2
    //   751: aload 20
    //   753: astore 16
    //   755: aload 22
    //   757: astore 14
    //   759: iload 9
    //   761: istore 5
    //   763: iload 6
    //   765: istore_3
    //   766: aload 17
    //   768: invokevirtual 235	java/net/HttpURLConnection:getContentLength	()I
    //   771: pop
    //   772: aload 19
    //   774: astore 15
    //   776: aload 18
    //   778: astore 13
    //   780: iload 8
    //   782: istore 4
    //   784: iload 6
    //   786: istore_2
    //   787: aload 20
    //   789: astore 16
    //   791: aload 22
    //   793: astore 14
    //   795: iload 9
    //   797: istore 5
    //   799: iload 6
    //   801: istore_3
    //   802: aload 17
    //   804: invokevirtual 156	java/net/HttpURLConnection:getInputStream	()Ljava/io/InputStream;
    //   807: astore 18
    //   809: aload 19
    //   811: astore 15
    //   813: aload 18
    //   815: astore 13
    //   817: iload 8
    //   819: istore 4
    //   821: iload 6
    //   823: istore_2
    //   824: aload 20
    //   826: astore 16
    //   828: aload 18
    //   830: astore 14
    //   832: iload 9
    //   834: istore 5
    //   836: iload 6
    //   838: istore_3
    //   839: aload_0
    //   840: getfield 21	com/tencent/mm/plugin/sns/storage/AdLandingPagesStorage/f:filePath	Ljava/lang/String;
    //   843: invokestatic 239	com/tencent/mm/vfs/u:Te	(Ljava/lang/String;)Ljava/io/OutputStream;
    //   846: astore 19
    //   848: aload 19
    //   850: astore 15
    //   852: aload 18
    //   854: astore 13
    //   856: iload 8
    //   858: istore 4
    //   860: iload 6
    //   862: istore_2
    //   863: aload 19
    //   865: astore 16
    //   867: aload 18
    //   869: astore 14
    //   871: iload 9
    //   873: istore 5
    //   875: iload 6
    //   877: istore_3
    //   878: sipush 4096
    //   881: newarray byte
    //   883: astore 20
    //   885: iload 7
    //   887: istore_1
    //   888: aload 19
    //   890: astore 15
    //   892: aload 18
    //   894: astore 13
    //   896: iload_1
    //   897: istore 4
    //   899: iload 6
    //   901: istore_2
    //   902: aload 19
    //   904: astore 16
    //   906: aload 18
    //   908: astore 14
    //   910: iload_1
    //   911: istore 5
    //   913: iload 6
    //   915: istore_3
    //   916: aload 18
    //   918: aload 20
    //   920: invokevirtual 243	java/io/InputStream:read	([B)I
    //   923: istore 7
    //   925: iload 7
    //   927: iconst_m1
    //   928: if_icmpeq +486 -> 1414
    //   931: aload 19
    //   933: astore 15
    //   935: aload 18
    //   937: astore 13
    //   939: iload_1
    //   940: istore 4
    //   942: iload 6
    //   944: istore_2
    //   945: aload 19
    //   947: astore 16
    //   949: aload 18
    //   951: astore 14
    //   953: iload_1
    //   954: istore 5
    //   956: iload 6
    //   958: istore_3
    //   959: aload_0
    //   960: invokevirtual 247	com/tencent/mm/plugin/sns/storage/AdLandingPagesStorage/f:isCancelled	()Z
    //   963: ifeq +405 -> 1368
    //   966: aload 19
    //   968: astore 15
    //   970: aload 18
    //   972: astore 13
    //   974: iload_1
    //   975: istore 4
    //   977: iload 6
    //   979: istore_2
    //   980: aload 19
    //   982: astore 16
    //   984: aload 18
    //   986: astore 14
    //   988: iload_1
    //   989: istore 5
    //   991: iload 6
    //   993: istore_3
    //   994: aload 18
    //   996: invokevirtual 161	java/io/InputStream:close	()V
    //   999: aload 19
    //   1001: ifnull +8 -> 1009
    //   1004: aload 19
    //   1006: invokevirtual 250	java/io/OutputStream:close	()V
    //   1009: aload 18
    //   1011: ifnull +8 -> 1019
    //   1014: aload 18
    //   1016: invokevirtual 161	java/io/InputStream:close	()V
    //   1019: aload 17
    //   1021: invokevirtual 156	java/net/HttpURLConnection:getInputStream	()Ljava/io/InputStream;
    //   1024: invokevirtual 161	java/io/InputStream:close	()V
    //   1027: aload 17
    //   1029: ifnull +8 -> 1037
    //   1032: aload 17
    //   1034: invokevirtual 164	java/net/HttpURLConnection:disconnect	()V
    //   1037: aload_0
    //   1038: getfield 18	com/tencent/mm/plugin/sns/storage/AdLandingPagesStorage/f:url	Ljava/lang/String;
    //   1041: invokestatic 170	com/tencent/mm/sdk/platformtools/MD5Util:getMD5String	(Ljava/lang/String;)Ljava/lang/String;
    //   1044: astore 14
    //   1046: aload_0
    //   1047: invokespecial 173	com/tencent/mm/plugin/sns/storage/AdLandingPagesStorage/f:getMediaType	()I
    //   1050: istore_2
    //   1051: lload 11
    //   1053: invokestatic 177	com/tencent/mm/sdk/platformtools/Util:milliSecondsToNow	(J)J
    //   1056: l2i
    //   1057: istore_3
    //   1058: new 179	com/tencent/mm/modelsns/n
    //   1061: dup
    //   1062: invokespecial 180	com/tencent/mm/modelsns/n:<init>	()V
    //   1065: astore 13
    //   1067: aload 13
    //   1069: ldc 182
    //   1071: new 75	java/lang/StringBuilder
    //   1074: dup
    //   1075: invokespecial 183	java/lang/StringBuilder:<init>	()V
    //   1078: aload 14
    //   1080: invokevirtual 84	java/lang/StringBuilder:append	(Ljava/lang/String;)Ljava/lang/StringBuilder;
    //   1083: ldc 185
    //   1085: invokevirtual 84	java/lang/StringBuilder:append	(Ljava/lang/String;)Ljava/lang/StringBuilder;
    //   1088: invokevirtual 89	java/lang/StringBuilder:toString	()Ljava/lang/String;
    //   1091: invokevirtual 189	com/tencent/mm/modelsns/n:m	(Ljava/lang/String;Ljava/lang/Object;)V
    //   1094: aload 13
    //   1096: ldc 191
    //   1098: new 75	java/lang/StringBuilder
    //   1101: dup
    //   1102: invokespecial 183	java/lang/StringBuilder:<init>	()V
    //   1105: iload_2
    //   1106: invokevirtual 145	java/lang/StringBuilder:append	(I)Ljava/lang/StringBuilder;
    //   1109: ldc 185
    //   1111: invokevirtual 84	java/lang/StringBuilder:append	(Ljava/lang/String;)Ljava/lang/StringBuilder;
    //   1114: invokevirtual 89	java/lang/StringBuilder:toString	()Ljava/lang/String;
    //   1117: invokevirtual 189	com/tencent/mm/modelsns/n:m	(Ljava/lang/String;Ljava/lang/Object;)V
    //   1120: new 75	java/lang/StringBuilder
    //   1123: dup
    //   1124: invokespecial 183	java/lang/StringBuilder:<init>	()V
    //   1127: astore 14
    //   1129: aload_0
    //   1130: getfield 25	com/tencent/mm/plugin/sns/storage/AdLandingPagesStorage/f:KxW	Z
    //   1133: ifeq +230 -> 1363
    //   1136: iconst_1
    //   1137: istore_2
    //   1138: aload 13
    //   1140: ldc 193
    //   1142: aload 14
    //   1144: iload_2
    //   1145: invokevirtual 145	java/lang/StringBuilder:append	(I)Ljava/lang/StringBuilder;
    //   1148: ldc 185
    //   1150: invokevirtual 84	java/lang/StringBuilder:append	(Ljava/lang/String;)Ljava/lang/StringBuilder;
    //   1153: invokevirtual 89	java/lang/StringBuilder:toString	()Ljava/lang/String;
    //   1156: invokevirtual 189	com/tencent/mm/modelsns/n:m	(Ljava/lang/String;Ljava/lang/Object;)V
    //   1159: aload 13
    //   1161: ldc 195
    //   1163: new 75	java/lang/StringBuilder
    //   1166: dup
    //   1167: invokespecial 183	java/lang/StringBuilder:<init>	()V
    //   1170: iload_3
    //   1171: invokevirtual 145	java/lang/StringBuilder:append	(I)Ljava/lang/StringBuilder;
    //   1174: ldc 185
    //   1176: invokevirtual 84	java/lang/StringBuilder:append	(Ljava/lang/String;)Ljava/lang/StringBuilder;
    //   1179: invokevirtual 89	java/lang/StringBuilder:toString	()Ljava/lang/String;
    //   1182: invokevirtual 189	com/tencent/mm/modelsns/n:m	(Ljava/lang/String;Ljava/lang/Object;)V
    //   1185: aload 13
    //   1187: ldc 197
    //   1189: new 75	java/lang/StringBuilder
    //   1192: dup
    //   1193: invokespecial 183	java/lang/StringBuilder:<init>	()V
    //   1196: iload 6
    //   1198: invokevirtual 145	java/lang/StringBuilder:append	(I)Ljava/lang/StringBuilder;
    //   1201: ldc 185
    //   1203: invokevirtual 84	java/lang/StringBuilder:append	(Ljava/lang/String;)Ljava/lang/StringBuilder;
    //   1206: invokevirtual 89	java/lang/StringBuilder:toString	()Ljava/lang/String;
    //   1209: invokevirtual 189	com/tencent/mm/modelsns/n:m	(Ljava/lang/String;Ljava/lang/Object;)V
    //   1212: aload 13
    //   1214: ldc 199
    //   1216: new 75	java/lang/StringBuilder
    //   1219: dup
    //   1220: invokespecial 183	java/lang/StringBuilder:<init>	()V
    //   1223: aload_0
    //   1224: getfield 32	com/tencent/mm/plugin/sns/storage/AdLandingPagesStorage/f:scene	I
    //   1227: invokevirtual 145	java/lang/StringBuilder:append	(I)Ljava/lang/StringBuilder;
    //   1230: ldc 185
    //   1232: invokevirtual 84	java/lang/StringBuilder:append	(Ljava/lang/String;)Ljava/lang/StringBuilder;
    //   1235: invokevirtual 89	java/lang/StringBuilder:toString	()Ljava/lang/String;
    //   1238: invokevirtual 189	com/tencent/mm/modelsns/n:m	(Ljava/lang/String;Ljava/lang/Object;)V
    //   1241: aload 13
    //   1243: ldc 201
    //   1245: new 75	java/lang/StringBuilder
    //   1248: dup
    //   1249: invokespecial 183	java/lang/StringBuilder:<init>	()V
    //   1252: iload_1
    //   1253: invokevirtual 145	java/lang/StringBuilder:append	(I)Ljava/lang/StringBuilder;
    //   1256: ldc 185
    //   1258: invokevirtual 84	java/lang/StringBuilder:append	(Ljava/lang/String;)Ljava/lang/StringBuilder;
    //   1261: invokevirtual 89	java/lang/StringBuilder:toString	()Ljava/lang/String;
    //   1264: invokevirtual 189	com/tencent/mm/modelsns/n:m	(Ljava/lang/String;Ljava/lang/Object;)V
    //   1267: aload 13
    //   1269: ldc 205
    //   1271: new 75	java/lang/StringBuilder
    //   1274: dup
    //   1275: invokespecial 183	java/lang/StringBuilder:<init>	()V
    //   1278: lload 11
    //   1280: ldc2_w 206
    //   1283: ldiv
    //   1284: invokevirtual 210	java/lang/StringBuilder:append	(J)Ljava/lang/StringBuilder;
    //   1287: ldc 185
    //   1289: invokevirtual 84	java/lang/StringBuilder:append	(Ljava/lang/String;)Ljava/lang/StringBuilder;
    //   1292: invokevirtual 89	java/lang/StringBuilder:toString	()Ljava/lang/String;
    //   1295: invokevirtual 189	com/tencent/mm/modelsns/n:m	(Ljava/lang/String;Ljava/lang/Object;)V
    //   1298: ldc 73
    //   1300: new 75	java/lang/StringBuilder
    //   1303: dup
    //   1304: ldc 212
    //   1306: invokespecial 80	java/lang/StringBuilder:<init>	(Ljava/lang/String;)V
    //   1309: aload 13
    //   1311: invokevirtual 215	com/tencent/mm/modelsns/n:agI	()Ljava/lang/String;
    //   1314: invokevirtual 84	java/lang/StringBuilder:append	(Ljava/lang/String;)Ljava/lang/StringBuilder;
    //   1317: invokevirtual 89	java/lang/StringBuilder:toString	()Ljava/lang/String;
    //   1320: invokestatic 94	com/tencent/mm/sdk/platformtools/Log:i	(Ljava/lang/String;Ljava/lang/String;)V
    //   1323: getstatic 221	com/tencent/mm/plugin/report/service/h:IzE	Lcom/tencent/mm/plugin/report/service/h;
    //   1326: sipush 13572
    //   1329: iconst_1
    //   1330: anewarray 223	java/lang/Object
    //   1333: dup
    //   1334: iconst_0
    //   1335: aload 13
    //   1337: aastore
    //   1338: invokevirtual 226	com/tencent/mm/plugin/report/service/h:a	(I[Ljava/lang/Object;)V
    //   1341: ldc 44
    //   1343: invokestatic 59	com/tencent/matrix/trace/core/AppMethodBeat:o	(I)V
    //   1346: aconst_null
    //   1347: areturn
    //   1348: astore 13
    //   1350: ldc 73
    //   1352: aload 13
    //   1354: invokevirtual 229	java/lang/Exception:getMessage	()Ljava/lang/String;
    //   1357: invokestatic 232	com/tencent/mm/sdk/platformtools/Log:e	(Ljava/lang/String;Ljava/lang/String;)V
    //   1360: goto -333 -> 1027
    //   1363: iconst_0
    //   1364: istore_2
    //   1365: goto -227 -> 1138
    //   1368: aload 19
    //   1370: astore 15
    //   1372: aload 18
    //   1374: astore 13
    //   1376: iload_1
    //   1377: istore 4
    //   1379: iload 6
    //   1381: istore_2
    //   1382: aload 19
    //   1384: astore 16
    //   1386: aload 18
    //   1388: astore 14
    //   1390: iload_1
    //   1391: istore 5
    //   1393: iload 6
    //   1395: istore_3
    //   1396: aload 19
    //   1398: aload 20
    //   1400: iconst_0
    //   1401: iload 7
    //   1403: invokevirtual 254	java/io/OutputStream:write	([BII)V
    //   1406: iload_1
    //   1407: iload 7
    //   1409: iadd
    //   1410: istore_1
    //   1411: goto -523 -> 888
    //   1414: aload 19
    //   1416: ifnull +8 -> 1424
    //   1419: aload 19
    //   1421: invokevirtual 250	java/io/OutputStream:close	()V
    //   1424: aload 18
    //   1426: ifnull +8 -> 1434
    //   1429: aload 18
    //   1431: invokevirtual 161	java/io/InputStream:close	()V
    //   1434: aload 17
    //   1436: invokevirtual 156	java/net/HttpURLConnection:getInputStream	()Ljava/io/InputStream;
    //   1439: invokevirtual 161	java/io/InputStream:close	()V
    //   1442: aload 17
    //   1444: ifnull +8 -> 1452
    //   1447: aload 17
    //   1449: invokevirtual 164	java/net/HttpURLConnection:disconnect	()V
    //   1452: aload_0
    //   1453: getfield 18	com/tencent/mm/plugin/sns/storage/AdLandingPagesStorage/f:url	Ljava/lang/String;
    //   1456: invokestatic 170	com/tencent/mm/sdk/platformtools/MD5Util:getMD5String	(Ljava/lang/String;)Ljava/lang/String;
    //   1459: astore 14
    //   1461: aload_0
    //   1462: invokespecial 173	com/tencent/mm/plugin/sns/storage/AdLandingPagesStorage/f:getMediaType	()I
    //   1465: istore_2
    //   1466: lload 11
    //   1468: invokestatic 177	com/tencent/mm/sdk/platformtools/Util:milliSecondsToNow	(J)J
    //   1471: l2i
    //   1472: istore_3
    //   1473: new 179	com/tencent/mm/modelsns/n
    //   1476: dup
    //   1477: invokespecial 180	com/tencent/mm/modelsns/n:<init>	()V
    //   1480: astore 13
    //   1482: aload 13
    //   1484: ldc 182
    //   1486: new 75	java/lang/StringBuilder
    //   1489: dup
    //   1490: invokespecial 183	java/lang/StringBuilder:<init>	()V
    //   1493: aload 14
    //   1495: invokevirtual 84	java/lang/StringBuilder:append	(Ljava/lang/String;)Ljava/lang/StringBuilder;
    //   1498: ldc 185
    //   1500: invokevirtual 84	java/lang/StringBuilder:append	(Ljava/lang/String;)Ljava/lang/StringBuilder;
    //   1503: invokevirtual 89	java/lang/StringBuilder:toString	()Ljava/lang/String;
    //   1506: invokevirtual 189	com/tencent/mm/modelsns/n:m	(Ljava/lang/String;Ljava/lang/Object;)V
    //   1509: aload 13
    //   1511: ldc 191
    //   1513: new 75	java/lang/StringBuilder
    //   1516: dup
    //   1517: invokespecial 183	java/lang/StringBuilder:<init>	()V
    //   1520: iload_2
    //   1521: invokevirtual 145	java/lang/StringBuilder:append	(I)Ljava/lang/StringBuilder;
    //   1524: ldc 185
    //   1526: invokevirtual 84	java/lang/StringBuilder:append	(Ljava/lang/String;)Ljava/lang/StringBuilder;
    //   1529: invokevirtual 89	java/lang/StringBuilder:toString	()Ljava/lang/String;
    //   1532: invokevirtual 189	com/tencent/mm/modelsns/n:m	(Ljava/lang/String;Ljava/lang/Object;)V
    //   1535: new 75	java/lang/StringBuilder
    //   1538: dup
    //   1539: invokespecial 183	java/lang/StringBuilder:<init>	()V
    //   1542: astore 14
    //   1544: aload_0
    //   1545: getfield 25	com/tencent/mm/plugin/sns/storage/AdLandingPagesStorage/f:KxW	Z
    //   1548: ifeq +230 -> 1778
    //   1551: iconst_1
    //   1552: istore_2
    //   1553: aload 13
    //   1555: ldc 193
    //   1557: aload 14
    //   1559: iload_2
    //   1560: invokevirtual 145	java/lang/StringBuilder:append	(I)Ljava/lang/StringBuilder;
    //   1563: ldc 185
    //   1565: invokevirtual 84	java/lang/StringBuilder:append	(Ljava/lang/String;)Ljava/lang/StringBuilder;
    //   1568: invokevirtual 89	java/lang/StringBuilder:toString	()Ljava/lang/String;
    //   1571: invokevirtual 189	com/tencent/mm/modelsns/n:m	(Ljava/lang/String;Ljava/lang/Object;)V
    //   1574: aload 13
    //   1576: ldc 195
    //   1578: new 75	java/lang/StringBuilder
    //   1581: dup
    //   1582: invokespecial 183	java/lang/StringBuilder:<init>	()V
    //   1585: iload_3
    //   1586: invokevirtual 145	java/lang/StringBuilder:append	(I)Ljava/lang/StringBuilder;
    //   1589: ldc 185
    //   1591: invokevirtual 84	java/lang/StringBuilder:append	(Ljava/lang/String;)Ljava/lang/StringBuilder;
    //   1594: invokevirtual 89	java/lang/StringBuilder:toString	()Ljava/lang/String;
    //   1597: invokevirtual 189	com/tencent/mm/modelsns/n:m	(Ljava/lang/String;Ljava/lang/Object;)V
    //   1600: aload 13
    //   1602: ldc 197
    //   1604: new 75	java/lang/StringBuilder
    //   1607: dup
    //   1608: invokespecial 183	java/lang/StringBuilder:<init>	()V
    //   1611: iload 6
    //   1613: invokevirtual 145	java/lang/StringBuilder:append	(I)Ljava/lang/StringBuilder;
    //   1616: ldc 185
    //   1618: invokevirtual 84	java/lang/StringBuilder:append	(Ljava/lang/String;)Ljava/lang/StringBuilder;
    //   1621: invokevirtual 89	java/lang/StringBuilder:toString	()Ljava/lang/String;
    //   1624: invokevirtual 189	com/tencent/mm/modelsns/n:m	(Ljava/lang/String;Ljava/lang/Object;)V
    //   1627: aload 13
    //   1629: ldc 199
    //   1631: new 75	java/lang/StringBuilder
    //   1634: dup
    //   1635: invokespecial 183	java/lang/StringBuilder:<init>	()V
    //   1638: aload_0
    //   1639: getfield 32	com/tencent/mm/plugin/sns/storage/AdLandingPagesStorage/f:scene	I
    //   1642: invokevirtual 145	java/lang/StringBuilder:append	(I)Ljava/lang/StringBuilder;
    //   1645: ldc 185
    //   1647: invokevirtual 84	java/lang/StringBuilder:append	(Ljava/lang/String;)Ljava/lang/StringBuilder;
    //   1650: invokevirtual 89	java/lang/StringBuilder:toString	()Ljava/lang/String;
    //   1653: invokevirtual 189	com/tencent/mm/modelsns/n:m	(Ljava/lang/String;Ljava/lang/Object;)V
    //   1656: aload 13
    //   1658: ldc 201
    //   1660: new 75	java/lang/StringBuilder
    //   1663: dup
    //   1664: invokespecial 183	java/lang/StringBuilder:<init>	()V
    //   1667: iload_1
    //   1668: invokevirtual 145	java/lang/StringBuilder:append	(I)Ljava/lang/StringBuilder;
    //   1671: ldc 185
    //   1673: invokevirtual 84	java/lang/StringBuilder:append	(Ljava/lang/String;)Ljava/lang/StringBuilder;
    //   1676: invokevirtual 89	java/lang/StringBuilder:toString	()Ljava/lang/String;
    //   1679: invokevirtual 189	com/tencent/mm/modelsns/n:m	(Ljava/lang/String;Ljava/lang/Object;)V
    //   1682: aload 13
    //   1684: ldc 205
    //   1686: new 75	java/lang/StringBuilder
    //   1689: dup
    //   1690: invokespecial 183	java/lang/StringBuilder:<init>	()V
    //   1693: lload 11
    //   1695: ldc2_w 206
    //   1698: ldiv
    //   1699: invokevirtual 210	java/lang/StringBuilder:append	(J)Ljava/lang/StringBuilder;
    //   1702: ldc 185
    //   1704: invokevirtual 84	java/lang/StringBuilder:append	(Ljava/lang/String;)Ljava/lang/StringBuilder;
    //   1707: invokevirtual 89	java/lang/StringBuilder:toString	()Ljava/lang/String;
    //   1710: invokevirtual 189	com/tencent/mm/modelsns/n:m	(Ljava/lang/String;Ljava/lang/Object;)V
    //   1713: ldc 73
    //   1715: new 75	java/lang/StringBuilder
    //   1718: dup
    //   1719: ldc 212
    //   1721: invokespecial 80	java/lang/StringBuilder:<init>	(Ljava/lang/String;)V
    //   1724: aload 13
    //   1726: invokevirtual 215	com/tencent/mm/modelsns/n:agI	()Ljava/lang/String;
    //   1729: invokevirtual 84	java/lang/StringBuilder:append	(Ljava/lang/String;)Ljava/lang/StringBuilder;
    //   1732: invokevirtual 89	java/lang/StringBuilder:toString	()Ljava/lang/String;
    //   1735: invokestatic 94	com/tencent/mm/sdk/platformtools/Log:i	(Ljava/lang/String;Ljava/lang/String;)V
    //   1738: getstatic 221	com/tencent/mm/plugin/report/service/h:IzE	Lcom/tencent/mm/plugin/report/service/h;
    //   1741: sipush 13572
    //   1744: iconst_1
    //   1745: anewarray 223	java/lang/Object
    //   1748: dup
    //   1749: iconst_0
    //   1750: aload 13
    //   1752: aastore
    //   1753: invokevirtual 226	com/tencent/mm/plugin/report/service/h:a	(I[Ljava/lang/Object;)V
    //   1756: ldc 44
    //   1758: invokestatic 59	com/tencent/matrix/trace/core/AppMethodBeat:o	(I)V
    //   1761: aconst_null
    //   1762: areturn
    //   1763: astore 13
    //   1765: ldc 73
    //   1767: aload 13
    //   1769: invokevirtual 229	java/lang/Exception:getMessage	()Ljava/lang/String;
    //   1772: invokestatic 232	com/tencent/mm/sdk/platformtools/Log:e	(Ljava/lang/String;Ljava/lang/String;)V
    //   1775: goto -333 -> 1442
    //   1778: iconst_0
    //   1779: istore_2
    //   1780: goto -227 -> 1553
    //   1783: astore 19
    //   1785: iload_3
    //   1786: istore_1
    //   1787: aload 23
    //   1789: astore 18
    //   1791: aload 21
    //   1793: astore 17
    //   1795: aload 17
    //   1797: astore 13
    //   1799: aload 16
    //   1801: astore 14
    //   1803: aload 18
    //   1805: astore 15
    //   1807: iload 5
    //   1809: istore_2
    //   1810: aload_0
    //   1811: getfield 21	com/tencent/mm/plugin/sns/storage/AdLandingPagesStorage/f:filePath	Ljava/lang/String;
    //   1814: invokestatic 257	com/tencent/mm/vfs/u:deleteFile	(Ljava/lang/String;)Z
    //   1817: pop
    //   1818: iconst_m1
    //   1819: istore_1
    //   1820: aload 17
    //   1822: astore 13
    //   1824: aload 16
    //   1826: astore 14
    //   1828: aload 18
    //   1830: astore 15
    //   1832: iload 5
    //   1834: istore_2
    //   1835: new 75	java/lang/StringBuilder
    //   1838: dup
    //   1839: ldc_w 259
    //   1842: invokespecial 80	java/lang/StringBuilder:<init>	(Ljava/lang/String;)V
    //   1845: aload 24
    //   1847: invokevirtual 84	java/lang/StringBuilder:append	(Ljava/lang/String;)Ljava/lang/StringBuilder;
    //   1850: ldc_w 261
    //   1853: invokevirtual 84	java/lang/StringBuilder:append	(Ljava/lang/String;)Ljava/lang/StringBuilder;
    //   1856: aload 19
    //   1858: invokevirtual 262	java/lang/Throwable:toString	()Ljava/lang/String;
    //   1861: invokevirtual 84	java/lang/StringBuilder:append	(Ljava/lang/String;)Ljava/lang/StringBuilder;
    //   1864: invokevirtual 89	java/lang/StringBuilder:toString	()Ljava/lang/String;
    //   1867: astore 19
    //   1869: aload 16
    //   1871: ifnull +8 -> 1879
    //   1874: aload 16
    //   1876: invokevirtual 250	java/io/OutputStream:close	()V
    //   1879: aload 18
    //   1881: ifnull +8 -> 1889
    //   1884: aload 18
    //   1886: invokevirtual 161	java/io/InputStream:close	()V
    //   1889: aload 17
    //   1891: invokevirtual 156	java/net/HttpURLConnection:getInputStream	()Ljava/io/InputStream;
    //   1894: invokevirtual 161	java/io/InputStream:close	()V
    //   1897: aload 17
    //   1899: ifnull +8 -> 1907
    //   1902: aload 17
    //   1904: invokevirtual 164	java/net/HttpURLConnection:disconnect	()V
    //   1907: aload_0
    //   1908: getfield 18	com/tencent/mm/plugin/sns/storage/AdLandingPagesStorage/f:url	Ljava/lang/String;
    //   1911: invokestatic 170	com/tencent/mm/sdk/platformtools/MD5Util:getMD5String	(Ljava/lang/String;)Ljava/lang/String;
    //   1914: astore 14
    //   1916: aload_0
    //   1917: invokespecial 173	com/tencent/mm/plugin/sns/storage/AdLandingPagesStorage/f:getMediaType	()I
    //   1920: istore_1
    //   1921: lload 11
    //   1923: invokestatic 177	com/tencent/mm/sdk/platformtools/Util:milliSecondsToNow	(J)J
    //   1926: l2i
    //   1927: istore_2
    //   1928: new 179	com/tencent/mm/modelsns/n
    //   1931: dup
    //   1932: invokespecial 180	com/tencent/mm/modelsns/n:<init>	()V
    //   1935: astore 13
    //   1937: aload 13
    //   1939: ldc 182
    //   1941: new 75	java/lang/StringBuilder
    //   1944: dup
    //   1945: invokespecial 183	java/lang/StringBuilder:<init>	()V
    //   1948: aload 14
    //   1950: invokevirtual 84	java/lang/StringBuilder:append	(Ljava/lang/String;)Ljava/lang/StringBuilder;
    //   1953: ldc 185
    //   1955: invokevirtual 84	java/lang/StringBuilder:append	(Ljava/lang/String;)Ljava/lang/StringBuilder;
    //   1958: invokevirtual 89	java/lang/StringBuilder:toString	()Ljava/lang/String;
    //   1961: invokevirtual 189	com/tencent/mm/modelsns/n:m	(Ljava/lang/String;Ljava/lang/Object;)V
    //   1964: aload 13
    //   1966: ldc 191
    //   1968: new 75	java/lang/StringBuilder
    //   1971: dup
    //   1972: invokespecial 183	java/lang/StringBuilder:<init>	()V
    //   1975: iload_1
    //   1976: invokevirtual 145	java/lang/StringBuilder:append	(I)Ljava/lang/StringBuilder;
    //   1979: ldc 185
    //   1981: invokevirtual 84	java/lang/StringBuilder:append	(Ljava/lang/String;)Ljava/lang/StringBuilder;
    //   1984: invokevirtual 89	java/lang/StringBuilder:toString	()Ljava/lang/String;
    //   1987: invokevirtual 189	com/tencent/mm/modelsns/n:m	(Ljava/lang/String;Ljava/lang/Object;)V
    //   1990: new 75	java/lang/StringBuilder
    //   1993: dup
    //   1994: invokespecial 183	java/lang/StringBuilder:<init>	()V
    //   1997: astore 14
    //   1999: aload_0
    //   2000: getfield 25	com/tencent/mm/plugin/sns/storage/AdLandingPagesStorage/f:KxW	Z
    //   2003: ifeq +215 -> 2218
    //   2006: iconst_1
    //   2007: istore_1
    //   2008: aload 13
    //   2010: ldc 193
    //   2012: aload 14
    //   2014: iload_1
    //   2015: invokevirtual 145	java/lang/StringBuilder:append	(I)Ljava/lang/StringBuilder;
    //   2018: ldc 185
    //   2020: invokevirtual 84	java/lang/StringBuilder:append	(Ljava/lang/String;)Ljava/lang/StringBuilder;
    //   2023: invokevirtual 89	java/lang/StringBuilder:toString	()Ljava/lang/String;
    //   2026: invokevirtual 189	com/tencent/mm/modelsns/n:m	(Ljava/lang/String;Ljava/lang/Object;)V
    //   2029: aload 13
    //   2031: ldc 195
    //   2033: new 75	java/lang/StringBuilder
    //   2036: dup
    //   2037: invokespecial 183	java/lang/StringBuilder:<init>	()V
    //   2040: iload_2
    //   2041: invokevirtual 145	java/lang/StringBuilder:append	(I)Ljava/lang/StringBuilder;
    //   2044: ldc 185
    //   2046: invokevirtual 84	java/lang/StringBuilder:append	(Ljava/lang/String;)Ljava/lang/StringBuilder;
    //   2049: invokevirtual 89	java/lang/StringBuilder:toString	()Ljava/lang/String;
    //   2052: invokevirtual 189	com/tencent/mm/modelsns/n:m	(Ljava/lang/String;Ljava/lang/Object;)V
    //   2055: aload 13
    //   2057: ldc 197
    //   2059: ldc_w 264
    //   2062: invokevirtual 189	com/tencent/mm/modelsns/n:m	(Ljava/lang/String;Ljava/lang/Object;)V
    //   2065: aload 13
    //   2067: ldc 199
    //   2069: new 75	java/lang/StringBuilder
    //   2072: dup
    //   2073: invokespecial 183	java/lang/StringBuilder:<init>	()V
    //   2076: aload_0
    //   2077: getfield 32	com/tencent/mm/plugin/sns/storage/AdLandingPagesStorage/f:scene	I
    //   2080: invokevirtual 145	java/lang/StringBuilder:append	(I)Ljava/lang/StringBuilder;
    //   2083: ldc 185
    //   2085: invokevirtual 84	java/lang/StringBuilder:append	(Ljava/lang/String;)Ljava/lang/StringBuilder;
    //   2088: invokevirtual 89	java/lang/StringBuilder:toString	()Ljava/lang/String;
    //   2091: invokevirtual 189	com/tencent/mm/modelsns/n:m	(Ljava/lang/String;Ljava/lang/Object;)V
    //   2094: aload 13
    //   2096: ldc 201
    //   2098: new 75	java/lang/StringBuilder
    //   2101: dup
    //   2102: invokespecial 183	java/lang/StringBuilder:<init>	()V
    //   2105: iload 5
    //   2107: invokevirtual 145	java/lang/StringBuilder:append	(I)Ljava/lang/StringBuilder;
    //   2110: ldc 185
    //   2112: invokevirtual 84	java/lang/StringBuilder:append	(Ljava/lang/String;)Ljava/lang/StringBuilder;
    //   2115: invokevirtual 89	java/lang/StringBuilder:toString	()Ljava/lang/String;
    //   2118: invokevirtual 189	com/tencent/mm/modelsns/n:m	(Ljava/lang/String;Ljava/lang/Object;)V
    //   2121: aload 13
    //   2123: ldc 205
    //   2125: new 75	java/lang/StringBuilder
    //   2128: dup
    //   2129: invokespecial 183	java/lang/StringBuilder:<init>	()V
    //   2132: lload 11
    //   2134: ldc2_w 206
    //   2137: ldiv
    //   2138: invokevirtual 210	java/lang/StringBuilder:append	(J)Ljava/lang/StringBuilder;
    //   2141: ldc 185
    //   2143: invokevirtual 84	java/lang/StringBuilder:append	(Ljava/lang/String;)Ljava/lang/StringBuilder;
    //   2146: invokevirtual 89	java/lang/StringBuilder:toString	()Ljava/lang/String;
    //   2149: invokevirtual 189	com/tencent/mm/modelsns/n:m	(Ljava/lang/String;Ljava/lang/Object;)V
    //   2152: ldc 73
    //   2154: new 75	java/lang/StringBuilder
    //   2157: dup
    //   2158: ldc 212
    //   2160: invokespecial 80	java/lang/StringBuilder:<init>	(Ljava/lang/String;)V
    //   2163: aload 13
    //   2165: invokevirtual 215	com/tencent/mm/modelsns/n:agI	()Ljava/lang/String;
    //   2168: invokevirtual 84	java/lang/StringBuilder:append	(Ljava/lang/String;)Ljava/lang/StringBuilder;
    //   2171: invokevirtual 89	java/lang/StringBuilder:toString	()Ljava/lang/String;
    //   2174: invokestatic 94	com/tencent/mm/sdk/platformtools/Log:i	(Ljava/lang/String;Ljava/lang/String;)V
    //   2177: getstatic 221	com/tencent/mm/plugin/report/service/h:IzE	Lcom/tencent/mm/plugin/report/service/h;
    //   2180: sipush 13572
    //   2183: iconst_1
    //   2184: anewarray 223	java/lang/Object
    //   2187: dup
    //   2188: iconst_0
    //   2189: aload 13
    //   2191: aastore
    //   2192: invokevirtual 226	com/tencent/mm/plugin/report/service/h:a	(I[Ljava/lang/Object;)V
    //   2195: ldc 44
    //   2197: invokestatic 59	com/tencent/matrix/trace/core/AppMethodBeat:o	(I)V
    //   2200: aload 19
    //   2202: areturn
    //   2203: astore 13
    //   2205: ldc 73
    //   2207: aload 13
    //   2209: invokevirtual 229	java/lang/Exception:getMessage	()Ljava/lang/String;
    //   2212: invokestatic 232	com/tencent/mm/sdk/platformtools/Log:e	(Ljava/lang/String;Ljava/lang/String;)V
    //   2215: goto -318 -> 1897
    //   2218: iconst_0
    //   2219: istore_1
    //   2220: goto -212 -> 2008
    //   2223: astore 17
    //   2225: iload_2
    //   2226: istore 4
    //   2228: aload 15
    //   2230: astore 18
    //   2232: aload 14
    //   2234: astore 15
    //   2236: aload 13
    //   2238: astore 16
    //   2240: aload 17
    //   2242: astore 14
    //   2244: aload 15
    //   2246: ifnull +8 -> 2254
    //   2249: aload 15
    //   2251: invokevirtual 250	java/io/OutputStream:close	()V
    //   2254: aload 18
    //   2256: ifnull +8 -> 2264
    //   2259: aload 18
    //   2261: invokevirtual 161	java/io/InputStream:close	()V
    //   2264: aload 16
    //   2266: invokevirtual 156	java/net/HttpURLConnection:getInputStream	()Ljava/io/InputStream;
    //   2269: invokevirtual 161	java/io/InputStream:close	()V
    //   2272: aload 16
    //   2274: ifnull +8 -> 2282
    //   2277: aload 16
    //   2279: invokevirtual 164	java/net/HttpURLConnection:disconnect	()V
    //   2282: aload_0
    //   2283: getfield 18	com/tencent/mm/plugin/sns/storage/AdLandingPagesStorage/f:url	Ljava/lang/String;
    //   2286: invokestatic 170	com/tencent/mm/sdk/platformtools/MD5Util:getMD5String	(Ljava/lang/String;)Ljava/lang/String;
    //   2289: astore 15
    //   2291: aload_0
    //   2292: invokespecial 173	com/tencent/mm/plugin/sns/storage/AdLandingPagesStorage/f:getMediaType	()I
    //   2295: istore_2
    //   2296: lload 11
    //   2298: invokestatic 177	com/tencent/mm/sdk/platformtools/Util:milliSecondsToNow	(J)J
    //   2301: l2i
    //   2302: istore_3
    //   2303: new 179	com/tencent/mm/modelsns/n
    //   2306: dup
    //   2307: invokespecial 180	com/tencent/mm/modelsns/n:<init>	()V
    //   2310: astore 13
    //   2312: aload 13
    //   2314: ldc 182
    //   2316: new 75	java/lang/StringBuilder
    //   2319: dup
    //   2320: invokespecial 183	java/lang/StringBuilder:<init>	()V
    //   2323: aload 15
    //   2325: invokevirtual 84	java/lang/StringBuilder:append	(Ljava/lang/String;)Ljava/lang/StringBuilder;
    //   2328: ldc 185
    //   2330: invokevirtual 84	java/lang/StringBuilder:append	(Ljava/lang/String;)Ljava/lang/StringBuilder;
    //   2333: invokevirtual 89	java/lang/StringBuilder:toString	()Ljava/lang/String;
    //   2336: invokevirtual 189	com/tencent/mm/modelsns/n:m	(Ljava/lang/String;Ljava/lang/Object;)V
    //   2339: aload 13
    //   2341: ldc 191
    //   2343: new 75	java/lang/StringBuilder
    //   2346: dup
    //   2347: invokespecial 183	java/lang/StringBuilder:<init>	()V
    //   2350: iload_2
    //   2351: invokevirtual 145	java/lang/StringBuilder:append	(I)Ljava/lang/StringBuilder;
    //   2354: ldc 185
    //   2356: invokevirtual 84	java/lang/StringBuilder:append	(Ljava/lang/String;)Ljava/lang/StringBuilder;
    //   2359: invokevirtual 89	java/lang/StringBuilder:toString	()Ljava/lang/String;
    //   2362: invokevirtual 189	com/tencent/mm/modelsns/n:m	(Ljava/lang/String;Ljava/lang/Object;)V
    //   2365: new 75	java/lang/StringBuilder
    //   2368: dup
    //   2369: invokespecial 183	java/lang/StringBuilder:<init>	()V
    //   2372: astore 15
    //   2374: aload_0
    //   2375: getfield 25	com/tencent/mm/plugin/sns/storage/AdLandingPagesStorage/f:KxW	Z
    //   2378: ifeq +231 -> 2609
    //   2381: iconst_1
    //   2382: istore_2
    //   2383: aload 13
    //   2385: ldc 193
    //   2387: aload 15
    //   2389: iload_2
    //   2390: invokevirtual 145	java/lang/StringBuilder:append	(I)Ljava/lang/StringBuilder;
    //   2393: ldc 185
    //   2395: invokevirtual 84	java/lang/StringBuilder:append	(Ljava/lang/String;)Ljava/lang/StringBuilder;
    //   2398: invokevirtual 89	java/lang/StringBuilder:toString	()Ljava/lang/String;
    //   2401: invokevirtual 189	com/tencent/mm/modelsns/n:m	(Ljava/lang/String;Ljava/lang/Object;)V
    //   2404: aload 13
    //   2406: ldc 195
    //   2408: new 75	java/lang/StringBuilder
    //   2411: dup
    //   2412: invokespecial 183	java/lang/StringBuilder:<init>	()V
    //   2415: iload_3
    //   2416: invokevirtual 145	java/lang/StringBuilder:append	(I)Ljava/lang/StringBuilder;
    //   2419: ldc 185
    //   2421: invokevirtual 84	java/lang/StringBuilder:append	(Ljava/lang/String;)Ljava/lang/StringBuilder;
    //   2424: invokevirtual 89	java/lang/StringBuilder:toString	()Ljava/lang/String;
    //   2427: invokevirtual 189	com/tencent/mm/modelsns/n:m	(Ljava/lang/String;Ljava/lang/Object;)V
    //   2430: aload 13
    //   2432: ldc 197
    //   2434: new 75	java/lang/StringBuilder
    //   2437: dup
    //   2438: invokespecial 183	java/lang/StringBuilder:<init>	()V
    //   2441: iload_1
    //   2442: invokevirtual 145	java/lang/StringBuilder:append	(I)Ljava/lang/StringBuilder;
    //   2445: ldc 185
    //   2447: invokevirtual 84	java/lang/StringBuilder:append	(Ljava/lang/String;)Ljava/lang/StringBuilder;
    //   2450: invokevirtual 89	java/lang/StringBuilder:toString	()Ljava/lang/String;
    //   2453: invokevirtual 189	com/tencent/mm/modelsns/n:m	(Ljava/lang/String;Ljava/lang/Object;)V
    //   2456: aload 13
    //   2458: ldc 199
    //   2460: new 75	java/lang/StringBuilder
    //   2463: dup
    //   2464: invokespecial 183	java/lang/StringBuilder:<init>	()V
    //   2467: aload_0
    //   2468: getfield 32	com/tencent/mm/plugin/sns/storage/AdLandingPagesStorage/f:scene	I
    //   2471: invokevirtual 145	java/lang/StringBuilder:append	(I)Ljava/lang/StringBuilder;
    //   2474: ldc 185
    //   2476: invokevirtual 84	java/lang/StringBuilder:append	(Ljava/lang/String;)Ljava/lang/StringBuilder;
    //   2479: invokevirtual 89	java/lang/StringBuilder:toString	()Ljava/lang/String;
    //   2482: invokevirtual 189	com/tencent/mm/modelsns/n:m	(Ljava/lang/String;Ljava/lang/Object;)V
    //   2485: aload 13
    //   2487: ldc 201
    //   2489: new 75	java/lang/StringBuilder
    //   2492: dup
    //   2493: invokespecial 183	java/lang/StringBuilder:<init>	()V
    //   2496: iload 4
    //   2498: invokevirtual 145	java/lang/StringBuilder:append	(I)Ljava/lang/StringBuilder;
    //   2501: ldc 185
    //   2503: invokevirtual 84	java/lang/StringBuilder:append	(Ljava/lang/String;)Ljava/lang/StringBuilder;
    //   2506: invokevirtual 89	java/lang/StringBuilder:toString	()Ljava/lang/String;
    //   2509: invokevirtual 189	com/tencent/mm/modelsns/n:m	(Ljava/lang/String;Ljava/lang/Object;)V
    //   2512: aload 13
    //   2514: ldc 205
    //   2516: new 75	java/lang/StringBuilder
    //   2519: dup
    //   2520: invokespecial 183	java/lang/StringBuilder:<init>	()V
    //   2523: lload 11
    //   2525: ldc2_w 206
    //   2528: ldiv
    //   2529: invokevirtual 210	java/lang/StringBuilder:append	(J)Ljava/lang/StringBuilder;
    //   2532: ldc 185
    //   2534: invokevirtual 84	java/lang/StringBuilder:append	(Ljava/lang/String;)Ljava/lang/StringBuilder;
    //   2537: invokevirtual 89	java/lang/StringBuilder:toString	()Ljava/lang/String;
    //   2540: invokevirtual 189	com/tencent/mm/modelsns/n:m	(Ljava/lang/String;Ljava/lang/Object;)V
    //   2543: ldc 73
    //   2545: new 75	java/lang/StringBuilder
    //   2548: dup
    //   2549: ldc 212
    //   2551: invokespecial 80	java/lang/StringBuilder:<init>	(Ljava/lang/String;)V
    //   2554: aload 13
    //   2556: invokevirtual 215	com/tencent/mm/modelsns/n:agI	()Ljava/lang/String;
    //   2559: invokevirtual 84	java/lang/StringBuilder:append	(Ljava/lang/String;)Ljava/lang/StringBuilder;
    //   2562: invokevirtual 89	java/lang/StringBuilder:toString	()Ljava/lang/String;
    //   2565: invokestatic 94	com/tencent/mm/sdk/platformtools/Log:i	(Ljava/lang/String;Ljava/lang/String;)V
    //   2568: getstatic 221	com/tencent/mm/plugin/report/service/h:IzE	Lcom/tencent/mm/plugin/report/service/h;
    //   2571: sipush 13572
    //   2574: iconst_1
    //   2575: anewarray 223	java/lang/Object
    //   2578: dup
    //   2579: iconst_0
    //   2580: aload 13
    //   2582: aastore
    //   2583: invokevirtual 226	com/tencent/mm/plugin/report/service/h:a	(I[Ljava/lang/Object;)V
    //   2586: ldc 44
    //   2588: invokestatic 59	com/tencent/matrix/trace/core/AppMethodBeat:o	(I)V
    //   2591: aload 14
    //   2593: athrow
    //   2594: astore 13
    //   2596: ldc 73
    //   2598: aload 13
    //   2600: invokevirtual 229	java/lang/Exception:getMessage	()Ljava/lang/String;
    //   2603: invokestatic 232	com/tencent/mm/sdk/platformtools/Log:e	(Ljava/lang/String;Ljava/lang/String;)V
    //   2606: goto -334 -> 2272
    //   2609: iconst_0
    //   2610: istore_2
    //   2611: goto -228 -> 2383
    //   2614: astore 13
    //   2616: goto -352 -> 2264
    //   2619: astore 14
    //   2621: aload 17
    //   2623: astore 16
    //   2625: aload 13
    //   2627: astore 18
    //   2629: iload_2
    //   2630: istore_1
    //   2631: goto -387 -> 2244
    //   2634: astore 13
    //   2636: goto -747 -> 1889
    //   2639: astore 19
    //   2641: aload 14
    //   2643: astore 18
    //   2645: iload_3
    //   2646: istore_1
    //   2647: goto -852 -> 1795
    //   2650: astore 13
    //   2652: goto -1218 -> 1434
    //   2655: astore 13
    //   2657: goto -1638 -> 1019
    // Local variable table:
    //   start	length	slot	name	signature
    //   0	2660	0	this	f
    //   70	2577	1	i	int
    //   83	2547	2	j	int
    //   78	2568	3	k	int
    //   182	2315	4	m	int
    //   80	2026	5	n	int
    //   72	1540	6	i1	int
    //   91	1319	7	i2	int
    //   85	772	8	i3	int
    //   88	784	9	i4	int
    //   75	236	10	i5	int
    //   67	2457	11	l	long
    //   139	564	13	localObject1	Object
    //   716	5	13	localException1	java.lang.Exception
    //   742	594	13	localObject2	Object
    //   1348	5	13	localException2	java.lang.Exception
    //   1374	377	13	localObject3	Object
    //   1763	5	13	localException3	java.lang.Exception
    //   1797	393	13	localObject4	Object
    //   2203	34	13	localException4	java.lang.Exception
    //   2310	271	13	localn	com.tencent.mm.modelsns.n
    //   2594	5	13	localException5	java.lang.Exception
    //   2614	12	13	localIOException1	java.io.IOException
    //   2634	1	13	localIOException2	java.io.IOException
    //   2650	1	13	localIOException3	java.io.IOException
    //   2655	1	13	localIOException4	java.io.IOException
    //   127	2465	14	localObject5	Object
    //   2619	23	14	localObject6	Object
    //   115	2273	15	localObject7	Object
    //   136	2488	16	localObject8	Object
    //   170	1733	17	localObject9	Object
    //   2223	399	17	localObject10	Object
    //   118	2526	18	localObject11	Object
    //   130	1290	19	localOutputStream	java.io.OutputStream
    //   1783	74	19	localThrowable1	java.lang.Throwable
    //   1867	334	19	str1	String
    //   2639	1	19	localThrowable2	java.lang.Throwable
    //   133	1266	20	arrayOfByte	byte[]
    //   142	1650	21	localObject12	Object
    //   121	671	22	localObject13	Object
    //   124	1664	23	localObject14	Object
    //   28	1818	24	str2	String
    // Exception table:
    //   from	to	target	type
    //   403	411	716	java/lang/Exception
    //   1019	1027	1348	java/lang/Exception
    //   1434	1442	1763	java/lang/Exception
    //   153	172	1783	java/lang/Throwable
    //   1889	1897	2203	java/lang/Exception
    //   153	172	2223	finally
    //   1810	1818	2223	finally
    //   1835	1869	2223	finally
    //   2264	2272	2594	java/lang/Exception
    //   2249	2254	2614	java/io/IOException
    //   2259	2264	2614	java/io/IOException
    //   202	210	2619	finally
    //   240	248	2619	finally
    //   278	283	2619	finally
    //   313	320	2619	finally
    //   358	403	2619	finally
    //   766	772	2619	finally
    //   802	809	2619	finally
    //   839	848	2619	finally
    //   878	885	2619	finally
    //   916	925	2619	finally
    //   959	966	2619	finally
    //   994	999	2619	finally
    //   1396	1406	2619	finally
    //   1874	1879	2634	java/io/IOException
    //   1884	1889	2634	java/io/IOException
    //   202	210	2639	java/lang/Throwable
    //   240	248	2639	java/lang/Throwable
    //   278	283	2639	java/lang/Throwable
    //   313	320	2639	java/lang/Throwable
    //   358	403	2639	java/lang/Throwable
    //   766	772	2639	java/lang/Throwable
    //   802	809	2639	java/lang/Throwable
    //   839	848	2639	java/lang/Throwable
    //   878	885	2639	java/lang/Throwable
    //   916	925	2639	java/lang/Throwable
    //   959	966	2639	java/lang/Throwable
    //   994	999	2639	java/lang/Throwable
    //   1396	1406	2639	java/lang/Throwable
    //   1419	1424	2650	java/io/IOException
    //   1429	1434	2650	java/io/IOException
    //   1004	1009	2655	java/io/IOException
    //   1014	1019	2655	java/io/IOException
  }
  
  private int getMediaType()
  {
    int i = 1;
    switch (this.KxX)
    {
    default: 
      i = 0;
    case 41: 
    case 44: 
    case 45: 
    case 133: 
    case 1000000001: 
      return i;
    case 61: 
      return 2;
    }
    return 3;
  }
  
  public static abstract interface a
  {
    public abstract void aYs(String paramString);
    
    public abstract void fJU();
    
    public abstract void fJV();
  }
}


/* Location:           L:\local\mybackup\temp\qq_apk\com.tencent.mm\classes4.jar
 * Qualified Name:     com.tencent.mm.plugin.sns.storage.AdLandingPagesStorage.f
 * JD-Core Version:    0.7.0.1
 */