package com.tencent.mm.booter.notification.a;

import android.content.Context;
import android.content.res.Resources;
import android.text.TextPaint;
import android.text.TextUtils;
import android.text.TextUtils.TruncateAt;
import com.tencent.matrix.trace.core.AppMethodBeat;
import com.tencent.mm.al.a.d;
import com.tencent.mm.al.a.l;
import com.tencent.mm.al.af;
import com.tencent.mm.cf.b;
import com.tencent.mm.g.c.av;
import com.tencent.mm.g.c.dy;
import com.tencent.mm.kernel.g;
import com.tencent.mm.model.aj;
import com.tencent.mm.model.az;
import com.tencent.mm.model.bi;
import com.tencent.mm.model.u;
import com.tencent.mm.model.v;
import com.tencent.mm.model.w;
import com.tencent.mm.plugin.biz.a.a;
import com.tencent.mm.pointers.PInt;
import com.tencent.mm.pointers.PString;
import com.tencent.mm.sdk.platformtools.BackwardSupportUtil.b;
import com.tencent.mm.sdk.platformtools.bs;
import com.tencent.mm.storage.RegionCodeDecoder;
import com.tencent.mm.storage.ae;
import com.tencent.mm.storage.bj;
import com.tencent.mm.storage.bo;
import java.lang.ref.WeakReference;

public final class h
{
  private static int fpA = 0;
  private static WeakReference<TextPaint> fpy;
  private static int fpz = 0;
  public String fpx = "";
  public String mDesc = "";
  public String mTitle = "";
  
  private static int C(String paramString, int paramInt)
  {
    AppMethodBeat.i(20088);
    while (paramInt < paramString.length())
    {
      if (paramString.charAt(paramInt) != '%')
      {
        AppMethodBeat.o(20088);
        return paramInt;
      }
      paramInt += 1;
    }
    paramInt = paramString.length();
    AppMethodBeat.o(20088);
    return paramInt;
  }
  
  private static int Vj()
  {
    AppMethodBeat.i(169682);
    if (fpA > 0)
    {
      i = fpA;
      AppMethodBeat.o(169682);
      return i;
    }
    int i = BackwardSupportUtil.b.g(com.tencent.mm.sdk.platformtools.ai.getContext(), 14.0F);
    AppMethodBeat.o(169682);
    return i;
  }
  
  private static int Vk()
  {
    AppMethodBeat.i(20087);
    if (fpz > 0)
    {
      i = fpz;
      AppMethodBeat.o(20087);
      return i;
    }
    int i = BackwardSupportUtil.b.g(com.tencent.mm.sdk.platformtools.ai.getContext(), 200.0F);
    AppMethodBeat.o(20087);
    return i;
  }
  
  private static CharSequence a(String paramString, TextPaint paramTextPaint)
  {
    AppMethodBeat.i(20086);
    paramString = TextUtils.ellipsize(com.tencent.mm.pluginsdk.ui.span.k.b(com.tencent.mm.sdk.platformtools.ai.getContext(), paramString, Vj()), paramTextPaint, Vk(), TextUtils.TruncateAt.END);
    AppMethodBeat.o(20086);
    return paramString;
  }
  
  public static String a(int paramInt1, String paramString1, String paramString2, int paramInt2, Context paramContext)
  {
    AppMethodBeat.i(20075);
    paramString1 = bs.nullAsNil(a(null, paramInt1, paramString1, paramString2, paramInt2, paramContext, new PString(), new PString(), new PInt(), false, false, "", 0));
    AppMethodBeat.o(20075);
    return paramString1;
  }
  
  private static String a(Context paramContext, int paramInt, String paramString1, String paramString2, String paramString3, PString paramPString1, PString paramPString2)
  {
    int j = 2131759556;
    AppMethodBeat.i(20077);
    String str3 = "";
    String str2;
    String str1;
    int i;
    if ((w.wM(paramString1)) || (w.wO(paramString1)))
    {
      str2 = str3;
      str1 = paramString2;
      if (paramString2 != null)
      {
        i = paramString2.indexOf(":");
        str2 = str3;
        str1 = paramString2;
        if (i >= 0)
        {
          str2 = str3;
          str1 = paramString2;
          if (i < paramString2.length())
          {
            paramString1 = paramString2.substring(0, i);
            if (!com.tencent.mm.storage.ai.aMZ(paramString1))
            {
              str2 = str3;
              str1 = paramString2;
              if (!com.tencent.mm.storage.ai.aNb(paramString1)) {}
            }
            else
            {
              str2 = v.wk(paramString1);
              paramPString2.value = paramString1;
              str1 = paramString2.substring(i + 1);
            }
          }
        }
      }
      if (bs.nullAsNil(str2).length() > 0) {
        break label316;
      }
      if (paramString3 != null) {
        break label309;
      }
    }
    for (;;)
    {
      paramPString1.value = str1;
      paramContext = paramPString1.value;
      AppMethodBeat.o(20077);
      return paramContext;
      if (!com.tencent.mm.storage.ai.aMZ(paramString1))
      {
        str2 = str3;
        str1 = paramString2;
        if (!com.tencent.mm.storage.ai.aNb(paramString1)) {
          break;
        }
      }
      v.wk(paramString1);
      paramPString2.value = paramString1;
      if (paramInt == 1)
      {
        paramContext = new StringBuilder().append(paramContext.getString(2131759556, new Object[] { "" }));
        if (paramString3 == null) {}
        for (;;)
        {
          paramPString1.value = paramString2;
          paramPString2.value = "";
          paramContext = paramPString1.value;
          AppMethodBeat.o(20077);
          return paramContext;
          paramString2 = paramString3;
        }
      }
      if (paramString3 == null) {}
      for (;;)
      {
        paramPString1.value = paramString2;
        paramPString2.value = "";
        paramContext = paramPString1.value;
        AppMethodBeat.o(20077);
        return paramContext;
        paramString2 = paramString3;
      }
      label309:
      str1 = paramString3;
    }
    label316:
    paramString1 = new StringBuilder();
    if (paramInt == 1)
    {
      i = 2131759556;
      paramString2 = paramString1.append(paramContext.getString(i));
      if (paramString3 != null) {
        break label430;
      }
      paramString1 = str1;
      label352:
      paramPString1.value = paramString1;
      paramString1 = new StringBuilder();
      if (paramInt != 1) {
        break label436;
      }
      paramInt = j;
      label381:
      paramContext = paramString1.append(paramContext.getString(paramInt, new Object[] { str2 }));
      if (paramString3 != null) {
        break label442;
      }
    }
    for (;;)
    {
      paramContext = str1;
      AppMethodBeat.o(20077);
      return paramContext;
      i = 2131759566;
      break;
      label430:
      paramString1 = paramString3;
      break label352;
      label436:
      paramInt = 2131759566;
      break label381;
      label442:
      str1 = paramString3;
    }
  }
  
  public static String a(Context paramContext, String paramString, int paramInt1, int paramInt2, int paramInt3, boolean paramBoolean)
  {
    AppMethodBeat.i(20092);
    if (paramBoolean)
    {
      String str = b.eXh().aMd(paramString);
      paramString = str;
      if (paramInt3 > 1) {
        paramString = paramContext.getResources().getQuantityString(2131623960, paramInt3, new Object[] { Integer.valueOf(paramInt3) }) + str;
      }
      AppMethodBeat.o(20092);
      return paramString;
    }
    paramContext = paramContext.getResources().getQuantityString(2131623961, paramInt1, new Object[] { Integer.valueOf(paramInt1), Integer.valueOf(paramInt2) });
    AppMethodBeat.o(20092);
    return paramContext;
  }
  
  public static String a(Context paramContext, String paramString1, String paramString2, int paramInt)
  {
    AppMethodBeat.i(20071);
    paramContext = a(0, paramString2, paramString1, paramInt, paramContext);
    paramContext = com.tencent.mm.pluginsdk.ui.span.k.aHF(b.eXh().aMd(paramContext));
    AppMethodBeat.o(20071);
    return paramContext;
  }
  
  public static String a(Context paramContext, String paramString1, String paramString2, int paramInt, bo parambo)
  {
    AppMethodBeat.i(20073);
    if (TextUtils.isEmpty(paramString2)) {
      parambo = null;
    }
    for (;;)
    {
      paramString1 = parambo;
      if (bs.isNullOrNil(parambo))
      {
        if (!com.tencent.mm.m.f.sQ(paramString2)) {
          break;
        }
        paramString1 = paramContext.getString(2131757293);
      }
      paramContext = b.eXh().aMd(paramString1);
      AppMethodBeat.o(20073);
      return paramContext;
      for (;;)
      {
        for (;;)
        {
          try
          {
            if (!b(paramString2, parambo)) {
              continue;
            }
            if (parambo == null) {
              continue;
            }
            localObject1 = af.aCY().bd(parambo.field_bizChatId);
            if (((com.tencent.mm.al.a.c)localObject1).isGroup()) {
              if (bs.isNullOrNil(((com.tencent.mm.al.a.c)localObject1).field_chatName)) {
                localObject1 = com.tencent.mm.sdk.platformtools.ai.getContext().getString(2131762623);
              }
            }
          }
          catch (Throwable parambo)
          {
            boolean bool;
            com.tencent.mm.storage.ai localai;
            Object localObject2;
            Object localObject1 = null;
            continue;
            localObject1 = null;
            continue;
            localObject1 = null;
            continue;
          }
          try
          {
            bool = TextUtils.isEmpty((CharSequence)localObject1);
            parambo = (bo)localObject1;
            if (!bool) {
              break;
            }
          }
          catch (Throwable parambo) {}
        }
        az.ayM();
        localai = com.tencent.mm.model.c.awB().aNt(paramString2);
        if (localai != null) {
          continue;
        }
        parambo = null;
        break;
        localObject1 = ((com.tencent.mm.al.a.c)localObject1).field_chatName;
        continue;
        parambo = af.aDa().dP(parambo.field_bizChatUserId);
        if (parambo == null) {
          continue;
        }
        localObject1 = parambo.field_userName;
      }
      localObject2 = localObject1;
      if (paramInt == 318767153)
      {
        localObject2 = localObject1;
        if (!TextUtils.isEmpty(paramString1))
        {
          localObject2 = ((a)g.ab(a.class)).aA(paramString1, paramString2);
          parambo = (bo)localObject2;
          if (!TextUtils.isEmpty((CharSequence)localObject2)) {
            continue;
          }
        }
      }
      if (w.xn(paramString2))
      {
        parambo = localai.aaR();
      }
      else
      {
        if (com.tencent.mm.storage.ai.ww(paramString2))
        {
          localObject1 = com.tencent.mm.sdk.platformtools.ai.getContext();
          if (localai != null) {
            if (RegionCodeDecoder.aOy(localai.getCountryCode()))
            {
              paramString1 = localai.getCity();
              if (bs.isNullOrNil(paramString1)) {}
            }
          }
          for (;;)
          {
            parambo = paramContext.getString(2131756698, new Object[] { paramString1 }).trim();
            break;
            parambo = v.wm(localai.getProvince());
            paramString1 = parambo;
            if (bs.isNullOrNil(parambo))
            {
              RegionCodeDecoder.fcs();
              paramString1 = RegionCodeDecoder.getLocName(localai.getCountryCode());
              continue;
              parambo = v.wm(localai.getProvince());
              paramString1 = parambo;
              if (bs.isNullOrNil(parambo)) {
                paramString1 = ((Context)localObject1).getString(2131756727);
              }
            }
          }
        }
        if ((com.tencent.mm.m.f.sQ(paramString2)) && (bs.isNullOrNil(localai.field_nickname)) && (bs.isNullOrNil(localai.field_conRemark)))
        {
          az.ayM();
          paramString1 = com.tencent.mm.model.c.awK().wk(paramString2);
          parambo = (bo)localObject2;
          if (!bs.isNullOrNil(paramString1)) {
            parambo = paramString1;
          }
        }
        else
        {
          parambo = (bo)localObject2;
          if (localai.aaS() != null)
          {
            parambo = (bo)localObject2;
            if (localai.aaS().length() > 0) {
              parambo = localai.aaS();
            }
          }
        }
      }
    }
    paramContext = paramContext.getString(2131760347);
    AppMethodBeat.o(20073);
    return paramContext;
  }
  
  /* Error */
  private static String a(String paramString1, int paramInt1, String paramString2, String paramString3, int paramInt2, Context paramContext, PString paramPString1, PString paramPString2, PInt paramPInt, boolean paramBoolean1, boolean paramBoolean2, String paramString4, int paramInt3)
  {
    // Byte code:
    //   0: ldc_w 360
    //   3: invokestatic 40	com/tencent/matrix/trace/core/AppMethodBeat:i	(I)V
    //   6: aload 5
    //   8: ifnull +65 -> 73
    //   11: iconst_1
    //   12: istore 17
    //   14: ldc_w 362
    //   17: iload 17
    //   19: invokestatic 368	junit/framework/Assert:assertTrue	(Ljava/lang/String;Z)V
    //   22: aload_2
    //   23: ifnull +56 -> 79
    //   26: aload_2
    //   27: invokevirtual 46	java/lang/String:length	()I
    //   30: ifle +49 -> 79
    //   33: iconst_1
    //   34: istore 17
    //   36: ldc_w 370
    //   39: iload 17
    //   41: invokestatic 368	junit/framework/Assert:assertTrue	(Ljava/lang/String;Z)V
    //   44: iload 9
    //   46: ifne +39 -> 85
    //   49: aload_2
    //   50: invokestatic 373	com/tencent/mm/booter/notification/a/h:rK	(Ljava/lang/String;)Z
    //   53: ifeq +32 -> 85
    //   56: aload 5
    //   58: ldc_w 374
    //   61: invokevirtual 169	android/content/Context:getString	(I)Ljava/lang/String;
    //   64: astore_0
    //   65: ldc_w 360
    //   68: invokestatic 53	com/tencent/matrix/trace/core/AppMethodBeat:o	(I)V
    //   71: aload_0
    //   72: areturn
    //   73: iconst_0
    //   74: istore 17
    //   76: goto -62 -> 14
    //   79: iconst_0
    //   80: istore 17
    //   82: goto -46 -> 36
    //   85: aload_2
    //   86: invokestatic 377	com/tencent/mm/model/w:wS	(Ljava/lang/String;)Z
    //   89: ifeq +31 -> 120
    //   92: iload 9
    //   94: ifeq +12 -> 106
    //   97: ldc_w 360
    //   100: invokestatic 53	com/tencent/matrix/trace/core/AppMethodBeat:o	(I)V
    //   103: ldc 26
    //   105: areturn
    //   106: aload 5
    //   108: invokestatic 381	com/tencent/mm/booter/notification/a/h:bT	(Landroid/content/Context;)Ljava/lang/String;
    //   111: astore_0
    //   112: ldc_w 360
    //   115: invokestatic 53	com/tencent/matrix/trace/core/AppMethodBeat:o	(I)V
    //   118: aload_0
    //   119: areturn
    //   120: aload_3
    //   121: ifnull +9063 -> 9184
    //   124: iload 9
    //   126: ifeq +9058 -> 9184
    //   129: aload_3
    //   130: invokestatic 384	com/tencent/mm/booter/notification/a/h:rI	(Ljava/lang/String;)Ljava/lang/String;
    //   133: astore_3
    //   134: iconst_1
    //   135: istore 15
    //   137: aload 6
    //   139: aload_3
    //   140: putfield 147	com/tencent/mm/pointers/PString:value	Ljava/lang/String;
    //   143: iload_1
    //   144: ifne +9026 -> 9170
    //   147: aload_2
    //   148: invokestatic 385	com/tencent/mm/model/w:sQ	(Ljava/lang/String;)Z
    //   151: ifne +10 -> 161
    //   154: aload_2
    //   155: invokestatic 388	com/tencent/mm/model/w:wq	(Ljava/lang/String;)Z
    //   158: ifeq +9012 -> 9170
    //   161: aload_3
    //   162: invokestatic 393	com/tencent/mm/model/bi:yi	(Ljava/lang/String;)I
    //   165: istore 13
    //   167: iload 13
    //   169: ifle +9001 -> 9170
    //   172: aload_3
    //   173: iconst_0
    //   174: iload 13
    //   176: invokevirtual 131	java/lang/String:substring	(II)Ljava/lang/String;
    //   179: invokevirtual 324	java/lang/String:trim	()Ljava/lang/String;
    //   182: astore 19
    //   184: aload 19
    //   186: aload_2
    //   187: invokestatic 396	com/tencent/mm/model/v:getDisplayName	(Ljava/lang/String;Ljava/lang/String;)Ljava/lang/String;
    //   190: astore 20
    //   192: new 152	java/lang/StringBuilder
    //   195: dup
    //   196: invokespecial 153	java/lang/StringBuilder:<init>	()V
    //   199: aload_3
    //   200: invokevirtual 163	java/lang/StringBuilder:append	(Ljava/lang/String;)Ljava/lang/StringBuilder;
    //   203: ldc_w 398
    //   206: invokevirtual 163	java/lang/StringBuilder:append	(Ljava/lang/String;)Ljava/lang/StringBuilder;
    //   209: invokevirtual 167	java/lang/StringBuilder:toString	()Ljava/lang/String;
    //   212: iload 13
    //   214: iconst_1
    //   215: iadd
    //   216: invokevirtual 150	java/lang/String:substring	(I)Ljava/lang/String;
    //   219: astore 21
    //   221: iconst_0
    //   222: istore 13
    //   224: aload_2
    //   225: invokestatic 401	com/tencent/mm/model/w:xg	(Ljava/lang/String;)Z
    //   228: ifne +10 -> 238
    //   231: aload_2
    //   232: invokestatic 404	com/tencent/mm/model/w:xp	(Ljava/lang/String;)Z
    //   235: ifeq +633 -> 868
    //   238: aload_3
    //   239: ldc 123
    //   241: invokevirtual 127	java/lang/String:indexOf	(Ljava/lang/String;)I
    //   244: istore 13
    //   246: aload_3
    //   247: astore 18
    //   249: iload 13
    //   251: iconst_m1
    //   252: if_icmpeq +25 -> 277
    //   255: aload 7
    //   257: aload_3
    //   258: iconst_0
    //   259: iload 13
    //   261: invokevirtual 131	java/lang/String:substring	(II)Ljava/lang/String;
    //   264: putfield 147	com/tencent/mm/pointers/PString:value	Ljava/lang/String;
    //   267: aload_3
    //   268: iload 13
    //   270: iconst_1
    //   271: iadd
    //   272: invokevirtual 150	java/lang/String:substring	(I)Ljava/lang/String;
    //   275: astore 18
    //   277: iconst_0
    //   278: istore 14
    //   280: aload 18
    //   282: astore_3
    //   283: iload 4
    //   285: lookupswitch	default:+539->824, -1879048191:+1261->1546, -1879048190:+1261->1546, -1879048189:+1261->1546, -1879048188:+1367->1652, -1879048186:+3736->4021, -1879048185:+3890->4175, -1879048183:+3890->4175, -1879048176:+3890->4175, 3:+675->960, 11:+882->1167, 13:+849->1134, 23:+675->960, 33:+675->960, 34:+908->1193, 35:+1726->2011, 36:+882->1167, 37:+1388->1673, 39:+849->1134, 40:+1643->1928, 42:+1797->2082, 43:+1074->1359, 47:+757->1042, 48:+2057->2342, 49:+4893->5178, 50:+1282->1567, 52:+1346->1631, 53:+1282->1567, 55:+7529->7814, 57:+7529->7814, 62:+1074->1359, 66:+1797->2082, 1048625:+757->1042, 12299999:+1240->1525, 16777265:+4893->5178, 268435505:+4893->5178, 285212721:+7402->7687, 318767153:+7465->7750, 335544369:+2184->2469, 369098801:+3176->3461, 402653233:+2297->2582, 419430449:+2381->2666, 436207665:+2726->3011, 452984881:+3327->3612, 469762097:+2726->3011, 486539313:+1074->1359, 503316529:+7555->7840, 520093745:+3537->3822, 536870961:+2949->3234, 553648177:+4893->5178, 570425393:+7639->7924, 587202609:+4893->5178, 603979825:+7762->8047, 671088689:+3078->3363, 687865905:+4893->5178, 704643121:+3991->4276, 721420337:+7800->8085, 738197553:+4893->5178, 754974769:+4126->4411, 771751985:+4512->4797, 788529201:+4687->4972, 805306417:+4893->5178, 822083633:+4893->5178, 838860849:+4299->4584, 855638065:+4815->5100, 872415281:+7827->8112, 889192497:+4738->5023
    //   825: astore_0
    //   826: ldc 26
    //   828: astore_3
    //   829: aconst_null
    //   830: astore 18
    //   832: iconst_0
    //   833: istore 13
    //   835: aload_2
    //   836: invokestatic 407	com/tencent/mm/model/w:wN	(Ljava/lang/String;)Z
    //   839: ifeq +7666 -> 8505
    //   842: iconst_1
    //   843: iload_1
    //   844: if_icmpne +7379 -> 8223
    //   847: aload_3
    //   848: invokestatic 214	com/tencent/mm/sdk/platformtools/bs:isNullOrNil	(Ljava/lang/String;)Z
    //   851: ifne +7323 -> 8174
    //   854: aload 6
    //   856: aload_3
    //   857: putfield 147	com/tencent/mm/pointers/PString:value	Ljava/lang/String;
    //   860: ldc_w 360
    //   863: invokestatic 53	com/tencent/matrix/trace/core/AppMethodBeat:o	(I)V
    //   866: aload_3
    //   867: areturn
    //   868: invokestatic 257	com/tencent/mm/model/az:ayM	()Lcom/tencent/mm/model/c;
    //   871: pop
    //   872: invokestatic 411	com/tencent/mm/model/c:awG	()Lcom/tencent/mm/storage/bk;
    //   875: aload_2
    //   876: invokeinterface 417 2 0
    //   881: astore 18
    //   883: aload 18
    //   885: ifnull +14 -> 899
    //   888: aload 18
    //   890: ldc_w 418
    //   893: invokevirtual 424	com/tencent/mm/storage/ap:lr	(I)Z
    //   896: ifne +8 -> 904
    //   899: iload 10
    //   901: ifeq +8262 -> 9163
    //   904: iconst_1
    //   905: istore 14
    //   907: iload 14
    //   909: istore 13
    //   911: aload_3
    //   912: ifnull +8251 -> 9163
    //   915: aload_3
    //   916: ldc 123
    //   918: invokevirtual 127	java/lang/String:indexOf	(Ljava/lang/String;)I
    //   921: istore 16
    //   923: iload 14
    //   925: istore 13
    //   927: iload 16
    //   929: iconst_m1
    //   930: if_icmpeq +8233 -> 9163
    //   933: aload 7
    //   935: aload_3
    //   936: iconst_0
    //   937: iload 16
    //   939: invokevirtual 131	java/lang/String:substring	(II)Ljava/lang/String;
    //   942: putfield 147	com/tencent/mm/pointers/PString:value	Ljava/lang/String;
    //   945: aload_3
    //   946: iload 16
    //   948: iconst_1
    //   949: iadd
    //   950: invokevirtual 150	java/lang/String:substring	(I)Ljava/lang/String;
    //   953: astore_3
    //   954: iconst_1
    //   955: istore 14
    //   957: goto -674 -> 283
    //   960: aload 5
    //   962: ldc_w 425
    //   965: invokevirtual 169	android/content/Context:getString	(I)Ljava/lang/String;
    //   968: astore 21
    //   970: aload 19
    //   972: invokevirtual 46	java/lang/String:length	()I
    //   975: ifle +55 -> 1030
    //   978: new 152	java/lang/StringBuilder
    //   981: dup
    //   982: invokespecial 153	java/lang/StringBuilder:<init>	()V
    //   985: aload 19
    //   987: invokevirtual 163	java/lang/StringBuilder:append	(Ljava/lang/String;)Ljava/lang/StringBuilder;
    //   990: ldc_w 427
    //   993: invokevirtual 163	java/lang/StringBuilder:append	(Ljava/lang/String;)Ljava/lang/StringBuilder;
    //   996: invokevirtual 167	java/lang/StringBuilder:toString	()Ljava/lang/String;
    //   999: astore_0
    //   1000: aload 19
    //   1002: invokevirtual 46	java/lang/String:length	()I
    //   1005: ifle +31 -> 1036
    //   1008: ldc_w 429
    //   1011: astore_3
    //   1012: aload 6
    //   1014: aload_3
    //   1015: putfield 147	com/tencent/mm/pointers/PString:value	Ljava/lang/String;
    //   1018: aconst_null
    //   1019: astore 18
    //   1021: iconst_0
    //   1022: istore 13
    //   1024: aload 21
    //   1026: astore_3
    //   1027: goto -192 -> 835
    //   1030: ldc 26
    //   1032: astore_0
    //   1033: goto -33 -> 1000
    //   1036: ldc 26
    //   1038: astore_3
    //   1039: goto -27 -> 1012
    //   1042: aload_3
    //   1043: invokestatic 435	com/tencent/mm/storage/au:aOb	(Ljava/lang/String;)Lcom/tencent/mm/storage/au;
    //   1046: astore 21
    //   1048: new 152	java/lang/StringBuilder
    //   1051: dup
    //   1052: invokespecial 153	java/lang/StringBuilder:<init>	()V
    //   1055: aload 21
    //   1057: invokevirtual 438	com/tencent/mm/storage/au:aJH	()Ljava/lang/String;
    //   1060: invokevirtual 163	java/lang/StringBuilder:append	(Ljava/lang/String;)Ljava/lang/StringBuilder;
    //   1063: ldc_w 427
    //   1066: invokevirtual 163	java/lang/StringBuilder:append	(Ljava/lang/String;)Ljava/lang/StringBuilder;
    //   1069: invokevirtual 167	java/lang/StringBuilder:toString	()Ljava/lang/String;
    //   1072: astore 18
    //   1074: aload_0
    //   1075: ifnull +47 -> 1122
    //   1078: aload_0
    //   1079: invokevirtual 46	java/lang/String:length	()I
    //   1082: bipush 32
    //   1084: if_icmpne +38 -> 1122
    //   1087: aload_0
    //   1088: astore_3
    //   1089: aload 6
    //   1091: ldc 26
    //   1093: putfield 147	com/tencent/mm/pointers/PString:value	Ljava/lang/String;
    //   1096: aload 7
    //   1098: aload 21
    //   1100: invokevirtual 438	com/tencent/mm/storage/au:aJH	()Ljava/lang/String;
    //   1103: putfield 147	com/tencent/mm/pointers/PString:value	Ljava/lang/String;
    //   1106: aconst_null
    //   1107: astore 21
    //   1109: iconst_0
    //   1110: istore 13
    //   1112: aload 18
    //   1114: astore_0
    //   1115: aload 21
    //   1117: astore 18
    //   1119: goto -284 -> 835
    //   1122: aload 5
    //   1124: ldc_w 439
    //   1127: invokevirtual 169	android/content/Context:getString	(I)Ljava/lang/String;
    //   1130: astore_3
    //   1131: goto -42 -> 1089
    //   1134: aload 5
    //   1136: iload_1
    //   1137: aload_2
    //   1138: aload_3
    //   1139: aload 5
    //   1141: ldc_w 425
    //   1144: invokevirtual 169	android/content/Context:getString	(I)Ljava/lang/String;
    //   1147: aload 6
    //   1149: aload 7
    //   1151: invokestatic 441	com/tencent/mm/booter/notification/a/h:a	(Landroid/content/Context;ILjava/lang/String;Ljava/lang/String;Ljava/lang/String;Lcom/tencent/mm/pointers/PString;Lcom/tencent/mm/pointers/PString;)Ljava/lang/String;
    //   1154: astore_0
    //   1155: ldc 26
    //   1157: astore_3
    //   1158: aconst_null
    //   1159: astore 18
    //   1161: iconst_0
    //   1162: istore 13
    //   1164: goto -329 -> 835
    //   1167: aload 5
    //   1169: iload_1
    //   1170: aload_2
    //   1171: aload_3
    //   1172: aconst_null
    //   1173: aload 6
    //   1175: aload 7
    //   1177: invokestatic 441	com/tencent/mm/booter/notification/a/h:a	(Landroid/content/Context;ILjava/lang/String;Ljava/lang/String;Ljava/lang/String;Lcom/tencent/mm/pointers/PString;Lcom/tencent/mm/pointers/PString;)Ljava/lang/String;
    //   1180: astore_0
    //   1181: ldc 26
    //   1183: astore_3
    //   1184: aconst_null
    //   1185: astore 18
    //   1187: iconst_0
    //   1188: istore 13
    //   1190: goto -355 -> 835
    //   1193: aload_2
    //   1194: invokestatic 136	com/tencent/mm/storage/ai:aMZ	(Ljava/lang/String;)Z
    //   1197: ifne +24 -> 1221
    //   1200: aload_2
    //   1201: invokestatic 139	com/tencent/mm/storage/ai:aNb	(Ljava/lang/String;)Z
    //   1204: ifne +17 -> 1221
    //   1207: aload_2
    //   1208: invokestatic 118	com/tencent/mm/model/w:wM	(Ljava/lang/String;)Z
    //   1211: ifne +10 -> 1221
    //   1214: aload_2
    //   1215: invokestatic 121	com/tencent/mm/model/w:wO	(Ljava/lang/String;)Z
    //   1218: ifeq +36 -> 1254
    //   1221: aload 5
    //   1223: iload_1
    //   1224: aload_2
    //   1225: aload_3
    //   1226: aload 5
    //   1228: ldc_w 442
    //   1231: invokevirtual 169	android/content/Context:getString	(I)Ljava/lang/String;
    //   1234: aload 6
    //   1236: aload 7
    //   1238: invokestatic 441	com/tencent/mm/booter/notification/a/h:a	(Landroid/content/Context;ILjava/lang/String;Ljava/lang/String;Ljava/lang/String;Lcom/tencent/mm/pointers/PString;Lcom/tencent/mm/pointers/PString;)Ljava/lang/String;
    //   1241: astore_0
    //   1242: ldc 26
    //   1244: astore_3
    //   1245: aconst_null
    //   1246: astore 18
    //   1248: iconst_0
    //   1249: istore 13
    //   1251: goto -416 -> 835
    //   1254: aload_3
    //   1255: astore_0
    //   1256: aload_3
    //   1257: ifnull +78 -> 1335
    //   1260: aload_3
    //   1261: astore_0
    //   1262: aload_3
    //   1263: invokevirtual 46	java/lang/String:length	()I
    //   1266: ifle +69 -> 1335
    //   1269: aload_3
    //   1270: astore_0
    //   1271: aload_2
    //   1272: invokestatic 407	com/tencent/mm/model/w:wN	(Ljava/lang/String;)Z
    //   1275: ifne +60 -> 1335
    //   1278: aload_2
    //   1279: invokestatic 385	com/tencent/mm/model/w:sQ	(Ljava/lang/String;)Z
    //   1282: ifeq +71 -> 1353
    //   1285: new 444	com/tencent/mm/modelvoice/p
    //   1288: dup
    //   1289: aload_3
    //   1290: invokespecial 447	com/tencent/mm/modelvoice/p:<init>	(Ljava/lang/String;)V
    //   1293: astore_3
    //   1294: new 152	java/lang/StringBuilder
    //   1297: dup
    //   1298: invokespecial 153	java/lang/StringBuilder:<init>	()V
    //   1301: aload_3
    //   1302: invokevirtual 448	com/tencent/mm/modelvoice/p:aJH	()Ljava/lang/String;
    //   1305: invokevirtual 163	java/lang/StringBuilder:append	(Ljava/lang/String;)Ljava/lang/StringBuilder;
    //   1308: ldc_w 427
    //   1311: invokevirtual 163	java/lang/StringBuilder:append	(Ljava/lang/String;)Ljava/lang/StringBuilder;
    //   1314: invokevirtual 167	java/lang/StringBuilder:toString	()Ljava/lang/String;
    //   1317: astore_0
    //   1318: aload 6
    //   1320: ldc_w 450
    //   1323: putfield 147	com/tencent/mm/pointers/PString:value	Ljava/lang/String;
    //   1326: aload 7
    //   1328: aload_3
    //   1329: invokevirtual 448	com/tencent/mm/modelvoice/p:aJH	()Ljava/lang/String;
    //   1332: putfield 147	com/tencent/mm/pointers/PString:value	Ljava/lang/String;
    //   1335: aload 5
    //   1337: ldc_w 442
    //   1340: invokevirtual 169	android/content/Context:getString	(I)Ljava/lang/String;
    //   1343: astore_3
    //   1344: aconst_null
    //   1345: astore 18
    //   1347: iconst_0
    //   1348: istore 13
    //   1350: goto -515 -> 835
    //   1353: ldc 26
    //   1355: astore_0
    //   1356: goto -21 -> 1335
    //   1359: aload_2
    //   1360: invokestatic 136	com/tencent/mm/storage/ai:aMZ	(Ljava/lang/String;)Z
    //   1363: ifne +24 -> 1387
    //   1366: aload_2
    //   1367: invokestatic 139	com/tencent/mm/storage/ai:aNb	(Ljava/lang/String;)Z
    //   1370: ifne +17 -> 1387
    //   1373: aload_2
    //   1374: invokestatic 118	com/tencent/mm/model/w:wM	(Ljava/lang/String;)Z
    //   1377: ifne +10 -> 1387
    //   1380: aload_2
    //   1381: invokestatic 121	com/tencent/mm/model/w:wO	(Ljava/lang/String;)Z
    //   1384: ifeq +36 -> 1420
    //   1387: aload 5
    //   1389: iload_1
    //   1390: aload_2
    //   1391: aload_3
    //   1392: aload 5
    //   1394: ldc_w 451
    //   1397: invokevirtual 169	android/content/Context:getString	(I)Ljava/lang/String;
    //   1400: aload 6
    //   1402: aload 7
    //   1404: invokestatic 441	com/tencent/mm/booter/notification/a/h:a	(Landroid/content/Context;ILjava/lang/String;Ljava/lang/String;Ljava/lang/String;Lcom/tencent/mm/pointers/PString;Lcom/tencent/mm/pointers/PString;)Ljava/lang/String;
    //   1407: astore_0
    //   1408: ldc 26
    //   1410: astore_3
    //   1411: aconst_null
    //   1412: astore 18
    //   1414: iconst_0
    //   1415: istore 13
    //   1417: goto -582 -> 835
    //   1420: aload_3
    //   1421: astore_0
    //   1422: aload_3
    //   1423: ifnull +78 -> 1501
    //   1426: aload_3
    //   1427: astore_0
    //   1428: aload_3
    //   1429: invokevirtual 46	java/lang/String:length	()I
    //   1432: ifle +69 -> 1501
    //   1435: aload_3
    //   1436: astore_0
    //   1437: aload_2
    //   1438: invokestatic 407	com/tencent/mm/model/w:wN	(Ljava/lang/String;)Z
    //   1441: ifne +60 -> 1501
    //   1444: aload_2
    //   1445: invokestatic 385	com/tencent/mm/model/w:sQ	(Ljava/lang/String;)Z
    //   1448: ifeq +71 -> 1519
    //   1451: new 453	com/tencent/mm/modelvideo/q
    //   1454: dup
    //   1455: aload_3
    //   1456: invokespecial 454	com/tencent/mm/modelvideo/q:<init>	(Ljava/lang/String;)V
    //   1459: astore_3
    //   1460: new 152	java/lang/StringBuilder
    //   1463: dup
    //   1464: invokespecial 153	java/lang/StringBuilder:<init>	()V
    //   1467: aload_3
    //   1468: invokevirtual 455	com/tencent/mm/modelvideo/q:aJH	()Ljava/lang/String;
    //   1471: invokevirtual 163	java/lang/StringBuilder:append	(Ljava/lang/String;)Ljava/lang/StringBuilder;
    //   1474: ldc_w 427
    //   1477: invokevirtual 163	java/lang/StringBuilder:append	(Ljava/lang/String;)Ljava/lang/StringBuilder;
    //   1480: invokevirtual 167	java/lang/StringBuilder:toString	()Ljava/lang/String;
    //   1483: astore_0
    //   1484: aload 6
    //   1486: ldc_w 450
    //   1489: putfield 147	com/tencent/mm/pointers/PString:value	Ljava/lang/String;
    //   1492: aload 7
    //   1494: aload_3
    //   1495: invokevirtual 455	com/tencent/mm/modelvideo/q:aJH	()Ljava/lang/String;
    //   1498: putfield 147	com/tencent/mm/pointers/PString:value	Ljava/lang/String;
    //   1501: aload 5
    //   1503: ldc_w 451
    //   1506: invokevirtual 169	android/content/Context:getString	(I)Ljava/lang/String;
    //   1509: astore_3
    //   1510: aconst_null
    //   1511: astore 18
    //   1513: iconst_0
    //   1514: istore 13
    //   1516: goto -681 -> 835
    //   1519: ldc 26
    //   1521: astore_0
    //   1522: goto -21 -> 1501
    //   1525: aload 5
    //   1527: ldc_w 456
    //   1530: invokevirtual 169	android/content/Context:getString	(I)Ljava/lang/String;
    //   1533: astore_3
    //   1534: aconst_null
    //   1535: astore 18
    //   1537: iconst_0
    //   1538: istore 13
    //   1540: ldc 26
    //   1542: astore_0
    //   1543: goto -708 -> 835
    //   1546: aload 5
    //   1548: ldc_w 457
    //   1551: invokevirtual 169	android/content/Context:getString	(I)Ljava/lang/String;
    //   1554: astore_3
    //   1555: aconst_null
    //   1556: astore 18
    //   1558: iconst_0
    //   1559: istore 13
    //   1561: ldc 26
    //   1563: astore_0
    //   1564: goto -729 -> 835
    //   1567: aload_3
    //   1568: getstatic 462	com/tencent/mm/storage/bo:GYP	Ljava/lang/String;
    //   1571: invokevirtual 466	java/lang/String:equals	(Ljava/lang/Object;)Z
    //   1574: ifeq +24 -> 1598
    //   1577: aload 5
    //   1579: ldc_w 456
    //   1582: invokevirtual 169	android/content/Context:getString	(I)Ljava/lang/String;
    //   1585: astore_3
    //   1586: aconst_null
    //   1587: astore 18
    //   1589: iconst_0
    //   1590: istore 13
    //   1592: ldc 26
    //   1594: astore_0
    //   1595: goto -760 -> 835
    //   1598: aload_3
    //   1599: astore_0
    //   1600: aload_3
    //   1601: getstatic 469	com/tencent/mm/storage/bo:GYO	Ljava/lang/String;
    //   1604: invokevirtual 466	java/lang/String:equals	(Ljava/lang/Object;)Z
    //   1607: ifeq -781 -> 826
    //   1610: aload 5
    //   1612: ldc_w 470
    //   1615: invokevirtual 169	android/content/Context:getString	(I)Ljava/lang/String;
    //   1618: astore_3
    //   1619: aconst_null
    //   1620: astore 18
    //   1622: iconst_0
    //   1623: istore 13
    //   1625: ldc 26
    //   1627: astore_0
    //   1628: goto -793 -> 835
    //   1631: aload 5
    //   1633: ldc_w 456
    //   1636: invokevirtual 169	android/content/Context:getString	(I)Ljava/lang/String;
    //   1639: astore_3
    //   1640: aconst_null
    //   1641: astore 18
    //   1643: iconst_0
    //   1644: istore 13
    //   1646: ldc 26
    //   1648: astore_0
    //   1649: goto -814 -> 835
    //   1652: aload 5
    //   1654: ldc_w 470
    //   1657: invokevirtual 169	android/content/Context:getString	(I)Ljava/lang/String;
    //   1660: astore_3
    //   1661: aconst_null
    //   1662: astore 18
    //   1664: iconst_0
    //   1665: istore 13
    //   1667: ldc 26
    //   1669: astore_0
    //   1670: goto -835 -> 835
    //   1673: aload_3
    //   1674: astore_0
    //   1675: aload_3
    //   1676: ifnull -850 -> 826
    //   1679: aload_3
    //   1680: astore_0
    //   1681: aload_3
    //   1682: invokevirtual 46	java/lang/String:length	()I
    //   1685: ifle -859 -> 826
    //   1688: aload_3
    //   1689: invokestatic 476	com/tencent/mm/storage/bo$d:aOn	(Ljava/lang/String;)Lcom/tencent/mm/storage/bo$d;
    //   1692: astore 18
    //   1694: aload_3
    //   1695: astore_0
    //   1696: aload 18
    //   1698: invokevirtual 479	com/tencent/mm/storage/bo$d:fck	()Ljava/lang/String;
    //   1701: ifnull +110 -> 1811
    //   1704: aload_3
    //   1705: astore_0
    //   1706: aload 18
    //   1708: invokevirtual 479	com/tencent/mm/storage/bo$d:fck	()Ljava/lang/String;
    //   1711: invokevirtual 46	java/lang/String:length	()I
    //   1714: ifle +97 -> 1811
    //   1717: aload 18
    //   1719: invokevirtual 482	com/tencent/mm/storage/bo$d:getScene	()I
    //   1722: tableswitch	default:+62 -> 1784, 18:+101->1823, 19:+62->1784, 20:+62->1784, 21:+62->1784, 22:+134->1856, 23:+134->1856, 24:+134->1856, 25:+167->1889, 26:+134->1856, 27:+134->1856, 28:+134->1856, 29:+134->1856
    //   1785: iconst_2
    //   1786: ldc_w 483
    //   1789: iconst_1
    //   1790: anewarray 4	java/lang/Object
    //   1793: dup
    //   1794: iconst_0
    //   1795: aload 18
    //   1797: invokevirtual 485	com/tencent/mm/storage/bo$d:getDisplayName	()Ljava/lang/String;
    //   1800: aastore
    //   1801: invokevirtual 159	android/content/Context:getString	(I[Ljava/lang/Object;)Ljava/lang/String;
    //   1804: astore_0
    //   1805: aload 6
    //   1807: aload_0
    //   1808: putfield 147	com/tencent/mm/pointers/PString:value	Ljava/lang/String;
    //   1811: ldc 26
    //   1813: astore_3
    //   1814: aconst_null
    //   1815: astore 18
    //   1817: iconst_0
    //   1818: istore 13
    //   1820: goto -985 -> 835
    //   1823: aload 5
    //   1825: ldc_w 486
    //   1828: iconst_1
    //   1829: anewarray 4	java/lang/Object
    //   1832: dup
    //   1833: iconst_0
    //   1834: aload 18
    //   1836: invokevirtual 485	com/tencent/mm/storage/bo$d:getDisplayName	()Ljava/lang/String;
    //   1839: aastore
    //   1840: invokevirtual 159	android/content/Context:getString	(I[Ljava/lang/Object;)Ljava/lang/String;
    //   1843: astore_0
    //   1844: ldc 26
    //   1846: astore_3
    //   1847: aconst_null
    //   1848: astore 18
    //   1850: iconst_0
    //   1851: istore 13
    //   1853: goto -1018 -> 835
    //   1856: aload 5
    //   1858: ldc_w 487
    //   1861: iconst_1
    //   1862: anewarray 4	java/lang/Object
    //   1865: dup
    //   1866: iconst_0
    //   1867: aload 18
    //   1869: invokevirtual 485	com/tencent/mm/storage/bo$d:getDisplayName	()Ljava/lang/String;
    //   1872: aastore
    //   1873: invokevirtual 159	android/content/Context:getString	(I[Ljava/lang/Object;)Ljava/lang/String;
    //   1876: astore_0
    //   1877: ldc 26
    //   1879: astore_3
    //   1880: aconst_null
    //   1881: astore 18
    //   1883: iconst_0
    //   1884: istore 13
    //   1886: goto -1051 -> 835
    //   1889: aload 5
    //   1891: ldc_w 488
    //   1894: iconst_1
    //   1895: anewarray 4	java/lang/Object
    //   1898: dup
    //   1899: iconst_0
    //   1900: aload 18
    //   1902: invokevirtual 485	com/tencent/mm/storage/bo$d:getDisplayName	()Ljava/lang/String;
    //   1905: aastore
    //   1906: invokevirtual 159	android/content/Context:getString	(I[Ljava/lang/Object;)Ljava/lang/String;
    //   1909: astore_0
    //   1910: aload 6
    //   1912: aload_0
    //   1913: putfield 147	com/tencent/mm/pointers/PString:value	Ljava/lang/String;
    //   1916: ldc 26
    //   1918: astore_3
    //   1919: aconst_null
    //   1920: astore 18
    //   1922: iconst_0
    //   1923: istore 13
    //   1925: goto -1090 -> 835
    //   1928: aload_3
    //   1929: astore_0
    //   1930: aload_3
    //   1931: ifnull -1105 -> 826
    //   1934: aload_3
    //   1935: astore_0
    //   1936: aload_3
    //   1937: invokevirtual 46	java/lang/String:length	()I
    //   1940: ifle -1114 -> 826
    //   1943: aload_3
    //   1944: invokestatic 494	com/tencent/mm/storage/bo$a:aOk	(Ljava/lang/String;)Lcom/tencent/mm/storage/bo$a;
    //   1947: astore 18
    //   1949: aload_3
    //   1950: astore_0
    //   1951: aload 18
    //   1953: invokevirtual 495	com/tencent/mm/storage/bo$a:fck	()Ljava/lang/String;
    //   1956: ifnull +43 -> 1999
    //   1959: aload_3
    //   1960: astore_0
    //   1961: aload 18
    //   1963: invokevirtual 495	com/tencent/mm/storage/bo$a:fck	()Ljava/lang/String;
    //   1966: invokevirtual 46	java/lang/String:length	()I
    //   1969: ifle +30 -> 1999
    //   1972: aload 5
    //   1974: ldc_w 496
    //   1977: iconst_1
    //   1978: anewarray 4	java/lang/Object
    //   1981: dup
    //   1982: iconst_0
    //   1983: aload 18
    //   1985: invokevirtual 497	com/tencent/mm/storage/bo$a:getDisplayName	()Ljava/lang/String;
    //   1988: aastore
    //   1989: invokevirtual 159	android/content/Context:getString	(I[Ljava/lang/Object;)Ljava/lang/String;
    //   1992: astore_0
    //   1993: aload 6
    //   1995: aload_0
    //   1996: putfield 147	com/tencent/mm/pointers/PString:value	Ljava/lang/String;
    //   1999: ldc 26
    //   2001: astore_3
    //   2002: aconst_null
    //   2003: astore 18
    //   2005: iconst_0
    //   2006: istore 13
    //   2008: goto -1173 -> 835
    //   2011: aload_3
    //   2012: astore_0
    //   2013: aload_3
    //   2014: invokestatic 110	com/tencent/mm/sdk/platformtools/bs:nullAsNil	(Ljava/lang/String;)Ljava/lang/String;
    //   2017: invokevirtual 46	java/lang/String:length	()I
    //   2020: ifle -1194 -> 826
    //   2023: invokestatic 257	com/tencent/mm/model/az:ayM	()Lcom/tencent/mm/model/c;
    //   2026: pop
    //   2027: invokestatic 501	com/tencent/mm/model/c:awD	()Lcom/tencent/mm/plugin/messenger/foundation/a/a/h;
    //   2030: aload_3
    //   2031: invokeinterface 507 2 0
    //   2036: astore_0
    //   2037: aload 5
    //   2039: ldc_w 508
    //   2042: iconst_2
    //   2043: anewarray 4	java/lang/Object
    //   2046: dup
    //   2047: iconst_0
    //   2048: aload_0
    //   2049: invokevirtual 513	com/tencent/mm/storage/bo$c:getSender	()Ljava/lang/String;
    //   2052: aastore
    //   2053: dup
    //   2054: iconst_1
    //   2055: aload_0
    //   2056: invokevirtual 516	com/tencent/mm/storage/bo$c:getTitle	()Ljava/lang/String;
    //   2059: aastore
    //   2060: invokevirtual 159	android/content/Context:getString	(I[Ljava/lang/Object;)Ljava/lang/String;
    //   2063: astore_0
    //   2064: aload 6
    //   2066: aload_0
    //   2067: putfield 147	com/tencent/mm/pointers/PString:value	Ljava/lang/String;
    //   2070: ldc 26
    //   2072: astore_3
    //   2073: aconst_null
    //   2074: astore 18
    //   2076: iconst_0
    //   2077: istore 13
    //   2079: goto -1244 -> 835
    //   2082: aload_3
    //   2083: astore_0
    //   2084: aload_3
    //   2085: invokestatic 110	com/tencent/mm/sdk/platformtools/bs:nullAsNil	(Ljava/lang/String;)Ljava/lang/String;
    //   2088: invokevirtual 46	java/lang/String:length	()I
    //   2091: ifle -1265 -> 826
    //   2094: aload_2
    //   2095: invokestatic 385	com/tencent/mm/model/w:sQ	(Ljava/lang/String;)Z
    //   2098: ifeq +20 -> 2118
    //   2101: aload_3
    //   2102: invokestatic 519	com/tencent/mm/model/bi:yl	(Ljava/lang/String;)Ljava/lang/String;
    //   2105: astore 18
    //   2107: aload 18
    //   2109: astore_0
    //   2110: aload 18
    //   2112: invokestatic 211	android/text/TextUtils:isEmpty	(Ljava/lang/CharSequence;)Z
    //   2115: ifeq +5 -> 2120
    //   2118: aload_2
    //   2119: astore_0
    //   2120: invokestatic 257	com/tencent/mm/model/az:ayM	()Lcom/tencent/mm/model/c;
    //   2123: pop
    //   2124: invokestatic 501	com/tencent/mm/model/c:awD	()Lcom/tencent/mm/plugin/messenger/foundation/a/a/h;
    //   2127: aload_3
    //   2128: invokeinterface 522 2 0
    //   2133: astore 21
    //   2135: invokestatic 257	com/tencent/mm/model/az:ayM	()Lcom/tencent/mm/model/c;
    //   2138: pop
    //   2139: invokestatic 263	com/tencent/mm/model/c:awB	()Lcom/tencent/mm/storage/bj;
    //   2142: aload_0
    //   2143: invokeinterface 269 2 0
    //   2148: invokevirtual 356	com/tencent/mm/storage/ai:aaS	()Ljava/lang/String;
    //   2151: astore 18
    //   2153: aload 18
    //   2155: astore_3
    //   2156: aload 18
    //   2158: invokestatic 385	com/tencent/mm/model/w:sQ	(Ljava/lang/String;)Z
    //   2161: ifeq +12 -> 2173
    //   2164: aload 18
    //   2166: invokestatic 528	com/tencent/mm/model/q:wc	(Ljava/lang/String;)Ljava/util/List;
    //   2169: invokestatic 532	com/tencent/mm/model/q:ad	(Ljava/util/List;)Ljava/lang/String;
    //   2172: astore_3
    //   2173: iload_1
    //   2174: iconst_1
    //   2175: if_icmpne +85 -> 2260
    //   2178: aload 5
    //   2180: ldc_w 533
    //   2183: iconst_2
    //   2184: anewarray 4	java/lang/Object
    //   2187: dup
    //   2188: iconst_0
    //   2189: aload_3
    //   2190: aastore
    //   2191: dup
    //   2192: iconst_1
    //   2193: aload 21
    //   2195: invokevirtual 497	com/tencent/mm/storage/bo$a:getDisplayName	()Ljava/lang/String;
    //   2198: aastore
    //   2199: invokevirtual 159	android/content/Context:getString	(I[Ljava/lang/Object;)Ljava/lang/String;
    //   2202: astore 18
    //   2204: aload 6
    //   2206: aload 5
    //   2208: ldc_w 533
    //   2211: iconst_2
    //   2212: anewarray 4	java/lang/Object
    //   2215: dup
    //   2216: iconst_0
    //   2217: ldc_w 535
    //   2220: aastore
    //   2221: dup
    //   2222: iconst_1
    //   2223: aload 21
    //   2225: invokevirtual 497	com/tencent/mm/storage/bo$a:getDisplayName	()Ljava/lang/String;
    //   2228: aastore
    //   2229: invokevirtual 159	android/content/Context:getString	(I[Ljava/lang/Object;)Ljava/lang/String;
    //   2232: putfield 147	com/tencent/mm/pointers/PString:value	Ljava/lang/String;
    //   2235: aload 7
    //   2237: aload_0
    //   2238: putfield 147	com/tencent/mm/pointers/PString:value	Ljava/lang/String;
    //   2241: ldc 26
    //   2243: astore_3
    //   2244: aconst_null
    //   2245: astore 21
    //   2247: iconst_0
    //   2248: istore 13
    //   2250: aload 18
    //   2252: astore_0
    //   2253: aload 21
    //   2255: astore 18
    //   2257: goto -1422 -> 835
    //   2260: aload 5
    //   2262: ldc_w 536
    //   2265: iconst_2
    //   2266: anewarray 4	java/lang/Object
    //   2269: dup
    //   2270: iconst_0
    //   2271: aload_3
    //   2272: aastore
    //   2273: dup
    //   2274: iconst_1
    //   2275: aload 21
    //   2277: invokevirtual 497	com/tencent/mm/storage/bo$a:getDisplayName	()Ljava/lang/String;
    //   2280: aastore
    //   2281: invokevirtual 159	android/content/Context:getString	(I[Ljava/lang/Object;)Ljava/lang/String;
    //   2284: astore 18
    //   2286: aload 6
    //   2288: aload 5
    //   2290: ldc_w 536
    //   2293: iconst_2
    //   2294: anewarray 4	java/lang/Object
    //   2297: dup
    //   2298: iconst_0
    //   2299: ldc_w 535
    //   2302: aastore
    //   2303: dup
    //   2304: iconst_1
    //   2305: aload 21
    //   2307: invokevirtual 497	com/tencent/mm/storage/bo$a:getDisplayName	()Ljava/lang/String;
    //   2310: aastore
    //   2311: invokevirtual 159	android/content/Context:getString	(I[Ljava/lang/Object;)Ljava/lang/String;
    //   2314: putfield 147	com/tencent/mm/pointers/PString:value	Ljava/lang/String;
    //   2317: aload 7
    //   2319: aload_0
    //   2320: putfield 147	com/tencent/mm/pointers/PString:value	Ljava/lang/String;
    //   2323: ldc 26
    //   2325: astore_3
    //   2326: aconst_null
    //   2327: astore 21
    //   2329: iconst_0
    //   2330: istore 13
    //   2332: aload 18
    //   2334: astore_0
    //   2335: aload 21
    //   2337: astore 18
    //   2339: goto -1504 -> 835
    //   2342: aload_3
    //   2343: astore_0
    //   2344: aload_3
    //   2345: invokestatic 110	com/tencent/mm/sdk/platformtools/bs:nullAsNil	(Ljava/lang/String;)Ljava/lang/String;
    //   2348: invokevirtual 46	java/lang/String:length	()I
    //   2351: ifle -1525 -> 826
    //   2354: aload_2
    //   2355: invokestatic 385	com/tencent/mm/model/w:sQ	(Ljava/lang/String;)Z
    //   2358: ifeq +6800 -> 9158
    //   2361: aload_3
    //   2362: invokestatic 393	com/tencent/mm/model/bi:yi	(Ljava/lang/String;)I
    //   2365: istore 13
    //   2367: iload 13
    //   2369: iconst_m1
    //   2370: if_icmpeq +6783 -> 9153
    //   2373: aload_3
    //   2374: iconst_0
    //   2375: iload 13
    //   2377: invokevirtual 131	java/lang/String:substring	(II)Ljava/lang/String;
    //   2380: invokevirtual 324	java/lang/String:trim	()Ljava/lang/String;
    //   2383: astore_0
    //   2384: aload_3
    //   2385: invokestatic 539	com/tencent/mm/model/bi:ym	(Ljava/lang/String;)Ljava/lang/String;
    //   2388: pop
    //   2389: iload_1
    //   2390: iconst_1
    //   2391: if_icmpne +30 -> 2421
    //   2394: aload 5
    //   2396: ldc_w 540
    //   2399: invokevirtual 169	android/content/Context:getString	(I)Ljava/lang/String;
    //   2402: astore_0
    //   2403: aload 6
    //   2405: aload_0
    //   2406: putfield 147	com/tencent/mm/pointers/PString:value	Ljava/lang/String;
    //   2409: ldc 26
    //   2411: astore_3
    //   2412: aconst_null
    //   2413: astore 18
    //   2415: iconst_0
    //   2416: istore 13
    //   2418: goto -1583 -> 835
    //   2421: aload 5
    //   2423: ldc_w 540
    //   2426: invokevirtual 169	android/content/Context:getString	(I)Ljava/lang/String;
    //   2429: astore 18
    //   2431: aload 6
    //   2433: aload 5
    //   2435: ldc_w 540
    //   2438: invokevirtual 169	android/content/Context:getString	(I)Ljava/lang/String;
    //   2441: putfield 147	com/tencent/mm/pointers/PString:value	Ljava/lang/String;
    //   2444: aload 7
    //   2446: aload_0
    //   2447: putfield 147	com/tencent/mm/pointers/PString:value	Ljava/lang/String;
    //   2450: ldc 26
    //   2452: astore_3
    //   2453: aconst_null
    //   2454: astore 21
    //   2456: iconst_0
    //   2457: istore 13
    //   2459: aload 18
    //   2461: astore_0
    //   2462: aload 21
    //   2464: astore 18
    //   2466: goto -1631 -> 835
    //   2469: aload 21
    //   2471: invokestatic 543	com/tencent/mm/sdk/platformtools/bs:aLx	(Ljava/lang/String;)Ljava/lang/String;
    //   2474: invokestatic 549	com/tencent/mm/ah/k$b:vA	(Ljava/lang/String;)Lcom/tencent/mm/ah/k$b;
    //   2477: astore_0
    //   2478: aload_0
    //   2479: getfield 552	com/tencent/mm/ah/k$b:hie	I
    //   2482: ifeq +88 -> 2570
    //   2485: aload_0
    //   2486: getfield 552	com/tencent/mm/ah/k$b:hie	I
    //   2489: iconst_1
    //   2490: if_icmpne +40 -> 2530
    //   2493: aload 5
    //   2495: ldc_w 553
    //   2498: invokevirtual 169	android/content/Context:getString	(I)Ljava/lang/String;
    //   2501: astore_0
    //   2502: aload 7
    //   2504: aload 19
    //   2506: putfield 147	com/tencent/mm/pointers/PString:value	Ljava/lang/String;
    //   2509: aload 6
    //   2511: ldc 26
    //   2513: putfield 147	com/tencent/mm/pointers/PString:value	Ljava/lang/String;
    //   2516: aload_0
    //   2517: astore_3
    //   2518: aconst_null
    //   2519: astore 18
    //   2521: iconst_0
    //   2522: istore 13
    //   2524: ldc 26
    //   2526: astore_0
    //   2527: goto -1692 -> 835
    //   2530: aload_0
    //   2531: getfield 552	com/tencent/mm/ah/k$b:hie	I
    //   2534: iconst_2
    //   2535: if_icmpne +15 -> 2550
    //   2538: aload 5
    //   2540: ldc_w 554
    //   2543: invokevirtual 169	android/content/Context:getString	(I)Ljava/lang/String;
    //   2546: astore_0
    //   2547: goto -45 -> 2502
    //   2550: aload_0
    //   2551: getfield 552	com/tencent/mm/ah/k$b:hie	I
    //   2554: iconst_3
    //   2555: if_icmpne +15 -> 2570
    //   2558: aload 5
    //   2560: ldc_w 555
    //   2563: invokevirtual 169	android/content/Context:getString	(I)Ljava/lang/String;
    //   2566: astore_0
    //   2567: goto -65 -> 2502
    //   2570: aload 5
    //   2572: ldc_w 556
    //   2575: invokevirtual 169	android/content/Context:getString	(I)Ljava/lang/String;
    //   2578: astore_0
    //   2579: goto -77 -> 2502
    //   2582: aload 21
    //   2584: invokestatic 543	com/tencent/mm/sdk/platformtools/bs:aLx	(Ljava/lang/String;)Ljava/lang/String;
    //   2587: astore 18
    //   2589: ldc 26
    //   2591: astore_3
    //   2592: ldc 26
    //   2594: astore_0
    //   2595: aload 18
    //   2597: invokestatic 549	com/tencent/mm/ah/k$b:vA	(Ljava/lang/String;)Lcom/tencent/mm/ah/k$b;
    //   2600: astore 18
    //   2602: aload 18
    //   2604: ifnull +46 -> 2650
    //   2607: aload 6
    //   2609: new 152	java/lang/StringBuilder
    //   2612: dup
    //   2613: invokespecial 153	java/lang/StringBuilder:<init>	()V
    //   2616: aload 5
    //   2618: ldc_w 557
    //   2621: invokevirtual 169	android/content/Context:getString	(I)Ljava/lang/String;
    //   2624: invokevirtual 163	java/lang/StringBuilder:append	(Ljava/lang/String;)Ljava/lang/StringBuilder;
    //   2627: aload 18
    //   2629: getfield 560	com/tencent/mm/ah/k$b:title	Ljava/lang/String;
    //   2632: invokestatic 110	com/tencent/mm/sdk/platformtools/bs:nullAsNil	(Ljava/lang/String;)Ljava/lang/String;
    //   2635: invokevirtual 163	java/lang/StringBuilder:append	(Ljava/lang/String;)Ljava/lang/StringBuilder;
    //   2638: invokevirtual 167	java/lang/StringBuilder:toString	()Ljava/lang/String;
    //   2641: putfield 147	com/tencent/mm/pointers/PString:value	Ljava/lang/String;
    //   2644: aload 6
    //   2646: getfield 147	com/tencent/mm/pointers/PString:value	Ljava/lang/String;
    //   2649: astore_0
    //   2650: aload 7
    //   2652: aload 19
    //   2654: putfield 147	com/tencent/mm/pointers/PString:value	Ljava/lang/String;
    //   2657: aconst_null
    //   2658: astore 18
    //   2660: iconst_0
    //   2661: istore 13
    //   2663: goto -1828 -> 835
    //   2666: aload 21
    //   2668: invokestatic 543	com/tencent/mm/sdk/platformtools/bs:aLx	(Ljava/lang/String;)Ljava/lang/String;
    //   2671: astore 18
    //   2673: ldc 26
    //   2675: astore_3
    //   2676: ldc 26
    //   2678: astore_0
    //   2679: aload 18
    //   2681: invokestatic 549	com/tencent/mm/ah/k$b:vA	(Ljava/lang/String;)Lcom/tencent/mm/ah/k$b;
    //   2684: astore 18
    //   2686: aload 18
    //   2688: ifnull +79 -> 2767
    //   2691: iload_1
    //   2692: iconst_1
    //   2693: if_icmpne +90 -> 2783
    //   2696: iconst_1
    //   2697: istore 13
    //   2699: aload 18
    //   2701: getfield 563	com/tencent/mm/ah/k$b:hiL	I
    //   2704: tableswitch	default:+44 -> 2748, 1:+85->2789, 2:+270->2974, 3:+122->2826, 4:+159->2863, 5:+196->2900, 6:+233->2937, 7:+85->2789
    //   2749: iconst_3
    //   2750: aload 18
    //   2752: getfield 560	com/tencent/mm/ah/k$b:title	Ljava/lang/String;
    //   2755: invokestatic 110	com/tencent/mm/sdk/platformtools/bs:nullAsNil	(Ljava/lang/String;)Ljava/lang/String;
    //   2758: putfield 147	com/tencent/mm/pointers/PString:value	Ljava/lang/String;
    //   2761: aload 6
    //   2763: getfield 147	com/tencent/mm/pointers/PString:value	Ljava/lang/String;
    //   2766: astore_0
    //   2767: aload 7
    //   2769: aload 19
    //   2771: putfield 147	com/tencent/mm/pointers/PString:value	Ljava/lang/String;
    //   2774: aconst_null
    //   2775: astore 18
    //   2777: iconst_0
    //   2778: istore 13
    //   2780: goto -1945 -> 835
    //   2783: iconst_0
    //   2784: istore 13
    //   2786: goto -87 -> 2699
    //   2789: iload 13
    //   2791: ifeq +19 -> 2810
    //   2794: aload 6
    //   2796: aload 5
    //   2798: ldc_w 564
    //   2801: invokevirtual 169	android/content/Context:getString	(I)Ljava/lang/String;
    //   2804: putfield 147	com/tencent/mm/pointers/PString:value	Ljava/lang/String;
    //   2807: goto -46 -> 2761
    //   2810: aload 6
    //   2812: aload 5
    //   2814: ldc_w 565
    //   2817: invokevirtual 169	android/content/Context:getString	(I)Ljava/lang/String;
    //   2820: putfield 147	com/tencent/mm/pointers/PString:value	Ljava/lang/String;
    //   2823: goto -62 -> 2761
    //   2826: iload 13
    //   2828: ifeq +19 -> 2847
    //   2831: aload 6
    //   2833: aload 5
    //   2835: ldc_w 566
    //   2838: invokevirtual 169	android/content/Context:getString	(I)Ljava/lang/String;
    //   2841: putfield 147	com/tencent/mm/pointers/PString:value	Ljava/lang/String;
    //   2844: goto -83 -> 2761
    //   2847: aload 6
    //   2849: aload 5
    //   2851: ldc_w 567
    //   2854: invokevirtual 169	android/content/Context:getString	(I)Ljava/lang/String;
    //   2857: putfield 147	com/tencent/mm/pointers/PString:value	Ljava/lang/String;
    //   2860: goto -99 -> 2761
    //   2863: iload 13
    //   2865: ifeq +19 -> 2884
    //   2868: aload 6
    //   2870: aload 5
    //   2872: ldc_w 568
    //   2875: invokevirtual 169	android/content/Context:getString	(I)Ljava/lang/String;
    //   2878: putfield 147	com/tencent/mm/pointers/PString:value	Ljava/lang/String;
    //   2881: goto -120 -> 2761
    //   2884: aload 6
    //   2886: aload 5
    //   2888: ldc_w 569
    //   2891: invokevirtual 169	android/content/Context:getString	(I)Ljava/lang/String;
    //   2894: putfield 147	com/tencent/mm/pointers/PString:value	Ljava/lang/String;
    //   2897: goto -136 -> 2761
    //   2900: iload 13
    //   2902: ifeq +19 -> 2921
    //   2905: aload 6
    //   2907: aload 5
    //   2909: ldc_w 570
    //   2912: invokevirtual 169	android/content/Context:getString	(I)Ljava/lang/String;
    //   2915: putfield 147	com/tencent/mm/pointers/PString:value	Ljava/lang/String;
    //   2918: goto -157 -> 2761
    //   2921: aload 6
    //   2923: aload 5
    //   2925: ldc_w 567
    //   2928: invokevirtual 169	android/content/Context:getString	(I)Ljava/lang/String;
    //   2931: putfield 147	com/tencent/mm/pointers/PString:value	Ljava/lang/String;
    //   2934: goto -173 -> 2761
    //   2937: iload 13
    //   2939: ifeq +19 -> 2958
    //   2942: aload 6
    //   2944: aload 5
    //   2946: ldc_w 571
    //   2949: invokevirtual 169	android/content/Context:getString	(I)Ljava/lang/String;
    //   2952: putfield 147	com/tencent/mm/pointers/PString:value	Ljava/lang/String;
    //   2955: goto -194 -> 2761
    //   2958: aload 6
    //   2960: aload 5
    //   2962: ldc_w 571
    //   2965: invokevirtual 169	android/content/Context:getString	(I)Ljava/lang/String;
    //   2968: putfield 147	com/tencent/mm/pointers/PString:value	Ljava/lang/String;
    //   2971: goto -210 -> 2761
    //   2974: iload 13
    //   2976: ifeq +19 -> 2995
    //   2979: aload 6
    //   2981: aload 5
    //   2983: ldc_w 572
    //   2986: invokevirtual 169	android/content/Context:getString	(I)Ljava/lang/String;
    //   2989: putfield 147	com/tencent/mm/pointers/PString:value	Ljava/lang/String;
    //   2992: goto -231 -> 2761
    //   2995: aload 6
    //   2997: aload 5
    //   2999: ldc_w 572
    //   3002: invokevirtual 169	android/content/Context:getString	(I)Ljava/lang/String;
    //   3005: putfield 147	com/tencent/mm/pointers/PString:value	Ljava/lang/String;
    //   3008: goto -247 -> 2761
    //   3011: aload 21
    //   3013: invokestatic 543	com/tencent/mm/sdk/platformtools/bs:aLx	(Ljava/lang/String;)Ljava/lang/String;
    //   3016: astore_0
    //   3017: ldc 26
    //   3019: astore 21
    //   3021: ldc 26
    //   3023: astore_3
    //   3024: aload_0
    //   3025: invokestatic 549	com/tencent/mm/ah/k$b:vA	(Ljava/lang/String;)Lcom/tencent/mm/ah/k$b;
    //   3028: astore_0
    //   3029: aload_0
    //   3030: ifnull +60 -> 3090
    //   3033: iload_1
    //   3034: iconst_1
    //   3035: if_icmpne +92 -> 3127
    //   3038: iconst_1
    //   3039: istore 13
    //   3041: iload 13
    //   3043: ifeq +90 -> 3133
    //   3046: aload 6
    //   3048: new 152	java/lang/StringBuilder
    //   3051: dup
    //   3052: ldc_w 574
    //   3055: invokespecial 575	java/lang/StringBuilder:<init>	(Ljava/lang/String;)V
    //   3058: aload_0
    //   3059: getfield 578	com/tencent/mm/ah/k$b:hjl	Ljava/lang/String;
    //   3062: invokevirtual 163	java/lang/StringBuilder:append	(Ljava/lang/String;)Ljava/lang/StringBuilder;
    //   3065: ldc_w 580
    //   3068: invokevirtual 163	java/lang/StringBuilder:append	(Ljava/lang/String;)Ljava/lang/StringBuilder;
    //   3071: aload_0
    //   3072: getfield 583	com/tencent/mm/ah/k$b:hji	Ljava/lang/String;
    //   3075: invokevirtual 163	java/lang/StringBuilder:append	(Ljava/lang/String;)Ljava/lang/StringBuilder;
    //   3078: invokevirtual 167	java/lang/StringBuilder:toString	()Ljava/lang/String;
    //   3081: putfield 147	com/tencent/mm/pointers/PString:value	Ljava/lang/String;
    //   3084: aload 6
    //   3086: getfield 147	com/tencent/mm/pointers/PString:value	Ljava/lang/String;
    //   3089: astore_3
    //   3090: aload_3
    //   3091: astore_0
    //   3092: aload_2
    //   3093: invokestatic 401	com/tencent/mm/model/w:xg	(Ljava/lang/String;)Z
    //   3096: ifne +6019 -> 9115
    //   3099: aload_3
    //   3100: astore_0
    //   3101: iload 14
    //   3103: ifne +6012 -> 9115
    //   3106: aload 7
    //   3108: aload 19
    //   3110: putfield 147	com/tencent/mm/pointers/PString:value	Ljava/lang/String;
    //   3113: aconst_null
    //   3114: astore 18
    //   3116: iconst_0
    //   3117: istore 13
    //   3119: aload_3
    //   3120: astore_0
    //   3121: aload 21
    //   3123: astore_3
    //   3124: goto -2289 -> 835
    //   3127: iconst_0
    //   3128: istore 13
    //   3130: goto -89 -> 3041
    //   3133: aload 20
    //   3135: invokestatic 214	com/tencent/mm/sdk/platformtools/bs:isNullOrNil	(Ljava/lang/String;)Z
    //   3138: ifne +55 -> 3193
    //   3141: aload 6
    //   3143: new 152	java/lang/StringBuilder
    //   3146: dup
    //   3147: invokespecial 153	java/lang/StringBuilder:<init>	()V
    //   3150: aload 20
    //   3152: invokestatic 110	com/tencent/mm/sdk/platformtools/bs:nullAsNil	(Ljava/lang/String;)Ljava/lang/String;
    //   3155: invokevirtual 163	java/lang/StringBuilder:append	(Ljava/lang/String;)Ljava/lang/StringBuilder;
    //   3158: ldc_w 585
    //   3161: invokevirtual 163	java/lang/StringBuilder:append	(Ljava/lang/String;)Ljava/lang/StringBuilder;
    //   3164: aload_0
    //   3165: getfield 578	com/tencent/mm/ah/k$b:hjl	Ljava/lang/String;
    //   3168: invokevirtual 163	java/lang/StringBuilder:append	(Ljava/lang/String;)Ljava/lang/StringBuilder;
    //   3171: ldc_w 580
    //   3174: invokevirtual 163	java/lang/StringBuilder:append	(Ljava/lang/String;)Ljava/lang/StringBuilder;
    //   3177: aload_0
    //   3178: getfield 588	com/tencent/mm/ah/k$b:hjh	Ljava/lang/String;
    //   3181: invokevirtual 163	java/lang/StringBuilder:append	(Ljava/lang/String;)Ljava/lang/StringBuilder;
    //   3184: invokevirtual 167	java/lang/StringBuilder:toString	()Ljava/lang/String;
    //   3187: putfield 147	com/tencent/mm/pointers/PString:value	Ljava/lang/String;
    //   3190: goto -106 -> 3084
    //   3193: aload 6
    //   3195: new 152	java/lang/StringBuilder
    //   3198: dup
    //   3199: ldc_w 574
    //   3202: invokespecial 575	java/lang/StringBuilder:<init>	(Ljava/lang/String;)V
    //   3205: aload_0
    //   3206: getfield 578	com/tencent/mm/ah/k$b:hjl	Ljava/lang/String;
    //   3209: invokevirtual 163	java/lang/StringBuilder:append	(Ljava/lang/String;)Ljava/lang/StringBuilder;
    //   3212: ldc_w 580
    //   3215: invokevirtual 163	java/lang/StringBuilder:append	(Ljava/lang/String;)Ljava/lang/StringBuilder;
    //   3218: aload_0
    //   3219: getfield 588	com/tencent/mm/ah/k$b:hjh	Ljava/lang/String;
    //   3222: invokevirtual 163	java/lang/StringBuilder:append	(Ljava/lang/String;)Ljava/lang/StringBuilder;
    //   3225: invokevirtual 167	java/lang/StringBuilder:toString	()Ljava/lang/String;
    //   3228: putfield 147	com/tencent/mm/pointers/PString:value	Ljava/lang/String;
    //   3231: goto -147 -> 3084
    //   3234: aload 21
    //   3236: invokestatic 543	com/tencent/mm/sdk/platformtools/bs:aLx	(Ljava/lang/String;)Ljava/lang/String;
    //   3239: astore 18
    //   3241: ldc 26
    //   3243: astore_3
    //   3244: ldc 26
    //   3246: astore_0
    //   3247: aload 18
    //   3249: invokestatic 549	com/tencent/mm/ah/k$b:vA	(Ljava/lang/String;)Lcom/tencent/mm/ah/k$b;
    //   3252: astore 18
    //   3254: aload 18
    //   3256: ifnull +5859 -> 9115
    //   3259: aload 18
    //   3261: ldc_w 590
    //   3264: invokevirtual 594	com/tencent/mm/ah/k$b:ao	(Ljava/lang/Class;)Lcom/tencent/mm/ah/f;
    //   3267: checkcast 590	com/tencent/mm/ah/b
    //   3270: astore_0
    //   3271: iload_1
    //   3272: iconst_1
    //   3273: if_icmpne +57 -> 3330
    //   3276: iconst_1
    //   3277: istore 13
    //   3279: iload 13
    //   3281: ifeq +55 -> 3336
    //   3284: aload 6
    //   3286: aload 5
    //   3288: ldc_w 595
    //   3291: iconst_1
    //   3292: anewarray 4	java/lang/Object
    //   3295: dup
    //   3296: iconst_0
    //   3297: aload_0
    //   3298: getfield 598	com/tencent/mm/ah/b:hgD	Ljava/lang/String;
    //   3301: aastore
    //   3302: invokevirtual 159	android/content/Context:getString	(I[Ljava/lang/Object;)Ljava/lang/String;
    //   3305: putfield 147	com/tencent/mm/pointers/PString:value	Ljava/lang/String;
    //   3308: aload 6
    //   3310: getfield 147	com/tencent/mm/pointers/PString:value	Ljava/lang/String;
    //   3313: astore_0
    //   3314: aload 7
    //   3316: aload 19
    //   3318: putfield 147	com/tencent/mm/pointers/PString:value	Ljava/lang/String;
    //   3321: aconst_null
    //   3322: astore 18
    //   3324: iconst_0
    //   3325: istore 13
    //   3327: goto -2492 -> 835
    //   3330: iconst_0
    //   3331: istore 13
    //   3333: goto -54 -> 3279
    //   3336: aload 6
    //   3338: aload 5
    //   3340: ldc_w 595
    //   3343: iconst_1
    //   3344: anewarray 4	java/lang/Object
    //   3347: dup
    //   3348: iconst_0
    //   3349: aload_0
    //   3350: getfield 601	com/tencent/mm/ah/b:hgE	Ljava/lang/String;
    //   3353: aastore
    //   3354: invokevirtual 159	android/content/Context:getString	(I[Ljava/lang/Object;)Ljava/lang/String;
    //   3357: putfield 147	com/tencent/mm/pointers/PString:value	Ljava/lang/String;
    //   3360: goto -52 -> 3308
    //   3363: aload 21
    //   3365: invokestatic 543	com/tencent/mm/sdk/platformtools/bs:aLx	(Ljava/lang/String;)Ljava/lang/String;
    //   3368: astore_3
    //   3369: ldc 26
    //   3371: astore_0
    //   3372: aload_3
    //   3373: invokestatic 549	com/tencent/mm/ah/k$b:vA	(Ljava/lang/String;)Lcom/tencent/mm/ah/k$b;
    //   3376: astore_3
    //   3377: aload_3
    //   3378: ifnull +42 -> 3420
    //   3381: aload_3
    //   3382: ldc_w 603
    //   3385: invokevirtual 594	com/tencent/mm/ah/k$b:ao	(Ljava/lang/Class;)Lcom/tencent/mm/ah/f;
    //   3388: checkcast 603	com/tencent/mm/ui/chatting/viewitems/k$a
    //   3391: astore_0
    //   3392: aload_0
    //   3393: getfield 606	com/tencent/mm/ui/chatting/viewitems/k$a:state	I
    //   3396: iconst_1
    //   3397: if_icmpne +41 -> 3438
    //   3400: aload 5
    //   3402: ldc_w 607
    //   3405: iconst_1
    //   3406: anewarray 4	java/lang/Object
    //   3409: dup
    //   3410: iconst_0
    //   3411: aload_0
    //   3412: getfield 610	com/tencent/mm/ui/chatting/viewitems/k$a:appName	Ljava/lang/String;
    //   3415: aastore
    //   3416: invokevirtual 159	android/content/Context:getString	(I[Ljava/lang/Object;)Ljava/lang/String;
    //   3419: astore_0
    //   3420: aload 6
    //   3422: aload_0
    //   3423: putfield 147	com/tencent/mm/pointers/PString:value	Ljava/lang/String;
    //   3426: ldc 26
    //   3428: astore_3
    //   3429: aconst_null
    //   3430: astore 18
    //   3432: iconst_0
    //   3433: istore 13
    //   3435: goto -2600 -> 835
    //   3438: aload 5
    //   3440: ldc_w 611
    //   3443: iconst_1
    //   3444: anewarray 4	java/lang/Object
    //   3447: dup
    //   3448: iconst_0
    //   3449: aload_0
    //   3450: getfield 610	com/tencent/mm/ui/chatting/viewitems/k$a:appName	Ljava/lang/String;
    //   3453: aastore
    //   3454: invokevirtual 159	android/content/Context:getString	(I[Ljava/lang/Object;)Ljava/lang/String;
    //   3457: astore_0
    //   3458: goto -38 -> 3420
    //   3461: aload 21
    //   3463: invokestatic 543	com/tencent/mm/sdk/platformtools/bs:aLx	(Ljava/lang/String;)Ljava/lang/String;
    //   3466: invokestatic 549	com/tencent/mm/ah/k$b:vA	(Ljava/lang/String;)Lcom/tencent/mm/ah/k$b;
    //   3469: getfield 552	com/tencent/mm/ah/k$b:hie	I
    //   3472: lookupswitch	default:+28->3500, 10000:+110->3582, 20000:+122->3594
    //   3501: iconst_2
    //   3502: ldc_w 612
    //   3505: invokevirtual 169	android/content/Context:getString	(I)Ljava/lang/String;
    //   3508: astore_0
    //   3509: aload 19
    //   3511: invokevirtual 46	java/lang/String:length	()I
    //   3514: ifle +92 -> 3606
    //   3517: new 152	java/lang/StringBuilder
    //   3520: dup
    //   3521: invokespecial 153	java/lang/StringBuilder:<init>	()V
    //   3524: aload 19
    //   3526: invokevirtual 163	java/lang/StringBuilder:append	(Ljava/lang/String;)Ljava/lang/StringBuilder;
    //   3529: ldc_w 427
    //   3532: invokevirtual 163	java/lang/StringBuilder:append	(Ljava/lang/String;)Ljava/lang/StringBuilder;
    //   3535: invokevirtual 167	java/lang/StringBuilder:toString	()Ljava/lang/String;
    //   3538: astore_3
    //   3539: aload_2
    //   3540: invokestatic 401	com/tencent/mm/model/w:xg	(Ljava/lang/String;)Z
    //   3543: ifne +15 -> 3558
    //   3546: iload 14
    //   3548: ifne +10 -> 3558
    //   3551: aload 7
    //   3553: aload 19
    //   3555: putfield 147	com/tencent/mm/pointers/PString:value	Ljava/lang/String;
    //   3558: aload 6
    //   3560: ldc 26
    //   3562: putfield 147	com/tencent/mm/pointers/PString:value	Ljava/lang/String;
    //   3565: aload_0
    //   3566: astore 21
    //   3568: aconst_null
    //   3569: astore 18
    //   3571: iconst_0
    //   3572: istore 13
    //   3574: aload_3
    //   3575: astore_0
    //   3576: aload 21
    //   3578: astore_3
    //   3579: goto -2744 -> 835
    //   3582: aload 5
    //   3584: ldc_w 613
    //   3587: invokevirtual 169	android/content/Context:getString	(I)Ljava/lang/String;
    //   3590: astore_0
    //   3591: goto -82 -> 3509
    //   3594: aload 5
    //   3596: ldc_w 614
    //   3599: invokevirtual 169	android/content/Context:getString	(I)Ljava/lang/String;
    //   3602: astore_0
    //   3603: goto -94 -> 3509
    //   3606: ldc 26
    //   3608: astore_3
    //   3609: goto -70 -> 3539
    //   3612: aload 21
    //   3614: invokestatic 543	com/tencent/mm/sdk/platformtools/bs:aLx	(Ljava/lang/String;)Ljava/lang/String;
    //   3617: invokestatic 549	com/tencent/mm/ah/k$b:vA	(Ljava/lang/String;)Lcom/tencent/mm/ah/k$b;
    //   3620: astore_3
    //   3621: aload_3
    //   3622: ifnonnull +21 -> 3643
    //   3625: ldc_w 616
    //   3628: ldc_w 618
    //   3631: invokestatic 624	com/tencent/mm/sdk/platformtools/ac:e	(Ljava/lang/String;Ljava/lang/String;)V
    //   3634: ldc_w 360
    //   3637: invokestatic 53	com/tencent/matrix/trace/core/AppMethodBeat:o	(I)V
    //   3640: ldc 26
    //   3642: areturn
    //   3643: ldc 26
    //   3645: astore 21
    //   3647: aload 5
    //   3649: ldc_w 625
    //   3652: invokevirtual 169	android/content/Context:getString	(I)Ljava/lang/String;
    //   3655: astore 18
    //   3657: aload 19
    //   3659: invokevirtual 46	java/lang/String:length	()I
    //   3662: ifle +108 -> 3770
    //   3665: new 152	java/lang/StringBuilder
    //   3668: dup
    //   3669: invokespecial 153	java/lang/StringBuilder:<init>	()V
    //   3672: aload 19
    //   3674: invokevirtual 163	java/lang/StringBuilder:append	(Ljava/lang/String;)Ljava/lang/StringBuilder;
    //   3677: ldc_w 427
    //   3680: invokevirtual 163	java/lang/StringBuilder:append	(Ljava/lang/String;)Ljava/lang/StringBuilder;
    //   3683: aload 18
    //   3685: invokevirtual 163	java/lang/StringBuilder:append	(Ljava/lang/String;)Ljava/lang/StringBuilder;
    //   3688: aload_3
    //   3689: getfield 560	com/tencent/mm/ah/k$b:title	Ljava/lang/String;
    //   3692: invokevirtual 163	java/lang/StringBuilder:append	(Ljava/lang/String;)Ljava/lang/StringBuilder;
    //   3695: invokevirtual 167	java/lang/StringBuilder:toString	()Ljava/lang/String;
    //   3698: astore_0
    //   3699: aload_2
    //   3700: invokestatic 401	com/tencent/mm/model/w:xg	(Ljava/lang/String;)Z
    //   3703: ifne +15 -> 3718
    //   3706: iload 14
    //   3708: ifne +10 -> 3718
    //   3711: aload 7
    //   3713: aload 19
    //   3715: putfield 147	com/tencent/mm/pointers/PString:value	Ljava/lang/String;
    //   3718: aload 19
    //   3720: invokevirtual 46	java/lang/String:length	()I
    //   3723: ifle +73 -> 3796
    //   3726: new 152	java/lang/StringBuilder
    //   3729: dup
    //   3730: ldc_w 429
    //   3733: invokespecial 575	java/lang/StringBuilder:<init>	(Ljava/lang/String;)V
    //   3736: aload 18
    //   3738: invokevirtual 163	java/lang/StringBuilder:append	(Ljava/lang/String;)Ljava/lang/StringBuilder;
    //   3741: aload_3
    //   3742: getfield 560	com/tencent/mm/ah/k$b:title	Ljava/lang/String;
    //   3745: invokevirtual 163	java/lang/StringBuilder:append	(Ljava/lang/String;)Ljava/lang/StringBuilder;
    //   3748: invokevirtual 167	java/lang/StringBuilder:toString	()Ljava/lang/String;
    //   3751: astore_3
    //   3752: aload 6
    //   3754: aload_3
    //   3755: putfield 147	com/tencent/mm/pointers/PString:value	Ljava/lang/String;
    //   3758: aconst_null
    //   3759: astore 18
    //   3761: iconst_0
    //   3762: istore 13
    //   3764: aload 21
    //   3766: astore_3
    //   3767: goto -2932 -> 835
    //   3770: new 152	java/lang/StringBuilder
    //   3773: dup
    //   3774: invokespecial 153	java/lang/StringBuilder:<init>	()V
    //   3777: aload 18
    //   3779: invokevirtual 163	java/lang/StringBuilder:append	(Ljava/lang/String;)Ljava/lang/StringBuilder;
    //   3782: aload_3
    //   3783: getfield 560	com/tencent/mm/ah/k$b:title	Ljava/lang/String;
    //   3786: invokevirtual 163	java/lang/StringBuilder:append	(Ljava/lang/String;)Ljava/lang/StringBuilder;
    //   3789: invokevirtual 167	java/lang/StringBuilder:toString	()Ljava/lang/String;
    //   3792: astore_0
    //   3793: goto -94 -> 3699
    //   3796: new 152	java/lang/StringBuilder
    //   3799: dup
    //   3800: invokespecial 153	java/lang/StringBuilder:<init>	()V
    //   3803: aload 18
    //   3805: invokevirtual 163	java/lang/StringBuilder:append	(Ljava/lang/String;)Ljava/lang/StringBuilder;
    //   3808: aload_3
    //   3809: getfield 560	com/tencent/mm/ah/k$b:title	Ljava/lang/String;
    //   3812: invokevirtual 163	java/lang/StringBuilder:append	(Ljava/lang/String;)Ljava/lang/StringBuilder;
    //   3815: invokevirtual 167	java/lang/StringBuilder:toString	()Ljava/lang/String;
    //   3818: astore_3
    //   3819: goto -67 -> 3752
    //   3822: aload 21
    //   3824: invokestatic 543	com/tencent/mm/sdk/platformtools/bs:aLx	(Ljava/lang/String;)Ljava/lang/String;
    //   3827: invokestatic 549	com/tencent/mm/ah/k$b:vA	(Ljava/lang/String;)Lcom/tencent/mm/ah/k$b;
    //   3830: astore_0
    //   3831: aload_0
    //   3832: ifnonnull +21 -> 3853
    //   3835: ldc_w 616
    //   3838: ldc_w 618
    //   3841: invokestatic 624	com/tencent/mm/sdk/platformtools/ac:e	(Ljava/lang/String;Ljava/lang/String;)V
    //   3844: ldc_w 360
    //   3847: invokestatic 53	com/tencent/matrix/trace/core/AppMethodBeat:o	(I)V
    //   3850: ldc 26
    //   3852: areturn
    //   3853: ldc 26
    //   3855: astore 21
    //   3857: aload 5
    //   3859: ldc_w 625
    //   3862: invokevirtual 169	android/content/Context:getString	(I)Ljava/lang/String;
    //   3865: astore_3
    //   3866: iload_1
    //   3867: iconst_1
    //   3868: if_icmpne +95 -> 3963
    //   3871: new 152	java/lang/StringBuilder
    //   3874: dup
    //   3875: invokespecial 153	java/lang/StringBuilder:<init>	()V
    //   3878: aload_3
    //   3879: invokevirtual 163	java/lang/StringBuilder:append	(Ljava/lang/String;)Ljava/lang/StringBuilder;
    //   3882: aload_0
    //   3883: getfield 628	com/tencent/mm/ah/k$b:hiZ	Ljava/lang/String;
    //   3886: invokevirtual 163	java/lang/StringBuilder:append	(Ljava/lang/String;)Ljava/lang/StringBuilder;
    //   3889: invokevirtual 167	java/lang/StringBuilder:toString	()Ljava/lang/String;
    //   3892: astore_3
    //   3893: aload 19
    //   3895: invokevirtual 46	java/lang/String:length	()I
    //   3898: ifle +57 -> 3955
    //   3901: ldc_w 429
    //   3904: aload_3
    //   3905: invokestatic 631	java/lang/String:valueOf	(Ljava/lang/Object;)Ljava/lang/String;
    //   3908: invokevirtual 634	java/lang/String:concat	(Ljava/lang/String;)Ljava/lang/String;
    //   3911: astore_0
    //   3912: aload 6
    //   3914: aload_0
    //   3915: putfield 147	com/tencent/mm/pointers/PString:value	Ljava/lang/String;
    //   3918: aload_3
    //   3919: astore_0
    //   3920: aload_2
    //   3921: invokestatic 401	com/tencent/mm/model/w:xg	(Ljava/lang/String;)Z
    //   3924: ifne +5191 -> 9115
    //   3927: aload_3
    //   3928: astore_0
    //   3929: iload 14
    //   3931: ifne +5184 -> 9115
    //   3934: aload 7
    //   3936: aload 19
    //   3938: putfield 147	com/tencent/mm/pointers/PString:value	Ljava/lang/String;
    //   3941: aconst_null
    //   3942: astore 18
    //   3944: iconst_0
    //   3945: istore 13
    //   3947: aload_3
    //   3948: astore_0
    //   3949: aload 21
    //   3951: astore_3
    //   3952: goto -3117 -> 835
    //   3955: aload_3
    //   3956: invokestatic 631	java/lang/String:valueOf	(Ljava/lang/Object;)Ljava/lang/String;
    //   3959: astore_0
    //   3960: goto -48 -> 3912
    //   3963: new 152	java/lang/StringBuilder
    //   3966: dup
    //   3967: invokespecial 153	java/lang/StringBuilder:<init>	()V
    //   3970: aload_3
    //   3971: invokevirtual 163	java/lang/StringBuilder:append	(Ljava/lang/String;)Ljava/lang/StringBuilder;
    //   3974: aload_0
    //   3975: getfield 637	com/tencent/mm/ah/k$b:hiY	Ljava/lang/String;
    //   3978: invokevirtual 163	java/lang/StringBuilder:append	(Ljava/lang/String;)Ljava/lang/StringBuilder;
    //   3981: invokevirtual 167	java/lang/StringBuilder:toString	()Ljava/lang/String;
    //   3984: astore_3
    //   3985: aload 19
    //   3987: invokevirtual 46	java/lang/String:length	()I
    //   3990: ifle +23 -> 4013
    //   3993: ldc_w 429
    //   3996: aload_3
    //   3997: invokestatic 631	java/lang/String:valueOf	(Ljava/lang/Object;)Ljava/lang/String;
    //   4000: invokevirtual 634	java/lang/String:concat	(Ljava/lang/String;)Ljava/lang/String;
    //   4003: astore_0
    //   4004: aload 6
    //   4006: aload_0
    //   4007: putfield 147	com/tencent/mm/pointers/PString:value	Ljava/lang/String;
    //   4010: goto -92 -> 3918
    //   4013: aload_3
    //   4014: invokestatic 631	java/lang/String:valueOf	(Ljava/lang/Object;)Ljava/lang/String;
    //   4017: astore_0
    //   4018: goto -14 -> 4004
    //   4021: aload 21
    //   4023: invokestatic 543	com/tencent/mm/sdk/platformtools/bs:aLx	(Ljava/lang/String;)Ljava/lang/String;
    //   4026: invokestatic 549	com/tencent/mm/ah/k$b:vA	(Ljava/lang/String;)Lcom/tencent/mm/ah/k$b;
    //   4029: astore_3
    //   4030: aload_3
    //   4031: ifnonnull +21 -> 4052
    //   4034: ldc_w 616
    //   4037: ldc_w 618
    //   4040: invokestatic 624	com/tencent/mm/sdk/platformtools/ac:e	(Ljava/lang/String;Ljava/lang/String;)V
    //   4043: ldc_w 360
    //   4046: invokestatic 53	com/tencent/matrix/trace/core/AppMethodBeat:o	(I)V
    //   4049: ldc 26
    //   4051: areturn
    //   4052: ldc 26
    //   4054: astore 21
    //   4056: aload 19
    //   4058: invokevirtual 46	java/lang/String:length	()I
    //   4061: ifle +98 -> 4159
    //   4064: new 152	java/lang/StringBuilder
    //   4067: dup
    //   4068: invokespecial 153	java/lang/StringBuilder:<init>	()V
    //   4071: aload 19
    //   4073: invokevirtual 163	java/lang/StringBuilder:append	(Ljava/lang/String;)Ljava/lang/StringBuilder;
    //   4076: ldc_w 427
    //   4079: invokevirtual 163	java/lang/StringBuilder:append	(Ljava/lang/String;)Ljava/lang/StringBuilder;
    //   4082: aload_3
    //   4083: getfield 560	com/tencent/mm/ah/k$b:title	Ljava/lang/String;
    //   4086: invokevirtual 163	java/lang/StringBuilder:append	(Ljava/lang/String;)Ljava/lang/StringBuilder;
    //   4089: invokevirtual 167	java/lang/StringBuilder:toString	()Ljava/lang/String;
    //   4092: astore_0
    //   4093: aload_2
    //   4094: invokestatic 401	com/tencent/mm/model/w:xg	(Ljava/lang/String;)Z
    //   4097: ifne +15 -> 4112
    //   4100: iload 14
    //   4102: ifne +10 -> 4112
    //   4105: aload 7
    //   4107: aload 19
    //   4109: putfield 147	com/tencent/mm/pointers/PString:value	Ljava/lang/String;
    //   4112: aload 19
    //   4114: invokevirtual 46	java/lang/String:length	()I
    //   4117: ifle +50 -> 4167
    //   4120: new 152	java/lang/StringBuilder
    //   4123: dup
    //   4124: ldc_w 429
    //   4127: invokespecial 575	java/lang/StringBuilder:<init>	(Ljava/lang/String;)V
    //   4130: aload_3
    //   4131: getfield 560	com/tencent/mm/ah/k$b:title	Ljava/lang/String;
    //   4134: invokevirtual 163	java/lang/StringBuilder:append	(Ljava/lang/String;)Ljava/lang/StringBuilder;
    //   4137: invokevirtual 167	java/lang/StringBuilder:toString	()Ljava/lang/String;
    //   4140: astore_3
    //   4141: aload 6
    //   4143: aload_3
    //   4144: putfield 147	com/tencent/mm/pointers/PString:value	Ljava/lang/String;
    //   4147: aconst_null
    //   4148: astore 18
    //   4150: iconst_0
    //   4151: istore 13
    //   4153: aload 21
    //   4155: astore_3
    //   4156: goto -3321 -> 835
    //   4159: aload_3
    //   4160: getfield 560	com/tencent/mm/ah/k$b:title	Ljava/lang/String;
    //   4163: astore_0
    //   4164: goto -71 -> 4093
    //   4167: aload_3
    //   4168: getfield 560	com/tencent/mm/ah/k$b:title	Ljava/lang/String;
    //   4171: astore_3
    //   4172: goto -31 -> 4141
    //   4175: aload 5
    //   4177: ldc_w 638
    //   4180: invokevirtual 169	android/content/Context:getString	(I)Ljava/lang/String;
    //   4183: astore 21
    //   4185: aload 19
    //   4187: invokevirtual 46	java/lang/String:length	()I
    //   4190: ifle +74 -> 4264
    //   4193: new 152	java/lang/StringBuilder
    //   4196: dup
    //   4197: invokespecial 153	java/lang/StringBuilder:<init>	()V
    //   4200: aload 19
    //   4202: invokevirtual 163	java/lang/StringBuilder:append	(Ljava/lang/String;)Ljava/lang/StringBuilder;
    //   4205: ldc_w 427
    //   4208: invokevirtual 163	java/lang/StringBuilder:append	(Ljava/lang/String;)Ljava/lang/StringBuilder;
    //   4211: invokevirtual 167	java/lang/StringBuilder:toString	()Ljava/lang/String;
    //   4214: astore_0
    //   4215: aload_2
    //   4216: invokestatic 401	com/tencent/mm/model/w:xg	(Ljava/lang/String;)Z
    //   4219: ifne +15 -> 4234
    //   4222: iload 14
    //   4224: ifne +10 -> 4234
    //   4227: aload 7
    //   4229: aload 19
    //   4231: putfield 147	com/tencent/mm/pointers/PString:value	Ljava/lang/String;
    //   4234: aload 19
    //   4236: invokevirtual 46	java/lang/String:length	()I
    //   4239: ifle +31 -> 4270
    //   4242: ldc_w 429
    //   4245: astore_3
    //   4246: aload 6
    //   4248: aload_3
    //   4249: putfield 147	com/tencent/mm/pointers/PString:value	Ljava/lang/String;
    //   4252: aconst_null
    //   4253: astore 18
    //   4255: iconst_0
    //   4256: istore 13
    //   4258: aload 21
    //   4260: astore_3
    //   4261: goto -3426 -> 835
    //   4264: ldc 26
    //   4266: astore_0
    //   4267: goto -52 -> 4215
    //   4270: ldc 26
    //   4272: astore_3
    //   4273: goto -27 -> 4246
    //   4276: aload 21
    //   4278: invokestatic 543	com/tencent/mm/sdk/platformtools/bs:aLx	(Ljava/lang/String;)Ljava/lang/String;
    //   4281: invokestatic 549	com/tencent/mm/ah/k$b:vA	(Ljava/lang/String;)Lcom/tencent/mm/ah/k$b;
    //   4284: astore_0
    //   4285: aload_0
    //   4286: ifnonnull +21 -> 4307
    //   4289: ldc_w 616
    //   4292: ldc_w 618
    //   4295: invokestatic 624	com/tencent/mm/sdk/platformtools/ac:e	(Ljava/lang/String;Ljava/lang/String;)V
    //   4298: ldc_w 360
    //   4301: invokestatic 53	com/tencent/matrix/trace/core/AppMethodBeat:o	(I)V
    //   4304: ldc 26
    //   4306: areturn
    //   4307: ldc 26
    //   4309: astore 21
    //   4311: aload_0
    //   4312: getfield 641	com/tencent/mm/ah/k$b:content	Ljava/lang/String;
    //   4315: ldc_w 643
    //   4318: invokestatic 648	java/net/URLDecoder:decode	(Ljava/lang/String;Ljava/lang/String;)Ljava/lang/String;
    //   4321: astore_0
    //   4322: aload_0
    //   4323: astore_3
    //   4324: aload_0
    //   4325: invokestatic 204	com/tencent/mm/pluginsdk/ui/span/k:aHF	(Ljava/lang/String;)Ljava/lang/String;
    //   4328: astore_0
    //   4329: aload_2
    //   4330: invokestatic 401	com/tencent/mm/model/w:xg	(Ljava/lang/String;)Z
    //   4333: ifne +15 -> 4348
    //   4336: iload 14
    //   4338: ifne +10 -> 4348
    //   4341: aload 7
    //   4343: aload 19
    //   4345: putfield 147	com/tencent/mm/pointers/PString:value	Ljava/lang/String;
    //   4348: aload 19
    //   4350: invokevirtual 46	java/lang/String:length	()I
    //   4353: ifle +53 -> 4406
    //   4356: ldc_w 429
    //   4359: aload_0
    //   4360: invokestatic 631	java/lang/String:valueOf	(Ljava/lang/Object;)Ljava/lang/String;
    //   4363: invokevirtual 634	java/lang/String:concat	(Ljava/lang/String;)Ljava/lang/String;
    //   4366: astore_3
    //   4367: aload 6
    //   4369: aload_3
    //   4370: putfield 147	com/tencent/mm/pointers/PString:value	Ljava/lang/String;
    //   4373: aconst_null
    //   4374: astore 18
    //   4376: iconst_0
    //   4377: istore 13
    //   4379: aload 21
    //   4381: astore_3
    //   4382: goto -3547 -> 835
    //   4385: astore 18
    //   4387: aload_3
    //   4388: astore_0
    //   4389: ldc_w 616
    //   4392: aload 18
    //   4394: ldc 26
    //   4396: iconst_0
    //   4397: anewarray 4	java/lang/Object
    //   4400: invokestatic 652	com/tencent/mm/sdk/platformtools/ac:printErrStackTrace	(Ljava/lang/String;Ljava/lang/Throwable;Ljava/lang/String;[Ljava/lang/Object;)V
    //   4403: goto -74 -> 4329
    //   4406: aload_0
    //   4407: astore_3
    //   4408: goto -41 -> 4367
    //   4411: ldc 26
    //   4413: astore 22
    //   4415: aload 21
    //   4417: invokestatic 543	com/tencent/mm/sdk/platformtools/bs:aLx	(Ljava/lang/String;)Ljava/lang/String;
    //   4420: invokestatic 549	com/tencent/mm/ah/k$b:vA	(Ljava/lang/String;)Lcom/tencent/mm/ah/k$b;
    //   4423: astore_3
    //   4424: aload_3
    //   4425: ifnonnull +21 -> 4446
    //   4428: ldc_w 616
    //   4431: ldc_w 618
    //   4434: invokestatic 624	com/tencent/mm/sdk/platformtools/ac:e	(Ljava/lang/String;Ljava/lang/String;)V
    //   4437: ldc_w 360
    //   4440: invokestatic 53	com/tencent/matrix/trace/core/AppMethodBeat:o	(I)V
    //   4443: ldc 26
    //   4445: areturn
    //   4446: aload_2
    //   4447: invokestatic 401	com/tencent/mm/model/w:xg	(Ljava/lang/String;)Z
    //   4450: ifne +15 -> 4465
    //   4453: iload 14
    //   4455: ifne +10 -> 4465
    //   4458: aload 7
    //   4460: aload 19
    //   4462: putfield 147	com/tencent/mm/pointers/PString:value	Ljava/lang/String;
    //   4465: aload 5
    //   4467: ldc_w 653
    //   4470: invokevirtual 169	android/content/Context:getString	(I)Ljava/lang/String;
    //   4473: astore_0
    //   4474: aload_3
    //   4475: ldc_w 655
    //   4478: invokevirtual 594	com/tencent/mm/ah/k$b:ao	(Ljava/lang/Class;)Lcom/tencent/mm/ah/f;
    //   4481: checkcast 655	com/tencent/mm/plugin/i/a/b
    //   4484: astore_3
    //   4485: aload_3
    //   4486: ifnull +4664 -> 9150
    //   4489: aload_3
    //   4490: invokevirtual 659	com/tencent/mm/plugin/i/a/b:cGK	()Lcom/tencent/mm/protocal/protobuf/anx;
    //   4493: getfield 664	com/tencent/mm/protocal/protobuf/anx:nickname	Ljava/lang/String;
    //   4496: invokestatic 214	com/tencent/mm/sdk/platformtools/bs:isNullOrNil	(Ljava/lang/String;)Z
    //   4499: ifne +4651 -> 9150
    //   4502: new 152	java/lang/StringBuilder
    //   4505: dup
    //   4506: invokespecial 153	java/lang/StringBuilder:<init>	()V
    //   4509: aload_0
    //   4510: invokevirtual 163	java/lang/StringBuilder:append	(Ljava/lang/String;)Ljava/lang/StringBuilder;
    //   4513: aload 5
    //   4515: ldc_w 665
    //   4518: iconst_1
    //   4519: anewarray 4	java/lang/Object
    //   4522: dup
    //   4523: iconst_0
    //   4524: aload_3
    //   4525: invokevirtual 659	com/tencent/mm/plugin/i/a/b:cGK	()Lcom/tencent/mm/protocal/protobuf/anx;
    //   4528: getfield 664	com/tencent/mm/protocal/protobuf/anx:nickname	Ljava/lang/String;
    //   4531: aastore
    //   4532: invokevirtual 159	android/content/Context:getString	(I[Ljava/lang/Object;)Ljava/lang/String;
    //   4535: invokevirtual 163	java/lang/StringBuilder:append	(Ljava/lang/String;)Ljava/lang/StringBuilder;
    //   4538: invokevirtual 167	java/lang/StringBuilder:toString	()Ljava/lang/String;
    //   4541: astore_0
    //   4542: aload 19
    //   4544: invokevirtual 46	java/lang/String:length	()I
    //   4547: ifle +32 -> 4579
    //   4550: ldc_w 429
    //   4553: aload_0
    //   4554: invokestatic 631	java/lang/String:valueOf	(Ljava/lang/Object;)Ljava/lang/String;
    //   4557: invokevirtual 634	java/lang/String:concat	(Ljava/lang/String;)Ljava/lang/String;
    //   4560: astore_3
    //   4561: aload 6
    //   4563: aload_3
    //   4564: putfield 147	com/tencent/mm/pointers/PString:value	Ljava/lang/String;
    //   4567: aconst_null
    //   4568: astore 18
    //   4570: iconst_0
    //   4571: istore 13
    //   4573: aload 22
    //   4575: astore_3
    //   4576: goto -3741 -> 835
    //   4579: aload_0
    //   4580: astore_3
    //   4581: goto -20 -> 4561
    //   4584: ldc 26
    //   4586: astore 22
    //   4588: aload 21
    //   4590: invokestatic 543	com/tencent/mm/sdk/platformtools/bs:aLx	(Ljava/lang/String;)Ljava/lang/String;
    //   4593: invokestatic 549	com/tencent/mm/ah/k$b:vA	(Ljava/lang/String;)Lcom/tencent/mm/ah/k$b;
    //   4596: astore_3
    //   4597: aload_3
    //   4598: ifnonnull +21 -> 4619
    //   4601: ldc_w 616
    //   4604: ldc_w 618
    //   4607: invokestatic 624	com/tencent/mm/sdk/platformtools/ac:e	(Ljava/lang/String;Ljava/lang/String;)V
    //   4610: ldc_w 360
    //   4613: invokestatic 53	com/tencent/matrix/trace/core/AppMethodBeat:o	(I)V
    //   4616: ldc 26
    //   4618: areturn
    //   4619: aload_2
    //   4620: invokestatic 401	com/tencent/mm/model/w:xg	(Ljava/lang/String;)Z
    //   4623: ifne +15 -> 4638
    //   4626: iload 14
    //   4628: ifne +10 -> 4638
    //   4631: aload 7
    //   4633: aload 19
    //   4635: putfield 147	com/tencent/mm/pointers/PString:value	Ljava/lang/String;
    //   4638: aload 5
    //   4640: ldc_w 653
    //   4643: invokevirtual 169	android/content/Context:getString	(I)Ljava/lang/String;
    //   4646: astore_0
    //   4647: aload_3
    //   4648: ldc_w 667
    //   4651: invokevirtual 594	com/tencent/mm/ah/k$b:ao	(Ljava/lang/Class;)Lcom/tencent/mm/ah/f;
    //   4654: checkcast 667	com/tencent/mm/plugin/i/a/c
    //   4657: astore_3
    //   4658: aload_3
    //   4659: ifnull +4488 -> 9147
    //   4662: aload_3
    //   4663: invokevirtual 671	com/tencent/mm/plugin/i/a/c:cGL	()Lcom/tencent/mm/protocal/protobuf/any;
    //   4666: getfield 676	com/tencent/mm/protocal/protobuf/any:dol	Ljava/lang/String;
    //   4669: invokestatic 214	com/tencent/mm/sdk/platformtools/bs:isNullOrNil	(Ljava/lang/String;)Z
    //   4672: ifne +4475 -> 9147
    //   4675: aload_3
    //   4676: invokevirtual 671	com/tencent/mm/plugin/i/a/c:cGL	()Lcom/tencent/mm/protocal/protobuf/any;
    //   4679: getfield 679	com/tencent/mm/protocal/protobuf/any:rPI	I
    //   4682: iconst_1
    //   4683: if_icmpne +81 -> 4764
    //   4686: new 152	java/lang/StringBuilder
    //   4689: dup
    //   4690: invokespecial 153	java/lang/StringBuilder:<init>	()V
    //   4693: aload_0
    //   4694: invokevirtual 163	java/lang/StringBuilder:append	(Ljava/lang/String;)Ljava/lang/StringBuilder;
    //   4697: invokestatic 61	com/tencent/mm/sdk/platformtools/ai:getContext	()Landroid/content/Context;
    //   4700: ldc_w 680
    //   4703: iconst_1
    //   4704: anewarray 4	java/lang/Object
    //   4707: dup
    //   4708: iconst_0
    //   4709: aload_3
    //   4710: invokevirtual 671	com/tencent/mm/plugin/i/a/c:cGL	()Lcom/tencent/mm/protocal/protobuf/any;
    //   4713: getfield 676	com/tencent/mm/protocal/protobuf/any:dol	Ljava/lang/String;
    //   4716: aastore
    //   4717: invokevirtual 159	android/content/Context:getString	(I[Ljava/lang/Object;)Ljava/lang/String;
    //   4720: invokevirtual 163	java/lang/StringBuilder:append	(Ljava/lang/String;)Ljava/lang/StringBuilder;
    //   4723: invokevirtual 167	java/lang/StringBuilder:toString	()Ljava/lang/String;
    //   4726: astore_0
    //   4727: aload 19
    //   4729: invokevirtual 46	java/lang/String:length	()I
    //   4732: ifle +60 -> 4792
    //   4735: ldc_w 429
    //   4738: aload_0
    //   4739: invokestatic 631	java/lang/String:valueOf	(Ljava/lang/Object;)Ljava/lang/String;
    //   4742: invokevirtual 634	java/lang/String:concat	(Ljava/lang/String;)Ljava/lang/String;
    //   4745: astore_3
    //   4746: aload 6
    //   4748: aload_3
    //   4749: putfield 147	com/tencent/mm/pointers/PString:value	Ljava/lang/String;
    //   4752: aconst_null
    //   4753: astore 18
    //   4755: iconst_0
    //   4756: istore 13
    //   4758: aload 22
    //   4760: astore_3
    //   4761: goto -3926 -> 835
    //   4764: new 152	java/lang/StringBuilder
    //   4767: dup
    //   4768: invokespecial 153	java/lang/StringBuilder:<init>	()V
    //   4771: aload_0
    //   4772: invokevirtual 163	java/lang/StringBuilder:append	(Ljava/lang/String;)Ljava/lang/StringBuilder;
    //   4775: aload_3
    //   4776: invokevirtual 671	com/tencent/mm/plugin/i/a/c:cGL	()Lcom/tencent/mm/protocal/protobuf/any;
    //   4779: getfield 676	com/tencent/mm/protocal/protobuf/any:dol	Ljava/lang/String;
    //   4782: invokevirtual 163	java/lang/StringBuilder:append	(Ljava/lang/String;)Ljava/lang/StringBuilder;
    //   4785: invokevirtual 167	java/lang/StringBuilder:toString	()Ljava/lang/String;
    //   4788: astore_0
    //   4789: goto -62 -> 4727
    //   4792: aload_0
    //   4793: astore_3
    //   4794: goto -48 -> 4746
    //   4797: ldc 26
    //   4799: astore 22
    //   4801: aload 21
    //   4803: invokestatic 543	com/tencent/mm/sdk/platformtools/bs:aLx	(Ljava/lang/String;)Ljava/lang/String;
    //   4806: invokestatic 549	com/tencent/mm/ah/k$b:vA	(Ljava/lang/String;)Lcom/tencent/mm/ah/k$b;
    //   4809: astore_0
    //   4810: aload_0
    //   4811: ifnonnull +21 -> 4832
    //   4814: ldc_w 616
    //   4817: ldc_w 618
    //   4820: invokestatic 624	com/tencent/mm/sdk/platformtools/ac:e	(Ljava/lang/String;Ljava/lang/String;)V
    //   4823: ldc_w 360
    //   4826: invokestatic 53	com/tencent/matrix/trace/core/AppMethodBeat:o	(I)V
    //   4829: ldc 26
    //   4831: areturn
    //   4832: aload_0
    //   4833: ldc_w 682
    //   4836: invokevirtual 594	com/tencent/mm/ah/k$b:ao	(Ljava/lang/Class;)Lcom/tencent/mm/ah/f;
    //   4839: checkcast 682	com/tencent/mm/plugin/i/a/a
    //   4842: astore_0
    //   4843: aload_0
    //   4844: ifnull +4297 -> 9141
    //   4847: aload_0
    //   4848: invokevirtual 685	com/tencent/mm/plugin/i/a/a:Tn	()Ljava/lang/String;
    //   4851: invokestatic 214	com/tencent/mm/sdk/platformtools/bs:isNullOrNil	(Ljava/lang/String;)Z
    //   4854: ifne +4287 -> 9141
    //   4857: iload_1
    //   4858: iconst_1
    //   4859: if_icmpne +60 -> 4919
    //   4862: aload 5
    //   4864: ldc_w 686
    //   4867: iconst_1
    //   4868: anewarray 4	java/lang/Object
    //   4871: dup
    //   4872: iconst_0
    //   4873: aload_0
    //   4874: invokevirtual 685	com/tencent/mm/plugin/i/a/a:Tn	()Ljava/lang/String;
    //   4877: aastore
    //   4878: invokevirtual 159	android/content/Context:getString	(I[Ljava/lang/Object;)Ljava/lang/String;
    //   4881: astore_0
    //   4882: aload 19
    //   4884: invokevirtual 46	java/lang/String:length	()I
    //   4887: ifle +80 -> 4967
    //   4890: ldc_w 429
    //   4893: aload_0
    //   4894: invokestatic 631	java/lang/String:valueOf	(Ljava/lang/Object;)Ljava/lang/String;
    //   4897: invokevirtual 634	java/lang/String:concat	(Ljava/lang/String;)Ljava/lang/String;
    //   4900: astore_3
    //   4901: aload 6
    //   4903: aload_3
    //   4904: putfield 147	com/tencent/mm/pointers/PString:value	Ljava/lang/String;
    //   4907: aconst_null
    //   4908: astore 18
    //   4910: iconst_0
    //   4911: istore 13
    //   4913: aload 22
    //   4915: astore_3
    //   4916: goto -4081 -> 835
    //   4919: aload 5
    //   4921: ldc_w 687
    //   4924: iconst_1
    //   4925: anewarray 4	java/lang/Object
    //   4928: dup
    //   4929: iconst_0
    //   4930: aload_0
    //   4931: invokevirtual 685	com/tencent/mm/plugin/i/a/a:Tn	()Ljava/lang/String;
    //   4934: aastore
    //   4935: invokevirtual 159	android/content/Context:getString	(I[Ljava/lang/Object;)Ljava/lang/String;
    //   4938: astore_3
    //   4939: aload_3
    //   4940: astore_0
    //   4941: aload_2
    //   4942: invokestatic 401	com/tencent/mm/model/w:xg	(Ljava/lang/String;)Z
    //   4945: ifne -63 -> 4882
    //   4948: aload_3
    //   4949: astore_0
    //   4950: iload 14
    //   4952: ifne -70 -> 4882
    //   4955: aload 7
    //   4957: aload 19
    //   4959: putfield 147	com/tencent/mm/pointers/PString:value	Ljava/lang/String;
    //   4962: aload_3
    //   4963: astore_0
    //   4964: goto -82 -> 4882
    //   4967: aload_0
    //   4968: astore_3
    //   4969: goto -68 -> 4901
    //   4972: new 152	java/lang/StringBuilder
    //   4975: dup
    //   4976: invokespecial 153	java/lang/StringBuilder:<init>	()V
    //   4979: aload 5
    //   4981: ldc_w 688
    //   4984: invokevirtual 169	android/content/Context:getString	(I)Ljava/lang/String;
    //   4987: invokevirtual 163	java/lang/StringBuilder:append	(Ljava/lang/String;)Ljava/lang/StringBuilder;
    //   4990: aload 5
    //   4992: ldc_w 689
    //   4995: invokevirtual 169	android/content/Context:getString	(I)Ljava/lang/String;
    //   4998: invokevirtual 163	java/lang/StringBuilder:append	(Ljava/lang/String;)Ljava/lang/StringBuilder;
    //   5001: invokevirtual 167	java/lang/StringBuilder:toString	()Ljava/lang/String;
    //   5004: astore_0
    //   5005: aload 6
    //   5007: aload_0
    //   5008: putfield 147	com/tencent/mm/pointers/PString:value	Ljava/lang/String;
    //   5011: ldc 26
    //   5013: astore_3
    //   5014: aconst_null
    //   5015: astore 18
    //   5017: iconst_0
    //   5018: istore 13
    //   5020: goto -4185 -> 835
    //   5023: ldc 26
    //   5025: astore 21
    //   5027: ldc_w 691
    //   5030: invokestatic 296	com/tencent/mm/kernel/g:ab	(Ljava/lang/Class;)Lcom/tencent/mm/kernel/c/a;
    //   5033: checkcast 691	com/tencent/mm/plugin/messenger/a/c
    //   5036: aload_3
    //   5037: invokeinterface 695 2 0
    //   5042: astore_0
    //   5043: aload_0
    //   5044: getfield 701	com/tencent/mm/protocal/protobuf/cdh:ulR	Ljava/util/LinkedList;
    //   5047: invokevirtual 706	java/util/LinkedList:size	()I
    //   5050: ifle +4077 -> 9127
    //   5053: aload 6
    //   5055: ldc_w 691
    //   5058: invokestatic 296	com/tencent/mm/kernel/g:ab	(Ljava/lang/Class;)Lcom/tencent/mm/kernel/c/a;
    //   5061: checkcast 691	com/tencent/mm/plugin/messenger/a/c
    //   5064: aload_0
    //   5065: getfield 701	com/tencent/mm/protocal/protobuf/cdh:ulR	Ljava/util/LinkedList;
    //   5068: invokevirtual 710	java/util/LinkedList:getLast	()Ljava/lang/Object;
    //   5071: checkcast 712	com/tencent/mm/protocal/protobuf/cdi
    //   5074: getfield 715	com/tencent/mm/protocal/protobuf/cdi:hlO	Ljava/lang/String;
    //   5077: aload_2
    //   5078: invokeinterface 718 3 0
    //   5083: putfield 147	com/tencent/mm/pointers/PString:value	Ljava/lang/String;
    //   5086: aconst_null
    //   5087: astore 18
    //   5089: iconst_0
    //   5090: istore 13
    //   5092: aload_3
    //   5093: astore_0
    //   5094: aload 21
    //   5096: astore_3
    //   5097: goto -4262 -> 835
    //   5100: aload 21
    //   5102: invokestatic 543	com/tencent/mm/sdk/platformtools/bs:aLx	(Ljava/lang/String;)Ljava/lang/String;
    //   5105: invokestatic 549	com/tencent/mm/ah/k$b:vA	(Ljava/lang/String;)Lcom/tencent/mm/ah/k$b;
    //   5108: astore_0
    //   5109: aload_0
    //   5110: ifnonnull +21 -> 5131
    //   5113: ldc_w 616
    //   5116: ldc_w 618
    //   5119: invokestatic 624	com/tencent/mm/sdk/platformtools/ac:e	(Ljava/lang/String;Ljava/lang/String;)V
    //   5122: ldc_w 360
    //   5125: invokestatic 53	com/tencent/matrix/trace/core/AppMethodBeat:o	(I)V
    //   5128: ldc 26
    //   5130: areturn
    //   5131: new 152	java/lang/StringBuilder
    //   5134: dup
    //   5135: invokespecial 153	java/lang/StringBuilder:<init>	()V
    //   5138: aload 5
    //   5140: ldc_w 719
    //   5143: invokevirtual 169	android/content/Context:getString	(I)Ljava/lang/String;
    //   5146: invokevirtual 163	java/lang/StringBuilder:append	(Ljava/lang/String;)Ljava/lang/StringBuilder;
    //   5149: aload_0
    //   5150: invokevirtual 720	com/tencent/mm/ah/k$b:getTitle	()Ljava/lang/String;
    //   5153: invokevirtual 163	java/lang/StringBuilder:append	(Ljava/lang/String;)Ljava/lang/StringBuilder;
    //   5156: invokevirtual 167	java/lang/StringBuilder:toString	()Ljava/lang/String;
    //   5159: astore_0
    //   5160: aload 6
    //   5162: aload_0
    //   5163: putfield 147	com/tencent/mm/pointers/PString:value	Ljava/lang/String;
    //   5166: ldc 26
    //   5168: astore_3
    //   5169: aconst_null
    //   5170: astore 18
    //   5172: iconst_0
    //   5173: istore 13
    //   5175: goto -4340 -> 835
    //   5178: aload 21
    //   5180: invokestatic 543	com/tencent/mm/sdk/platformtools/bs:aLx	(Ljava/lang/String;)Ljava/lang/String;
    //   5183: astore_0
    //   5184: aload_0
    //   5185: invokestatic 549	com/tencent/mm/ah/k$b:vA	(Ljava/lang/String;)Lcom/tencent/mm/ah/k$b;
    //   5188: astore 18
    //   5190: aload 18
    //   5192: ifnonnull +21 -> 5213
    //   5195: ldc_w 616
    //   5198: ldc_w 618
    //   5201: invokestatic 624	com/tencent/mm/sdk/platformtools/ac:e	(Ljava/lang/String;Ljava/lang/String;)V
    //   5204: ldc_w 360
    //   5207: invokestatic 53	com/tencent/matrix/trace/core/AppMethodBeat:o	(I)V
    //   5210: ldc 26
    //   5212: areturn
    //   5213: aload 18
    //   5215: getfield 723	com/tencent/mm/ah/k$b:type	I
    //   5218: tableswitch	default:+242 -> 5460, 1:+263->5481, 2:+390->5608, 3:+491->5709, 4:+596->5814, 5:+907->6125, 6:+701->5919, 7:+806->6024, 8:+1449->6667, 9:+242->5460, 10:+242->5460, 11:+242->5460, 12:+242->5460, 13:+242->5460, 14:+242->5460, 15:+1529->6747, 16:+2094->7312, 17:+1689->6907, 18:+242->5460, 19:+1816->7034, 20:+242->5460, 21:+242->5460, 22:+242->5460, 23:+242->5460, 24:+1917->7135, 25:+1609->6827, 26:+1529->6747, 27:+1529->6747, 28:+242->5460, 29:+242->5460, 30:+242->5460, 31:+242->5460, 32:+242->5460, 33:+1040->6258, 34:+2239->7457, 35:+242->5460, 36:+1040->6258, 37:+242->5460, 38:+242->5460, 39:+242->5460, 40:+2409->7627, 41:+242->5460, 42:+242->5460, 43:+242->5460, 44:+1225->6443, 45:+242->5460, 46:+1019->6237, 47:+242->5460, 48:+242->5460, 49:+242->5460, 50:+242->5460, 51:+242->5460, 52:+242->5460, 53:+263->5481, 54:+242->5460, 55:+242->5460, 56:+242->5460, 57:+263->5481
    //   5461: iconst_2
    //   5462: ldc_w 638
    //   5465: invokevirtual 169	android/content/Context:getString	(I)Ljava/lang/String;
    //   5468: astore_3
    //   5469: aconst_null
    //   5470: astore 18
    //   5472: iconst_0
    //   5473: istore 13
    //   5475: ldc 26
    //   5477: astore_0
    //   5478: goto -4643 -> 835
    //   5481: ldc 26
    //   5483: astore 21
    //   5485: aload 19
    //   5487: invokevirtual 46	java/lang/String:length	()I
    //   5490: ifle +100 -> 5590
    //   5493: new 152	java/lang/StringBuilder
    //   5496: dup
    //   5497: invokespecial 153	java/lang/StringBuilder:<init>	()V
    //   5500: aload 19
    //   5502: invokevirtual 163	java/lang/StringBuilder:append	(Ljava/lang/String;)Ljava/lang/StringBuilder;
    //   5505: ldc_w 427
    //   5508: invokevirtual 163	java/lang/StringBuilder:append	(Ljava/lang/String;)Ljava/lang/StringBuilder;
    //   5511: aload 18
    //   5513: getfield 560	com/tencent/mm/ah/k$b:title	Ljava/lang/String;
    //   5516: invokevirtual 163	java/lang/StringBuilder:append	(Ljava/lang/String;)Ljava/lang/StringBuilder;
    //   5519: invokevirtual 167	java/lang/StringBuilder:toString	()Ljava/lang/String;
    //   5522: astore_0
    //   5523: aload_2
    //   5524: invokestatic 401	com/tencent/mm/model/w:xg	(Ljava/lang/String;)Z
    //   5527: ifne +15 -> 5542
    //   5530: iload 14
    //   5532: ifne +10 -> 5542
    //   5535: aload 7
    //   5537: aload 19
    //   5539: putfield 147	com/tencent/mm/pointers/PString:value	Ljava/lang/String;
    //   5542: aload 19
    //   5544: invokevirtual 46	java/lang/String:length	()I
    //   5547: ifle +52 -> 5599
    //   5550: new 152	java/lang/StringBuilder
    //   5553: dup
    //   5554: ldc_w 429
    //   5557: invokespecial 575	java/lang/StringBuilder:<init>	(Ljava/lang/String;)V
    //   5560: aload 18
    //   5562: getfield 560	com/tencent/mm/ah/k$b:title	Ljava/lang/String;
    //   5565: invokevirtual 163	java/lang/StringBuilder:append	(Ljava/lang/String;)Ljava/lang/StringBuilder;
    //   5568: invokevirtual 167	java/lang/StringBuilder:toString	()Ljava/lang/String;
    //   5571: astore_3
    //   5572: aload 6
    //   5574: aload_3
    //   5575: putfield 147	com/tencent/mm/pointers/PString:value	Ljava/lang/String;
    //   5578: aconst_null
    //   5579: astore 18
    //   5581: iconst_0
    //   5582: istore 13
    //   5584: aload 21
    //   5586: astore_3
    //   5587: goto -4752 -> 835
    //   5590: aload 18
    //   5592: getfield 560	com/tencent/mm/ah/k$b:title	Ljava/lang/String;
    //   5595: astore_0
    //   5596: goto -73 -> 5523
    //   5599: aload 18
    //   5601: getfield 560	com/tencent/mm/ah/k$b:title	Ljava/lang/String;
    //   5604: astore_3
    //   5605: goto -33 -> 5572
    //   5608: aload 5
    //   5610: ldc_w 425
    //   5613: invokevirtual 169	android/content/Context:getString	(I)Ljava/lang/String;
    //   5616: astore 21
    //   5618: aload 19
    //   5620: invokevirtual 46	java/lang/String:length	()I
    //   5623: ifle +74 -> 5697
    //   5626: new 152	java/lang/StringBuilder
    //   5629: dup
    //   5630: invokespecial 153	java/lang/StringBuilder:<init>	()V
    //   5633: aload 19
    //   5635: invokevirtual 163	java/lang/StringBuilder:append	(Ljava/lang/String;)Ljava/lang/StringBuilder;
    //   5638: ldc_w 427
    //   5641: invokevirtual 163	java/lang/StringBuilder:append	(Ljava/lang/String;)Ljava/lang/StringBuilder;
    //   5644: invokevirtual 167	java/lang/StringBuilder:toString	()Ljava/lang/String;
    //   5647: astore_0
    //   5648: aload_2
    //   5649: invokestatic 401	com/tencent/mm/model/w:xg	(Ljava/lang/String;)Z
    //   5652: ifne +15 -> 5667
    //   5655: iload 14
    //   5657: ifne +10 -> 5667
    //   5660: aload 7
    //   5662: aload 19
    //   5664: putfield 147	com/tencent/mm/pointers/PString:value	Ljava/lang/String;
    //   5667: aload 19
    //   5669: invokevirtual 46	java/lang/String:length	()I
    //   5672: ifle +31 -> 5703
    //   5675: ldc_w 429
    //   5678: astore_3
    //   5679: aload 6
    //   5681: aload_3
    //   5682: putfield 147	com/tencent/mm/pointers/PString:value	Ljava/lang/String;
    //   5685: aconst_null
    //   5686: astore 18
    //   5688: iconst_0
    //   5689: istore 13
    //   5691: aload 21
    //   5693: astore_3
    //   5694: goto -4859 -> 835
    //   5697: ldc 26
    //   5699: astore_0
    //   5700: goto -52 -> 5648
    //   5703: ldc 26
    //   5705: astore_3
    //   5706: goto -27 -> 5679
    //   5709: aload 5
    //   5711: ldc_w 724
    //   5714: invokevirtual 169	android/content/Context:getString	(I)Ljava/lang/String;
    //   5717: astore 21
    //   5719: aload 19
    //   5721: invokevirtual 46	java/lang/String:length	()I
    //   5724: ifle +78 -> 5802
    //   5727: new 152	java/lang/StringBuilder
    //   5730: dup
    //   5731: invokespecial 153	java/lang/StringBuilder:<init>	()V
    //   5734: aload 19
    //   5736: invokevirtual 163	java/lang/StringBuilder:append	(Ljava/lang/String;)Ljava/lang/StringBuilder;
    //   5739: ldc_w 427
    //   5742: invokevirtual 163	java/lang/StringBuilder:append	(Ljava/lang/String;)Ljava/lang/StringBuilder;
    //   5745: invokevirtual 167	java/lang/StringBuilder:toString	()Ljava/lang/String;
    //   5748: astore_0
    //   5749: aload_2
    //   5750: invokestatic 401	com/tencent/mm/model/w:xg	(Ljava/lang/String;)Z
    //   5753: ifne +15 -> 5768
    //   5756: iload 14
    //   5758: ifne +10 -> 5768
    //   5761: aload 7
    //   5763: aload 19
    //   5765: putfield 147	com/tencent/mm/pointers/PString:value	Ljava/lang/String;
    //   5768: aload 19
    //   5770: invokevirtual 46	java/lang/String:length	()I
    //   5773: ifle +35 -> 5808
    //   5776: ldc_w 429
    //   5779: astore_3
    //   5780: aload 6
    //   5782: aload_3
    //   5783: putfield 147	com/tencent/mm/pointers/PString:value	Ljava/lang/String;
    //   5786: aload 18
    //   5788: getfield 560	com/tencent/mm/ah/k$b:title	Ljava/lang/String;
    //   5791: astore 18
    //   5793: iconst_1
    //   5794: istore 13
    //   5796: aload 21
    //   5798: astore_3
    //   5799: goto -4964 -> 835
    //   5802: ldc 26
    //   5804: astore_0
    //   5805: goto -56 -> 5749
    //   5808: ldc 26
    //   5810: astore_3
    //   5811: goto -31 -> 5780
    //   5814: aload 5
    //   5816: ldc_w 451
    //   5819: invokevirtual 169	android/content/Context:getString	(I)Ljava/lang/String;
    //   5822: astore 21
    //   5824: aload 19
    //   5826: invokevirtual 46	java/lang/String:length	()I
    //   5829: ifle +78 -> 5907
    //   5832: new 152	java/lang/StringBuilder
    //   5835: dup
    //   5836: invokespecial 153	java/lang/StringBuilder:<init>	()V
    //   5839: aload 19
    //   5841: invokevirtual 163	java/lang/StringBuilder:append	(Ljava/lang/String;)Ljava/lang/StringBuilder;
    //   5844: ldc_w 427
    //   5847: invokevirtual 163	java/lang/StringBuilder:append	(Ljava/lang/String;)Ljava/lang/StringBuilder;
    //   5850: invokevirtual 167	java/lang/StringBuilder:toString	()Ljava/lang/String;
    //   5853: astore_0
    //   5854: aload_2
    //   5855: invokestatic 401	com/tencent/mm/model/w:xg	(Ljava/lang/String;)Z
    //   5858: ifne +15 -> 5873
    //   5861: iload 14
    //   5863: ifne +10 -> 5873
    //   5866: aload 7
    //   5868: aload 19
    //   5870: putfield 147	com/tencent/mm/pointers/PString:value	Ljava/lang/String;
    //   5873: aload 19
    //   5875: invokevirtual 46	java/lang/String:length	()I
    //   5878: ifle +35 -> 5913
    //   5881: ldc_w 429
    //   5884: astore_3
    //   5885: aload 6
    //   5887: aload_3
    //   5888: putfield 147	com/tencent/mm/pointers/PString:value	Ljava/lang/String;
    //   5891: aload 18
    //   5893: getfield 560	com/tencent/mm/ah/k$b:title	Ljava/lang/String;
    //   5896: astore 18
    //   5898: iconst_1
    //   5899: istore 13
    //   5901: aload 21
    //   5903: astore_3
    //   5904: goto -5069 -> 835
    //   5907: ldc 26
    //   5909: astore_0
    //   5910: goto -56 -> 5854
    //   5913: ldc 26
    //   5915: astore_3
    //   5916: goto -31 -> 5885
    //   5919: aload 5
    //   5921: ldc_w 725
    //   5924: invokevirtual 169	android/content/Context:getString	(I)Ljava/lang/String;
    //   5927: astore 21
    //   5929: aload 19
    //   5931: invokevirtual 46	java/lang/String:length	()I
    //   5934: ifle +78 -> 6012
    //   5937: new 152	java/lang/StringBuilder
    //   5940: dup
    //   5941: invokespecial 153	java/lang/StringBuilder:<init>	()V
    //   5944: aload 19
    //   5946: invokevirtual 163	java/lang/StringBuilder:append	(Ljava/lang/String;)Ljava/lang/StringBuilder;
    //   5949: ldc_w 427
    //   5952: invokevirtual 163	java/lang/StringBuilder:append	(Ljava/lang/String;)Ljava/lang/StringBuilder;
    //   5955: invokevirtual 167	java/lang/StringBuilder:toString	()Ljava/lang/String;
    //   5958: astore_0
    //   5959: aload_2
    //   5960: invokestatic 401	com/tencent/mm/model/w:xg	(Ljava/lang/String;)Z
    //   5963: ifne +15 -> 5978
    //   5966: iload 14
    //   5968: ifne +10 -> 5978
    //   5971: aload 7
    //   5973: aload 19
    //   5975: putfield 147	com/tencent/mm/pointers/PString:value	Ljava/lang/String;
    //   5978: aload 19
    //   5980: invokevirtual 46	java/lang/String:length	()I
    //   5983: ifle +35 -> 6018
    //   5986: ldc_w 429
    //   5989: astore_3
    //   5990: aload 6
    //   5992: aload_3
    //   5993: putfield 147	com/tencent/mm/pointers/PString:value	Ljava/lang/String;
    //   5996: aload 18
    //   5998: getfield 560	com/tencent/mm/ah/k$b:title	Ljava/lang/String;
    //   6001: astore 18
    //   6003: iconst_1
    //   6004: istore 13
    //   6006: aload 21
    //   6008: astore_3
    //   6009: goto -5174 -> 835
    //   6012: ldc 26
    //   6014: astore_0
    //   6015: goto -56 -> 5959
    //   6018: ldc 26
    //   6020: astore_3
    //   6021: goto -31 -> 5990
    //   6024: aload 5
    //   6026: ldc_w 638
    //   6029: invokevirtual 169	android/content/Context:getString	(I)Ljava/lang/String;
    //   6032: astore 21
    //   6034: aload 19
    //   6036: invokevirtual 46	java/lang/String:length	()I
    //   6039: ifle +74 -> 6113
    //   6042: new 152	java/lang/StringBuilder
    //   6045: dup
    //   6046: invokespecial 153	java/lang/StringBuilder:<init>	()V
    //   6049: aload 19
    //   6051: invokevirtual 163	java/lang/StringBuilder:append	(Ljava/lang/String;)Ljava/lang/StringBuilder;
    //   6054: ldc_w 427
    //   6057: invokevirtual 163	java/lang/StringBuilder:append	(Ljava/lang/String;)Ljava/lang/StringBuilder;
    //   6060: invokevirtual 167	java/lang/StringBuilder:toString	()Ljava/lang/String;
    //   6063: astore_0
    //   6064: aload_2
    //   6065: invokestatic 401	com/tencent/mm/model/w:xg	(Ljava/lang/String;)Z
    //   6068: ifne +15 -> 6083
    //   6071: iload 14
    //   6073: ifne +10 -> 6083
    //   6076: aload 7
    //   6078: aload 19
    //   6080: putfield 147	com/tencent/mm/pointers/PString:value	Ljava/lang/String;
    //   6083: aload 19
    //   6085: invokevirtual 46	java/lang/String:length	()I
    //   6088: ifle +31 -> 6119
    //   6091: ldc_w 429
    //   6094: astore_3
    //   6095: aload 6
    //   6097: aload_3
    //   6098: putfield 147	com/tencent/mm/pointers/PString:value	Ljava/lang/String;
    //   6101: aconst_null
    //   6102: astore 18
    //   6104: iconst_0
    //   6105: istore 13
    //   6107: aload 21
    //   6109: astore_3
    //   6110: goto -5275 -> 835
    //   6113: ldc 26
    //   6115: astore_0
    //   6116: goto -52 -> 6064
    //   6119: ldc 26
    //   6121: astore_3
    //   6122: goto -27 -> 6095
    //   6125: aload 5
    //   6127: ldc_w 726
    //   6130: invokevirtual 169	android/content/Context:getString	(I)Ljava/lang/String;
    //   6133: astore 21
    //   6135: aload 19
    //   6137: invokevirtual 46	java/lang/String:length	()I
    //   6140: ifle +85 -> 6225
    //   6143: new 152	java/lang/StringBuilder
    //   6146: dup
    //   6147: invokespecial 153	java/lang/StringBuilder:<init>	()V
    //   6150: aload 19
    //   6152: invokevirtual 163	java/lang/StringBuilder:append	(Ljava/lang/String;)Ljava/lang/StringBuilder;
    //   6155: ldc_w 427
    //   6158: invokevirtual 163	java/lang/StringBuilder:append	(Ljava/lang/String;)Ljava/lang/StringBuilder;
    //   6161: invokevirtual 167	java/lang/StringBuilder:toString	()Ljava/lang/String;
    //   6164: astore_0
    //   6165: aload_2
    //   6166: invokestatic 401	com/tencent/mm/model/w:xg	(Ljava/lang/String;)Z
    //   6169: ifne +22 -> 6191
    //   6172: iload 14
    //   6174: ifne +17 -> 6191
    //   6177: aload_2
    //   6178: invokestatic 404	com/tencent/mm/model/w:xp	(Ljava/lang/String;)Z
    //   6181: ifne +10 -> 6191
    //   6184: aload 7
    //   6186: aload 19
    //   6188: putfield 147	com/tencent/mm/pointers/PString:value	Ljava/lang/String;
    //   6191: aload 19
    //   6193: invokevirtual 46	java/lang/String:length	()I
    //   6196: ifle +35 -> 6231
    //   6199: ldc_w 429
    //   6202: astore_3
    //   6203: aload 6
    //   6205: aload_3
    //   6206: putfield 147	com/tencent/mm/pointers/PString:value	Ljava/lang/String;
    //   6209: aload 18
    //   6211: invokevirtual 720	com/tencent/mm/ah/k$b:getTitle	()Ljava/lang/String;
    //   6214: astore 18
    //   6216: iconst_1
    //   6217: istore 13
    //   6219: aload 21
    //   6221: astore_3
    //   6222: goto -5387 -> 835
    //   6225: ldc 26
    //   6227: astore_0
    //   6228: goto -63 -> 6165
    //   6231: ldc 26
    //   6233: astore_3
    //   6234: goto -31 -> 6203
    //   6237: aload 5
    //   6239: ldc_w 638
    //   6242: invokevirtual 169	android/content/Context:getString	(I)Ljava/lang/String;
    //   6245: astore_3
    //   6246: aconst_null
    //   6247: astore 18
    //   6249: iconst_0
    //   6250: istore 13
    //   6252: ldc 26
    //   6254: astore_0
    //   6255: goto -5420 -> 835
    //   6258: ldc 26
    //   6260: astore 21
    //   6262: aload 5
    //   6264: ldc_w 727
    //   6267: invokevirtual 169	android/content/Context:getString	(I)Ljava/lang/String;
    //   6270: astore_3
    //   6271: aload 19
    //   6273: invokevirtual 46	java/lang/String:length	()I
    //   6276: ifle +115 -> 6391
    //   6279: new 152	java/lang/StringBuilder
    //   6282: dup
    //   6283: invokespecial 153	java/lang/StringBuilder:<init>	()V
    //   6286: aload 19
    //   6288: invokevirtual 163	java/lang/StringBuilder:append	(Ljava/lang/String;)Ljava/lang/StringBuilder;
    //   6291: ldc_w 427
    //   6294: invokevirtual 163	java/lang/StringBuilder:append	(Ljava/lang/String;)Ljava/lang/StringBuilder;
    //   6297: aload_3
    //   6298: invokevirtual 163	java/lang/StringBuilder:append	(Ljava/lang/String;)Ljava/lang/StringBuilder;
    //   6301: aload 18
    //   6303: getfield 560	com/tencent/mm/ah/k$b:title	Ljava/lang/String;
    //   6306: invokevirtual 163	java/lang/StringBuilder:append	(Ljava/lang/String;)Ljava/lang/StringBuilder;
    //   6309: invokevirtual 167	java/lang/StringBuilder:toString	()Ljava/lang/String;
    //   6312: astore_0
    //   6313: aload_2
    //   6314: invokestatic 401	com/tencent/mm/model/w:xg	(Ljava/lang/String;)Z
    //   6317: ifne +22 -> 6339
    //   6320: iload 14
    //   6322: ifne +17 -> 6339
    //   6325: aload_2
    //   6326: invokestatic 404	com/tencent/mm/model/w:xp	(Ljava/lang/String;)Z
    //   6329: ifne +10 -> 6339
    //   6332: aload 7
    //   6334: aload 19
    //   6336: putfield 147	com/tencent/mm/pointers/PString:value	Ljava/lang/String;
    //   6339: aload 19
    //   6341: invokevirtual 46	java/lang/String:length	()I
    //   6344: ifle +73 -> 6417
    //   6347: new 152	java/lang/StringBuilder
    //   6350: dup
    //   6351: ldc_w 429
    //   6354: invokespecial 575	java/lang/StringBuilder:<init>	(Ljava/lang/String;)V
    //   6357: aload_3
    //   6358: invokevirtual 163	java/lang/StringBuilder:append	(Ljava/lang/String;)Ljava/lang/StringBuilder;
    //   6361: aload 18
    //   6363: getfield 560	com/tencent/mm/ah/k$b:title	Ljava/lang/String;
    //   6366: invokevirtual 163	java/lang/StringBuilder:append	(Ljava/lang/String;)Ljava/lang/StringBuilder;
    //   6369: invokevirtual 167	java/lang/StringBuilder:toString	()Ljava/lang/String;
    //   6372: astore_3
    //   6373: aload 6
    //   6375: aload_3
    //   6376: putfield 147	com/tencent/mm/pointers/PString:value	Ljava/lang/String;
    //   6379: aconst_null
    //   6380: astore 18
    //   6382: iconst_0
    //   6383: istore 13
    //   6385: aload 21
    //   6387: astore_3
    //   6388: goto -5553 -> 835
    //   6391: new 152	java/lang/StringBuilder
    //   6394: dup
    //   6395: invokespecial 153	java/lang/StringBuilder:<init>	()V
    //   6398: aload_3
    //   6399: invokevirtual 163	java/lang/StringBuilder:append	(Ljava/lang/String;)Ljava/lang/StringBuilder;
    //   6402: aload 18
    //   6404: getfield 560	com/tencent/mm/ah/k$b:title	Ljava/lang/String;
    //   6407: invokevirtual 163	java/lang/StringBuilder:append	(Ljava/lang/String;)Ljava/lang/StringBuilder;
    //   6410: invokevirtual 167	java/lang/StringBuilder:toString	()Ljava/lang/String;
    //   6413: astore_0
    //   6414: goto -101 -> 6313
    //   6417: new 152	java/lang/StringBuilder
    //   6420: dup
    //   6421: invokespecial 153	java/lang/StringBuilder:<init>	()V
    //   6424: aload_3
    //   6425: invokevirtual 163	java/lang/StringBuilder:append	(Ljava/lang/String;)Ljava/lang/StringBuilder;
    //   6428: aload 18
    //   6430: getfield 560	com/tencent/mm/ah/k$b:title	Ljava/lang/String;
    //   6433: invokevirtual 163	java/lang/StringBuilder:append	(Ljava/lang/String;)Ljava/lang/StringBuilder;
    //   6436: invokevirtual 167	java/lang/StringBuilder:toString	()Ljava/lang/String;
    //   6439: astore_3
    //   6440: goto -67 -> 6373
    //   6443: aload 18
    //   6445: iconst_0
    //   6446: invokevirtual 731	com/tencent/mm/ah/k$b:et	(Z)Z
    //   6449: ifeq +197 -> 6646
    //   6452: ldc 26
    //   6454: astore 21
    //   6456: aload 18
    //   6458: aload 5
    //   6460: iconst_1
    //   6461: invokevirtual 735	com/tencent/mm/ah/k$b:r	(Landroid/content/Context;Z)Ljava/lang/String;
    //   6464: astore_3
    //   6465: aload_3
    //   6466: invokestatic 214	com/tencent/mm/sdk/platformtools/bs:isNullOrNil	(Ljava/lang/String;)Z
    //   6469: ifne +156 -> 6625
    //   6472: aload 19
    //   6474: invokevirtual 46	java/lang/String:length	()I
    //   6477: ifle +96 -> 6573
    //   6480: new 152	java/lang/StringBuilder
    //   6483: dup
    //   6484: invokespecial 153	java/lang/StringBuilder:<init>	()V
    //   6487: aload 19
    //   6489: invokevirtual 163	java/lang/StringBuilder:append	(Ljava/lang/String;)Ljava/lang/StringBuilder;
    //   6492: ldc_w 427
    //   6495: invokevirtual 163	java/lang/StringBuilder:append	(Ljava/lang/String;)Ljava/lang/StringBuilder;
    //   6498: aload_3
    //   6499: invokevirtual 163	java/lang/StringBuilder:append	(Ljava/lang/String;)Ljava/lang/StringBuilder;
    //   6502: aload 18
    //   6504: getfield 560	com/tencent/mm/ah/k$b:title	Ljava/lang/String;
    //   6507: invokevirtual 163	java/lang/StringBuilder:append	(Ljava/lang/String;)Ljava/lang/StringBuilder;
    //   6510: invokevirtual 167	java/lang/StringBuilder:toString	()Ljava/lang/String;
    //   6513: astore_0
    //   6514: aload 7
    //   6516: aload 19
    //   6518: putfield 147	com/tencent/mm/pointers/PString:value	Ljava/lang/String;
    //   6521: aload 19
    //   6523: invokevirtual 46	java/lang/String:length	()I
    //   6526: ifle +73 -> 6599
    //   6529: new 152	java/lang/StringBuilder
    //   6532: dup
    //   6533: ldc_w 429
    //   6536: invokespecial 575	java/lang/StringBuilder:<init>	(Ljava/lang/String;)V
    //   6539: aload_3
    //   6540: invokevirtual 163	java/lang/StringBuilder:append	(Ljava/lang/String;)Ljava/lang/StringBuilder;
    //   6543: aload 18
    //   6545: getfield 560	com/tencent/mm/ah/k$b:title	Ljava/lang/String;
    //   6548: invokevirtual 163	java/lang/StringBuilder:append	(Ljava/lang/String;)Ljava/lang/StringBuilder;
    //   6551: invokevirtual 167	java/lang/StringBuilder:toString	()Ljava/lang/String;
    //   6554: astore_3
    //   6555: aload 6
    //   6557: aload_3
    //   6558: putfield 147	com/tencent/mm/pointers/PString:value	Ljava/lang/String;
    //   6561: aconst_null
    //   6562: astore 18
    //   6564: iconst_0
    //   6565: istore 13
    //   6567: aload 21
    //   6569: astore_3
    //   6570: goto -5735 -> 835
    //   6573: new 152	java/lang/StringBuilder
    //   6576: dup
    //   6577: invokespecial 153	java/lang/StringBuilder:<init>	()V
    //   6580: aload_3
    //   6581: invokevirtual 163	java/lang/StringBuilder:append	(Ljava/lang/String;)Ljava/lang/StringBuilder;
    //   6584: aload 18
    //   6586: getfield 560	com/tencent/mm/ah/k$b:title	Ljava/lang/String;
    //   6589: invokevirtual 163	java/lang/StringBuilder:append	(Ljava/lang/String;)Ljava/lang/StringBuilder;
    //   6592: invokevirtual 167	java/lang/StringBuilder:toString	()Ljava/lang/String;
    //   6595: astore_0
    //   6596: goto -82 -> 6514
    //   6599: new 152	java/lang/StringBuilder
    //   6602: dup
    //   6603: invokespecial 153	java/lang/StringBuilder:<init>	()V
    //   6606: aload_3
    //   6607: invokevirtual 163	java/lang/StringBuilder:append	(Ljava/lang/String;)Ljava/lang/StringBuilder;
    //   6610: aload 18
    //   6612: getfield 560	com/tencent/mm/ah/k$b:title	Ljava/lang/String;
    //   6615: invokevirtual 163	java/lang/StringBuilder:append	(Ljava/lang/String;)Ljava/lang/StringBuilder;
    //   6618: invokevirtual 167	java/lang/StringBuilder:toString	()Ljava/lang/String;
    //   6621: astore_3
    //   6622: goto -67 -> 6555
    //   6625: aload 5
    //   6627: ldc_w 638
    //   6630: invokevirtual 169	android/content/Context:getString	(I)Ljava/lang/String;
    //   6633: astore_3
    //   6634: aconst_null
    //   6635: astore 18
    //   6637: iconst_0
    //   6638: istore 13
    //   6640: ldc 26
    //   6642: astore_0
    //   6643: goto -5808 -> 835
    //   6646: aload 5
    //   6648: ldc_w 638
    //   6651: invokevirtual 169	android/content/Context:getString	(I)Ljava/lang/String;
    //   6654: astore_3
    //   6655: aconst_null
    //   6656: astore 18
    //   6658: iconst_0
    //   6659: istore 13
    //   6661: ldc 26
    //   6663: astore_0
    //   6664: goto -5829 -> 835
    //   6667: aload 5
    //   6669: ldc_w 736
    //   6672: invokevirtual 169	android/content/Context:getString	(I)Ljava/lang/String;
    //   6675: astore_3
    //   6676: aload 19
    //   6678: invokevirtual 46	java/lang/String:length	()I
    //   6681: ifle +60 -> 6741
    //   6684: new 152	java/lang/StringBuilder
    //   6687: dup
    //   6688: invokespecial 153	java/lang/StringBuilder:<init>	()V
    //   6691: aload 19
    //   6693: invokevirtual 163	java/lang/StringBuilder:append	(Ljava/lang/String;)Ljava/lang/StringBuilder;
    //   6696: ldc_w 427
    //   6699: invokevirtual 163	java/lang/StringBuilder:append	(Ljava/lang/String;)Ljava/lang/StringBuilder;
    //   6702: invokevirtual 167	java/lang/StringBuilder:toString	()Ljava/lang/String;
    //   6705: astore_0
    //   6706: aload_2
    //   6707: invokestatic 401	com/tencent/mm/model/w:xg	(Ljava/lang/String;)Z
    //   6710: ifne +15 -> 6725
    //   6713: iload 14
    //   6715: ifne +10 -> 6725
    //   6718: aload 7
    //   6720: aload 19
    //   6722: putfield 147	com/tencent/mm/pointers/PString:value	Ljava/lang/String;
    //   6725: aload 6
    //   6727: ldc 26
    //   6729: putfield 147	com/tencent/mm/pointers/PString:value	Ljava/lang/String;
    //   6732: aconst_null
    //   6733: astore 18
    //   6735: iconst_0
    //   6736: istore 13
    //   6738: goto -5903 -> 835
    //   6741: ldc 26
    //   6743: astore_0
    //   6744: goto -38 -> 6706
    //   6747: aload 5
    //   6749: ldc_w 737
    //   6752: invokevirtual 169	android/content/Context:getString	(I)Ljava/lang/String;
    //   6755: astore_3
    //   6756: aload 19
    //   6758: invokevirtual 46	java/lang/String:length	()I
    //   6761: ifle +60 -> 6821
    //   6764: new 152	java/lang/StringBuilder
    //   6767: dup
    //   6768: invokespecial 153	java/lang/StringBuilder:<init>	()V
    //   6771: aload 19
    //   6773: invokevirtual 163	java/lang/StringBuilder:append	(Ljava/lang/String;)Ljava/lang/StringBuilder;
    //   6776: ldc_w 427
    //   6779: invokevirtual 163	java/lang/StringBuilder:append	(Ljava/lang/String;)Ljava/lang/StringBuilder;
    //   6782: invokevirtual 167	java/lang/StringBuilder:toString	()Ljava/lang/String;
    //   6785: astore_0
    //   6786: aload_2
    //   6787: invokestatic 401	com/tencent/mm/model/w:xg	(Ljava/lang/String;)Z
    //   6790: ifne +15 -> 6805
    //   6793: iload 14
    //   6795: ifne +10 -> 6805
    //   6798: aload 7
    //   6800: aload 19
    //   6802: putfield 147	com/tencent/mm/pointers/PString:value	Ljava/lang/String;
    //   6805: aload 6
    //   6807: ldc 26
    //   6809: putfield 147	com/tencent/mm/pointers/PString:value	Ljava/lang/String;
    //   6812: aconst_null
    //   6813: astore 18
    //   6815: iconst_0
    //   6816: istore 13
    //   6818: goto -5983 -> 835
    //   6821: ldc 26
    //   6823: astore_0
    //   6824: goto -38 -> 6786
    //   6827: aload 5
    //   6829: ldc_w 738
    //   6832: invokevirtual 169	android/content/Context:getString	(I)Ljava/lang/String;
    //   6835: astore_3
    //   6836: aload 19
    //   6838: invokevirtual 46	java/lang/String:length	()I
    //   6841: ifle +60 -> 6901
    //   6844: new 152	java/lang/StringBuilder
    //   6847: dup
    //   6848: invokespecial 153	java/lang/StringBuilder:<init>	()V
    //   6851: aload 19
    //   6853: invokevirtual 163	java/lang/StringBuilder:append	(Ljava/lang/String;)Ljava/lang/StringBuilder;
    //   6856: ldc_w 427
    //   6859: invokevirtual 163	java/lang/StringBuilder:append	(Ljava/lang/String;)Ljava/lang/StringBuilder;
    //   6862: invokevirtual 167	java/lang/StringBuilder:toString	()Ljava/lang/String;
    //   6865: astore_0
    //   6866: aload_2
    //   6867: invokestatic 401	com/tencent/mm/model/w:xg	(Ljava/lang/String;)Z
    //   6870: ifne +15 -> 6885
    //   6873: iload 14
    //   6875: ifne +10 -> 6885
    //   6878: aload 7
    //   6880: aload 19
    //   6882: putfield 147	com/tencent/mm/pointers/PString:value	Ljava/lang/String;
    //   6885: aload 6
    //   6887: ldc 26
    //   6889: putfield 147	com/tencent/mm/pointers/PString:value	Ljava/lang/String;
    //   6892: aconst_null
    //   6893: astore 18
    //   6895: iconst_0
    //   6896: istore 13
    //   6898: goto -6063 -> 835
    //   6901: ldc 26
    //   6903: astore_0
    //   6904: goto -38 -> 6866
    //   6907: ldc 26
    //   6909: astore 21
    //   6911: aload 19
    //   6913: invokevirtual 46	java/lang/String:length	()I
    //   6916: ifle +100 -> 7016
    //   6919: new 152	java/lang/StringBuilder
    //   6922: dup
    //   6923: invokespecial 153	java/lang/StringBuilder:<init>	()V
    //   6926: aload 19
    //   6928: invokevirtual 163	java/lang/StringBuilder:append	(Ljava/lang/String;)Ljava/lang/StringBuilder;
    //   6931: ldc_w 427
    //   6934: invokevirtual 163	java/lang/StringBuilder:append	(Ljava/lang/String;)Ljava/lang/StringBuilder;
    //   6937: aload 18
    //   6939: getfield 560	com/tencent/mm/ah/k$b:title	Ljava/lang/String;
    //   6942: invokevirtual 163	java/lang/StringBuilder:append	(Ljava/lang/String;)Ljava/lang/StringBuilder;
    //   6945: invokevirtual 167	java/lang/StringBuilder:toString	()Ljava/lang/String;
    //   6948: astore_0
    //   6949: aload_2
    //   6950: invokestatic 401	com/tencent/mm/model/w:xg	(Ljava/lang/String;)Z
    //   6953: ifne +15 -> 6968
    //   6956: iload 14
    //   6958: ifne +10 -> 6968
    //   6961: aload 7
    //   6963: aload 19
    //   6965: putfield 147	com/tencent/mm/pointers/PString:value	Ljava/lang/String;
    //   6968: aload 19
    //   6970: invokevirtual 46	java/lang/String:length	()I
    //   6973: ifle +52 -> 7025
    //   6976: new 152	java/lang/StringBuilder
    //   6979: dup
    //   6980: ldc_w 429
    //   6983: invokespecial 575	java/lang/StringBuilder:<init>	(Ljava/lang/String;)V
    //   6986: aload 18
    //   6988: getfield 560	com/tencent/mm/ah/k$b:title	Ljava/lang/String;
    //   6991: invokevirtual 163	java/lang/StringBuilder:append	(Ljava/lang/String;)Ljava/lang/StringBuilder;
    //   6994: invokevirtual 167	java/lang/StringBuilder:toString	()Ljava/lang/String;
    //   6997: astore_3
    //   6998: aload 6
    //   7000: aload_3
    //   7001: putfield 147	com/tencent/mm/pointers/PString:value	Ljava/lang/String;
    //   7004: aconst_null
    //   7005: astore 18
    //   7007: iconst_0
    //   7008: istore 13
    //   7010: aload 21
    //   7012: astore_3
    //   7013: goto -6178 -> 835
    //   7016: aload 18
    //   7018: getfield 560	com/tencent/mm/ah/k$b:title	Ljava/lang/String;
    //   7021: astore_0
    //   7022: goto -73 -> 6949
    //   7025: aload 18
    //   7027: getfield 560	com/tencent/mm/ah/k$b:title	Ljava/lang/String;
    //   7030: astore_3
    //   7031: goto -33 -> 6998
    //   7034: aload 5
    //   7036: ldc_w 739
    //   7039: invokevirtual 169	android/content/Context:getString	(I)Ljava/lang/String;
    //   7042: astore 21
    //   7044: aload 19
    //   7046: invokevirtual 46	java/lang/String:length	()I
    //   7049: ifle +74 -> 7123
    //   7052: new 152	java/lang/StringBuilder
    //   7055: dup
    //   7056: invokespecial 153	java/lang/StringBuilder:<init>	()V
    //   7059: aload 19
    //   7061: invokevirtual 163	java/lang/StringBuilder:append	(Ljava/lang/String;)Ljava/lang/StringBuilder;
    //   7064: ldc_w 427
    //   7067: invokevirtual 163	java/lang/StringBuilder:append	(Ljava/lang/String;)Ljava/lang/StringBuilder;
    //   7070: invokevirtual 167	java/lang/StringBuilder:toString	()Ljava/lang/String;
    //   7073: astore_0
    //   7074: aload_2
    //   7075: invokestatic 401	com/tencent/mm/model/w:xg	(Ljava/lang/String;)Z
    //   7078: ifne +15 -> 7093
    //   7081: iload 14
    //   7083: ifne +10 -> 7093
    //   7086: aload 7
    //   7088: aload 19
    //   7090: putfield 147	com/tencent/mm/pointers/PString:value	Ljava/lang/String;
    //   7093: aload 19
    //   7095: invokevirtual 46	java/lang/String:length	()I
    //   7098: ifle +31 -> 7129
    //   7101: ldc_w 429
    //   7104: astore_3
    //   7105: aload 6
    //   7107: aload_3
    //   7108: putfield 147	com/tencent/mm/pointers/PString:value	Ljava/lang/String;
    //   7111: aconst_null
    //   7112: astore 18
    //   7114: iconst_0
    //   7115: istore 13
    //   7117: aload 21
    //   7119: astore_3
    //   7120: goto -6285 -> 835
    //   7123: ldc 26
    //   7125: astore_0
    //   7126: goto -52 -> 7074
    //   7129: ldc 26
    //   7131: astore_3
    //   7132: goto -27 -> 7105
    //   7135: ldc 26
    //   7137: astore_0
    //   7138: aload 18
    //   7140: getfield 742	com/tencent/mm/ah/k$b:description	Ljava/lang/String;
    //   7143: invokestatic 214	com/tencent/mm/sdk/platformtools/bs:isNullOrNil	(Ljava/lang/String;)Z
    //   7146: ifne +35 -> 7181
    //   7149: aload 18
    //   7151: getfield 742	com/tencent/mm/ah/k$b:description	Ljava/lang/String;
    //   7154: ldc_w 744
    //   7157: invokevirtual 127	java/lang/String:indexOf	(Ljava/lang/String;)I
    //   7160: istore 13
    //   7162: aload 18
    //   7164: getfield 742	com/tencent/mm/ah/k$b:description	Ljava/lang/String;
    //   7167: astore_0
    //   7168: iload 13
    //   7170: ifle +117 -> 7287
    //   7173: aload_0
    //   7174: iconst_0
    //   7175: iload 13
    //   7177: invokevirtual 131	java/lang/String:substring	(II)Ljava/lang/String;
    //   7180: astore_0
    //   7181: new 152	java/lang/StringBuilder
    //   7184: dup
    //   7185: invokespecial 153	java/lang/StringBuilder:<init>	()V
    //   7188: aload 5
    //   7190: ldc_w 745
    //   7193: invokevirtual 169	android/content/Context:getString	(I)Ljava/lang/String;
    //   7196: invokevirtual 163	java/lang/StringBuilder:append	(Ljava/lang/String;)Ljava/lang/StringBuilder;
    //   7199: aload_0
    //   7200: invokevirtual 163	java/lang/StringBuilder:append	(Ljava/lang/String;)Ljava/lang/StringBuilder;
    //   7203: invokevirtual 167	java/lang/StringBuilder:toString	()Ljava/lang/String;
    //   7206: astore 21
    //   7208: aload 19
    //   7210: invokevirtual 46	java/lang/String:length	()I
    //   7213: ifle +87 -> 7300
    //   7216: new 152	java/lang/StringBuilder
    //   7219: dup
    //   7220: invokespecial 153	java/lang/StringBuilder:<init>	()V
    //   7223: aload 19
    //   7225: invokevirtual 163	java/lang/StringBuilder:append	(Ljava/lang/String;)Ljava/lang/StringBuilder;
    //   7228: ldc_w 427
    //   7231: invokevirtual 163	java/lang/StringBuilder:append	(Ljava/lang/String;)Ljava/lang/StringBuilder;
    //   7234: invokevirtual 167	java/lang/StringBuilder:toString	()Ljava/lang/String;
    //   7237: astore_0
    //   7238: aload_2
    //   7239: invokestatic 401	com/tencent/mm/model/w:xg	(Ljava/lang/String;)Z
    //   7242: ifne +15 -> 7257
    //   7245: iload 14
    //   7247: ifne +10 -> 7257
    //   7250: aload 7
    //   7252: aload 19
    //   7254: putfield 147	com/tencent/mm/pointers/PString:value	Ljava/lang/String;
    //   7257: aload 19
    //   7259: invokevirtual 46	java/lang/String:length	()I
    //   7262: ifle +44 -> 7306
    //   7265: ldc_w 429
    //   7268: astore_3
    //   7269: aload 6
    //   7271: aload_3
    //   7272: putfield 147	com/tencent/mm/pointers/PString:value	Ljava/lang/String;
    //   7275: aconst_null
    //   7276: astore 18
    //   7278: iconst_0
    //   7279: istore 13
    //   7281: aload 21
    //   7283: astore_3
    //   7284: goto -6449 -> 835
    //   7287: aload 18
    //   7289: getfield 742	com/tencent/mm/ah/k$b:description	Ljava/lang/String;
    //   7292: invokevirtual 46	java/lang/String:length	()I
    //   7295: istore 13
    //   7297: goto -124 -> 7173
    //   7300: ldc 26
    //   7302: astore_0
    //   7303: goto -65 -> 7238
    //   7306: ldc 26
    //   7308: astore_3
    //   7309: goto -40 -> 7269
    //   7312: ldc 26
    //   7314: astore 21
    //   7316: aload 5
    //   7318: ldc_w 625
    //   7321: invokevirtual 169	android/content/Context:getString	(I)Ljava/lang/String;
    //   7324: astore_3
    //   7325: aload 19
    //   7327: invokevirtual 46	java/lang/String:length	()I
    //   7330: ifle +93 -> 7423
    //   7333: new 152	java/lang/StringBuilder
    //   7336: dup
    //   7337: invokespecial 153	java/lang/StringBuilder:<init>	()V
    //   7340: aload 19
    //   7342: invokevirtual 163	java/lang/StringBuilder:append	(Ljava/lang/String;)Ljava/lang/StringBuilder;
    //   7345: ldc_w 427
    //   7348: invokevirtual 163	java/lang/StringBuilder:append	(Ljava/lang/String;)Ljava/lang/StringBuilder;
    //   7351: aload_3
    //   7352: invokevirtual 163	java/lang/StringBuilder:append	(Ljava/lang/String;)Ljava/lang/StringBuilder;
    //   7355: aload 18
    //   7357: getfield 560	com/tencent/mm/ah/k$b:title	Ljava/lang/String;
    //   7360: invokevirtual 163	java/lang/StringBuilder:append	(Ljava/lang/String;)Ljava/lang/StringBuilder;
    //   7363: invokevirtual 167	java/lang/StringBuilder:toString	()Ljava/lang/String;
    //   7366: astore_0
    //   7367: aload_2
    //   7368: invokestatic 401	com/tencent/mm/model/w:xg	(Ljava/lang/String;)Z
    //   7371: ifne +15 -> 7386
    //   7374: iload 14
    //   7376: ifne +10 -> 7386
    //   7379: aload 7
    //   7381: aload 19
    //   7383: putfield 147	com/tencent/mm/pointers/PString:value	Ljava/lang/String;
    //   7386: aload 19
    //   7388: invokevirtual 46	java/lang/String:length	()I
    //   7391: ifle +58 -> 7449
    //   7394: ldc_w 429
    //   7397: aload_3
    //   7398: invokestatic 631	java/lang/String:valueOf	(Ljava/lang/Object;)Ljava/lang/String;
    //   7401: invokevirtual 634	java/lang/String:concat	(Ljava/lang/String;)Ljava/lang/String;
    //   7404: astore_3
    //   7405: aload 6
    //   7407: aload_3
    //   7408: putfield 147	com/tencent/mm/pointers/PString:value	Ljava/lang/String;
    //   7411: aconst_null
    //   7412: astore 18
    //   7414: iconst_0
    //   7415: istore 13
    //   7417: aload 21
    //   7419: astore_3
    //   7420: goto -6585 -> 835
    //   7423: new 152	java/lang/StringBuilder
    //   7426: dup
    //   7427: invokespecial 153	java/lang/StringBuilder:<init>	()V
    //   7430: aload_3
    //   7431: invokevirtual 163	java/lang/StringBuilder:append	(Ljava/lang/String;)Ljava/lang/StringBuilder;
    //   7434: aload 18
    //   7436: getfield 560	com/tencent/mm/ah/k$b:title	Ljava/lang/String;
    //   7439: invokevirtual 163	java/lang/StringBuilder:append	(Ljava/lang/String;)Ljava/lang/StringBuilder;
    //   7442: invokevirtual 167	java/lang/StringBuilder:toString	()Ljava/lang/String;
    //   7445: astore_0
    //   7446: goto -79 -> 7367
    //   7449: aload_3
    //   7450: invokestatic 631	java/lang/String:valueOf	(Ljava/lang/Object;)Ljava/lang/String;
    //   7453: astore_3
    //   7454: goto -49 -> 7405
    //   7457: ldc 26
    //   7459: astore 21
    //   7461: aload 5
    //   7463: ldc_w 625
    //   7466: invokevirtual 169	android/content/Context:getString	(I)Ljava/lang/String;
    //   7469: astore_0
    //   7470: iload_1
    //   7471: iconst_1
    //   7472: if_icmpne +96 -> 7568
    //   7475: new 152	java/lang/StringBuilder
    //   7478: dup
    //   7479: invokespecial 153	java/lang/StringBuilder:<init>	()V
    //   7482: aload_0
    //   7483: invokevirtual 163	java/lang/StringBuilder:append	(Ljava/lang/String;)Ljava/lang/StringBuilder;
    //   7486: aload 18
    //   7488: getfield 628	com/tencent/mm/ah/k$b:hiZ	Ljava/lang/String;
    //   7491: invokevirtual 163	java/lang/StringBuilder:append	(Ljava/lang/String;)Ljava/lang/StringBuilder;
    //   7494: invokevirtual 167	java/lang/StringBuilder:toString	()Ljava/lang/String;
    //   7497: astore_3
    //   7498: aload 19
    //   7500: invokevirtual 46	java/lang/String:length	()I
    //   7503: ifle +57 -> 7560
    //   7506: ldc_w 429
    //   7509: aload_3
    //   7510: invokestatic 631	java/lang/String:valueOf	(Ljava/lang/Object;)Ljava/lang/String;
    //   7513: invokevirtual 634	java/lang/String:concat	(Ljava/lang/String;)Ljava/lang/String;
    //   7516: astore_0
    //   7517: aload 6
    //   7519: aload_0
    //   7520: putfield 147	com/tencent/mm/pointers/PString:value	Ljava/lang/String;
    //   7523: aload_3
    //   7524: astore_0
    //   7525: aload_2
    //   7526: invokestatic 401	com/tencent/mm/model/w:xg	(Ljava/lang/String;)Z
    //   7529: ifne +1586 -> 9115
    //   7532: aload_3
    //   7533: astore_0
    //   7534: iload 14
    //   7536: ifne +1579 -> 9115
    //   7539: aload 7
    //   7541: aload 19
    //   7543: putfield 147	com/tencent/mm/pointers/PString:value	Ljava/lang/String;
    //   7546: aconst_null
    //   7547: astore 18
    //   7549: iconst_0
    //   7550: istore 13
    //   7552: aload_3
    //   7553: astore_0
    //   7554: aload 21
    //   7556: astore_3
    //   7557: goto -6722 -> 835
    //   7560: aload_3
    //   7561: invokestatic 631	java/lang/String:valueOf	(Ljava/lang/Object;)Ljava/lang/String;
    //   7564: astore_0
    //   7565: goto -48 -> 7517
    //   7568: new 152	java/lang/StringBuilder
    //   7571: dup
    //   7572: invokespecial 153	java/lang/StringBuilder:<init>	()V
    //   7575: aload_0
    //   7576: invokevirtual 163	java/lang/StringBuilder:append	(Ljava/lang/String;)Ljava/lang/StringBuilder;
    //   7579: aload 18
    //   7581: getfield 637	com/tencent/mm/ah/k$b:hiY	Ljava/lang/String;
    //   7584: invokevirtual 163	java/lang/StringBuilder:append	(Ljava/lang/String;)Ljava/lang/StringBuilder;
    //   7587: invokevirtual 167	java/lang/StringBuilder:toString	()Ljava/lang/String;
    //   7590: astore_3
    //   7591: aload 19
    //   7593: invokevirtual 46	java/lang/String:length	()I
    //   7596: ifle +23 -> 7619
    //   7599: ldc_w 429
    //   7602: aload_3
    //   7603: invokestatic 631	java/lang/String:valueOf	(Ljava/lang/Object;)Ljava/lang/String;
    //   7606: invokevirtual 634	java/lang/String:concat	(Ljava/lang/String;)Ljava/lang/String;
    //   7609: astore_0
    //   7610: aload 6
    //   7612: aload_0
    //   7613: putfield 147	com/tencent/mm/pointers/PString:value	Ljava/lang/String;
    //   7616: goto -93 -> 7523
    //   7619: aload_3
    //   7620: invokestatic 631	java/lang/String:valueOf	(Ljava/lang/Object;)Ljava/lang/String;
    //   7623: astore_0
    //   7624: goto -14 -> 7610
    //   7627: aload_0
    //   7628: invokestatic 751	com/tencent/mm/ah/t:vF	(Ljava/lang/String;)Lcom/tencent/mm/ah/t;
    //   7631: getfield 754	com/tencent/mm/ah/t:hla	I
    //   7634: bipush 19
    //   7636: if_icmpne +27 -> 7663
    //   7639: aload 5
    //   7641: ldc_w 739
    //   7644: invokevirtual 169	android/content/Context:getString	(I)Ljava/lang/String;
    //   7647: astore 21
    //   7649: aconst_null
    //   7650: astore 18
    //   7652: iconst_0
    //   7653: istore 13
    //   7655: aload_3
    //   7656: astore_0
    //   7657: aload 21
    //   7659: astore_3
    //   7660: goto -6825 -> 835
    //   7663: aload 5
    //   7665: ldc_w 638
    //   7668: invokevirtual 169	android/content/Context:getString	(I)Ljava/lang/String;
    //   7671: astore 21
    //   7673: aconst_null
    //   7674: astore 18
    //   7676: iconst_0
    //   7677: istore 13
    //   7679: aload_3
    //   7680: astore_0
    //   7681: aload 21
    //   7683: astore_3
    //   7684: goto -6849 -> 835
    //   7687: aload_3
    //   7688: astore_0
    //   7689: iload 15
    //   7691: ifeq +8 -> 7699
    //   7694: aload_3
    //   7695: invokestatic 757	com/tencent/mm/booter/notification/a/h:rJ	(Ljava/lang/String;)Ljava/lang/String;
    //   7698: astore_0
    //   7699: ldc_w 290
    //   7702: invokestatic 296	com/tencent/mm/kernel/g:ab	(Ljava/lang/Class;)Lcom/tencent/mm/kernel/c/a;
    //   7705: checkcast 290	com/tencent/mm/plugin/biz/a/a
    //   7708: aload_0
    //   7709: invokeinterface 760 2 0
    //   7714: astore_3
    //   7715: aload_3
    //   7716: astore_0
    //   7717: iload 15
    //   7719: ifeq +8 -> 7727
    //   7722: aload_3
    //   7723: invokestatic 384	com/tencent/mm/booter/notification/a/h:rI	(Ljava/lang/String;)Ljava/lang/String;
    //   7726: astore_0
    //   7727: aload_0
    //   7728: invokestatic 204	com/tencent/mm/pluginsdk/ui/span/k:aHF	(Ljava/lang/String;)Ljava/lang/String;
    //   7731: astore_0
    //   7732: aload 6
    //   7734: aload_0
    //   7735: putfield 147	com/tencent/mm/pointers/PString:value	Ljava/lang/String;
    //   7738: ldc 26
    //   7740: astore_3
    //   7741: aconst_null
    //   7742: astore 18
    //   7744: iconst_0
    //   7745: istore 13
    //   7747: goto -6912 -> 835
    //   7750: aload 6
    //   7752: ldc_w 290
    //   7755: invokestatic 296	com/tencent/mm/kernel/g:ab	(Ljava/lang/Class;)Lcom/tencent/mm/kernel/c/a;
    //   7758: checkcast 290	com/tencent/mm/plugin/biz/a/a
    //   7761: aload_3
    //   7762: invokeinterface 763 2 0
    //   7767: putfield 147	com/tencent/mm/pointers/PString:value	Ljava/lang/String;
    //   7770: aload 6
    //   7772: getfield 147	com/tencent/mm/pointers/PString:value	Ljava/lang/String;
    //   7775: astore_3
    //   7776: ldc_w 616
    //   7779: ldc_w 765
    //   7782: iconst_2
    //   7783: anewarray 4	java/lang/Object
    //   7786: dup
    //   7787: iconst_0
    //   7788: ldc_w 288
    //   7791: invokestatic 191	java/lang/Integer:valueOf	(I)Ljava/lang/Integer;
    //   7794: aastore
    //   7795: dup
    //   7796: iconst_1
    //   7797: aload_3
    //   7798: aastore
    //   7799: invokestatic 768	com/tencent/mm/sdk/platformtools/ac:i	(Ljava/lang/String;Ljava/lang/String;[Ljava/lang/Object;)V
    //   7802: aconst_null
    //   7803: astore 18
    //   7805: iconst_0
    //   7806: istore 13
    //   7808: ldc 26
    //   7810: astore_0
    //   7811: goto -6976 -> 835
    //   7814: aload_3
    //   7815: invokestatic 774	com/tencent/mm/am/a$a:BH	(Ljava/lang/String;)Lcom/tencent/mm/am/a$a;
    //   7818: invokestatic 779	com/tencent/mm/am/a:b	(Lcom/tencent/mm/am/a$a;)Ljava/lang/String;
    //   7821: astore_0
    //   7822: aload 6
    //   7824: aload_0
    //   7825: putfield 147	com/tencent/mm/pointers/PString:value	Ljava/lang/String;
    //   7828: ldc 26
    //   7830: astore_3
    //   7831: aconst_null
    //   7832: astore 18
    //   7834: iconst_0
    //   7835: istore 13
    //   7837: goto -7002 -> 835
    //   7840: ldc 26
    //   7842: astore_3
    //   7843: aload 21
    //   7845: invokestatic 549	com/tencent/mm/ah/k$b:vA	(Ljava/lang/String;)Lcom/tencent/mm/ah/k$b;
    //   7848: astore 18
    //   7850: aload_3
    //   7851: astore_0
    //   7852: aload 18
    //   7854: ifnull -7028 -> 826
    //   7857: aload_3
    //   7858: astore_0
    //   7859: aload 18
    //   7861: getfield 641	com/tencent/mm/ah/k$b:content	Ljava/lang/String;
    //   7864: ldc_w 643
    //   7867: invokestatic 648	java/net/URLDecoder:decode	(Ljava/lang/String;Ljava/lang/String;)Ljava/lang/String;
    //   7870: astore_3
    //   7871: aload_3
    //   7872: astore_0
    //   7873: aload_3
    //   7874: invokestatic 204	com/tencent/mm/pluginsdk/ui/span/k:aHF	(Ljava/lang/String;)Ljava/lang/String;
    //   7877: astore_3
    //   7878: aload_3
    //   7879: astore_0
    //   7880: aload 6
    //   7882: aload_0
    //   7883: putfield 147	com/tencent/mm/pointers/PString:value	Ljava/lang/String;
    //   7886: ldc 26
    //   7888: astore_3
    //   7889: aconst_null
    //   7890: astore 18
    //   7892: iconst_0
    //   7893: istore 13
    //   7895: goto -7060 -> 835
    //   7898: astore_3
    //   7899: ldc_w 616
    //   7902: aload_3
    //   7903: ldc 26
    //   7905: iconst_0
    //   7906: anewarray 4	java/lang/Object
    //   7909: invokestatic 652	com/tencent/mm/sdk/platformtools/ac:printErrStackTrace	(Ljava/lang/String;Ljava/lang/Throwable;Ljava/lang/String;[Ljava/lang/Object;)V
    //   7912: ldc 26
    //   7914: astore_3
    //   7915: aconst_null
    //   7916: astore 18
    //   7918: iconst_0
    //   7919: istore 13
    //   7921: goto -7086 -> 835
    //   7924: ldc_w 781
    //   7927: invokestatic 296	com/tencent/mm/kernel/g:ab	(Ljava/lang/Class;)Lcom/tencent/mm/kernel/c/a;
    //   7930: checkcast 781	com/tencent/mm/plugin/messenger/a/f
    //   7933: aload_3
    //   7934: invokeinterface 785 2 0
    //   7939: astore_0
    //   7940: aload_0
    //   7941: ifnull +100 -> 8041
    //   7944: aload_0
    //   7945: invokeinterface 788 1 0
    //   7950: astore_3
    //   7951: aload_3
    //   7952: astore_0
    //   7953: iload 9
    //   7955: ifeq +68 -> 8023
    //   7958: aload_3
    //   7959: astore_0
    //   7960: aload_2
    //   7961: invokestatic 385	com/tencent/mm/model/w:sQ	(Ljava/lang/String;)Z
    //   7964: ifeq +59 -> 8023
    //   7967: aload_3
    //   7968: astore_0
    //   7969: aload_3
    //   7970: aload 5
    //   7972: ldc_w 789
    //   7975: invokevirtual 169	android/content/Context:getString	(I)Ljava/lang/String;
    //   7978: invokevirtual 792	java/lang/String:endsWith	(Ljava/lang/String;)Z
    //   7981: ifeq +42 -> 8023
    //   7984: ldc_w 616
    //   7987: ldc_w 794
    //   7990: iconst_1
    //   7991: anewarray 4	java/lang/Object
    //   7994: dup
    //   7995: iconst_0
    //   7996: aload_3
    //   7997: aastore
    //   7998: invokestatic 768	com/tencent/mm/sdk/platformtools/ac:i	(Ljava/lang/String;Ljava/lang/String;[Ljava/lang/Object;)V
    //   8001: aload_3
    //   8002: iconst_0
    //   8003: aload_3
    //   8004: invokevirtual 46	java/lang/String:length	()I
    //   8007: aload 5
    //   8009: ldc_w 789
    //   8012: invokevirtual 169	android/content/Context:getString	(I)Ljava/lang/String;
    //   8015: invokevirtual 46	java/lang/String:length	()I
    //   8018: isub
    //   8019: invokevirtual 131	java/lang/String:substring	(II)Ljava/lang/String;
    //   8022: astore_0
    //   8023: aload 6
    //   8025: aload_0
    //   8026: putfield 147	com/tencent/mm/pointers/PString:value	Ljava/lang/String;
    //   8029: ldc 26
    //   8031: astore_3
    //   8032: aconst_null
    //   8033: astore 18
    //   8035: iconst_0
    //   8036: istore 13
    //   8038: goto -7203 -> 835
    //   8041: ldc 26
    //   8043: astore_3
    //   8044: goto -93 -> 7951
    //   8047: aload_3
    //   8048: invokestatic 800	com/tencent/mm/ah/a/b:vJ	(Ljava/lang/String;)Lcom/tencent/mm/ah/a/b;
    //   8051: getfield 801	com/tencent/mm/ah/a/b:content	Ljava/lang/String;
    //   8054: astore_3
    //   8055: aload_3
    //   8056: astore_0
    //   8057: aload_3
    //   8058: invokestatic 214	com/tencent/mm/sdk/platformtools/bs:isNullOrNil	(Ljava/lang/String;)Z
    //   8061: ifeq +6 -> 8067
    //   8064: ldc 26
    //   8066: astore_0
    //   8067: aload 6
    //   8069: aload_0
    //   8070: putfield 147	com/tencent/mm/pointers/PString:value	Ljava/lang/String;
    //   8073: ldc 26
    //   8075: astore_3
    //   8076: aconst_null
    //   8077: astore 18
    //   8079: iconst_0
    //   8080: istore 13
    //   8082: goto -7247 -> 835
    //   8085: aload 5
    //   8087: ldc_w 802
    //   8090: invokevirtual 169	android/content/Context:getString	(I)Ljava/lang/String;
    //   8093: astore_0
    //   8094: aload 6
    //   8096: aload_0
    //   8097: putfield 147	com/tencent/mm/pointers/PString:value	Ljava/lang/String;
    //   8100: ldc 26
    //   8102: astore_3
    //   8103: aconst_null
    //   8104: astore 18
    //   8106: iconst_0
    //   8107: istore 13
    //   8109: goto -7274 -> 835
    //   8112: aload_3
    //   8113: invokestatic 808	com/tencent/mm/ah/a/a:vH	(Ljava/lang/String;)Lcom/tencent/mm/ah/a/a;
    //   8116: astore_0
    //   8117: aload_0
    //   8118: getfield 809	com/tencent/mm/ah/a/a:nickname	Ljava/lang/String;
    //   8121: invokestatic 214	com/tencent/mm/sdk/platformtools/bs:isNullOrNil	(Ljava/lang/String;)Z
    //   8124: ifne +13 -> 8137
    //   8127: aload_0
    //   8128: getfield 810	com/tencent/mm/ah/a/a:title	Ljava/lang/String;
    //   8131: invokestatic 214	com/tencent/mm/sdk/platformtools/bs:isNullOrNil	(Ljava/lang/String;)Z
    //   8134: ifeq +9 -> 8143
    //   8137: ldc 26
    //   8139: astore_0
    //   8140: goto -46 -> 8094
    //   8143: getstatic 816	java/util/Locale:US	Ljava/util/Locale;
    //   8146: ldc_w 818
    //   8149: iconst_2
    //   8150: anewarray 4	java/lang/Object
    //   8153: dup
    //   8154: iconst_0
    //   8155: aload_0
    //   8156: getfield 809	com/tencent/mm/ah/a/a:nickname	Ljava/lang/String;
    //   8159: aastore
    //   8160: dup
    //   8161: iconst_1
    //   8162: aload_0
    //   8163: getfield 810	com/tencent/mm/ah/a/a:title	Ljava/lang/String;
    //   8166: aastore
    //   8167: invokestatic 822	java/lang/String:format	(Ljava/util/Locale;Ljava/lang/String;[Ljava/lang/Object;)Ljava/lang/String;
    //   8170: astore_0
    //   8171: goto -77 -> 8094
    //   8174: aload_0
    //   8175: ldc_w 824
    //   8178: invokevirtual 828	java/lang/String:split	(Ljava/lang/String;)[Ljava/lang/String;
    //   8181: astore_0
    //   8182: aload_0
    //   8183: arraylength
    //   8184: iconst_1
    //   8185: if_icmple +23 -> 8208
    //   8188: aload 6
    //   8190: aload_0
    //   8191: iconst_1
    //   8192: aaload
    //   8193: putfield 147	com/tencent/mm/pointers/PString:value	Ljava/lang/String;
    //   8196: aload_0
    //   8197: iconst_1
    //   8198: aaload
    //   8199: astore_0
    //   8200: ldc_w 360
    //   8203: invokestatic 53	com/tencent/matrix/trace/core/AppMethodBeat:o	(I)V
    //   8206: aload_0
    //   8207: areturn
    //   8208: aload 6
    //   8210: ldc 26
    //   8212: putfield 147	com/tencent/mm/pointers/PString:value	Ljava/lang/String;
    //   8215: ldc_w 360
    //   8218: invokestatic 53	com/tencent/matrix/trace/core/AppMethodBeat:o	(I)V
    //   8221: aconst_null
    //   8222: areturn
    //   8223: aconst_null
    //   8224: astore_2
    //   8225: aconst_null
    //   8226: astore 7
    //   8228: aload_0
    //   8229: ldc 123
    //   8231: invokevirtual 828	java/lang/String:split	(Ljava/lang/String;)[Ljava/lang/String;
    //   8234: astore 5
    //   8236: aload 5
    //   8238: ifnull +9 -> 8247
    //   8241: aload 5
    //   8243: arraylength
    //   8244: ifgt +18 -> 8262
    //   8247: aload 6
    //   8249: ldc 26
    //   8251: putfield 147	com/tencent/mm/pointers/PString:value	Ljava/lang/String;
    //   8254: ldc_w 360
    //   8257: invokestatic 53	com/tencent/matrix/trace/core/AppMethodBeat:o	(I)V
    //   8260: aconst_null
    //   8261: areturn
    //   8262: aload 5
    //   8264: iconst_0
    //   8265: aaload
    //   8266: astore 5
    //   8268: aload 5
    //   8270: invokestatic 214	com/tencent/mm/sdk/platformtools/bs:isNullOrNil	(Ljava/lang/String;)Z
    //   8273: ifne +69 -> 8342
    //   8276: invokestatic 257	com/tencent/mm/model/az:ayM	()Lcom/tencent/mm/model/c;
    //   8279: pop
    //   8280: invokestatic 263	com/tencent/mm/model/c:awB	()Lcom/tencent/mm/storage/bj;
    //   8283: aload 5
    //   8285: invokeinterface 269 2 0
    //   8290: astore 8
    //   8292: aload 7
    //   8294: astore 5
    //   8296: aload 8
    //   8298: ifnull +22 -> 8320
    //   8301: aload 7
    //   8303: astore 5
    //   8305: aload 8
    //   8307: invokevirtual 320	com/tencent/mm/storage/ai:getCity	()Ljava/lang/String;
    //   8310: ifnull +10 -> 8320
    //   8313: aload 8
    //   8315: invokevirtual 320	com/tencent/mm/storage/ai:getCity	()Ljava/lang/String;
    //   8318: astore 5
    //   8320: aload 5
    //   8322: ifnull +14 -> 8336
    //   8325: aload 5
    //   8327: astore_2
    //   8328: aload 5
    //   8330: invokevirtual 46	java/lang/String:length	()I
    //   8333: ifgt +9 -> 8342
    //   8336: aload 8
    //   8338: invokevirtual 327	com/tencent/mm/storage/ai:getProvince	()Ljava/lang/String;
    //   8341: astore_2
    //   8342: aload_3
    //   8343: invokestatic 214	com/tencent/mm/sdk/platformtools/bs:isNullOrNil	(Ljava/lang/String;)Z
    //   8346: ifne +65 -> 8411
    //   8349: aload 6
    //   8351: new 152	java/lang/StringBuilder
    //   8354: dup
    //   8355: invokespecial 153	java/lang/StringBuilder:<init>	()V
    //   8358: aload_2
    //   8359: invokevirtual 163	java/lang/StringBuilder:append	(Ljava/lang/String;)Ljava/lang/StringBuilder;
    //   8362: ldc_w 427
    //   8365: invokevirtual 163	java/lang/StringBuilder:append	(Ljava/lang/String;)Ljava/lang/StringBuilder;
    //   8368: aload_3
    //   8369: invokevirtual 163	java/lang/StringBuilder:append	(Ljava/lang/String;)Ljava/lang/StringBuilder;
    //   8372: invokevirtual 167	java/lang/StringBuilder:toString	()Ljava/lang/String;
    //   8375: putfield 147	com/tencent/mm/pointers/PString:value	Ljava/lang/String;
    //   8378: new 152	java/lang/StringBuilder
    //   8381: dup
    //   8382: invokespecial 153	java/lang/StringBuilder:<init>	()V
    //   8385: aload_2
    //   8386: invokevirtual 163	java/lang/StringBuilder:append	(Ljava/lang/String;)Ljava/lang/StringBuilder;
    //   8389: ldc_w 427
    //   8392: invokevirtual 163	java/lang/StringBuilder:append	(Ljava/lang/String;)Ljava/lang/StringBuilder;
    //   8395: aload_3
    //   8396: invokevirtual 163	java/lang/StringBuilder:append	(Ljava/lang/String;)Ljava/lang/StringBuilder;
    //   8399: invokevirtual 167	java/lang/StringBuilder:toString	()Ljava/lang/String;
    //   8402: astore_0
    //   8403: ldc_w 360
    //   8406: invokestatic 53	com/tencent/matrix/trace/core/AppMethodBeat:o	(I)V
    //   8409: aload_0
    //   8410: areturn
    //   8411: aload_0
    //   8412: ldc_w 824
    //   8415: invokevirtual 828	java/lang/String:split	(Ljava/lang/String;)[Ljava/lang/String;
    //   8418: astore_0
    //   8419: aload_0
    //   8420: arraylength
    //   8421: iconst_1
    //   8422: if_icmple +69 -> 8491
    //   8425: aload 6
    //   8427: new 152	java/lang/StringBuilder
    //   8430: dup
    //   8431: invokespecial 153	java/lang/StringBuilder:<init>	()V
    //   8434: aload_2
    //   8435: invokevirtual 163	java/lang/StringBuilder:append	(Ljava/lang/String;)Ljava/lang/StringBuilder;
    //   8438: ldc_w 427
    //   8441: invokevirtual 163	java/lang/StringBuilder:append	(Ljava/lang/String;)Ljava/lang/StringBuilder;
    //   8444: aload_0
    //   8445: iconst_1
    //   8446: aaload
    //   8447: invokevirtual 163	java/lang/StringBuilder:append	(Ljava/lang/String;)Ljava/lang/StringBuilder;
    //   8450: invokevirtual 167	java/lang/StringBuilder:toString	()Ljava/lang/String;
    //   8453: putfield 147	com/tencent/mm/pointers/PString:value	Ljava/lang/String;
    //   8456: new 152	java/lang/StringBuilder
    //   8459: dup
    //   8460: invokespecial 153	java/lang/StringBuilder:<init>	()V
    //   8463: aload_2
    //   8464: invokevirtual 163	java/lang/StringBuilder:append	(Ljava/lang/String;)Ljava/lang/StringBuilder;
    //   8467: ldc_w 427
    //   8470: invokevirtual 163	java/lang/StringBuilder:append	(Ljava/lang/String;)Ljava/lang/StringBuilder;
    //   8473: aload_0
    //   8474: iconst_1
    //   8475: aaload
    //   8476: invokevirtual 163	java/lang/StringBuilder:append	(Ljava/lang/String;)Ljava/lang/StringBuilder;
    //   8479: invokevirtual 167	java/lang/StringBuilder:toString	()Ljava/lang/String;
    //   8482: astore_0
    //   8483: ldc_w 360
    //   8486: invokestatic 53	com/tencent/matrix/trace/core/AppMethodBeat:o	(I)V
    //   8489: aload_0
    //   8490: areturn
    //   8491: aload 6
    //   8493: aload_2
    //   8494: putfield 147	com/tencent/mm/pointers/PString:value	Ljava/lang/String;
    //   8497: ldc_w 360
    //   8500: invokestatic 53	com/tencent/matrix/trace/core/AppMethodBeat:o	(I)V
    //   8503: aload_2
    //   8504: areturn
    //   8505: aload_0
    //   8506: invokestatic 214	com/tencent/mm/sdk/platformtools/bs:isNullOrNil	(Ljava/lang/String;)Z
    //   8509: ifeq +10 -> 8519
    //   8512: aload 6
    //   8514: ldc 26
    //   8516: putfield 147	com/tencent/mm/pointers/PString:value	Ljava/lang/String;
    //   8519: aload 19
    //   8521: invokestatic 214	com/tencent/mm/sdk/platformtools/bs:isNullOrNil	(Ljava/lang/String;)Z
    //   8524: ifne +202 -> 8726
    //   8527: aload_0
    //   8528: astore_2
    //   8529: aload 20
    //   8531: ifnull +22 -> 8553
    //   8534: aload_0
    //   8535: astore_2
    //   8536: aload 20
    //   8538: invokevirtual 46	java/lang/String:length	()I
    //   8541: ifle +12 -> 8553
    //   8544: aload_0
    //   8545: aload 19
    //   8547: aload 20
    //   8549: invokestatic 832	com/tencent/mm/booter/notification/a/h:f	(Ljava/lang/String;Ljava/lang/String;Ljava/lang/String;)Ljava/lang/String;
    //   8552: astore_2
    //   8553: aload 7
    //   8555: getfield 147	com/tencent/mm/pointers/PString:value	Ljava/lang/String;
    //   8558: invokestatic 214	com/tencent/mm/sdk/platformtools/bs:isNullOrNil	(Ljava/lang/String;)Z
    //   8561: ifeq +28 -> 8589
    //   8564: aload 6
    //   8566: aload 6
    //   8568: getfield 147	com/tencent/mm/pointers/PString:value	Ljava/lang/String;
    //   8571: aload 19
    //   8573: ldc_w 535
    //   8576: invokestatic 832	com/tencent/mm/booter/notification/a/h:f	(Ljava/lang/String;Ljava/lang/String;Ljava/lang/String;)Ljava/lang/String;
    //   8579: putfield 147	com/tencent/mm/pointers/PString:value	Ljava/lang/String;
    //   8582: aload 7
    //   8584: aload 19
    //   8586: putfield 147	com/tencent/mm/pointers/PString:value	Ljava/lang/String;
    //   8589: aload_2
    //   8590: invokestatic 837	com/tencent/mm/compatible/util/n:sG	(Ljava/lang/String;)Ljava/lang/String;
    //   8593: astore_0
    //   8594: aload 6
    //   8596: aload 6
    //   8598: getfield 147	com/tencent/mm/pointers/PString:value	Ljava/lang/String;
    //   8601: invokestatic 837	com/tencent/mm/compatible/util/n:sG	(Ljava/lang/String;)Ljava/lang/String;
    //   8604: putfield 147	com/tencent/mm/pointers/PString:value	Ljava/lang/String;
    //   8607: new 152	java/lang/StringBuilder
    //   8610: dup
    //   8611: invokespecial 153	java/lang/StringBuilder:<init>	()V
    //   8614: aload_0
    //   8615: invokevirtual 163	java/lang/StringBuilder:append	(Ljava/lang/String;)Ljava/lang/StringBuilder;
    //   8618: aload_3
    //   8619: invokevirtual 163	java/lang/StringBuilder:append	(Ljava/lang/String;)Ljava/lang/StringBuilder;
    //   8622: invokevirtual 167	java/lang/StringBuilder:toString	()Ljava/lang/String;
    //   8625: astore_2
    //   8626: aload 6
    //   8628: new 152	java/lang/StringBuilder
    //   8631: dup
    //   8632: invokespecial 153	java/lang/StringBuilder:<init>	()V
    //   8635: aload 6
    //   8637: getfield 147	com/tencent/mm/pointers/PString:value	Ljava/lang/String;
    //   8640: invokevirtual 163	java/lang/StringBuilder:append	(Ljava/lang/String;)Ljava/lang/StringBuilder;
    //   8643: aload_3
    //   8644: invokevirtual 163	java/lang/StringBuilder:append	(Ljava/lang/String;)Ljava/lang/StringBuilder;
    //   8647: invokevirtual 167	java/lang/StringBuilder:toString	()Ljava/lang/String;
    //   8650: putfield 147	com/tencent/mm/pointers/PString:value	Ljava/lang/String;
    //   8653: iload 9
    //   8655: ifeq +25 -> 8680
    //   8658: iload 4
    //   8660: aload 6
    //   8662: aload_2
    //   8663: invokestatic 840	com/tencent/mm/booter/notification/a/h:a	(ILcom/tencent/mm/pointers/PString;Ljava/lang/String;)Z
    //   8666: ifne +14 -> 8680
    //   8669: iload 4
    //   8671: aload 6
    //   8673: aload 7
    //   8675: aload 8
    //   8677: invokestatic 843	com/tencent/mm/booter/notification/a/h:a	(ILcom/tencent/mm/pointers/PString;Lcom/tencent/mm/pointers/PString;Lcom/tencent/mm/pointers/PInt;)V
    //   8680: aload_2
    //   8681: astore_0
    //   8682: iload 13
    //   8684: ifeq +29 -> 8713
    //   8687: aload_2
    //   8688: new 152	java/lang/StringBuilder
    //   8691: dup
    //   8692: ldc_w 398
    //   8695: invokespecial 575	java/lang/StringBuilder:<init>	(Ljava/lang/String;)V
    //   8698: aload 18
    //   8700: invokestatic 110	com/tencent/mm/sdk/platformtools/bs:nullAsNil	(Ljava/lang/String;)Ljava/lang/String;
    //   8703: invokevirtual 163	java/lang/StringBuilder:append	(Ljava/lang/String;)Ljava/lang/StringBuilder;
    //   8706: invokevirtual 167	java/lang/StringBuilder:toString	()Ljava/lang/String;
    //   8709: invokevirtual 634	java/lang/String:concat	(Ljava/lang/String;)Ljava/lang/String;
    //   8712: astore_0
    //   8713: aload_0
    //   8714: invokestatic 110	com/tencent/mm/sdk/platformtools/bs:nullAsNil	(Ljava/lang/String;)Ljava/lang/String;
    //   8717: astore_0
    //   8718: ldc_w 360
    //   8721: invokestatic 53	com/tencent/matrix/trace/core/AppMethodBeat:o	(I)V
    //   8724: aload_0
    //   8725: areturn
    //   8726: aload_2
    //   8727: invokestatic 401	com/tencent/mm/model/w:xg	(Ljava/lang/String;)Z
    //   8730: ifne +15 -> 8745
    //   8733: iload 14
    //   8735: ifne +10 -> 8745
    //   8738: aload_2
    //   8739: invokestatic 404	com/tencent/mm/model/w:xp	(Ljava/lang/String;)Z
    //   8742: ifeq +324 -> 9066
    //   8745: aload_0
    //   8746: astore 19
    //   8748: aload_3
    //   8749: ifnull +16 -> 8765
    //   8752: aload_0
    //   8753: astore 19
    //   8755: aload_3
    //   8756: invokevirtual 46	java/lang/String:length	()I
    //   8759: ifle +6 -> 8765
    //   8762: aload_3
    //   8763: astore 19
    //   8765: aload 19
    //   8767: invokestatic 214	com/tencent/mm/sdk/platformtools/bs:isNullOrNil	(Ljava/lang/String;)Z
    //   8770: ifeq +26 -> 8796
    //   8773: aload 6
    //   8775: ldc 26
    //   8777: putfield 147	com/tencent/mm/pointers/PString:value	Ljava/lang/String;
    //   8780: aload 7
    //   8782: ldc 26
    //   8784: putfield 147	com/tencent/mm/pointers/PString:value	Ljava/lang/String;
    //   8787: ldc_w 360
    //   8790: invokestatic 53	com/tencent/matrix/trace/core/AppMethodBeat:o	(I)V
    //   8793: ldc 26
    //   8795: areturn
    //   8796: iload_1
    //   8797: ifne +190 -> 8987
    //   8800: aload 6
    //   8802: ldc_w 450
    //   8805: aload 19
    //   8807: invokestatic 631	java/lang/String:valueOf	(Ljava/lang/Object;)Ljava/lang/String;
    //   8810: invokevirtual 634	java/lang/String:concat	(Ljava/lang/String;)Ljava/lang/String;
    //   8813: putfield 147	com/tencent/mm/pointers/PString:value	Ljava/lang/String;
    //   8816: iload 9
    //   8818: ifeq +208 -> 9026
    //   8821: iload 4
    //   8823: aload 6
    //   8825: aload 7
    //   8827: aload 8
    //   8829: invokestatic 843	com/tencent/mm/booter/notification/a/h:a	(ILcom/tencent/mm/pointers/PString;Lcom/tencent/mm/pointers/PString;Lcom/tencent/mm/pointers/PInt;)V
    //   8832: aload 19
    //   8834: astore_0
    //   8835: aload_0
    //   8836: astore_3
    //   8837: iload 13
    //   8839: ifeq +26 -> 8865
    //   8842: aload_0
    //   8843: astore_3
    //   8844: aload 18
    //   8846: ifnull +19 -> 8865
    //   8849: aload_0
    //   8850: ldc_w 398
    //   8853: aload 18
    //   8855: invokestatic 631	java/lang/String:valueOf	(Ljava/lang/Object;)Ljava/lang/String;
    //   8858: invokevirtual 634	java/lang/String:concat	(Ljava/lang/String;)Ljava/lang/String;
    //   8861: invokevirtual 634	java/lang/String:concat	(Ljava/lang/String;)Ljava/lang/String;
    //   8864: astore_3
    //   8865: aload_3
    //   8866: astore_0
    //   8867: iload 15
    //   8869: ifeq +8 -> 8877
    //   8872: aload_3
    //   8873: invokestatic 757	com/tencent/mm/booter/notification/a/h:rJ	(Ljava/lang/String;)Ljava/lang/String;
    //   8876: astore_0
    //   8877: aload 11
    //   8879: invokestatic 214	com/tencent/mm/sdk/platformtools/bs:isNullOrNil	(Ljava/lang/String;)Z
    //   8882: ifne +92 -> 8974
    //   8885: aload_2
    //   8886: invokestatic 848	com/tencent/mm/al/f:AM	(Ljava/lang/String;)Z
    //   8889: ifeq +85 -> 8974
    //   8892: invokestatic 852	com/tencent/mm/al/af:aCV	()Lcom/tencent/mm/al/i;
    //   8895: aload 11
    //   8897: invokevirtual 858	com/tencent/mm/al/i:AX	(Ljava/lang/String;)Lcom/tencent/mm/al/g;
    //   8900: astore_2
    //   8901: aload_2
    //   8902: ifnull +72 -> 8974
    //   8905: aload_2
    //   8906: getfield 863	com/tencent/mm/al/g:field_openId	Ljava/lang/String;
    //   8909: invokestatic 214	com/tencent/mm/sdk/platformtools/bs:isNullOrNil	(Ljava/lang/String;)Z
    //   8912: ifne +62 -> 8974
    //   8915: aload_2
    //   8916: getfield 864	com/tencent/mm/al/g:field_nickname	Ljava/lang/String;
    //   8919: invokestatic 214	com/tencent/mm/sdk/platformtools/bs:isNullOrNil	(Ljava/lang/String;)Z
    //   8922: ifne +52 -> 8974
    //   8925: iload 12
    //   8927: iconst_2
    //   8928: if_icmpeq +11 -> 8939
    //   8931: aload_2
    //   8932: getfield 867	com/tencent/mm/al/g:field_kfType	I
    //   8935: iconst_2
    //   8936: if_icmpne +38 -> 8974
    //   8939: aload 6
    //   8941: new 152	java/lang/StringBuilder
    //   8944: dup
    //   8945: ldc_w 450
    //   8948: invokespecial 575	java/lang/StringBuilder:<init>	(Ljava/lang/String;)V
    //   8951: aload 6
    //   8953: getfield 147	com/tencent/mm/pointers/PString:value	Ljava/lang/String;
    //   8956: invokevirtual 163	java/lang/StringBuilder:append	(Ljava/lang/String;)Ljava/lang/StringBuilder;
    //   8959: invokevirtual 167	java/lang/StringBuilder:toString	()Ljava/lang/String;
    //   8962: putfield 147	com/tencent/mm/pointers/PString:value	Ljava/lang/String;
    //   8965: aload 7
    //   8967: aload_2
    //   8968: getfield 864	com/tencent/mm/al/g:field_nickname	Ljava/lang/String;
    //   8971: putfield 147	com/tencent/mm/pointers/PString:value	Ljava/lang/String;
    //   8974: aload_0
    //   8975: invokestatic 110	com/tencent/mm/sdk/platformtools/bs:nullAsNil	(Ljava/lang/String;)Ljava/lang/String;
    //   8978: astore_0
    //   8979: ldc_w 360
    //   8982: invokestatic 53	com/tencent/matrix/trace/core/AppMethodBeat:o	(I)V
    //   8985: aload_0
    //   8986: areturn
    //   8987: aload 6
    //   8989: new 152	java/lang/StringBuilder
    //   8992: dup
    //   8993: invokespecial 153	java/lang/StringBuilder:<init>	()V
    //   8996: aload 5
    //   8998: ldc_w 868
    //   9001: invokevirtual 169	android/content/Context:getString	(I)Ljava/lang/String;
    //   9004: invokevirtual 163	java/lang/StringBuilder:append	(Ljava/lang/String;)Ljava/lang/StringBuilder;
    //   9007: ldc 123
    //   9009: invokevirtual 163	java/lang/StringBuilder:append	(Ljava/lang/String;)Ljava/lang/StringBuilder;
    //   9012: aload 19
    //   9014: invokevirtual 163	java/lang/StringBuilder:append	(Ljava/lang/String;)Ljava/lang/StringBuilder;
    //   9017: invokevirtual 167	java/lang/StringBuilder:toString	()Ljava/lang/String;
    //   9020: putfield 147	com/tencent/mm/pointers/PString:value	Ljava/lang/String;
    //   9023: goto -207 -> 8816
    //   9026: new 152	java/lang/StringBuilder
    //   9029: dup
    //   9030: invokespecial 153	java/lang/StringBuilder:<init>	()V
    //   9033: aload 7
    //   9035: getfield 147	com/tencent/mm/pointers/PString:value	Ljava/lang/String;
    //   9038: invokestatic 144	com/tencent/mm/model/v:wk	(Ljava/lang/String;)Ljava/lang/String;
    //   9041: invokevirtual 163	java/lang/StringBuilder:append	(Ljava/lang/String;)Ljava/lang/StringBuilder;
    //   9044: ldc 123
    //   9046: invokevirtual 163	java/lang/StringBuilder:append	(Ljava/lang/String;)Ljava/lang/StringBuilder;
    //   9049: aload 19
    //   9051: invokevirtual 163	java/lang/StringBuilder:append	(Ljava/lang/String;)Ljava/lang/StringBuilder;
    //   9054: invokevirtual 167	java/lang/StringBuilder:toString	()Ljava/lang/String;
    //   9057: astore_0
    //   9058: ldc_w 360
    //   9061: invokestatic 53	com/tencent/matrix/trace/core/AppMethodBeat:o	(I)V
    //   9064: aload_0
    //   9065: areturn
    //   9066: aload_3
    //   9067: ifnull +43 -> 9110
    //   9070: aload_3
    //   9071: invokevirtual 46	java/lang/String:length	()I
    //   9074: ifle +36 -> 9110
    //   9077: aload 6
    //   9079: aload_3
    //   9080: putfield 147	com/tencent/mm/pointers/PString:value	Ljava/lang/String;
    //   9083: aload_3
    //   9084: astore_0
    //   9085: iload 9
    //   9087: ifeq -252 -> 8835
    //   9090: iload 4
    //   9092: aload 6
    //   9094: aload 7
    //   9096: aload 8
    //   9098: invokestatic 843	com/tencent/mm/booter/notification/a/h:a	(ILcom/tencent/mm/pointers/PString;Lcom/tencent/mm/pointers/PString;Lcom/tencent/mm/pointers/PInt;)V
    //   9101: aload_3
    //   9102: astore_0
    //   9103: goto -268 -> 8835
    //   9106: astore_3
    //   9107: goto -1208 -> 7899
    //   9110: aload_0
    //   9111: astore_3
    //   9112: goto -29 -> 9083
    //   9115: ldc 26
    //   9117: astore_3
    //   9118: aconst_null
    //   9119: astore 18
    //   9121: iconst_0
    //   9122: istore 13
    //   9124: goto -8289 -> 835
    //   9127: aconst_null
    //   9128: astore 18
    //   9130: iconst_0
    //   9131: istore 13
    //   9133: aload_3
    //   9134: astore_0
    //   9135: aload 21
    //   9137: astore_3
    //   9138: goto -8303 -> 835
    //   9141: ldc 26
    //   9143: astore_0
    //   9144: goto -4262 -> 4882
    //   9147: goto -4420 -> 4727
    //   9150: goto -4608 -> 4542
    //   9153: aload_2
    //   9154: astore_0
    //   9155: goto -6771 -> 2384
    //   9158: aload_2
    //   9159: astore_0
    //   9160: goto -6771 -> 2389
    //   9163: iload 13
    //   9165: istore 14
    //   9167: goto -8884 -> 283
    //   9170: aload_3
    //   9171: astore 21
    //   9173: ldc 26
    //   9175: astore 20
    //   9177: ldc 26
    //   9179: astore 19
    //   9181: goto -8960 -> 221
    //   9184: iconst_0
    //   9185: istore 15
    //   9187: goto -9050 -> 137
    // Local variable table:
    //   start	length	slot	name	signature
    //   0	9190	0	paramString1	String
    //   0	9190	1	paramInt1	int
    //   0	9190	2	paramString2	String
    //   0	9190	3	paramString3	String
    //   0	9190	4	paramInt2	int
    //   0	9190	5	paramContext	Context
    //   0	9190	6	paramPString1	PString
    //   0	9190	7	paramPString2	PString
    //   0	9190	8	paramPInt	PInt
    //   0	9190	9	paramBoolean1	boolean
    //   0	9190	10	paramBoolean2	boolean
    //   0	9190	11	paramString4	String
    //   0	9190	12	paramInt3	int
    //   165	8999	13	i	int
    //   278	8888	14	j	int
    //   135	9051	15	k	int
    //   921	29	16	m	int
    //   12	69	17	bool	boolean
    //   247	4128	18	localObject1	Object
    //   4385	8	18	localException	Exception
    //   4568	4561	18	localObject2	Object
    //   182	8998	19	str1	String
    //   190	8986	20	str2	String
    //   219	8953	21	localObject3	Object
    //   4413	501	22	str3	String
    // Exception table:
    //   from	to	target	type
    //   4311	4322	4385	java/lang/Exception
    //   4324	4329	4385	java/lang/Exception
    //   7859	7871	7898	java/lang/Exception
    //   7873	7878	7898	java/lang/Exception
    //   7880	7886	9106	java/lang/Exception
  }
  
  private static void a(int paramInt, PString paramPString1, PString paramPString2, PInt paramPInt)
  {
    AppMethodBeat.i(20085);
    if ((paramPString1.value.length() == 32) && ((paramInt == 47) || (paramInt == 1048625)))
    {
      AppMethodBeat.o(20085);
      return;
    }
    if (paramPString1.value.length() >= 150) {
      paramPString1.value = paramPString1.value.substring(0, C(paramPString1.value, 150));
    }
    TextPaint localTextPaint = getTextPaint();
    if ((paramPString1.value.replace("%%", "").contains("%s")) || (localTextPaint == null))
    {
      paramPInt.value = 0;
      AppMethodBeat.o(20085);
      return;
    }
    try
    {
      paramPString2 = String.format(paramPString1.value, new Object[] { paramPString2.value });
      paramPString1.value = a(paramPString2, localTextPaint).toString();
      paramPInt.value = 1;
      AppMethodBeat.o(20085);
      return;
    }
    catch (Exception paramPString2)
    {
      for (;;)
      {
        paramPString2 = paramPString1.value;
      }
    }
  }
  
  private static boolean a(int paramInt, PString paramPString, String paramString)
  {
    AppMethodBeat.i(20081);
    if ((paramPString.value.length() == 32) && ((paramInt == 47) || (paramInt == 1048625)))
    {
      paramPString.value = paramString;
      AppMethodBeat.o(20081);
      return true;
    }
    AppMethodBeat.o(20081);
    return false;
  }
  
  public static String b(bo parambo, PString paramPString1, PString paramPString2, PInt paramPInt, boolean paramBoolean)
  {
    AppMethodBeat.i(20074);
    String str;
    if (parambo.fbA())
    {
      str = parambo.fci();
      if (!parambo.eZj()) {
        break label90;
      }
    }
    for (parambo = com.tencent.mm.pluginsdk.ui.span.k.aHF(a(parambo.field_imgPath, parambo.field_isSend, parambo.field_talker, str, parambo.getType(), com.tencent.mm.sdk.platformtools.ai.getContext(), paramPString1, paramPString2, paramPInt, true, paramBoolean, parambo.eSj, parambo.eSp));; parambo = a(parambo.field_imgPath, parambo.field_isSend, parambo.field_talker, str, parambo.getType(), com.tencent.mm.sdk.platformtools.ai.getContext(), paramPString1, paramPString2, paramPInt, true, paramBoolean, parambo.eSj, parambo.eSp))
    {
      parambo = bs.nullAsNil(parambo);
      AppMethodBeat.o(20074);
      return parambo;
      str = parambo.field_content;
      break;
      label90:
      str = com.tencent.mm.pluginsdk.ui.span.k.aHF(str);
    }
  }
  
  public static void b(TextPaint paramTextPaint)
  {
    AppMethodBeat.i(20090);
    if ((fpy == null) || (fpy.get() == null)) {
      fpy = new WeakReference(paramTextPaint);
    }
    AppMethodBeat.o(20090);
  }
  
  public static boolean b(String paramString, bo parambo)
  {
    AppMethodBeat.i(20070);
    if ((parambo != null) && (parambo.field_bizChatId != -1L) && (com.tencent.mm.al.f.so(paramString)))
    {
      AppMethodBeat.o(20070);
      return true;
    }
    AppMethodBeat.o(20070);
    return false;
  }
  
  private static String bT(Context paramContext)
  {
    AppMethodBeat.i(20078);
    boolean bool = u.axT();
    az.ayM();
    long l = bs.a((Long)com.tencent.mm.model.c.agA().get(65793, null), 0L);
    if (!bool)
    {
      paramContext = paramContext.getString(2131763356);
      AppMethodBeat.o(20078);
      return paramContext;
    }
    if (l == 0L)
    {
      paramContext = paramContext.getString(2131759554);
      AppMethodBeat.o(20078);
      return paramContext;
    }
    if (bs.pN(l) * 1000L > 1209600000L)
    {
      paramContext = paramContext.getString(2131759553, new Object[] { Long.valueOf(bs.pN(l) * 1000L / 86400000L) });
      AppMethodBeat.o(20078);
      return paramContext;
    }
    AppMethodBeat.o(20078);
    return "";
  }
  
  public static String d(Context paramContext, String paramString, boolean paramBoolean)
  {
    AppMethodBeat.i(20091);
    paramString = b.eXh().aMd(paramString);
    if (paramBoolean)
    {
      AppMethodBeat.o(20091);
      return paramString;
    }
    paramContext = paramContext.getString(2131760347);
    AppMethodBeat.o(20091);
    return paramContext;
  }
  
  public static String e(Context paramContext, String paramString, boolean paramBoolean)
  {
    AppMethodBeat.i(20093);
    if (paramBoolean)
    {
      paramContext = b.eXh().aMd(paramString);
      AppMethodBeat.o(20093);
      return paramContext;
    }
    paramContext = paramContext.getString(2131761718);
    AppMethodBeat.o(20093);
    return paramContext;
  }
  
  public static String f(Context paramContext, String paramString1, String paramString2)
  {
    AppMethodBeat.i(20072);
    if (w.sQ(paramString1))
    {
      paramString2 = bi.yl(paramString2);
      if (paramString2 != null) {
        paramString2 = v.wk(paramString2.trim());
      }
    }
    while (paramString1.contains("@bottle"))
    {
      paramContext = paramContext.getResources().getQuantityString(2131623959, 1, new Object[] { Integer.valueOf(1) });
      AppMethodBeat.o(20072);
      return paramContext;
      paramString2 = v.wk(paramString1);
      continue;
      paramString2 = v.wk(paramString1);
    }
    String str = paramString2;
    if (bs.isNullOrNil(paramString2))
    {
      str = paramString2;
      if (w.sQ(paramString1)) {
        str = paramContext.getString(2131757293);
      }
    }
    paramContext = b.eXh().aMd(str);
    AppMethodBeat.o(20072);
    return paramContext;
  }
  
  private static String f(String paramString1, String paramString2, String paramString3)
  {
    AppMethodBeat.i(20080);
    if ((bs.isNullOrNil(paramString1)) || (bs.isNullOrNil(paramString2)) || (bs.isNullOrNil(paramString3)))
    {
      AppMethodBeat.o(20080);
      return paramString1;
    }
    int i = paramString1.indexOf(paramString2);
    if (i < 0)
    {
      AppMethodBeat.o(20080);
      return paramString1;
    }
    paramString1 = paramString1.substring(0, i) + paramString3 + paramString1.substring(i + paramString2.length());
    AppMethodBeat.o(20080);
    return paramString1;
  }
  
  private static TextPaint getTextPaint()
  {
    AppMethodBeat.i(20089);
    if (fpy == null)
    {
      AppMethodBeat.o(20089);
      return null;
    }
    TextPaint localTextPaint = (TextPaint)fpy.get();
    AppMethodBeat.o(20089);
    return localTextPaint;
  }
  
  public static void kB(int paramInt)
  {
    fpz = paramInt;
  }
  
  public static void kC(int paramInt)
  {
    fpA = paramInt;
  }
  
  private static String rI(String paramString)
  {
    AppMethodBeat.i(20079);
    if (paramString != null)
    {
      paramString = paramString.replaceAll("%", "%%");
      AppMethodBeat.o(20079);
      return paramString;
    }
    AppMethodBeat.o(20079);
    return paramString;
  }
  
  private static String rJ(String paramString)
  {
    AppMethodBeat.i(20082);
    if (paramString != null)
    {
      paramString = paramString.replaceAll("%%", "%");
      AppMethodBeat.o(20082);
      return paramString;
    }
    AppMethodBeat.o(20082);
    return paramString;
  }
  
  private static boolean rK(String paramString)
  {
    AppMethodBeat.i(20083);
    if ((w.wM(paramString)) && (!u.axQ()))
    {
      AppMethodBeat.o(20083);
      return true;
    }
    if ((w.wO(paramString)) && (!u.axJ()))
    {
      AppMethodBeat.o(20083);
      return true;
    }
    if ((w.wS(paramString)) && (!u.axT()))
    {
      AppMethodBeat.o(20083);
      return true;
    }
    AppMethodBeat.o(20083);
    return false;
  }
  
  public static String rL(String paramString)
  {
    AppMethodBeat.i(20084);
    if (paramString == null)
    {
      AppMethodBeat.o(20084);
      return "";
    }
    if (paramString.length() < 150)
    {
      AppMethodBeat.o(20084);
      return paramString;
    }
    paramString = paramString.substring(0, 150) + "...";
    AppMethodBeat.o(20084);
    return paramString;
  }
}


/* Location:           L:\local\mybackup\temp\qq_apk\com.tencent.mm\classes3.jar
 * Qualified Name:     com.tencent.mm.booter.notification.a.h
 * JD-Core Version:    0.7.0.1
 */