package midas.x;

import com.pay.tool.APAppDataInterface;
import org.json.JSONArray;
import org.json.JSONException;
import org.json.JSONObject;

public class e3
  extends d2
{
  public e3(fc paramfc)
  {
    super(paramfc);
  }
  
  /* Error */
  public boolean d(gb paramgb)
  {
    // Byte code:
    //   0: aload_1
    //   1: getfield 21	midas/x/gb:b	Ljava/lang/String;
    //   4: astore 5
    //   6: new 23	java/lang/StringBuilder
    //   9: dup
    //   10: invokespecial 26	java/lang/StringBuilder:<init>	()V
    //   13: astore 6
    //   15: aload 6
    //   17: ldc 28
    //   19: invokevirtual 32	java/lang/StringBuilder:append	(Ljava/lang/String;)Ljava/lang/StringBuilder;
    //   22: pop
    //   23: aload 6
    //   25: aload 5
    //   27: invokevirtual 32	java/lang/StringBuilder:append	(Ljava/lang/String;)Ljava/lang/StringBuilder;
    //   30: pop
    //   31: ldc 34
    //   33: aload 6
    //   35: invokevirtual 38	java/lang/StringBuilder:toString	()Ljava/lang/String;
    //   38: invokestatic 44	com/tencent/midas/comm/APLog:i	(Ljava/lang/String;Ljava/lang/String;)V
    //   41: invokestatic 50	midas/x/p4:p	()Lmidas/x/p4;
    //   44: invokevirtual 54	midas/x/p4:e	()Lmidas/x/o4;
    //   47: getfield 59	midas/x/o4:b	Lcom/pay/api/request/APBaseRequest;
    //   50: ifnull +1397 -> 1447
    //   53: invokestatic 50	midas/x/p4:p	()Lmidas/x/p4;
    //   56: invokevirtual 54	midas/x/p4:e	()Lmidas/x/o4;
    //   59: getfield 59	midas/x/o4:b	Lcom/pay/api/request/APBaseRequest;
    //   62: instanceof 61
    //   65: ifne +6 -> 71
    //   68: goto +1379 -> 1447
    //   71: aload_0
    //   72: invokestatic 50	midas/x/p4:p	()Lmidas/x/p4;
    //   75: invokevirtual 54	midas/x/p4:e	()Lmidas/x/o4;
    //   78: putfield 65	midas/x/d2:n	Lmidas/x/o4;
    //   81: new 67	org/json/JSONObject
    //   84: dup
    //   85: aload 5
    //   87: invokespecial 70	org/json/JSONObject:<init>	(Ljava/lang/String;)V
    //   90: astore 6
    //   92: aload_0
    //   93: aload 6
    //   95: ldc 72
    //   97: invokevirtual 76	org/json/JSONObject:getString	(Ljava/lang/String;)Ljava/lang/String;
    //   100: invokestatic 82	java/lang/Integer:parseInt	(Ljava/lang/String;)I
    //   103: putfield 88	midas/x/ob:a	I
    //   106: aload_0
    //   107: aload 6
    //   109: ldc 90
    //   111: invokevirtual 76	org/json/JSONObject:getString	(Ljava/lang/String;)Ljava/lang/String;
    //   114: putfield 91	midas/x/ob:b	Ljava/lang/String;
    //   117: aload_0
    //   118: getfield 88	midas/x/ob:a	I
    //   121: istore_2
    //   122: iload_2
    //   123: ifne +1164 -> 1287
    //   126: aload 6
    //   128: ldc 93
    //   130: invokevirtual 97	org/json/JSONObject:getJSONObject	(Ljava/lang/String;)Lorg/json/JSONObject;
    //   133: astore 7
    //   135: aload 7
    //   137: ldc 99
    //   139: invokevirtual 103	org/json/JSONObject:has	(Ljava/lang/String;)Z
    //   142: ifeq +21 -> 163
    //   145: aload 7
    //   147: ldc 99
    //   149: invokevirtual 76	org/json/JSONObject:getString	(Ljava/lang/String;)Ljava/lang/String;
    //   152: astore 5
    //   154: aload 5
    //   156: invokestatic 82	java/lang/Integer:parseInt	(Ljava/lang/String;)I
    //   159: istore_2
    //   160: goto +5 -> 165
    //   163: iconst_0
    //   164: istore_2
    //   165: aload 7
    //   167: ldc 105
    //   169: invokevirtual 103	org/json/JSONObject:has	(Ljava/lang/String;)Z
    //   172: ifeq +9 -> 181
    //   175: aload_0
    //   176: aload 7
    //   178: invokevirtual 109	midas/x/e3:t	(Lorg/json/JSONObject;)V
    //   181: ldc 111
    //   183: aload_0
    //   184: getfield 65	midas/x/d2:n	Lmidas/x/o4;
    //   187: getfield 59	midas/x/o4:b	Lcom/pay/api/request/APBaseRequest;
    //   190: getfield 116	com/pay/api/request/APBaseRequest:acctType	Ljava/lang/String;
    //   193: invokevirtual 122	java/lang/String:equals	(Ljava/lang/Object;)Z
    //   196: istore_3
    //   197: iload_3
    //   198: ifeq +60 -> 258
    //   201: aload_0
    //   202: getfield 65	midas/x/d2:n	Lmidas/x/o4;
    //   205: getfield 126	midas/x/o4:c	Lmidas/x/w4;
    //   208: checkcast 128	midas/x/a5
    //   211: astore 5
    //   213: aload 5
    //   215: aload 7
    //   217: ldc 130
    //   219: invokevirtual 76	org/json/JSONObject:getString	(Ljava/lang/String;)Ljava/lang/String;
    //   222: putfield 134	midas/x/w4:a	Ljava/lang/String;
    //   225: aload 5
    //   227: aload 7
    //   229: ldc 136
    //   231: invokevirtual 76	org/json/JSONObject:getString	(Ljava/lang/String;)Ljava/lang/String;
    //   234: putfield 137	midas/x/w4:b	Ljava/lang/String;
    //   237: aload 5
    //   239: aload 7
    //   241: ldc 139
    //   243: invokevirtual 76	org/json/JSONObject:getString	(Ljava/lang/String;)Ljava/lang/String;
    //   246: putfield 141	midas/x/w4:c	Ljava/lang/String;
    //   249: aload 5
    //   251: iload_2
    //   252: putfield 143	midas/x/w4:e	I
    //   255: goto +57 -> 312
    //   258: aload_0
    //   259: getfield 65	midas/x/d2:n	Lmidas/x/o4;
    //   262: getfield 126	midas/x/o4:c	Lmidas/x/w4;
    //   265: checkcast 145	midas/x/x4
    //   268: astore 5
    //   270: aload 5
    //   272: aload 7
    //   274: ldc 130
    //   276: invokevirtual 76	org/json/JSONObject:getString	(Ljava/lang/String;)Ljava/lang/String;
    //   279: putfield 134	midas/x/w4:a	Ljava/lang/String;
    //   282: aload 5
    //   284: aload 7
    //   286: ldc 136
    //   288: invokevirtual 76	org/json/JSONObject:getString	(Ljava/lang/String;)Ljava/lang/String;
    //   291: putfield 137	midas/x/w4:b	Ljava/lang/String;
    //   294: aload 5
    //   296: aload 7
    //   298: ldc 139
    //   300: invokevirtual 76	org/json/JSONObject:getString	(Ljava/lang/String;)Ljava/lang/String;
    //   303: putfield 141	midas/x/w4:c	Ljava/lang/String;
    //   306: aload 5
    //   308: iload_2
    //   309: putfield 143	midas/x/w4:e	I
    //   312: aload 7
    //   314: ldc 147
    //   316: invokevirtual 76	org/json/JSONObject:getString	(Ljava/lang/String;)Ljava/lang/String;
    //   319: astore 5
    //   321: goto +7 -> 328
    //   324: ldc 149
    //   326: astore 5
    //   328: aload_0
    //   329: getfield 65	midas/x/d2:n	Lmidas/x/o4;
    //   332: getfield 153	midas/x/o4:f	Lmidas/x/d5;
    //   335: aload 5
    //   337: putfield 157	midas/x/d5:i	Ljava/lang/String;
    //   340: aload_0
    //   341: getfield 65	midas/x/d2:n	Lmidas/x/o4;
    //   344: getfield 153	midas/x/o4:f	Lmidas/x/d5;
    //   347: aload 5
    //   349: putfield 160	midas/x/d5:j	Ljava/lang/String;
    //   352: aload_0
    //   353: invokevirtual 162	midas/x/ob:b	()Ljava/lang/String;
    //   356: astore 5
    //   358: aload 5
    //   360: invokestatic 168	android/text/TextUtils:isEmpty	(Ljava/lang/CharSequence;)Z
    //   363: ifeq +10 -> 373
    //   366: ldc 170
    //   368: ldc 172
    //   370: invokestatic 174	com/tencent/midas/comm/APLog:e	(Ljava/lang/String;Ljava/lang/String;)V
    //   373: aload_0
    //   374: aload 7
    //   376: invokevirtual 176	midas/x/d2:j	(Lorg/json/JSONObject;)V
    //   379: aload 7
    //   381: ldc 178
    //   383: aload 5
    //   385: invokestatic 183	midas/x/n4:d	(Lorg/json/JSONObject;Ljava/lang/String;Ljava/lang/String;)Ljava/lang/String;
    //   388: ldc 185
    //   390: invokevirtual 122	java/lang/String:equals	(Ljava/lang/Object;)Z
    //   393: ifeq +17 -> 410
    //   396: aload_0
    //   397: getfield 65	midas/x/d2:n	Lmidas/x/o4;
    //   400: getfield 188	midas/x/o4:e	Lmidas/x/c5;
    //   403: iconst_1
    //   404: putfield 193	midas/x/c5:d	Z
    //   407: goto +14 -> 421
    //   410: aload_0
    //   411: getfield 65	midas/x/d2:n	Lmidas/x/o4;
    //   414: getfield 188	midas/x/o4:e	Lmidas/x/c5;
    //   417: iconst_0
    //   418: putfield 193	midas/x/c5:d	Z
    //   421: aload 7
    //   423: ldc 195
    //   425: aload 5
    //   427: invokestatic 183	midas/x/n4:d	(Lorg/json/JSONObject;Ljava/lang/String;Ljava/lang/String;)Ljava/lang/String;
    //   430: ldc 185
    //   432: invokevirtual 122	java/lang/String:equals	(Ljava/lang/Object;)Z
    //   435: ifeq +17 -> 452
    //   438: aload_0
    //   439: getfield 65	midas/x/d2:n	Lmidas/x/o4;
    //   442: getfield 188	midas/x/o4:e	Lmidas/x/c5;
    //   445: iconst_1
    //   446: putfield 197	midas/x/c5:c	Z
    //   449: goto +14 -> 463
    //   452: aload_0
    //   453: getfield 65	midas/x/d2:n	Lmidas/x/o4;
    //   456: getfield 188	midas/x/o4:e	Lmidas/x/c5;
    //   459: iconst_0
    //   460: putfield 197	midas/x/c5:c	Z
    //   463: aload 7
    //   465: ldc 199
    //   467: aload 5
    //   469: invokestatic 183	midas/x/n4:d	(Lorg/json/JSONObject;Ljava/lang/String;Ljava/lang/String;)Ljava/lang/String;
    //   472: astore 8
    //   474: aload_0
    //   475: getfield 65	midas/x/d2:n	Lmidas/x/o4;
    //   478: getfield 188	midas/x/o4:e	Lmidas/x/c5;
    //   481: iconst_0
    //   482: putfield 201	midas/x/c5:e	Z
    //   485: aload 8
    //   487: ldc 185
    //   489: invokevirtual 122	java/lang/String:equals	(Ljava/lang/Object;)Z
    //   492: ifeq +17 -> 509
    //   495: aload_0
    //   496: getfield 65	midas/x/d2:n	Lmidas/x/o4;
    //   499: getfield 188	midas/x/o4:e	Lmidas/x/c5;
    //   502: iconst_1
    //   503: putfield 201	midas/x/c5:e	Z
    //   506: goto +14 -> 520
    //   509: aload_0
    //   510: getfield 65	midas/x/d2:n	Lmidas/x/o4;
    //   513: getfield 188	midas/x/o4:e	Lmidas/x/c5;
    //   516: iconst_0
    //   517: putfield 201	midas/x/c5:e	Z
    //   520: new 23	java/lang/StringBuilder
    //   523: dup
    //   524: invokespecial 26	java/lang/StringBuilder:<init>	()V
    //   527: astore 8
    //   529: aload 8
    //   531: ldc 203
    //   533: invokevirtual 32	java/lang/StringBuilder:append	(Ljava/lang/String;)Ljava/lang/StringBuilder;
    //   536: pop
    //   537: aload 8
    //   539: aload_0
    //   540: getfield 65	midas/x/d2:n	Lmidas/x/o4;
    //   543: getfield 188	midas/x/o4:e	Lmidas/x/c5;
    //   546: getfield 201	midas/x/c5:e	Z
    //   549: invokevirtual 206	java/lang/StringBuilder:append	(Z)Ljava/lang/StringBuilder;
    //   552: pop
    //   553: ldc 208
    //   555: aload 8
    //   557: invokevirtual 38	java/lang/StringBuilder:toString	()Ljava/lang/String;
    //   560: invokestatic 211	com/tencent/midas/comm/APLog:w	(Ljava/lang/String;Ljava/lang/String;)V
    //   563: aload_0
    //   564: getfield 65	midas/x/d2:n	Lmidas/x/o4;
    //   567: getfield 188	midas/x/o4:e	Lmidas/x/c5;
    //   570: iconst_0
    //   571: putfield 213	midas/x/c5:b	Z
    //   574: aload 7
    //   576: ldc 215
    //   578: invokevirtual 103	org/json/JSONObject:has	(Ljava/lang/String;)Z
    //   581: ifeq +29 -> 610
    //   584: aload 7
    //   586: ldc 215
    //   588: invokevirtual 76	org/json/JSONObject:getString	(Ljava/lang/String;)Ljava/lang/String;
    //   591: ldc 185
    //   593: invokevirtual 122	java/lang/String:equals	(Ljava/lang/Object;)Z
    //   596: ifeq +14 -> 610
    //   599: aload_0
    //   600: getfield 65	midas/x/d2:n	Lmidas/x/o4;
    //   603: getfield 188	midas/x/o4:e	Lmidas/x/c5;
    //   606: iconst_1
    //   607: putfield 213	midas/x/c5:b	Z
    //   610: aload 7
    //   612: ldc 217
    //   614: aload 5
    //   616: invokestatic 183	midas/x/n4:d	(Lorg/json/JSONObject;Ljava/lang/String;Ljava/lang/String;)Ljava/lang/String;
    //   619: astore 8
    //   621: aload 8
    //   623: invokestatic 82	java/lang/Integer:parseInt	(Ljava/lang/String;)I
    //   626: istore_2
    //   627: goto +5 -> 632
    //   630: iconst_0
    //   631: istore_2
    //   632: aload_0
    //   633: getfield 65	midas/x/d2:n	Lmidas/x/o4;
    //   636: getfield 188	midas/x/o4:e	Lmidas/x/c5;
    //   639: iload_2
    //   640: putfield 220	midas/x/c5:g	I
    //   643: invokestatic 226	midas/x/c6:s0	()Lmidas/x/c6;
    //   646: astore 8
    //   648: aload 7
    //   650: ldc 228
    //   652: invokevirtual 103	org/json/JSONObject:has	(Ljava/lang/String;)Z
    //   655: ifeq +9 -> 664
    //   658: aload_0
    //   659: aload 7
    //   661: invokevirtual 231	midas/x/d2:r	(Lorg/json/JSONObject;)V
    //   664: new 23	java/lang/StringBuilder
    //   667: dup
    //   668: invokespecial 26	java/lang/StringBuilder:<init>	()V
    //   671: astore 9
    //   673: aload 9
    //   675: ldc 233
    //   677: invokevirtual 32	java/lang/StringBuilder:append	(Ljava/lang/String;)Ljava/lang/StringBuilder;
    //   680: pop
    //   681: aload 9
    //   683: aload_0
    //   684: getfield 65	midas/x/d2:n	Lmidas/x/o4;
    //   687: getfield 188	midas/x/o4:e	Lmidas/x/c5;
    //   690: getfield 236	midas/x/c5:k	Ljava/lang/String;
    //   693: invokevirtual 32	java/lang/StringBuilder:append	(Ljava/lang/String;)Ljava/lang/StringBuilder;
    //   696: pop
    //   697: ldc 208
    //   699: aload 9
    //   701: invokevirtual 38	java/lang/StringBuilder:toString	()Ljava/lang/String;
    //   704: invokestatic 211	com/tencent/midas/comm/APLog:w	(Ljava/lang/String;Ljava/lang/String;)V
    //   707: aload 7
    //   709: ldc 238
    //   711: invokevirtual 103	org/json/JSONObject:has	(Ljava/lang/String;)Z
    //   714: istore_3
    //   715: iload_3
    //   716: ifeq +15 -> 731
    //   719: aload 8
    //   721: aload 7
    //   723: ldc 238
    //   725: invokevirtual 76	org/json/JSONObject:getString	(Ljava/lang/String;)Ljava/lang/String;
    //   728: invokevirtual 240	midas/x/c6:p	(Ljava/lang/String;)V
    //   731: aload 7
    //   733: ldc 242
    //   735: invokevirtual 103	org/json/JSONObject:has	(Ljava/lang/String;)Z
    //   738: ifeq +735 -> 1473
    //   741: aload_0
    //   742: aload 7
    //   744: invokevirtual 245	midas/x/d2:i	(Lorg/json/JSONObject;)Z
    //   747: istore_3
    //   748: goto +3 -> 751
    //   751: aload 7
    //   753: ldc 247
    //   755: invokevirtual 103	org/json/JSONObject:has	(Ljava/lang/String;)Z
    //   758: ifeq +9 -> 767
    //   761: aload_0
    //   762: aload 7
    //   764: invokevirtual 249	midas/x/d2:p	(Lorg/json/JSONObject;)V
    //   767: aload 7
    //   769: ldc 251
    //   771: invokevirtual 103	org/json/JSONObject:has	(Ljava/lang/String;)Z
    //   774: ifeq +9 -> 783
    //   777: aload_0
    //   778: aload 7
    //   780: invokevirtual 253	midas/x/d2:b	(Lorg/json/JSONObject;)V
    //   783: aload 7
    //   785: ldc 255
    //   787: invokevirtual 103	org/json/JSONObject:has	(Ljava/lang/String;)Z
    //   790: ifeq +16 -> 806
    //   793: invokestatic 261	midas/x/p:o	()Lmidas/x/p;
    //   796: aload 7
    //   798: ldc 255
    //   800: invokevirtual 76	org/json/JSONObject:getString	(Ljava/lang/String;)Ljava/lang/String;
    //   803: invokevirtual 263	midas/x/p:c	(Ljava/lang/String;)V
    //   806: aload 7
    //   808: ldc_w 265
    //   811: invokevirtual 103	org/json/JSONObject:has	(Ljava/lang/String;)Z
    //   814: ifeq +186 -> 1000
    //   817: aload 7
    //   819: ldc_w 265
    //   822: invokevirtual 97	org/json/JSONObject:getJSONObject	(Ljava/lang/String;)Lorg/json/JSONObject;
    //   825: astore 8
    //   827: aload 8
    //   829: ldc_w 267
    //   832: invokevirtual 103	org/json/JSONObject:has	(Ljava/lang/String;)Z
    //   835: ifne +47 -> 882
    //   838: aload 8
    //   840: ldc_w 269
    //   843: invokevirtual 103	org/json/JSONObject:has	(Ljava/lang/String;)Z
    //   846: ifne +36 -> 882
    //   849: aload 8
    //   851: ldc_w 271
    //   854: invokevirtual 103	org/json/JSONObject:has	(Ljava/lang/String;)Z
    //   857: ifne +25 -> 882
    //   860: aload 8
    //   862: ldc_w 273
    //   865: invokevirtual 103	org/json/JSONObject:has	(Ljava/lang/String;)Z
    //   868: ifne +14 -> 882
    //   871: aload 8
    //   873: ldc_w 275
    //   876: invokevirtual 103	org/json/JSONObject:has	(Ljava/lang/String;)Z
    //   879: ifeq +16 -> 895
    //   882: invokestatic 280	midas/x/d0:i	()Lmidas/x/d0;
    //   885: aload 8
    //   887: invokevirtual 281	org/json/JSONObject:toString	()Ljava/lang/String;
    //   890: invokevirtual 283	midas/x/d0:a	(Ljava/lang/String;)V
    //   893: iconst_1
    //   894: istore_3
    //   895: aload 7
    //   897: ldc 251
    //   899: invokevirtual 97	org/json/JSONObject:getJSONObject	(Ljava/lang/String;)Lorg/json/JSONObject;
    //   902: astore 9
    //   904: aload 9
    //   906: ldc_w 285
    //   909: invokevirtual 103	org/json/JSONObject:has	(Ljava/lang/String;)Z
    //   912: ifeq +44 -> 956
    //   915: ldc 185
    //   917: invokestatic 290	midas/x/x:f	()Lmidas/x/x;
    //   920: invokevirtual 292	midas/x/x:e	()Ljava/lang/String;
    //   923: invokevirtual 122	java/lang/String:equals	(Ljava/lang/Object;)Z
    //   926: ifeq +30 -> 956
    //   929: ldc 185
    //   931: aload 9
    //   933: ldc_w 285
    //   936: invokevirtual 76	org/json/JSONObject:getString	(Ljava/lang/String;)Ljava/lang/String;
    //   939: invokevirtual 122	java/lang/String:equals	(Ljava/lang/Object;)Z
    //   942: ifeq +14 -> 956
    //   945: invokestatic 290	midas/x/x:f	()Lmidas/x/x;
    //   948: ldc 185
    //   950: invokevirtual 294	midas/x/x:d	(Ljava/lang/String;)V
    //   953: goto +12 -> 965
    //   956: invokestatic 290	midas/x/x:f	()Lmidas/x/x;
    //   959: ldc_w 296
    //   962: invokevirtual 294	midas/x/x:d	(Ljava/lang/String;)V
    //   965: invokestatic 280	midas/x/d0:i	()Lmidas/x/d0;
    //   968: aload 8
    //   970: invokevirtual 298	midas/x/d0:g	(Lorg/json/JSONObject;)V
    //   973: invokestatic 280	midas/x/d0:i	()Lmidas/x/d0;
    //   976: aload 8
    //   978: invokevirtual 300	midas/x/d0:e	(Lorg/json/JSONObject;)Z
    //   981: istore 4
    //   983: invokestatic 305	midas/x/j6:e	()Lmidas/x/j6;
    //   986: iload 4
    //   988: invokevirtual 308	midas/x/j6:a	(Z)V
    //   991: aload_0
    //   992: aload 8
    //   994: invokevirtual 310	midas/x/d2:o	(Lorg/json/JSONObject;)V
    //   997: goto +25 -> 1022
    //   1000: ldc_w 312
    //   1003: ldc_w 314
    //   1006: invokestatic 44	com/tencent/midas/comm/APLog:i	(Ljava/lang/String;Ljava/lang/String;)V
    //   1009: invokestatic 305	midas/x/j6:e	()Lmidas/x/j6;
    //   1012: iconst_0
    //   1013: invokevirtual 308	midas/x/j6:a	(Z)V
    //   1016: invokestatic 261	midas/x/p:o	()Lmidas/x/p;
    //   1019: invokevirtual 316	midas/x/p:a	()V
    //   1022: invokestatic 261	midas/x/p:o	()Lmidas/x/p;
    //   1025: invokevirtual 319	midas/x/p:g	()Z
    //   1028: istore 4
    //   1030: invokestatic 261	midas/x/p:o	()Lmidas/x/p;
    //   1033: iconst_1
    //   1034: invokevirtual 320	midas/x/p:a	(Z)V
    //   1037: invokestatic 261	midas/x/p:o	()Lmidas/x/p;
    //   1040: invokevirtual 323	midas/x/p:h	()Z
    //   1043: ifne +11 -> 1054
    //   1046: invokestatic 261	midas/x/p:o	()Lmidas/x/p;
    //   1049: ldc 149
    //   1051: invokevirtual 263	midas/x/p:c	(Ljava/lang/String;)V
    //   1054: invokestatic 261	midas/x/p:o	()Lmidas/x/p;
    //   1057: iload 4
    //   1059: invokevirtual 320	midas/x/p:a	(Z)V
    //   1062: new 23	java/lang/StringBuilder
    //   1065: dup
    //   1066: invokespecial 26	java/lang/StringBuilder:<init>	()V
    //   1069: astore 8
    //   1071: aload 8
    //   1073: ldc_w 325
    //   1076: invokevirtual 32	java/lang/StringBuilder:append	(Ljava/lang/String;)Ljava/lang/StringBuilder;
    //   1079: pop
    //   1080: aload 8
    //   1082: iload_3
    //   1083: invokevirtual 206	java/lang/StringBuilder:append	(Z)Ljava/lang/StringBuilder;
    //   1086: pop
    //   1087: ldc 34
    //   1089: aload 8
    //   1091: invokevirtual 38	java/lang/StringBuilder:toString	()Ljava/lang/String;
    //   1094: invokestatic 44	com/tencent/midas/comm/APLog:i	(Ljava/lang/String;Ljava/lang/String;)V
    //   1097: iload_3
    //   1098: ifne +16 -> 1114
    //   1101: invokestatic 280	midas/x/d0:i	()Lmidas/x/d0;
    //   1104: aconst_null
    //   1105: invokevirtual 283	midas/x/d0:a	(Ljava/lang/String;)V
    //   1108: invokestatic 290	midas/x/x:f	()Lmidas/x/x;
    //   1111: invokevirtual 326	midas/x/x:a	()V
    //   1114: aload 7
    //   1116: ldc_w 328
    //   1119: invokevirtual 103	org/json/JSONObject:has	(Ljava/lang/String;)Z
    //   1122: ifeq +17 -> 1139
    //   1125: aload 7
    //   1127: ldc_w 328
    //   1130: invokevirtual 76	org/json/JSONObject:getString	(Ljava/lang/String;)Ljava/lang/String;
    //   1133: putstatic 333	com/pay/paychannel/hfpay/APHFChannel:v	Ljava/lang/String;
    //   1136: goto +8 -> 1144
    //   1139: ldc 149
    //   1141: putstatic 333	com/pay/paychannel/hfpay/APHFChannel:v	Ljava/lang/String;
    //   1144: aload 7
    //   1146: ldc_w 335
    //   1149: invokevirtual 103	org/json/JSONObject:has	(Ljava/lang/String;)Z
    //   1152: ifeq +25 -> 1177
    //   1155: aload 7
    //   1157: ldc_w 335
    //   1160: invokevirtual 338	org/json/JSONObject:getInt	(Ljava/lang/String;)I
    //   1163: iconst_1
    //   1164: if_icmpne +13 -> 1177
    //   1167: invokestatic 226	midas/x/c6:s0	()Lmidas/x/c6;
    //   1170: iconst_1
    //   1171: invokevirtual 340	midas/x/c6:t	(Z)V
    //   1174: goto +10 -> 1184
    //   1177: invokestatic 226	midas/x/c6:s0	()Lmidas/x/c6;
    //   1180: iconst_0
    //   1181: invokevirtual 340	midas/x/c6:t	(Z)V
    //   1184: aload 7
    //   1186: ldc_w 342
    //   1189: aload 5
    //   1191: invokestatic 345	midas/x/n4:a	(Lorg/json/JSONObject;Ljava/lang/String;Ljava/lang/String;)I
    //   1194: istore_2
    //   1195: aload_0
    //   1196: getfield 65	midas/x/d2:n	Lmidas/x/o4;
    //   1199: getfield 188	midas/x/o4:e	Lmidas/x/c5;
    //   1202: iload_2
    //   1203: putfield 347	midas/x/c5:h	I
    //   1206: new 23	java/lang/StringBuilder
    //   1209: dup
    //   1210: invokespecial 26	java/lang/StringBuilder:<init>	()V
    //   1213: astore 5
    //   1215: aload 5
    //   1217: ldc_w 349
    //   1220: invokevirtual 32	java/lang/StringBuilder:append	(Ljava/lang/String;)Ljava/lang/StringBuilder;
    //   1223: pop
    //   1224: aload 5
    //   1226: iload_2
    //   1227: invokevirtual 352	java/lang/StringBuilder:append	(I)Ljava/lang/StringBuilder;
    //   1230: pop
    //   1231: ldc_w 354
    //   1234: aload 5
    //   1236: invokevirtual 38	java/lang/StringBuilder:toString	()Ljava/lang/String;
    //   1239: invokestatic 44	com/tencent/midas/comm/APLog:i	(Ljava/lang/String;Ljava/lang/String;)V
    //   1242: aload_0
    //   1243: aload 7
    //   1245: invokevirtual 357	midas/x/e3:u	(Lorg/json/JSONObject;)V
    //   1248: aload_0
    //   1249: aload 7
    //   1251: invokevirtual 359	midas/x/d2:k	(Lorg/json/JSONObject;)V
    //   1254: aload_0
    //   1255: aload 7
    //   1257: invokevirtual 361	midas/x/d2:e	(Lorg/json/JSONObject;)V
    //   1260: aload_0
    //   1261: aload 7
    //   1263: invokevirtual 363	midas/x/e3:v	(Lorg/json/JSONObject;)V
    //   1266: aload_0
    //   1267: aload 7
    //   1269: invokevirtual 366	midas/x/d2:l	(Lorg/json/JSONObject;)V
    //   1272: aload_0
    //   1273: aload 7
    //   1275: invokevirtual 369	midas/x/d2:m	(Lorg/json/JSONObject;)V
    //   1278: aload_0
    //   1279: aload 7
    //   1281: invokevirtual 371	midas/x/d2:h	(Lorg/json/JSONObject;)V
    //   1284: goto +70 -> 1354
    //   1287: aload 6
    //   1289: ldc_w 373
    //   1292: invokevirtual 76	org/json/JSONObject:getString	(Ljava/lang/String;)Ljava/lang/String;
    //   1295: invokevirtual 374	java/lang/String:toString	()Ljava/lang/String;
    //   1298: astore 5
    //   1300: aload 5
    //   1302: ldc 149
    //   1304: invokevirtual 122	java/lang/String:equals	(Ljava/lang/Object;)Z
    //   1307: ifne +47 -> 1354
    //   1310: new 23	java/lang/StringBuilder
    //   1313: dup
    //   1314: invokespecial 26	java/lang/StringBuilder:<init>	()V
    //   1317: astore 7
    //   1319: aload 7
    //   1321: ldc_w 376
    //   1324: invokevirtual 32	java/lang/StringBuilder:append	(Ljava/lang/String;)Ljava/lang/StringBuilder;
    //   1327: pop
    //   1328: aload 7
    //   1330: aload 5
    //   1332: invokevirtual 32	java/lang/StringBuilder:append	(Ljava/lang/String;)Ljava/lang/StringBuilder;
    //   1335: pop
    //   1336: aload 7
    //   1338: ldc_w 378
    //   1341: invokevirtual 32	java/lang/StringBuilder:append	(Ljava/lang/String;)Ljava/lang/StringBuilder;
    //   1344: pop
    //   1345: aload_0
    //   1346: aload 7
    //   1348: invokevirtual 38	java/lang/StringBuilder:toString	()Ljava/lang/String;
    //   1351: putfield 91	midas/x/ob:b	Ljava/lang/String;
    //   1354: aload 6
    //   1356: ldc 93
    //   1358: invokevirtual 103	org/json/JSONObject:has	(Ljava/lang/String;)Z
    //   1361: ifeq +80 -> 1441
    //   1364: aload 6
    //   1366: ldc 93
    //   1368: invokevirtual 97	org/json/JSONObject:getJSONObject	(Ljava/lang/String;)Lorg/json/JSONObject;
    //   1371: astore 5
    //   1373: aload_0
    //   1374: aload 5
    //   1376: invokevirtual 379	midas/x/d2:g	(Lorg/json/JSONObject;)V
    //   1379: aload_0
    //   1380: aload 5
    //   1382: invokevirtual 381	midas/x/e3:w	(Lorg/json/JSONObject;)V
    //   1385: aload_0
    //   1386: aload 5
    //   1388: invokevirtual 383	midas/x/d2:d	(Lorg/json/JSONObject;)V
    //   1391: aload_0
    //   1392: aload 5
    //   1394: invokevirtual 385	midas/x/d2:f	(Lorg/json/JSONObject;)V
    //   1397: aload_0
    //   1398: aload 5
    //   1400: invokevirtual 388	midas/x/d2:s	(Lorg/json/JSONObject;)V
    //   1403: aload_0
    //   1404: aload 5
    //   1406: invokevirtual 390	midas/x/d2:c	(Lorg/json/JSONObject;)V
    //   1409: aload_0
    //   1410: aload 5
    //   1412: invokevirtual 392	midas/x/d2:a	(Lorg/json/JSONObject;)V
    //   1415: aload_0
    //   1416: aload 5
    //   1418: invokevirtual 394	midas/x/d2:n	(Lorg/json/JSONObject;)V
    //   1421: goto +20 -> 1441
    //   1424: astore 5
    //   1426: aload 5
    //   1428: invokevirtual 397	org/json/JSONException:printStackTrace	()V
    //   1431: ldc 34
    //   1433: aload 5
    //   1435: invokevirtual 400	org/json/JSONException:getMessage	()Ljava/lang/String;
    //   1438: invokestatic 211	com/tencent/midas/comm/APLog:w	(Ljava/lang/String;Ljava/lang/String;)V
    //   1441: aload_0
    //   1442: aload_1
    //   1443: invokespecial 402	midas/x/ob:d	(Lmidas/x/gb;)Z
    //   1446: ireturn
    //   1447: aload_0
    //   1448: aload_1
    //   1449: invokespecial 402	midas/x/ob:d	(Lmidas/x/gb;)Z
    //   1452: ireturn
    //   1453: astore 5
    //   1455: goto -1292 -> 163
    //   1458: astore 5
    //   1460: goto -1136 -> 324
    //   1463: astore 8
    //   1465: goto -835 -> 630
    //   1468: astore 8
    //   1470: goto -739 -> 731
    //   1473: iconst_0
    //   1474: istore_3
    //   1475: goto -724 -> 751
    // Local variable table:
    //   start	length	slot	name	signature
    //   0	1478	0	this	e3
    //   0	1478	1	paramgb	gb
    //   121	1106	2	i	int
    //   196	1279	3	bool1	boolean
    //   981	77	4	bool2	boolean
    //   4	1413	5	localObject1	Object
    //   1424	10	5	localJSONException	JSONException
    //   1453	1	5	localException1	Exception
    //   1458	1	5	localException2	Exception
    //   13	1352	6	localObject2	Object
    //   133	1214	7	localObject3	Object
    //   472	618	8	localObject4	Object
    //   1463	1	8	localException3	Exception
    //   1468	1	8	localException4	Exception
    //   671	261	9	localObject5	Object
    // Exception table:
    //   from	to	target	type
    //   81	122	1424	org/json/JSONException
    //   126	154	1424	org/json/JSONException
    //   165	181	1424	org/json/JSONException
    //   181	197	1424	org/json/JSONException
    //   201	255	1424	org/json/JSONException
    //   258	312	1424	org/json/JSONException
    //   328	373	1424	org/json/JSONException
    //   373	407	1424	org/json/JSONException
    //   410	421	1424	org/json/JSONException
    //   421	449	1424	org/json/JSONException
    //   452	463	1424	org/json/JSONException
    //   463	506	1424	org/json/JSONException
    //   509	520	1424	org/json/JSONException
    //   520	610	1424	org/json/JSONException
    //   610	621	1424	org/json/JSONException
    //   632	664	1424	org/json/JSONException
    //   664	715	1424	org/json/JSONException
    //   731	748	1424	org/json/JSONException
    //   751	767	1424	org/json/JSONException
    //   767	783	1424	org/json/JSONException
    //   783	806	1424	org/json/JSONException
    //   806	871	1424	org/json/JSONException
    //   871	882	1424	org/json/JSONException
    //   882	893	1424	org/json/JSONException
    //   895	953	1424	org/json/JSONException
    //   956	965	1424	org/json/JSONException
    //   965	997	1424	org/json/JSONException
    //   1000	1022	1424	org/json/JSONException
    //   1022	1054	1424	org/json/JSONException
    //   1054	1097	1424	org/json/JSONException
    //   1101	1114	1424	org/json/JSONException
    //   1114	1136	1424	org/json/JSONException
    //   1139	1144	1424	org/json/JSONException
    //   1144	1174	1424	org/json/JSONException
    //   1177	1184	1424	org/json/JSONException
    //   1184	1284	1424	org/json/JSONException
    //   1287	1354	1424	org/json/JSONException
    //   1354	1421	1424	org/json/JSONException
    //   154	160	1453	java/lang/Exception
    //   312	321	1458	java/lang/Exception
    //   621	627	1463	java/lang/Exception
    //   719	731	1468	java/lang/Exception
  }
  
  public String l()
  {
    return this.m;
  }
  
  public final void t(JSONObject paramJSONObject)
  {
    try
    {
      Object localObject = paramJSONObject.getJSONObject("frindspay_info");
      ((JSONObject)localObject).getString("friendspay_url");
      paramJSONObject = ((JSONObject)localObject).getString("friendspay_title");
      String str = ((JSONObject)localObject).getString("friendspay_summay");
      localObject = ((JSONObject)localObject).getString("friendspay_gameimageurl");
      APAppDataInterface.singleton().d((String)localObject);
      APAppDataInterface.singleton().l(paramJSONObject);
      APAppDataInterface.singleton().o(str);
      return;
    }
    catch (Exception paramJSONObject)
    {
      paramJSONObject.printStackTrace();
    }
  }
  
  public final void u(JSONObject paramJSONObject)
  {
    try
    {
      paramJSONObject = paramJSONObject.getJSONArray("recommend_list");
      int j = paramJSONObject.length();
      String[] arrayOfString = new String[j];
      int i = 0;
      while (i < j)
      {
        arrayOfString[i] = paramJSONObject.get(i).toString();
        i += 1;
      }
      r7.e().c(arrayOfString);
      return;
    }
    catch (JSONException paramJSONObject)
    {
      paramJSONObject.printStackTrace();
    }
  }
  
  public final void v(JSONObject paramJSONObject)
  {
    try
    {
      paramJSONObject = paramJSONObject.getJSONObject("mp");
      int i = paramJSONObject.getInt("firstsave_present_count");
      h6.b().a(i);
      paramJSONObject = paramJSONObject.getString("present_level");
      if ((paramJSONObject != null) && (!paramJSONObject.equals("null")))
      {
        z5.a(paramJSONObject, h6.b().a());
        return;
      }
    }
    catch (Exception paramJSONObject)
    {
      paramJSONObject.printStackTrace();
    }
  }
  
  public final void w(JSONObject paramJSONObject)
  {
    String str1 = "";
    try
    {
      paramJSONObject = paramJSONObject.getJSONObject("user_info");
      String str3 = paramJSONObject.getString("uin");
      String str2 = paramJSONObject.getString("uin_type");
      int i = paramJSONObject.getInt("uin_len");
      int j = paramJSONObject.getInt("codeindex");
      if ((!str3.equals("")) && (j < d2.o.length))
      {
        str3 = l6.a(str3, d2.o[j]);
        paramJSONObject = str1;
        if (str3.length() >= i) {
          paramJSONObject = str3.substring(0, i);
        }
        this.n.e.i = paramJSONObject;
      }
      this.n.e.j = str2;
      return;
    }
    catch (Exception paramJSONObject)
    {
      paramJSONObject.printStackTrace();
    }
  }
}


/* Location:           L:\local\mybackup\temp\qq_apk\com.tencent.mm\assets\MidasPay_zip\MidasPay_1.7.9a_179010_92809280434fe4a46110cc442b537591.jar\classes.jar
 * Qualified Name:     midas.x.e3
 * JD-Core Version:    0.7.0.1
 */