package midas.x;

public class u9
{
  public static u9 a()
  {
    return e.a();
  }
  
  /* Error */
  public void a(java.lang.Long paramLong, java.util.concurrent.TimeUnit paramTimeUnit)
  {
    // Byte code:
    //   0: aload_0
    //   1: monitorenter
    //   2: invokestatic 35	midas/x/ha:c	()Lmidas/x/ha;
    //   5: aload_1
    //   6: aload_2
    //   7: invokevirtual 37	midas/x/ha:a	(Ljava/lang/Long;Ljava/util/concurrent/TimeUnit;)V
    //   10: goto +17 -> 27
    //   13: astore_1
    //   14: aload_1
    //   15: invokevirtual 42	java/lang/Throwable:printStackTrace	()V
    //   18: ldc 44
    //   20: aload_1
    //   21: invokevirtual 48	java/lang/Throwable:toString	()Ljava/lang/String;
    //   24: invokestatic 53	midas/x/ca:b	(Ljava/lang/String;Ljava/lang/String;)V
    //   27: aload_0
    //   28: monitorexit
    //   29: return
    //   30: astore_1
    //   31: aload_0
    //   32: monitorexit
    //   33: aload_1
    //   34: athrow
    // Local variable table:
    //   start	length	slot	name	signature
    //   0	35	0	this	u9
    //   0	35	1	paramLong	java.lang.Long
    //   0	35	2	paramTimeUnit	java.util.concurrent.TimeUnit
    // Exception table:
    //   from	to	target	type
    //   2	10	13	finally
    //   14	27	30	finally
  }
  
  public void a(String paramString)
  {
    try
    {
      oa.a(paramString);
      return;
    }
    finally
    {
      paramString = finally;
      throw paramString;
    }
  }
  
  public void a(b paramb)
  {
    try
    {
      ca.a(paramb);
      return;
    }
    finally
    {
      paramb = finally;
      throw paramb;
    }
  }
  
  public void a(c paramc)
  {
    try
    {
      da.a(paramc);
      return;
    }
    finally
    {
      paramc = finally;
      throw paramc;
    }
  }
  
  public void a(d paramd)
  {
    try
    {
      ea.a(paramd);
      return;
    }
    finally
    {
      paramd = finally;
      throw paramd;
    }
  }
  
  public static abstract interface b
  {
    public abstract void a(String paramString1, String paramString2);
    
    public abstract void b(String paramString1, String paramString2);
    
    public abstract void c(String paramString1, String paramString2);
    
    public abstract void d(String paramString1, String paramString2);
  }
  
  public static abstract interface c {}
  
  public static abstract interface d
  {
    public abstract void a(Runnable paramRunnable);
    
    public abstract boolean b(Runnable paramRunnable);
  }
  
  public static class e
  {
    public static u9 a = new u9(null);
  }
}


/* Location:           L:\local\mybackup\temp\qq_apk\com.tencent.mm\assets\MidasPay_zip\MidasPay_1.7.9a_179010_92809280434fe4a46110cc442b537591.jar\classes.jar
 * Qualified Name:     midas.x.u9
 * JD-Core Version:    0.7.0.1
 */