package com.tencent.biz.qqstory.channel;

class QQStoryCmdMonitor$1
  implements Runnable
{
  /* Error */
  public void run()
  {
    // Byte code:
    //   0: new 17	java/util/ArrayList
    //   3: dup
    //   4: aload_0
    //   5: getfield 19	com/tencent/biz/qqstory/channel/QQStoryCmdMonitor$1:jdField_a_of_type_ComTencentBizQqstoryChannelQQStoryCmdHandler	Lcom/tencent/biz/qqstory/channel/QQStoryCmdHandler;
    //   8: getfield 24	com/tencent/biz/qqstory/channel/QQStoryCmdHandler:a	Ljava/util/List;
    //   11: invokespecial 28	java/util/ArrayList:<init>	(Ljava/util/Collection;)V
    //   14: astore 10
    //   16: aconst_null
    //   17: astore 9
    //   19: aconst_null
    //   20: astore 8
    //   22: aload 8
    //   24: astore 7
    //   26: new 30	java/io/File
    //   29: dup
    //   30: getstatic 36	com/tencent/biz/qqstory/app/QQStoryConstant:e	Ljava/lang/String;
    //   33: invokespecial 39	java/io/File:<init>	(Ljava/lang/String;)V
    //   36: astore 11
    //   38: aload 8
    //   40: astore 7
    //   42: aload 11
    //   44: invokevirtual 43	java/io/File:exists	()Z
    //   47: ifne +13 -> 60
    //   50: aload 8
    //   52: astore 7
    //   54: aload 11
    //   56: invokevirtual 46	java/io/File:mkdirs	()Z
    //   59: pop
    //   60: aload 8
    //   62: astore 7
    //   64: new 30	java/io/File
    //   67: dup
    //   68: aload 11
    //   70: ldc 48
    //   72: invokespecial 51	java/io/File:<init>	(Ljava/io/File;Ljava/lang/String;)V
    //   75: astore 11
    //   77: aload 8
    //   79: astore 7
    //   81: aload 11
    //   83: invokevirtual 43	java/io/File:exists	()Z
    //   86: ifeq +13 -> 99
    //   89: aload 8
    //   91: astore 7
    //   93: aload 11
    //   95: invokevirtual 54	java/io/File:delete	()Z
    //   98: pop
    //   99: aload 8
    //   101: astore 7
    //   103: new 56	java/io/FileWriter
    //   106: dup
    //   107: aload 11
    //   109: invokespecial 59	java/io/FileWriter:<init>	(Ljava/io/File;)V
    //   112: astore 8
    //   114: new 61	java/lang/StringBuilder
    //   117: dup
    //   118: sipush 1024
    //   121: invokespecial 64	java/lang/StringBuilder:<init>	(I)V
    //   124: astore 7
    //   126: new 17	java/util/ArrayList
    //   129: dup
    //   130: invokespecial 66	java/util/ArrayList:<init>	()V
    //   133: astore 9
    //   135: iconst_0
    //   136: istore 5
    //   138: aload 10
    //   140: invokeinterface 72 1 0
    //   145: istore 6
    //   147: iload 5
    //   149: iload 6
    //   151: if_icmpge +143 -> 294
    //   154: aload 10
    //   156: iload 5
    //   158: invokeinterface 76 2 0
    //   163: checkcast 78	com/tencent/biz/qqstory/channel/QQStoryCmdHandler$CmdDumpInfo
    //   166: astore 12
    //   168: iload 5
    //   170: iconst_1
    //   171: iadd
    //   172: istore 5
    //   174: aload 7
    //   176: iload 5
    //   178: invokestatic 84	java/lang/String:valueOf	(I)Ljava/lang/String;
    //   181: invokevirtual 88	java/lang/StringBuilder:append	(Ljava/lang/String;)Ljava/lang/StringBuilder;
    //   184: pop
    //   185: aload 7
    //   187: ldc 90
    //   189: invokevirtual 88	java/lang/StringBuilder:append	(Ljava/lang/String;)Ljava/lang/StringBuilder;
    //   192: pop
    //   193: aload 7
    //   195: aload 12
    //   197: invokevirtual 94	com/tencent/biz/qqstory/channel/QQStoryCmdHandler$CmdDumpInfo:toString	()Ljava/lang/String;
    //   200: invokevirtual 88	java/lang/StringBuilder:append	(Ljava/lang/String;)Ljava/lang/StringBuilder;
    //   203: pop
    //   204: aload 7
    //   206: ldc 96
    //   208: invokevirtual 88	java/lang/StringBuilder:append	(Ljava/lang/String;)Ljava/lang/StringBuilder;
    //   211: pop
    //   212: aload 7
    //   214: ldc 96
    //   216: invokevirtual 88	java/lang/StringBuilder:append	(Ljava/lang/String;)Ljava/lang/StringBuilder;
    //   219: pop
    //   220: aload 8
    //   222: aload 7
    //   224: invokevirtual 97	java/lang/StringBuilder:toString	()Ljava/lang/String;
    //   227: invokevirtual 100	java/io/FileWriter:write	(Ljava/lang/String;)V
    //   230: aload 7
    //   232: iconst_0
    //   233: invokevirtual 103	java/lang/StringBuilder:setLength	(I)V
    //   236: aload 9
    //   238: aload 12
    //   240: invokevirtual 107	java/util/ArrayList:indexOf	(Ljava/lang/Object;)I
    //   243: istore 6
    //   245: iload 6
    //   247: ifge +20 -> 267
    //   250: aload 12
    //   252: iconst_1
    //   253: putfield 110	com/tencent/biz/qqstory/channel/QQStoryCmdHandler$CmdDumpInfo:jdField_a_of_type_Int	I
    //   256: aload 9
    //   258: aload 12
    //   260: invokevirtual 114	java/util/ArrayList:add	(Ljava/lang/Object;)Z
    //   263: pop
    //   264: goto -126 -> 138
    //   267: aload 9
    //   269: iload 6
    //   271: invokevirtual 115	java/util/ArrayList:get	(I)Ljava/lang/Object;
    //   274: checkcast 78	com/tencent/biz/qqstory/channel/QQStoryCmdHandler$CmdDumpInfo
    //   277: astore 12
    //   279: aload 12
    //   281: aload 12
    //   283: getfield 110	com/tencent/biz/qqstory/channel/QQStoryCmdHandler$CmdDumpInfo:jdField_a_of_type_Int	I
    //   286: iconst_1
    //   287: iadd
    //   288: putfield 110	com/tencent/biz/qqstory/channel/QQStoryCmdHandler$CmdDumpInfo:jdField_a_of_type_Int	I
    //   291: goto -153 -> 138
    //   294: aload 9
    //   296: invokevirtual 116	java/util/ArrayList:size	()I
    //   299: ifle +251 -> 550
    //   302: aload 9
    //   304: new 118	com/tencent/biz/qqstory/channel/QQStoryCmdMonitor$CmdDumpInfoComp
    //   307: dup
    //   308: aload_0
    //   309: getfield 120	com/tencent/biz/qqstory/channel/QQStoryCmdMonitor$1:this$0	Lcom/tencent/biz/qqstory/channel/QQStoryCmdMonitor;
    //   312: aconst_null
    //   313: invokespecial 123	com/tencent/biz/qqstory/channel/QQStoryCmdMonitor$CmdDumpInfoComp:<init>	(Lcom/tencent/biz/qqstory/channel/QQStoryCmdMonitor;Lcom/tencent/biz/qqstory/channel/QQStoryCmdMonitor$1;)V
    //   316: invokestatic 129	java/util/Collections:sort	(Ljava/util/List;Ljava/util/Comparator;)V
    //   319: aload 7
    //   321: ldc 96
    //   323: invokevirtual 88	java/lang/StringBuilder:append	(Ljava/lang/String;)Ljava/lang/StringBuilder;
    //   326: pop
    //   327: aload 7
    //   329: ldc 96
    //   331: invokevirtual 88	java/lang/StringBuilder:append	(Ljava/lang/String;)Ljava/lang/StringBuilder;
    //   334: pop
    //   335: aload 7
    //   337: ldc 96
    //   339: invokevirtual 88	java/lang/StringBuilder:append	(Ljava/lang/String;)Ljava/lang/StringBuilder;
    //   342: pop
    //   343: aload 7
    //   345: ldc 131
    //   347: invokevirtual 88	java/lang/StringBuilder:append	(Ljava/lang/String;)Ljava/lang/StringBuilder;
    //   350: pop
    //   351: aload 7
    //   353: ldc 96
    //   355: invokevirtual 88	java/lang/StringBuilder:append	(Ljava/lang/String;)Ljava/lang/StringBuilder;
    //   358: pop
    //   359: aload 7
    //   361: ldc 96
    //   363: invokevirtual 88	java/lang/StringBuilder:append	(Ljava/lang/String;)Ljava/lang/StringBuilder;
    //   366: pop
    //   367: aload 8
    //   369: aload 7
    //   371: invokevirtual 97	java/lang/StringBuilder:toString	()Ljava/lang/String;
    //   374: invokevirtual 100	java/io/FileWriter:write	(Ljava/lang/String;)V
    //   377: aload 7
    //   379: iconst_0
    //   380: invokevirtual 103	java/lang/StringBuilder:setLength	(I)V
    //   383: aload 9
    //   385: invokevirtual 135	java/util/ArrayList:iterator	()Ljava/util/Iterator;
    //   388: astore 9
    //   390: aload 9
    //   392: invokeinterface 140 1 0
    //   397: ifeq +153 -> 550
    //   400: aload 9
    //   402: invokeinterface 144 1 0
    //   407: checkcast 78	com/tencent/biz/qqstory/channel/QQStoryCmdHandler$CmdDumpInfo
    //   410: astore 12
    //   412: aload 7
    //   414: aload 12
    //   416: getfield 146	com/tencent/biz/qqstory/channel/QQStoryCmdHandler$CmdDumpInfo:jdField_a_of_type_JavaLangString	Ljava/lang/String;
    //   419: invokevirtual 88	java/lang/StringBuilder:append	(Ljava/lang/String;)Ljava/lang/StringBuilder;
    //   422: pop
    //   423: aload 7
    //   425: ldc 96
    //   427: invokevirtual 88	java/lang/StringBuilder:append	(Ljava/lang/String;)Ljava/lang/StringBuilder;
    //   430: pop
    //   431: aload 7
    //   433: ldc 148
    //   435: invokevirtual 88	java/lang/StringBuilder:append	(Ljava/lang/String;)Ljava/lang/StringBuilder;
    //   438: pop
    //   439: aload 7
    //   441: aload 12
    //   443: getfield 110	com/tencent/biz/qqstory/channel/QQStoryCmdHandler$CmdDumpInfo:jdField_a_of_type_Int	I
    //   446: invokevirtual 151	java/lang/StringBuilder:append	(I)Ljava/lang/StringBuilder;
    //   449: pop
    //   450: aload 7
    //   452: ldc 153
    //   454: invokevirtual 88	java/lang/StringBuilder:append	(Ljava/lang/String;)Ljava/lang/StringBuilder;
    //   457: pop
    //   458: aload 12
    //   460: getfield 110	com/tencent/biz/qqstory/channel/QQStoryCmdHandler$CmdDumpInfo:jdField_a_of_type_Int	I
    //   463: i2d
    //   464: dstore_1
    //   465: aload 10
    //   467: invokeinterface 72 1 0
    //   472: istore 5
    //   474: iload 5
    //   476: i2d
    //   477: dstore_3
    //   478: dload_1
    //   479: invokestatic 159	java/lang/Double:isNaN	(D)Z
    //   482: pop
    //   483: dload_3
    //   484: invokestatic 159	java/lang/Double:isNaN	(D)Z
    //   487: pop
    //   488: dload_1
    //   489: dload_3
    //   490: ddiv
    //   491: dstore_1
    //   492: invokestatic 165	java/text/NumberFormat:getPercentInstance	()Ljava/text/NumberFormat;
    //   495: astore 12
    //   497: aload 12
    //   499: iconst_2
    //   500: invokevirtual 168	java/text/NumberFormat:setMinimumFractionDigits	(I)V
    //   503: aload 7
    //   505: aload 12
    //   507: dload_1
    //   508: invokevirtual 172	java/text/NumberFormat:format	(D)Ljava/lang/String;
    //   511: invokevirtual 88	java/lang/StringBuilder:append	(Ljava/lang/String;)Ljava/lang/StringBuilder;
    //   514: pop
    //   515: aload 7
    //   517: ldc 96
    //   519: invokevirtual 88	java/lang/StringBuilder:append	(Ljava/lang/String;)Ljava/lang/StringBuilder;
    //   522: pop
    //   523: aload 7
    //   525: ldc 96
    //   527: invokevirtual 88	java/lang/StringBuilder:append	(Ljava/lang/String;)Ljava/lang/StringBuilder;
    //   530: pop
    //   531: aload 8
    //   533: aload 7
    //   535: invokevirtual 97	java/lang/StringBuilder:toString	()Ljava/lang/String;
    //   538: invokevirtual 100	java/io/FileWriter:write	(Ljava/lang/String;)V
    //   541: aload 7
    //   543: iconst_0
    //   544: invokevirtual 103	java/lang/StringBuilder:setLength	(I)V
    //   547: goto -157 -> 390
    //   550: aload_0
    //   551: getfield 120	com/tencent/biz/qqstory/channel/QQStoryCmdMonitor$1:this$0	Lcom/tencent/biz/qqstory/channel/QQStoryCmdMonitor;
    //   554: aload_0
    //   555: getfield 174	com/tencent/biz/qqstory/channel/QQStoryCmdMonitor$1:jdField_a_of_type_AndroidContentContext	Landroid/content/Context;
    //   558: aload 11
    //   560: invokevirtual 177	java/io/File:getAbsolutePath	()Ljava/lang/String;
    //   563: ldc 179
    //   565: invokestatic 184	com/tencent/biz/qqstory/channel/QQStoryCmdMonitor:a	(Lcom/tencent/biz/qqstory/channel/QQStoryCmdMonitor;Landroid/content/Context;Ljava/lang/String;Ljava/lang/String;)V
    //   568: aload 8
    //   570: invokevirtual 187	java/io/FileWriter:close	()V
    //   573: goto +50 -> 623
    //   576: astore 7
    //   578: goto +55 -> 633
    //   581: goto +16 -> 597
    //   584: astore 9
    //   586: aload 7
    //   588: astore 8
    //   590: aload 9
    //   592: astore 7
    //   594: goto +39 -> 633
    //   597: aload 8
    //   599: astore 7
    //   601: getstatic 193	com/tencent/common/app/BaseApplicationImpl:sApplication	Lcom/tencent/common/app/BaseApplicationImpl;
    //   604: ldc 195
    //   606: iconst_0
    //   607: invokestatic 201	android/widget/Toast:makeText	(Landroid/content/Context;Ljava/lang/CharSequence;I)Landroid/widget/Toast;
    //   610: invokevirtual 204	android/widget/Toast:show	()V
    //   613: aload 8
    //   615: ifnull +8 -> 623
    //   618: aload 8
    //   620: invokevirtual 187	java/io/FileWriter:close	()V
    //   623: aload_0
    //   624: getfield 120	com/tencent/biz/qqstory/channel/QQStoryCmdMonitor$1:this$0	Lcom/tencent/biz/qqstory/channel/QQStoryCmdMonitor;
    //   627: iconst_0
    //   628: invokestatic 207	com/tencent/biz/qqstory/channel/QQStoryCmdMonitor:a	(Lcom/tencent/biz/qqstory/channel/QQStoryCmdMonitor;Z)Z
    //   631: pop
    //   632: return
    //   633: aload 8
    //   635: ifnull +8 -> 643
    //   638: aload 8
    //   640: invokevirtual 187	java/io/FileWriter:close	()V
    //   643: aload_0
    //   644: getfield 120	com/tencent/biz/qqstory/channel/QQStoryCmdMonitor$1:this$0	Lcom/tencent/biz/qqstory/channel/QQStoryCmdMonitor;
    //   647: iconst_0
    //   648: invokestatic 207	com/tencent/biz/qqstory/channel/QQStoryCmdMonitor:a	(Lcom/tencent/biz/qqstory/channel/QQStoryCmdMonitor;Z)Z
    //   651: pop
    //   652: goto +6 -> 658
    //   655: aload 7
    //   657: athrow
    //   658: goto -3 -> 655
    //   661: astore 7
    //   663: aload 9
    //   665: astore 8
    //   667: goto -70 -> 597
    //   670: astore 7
    //   672: goto -91 -> 581
    //   675: astore 7
    //   677: goto -54 -> 623
    //   680: astore 8
    //   682: goto -39 -> 643
    // Local variable table:
    //   start	length	slot	name	signature
    //   0	685	0	this	1
    //   464	44	1	d1	double
    //   477	13	3	d2	double
    //   136	339	5	i	int
    //   145	125	6	j	int
    //   24	518	7	localObject1	Object
    //   576	11	7	localObject2	Object
    //   592	64	7	localObject3	Object
    //   661	1	7	localException1	java.lang.Exception
    //   670	1	7	localException2	java.lang.Exception
    //   675	1	7	localException3	java.lang.Exception
    //   20	646	8	localObject4	Object
    //   680	1	8	localException4	java.lang.Exception
    //   17	384	9	localObject5	Object
    //   584	80	9	localObject6	Object
    //   14	452	10	localArrayList	java.util.ArrayList
    //   36	523	11	localFile	java.io.File
    //   166	340	12	localObject7	Object
    // Exception table:
    //   from	to	target	type
    //   114	135	576	finally
    //   138	147	576	finally
    //   154	168	576	finally
    //   174	245	576	finally
    //   250	264	576	finally
    //   267	291	576	finally
    //   294	390	576	finally
    //   390	474	576	finally
    //   492	547	576	finally
    //   550	568	576	finally
    //   26	38	584	finally
    //   42	50	584	finally
    //   54	60	584	finally
    //   64	77	584	finally
    //   81	89	584	finally
    //   93	99	584	finally
    //   103	114	584	finally
    //   601	613	584	finally
    //   26	38	661	java/lang/Exception
    //   42	50	661	java/lang/Exception
    //   54	60	661	java/lang/Exception
    //   64	77	661	java/lang/Exception
    //   81	89	661	java/lang/Exception
    //   93	99	661	java/lang/Exception
    //   103	114	661	java/lang/Exception
    //   114	135	670	java/lang/Exception
    //   138	147	670	java/lang/Exception
    //   154	168	670	java/lang/Exception
    //   174	245	670	java/lang/Exception
    //   250	264	670	java/lang/Exception
    //   267	291	670	java/lang/Exception
    //   294	390	670	java/lang/Exception
    //   390	474	670	java/lang/Exception
    //   492	547	670	java/lang/Exception
    //   550	568	670	java/lang/Exception
    //   568	573	675	java/lang/Exception
    //   618	623	675	java/lang/Exception
    //   638	643	680	java/lang/Exception
  }
}


/* Location:           L:\local\mybackup\temp\qq_apk\com.tencent.mobileqq\classes2.jar
 * Qualified Name:     com.tencent.biz.qqstory.channel.QQStoryCmdMonitor.1
 * JD-Core Version:    0.7.0.1
 */