package com.tencent.mm.model.d;

public final class b$3
  implements Runnable
{
  public b$3(b paramb, String paramString) {}
  
  /* Error */
  public final void run()
  {
    // Byte code:
    //   0: sipush 16393
    //   3: invokestatic 33	com/tencent/matrix/trace/core/AppMethodBeat:i	(I)V
    //   6: aload_0
    //   7: getfield 16	com/tencent/mm/model/d/b$3:fpI	Lcom/tencent/mm/model/d/b;
    //   10: astore 4
    //   12: new 35	java/lang/StringBuilder
    //   15: dup
    //   16: invokespecial 36	java/lang/StringBuilder:<init>	()V
    //   19: invokestatic 40	com/tencent/mm/model/d/b:access$000	()Ljava/lang/String;
    //   22: invokevirtual 44	java/lang/StringBuilder:append	(Ljava/lang/String;)Ljava/lang/StringBuilder;
    //   25: ldc 46
    //   27: invokevirtual 44	java/lang/StringBuilder:append	(Ljava/lang/String;)Ljava/lang/StringBuilder;
    //   30: invokevirtual 49	java/lang/StringBuilder:toString	()Ljava/lang/String;
    //   33: astore_1
    //   34: new 35	java/lang/StringBuilder
    //   37: dup
    //   38: invokespecial 36	java/lang/StringBuilder:<init>	()V
    //   41: aload_0
    //   42: getfield 18	com/tencent/mm/model/d/b$3:fpJ	Ljava/lang/String;
    //   45: invokevirtual 44	java/lang/StringBuilder:append	(Ljava/lang/String;)Ljava/lang/StringBuilder;
    //   48: ldc 51
    //   50: invokevirtual 44	java/lang/StringBuilder:append	(Ljava/lang/String;)Ljava/lang/StringBuilder;
    //   53: invokevirtual 49	java/lang/StringBuilder:toString	()Ljava/lang/String;
    //   56: astore_3
    //   57: invokestatic 57	com/tencent/mm/compatible/util/f:Mi	()Z
    //   60: ifne +17 -> 77
    //   63: ldc 59
    //   65: ldc 61
    //   67: invokestatic 66	com/tencent/mm/sdk/platformtools/ab:i	(Ljava/lang/String;Ljava/lang/String;)V
    //   70: sipush 16393
    //   73: invokestatic 69	com/tencent/matrix/trace/core/AppMethodBeat:o	(I)V
    //   76: return
    //   77: new 71	java/io/File
    //   80: dup
    //   81: getstatic 74	com/tencent/mm/model/d/b:fpy	Ljava/lang/String;
    //   84: invokespecial 77	java/io/File:<init>	(Ljava/lang/String;)V
    //   87: astore_2
    //   88: aload_2
    //   89: invokevirtual 80	java/io/File:exists	()Z
    //   92: ifne +8 -> 100
    //   95: aload_2
    //   96: invokevirtual 83	java/io/File:mkdirs	()Z
    //   99: pop
    //   100: aload 4
    //   102: new 71	java/io/File
    //   105: dup
    //   106: getstatic 74	com/tencent/mm/model/d/b:fpy	Ljava/lang/String;
    //   109: ldc 46
    //   111: invokespecial 85	java/io/File:<init>	(Ljava/lang/String;Ljava/lang/String;)V
    //   114: iconst_0
    //   115: invokevirtual 89	com/tencent/mm/model/d/b:b	(Ljava/io/File;Z)V
    //   118: new 71	java/io/File
    //   121: dup
    //   122: aload_1
    //   123: invokespecial 77	java/io/File:<init>	(Ljava/lang/String;)V
    //   126: astore_2
    //   127: aload_2
    //   128: invokevirtual 93	java/io/File:length	()J
    //   131: aload 4
    //   133: getfield 97	com/tencent/mm/model/d/b:fpD	J
    //   136: lcmp
    //   137: ifle +17 -> 154
    //   140: ldc 59
    //   142: ldc 99
    //   144: invokestatic 102	com/tencent/mm/sdk/platformtools/ab:e	(Ljava/lang/String;Ljava/lang/String;)V
    //   147: aload 4
    //   149: aload_2
    //   150: iconst_1
    //   151: invokevirtual 89	com/tencent/mm/model/d/b:b	(Ljava/io/File;Z)V
    //   154: new 104	java/io/RandomAccessFile
    //   157: dup
    //   158: aload_1
    //   159: ldc 106
    //   161: invokespecial 107	java/io/RandomAccessFile:<init>	(Ljava/lang/String;Ljava/lang/String;)V
    //   164: astore_2
    //   165: aload_2
    //   166: astore_1
    //   167: aload_2
    //   168: aload_2
    //   169: invokevirtual 108	java/io/RandomAccessFile:length	()J
    //   172: invokevirtual 112	java/io/RandomAccessFile:seek	(J)V
    //   175: aload_2
    //   176: astore_1
    //   177: aload_2
    //   178: aload_3
    //   179: invokevirtual 118	java/lang/String:getBytes	()[B
    //   182: invokestatic 124	com/tencent/mm/ci/e:ch	([B)[B
    //   185: invokevirtual 128	java/io/RandomAccessFile:write	([B)V
    //   188: aload_2
    //   189: invokevirtual 131	java/io/RandomAccessFile:close	()V
    //   192: aload 4
    //   194: new 71	java/io/File
    //   197: dup
    //   198: new 35	java/lang/StringBuilder
    //   201: dup
    //   202: invokespecial 36	java/lang/StringBuilder:<init>	()V
    //   205: getstatic 74	com/tencent/mm/model/d/b:fpy	Ljava/lang/String;
    //   208: invokevirtual 44	java/lang/StringBuilder:append	(Ljava/lang/String;)Ljava/lang/StringBuilder;
    //   211: ldc 46
    //   213: invokevirtual 44	java/lang/StringBuilder:append	(Ljava/lang/String;)Ljava/lang/StringBuilder;
    //   216: invokevirtual 49	java/lang/StringBuilder:toString	()Ljava/lang/String;
    //   219: invokespecial 77	java/io/File:<init>	(Ljava/lang/String;)V
    //   222: invokevirtual 135	com/tencent/mm/model/d/b:w	(Ljava/io/File;)V
    //   225: sipush 16393
    //   228: invokestatic 69	com/tencent/matrix/trace/core/AppMethodBeat:o	(I)V
    //   231: return
    //   232: astore_2
    //   233: ldc 59
    //   235: ldc 137
    //   237: invokestatic 102	com/tencent/mm/sdk/platformtools/ab:e	(Ljava/lang/String;Ljava/lang/String;)V
    //   240: goto -122 -> 118
    //   243: astore_1
    //   244: ldc 59
    //   246: aload_1
    //   247: ldc 139
    //   249: iconst_0
    //   250: anewarray 4	java/lang/Object
    //   253: invokestatic 143	com/tencent/mm/sdk/platformtools/ab:printErrStackTrace	(Ljava/lang/String;Ljava/lang/Throwable;Ljava/lang/String;[Ljava/lang/Object;)V
    //   256: goto -64 -> 192
    //   259: astore_3
    //   260: aconst_null
    //   261: astore_2
    //   262: aload_2
    //   263: astore_1
    //   264: ldc 59
    //   266: aload_3
    //   267: ldc 139
    //   269: iconst_0
    //   270: anewarray 4	java/lang/Object
    //   273: invokestatic 143	com/tencent/mm/sdk/platformtools/ab:printErrStackTrace	(Ljava/lang/String;Ljava/lang/Throwable;Ljava/lang/String;[Ljava/lang/Object;)V
    //   276: aload_2
    //   277: ifnull -85 -> 192
    //   280: aload_2
    //   281: invokevirtual 131	java/io/RandomAccessFile:close	()V
    //   284: goto -92 -> 192
    //   287: astore_1
    //   288: ldc 59
    //   290: aload_1
    //   291: ldc 139
    //   293: iconst_0
    //   294: anewarray 4	java/lang/Object
    //   297: invokestatic 143	com/tencent/mm/sdk/platformtools/ab:printErrStackTrace	(Ljava/lang/String;Ljava/lang/Throwable;Ljava/lang/String;[Ljava/lang/Object;)V
    //   300: goto -108 -> 192
    //   303: astore_2
    //   304: aconst_null
    //   305: astore_1
    //   306: aload_1
    //   307: ifnull +7 -> 314
    //   310: aload_1
    //   311: invokevirtual 131	java/io/RandomAccessFile:close	()V
    //   314: sipush 16393
    //   317: invokestatic 69	com/tencent/matrix/trace/core/AppMethodBeat:o	(I)V
    //   320: aload_2
    //   321: athrow
    //   322: astore_1
    //   323: ldc 59
    //   325: aload_1
    //   326: ldc 139
    //   328: iconst_0
    //   329: anewarray 4	java/lang/Object
    //   332: invokestatic 143	com/tencent/mm/sdk/platformtools/ab:printErrStackTrace	(Ljava/lang/String;Ljava/lang/Throwable;Ljava/lang/String;[Ljava/lang/Object;)V
    //   335: goto -21 -> 314
    //   338: astore_2
    //   339: goto -33 -> 306
    //   342: astore_3
    //   343: goto -81 -> 262
    // Local variable table:
    //   start	length	slot	name	signature
    //   0	346	0	this	3
    //   33	144	1	localObject1	Object
    //   243	4	1	localException1	java.lang.Exception
    //   263	1	1	localObject2	Object
    //   287	4	1	localException2	java.lang.Exception
    //   305	6	1	localObject3	Object
    //   322	4	1	localException3	java.lang.Exception
    //   87	102	2	localObject4	Object
    //   232	1	2	localException4	java.lang.Exception
    //   261	20	2	localObject5	Object
    //   303	18	2	localObject6	Object
    //   338	1	2	localObject7	Object
    //   56	123	3	str	String
    //   259	8	3	localIOException1	java.io.IOException
    //   342	1	3	localIOException2	java.io.IOException
    //   10	183	4	localb	b
    // Exception table:
    //   from	to	target	type
    //   77	100	232	java/lang/Exception
    //   100	118	232	java/lang/Exception
    //   188	192	243	java/lang/Exception
    //   154	165	259	java/io/IOException
    //   280	284	287	java/lang/Exception
    //   154	165	303	finally
    //   310	314	322	java/lang/Exception
    //   167	175	338	finally
    //   177	188	338	finally
    //   264	276	338	finally
    //   167	175	342	java/io/IOException
    //   177	188	342	java/io/IOException
  }
}


/* Location:           L:\local\mybackup\temp\qq_apk\com.tencent.mm\classes2.jar
 * Qualified Name:     com.tencent.mm.model.d.b.3
 * JD-Core Version:    0.7.0.1
 */