package com.tencent.token;

import android.content.Context;

public final class a
  extends i
{
  String a = "UTF-8";
  j b;
  private Context c = null;
  
  public a(Context paramContext, String paramString)
  {
    this.c = paramContext;
    try
    {
      this.b = new j();
      k.a(paramContext, paramString);
      return;
    }
    catch (Throwable paramContext)
    {
      a(paramContext);
    }
  }
  
  /* Error */
  private byte[] b()
  {
    // Byte code:
    //   0: aconst_null
    //   1: astore 5
    //   3: aconst_null
    //   4: astore 4
    //   6: aload 4
    //   8: astore_2
    //   9: aload 5
    //   11: astore_3
    //   12: invokestatic 43	com/tencent/token/k:d	()Z
    //   15: ifeq +5 -> 20
    //   18: aconst_null
    //   19: areturn
    //   20: aload 4
    //   22: astore_2
    //   23: aload 5
    //   25: astore_3
    //   26: invokestatic 45	com/tencent/token/k:c	()V
    //   29: aload 4
    //   31: astore_2
    //   32: aload 5
    //   34: astore_3
    //   35: new 30	com/tencent/token/k
    //   38: dup
    //   39: invokespecial 46	com/tencent/token/k:<init>	()V
    //   42: astore 10
    //   44: aload 4
    //   46: astore_2
    //   47: aload 5
    //   49: astore_3
    //   50: new 48	com/tencent/token/c
    //   53: dup
    //   54: aload_0
    //   55: getfield 19	com/tencent/token/a:c	Landroid/content/Context;
    //   58: invokespecial 51	com/tencent/token/c:<init>	(Landroid/content/Context;)V
    //   61: astore 6
    //   63: aload 4
    //   65: astore_2
    //   66: aload 5
    //   68: astore_3
    //   69: new 53	com/tencent/token/d
    //   72: dup
    //   73: aload_0
    //   74: getfield 19	com/tencent/token/a:c	Landroid/content/Context;
    //   77: invokespecial 54	com/tencent/token/d:<init>	(Landroid/content/Context;)V
    //   80: astore 7
    //   82: aload 4
    //   84: astore_2
    //   85: aload 5
    //   87: astore_3
    //   88: new 56	com/tencent/token/b
    //   91: dup
    //   92: invokespecial 57	com/tencent/token/b:<init>	()V
    //   95: astore 8
    //   97: aload 4
    //   99: astore_2
    //   100: aload 5
    //   102: astore_3
    //   103: new 59	com/tencent/token/h
    //   106: dup
    //   107: aload_0
    //   108: getfield 19	com/tencent/token/a:c	Landroid/content/Context;
    //   111: invokespecial 60	com/tencent/token/h:<init>	(Landroid/content/Context;)V
    //   114: astore 9
    //   116: aload 6
    //   118: invokevirtual 63	com/tencent/token/c:a	()Ljava/lang/String;
    //   121: astore_2
    //   122: aload 7
    //   124: aload_2
    //   125: invokevirtual 66	com/tencent/token/d:b	(Ljava/lang/String;)Ljava/security/PublicKey;
    //   128: astore_1
    //   129: aload_1
    //   130: ifnull +449 -> 579
    //   133: aload_1
    //   134: invokevirtual 71	java/lang/Object:toString	()Ljava/lang/String;
    //   137: astore_1
    //   138: aload 10
    //   140: aload 8
    //   142: aload_1
    //   143: invokevirtual 74	com/tencent/token/b:d	(Ljava/lang/String;)Ljava/lang/String;
    //   146: invokevirtual 77	com/tencent/token/k:a	(Ljava/lang/String;)V
    //   149: aload 7
    //   151: aload_2
    //   152: invokevirtual 79	com/tencent/token/d:c	(Ljava/lang/String;)Ljava/security/PublicKey;
    //   155: astore_1
    //   156: aload_1
    //   157: ifnull +623 -> 780
    //   160: aload_1
    //   161: invokevirtual 71	java/lang/Object:toString	()Ljava/lang/String;
    //   164: astore_1
    //   165: aload 10
    //   167: aload 8
    //   169: aload_1
    //   170: invokevirtual 74	com/tencent/token/b:d	(Ljava/lang/String;)Ljava/lang/String;
    //   173: invokevirtual 77	com/tencent/token/k:a	(Ljava/lang/String;)V
    //   176: aload 7
    //   178: aload_2
    //   179: invokevirtual 81	com/tencent/token/d:d	(Ljava/lang/String;)Ljava/security/PublicKey;
    //   182: astore_1
    //   183: aload_1
    //   184: ifnull +602 -> 786
    //   187: aload_1
    //   188: invokevirtual 71	java/lang/Object:toString	()Ljava/lang/String;
    //   191: astore_1
    //   192: aload 10
    //   194: aload 8
    //   196: aload_1
    //   197: invokevirtual 74	com/tencent/token/b:d	(Ljava/lang/String;)Ljava/lang/String;
    //   200: invokevirtual 77	com/tencent/token/k:a	(Ljava/lang/String;)V
    //   203: aload 7
    //   205: invokevirtual 84	com/tencent/token/d:a	()Ljava/security/PublicKey;
    //   208: astore_1
    //   209: aload_1
    //   210: ifnull +582 -> 792
    //   213: aload_1
    //   214: invokevirtual 71	java/lang/Object:toString	()Ljava/lang/String;
    //   217: astore_1
    //   218: aload 10
    //   220: aload 8
    //   222: aload_1
    //   223: invokevirtual 74	com/tencent/token/b:d	(Ljava/lang/String;)Ljava/lang/String;
    //   226: invokevirtual 77	com/tencent/token/k:a	(Ljava/lang/String;)V
    //   229: aload 7
    //   231: aload_2
    //   232: invokevirtual 86	com/tencent/token/d:a	(Ljava/lang/String;)Ljava/security/PublicKey;
    //   235: astore_1
    //   236: aload_1
    //   237: ifnull +348 -> 585
    //   240: aload_1
    //   241: invokevirtual 71	java/lang/Object:toString	()Ljava/lang/String;
    //   244: astore_1
    //   245: aload 10
    //   247: aload 8
    //   249: aload_1
    //   250: invokevirtual 74	com/tencent/token/b:d	(Ljava/lang/String;)Ljava/lang/String;
    //   253: invokevirtual 77	com/tencent/token/k:a	(Ljava/lang/String;)V
    //   256: aload 10
    //   258: aload 8
    //   260: aload_2
    //   261: invokevirtual 88	com/tencent/token/b:a	(Ljava/lang/String;)Ljava/lang/String;
    //   264: invokevirtual 77	com/tencent/token/k:a	(Ljava/lang/String;)V
    //   267: aload 10
    //   269: aload 8
    //   271: aload_2
    //   272: invokevirtual 90	com/tencent/token/b:b	(Ljava/lang/String;)Ljava/lang/String;
    //   275: invokevirtual 77	com/tencent/token/k:a	(Ljava/lang/String;)V
    //   278: aload 10
    //   280: aload 8
    //   282: invokestatic 92	com/tencent/token/k:b	()Ljava/lang/String;
    //   285: invokevirtual 94	com/tencent/token/b:c	(Ljava/lang/String;)Ljava/lang/String;
    //   288: invokevirtual 77	com/tencent/token/k:a	(Ljava/lang/String;)V
    //   291: aload 10
    //   293: aload 6
    //   295: invokevirtual 97	com/tencent/token/c:l	()Ljava/lang/String;
    //   298: putfield 100	com/tencent/token/k:u	Ljava/lang/String;
    //   301: aload 10
    //   303: aload 6
    //   305: invokevirtual 103	com/tencent/token/c:k	()Ljava/lang/String;
    //   308: putfield 106	com/tencent/token/k:t	Ljava/lang/String;
    //   311: aload 10
    //   313: aload 6
    //   315: invokevirtual 108	com/tencent/token/c:c	()Ljava/lang/String;
    //   318: putfield 110	com/tencent/token/k:k	Ljava/lang/String;
    //   321: aload 10
    //   323: aload 6
    //   325: invokevirtual 113	com/tencent/token/c:h	()Ljava/lang/String;
    //   328: putfield 116	com/tencent/token/k:q	Ljava/lang/String;
    //   331: aload 10
    //   333: aload 6
    //   335: invokevirtual 119	com/tencent/token/c:j	()Ljava/lang/String;
    //   338: putfield 122	com/tencent/token/k:s	Ljava/lang/String;
    //   341: aload 10
    //   343: aload 6
    //   345: invokevirtual 125	com/tencent/token/c:m	()Ljava/lang/String;
    //   348: putfield 128	com/tencent/token/k:v	Ljava/lang/String;
    //   351: aload 10
    //   353: aload 6
    //   355: invokevirtual 131	com/tencent/token/c:i	()Ljava/lang/String;
    //   358: putfield 134	com/tencent/token/k:r	Ljava/lang/String;
    //   361: aload 10
    //   363: aload 6
    //   365: invokevirtual 137	com/tencent/token/c:n	()Ljava/lang/String;
    //   368: putfield 140	com/tencent/token/k:w	Ljava/lang/String;
    //   371: aload 10
    //   373: aload 6
    //   375: invokevirtual 143	com/tencent/token/c:o	()Ljava/lang/String;
    //   378: putfield 146	com/tencent/token/k:x	Ljava/lang/String;
    //   381: aload 10
    //   383: aload 6
    //   385: invokevirtual 149	com/tencent/token/c:e	()Ljava/lang/String;
    //   388: putfield 151	com/tencent/token/k:n	Ljava/lang/String;
    //   391: aload 10
    //   393: aload 6
    //   395: invokevirtual 152	com/tencent/token/c:b	()Ljava/lang/String;
    //   398: putfield 154	com/tencent/token/k:j	Ljava/lang/String;
    //   401: aload 10
    //   403: aload 6
    //   405: invokevirtual 158	com/tencent/token/c:f	()I
    //   408: putfield 161	com/tencent/token/k:o	I
    //   411: aload 10
    //   413: aload 6
    //   415: invokevirtual 163	com/tencent/token/c:d	()Ljava/lang/String;
    //   418: putfield 165	com/tencent/token/k:l	Ljava/lang/String;
    //   421: aload 10
    //   423: aload 6
    //   425: invokevirtual 168	com/tencent/token/c:p	()Ljava/lang/String;
    //   428: putfield 171	com/tencent/token/k:y	Ljava/lang/String;
    //   431: aload 10
    //   433: iconst_1
    //   434: putfield 173	com/tencent/token/k:m	I
    //   437: aload 10
    //   439: aload 6
    //   441: invokevirtual 176	com/tencent/token/c:g	()Ljava/lang/String;
    //   444: putfield 178	com/tencent/token/k:p	Ljava/lang/String;
    //   447: aload 10
    //   449: aload 6
    //   451: invokevirtual 180	com/tencent/token/c:q	()Ljava/lang/String;
    //   454: putfield 183	com/tencent/token/k:z	Ljava/lang/String;
    //   457: aload 10
    //   459: aload 6
    //   461: invokevirtual 185	com/tencent/token/c:r	()Ljava/lang/String;
    //   464: putfield 188	com/tencent/token/k:A	Ljava/lang/String;
    //   467: aload 10
    //   469: aload 9
    //   471: invokevirtual 189	com/tencent/token/h:b	()Ljava/lang/String;
    //   474: putfield 191	com/tencent/token/k:g	Ljava/lang/String;
    //   477: aload 10
    //   479: getstatic 196	android/os/Build:MODEL	Ljava/lang/String;
    //   482: putfield 198	com/tencent/token/k:i	Ljava/lang/String;
    //   485: aload 10
    //   487: aload 9
    //   489: invokevirtual 199	com/tencent/token/h:a	()Ljava/lang/String;
    //   492: putfield 201	com/tencent/token/k:f	Ljava/lang/String;
    //   495: aload 10
    //   497: getstatic 204	android/os/Build:PRODUCT	Ljava/lang/String;
    //   500: putfield 206	com/tencent/token/k:h	Ljava/lang/String;
    //   503: aload 8
    //   505: aload 8
    //   507: aload 10
    //   509: invokevirtual 208	com/tencent/token/k:a	()[B
    //   512: invokevirtual 211	com/tencent/token/b:b	([B)[B
    //   515: invokevirtual 213	com/tencent/token/b:c	([B)[B
    //   518: astore_1
    //   519: aload_1
    //   520: astore_2
    //   521: aload_1
    //   522: astore_3
    //   523: aload_0
    //   524: new 215	java/lang/StringBuilder
    //   527: dup
    //   528: aload 6
    //   530: invokevirtual 217	com/tencent/token/c:s	()Ljava/lang/String;
    //   533: invokestatic 223	java/lang/String:valueOf	(Ljava/lang/Object;)Ljava/lang/String;
    //   536: invokespecial 225	java/lang/StringBuilder:<init>	(Ljava/lang/String;)V
    //   539: aload 7
    //   541: invokevirtual 226	com/tencent/token/d:s	()Ljava/lang/String;
    //   544: invokevirtual 230	java/lang/StringBuilder:append	(Ljava/lang/String;)Ljava/lang/StringBuilder;
    //   547: aload 8
    //   549: invokevirtual 231	com/tencent/token/b:s	()Ljava/lang/String;
    //   552: invokevirtual 230	java/lang/StringBuilder:append	(Ljava/lang/String;)Ljava/lang/StringBuilder;
    //   555: aload 9
    //   557: invokevirtual 232	com/tencent/token/h:s	()Ljava/lang/String;
    //   560: invokevirtual 230	java/lang/StringBuilder:append	(Ljava/lang/String;)Ljava/lang/StringBuilder;
    //   563: invokevirtual 233	java/lang/StringBuilder:toString	()Ljava/lang/String;
    //   566: invokevirtual 235	com/tencent/token/a:e	(Ljava/lang/String;)V
    //   569: aload_1
    //   570: areturn
    //   571: astore_1
    //   572: aload_0
    //   573: aload_1
    //   574: invokevirtual 238	com/tencent/token/a:a	(Ljava/lang/Exception;)V
    //   577: aload_2
    //   578: areturn
    //   579: ldc 240
    //   581: astore_1
    //   582: goto -444 -> 138
    //   585: ldc 240
    //   587: astore_1
    //   588: goto -343 -> 245
    //   591: astore_1
    //   592: aload_0
    //   593: aload_1
    //   594: invokevirtual 238	com/tencent/token/a:a	(Ljava/lang/Exception;)V
    //   597: aload 4
    //   599: astore_2
    //   600: aload 5
    //   602: astore_3
    //   603: aload_0
    //   604: new 215	java/lang/StringBuilder
    //   607: dup
    //   608: aload 6
    //   610: invokevirtual 217	com/tencent/token/c:s	()Ljava/lang/String;
    //   613: invokestatic 223	java/lang/String:valueOf	(Ljava/lang/Object;)Ljava/lang/String;
    //   616: invokespecial 225	java/lang/StringBuilder:<init>	(Ljava/lang/String;)V
    //   619: aload 7
    //   621: invokevirtual 226	com/tencent/token/d:s	()Ljava/lang/String;
    //   624: invokevirtual 230	java/lang/StringBuilder:append	(Ljava/lang/String;)Ljava/lang/StringBuilder;
    //   627: aload 8
    //   629: invokevirtual 231	com/tencent/token/b:s	()Ljava/lang/String;
    //   632: invokevirtual 230	java/lang/StringBuilder:append	(Ljava/lang/String;)Ljava/lang/StringBuilder;
    //   635: aload 9
    //   637: invokevirtual 232	com/tencent/token/h:s	()Ljava/lang/String;
    //   640: invokevirtual 230	java/lang/StringBuilder:append	(Ljava/lang/String;)Ljava/lang/StringBuilder;
    //   643: invokevirtual 233	java/lang/StringBuilder:toString	()Ljava/lang/String;
    //   646: invokevirtual 235	com/tencent/token/a:e	(Ljava/lang/String;)V
    //   649: aconst_null
    //   650: areturn
    //   651: astore_1
    //   652: aload_0
    //   653: aload_1
    //   654: invokevirtual 35	com/tencent/token/a:a	(Ljava/lang/Throwable;)V
    //   657: aload_3
    //   658: areturn
    //   659: astore_1
    //   660: aload_0
    //   661: aload_1
    //   662: invokevirtual 35	com/tencent/token/a:a	(Ljava/lang/Throwable;)V
    //   665: aload 4
    //   667: astore_2
    //   668: aload 5
    //   670: astore_3
    //   671: aload_0
    //   672: new 215	java/lang/StringBuilder
    //   675: dup
    //   676: aload 6
    //   678: invokevirtual 217	com/tencent/token/c:s	()Ljava/lang/String;
    //   681: invokestatic 223	java/lang/String:valueOf	(Ljava/lang/Object;)Ljava/lang/String;
    //   684: invokespecial 225	java/lang/StringBuilder:<init>	(Ljava/lang/String;)V
    //   687: aload 7
    //   689: invokevirtual 226	com/tencent/token/d:s	()Ljava/lang/String;
    //   692: invokevirtual 230	java/lang/StringBuilder:append	(Ljava/lang/String;)Ljava/lang/StringBuilder;
    //   695: aload 8
    //   697: invokevirtual 231	com/tencent/token/b:s	()Ljava/lang/String;
    //   700: invokevirtual 230	java/lang/StringBuilder:append	(Ljava/lang/String;)Ljava/lang/StringBuilder;
    //   703: aload 9
    //   705: invokevirtual 232	com/tencent/token/h:s	()Ljava/lang/String;
    //   708: invokevirtual 230	java/lang/StringBuilder:append	(Ljava/lang/String;)Ljava/lang/StringBuilder;
    //   711: invokevirtual 233	java/lang/StringBuilder:toString	()Ljava/lang/String;
    //   714: invokevirtual 235	com/tencent/token/a:e	(Ljava/lang/String;)V
    //   717: aconst_null
    //   718: areturn
    //   719: astore_1
    //   720: aload 4
    //   722: astore_2
    //   723: aload 5
    //   725: astore_3
    //   726: aload_0
    //   727: new 215	java/lang/StringBuilder
    //   730: dup
    //   731: aload 6
    //   733: invokevirtual 217	com/tencent/token/c:s	()Ljava/lang/String;
    //   736: invokestatic 223	java/lang/String:valueOf	(Ljava/lang/Object;)Ljava/lang/String;
    //   739: invokespecial 225	java/lang/StringBuilder:<init>	(Ljava/lang/String;)V
    //   742: aload 7
    //   744: invokevirtual 226	com/tencent/token/d:s	()Ljava/lang/String;
    //   747: invokevirtual 230	java/lang/StringBuilder:append	(Ljava/lang/String;)Ljava/lang/StringBuilder;
    //   750: aload 8
    //   752: invokevirtual 231	com/tencent/token/b:s	()Ljava/lang/String;
    //   755: invokevirtual 230	java/lang/StringBuilder:append	(Ljava/lang/String;)Ljava/lang/StringBuilder;
    //   758: aload 9
    //   760: invokevirtual 232	com/tencent/token/h:s	()Ljava/lang/String;
    //   763: invokevirtual 230	java/lang/StringBuilder:append	(Ljava/lang/String;)Ljava/lang/StringBuilder;
    //   766: invokevirtual 233	java/lang/StringBuilder:toString	()Ljava/lang/String;
    //   769: invokevirtual 235	com/tencent/token/a:e	(Ljava/lang/String;)V
    //   772: aload 4
    //   774: astore_2
    //   775: aload 5
    //   777: astore_3
    //   778: aload_1
    //   779: athrow
    //   780: ldc 240
    //   782: astore_1
    //   783: goto -618 -> 165
    //   786: ldc 240
    //   788: astore_1
    //   789: goto -597 -> 192
    //   792: ldc 240
    //   794: astore_1
    //   795: goto -577 -> 218
    // Local variable table:
    //   start	length	slot	name	signature
    //   0	798	0	this	a
    //   128	442	1	localObject1	Object
    //   571	3	1	localException1	java.lang.Exception
    //   581	7	1	str1	String
    //   591	3	1	localException2	java.lang.Exception
    //   651	3	1	localThrowable1	Throwable
    //   659	3	1	localThrowable2	Throwable
    //   719	60	1	localObject2	Object
    //   782	13	1	str2	String
    //   8	767	2	localObject3	Object
    //   11	767	3	localObject4	Object
    //   4	769	4	localObject5	Object
    //   1	775	5	localObject6	Object
    //   61	671	6	localc	c
    //   80	663	7	locald	d
    //   95	656	8	localb	b
    //   114	645	9	localh	h
    //   42	466	10	localk	k
    // Exception table:
    //   from	to	target	type
    //   12	18	571	java/lang/Exception
    //   26	29	571	java/lang/Exception
    //   35	44	571	java/lang/Exception
    //   50	63	571	java/lang/Exception
    //   69	82	571	java/lang/Exception
    //   88	97	571	java/lang/Exception
    //   103	116	571	java/lang/Exception
    //   523	569	571	java/lang/Exception
    //   603	649	571	java/lang/Exception
    //   671	717	571	java/lang/Exception
    //   726	772	571	java/lang/Exception
    //   778	780	571	java/lang/Exception
    //   116	129	591	java/lang/Exception
    //   133	138	591	java/lang/Exception
    //   138	156	591	java/lang/Exception
    //   160	165	591	java/lang/Exception
    //   165	183	591	java/lang/Exception
    //   187	192	591	java/lang/Exception
    //   192	209	591	java/lang/Exception
    //   213	218	591	java/lang/Exception
    //   218	236	591	java/lang/Exception
    //   240	245	591	java/lang/Exception
    //   245	519	591	java/lang/Exception
    //   12	18	651	java/lang/Throwable
    //   26	29	651	java/lang/Throwable
    //   35	44	651	java/lang/Throwable
    //   50	63	651	java/lang/Throwable
    //   69	82	651	java/lang/Throwable
    //   88	97	651	java/lang/Throwable
    //   103	116	651	java/lang/Throwable
    //   523	569	651	java/lang/Throwable
    //   603	649	651	java/lang/Throwable
    //   671	717	651	java/lang/Throwable
    //   726	772	651	java/lang/Throwable
    //   778	780	651	java/lang/Throwable
    //   116	129	659	java/lang/Throwable
    //   133	138	659	java/lang/Throwable
    //   138	156	659	java/lang/Throwable
    //   160	165	659	java/lang/Throwable
    //   165	183	659	java/lang/Throwable
    //   187	192	659	java/lang/Throwable
    //   192	209	659	java/lang/Throwable
    //   213	218	659	java/lang/Throwable
    //   218	236	659	java/lang/Throwable
    //   240	245	659	java/lang/Throwable
    //   245	519	659	java/lang/Throwable
    //   116	129	719	finally
    //   133	138	719	finally
    //   138	156	719	finally
    //   160	165	719	finally
    //   165	183	719	finally
    //   187	192	719	finally
    //   192	209	719	finally
    //   213	218	719	finally
    //   218	236	719	finally
    //   240	245	719	finally
    //   245	519	719	finally
    //   592	597	719	finally
    //   660	665	719	finally
  }
  
  public final String a()
  {
    int i = 0;
    Object localObject1 = "";
    byte[] arrayOfByte = b();
    Object localObject4 = localObject1;
    Object localObject3;
    String str;
    if (arrayOfByte != null)
    {
      localObject3 = localObject1;
      try
      {
        localb = new b();
        localObject3 = localObject1;
        str = s();
        localObject4 = localObject1;
        localObject3 = localObject1;
        if (str.length() > 1024)
        {
          localObject3 = localObject1;
          i = str.length();
          i -= 1024;
          localObject1 = "";
        }
      }
      catch (Throwable localThrowable1)
      {
        b localb;
        int j;
        label92:
        a(localThrowable1);
        return localObject3;
      }
      try
      {
        j = str.length() - i;
        if (str != null) {
          break label254;
        }
        localObject3 = "";
      }
      catch (Throwable localThrowable2)
      {
        localObject3 = localThrowable1;
        Object localObject2 = localThrowable2;
        break label235;
        localObject3 = str;
        break label92;
      }
      localObject4 = localObject3;
      if (((String)localObject3).length() > j) {
        localObject4 = ((String)localObject3).substring(0, j);
      }
      localObject3 = localb.a(this.b.a(arrayOfByte, localb.b(((String)localObject4).getBytes(this.a))));
      localObject1 = localObject3;
      localObject3 = localObject1;
      if (i >= str.length())
      {
        localObject3 = localObject1;
        if (i == str.length())
        {
          localObject3 = localObject1;
          localObject4 = localObject1;
          if (((String)localObject1).length() > 1024) {
            return "";
          }
        }
        else
        {
          localObject3 = localObject1;
          i = str.length();
        }
      }
      else
      {
        for (;;)
        {
          localObject3 = localObject1;
          j = ((String)localObject1).length();
          localObject4 = localObject1;
          if (j <= 1024) {
            break label261;
          }
          localObject4 = localObject1;
          localObject1 = localObject4;
          break;
          i += 10;
        }
      }
    }
    label235:
    label254:
    return localThrowable2;
  }
}


/* Location:           L:\local\mybackup\temp\qq_apk\com.tencent.token\classes.jar
 * Qualified Name:     com.tencent.token.a
 * JD-Core Version:    0.7.0.1
 */