package com.tencent.token;

import com.tencent.turingfd.sdk.qps.Date;

public class adv
{
  public static int a;
  public static Date b;
  
  /* Error */
  public static void a(android.content.Context paramContext)
  {
    // Byte code:
    //   0: ldc 2
    //   2: monitorenter
    //   3: getstatic 13	com/tencent/token/adv:a	I
    //   6: ifeq +9 -> 15
    //   9: getstatic 15	com/tencent/token/adv:b	Lcom/tencent/turingfd/sdk/qps/Date;
    //   12: ifnonnull +126 -> 138
    //   15: new 17	android/util/SparseArray
    //   18: dup
    //   19: invokespecial 21	android/util/SparseArray:<init>	()V
    //   22: astore_1
    //   23: new 17	android/util/SparseArray
    //   26: dup
    //   27: invokespecial 21	android/util/SparseArray:<init>	()V
    //   30: aload_0
    //   31: sipush 201
    //   34: invokestatic 27	com/tencent/turingfd/sdk/qps/TNative$aa:d	(Landroid/util/SparseArray;Landroid/content/Context;I)Landroid/util/SparseArray;
    //   37: astore_2
    //   38: aload_2
    //   39: astore_1
    //   40: aload_1
    //   41: sipush 201
    //   44: ldc 29
    //   46: invokestatic 34	com/tencent/token/agn:a	(Landroid/util/SparseArray;ILjava/lang/Class;)Ljava/lang/Object;
    //   49: checkcast 29	java/lang/String
    //   52: astore_3
    //   53: aload_3
    //   54: astore_2
    //   55: aload_3
    //   56: ifnonnull +6 -> 62
    //   59: ldc 36
    //   61: astore_2
    //   62: aload_2
    //   63: invokestatic 42	java/lang/Integer:valueOf	(Ljava/lang/String;)Ljava/lang/Integer;
    //   66: invokevirtual 46	java/lang/Integer:intValue	()I
    //   69: putstatic 13	com/tencent/token/adv:a	I
    //   72: new 17	android/util/SparseArray
    //   75: dup
    //   76: invokespecial 21	android/util/SparseArray:<init>	()V
    //   79: aload_0
    //   80: sipush 203
    //   83: invokestatic 27	com/tencent/turingfd/sdk/qps/TNative$aa:d	(Landroid/util/SparseArray;Landroid/content/Context;I)Landroid/util/SparseArray;
    //   86: astore_0
    //   87: aload_0
    //   88: astore_1
    //   89: aload_1
    //   90: sipush 202
    //   93: ldc 29
    //   95: invokestatic 34	com/tencent/token/agn:a	(Landroid/util/SparseArray;ILjava/lang/Class;)Ljava/lang/Object;
    //   98: checkcast 29	java/lang/String
    //   101: astore_1
    //   102: aload_1
    //   103: astore_0
    //   104: aload_1
    //   105: ifnonnull +6 -> 111
    //   108: ldc 36
    //   110: astore_0
    //   111: new 48	com/tencent/turingfd/sdk/qps/Date
    //   114: dup
    //   115: invokespecial 49	com/tencent/turingfd/sdk/qps/Date:<init>	()V
    //   118: astore_1
    //   119: aload_1
    //   120: putstatic 15	com/tencent/token/adv:b	Lcom/tencent/turingfd/sdk/qps/Date;
    //   123: aload_1
    //   124: aload_0
    //   125: invokestatic 42	java/lang/Integer:valueOf	(Ljava/lang/String;)Ljava/lang/Integer;
    //   128: invokevirtual 46	java/lang/Integer:intValue	()I
    //   131: putfield 50	com/tencent/turingfd/sdk/qps/Date:a	I
    //   134: ldc 2
    //   136: monitorexit
    //   137: return
    //   138: ldc 2
    //   140: monitorexit
    //   141: return
    //   142: astore_0
    //   143: ldc 2
    //   145: monitorexit
    //   146: aload_0
    //   147: athrow
    //   148: astore_2
    //   149: goto -109 -> 40
    //   152: astore_2
    //   153: goto -81 -> 72
    //   156: astore_0
    //   157: goto -68 -> 89
    //   160: astore_0
    //   161: goto -23 -> 138
    // Local variable table:
    //   start	length	slot	name	signature
    //   0	164	0	paramContext	android.content.Context
    //   22	102	1	localObject1	Object
    //   37	26	2	localObject2	Object
    //   148	1	2	localObject3	Object
    //   152	1	2	localNumberFormatException	java.lang.NumberFormatException
    //   52	4	3	str	java.lang.String
    // Exception table:
    //   from	to	target	type
    //   3	15	142	finally
    //   15	23	142	finally
    //   40	53	142	finally
    //   62	72	142	finally
    //   89	102	142	finally
    //   111	123	142	finally
    //   123	134	142	finally
    //   23	38	148	finally
    //   62	72	152	java/lang/NumberFormatException
    //   72	87	156	finally
    //   123	134	160	java/lang/NumberFormatException
  }
}


/* Location:           L:\local\mybackup\temp\qq_apk\com.tencent.token\classes.jar
 * Qualified Name:     com.tencent.token.adv
 * JD-Core Version:    0.7.0.1
 */