package com.tencent.token;

import com.tencent.halley.downloader.c.d.a;
import com.tencent.halley.downloader.c.d.a.a;
import java.util.Iterator;
import java.util.List;
import java.util.Map;

public final class mf
  implements la, lh, Runnable
{
  public boolean a = true;
  public md b;
  public a c;
  public int d = 0;
  public String e = "";
  public boolean f = false;
  private mk g;
  private long h = -1L;
  private lh i;
  private me j;
  private Map k = null;
  private boolean l = false;
  private long m = 0L;
  private lb n;
  private Object o = new Object();
  private mi p = new mi();
  private String q;
  private boolean r = true;
  
  public mf(mk parammk, boolean paramBoolean1, long paramLong, lh paramlh, me paramme, Map paramMap, boolean paramBoolean2)
  {
    this.g = parammk;
    this.a = paramBoolean1;
    this.h = paramLong;
    this.p.a = paramBoolean1;
    this.i = paramlh;
    this.j = paramme;
    this.k = paramMap;
    this.r = paramBoolean2;
  }
  
  private void a(kz paramkz)
  {
    paramkz = paramkz.p;
    if ((paramkz != null) && (paramkz.size() > 0))
    {
      paramkz = paramkz.iterator();
      while (paramkz.hasNext())
      {
        String str = (String)paramkz.next();
        this.g.a(ld.a, str, a.a.e);
        StringBuilder localStringBuilder = new StringBuilder("add header schedule url...apn:");
        localStringBuilder.append(ld.a);
        localStringBuilder.append(",type:");
        localStringBuilder.append(a.a.e);
        localStringBuilder.append(",url:");
        localStringBuilder.append(str);
        li.a("SectionTransport", localStringBuilder.toString());
      }
    }
  }
  
  public final boolean a()
  {
    if (this.l) {
      return true;
    }
    lh locallh = this.i;
    if (locallh != null) {
      return locallh.a();
    }
    li.d("SectionTransport", "cancelChecker is null");
    return true;
  }
  
  public final boolean a(byte[] paramArrayOfByte, int paramInt, boolean paramBoolean)
  {
    if (paramBoolean)
    {
      StringBuilder localStringBuilder = new StringBuilder("is direct:");
      localStringBuilder.append(this.a);
      localStringBuilder.append(",onReceiveData...len:");
      localStringBuilder.append(paramInt);
      localStringBuilder.append(",section:");
      localStringBuilder.append(this.b);
      li.a("DownloadTest", localStringBuilder.toString());
    }
    int i2 = 1;
    if (this.j != null)
    {
      int i1 = paramInt;
      if (this.b.g + paramInt >= this.b.h)
      {
        i1 = (int)(this.b.h - this.b.g);
        i2 = 0;
      }
      paramBoolean = i2 & this.j.a(this, this.b.g, paramArrayOfByte, i1, paramBoolean);
      if (!paramBoolean)
      {
        paramArrayOfByte = new StringBuilder("is direct:");
        paramArrayOfByte.append(this.a);
        paramArrayOfByte.append(",stop read data...len:");
        paramArrayOfByte.append(i1);
        paramArrayOfByte.append(",section:");
        paramArrayOfByte.append(this.b);
        li.a("DownloadTest", paramArrayOfByte.toString());
      }
      this.m += i1;
      return paramBoolean;
    }
    li.d("SectionTransport", "listener in Ant is null.");
    return true;
  }
  
  public final void b()
  {
    try
    {
      this.l = true;
      if (this.n != null) {
        this.n.f();
      }
      synchronized (this.o)
      {
        this.o.notifyAll();
        return;
      }
      return;
    }
    catch (Throwable localThrowable) {}
  }
  
  public final String c()
  {
    Object localObject = this.p;
    if (localObject != null)
    {
      StringBuilder localStringBuilder = new StringBuilder();
      localObject = ((mi)localObject).e.iterator();
      while (((Iterator)localObject).hasNext())
      {
        localStringBuilder.append((mi.a)((Iterator)localObject).next());
        localStringBuilder.append(";");
      }
      return localStringBuilder.toString();
    }
    return "";
  }
  
  public final String d()
  {
    mi localmi = this.p;
    if (localmi != null) {
      return localmi.toString();
    }
    return "";
  }
  
  public final String e()
  {
    StringBuilder localStringBuilder1 = new StringBuilder();
    StringBuilder localStringBuilder2 = new StringBuilder();
    localStringBuilder2.append(this.a ^ true);
    localStringBuilder1.append(localStringBuilder2.toString());
    localStringBuilder1.append(",");
    localStringBuilder1.append(",");
    localStringBuilder1.append(",");
    localStringBuilder2 = new StringBuilder();
    localStringBuilder2.append(this.q);
    localStringBuilder1.append(localStringBuilder2.toString());
    localStringBuilder1.append(",");
    localStringBuilder1.append(",");
    localStringBuilder1.append(",");
    localStringBuilder1.append(",");
    localStringBuilder1.append(",");
    localStringBuilder1.append(",");
    localStringBuilder1.append(",");
    localStringBuilder1.append(",");
    localStringBuilder1.append(",");
    localStringBuilder1.append(",");
    localStringBuilder1.append(",");
    localStringBuilder2 = new StringBuilder();
    localStringBuilder2.append(this.d);
    localStringBuilder1.append(localStringBuilder2.toString());
    localStringBuilder1.append(",");
    localStringBuilder1.append(",");
    localStringBuilder1.append(",");
    localStringBuilder1.append(";");
    return localStringBuilder1.toString();
  }
  
  /* Error */
  public final void run()
  {
    // Byte code:
    //   0: aload_0
    //   1: getfield 73	com/tencent/token/mf:p	Lcom/tencent/token/mi;
    //   4: invokestatic 225	java/lang/System:currentTimeMillis	()J
    //   7: putfield 227	com/tencent/token/mi:b	J
    //   10: invokestatic 232	android/os/SystemClock:elapsedRealtime	()J
    //   13: lstore 8
    //   15: iconst_1
    //   16: istore_1
    //   17: iconst_0
    //   18: istore_2
    //   19: lconst_0
    //   20: lstore 6
    //   22: iconst_0
    //   23: istore 12
    //   25: aload_0
    //   26: invokevirtual 233	com/tencent/token/mf:a	()Z
    //   29: ifne +2909 -> 2938
    //   32: aload_0
    //   33: getfield 48	com/tencent/token/mf:a	Z
    //   36: ifne +331 -> 367
    //   39: aload_0
    //   40: getfield 77	com/tencent/token/mf:g	Lcom/tencent/token/mk;
    //   43: getfield 234	com/tencent/token/mk:a	Z
    //   46: ifeq +321 -> 367
    //   49: invokestatic 236	com/tencent/token/ld:b	()V
    //   52: getstatic 115	com/tencent/token/ld:a	Ljava/lang/String;
    //   55: astore 14
    //   57: aload_0
    //   58: getfield 77	com/tencent/token/mf:g	Lcom/tencent/token/mk;
    //   61: astore 15
    //   63: aload 14
    //   65: invokestatic 242	android/text/TextUtils:isEmpty	(Ljava/lang/CharSequence;)Z
    //   68: ifne +2984 -> 3052
    //   71: aload 15
    //   73: getfield 244	com/tencent/token/mk:d	Ljava/util/Map;
    //   76: aload 14
    //   78: invokeinterface 250 2 0
    //   83: checkcast 252	com/tencent/token/mk$a
    //   86: astore 15
    //   88: aload 15
    //   90: ifnull +2957 -> 3047
    //   93: aload 15
    //   95: getfield 254	com/tencent/token/mk$a:b	Z
    //   98: ifeq +6 -> 104
    //   101: goto +2935 -> 3036
    //   104: aload 15
    //   106: getfield 256	com/tencent/token/mk$a:a	Ljava/util/List;
    //   109: ifnull +2932 -> 3041
    //   112: aload 15
    //   114: getfield 256	com/tencent/token/mk$a:a	Ljava/util/List;
    //   117: invokeinterface 95 1 0
    //   122: ifle +2919 -> 3041
    //   125: goto +2911 -> 3036
    //   128: iload_3
    //   129: ifeq +238 -> 367
    //   132: aload_0
    //   133: getfield 77	com/tencent/token/mf:g	Lcom/tencent/token/mk;
    //   136: getfield 258	com/tencent/token/mk:b	Lcom/tencent/halley/downloader/c/d/a;
    //   139: getfield 261	com/tencent/halley/downloader/c/d/a:a	Ljava/lang/String;
    //   142: aload_0
    //   143: getfield 52	com/tencent/token/mf:h	J
    //   146: invokestatic 266	com/tencent/token/kv:a	(Ljava/lang/String;J)Ljava/util/List;
    //   149: astore 16
    //   151: aload 16
    //   153: ifnull +214 -> 367
    //   156: invokestatic 236	com/tencent/token/ld:b	()V
    //   159: getstatic 115	com/tencent/token/ld:a	Ljava/lang/String;
    //   162: astore 15
    //   164: aload 15
    //   166: invokestatic 242	android/text/TextUtils:isEmpty	(Ljava/lang/CharSequence;)Z
    //   169: ifne +198 -> 367
    //   172: aload 15
    //   174: aload 14
    //   176: invokevirtual 270	java/lang/String:equals	(Ljava/lang/Object;)Z
    //   179: ifne +6 -> 185
    //   182: goto +185 -> 367
    //   185: aload_0
    //   186: getfield 77	com/tencent/token/mf:g	Lcom/tencent/token/mk;
    //   189: astore 14
    //   191: aload 15
    //   193: invokestatic 242	android/text/TextUtils:isEmpty	(Ljava/lang/CharSequence;)Z
    //   196: ifne +23 -> 219
    //   199: aload 14
    //   201: aload 15
    //   203: invokevirtual 273	com/tencent/token/mk:a	(Ljava/lang/String;)Lcom/tencent/token/mk$a;
    //   206: astore 14
    //   208: aload 14
    //   210: ifnull +9 -> 219
    //   213: aload 14
    //   215: iconst_1
    //   216: putfield 254	com/tencent/token/mk$a:b	Z
    //   219: aload 16
    //   221: invokeinterface 99 1 0
    //   226: astore 16
    //   228: aload 16
    //   230: invokeinterface 105 1 0
    //   235: ifeq +132 -> 367
    //   238: aload 16
    //   240: invokeinterface 109 1 0
    //   245: checkcast 111	java/lang/String
    //   248: astore 17
    //   250: aload 17
    //   252: invokestatic 242	android/text/TextUtils:isEmpty	(Ljava/lang/CharSequence;)Z
    //   255: ifne +102 -> 357
    //   258: getstatic 275	com/tencent/halley/downloader/c/d/a$a:f	Lcom/tencent/halley/downloader/c/d/a$a;
    //   261: astore 14
    //   263: aload 17
    //   265: invokevirtual 278	java/lang/String:toLowerCase	()Ljava/lang/String;
    //   268: ldc_w 280
    //   271: invokevirtual 284	java/lang/String:startsWith	(Ljava/lang/String;)Z
    //   274: ifeq +8 -> 282
    //   277: getstatic 286	com/tencent/halley/downloader/c/d/a$a:j	Lcom/tencent/halley/downloader/c/d/a$a;
    //   280: astore 14
    //   282: aload_0
    //   283: getfield 77	com/tencent/token/mf:g	Lcom/tencent/token/mk;
    //   286: aload 15
    //   288: aload 17
    //   290: aload 14
    //   292: invokevirtual 125	com/tencent/token/mk:a	(Ljava/lang/String;Ljava/lang/String;Lcom/tencent/halley/downloader/c/d/a$a;)V
    //   295: new 127	java/lang/StringBuilder
    //   298: dup
    //   299: ldc_w 288
    //   302: invokespecial 132	java/lang/StringBuilder:<init>	(Ljava/lang/String;)V
    //   305: astore 18
    //   307: aload 18
    //   309: aload 15
    //   311: invokevirtual 136	java/lang/StringBuilder:append	(Ljava/lang/String;)Ljava/lang/StringBuilder;
    //   314: pop
    //   315: aload 18
    //   317: ldc 138
    //   319: invokevirtual 136	java/lang/StringBuilder:append	(Ljava/lang/String;)Ljava/lang/StringBuilder;
    //   322: pop
    //   323: aload 18
    //   325: aload 14
    //   327: invokevirtual 141	java/lang/StringBuilder:append	(Ljava/lang/Object;)Ljava/lang/StringBuilder;
    //   330: pop
    //   331: aload 18
    //   333: ldc 143
    //   335: invokevirtual 136	java/lang/StringBuilder:append	(Ljava/lang/String;)Ljava/lang/StringBuilder;
    //   338: pop
    //   339: aload 18
    //   341: aload 17
    //   343: invokevirtual 136	java/lang/StringBuilder:append	(Ljava/lang/String;)Ljava/lang/StringBuilder;
    //   346: pop
    //   347: ldc 145
    //   349: aload 18
    //   351: invokevirtual 149	java/lang/StringBuilder:toString	()Ljava/lang/String;
    //   354: invokestatic 154	com/tencent/token/li:a	(Ljava/lang/String;Ljava/lang/String;)V
    //   357: goto -129 -> 228
    //   360: astore 14
    //   362: aload 14
    //   364: invokevirtual 291	java/lang/Exception:printStackTrace	()V
    //   367: aload_0
    //   368: invokevirtual 233	com/tencent/token/mf:a	()Z
    //   371: ifne +2567 -> 2938
    //   374: aload_0
    //   375: getfield 48	com/tencent/token/mf:a	Z
    //   378: ifne +10 -> 388
    //   381: aload_0
    //   382: getfield 75	com/tencent/token/mf:r	Z
    //   385: ifeq +2553 -> 2938
    //   388: iload_2
    //   389: ifle +48 -> 437
    //   392: aload_0
    //   393: getfield 68	com/tencent/token/mf:o	Ljava/lang/Object;
    //   396: astore 14
    //   398: aload 14
    //   400: monitorenter
    //   401: aload_0
    //   402: getfield 68	com/tencent/token/mf:o	Ljava/lang/Object;
    //   405: iload_2
    //   406: i2l
    //   407: invokevirtual 295	java/lang/Object:wait	(J)V
    //   410: goto +15 -> 425
    //   413: astore 15
    //   415: goto +16 -> 431
    //   418: astore 15
    //   420: aload 15
    //   422: invokevirtual 296	java/lang/InterruptedException:printStackTrace	()V
    //   425: aload 14
    //   427: monitorexit
    //   428: goto +9 -> 437
    //   431: aload 14
    //   433: monitorexit
    //   434: aload 15
    //   436: athrow
    //   437: aload_0
    //   438: invokevirtual 233	com/tencent/token/mf:a	()Z
    //   441: ifne +2497 -> 2938
    //   444: lload 6
    //   446: lstore 4
    //   448: lload 6
    //   450: lconst_0
    //   451: lcmp
    //   452: ifne +8 -> 460
    //   455: invokestatic 232	android/os/SystemClock:elapsedRealtime	()J
    //   458: lstore 4
    //   460: iload_1
    //   461: ifeq +152 -> 613
    //   464: aload_0
    //   465: getfield 56	com/tencent/token/mf:d	I
    //   468: istore_1
    //   469: iload_1
    //   470: sipush 404
    //   473: if_icmpeq +18 -> 491
    //   476: iload_1
    //   477: bipush 246
    //   479: if_icmpne +6 -> 485
    //   482: goto +9 -> 491
    //   485: iconst_0
    //   486: istore 13
    //   488: goto +6 -> 494
    //   491: iconst_1
    //   492: istore 13
    //   494: aload_0
    //   495: aload_0
    //   496: getfield 77	com/tencent/token/mf:g	Lcom/tencent/token/mk;
    //   499: getstatic 115	com/tencent/token/ld:a	Ljava/lang/String;
    //   502: aload_0
    //   503: getfield 298	com/tencent/token/mf:c	Lcom/tencent/halley/downloader/c/d/a;
    //   506: aload_0
    //   507: getfield 48	com/tencent/token/mf:a	Z
    //   510: iload 13
    //   512: invokevirtual 301	com/tencent/token/mk:a	(Ljava/lang/String;Lcom/tencent/halley/downloader/c/d/a;ZZ)Lcom/tencent/halley/downloader/c/d/a;
    //   515: putfield 298	com/tencent/token/mf:c	Lcom/tencent/halley/downloader/c/d/a;
    //   518: new 127	java/lang/StringBuilder
    //   521: dup
    //   522: ldc_w 303
    //   525: invokespecial 132	java/lang/StringBuilder:<init>	(Ljava/lang/String;)V
    //   528: astore 14
    //   530: aload 14
    //   532: aload_0
    //   533: getfield 48	com/tencent/token/mf:a	Z
    //   536: invokevirtual 166	java/lang/StringBuilder:append	(Z)Ljava/lang/StringBuilder;
    //   539: pop
    //   540: aload 14
    //   542: ldc_w 305
    //   545: invokevirtual 136	java/lang/StringBuilder:append	(Ljava/lang/String;)Ljava/lang/StringBuilder;
    //   548: pop
    //   549: aload 14
    //   551: aload_0
    //   552: getfield 298	com/tencent/token/mf:c	Lcom/tencent/halley/downloader/c/d/a;
    //   555: getfield 307	com/tencent/halley/downloader/c/d/a:b	Lcom/tencent/halley/downloader/c/d/a$a;
    //   558: invokevirtual 141	java/lang/StringBuilder:append	(Ljava/lang/Object;)Ljava/lang/StringBuilder;
    //   561: pop
    //   562: aload 14
    //   564: ldc_w 309
    //   567: invokevirtual 136	java/lang/StringBuilder:append	(Ljava/lang/String;)Ljava/lang/StringBuilder;
    //   570: pop
    //   571: aload 14
    //   573: iload 13
    //   575: invokevirtual 166	java/lang/StringBuilder:append	(Z)Ljava/lang/StringBuilder;
    //   578: pop
    //   579: aload 14
    //   581: ldc 143
    //   583: invokevirtual 136	java/lang/StringBuilder:append	(Ljava/lang/String;)Ljava/lang/StringBuilder;
    //   586: pop
    //   587: aload 14
    //   589: aload_0
    //   590: getfield 298	com/tencent/token/mf:c	Lcom/tencent/halley/downloader/c/d/a;
    //   593: getfield 261	com/tencent/halley/downloader/c/d/a:a	Ljava/lang/String;
    //   596: invokevirtual 136	java/lang/StringBuilder:append	(Ljava/lang/String;)Ljava/lang/StringBuilder;
    //   599: pop
    //   600: ldc 145
    //   602: aload 14
    //   604: invokevirtual 149	java/lang/StringBuilder:toString	()Ljava/lang/String;
    //   607: invokestatic 154	com/tencent/token/li:a	(Ljava/lang/String;Ljava/lang/String;)V
    //   610: goto +225 -> 835
    //   613: aload_0
    //   614: getfield 298	com/tencent/token/mf:c	Lcom/tencent/halley/downloader/c/d/a;
    //   617: getfield 307	com/tencent/halley/downloader/c/d/a:b	Lcom/tencent/halley/downloader/c/d/a$a;
    //   620: getstatic 310	com/tencent/halley/downloader/c/d/a$a:b	Lcom/tencent/halley/downloader/c/d/a$a;
    //   623: if_acmpeq +101 -> 724
    //   626: aload_0
    //   627: getfield 298	com/tencent/token/mf:c	Lcom/tencent/halley/downloader/c/d/a;
    //   630: getfield 307	com/tencent/halley/downloader/c/d/a:b	Lcom/tencent/halley/downloader/c/d/a$a;
    //   633: getstatic 312	com/tencent/halley/downloader/c/d/a$a:a	Lcom/tencent/halley/downloader/c/d/a$a;
    //   636: if_acmpne +6 -> 642
    //   639: goto +85 -> 724
    //   642: new 127	java/lang/StringBuilder
    //   645: dup
    //   646: ldc_w 303
    //   649: invokespecial 132	java/lang/StringBuilder:<init>	(Ljava/lang/String;)V
    //   652: astore 14
    //   654: aload 14
    //   656: aload_0
    //   657: getfield 48	com/tencent/token/mf:a	Z
    //   660: invokevirtual 166	java/lang/StringBuilder:append	(Z)Ljava/lang/StringBuilder;
    //   663: pop
    //   664: ldc_w 314
    //   667: astore 15
    //   669: aload 14
    //   671: aload 15
    //   673: invokevirtual 136	java/lang/StringBuilder:append	(Ljava/lang/String;)Ljava/lang/StringBuilder;
    //   676: pop
    //   677: aload 14
    //   679: aload_0
    //   680: getfield 298	com/tencent/token/mf:c	Lcom/tencent/halley/downloader/c/d/a;
    //   683: getfield 307	com/tencent/halley/downloader/c/d/a:b	Lcom/tencent/halley/downloader/c/d/a$a;
    //   686: invokevirtual 141	java/lang/StringBuilder:append	(Ljava/lang/Object;)Ljava/lang/StringBuilder;
    //   689: pop
    //   690: aload 14
    //   692: ldc 143
    //   694: invokevirtual 136	java/lang/StringBuilder:append	(Ljava/lang/String;)Ljava/lang/StringBuilder;
    //   697: pop
    //   698: aload 14
    //   700: aload_0
    //   701: getfield 298	com/tencent/token/mf:c	Lcom/tencent/halley/downloader/c/d/a;
    //   704: getfield 261	com/tencent/halley/downloader/c/d/a:a	Ljava/lang/String;
    //   707: invokevirtual 136	java/lang/StringBuilder:append	(Ljava/lang/String;)Ljava/lang/StringBuilder;
    //   710: pop
    //   711: ldc 145
    //   713: aload 14
    //   715: invokevirtual 149	java/lang/StringBuilder:toString	()Ljava/lang/String;
    //   718: invokestatic 154	com/tencent/token/li:a	(Ljava/lang/String;Ljava/lang/String;)V
    //   721: goto +114 -> 835
    //   724: aload_0
    //   725: getfield 77	com/tencent/token/mf:g	Lcom/tencent/token/mk;
    //   728: astore 15
    //   730: getstatic 115	com/tencent/token/ld:a	Ljava/lang/String;
    //   733: astore 16
    //   735: aload_0
    //   736: getfield 298	com/tencent/token/mf:c	Lcom/tencent/halley/downloader/c/d/a;
    //   739: astore 14
    //   741: aload 14
    //   743: getfield 307	com/tencent/halley/downloader/c/d/a:b	Lcom/tencent/halley/downloader/c/d/a$a;
    //   746: getstatic 310	com/tencent/halley/downloader/c/d/a$a:b	Lcom/tencent/halley/downloader/c/d/a$a;
    //   749: if_acmpeq +14 -> 763
    //   752: aload 14
    //   754: getfield 307	com/tencent/halley/downloader/c/d/a:b	Lcom/tencent/halley/downloader/c/d/a$a;
    //   757: getstatic 312	com/tencent/halley/downloader/c/d/a$a:a	Lcom/tencent/halley/downloader/c/d/a$a;
    //   760: if_acmpne +39 -> 799
    //   763: aload 15
    //   765: aload 16
    //   767: invokevirtual 273	com/tencent/token/mk:a	(Ljava/lang/String;)Lcom/tencent/token/mk$a;
    //   770: astore 15
    //   772: aload 15
    //   774: ifnull +25 -> 799
    //   777: aload 15
    //   779: getstatic 316	com/tencent/halley/downloader/c/d/a$a:d	Lcom/tencent/halley/downloader/c/d/a$a;
    //   782: invokevirtual 319	com/tencent/token/mk$a:a	(Lcom/tencent/halley/downloader/c/d/a$a;)Lcom/tencent/halley/downloader/c/d/a;
    //   785: astore 15
    //   787: aload 15
    //   789: ifnull +10 -> 799
    //   792: aload 15
    //   794: astore 14
    //   796: goto +3 -> 799
    //   799: aload_0
    //   800: aload 14
    //   802: putfield 298	com/tencent/token/mf:c	Lcom/tencent/halley/downloader/c/d/a;
    //   805: new 127	java/lang/StringBuilder
    //   808: dup
    //   809: ldc_w 303
    //   812: invokespecial 132	java/lang/StringBuilder:<init>	(Ljava/lang/String;)V
    //   815: astore 14
    //   817: aload 14
    //   819: aload_0
    //   820: getfield 48	com/tencent/token/mf:a	Z
    //   823: invokevirtual 166	java/lang/StringBuilder:append	(Z)Ljava/lang/StringBuilder;
    //   826: pop
    //   827: ldc_w 321
    //   830: astore 15
    //   832: goto -163 -> 669
    //   835: aload_0
    //   836: aload_0
    //   837: getfield 82	com/tencent/token/mf:j	Lcom/tencent/token/me;
    //   840: aload_0
    //   841: invokeinterface 324 2 0
    //   846: putfield 175	com/tencent/token/mf:b	Lcom/tencent/token/md;
    //   849: new 127	java/lang/StringBuilder
    //   852: dup
    //   853: ldc_w 303
    //   856: invokespecial 132	java/lang/StringBuilder:<init>	(Ljava/lang/String;)V
    //   859: astore 14
    //   861: aload 14
    //   863: aload_0
    //   864: getfield 48	com/tencent/token/mf:a	Z
    //   867: invokevirtual 166	java/lang/StringBuilder:append	(Z)Ljava/lang/StringBuilder;
    //   870: pop
    //   871: aload 14
    //   873: ldc_w 326
    //   876: invokevirtual 136	java/lang/StringBuilder:append	(Ljava/lang/String;)Ljava/lang/StringBuilder;
    //   879: pop
    //   880: aload 14
    //   882: aload_0
    //   883: getfield 175	com/tencent/token/mf:b	Lcom/tencent/token/md;
    //   886: invokevirtual 141	java/lang/StringBuilder:append	(Ljava/lang/Object;)Ljava/lang/StringBuilder;
    //   889: pop
    //   890: ldc 177
    //   892: aload 14
    //   894: invokevirtual 149	java/lang/StringBuilder:toString	()Ljava/lang/String;
    //   897: invokestatic 328	com/tencent/token/li:b	(Ljava/lang/String;Ljava/lang/String;)V
    //   900: aload_0
    //   901: getfield 175	com/tencent/token/mf:b	Lcom/tencent/token/md;
    //   904: ifnull +2034 -> 2938
    //   907: iload 12
    //   909: ifeq +2164 -> 3073
    //   912: invokestatic 330	com/tencent/token/ld:d	()Z
    //   915: ifne +2158 -> 3073
    //   918: iconst_0
    //   919: istore 12
    //   921: goto +3 -> 924
    //   924: iconst_m1
    //   925: istore_1
    //   926: iload 12
    //   928: ifeq +7 -> 935
    //   931: invokestatic 334	com/tencent/token/ky:f	()I
    //   934: istore_1
    //   935: aload_0
    //   936: getfield 175	com/tencent/token/mf:b	Lcom/tencent/token/md;
    //   939: astore 14
    //   941: aload_0
    //   942: getfield 82	com/tencent/token/mf:j	Lcom/tencent/token/me;
    //   945: invokeinterface 335 1 0
    //   950: istore 13
    //   952: aload 14
    //   954: getfield 182	com/tencent/token/md:h	J
    //   957: lstore 6
    //   959: iload_1
    //   960: ifle +79 -> 1039
    //   963: aload 14
    //   965: getfield 182	com/tencent/token/md:h	J
    //   968: ldc2_w 49
    //   971: lcmp
    //   972: ifne +16 -> 988
    //   975: aload 14
    //   977: getfield 181	com/tencent/token/md:g	J
    //   980: iload_1
    //   981: i2l
    //   982: ladd
    //   983: lstore 6
    //   985: goto +54 -> 1039
    //   988: iload_1
    //   989: i2l
    //   990: lstore 10
    //   992: lload 10
    //   994: aload 14
    //   996: getfield 182	com/tencent/token/md:h	J
    //   999: aload 14
    //   1001: getfield 181	com/tencent/token/md:g	J
    //   1004: lsub
    //   1005: lcmp
    //   1006: ifge +20 -> 1026
    //   1009: aload 14
    //   1011: getfield 181	com/tencent/token/md:g	J
    //   1014: lstore 6
    //   1016: lload 6
    //   1018: lload 10
    //   1020: ladd
    //   1021: lstore 6
    //   1023: goto +16 -> 1039
    //   1026: iload 13
    //   1028: ifne +11 -> 1039
    //   1031: ldc2_w 49
    //   1034: lstore 6
    //   1036: goto +3 -> 1039
    //   1039: new 337	com/tencent/token/kz$a
    //   1042: dup
    //   1043: aload 14
    //   1045: getfield 181	com/tencent/token/md:g	J
    //   1048: lload 6
    //   1050: invokespecial 340	com/tencent/token/kz$a:<init>	(JJ)V
    //   1053: astore 14
    //   1055: new 342	com/tencent/token/lc
    //   1058: dup
    //   1059: aload_0
    //   1060: getfield 298	com/tencent/token/mf:c	Lcom/tencent/halley/downloader/c/d/a;
    //   1063: getfield 261	com/tencent/halley/downloader/c/d/a:a	Ljava/lang/String;
    //   1066: aload_0
    //   1067: getfield 54	com/tencent/token/mf:k	Ljava/util/Map;
    //   1070: aload 14
    //   1072: iload 12
    //   1074: aload_0
    //   1075: invokespecial 345	com/tencent/token/lc:<init>	(Ljava/lang/String;Ljava/util/Map;Lcom/tencent/token/kz$a;ZLcom/tencent/token/lh;)V
    //   1078: astore 15
    //   1080: aload_0
    //   1081: aload 15
    //   1083: putfield 195	com/tencent/token/mf:n	Lcom/tencent/token/lb;
    //   1086: aload_0
    //   1087: invokevirtual 233	com/tencent/token/mf:a	()Z
    //   1090: istore 13
    //   1092: iload 13
    //   1094: ifeq +35 -> 1129
    //   1097: aload_0
    //   1098: getfield 82	com/tencent/token/mf:j	Lcom/tencent/token/me;
    //   1101: aload_0
    //   1102: invokeinterface 348 2 0
    //   1107: aload_0
    //   1108: aconst_null
    //   1109: putfield 195	com/tencent/token/mf:n	Lcom/tencent/token/lb;
    //   1112: aload_0
    //   1113: aload 15
    //   1115: invokevirtual 350	com/tencent/token/lc:a	()Ljava/lang/String;
    //   1118: putfield 214	com/tencent/token/mf:q	Ljava/lang/String;
    //   1121: aload 15
    //   1123: invokevirtual 352	com/tencent/token/lc:e	()V
    //   1126: goto +1812 -> 2938
    //   1129: aload_0
    //   1130: getfield 73	com/tencent/token/mf:p	Lcom/tencent/token/mi;
    //   1133: astore 16
    //   1135: aload 16
    //   1137: getfield 353	com/tencent/token/mi:d	I
    //   1140: istore_1
    //   1141: aload 16
    //   1143: iload_1
    //   1144: iconst_1
    //   1145: iadd
    //   1146: putfield 353	com/tencent/token/mi:d	I
    //   1149: new 207	com/tencent/token/mi$a
    //   1152: dup
    //   1153: iload_1
    //   1154: aload_0
    //   1155: getfield 298	com/tencent/token/mf:c	Lcom/tencent/halley/downloader/c/d/a;
    //   1158: invokespecial 356	com/tencent/token/mi$a:<init>	(ILcom/tencent/halley/downloader/c/d/a;)V
    //   1161: astore 19
    //   1163: aload 19
    //   1165: invokestatic 232	android/os/SystemClock:elapsedRealtime	()J
    //   1168: lload 8
    //   1170: lsub
    //   1171: putfield 358	com/tencent/token/mi$a:c	J
    //   1174: aload 19
    //   1176: iload 12
    //   1178: putfield 359	com/tencent/token/mi$a:a	Z
    //   1181: aload 19
    //   1183: aload_0
    //   1184: getfield 175	com/tencent/token/mf:b	Lcom/tencent/token/md;
    //   1187: invokevirtual 360	com/tencent/token/md:toString	()Ljava/lang/String;
    //   1190: putfield 362	com/tencent/token/mi$a:b	Ljava/lang/String;
    //   1193: aload 19
    //   1195: aload 14
    //   1197: invokevirtual 363	com/tencent/token/kz$a:toString	()Ljava/lang/String;
    //   1200: putfield 365	com/tencent/token/mi$a:f	Ljava/lang/String;
    //   1203: invokestatic 232	android/os/SystemClock:elapsedRealtime	()J
    //   1206: lstore 6
    //   1208: aload 15
    //   1210: invokevirtual 367	com/tencent/token/lc:d	()V
    //   1213: aload_0
    //   1214: invokevirtual 233	com/tencent/token/mf:a	()Z
    //   1217: ifeq +6 -> 1223
    //   1220: goto -123 -> 1097
    //   1223: aload_0
    //   1224: aload 15
    //   1226: getfield 369	com/tencent/token/kz:e	I
    //   1229: putfield 56	com/tencent/token/mf:d	I
    //   1232: aload_0
    //   1233: aload 15
    //   1235: getfield 370	com/tencent/token/kz:f	Ljava/lang/String;
    //   1238: putfield 60	com/tencent/token/mf:e	Ljava/lang/String;
    //   1241: aload 19
    //   1243: aload_0
    //   1244: getfield 56	com/tencent/token/mf:d	I
    //   1247: putfield 371	com/tencent/token/mi$a:e	I
    //   1250: aload 19
    //   1252: invokestatic 232	android/os/SystemClock:elapsedRealtime	()J
    //   1255: lload 8
    //   1257: lsub
    //   1258: putfield 373	com/tencent/token/mi$a:d	J
    //   1261: aload 19
    //   1263: aload 15
    //   1265: getfield 375	com/tencent/token/kz:h	Ljava/lang/String;
    //   1268: putfield 377	com/tencent/token/mi$a:g	Ljava/lang/String;
    //   1271: aload 19
    //   1273: aload 15
    //   1275: getfield 379	com/tencent/token/kz:j	Ljava/lang/String;
    //   1278: putfield 381	com/tencent/token/mi$a:i	Ljava/lang/String;
    //   1281: aload 19
    //   1283: aload 15
    //   1285: getfield 383	com/tencent/token/kz:k	Ljava/lang/String;
    //   1288: putfield 384	com/tencent/token/mi$a:j	Ljava/lang/String;
    //   1291: aload 19
    //   1293: aload 15
    //   1295: getfield 386	com/tencent/token/kz:o	J
    //   1298: putfield 387	com/tencent/token/mi$a:h	J
    //   1301: aload 19
    //   1303: aload 15
    //   1305: getfield 388	com/tencent/token/kz:i	Ljava/lang/String;
    //   1308: putfield 389	com/tencent/token/mi$a:k	Ljava/lang/String;
    //   1311: aload 19
    //   1313: aload 15
    //   1315: getfield 391	com/tencent/token/kz:m	Ljava/lang/String;
    //   1318: putfield 393	com/tencent/token/mi$a:l	Ljava/lang/String;
    //   1321: aload 19
    //   1323: aload 15
    //   1325: getfield 395	com/tencent/token/kz:n	Ljava/lang/String;
    //   1328: putfield 396	com/tencent/token/mi$a:m	Ljava/lang/String;
    //   1331: aload 19
    //   1333: aload 15
    //   1335: invokevirtual 398	com/tencent/token/lc:c	()Ljava/lang/String;
    //   1338: putfield 400	com/tencent/token/mi$a:r	Ljava/lang/String;
    //   1341: aload 19
    //   1343: aload 15
    //   1345: invokevirtual 402	com/tencent/token/lc:b	()Ljava/lang/String;
    //   1348: putfield 405	com/tencent/token/mi$a:s	Ljava/lang/String;
    //   1351: aload_0
    //   1352: getfield 73	com/tencent/token/mf:p	Lcom/tencent/token/mi;
    //   1355: aload 19
    //   1357: invokevirtual 408	com/tencent/token/mi:a	(Lcom/tencent/token/mi$a;)V
    //   1360: aload_0
    //   1361: getfield 56	com/tencent/token/mf:d	I
    //   1364: istore_1
    //   1365: aload 19
    //   1367: astore 18
    //   1369: aload 15
    //   1371: astore 14
    //   1373: iload_1
    //   1374: bipush 203
    //   1376: if_icmpne +369 -> 1745
    //   1379: aload 15
    //   1381: astore 16
    //   1383: aload 15
    //   1385: astore 17
    //   1387: aload 19
    //   1389: astore 18
    //   1391: aload 15
    //   1393: astore 14
    //   1395: aload_0
    //   1396: getfield 82	com/tencent/token/mf:j	Lcom/tencent/token/me;
    //   1399: invokeinterface 335 1 0
    //   1404: ifne +341 -> 1745
    //   1407: aload 15
    //   1409: astore 16
    //   1411: aload 15
    //   1413: astore 17
    //   1415: new 342	com/tencent/token/lc
    //   1418: dup
    //   1419: aload_0
    //   1420: getfield 298	com/tencent/token/mf:c	Lcom/tencent/halley/downloader/c/d/a;
    //   1423: getfield 261	com/tencent/halley/downloader/c/d/a:a	Ljava/lang/String;
    //   1426: aload_0
    //   1427: getfield 54	com/tencent/token/mf:k	Ljava/util/Map;
    //   1430: aconst_null
    //   1431: iload 12
    //   1433: aload_0
    //   1434: invokespecial 345	com/tencent/token/lc:<init>	(Ljava/lang/String;Ljava/util/Map;Lcom/tencent/token/kz$a;ZLcom/tencent/token/lh;)V
    //   1437: astore 14
    //   1439: aload_0
    //   1440: aload 14
    //   1442: putfield 195	com/tencent/token/mf:n	Lcom/tencent/token/lb;
    //   1445: aload_0
    //   1446: invokevirtual 233	com/tencent/token/mf:a	()Z
    //   1449: istore 13
    //   1451: iload 13
    //   1453: ifeq +35 -> 1488
    //   1456: aload_0
    //   1457: getfield 82	com/tencent/token/mf:j	Lcom/tencent/token/me;
    //   1460: aload_0
    //   1461: invokeinterface 348 2 0
    //   1466: aload_0
    //   1467: aconst_null
    //   1468: putfield 195	com/tencent/token/mf:n	Lcom/tencent/token/lb;
    //   1471: aload_0
    //   1472: aload 14
    //   1474: invokevirtual 350	com/tencent/token/lc:a	()Ljava/lang/String;
    //   1477: putfield 214	com/tencent/token/mf:q	Ljava/lang/String;
    //   1480: aload 14
    //   1482: invokevirtual 352	com/tencent/token/lc:e	()V
    //   1485: goto +1453 -> 2938
    //   1488: aload_0
    //   1489: getfield 73	com/tencent/token/mf:p	Lcom/tencent/token/mi;
    //   1492: astore 15
    //   1494: aload 15
    //   1496: getfield 353	com/tencent/token/mi:d	I
    //   1499: istore_1
    //   1500: aload 15
    //   1502: iload_1
    //   1503: iconst_1
    //   1504: iadd
    //   1505: putfield 353	com/tencent/token/mi:d	I
    //   1508: new 207	com/tencent/token/mi$a
    //   1511: dup
    //   1512: iload_1
    //   1513: aload_0
    //   1514: getfield 298	com/tencent/token/mf:c	Lcom/tencent/halley/downloader/c/d/a;
    //   1517: invokespecial 356	com/tencent/token/mi$a:<init>	(ILcom/tencent/halley/downloader/c/d/a;)V
    //   1520: astore 18
    //   1522: aload 18
    //   1524: invokestatic 232	android/os/SystemClock:elapsedRealtime	()J
    //   1527: lload 8
    //   1529: lsub
    //   1530: putfield 358	com/tencent/token/mi$a:c	J
    //   1533: aload 18
    //   1535: iload 12
    //   1537: putfield 359	com/tencent/token/mi$a:a	Z
    //   1540: aload 18
    //   1542: aload_0
    //   1543: getfield 175	com/tencent/token/mf:b	Lcom/tencent/token/md;
    //   1546: invokevirtual 360	com/tencent/token/md:toString	()Ljava/lang/String;
    //   1549: putfield 362	com/tencent/token/mi$a:b	Ljava/lang/String;
    //   1552: aload 18
    //   1554: ldc 58
    //   1556: putfield 365	com/tencent/token/mi$a:f	Ljava/lang/String;
    //   1559: aload 14
    //   1561: invokevirtual 367	com/tencent/token/lc:d	()V
    //   1564: aload_0
    //   1565: invokevirtual 233	com/tencent/token/mf:a	()Z
    //   1568: ifeq +6 -> 1574
    //   1571: goto -115 -> 1456
    //   1574: aload_0
    //   1575: aload 14
    //   1577: getfield 369	com/tencent/token/kz:e	I
    //   1580: putfield 56	com/tencent/token/mf:d	I
    //   1583: aload_0
    //   1584: aload 14
    //   1586: getfield 370	com/tencent/token/kz:f	Ljava/lang/String;
    //   1589: putfield 60	com/tencent/token/mf:e	Ljava/lang/String;
    //   1592: aload 18
    //   1594: invokestatic 232	android/os/SystemClock:elapsedRealtime	()J
    //   1597: lload 8
    //   1599: lsub
    //   1600: putfield 373	com/tencent/token/mi$a:d	J
    //   1603: aload 18
    //   1605: aload 14
    //   1607: getfield 375	com/tencent/token/kz:h	Ljava/lang/String;
    //   1610: putfield 377	com/tencent/token/mi$a:g	Ljava/lang/String;
    //   1613: aload 18
    //   1615: aload 14
    //   1617: getfield 379	com/tencent/token/kz:j	Ljava/lang/String;
    //   1620: putfield 381	com/tencent/token/mi$a:i	Ljava/lang/String;
    //   1623: aload 18
    //   1625: aload 14
    //   1627: getfield 383	com/tencent/token/kz:k	Ljava/lang/String;
    //   1630: putfield 384	com/tencent/token/mi$a:j	Ljava/lang/String;
    //   1633: aload 18
    //   1635: aload 14
    //   1637: getfield 386	com/tencent/token/kz:o	J
    //   1640: putfield 387	com/tencent/token/mi$a:h	J
    //   1643: aload 18
    //   1645: aload 14
    //   1647: getfield 388	com/tencent/token/kz:i	Ljava/lang/String;
    //   1650: putfield 389	com/tencent/token/mi$a:k	Ljava/lang/String;
    //   1653: aload 18
    //   1655: aload 14
    //   1657: getfield 391	com/tencent/token/kz:m	Ljava/lang/String;
    //   1660: putfield 393	com/tencent/token/mi$a:l	Ljava/lang/String;
    //   1663: aload 18
    //   1665: aload 14
    //   1667: getfield 395	com/tencent/token/kz:n	Ljava/lang/String;
    //   1670: putfield 396	com/tencent/token/mi$a:m	Ljava/lang/String;
    //   1673: aload 18
    //   1675: aload 14
    //   1677: invokevirtual 398	com/tencent/token/lc:c	()Ljava/lang/String;
    //   1680: putfield 400	com/tencent/token/mi$a:r	Ljava/lang/String;
    //   1683: aload 18
    //   1685: aload 14
    //   1687: invokevirtual 402	com/tencent/token/lc:b	()Ljava/lang/String;
    //   1690: putfield 405	com/tencent/token/mi$a:s	Ljava/lang/String;
    //   1693: aload_0
    //   1694: getfield 73	com/tencent/token/mf:p	Lcom/tencent/token/mi;
    //   1697: aload 18
    //   1699: invokevirtual 408	com/tencent/token/mi:a	(Lcom/tencent/token/mi$a;)V
    //   1702: goto +43 -> 1745
    //   1705: astore 15
    //   1707: aload 14
    //   1709: astore 16
    //   1711: aload 15
    //   1713: astore 14
    //   1715: aload 16
    //   1717: astore 15
    //   1719: goto +14 -> 1733
    //   1722: astore 15
    //   1724: goto +1346 -> 3070
    //   1727: astore 14
    //   1729: aload 16
    //   1731: astore 15
    //   1733: goto +1168 -> 2901
    //   1736: astore 15
    //   1738: aload 17
    //   1740: astore 14
    //   1742: goto +1328 -> 3070
    //   1745: invokestatic 232	android/os/SystemClock:elapsedRealtime	()J
    //   1748: lstore 10
    //   1750: new 127	java/lang/StringBuilder
    //   1753: dup
    //   1754: ldc_w 303
    //   1757: invokespecial 132	java/lang/StringBuilder:<init>	(Ljava/lang/String;)V
    //   1760: astore 15
    //   1762: aload 15
    //   1764: aload_0
    //   1765: getfield 48	com/tencent/token/mf:a	Z
    //   1768: invokevirtual 166	java/lang/StringBuilder:append	(Z)Ljava/lang/StringBuilder;
    //   1771: pop
    //   1772: aload 15
    //   1774: ldc_w 410
    //   1777: invokevirtual 136	java/lang/StringBuilder:append	(Ljava/lang/String;)Ljava/lang/StringBuilder;
    //   1780: pop
    //   1781: aload 15
    //   1783: aload_0
    //   1784: getfield 56	com/tencent/token/mf:d	I
    //   1787: invokevirtual 171	java/lang/StringBuilder:append	(I)Ljava/lang/StringBuilder;
    //   1790: pop
    //   1791: aload 15
    //   1793: ldc_w 412
    //   1796: invokevirtual 136	java/lang/StringBuilder:append	(Ljava/lang/String;)Ljava/lang/StringBuilder;
    //   1799: pop
    //   1800: aload 15
    //   1802: aload_0
    //   1803: getfield 60	com/tencent/token/mf:e	Ljava/lang/String;
    //   1806: invokevirtual 136	java/lang/StringBuilder:append	(Ljava/lang/String;)Ljava/lang/StringBuilder;
    //   1809: pop
    //   1810: ldc 145
    //   1812: aload 15
    //   1814: invokevirtual 149	java/lang/StringBuilder:toString	()Ljava/lang/String;
    //   1817: invokestatic 328	com/tencent/token/li:b	(Ljava/lang/String;Ljava/lang/String;)V
    //   1820: aload_0
    //   1821: getfield 56	com/tencent/token/mf:d	I
    //   1824: istore_1
    //   1825: iload_1
    //   1826: ifeq +138 -> 1964
    //   1829: aload 14
    //   1831: astore 16
    //   1833: aload 14
    //   1835: astore 17
    //   1837: aload_0
    //   1838: getfield 56	com/tencent/token/mf:d	I
    //   1841: istore_1
    //   1842: iload_1
    //   1843: bipush 245
    //   1845: if_icmpne +35 -> 1880
    //   1848: aload_0
    //   1849: getfield 82	com/tencent/token/mf:j	Lcom/tencent/token/me;
    //   1852: aload_0
    //   1853: invokeinterface 348 2 0
    //   1858: aload_0
    //   1859: aconst_null
    //   1860: putfield 195	com/tencent/token/mf:n	Lcom/tencent/token/lb;
    //   1863: aload_0
    //   1864: aload 14
    //   1866: invokevirtual 350	com/tencent/token/lc:a	()Ljava/lang/String;
    //   1869: putfield 214	com/tencent/token/mf:q	Ljava/lang/String;
    //   1872: aload 14
    //   1874: invokevirtual 352	com/tencent/token/lc:e	()V
    //   1877: goto +1061 -> 2938
    //   1880: aload 14
    //   1882: astore 16
    //   1884: aload 14
    //   1886: astore 17
    //   1888: aload_0
    //   1889: getfield 56	com/tencent/token/mf:d	I
    //   1892: bipush 197
    //   1894: if_icmpne +1182 -> 3076
    //   1897: iconst_0
    //   1898: istore_1
    //   1899: iconst_1
    //   1900: istore 12
    //   1902: goto +1176 -> 3078
    //   1905: aload 14
    //   1907: astore 16
    //   1909: aload 14
    //   1911: astore 17
    //   1913: aload_0
    //   1914: getfield 56	com/tencent/token/mf:d	I
    //   1917: istore_2
    //   1918: iload_2
    //   1919: bipush 240
    //   1921: if_icmpeq +23 -> 1944
    //   1924: iload_2
    //   1925: bipush 241
    //   1927: if_icmpeq +17 -> 1944
    //   1930: iload_2
    //   1931: bipush 204
    //   1933: if_icmpne +6 -> 1939
    //   1936: goto +8 -> 1944
    //   1939: iconst_0
    //   1940: istore_2
    //   1941: goto +5 -> 1946
    //   1944: iconst_1
    //   1945: istore_2
    //   1946: iload_2
    //   1947: ifeq +10 -> 1957
    //   1950: sipush 3000
    //   1953: istore_2
    //   1954: goto +1138 -> 3092
    //   1957: sipush 1000
    //   1960: istore_2
    //   1961: goto +1131 -> 3092
    //   1964: aload_0
    //   1965: aload 14
    //   1967: invokespecial 414	com/tencent/token/mf:a	(Lcom/tencent/token/kz;)V
    //   1970: aload_0
    //   1971: invokevirtual 233	com/tencent/token/mf:a	()Z
    //   1974: istore 13
    //   1976: iload 13
    //   1978: ifeq +21 -> 1999
    //   1981: aload_0
    //   1982: getfield 82	com/tencent/token/mf:j	Lcom/tencent/token/me;
    //   1985: aload_0
    //   1986: invokeinterface 348 2 0
    //   1991: aload_0
    //   1992: aconst_null
    //   1993: putfield 195	com/tencent/token/mf:n	Lcom/tencent/token/lb;
    //   1996: goto -133 -> 1863
    //   1999: aload_0
    //   2000: getfield 82	com/tencent/token/mf:j	Lcom/tencent/token/me;
    //   2003: astore 17
    //   2005: aload_0
    //   2006: getfield 298	com/tencent/token/mf:c	Lcom/tencent/halley/downloader/c/d/a;
    //   2009: astore 19
    //   2011: aload 14
    //   2013: getfield 416	com/tencent/token/kz:b	Ljava/util/List;
    //   2016: astore 15
    //   2018: aload 15
    //   2020: ifnull +67 -> 2087
    //   2023: aload 14
    //   2025: getfield 416	com/tencent/token/kz:b	Ljava/util/List;
    //   2028: invokeinterface 95 1 0
    //   2033: ifle +54 -> 2087
    //   2036: aload 14
    //   2038: getfield 416	com/tencent/token/kz:b	Ljava/util/List;
    //   2041: astore 15
    //   2043: aload 14
    //   2045: getfield 416	com/tencent/token/kz:b	Ljava/util/List;
    //   2048: invokeinterface 95 1 0
    //   2053: istore_1
    //   2054: aload 15
    //   2056: iload_1
    //   2057: iconst_1
    //   2058: isub
    //   2059: invokeinterface 419 2 0
    //   2064: checkcast 111	java/lang/String
    //   2067: astore 15
    //   2069: goto +21 -> 2090
    //   2072: astore 15
    //   2074: goto +10 -> 2084
    //   2077: astore 15
    //   2079: goto +714 -> 2793
    //   2082: astore 15
    //   2084: goto +734 -> 2818
    //   2087: aconst_null
    //   2088: astore 15
    //   2090: aload 14
    //   2092: getfield 386	com/tencent/token/kz:o	J
    //   2095: lstore 6
    //   2097: aload 14
    //   2099: getfield 422	com/tencent/token/kz:c	Lcom/tencent/token/kz$b;
    //   2102: invokevirtual 426	com/tencent/token/kz$b:a	()I
    //   2105: ifle +992 -> 3097
    //   2108: iconst_1
    //   2109: istore 13
    //   2111: goto +3 -> 2114
    //   2114: aload 14
    //   2116: getfield 391	com/tencent/token/kz:m	Ljava/lang/String;
    //   2119: astore 20
    //   2121: aload 14
    //   2123: getfield 395	com/tencent/token/kz:n	Ljava/lang/String;
    //   2126: astore 21
    //   2128: aload 14
    //   2130: getfield 388	com/tencent/token/kz:i	Ljava/lang/String;
    //   2133: astore 22
    //   2135: aload 14
    //   2137: getfield 427	com/tencent/token/kz:l	Ljava/lang/String;
    //   2140: astore 23
    //   2142: aload 14
    //   2144: astore 16
    //   2146: aload 17
    //   2148: aload_0
    //   2149: aload 19
    //   2151: aload 15
    //   2153: lload 6
    //   2155: iload 13
    //   2157: aload 20
    //   2159: aload 21
    //   2161: aload 22
    //   2163: aload 23
    //   2165: invokeinterface 430 11 0
    //   2170: astore 15
    //   2172: new 127	java/lang/StringBuilder
    //   2175: dup
    //   2176: ldc_w 303
    //   2179: invokespecial 132	java/lang/StringBuilder:<init>	(Ljava/lang/String;)V
    //   2182: astore 17
    //   2184: aload 17
    //   2186: aload_0
    //   2187: getfield 48	com/tencent/token/mf:a	Z
    //   2190: invokevirtual 166	java/lang/StringBuilder:append	(Z)Ljava/lang/StringBuilder;
    //   2193: pop
    //   2194: aload 17
    //   2196: ldc_w 432
    //   2199: invokevirtual 136	java/lang/StringBuilder:append	(Ljava/lang/String;)Ljava/lang/StringBuilder;
    //   2202: pop
    //   2203: aload 17
    //   2205: aload 15
    //   2207: getfield 436	com/tencent/token/lo:a	I
    //   2210: invokevirtual 171	java/lang/StringBuilder:append	(I)Ljava/lang/StringBuilder;
    //   2213: pop
    //   2214: aload 17
    //   2216: ldc 212
    //   2218: invokevirtual 136	java/lang/StringBuilder:append	(Ljava/lang/String;)Ljava/lang/StringBuilder;
    //   2221: pop
    //   2222: aload 17
    //   2224: aload 15
    //   2226: getfield 437	com/tencent/token/lo:b	Ljava/lang/String;
    //   2229: invokevirtual 136	java/lang/StringBuilder:append	(Ljava/lang/String;)Ljava/lang/StringBuilder;
    //   2232: pop
    //   2233: ldc 145
    //   2235: aload 17
    //   2237: invokevirtual 149	java/lang/StringBuilder:toString	()Ljava/lang/String;
    //   2240: invokestatic 328	com/tencent/token/li:b	(Ljava/lang/String;Ljava/lang/String;)V
    //   2243: aload_0
    //   2244: invokevirtual 233	com/tencent/token/mf:a	()Z
    //   2247: istore 13
    //   2249: iload 13
    //   2251: ifeq +35 -> 2286
    //   2254: aload_0
    //   2255: getfield 82	com/tencent/token/mf:j	Lcom/tencent/token/me;
    //   2258: aload_0
    //   2259: invokeinterface 348 2 0
    //   2264: aload_0
    //   2265: aconst_null
    //   2266: putfield 195	com/tencent/token/mf:n	Lcom/tencent/token/lb;
    //   2269: aload_0
    //   2270: aload 16
    //   2272: invokevirtual 350	com/tencent/token/lc:a	()Ljava/lang/String;
    //   2275: putfield 214	com/tencent/token/mf:q	Ljava/lang/String;
    //   2278: aload 16
    //   2280: invokevirtual 352	com/tencent/token/lc:e	()V
    //   2283: goto +655 -> 2938
    //   2286: aload 18
    //   2288: aload 15
    //   2290: getfield 436	com/tencent/token/lo:a	I
    //   2293: putfield 439	com/tencent/token/mi$a:n	I
    //   2296: aload 15
    //   2298: getfield 436	com/tencent/token/lo:a	I
    //   2301: ifne +202 -> 2503
    //   2304: aload_0
    //   2305: invokevirtual 233	com/tencent/token/mf:a	()Z
    //   2308: ifeq +6 -> 2314
    //   2311: goto -57 -> 2254
    //   2314: new 127	java/lang/StringBuilder
    //   2317: dup
    //   2318: ldc_w 303
    //   2321: invokespecial 132	java/lang/StringBuilder:<init>	(Ljava/lang/String;)V
    //   2324: astore 15
    //   2326: aload 15
    //   2328: aload_0
    //   2329: getfield 48	com/tencent/token/mf:a	Z
    //   2332: invokevirtual 166	java/lang/StringBuilder:append	(Z)Ljava/lang/StringBuilder;
    //   2335: pop
    //   2336: aload 15
    //   2338: ldc_w 441
    //   2341: invokevirtual 136	java/lang/StringBuilder:append	(Ljava/lang/String;)Ljava/lang/StringBuilder;
    //   2344: pop
    //   2345: aload 15
    //   2347: aload_0
    //   2348: getfield 175	com/tencent/token/mf:b	Lcom/tencent/token/md;
    //   2351: invokevirtual 141	java/lang/StringBuilder:append	(Ljava/lang/Object;)Ljava/lang/StringBuilder;
    //   2354: pop
    //   2355: ldc 145
    //   2357: aload 15
    //   2359: invokevirtual 149	java/lang/StringBuilder:toString	()Ljava/lang/String;
    //   2362: invokestatic 328	com/tencent/token/li:b	(Ljava/lang/String;Ljava/lang/String;)V
    //   2365: aload 16
    //   2367: aload_0
    //   2368: invokevirtual 444	com/tencent/token/lc:a	(Lcom/tencent/token/la;)V
    //   2371: aload_0
    //   2372: aload 16
    //   2374: getfield 369	com/tencent/token/kz:e	I
    //   2377: putfield 56	com/tencent/token/mf:d	I
    //   2380: aload_0
    //   2381: aload 16
    //   2383: getfield 370	com/tencent/token/kz:f	Ljava/lang/String;
    //   2386: putfield 60	com/tencent/token/mf:e	Ljava/lang/String;
    //   2389: new 127	java/lang/StringBuilder
    //   2392: dup
    //   2393: ldc_w 303
    //   2396: invokespecial 132	java/lang/StringBuilder:<init>	(Ljava/lang/String;)V
    //   2399: astore 15
    //   2401: aload 15
    //   2403: aload_0
    //   2404: getfield 48	com/tencent/token/mf:a	Z
    //   2407: invokevirtual 166	java/lang/StringBuilder:append	(Z)Ljava/lang/StringBuilder;
    //   2410: pop
    //   2411: aload 15
    //   2413: ldc_w 446
    //   2416: invokevirtual 136	java/lang/StringBuilder:append	(Ljava/lang/String;)Ljava/lang/StringBuilder;
    //   2419: pop
    //   2420: aload 15
    //   2422: aload_0
    //   2423: getfield 56	com/tencent/token/mf:d	I
    //   2426: invokevirtual 171	java/lang/StringBuilder:append	(I)Ljava/lang/StringBuilder;
    //   2429: pop
    //   2430: aload 15
    //   2432: ldc_w 448
    //   2435: invokevirtual 136	java/lang/StringBuilder:append	(Ljava/lang/String;)Ljava/lang/StringBuilder;
    //   2438: pop
    //   2439: aload 15
    //   2441: aload_0
    //   2442: getfield 60	com/tencent/token/mf:e	Ljava/lang/String;
    //   2445: invokevirtual 136	java/lang/StringBuilder:append	(Ljava/lang/String;)Ljava/lang/StringBuilder;
    //   2448: pop
    //   2449: ldc 145
    //   2451: aload 15
    //   2453: invokevirtual 149	java/lang/StringBuilder:toString	()Ljava/lang/String;
    //   2456: invokestatic 328	com/tencent/token/li:b	(Ljava/lang/String;Ljava/lang/String;)V
    //   2459: aload 18
    //   2461: aload_0
    //   2462: getfield 56	com/tencent/token/mf:d	I
    //   2465: putfield 450	com/tencent/token/mi$a:o	I
    //   2468: aload 18
    //   2470: aload_0
    //   2471: getfield 175	com/tencent/token/mf:b	Lcom/tencent/token/md;
    //   2474: invokevirtual 360	com/tencent/token/md:toString	()Ljava/lang/String;
    //   2477: putfield 452	com/tencent/token/mi$a:p	Ljava/lang/String;
    //   2480: aload 18
    //   2482: invokestatic 232	android/os/SystemClock:elapsedRealtime	()J
    //   2485: lload 8
    //   2487: lsub
    //   2488: putfield 454	com/tencent/token/mi$a:q	J
    //   2491: aload_0
    //   2492: getfield 56	com/tencent/token/mf:d	I
    //   2495: ifeq +608 -> 3103
    //   2498: iconst_1
    //   2499: istore_1
    //   2500: goto +605 -> 3105
    //   2503: aload 15
    //   2505: getfield 436	com/tencent/token/lo:a	I
    //   2508: ifge +607 -> 3115
    //   2511: aload_0
    //   2512: aload 15
    //   2514: getfield 436	com/tencent/token/lo:a	I
    //   2517: putfield 56	com/tencent/token/mf:d	I
    //   2520: aload_0
    //   2521: aload 15
    //   2523: getfield 437	com/tencent/token/lo:b	Ljava/lang/String;
    //   2526: putfield 60	com/tencent/token/mf:e	Ljava/lang/String;
    //   2529: iconst_1
    //   2530: istore_1
    //   2531: goto +586 -> 3117
    //   2534: aload 14
    //   2536: astore 15
    //   2538: iload_3
    //   2539: ifeq +176 -> 2715
    //   2542: invokestatic 232	android/os/SystemClock:elapsedRealtime	()J
    //   2545: lload 4
    //   2547: lsub
    //   2548: lstore 6
    //   2550: invokestatic 456	com/tencent/token/ky:i	()I
    //   2553: pop
    //   2554: lload 6
    //   2556: ldc2_w 457
    //   2559: lcmp
    //   2560: ifle +35 -> 2595
    //   2563: aload_0
    //   2564: getfield 82	com/tencent/token/mf:j	Lcom/tencent/token/me;
    //   2567: aload_0
    //   2568: invokeinterface 348 2 0
    //   2573: aload_0
    //   2574: aconst_null
    //   2575: putfield 195	com/tencent/token/mf:n	Lcom/tencent/token/lb;
    //   2578: aload_0
    //   2579: aload 15
    //   2581: invokevirtual 350	com/tencent/token/lc:a	()Ljava/lang/String;
    //   2584: putfield 214	com/tencent/token/mf:q	Ljava/lang/String;
    //   2587: aload 15
    //   2589: invokevirtual 352	com/tencent/token/lc:e	()V
    //   2592: goto +346 -> 2938
    //   2595: aload_0
    //   2596: getfield 56	com/tencent/token/mf:d	I
    //   2599: istore_3
    //   2600: iload_3
    //   2601: bipush 240
    //   2603: if_icmpeq +528 -> 3131
    //   2606: iload_3
    //   2607: bipush 241
    //   2609: if_icmpeq +522 -> 3131
    //   2612: iload_3
    //   2613: bipush 204
    //   2615: if_icmpne +511 -> 3126
    //   2618: goto +513 -> 3131
    //   2621: iload_3
    //   2622: ifeq +19 -> 2641
    //   2625: invokestatic 460	com/tencent/token/ky:j	()I
    //   2628: pop
    //   2629: lload 6
    //   2631: ldc2_w 461
    //   2634: lcmp
    //   2635: ifle +6 -> 2641
    //   2638: goto -75 -> 2563
    //   2641: aload_0
    //   2642: getfield 56	com/tencent/token/mf:d	I
    //   2645: istore_3
    //   2646: iload_3
    //   2647: bipush 246
    //   2649: if_icmpeq +492 -> 3141
    //   2652: iload_3
    //   2653: bipush 213
    //   2655: if_icmpne +481 -> 3136
    //   2658: goto +483 -> 3141
    //   2661: iload_3
    //   2662: ifeq +19 -> 2681
    //   2665: invokestatic 456	com/tencent/token/ky:i	()I
    //   2668: pop
    //   2669: lload 6
    //   2671: ldc2_w 463
    //   2674: lcmp
    //   2675: ifle +6 -> 2681
    //   2678: goto -115 -> 2563
    //   2681: aload_0
    //   2682: getfield 56	com/tencent/token/mf:d	I
    //   2685: bipush 241
    //   2687: if_icmpne +28 -> 2715
    //   2690: invokestatic 466	com/tencent/token/ky:k	()I
    //   2693: istore_3
    //   2694: lload 6
    //   2696: iload_3
    //   2697: i2l
    //   2698: lcmp
    //   2699: ifle +16 -> 2715
    //   2702: goto -139 -> 2563
    //   2705: astore 15
    //   2707: goto +56 -> 2763
    //   2710: astore 15
    //   2712: goto +68 -> 2780
    //   2715: aload_0
    //   2716: getfield 82	com/tencent/token/mf:j	Lcom/tencent/token/me;
    //   2719: aload_0
    //   2720: invokeinterface 348 2 0
    //   2725: aload_0
    //   2726: aconst_null
    //   2727: putfield 195	com/tencent/token/mf:n	Lcom/tencent/token/lb;
    //   2730: aload_0
    //   2731: aload 15
    //   2733: invokevirtual 350	com/tencent/token/lc:a	()Ljava/lang/String;
    //   2736: putfield 214	com/tencent/token/mf:q	Ljava/lang/String;
    //   2739: aload 15
    //   2741: invokevirtual 352	com/tencent/token/lc:e	()V
    //   2744: lload 4
    //   2746: lstore 6
    //   2748: goto -2723 -> 25
    //   2751: astore 15
    //   2753: goto +10 -> 2763
    //   2756: astore 15
    //   2758: goto +22 -> 2780
    //   2761: astore 15
    //   2763: aload 14
    //   2765: astore 16
    //   2767: aload 15
    //   2769: astore 14
    //   2771: aload 16
    //   2773: astore 15
    //   2775: goto +126 -> 2901
    //   2778: astore 15
    //   2780: goto +54 -> 2834
    //   2783: astore 16
    //   2785: aload 15
    //   2787: astore 14
    //   2789: aload 16
    //   2791: astore 15
    //   2793: aload 14
    //   2795: astore 16
    //   2797: aload 15
    //   2799: astore 14
    //   2801: aload 16
    //   2803: astore 15
    //   2805: goto +96 -> 2901
    //   2808: astore 16
    //   2810: aload 15
    //   2812: astore 14
    //   2814: aload 16
    //   2816: astore 15
    //   2818: goto +16 -> 2834
    //   2821: astore 14
    //   2823: aconst_null
    //   2824: astore 15
    //   2826: goto +75 -> 2901
    //   2829: astore 15
    //   2831: aconst_null
    //   2832: astore 14
    //   2834: aload 15
    //   2836: invokevirtual 467	java/lang/Throwable:printStackTrace	()V
    //   2839: aload_0
    //   2840: bipush 195
    //   2842: putfield 56	com/tencent/token/mf:d	I
    //   2845: aload_0
    //   2846: aload 15
    //   2848: invokestatic 471	java/lang/String:valueOf	(Ljava/lang/Object;)Ljava/lang/String;
    //   2851: putfield 60	com/tencent/token/mf:e	Ljava/lang/String;
    //   2854: aload_0
    //   2855: getfield 82	com/tencent/token/mf:j	Lcom/tencent/token/me;
    //   2858: aload_0
    //   2859: invokeinterface 348 2 0
    //   2864: aload_0
    //   2865: aconst_null
    //   2866: putfield 195	com/tencent/token/mf:n	Lcom/tencent/token/lb;
    //   2869: aload 14
    //   2871: ifnull +67 -> 2938
    //   2874: aload_0
    //   2875: aload 14
    //   2877: invokevirtual 350	com/tencent/token/lc:a	()Ljava/lang/String;
    //   2880: putfield 214	com/tencent/token/mf:q	Ljava/lang/String;
    //   2883: aload 14
    //   2885: invokevirtual 352	com/tencent/token/lc:e	()V
    //   2888: goto +50 -> 2938
    //   2891: astore 16
    //   2893: aload 14
    //   2895: astore 15
    //   2897: aload 16
    //   2899: astore 14
    //   2901: aload_0
    //   2902: getfield 82	com/tencent/token/mf:j	Lcom/tencent/token/me;
    //   2905: aload_0
    //   2906: invokeinterface 348 2 0
    //   2911: aload_0
    //   2912: aconst_null
    //   2913: putfield 195	com/tencent/token/mf:n	Lcom/tencent/token/lb;
    //   2916: aload 15
    //   2918: ifnull +17 -> 2935
    //   2921: aload_0
    //   2922: aload 15
    //   2924: invokevirtual 350	com/tencent/token/lc:a	()Ljava/lang/String;
    //   2927: putfield 214	com/tencent/token/mf:q	Ljava/lang/String;
    //   2930: aload 15
    //   2932: invokevirtual 352	com/tencent/token/lc:e	()V
    //   2935: aload 14
    //   2937: athrow
    //   2938: new 127	java/lang/StringBuilder
    //   2941: dup
    //   2942: ldc_w 473
    //   2945: invokespecial 132	java/lang/StringBuilder:<init>	(Ljava/lang/String;)V
    //   2948: astore 14
    //   2950: aload 14
    //   2952: aload_0
    //   2953: getfield 56	com/tencent/token/mf:d	I
    //   2956: invokevirtual 171	java/lang/StringBuilder:append	(I)Ljava/lang/StringBuilder;
    //   2959: pop
    //   2960: aload 14
    //   2962: ldc_w 412
    //   2965: invokevirtual 136	java/lang/StringBuilder:append	(Ljava/lang/String;)Ljava/lang/StringBuilder;
    //   2968: pop
    //   2969: aload 14
    //   2971: aload_0
    //   2972: getfield 60	com/tencent/token/mf:e	Ljava/lang/String;
    //   2975: invokevirtual 136	java/lang/StringBuilder:append	(Ljava/lang/String;)Ljava/lang/StringBuilder;
    //   2978: pop
    //   2979: ldc 145
    //   2981: aload 14
    //   2983: invokevirtual 149	java/lang/StringBuilder:toString	()Ljava/lang/String;
    //   2986: invokestatic 475	com/tencent/token/li:c	(Ljava/lang/String;Ljava/lang/String;)V
    //   2989: aload_0
    //   2990: iconst_1
    //   2991: putfield 64	com/tencent/token/mf:f	Z
    //   2994: aload_0
    //   2995: getfield 73	com/tencent/token/mf:p	Lcom/tencent/token/mi;
    //   2998: invokestatic 225	java/lang/System:currentTimeMillis	()J
    //   3001: aload_0
    //   3002: getfield 73	com/tencent/token/mf:p	Lcom/tencent/token/mi;
    //   3005: getfield 227	com/tencent/token/mi:b	J
    //   3008: lsub
    //   3009: putfield 476	com/tencent/token/mi:c	J
    //   3012: aload_0
    //   3013: getfield 82	com/tencent/token/mf:j	Lcom/tencent/token/me;
    //   3016: aload_0
    //   3017: invokeinterface 478 2 0
    //   3022: return
    //   3023: astore 14
    //   3025: aload 14
    //   3027: invokevirtual 467	java/lang/Throwable:printStackTrace	()V
    //   3030: return
    //   3031: astore 14
    //   3033: goto -2133 -> 900
    //   3036: iconst_0
    //   3037: istore_3
    //   3038: goto +5 -> 3043
    //   3041: iconst_1
    //   3042: istore_3
    //   3043: iload_3
    //   3044: ifeq +8 -> 3052
    //   3047: iconst_1
    //   3048: istore_3
    //   3049: goto -2921 -> 128
    //   3052: iconst_0
    //   3053: istore_3
    //   3054: goto -2926 -> 128
    //   3057: astore 14
    //   3059: aconst_null
    //   3060: astore 15
    //   3062: goto -161 -> 2901
    //   3065: astore 15
    //   3067: aconst_null
    //   3068: astore 14
    //   3070: goto -236 -> 2834
    //   3073: goto -2149 -> 924
    //   3076: iconst_1
    //   3077: istore_1
    //   3078: lload 10
    //   3080: lload 6
    //   3082: lsub
    //   3083: ldc2_w 479
    //   3086: lcmp
    //   3087: ifle -1182 -> 1905
    //   3090: iconst_0
    //   3091: istore_2
    //   3092: iconst_1
    //   3093: istore_3
    //   3094: goto -560 -> 2534
    //   3097: iconst_0
    //   3098: istore 13
    //   3100: goto -986 -> 2114
    //   3103: iconst_0
    //   3104: istore_1
    //   3105: iconst_0
    //   3106: istore_2
    //   3107: lconst_0
    //   3108: lstore 4
    //   3110: iconst_0
    //   3111: istore_3
    //   3112: goto -578 -> 2534
    //   3115: iconst_0
    //   3116: istore_1
    //   3117: sipush 1000
    //   3120: istore_2
    //   3121: iconst_1
    //   3122: istore_3
    //   3123: goto -589 -> 2534
    //   3126: iconst_0
    //   3127: istore_3
    //   3128: goto -507 -> 2621
    //   3131: iconst_1
    //   3132: istore_3
    //   3133: goto -512 -> 2621
    //   3136: iconst_0
    //   3137: istore_3
    //   3138: goto -477 -> 2661
    //   3141: iconst_1
    //   3142: istore_3
    //   3143: goto -482 -> 2661
    // Local variable table:
    //   start	length	slot	name	signature
    //   0	3146	0	this	mf
    //   16	3101	1	i1	int
    //   18	3103	2	i2	int
    //   128	3015	3	i3	int
    //   446	2663	4	l1	long
    //   20	3061	6	l2	long
    //   13	2473	8	l3	long
    //   990	2089	10	l4	long
    //   23	1878	12	bool1	boolean
    //   486	2613	13	bool2	boolean
    //   55	271	14	localObject1	Object
    //   360	3	14	localException1	java.lang.Exception
    //   396	1318	14	localObject2	Object
    //   1727	1	14	localObject3	Object
    //   1740	1073	14	localObject4	Object
    //   2821	1	14	localObject5	Object
    //   2832	150	14	localObject6	Object
    //   3023	3	14	localThrowable1	Throwable
    //   3031	1	14	localException2	java.lang.Exception
    //   3057	1	14	localObject7	Object
    //   3068	1	14	localObject8	Object
    //   61	249	15	localObject9	Object
    //   413	1	15	localObject10	Object
    //   418	17	15	localInterruptedException	java.lang.InterruptedException
    //   667	834	15	localObject11	Object
    //   1705	7	15	localObject12	Object
    //   1717	1	15	localObject13	Object
    //   1722	1	15	localThrowable2	Throwable
    //   1731	1	15	localObject14	Object
    //   1736	1	15	localThrowable3	Throwable
    //   1760	308	15	localObject15	Object
    //   2072	1	15	localThrowable4	Throwable
    //   2077	1	15	localObject16	Object
    //   2082	1	15	localThrowable5	Throwable
    //   2088	500	15	localObject17	Object
    //   2705	1	15	localObject18	Object
    //   2710	30	15	localThrowable6	Throwable
    //   2751	1	15	localObject19	Object
    //   2756	1	15	localThrowable7	Throwable
    //   2761	7	15	localObject20	Object
    //   2773	1	15	localObject21	Object
    //   2778	8	15	localThrowable8	Throwable
    //   2791	34	15	localObject22	Object
    //   2829	18	15	localThrowable9	Throwable
    //   2895	166	15	localObject23	Object
    //   3065	1	15	localThrowable10	Throwable
    //   149	2623	16	localObject24	Object
    //   2783	7	16	localObject25	Object
    //   2795	7	16	localObject26	Object
    //   2808	7	16	localThrowable11	Throwable
    //   2891	7	16	localObject27	Object
    //   248	1988	17	localObject28	Object
    //   305	2176	18	localObject29	Object
    //   1161	989	19	localObject30	Object
    //   2119	39	20	str1	String
    //   2126	34	21	str2	String
    //   2133	29	22	str3	String
    //   2140	24	23	str4	String
    // Exception table:
    //   from	to	target	type
    //   32	88	360	java/lang/Exception
    //   93	101	360	java/lang/Exception
    //   104	125	360	java/lang/Exception
    //   132	151	360	java/lang/Exception
    //   156	182	360	java/lang/Exception
    //   185	208	360	java/lang/Exception
    //   213	219	360	java/lang/Exception
    //   219	228	360	java/lang/Exception
    //   228	263	360	java/lang/Exception
    //   263	282	360	java/lang/Exception
    //   282	357	360	java/lang/Exception
    //   401	410	413	finally
    //   420	425	413	finally
    //   425	428	413	finally
    //   401	410	418	java/lang/InterruptedException
    //   1439	1451	1705	finally
    //   1488	1571	1705	finally
    //   1574	1702	1705	finally
    //   1439	1451	1722	java/lang/Throwable
    //   1488	1571	1722	java/lang/Throwable
    //   1574	1702	1722	java/lang/Throwable
    //   1395	1407	1727	finally
    //   1415	1439	1727	finally
    //   1837	1842	1727	finally
    //   1888	1897	1727	finally
    //   1913	1918	1727	finally
    //   1395	1407	1736	java/lang/Throwable
    //   1415	1439	1736	java/lang/Throwable
    //   1837	1842	1736	java/lang/Throwable
    //   1888	1897	1736	java/lang/Throwable
    //   1913	1918	1736	java/lang/Throwable
    //   2054	2069	2072	java/lang/Throwable
    //   2023	2054	2077	finally
    //   2054	2069	2077	finally
    //   2023	2054	2082	java/lang/Throwable
    //   2146	2249	2705	finally
    //   2286	2311	2705	finally
    //   2314	2498	2705	finally
    //   2503	2529	2705	finally
    //   2542	2554	2705	finally
    //   2595	2600	2705	finally
    //   2625	2629	2705	finally
    //   2641	2646	2705	finally
    //   2665	2669	2705	finally
    //   2681	2694	2705	finally
    //   2146	2249	2710	java/lang/Throwable
    //   2286	2311	2710	java/lang/Throwable
    //   2314	2498	2710	java/lang/Throwable
    //   2503	2529	2710	java/lang/Throwable
    //   2542	2554	2710	java/lang/Throwable
    //   2595	2600	2710	java/lang/Throwable
    //   2625	2629	2710	java/lang/Throwable
    //   2641	2646	2710	java/lang/Throwable
    //   2665	2669	2710	java/lang/Throwable
    //   2681	2694	2710	java/lang/Throwable
    //   1999	2018	2751	finally
    //   1999	2018	2756	java/lang/Throwable
    //   1745	1825	2761	finally
    //   1964	1976	2761	finally
    //   2090	2108	2761	finally
    //   2114	2142	2761	finally
    //   1745	1825	2778	java/lang/Throwable
    //   1964	1976	2778	java/lang/Throwable
    //   2090	2108	2778	java/lang/Throwable
    //   2114	2142	2778	java/lang/Throwable
    //   1080	1092	2783	finally
    //   1129	1220	2783	finally
    //   1223	1365	2783	finally
    //   1080	1092	2808	java/lang/Throwable
    //   1129	1220	2808	java/lang/Throwable
    //   1223	1365	2808	java/lang/Throwable
    //   935	959	2821	finally
    //   1039	1080	2821	finally
    //   935	959	2829	java/lang/Throwable
    //   1039	1080	2829	java/lang/Throwable
    //   2834	2854	2891	finally
    //   3012	3022	3023	java/lang/Throwable
    //   849	900	3031	java/lang/Exception
    //   912	918	3057	finally
    //   931	935	3057	finally
    //   963	985	3057	finally
    //   992	1016	3057	finally
    //   912	918	3065	java/lang/Throwable
    //   931	935	3065	java/lang/Throwable
    //   963	985	3065	java/lang/Throwable
    //   992	1016	3065	java/lang/Throwable
  }
}


/* Location:           L:\local\mybackup\temp\qq_apk\com.tencent.token\classes.jar
 * Qualified Name:     com.tencent.token.mf
 * JD-Core Version:    0.7.0.1
 */