package com.tencent.mm.plugin.wallet_core.model;

import java.util.Map;

final class o$7$1
  implements Runnable
{
  o$7$1(o.7 param7, Map paramMap) {}
  
  /* Error */
  public final void run()
  {
    // Byte code:
    //   0: aconst_null
    //   1: astore 8
    //   3: aconst_null
    //   4: astore 7
    //   6: aload 7
    //   8: astore 4
    //   10: aload 8
    //   12: astore_2
    //   13: aload_0
    //   14: getfield 21	com/tencent/mm/plugin/wallet_core/model/o$7$1:qys	Ljava/util/Map;
    //   17: ldc 30
    //   19: invokeinterface 36 2 0
    //   24: checkcast 38	java/lang/String
    //   27: astore_3
    //   28: aload 7
    //   30: astore 4
    //   32: aload 8
    //   34: astore_2
    //   35: aload_0
    //   36: getfield 21	com/tencent/mm/plugin/wallet_core/model/o$7$1:qys	Ljava/util/Map;
    //   39: ldc 40
    //   41: invokeinterface 36 2 0
    //   46: checkcast 38	java/lang/String
    //   49: astore 5
    //   51: aload 7
    //   53: astore 4
    //   55: aload 8
    //   57: astore_2
    //   58: aload_0
    //   59: getfield 21	com/tencent/mm/plugin/wallet_core/model/o$7$1:qys	Ljava/util/Map;
    //   62: ldc 42
    //   64: invokeinterface 36 2 0
    //   69: checkcast 38	java/lang/String
    //   72: astore 6
    //   74: aload 7
    //   76: astore 4
    //   78: aload 8
    //   80: astore_2
    //   81: aload_0
    //   82: getfield 21	com/tencent/mm/plugin/wallet_core/model/o$7$1:qys	Ljava/util/Map;
    //   85: ldc 44
    //   87: invokeinterface 36 2 0
    //   92: checkcast 38	java/lang/String
    //   95: astore 10
    //   97: aload 7
    //   99: astore 4
    //   101: aload 8
    //   103: astore_2
    //   104: aload_3
    //   105: ldc 46
    //   107: invokestatic 52	java/net/URLDecoder:decode	(Ljava/lang/String;Ljava/lang/String;)Ljava/lang/String;
    //   110: astore 9
    //   112: aload 7
    //   114: astore 4
    //   116: aload 8
    //   118: astore_2
    //   119: aload 5
    //   121: invokestatic 58	com/tencent/mm/sdk/platformtools/bk:bl	(Ljava/lang/String;)Z
    //   124: ifne +359 -> 483
    //   127: aload 7
    //   129: astore 4
    //   131: aload 8
    //   133: astore_2
    //   134: aload 5
    //   136: invokestatic 64	com/tencent/mm/model/q:Gj	()Ljava/lang/String;
    //   139: invokevirtual 68	java/lang/String:equals	(Ljava/lang/Object;)Z
    //   142: ifne +341 -> 483
    //   145: aload 5
    //   147: astore_3
    //   148: aload 7
    //   150: astore 4
    //   152: aload 8
    //   154: astore_2
    //   155: aload 5
    //   157: invokestatic 73	com/tencent/mm/model/s:fn	(Ljava/lang/String;)Z
    //   160: ifeq +329 -> 489
    //   163: aload 5
    //   165: astore_3
    //   166: aload 7
    //   168: astore 4
    //   170: aload 8
    //   172: astore_2
    //   173: ldc 75
    //   175: ldc 77
    //   177: iconst_5
    //   178: anewarray 4	java/lang/Object
    //   181: dup
    //   182: iconst_0
    //   183: invokestatic 64	com/tencent/mm/model/q:Gj	()Ljava/lang/String;
    //   186: aastore
    //   187: dup
    //   188: iconst_1
    //   189: aload 5
    //   191: aastore
    //   192: dup
    //   193: iconst_2
    //   194: aload 6
    //   196: aastore
    //   197: dup
    //   198: iconst_3
    //   199: aload_3
    //   200: aastore
    //   201: dup
    //   202: iconst_4
    //   203: aload 10
    //   205: aastore
    //   206: invokestatic 83	com/tencent/mm/sdk/platformtools/y:i	(Ljava/lang/String;Ljava/lang/String;[Ljava/lang/Object;)V
    //   209: aload 7
    //   211: astore 4
    //   213: aload 8
    //   215: astore_2
    //   216: aload 9
    //   218: invokestatic 89	com/tencent/mm/ae/g$a:gp	(Ljava/lang/String;)Lcom/tencent/mm/ae/g$a;
    //   221: astore 6
    //   223: aload 7
    //   225: astore 4
    //   227: aload 8
    //   229: astore_2
    //   230: ldc 75
    //   232: ldc 91
    //   234: iconst_2
    //   235: anewarray 4	java/lang/Object
    //   238: dup
    //   239: iconst_0
    //   240: aload 9
    //   242: aastore
    //   243: dup
    //   244: iconst_1
    //   245: aload 6
    //   247: aastore
    //   248: invokestatic 83	com/tencent/mm/sdk/platformtools/y:i	(Ljava/lang/String;Ljava/lang/String;[Ljava/lang/Object;)V
    //   251: aload 7
    //   253: astore 4
    //   255: aload 8
    //   257: astore_2
    //   258: new 93	java/util/ArrayList
    //   261: dup
    //   262: invokespecial 94	java/util/ArrayList:<init>	()V
    //   265: astore 5
    //   267: aload 6
    //   269: ifnull +466 -> 735
    //   272: aload 7
    //   274: astore 4
    //   276: aload 8
    //   278: astore_2
    //   279: ldc 96
    //   281: invokestatic 102	com/tencent/mm/kernel/g:r	(Ljava/lang/Class;)Lcom/tencent/mm/kernel/c/a;
    //   284: checkcast 96	com/tencent/mm/plugin/messenger/foundation/a/j
    //   287: invokeinterface 106 1 0
    //   292: aload_3
    //   293: invokeinterface 112 2 0
    //   298: astore_3
    //   299: aload_3
    //   300: ifnull +240 -> 540
    //   303: aload_3
    //   304: invokeinterface 118 1 0
    //   309: ifeq +231 -> 540
    //   312: new 120	com/tencent/mm/storage/bi
    //   315: dup
    //   316: invokespecial 121	com/tencent/mm/storage/bi:<init>	()V
    //   319: astore_2
    //   320: aload_2
    //   321: aload_3
    //   322: invokevirtual 125	com/tencent/mm/storage/bi:d	(Landroid/database/Cursor;)V
    //   325: aload_2
    //   326: getfield 131	com/tencent/mm/h/c/cs:field_content	Ljava/lang/String;
    //   329: invokestatic 89	com/tencent/mm/ae/g$a:gp	(Ljava/lang/String;)Lcom/tencent/mm/ae/g$a;
    //   332: astore 4
    //   334: aload 4
    //   336: ifnull -33 -> 303
    //   339: aload 4
    //   341: getfield 134	com/tencent/mm/ae/g$a:dSk	Ljava/lang/String;
    //   344: invokestatic 58	com/tencent/mm/sdk/platformtools/bk:bl	(Ljava/lang/String;)Z
    //   347: ifne -44 -> 303
    //   350: aload 4
    //   352: getfield 134	com/tencent/mm/ae/g$a:dSk	Ljava/lang/String;
    //   355: aload 6
    //   357: getfield 134	com/tencent/mm/ae/g$a:dSk	Ljava/lang/String;
    //   360: invokevirtual 68	java/lang/String:equals	(Ljava/lang/Object;)Z
    //   363: ifeq -60 -> 303
    //   366: ldc 75
    //   368: ldc 136
    //   370: iconst_3
    //   371: anewarray 4	java/lang/Object
    //   374: dup
    //   375: iconst_0
    //   376: aload_2
    //   377: getfield 140	com/tencent/mm/h/c/cs:field_msgId	J
    //   380: invokestatic 146	java/lang/Long:valueOf	(J)Ljava/lang/Long;
    //   383: aastore
    //   384: dup
    //   385: iconst_1
    //   386: aload_2
    //   387: getfield 149	com/tencent/mm/h/c/cs:field_talker	Ljava/lang/String;
    //   390: aastore
    //   391: dup
    //   392: iconst_2
    //   393: aload_2
    //   394: getfield 153	com/tencent/mm/h/c/cs:field_isSend	I
    //   397: invokestatic 158	java/lang/Integer:valueOf	(I)Ljava/lang/Integer;
    //   400: aastore
    //   401: invokestatic 83	com/tencent/mm/sdk/platformtools/y:i	(Ljava/lang/String;Ljava/lang/String;[Ljava/lang/Object;)V
    //   404: aload_2
    //   405: getfield 149	com/tencent/mm/h/c/cs:field_talker	Ljava/lang/String;
    //   408: invokestatic 73	com/tencent/mm/model/s:fn	(Ljava/lang/String;)Z
    //   411: ifeq +101 -> 512
    //   414: aload_2
    //   415: aload 9
    //   417: aload_2
    //   418: getfield 131	com/tencent/mm/h/c/cs:field_content	Ljava/lang/String;
    //   421: invokestatic 164	com/tencent/mm/model/bd:iI	(Ljava/lang/String;)Ljava/lang/String;
    //   424: invokestatic 167	com/tencent/mm/model/bd:Z	(Ljava/lang/String;Ljava/lang/String;)Ljava/lang/String;
    //   427: invokevirtual 171	com/tencent/mm/storage/bi:setContent	(Ljava/lang/String;)V
    //   430: aload 5
    //   432: aload_2
    //   433: invokeinterface 176 2 0
    //   438: pop
    //   439: goto -136 -> 303
    //   442: astore_2
    //   443: aload_3
    //   444: astore 4
    //   446: aload_2
    //   447: astore_3
    //   448: aload 4
    //   450: astore_2
    //   451: ldc 75
    //   453: aload_3
    //   454: ldc 178
    //   456: iconst_1
    //   457: anewarray 4	java/lang/Object
    //   460: dup
    //   461: iconst_0
    //   462: aload_3
    //   463: invokevirtual 181	java/lang/Exception:getMessage	()Ljava/lang/String;
    //   466: aastore
    //   467: invokestatic 185	com/tencent/mm/sdk/platformtools/y:printErrStackTrace	(Ljava/lang/String;Ljava/lang/Throwable;Ljava/lang/String;[Ljava/lang/Object;)V
    //   470: aload 4
    //   472: ifnull +10 -> 482
    //   475: aload 4
    //   477: invokeinterface 188 1 0
    //   482: return
    //   483: aload 6
    //   485: astore_3
    //   486: goto -338 -> 148
    //   489: aload 7
    //   491: astore 4
    //   493: aload 8
    //   495: astore_2
    //   496: aload 6
    //   498: invokestatic 73	com/tencent/mm/model/s:fn	(Ljava/lang/String;)Z
    //   501: istore_1
    //   502: iload_1
    //   503: ifeq +237 -> 740
    //   506: aload 6
    //   508: astore_3
    //   509: goto -343 -> 166
    //   512: aload_2
    //   513: aload 9
    //   515: invokevirtual 171	com/tencent/mm/storage/bi:setContent	(Ljava/lang/String;)V
    //   518: goto -88 -> 430
    //   521: astore 4
    //   523: aload_3
    //   524: astore_2
    //   525: aload 4
    //   527: astore_3
    //   528: aload_2
    //   529: ifnull +9 -> 538
    //   532: aload_2
    //   533: invokeinterface 188 1 0
    //   538: aload_3
    //   539: athrow
    //   540: aload_3
    //   541: astore_2
    //   542: aload_2
    //   543: astore_3
    //   544: aload_2
    //   545: ifnull +11 -> 556
    //   548: aload_2
    //   549: invokeinterface 188 1 0
    //   554: aconst_null
    //   555: astore_3
    //   556: aload_3
    //   557: astore 4
    //   559: aload_3
    //   560: astore_2
    //   561: ldc 75
    //   563: ldc 190
    //   565: iconst_1
    //   566: anewarray 4	java/lang/Object
    //   569: dup
    //   570: iconst_0
    //   571: aload 5
    //   573: aastore
    //   574: invokestatic 83	com/tencent/mm/sdk/platformtools/y:i	(Ljava/lang/String;Ljava/lang/String;[Ljava/lang/Object;)V
    //   577: aload_3
    //   578: astore 4
    //   580: aload_3
    //   581: astore_2
    //   582: aload 5
    //   584: invokeinterface 194 1 0
    //   589: ifle +127 -> 716
    //   592: aload_3
    //   593: astore 4
    //   595: aload_3
    //   596: astore_2
    //   597: aload 5
    //   599: invokeinterface 198 1 0
    //   604: astore 5
    //   606: aload_3
    //   607: astore 4
    //   609: aload_3
    //   610: astore_2
    //   611: aload 5
    //   613: invokeinterface 203 1 0
    //   618: ifeq +98 -> 716
    //   621: aload_3
    //   622: astore 4
    //   624: aload_3
    //   625: astore_2
    //   626: aload 5
    //   628: invokeinterface 207 1 0
    //   633: checkcast 120	com/tencent/mm/storage/bi
    //   636: astore 6
    //   638: aload_3
    //   639: astore 4
    //   641: aload_3
    //   642: astore_2
    //   643: ldc 75
    //   645: ldc 209
    //   647: iconst_2
    //   648: anewarray 4	java/lang/Object
    //   651: dup
    //   652: iconst_0
    //   653: aload 6
    //   655: getfield 140	com/tencent/mm/h/c/cs:field_msgId	J
    //   658: invokestatic 146	java/lang/Long:valueOf	(J)Ljava/lang/Long;
    //   661: aastore
    //   662: dup
    //   663: iconst_1
    //   664: aload 6
    //   666: getfield 131	com/tencent/mm/h/c/cs:field_content	Ljava/lang/String;
    //   669: aastore
    //   670: invokestatic 83	com/tencent/mm/sdk/platformtools/y:i	(Ljava/lang/String;Ljava/lang/String;[Ljava/lang/Object;)V
    //   673: aload_3
    //   674: astore 4
    //   676: aload_3
    //   677: astore_2
    //   678: ldc 96
    //   680: invokestatic 102	com/tencent/mm/kernel/g:r	(Ljava/lang/Class;)Lcom/tencent/mm/kernel/c/a;
    //   683: checkcast 96	com/tencent/mm/plugin/messenger/foundation/a/j
    //   686: invokeinterface 106 1 0
    //   691: aload 6
    //   693: getfield 140	com/tencent/mm/h/c/cs:field_msgId	J
    //   696: aload 6
    //   698: invokeinterface 212 4 0
    //   703: goto -97 -> 606
    //   706: astore_3
    //   707: goto -259 -> 448
    //   710: astore_3
    //   711: aload_2
    //   712: astore_3
    //   713: goto -157 -> 556
    //   716: aload_3
    //   717: ifnull -235 -> 482
    //   720: aload_3
    //   721: invokeinterface 188 1 0
    //   726: return
    //   727: astore_3
    //   728: goto -200 -> 528
    //   731: astore_3
    //   732: goto -204 -> 528
    //   735: aconst_null
    //   736: astore_2
    //   737: goto -195 -> 542
    //   740: goto -574 -> 166
    // Local variable table:
    //   start	length	slot	name	signature
    //   0	743	0	this	1
    //   501	2	1	bool	boolean
    //   12	421	2	localObject1	Object
    //   442	5	2	localException1	java.lang.Exception
    //   450	287	2	localObject2	Object
    //   27	650	3	localObject3	Object
    //   706	1	3	localException2	java.lang.Exception
    //   710	1	3	localException3	java.lang.Exception
    //   712	9	3	localObject4	Object
    //   727	1	3	localObject5	Object
    //   731	1	3	localObject6	Object
    //   8	484	4	localObject7	Object
    //   521	5	4	localObject8	Object
    //   557	118	4	localObject9	Object
    //   49	578	5	localObject10	Object
    //   72	625	6	localObject11	Object
    //   4	486	7	localObject12	Object
    //   1	493	8	localObject13	Object
    //   110	404	9	str1	java.lang.String
    //   95	109	10	str2	java.lang.String
    // Exception table:
    //   from	to	target	type
    //   303	334	442	java/lang/Exception
    //   339	430	442	java/lang/Exception
    //   430	439	442	java/lang/Exception
    //   512	518	442	java/lang/Exception
    //   303	334	521	finally
    //   339	430	521	finally
    //   430	439	521	finally
    //   512	518	521	finally
    //   13	28	706	java/lang/Exception
    //   35	51	706	java/lang/Exception
    //   58	74	706	java/lang/Exception
    //   81	97	706	java/lang/Exception
    //   104	112	706	java/lang/Exception
    //   119	127	706	java/lang/Exception
    //   134	145	706	java/lang/Exception
    //   155	163	706	java/lang/Exception
    //   173	209	706	java/lang/Exception
    //   216	223	706	java/lang/Exception
    //   230	251	706	java/lang/Exception
    //   258	267	706	java/lang/Exception
    //   279	299	706	java/lang/Exception
    //   496	502	706	java/lang/Exception
    //   561	577	706	java/lang/Exception
    //   582	592	706	java/lang/Exception
    //   597	606	706	java/lang/Exception
    //   611	621	706	java/lang/Exception
    //   626	638	706	java/lang/Exception
    //   643	673	706	java/lang/Exception
    //   678	703	706	java/lang/Exception
    //   548	554	710	java/lang/Exception
    //   13	28	727	finally
    //   35	51	727	finally
    //   58	74	727	finally
    //   81	97	727	finally
    //   104	112	727	finally
    //   119	127	727	finally
    //   134	145	727	finally
    //   155	163	727	finally
    //   173	209	727	finally
    //   216	223	727	finally
    //   230	251	727	finally
    //   258	267	727	finally
    //   279	299	727	finally
    //   451	470	727	finally
    //   496	502	727	finally
    //   561	577	727	finally
    //   582	592	727	finally
    //   597	606	727	finally
    //   611	621	727	finally
    //   626	638	727	finally
    //   643	673	727	finally
    //   678	703	727	finally
    //   548	554	731	finally
  }
}


/* Location:           L:\local\mybackup\temp\qq_apk\com.tencent.mm\classes6.jar
 * Qualified Name:     com.tencent.mm.plugin.wallet_core.model.o.7.1
 * JD-Core Version:    0.7.0.1
 */