package com.tencent.map.sdk.a;

final class cu
  implements Runnable
{
  cu(cn paramcn) {}
  
  /* Error */
  public final void run()
  {
    // Byte code:
    //   0: aload_0
    //   1: getfield 12	com/tencent/map/sdk/a/cu:a	Lcom/tencent/map/sdk/a/cn;
    //   4: invokestatic 25	com/tencent/map/sdk/a/cn:c	(Lcom/tencent/map/sdk/a/cn;)Z
    //   7: ifeq +4 -> 11
    //   10: return
    //   11: aload_0
    //   12: getfield 12	com/tencent/map/sdk/a/cu:a	Lcom/tencent/map/sdk/a/cn;
    //   15: iconst_1
    //   16: invokestatic 28	com/tencent/map/sdk/a/cn:a	(Lcom/tencent/map/sdk/a/cn;Z)Z
    //   19: pop
    //   20: invokestatic 34	android/os/SystemClock:elapsedRealtime	()J
    //   23: lstore 5
    //   25: new 36	com/tencent/map/sdk/a/cf
    //   28: dup
    //   29: invokespecial 37	com/tencent/map/sdk/a/cf:<init>	()V
    //   32: astore 7
    //   34: aload_0
    //   35: getfield 12	com/tencent/map/sdk/a/cu:a	Lcom/tencent/map/sdk/a/cn;
    //   38: invokestatic 41	com/tencent/map/sdk/a/cn:e	(Lcom/tencent/map/sdk/a/cn;)Ljava/util/Map;
    //   41: invokeinterface 47 1 0
    //   46: invokeinterface 53 1 0
    //   51: astore 8
    //   53: aload 8
    //   55: invokeinterface 59 1 0
    //   60: ifeq +21 -> 81
    //   63: aload 8
    //   65: invokeinterface 63 1 0
    //   70: checkcast 65	com/tencent/map/sdk/a/cj
    //   73: aload 7
    //   75: invokevirtual 68	com/tencent/map/sdk/a/cj:a	(Lcom/tencent/map/sdk/a/cf;)V
    //   78: goto -25 -> 53
    //   81: aload 7
    //   83: invokevirtual 71	com/tencent/map/sdk/a/cf:a	()[B
    //   86: astore 7
    //   88: aload 7
    //   90: invokestatic 76	com/tencent/map/sdk/a/dg:a	([B)Z
    //   93: ifne +355 -> 448
    //   96: invokestatic 80	com/tencent/map/sdk/a/dg:d	()Ljava/lang/String;
    //   99: astore 8
    //   101: invokestatic 85	com/tencent/map/sdk/a/cy:d	()Lcom/tencent/map/sdk/a/cy;
    //   104: invokevirtual 89	com/tencent/map/sdk/a/cy:f	()Lcom/tencent/map/sdk/a/am;
    //   107: pop
    //   108: ldc 91
    //   110: aconst_null
    //   111: aload 7
    //   113: sipush 15000
    //   116: aload 8
    //   118: invokestatic 96	com/tencent/map/sdk/a/be:a	(Ljava/lang/String;Ljava/util/Map;[BILjava/lang/String;)Lcom/tencent/map/sdk/a/be;
    //   121: astore 9
    //   123: invokestatic 99	com/tencent/map/sdk/a/cn:f	()I
    //   126: pop
    //   127: aload 9
    //   129: ldc 101
    //   131: putfield 105	com/tencent/map/sdk/a/be:p	Ljava/lang/String;
    //   134: aload 9
    //   136: invokevirtual 108	com/tencent/map/sdk/a/be:a	()Lcom/tencent/map/sdk/a/bh;
    //   139: astore 10
    //   141: aload 10
    //   143: getfield 113	com/tencent/map/sdk/a/bh:a	I
    //   146: istore 4
    //   148: iload 4
    //   150: istore_1
    //   151: iload 4
    //   153: istore_3
    //   154: iload 4
    //   156: istore_2
    //   157: aload 10
    //   159: getfield 113	com/tencent/map/sdk/a/bh:a	I
    //   162: ifne +253 -> 415
    //   165: iload 4
    //   167: istore_1
    //   168: iload 4
    //   170: istore_3
    //   171: iload 4
    //   173: istore_2
    //   174: aload 10
    //   176: getfield 115	com/tencent/map/sdk/a/bh:c	I
    //   179: sipush 200
    //   182: if_icmpne +233 -> 415
    //   185: iload 4
    //   187: istore_3
    //   188: iload 4
    //   190: istore_2
    //   191: aload 10
    //   193: getfield 118	com/tencent/map/sdk/a/bh:d	[B
    //   196: invokestatic 76	com/tencent/map/sdk/a/dg:a	([B)Z
    //   199: ifne +370 -> 569
    //   202: iload 4
    //   204: istore_2
    //   205: new 120	java/lang/String
    //   208: dup
    //   209: aload 10
    //   211: getfield 118	com/tencent/map/sdk/a/bh:d	[B
    //   214: invokespecial 123	java/lang/String:<init>	([B)V
    //   217: astore 7
    //   219: iload 4
    //   221: istore_2
    //   222: new 125	org/json/JSONObject
    //   225: dup
    //   226: aload 7
    //   228: invokespecial 128	org/json/JSONObject:<init>	(Ljava/lang/String;)V
    //   231: astore 8
    //   233: iload 4
    //   235: istore_2
    //   236: invokestatic 132	com/tencent/map/sdk/a/ao:e	()V
    //   239: iload 4
    //   241: istore_2
    //   242: aload_0
    //   243: getfield 12	com/tencent/map/sdk/a/cu:a	Lcom/tencent/map/sdk/a/cn;
    //   246: invokestatic 41	com/tencent/map/sdk/a/cn:e	(Lcom/tencent/map/sdk/a/cn;)Ljava/util/Map;
    //   249: invokeinterface 47 1 0
    //   254: invokeinterface 53 1 0
    //   259: astore 11
    //   261: iload 4
    //   263: istore_1
    //   264: iload 4
    //   266: istore_2
    //   267: aload 11
    //   269: invokeinterface 59 1 0
    //   274: ifeq +141 -> 415
    //   277: iload 4
    //   279: istore_2
    //   280: aload 11
    //   282: invokeinterface 63 1 0
    //   287: checkcast 65	com/tencent/map/sdk/a/cj
    //   290: aload 8
    //   292: invokevirtual 135	com/tencent/map/sdk/a/cj:a	(Lorg/json/JSONObject;)V
    //   295: goto -34 -> 261
    //   298: astore 8
    //   300: goto +9 -> 309
    //   303: astore 8
    //   305: ldc 137
    //   307: astore 7
    //   309: iload 4
    //   311: istore_3
    //   312: iload 4
    //   314: istore_2
    //   315: aload 8
    //   317: invokevirtual 140	java/lang/Throwable:printStackTrace	()V
    //   320: sipush -321
    //   323: istore_1
    //   324: iload_1
    //   325: istore_3
    //   326: iload_1
    //   327: istore_2
    //   328: ldc 142
    //   330: invokestatic 145	com/tencent/map/sdk/a/dg:c	(Ljava/lang/String;)Ljava/lang/String;
    //   333: astore 8
    //   335: iload_1
    //   336: istore_3
    //   337: iload_1
    //   338: istore_2
    //   339: new 147	java/lang/StringBuilder
    //   342: dup
    //   343: invokespecial 148	java/lang/StringBuilder:<init>	()V
    //   346: astore 11
    //   348: iload_1
    //   349: istore_3
    //   350: iload_1
    //   351: istore_2
    //   352: aload 11
    //   354: aload 8
    //   356: invokevirtual 152	java/lang/StringBuilder:append	(Ljava/lang/String;)Ljava/lang/StringBuilder;
    //   359: pop
    //   360: iload_1
    //   361: istore_3
    //   362: iload_1
    //   363: istore_2
    //   364: aload 11
    //   366: ldc 154
    //   368: invokevirtual 152	java/lang/StringBuilder:append	(Ljava/lang/String;)Ljava/lang/StringBuilder;
    //   371: pop
    //   372: iload_1
    //   373: istore_3
    //   374: iload_1
    //   375: istore_2
    //   376: aload 11
    //   378: aload 7
    //   380: iconst_0
    //   381: aload 7
    //   383: invokevirtual 157	java/lang/String:length	()I
    //   386: bipush 20
    //   388: invokestatic 163	java/lang/Math:min	(II)I
    //   391: invokevirtual 167	java/lang/String:substring	(II)Ljava/lang/String;
    //   394: invokevirtual 152	java/lang/StringBuilder:append	(Ljava/lang/String;)Ljava/lang/StringBuilder;
    //   397: pop
    //   398: iload_1
    //   399: istore_3
    //   400: iload_1
    //   401: istore_2
    //   402: aload 10
    //   404: aload 11
    //   406: invokevirtual 170	java/lang/StringBuilder:toString	()Ljava/lang/String;
    //   409: putfield 173	com/tencent/map/sdk/a/bh:b	Ljava/lang/String;
    //   412: goto +3 -> 415
    //   415: iload_1
    //   416: istore_3
    //   417: iload_1
    //   418: istore_2
    //   419: aload 9
    //   421: invokestatic 34	android/os/SystemClock:elapsedRealtime	()J
    //   424: lload 5
    //   426: lsub
    //   427: putfield 177	com/tencent/map/sdk/a/be:l	J
    //   430: iload_1
    //   431: istore_3
    //   432: iload_1
    //   433: istore_2
    //   434: aload 9
    //   436: iconst_0
    //   437: invokevirtual 180	com/tencent/map/sdk/a/be:a	(Z)V
    //   440: goto +10 -> 450
    //   443: astore 7
    //   445: goto +59 -> 504
    //   448: iconst_0
    //   449: istore_1
    //   450: aload_0
    //   451: getfield 12	com/tencent/map/sdk/a/cu:a	Lcom/tencent/map/sdk/a/cn;
    //   454: invokestatic 182	com/tencent/map/sdk/a/ao:b	()Ljava/lang/String;
    //   457: invokestatic 185	com/tencent/map/sdk/a/cn:a	(Lcom/tencent/map/sdk/a/cn;Ljava/lang/String;)Lcom/tencent/map/sdk/a/cn$a;
    //   460: astore 7
    //   462: aload 7
    //   464: invokestatic 34	android/os/SystemClock:elapsedRealtime	()J
    //   467: putfield 189	com/tencent/map/sdk/a/cn$a:a	J
    //   470: aload 7
    //   472: iload_1
    //   473: putfield 191	com/tencent/map/sdk/a/cn$a:b	I
    //   476: aload_0
    //   477: getfield 12	com/tencent/map/sdk/a/cu:a	Lcom/tencent/map/sdk/a/cn;
    //   480: invokestatic 193	com/tencent/map/sdk/a/cn:f	(Lcom/tencent/map/sdk/a/cn;)V
    //   483: aload_0
    //   484: getfield 12	com/tencent/map/sdk/a/cu:a	Lcom/tencent/map/sdk/a/cn;
    //   487: iconst_0
    //   488: invokestatic 28	com/tencent/map/sdk/a/cn:a	(Lcom/tencent/map/sdk/a/cn;Z)Z
    //   491: pop
    //   492: return
    //   493: astore 7
    //   495: iconst_0
    //   496: istore_2
    //   497: goto +21 -> 518
    //   500: astore 7
    //   502: iconst_0
    //   503: istore_3
    //   504: iload_3
    //   505: istore_2
    //   506: aload 7
    //   508: invokevirtual 140	java/lang/Throwable:printStackTrace	()V
    //   511: iload_3
    //   512: istore_1
    //   513: goto -63 -> 450
    //   516: astore 7
    //   518: aload_0
    //   519: getfield 12	com/tencent/map/sdk/a/cu:a	Lcom/tencent/map/sdk/a/cn;
    //   522: invokestatic 182	com/tencent/map/sdk/a/ao:b	()Ljava/lang/String;
    //   525: invokestatic 185	com/tencent/map/sdk/a/cn:a	(Lcom/tencent/map/sdk/a/cn;Ljava/lang/String;)Lcom/tencent/map/sdk/a/cn$a;
    //   528: astore 8
    //   530: aload 8
    //   532: invokestatic 34	android/os/SystemClock:elapsedRealtime	()J
    //   535: putfield 189	com/tencent/map/sdk/a/cn$a:a	J
    //   538: aload 8
    //   540: iload_2
    //   541: putfield 191	com/tencent/map/sdk/a/cn$a:b	I
    //   544: aload_0
    //   545: getfield 12	com/tencent/map/sdk/a/cu:a	Lcom/tencent/map/sdk/a/cn;
    //   548: invokestatic 193	com/tencent/map/sdk/a/cn:f	(Lcom/tencent/map/sdk/a/cn;)V
    //   551: aload_0
    //   552: getfield 12	com/tencent/map/sdk/a/cu:a	Lcom/tencent/map/sdk/a/cn;
    //   555: iconst_0
    //   556: invokestatic 28	com/tencent/map/sdk/a/cn:a	(Lcom/tencent/map/sdk/a/cn;Z)Z
    //   559: pop
    //   560: goto +6 -> 566
    //   563: aload 7
    //   565: athrow
    //   566: goto -3 -> 563
    //   569: sipush -320
    //   572: istore_1
    //   573: goto -158 -> 415
    // Local variable table:
    //   start	length	slot	name	signature
    //   0	576	0	this	cu
    //   150	423	1	i	int
    //   156	385	2	j	int
    //   153	359	3	k	int
    //   146	167	4	m	int
    //   23	402	5	l	long
    //   32	350	7	localObject1	Object
    //   443	1	7	localThrowable1	java.lang.Throwable
    //   460	11	7	locala	cn.a
    //   493	1	7	localObject2	Object
    //   500	7	7	localThrowable2	java.lang.Throwable
    //   516	48	7	localObject3	Object
    //   51	240	8	localObject4	Object
    //   298	1	8	localThrowable3	java.lang.Throwable
    //   303	13	8	localThrowable4	java.lang.Throwable
    //   333	206	8	localObject5	Object
    //   121	314	9	localbe	be
    //   139	264	10	localbh	bh
    //   259	146	11	localObject6	Object
    // Exception table:
    //   from	to	target	type
    //   222	233	298	java/lang/Throwable
    //   236	239	298	java/lang/Throwable
    //   242	261	298	java/lang/Throwable
    //   267	277	298	java/lang/Throwable
    //   280	295	298	java/lang/Throwable
    //   205	219	303	java/lang/Throwable
    //   157	165	443	java/lang/Throwable
    //   174	185	443	java/lang/Throwable
    //   191	202	443	java/lang/Throwable
    //   315	320	443	java/lang/Throwable
    //   328	335	443	java/lang/Throwable
    //   339	348	443	java/lang/Throwable
    //   352	360	443	java/lang/Throwable
    //   364	372	443	java/lang/Throwable
    //   376	398	443	java/lang/Throwable
    //   402	412	443	java/lang/Throwable
    //   419	430	443	java/lang/Throwable
    //   434	440	443	java/lang/Throwable
    //   25	53	493	finally
    //   53	78	493	finally
    //   81	148	493	finally
    //   25	53	500	java/lang/Throwable
    //   53	78	500	java/lang/Throwable
    //   81	148	500	java/lang/Throwable
    //   157	165	516	finally
    //   174	185	516	finally
    //   191	202	516	finally
    //   205	219	516	finally
    //   222	233	516	finally
    //   236	239	516	finally
    //   242	261	516	finally
    //   267	277	516	finally
    //   280	295	516	finally
    //   315	320	516	finally
    //   328	335	516	finally
    //   339	348	516	finally
    //   352	360	516	finally
    //   364	372	516	finally
    //   376	398	516	finally
    //   402	412	516	finally
    //   419	430	516	finally
    //   434	440	516	finally
    //   506	511	516	finally
  }
}


/* Location:           L:\local\mybackup\temp\qq_apk\com.tencent.mobileqq\classes4.jar
 * Qualified Name:     com.tencent.map.sdk.a.cu
 * JD-Core Version:    0.7.0.1
 */