package com.tencent.map.sdk.a;

final class jr$3
  extends Thread
{
  jr$3(jr paramjr, String paramString1, String paramString2) {}
  
  /* Error */
  public final void run()
  {
    // Byte code:
    //   0: aload_0
    //   1: invokespecial 26	java/lang/Thread:run	()V
    //   4: aconst_null
    //   5: astore_2
    //   6: new 28	java/net/URL
    //   9: dup
    //   10: aload_0
    //   11: getfield 15	com/tencent/map/sdk/a/jr$3:a	Ljava/lang/String;
    //   14: invokespecial 31	java/net/URL:<init>	(Ljava/lang/String;)V
    //   17: invokevirtual 35	java/net/URL:openConnection	()Ljava/net/URLConnection;
    //   20: checkcast 37	java/net/HttpURLConnection
    //   23: astore_1
    //   24: aload_1
    //   25: sipush 3000
    //   28: invokevirtual 41	java/net/HttpURLConnection:setConnectTimeout	(I)V
    //   31: aload_1
    //   32: invokevirtual 45	java/net/HttpURLConnection:getResponseCode	()I
    //   35: sipush 200
    //   38: if_icmpne +70 -> 108
    //   41: aload_1
    //   42: invokevirtual 49	java/net/HttpURLConnection:getInputStream	()Ljava/io/InputStream;
    //   45: invokestatic 55	android/graphics/BitmapFactory:decodeStream	(Ljava/io/InputStream;)Landroid/graphics/Bitmap;
    //   48: astore_2
    //   49: aload_2
    //   50: ifnull +15 -> 65
    //   53: invokestatic 61	com/tencent/map/sdk/a/jr:j	()Ljava/util/concurrent/ConcurrentHashMap;
    //   56: aload_0
    //   57: getfield 17	com/tencent/map/sdk/a/jr$3:b	Ljava/lang/String;
    //   60: aload_2
    //   61: invokevirtual 67	java/util/concurrent/ConcurrentHashMap:put	(Ljava/lang/Object;Ljava/lang/Object;)Ljava/lang/Object;
    //   64: pop
    //   65: aload_0
    //   66: getfield 13	com/tencent/map/sdk/a/jr$3:c	Lcom/tencent/map/sdk/a/jr;
    //   69: invokestatic 70	com/tencent/map/sdk/a/jr:c	(Lcom/tencent/map/sdk/a/jr;)Landroid/widget/ImageView;
    //   72: ifnull +23 -> 95
    //   75: aload_0
    //   76: getfield 13	com/tencent/map/sdk/a/jr$3:c	Lcom/tencent/map/sdk/a/jr;
    //   79: invokestatic 70	com/tencent/map/sdk/a/jr:c	(Lcom/tencent/map/sdk/a/jr;)Landroid/widget/ImageView;
    //   82: new 72	com/tencent/map/sdk/a/jr$3$1
    //   85: dup
    //   86: aload_0
    //   87: aload_2
    //   88: invokespecial 75	com/tencent/map/sdk/a/jr$3$1:<init>	(Lcom/tencent/map/sdk/a/jr$3;Landroid/graphics/Bitmap;)V
    //   91: invokevirtual 81	android/widget/ImageView:post	(Ljava/lang/Runnable;)Z
    //   94: pop
    //   95: aload_0
    //   96: getfield 13	com/tencent/map/sdk/a/jr$3:c	Lcom/tencent/map/sdk/a/jr;
    //   99: aload_0
    //   100: getfield 17	com/tencent/map/sdk/a/jr$3:b	Ljava/lang/String;
    //   103: aload_2
    //   104: invokestatic 84	com/tencent/map/sdk/a/jr:a	(Lcom/tencent/map/sdk/a/jr;Ljava/lang/String;Landroid/graphics/Bitmap;)Z
    //   107: pop
    //   108: aload_1
    //   109: ifnull +7 -> 116
    //   112: aload_1
    //   113: invokevirtual 87	java/net/HttpURLConnection:disconnect	()V
    //   116: invokestatic 91	com/tencent/map/sdk/a/jr:k	()Ljava/util/List;
    //   119: aload_0
    //   120: getfield 17	com/tencent/map/sdk/a/jr$3:b	Ljava/lang/String;
    //   123: invokeinterface 97 2 0
    //   128: pop
    //   129: return
    //   130: astore_2
    //   131: aload_1
    //   132: astore_3
    //   133: goto +11 -> 144
    //   136: goto +31 -> 167
    //   139: astore_1
    //   140: aconst_null
    //   141: astore_3
    //   142: aload_1
    //   143: astore_2
    //   144: aload_3
    //   145: ifnull +7 -> 152
    //   148: aload_3
    //   149: invokevirtual 87	java/net/HttpURLConnection:disconnect	()V
    //   152: invokestatic 91	com/tencent/map/sdk/a/jr:k	()Ljava/util/List;
    //   155: aload_0
    //   156: getfield 17	com/tencent/map/sdk/a/jr$3:b	Ljava/lang/String;
    //   159: invokeinterface 97 2 0
    //   164: pop
    //   165: aload_2
    //   166: athrow
    //   167: aload_1
    //   168: ifnull -52 -> 116
    //   171: aload_1
    //   172: invokevirtual 87	java/net/HttpURLConnection:disconnect	()V
    //   175: goto -59 -> 116
    //   178: astore_1
    //   179: aload_2
    //   180: astore_1
    //   181: goto -14 -> 167
    //   184: astore_2
    //   185: goto -49 -> 136
    // Local variable table:
    //   start	length	slot	name	signature
    //   0	188	0	this	3
    //   23	109	1	localHttpURLConnection1	java.net.HttpURLConnection
    //   139	33	1	localObject1	java.lang.Object
    //   178	1	1	localThrowable1	java.lang.Throwable
    //   180	1	1	localObject2	java.lang.Object
    //   5	99	2	localBitmap	android.graphics.Bitmap
    //   130	1	2	localObject3	java.lang.Object
    //   143	37	2	localObject4	java.lang.Object
    //   184	1	2	localThrowable2	java.lang.Throwable
    //   132	17	3	localHttpURLConnection2	java.net.HttpURLConnection
    // Exception table:
    //   from	to	target	type
    //   24	49	130	finally
    //   53	65	130	finally
    //   65	95	130	finally
    //   95	108	130	finally
    //   6	24	139	finally
    //   6	24	178	java/lang/Throwable
    //   24	49	184	java/lang/Throwable
    //   53	65	184	java/lang/Throwable
    //   65	95	184	java/lang/Throwable
    //   95	108	184	java/lang/Throwable
  }
}


/* Location:           L:\local\mybackup\temp\qq_apk\com.tencent.mobileqq\classes4.jar
 * Qualified Name:     com.tencent.map.sdk.a.jr.3
 * JD-Core Version:    0.7.0.1
 */