package com.tencent.upload.network.route;

final class DomainNameParser$1
  implements Runnable
{
  DomainNameParser$1(String paramString, byte[] paramArrayOfByte, DomainNameParser.ParseResult paramParseResult) {}
  
  /* Error */
  public void run()
  {
    // Byte code:
    //   0: invokestatic 33	java/lang/Thread:currentThread	()Ljava/lang/Thread;
    //   3: invokevirtual 37	java/lang/Thread:getName	()Ljava/lang/String;
    //   6: astore_3
    //   7: aload_0
    //   8: getfield 16	com/tencent/upload/network/route/DomainNameParser$1:val$domainName	Ljava/lang/String;
    //   11: invokestatic 43	java/net/InetAddress:getByName	(Ljava/lang/String;)Ljava/net/InetAddress;
    //   14: invokevirtual 46	java/net/InetAddress:getHostAddress	()Ljava/lang/String;
    //   17: astore_1
    //   18: ldc 48
    //   20: new 50	java/lang/StringBuilder
    //   23: dup
    //   24: invokespecial 51	java/lang/StringBuilder:<init>	()V
    //   27: ldc 53
    //   29: invokevirtual 57	java/lang/StringBuilder:append	(Ljava/lang/String;)Ljava/lang/StringBuilder;
    //   32: aload_1
    //   33: invokevirtual 57	java/lang/StringBuilder:append	(Ljava/lang/String;)Ljava/lang/StringBuilder;
    //   36: ldc 59
    //   38: invokevirtual 57	java/lang/StringBuilder:append	(Ljava/lang/String;)Ljava/lang/StringBuilder;
    //   41: aload_0
    //   42: getfield 16	com/tencent/upload/network/route/DomainNameParser$1:val$domainName	Ljava/lang/String;
    //   45: invokevirtual 57	java/lang/StringBuilder:append	(Ljava/lang/String;)Ljava/lang/StringBuilder;
    //   48: ldc 61
    //   50: invokevirtual 57	java/lang/StringBuilder:append	(Ljava/lang/String;)Ljava/lang/StringBuilder;
    //   53: aload_3
    //   54: invokevirtual 57	java/lang/StringBuilder:append	(Ljava/lang/String;)Ljava/lang/StringBuilder;
    //   57: invokevirtual 64	java/lang/StringBuilder:toString	()Ljava/lang/String;
    //   60: invokestatic 70	com/tencent/upload/utils/UploadLog:i	(Ljava/lang/String;Ljava/lang/String;)V
    //   63: aload_0
    //   64: getfield 18	com/tencent/upload/network/route/DomainNameParser$1:val$lock	[B
    //   67: astore_2
    //   68: aload_2
    //   69: monitorenter
    //   70: aload_1
    //   71: invokestatic 76	android/text/TextUtils:isEmpty	(Ljava/lang/CharSequence;)Z
    //   74: ifne +17 -> 91
    //   77: invokestatic 82	com/tencent/upload/network/route/DomainNameParser:access$000	()Ljava/util/Map;
    //   80: aload_0
    //   81: getfield 16	com/tencent/upload/network/route/DomainNameParser$1:val$domainName	Ljava/lang/String;
    //   84: aload_1
    //   85: invokeinterface 88 3 0
    //   90: pop
    //   91: aload_0
    //   92: getfield 20	com/tencent/upload/network/route/DomainNameParser$1:val$parseResult	Lcom/tencent/upload/network/route/DomainNameParser$ParseResult;
    //   95: aload_1
    //   96: putfield 93	com/tencent/upload/network/route/DomainNameParser$ParseResult:parsedIp	Ljava/lang/String;
    //   99: ldc 48
    //   101: new 50	java/lang/StringBuilder
    //   104: dup
    //   105: invokespecial 51	java/lang/StringBuilder:<init>	()V
    //   108: ldc 95
    //   110: invokevirtual 57	java/lang/StringBuilder:append	(Ljava/lang/String;)Ljava/lang/StringBuilder;
    //   113: aload_0
    //   114: getfield 20	com/tencent/upload/network/route/DomainNameParser$1:val$parseResult	Lcom/tencent/upload/network/route/DomainNameParser$ParseResult;
    //   117: getfield 93	com/tencent/upload/network/route/DomainNameParser$ParseResult:parsedIp	Ljava/lang/String;
    //   120: invokevirtual 57	java/lang/StringBuilder:append	(Ljava/lang/String;)Ljava/lang/StringBuilder;
    //   123: ldc 59
    //   125: invokevirtual 57	java/lang/StringBuilder:append	(Ljava/lang/String;)Ljava/lang/StringBuilder;
    //   128: aload_0
    //   129: getfield 16	com/tencent/upload/network/route/DomainNameParser$1:val$domainName	Ljava/lang/String;
    //   132: invokevirtual 57	java/lang/StringBuilder:append	(Ljava/lang/String;)Ljava/lang/StringBuilder;
    //   135: ldc 61
    //   137: invokevirtual 57	java/lang/StringBuilder:append	(Ljava/lang/String;)Ljava/lang/StringBuilder;
    //   140: aload_3
    //   141: invokevirtual 57	java/lang/StringBuilder:append	(Ljava/lang/String;)Ljava/lang/StringBuilder;
    //   144: ldc 97
    //   146: invokevirtual 57	java/lang/StringBuilder:append	(Ljava/lang/String;)Ljava/lang/StringBuilder;
    //   149: aload_0
    //   150: getfield 18	com/tencent/upload/network/route/DomainNameParser$1:val$lock	[B
    //   153: invokevirtual 101	java/lang/Object:hashCode	()I
    //   156: invokevirtual 104	java/lang/StringBuilder:append	(I)Ljava/lang/StringBuilder;
    //   159: invokevirtual 64	java/lang/StringBuilder:toString	()Ljava/lang/String;
    //   162: invokestatic 70	com/tencent/upload/utils/UploadLog:i	(Ljava/lang/String;Ljava/lang/String;)V
    //   165: aload_0
    //   166: getfield 18	com/tencent/upload/network/route/DomainNameParser$1:val$lock	[B
    //   169: invokevirtual 107	java/lang/Object:notify	()V
    //   172: aload_2
    //   173: monitorexit
    //   174: return
    //   175: astore_2
    //   176: aconst_null
    //   177: astore_1
    //   178: ldc 48
    //   180: new 50	java/lang/StringBuilder
    //   183: dup
    //   184: invokespecial 51	java/lang/StringBuilder:<init>	()V
    //   187: ldc 109
    //   189: invokevirtual 57	java/lang/StringBuilder:append	(Ljava/lang/String;)Ljava/lang/StringBuilder;
    //   192: aload_2
    //   193: invokevirtual 112	java/lang/StringBuilder:append	(Ljava/lang/Object;)Ljava/lang/StringBuilder;
    //   196: invokevirtual 64	java/lang/StringBuilder:toString	()Ljava/lang/String;
    //   199: invokestatic 115	com/tencent/upload/utils/UploadLog:w	(Ljava/lang/String;Ljava/lang/String;)V
    //   202: goto -139 -> 63
    //   205: astore_1
    //   206: aload_2
    //   207: monitorexit
    //   208: aload_1
    //   209: athrow
    //   210: astore_2
    //   211: goto -33 -> 178
    // Local variable table:
    //   start	length	slot	name	signature
    //   0	214	0	this	1
    //   17	161	1	str1	String
    //   205	4	1	localObject	Object
    //   175	32	2	localThrowable1	java.lang.Throwable
    //   210	1	2	localThrowable2	java.lang.Throwable
    //   6	135	3	str2	String
    // Exception table:
    //   from	to	target	type
    //   7	18	175	java/lang/Throwable
    //   70	91	205	finally
    //   91	174	205	finally
    //   206	208	205	finally
    //   18	63	210	java/lang/Throwable
  }
}


/* Location:           L:\local\mybackup\temp\qq_apk\com.tencent.mobileqq\classes10.jar
 * Qualified Name:     com.tencent.upload.network.route.DomainNameParser.1
 * JD-Core Version:    0.7.0.1
 */