import android.view.View.OnClickListener;
import com.tencent.mobileqq.fragment.NearbyHybridFragment;

public class aqie
  implements View.OnClickListener
{
  public aqie(NearbyHybridFragment paramNearbyHybridFragment) {}
  
  /* Error */
  public void onClick(android.view.View paramView)
  {
    // Byte code:
    //   0: aload_1
    //   1: invokevirtual 26	android/view/View:getId	()I
    //   4: istore_2
    //   5: iload_2
    //   6: ldc 27
    //   8: if_icmpne +129 -> 137
    //   11: invokestatic 32	atym:a	()Ljava/util/ArrayList;
    //   14: astore_1
    //   15: new 34	atyi
    //   18: dup
    //   19: aload_0
    //   20: getfield 12	aqie:a	Lcom/tencent/mobileqq/fragment/NearbyHybridFragment;
    //   23: getfield 39	com/tencent/mobileqq/fragment/NearbyHybridFragment:jdField_a_of_type_ComTencentMobileqqAppIphoneTitleBarActivity	Lcom/tencent/mobileqq/app/IphoneTitleBarActivity;
    //   26: aload_1
    //   27: invokespecial 42	atyi:<init>	(Landroid/content/Context;Ljava/util/ArrayList;)V
    //   30: astore_1
    //   31: aload_1
    //   32: aload_0
    //   33: getfield 12	aqie:a	Lcom/tencent/mobileqq/fragment/NearbyHybridFragment;
    //   36: getfield 45	com/tencent/mobileqq/fragment/NearbyHybridFragment:jdField_a_of_type_Atyl	Latyl;
    //   39: invokevirtual 48	atyi:a	(Latyl;)V
    //   42: aload_1
    //   43: aload_0
    //   44: getfield 12	aqie:a	Lcom/tencent/mobileqq/fragment/NearbyHybridFragment;
    //   47: getfield 39	com/tencent/mobileqq/fragment/NearbyHybridFragment:jdField_a_of_type_ComTencentMobileqqAppIphoneTitleBarActivity	Lcom/tencent/mobileqq/app/IphoneTitleBarActivity;
    //   50: ldc 49
    //   52: invokestatic 54	baxn:a	(Landroid/content/Context;F)I
    //   55: aload_0
    //   56: getfield 12	aqie:a	Lcom/tencent/mobileqq/fragment/NearbyHybridFragment;
    //   59: getfield 39	com/tencent/mobileqq/fragment/NearbyHybridFragment:jdField_a_of_type_ComTencentMobileqqAppIphoneTitleBarActivity	Lcom/tencent/mobileqq/app/IphoneTitleBarActivity;
    //   62: ldc 55
    //   64: invokestatic 54	baxn:a	(Landroid/content/Context;F)I
    //   67: aload_0
    //   68: getfield 12	aqie:a	Lcom/tencent/mobileqq/fragment/NearbyHybridFragment;
    //   71: getfield 59	com/tencent/mobileqq/fragment/NearbyHybridFragment:b	Landroid/view/View;
    //   74: invokevirtual 62	android/view/View:getHeight	()I
    //   77: iadd
    //   78: ldc 63
    //   80: invokevirtual 66	atyi:a	(IIF)V
    //   83: new 68	axrc
    //   86: dup
    //   87: aload_0
    //   88: getfield 12	aqie:a	Lcom/tencent/mobileqq/fragment/NearbyHybridFragment;
    //   91: getfield 39	com/tencent/mobileqq/fragment/NearbyHybridFragment:jdField_a_of_type_ComTencentMobileqqAppIphoneTitleBarActivity	Lcom/tencent/mobileqq/app/IphoneTitleBarActivity;
    //   94: getfield 74	com/tencent/mobileqq/app/IphoneTitleBarActivity:app	Lcom/tencent/mobileqq/app/QQAppInterface;
    //   97: invokespecial 77	axrc:<init>	(Lcom/tencent/mobileqq/app/QQAppInterface;)V
    //   100: ldc 79
    //   102: invokevirtual 82	axrc:a	(Ljava/lang/String;)Laxrc;
    //   105: ldc 84
    //   107: invokevirtual 86	axrc:b	(Ljava/lang/String;)Laxrc;
    //   110: ldc 88
    //   112: invokevirtual 91	axrc:c	(Ljava/lang/String;)Laxrc;
    //   115: ldc 93
    //   117: invokevirtual 96	axrc:d	(Ljava/lang/String;)Laxrc;
    //   120: invokevirtual 98	axrc:a	()V
    //   123: aload_0
    //   124: getfield 12	aqie:a	Lcom/tencent/mobileqq/fragment/NearbyHybridFragment;
    //   127: getfield 101	com/tencent/mobileqq/fragment/NearbyHybridFragment:jdField_a_of_type_ComTencentMobileqqNearbyNearbyAppInterface	Lcom/tencent/mobileqq/nearby/NearbyAppInterface;
    //   130: ldc 103
    //   132: iconst_1
    //   133: invokestatic 108	atbr:a	(Lcom/tencent/mobileqq/nearby/NearbyAppInterface;Ljava/lang/String;I)V
    //   136: return
    //   137: iload_2
    //   138: ldc 109
    //   140: if_icmpne -4 -> 136
    //   143: aload_0
    //   144: getfield 12	aqie:a	Lcom/tencent/mobileqq/fragment/NearbyHybridFragment;
    //   147: getfield 101	com/tencent/mobileqq/fragment/NearbyHybridFragment:jdField_a_of_type_ComTencentMobileqqNearbyNearbyAppInterface	Lcom/tencent/mobileqq/nearby/NearbyAppInterface;
    //   150: invokevirtual 114	com/tencent/mobileqq/nearby/NearbyAppInterface:a	()Latfz;
    //   153: astore 4
    //   155: aload 4
    //   157: bipush 10
    //   159: invokevirtual 119	atfz:a	(I)Lcom/tencent/pb/getbusiinfo/BusinessInfoCheckUpdate$RedTypeInfo;
    //   162: astore_1
    //   163: aload_1
    //   164: ifnull +199 -> 363
    //   167: new 121	org/json/JSONObject
    //   170: dup
    //   171: aload_1
    //   172: getfield 127	com/tencent/pb/getbusiinfo/BusinessInfoCheckUpdate$RedTypeInfo:red_desc	Lcom/tencent/mobileqq/pb/PBStringField;
    //   175: invokevirtual 133	com/tencent/mobileqq/pb/PBStringField:get	()Ljava/lang/String;
    //   178: invokespecial 136	org/json/JSONObject:<init>	(Ljava/lang/String;)V
    //   181: ldc 138
    //   183: invokevirtual 142	org/json/JSONObject:optBoolean	(Ljava/lang/String;)Z
    //   186: istore_3
    //   187: aload_1
    //   188: getfield 145	com/tencent/pb/getbusiinfo/BusinessInfoCheckUpdate$RedTypeInfo:red_content	Lcom/tencent/mobileqq/pb/PBStringField;
    //   191: invokevirtual 133	com/tencent/mobileqq/pb/PBStringField:get	()Ljava/lang/String;
    //   194: invokestatic 151	java/lang/Integer:valueOf	(Ljava/lang/String;)Ljava/lang/Integer;
    //   197: invokevirtual 154	java/lang/Integer:intValue	()I
    //   200: istore_2
    //   201: iload_3
    //   202: ifeq +117 -> 319
    //   205: new 156	android/content/Intent
    //   208: dup
    //   209: aload_0
    //   210: getfield 12	aqie:a	Lcom/tencent/mobileqq/fragment/NearbyHybridFragment;
    //   213: getfield 39	com/tencent/mobileqq/fragment/NearbyHybridFragment:jdField_a_of_type_ComTencentMobileqqAppIphoneTitleBarActivity	Lcom/tencent/mobileqq/app/IphoneTitleBarActivity;
    //   216: ldc 158
    //   218: invokespecial 161	android/content/Intent:<init>	(Landroid/content/Context;Ljava/lang/Class;)V
    //   221: astore_1
    //   222: aload_1
    //   223: ldc 163
    //   225: ldc 165
    //   227: invokevirtual 169	android/content/Intent:putExtra	(Ljava/lang/String;Ljava/lang/String;)Landroid/content/Intent;
    //   230: pop
    //   231: iload_2
    //   232: iconst_1
    //   233: if_icmple +72 -> 305
    //   236: aload_0
    //   237: getfield 12	aqie:a	Lcom/tencent/mobileqq/fragment/NearbyHybridFragment;
    //   240: getfield 39	com/tencent/mobileqq/fragment/NearbyHybridFragment:jdField_a_of_type_ComTencentMobileqqAppIphoneTitleBarActivity	Lcom/tencent/mobileqq/app/IphoneTitleBarActivity;
    //   243: aload_1
    //   244: sipush 10002
    //   247: invokevirtual 173	com/tencent/mobileqq/app/IphoneTitleBarActivity:startActivityForResult	(Landroid/content/Intent;I)V
    //   250: aload 4
    //   252: bipush 38
    //   254: invokevirtual 176	atfz:a	(I)V
    //   257: aload_0
    //   258: getfield 12	aqie:a	Lcom/tencent/mobileqq/fragment/NearbyHybridFragment;
    //   261: getfield 179	com/tencent/mobileqq/fragment/NearbyHybridFragment:jdField_a_of_type_AndroidOsHandler	Landroid/os/Handler;
    //   264: new 181	com/tencent/mobileqq/fragment/NearbyHybridFragment$11$1
    //   267: dup
    //   268: aload_0
    //   269: invokespecial 184	com/tencent/mobileqq/fragment/NearbyHybridFragment$11$1:<init>	(Laqie;)V
    //   272: ldc2_w 185
    //   275: invokevirtual 192	android/os/Handler:postDelayed	(Ljava/lang/Runnable;J)Z
    //   278: pop
    //   279: aload_0
    //   280: getfield 12	aqie:a	Lcom/tencent/mobileqq/fragment/NearbyHybridFragment;
    //   283: getfield 101	com/tencent/mobileqq/fragment/NearbyHybridFragment:jdField_a_of_type_ComTencentMobileqqNearbyNearbyAppInterface	Lcom/tencent/mobileqq/nearby/NearbyAppInterface;
    //   286: ldc 194
    //   288: iconst_0
    //   289: invokestatic 108	atbr:a	(Lcom/tencent/mobileqq/nearby/NearbyAppInterface;Ljava/lang/String;I)V
    //   292: return
    //   293: astore_1
    //   294: iconst_0
    //   295: istore_3
    //   296: aload_1
    //   297: invokevirtual 197	java/lang/Exception:printStackTrace	()V
    //   300: iconst_0
    //   301: istore_2
    //   302: goto -101 -> 201
    //   305: aload_0
    //   306: getfield 12	aqie:a	Lcom/tencent/mobileqq/fragment/NearbyHybridFragment;
    //   309: getfield 39	com/tencent/mobileqq/fragment/NearbyHybridFragment:jdField_a_of_type_ComTencentMobileqqAppIphoneTitleBarActivity	Lcom/tencent/mobileqq/app/IphoneTitleBarActivity;
    //   312: aload_1
    //   313: invokevirtual 201	com/tencent/mobileqq/app/IphoneTitleBarActivity:startActivity	(Landroid/content/Intent;)V
    //   316: goto -66 -> 250
    //   319: new 156	android/content/Intent
    //   322: dup
    //   323: aload_0
    //   324: getfield 12	aqie:a	Lcom/tencent/mobileqq/fragment/NearbyHybridFragment;
    //   327: getfield 39	com/tencent/mobileqq/fragment/NearbyHybridFragment:jdField_a_of_type_ComTencentMobileqqAppIphoneTitleBarActivity	Lcom/tencent/mobileqq/app/IphoneTitleBarActivity;
    //   330: ldc 158
    //   332: invokespecial 161	android/content/Intent:<init>	(Landroid/content/Context;Ljava/lang/Class;)V
    //   335: astore_1
    //   336: aload_1
    //   337: ldc 163
    //   339: ldc 203
    //   341: invokevirtual 169	android/content/Intent:putExtra	(Ljava/lang/String;Ljava/lang/String;)Landroid/content/Intent;
    //   344: pop
    //   345: aload_0
    //   346: getfield 12	aqie:a	Lcom/tencent/mobileqq/fragment/NearbyHybridFragment;
    //   349: getfield 39	com/tencent/mobileqq/fragment/NearbyHybridFragment:jdField_a_of_type_ComTencentMobileqqAppIphoneTitleBarActivity	Lcom/tencent/mobileqq/app/IphoneTitleBarActivity;
    //   352: aload_1
    //   353: invokevirtual 201	com/tencent/mobileqq/app/IphoneTitleBarActivity:startActivity	(Landroid/content/Intent;)V
    //   356: goto -106 -> 250
    //   359: astore_1
    //   360: goto -64 -> 296
    //   363: iconst_0
    //   364: istore_2
    //   365: iconst_0
    //   366: istore_3
    //   367: goto -166 -> 201
    // Local variable table:
    //   start	length	slot	name	signature
    //   0	370	0	this	aqie
    //   0	370	1	paramView	android.view.View
    //   4	361	2	i	int
    //   186	181	3	bool	boolean
    //   153	98	4	localatfz	atfz
    // Exception table:
    //   from	to	target	type
    //   167	187	293	java/lang/Exception
    //   187	201	359	java/lang/Exception
  }
}


/* Location:           L:\local\mybackup\temp\qq_apk\com.tencent.mobileqq\classes2.jar
 * Qualified Name:     aqie
 * JD-Core Version:    0.7.0.1
 */