import java.util.List;

public class assb
{
  public String a;
  public List<assc> a;
  public String b;
  public String c;
  
  /* Error */
  public static assb a(String paramString)
  {
    // Byte code:
    //   0: ldc 2
    //   2: monitorenter
    //   3: new 2	assb
    //   6: dup
    //   7: invokespecial 19	assb:<init>	()V
    //   10: astore_3
    //   11: new 21	org/json/JSONObject
    //   14: dup
    //   15: aload_0
    //   16: invokespecial 24	org/json/JSONObject:<init>	(Ljava/lang/String;)V
    //   19: astore_0
    //   20: aload_3
    //   21: aload_0
    //   22: ldc 26
    //   24: invokevirtual 30	org/json/JSONObject:optString	(Ljava/lang/String;)Ljava/lang/String;
    //   27: putfield 32	assb:jdField_a_of_type_JavaLangString	Ljava/lang/String;
    //   30: aload_3
    //   31: aload_0
    //   32: ldc 34
    //   34: invokevirtual 30	org/json/JSONObject:optString	(Ljava/lang/String;)Ljava/lang/String;
    //   37: putfield 36	assb:jdField_b_of_type_JavaLangString	Ljava/lang/String;
    //   40: aload_3
    //   41: aload_0
    //   42: ldc 38
    //   44: invokevirtual 30	org/json/JSONObject:optString	(Ljava/lang/String;)Ljava/lang/String;
    //   47: putfield 40	assb:jdField_c_of_type_JavaLangString	Ljava/lang/String;
    //   50: aload_0
    //   51: ldc 42
    //   53: invokevirtual 46	org/json/JSONObject:optJSONArray	(Ljava/lang/String;)Lorg/json/JSONArray;
    //   56: astore 4
    //   58: aload_3
    //   59: new 48	java/util/LinkedList
    //   62: dup
    //   63: invokespecial 49	java/util/LinkedList:<init>	()V
    //   66: putfield 51	assb:jdField_a_of_type_JavaUtilList	Ljava/util/List;
    //   69: aload_3
    //   70: astore_0
    //   71: aload 4
    //   73: ifnull +725 -> 798
    //   76: iconst_0
    //   77: istore_1
    //   78: aload_3
    //   79: astore_0
    //   80: iload_1
    //   81: aload 4
    //   83: invokevirtual 57	org/json/JSONArray:length	()I
    //   86: if_icmpge +712 -> 798
    //   89: aload 4
    //   91: iload_1
    //   92: invokevirtual 61	org/json/JSONArray:getJSONObject	(I)Lorg/json/JSONObject;
    //   95: astore 5
    //   97: new 63	assc
    //   100: dup
    //   101: invokespecial 64	assc:<init>	()V
    //   104: astore_0
    //   105: aload_0
    //   106: aload 5
    //   108: ldc 66
    //   110: invokevirtual 70	org/json/JSONObject:optInt	(Ljava/lang/String;)I
    //   113: putfield 73	assc:jdField_a_of_type_Int	I
    //   116: aload_0
    //   117: aload 5
    //   119: ldc 75
    //   121: invokevirtual 30	org/json/JSONObject:optString	(Ljava/lang/String;)Ljava/lang/String;
    //   124: putfield 76	assc:jdField_c_of_type_JavaLangString	Ljava/lang/String;
    //   127: aload_0
    //   128: aload 5
    //   130: ldc 78
    //   132: invokevirtual 30	org/json/JSONObject:optString	(Ljava/lang/String;)Ljava/lang/String;
    //   135: putfield 79	assc:jdField_a_of_type_JavaLangString	Ljava/lang/String;
    //   138: aload_0
    //   139: aload 5
    //   141: ldc 81
    //   143: invokevirtual 30	org/json/JSONObject:optString	(Ljava/lang/String;)Ljava/lang/String;
    //   146: putfield 82	assc:jdField_b_of_type_JavaLangString	Ljava/lang/String;
    //   149: aload_0
    //   150: aload 5
    //   152: ldc 84
    //   154: invokevirtual 30	org/json/JSONObject:optString	(Ljava/lang/String;)Ljava/lang/String;
    //   157: putfield 87	assc:d	Ljava/lang/String;
    //   160: aload 5
    //   162: ldc 89
    //   164: invokevirtual 46	org/json/JSONObject:optJSONArray	(Ljava/lang/String;)Lorg/json/JSONArray;
    //   167: astore 6
    //   169: aload_0
    //   170: iconst_2
    //   171: newarray int
    //   173: putfield 92	assc:jdField_a_of_type_ArrayOfInt	[I
    //   176: aload 6
    //   178: ifnull +36 -> 214
    //   181: aload 6
    //   183: invokevirtual 57	org/json/JSONArray:length	()I
    //   186: iconst_2
    //   187: if_icmpne +27 -> 214
    //   190: aload_0
    //   191: getfield 92	assc:jdField_a_of_type_ArrayOfInt	[I
    //   194: iconst_0
    //   195: aload 6
    //   197: iconst_0
    //   198: invokevirtual 96	org/json/JSONArray:getInt	(I)I
    //   201: iastore
    //   202: aload_0
    //   203: getfield 92	assc:jdField_a_of_type_ArrayOfInt	[I
    //   206: iconst_1
    //   207: aload 6
    //   209: iconst_1
    //   210: invokevirtual 96	org/json/JSONArray:getInt	(I)I
    //   213: iastore
    //   214: aload_0
    //   215: new 48	java/util/LinkedList
    //   218: dup
    //   219: invokespecial 49	java/util/LinkedList:<init>	()V
    //   222: putfield 97	assc:jdField_a_of_type_JavaUtilList	Ljava/util/List;
    //   225: aload 5
    //   227: ldc 99
    //   229: invokevirtual 46	org/json/JSONObject:optJSONArray	(Ljava/lang/String;)Lorg/json/JSONArray;
    //   232: astore 6
    //   234: aload 6
    //   236: ifnull +188 -> 424
    //   239: iconst_0
    //   240: istore_2
    //   241: iload_2
    //   242: aload 6
    //   244: invokevirtual 57	org/json/JSONArray:length	()I
    //   247: if_icmpge +177 -> 424
    //   250: aload 6
    //   252: iload_2
    //   253: invokevirtual 61	org/json/JSONArray:getJSONObject	(I)Lorg/json/JSONObject;
    //   256: astore 8
    //   258: new 101	assd
    //   261: dup
    //   262: invokespecial 102	assd:<init>	()V
    //   265: astore 7
    //   267: aload 7
    //   269: aload 8
    //   271: ldc 104
    //   273: invokevirtual 30	org/json/JSONObject:optString	(Ljava/lang/String;)Ljava/lang/String;
    //   276: putfield 105	assd:jdField_a_of_type_JavaLangString	Ljava/lang/String;
    //   279: aload 7
    //   281: aload 8
    //   283: ldc 107
    //   285: invokevirtual 70	org/json/JSONObject:optInt	(Ljava/lang/String;)I
    //   288: putfield 108	assd:jdField_a_of_type_Int	I
    //   291: aload 7
    //   293: iconst_2
    //   294: newarray int
    //   296: putfield 110	assd:jdField_b_of_type_ArrayOfInt	[I
    //   299: aload 8
    //   301: ldc 112
    //   303: invokevirtual 46	org/json/JSONObject:optJSONArray	(Ljava/lang/String;)Lorg/json/JSONArray;
    //   306: astore 9
    //   308: aload 9
    //   310: ifnull +38 -> 348
    //   313: aload 9
    //   315: invokevirtual 57	org/json/JSONArray:length	()I
    //   318: iconst_2
    //   319: if_icmpne +29 -> 348
    //   322: aload 7
    //   324: getfield 110	assd:jdField_b_of_type_ArrayOfInt	[I
    //   327: iconst_0
    //   328: aload 9
    //   330: iconst_0
    //   331: invokevirtual 96	org/json/JSONArray:getInt	(I)I
    //   334: iastore
    //   335: aload 7
    //   337: getfield 110	assd:jdField_b_of_type_ArrayOfInt	[I
    //   340: iconst_1
    //   341: aload 9
    //   343: iconst_1
    //   344: invokevirtual 96	org/json/JSONArray:getInt	(I)I
    //   347: iastore
    //   348: aload 7
    //   350: iconst_2
    //   351: newarray int
    //   353: putfield 113	assd:jdField_a_of_type_ArrayOfInt	[I
    //   356: aload 8
    //   358: ldc 115
    //   360: invokevirtual 46	org/json/JSONObject:optJSONArray	(Ljava/lang/String;)Lorg/json/JSONArray;
    //   363: astore 8
    //   365: aload 8
    //   367: ifnull +38 -> 405
    //   370: aload 8
    //   372: invokevirtual 57	org/json/JSONArray:length	()I
    //   375: iconst_2
    //   376: if_icmpne +29 -> 405
    //   379: aload 7
    //   381: getfield 113	assd:jdField_a_of_type_ArrayOfInt	[I
    //   384: iconst_0
    //   385: aload 8
    //   387: iconst_0
    //   388: invokevirtual 96	org/json/JSONArray:getInt	(I)I
    //   391: iastore
    //   392: aload 7
    //   394: getfield 113	assd:jdField_a_of_type_ArrayOfInt	[I
    //   397: iconst_1
    //   398: aload 8
    //   400: iconst_1
    //   401: invokevirtual 96	org/json/JSONArray:getInt	(I)I
    //   404: iastore
    //   405: aload_0
    //   406: getfield 97	assc:jdField_a_of_type_JavaUtilList	Ljava/util/List;
    //   409: aload 7
    //   411: invokeinterface 121 2 0
    //   416: pop
    //   417: iload_2
    //   418: iconst_1
    //   419: iadd
    //   420: istore_2
    //   421: goto -180 -> 241
    //   424: aload_0
    //   425: new 48	java/util/LinkedList
    //   428: dup
    //   429: invokespecial 49	java/util/LinkedList:<init>	()V
    //   432: putfield 123	assc:jdField_b_of_type_JavaUtilList	Ljava/util/List;
    //   435: aload 5
    //   437: ldc 125
    //   439: invokevirtual 46	org/json/JSONObject:optJSONArray	(Ljava/lang/String;)Lorg/json/JSONArray;
    //   442: astore 5
    //   444: aload 5
    //   446: ifnull +331 -> 777
    //   449: iconst_0
    //   450: istore_2
    //   451: iload_2
    //   452: aload 5
    //   454: invokevirtual 57	org/json/JSONArray:length	()I
    //   457: if_icmpge +320 -> 777
    //   460: aload 5
    //   462: iload_2
    //   463: invokevirtual 61	org/json/JSONArray:getJSONObject	(I)Lorg/json/JSONObject;
    //   466: astore 7
    //   468: new 127	asse
    //   471: dup
    //   472: invokespecial 128	asse:<init>	()V
    //   475: astore 6
    //   477: aload 6
    //   479: aload 7
    //   481: ldc 130
    //   483: invokevirtual 30	org/json/JSONObject:optString	(Ljava/lang/String;)Ljava/lang/String;
    //   486: putfield 131	asse:jdField_c_of_type_JavaLangString	Ljava/lang/String;
    //   489: aload 6
    //   491: aload 7
    //   493: ldc 133
    //   495: invokevirtual 70	org/json/JSONObject:optInt	(Ljava/lang/String;)I
    //   498: putfield 134	asse:jdField_a_of_type_Int	I
    //   501: aload 6
    //   503: aload 7
    //   505: ldc 136
    //   507: invokevirtual 70	org/json/JSONObject:optInt	(Ljava/lang/String;)I
    //   510: putfield 138	asse:jdField_b_of_type_Int	I
    //   513: aload 6
    //   515: aload 7
    //   517: ldc 140
    //   519: invokevirtual 30	org/json/JSONObject:optString	(Ljava/lang/String;)Ljava/lang/String;
    //   522: putfield 141	asse:d	Ljava/lang/String;
    //   525: aload 6
    //   527: aload 7
    //   529: ldc 143
    //   531: invokevirtual 70	org/json/JSONObject:optInt	(Ljava/lang/String;)I
    //   534: putfield 145	asse:jdField_c_of_type_Int	I
    //   537: aload 6
    //   539: aload 7
    //   541: ldc 147
    //   543: invokevirtual 30	org/json/JSONObject:optString	(Ljava/lang/String;)Ljava/lang/String;
    //   546: putfield 148	asse:jdField_a_of_type_JavaLangString	Ljava/lang/String;
    //   549: aload 6
    //   551: aload 7
    //   553: ldc 150
    //   555: invokevirtual 30	org/json/JSONObject:optString	(Ljava/lang/String;)Ljava/lang/String;
    //   558: putfield 151	asse:jdField_b_of_type_JavaLangString	Ljava/lang/String;
    //   561: aload 6
    //   563: iconst_2
    //   564: newarray int
    //   566: putfield 153	asse:jdField_c_of_type_ArrayOfInt	[I
    //   569: aload 7
    //   571: ldc 155
    //   573: invokevirtual 46	org/json/JSONObject:optJSONArray	(Ljava/lang/String;)Lorg/json/JSONArray;
    //   576: astore 8
    //   578: aload 8
    //   580: ifnull +38 -> 618
    //   583: aload 8
    //   585: invokevirtual 57	org/json/JSONArray:length	()I
    //   588: iconst_2
    //   589: if_icmpne +29 -> 618
    //   592: aload 6
    //   594: getfield 153	asse:jdField_c_of_type_ArrayOfInt	[I
    //   597: iconst_0
    //   598: aload 8
    //   600: iconst_0
    //   601: invokevirtual 96	org/json/JSONArray:getInt	(I)I
    //   604: iastore
    //   605: aload 6
    //   607: getfield 153	asse:jdField_c_of_type_ArrayOfInt	[I
    //   610: iconst_1
    //   611: aload 8
    //   613: iconst_1
    //   614: invokevirtual 96	org/json/JSONArray:getInt	(I)I
    //   617: iastore
    //   618: aload 6
    //   620: iconst_2
    //   621: newarray int
    //   623: putfield 156	asse:jdField_a_of_type_ArrayOfInt	[I
    //   626: aload 7
    //   628: ldc 158
    //   630: invokevirtual 46	org/json/JSONObject:optJSONArray	(Ljava/lang/String;)Lorg/json/JSONArray;
    //   633: astore 8
    //   635: aload 8
    //   637: ifnull +38 -> 675
    //   640: aload 8
    //   642: invokevirtual 57	org/json/JSONArray:length	()I
    //   645: iconst_2
    //   646: if_icmpne +29 -> 675
    //   649: aload 6
    //   651: getfield 156	asse:jdField_a_of_type_ArrayOfInt	[I
    //   654: iconst_0
    //   655: aload 8
    //   657: iconst_0
    //   658: invokevirtual 96	org/json/JSONArray:getInt	(I)I
    //   661: iastore
    //   662: aload 6
    //   664: getfield 156	asse:jdField_a_of_type_ArrayOfInt	[I
    //   667: iconst_1
    //   668: aload 8
    //   670: iconst_1
    //   671: invokevirtual 96	org/json/JSONArray:getInt	(I)I
    //   674: iastore
    //   675: aload 7
    //   677: ldc 160
    //   679: invokevirtual 46	org/json/JSONObject:optJSONArray	(Ljava/lang/String;)Lorg/json/JSONArray;
    //   682: astore 7
    //   684: aload 7
    //   686: ifnull +72 -> 758
    //   689: aload 7
    //   691: invokevirtual 57	org/json/JSONArray:length	()I
    //   694: iconst_4
    //   695: if_icmpne +63 -> 758
    //   698: aload 6
    //   700: iconst_4
    //   701: newarray int
    //   703: putfield 161	asse:jdField_b_of_type_ArrayOfInt	[I
    //   706: aload 6
    //   708: getfield 161	asse:jdField_b_of_type_ArrayOfInt	[I
    //   711: iconst_0
    //   712: aload 7
    //   714: iconst_0
    //   715: invokevirtual 96	org/json/JSONArray:getInt	(I)I
    //   718: iastore
    //   719: aload 6
    //   721: getfield 161	asse:jdField_b_of_type_ArrayOfInt	[I
    //   724: iconst_1
    //   725: aload 7
    //   727: iconst_1
    //   728: invokevirtual 96	org/json/JSONArray:getInt	(I)I
    //   731: iastore
    //   732: aload 6
    //   734: getfield 161	asse:jdField_b_of_type_ArrayOfInt	[I
    //   737: iconst_2
    //   738: aload 7
    //   740: iconst_2
    //   741: invokevirtual 96	org/json/JSONArray:getInt	(I)I
    //   744: iastore
    //   745: aload 6
    //   747: getfield 161	asse:jdField_b_of_type_ArrayOfInt	[I
    //   750: iconst_3
    //   751: aload 7
    //   753: iconst_3
    //   754: invokevirtual 96	org/json/JSONArray:getInt	(I)I
    //   757: iastore
    //   758: aload_0
    //   759: getfield 123	assc:jdField_b_of_type_JavaUtilList	Ljava/util/List;
    //   762: aload 6
    //   764: invokeinterface 121 2 0
    //   769: pop
    //   770: iload_2
    //   771: iconst_1
    //   772: iadd
    //   773: istore_2
    //   774: goto -323 -> 451
    //   777: aload_3
    //   778: getfield 51	assb:jdField_a_of_type_JavaUtilList	Ljava/util/List;
    //   781: aload_0
    //   782: invokeinterface 121 2 0
    //   787: pop
    //   788: iload_1
    //   789: iconst_1
    //   790: iadd
    //   791: istore_1
    //   792: goto -714 -> 78
    //   795: astore_0
    //   796: aconst_null
    //   797: astore_0
    //   798: ldc 2
    //   800: monitorexit
    //   801: aload_0
    //   802: areturn
    //   803: astore_0
    //   804: ldc 2
    //   806: monitorexit
    //   807: aload_0
    //   808: athrow
    // Local variable table:
    //   start	length	slot	name	signature
    //   0	809	0	paramString	String
    //   77	715	1	i	int
    //   240	534	2	j	int
    //   10	768	3	localassb	assb
    //   56	34	4	localJSONArray1	org.json.JSONArray
    //   95	366	5	localObject1	Object
    //   167	596	6	localObject2	Object
    //   265	487	7	localObject3	Object
    //   256	413	8	localObject4	Object
    //   306	36	9	localJSONArray2	org.json.JSONArray
    // Exception table:
    //   from	to	target	type
    //   3	69	795	java/lang/Exception
    //   80	176	795	java/lang/Exception
    //   181	214	795	java/lang/Exception
    //   214	234	795	java/lang/Exception
    //   241	308	795	java/lang/Exception
    //   313	348	795	java/lang/Exception
    //   348	365	795	java/lang/Exception
    //   370	405	795	java/lang/Exception
    //   405	417	795	java/lang/Exception
    //   424	444	795	java/lang/Exception
    //   451	578	795	java/lang/Exception
    //   583	618	795	java/lang/Exception
    //   618	635	795	java/lang/Exception
    //   640	675	795	java/lang/Exception
    //   675	684	795	java/lang/Exception
    //   689	758	795	java/lang/Exception
    //   758	770	795	java/lang/Exception
    //   777	788	795	java/lang/Exception
    //   3	69	803	finally
    //   80	176	803	finally
    //   181	214	803	finally
    //   214	234	803	finally
    //   241	308	803	finally
    //   313	348	803	finally
    //   348	365	803	finally
    //   370	405	803	finally
    //   405	417	803	finally
    //   424	444	803	finally
    //   451	578	803	finally
    //   583	618	803	finally
    //   618	635	803	finally
    //   640	675	803	finally
    //   675	684	803	finally
    //   689	758	803	finally
    //   758	770	803	finally
    //   777	788	803	finally
  }
}


/* Location:           L:\local\mybackup\temp\qq_apk\com.tencent.mobileqq\classes3.jar
 * Qualified Name:     assb
 * JD-Core Version:    0.7.0.1
 */