import android.os.IBinder;
import android.os.Parcel;

class axqr
  implements axqp
{
  private IBinder a;
  
  axqr(IBinder paramIBinder)
  {
    this.a = paramIBinder;
  }
  
  public IBinder asBinder()
  {
    return this.a;
  }
  
  /* Error */
  public void onPlaySongChanged(com.tencent.mobileqq.music.SongInfo paramSongInfo)
  {
    // Byte code:
    //   0: invokestatic 26	android/os/Parcel:obtain	()Landroid/os/Parcel;
    //   3: astore_2
    //   4: aload_2
    //   5: ldc 28
    //   7: invokevirtual 32	android/os/Parcel:writeInterfaceToken	(Ljava/lang/String;)V
    //   10: aload_1
    //   11: ifnull +33 -> 44
    //   14: aload_2
    //   15: iconst_1
    //   16: invokevirtual 36	android/os/Parcel:writeInt	(I)V
    //   19: aload_1
    //   20: aload_2
    //   21: iconst_0
    //   22: invokevirtual 42	com/tencent/mobileqq/music/SongInfo:writeToParcel	(Landroid/os/Parcel;I)V
    //   25: aload_0
    //   26: getfield 15	axqr:a	Landroid/os/IBinder;
    //   29: iconst_2
    //   30: aload_2
    //   31: aconst_null
    //   32: iconst_1
    //   33: invokeinterface 48 5 0
    //   38: pop
    //   39: aload_2
    //   40: invokevirtual 51	android/os/Parcel:recycle	()V
    //   43: return
    //   44: aload_2
    //   45: iconst_0
    //   46: invokevirtual 36	android/os/Parcel:writeInt	(I)V
    //   49: goto -24 -> 25
    //   52: astore_1
    //   53: aload_2
    //   54: invokevirtual 51	android/os/Parcel:recycle	()V
    //   57: aload_1
    //   58: athrow
    // Local variable table:
    //   start	length	slot	name	signature
    //   0	59	0	this	axqr
    //   0	59	1	paramSongInfo	com.tencent.mobileqq.music.SongInfo
    //   3	51	2	localParcel	Parcel
    // Exception table:
    //   from	to	target	type
    //   4	10	52	finally
    //   14	25	52	finally
    //   25	39	52	finally
    //   44	49	52	finally
  }
  
  public void onPlayStateChanged(int paramInt)
  {
    Parcel localParcel = Parcel.obtain();
    try
    {
      localParcel.writeInterfaceToken("com.tencent.mobileqq.music.IQQPlayerCallback");
      localParcel.writeInt(paramInt);
      this.a.transact(1, localParcel, null, 1);
      return;
    }
    finally
    {
      localParcel.recycle();
    }
  }
}


/* Location:           L:\local\mybackup\temp\qq_apk\com.tencent.mobileqq\classes4.jar
 * Qualified Name:     axqr
 * JD-Core Version:    0.7.0.1
 */