import com.tencent.biz.pubaccount.readinjoy.logic.SMRM;
import com.tencent.mobileqq.app.QQAppInterface;

public class lrj
  implements Runnable
{
  public lrj(SMRM paramSMRM, QQAppInterface paramQQAppInterface) {}
  
  /* Error */
  public void run()
  {
    // Byte code:
    //   0: invokestatic 28	java/lang/System:currentTimeMillis	()J
    //   3: lstore_3
    //   4: aload_0
    //   5: getfield 15	lrj:jdField_a_of_type_ComTencentMobileqqAppQQAppInterface	Lcom/tencent/mobileqq/app/QQAppInterface;
    //   8: invokestatic 33	com/tencent/biz/pubaccount/readinjoy/logic/SMRM:a	(Lmqq/app/AppRuntime;)Z
    //   11: istore 7
    //   13: aload_0
    //   14: getfield 13	lrj:jdField_a_of_type_ComTencentBizPubaccountReadinjoyLogicSMRM	Lcom/tencent/biz/pubaccount/readinjoy/logic/SMRM;
    //   17: invokevirtual 36	com/tencent/biz/pubaccount/readinjoy/logic/SMRM:a	()Z
    //   20: ifeq +29 -> 49
    //   23: ldc 38
    //   25: iconst_2
    //   26: new 40	java/lang/StringBuilder
    //   29: dup
    //   30: invokespecial 41	java/lang/StringBuilder:<init>	()V
    //   33: ldc 43
    //   35: invokevirtual 47	java/lang/StringBuilder:append	(Ljava/lang/String;)Ljava/lang/StringBuilder;
    //   38: iload 7
    //   40: invokevirtual 50	java/lang/StringBuilder:append	(Z)Ljava/lang/StringBuilder;
    //   43: invokevirtual 54	java/lang/StringBuilder:toString	()Ljava/lang/String;
    //   46: invokestatic 60	com/tencent/qphone/base/util/QLog:d	(Ljava/lang/String;ILjava/lang/String;)V
    //   49: aload_0
    //   50: getfield 15	lrj:jdField_a_of_type_ComTencentMobileqqAppQQAppInterface	Lcom/tencent/mobileqq/app/QQAppInterface;
    //   53: invokestatic 33	com/tencent/biz/pubaccount/readinjoy/logic/SMRM:a	(Lmqq/app/AppRuntime;)Z
    //   56: ifne +15 -> 71
    //   59: aload_0
    //   60: getfield 13	lrj:jdField_a_of_type_ComTencentBizPubaccountReadinjoyLogicSMRM	Lcom/tencent/biz/pubaccount/readinjoy/logic/SMRM;
    //   63: getfield 63	com/tencent/biz/pubaccount/readinjoy/logic/SMRM:a	J
    //   66: lconst_0
    //   67: lcmp
    //   68: ifeq +215 -> 283
    //   71: aload_0
    //   72: getfield 13	lrj:jdField_a_of_type_ComTencentBizPubaccountReadinjoyLogicSMRM	Lcom/tencent/biz/pubaccount/readinjoy/logic/SMRM;
    //   75: aload_0
    //   76: getfield 15	lrj:jdField_a_of_type_ComTencentMobileqqAppQQAppInterface	Lcom/tencent/mobileqq/app/QQAppInterface;
    //   79: invokestatic 65	com/tencent/biz/pubaccount/readinjoy/logic/SMRM:a	(Lcom/tencent/biz/pubaccount/readinjoy/logic/SMRM;Lcom/tencent/mobileqq/app/QQAppInterface;)V
    //   82: aload_0
    //   83: getfield 13	lrj:jdField_a_of_type_ComTencentBizPubaccountReadinjoyLogicSMRM	Lcom/tencent/biz/pubaccount/readinjoy/logic/SMRM;
    //   86: invokevirtual 67	com/tencent/biz/pubaccount/readinjoy/logic/SMRM:a	()J
    //   89: lstore 5
    //   91: aload_0
    //   92: getfield 13	lrj:jdField_a_of_type_ComTencentBizPubaccountReadinjoyLogicSMRM	Lcom/tencent/biz/pubaccount/readinjoy/logic/SMRM;
    //   95: invokevirtual 36	com/tencent/biz/pubaccount/readinjoy/logic/SMRM:a	()Z
    //   98: ifeq +118 -> 216
    //   101: invokestatic 28	java/lang/System:currentTimeMillis	()J
    //   104: ldc2_w 68
    //   107: ldiv
    //   108: lstore_1
    //   109: aload_0
    //   110: getfield 13	lrj:jdField_a_of_type_ComTencentBizPubaccountReadinjoyLogicSMRM	Lcom/tencent/biz/pubaccount/readinjoy/logic/SMRM;
    //   113: getfield 63	com/tencent/biz/pubaccount/readinjoy/logic/SMRM:a	J
    //   116: lconst_0
    //   117: lcmp
    //   118: ifne +109 -> 227
    //   121: lload_1
    //   122: ldc2_w 70
    //   125: ladd
    //   126: ldc2_w 72
    //   129: ldiv
    //   130: lload 5
    //   132: ldc2_w 70
    //   135: ladd
    //   136: ldc2_w 72
    //   139: ldiv
    //   140: lcmp
    //   141: ifne +86 -> 227
    //   144: ldc 38
    //   146: iconst_2
    //   147: ldc 75
    //   149: invokestatic 78	com/tencent/qphone/base/util/QLog:e	(Ljava/lang/String;ILjava/lang/String;)V
    //   152: aload_0
    //   153: getfield 13	lrj:jdField_a_of_type_ComTencentBizPubaccountReadinjoyLogicSMRM	Lcom/tencent/biz/pubaccount/readinjoy/logic/SMRM;
    //   156: invokestatic 81	com/tencent/biz/pubaccount/readinjoy/logic/SMRM:a	(Lcom/tencent/biz/pubaccount/readinjoy/logic/SMRM;)V
    //   159: aload_0
    //   160: getfield 13	lrj:jdField_a_of_type_ComTencentBizPubaccountReadinjoyLogicSMRM	Lcom/tencent/biz/pubaccount/readinjoy/logic/SMRM;
    //   163: iconst_0
    //   164: invokestatic 84	com/tencent/biz/pubaccount/readinjoy/logic/SMRM:a	(Lcom/tencent/biz/pubaccount/readinjoy/logic/SMRM;Z)Z
    //   167: pop
    //   168: aload_0
    //   169: getfield 13	lrj:jdField_a_of_type_ComTencentBizPubaccountReadinjoyLogicSMRM	Lcom/tencent/biz/pubaccount/readinjoy/logic/SMRM;
    //   172: lconst_0
    //   173: putfield 63	com/tencent/biz/pubaccount/readinjoy/logic/SMRM:a	J
    //   176: aload_0
    //   177: getfield 13	lrj:jdField_a_of_type_ComTencentBizPubaccountReadinjoyLogicSMRM	Lcom/tencent/biz/pubaccount/readinjoy/logic/SMRM;
    //   180: invokevirtual 36	com/tencent/biz/pubaccount/readinjoy/logic/SMRM:a	()Z
    //   183: ifeq +32 -> 215
    //   186: ldc 38
    //   188: iconst_2
    //   189: new 40	java/lang/StringBuilder
    //   192: dup
    //   193: invokespecial 41	java/lang/StringBuilder:<init>	()V
    //   196: ldc 86
    //   198: invokevirtual 47	java/lang/StringBuilder:append	(Ljava/lang/String;)Ljava/lang/StringBuilder;
    //   201: invokestatic 28	java/lang/System:currentTimeMillis	()J
    //   204: lload_3
    //   205: lsub
    //   206: invokevirtual 89	java/lang/StringBuilder:append	(J)Ljava/lang/StringBuilder;
    //   209: invokevirtual 54	java/lang/StringBuilder:toString	()Ljava/lang/String;
    //   212: invokestatic 60	com/tencent/qphone/base/util/QLog:d	(Ljava/lang/String;ILjava/lang/String;)V
    //   215: return
    //   216: aload_0
    //   217: getfield 13	lrj:jdField_a_of_type_ComTencentBizPubaccountReadinjoyLogicSMRM	Lcom/tencent/biz/pubaccount/readinjoy/logic/SMRM;
    //   220: invokestatic 92	com/tencent/biz/pubaccount/readinjoy/logic/SMRM:a	(Lcom/tencent/biz/pubaccount/readinjoy/logic/SMRM;)J
    //   223: lstore_1
    //   224: goto -115 -> 109
    //   227: aload_0
    //   228: getfield 13	lrj:jdField_a_of_type_ComTencentBizPubaccountReadinjoyLogicSMRM	Lcom/tencent/biz/pubaccount/readinjoy/logic/SMRM;
    //   231: lload 5
    //   233: invokevirtual 95	com/tencent/biz/pubaccount/readinjoy/logic/SMRM:a	(J)V
    //   236: aload_0
    //   237: getfield 13	lrj:jdField_a_of_type_ComTencentBizPubaccountReadinjoyLogicSMRM	Lcom/tencent/biz/pubaccount/readinjoy/logic/SMRM;
    //   240: aload_0
    //   241: getfield 15	lrj:jdField_a_of_type_ComTencentMobileqqAppQQAppInterface	Lcom/tencent/mobileqq/app/QQAppInterface;
    //   244: invokestatic 98	com/tencent/biz/pubaccount/readinjoy/logic/SMRM:b	(Lcom/tencent/biz/pubaccount/readinjoy/logic/SMRM;Lcom/tencent/mobileqq/app/QQAppInterface;)V
    //   247: aload_0
    //   248: getfield 13	lrj:jdField_a_of_type_ComTencentBizPubaccountReadinjoyLogicSMRM	Lcom/tencent/biz/pubaccount/readinjoy/logic/SMRM;
    //   251: aload_0
    //   252: getfield 15	lrj:jdField_a_of_type_ComTencentMobileqqAppQQAppInterface	Lcom/tencent/mobileqq/app/QQAppInterface;
    //   255: invokestatic 101	com/tencent/biz/pubaccount/readinjoy/logic/SMRM:c	(Lcom/tencent/biz/pubaccount/readinjoy/logic/SMRM;Lcom/tencent/mobileqq/app/QQAppInterface;)V
    //   258: aload_0
    //   259: getfield 13	lrj:jdField_a_of_type_ComTencentBizPubaccountReadinjoyLogicSMRM	Lcom/tencent/biz/pubaccount/readinjoy/logic/SMRM;
    //   262: aload_0
    //   263: getfield 15	lrj:jdField_a_of_type_ComTencentMobileqqAppQQAppInterface	Lcom/tencent/mobileqq/app/QQAppInterface;
    //   266: invokestatic 103	com/tencent/biz/pubaccount/readinjoy/logic/SMRM:d	(Lcom/tencent/biz/pubaccount/readinjoy/logic/SMRM;Lcom/tencent/mobileqq/app/QQAppInterface;)V
    //   269: aload_0
    //   270: getfield 13	lrj:jdField_a_of_type_ComTencentBizPubaccountReadinjoyLogicSMRM	Lcom/tencent/biz/pubaccount/readinjoy/logic/SMRM;
    //   273: aload_0
    //   274: getfield 13	lrj:jdField_a_of_type_ComTencentBizPubaccountReadinjoyLogicSMRM	Lcom/tencent/biz/pubaccount/readinjoy/logic/SMRM;
    //   277: invokestatic 92	com/tencent/biz/pubaccount/readinjoy/logic/SMRM:a	(Lcom/tencent/biz/pubaccount/readinjoy/logic/SMRM;)J
    //   280: invokestatic 106	com/tencent/biz/pubaccount/readinjoy/logic/SMRM:a	(Lcom/tencent/biz/pubaccount/readinjoy/logic/SMRM;J)V
    //   283: aload_0
    //   284: getfield 13	lrj:jdField_a_of_type_ComTencentBizPubaccountReadinjoyLogicSMRM	Lcom/tencent/biz/pubaccount/readinjoy/logic/SMRM;
    //   287: invokestatic 81	com/tencent/biz/pubaccount/readinjoy/logic/SMRM:a	(Lcom/tencent/biz/pubaccount/readinjoy/logic/SMRM;)V
    //   290: aload_0
    //   291: getfield 13	lrj:jdField_a_of_type_ComTencentBizPubaccountReadinjoyLogicSMRM	Lcom/tencent/biz/pubaccount/readinjoy/logic/SMRM;
    //   294: iconst_0
    //   295: invokestatic 84	com/tencent/biz/pubaccount/readinjoy/logic/SMRM:a	(Lcom/tencent/biz/pubaccount/readinjoy/logic/SMRM;Z)Z
    //   298: pop
    //   299: aload_0
    //   300: getfield 13	lrj:jdField_a_of_type_ComTencentBizPubaccountReadinjoyLogicSMRM	Lcom/tencent/biz/pubaccount/readinjoy/logic/SMRM;
    //   303: lconst_0
    //   304: putfield 63	com/tencent/biz/pubaccount/readinjoy/logic/SMRM:a	J
    //   307: aload_0
    //   308: getfield 13	lrj:jdField_a_of_type_ComTencentBizPubaccountReadinjoyLogicSMRM	Lcom/tencent/biz/pubaccount/readinjoy/logic/SMRM;
    //   311: invokevirtual 36	com/tencent/biz/pubaccount/readinjoy/logic/SMRM:a	()Z
    //   314: ifeq -99 -> 215
    //   317: ldc 38
    //   319: iconst_2
    //   320: new 40	java/lang/StringBuilder
    //   323: dup
    //   324: invokespecial 41	java/lang/StringBuilder:<init>	()V
    //   327: ldc 86
    //   329: invokevirtual 47	java/lang/StringBuilder:append	(Ljava/lang/String;)Ljava/lang/StringBuilder;
    //   332: invokestatic 28	java/lang/System:currentTimeMillis	()J
    //   335: lload_3
    //   336: lsub
    //   337: invokevirtual 89	java/lang/StringBuilder:append	(J)Ljava/lang/StringBuilder;
    //   340: invokevirtual 54	java/lang/StringBuilder:toString	()Ljava/lang/String;
    //   343: invokestatic 60	com/tencent/qphone/base/util/QLog:d	(Ljava/lang/String;ILjava/lang/String;)V
    //   346: return
    //   347: astore 8
    //   349: ldc 38
    //   351: iconst_2
    //   352: ldc 108
    //   354: aload 8
    //   356: invokestatic 111	com/tencent/qphone/base/util/QLog:e	(Ljava/lang/String;ILjava/lang/String;Ljava/lang/Throwable;)V
    //   359: goto -112 -> 247
    //   362: astore 8
    //   364: ldc 38
    //   366: iconst_2
    //   367: ldc 112
    //   369: aload 8
    //   371: invokestatic 111	com/tencent/qphone/base/util/QLog:e	(Ljava/lang/String;ILjava/lang/String;Ljava/lang/Throwable;)V
    //   374: aload_0
    //   375: getfield 13	lrj:jdField_a_of_type_ComTencentBizPubaccountReadinjoyLogicSMRM	Lcom/tencent/biz/pubaccount/readinjoy/logic/SMRM;
    //   378: invokestatic 81	com/tencent/biz/pubaccount/readinjoy/logic/SMRM:a	(Lcom/tencent/biz/pubaccount/readinjoy/logic/SMRM;)V
    //   381: aload_0
    //   382: getfield 13	lrj:jdField_a_of_type_ComTencentBizPubaccountReadinjoyLogicSMRM	Lcom/tencent/biz/pubaccount/readinjoy/logic/SMRM;
    //   385: iconst_0
    //   386: invokestatic 84	com/tencent/biz/pubaccount/readinjoy/logic/SMRM:a	(Lcom/tencent/biz/pubaccount/readinjoy/logic/SMRM;Z)Z
    //   389: pop
    //   390: aload_0
    //   391: getfield 13	lrj:jdField_a_of_type_ComTencentBizPubaccountReadinjoyLogicSMRM	Lcom/tencent/biz/pubaccount/readinjoy/logic/SMRM;
    //   394: lconst_0
    //   395: putfield 63	com/tencent/biz/pubaccount/readinjoy/logic/SMRM:a	J
    //   398: aload_0
    //   399: getfield 13	lrj:jdField_a_of_type_ComTencentBizPubaccountReadinjoyLogicSMRM	Lcom/tencent/biz/pubaccount/readinjoy/logic/SMRM;
    //   402: invokevirtual 36	com/tencent/biz/pubaccount/readinjoy/logic/SMRM:a	()Z
    //   405: ifeq -190 -> 215
    //   408: ldc 38
    //   410: iconst_2
    //   411: new 40	java/lang/StringBuilder
    //   414: dup
    //   415: invokespecial 41	java/lang/StringBuilder:<init>	()V
    //   418: ldc 86
    //   420: invokevirtual 47	java/lang/StringBuilder:append	(Ljava/lang/String;)Ljava/lang/StringBuilder;
    //   423: invokestatic 28	java/lang/System:currentTimeMillis	()J
    //   426: lload_3
    //   427: lsub
    //   428: invokevirtual 89	java/lang/StringBuilder:append	(J)Ljava/lang/StringBuilder;
    //   431: invokevirtual 54	java/lang/StringBuilder:toString	()Ljava/lang/String;
    //   434: invokestatic 60	com/tencent/qphone/base/util/QLog:d	(Ljava/lang/String;ILjava/lang/String;)V
    //   437: return
    //   438: astore 8
    //   440: ldc 38
    //   442: iconst_2
    //   443: ldc 114
    //   445: aload 8
    //   447: invokestatic 111	com/tencent/qphone/base/util/QLog:e	(Ljava/lang/String;ILjava/lang/String;Ljava/lang/Throwable;)V
    //   450: goto -192 -> 258
    //   453: astore 8
    //   455: aload_0
    //   456: getfield 13	lrj:jdField_a_of_type_ComTencentBizPubaccountReadinjoyLogicSMRM	Lcom/tencent/biz/pubaccount/readinjoy/logic/SMRM;
    //   459: invokestatic 81	com/tencent/biz/pubaccount/readinjoy/logic/SMRM:a	(Lcom/tencent/biz/pubaccount/readinjoy/logic/SMRM;)V
    //   462: aload_0
    //   463: getfield 13	lrj:jdField_a_of_type_ComTencentBizPubaccountReadinjoyLogicSMRM	Lcom/tencent/biz/pubaccount/readinjoy/logic/SMRM;
    //   466: iconst_0
    //   467: invokestatic 84	com/tencent/biz/pubaccount/readinjoy/logic/SMRM:a	(Lcom/tencent/biz/pubaccount/readinjoy/logic/SMRM;Z)Z
    //   470: pop
    //   471: aload_0
    //   472: getfield 13	lrj:jdField_a_of_type_ComTencentBizPubaccountReadinjoyLogicSMRM	Lcom/tencent/biz/pubaccount/readinjoy/logic/SMRM;
    //   475: lconst_0
    //   476: putfield 63	com/tencent/biz/pubaccount/readinjoy/logic/SMRM:a	J
    //   479: aload_0
    //   480: getfield 13	lrj:jdField_a_of_type_ComTencentBizPubaccountReadinjoyLogicSMRM	Lcom/tencent/biz/pubaccount/readinjoy/logic/SMRM;
    //   483: invokevirtual 36	com/tencent/biz/pubaccount/readinjoy/logic/SMRM:a	()Z
    //   486: ifeq +32 -> 518
    //   489: ldc 38
    //   491: iconst_2
    //   492: new 40	java/lang/StringBuilder
    //   495: dup
    //   496: invokespecial 41	java/lang/StringBuilder:<init>	()V
    //   499: ldc 86
    //   501: invokevirtual 47	java/lang/StringBuilder:append	(Ljava/lang/String;)Ljava/lang/StringBuilder;
    //   504: invokestatic 28	java/lang/System:currentTimeMillis	()J
    //   507: lload_3
    //   508: lsub
    //   509: invokevirtual 89	java/lang/StringBuilder:append	(J)Ljava/lang/StringBuilder;
    //   512: invokevirtual 54	java/lang/StringBuilder:toString	()Ljava/lang/String;
    //   515: invokestatic 60	com/tencent/qphone/base/util/QLog:d	(Ljava/lang/String;ILjava/lang/String;)V
    //   518: aload 8
    //   520: athrow
    //   521: astore 8
    //   523: ldc 38
    //   525: iconst_2
    //   526: ldc 116
    //   528: aload 8
    //   530: invokestatic 111	com/tencent/qphone/base/util/QLog:e	(Ljava/lang/String;ILjava/lang/String;Ljava/lang/Throwable;)V
    //   533: goto -264 -> 269
    // Local variable table:
    //   start	length	slot	name	signature
    //   0	536	0	this	lrj
    //   108	116	1	l1	long
    //   3	505	3	l2	long
    //   89	143	5	l3	long
    //   11	28	7	bool	boolean
    //   347	8	8	localException1	java.lang.Exception
    //   362	8	8	localException2	java.lang.Exception
    //   438	8	8	localException3	java.lang.Exception
    //   453	66	8	localObject	Object
    //   521	8	8	localException4	java.lang.Exception
    // Exception table:
    //   from	to	target	type
    //   236	247	347	java/lang/Exception
    //   4	49	362	java/lang/Exception
    //   49	71	362	java/lang/Exception
    //   71	109	362	java/lang/Exception
    //   109	152	362	java/lang/Exception
    //   216	224	362	java/lang/Exception
    //   227	236	362	java/lang/Exception
    //   269	283	362	java/lang/Exception
    //   349	359	362	java/lang/Exception
    //   440	450	362	java/lang/Exception
    //   523	533	362	java/lang/Exception
    //   247	258	438	java/lang/Exception
    //   4	49	453	finally
    //   49	71	453	finally
    //   71	109	453	finally
    //   109	152	453	finally
    //   216	224	453	finally
    //   227	236	453	finally
    //   236	247	453	finally
    //   247	258	453	finally
    //   258	269	453	finally
    //   269	283	453	finally
    //   349	359	453	finally
    //   364	374	453	finally
    //   440	450	453	finally
    //   523	533	453	finally
    //   258	269	521	java/lang/Exception
  }
}


/* Location:           L:\local\mybackup\temp\qq_apk\com.tencent.mobileqq\classes5.jar
 * Qualified Name:     lrj
 * JD-Core Version:    0.7.0.1
 */