package com.tencent.mm.plugin.appbrand.m;

import com.tencent.matrix.trace.core.AppMethodBeat;
import com.tencent.mm.plugin.appbrand.jsapi.c;
import com.tencent.mm.sdk.platformtools.ab;
import java.io.InputStream;
import java.net.HttpURLConnection;
import java.util.ArrayList;
import java.util.Iterator;
import java.util.Map;
import javax.net.ssl.SSLContext;
import org.json.JSONObject;

public final class d
{
  private c hrA;
  private final String igf;
  protected final ArrayList<String> isA;
  protected final ArrayList<e> isH;
  int isI;
  private SSLContext isz;
  
  public d(c paramc)
  {
    AppMethodBeat.i(108149);
    this.isH = new ArrayList();
    this.isA = new ArrayList();
    this.hrA = paramc;
    paramc = (a)paramc.U(a.class);
    if (paramc == null)
    {
      ab.e("MicroMsg.AppBrandNetworkRequest", "hy: config not found");
      this.igf = "";
      AppMethodBeat.o(108149);
      return;
    }
    this.isI = paramc.bDq;
    this.igf = paramc.isv;
    this.isz = j.a(paramc);
    AppMethodBeat.o(108149);
  }
  
  static boolean DQ(String paramString)
  {
    AppMethodBeat.i(108154);
    if ((paramString.equalsIgnoreCase("POST")) || (paramString.equalsIgnoreCase("PUT")) || (paramString.equalsIgnoreCase("DELETE")))
    {
      AppMethodBeat.o(108154);
      return true;
    }
    AppMethodBeat.o(108154);
    return false;
  }
  
  private void a(d.a parama, String paramString1, Object paramObject, int paramInt, JSONObject paramJSONObject, String paramString2, HttpURLConnection paramHttpURLConnection)
  {
    AppMethodBeat.i(138237);
    a(paramString2, paramHttpURLConnection);
    parama.a(paramString1, paramObject, paramInt, paramJSONObject);
    AppMethodBeat.o(138237);
  }
  
  private void a(d.a parama, String paramString1, String paramString2, HttpURLConnection paramHttpURLConnection)
  {
    AppMethodBeat.i(138236);
    a(paramString2, paramHttpURLConnection);
    parama.CC(paramString1);
    AppMethodBeat.o(138236);
  }
  
  /* Error */
  private void a(e parame)
  {
    // Byte code:
    //   0: ldc 138
    //   2: invokestatic 31	com/tencent/matrix/trace/core/AppMethodBeat:i	(I)V
    //   5: aconst_null
    //   6: astore 30
    //   8: aconst_null
    //   9: astore 31
    //   11: aconst_null
    //   12: astore 32
    //   14: aconst_null
    //   15: astore 33
    //   17: aconst_null
    //   18: astore 34
    //   20: aconst_null
    //   21: astore 35
    //   23: aconst_null
    //   24: astore 36
    //   26: aconst_null
    //   27: astore 37
    //   29: aconst_null
    //   30: astore 29
    //   32: aconst_null
    //   33: astore 39
    //   35: aconst_null
    //   36: astore 49
    //   38: aconst_null
    //   39: astore 50
    //   41: aconst_null
    //   42: astore 56
    //   44: aconst_null
    //   45: astore 57
    //   47: aconst_null
    //   48: astore 51
    //   50: aconst_null
    //   51: astore 52
    //   53: aconst_null
    //   54: astore 53
    //   56: aconst_null
    //   57: astore 54
    //   59: aconst_null
    //   60: astore 55
    //   62: aconst_null
    //   63: astore 40
    //   65: aconst_null
    //   66: astore 41
    //   68: aconst_null
    //   69: astore 42
    //   71: aconst_null
    //   72: astore 43
    //   74: aconst_null
    //   75: astore 44
    //   77: aconst_null
    //   78: astore 45
    //   80: aconst_null
    //   81: astore 46
    //   83: aconst_null
    //   84: astore 47
    //   86: aconst_null
    //   87: astore 48
    //   89: aconst_null
    //   90: astore 38
    //   92: aload_1
    //   93: getfield 144	com/tencent/mm/plugin/appbrand/m/e:isS	Lcom/tencent/mm/plugin/appbrand/m/d$a;
    //   96: astore 59
    //   98: aload_1
    //   99: getfield 148	com/tencent/mm/plugin/appbrand/m/e:isT	Ljava/util/Map;
    //   102: astore 27
    //   104: iconst_0
    //   105: istore 6
    //   107: iconst_0
    //   108: istore 7
    //   110: iconst_0
    //   111: istore 22
    //   113: iconst_0
    //   114: istore 4
    //   116: iconst_0
    //   117: istore 8
    //   119: iconst_0
    //   120: istore 9
    //   122: iconst_0
    //   123: istore 10
    //   125: iconst_0
    //   126: istore 11
    //   128: iconst_0
    //   129: istore 12
    //   131: iconst_0
    //   132: istore 5
    //   134: iconst_0
    //   135: istore 14
    //   137: iconst_0
    //   138: istore 15
    //   140: iconst_0
    //   141: istore 16
    //   143: iconst_0
    //   144: istore 23
    //   146: iconst_0
    //   147: istore_2
    //   148: iconst_0
    //   149: istore 17
    //   151: iconst_0
    //   152: istore 18
    //   154: iconst_0
    //   155: istore 19
    //   157: iconst_0
    //   158: istore 20
    //   160: iconst_0
    //   161: istore 21
    //   163: iconst_0
    //   164: istore 13
    //   166: aload_1
    //   167: getfield 151	com/tencent/mm/plugin/appbrand/m/e:isU	Ljava/util/ArrayList;
    //   170: astore 58
    //   172: aload 58
    //   174: ifnull +94 -> 268
    //   177: aload 58
    //   179: aload_1
    //   180: getfield 154	com/tencent/mm/plugin/appbrand/m/e:mUrl	Ljava/lang/String;
    //   183: invokestatic 158	com/tencent/mm/plugin/appbrand/m/j:c	(Ljava/util/ArrayList;Ljava/lang/String;)Z
    //   186: ifne +82 -> 268
    //   189: aload_0
    //   190: aload 59
    //   192: ldc 160
    //   194: aload_1
    //   195: getfield 163	com/tencent/mm/plugin/appbrand/m/e:hwp	Ljava/lang/String;
    //   198: aconst_null
    //   199: invokespecial 165	com/tencent/mm/plugin/appbrand/m/d:a	(Lcom/tencent/mm/plugin/appbrand/m/d$a;Ljava/lang/String;Ljava/lang/String;Ljava/net/HttpURLConnection;)V
    //   202: ldc 167
    //   204: invokestatic 173	com/tencent/luggage/a/e:r	(Ljava/lang/Class;)Lcom/tencent/luggage/a/d;
    //   207: checkcast 167	com/tencent/mm/plugin/appbrand/m/o
    //   210: aload_0
    //   211: getfield 40	com/tencent/mm/plugin/appbrand/m/d:hrA	Lcom/tencent/mm/plugin/appbrand/jsapi/c;
    //   214: invokeinterface 177 1 0
    //   219: aload_1
    //   220: getfield 180	com/tencent/mm/plugin/appbrand/m/e:isY	Ljava/lang/String;
    //   223: aload_1
    //   224: getfield 183	com/tencent/mm/plugin/appbrand/m/e:bxW	Ljava/lang/String;
    //   227: aload_1
    //   228: getfield 154	com/tencent/mm/plugin/appbrand/m/e:mUrl	Ljava/lang/String;
    //   231: lconst_0
    //   232: lconst_0
    //   233: iconst_0
    //   234: iconst_2
    //   235: aload_1
    //   236: invokevirtual 187	com/tencent/mm/plugin/appbrand/m/e:aIj	()I
    //   239: invokeinterface 190 12 0
    //   244: ldc 50
    //   246: ldc 192
    //   248: iconst_1
    //   249: anewarray 4	java/lang/Object
    //   252: dup
    //   253: iconst_0
    //   254: aload_1
    //   255: getfield 154	com/tencent/mm/plugin/appbrand/m/e:mUrl	Ljava/lang/String;
    //   258: aastore
    //   259: invokestatic 195	com/tencent/mm/sdk/platformtools/ab:i	(Ljava/lang/String;Ljava/lang/String;[Ljava/lang/Object;)V
    //   262: ldc 138
    //   264: invokestatic 65	com/tencent/matrix/trace/core/AppMethodBeat:o	(I)V
    //   267: return
    //   268: ldc 197
    //   270: invokestatic 173	com/tencent/luggage/a/e:r	(Ljava/lang/Class;)Lcom/tencent/luggage/a/d;
    //   273: checkcast 197	com/tencent/mm/plugin/appbrand/o/a
    //   276: ldc2_w 198
    //   279: lconst_0
    //   280: lconst_1
    //   281: iconst_0
    //   282: invokeinterface 203 8 0
    //   287: ldc 50
    //   289: ldc 205
    //   291: iconst_3
    //   292: anewarray 4	java/lang/Object
    //   295: dup
    //   296: iconst_0
    //   297: aload_1
    //   298: getfield 163	com/tencent/mm/plugin/appbrand/m/e:hwp	Ljava/lang/String;
    //   301: aastore
    //   302: dup
    //   303: iconst_1
    //   304: aload_1
    //   305: getfield 154	com/tencent/mm/plugin/appbrand/m/e:mUrl	Ljava/lang/String;
    //   308: aastore
    //   309: dup
    //   310: iconst_2
    //   311: aload_1
    //   312: getfield 183	com/tencent/mm/plugin/appbrand/m/e:bxW	Ljava/lang/String;
    //   315: aastore
    //   316: invokestatic 195	com/tencent/mm/sdk/platformtools/ab:i	(Ljava/lang/String;Ljava/lang/String;[Ljava/lang/Object;)V
    //   319: new 207	java/net/URL
    //   322: dup
    //   323: aload_1
    //   324: getfield 154	com/tencent/mm/plugin/appbrand/m/e:mUrl	Ljava/lang/String;
    //   327: invokespecial 209	java/net/URL:<init>	(Ljava/lang/String;)V
    //   330: invokevirtual 213	java/net/URL:openConnection	()Ljava/net/URLConnection;
    //   333: checkcast 215	java/net/HttpURLConnection
    //   336: astore 28
    //   338: aload 28
    //   340: astore 29
    //   342: aload 28
    //   344: astore 30
    //   346: aload 28
    //   348: astore 31
    //   350: aload 28
    //   352: astore 32
    //   354: aload 28
    //   356: astore 33
    //   358: aload 28
    //   360: astore 34
    //   362: aload 28
    //   364: astore 35
    //   366: aload 28
    //   368: astore 36
    //   370: aload 28
    //   372: astore 37
    //   374: aload_1
    //   375: getfield 163	com/tencent/mm/plugin/appbrand/m/e:hwp	Ljava/lang/String;
    //   378: invokestatic 220	com/tencent/mm/sdk/platformtools/bo:isNullOrNil	(Ljava/lang/String;)Z
    //   381: ifne +45 -> 426
    //   384: aload 28
    //   386: astore 29
    //   388: aload 28
    //   390: astore 30
    //   392: aload 28
    //   394: astore 31
    //   396: aload 28
    //   398: astore 32
    //   400: aload 28
    //   402: astore 33
    //   404: aload 28
    //   406: astore 34
    //   408: aload 28
    //   410: astore 35
    //   412: aload 28
    //   414: astore 36
    //   416: aload 28
    //   418: astore 37
    //   420: aload_1
    //   421: aload 28
    //   423: putfield 224	com/tencent/mm/plugin/appbrand/m/e:isX	Ljava/net/HttpURLConnection;
    //   426: aload 28
    //   428: ifnonnull +235 -> 663
    //   431: aload 28
    //   433: astore 29
    //   435: aload 28
    //   437: astore 30
    //   439: aload 28
    //   441: astore 31
    //   443: aload 28
    //   445: astore 32
    //   447: aload 28
    //   449: astore 33
    //   451: aload 28
    //   453: astore 34
    //   455: aload 28
    //   457: astore 35
    //   459: aload 28
    //   461: astore 36
    //   463: aload 28
    //   465: astore 37
    //   467: ldc 197
    //   469: invokestatic 173	com/tencent/luggage/a/e:r	(Ljava/lang/Class;)Lcom/tencent/luggage/a/d;
    //   472: checkcast 197	com/tencent/mm/plugin/appbrand/o/a
    //   475: ldc2_w 198
    //   478: ldc2_w 225
    //   481: lconst_1
    //   482: iconst_0
    //   483: invokeinterface 203 8 0
    //   488: aload 28
    //   490: astore 29
    //   492: aload 28
    //   494: astore 30
    //   496: aload 28
    //   498: astore 31
    //   500: aload 28
    //   502: astore 32
    //   504: aload 28
    //   506: astore 33
    //   508: aload 28
    //   510: astore 34
    //   512: aload 28
    //   514: astore 35
    //   516: aload 28
    //   518: astore 36
    //   520: aload 28
    //   522: astore 37
    //   524: ldc 50
    //   526: ldc 228
    //   528: iconst_2
    //   529: anewarray 4	java/lang/Object
    //   532: dup
    //   533: iconst_0
    //   534: aload_1
    //   535: getfield 163	com/tencent/mm/plugin/appbrand/m/e:hwp	Ljava/lang/String;
    //   538: aastore
    //   539: dup
    //   540: iconst_1
    //   541: aload_1
    //   542: getfield 154	com/tencent/mm/plugin/appbrand/m/e:mUrl	Ljava/lang/String;
    //   545: aastore
    //   546: invokestatic 230	com/tencent/mm/sdk/platformtools/ab:e	(Ljava/lang/String;Ljava/lang/String;[Ljava/lang/Object;)V
    //   549: ldc 167
    //   551: invokestatic 173	com/tencent/luggage/a/e:r	(Ljava/lang/Class;)Lcom/tencent/luggage/a/d;
    //   554: checkcast 167	com/tencent/mm/plugin/appbrand/m/o
    //   557: aload_0
    //   558: getfield 40	com/tencent/mm/plugin/appbrand/m/d:hrA	Lcom/tencent/mm/plugin/appbrand/jsapi/c;
    //   561: invokeinterface 177 1 0
    //   566: aload_1
    //   567: getfield 180	com/tencent/mm/plugin/appbrand/m/e:isY	Ljava/lang/String;
    //   570: aload_1
    //   571: getfield 183	com/tencent/mm/plugin/appbrand/m/e:bxW	Ljava/lang/String;
    //   574: aload_1
    //   575: getfield 154	com/tencent/mm/plugin/appbrand/m/e:mUrl	Ljava/lang/String;
    //   578: aload_1
    //   579: invokevirtual 234	com/tencent/mm/plugin/appbrand/m/e:getDataSize	()J
    //   582: lconst_0
    //   583: iconst_0
    //   584: iconst_2
    //   585: aload_1
    //   586: invokevirtual 187	com/tencent/mm/plugin/appbrand/m/e:aIj	()I
    //   589: invokeinterface 190 12 0
    //   594: invokestatic 240	com/tencent/mm/sdk/platformtools/ah:getContext	()Landroid/content/Context;
    //   597: invokestatic 246	com/tencent/mm/sdk/platformtools/at:getNetType	(Landroid/content/Context;)I
    //   600: istore_2
    //   601: iload_2
    //   602: iconst_m1
    //   603: if_icmpne +24 -> 627
    //   606: ldc 197
    //   608: invokestatic 173	com/tencent/luggage/a/e:r	(Ljava/lang/Class;)Lcom/tencent/luggage/a/d;
    //   611: checkcast 197	com/tencent/mm/plugin/appbrand/o/a
    //   614: ldc2_w 198
    //   617: ldc2_w 247
    //   620: lconst_1
    //   621: iconst_0
    //   622: invokeinterface 203 8 0
    //   627: ldc 50
    //   629: ldc 250
    //   631: iconst_1
    //   632: anewarray 4	java/lang/Object
    //   635: dup
    //   636: iconst_0
    //   637: iload_2
    //   638: invokestatic 256	java/lang/Integer:valueOf	(I)Ljava/lang/Integer;
    //   641: aastore
    //   642: invokestatic 195	com/tencent/mm/sdk/platformtools/ab:i	(Ljava/lang/String;Ljava/lang/String;[Ljava/lang/Object;)V
    //   645: aload_0
    //   646: getfield 38	com/tencent/mm/plugin/appbrand/m/d:isA	Ljava/util/ArrayList;
    //   649: aload_1
    //   650: getfield 163	com/tencent/mm/plugin/appbrand/m/e:hwp	Ljava/lang/String;
    //   653: invokevirtual 260	java/util/ArrayList:remove	(Ljava/lang/Object;)Z
    //   656: pop
    //   657: ldc 138
    //   659: invokestatic 65	com/tencent/matrix/trace/core/AppMethodBeat:o	(I)V
    //   662: return
    //   663: aload 28
    //   665: astore 29
    //   667: aload 28
    //   669: astore 30
    //   671: aload 28
    //   673: astore 31
    //   675: aload 28
    //   677: astore 32
    //   679: aload 28
    //   681: astore 33
    //   683: aload 28
    //   685: astore 34
    //   687: aload 28
    //   689: astore 35
    //   691: aload 28
    //   693: astore 36
    //   695: aload 28
    //   697: astore 37
    //   699: aload 28
    //   701: instanceof 262
    //   704: ifeq +192 -> 896
    //   707: aload 28
    //   709: astore 29
    //   711: aload 28
    //   713: astore 30
    //   715: aload 28
    //   717: astore 31
    //   719: aload 28
    //   721: astore 32
    //   723: aload 28
    //   725: astore 33
    //   727: aload 28
    //   729: astore 34
    //   731: aload 28
    //   733: astore 35
    //   735: aload 28
    //   737: astore 36
    //   739: aload 28
    //   741: astore 37
    //   743: aload_0
    //   744: getfield 81	com/tencent/mm/plugin/appbrand/m/d:isz	Ljavax/net/ssl/SSLContext;
    //   747: ifnull +54 -> 801
    //   750: aload 28
    //   752: astore 29
    //   754: aload 28
    //   756: astore 30
    //   758: aload 28
    //   760: astore 31
    //   762: aload 28
    //   764: astore 32
    //   766: aload 28
    //   768: astore 33
    //   770: aload 28
    //   772: astore 34
    //   774: aload 28
    //   776: astore 35
    //   778: aload 28
    //   780: astore 36
    //   782: aload 28
    //   784: astore 37
    //   786: aload 28
    //   788: checkcast 262	javax/net/ssl/HttpsURLConnection
    //   791: aload_0
    //   792: getfield 81	com/tencent/mm/plugin/appbrand/m/d:isz	Ljavax/net/ssl/SSLContext;
    //   795: invokevirtual 268	javax/net/ssl/SSLContext:getSocketFactory	()Ljavax/net/ssl/SSLSocketFactory;
    //   798: invokevirtual 272	javax/net/ssl/HttpsURLConnection:setSSLSocketFactory	(Ljavax/net/ssl/SSLSocketFactory;)V
    //   801: aload 28
    //   803: astore 29
    //   805: aload 28
    //   807: astore 30
    //   809: aload 28
    //   811: astore 31
    //   813: aload 28
    //   815: astore 32
    //   817: aload 28
    //   819: astore 33
    //   821: aload 28
    //   823: astore 34
    //   825: aload 28
    //   827: astore 35
    //   829: aload 28
    //   831: astore 36
    //   833: aload 28
    //   835: astore 37
    //   837: ldc 50
    //   839: ldc_w 274
    //   842: aload 58
    //   844: invokestatic 277	java/lang/String:valueOf	(Ljava/lang/Object;)Ljava/lang/String;
    //   847: invokevirtual 281	java/lang/String:concat	(Ljava/lang/String;)Ljava/lang/String;
    //   850: invokestatic 283	com/tencent/mm/sdk/platformtools/ab:i	(Ljava/lang/String;Ljava/lang/String;)V
    //   853: aload 28
    //   855: astore 29
    //   857: aload 28
    //   859: astore 30
    //   861: aload 28
    //   863: astore 31
    //   865: aload 28
    //   867: astore 32
    //   869: aload 28
    //   871: astore 33
    //   873: aload 28
    //   875: astore 34
    //   877: aload 28
    //   879: astore 35
    //   881: aload 28
    //   883: astore 36
    //   885: aload 28
    //   887: astore 37
    //   889: aload 28
    //   891: aload 58
    //   893: invokestatic 286	com/tencent/mm/plugin/appbrand/m/j:a	(Ljava/net/HttpURLConnection;Ljava/util/ArrayList;)V
    //   896: aload 28
    //   898: astore 29
    //   900: aload 28
    //   902: astore 30
    //   904: aload 28
    //   906: astore 31
    //   908: aload 28
    //   910: astore 32
    //   912: aload 28
    //   914: astore 33
    //   916: aload 28
    //   918: astore 34
    //   920: aload 28
    //   922: astore 35
    //   924: aload 28
    //   926: astore 36
    //   928: aload 28
    //   930: astore 37
    //   932: ldc 50
    //   934: ldc_w 288
    //   937: iconst_1
    //   938: anewarray 4	java/lang/Object
    //   941: dup
    //   942: iconst_0
    //   943: aload_1
    //   944: getfield 291	com/tencent/mm/plugin/appbrand/m/e:isQ	I
    //   947: invokestatic 256	java/lang/Integer:valueOf	(I)Ljava/lang/Integer;
    //   950: aastore
    //   951: invokestatic 195	com/tencent/mm/sdk/platformtools/ab:i	(Ljava/lang/String;Ljava/lang/String;[Ljava/lang/Object;)V
    //   954: aload 28
    //   956: astore 29
    //   958: aload 28
    //   960: astore 30
    //   962: aload 28
    //   964: astore 31
    //   966: aload 28
    //   968: astore 32
    //   970: aload 28
    //   972: astore 33
    //   974: aload 28
    //   976: astore 34
    //   978: aload 28
    //   980: astore 35
    //   982: aload 28
    //   984: astore 36
    //   986: aload 28
    //   988: astore 37
    //   990: aload 28
    //   992: aload_1
    //   993: getfield 291	com/tencent/mm/plugin/appbrand/m/e:isQ	I
    //   996: invokevirtual 294	java/net/HttpURLConnection:setConnectTimeout	(I)V
    //   999: aload 28
    //   1001: astore 29
    //   1003: aload 28
    //   1005: astore 30
    //   1007: aload 28
    //   1009: astore 31
    //   1011: aload 28
    //   1013: astore 32
    //   1015: aload 28
    //   1017: astore 33
    //   1019: aload 28
    //   1021: astore 34
    //   1023: aload 28
    //   1025: astore 35
    //   1027: aload 28
    //   1029: astore 36
    //   1031: aload 28
    //   1033: astore 37
    //   1035: aload 28
    //   1037: aload_1
    //   1038: getfield 291	com/tencent/mm/plugin/appbrand/m/e:isQ	I
    //   1041: invokevirtual 297	java/net/HttpURLConnection:setReadTimeout	(I)V
    //   1044: aload 28
    //   1046: astore 29
    //   1048: aload 28
    //   1050: astore 30
    //   1052: aload 28
    //   1054: astore 31
    //   1056: aload 28
    //   1058: astore 32
    //   1060: aload 28
    //   1062: astore 33
    //   1064: aload 28
    //   1066: astore 34
    //   1068: aload 28
    //   1070: astore 35
    //   1072: aload 28
    //   1074: astore 36
    //   1076: aload 28
    //   1078: astore 37
    //   1080: aload 28
    //   1082: ldc_w 299
    //   1085: ldc_w 301
    //   1088: invokevirtual 304	java/net/HttpURLConnection:setRequestProperty	(Ljava/lang/String;Ljava/lang/String;)V
    //   1091: aload 28
    //   1093: astore 29
    //   1095: aload 28
    //   1097: astore 30
    //   1099: aload 28
    //   1101: astore 31
    //   1103: aload 28
    //   1105: astore 32
    //   1107: aload 28
    //   1109: astore 33
    //   1111: aload 28
    //   1113: astore 34
    //   1115: aload 28
    //   1117: astore 35
    //   1119: aload 28
    //   1121: astore 36
    //   1123: aload 28
    //   1125: astore 37
    //   1127: aload 28
    //   1129: iconst_0
    //   1130: invokevirtual 308	java/net/HttpURLConnection:setInstanceFollowRedirects	(Z)V
    //   1133: aload 28
    //   1135: astore 29
    //   1137: aload 28
    //   1139: astore 30
    //   1141: aload 28
    //   1143: astore 31
    //   1145: aload 28
    //   1147: astore 32
    //   1149: aload 28
    //   1151: astore 33
    //   1153: aload 28
    //   1155: astore 34
    //   1157: aload 28
    //   1159: astore 35
    //   1161: aload 28
    //   1163: astore 36
    //   1165: aload 28
    //   1167: astore 37
    //   1169: getstatic 313	android/os/Build$VERSION:SDK_INT	I
    //   1172: bipush 19
    //   1174: if_icmpgt +827 -> 2001
    //   1177: aload 28
    //   1179: astore 29
    //   1181: aload 28
    //   1183: astore 30
    //   1185: aload 28
    //   1187: astore 31
    //   1189: aload 28
    //   1191: astore 32
    //   1193: aload 28
    //   1195: astore 33
    //   1197: aload 28
    //   1199: astore 34
    //   1201: aload 28
    //   1203: astore 35
    //   1205: aload 28
    //   1207: astore 36
    //   1209: aload 28
    //   1211: astore 37
    //   1213: aload_1
    //   1214: getfield 183	com/tencent/mm/plugin/appbrand/m/e:bxW	Ljava/lang/String;
    //   1217: ldc 96
    //   1219: invokevirtual 92	java/lang/String:equalsIgnoreCase	(Ljava/lang/String;)Z
    //   1222: ifeq +779 -> 2001
    //   1225: aload 28
    //   1227: astore 29
    //   1229: aload 28
    //   1231: astore 30
    //   1233: aload 28
    //   1235: astore 31
    //   1237: aload 28
    //   1239: astore 32
    //   1241: aload 28
    //   1243: astore 33
    //   1245: aload 28
    //   1247: astore 34
    //   1249: aload 28
    //   1251: astore 35
    //   1253: aload 28
    //   1255: astore 36
    //   1257: aload 28
    //   1259: astore 37
    //   1261: ldc 50
    //   1263: ldc_w 315
    //   1266: invokestatic 283	com/tencent/mm/sdk/platformtools/ab:i	(Ljava/lang/String;Ljava/lang/String;)V
    //   1269: aload 28
    //   1271: astore 29
    //   1273: aload 28
    //   1275: astore 30
    //   1277: aload 28
    //   1279: astore 31
    //   1281: aload 28
    //   1283: astore 32
    //   1285: aload 28
    //   1287: astore 33
    //   1289: aload 28
    //   1291: astore 34
    //   1293: aload 28
    //   1295: astore 35
    //   1297: aload 28
    //   1299: astore 36
    //   1301: aload 28
    //   1303: astore 37
    //   1305: aload 28
    //   1307: ldc_w 317
    //   1310: ldc 96
    //   1312: invokevirtual 304	java/net/HttpURLConnection:setRequestProperty	(Ljava/lang/String;Ljava/lang/String;)V
    //   1315: aload 28
    //   1317: astore 29
    //   1319: aload 28
    //   1321: astore 30
    //   1323: aload 28
    //   1325: astore 31
    //   1327: aload 28
    //   1329: astore 32
    //   1331: aload 28
    //   1333: astore 33
    //   1335: aload 28
    //   1337: astore 34
    //   1339: aload 28
    //   1341: astore 35
    //   1343: aload 28
    //   1345: astore 36
    //   1347: aload 28
    //   1349: astore 37
    //   1351: aload 28
    //   1353: ldc 87
    //   1355: invokevirtual 320	java/net/HttpURLConnection:setRequestMethod	(Ljava/lang/String;)V
    //   1358: aload 28
    //   1360: astore 29
    //   1362: aload 28
    //   1364: astore 30
    //   1366: aload 28
    //   1368: astore 31
    //   1370: aload 28
    //   1372: astore 32
    //   1374: aload 28
    //   1376: astore 33
    //   1378: aload 28
    //   1380: astore 34
    //   1382: aload 28
    //   1384: astore 35
    //   1386: aload 28
    //   1388: astore 36
    //   1390: aload 28
    //   1392: astore 37
    //   1394: aload 28
    //   1396: iconst_1
    //   1397: invokevirtual 323	java/net/HttpURLConnection:setUseCaches	(Z)V
    //   1400: aload 28
    //   1402: astore 29
    //   1404: aload 28
    //   1406: astore 30
    //   1408: aload 28
    //   1410: astore 31
    //   1412: aload 28
    //   1414: astore 32
    //   1416: aload 28
    //   1418: astore 33
    //   1420: aload 28
    //   1422: astore 34
    //   1424: aload 28
    //   1426: astore 35
    //   1428: aload 28
    //   1430: astore 36
    //   1432: aload 28
    //   1434: astore 37
    //   1436: aload 28
    //   1438: ldc_w 325
    //   1441: ldc_w 327
    //   1444: invokevirtual 304	java/net/HttpURLConnection:setRequestProperty	(Ljava/lang/String;Ljava/lang/String;)V
    //   1447: aload 27
    //   1449: ifnull +853 -> 2302
    //   1452: aload 28
    //   1454: astore 29
    //   1456: aload 28
    //   1458: astore 30
    //   1460: aload 28
    //   1462: astore 31
    //   1464: aload 28
    //   1466: astore 32
    //   1468: aload 28
    //   1470: astore 33
    //   1472: aload 28
    //   1474: astore 34
    //   1476: aload 28
    //   1478: astore 35
    //   1480: aload 28
    //   1482: astore 36
    //   1484: aload 28
    //   1486: astore 37
    //   1488: ldc 50
    //   1490: ldc_w 329
    //   1493: iconst_1
    //   1494: anewarray 4	java/lang/Object
    //   1497: dup
    //   1498: iconst_0
    //   1499: aload_1
    //   1500: getfield 154	com/tencent/mm/plugin/appbrand/m/e:mUrl	Ljava/lang/String;
    //   1503: aastore
    //   1504: invokestatic 195	com/tencent/mm/sdk/platformtools/ab:i	(Ljava/lang/String;Ljava/lang/String;[Ljava/lang/Object;)V
    //   1507: aload 28
    //   1509: astore 29
    //   1511: aload 28
    //   1513: astore 30
    //   1515: aload 28
    //   1517: astore 31
    //   1519: aload 28
    //   1521: astore 32
    //   1523: aload 28
    //   1525: astore 33
    //   1527: aload 28
    //   1529: astore 34
    //   1531: aload 28
    //   1533: astore 35
    //   1535: aload 28
    //   1537: astore 36
    //   1539: aload 28
    //   1541: astore 37
    //   1543: aload 27
    //   1545: invokeinterface 335 1 0
    //   1550: invokeinterface 341 1 0
    //   1555: astore 27
    //   1557: aload 28
    //   1559: astore 29
    //   1561: aload 28
    //   1563: astore 30
    //   1565: aload 28
    //   1567: astore 31
    //   1569: aload 28
    //   1571: astore 32
    //   1573: aload 28
    //   1575: astore 33
    //   1577: aload 28
    //   1579: astore 34
    //   1581: aload 28
    //   1583: astore 35
    //   1585: aload 28
    //   1587: astore 36
    //   1589: aload 28
    //   1591: astore 37
    //   1593: aload 27
    //   1595: invokeinterface 347 1 0
    //   1600: ifeq +702 -> 2302
    //   1603: aload 28
    //   1605: astore 29
    //   1607: aload 28
    //   1609: astore 30
    //   1611: aload 28
    //   1613: astore 31
    //   1615: aload 28
    //   1617: astore 32
    //   1619: aload 28
    //   1621: astore 33
    //   1623: aload 28
    //   1625: astore 34
    //   1627: aload 28
    //   1629: astore 35
    //   1631: aload 28
    //   1633: astore 36
    //   1635: aload 28
    //   1637: astore 37
    //   1639: aload 27
    //   1641: invokeinterface 351 1 0
    //   1646: checkcast 353	java/util/Map$Entry
    //   1649: astore 58
    //   1651: aload 28
    //   1653: astore 29
    //   1655: aload 28
    //   1657: astore 30
    //   1659: aload 28
    //   1661: astore 31
    //   1663: aload 28
    //   1665: astore 32
    //   1667: aload 28
    //   1669: astore 33
    //   1671: aload 28
    //   1673: astore 34
    //   1675: aload 28
    //   1677: astore 35
    //   1679: aload 28
    //   1681: astore 36
    //   1683: aload 28
    //   1685: astore 37
    //   1687: aload 28
    //   1689: aload 58
    //   1691: invokeinterface 356 1 0
    //   1696: checkcast 89	java/lang/String
    //   1699: aload 58
    //   1701: invokeinterface 359 1 0
    //   1706: checkcast 89	java/lang/String
    //   1709: invokevirtual 304	java/net/HttpURLConnection:setRequestProperty	(Ljava/lang/String;Ljava/lang/String;)V
    //   1712: aload 28
    //   1714: astore 29
    //   1716: aload 28
    //   1718: astore 30
    //   1720: aload 28
    //   1722: astore 31
    //   1724: aload 28
    //   1726: astore 32
    //   1728: aload 28
    //   1730: astore 33
    //   1732: aload 28
    //   1734: astore 34
    //   1736: aload 28
    //   1738: astore 35
    //   1740: aload 28
    //   1742: astore 36
    //   1744: aload 28
    //   1746: astore 37
    //   1748: ldc 50
    //   1750: ldc_w 361
    //   1753: iconst_3
    //   1754: anewarray 4	java/lang/Object
    //   1757: dup
    //   1758: iconst_0
    //   1759: aload_1
    //   1760: getfield 154	com/tencent/mm/plugin/appbrand/m/e:mUrl	Ljava/lang/String;
    //   1763: aastore
    //   1764: dup
    //   1765: iconst_1
    //   1766: aload 58
    //   1768: invokeinterface 356 1 0
    //   1773: aastore
    //   1774: dup
    //   1775: iconst_2
    //   1776: aload 58
    //   1778: invokeinterface 359 1 0
    //   1783: aastore
    //   1784: invokestatic 195	com/tencent/mm/sdk/platformtools/ab:i	(Ljava/lang/String;Ljava/lang/String;[Ljava/lang/Object;)V
    //   1787: goto -230 -> 1557
    //   1790: astore 30
    //   1792: iconst_0
    //   1793: istore_2
    //   1794: aconst_null
    //   1795: astore 27
    //   1797: aconst_null
    //   1798: astore 31
    //   1800: aload 29
    //   1802: astore 28
    //   1804: aload 31
    //   1806: astore 29
    //   1808: iload 13
    //   1810: istore_3
    //   1811: ldc 197
    //   1813: invokestatic 173	com/tencent/luggage/a/e:r	(Ljava/lang/Class;)Lcom/tencent/luggage/a/d;
    //   1816: checkcast 197	com/tencent/mm/plugin/appbrand/o/a
    //   1819: ldc2_w 198
    //   1822: lconst_1
    //   1823: lconst_1
    //   1824: iconst_0
    //   1825: invokeinterface 203 8 0
    //   1830: ldc 50
    //   1832: aload 30
    //   1834: ldc_w 363
    //   1837: iconst_1
    //   1838: anewarray 4	java/lang/Object
    //   1841: dup
    //   1842: iconst_0
    //   1843: aload_1
    //   1844: getfield 154	com/tencent/mm/plugin/appbrand/m/e:mUrl	Ljava/lang/String;
    //   1847: aastore
    //   1848: invokestatic 367	com/tencent/mm/sdk/platformtools/ab:printErrStackTrace	(Ljava/lang/String;Ljava/lang/Throwable;Ljava/lang/String;[Ljava/lang/Object;)V
    //   1851: aload_0
    //   1852: aload 59
    //   1854: ldc_w 369
    //   1857: aload_1
    //   1858: getfield 163	com/tencent/mm/plugin/appbrand/m/e:hwp	Ljava/lang/String;
    //   1861: aload 28
    //   1863: invokespecial 165	com/tencent/mm/plugin/appbrand/m/d:a	(Lcom/tencent/mm/plugin/appbrand/m/d$a;Ljava/lang/String;Ljava/lang/String;Ljava/net/HttpURLConnection;)V
    //   1866: ldc 167
    //   1868: invokestatic 173	com/tencent/luggage/a/e:r	(Ljava/lang/Class;)Lcom/tencent/luggage/a/d;
    //   1871: checkcast 167	com/tencent/mm/plugin/appbrand/m/o
    //   1874: aload_0
    //   1875: getfield 40	com/tencent/mm/plugin/appbrand/m/d:hrA	Lcom/tencent/mm/plugin/appbrand/jsapi/c;
    //   1878: invokeinterface 177 1 0
    //   1883: aload_1
    //   1884: getfield 180	com/tencent/mm/plugin/appbrand/m/e:isY	Ljava/lang/String;
    //   1887: aload_1
    //   1888: getfield 183	com/tencent/mm/plugin/appbrand/m/e:bxW	Ljava/lang/String;
    //   1891: aload_1
    //   1892: getfield 154	com/tencent/mm/plugin/appbrand/m/e:mUrl	Ljava/lang/String;
    //   1895: aload_1
    //   1896: invokevirtual 234	com/tencent/mm/plugin/appbrand/m/e:getDataSize	()J
    //   1899: iload_2
    //   1900: i2l
    //   1901: iload_3
    //   1902: iconst_2
    //   1903: aload_1
    //   1904: invokevirtual 187	com/tencent/mm/plugin/appbrand/m/e:aIj	()I
    //   1907: invokeinterface 190 12 0
    //   1912: invokestatic 240	com/tencent/mm/sdk/platformtools/ah:getContext	()Landroid/content/Context;
    //   1915: invokestatic 246	com/tencent/mm/sdk/platformtools/at:getNetType	(Landroid/content/Context;)I
    //   1918: istore_2
    //   1919: iload_2
    //   1920: iconst_m1
    //   1921: if_icmpne +24 -> 1945
    //   1924: ldc 197
    //   1926: invokestatic 173	com/tencent/luggage/a/e:r	(Ljava/lang/Class;)Lcom/tencent/luggage/a/d;
    //   1929: checkcast 197	com/tencent/mm/plugin/appbrand/o/a
    //   1932: ldc2_w 198
    //   1935: ldc2_w 247
    //   1938: lconst_1
    //   1939: iconst_0
    //   1940: invokeinterface 203 8 0
    //   1945: ldc 50
    //   1947: ldc 250
    //   1949: iconst_1
    //   1950: anewarray 4	java/lang/Object
    //   1953: dup
    //   1954: iconst_0
    //   1955: iload_2
    //   1956: invokestatic 256	java/lang/Integer:valueOf	(I)Ljava/lang/Integer;
    //   1959: aastore
    //   1960: invokestatic 195	com/tencent/mm/sdk/platformtools/ab:i	(Ljava/lang/String;Ljava/lang/String;[Ljava/lang/Object;)V
    //   1963: aload 29
    //   1965: ifnull +8 -> 1973
    //   1968: aload 29
    //   1970: invokevirtual 374	java/io/InputStream:close	()V
    //   1973: aload 27
    //   1975: ifnull +8 -> 1983
    //   1978: aload 27
    //   1980: invokevirtual 377	java/io/DataOutputStream:close	()V
    //   1983: aload_0
    //   1984: getfield 38	com/tencent/mm/plugin/appbrand/m/d:isA	Ljava/util/ArrayList;
    //   1987: aload_1
    //   1988: getfield 163	com/tencent/mm/plugin/appbrand/m/e:hwp	Ljava/lang/String;
    //   1991: invokevirtual 260	java/util/ArrayList:remove	(Ljava/lang/Object;)Z
    //   1994: pop
    //   1995: ldc 138
    //   1997: invokestatic 65	com/tencent/matrix/trace/core/AppMethodBeat:o	(I)V
    //   2000: return
    //   2001: aload 28
    //   2003: astore 29
    //   2005: aload 28
    //   2007: astore 30
    //   2009: aload 28
    //   2011: astore 31
    //   2013: aload 28
    //   2015: astore 32
    //   2017: aload 28
    //   2019: astore 33
    //   2021: aload 28
    //   2023: astore 34
    //   2025: aload 28
    //   2027: astore 35
    //   2029: aload 28
    //   2031: astore 36
    //   2033: aload 28
    //   2035: astore 37
    //   2037: aload 28
    //   2039: aload_1
    //   2040: getfield 183	com/tencent/mm/plugin/appbrand/m/e:bxW	Ljava/lang/String;
    //   2043: invokevirtual 320	java/net/HttpURLConnection:setRequestMethod	(Ljava/lang/String;)V
    //   2046: goto -688 -> 1358
    //   2049: astore 31
    //   2051: aconst_null
    //   2052: astore 29
    //   2054: aload 38
    //   2056: astore 28
    //   2058: aload 30
    //   2060: astore 32
    //   2062: iload 14
    //   2064: istore 4
    //   2066: iload 4
    //   2068: istore_2
    //   2069: iload 5
    //   2071: istore_3
    //   2072: aload 29
    //   2074: astore 27
    //   2076: aload 28
    //   2078: astore 30
    //   2080: ldc 197
    //   2082: invokestatic 173	com/tencent/luggage/a/e:r	(Ljava/lang/Class;)Lcom/tencent/luggage/a/d;
    //   2085: checkcast 197	com/tencent/mm/plugin/appbrand/o/a
    //   2088: ldc2_w 198
    //   2091: ldc2_w 378
    //   2094: lconst_1
    //   2095: iconst_0
    //   2096: invokeinterface 203 8 0
    //   2101: iload 4
    //   2103: istore_2
    //   2104: iload 5
    //   2106: istore_3
    //   2107: aload 29
    //   2109: astore 27
    //   2111: aload 28
    //   2113: astore 30
    //   2115: ldc 50
    //   2117: aload 31
    //   2119: ldc_w 381
    //   2122: iconst_1
    //   2123: anewarray 4	java/lang/Object
    //   2126: dup
    //   2127: iconst_0
    //   2128: aload_1
    //   2129: getfield 154	com/tencent/mm/plugin/appbrand/m/e:mUrl	Ljava/lang/String;
    //   2132: aastore
    //   2133: invokestatic 367	com/tencent/mm/sdk/platformtools/ab:printErrStackTrace	(Ljava/lang/String;Ljava/lang/Throwable;Ljava/lang/String;[Ljava/lang/Object;)V
    //   2136: iload 4
    //   2138: istore_2
    //   2139: iload 5
    //   2141: istore_3
    //   2142: aload 29
    //   2144: astore 27
    //   2146: aload 28
    //   2148: astore 30
    //   2150: aload_0
    //   2151: aload 59
    //   2153: ldc_w 383
    //   2156: aload_1
    //   2157: getfield 163	com/tencent/mm/plugin/appbrand/m/e:hwp	Ljava/lang/String;
    //   2160: aload 32
    //   2162: invokespecial 165	com/tencent/mm/plugin/appbrand/m/d:a	(Lcom/tencent/mm/plugin/appbrand/m/d$a;Ljava/lang/String;Ljava/lang/String;Ljava/net/HttpURLConnection;)V
    //   2165: ldc 167
    //   2167: invokestatic 173	com/tencent/luggage/a/e:r	(Ljava/lang/Class;)Lcom/tencent/luggage/a/d;
    //   2170: checkcast 167	com/tencent/mm/plugin/appbrand/m/o
    //   2173: aload_0
    //   2174: getfield 40	com/tencent/mm/plugin/appbrand/m/d:hrA	Lcom/tencent/mm/plugin/appbrand/jsapi/c;
    //   2177: invokeinterface 177 1 0
    //   2182: aload_1
    //   2183: getfield 180	com/tencent/mm/plugin/appbrand/m/e:isY	Ljava/lang/String;
    //   2186: aload_1
    //   2187: getfield 183	com/tencent/mm/plugin/appbrand/m/e:bxW	Ljava/lang/String;
    //   2190: aload_1
    //   2191: getfield 154	com/tencent/mm/plugin/appbrand/m/e:mUrl	Ljava/lang/String;
    //   2194: aload_1
    //   2195: invokevirtual 234	com/tencent/mm/plugin/appbrand/m/e:getDataSize	()J
    //   2198: iload 5
    //   2200: i2l
    //   2201: iload 4
    //   2203: iconst_2
    //   2204: aload_1
    //   2205: invokevirtual 187	com/tencent/mm/plugin/appbrand/m/e:aIj	()I
    //   2208: invokeinterface 190 12 0
    //   2213: invokestatic 240	com/tencent/mm/sdk/platformtools/ah:getContext	()Landroid/content/Context;
    //   2216: invokestatic 246	com/tencent/mm/sdk/platformtools/at:getNetType	(Landroid/content/Context;)I
    //   2219: istore_2
    //   2220: iload_2
    //   2221: iconst_m1
    //   2222: if_icmpne +24 -> 2246
    //   2225: ldc 197
    //   2227: invokestatic 173	com/tencent/luggage/a/e:r	(Ljava/lang/Class;)Lcom/tencent/luggage/a/d;
    //   2230: checkcast 197	com/tencent/mm/plugin/appbrand/o/a
    //   2233: ldc2_w 198
    //   2236: ldc2_w 247
    //   2239: lconst_1
    //   2240: iconst_0
    //   2241: invokeinterface 203 8 0
    //   2246: ldc 50
    //   2248: ldc 250
    //   2250: iconst_1
    //   2251: anewarray 4	java/lang/Object
    //   2254: dup
    //   2255: iconst_0
    //   2256: iload_2
    //   2257: invokestatic 256	java/lang/Integer:valueOf	(I)Ljava/lang/Integer;
    //   2260: aastore
    //   2261: invokestatic 195	com/tencent/mm/sdk/platformtools/ab:i	(Ljava/lang/String;Ljava/lang/String;[Ljava/lang/Object;)V
    //   2264: aload 28
    //   2266: ifnull +8 -> 2274
    //   2269: aload 28
    //   2271: invokevirtual 374	java/io/InputStream:close	()V
    //   2274: aload 29
    //   2276: ifnull +8 -> 2284
    //   2279: aload 29
    //   2281: invokevirtual 377	java/io/DataOutputStream:close	()V
    //   2284: aload_0
    //   2285: getfield 38	com/tencent/mm/plugin/appbrand/m/d:isA	Ljava/util/ArrayList;
    //   2288: aload_1
    //   2289: getfield 163	com/tencent/mm/plugin/appbrand/m/e:hwp	Ljava/lang/String;
    //   2292: invokevirtual 260	java/util/ArrayList:remove	(Ljava/lang/Object;)Z
    //   2295: pop
    //   2296: ldc 138
    //   2298: invokestatic 65	com/tencent/matrix/trace/core/AppMethodBeat:o	(I)V
    //   2301: return
    //   2302: aload 28
    //   2304: astore 29
    //   2306: aload 28
    //   2308: astore 30
    //   2310: aload 28
    //   2312: astore 31
    //   2314: aload 28
    //   2316: astore 32
    //   2318: aload 28
    //   2320: astore 33
    //   2322: aload 28
    //   2324: astore 34
    //   2326: aload 28
    //   2328: astore 35
    //   2330: aload 28
    //   2332: astore 36
    //   2334: aload 28
    //   2336: astore 37
    //   2338: aload 28
    //   2340: ldc_w 385
    //   2343: aload_0
    //   2344: getfield 62	com/tencent/mm/plugin/appbrand/m/d:igf	Ljava/lang/String;
    //   2347: invokevirtual 304	java/net/HttpURLConnection:setRequestProperty	(Ljava/lang/String;Ljava/lang/String;)V
    //   2350: aload 28
    //   2352: astore 29
    //   2354: aload 28
    //   2356: astore 30
    //   2358: aload 28
    //   2360: astore 31
    //   2362: aload 28
    //   2364: astore 32
    //   2366: aload 28
    //   2368: astore 33
    //   2370: aload 28
    //   2372: astore 34
    //   2374: aload 28
    //   2376: astore 35
    //   2378: aload 28
    //   2380: astore 36
    //   2382: aload 28
    //   2384: astore 37
    //   2386: aload_1
    //   2387: getfield 183	com/tencent/mm/plugin/appbrand/m/e:bxW	Ljava/lang/String;
    //   2390: invokestatic 387	com/tencent/mm/plugin/appbrand/m/d:DQ	(Ljava/lang/String;)Z
    //   2393: ifeq +888 -> 3281
    //   2396: aload 28
    //   2398: astore 29
    //   2400: aload 28
    //   2402: astore 30
    //   2404: aload 28
    //   2406: astore 31
    //   2408: aload 28
    //   2410: astore 32
    //   2412: aload 28
    //   2414: astore 33
    //   2416: aload 28
    //   2418: astore 34
    //   2420: aload 28
    //   2422: astore 35
    //   2424: aload 28
    //   2426: astore 36
    //   2428: aload 28
    //   2430: astore 37
    //   2432: ldc 50
    //   2434: ldc_w 389
    //   2437: invokestatic 283	com/tencent/mm/sdk/platformtools/ab:i	(Ljava/lang/String;Ljava/lang/String;)V
    //   2440: aload 28
    //   2442: astore 29
    //   2444: aload 28
    //   2446: astore 30
    //   2448: aload 28
    //   2450: astore 31
    //   2452: aload 28
    //   2454: astore 32
    //   2456: aload 28
    //   2458: astore 33
    //   2460: aload 28
    //   2462: astore 34
    //   2464: aload 28
    //   2466: astore 35
    //   2468: aload 28
    //   2470: astore 36
    //   2472: aload 28
    //   2474: astore 37
    //   2476: aload 28
    //   2478: ldc_w 391
    //   2481: aload_1
    //   2482: getfield 395	com/tencent/mm/plugin/appbrand/m/e:isR	[B
    //   2485: arraylength
    //   2486: invokestatic 399	java/lang/Integer:toString	(I)Ljava/lang/String;
    //   2489: invokevirtual 304	java/net/HttpURLConnection:setRequestProperty	(Ljava/lang/String;Ljava/lang/String;)V
    //   2492: aload 28
    //   2494: astore 29
    //   2496: aload 28
    //   2498: astore 30
    //   2500: aload 28
    //   2502: astore 31
    //   2504: aload 28
    //   2506: astore 32
    //   2508: aload 28
    //   2510: astore 33
    //   2512: aload 28
    //   2514: astore 34
    //   2516: aload 28
    //   2518: astore 35
    //   2520: aload 28
    //   2522: astore 36
    //   2524: aload 28
    //   2526: astore 37
    //   2528: aload 28
    //   2530: iconst_1
    //   2531: invokevirtual 402	java/net/HttpURLConnection:setDoOutput	(Z)V
    //   2534: aload 28
    //   2536: astore 29
    //   2538: aload 28
    //   2540: astore 30
    //   2542: aload 28
    //   2544: astore 31
    //   2546: aload 28
    //   2548: astore 32
    //   2550: aload 28
    //   2552: astore 33
    //   2554: aload 28
    //   2556: astore 34
    //   2558: aload 28
    //   2560: astore 35
    //   2562: aload 28
    //   2564: astore 36
    //   2566: aload 28
    //   2568: astore 37
    //   2570: aload 28
    //   2572: invokestatic 406	com/tencent/mm/plugin/appbrand/m/j:g	(Ljava/net/HttpURLConnection;)Lorg/json/JSONObject;
    //   2575: astore 58
    //   2577: aload 28
    //   2579: astore 29
    //   2581: aload 28
    //   2583: astore 30
    //   2585: aload 28
    //   2587: astore 31
    //   2589: aload 28
    //   2591: astore 32
    //   2593: aload 28
    //   2595: astore 33
    //   2597: aload 28
    //   2599: astore 34
    //   2601: aload 28
    //   2603: astore 35
    //   2605: aload 28
    //   2607: astore 36
    //   2609: aload 28
    //   2611: astore 37
    //   2613: new 376	java/io/DataOutputStream
    //   2616: dup
    //   2617: aload 28
    //   2619: invokevirtual 410	java/net/HttpURLConnection:getOutputStream	()Ljava/io/OutputStream;
    //   2622: invokespecial 413	java/io/DataOutputStream:<init>	(Ljava/io/OutputStream;)V
    //   2625: astore 27
    //   2627: aload 27
    //   2629: aload_1
    //   2630: getfield 395	com/tencent/mm/plugin/appbrand/m/e:isR	[B
    //   2633: invokevirtual 417	java/io/DataOutputStream:write	([B)V
    //   2636: aload 27
    //   2638: invokevirtual 420	java/io/DataOutputStream:flush	()V
    //   2641: aload 27
    //   2643: invokevirtual 377	java/io/DataOutputStream:close	()V
    //   2646: aload 27
    //   2648: astore 29
    //   2650: aload 58
    //   2652: astore 31
    //   2654: iload 23
    //   2656: istore_2
    //   2657: iload 22
    //   2659: istore_3
    //   2660: aload 29
    //   2662: astore 27
    //   2664: aload 56
    //   2666: astore 30
    //   2668: aload 59
    //   2670: aload 31
    //   2672: invokeinterface 424 2 0
    //   2677: iload 23
    //   2679: istore_2
    //   2680: iload 22
    //   2682: istore_3
    //   2683: aload 29
    //   2685: astore 27
    //   2687: aload 56
    //   2689: astore 30
    //   2691: aload 28
    //   2693: invokevirtual 427	java/net/HttpURLConnection:getResponseCode	()I
    //   2696: istore 24
    //   2698: iload 24
    //   2700: istore_2
    //   2701: aload 40
    //   2703: astore 31
    //   2705: aload 41
    //   2707: astore 38
    //   2709: aload 42
    //   2711: astore 30
    //   2713: aload 43
    //   2715: astore 32
    //   2717: aload 44
    //   2719: astore 33
    //   2721: aload 45
    //   2723: astore 34
    //   2725: aload 46
    //   2727: astore 35
    //   2729: aload 47
    //   2731: astore 36
    //   2733: aload 48
    //   2735: astore 37
    //   2737: aload 28
    //   2739: invokestatic 430	com/tencent/mm/plugin/appbrand/m/j:f	(Ljava/net/HttpURLConnection;)Lorg/json/JSONObject;
    //   2742: astore 49
    //   2744: aload 40
    //   2746: astore 31
    //   2748: aload 41
    //   2750: astore 38
    //   2752: aload 42
    //   2754: astore 30
    //   2756: aload 43
    //   2758: astore 32
    //   2760: aload 44
    //   2762: astore 33
    //   2764: aload 45
    //   2766: astore 34
    //   2768: aload 46
    //   2770: astore 35
    //   2772: aload 47
    //   2774: astore 36
    //   2776: aload 48
    //   2778: astore 37
    //   2780: aload 59
    //   2782: aload 49
    //   2784: invokeinterface 424 2 0
    //   2789: aload 40
    //   2791: astore 31
    //   2793: aload 41
    //   2795: astore 38
    //   2797: aload 42
    //   2799: astore 30
    //   2801: aload 43
    //   2803: astore 32
    //   2805: aload 44
    //   2807: astore 33
    //   2809: aload 45
    //   2811: astore 34
    //   2813: aload 46
    //   2815: astore 35
    //   2817: aload 47
    //   2819: astore 36
    //   2821: aload 48
    //   2823: astore 37
    //   2825: ldc 50
    //   2827: ldc_w 432
    //   2830: iconst_2
    //   2831: anewarray 4	java/lang/Object
    //   2834: dup
    //   2835: iconst_0
    //   2836: iload_2
    //   2837: invokestatic 256	java/lang/Integer:valueOf	(I)Ljava/lang/Integer;
    //   2840: aastore
    //   2841: dup
    //   2842: iconst_1
    //   2843: aload_1
    //   2844: getfield 154	com/tencent/mm/plugin/appbrand/m/e:mUrl	Ljava/lang/String;
    //   2847: aastore
    //   2848: invokestatic 195	com/tencent/mm/sdk/platformtools/ab:i	(Ljava/lang/String;Ljava/lang/String;[Ljava/lang/Object;)V
    //   2851: iload_2
    //   2852: sipush 200
    //   2855: if_icmpeq +976 -> 3831
    //   2858: aload 40
    //   2860: astore 31
    //   2862: aload 41
    //   2864: astore 38
    //   2866: aload 42
    //   2868: astore 30
    //   2870: aload 43
    //   2872: astore 32
    //   2874: aload 44
    //   2876: astore 33
    //   2878: aload 45
    //   2880: astore 34
    //   2882: aload 46
    //   2884: astore 35
    //   2886: aload 47
    //   2888: astore 36
    //   2890: aload 48
    //   2892: astore 37
    //   2894: ldc 50
    //   2896: ldc_w 434
    //   2899: iconst_2
    //   2900: anewarray 4	java/lang/Object
    //   2903: dup
    //   2904: iconst_0
    //   2905: aload_1
    //   2906: getfield 154	com/tencent/mm/plugin/appbrand/m/e:mUrl	Ljava/lang/String;
    //   2909: aastore
    //   2910: dup
    //   2911: iconst_1
    //   2912: iload_2
    //   2913: invokestatic 256	java/lang/Integer:valueOf	(I)Ljava/lang/Integer;
    //   2916: aastore
    //   2917: invokestatic 230	com/tencent/mm/sdk/platformtools/ab:e	(Ljava/lang/String;Ljava/lang/String;[Ljava/lang/Object;)V
    //   2920: aload 40
    //   2922: astore 31
    //   2924: aload 41
    //   2926: astore 38
    //   2928: aload 42
    //   2930: astore 30
    //   2932: aload 43
    //   2934: astore 32
    //   2936: aload 44
    //   2938: astore 33
    //   2940: aload 45
    //   2942: astore 34
    //   2944: aload 46
    //   2946: astore 35
    //   2948: aload 47
    //   2950: astore 36
    //   2952: aload 48
    //   2954: astore 37
    //   2956: iload_2
    //   2957: invokestatic 438	com/tencent/mm/plugin/appbrand/m/j:oX	(I)Z
    //   2960: ifeq +814 -> 3774
    //   2963: aload 40
    //   2965: astore 31
    //   2967: aload 41
    //   2969: astore 38
    //   2971: aload 42
    //   2973: astore 30
    //   2975: aload 43
    //   2977: astore 32
    //   2979: aload 44
    //   2981: astore 33
    //   2983: aload 45
    //   2985: astore 34
    //   2987: aload 46
    //   2989: astore 35
    //   2991: aload 47
    //   2993: astore 36
    //   2995: aload 48
    //   2997: astore 37
    //   2999: aload 28
    //   3001: invokestatic 442	com/tencent/mm/plugin/appbrand/m/j:d	(Ljava/net/HttpURLConnection;)Ljava/lang/String;
    //   3004: astore 27
    //   3006: aload 40
    //   3008: astore 31
    //   3010: aload 41
    //   3012: astore 38
    //   3014: aload 42
    //   3016: astore 30
    //   3018: aload 43
    //   3020: astore 32
    //   3022: aload 44
    //   3024: astore 33
    //   3026: aload 45
    //   3028: astore 34
    //   3030: aload 46
    //   3032: astore 35
    //   3034: aload 47
    //   3036: astore 36
    //   3038: aload 48
    //   3040: astore 37
    //   3042: aload_1
    //   3043: getfield 445	com/tencent/mm/plugin/appbrand/m/e:isV	I
    //   3046: istore_3
    //   3047: aload 40
    //   3049: astore 31
    //   3051: aload 41
    //   3053: astore 38
    //   3055: aload 42
    //   3057: astore 30
    //   3059: aload 43
    //   3061: astore 32
    //   3063: aload 44
    //   3065: astore 33
    //   3067: aload 45
    //   3069: astore 34
    //   3071: aload 46
    //   3073: astore 35
    //   3075: aload 47
    //   3077: astore 36
    //   3079: aload 48
    //   3081: astore 37
    //   3083: aload 27
    //   3085: invokestatic 451	android/text/TextUtils:isEmpty	(Ljava/lang/CharSequence;)Z
    //   3088: ifne +686 -> 3774
    //   3091: iload_3
    //   3092: ifgt +289 -> 3381
    //   3095: aload 40
    //   3097: astore 31
    //   3099: aload 41
    //   3101: astore 38
    //   3103: aload 42
    //   3105: astore 30
    //   3107: aload 43
    //   3109: astore 32
    //   3111: aload 44
    //   3113: astore 33
    //   3115: aload 45
    //   3117: astore 34
    //   3119: aload 46
    //   3121: astore 35
    //   3123: aload 47
    //   3125: astore 36
    //   3127: aload 48
    //   3129: astore 37
    //   3131: ldc 50
    //   3133: ldc_w 453
    //   3136: iconst_1
    //   3137: anewarray 4	java/lang/Object
    //   3140: dup
    //   3141: iconst_0
    //   3142: bipush 15
    //   3144: invokestatic 256	java/lang/Integer:valueOf	(I)Ljava/lang/Integer;
    //   3147: aastore
    //   3148: invokestatic 456	com/tencent/mm/sdk/platformtools/ab:w	(Ljava/lang/String;Ljava/lang/String;[Ljava/lang/Object;)V
    //   3151: aload 40
    //   3153: astore 31
    //   3155: aload 41
    //   3157: astore 38
    //   3159: aload 42
    //   3161: astore 30
    //   3163: aload 43
    //   3165: astore 32
    //   3167: aload 44
    //   3169: astore 33
    //   3171: aload 45
    //   3173: astore 34
    //   3175: aload 46
    //   3177: astore 35
    //   3179: aload 47
    //   3181: astore 36
    //   3183: aload 48
    //   3185: astore 37
    //   3187: aload_0
    //   3188: aload 59
    //   3190: ldc_w 458
    //   3193: ldc_w 460
    //   3196: iload_2
    //   3197: aload 49
    //   3199: aload_1
    //   3200: getfield 163	com/tencent/mm/plugin/appbrand/m/e:hwp	Ljava/lang/String;
    //   3203: aload 28
    //   3205: invokespecial 462	com/tencent/mm/plugin/appbrand/m/d:a	(Lcom/tencent/mm/plugin/appbrand/m/d$a;Ljava/lang/String;Ljava/lang/Object;ILorg/json/JSONObject;Ljava/lang/String;Ljava/net/HttpURLConnection;)V
    //   3208: ldc 167
    //   3210: invokestatic 173	com/tencent/luggage/a/e:r	(Ljava/lang/Class;)Lcom/tencent/luggage/a/d;
    //   3213: checkcast 167	com/tencent/mm/plugin/appbrand/m/o
    //   3216: aload_0
    //   3217: getfield 40	com/tencent/mm/plugin/appbrand/m/d:hrA	Lcom/tencent/mm/plugin/appbrand/jsapi/c;
    //   3220: invokeinterface 177 1 0
    //   3225: aload_1
    //   3226: getfield 180	com/tencent/mm/plugin/appbrand/m/e:isY	Ljava/lang/String;
    //   3229: aload_1
    //   3230: getfield 183	com/tencent/mm/plugin/appbrand/m/e:bxW	Ljava/lang/String;
    //   3233: aload_1
    //   3234: getfield 154	com/tencent/mm/plugin/appbrand/m/e:mUrl	Ljava/lang/String;
    //   3237: aload_1
    //   3238: invokevirtual 234	com/tencent/mm/plugin/appbrand/m/e:getDataSize	()J
    //   3241: lconst_0
    //   3242: iload_2
    //   3243: iconst_1
    //   3244: aload_1
    //   3245: invokevirtual 187	com/tencent/mm/plugin/appbrand/m/e:aIj	()I
    //   3248: invokeinterface 190 12 0
    //   3253: aload 29
    //   3255: ifnull +8 -> 3263
    //   3258: aload 29
    //   3260: invokevirtual 377	java/io/DataOutputStream:close	()V
    //   3263: aload_0
    //   3264: getfield 38	com/tencent/mm/plugin/appbrand/m/d:isA	Ljava/util/ArrayList;
    //   3267: aload_1
    //   3268: getfield 163	com/tencent/mm/plugin/appbrand/m/e:hwp	Ljava/lang/String;
    //   3271: invokevirtual 260	java/util/ArrayList:remove	(Ljava/lang/Object;)Z
    //   3274: pop
    //   3275: ldc 138
    //   3277: invokestatic 65	com/tencent/matrix/trace/core/AppMethodBeat:o	(I)V
    //   3280: return
    //   3281: aload 28
    //   3283: astore 29
    //   3285: aload 28
    //   3287: astore 30
    //   3289: aload 28
    //   3291: astore 31
    //   3293: aload 28
    //   3295: astore 32
    //   3297: aload 28
    //   3299: astore 33
    //   3301: aload 28
    //   3303: astore 34
    //   3305: aload 28
    //   3307: astore 35
    //   3309: aload 28
    //   3311: astore 36
    //   3313: aload 28
    //   3315: astore 37
    //   3317: aload 28
    //   3319: invokestatic 406	com/tencent/mm/plugin/appbrand/m/j:g	(Ljava/net/HttpURLConnection;)Lorg/json/JSONObject;
    //   3322: astore 27
    //   3324: aload 27
    //   3326: astore 31
    //   3328: aconst_null
    //   3329: astore 29
    //   3331: goto -677 -> 2654
    //   3334: astore 27
    //   3336: iload 23
    //   3338: istore_2
    //   3339: iload 22
    //   3341: istore_3
    //   3342: aload 29
    //   3344: astore 27
    //   3346: aload 56
    //   3348: astore 30
    //   3350: aload 28
    //   3352: invokevirtual 427	java/net/HttpURLConnection:getResponseCode	()I
    //   3355: istore 22
    //   3357: iload 22
    //   3359: istore_2
    //   3360: goto -659 -> 2701
    //   3363: astore 27
    //   3365: ldc 50
    //   3367: aload 27
    //   3369: ldc 60
    //   3371: iconst_0
    //   3372: anewarray 4	java/lang/Object
    //   3375: invokestatic 367	com/tencent/mm/sdk/platformtools/ab:printErrStackTrace	(Ljava/lang/String;Ljava/lang/Throwable;Ljava/lang/String;[Ljava/lang/Object;)V
    //   3378: goto -115 -> 3263
    //   3381: aload 40
    //   3383: astore 31
    //   3385: aload 41
    //   3387: astore 38
    //   3389: aload 42
    //   3391: astore 30
    //   3393: aload 43
    //   3395: astore 32
    //   3397: aload 44
    //   3399: astore 33
    //   3401: aload 45
    //   3403: astore 34
    //   3405: aload 46
    //   3407: astore 35
    //   3409: aload 47
    //   3411: astore 36
    //   3413: aload 48
    //   3415: astore 37
    //   3417: ldc 50
    //   3419: ldc_w 464
    //   3422: iconst_3
    //   3423: anewarray 4	java/lang/Object
    //   3426: dup
    //   3427: iconst_0
    //   3428: iload_3
    //   3429: invokestatic 256	java/lang/Integer:valueOf	(I)Ljava/lang/Integer;
    //   3432: aastore
    //   3433: dup
    //   3434: iconst_1
    //   3435: aload_1
    //   3436: getfield 154	com/tencent/mm/plugin/appbrand/m/e:mUrl	Ljava/lang/String;
    //   3439: aastore
    //   3440: dup
    //   3441: iconst_2
    //   3442: aload 27
    //   3444: aastore
    //   3445: invokestatic 195	com/tencent/mm/sdk/platformtools/ab:i	(Ljava/lang/String;Ljava/lang/String;[Ljava/lang/Object;)V
    //   3448: aload 40
    //   3450: astore 31
    //   3452: aload 41
    //   3454: astore 38
    //   3456: aload 42
    //   3458: astore 30
    //   3460: aload 43
    //   3462: astore 32
    //   3464: aload 44
    //   3466: astore 33
    //   3468: aload 45
    //   3470: astore 34
    //   3472: aload 46
    //   3474: astore 35
    //   3476: aload 47
    //   3478: astore 36
    //   3480: aload 48
    //   3482: astore 37
    //   3484: aload_1
    //   3485: aload 27
    //   3487: putfield 154	com/tencent/mm/plugin/appbrand/m/e:mUrl	Ljava/lang/String;
    //   3490: aload 40
    //   3492: astore 31
    //   3494: aload 41
    //   3496: astore 38
    //   3498: aload 42
    //   3500: astore 30
    //   3502: aload 43
    //   3504: astore 32
    //   3506: aload 44
    //   3508: astore 33
    //   3510: aload 45
    //   3512: astore 34
    //   3514: aload 46
    //   3516: astore 35
    //   3518: aload 47
    //   3520: astore 36
    //   3522: aload 48
    //   3524: astore 37
    //   3526: aload_1
    //   3527: iload_3
    //   3528: iconst_1
    //   3529: isub
    //   3530: putfield 445	com/tencent/mm/plugin/appbrand/m/e:isV	I
    //   3533: aload 40
    //   3535: astore 31
    //   3537: aload 41
    //   3539: astore 38
    //   3541: aload 42
    //   3543: astore 30
    //   3545: aload 43
    //   3547: astore 32
    //   3549: aload 44
    //   3551: astore 33
    //   3553: aload 45
    //   3555: astore 34
    //   3557: aload 46
    //   3559: astore 35
    //   3561: aload 47
    //   3563: astore 36
    //   3565: aload 48
    //   3567: astore 37
    //   3569: ldc 50
    //   3571: ldc_w 466
    //   3574: iconst_1
    //   3575: anewarray 4	java/lang/Object
    //   3578: dup
    //   3579: iconst_0
    //   3580: aload_1
    //   3581: getfield 445	com/tencent/mm/plugin/appbrand/m/e:isV	I
    //   3584: invokestatic 256	java/lang/Integer:valueOf	(I)Ljava/lang/Integer;
    //   3587: aastore
    //   3588: invokestatic 195	com/tencent/mm/sdk/platformtools/ab:i	(Ljava/lang/String;Ljava/lang/String;[Ljava/lang/Object;)V
    //   3591: aload 40
    //   3593: astore 31
    //   3595: aload 41
    //   3597: astore 38
    //   3599: aload 42
    //   3601: astore 30
    //   3603: aload 43
    //   3605: astore 32
    //   3607: aload 44
    //   3609: astore 33
    //   3611: aload 45
    //   3613: astore 34
    //   3615: aload 46
    //   3617: astore 35
    //   3619: aload 47
    //   3621: astore 36
    //   3623: aload 48
    //   3625: astore 37
    //   3627: aload_0
    //   3628: aload_1
    //   3629: invokespecial 115	com/tencent/mm/plugin/appbrand/m/d:a	(Lcom/tencent/mm/plugin/appbrand/m/e;)V
    //   3632: ldc 167
    //   3634: invokestatic 173	com/tencent/luggage/a/e:r	(Ljava/lang/Class;)Lcom/tencent/luggage/a/d;
    //   3637: checkcast 167	com/tencent/mm/plugin/appbrand/m/o
    //   3640: aload_0
    //   3641: getfield 40	com/tencent/mm/plugin/appbrand/m/d:hrA	Lcom/tencent/mm/plugin/appbrand/jsapi/c;
    //   3644: invokeinterface 177 1 0
    //   3649: aload_1
    //   3650: getfield 180	com/tencent/mm/plugin/appbrand/m/e:isY	Ljava/lang/String;
    //   3653: aload_1
    //   3654: getfield 183	com/tencent/mm/plugin/appbrand/m/e:bxW	Ljava/lang/String;
    //   3657: aload_1
    //   3658: getfield 154	com/tencent/mm/plugin/appbrand/m/e:mUrl	Ljava/lang/String;
    //   3661: aload_1
    //   3662: invokevirtual 234	com/tencent/mm/plugin/appbrand/m/e:getDataSize	()J
    //   3665: lconst_0
    //   3666: iload_2
    //   3667: iconst_2
    //   3668: aload_1
    //   3669: invokevirtual 187	com/tencent/mm/plugin/appbrand/m/e:aIj	()I
    //   3672: invokeinterface 190 12 0
    //   3677: invokestatic 240	com/tencent/mm/sdk/platformtools/ah:getContext	()Landroid/content/Context;
    //   3680: invokestatic 246	com/tencent/mm/sdk/platformtools/at:getNetType	(Landroid/content/Context;)I
    //   3683: istore_2
    //   3684: iload_2
    //   3685: iconst_m1
    //   3686: if_icmpne +24 -> 3710
    //   3689: ldc 197
    //   3691: invokestatic 173	com/tencent/luggage/a/e:r	(Ljava/lang/Class;)Lcom/tencent/luggage/a/d;
    //   3694: checkcast 197	com/tencent/mm/plugin/appbrand/o/a
    //   3697: ldc2_w 198
    //   3700: ldc2_w 247
    //   3703: lconst_1
    //   3704: iconst_0
    //   3705: invokeinterface 203 8 0
    //   3710: ldc 50
    //   3712: ldc 250
    //   3714: iconst_1
    //   3715: anewarray 4	java/lang/Object
    //   3718: dup
    //   3719: iconst_0
    //   3720: iload_2
    //   3721: invokestatic 256	java/lang/Integer:valueOf	(I)Ljava/lang/Integer;
    //   3724: aastore
    //   3725: invokestatic 195	com/tencent/mm/sdk/platformtools/ab:i	(Ljava/lang/String;Ljava/lang/String;[Ljava/lang/Object;)V
    //   3728: aload 29
    //   3730: ifnull +8 -> 3738
    //   3733: aload 29
    //   3735: invokevirtual 377	java/io/DataOutputStream:close	()V
    //   3738: aload_0
    //   3739: getfield 38	com/tencent/mm/plugin/appbrand/m/d:isA	Ljava/util/ArrayList;
    //   3742: aload_1
    //   3743: getfield 163	com/tencent/mm/plugin/appbrand/m/e:hwp	Ljava/lang/String;
    //   3746: invokevirtual 260	java/util/ArrayList:remove	(Ljava/lang/Object;)Z
    //   3749: pop
    //   3750: ldc 138
    //   3752: invokestatic 65	com/tencent/matrix/trace/core/AppMethodBeat:o	(I)V
    //   3755: return
    //   3756: astore 27
    //   3758: ldc 50
    //   3760: aload 27
    //   3762: ldc 60
    //   3764: iconst_0
    //   3765: anewarray 4	java/lang/Object
    //   3768: invokestatic 367	com/tencent/mm/sdk/platformtools/ab:printErrStackTrace	(Ljava/lang/String;Ljava/lang/Throwable;Ljava/lang/String;[Ljava/lang/Object;)V
    //   3771: goto -33 -> 3738
    //   3774: aload 40
    //   3776: astore 31
    //   3778: aload 41
    //   3780: astore 38
    //   3782: aload 42
    //   3784: astore 30
    //   3786: aload 43
    //   3788: astore 32
    //   3790: aload 44
    //   3792: astore 33
    //   3794: aload 45
    //   3796: astore 34
    //   3798: aload 46
    //   3800: astore 35
    //   3802: aload 47
    //   3804: astore 36
    //   3806: aload 48
    //   3808: astore 37
    //   3810: ldc 197
    //   3812: invokestatic 173	com/tencent/luggage/a/e:r	(Ljava/lang/Class;)Lcom/tencent/luggage/a/d;
    //   3815: checkcast 197	com/tencent/mm/plugin/appbrand/o/a
    //   3818: ldc2_w 198
    //   3821: ldc2_w 467
    //   3824: lconst_1
    //   3825: iconst_0
    //   3826: invokeinterface 203 8 0
    //   3831: aload 40
    //   3833: astore 31
    //   3835: aload 41
    //   3837: astore 38
    //   3839: aload 42
    //   3841: astore 30
    //   3843: aload 43
    //   3845: astore 32
    //   3847: aload 44
    //   3849: astore 33
    //   3851: aload 45
    //   3853: astore 34
    //   3855: aload 46
    //   3857: astore 35
    //   3859: aload 47
    //   3861: astore 36
    //   3863: aload 48
    //   3865: astore 37
    //   3867: new 470	java/io/ByteArrayOutputStream
    //   3870: dup
    //   3871: invokespecial 471	java/io/ByteArrayOutputStream:<init>	()V
    //   3874: astore 50
    //   3876: aload 40
    //   3878: astore 31
    //   3880: aload 42
    //   3882: astore 30
    //   3884: aload 43
    //   3886: astore 32
    //   3888: aload 44
    //   3890: astore 33
    //   3892: aload 45
    //   3894: astore 34
    //   3896: aload 46
    //   3898: astore 35
    //   3900: aload 47
    //   3902: astore 36
    //   3904: aload 48
    //   3906: astore 37
    //   3908: ldc_w 327
    //   3911: aload 28
    //   3913: invokevirtual 474	java/net/HttpURLConnection:getContentEncoding	()Ljava/lang/String;
    //   3916: invokevirtual 477	java/lang/String:equals	(Ljava/lang/Object;)Z
    //   3919: ifeq +428 -> 4347
    //   3922: aload 40
    //   3924: astore 31
    //   3926: aload 42
    //   3928: astore 30
    //   3930: aload 43
    //   3932: astore 32
    //   3934: aload 44
    //   3936: astore 33
    //   3938: aload 45
    //   3940: astore 34
    //   3942: aload 46
    //   3944: astore 35
    //   3946: aload 47
    //   3948: astore 36
    //   3950: aload 48
    //   3952: astore 37
    //   3954: new 479	java/util/zip/GZIPInputStream
    //   3957: dup
    //   3958: aload 28
    //   3960: invokevirtual 483	java/net/HttpURLConnection:getInputStream	()Ljava/io/InputStream;
    //   3963: invokespecial 486	java/util/zip/GZIPInputStream:<init>	(Ljava/io/InputStream;)V
    //   3966: astore 27
    //   3968: aconst_null
    //   3969: astore 30
    //   3971: aload 27
    //   3973: ifnull +4993 -> 8966
    //   3976: aload 27
    //   3978: astore 31
    //   3980: aload 27
    //   3982: astore 38
    //   3984: aload 27
    //   3986: astore 30
    //   3988: aload 27
    //   3990: astore 32
    //   3992: aload 27
    //   3994: astore 33
    //   3996: aload 27
    //   3998: astore 34
    //   4000: aload 27
    //   4002: astore 35
    //   4004: aload 27
    //   4006: astore 36
    //   4008: aload 27
    //   4010: astore 37
    //   4012: getstatic 313	android/os/Build$VERSION:SDK_INT	I
    //   4015: bipush 24
    //   4017: if_icmplt +642 -> 4659
    //   4020: aload 27
    //   4022: astore 31
    //   4024: aload 27
    //   4026: astore 38
    //   4028: aload 27
    //   4030: astore 30
    //   4032: aload 27
    //   4034: astore 32
    //   4036: aload 27
    //   4038: astore 33
    //   4040: aload 27
    //   4042: astore 34
    //   4044: aload 27
    //   4046: astore 35
    //   4048: aload 27
    //   4050: astore 36
    //   4052: aload 27
    //   4054: astore 37
    //   4056: aload 28
    //   4058: invokevirtual 489	java/net/HttpURLConnection:getContentLengthLong	()J
    //   4061: lstore 25
    //   4063: aload 27
    //   4065: astore 31
    //   4067: aload 27
    //   4069: astore 38
    //   4071: aload 27
    //   4073: astore 30
    //   4075: aload 27
    //   4077: astore 32
    //   4079: aload 27
    //   4081: astore 33
    //   4083: aload 27
    //   4085: astore 34
    //   4087: aload 27
    //   4089: astore 35
    //   4091: aload 27
    //   4093: astore 36
    //   4095: aload 27
    //   4097: astore 37
    //   4099: ldc 50
    //   4101: ldc_w 491
    //   4104: iconst_1
    //   4105: anewarray 4	java/lang/Object
    //   4108: dup
    //   4109: iconst_0
    //   4110: lload 25
    //   4112: invokestatic 496	java/lang/Long:valueOf	(J)Ljava/lang/Long;
    //   4115: aastore
    //   4116: invokestatic 498	com/tencent/mm/sdk/platformtools/ab:d	(Ljava/lang/String;Ljava/lang/String;[Ljava/lang/Object;)V
    //   4119: aload 27
    //   4121: astore 31
    //   4123: aload 27
    //   4125: astore 38
    //   4127: aload 27
    //   4129: astore 30
    //   4131: aload 27
    //   4133: astore 32
    //   4135: aload 27
    //   4137: astore 33
    //   4139: aload 27
    //   4141: astore 34
    //   4143: aload 27
    //   4145: astore 35
    //   4147: aload 27
    //   4149: astore 36
    //   4151: aload 27
    //   4153: astore 37
    //   4155: lload 25
    //   4157: iconst_1
    //   4158: invokestatic 501	com/tencent/mm/plugin/appbrand/m/j:g	(JI)I
    //   4161: newarray byte
    //   4163: astore 39
    //   4165: iconst_0
    //   4166: istore_3
    //   4167: aload 27
    //   4169: aload 39
    //   4171: invokevirtual 505	java/io/InputStream:read	([B)I
    //   4174: istore 4
    //   4176: iload 4
    //   4178: iconst_m1
    //   4179: if_icmpeq +619 -> 4798
    //   4182: aload_0
    //   4183: getfield 40	com/tencent/mm/plugin/appbrand/m/d:hrA	Lcom/tencent/mm/plugin/appbrand/jsapi/c;
    //   4186: invokestatic 509	com/tencent/mm/plugin/appbrand/m/j:A	(Lcom/tencent/mm/plugin/appbrand/jsapi/c;)Z
    //   4189: ifeq +591 -> 4780
    //   4192: aload_0
    //   4193: aload 59
    //   4195: ldc_w 511
    //   4198: aload_1
    //   4199: getfield 163	com/tencent/mm/plugin/appbrand/m/e:hwp	Ljava/lang/String;
    //   4202: aload 28
    //   4204: invokespecial 165	com/tencent/mm/plugin/appbrand/m/d:a	(Lcom/tencent/mm/plugin/appbrand/m/d$a;Ljava/lang/String;Ljava/lang/String;Ljava/net/HttpURLConnection;)V
    //   4207: aload 27
    //   4209: invokevirtual 374	java/io/InputStream:close	()V
    //   4212: ldc 167
    //   4214: invokestatic 173	com/tencent/luggage/a/e:r	(Ljava/lang/Class;)Lcom/tencent/luggage/a/d;
    //   4217: checkcast 167	com/tencent/mm/plugin/appbrand/m/o
    //   4220: aload_0
    //   4221: getfield 40	com/tencent/mm/plugin/appbrand/m/d:hrA	Lcom/tencent/mm/plugin/appbrand/jsapi/c;
    //   4224: invokeinterface 177 1 0
    //   4229: aload_1
    //   4230: getfield 180	com/tencent/mm/plugin/appbrand/m/e:isY	Ljava/lang/String;
    //   4233: aload_1
    //   4234: getfield 183	com/tencent/mm/plugin/appbrand/m/e:bxW	Ljava/lang/String;
    //   4237: aload_1
    //   4238: getfield 154	com/tencent/mm/plugin/appbrand/m/e:mUrl	Ljava/lang/String;
    //   4241: aload_1
    //   4242: invokevirtual 234	com/tencent/mm/plugin/appbrand/m/e:getDataSize	()J
    //   4245: iload_3
    //   4246: i2l
    //   4247: iload_2
    //   4248: iconst_2
    //   4249: aload_1
    //   4250: invokevirtual 187	com/tencent/mm/plugin/appbrand/m/e:aIj	()I
    //   4253: invokeinterface 190 12 0
    //   4258: invokestatic 240	com/tencent/mm/sdk/platformtools/ah:getContext	()Landroid/content/Context;
    //   4261: invokestatic 246	com/tencent/mm/sdk/platformtools/at:getNetType	(Landroid/content/Context;)I
    //   4264: istore_2
    //   4265: iload_2
    //   4266: iconst_m1
    //   4267: if_icmpne +24 -> 4291
    //   4270: ldc 197
    //   4272: invokestatic 173	com/tencent/luggage/a/e:r	(Ljava/lang/Class;)Lcom/tencent/luggage/a/d;
    //   4275: checkcast 197	com/tencent/mm/plugin/appbrand/o/a
    //   4278: ldc2_w 198
    //   4281: ldc2_w 247
    //   4284: lconst_1
    //   4285: iconst_0
    //   4286: invokeinterface 203 8 0
    //   4291: ldc 50
    //   4293: ldc 250
    //   4295: iconst_1
    //   4296: anewarray 4	java/lang/Object
    //   4299: dup
    //   4300: iconst_0
    //   4301: iload_2
    //   4302: invokestatic 256	java/lang/Integer:valueOf	(I)Ljava/lang/Integer;
    //   4305: aastore
    //   4306: invokestatic 195	com/tencent/mm/sdk/platformtools/ab:i	(Ljava/lang/String;Ljava/lang/String;[Ljava/lang/Object;)V
    //   4309: aload 27
    //   4311: ifnull +8 -> 4319
    //   4314: aload 27
    //   4316: invokevirtual 374	java/io/InputStream:close	()V
    //   4319: aload 29
    //   4321: ifnull +8 -> 4329
    //   4324: aload 29
    //   4326: invokevirtual 377	java/io/DataOutputStream:close	()V
    //   4329: aload_0
    //   4330: getfield 38	com/tencent/mm/plugin/appbrand/m/d:isA	Ljava/util/ArrayList;
    //   4333: aload_1
    //   4334: getfield 163	com/tencent/mm/plugin/appbrand/m/e:hwp	Ljava/lang/String;
    //   4337: invokevirtual 260	java/util/ArrayList:remove	(Ljava/lang/Object;)Z
    //   4340: pop
    //   4341: ldc 138
    //   4343: invokestatic 65	com/tencent/matrix/trace/core/AppMethodBeat:o	(I)V
    //   4346: return
    //   4347: aload 40
    //   4349: astore 31
    //   4351: aload 42
    //   4353: astore 30
    //   4355: aload 43
    //   4357: astore 32
    //   4359: aload 44
    //   4361: astore 33
    //   4363: aload 45
    //   4365: astore 34
    //   4367: aload 46
    //   4369: astore 35
    //   4371: aload 47
    //   4373: astore 36
    //   4375: aload 48
    //   4377: astore 37
    //   4379: aload 28
    //   4381: invokevirtual 483	java/net/HttpURLConnection:getInputStream	()Ljava/io/InputStream;
    //   4384: astore 27
    //   4386: goto -418 -> 3968
    //   4389: astore 27
    //   4391: aload 40
    //   4393: astore 31
    //   4395: aload 41
    //   4397: astore 38
    //   4399: aload 42
    //   4401: astore 30
    //   4403: aload 43
    //   4405: astore 32
    //   4407: aload 44
    //   4409: astore 33
    //   4411: aload 45
    //   4413: astore 34
    //   4415: aload 46
    //   4417: astore 35
    //   4419: aload 47
    //   4421: astore 36
    //   4423: aload 48
    //   4425: astore 37
    //   4427: ldc 50
    //   4429: ldc_w 513
    //   4432: iconst_1
    //   4433: anewarray 4	java/lang/Object
    //   4436: dup
    //   4437: iconst_0
    //   4438: aload 27
    //   4440: invokevirtual 515	java/lang/Exception:toString	()Ljava/lang/String;
    //   4443: aastore
    //   4444: invokestatic 230	com/tencent/mm/sdk/platformtools/ab:e	(Ljava/lang/String;Ljava/lang/String;[Ljava/lang/Object;)V
    //   4447: aload 40
    //   4449: astore 31
    //   4451: aload 42
    //   4453: astore 30
    //   4455: aload 43
    //   4457: astore 32
    //   4459: aload 44
    //   4461: astore 33
    //   4463: aload 45
    //   4465: astore 34
    //   4467: aload 46
    //   4469: astore 35
    //   4471: aload 47
    //   4473: astore 36
    //   4475: aload 48
    //   4477: astore 37
    //   4479: ldc_w 327
    //   4482: aload 28
    //   4484: invokevirtual 474	java/net/HttpURLConnection:getContentEncoding	()Ljava/lang/String;
    //   4487: invokevirtual 477	java/lang/String:equals	(Ljava/lang/Object;)Z
    //   4490: ifeq +52 -> 4542
    //   4493: aload 40
    //   4495: astore 31
    //   4497: aload 42
    //   4499: astore 30
    //   4501: aload 43
    //   4503: astore 32
    //   4505: aload 44
    //   4507: astore 33
    //   4509: aload 45
    //   4511: astore 34
    //   4513: aload 46
    //   4515: astore 35
    //   4517: aload 47
    //   4519: astore 36
    //   4521: aload 48
    //   4523: astore 37
    //   4525: new 479	java/util/zip/GZIPInputStream
    //   4528: dup
    //   4529: aload 28
    //   4531: invokevirtual 518	java/net/HttpURLConnection:getErrorStream	()Ljava/io/InputStream;
    //   4534: invokespecial 486	java/util/zip/GZIPInputStream:<init>	(Ljava/io/InputStream;)V
    //   4537: astore 27
    //   4539: goto -571 -> 3968
    //   4542: aload 40
    //   4544: astore 31
    //   4546: aload 42
    //   4548: astore 30
    //   4550: aload 43
    //   4552: astore 32
    //   4554: aload 44
    //   4556: astore 33
    //   4558: aload 45
    //   4560: astore 34
    //   4562: aload 46
    //   4564: astore 35
    //   4566: aload 47
    //   4568: astore 36
    //   4570: aload 48
    //   4572: astore 37
    //   4574: aload 28
    //   4576: invokevirtual 518	java/net/HttpURLConnection:getErrorStream	()Ljava/io/InputStream;
    //   4579: astore 27
    //   4581: goto -613 -> 3968
    //   4584: astore 27
    //   4586: aload 40
    //   4588: astore 31
    //   4590: aload 41
    //   4592: astore 38
    //   4594: aload 42
    //   4596: astore 30
    //   4598: aload 43
    //   4600: astore 32
    //   4602: aload 44
    //   4604: astore 33
    //   4606: aload 45
    //   4608: astore 34
    //   4610: aload 46
    //   4612: astore 35
    //   4614: aload 47
    //   4616: astore 36
    //   4618: aload 48
    //   4620: astore 37
    //   4622: ldc 50
    //   4624: aload 27
    //   4626: ldc_w 520
    //   4629: iconst_0
    //   4630: anewarray 4	java/lang/Object
    //   4633: invokestatic 367	com/tencent/mm/sdk/platformtools/ab:printErrStackTrace	(Ljava/lang/String;Ljava/lang/Throwable;Ljava/lang/String;[Ljava/lang/Object;)V
    //   4636: aload 39
    //   4638: astore 27
    //   4640: goto -672 -> 3968
    //   4643: astore 30
    //   4645: iload_2
    //   4646: istore_3
    //   4647: iconst_0
    //   4648: istore_2
    //   4649: aload 29
    //   4651: astore 27
    //   4653: aconst_null
    //   4654: astore 29
    //   4656: goto -2845 -> 1811
    //   4659: aload 27
    //   4661: astore 31
    //   4663: aload 27
    //   4665: astore 38
    //   4667: aload 27
    //   4669: astore 30
    //   4671: aload 27
    //   4673: astore 32
    //   4675: aload 27
    //   4677: astore 33
    //   4679: aload 27
    //   4681: astore 34
    //   4683: aload 27
    //   4685: astore 35
    //   4687: aload 27
    //   4689: astore 36
    //   4691: aload 27
    //   4693: astore 37
    //   4695: aload 28
    //   4697: invokevirtual 523	java/net/HttpURLConnection:getContentLength	()I
    //   4700: istore_3
    //   4701: iload_3
    //   4702: i2l
    //   4703: lstore 25
    //   4705: goto -642 -> 4063
    //   4708: astore 27
    //   4710: ldc 50
    //   4712: aload 27
    //   4714: ldc 60
    //   4716: iconst_0
    //   4717: anewarray 4	java/lang/Object
    //   4720: invokestatic 367	com/tencent/mm/sdk/platformtools/ab:printErrStackTrace	(Ljava/lang/String;Ljava/lang/Throwable;Ljava/lang/String;[Ljava/lang/Object;)V
    //   4723: goto -404 -> 4319
    //   4726: astore 27
    //   4728: ldc 50
    //   4730: aload 27
    //   4732: ldc 60
    //   4734: iconst_0
    //   4735: anewarray 4	java/lang/Object
    //   4738: invokestatic 367	com/tencent/mm/sdk/platformtools/ab:printErrStackTrace	(Ljava/lang/String;Ljava/lang/Throwable;Ljava/lang/String;[Ljava/lang/Object;)V
    //   4741: goto -422 -> 4319
    //   4744: astore 27
    //   4746: ldc 50
    //   4748: aload 27
    //   4750: ldc 60
    //   4752: iconst_0
    //   4753: anewarray 4	java/lang/Object
    //   4756: invokestatic 367	com/tencent/mm/sdk/platformtools/ab:printErrStackTrace	(Ljava/lang/String;Ljava/lang/Throwable;Ljava/lang/String;[Ljava/lang/Object;)V
    //   4759: goto -440 -> 4319
    //   4762: astore 27
    //   4764: ldc 50
    //   4766: aload 27
    //   4768: ldc 60
    //   4770: iconst_0
    //   4771: anewarray 4	java/lang/Object
    //   4774: invokestatic 367	com/tencent/mm/sdk/platformtools/ab:printErrStackTrace	(Ljava/lang/String;Ljava/lang/Throwable;Ljava/lang/String;[Ljava/lang/Object;)V
    //   4777: goto -448 -> 4329
    //   4780: aload 50
    //   4782: aload 39
    //   4784: iconst_0
    //   4785: iload 4
    //   4787: invokevirtual 526	java/io/ByteArrayOutputStream:write	([BII)V
    //   4790: iload_3
    //   4791: iload 4
    //   4793: iadd
    //   4794: istore_3
    //   4795: goto -628 -> 4167
    //   4798: aload 50
    //   4800: invokevirtual 527	java/io/ByteArrayOutputStream:flush	()V
    //   4803: aload 27
    //   4805: invokevirtual 374	java/io/InputStream:close	()V
    //   4808: aload 28
    //   4810: invokevirtual 530	java/net/HttpURLConnection:disconnect	()V
    //   4813: ldc_w 532
    //   4816: aload_1
    //   4817: getfield 535	com/tencent/mm/plugin/appbrand/m/e:isW	Ljava/lang/String;
    //   4820: invokevirtual 477	java/lang/String:equals	(Ljava/lang/Object;)Z
    //   4823: ifeq +147 -> 4970
    //   4826: aload 50
    //   4828: invokevirtual 539	java/io/ByteArrayOutputStream:toByteArray	()[B
    //   4831: invokestatic 545	com/tencent/mm/plugin/appbrand/t/q:ak	([B)Ljava/nio/ByteBuffer;
    //   4834: astore 30
    //   4836: ldc 50
    //   4838: ldc_w 547
    //   4841: iconst_2
    //   4842: anewarray 4	java/lang/Object
    //   4845: dup
    //   4846: iconst_0
    //   4847: aload_1
    //   4848: getfield 154	com/tencent/mm/plugin/appbrand/m/e:mUrl	Ljava/lang/String;
    //   4851: aastore
    //   4852: dup
    //   4853: iconst_1
    //   4854: aload 50
    //   4856: invokevirtual 550	java/io/ByteArrayOutputStream:size	()I
    //   4859: invokestatic 256	java/lang/Integer:valueOf	(I)Ljava/lang/Integer;
    //   4862: aastore
    //   4863: invokestatic 552	com/tencent/mm/sdk/platformtools/ab:v	(Ljava/lang/String;Ljava/lang/String;[Ljava/lang/Object;)V
    //   4866: aload_0
    //   4867: aload 59
    //   4869: ldc_w 458
    //   4872: aload 30
    //   4874: iload_2
    //   4875: aload 49
    //   4877: aload_1
    //   4878: getfield 163	com/tencent/mm/plugin/appbrand/m/e:hwp	Ljava/lang/String;
    //   4881: aload 28
    //   4883: invokespecial 462	com/tencent/mm/plugin/appbrand/m/d:a	(Lcom/tencent/mm/plugin/appbrand/m/d$a;Ljava/lang/String;Ljava/lang/Object;ILorg/json/JSONObject;Ljava/lang/String;Ljava/net/HttpURLConnection;)V
    //   4886: ldc 167
    //   4888: invokestatic 173	com/tencent/luggage/a/e:r	(Ljava/lang/Class;)Lcom/tencent/luggage/a/d;
    //   4891: checkcast 167	com/tencent/mm/plugin/appbrand/m/o
    //   4894: aload_0
    //   4895: getfield 40	com/tencent/mm/plugin/appbrand/m/d:hrA	Lcom/tencent/mm/plugin/appbrand/jsapi/c;
    //   4898: invokeinterface 177 1 0
    //   4903: aload_1
    //   4904: getfield 180	com/tencent/mm/plugin/appbrand/m/e:isY	Ljava/lang/String;
    //   4907: aload_1
    //   4908: getfield 183	com/tencent/mm/plugin/appbrand/m/e:bxW	Ljava/lang/String;
    //   4911: aload_1
    //   4912: getfield 154	com/tencent/mm/plugin/appbrand/m/e:mUrl	Ljava/lang/String;
    //   4915: aload_1
    //   4916: invokevirtual 234	com/tencent/mm/plugin/appbrand/m/e:getDataSize	()J
    //   4919: iload_3
    //   4920: i2l
    //   4921: iload_2
    //   4922: iconst_1
    //   4923: aload_1
    //   4924: invokevirtual 187	com/tencent/mm/plugin/appbrand/m/e:aIj	()I
    //   4927: invokeinterface 190 12 0
    //   4932: aload 27
    //   4934: ifnull +8 -> 4942
    //   4937: aload 27
    //   4939: invokevirtual 374	java/io/InputStream:close	()V
    //   4942: aload 29
    //   4944: ifnull +8 -> 4952
    //   4947: aload 29
    //   4949: invokevirtual 377	java/io/DataOutputStream:close	()V
    //   4952: aload_0
    //   4953: getfield 38	com/tencent/mm/plugin/appbrand/m/d:isA	Ljava/util/ArrayList;
    //   4956: aload_1
    //   4957: getfield 163	com/tencent/mm/plugin/appbrand/m/e:hwp	Ljava/lang/String;
    //   4960: invokevirtual 260	java/util/ArrayList:remove	(Ljava/lang/Object;)Z
    //   4963: pop
    //   4964: ldc 138
    //   4966: invokestatic 65	com/tencent/matrix/trace/core/AppMethodBeat:o	(I)V
    //   4969: return
    //   4970: aload 50
    //   4972: ldc_w 554
    //   4975: invokevirtual 556	java/io/ByteArrayOutputStream:toString	(Ljava/lang/String;)Ljava/lang/String;
    //   4978: invokestatic 561	com/tencent/mm/plugin/appbrand/t/r:Fq	(Ljava/lang/String;)Ljava/lang/String;
    //   4981: astore 30
    //   4983: goto -147 -> 4836
    //   4986: astore 27
    //   4988: ldc 50
    //   4990: aload 27
    //   4992: ldc 60
    //   4994: iconst_0
    //   4995: anewarray 4	java/lang/Object
    //   4998: invokestatic 367	com/tencent/mm/sdk/platformtools/ab:printErrStackTrace	(Ljava/lang/String;Ljava/lang/Throwable;Ljava/lang/String;[Ljava/lang/Object;)V
    //   5001: goto -59 -> 4942
    //   5004: astore 27
    //   5006: ldc 50
    //   5008: aload 27
    //   5010: ldc 60
    //   5012: iconst_0
    //   5013: anewarray 4	java/lang/Object
    //   5016: invokestatic 367	com/tencent/mm/sdk/platformtools/ab:printErrStackTrace	(Ljava/lang/String;Ljava/lang/Throwable;Ljava/lang/String;[Ljava/lang/Object;)V
    //   5019: goto -77 -> 4942
    //   5022: astore 27
    //   5024: ldc 50
    //   5026: aload 27
    //   5028: ldc 60
    //   5030: iconst_0
    //   5031: anewarray 4	java/lang/Object
    //   5034: invokestatic 367	com/tencent/mm/sdk/platformtools/ab:printErrStackTrace	(Ljava/lang/String;Ljava/lang/Throwable;Ljava/lang/String;[Ljava/lang/Object;)V
    //   5037: goto -95 -> 4942
    //   5040: astore 27
    //   5042: ldc 50
    //   5044: aload 27
    //   5046: ldc 60
    //   5048: iconst_0
    //   5049: anewarray 4	java/lang/Object
    //   5052: invokestatic 367	com/tencent/mm/sdk/platformtools/ab:printErrStackTrace	(Ljava/lang/String;Ljava/lang/Throwable;Ljava/lang/String;[Ljava/lang/Object;)V
    //   5055: goto -103 -> 4952
    //   5058: astore 28
    //   5060: ldc 50
    //   5062: aload 28
    //   5064: ldc 60
    //   5066: iconst_0
    //   5067: anewarray 4	java/lang/Object
    //   5070: invokestatic 367	com/tencent/mm/sdk/platformtools/ab:printErrStackTrace	(Ljava/lang/String;Ljava/lang/Throwable;Ljava/lang/String;[Ljava/lang/Object;)V
    //   5073: goto -3100 -> 1973
    //   5076: astore 28
    //   5078: ldc 50
    //   5080: aload 28
    //   5082: ldc 60
    //   5084: iconst_0
    //   5085: anewarray 4	java/lang/Object
    //   5088: invokestatic 367	com/tencent/mm/sdk/platformtools/ab:printErrStackTrace	(Ljava/lang/String;Ljava/lang/Throwable;Ljava/lang/String;[Ljava/lang/Object;)V
    //   5091: goto -3118 -> 1973
    //   5094: astore 28
    //   5096: ldc 50
    //   5098: aload 28
    //   5100: ldc 60
    //   5102: iconst_0
    //   5103: anewarray 4	java/lang/Object
    //   5106: invokestatic 367	com/tencent/mm/sdk/platformtools/ab:printErrStackTrace	(Ljava/lang/String;Ljava/lang/Throwable;Ljava/lang/String;[Ljava/lang/Object;)V
    //   5109: goto -3136 -> 1973
    //   5112: astore 27
    //   5114: ldc 50
    //   5116: aload 27
    //   5118: ldc 60
    //   5120: iconst_0
    //   5121: anewarray 4	java/lang/Object
    //   5124: invokestatic 367	com/tencent/mm/sdk/platformtools/ab:printErrStackTrace	(Ljava/lang/String;Ljava/lang/Throwable;Ljava/lang/String;[Ljava/lang/Object;)V
    //   5127: goto -3144 -> 1983
    //   5130: astore 27
    //   5132: ldc 50
    //   5134: aload 27
    //   5136: ldc 60
    //   5138: iconst_0
    //   5139: anewarray 4	java/lang/Object
    //   5142: invokestatic 367	com/tencent/mm/sdk/platformtools/ab:printErrStackTrace	(Ljava/lang/String;Ljava/lang/Throwable;Ljava/lang/String;[Ljava/lang/Object;)V
    //   5145: goto -2871 -> 2274
    //   5148: astore 27
    //   5150: ldc 50
    //   5152: aload 27
    //   5154: ldc 60
    //   5156: iconst_0
    //   5157: anewarray 4	java/lang/Object
    //   5160: invokestatic 367	com/tencent/mm/sdk/platformtools/ab:printErrStackTrace	(Ljava/lang/String;Ljava/lang/Throwable;Ljava/lang/String;[Ljava/lang/Object;)V
    //   5163: goto -2889 -> 2274
    //   5166: astore 27
    //   5168: ldc 50
    //   5170: aload 27
    //   5172: ldc 60
    //   5174: iconst_0
    //   5175: anewarray 4	java/lang/Object
    //   5178: invokestatic 367	com/tencent/mm/sdk/platformtools/ab:printErrStackTrace	(Ljava/lang/String;Ljava/lang/Throwable;Ljava/lang/String;[Ljava/lang/Object;)V
    //   5181: goto -2907 -> 2274
    //   5184: astore 27
    //   5186: ldc 50
    //   5188: aload 27
    //   5190: ldc 60
    //   5192: iconst_0
    //   5193: anewarray 4	java/lang/Object
    //   5196: invokestatic 367	com/tencent/mm/sdk/platformtools/ab:printErrStackTrace	(Ljava/lang/String;Ljava/lang/Throwable;Ljava/lang/String;[Ljava/lang/Object;)V
    //   5199: goto -2915 -> 2284
    //   5202: astore 27
    //   5204: aconst_null
    //   5205: astore 29
    //   5207: aload 49
    //   5209: astore 28
    //   5211: iload 6
    //   5213: istore 5
    //   5215: aload 31
    //   5217: astore 32
    //   5219: iload 15
    //   5221: istore 4
    //   5223: aload 27
    //   5225: astore 31
    //   5227: iload 4
    //   5229: istore_2
    //   5230: iload 5
    //   5232: istore_3
    //   5233: aload 29
    //   5235: astore 27
    //   5237: aload 28
    //   5239: astore 30
    //   5241: ldc 197
    //   5243: invokestatic 173	com/tencent/luggage/a/e:r	(Ljava/lang/Class;)Lcom/tencent/luggage/a/d;
    //   5246: checkcast 197	com/tencent/mm/plugin/appbrand/o/a
    //   5249: ldc2_w 198
    //   5252: ldc2_w 562
    //   5255: lconst_1
    //   5256: iconst_0
    //   5257: invokeinterface 203 8 0
    //   5262: iload 4
    //   5264: istore_2
    //   5265: iload 5
    //   5267: istore_3
    //   5268: aload 29
    //   5270: astore 27
    //   5272: aload 28
    //   5274: astore 30
    //   5276: ldc 50
    //   5278: aload 31
    //   5280: ldc_w 565
    //   5283: iconst_1
    //   5284: anewarray 4	java/lang/Object
    //   5287: dup
    //   5288: iconst_0
    //   5289: aload_1
    //   5290: getfield 154	com/tencent/mm/plugin/appbrand/m/e:mUrl	Ljava/lang/String;
    //   5293: aastore
    //   5294: invokestatic 367	com/tencent/mm/sdk/platformtools/ab:printErrStackTrace	(Ljava/lang/String;Ljava/lang/Throwable;Ljava/lang/String;[Ljava/lang/Object;)V
    //   5297: iload 4
    //   5299: istore_2
    //   5300: iload 5
    //   5302: istore_3
    //   5303: aload 29
    //   5305: astore 27
    //   5307: aload 28
    //   5309: astore 30
    //   5311: aload_0
    //   5312: aload 59
    //   5314: ldc_w 567
    //   5317: aload_1
    //   5318: getfield 163	com/tencent/mm/plugin/appbrand/m/e:hwp	Ljava/lang/String;
    //   5321: aload 32
    //   5323: invokespecial 165	com/tencent/mm/plugin/appbrand/m/d:a	(Lcom/tencent/mm/plugin/appbrand/m/d$a;Ljava/lang/String;Ljava/lang/String;Ljava/net/HttpURLConnection;)V
    //   5326: ldc 167
    //   5328: invokestatic 173	com/tencent/luggage/a/e:r	(Ljava/lang/Class;)Lcom/tencent/luggage/a/d;
    //   5331: checkcast 167	com/tencent/mm/plugin/appbrand/m/o
    //   5334: aload_0
    //   5335: getfield 40	com/tencent/mm/plugin/appbrand/m/d:hrA	Lcom/tencent/mm/plugin/appbrand/jsapi/c;
    //   5338: invokeinterface 177 1 0
    //   5343: aload_1
    //   5344: getfield 180	com/tencent/mm/plugin/appbrand/m/e:isY	Ljava/lang/String;
    //   5347: aload_1
    //   5348: getfield 183	com/tencent/mm/plugin/appbrand/m/e:bxW	Ljava/lang/String;
    //   5351: aload_1
    //   5352: getfield 154	com/tencent/mm/plugin/appbrand/m/e:mUrl	Ljava/lang/String;
    //   5355: aload_1
    //   5356: invokevirtual 234	com/tencent/mm/plugin/appbrand/m/e:getDataSize	()J
    //   5359: iload 5
    //   5361: i2l
    //   5362: iload 4
    //   5364: iconst_2
    //   5365: aload_1
    //   5366: invokevirtual 187	com/tencent/mm/plugin/appbrand/m/e:aIj	()I
    //   5369: invokeinterface 190 12 0
    //   5374: invokestatic 240	com/tencent/mm/sdk/platformtools/ah:getContext	()Landroid/content/Context;
    //   5377: invokestatic 246	com/tencent/mm/sdk/platformtools/at:getNetType	(Landroid/content/Context;)I
    //   5380: istore_2
    //   5381: iload_2
    //   5382: iconst_m1
    //   5383: if_icmpne +24 -> 5407
    //   5386: ldc 197
    //   5388: invokestatic 173	com/tencent/luggage/a/e:r	(Ljava/lang/Class;)Lcom/tencent/luggage/a/d;
    //   5391: checkcast 197	com/tencent/mm/plugin/appbrand/o/a
    //   5394: ldc2_w 198
    //   5397: ldc2_w 247
    //   5400: lconst_1
    //   5401: iconst_0
    //   5402: invokeinterface 203 8 0
    //   5407: ldc 50
    //   5409: ldc 250
    //   5411: iconst_1
    //   5412: anewarray 4	java/lang/Object
    //   5415: dup
    //   5416: iconst_0
    //   5417: iload_2
    //   5418: invokestatic 256	java/lang/Integer:valueOf	(I)Ljava/lang/Integer;
    //   5421: aastore
    //   5422: invokestatic 195	com/tencent/mm/sdk/platformtools/ab:i	(Ljava/lang/String;Ljava/lang/String;[Ljava/lang/Object;)V
    //   5425: aload 28
    //   5427: ifnull +8 -> 5435
    //   5430: aload 28
    //   5432: invokevirtual 374	java/io/InputStream:close	()V
    //   5435: aload 29
    //   5437: ifnull +8 -> 5445
    //   5440: aload 29
    //   5442: invokevirtual 377	java/io/DataOutputStream:close	()V
    //   5445: aload_0
    //   5446: getfield 38	com/tencent/mm/plugin/appbrand/m/d:isA	Ljava/util/ArrayList;
    //   5449: aload_1
    //   5450: getfield 163	com/tencent/mm/plugin/appbrand/m/e:hwp	Ljava/lang/String;
    //   5453: invokevirtual 260	java/util/ArrayList:remove	(Ljava/lang/Object;)Z
    //   5456: pop
    //   5457: ldc 138
    //   5459: invokestatic 65	com/tencent/matrix/trace/core/AppMethodBeat:o	(I)V
    //   5462: return
    //   5463: astore 27
    //   5465: ldc 50
    //   5467: aload 27
    //   5469: ldc 60
    //   5471: iconst_0
    //   5472: anewarray 4	java/lang/Object
    //   5475: invokestatic 367	com/tencent/mm/sdk/platformtools/ab:printErrStackTrace	(Ljava/lang/String;Ljava/lang/Throwable;Ljava/lang/String;[Ljava/lang/Object;)V
    //   5478: goto -43 -> 5435
    //   5481: astore 27
    //   5483: ldc 50
    //   5485: aload 27
    //   5487: ldc 60
    //   5489: iconst_0
    //   5490: anewarray 4	java/lang/Object
    //   5493: invokestatic 367	com/tencent/mm/sdk/platformtools/ab:printErrStackTrace	(Ljava/lang/String;Ljava/lang/Throwable;Ljava/lang/String;[Ljava/lang/Object;)V
    //   5496: goto -61 -> 5435
    //   5499: astore 27
    //   5501: ldc 50
    //   5503: aload 27
    //   5505: ldc 60
    //   5507: iconst_0
    //   5508: anewarray 4	java/lang/Object
    //   5511: invokestatic 367	com/tencent/mm/sdk/platformtools/ab:printErrStackTrace	(Ljava/lang/String;Ljava/lang/Throwable;Ljava/lang/String;[Ljava/lang/Object;)V
    //   5514: goto -79 -> 5435
    //   5517: astore 27
    //   5519: ldc 50
    //   5521: aload 27
    //   5523: ldc 60
    //   5525: iconst_0
    //   5526: anewarray 4	java/lang/Object
    //   5529: invokestatic 367	com/tencent/mm/sdk/platformtools/ab:printErrStackTrace	(Ljava/lang/String;Ljava/lang/Throwable;Ljava/lang/String;[Ljava/lang/Object;)V
    //   5532: goto -87 -> 5445
    //   5535: astore 31
    //   5537: aconst_null
    //   5538: astore 29
    //   5540: aload 50
    //   5542: astore 28
    //   5544: iload 7
    //   5546: istore 5
    //   5548: iload 16
    //   5550: istore 4
    //   5552: iload 4
    //   5554: istore_2
    //   5555: iload 5
    //   5557: istore_3
    //   5558: aload 29
    //   5560: astore 27
    //   5562: aload 28
    //   5564: astore 30
    //   5566: ldc 197
    //   5568: invokestatic 173	com/tencent/luggage/a/e:r	(Ljava/lang/Class;)Lcom/tencent/luggage/a/d;
    //   5571: checkcast 197	com/tencent/mm/plugin/appbrand/o/a
    //   5574: ldc2_w 198
    //   5577: ldc2_w 568
    //   5580: lconst_1
    //   5581: iconst_0
    //   5582: invokeinterface 203 8 0
    //   5587: iload 4
    //   5589: istore_2
    //   5590: iload 5
    //   5592: istore_3
    //   5593: aload 29
    //   5595: astore 27
    //   5597: aload 28
    //   5599: astore 30
    //   5601: aload_1
    //   5602: getfield 291	com/tencent/mm/plugin/appbrand/m/e:isQ	I
    //   5605: sipush 1000
    //   5608: if_icmpgt +266 -> 5874
    //   5611: iload 4
    //   5613: istore_2
    //   5614: iload 5
    //   5616: istore_3
    //   5617: aload 29
    //   5619: astore 27
    //   5621: aload 28
    //   5623: astore 30
    //   5625: ldc 197
    //   5627: invokestatic 173	com/tencent/luggage/a/e:r	(Ljava/lang/Class;)Lcom/tencent/luggage/a/d;
    //   5630: checkcast 197	com/tencent/mm/plugin/appbrand/o/a
    //   5633: ldc2_w 198
    //   5636: ldc2_w 570
    //   5639: lconst_1
    //   5640: iconst_0
    //   5641: invokeinterface 203 8 0
    //   5646: iload 4
    //   5648: istore_2
    //   5649: iload 5
    //   5651: istore_3
    //   5652: aload 29
    //   5654: astore 27
    //   5656: aload 28
    //   5658: astore 30
    //   5660: ldc 50
    //   5662: aload 31
    //   5664: ldc_w 573
    //   5667: iconst_2
    //   5668: anewarray 4	java/lang/Object
    //   5671: dup
    //   5672: iconst_0
    //   5673: aload_1
    //   5674: getfield 154	com/tencent/mm/plugin/appbrand/m/e:mUrl	Ljava/lang/String;
    //   5677: aastore
    //   5678: dup
    //   5679: iconst_1
    //   5680: aload_1
    //   5681: getfield 291	com/tencent/mm/plugin/appbrand/m/e:isQ	I
    //   5684: invokestatic 256	java/lang/Integer:valueOf	(I)Ljava/lang/Integer;
    //   5687: aastore
    //   5688: invokestatic 367	com/tencent/mm/sdk/platformtools/ab:printErrStackTrace	(Ljava/lang/String;Ljava/lang/Throwable;Ljava/lang/String;[Ljava/lang/Object;)V
    //   5691: iload 4
    //   5693: istore_2
    //   5694: iload 5
    //   5696: istore_3
    //   5697: aload 29
    //   5699: astore 27
    //   5701: aload 28
    //   5703: astore 30
    //   5705: aload_0
    //   5706: aload 59
    //   5708: new 575	java/lang/StringBuilder
    //   5711: dup
    //   5712: ldc_w 577
    //   5715: invokespecial 578	java/lang/StringBuilder:<init>	(Ljava/lang/String;)V
    //   5718: aload_1
    //   5719: getfield 291	com/tencent/mm/plugin/appbrand/m/e:isQ	I
    //   5722: invokevirtual 582	java/lang/StringBuilder:append	(I)Ljava/lang/StringBuilder;
    //   5725: invokevirtual 583	java/lang/StringBuilder:toString	()Ljava/lang/String;
    //   5728: aload_1
    //   5729: getfield 163	com/tencent/mm/plugin/appbrand/m/e:hwp	Ljava/lang/String;
    //   5732: aload 32
    //   5734: invokespecial 165	com/tencent/mm/plugin/appbrand/m/d:a	(Lcom/tencent/mm/plugin/appbrand/m/d$a;Ljava/lang/String;Ljava/lang/String;Ljava/net/HttpURLConnection;)V
    //   5737: ldc 167
    //   5739: invokestatic 173	com/tencent/luggage/a/e:r	(Ljava/lang/Class;)Lcom/tencent/luggage/a/d;
    //   5742: checkcast 167	com/tencent/mm/plugin/appbrand/m/o
    //   5745: aload_0
    //   5746: getfield 40	com/tencent/mm/plugin/appbrand/m/d:hrA	Lcom/tencent/mm/plugin/appbrand/jsapi/c;
    //   5749: invokeinterface 177 1 0
    //   5754: aload_1
    //   5755: getfield 180	com/tencent/mm/plugin/appbrand/m/e:isY	Ljava/lang/String;
    //   5758: aload_1
    //   5759: getfield 183	com/tencent/mm/plugin/appbrand/m/e:bxW	Ljava/lang/String;
    //   5762: aload_1
    //   5763: getfield 154	com/tencent/mm/plugin/appbrand/m/e:mUrl	Ljava/lang/String;
    //   5766: aload_1
    //   5767: invokevirtual 234	com/tencent/mm/plugin/appbrand/m/e:getDataSize	()J
    //   5770: iload 5
    //   5772: i2l
    //   5773: iload 4
    //   5775: iconst_2
    //   5776: aload_1
    //   5777: invokevirtual 187	com/tencent/mm/plugin/appbrand/m/e:aIj	()I
    //   5780: invokeinterface 190 12 0
    //   5785: invokestatic 240	com/tencent/mm/sdk/platformtools/ah:getContext	()Landroid/content/Context;
    //   5788: invokestatic 246	com/tencent/mm/sdk/platformtools/at:getNetType	(Landroid/content/Context;)I
    //   5791: istore_2
    //   5792: iload_2
    //   5793: iconst_m1
    //   5794: if_icmpne +24 -> 5818
    //   5797: ldc 197
    //   5799: invokestatic 173	com/tencent/luggage/a/e:r	(Ljava/lang/Class;)Lcom/tencent/luggage/a/d;
    //   5802: checkcast 197	com/tencent/mm/plugin/appbrand/o/a
    //   5805: ldc2_w 198
    //   5808: ldc2_w 247
    //   5811: lconst_1
    //   5812: iconst_0
    //   5813: invokeinterface 203 8 0
    //   5818: ldc 50
    //   5820: ldc 250
    //   5822: iconst_1
    //   5823: anewarray 4	java/lang/Object
    //   5826: dup
    //   5827: iconst_0
    //   5828: iload_2
    //   5829: invokestatic 256	java/lang/Integer:valueOf	(I)Ljava/lang/Integer;
    //   5832: aastore
    //   5833: invokestatic 195	com/tencent/mm/sdk/platformtools/ab:i	(Ljava/lang/String;Ljava/lang/String;[Ljava/lang/Object;)V
    //   5836: aload 28
    //   5838: ifnull +8 -> 5846
    //   5841: aload 28
    //   5843: invokevirtual 374	java/io/InputStream:close	()V
    //   5846: aload 29
    //   5848: ifnull +8 -> 5856
    //   5851: aload 29
    //   5853: invokevirtual 377	java/io/DataOutputStream:close	()V
    //   5856: aload_0
    //   5857: getfield 38	com/tencent/mm/plugin/appbrand/m/d:isA	Ljava/util/ArrayList;
    //   5860: aload_1
    //   5861: getfield 163	com/tencent/mm/plugin/appbrand/m/e:hwp	Ljava/lang/String;
    //   5864: invokevirtual 260	java/util/ArrayList:remove	(Ljava/lang/Object;)Z
    //   5867: pop
    //   5868: ldc 138
    //   5870: invokestatic 65	com/tencent/matrix/trace/core/AppMethodBeat:o	(I)V
    //   5873: return
    //   5874: iload 4
    //   5876: istore_2
    //   5877: iload 5
    //   5879: istore_3
    //   5880: aload 29
    //   5882: astore 27
    //   5884: aload 28
    //   5886: astore 30
    //   5888: aload_1
    //   5889: getfield 291	com/tencent/mm/plugin/appbrand/m/e:isQ	I
    //   5892: sipush 5000
    //   5895: if_icmpgt +184 -> 6079
    //   5898: iload 4
    //   5900: istore_2
    //   5901: iload 5
    //   5903: istore_3
    //   5904: aload 29
    //   5906: astore 27
    //   5908: aload 28
    //   5910: astore 30
    //   5912: ldc 197
    //   5914: invokestatic 173	com/tencent/luggage/a/e:r	(Ljava/lang/Class;)Lcom/tencent/luggage/a/d;
    //   5917: checkcast 197	com/tencent/mm/plugin/appbrand/o/a
    //   5920: ldc2_w 198
    //   5923: ldc2_w 584
    //   5926: lconst_1
    //   5927: iconst_0
    //   5928: invokeinterface 203 8 0
    //   5933: goto -287 -> 5646
    //   5936: astore 28
    //   5938: aload 27
    //   5940: astore 29
    //   5942: ldc 167
    //   5944: invokestatic 173	com/tencent/luggage/a/e:r	(Ljava/lang/Class;)Lcom/tencent/luggage/a/d;
    //   5947: checkcast 167	com/tencent/mm/plugin/appbrand/m/o
    //   5950: aload_0
    //   5951: getfield 40	com/tencent/mm/plugin/appbrand/m/d:hrA	Lcom/tencent/mm/plugin/appbrand/jsapi/c;
    //   5954: invokeinterface 177 1 0
    //   5959: aload_1
    //   5960: getfield 180	com/tencent/mm/plugin/appbrand/m/e:isY	Ljava/lang/String;
    //   5963: aload_1
    //   5964: getfield 183	com/tencent/mm/plugin/appbrand/m/e:bxW	Ljava/lang/String;
    //   5967: aload_1
    //   5968: getfield 154	com/tencent/mm/plugin/appbrand/m/e:mUrl	Ljava/lang/String;
    //   5971: aload_1
    //   5972: invokevirtual 234	com/tencent/mm/plugin/appbrand/m/e:getDataSize	()J
    //   5975: iload_3
    //   5976: i2l
    //   5977: iload_2
    //   5978: iconst_2
    //   5979: aload_1
    //   5980: invokevirtual 187	com/tencent/mm/plugin/appbrand/m/e:aIj	()I
    //   5983: invokeinterface 190 12 0
    //   5988: invokestatic 240	com/tencent/mm/sdk/platformtools/ah:getContext	()Landroid/content/Context;
    //   5991: invokestatic 246	com/tencent/mm/sdk/platformtools/at:getNetType	(Landroid/content/Context;)I
    //   5994: istore_2
    //   5995: iload_2
    //   5996: iconst_m1
    //   5997: if_icmpne +24 -> 6021
    //   6000: ldc 197
    //   6002: invokestatic 173	com/tencent/luggage/a/e:r	(Ljava/lang/Class;)Lcom/tencent/luggage/a/d;
    //   6005: checkcast 197	com/tencent/mm/plugin/appbrand/o/a
    //   6008: ldc2_w 198
    //   6011: ldc2_w 247
    //   6014: lconst_1
    //   6015: iconst_0
    //   6016: invokeinterface 203 8 0
    //   6021: ldc 50
    //   6023: ldc 250
    //   6025: iconst_1
    //   6026: anewarray 4	java/lang/Object
    //   6029: dup
    //   6030: iconst_0
    //   6031: iload_2
    //   6032: invokestatic 256	java/lang/Integer:valueOf	(I)Ljava/lang/Integer;
    //   6035: aastore
    //   6036: invokestatic 195	com/tencent/mm/sdk/platformtools/ab:i	(Ljava/lang/String;Ljava/lang/String;[Ljava/lang/Object;)V
    //   6039: aload 30
    //   6041: ifnull +8 -> 6049
    //   6044: aload 30
    //   6046: invokevirtual 374	java/io/InputStream:close	()V
    //   6049: aload 29
    //   6051: ifnull +8 -> 6059
    //   6054: aload 29
    //   6056: invokevirtual 377	java/io/DataOutputStream:close	()V
    //   6059: aload_0
    //   6060: getfield 38	com/tencent/mm/plugin/appbrand/m/d:isA	Ljava/util/ArrayList;
    //   6063: aload_1
    //   6064: getfield 163	com/tencent/mm/plugin/appbrand/m/e:hwp	Ljava/lang/String;
    //   6067: invokevirtual 260	java/util/ArrayList:remove	(Ljava/lang/Object;)Z
    //   6070: pop
    //   6071: ldc 138
    //   6073: invokestatic 65	com/tencent/matrix/trace/core/AppMethodBeat:o	(I)V
    //   6076: aload 28
    //   6078: athrow
    //   6079: iload 4
    //   6081: istore_2
    //   6082: iload 5
    //   6084: istore_3
    //   6085: aload 29
    //   6087: astore 27
    //   6089: aload 28
    //   6091: astore 30
    //   6093: aload_1
    //   6094: getfield 291	com/tencent/mm/plugin/appbrand/m/e:isQ	I
    //   6097: sipush 10000
    //   6100: if_icmpgt +41 -> 6141
    //   6103: iload 4
    //   6105: istore_2
    //   6106: iload 5
    //   6108: istore_3
    //   6109: aload 29
    //   6111: astore 27
    //   6113: aload 28
    //   6115: astore 30
    //   6117: ldc 197
    //   6119: invokestatic 173	com/tencent/luggage/a/e:r	(Ljava/lang/Class;)Lcom/tencent/luggage/a/d;
    //   6122: checkcast 197	com/tencent/mm/plugin/appbrand/o/a
    //   6125: ldc2_w 198
    //   6128: ldc2_w 586
    //   6131: lconst_1
    //   6132: iconst_0
    //   6133: invokeinterface 203 8 0
    //   6138: goto -492 -> 5646
    //   6141: iload 4
    //   6143: istore_2
    //   6144: iload 5
    //   6146: istore_3
    //   6147: aload 29
    //   6149: astore 27
    //   6151: aload 28
    //   6153: astore 30
    //   6155: ldc 197
    //   6157: invokestatic 173	com/tencent/luggage/a/e:r	(Ljava/lang/Class;)Lcom/tencent/luggage/a/d;
    //   6160: checkcast 197	com/tencent/mm/plugin/appbrand/o/a
    //   6163: ldc2_w 198
    //   6166: ldc2_w 588
    //   6169: lconst_1
    //   6170: iconst_0
    //   6171: invokeinterface 203 8 0
    //   6176: goto -530 -> 5646
    //   6179: astore 27
    //   6181: ldc 50
    //   6183: aload 27
    //   6185: ldc 60
    //   6187: iconst_0
    //   6188: anewarray 4	java/lang/Object
    //   6191: invokestatic 367	com/tencent/mm/sdk/platformtools/ab:printErrStackTrace	(Ljava/lang/String;Ljava/lang/Throwable;Ljava/lang/String;[Ljava/lang/Object;)V
    //   6194: goto -348 -> 5846
    //   6197: astore 27
    //   6199: ldc 50
    //   6201: aload 27
    //   6203: ldc 60
    //   6205: iconst_0
    //   6206: anewarray 4	java/lang/Object
    //   6209: invokestatic 367	com/tencent/mm/sdk/platformtools/ab:printErrStackTrace	(Ljava/lang/String;Ljava/lang/Throwable;Ljava/lang/String;[Ljava/lang/Object;)V
    //   6212: goto -366 -> 5846
    //   6215: astore 27
    //   6217: ldc 50
    //   6219: aload 27
    //   6221: ldc 60
    //   6223: iconst_0
    //   6224: anewarray 4	java/lang/Object
    //   6227: invokestatic 367	com/tencent/mm/sdk/platformtools/ab:printErrStackTrace	(Ljava/lang/String;Ljava/lang/Throwable;Ljava/lang/String;[Ljava/lang/Object;)V
    //   6230: goto -384 -> 5846
    //   6233: astore 27
    //   6235: ldc 50
    //   6237: aload 27
    //   6239: ldc 60
    //   6241: iconst_0
    //   6242: anewarray 4	java/lang/Object
    //   6245: invokestatic 367	com/tencent/mm/sdk/platformtools/ab:printErrStackTrace	(Ljava/lang/String;Ljava/lang/Throwable;Ljava/lang/String;[Ljava/lang/Object;)V
    //   6248: goto -392 -> 5856
    //   6251: astore 31
    //   6253: aconst_null
    //   6254: astore 29
    //   6256: aload 51
    //   6258: astore 28
    //   6260: iload 8
    //   6262: istore 5
    //   6264: iload 17
    //   6266: istore 4
    //   6268: iload 4
    //   6270: istore_2
    //   6271: iload 5
    //   6273: istore_3
    //   6274: aload 29
    //   6276: astore 27
    //   6278: aload 28
    //   6280: astore 30
    //   6282: ldc 197
    //   6284: invokestatic 173	com/tencent/luggage/a/e:r	(Ljava/lang/Class;)Lcom/tencent/luggage/a/d;
    //   6287: checkcast 197	com/tencent/mm/plugin/appbrand/o/a
    //   6290: ldc2_w 198
    //   6293: ldc2_w 590
    //   6296: lconst_1
    //   6297: iconst_0
    //   6298: invokeinterface 203 8 0
    //   6303: iload 4
    //   6305: istore_2
    //   6306: iload 5
    //   6308: istore_3
    //   6309: aload 29
    //   6311: astore 27
    //   6313: aload 28
    //   6315: astore 30
    //   6317: ldc 50
    //   6319: aload 31
    //   6321: ldc_w 593
    //   6324: iconst_1
    //   6325: anewarray 4	java/lang/Object
    //   6328: dup
    //   6329: iconst_0
    //   6330: aload_1
    //   6331: getfield 154	com/tencent/mm/plugin/appbrand/m/e:mUrl	Ljava/lang/String;
    //   6334: aastore
    //   6335: invokestatic 367	com/tencent/mm/sdk/platformtools/ab:printErrStackTrace	(Ljava/lang/String;Ljava/lang/Throwable;Ljava/lang/String;[Ljava/lang/Object;)V
    //   6338: iload 4
    //   6340: istore_2
    //   6341: iload 5
    //   6343: istore_3
    //   6344: aload 29
    //   6346: astore 27
    //   6348: aload 28
    //   6350: astore 30
    //   6352: aload_0
    //   6353: aload 59
    //   6355: ldc_w 595
    //   6358: aload_1
    //   6359: getfield 163	com/tencent/mm/plugin/appbrand/m/e:hwp	Ljava/lang/String;
    //   6362: aload 33
    //   6364: invokespecial 165	com/tencent/mm/plugin/appbrand/m/d:a	(Lcom/tencent/mm/plugin/appbrand/m/d$a;Ljava/lang/String;Ljava/lang/String;Ljava/net/HttpURLConnection;)V
    //   6367: ldc 167
    //   6369: invokestatic 173	com/tencent/luggage/a/e:r	(Ljava/lang/Class;)Lcom/tencent/luggage/a/d;
    //   6372: checkcast 167	com/tencent/mm/plugin/appbrand/m/o
    //   6375: aload_0
    //   6376: getfield 40	com/tencent/mm/plugin/appbrand/m/d:hrA	Lcom/tencent/mm/plugin/appbrand/jsapi/c;
    //   6379: invokeinterface 177 1 0
    //   6384: aload_1
    //   6385: getfield 180	com/tencent/mm/plugin/appbrand/m/e:isY	Ljava/lang/String;
    //   6388: aload_1
    //   6389: getfield 183	com/tencent/mm/plugin/appbrand/m/e:bxW	Ljava/lang/String;
    //   6392: aload_1
    //   6393: getfield 154	com/tencent/mm/plugin/appbrand/m/e:mUrl	Ljava/lang/String;
    //   6396: aload_1
    //   6397: invokevirtual 234	com/tencent/mm/plugin/appbrand/m/e:getDataSize	()J
    //   6400: iload 5
    //   6402: i2l
    //   6403: iload 4
    //   6405: iconst_2
    //   6406: aload_1
    //   6407: invokevirtual 187	com/tencent/mm/plugin/appbrand/m/e:aIj	()I
    //   6410: invokeinterface 190 12 0
    //   6415: invokestatic 240	com/tencent/mm/sdk/platformtools/ah:getContext	()Landroid/content/Context;
    //   6418: invokestatic 246	com/tencent/mm/sdk/platformtools/at:getNetType	(Landroid/content/Context;)I
    //   6421: istore_2
    //   6422: iload_2
    //   6423: iconst_m1
    //   6424: if_icmpne +24 -> 6448
    //   6427: ldc 197
    //   6429: invokestatic 173	com/tencent/luggage/a/e:r	(Ljava/lang/Class;)Lcom/tencent/luggage/a/d;
    //   6432: checkcast 197	com/tencent/mm/plugin/appbrand/o/a
    //   6435: ldc2_w 198
    //   6438: ldc2_w 247
    //   6441: lconst_1
    //   6442: iconst_0
    //   6443: invokeinterface 203 8 0
    //   6448: ldc 50
    //   6450: ldc 250
    //   6452: iconst_1
    //   6453: anewarray 4	java/lang/Object
    //   6456: dup
    //   6457: iconst_0
    //   6458: iload_2
    //   6459: invokestatic 256	java/lang/Integer:valueOf	(I)Ljava/lang/Integer;
    //   6462: aastore
    //   6463: invokestatic 195	com/tencent/mm/sdk/platformtools/ab:i	(Ljava/lang/String;Ljava/lang/String;[Ljava/lang/Object;)V
    //   6466: aload 28
    //   6468: ifnull +8 -> 6476
    //   6471: aload 28
    //   6473: invokevirtual 374	java/io/InputStream:close	()V
    //   6476: aload 29
    //   6478: ifnull +8 -> 6486
    //   6481: aload 29
    //   6483: invokevirtual 377	java/io/DataOutputStream:close	()V
    //   6486: aload_0
    //   6487: getfield 38	com/tencent/mm/plugin/appbrand/m/d:isA	Ljava/util/ArrayList;
    //   6490: aload_1
    //   6491: getfield 163	com/tencent/mm/plugin/appbrand/m/e:hwp	Ljava/lang/String;
    //   6494: invokevirtual 260	java/util/ArrayList:remove	(Ljava/lang/Object;)Z
    //   6497: pop
    //   6498: ldc 138
    //   6500: invokestatic 65	com/tencent/matrix/trace/core/AppMethodBeat:o	(I)V
    //   6503: return
    //   6504: astore 27
    //   6506: ldc 50
    //   6508: aload 27
    //   6510: ldc 60
    //   6512: iconst_0
    //   6513: anewarray 4	java/lang/Object
    //   6516: invokestatic 367	com/tencent/mm/sdk/platformtools/ab:printErrStackTrace	(Ljava/lang/String;Ljava/lang/Throwable;Ljava/lang/String;[Ljava/lang/Object;)V
    //   6519: goto -43 -> 6476
    //   6522: astore 27
    //   6524: ldc 50
    //   6526: aload 27
    //   6528: ldc 60
    //   6530: iconst_0
    //   6531: anewarray 4	java/lang/Object
    //   6534: invokestatic 367	com/tencent/mm/sdk/platformtools/ab:printErrStackTrace	(Ljava/lang/String;Ljava/lang/Throwable;Ljava/lang/String;[Ljava/lang/Object;)V
    //   6537: goto -61 -> 6476
    //   6540: astore 27
    //   6542: ldc 50
    //   6544: aload 27
    //   6546: ldc 60
    //   6548: iconst_0
    //   6549: anewarray 4	java/lang/Object
    //   6552: invokestatic 367	com/tencent/mm/sdk/platformtools/ab:printErrStackTrace	(Ljava/lang/String;Ljava/lang/Throwable;Ljava/lang/String;[Ljava/lang/Object;)V
    //   6555: goto -79 -> 6476
    //   6558: astore 27
    //   6560: ldc 50
    //   6562: aload 27
    //   6564: ldc 60
    //   6566: iconst_0
    //   6567: anewarray 4	java/lang/Object
    //   6570: invokestatic 367	com/tencent/mm/sdk/platformtools/ab:printErrStackTrace	(Ljava/lang/String;Ljava/lang/Throwable;Ljava/lang/String;[Ljava/lang/Object;)V
    //   6573: goto -87 -> 6486
    //   6576: astore 31
    //   6578: aconst_null
    //   6579: astore 29
    //   6581: aload 52
    //   6583: astore 28
    //   6585: iload 9
    //   6587: istore 5
    //   6589: iload 18
    //   6591: istore 4
    //   6593: iload 4
    //   6595: istore_2
    //   6596: iload 5
    //   6598: istore_3
    //   6599: aload 29
    //   6601: astore 27
    //   6603: aload 28
    //   6605: astore 30
    //   6607: ldc 197
    //   6609: invokestatic 173	com/tencent/luggage/a/e:r	(Ljava/lang/Class;)Lcom/tencent/luggage/a/d;
    //   6612: checkcast 197	com/tencent/mm/plugin/appbrand/o/a
    //   6615: ldc2_w 198
    //   6618: ldc2_w 596
    //   6621: lconst_1
    //   6622: iconst_0
    //   6623: invokeinterface 203 8 0
    //   6628: iload 4
    //   6630: istore_2
    //   6631: iload 5
    //   6633: istore_3
    //   6634: aload 29
    //   6636: astore 27
    //   6638: aload 28
    //   6640: astore 30
    //   6642: ldc 50
    //   6644: aload 31
    //   6646: ldc_w 599
    //   6649: iconst_1
    //   6650: anewarray 4	java/lang/Object
    //   6653: dup
    //   6654: iconst_0
    //   6655: aload_1
    //   6656: getfield 154	com/tencent/mm/plugin/appbrand/m/e:mUrl	Ljava/lang/String;
    //   6659: aastore
    //   6660: invokestatic 367	com/tencent/mm/sdk/platformtools/ab:printErrStackTrace	(Ljava/lang/String;Ljava/lang/Throwable;Ljava/lang/String;[Ljava/lang/Object;)V
    //   6663: iload 4
    //   6665: istore_2
    //   6666: iload 5
    //   6668: istore_3
    //   6669: aload 29
    //   6671: astore 27
    //   6673: aload 28
    //   6675: astore 30
    //   6677: aload_0
    //   6678: aload 59
    //   6680: ldc_w 601
    //   6683: aload_1
    //   6684: getfield 163	com/tencent/mm/plugin/appbrand/m/e:hwp	Ljava/lang/String;
    //   6687: aload 34
    //   6689: invokespecial 165	com/tencent/mm/plugin/appbrand/m/d:a	(Lcom/tencent/mm/plugin/appbrand/m/d$a;Ljava/lang/String;Ljava/lang/String;Ljava/net/HttpURLConnection;)V
    //   6692: ldc 167
    //   6694: invokestatic 173	com/tencent/luggage/a/e:r	(Ljava/lang/Class;)Lcom/tencent/luggage/a/d;
    //   6697: checkcast 167	com/tencent/mm/plugin/appbrand/m/o
    //   6700: aload_0
    //   6701: getfield 40	com/tencent/mm/plugin/appbrand/m/d:hrA	Lcom/tencent/mm/plugin/appbrand/jsapi/c;
    //   6704: invokeinterface 177 1 0
    //   6709: aload_1
    //   6710: getfield 180	com/tencent/mm/plugin/appbrand/m/e:isY	Ljava/lang/String;
    //   6713: aload_1
    //   6714: getfield 183	com/tencent/mm/plugin/appbrand/m/e:bxW	Ljava/lang/String;
    //   6717: aload_1
    //   6718: getfield 154	com/tencent/mm/plugin/appbrand/m/e:mUrl	Ljava/lang/String;
    //   6721: aload_1
    //   6722: invokevirtual 234	com/tencent/mm/plugin/appbrand/m/e:getDataSize	()J
    //   6725: iload 5
    //   6727: i2l
    //   6728: iload 4
    //   6730: iconst_2
    //   6731: aload_1
    //   6732: invokevirtual 187	com/tencent/mm/plugin/appbrand/m/e:aIj	()I
    //   6735: invokeinterface 190 12 0
    //   6740: invokestatic 240	com/tencent/mm/sdk/platformtools/ah:getContext	()Landroid/content/Context;
    //   6743: invokestatic 246	com/tencent/mm/sdk/platformtools/at:getNetType	(Landroid/content/Context;)I
    //   6746: istore_2
    //   6747: iload_2
    //   6748: iconst_m1
    //   6749: if_icmpne +24 -> 6773
    //   6752: ldc 197
    //   6754: invokestatic 173	com/tencent/luggage/a/e:r	(Ljava/lang/Class;)Lcom/tencent/luggage/a/d;
    //   6757: checkcast 197	com/tencent/mm/plugin/appbrand/o/a
    //   6760: ldc2_w 198
    //   6763: ldc2_w 247
    //   6766: lconst_1
    //   6767: iconst_0
    //   6768: invokeinterface 203 8 0
    //   6773: ldc 50
    //   6775: ldc 250
    //   6777: iconst_1
    //   6778: anewarray 4	java/lang/Object
    //   6781: dup
    //   6782: iconst_0
    //   6783: iload_2
    //   6784: invokestatic 256	java/lang/Integer:valueOf	(I)Ljava/lang/Integer;
    //   6787: aastore
    //   6788: invokestatic 195	com/tencent/mm/sdk/platformtools/ab:i	(Ljava/lang/String;Ljava/lang/String;[Ljava/lang/Object;)V
    //   6791: aload 28
    //   6793: ifnull +8 -> 6801
    //   6796: aload 28
    //   6798: invokevirtual 374	java/io/InputStream:close	()V
    //   6801: aload 29
    //   6803: ifnull +8 -> 6811
    //   6806: aload 29
    //   6808: invokevirtual 377	java/io/DataOutputStream:close	()V
    //   6811: aload_0
    //   6812: getfield 38	com/tencent/mm/plugin/appbrand/m/d:isA	Ljava/util/ArrayList;
    //   6815: aload_1
    //   6816: getfield 163	com/tencent/mm/plugin/appbrand/m/e:hwp	Ljava/lang/String;
    //   6819: invokevirtual 260	java/util/ArrayList:remove	(Ljava/lang/Object;)Z
    //   6822: pop
    //   6823: ldc 138
    //   6825: invokestatic 65	com/tencent/matrix/trace/core/AppMethodBeat:o	(I)V
    //   6828: return
    //   6829: astore 27
    //   6831: ldc 50
    //   6833: aload 27
    //   6835: ldc 60
    //   6837: iconst_0
    //   6838: anewarray 4	java/lang/Object
    //   6841: invokestatic 367	com/tencent/mm/sdk/platformtools/ab:printErrStackTrace	(Ljava/lang/String;Ljava/lang/Throwable;Ljava/lang/String;[Ljava/lang/Object;)V
    //   6844: goto -43 -> 6801
    //   6847: astore 27
    //   6849: ldc 50
    //   6851: aload 27
    //   6853: ldc 60
    //   6855: iconst_0
    //   6856: anewarray 4	java/lang/Object
    //   6859: invokestatic 367	com/tencent/mm/sdk/platformtools/ab:printErrStackTrace	(Ljava/lang/String;Ljava/lang/Throwable;Ljava/lang/String;[Ljava/lang/Object;)V
    //   6862: goto -61 -> 6801
    //   6865: astore 27
    //   6867: ldc 50
    //   6869: aload 27
    //   6871: ldc 60
    //   6873: iconst_0
    //   6874: anewarray 4	java/lang/Object
    //   6877: invokestatic 367	com/tencent/mm/sdk/platformtools/ab:printErrStackTrace	(Ljava/lang/String;Ljava/lang/Throwable;Ljava/lang/String;[Ljava/lang/Object;)V
    //   6880: goto -79 -> 6801
    //   6883: astore 27
    //   6885: ldc 50
    //   6887: aload 27
    //   6889: ldc 60
    //   6891: iconst_0
    //   6892: anewarray 4	java/lang/Object
    //   6895: invokestatic 367	com/tencent/mm/sdk/platformtools/ab:printErrStackTrace	(Ljava/lang/String;Ljava/lang/Throwable;Ljava/lang/String;[Ljava/lang/Object;)V
    //   6898: goto -87 -> 6811
    //   6901: astore 31
    //   6903: aconst_null
    //   6904: astore 29
    //   6906: aload 53
    //   6908: astore 28
    //   6910: iload 10
    //   6912: istore 5
    //   6914: iload 19
    //   6916: istore 4
    //   6918: iload 4
    //   6920: istore_2
    //   6921: iload 5
    //   6923: istore_3
    //   6924: aload 29
    //   6926: astore 27
    //   6928: aload 28
    //   6930: astore 30
    //   6932: ldc 197
    //   6934: invokestatic 173	com/tencent/luggage/a/e:r	(Ljava/lang/Class;)Lcom/tencent/luggage/a/d;
    //   6937: checkcast 197	com/tencent/mm/plugin/appbrand/o/a
    //   6940: ldc2_w 198
    //   6943: ldc2_w 602
    //   6946: lconst_1
    //   6947: iconst_0
    //   6948: invokeinterface 203 8 0
    //   6953: iload 4
    //   6955: istore_2
    //   6956: iload 5
    //   6958: istore_3
    //   6959: aload 29
    //   6961: astore 27
    //   6963: aload 28
    //   6965: astore 30
    //   6967: ldc 50
    //   6969: aload 31
    //   6971: ldc_w 605
    //   6974: iconst_1
    //   6975: anewarray 4	java/lang/Object
    //   6978: dup
    //   6979: iconst_0
    //   6980: aload_1
    //   6981: getfield 154	com/tencent/mm/plugin/appbrand/m/e:mUrl	Ljava/lang/String;
    //   6984: aastore
    //   6985: invokestatic 367	com/tencent/mm/sdk/platformtools/ab:printErrStackTrace	(Ljava/lang/String;Ljava/lang/Throwable;Ljava/lang/String;[Ljava/lang/Object;)V
    //   6988: iload 4
    //   6990: istore_2
    //   6991: iload 5
    //   6993: istore_3
    //   6994: aload 29
    //   6996: astore 27
    //   6998: aload 28
    //   7000: astore 30
    //   7002: aload_0
    //   7003: aload 59
    //   7005: ldc_w 607
    //   7008: aload_1
    //   7009: getfield 163	com/tencent/mm/plugin/appbrand/m/e:hwp	Ljava/lang/String;
    //   7012: aload 35
    //   7014: invokespecial 165	com/tencent/mm/plugin/appbrand/m/d:a	(Lcom/tencent/mm/plugin/appbrand/m/d$a;Ljava/lang/String;Ljava/lang/String;Ljava/net/HttpURLConnection;)V
    //   7017: ldc 167
    //   7019: invokestatic 173	com/tencent/luggage/a/e:r	(Ljava/lang/Class;)Lcom/tencent/luggage/a/d;
    //   7022: checkcast 167	com/tencent/mm/plugin/appbrand/m/o
    //   7025: aload_0
    //   7026: getfield 40	com/tencent/mm/plugin/appbrand/m/d:hrA	Lcom/tencent/mm/plugin/appbrand/jsapi/c;
    //   7029: invokeinterface 177 1 0
    //   7034: aload_1
    //   7035: getfield 180	com/tencent/mm/plugin/appbrand/m/e:isY	Ljava/lang/String;
    //   7038: aload_1
    //   7039: getfield 183	com/tencent/mm/plugin/appbrand/m/e:bxW	Ljava/lang/String;
    //   7042: aload_1
    //   7043: getfield 154	com/tencent/mm/plugin/appbrand/m/e:mUrl	Ljava/lang/String;
    //   7046: aload_1
    //   7047: invokevirtual 234	com/tencent/mm/plugin/appbrand/m/e:getDataSize	()J
    //   7050: iload 5
    //   7052: i2l
    //   7053: iload 4
    //   7055: iconst_2
    //   7056: aload_1
    //   7057: invokevirtual 187	com/tencent/mm/plugin/appbrand/m/e:aIj	()I
    //   7060: invokeinterface 190 12 0
    //   7065: invokestatic 240	com/tencent/mm/sdk/platformtools/ah:getContext	()Landroid/content/Context;
    //   7068: invokestatic 246	com/tencent/mm/sdk/platformtools/at:getNetType	(Landroid/content/Context;)I
    //   7071: istore_2
    //   7072: iload_2
    //   7073: iconst_m1
    //   7074: if_icmpne +24 -> 7098
    //   7077: ldc 197
    //   7079: invokestatic 173	com/tencent/luggage/a/e:r	(Ljava/lang/Class;)Lcom/tencent/luggage/a/d;
    //   7082: checkcast 197	com/tencent/mm/plugin/appbrand/o/a
    //   7085: ldc2_w 198
    //   7088: ldc2_w 247
    //   7091: lconst_1
    //   7092: iconst_0
    //   7093: invokeinterface 203 8 0
    //   7098: ldc 50
    //   7100: ldc 250
    //   7102: iconst_1
    //   7103: anewarray 4	java/lang/Object
    //   7106: dup
    //   7107: iconst_0
    //   7108: iload_2
    //   7109: invokestatic 256	java/lang/Integer:valueOf	(I)Ljava/lang/Integer;
    //   7112: aastore
    //   7113: invokestatic 195	com/tencent/mm/sdk/platformtools/ab:i	(Ljava/lang/String;Ljava/lang/String;[Ljava/lang/Object;)V
    //   7116: aload 28
    //   7118: ifnull +8 -> 7126
    //   7121: aload 28
    //   7123: invokevirtual 374	java/io/InputStream:close	()V
    //   7126: aload 29
    //   7128: ifnull +8 -> 7136
    //   7131: aload 29
    //   7133: invokevirtual 377	java/io/DataOutputStream:close	()V
    //   7136: aload_0
    //   7137: getfield 38	com/tencent/mm/plugin/appbrand/m/d:isA	Ljava/util/ArrayList;
    //   7140: aload_1
    //   7141: getfield 163	com/tencent/mm/plugin/appbrand/m/e:hwp	Ljava/lang/String;
    //   7144: invokevirtual 260	java/util/ArrayList:remove	(Ljava/lang/Object;)Z
    //   7147: pop
    //   7148: ldc 138
    //   7150: invokestatic 65	com/tencent/matrix/trace/core/AppMethodBeat:o	(I)V
    //   7153: return
    //   7154: astore 27
    //   7156: ldc 50
    //   7158: aload 27
    //   7160: ldc 60
    //   7162: iconst_0
    //   7163: anewarray 4	java/lang/Object
    //   7166: invokestatic 367	com/tencent/mm/sdk/platformtools/ab:printErrStackTrace	(Ljava/lang/String;Ljava/lang/Throwable;Ljava/lang/String;[Ljava/lang/Object;)V
    //   7169: goto -43 -> 7126
    //   7172: astore 27
    //   7174: ldc 50
    //   7176: aload 27
    //   7178: ldc 60
    //   7180: iconst_0
    //   7181: anewarray 4	java/lang/Object
    //   7184: invokestatic 367	com/tencent/mm/sdk/platformtools/ab:printErrStackTrace	(Ljava/lang/String;Ljava/lang/Throwable;Ljava/lang/String;[Ljava/lang/Object;)V
    //   7187: goto -61 -> 7126
    //   7190: astore 27
    //   7192: ldc 50
    //   7194: aload 27
    //   7196: ldc 60
    //   7198: iconst_0
    //   7199: anewarray 4	java/lang/Object
    //   7202: invokestatic 367	com/tencent/mm/sdk/platformtools/ab:printErrStackTrace	(Ljava/lang/String;Ljava/lang/Throwable;Ljava/lang/String;[Ljava/lang/Object;)V
    //   7205: goto -79 -> 7126
    //   7208: astore 27
    //   7210: ldc 50
    //   7212: aload 27
    //   7214: ldc 60
    //   7216: iconst_0
    //   7217: anewarray 4	java/lang/Object
    //   7220: invokestatic 367	com/tencent/mm/sdk/platformtools/ab:printErrStackTrace	(Ljava/lang/String;Ljava/lang/Throwable;Ljava/lang/String;[Ljava/lang/Object;)V
    //   7223: goto -87 -> 7136
    //   7226: astore 31
    //   7228: aconst_null
    //   7229: astore 29
    //   7231: aload 54
    //   7233: astore 28
    //   7235: iload 11
    //   7237: istore 5
    //   7239: iload 20
    //   7241: istore 4
    //   7243: iload 4
    //   7245: istore_2
    //   7246: iload 5
    //   7248: istore_3
    //   7249: aload 29
    //   7251: astore 27
    //   7253: aload 28
    //   7255: astore 30
    //   7257: ldc 197
    //   7259: invokestatic 173	com/tencent/luggage/a/e:r	(Ljava/lang/Class;)Lcom/tencent/luggage/a/d;
    //   7262: checkcast 197	com/tencent/mm/plugin/appbrand/o/a
    //   7265: ldc2_w 198
    //   7268: ldc2_w 608
    //   7271: lconst_1
    //   7272: iconst_0
    //   7273: invokeinterface 203 8 0
    //   7278: iload 4
    //   7280: istore_2
    //   7281: iload 5
    //   7283: istore_3
    //   7284: aload 29
    //   7286: astore 27
    //   7288: aload 28
    //   7290: astore 30
    //   7292: ldc 50
    //   7294: aload 31
    //   7296: ldc_w 611
    //   7299: iconst_1
    //   7300: anewarray 4	java/lang/Object
    //   7303: dup
    //   7304: iconst_0
    //   7305: aload_1
    //   7306: getfield 154	com/tencent/mm/plugin/appbrand/m/e:mUrl	Ljava/lang/String;
    //   7309: aastore
    //   7310: invokestatic 367	com/tencent/mm/sdk/platformtools/ab:printErrStackTrace	(Ljava/lang/String;Ljava/lang/Throwable;Ljava/lang/String;[Ljava/lang/Object;)V
    //   7313: iload 4
    //   7315: istore_2
    //   7316: iload 5
    //   7318: istore_3
    //   7319: aload 29
    //   7321: astore 27
    //   7323: aload 28
    //   7325: astore 30
    //   7327: aload_0
    //   7328: aload 59
    //   7330: ldc_w 613
    //   7333: aload_1
    //   7334: getfield 163	com/tencent/mm/plugin/appbrand/m/e:hwp	Ljava/lang/String;
    //   7337: aload 36
    //   7339: invokespecial 165	com/tencent/mm/plugin/appbrand/m/d:a	(Lcom/tencent/mm/plugin/appbrand/m/d$a;Ljava/lang/String;Ljava/lang/String;Ljava/net/HttpURLConnection;)V
    //   7342: ldc 167
    //   7344: invokestatic 173	com/tencent/luggage/a/e:r	(Ljava/lang/Class;)Lcom/tencent/luggage/a/d;
    //   7347: checkcast 167	com/tencent/mm/plugin/appbrand/m/o
    //   7350: aload_0
    //   7351: getfield 40	com/tencent/mm/plugin/appbrand/m/d:hrA	Lcom/tencent/mm/plugin/appbrand/jsapi/c;
    //   7354: invokeinterface 177 1 0
    //   7359: aload_1
    //   7360: getfield 180	com/tencent/mm/plugin/appbrand/m/e:isY	Ljava/lang/String;
    //   7363: aload_1
    //   7364: getfield 183	com/tencent/mm/plugin/appbrand/m/e:bxW	Ljava/lang/String;
    //   7367: aload_1
    //   7368: getfield 154	com/tencent/mm/plugin/appbrand/m/e:mUrl	Ljava/lang/String;
    //   7371: aload_1
    //   7372: invokevirtual 234	com/tencent/mm/plugin/appbrand/m/e:getDataSize	()J
    //   7375: iload 5
    //   7377: i2l
    //   7378: iload 4
    //   7380: iconst_2
    //   7381: aload_1
    //   7382: invokevirtual 187	com/tencent/mm/plugin/appbrand/m/e:aIj	()I
    //   7385: invokeinterface 190 12 0
    //   7390: invokestatic 240	com/tencent/mm/sdk/platformtools/ah:getContext	()Landroid/content/Context;
    //   7393: invokestatic 246	com/tencent/mm/sdk/platformtools/at:getNetType	(Landroid/content/Context;)I
    //   7396: istore_2
    //   7397: iload_2
    //   7398: iconst_m1
    //   7399: if_icmpne +24 -> 7423
    //   7402: ldc 197
    //   7404: invokestatic 173	com/tencent/luggage/a/e:r	(Ljava/lang/Class;)Lcom/tencent/luggage/a/d;
    //   7407: checkcast 197	com/tencent/mm/plugin/appbrand/o/a
    //   7410: ldc2_w 198
    //   7413: ldc2_w 247
    //   7416: lconst_1
    //   7417: iconst_0
    //   7418: invokeinterface 203 8 0
    //   7423: ldc 50
    //   7425: ldc 250
    //   7427: iconst_1
    //   7428: anewarray 4	java/lang/Object
    //   7431: dup
    //   7432: iconst_0
    //   7433: iload_2
    //   7434: invokestatic 256	java/lang/Integer:valueOf	(I)Ljava/lang/Integer;
    //   7437: aastore
    //   7438: invokestatic 195	com/tencent/mm/sdk/platformtools/ab:i	(Ljava/lang/String;Ljava/lang/String;[Ljava/lang/Object;)V
    //   7441: aload 28
    //   7443: ifnull +8 -> 7451
    //   7446: aload 28
    //   7448: invokevirtual 374	java/io/InputStream:close	()V
    //   7451: aload 29
    //   7453: ifnull +8 -> 7461
    //   7456: aload 29
    //   7458: invokevirtual 377	java/io/DataOutputStream:close	()V
    //   7461: aload_0
    //   7462: getfield 38	com/tencent/mm/plugin/appbrand/m/d:isA	Ljava/util/ArrayList;
    //   7465: aload_1
    //   7466: getfield 163	com/tencent/mm/plugin/appbrand/m/e:hwp	Ljava/lang/String;
    //   7469: invokevirtual 260	java/util/ArrayList:remove	(Ljava/lang/Object;)Z
    //   7472: pop
    //   7473: ldc 138
    //   7475: invokestatic 65	com/tencent/matrix/trace/core/AppMethodBeat:o	(I)V
    //   7478: return
    //   7479: astore 27
    //   7481: ldc 50
    //   7483: aload 27
    //   7485: ldc 60
    //   7487: iconst_0
    //   7488: anewarray 4	java/lang/Object
    //   7491: invokestatic 367	com/tencent/mm/sdk/platformtools/ab:printErrStackTrace	(Ljava/lang/String;Ljava/lang/Throwable;Ljava/lang/String;[Ljava/lang/Object;)V
    //   7494: goto -43 -> 7451
    //   7497: astore 27
    //   7499: ldc 50
    //   7501: aload 27
    //   7503: ldc 60
    //   7505: iconst_0
    //   7506: anewarray 4	java/lang/Object
    //   7509: invokestatic 367	com/tencent/mm/sdk/platformtools/ab:printErrStackTrace	(Ljava/lang/String;Ljava/lang/Throwable;Ljava/lang/String;[Ljava/lang/Object;)V
    //   7512: goto -61 -> 7451
    //   7515: astore 27
    //   7517: ldc 50
    //   7519: aload 27
    //   7521: ldc 60
    //   7523: iconst_0
    //   7524: anewarray 4	java/lang/Object
    //   7527: invokestatic 367	com/tencent/mm/sdk/platformtools/ab:printErrStackTrace	(Ljava/lang/String;Ljava/lang/Throwable;Ljava/lang/String;[Ljava/lang/Object;)V
    //   7530: goto -79 -> 7451
    //   7533: astore 27
    //   7535: ldc 50
    //   7537: aload 27
    //   7539: ldc 60
    //   7541: iconst_0
    //   7542: anewarray 4	java/lang/Object
    //   7545: invokestatic 367	com/tencent/mm/sdk/platformtools/ab:printErrStackTrace	(Ljava/lang/String;Ljava/lang/Throwable;Ljava/lang/String;[Ljava/lang/Object;)V
    //   7548: goto -87 -> 7461
    //   7551: astore 31
    //   7553: aconst_null
    //   7554: astore 29
    //   7556: aload 55
    //   7558: astore 28
    //   7560: iload 12
    //   7562: istore 5
    //   7564: iload 21
    //   7566: istore 4
    //   7568: iload 4
    //   7570: istore_2
    //   7571: iload 5
    //   7573: istore_3
    //   7574: aload 29
    //   7576: astore 27
    //   7578: aload 28
    //   7580: astore 30
    //   7582: ldc 197
    //   7584: invokestatic 173	com/tencent/luggage/a/e:r	(Ljava/lang/Class;)Lcom/tencent/luggage/a/d;
    //   7587: checkcast 197	com/tencent/mm/plugin/appbrand/o/a
    //   7590: ldc2_w 198
    //   7593: ldc2_w 614
    //   7596: lconst_1
    //   7597: iconst_0
    //   7598: invokeinterface 203 8 0
    //   7603: iload 4
    //   7605: istore_2
    //   7606: iload 5
    //   7608: istore_3
    //   7609: aload 29
    //   7611: astore 27
    //   7613: aload 28
    //   7615: astore 30
    //   7617: ldc 50
    //   7619: aload 31
    //   7621: ldc_w 617
    //   7624: iconst_1
    //   7625: anewarray 4	java/lang/Object
    //   7628: dup
    //   7629: iconst_0
    //   7630: aload_1
    //   7631: getfield 154	com/tencent/mm/plugin/appbrand/m/e:mUrl	Ljava/lang/String;
    //   7634: aastore
    //   7635: invokestatic 367	com/tencent/mm/sdk/platformtools/ab:printErrStackTrace	(Ljava/lang/String;Ljava/lang/Throwable;Ljava/lang/String;[Ljava/lang/Object;)V
    //   7638: iload 4
    //   7640: istore_2
    //   7641: iload 5
    //   7643: istore_3
    //   7644: aload 29
    //   7646: astore 27
    //   7648: aload 28
    //   7650: astore 30
    //   7652: aload_0
    //   7653: aload 59
    //   7655: new 575	java/lang/StringBuilder
    //   7658: dup
    //   7659: invokespecial 618	java/lang/StringBuilder:<init>	()V
    //   7662: aload 31
    //   7664: invokevirtual 621	java/lang/Exception:getMessage	()Ljava/lang/String;
    //   7667: invokevirtual 624	java/lang/StringBuilder:append	(Ljava/lang/String;)Ljava/lang/StringBuilder;
    //   7670: invokevirtual 583	java/lang/StringBuilder:toString	()Ljava/lang/String;
    //   7673: aload_1
    //   7674: getfield 163	com/tencent/mm/plugin/appbrand/m/e:hwp	Ljava/lang/String;
    //   7677: aload 37
    //   7679: invokespecial 165	com/tencent/mm/plugin/appbrand/m/d:a	(Lcom/tencent/mm/plugin/appbrand/m/d$a;Ljava/lang/String;Ljava/lang/String;Ljava/net/HttpURLConnection;)V
    //   7682: ldc 167
    //   7684: invokestatic 173	com/tencent/luggage/a/e:r	(Ljava/lang/Class;)Lcom/tencent/luggage/a/d;
    //   7687: checkcast 167	com/tencent/mm/plugin/appbrand/m/o
    //   7690: aload_0
    //   7691: getfield 40	com/tencent/mm/plugin/appbrand/m/d:hrA	Lcom/tencent/mm/plugin/appbrand/jsapi/c;
    //   7694: invokeinterface 177 1 0
    //   7699: aload_1
    //   7700: getfield 180	com/tencent/mm/plugin/appbrand/m/e:isY	Ljava/lang/String;
    //   7703: aload_1
    //   7704: getfield 183	com/tencent/mm/plugin/appbrand/m/e:bxW	Ljava/lang/String;
    //   7707: aload_1
    //   7708: getfield 154	com/tencent/mm/plugin/appbrand/m/e:mUrl	Ljava/lang/String;
    //   7711: aload_1
    //   7712: invokevirtual 234	com/tencent/mm/plugin/appbrand/m/e:getDataSize	()J
    //   7715: iload 5
    //   7717: i2l
    //   7718: iload 4
    //   7720: iconst_2
    //   7721: aload_1
    //   7722: invokevirtual 187	com/tencent/mm/plugin/appbrand/m/e:aIj	()I
    //   7725: invokeinterface 190 12 0
    //   7730: invokestatic 240	com/tencent/mm/sdk/platformtools/ah:getContext	()Landroid/content/Context;
    //   7733: invokestatic 246	com/tencent/mm/sdk/platformtools/at:getNetType	(Landroid/content/Context;)I
    //   7736: istore_2
    //   7737: iload_2
    //   7738: iconst_m1
    //   7739: if_icmpne +24 -> 7763
    //   7742: ldc 197
    //   7744: invokestatic 173	com/tencent/luggage/a/e:r	(Ljava/lang/Class;)Lcom/tencent/luggage/a/d;
    //   7747: checkcast 197	com/tencent/mm/plugin/appbrand/o/a
    //   7750: ldc2_w 198
    //   7753: ldc2_w 247
    //   7756: lconst_1
    //   7757: iconst_0
    //   7758: invokeinterface 203 8 0
    //   7763: ldc 50
    //   7765: ldc 250
    //   7767: iconst_1
    //   7768: anewarray 4	java/lang/Object
    //   7771: dup
    //   7772: iconst_0
    //   7773: iload_2
    //   7774: invokestatic 256	java/lang/Integer:valueOf	(I)Ljava/lang/Integer;
    //   7777: aastore
    //   7778: invokestatic 195	com/tencent/mm/sdk/platformtools/ab:i	(Ljava/lang/String;Ljava/lang/String;[Ljava/lang/Object;)V
    //   7781: aload 28
    //   7783: ifnull +8 -> 7791
    //   7786: aload 28
    //   7788: invokevirtual 374	java/io/InputStream:close	()V
    //   7791: aload 29
    //   7793: ifnull +8 -> 7801
    //   7796: aload 29
    //   7798: invokevirtual 377	java/io/DataOutputStream:close	()V
    //   7801: aload_0
    //   7802: getfield 38	com/tencent/mm/plugin/appbrand/m/d:isA	Ljava/util/ArrayList;
    //   7805: aload_1
    //   7806: getfield 163	com/tencent/mm/plugin/appbrand/m/e:hwp	Ljava/lang/String;
    //   7809: invokevirtual 260	java/util/ArrayList:remove	(Ljava/lang/Object;)Z
    //   7812: pop
    //   7813: ldc 138
    //   7815: invokestatic 65	com/tencent/matrix/trace/core/AppMethodBeat:o	(I)V
    //   7818: return
    //   7819: astore 27
    //   7821: ldc 50
    //   7823: aload 27
    //   7825: ldc 60
    //   7827: iconst_0
    //   7828: anewarray 4	java/lang/Object
    //   7831: invokestatic 367	com/tencent/mm/sdk/platformtools/ab:printErrStackTrace	(Ljava/lang/String;Ljava/lang/Throwable;Ljava/lang/String;[Ljava/lang/Object;)V
    //   7834: goto -43 -> 7791
    //   7837: astore 27
    //   7839: ldc 50
    //   7841: aload 27
    //   7843: ldc 60
    //   7845: iconst_0
    //   7846: anewarray 4	java/lang/Object
    //   7849: invokestatic 367	com/tencent/mm/sdk/platformtools/ab:printErrStackTrace	(Ljava/lang/String;Ljava/lang/Throwable;Ljava/lang/String;[Ljava/lang/Object;)V
    //   7852: goto -61 -> 7791
    //   7855: astore 27
    //   7857: ldc 50
    //   7859: aload 27
    //   7861: ldc 60
    //   7863: iconst_0
    //   7864: anewarray 4	java/lang/Object
    //   7867: invokestatic 367	com/tencent/mm/sdk/platformtools/ab:printErrStackTrace	(Ljava/lang/String;Ljava/lang/Throwable;Ljava/lang/String;[Ljava/lang/Object;)V
    //   7870: goto -79 -> 7791
    //   7873: astore 27
    //   7875: ldc 50
    //   7877: aload 27
    //   7879: ldc 60
    //   7881: iconst_0
    //   7882: anewarray 4	java/lang/Object
    //   7885: invokestatic 367	com/tencent/mm/sdk/platformtools/ab:printErrStackTrace	(Ljava/lang/String;Ljava/lang/Throwable;Ljava/lang/String;[Ljava/lang/Object;)V
    //   7888: goto -87 -> 7801
    //   7891: astore 27
    //   7893: ldc 50
    //   7895: aload 27
    //   7897: ldc 60
    //   7899: iconst_0
    //   7900: anewarray 4	java/lang/Object
    //   7903: invokestatic 367	com/tencent/mm/sdk/platformtools/ab:printErrStackTrace	(Ljava/lang/String;Ljava/lang/Throwable;Ljava/lang/String;[Ljava/lang/Object;)V
    //   7906: goto -1857 -> 6049
    //   7909: astore 27
    //   7911: ldc 50
    //   7913: aload 27
    //   7915: ldc 60
    //   7917: iconst_0
    //   7918: anewarray 4	java/lang/Object
    //   7921: invokestatic 367	com/tencent/mm/sdk/platformtools/ab:printErrStackTrace	(Ljava/lang/String;Ljava/lang/Throwable;Ljava/lang/String;[Ljava/lang/Object;)V
    //   7924: goto -1875 -> 6049
    //   7927: astore 27
    //   7929: ldc 50
    //   7931: aload 27
    //   7933: ldc 60
    //   7935: iconst_0
    //   7936: anewarray 4	java/lang/Object
    //   7939: invokestatic 367	com/tencent/mm/sdk/platformtools/ab:printErrStackTrace	(Ljava/lang/String;Ljava/lang/Throwable;Ljava/lang/String;[Ljava/lang/Object;)V
    //   7942: goto -1893 -> 6049
    //   7945: astore 27
    //   7947: ldc 50
    //   7949: aload 27
    //   7951: ldc 60
    //   7953: iconst_0
    //   7954: anewarray 4	java/lang/Object
    //   7957: invokestatic 367	com/tencent/mm/sdk/platformtools/ab:printErrStackTrace	(Ljava/lang/String;Ljava/lang/Throwable;Ljava/lang/String;[Ljava/lang/Object;)V
    //   7960: goto -1901 -> 6059
    //   7963: astore 28
    //   7965: aconst_null
    //   7966: astore 29
    //   7968: iload 4
    //   7970: istore_3
    //   7971: aload 57
    //   7973: astore 30
    //   7975: goto -2033 -> 5942
    //   7978: astore 28
    //   7980: iload 4
    //   7982: istore_3
    //   7983: aload 27
    //   7985: astore 29
    //   7987: aload 57
    //   7989: astore 30
    //   7991: goto -2049 -> 5942
    //   7994: astore 28
    //   7996: iload 4
    //   7998: istore_3
    //   7999: aload 31
    //   8001: astore 30
    //   8003: goto -2061 -> 5942
    //   8006: astore 28
    //   8008: aload 27
    //   8010: astore 30
    //   8012: goto -2070 -> 5942
    //   8015: astore 28
    //   8017: aload 27
    //   8019: astore 30
    //   8021: goto -2079 -> 5942
    //   8024: astore 28
    //   8026: iload_2
    //   8027: istore 4
    //   8029: aload 29
    //   8031: astore 30
    //   8033: iload_3
    //   8034: istore_2
    //   8035: iload 4
    //   8037: istore_3
    //   8038: aload 27
    //   8040: astore 29
    //   8042: goto -2100 -> 5942
    //   8045: astore 31
    //   8047: iload 21
    //   8049: istore 4
    //   8051: aload 28
    //   8053: astore 37
    //   8055: iload 12
    //   8057: istore 5
    //   8059: aload 27
    //   8061: astore 29
    //   8063: aload 55
    //   8065: astore 28
    //   8067: goto -499 -> 7568
    //   8070: astore 31
    //   8072: iload 21
    //   8074: istore 4
    //   8076: aload 28
    //   8078: astore 37
    //   8080: iload 12
    //   8082: istore 5
    //   8084: aload 55
    //   8086: astore 28
    //   8088: goto -520 -> 7568
    //   8091: astore 31
    //   8093: iload_2
    //   8094: istore 4
    //   8096: aload 28
    //   8098: astore 37
    //   8100: iload 12
    //   8102: istore 5
    //   8104: aload 38
    //   8106: astore 28
    //   8108: goto -540 -> 7568
    //   8111: astore 31
    //   8113: iload_2
    //   8114: istore 4
    //   8116: aload 28
    //   8118: astore 37
    //   8120: iload_3
    //   8121: istore 5
    //   8123: aload 27
    //   8125: astore 28
    //   8127: goto -559 -> 7568
    //   8130: astore 31
    //   8132: iload_2
    //   8133: istore 4
    //   8135: aload 28
    //   8137: astore 37
    //   8139: iload_3
    //   8140: istore 5
    //   8142: aload 27
    //   8144: astore 28
    //   8146: goto -578 -> 7568
    //   8149: astore 31
    //   8151: iload 20
    //   8153: istore 4
    //   8155: aload 28
    //   8157: astore 36
    //   8159: iload 11
    //   8161: istore 5
    //   8163: aload 27
    //   8165: astore 29
    //   8167: aload 54
    //   8169: astore 28
    //   8171: goto -928 -> 7243
    //   8174: astore 31
    //   8176: iload 20
    //   8178: istore 4
    //   8180: aload 28
    //   8182: astore 36
    //   8184: iload 11
    //   8186: istore 5
    //   8188: aload 54
    //   8190: astore 28
    //   8192: goto -949 -> 7243
    //   8195: astore 31
    //   8197: iload_2
    //   8198: istore 4
    //   8200: aload 28
    //   8202: astore 36
    //   8204: iload 11
    //   8206: istore 5
    //   8208: aload 30
    //   8210: astore 28
    //   8212: goto -969 -> 7243
    //   8215: astore 31
    //   8217: iload_2
    //   8218: istore 4
    //   8220: aload 28
    //   8222: astore 36
    //   8224: iload_3
    //   8225: istore 5
    //   8227: aload 27
    //   8229: astore 28
    //   8231: goto -988 -> 7243
    //   8234: astore 31
    //   8236: iload_2
    //   8237: istore 4
    //   8239: aload 28
    //   8241: astore 36
    //   8243: iload_3
    //   8244: istore 5
    //   8246: aload 27
    //   8248: astore 28
    //   8250: goto -1007 -> 7243
    //   8253: astore 31
    //   8255: iload 19
    //   8257: istore 4
    //   8259: aload 28
    //   8261: astore 35
    //   8263: iload 10
    //   8265: istore 5
    //   8267: aload 27
    //   8269: astore 29
    //   8271: aload 53
    //   8273: astore 28
    //   8275: goto -1357 -> 6918
    //   8278: astore 31
    //   8280: iload 19
    //   8282: istore 4
    //   8284: aload 28
    //   8286: astore 35
    //   8288: iload 10
    //   8290: istore 5
    //   8292: aload 53
    //   8294: astore 28
    //   8296: goto -1378 -> 6918
    //   8299: astore 31
    //   8301: iload_2
    //   8302: istore 4
    //   8304: aload 28
    //   8306: astore 35
    //   8308: iload 10
    //   8310: istore 5
    //   8312: aload 32
    //   8314: astore 28
    //   8316: goto -1398 -> 6918
    //   8319: astore 31
    //   8321: iload_2
    //   8322: istore 4
    //   8324: aload 28
    //   8326: astore 35
    //   8328: iload_3
    //   8329: istore 5
    //   8331: aload 27
    //   8333: astore 28
    //   8335: goto -1417 -> 6918
    //   8338: astore 31
    //   8340: iload_2
    //   8341: istore 4
    //   8343: aload 28
    //   8345: astore 35
    //   8347: iload_3
    //   8348: istore 5
    //   8350: aload 27
    //   8352: astore 28
    //   8354: goto -1436 -> 6918
    //   8357: astore 31
    //   8359: iload 18
    //   8361: istore 4
    //   8363: aload 28
    //   8365: astore 34
    //   8367: iload 9
    //   8369: istore 5
    //   8371: aload 27
    //   8373: astore 29
    //   8375: aload 52
    //   8377: astore 28
    //   8379: goto -1786 -> 6593
    //   8382: astore 31
    //   8384: iload 18
    //   8386: istore 4
    //   8388: aload 28
    //   8390: astore 34
    //   8392: iload 9
    //   8394: istore 5
    //   8396: aload 52
    //   8398: astore 28
    //   8400: goto -1807 -> 6593
    //   8403: astore 31
    //   8405: iload_2
    //   8406: istore 4
    //   8408: aload 28
    //   8410: astore 34
    //   8412: iload 9
    //   8414: istore 5
    //   8416: aload 33
    //   8418: astore 28
    //   8420: goto -1827 -> 6593
    //   8423: astore 31
    //   8425: iload_2
    //   8426: istore 4
    //   8428: aload 28
    //   8430: astore 34
    //   8432: iload_3
    //   8433: istore 5
    //   8435: aload 27
    //   8437: astore 28
    //   8439: goto -1846 -> 6593
    //   8442: astore 31
    //   8444: iload_2
    //   8445: istore 4
    //   8447: aload 28
    //   8449: astore 34
    //   8451: iload_3
    //   8452: istore 5
    //   8454: aload 27
    //   8456: astore 28
    //   8458: goto -1865 -> 6593
    //   8461: astore 31
    //   8463: iload 17
    //   8465: istore 4
    //   8467: aload 28
    //   8469: astore 33
    //   8471: iload 8
    //   8473: istore 5
    //   8475: aload 27
    //   8477: astore 29
    //   8479: aload 51
    //   8481: astore 28
    //   8483: goto -2215 -> 6268
    //   8486: astore 31
    //   8488: iload 17
    //   8490: istore 4
    //   8492: aload 28
    //   8494: astore 33
    //   8496: iload 8
    //   8498: istore 5
    //   8500: aload 51
    //   8502: astore 28
    //   8504: goto -2236 -> 6268
    //   8507: astore 31
    //   8509: iload_2
    //   8510: istore 4
    //   8512: aload 28
    //   8514: astore 33
    //   8516: iload 8
    //   8518: istore 5
    //   8520: aload 34
    //   8522: astore 28
    //   8524: goto -2256 -> 6268
    //   8527: astore 31
    //   8529: iload_2
    //   8530: istore 4
    //   8532: aload 28
    //   8534: astore 33
    //   8536: iload_3
    //   8537: istore 5
    //   8539: aload 27
    //   8541: astore 28
    //   8543: goto -2275 -> 6268
    //   8546: astore 31
    //   8548: iload_2
    //   8549: istore 4
    //   8551: aload 28
    //   8553: astore 33
    //   8555: iload_3
    //   8556: istore 5
    //   8558: aload 27
    //   8560: astore 28
    //   8562: goto -2294 -> 6268
    //   8565: astore 31
    //   8567: iload 16
    //   8569: istore 4
    //   8571: aload 28
    //   8573: astore 32
    //   8575: iload 7
    //   8577: istore 5
    //   8579: aload 27
    //   8581: astore 29
    //   8583: aload 50
    //   8585: astore 28
    //   8587: goto -3035 -> 5552
    //   8590: astore 31
    //   8592: iload 16
    //   8594: istore 4
    //   8596: aload 28
    //   8598: astore 32
    //   8600: iload 7
    //   8602: istore 5
    //   8604: aload 50
    //   8606: astore 28
    //   8608: goto -3056 -> 5552
    //   8611: astore 31
    //   8613: iload_2
    //   8614: istore 4
    //   8616: aload 28
    //   8618: astore 32
    //   8620: iload 7
    //   8622: istore 5
    //   8624: aload 35
    //   8626: astore 28
    //   8628: goto -3076 -> 5552
    //   8631: astore 31
    //   8633: iload_2
    //   8634: istore 4
    //   8636: aload 28
    //   8638: astore 32
    //   8640: iload_3
    //   8641: istore 5
    //   8643: aload 27
    //   8645: astore 28
    //   8647: goto -3095 -> 5552
    //   8650: astore 31
    //   8652: iload_2
    //   8653: istore 4
    //   8655: aload 28
    //   8657: astore 32
    //   8659: iload_3
    //   8660: istore 5
    //   8662: aload 27
    //   8664: astore 28
    //   8666: goto -3114 -> 5552
    //   8669: astore 31
    //   8671: iload 15
    //   8673: istore 4
    //   8675: aload 28
    //   8677: astore 32
    //   8679: iload 6
    //   8681: istore 5
    //   8683: aload 27
    //   8685: astore 29
    //   8687: aload 49
    //   8689: astore 28
    //   8691: goto -3464 -> 5227
    //   8694: astore 31
    //   8696: iload 15
    //   8698: istore 4
    //   8700: aload 28
    //   8702: astore 32
    //   8704: iload 6
    //   8706: istore 5
    //   8708: aload 49
    //   8710: astore 28
    //   8712: goto -3485 -> 5227
    //   8715: astore 31
    //   8717: iload_2
    //   8718: istore 4
    //   8720: aload 28
    //   8722: astore 32
    //   8724: iload 6
    //   8726: istore 5
    //   8728: aload 36
    //   8730: astore 28
    //   8732: goto -3505 -> 5227
    //   8735: astore 31
    //   8737: iload_2
    //   8738: istore 4
    //   8740: aload 28
    //   8742: astore 32
    //   8744: iload_3
    //   8745: istore 5
    //   8747: aload 27
    //   8749: astore 28
    //   8751: goto -3524 -> 5227
    //   8754: astore 31
    //   8756: iload_2
    //   8757: istore 4
    //   8759: aload 28
    //   8761: astore 32
    //   8763: iload_3
    //   8764: istore 5
    //   8766: aload 27
    //   8768: astore 28
    //   8770: goto -3543 -> 5227
    //   8773: astore 31
    //   8775: iload 14
    //   8777: istore 4
    //   8779: aload 28
    //   8781: astore 32
    //   8783: aload 27
    //   8785: astore 29
    //   8787: aload 38
    //   8789: astore 28
    //   8791: goto -6725 -> 2066
    //   8794: astore 31
    //   8796: iload 14
    //   8798: istore 4
    //   8800: aload 28
    //   8802: astore 32
    //   8804: aload 38
    //   8806: astore 28
    //   8808: goto -6742 -> 2066
    //   8811: astore 31
    //   8813: iload_2
    //   8814: istore 4
    //   8816: aload 28
    //   8818: astore 32
    //   8820: aload 37
    //   8822: astore 28
    //   8824: goto -6758 -> 2066
    //   8827: astore 31
    //   8829: iload_2
    //   8830: istore 4
    //   8832: aload 28
    //   8834: astore 32
    //   8836: iload_3
    //   8837: istore 5
    //   8839: aload 27
    //   8841: astore 28
    //   8843: goto -6777 -> 2066
    //   8846: astore 31
    //   8848: iload_2
    //   8849: istore 4
    //   8851: aload 28
    //   8853: astore 32
    //   8855: iload_3
    //   8856: istore 5
    //   8858: aload 27
    //   8860: astore 28
    //   8862: goto -6796 -> 2066
    //   8865: astore 30
    //   8867: iconst_0
    //   8868: istore_2
    //   8869: aconst_null
    //   8870: astore 29
    //   8872: iload 13
    //   8874: istore_3
    //   8875: goto -7064 -> 1811
    //   8878: astore 30
    //   8880: iconst_0
    //   8881: istore_2
    //   8882: aload 29
    //   8884: astore 27
    //   8886: aconst_null
    //   8887: astore 29
    //   8889: iload 13
    //   8891: istore_3
    //   8892: goto -7081 -> 1811
    //   8895: astore 30
    //   8897: iload_2
    //   8898: istore_3
    //   8899: iconst_0
    //   8900: istore_2
    //   8901: aload 27
    //   8903: astore 31
    //   8905: aload 29
    //   8907: astore 27
    //   8909: aload 31
    //   8911: astore 29
    //   8913: goto -7102 -> 1811
    //   8916: astore 30
    //   8918: iload_2
    //   8919: istore 4
    //   8921: iload_3
    //   8922: istore_2
    //   8923: aload 27
    //   8925: astore 31
    //   8927: iload 4
    //   8929: istore_3
    //   8930: aload 29
    //   8932: astore 27
    //   8934: aload 31
    //   8936: astore 29
    //   8938: goto -7127 -> 1811
    //   8941: astore 30
    //   8943: iload_2
    //   8944: istore 4
    //   8946: iload_3
    //   8947: istore_2
    //   8948: aload 27
    //   8950: astore 31
    //   8952: iload 4
    //   8954: istore_3
    //   8955: aload 29
    //   8957: astore 27
    //   8959: aload 31
    //   8961: astore 29
    //   8963: goto -7152 -> 1811
    //   8966: iconst_0
    //   8967: istore_3
    //   8968: goto -4102 -> 4866
    // Local variable table:
    //   start	length	slot	name	signature
    //   0	8971	0	this	d
    //   0	8971	1	parame	e
    //   147	8801	2	i	int
    //   1810	7158	3	j	int
    //   114	8839	4	k	int
    //   132	8725	5	m	int
    //   105	8620	6	n	int
    //   108	8513	7	i1	int
    //   117	8400	8	i2	int
    //   120	8293	9	i3	int
    //   123	8186	10	i4	int
    //   126	8079	11	i5	int
    //   129	7972	12	i6	int
    //   164	8726	13	i7	int
    //   135	8662	14	i8	int
    //   138	8559	15	i9	int
    //   141	8452	16	i10	int
    //   149	8340	17	i11	int
    //   152	8233	18	i12	int
    //   155	8126	19	i13	int
    //   158	8019	20	i14	int
    //   161	7912	21	i15	int
    //   111	3247	22	i16	int
    //   144	3193	23	i17	int
    //   2696	3	24	i18	int
    //   4061	643	25	l	long
    //   102	3223	27	localObject1	Object
    //   3334	1	27	localIOException1	java.io.IOException
    //   3344	1	27	localObject2	Object
    //   3363	123	27	localIOException2	java.io.IOException
    //   3756	5	27	localIOException3	java.io.IOException
    //   3966	419	27	localObject3	Object
    //   4389	50	27	localException1	Exception
    //   4537	43	27	localObject4	Object
    //   4584	41	27	localException2	Exception
    //   4638	54	27	localObject5	Object
    //   4708	5	27	localIOException4	java.io.IOException
    //   4726	5	27	localArrayIndexOutOfBoundsException1	java.lang.ArrayIndexOutOfBoundsException
    //   4744	5	27	localThrowable1	java.lang.Throwable
    //   4762	176	27	localIOException5	java.io.IOException
    //   4986	5	27	localIOException6	java.io.IOException
    //   5004	5	27	localArrayIndexOutOfBoundsException2	java.lang.ArrayIndexOutOfBoundsException
    //   5022	5	27	localThrowable2	java.lang.Throwable
    //   5040	5	27	localIOException7	java.io.IOException
    //   5112	5	27	localIOException8	java.io.IOException
    //   5130	5	27	localIOException9	java.io.IOException
    //   5148	5	27	localArrayIndexOutOfBoundsException3	java.lang.ArrayIndexOutOfBoundsException
    //   5166	5	27	localThrowable3	java.lang.Throwable
    //   5184	5	27	localIOException10	java.io.IOException
    //   5202	22	27	localFileNotFoundException1	java.io.FileNotFoundException
    //   5235	71	27	localObject6	Object
    //   5463	5	27	localIOException11	java.io.IOException
    //   5481	5	27	localArrayIndexOutOfBoundsException4	java.lang.ArrayIndexOutOfBoundsException
    //   5499	5	27	localThrowable4	java.lang.Throwable
    //   5517	5	27	localIOException12	java.io.IOException
    //   5560	590	27	localObject7	Object
    //   6179	5	27	localIOException13	java.io.IOException
    //   6197	5	27	localArrayIndexOutOfBoundsException5	java.lang.ArrayIndexOutOfBoundsException
    //   6215	5	27	localThrowable5	java.lang.Throwable
    //   6233	5	27	localIOException14	java.io.IOException
    //   6276	71	27	localObject8	Object
    //   6504	5	27	localIOException15	java.io.IOException
    //   6522	5	27	localArrayIndexOutOfBoundsException6	java.lang.ArrayIndexOutOfBoundsException
    //   6540	5	27	localThrowable6	java.lang.Throwable
    //   6558	5	27	localIOException16	java.io.IOException
    //   6601	71	27	localObject9	Object
    //   6829	5	27	localIOException17	java.io.IOException
    //   6847	5	27	localArrayIndexOutOfBoundsException7	java.lang.ArrayIndexOutOfBoundsException
    //   6865	5	27	localThrowable7	java.lang.Throwable
    //   6883	5	27	localIOException18	java.io.IOException
    //   6926	71	27	localObject10	Object
    //   7154	5	27	localIOException19	java.io.IOException
    //   7172	5	27	localArrayIndexOutOfBoundsException8	java.lang.ArrayIndexOutOfBoundsException
    //   7190	5	27	localThrowable8	java.lang.Throwable
    //   7208	5	27	localIOException20	java.io.IOException
    //   7251	71	27	localObject11	Object
    //   7479	5	27	localIOException21	java.io.IOException
    //   7497	5	27	localArrayIndexOutOfBoundsException9	java.lang.ArrayIndexOutOfBoundsException
    //   7515	5	27	localThrowable9	java.lang.Throwable
    //   7533	5	27	localIOException22	java.io.IOException
    //   7576	71	27	localObject12	Object
    //   7819	5	27	localIOException23	java.io.IOException
    //   7837	5	27	localArrayIndexOutOfBoundsException10	java.lang.ArrayIndexOutOfBoundsException
    //   7855	5	27	localThrowable10	java.lang.Throwable
    //   7873	5	27	localIOException24	java.io.IOException
    //   7891	5	27	localIOException25	java.io.IOException
    //   7909	5	27	localArrayIndexOutOfBoundsException11	java.lang.ArrayIndexOutOfBoundsException
    //   7927	5	27	localThrowable11	java.lang.Throwable
    //   7945	914	27	localIOException26	java.io.IOException
    //   8884	74	27	localObject13	Object
    //   336	4546	28	localObject14	Object
    //   5058	5	28	localIOException27	java.io.IOException
    //   5076	5	28	localArrayIndexOutOfBoundsException12	java.lang.ArrayIndexOutOfBoundsException
    //   5094	5	28	localThrowable12	java.lang.Throwable
    //   5209	700	28	localObject15	Object
    //   5936	216	28	localObject16	Object
    //   6258	1529	28	localObject17	Object
    //   7963	1	28	localObject18	Object
    //   7978	1	28	localObject19	Object
    //   7994	1	28	localObject20	Object
    //   8006	1	28	localObject21	Object
    //   8015	1	28	localObject22	Object
    //   8024	28	28	localObject23	Object
    //   8065	796	28	localObject24	Object
    //   30	8932	29	localObject25	Object
    //   6	1713	30	localObject26	Object
    //   1790	43	30	localUnsupportedEncodingException1	java.io.UnsupportedEncodingException
    //   2007	2590	30	localObject27	Object
    //   4643	1	30	localUnsupportedEncodingException2	java.io.UnsupportedEncodingException
    //   4669	3540	30	localObject28	Object
    //   8865	1	30	localUnsupportedEncodingException3	java.io.UnsupportedEncodingException
    //   8878	1	30	localUnsupportedEncodingException4	java.io.UnsupportedEncodingException
    //   8895	1	30	localUnsupportedEncodingException5	java.io.UnsupportedEncodingException
    //   8916	1	30	localUnsupportedEncodingException6	java.io.UnsupportedEncodingException
    //   8941	1	30	localUnsupportedEncodingException7	java.io.UnsupportedEncodingException
    //   9	2003	31	localObject29	Object
    //   2049	69	31	localSSLHandshakeException1	javax.net.ssl.SSLHandshakeException
    //   2312	2967	31	localObject30	Object
    //   5535	128	31	localSocketTimeoutException1	java.net.SocketTimeoutException
    //   6251	69	31	localConnectException1	java.net.ConnectException
    //   6576	69	31	localProtocolException1	java.net.ProtocolException
    //   6901	69	31	localArrayIndexOutOfBoundsException13	java.lang.ArrayIndexOutOfBoundsException
    //   7226	69	31	localUnknownHostException1	java.net.UnknownHostException
    //   7551	449	31	localException3	Exception
    //   8045	1	31	localException4	Exception
    //   8070	1	31	localException5	Exception
    //   8091	1	31	localException6	Exception
    //   8111	1	31	localException7	Exception
    //   8130	1	31	localException8	Exception
    //   8149	1	31	localUnknownHostException2	java.net.UnknownHostException
    //   8174	1	31	localUnknownHostException3	java.net.UnknownHostException
    //   8195	1	31	localUnknownHostException4	java.net.UnknownHostException
    //   8215	1	31	localUnknownHostException5	java.net.UnknownHostException
    //   8234	1	31	localUnknownHostException6	java.net.UnknownHostException
    //   8253	1	31	localArrayIndexOutOfBoundsException14	java.lang.ArrayIndexOutOfBoundsException
    //   8278	1	31	localArrayIndexOutOfBoundsException15	java.lang.ArrayIndexOutOfBoundsException
    //   8299	1	31	localArrayIndexOutOfBoundsException16	java.lang.ArrayIndexOutOfBoundsException
    //   8319	1	31	localArrayIndexOutOfBoundsException17	java.lang.ArrayIndexOutOfBoundsException
    //   8338	1	31	localArrayIndexOutOfBoundsException18	java.lang.ArrayIndexOutOfBoundsException
    //   8357	1	31	localProtocolException2	java.net.ProtocolException
    //   8382	1	31	localProtocolException3	java.net.ProtocolException
    //   8403	1	31	localProtocolException4	java.net.ProtocolException
    //   8423	1	31	localProtocolException5	java.net.ProtocolException
    //   8442	1	31	localProtocolException6	java.net.ProtocolException
    //   8461	1	31	localConnectException2	java.net.ConnectException
    //   8486	1	31	localConnectException3	java.net.ConnectException
    //   8507	1	31	localConnectException4	java.net.ConnectException
    //   8527	1	31	localConnectException5	java.net.ConnectException
    //   8546	1	31	localConnectException6	java.net.ConnectException
    //   8565	1	31	localSocketTimeoutException2	java.net.SocketTimeoutException
    //   8590	1	31	localSocketTimeoutException3	java.net.SocketTimeoutException
    //   8611	1	31	localSocketTimeoutException4	java.net.SocketTimeoutException
    //   8631	1	31	localSocketTimeoutException5	java.net.SocketTimeoutException
    //   8650	1	31	localSocketTimeoutException6	java.net.SocketTimeoutException
    //   8669	1	31	localFileNotFoundException2	java.io.FileNotFoundException
    //   8694	1	31	localFileNotFoundException3	java.io.FileNotFoundException
    //   8715	1	31	localFileNotFoundException4	java.io.FileNotFoundException
    //   8735	1	31	localFileNotFoundException5	java.io.FileNotFoundException
    //   8754	1	31	localFileNotFoundException6	java.io.FileNotFoundException
    //   8773	1	31	localSSLHandshakeException2	javax.net.ssl.SSLHandshakeException
    //   8794	1	31	localSSLHandshakeException3	javax.net.ssl.SSLHandshakeException
    //   8811	1	31	localSSLHandshakeException4	javax.net.ssl.SSLHandshakeException
    //   8827	1	31	localSSLHandshakeException5	javax.net.ssl.SSLHandshakeException
    //   8846	1	31	localSSLHandshakeException6	javax.net.ssl.SSLHandshakeException
    //   8903	57	31	localObject31	Object
    //   12	8842	32	localObject32	Object
    //   15	8539	33	localObject33	Object
    //   18	8503	34	localObject34	Object
    //   21	8604	35	localObject35	Object
    //   24	8705	36	localObject36	Object
    //   27	8794	37	localObject37	Object
    //   90	8715	38	localObject38	Object
    //   33	4750	39	arrayOfByte	byte[]
    //   63	4524	40	localObject39	Object
    //   66	4525	41	localObject40	Object
    //   69	4526	42	localObject41	Object
    //   72	4527	43	localObject42	Object
    //   75	4528	44	localObject43	Object
    //   78	4529	45	localObject44	Object
    //   81	4530	46	localObject45	Object
    //   84	4531	47	localObject46	Object
    //   87	4532	48	localObject47	Object
    //   36	8673	49	localJSONObject	JSONObject
    //   39	8566	50	localByteArrayOutputStream	java.io.ByteArrayOutputStream
    //   48	8453	51	localObject48	Object
    //   51	8346	52	localObject49	Object
    //   54	8239	53	localObject50	Object
    //   57	8132	54	localObject51	Object
    //   60	8025	55	localObject52	Object
    //   42	3305	56	localObject53	Object
    //   45	7943	57	localObject54	Object
    //   170	2481	58	localObject55	Object
    //   96	7558	59	locala	d.a
    // Exception table:
    //   from	to	target	type
    //   319	338	1790	java/io/UnsupportedEncodingException
    //   374	384	1790	java/io/UnsupportedEncodingException
    //   420	426	1790	java/io/UnsupportedEncodingException
    //   467	488	1790	java/io/UnsupportedEncodingException
    //   524	549	1790	java/io/UnsupportedEncodingException
    //   699	707	1790	java/io/UnsupportedEncodingException
    //   743	750	1790	java/io/UnsupportedEncodingException
    //   786	801	1790	java/io/UnsupportedEncodingException
    //   837	853	1790	java/io/UnsupportedEncodingException
    //   889	896	1790	java/io/UnsupportedEncodingException
    //   932	954	1790	java/io/UnsupportedEncodingException
    //   990	999	1790	java/io/UnsupportedEncodingException
    //   1035	1044	1790	java/io/UnsupportedEncodingException
    //   1080	1091	1790	java/io/UnsupportedEncodingException
    //   1127	1133	1790	java/io/UnsupportedEncodingException
    //   1169	1177	1790	java/io/UnsupportedEncodingException
    //   1213	1225	1790	java/io/UnsupportedEncodingException
    //   1261	1269	1790	java/io/UnsupportedEncodingException
    //   1305	1315	1790	java/io/UnsupportedEncodingException
    //   1351	1358	1790	java/io/UnsupportedEncodingException
    //   1394	1400	1790	java/io/UnsupportedEncodingException
    //   1436	1447	1790	java/io/UnsupportedEncodingException
    //   1488	1507	1790	java/io/UnsupportedEncodingException
    //   1543	1557	1790	java/io/UnsupportedEncodingException
    //   1593	1603	1790	java/io/UnsupportedEncodingException
    //   1639	1651	1790	java/io/UnsupportedEncodingException
    //   1687	1712	1790	java/io/UnsupportedEncodingException
    //   1748	1787	1790	java/io/UnsupportedEncodingException
    //   2037	2046	1790	java/io/UnsupportedEncodingException
    //   2338	2350	1790	java/io/UnsupportedEncodingException
    //   2386	2396	1790	java/io/UnsupportedEncodingException
    //   2432	2440	1790	java/io/UnsupportedEncodingException
    //   2476	2492	1790	java/io/UnsupportedEncodingException
    //   2528	2534	1790	java/io/UnsupportedEncodingException
    //   2570	2577	1790	java/io/UnsupportedEncodingException
    //   2613	2627	1790	java/io/UnsupportedEncodingException
    //   3317	3324	1790	java/io/UnsupportedEncodingException
    //   319	338	2049	javax/net/ssl/SSLHandshakeException
    //   374	384	2049	javax/net/ssl/SSLHandshakeException
    //   420	426	2049	javax/net/ssl/SSLHandshakeException
    //   467	488	2049	javax/net/ssl/SSLHandshakeException
    //   524	549	2049	javax/net/ssl/SSLHandshakeException
    //   699	707	2049	javax/net/ssl/SSLHandshakeException
    //   743	750	2049	javax/net/ssl/SSLHandshakeException
    //   786	801	2049	javax/net/ssl/SSLHandshakeException
    //   837	853	2049	javax/net/ssl/SSLHandshakeException
    //   889	896	2049	javax/net/ssl/SSLHandshakeException
    //   932	954	2049	javax/net/ssl/SSLHandshakeException
    //   990	999	2049	javax/net/ssl/SSLHandshakeException
    //   1035	1044	2049	javax/net/ssl/SSLHandshakeException
    //   1080	1091	2049	javax/net/ssl/SSLHandshakeException
    //   1127	1133	2049	javax/net/ssl/SSLHandshakeException
    //   1169	1177	2049	javax/net/ssl/SSLHandshakeException
    //   1213	1225	2049	javax/net/ssl/SSLHandshakeException
    //   1261	1269	2049	javax/net/ssl/SSLHandshakeException
    //   1305	1315	2049	javax/net/ssl/SSLHandshakeException
    //   1351	1358	2049	javax/net/ssl/SSLHandshakeException
    //   1394	1400	2049	javax/net/ssl/SSLHandshakeException
    //   1436	1447	2049	javax/net/ssl/SSLHandshakeException
    //   1488	1507	2049	javax/net/ssl/SSLHandshakeException
    //   1543	1557	2049	javax/net/ssl/SSLHandshakeException
    //   1593	1603	2049	javax/net/ssl/SSLHandshakeException
    //   1639	1651	2049	javax/net/ssl/SSLHandshakeException
    //   1687	1712	2049	javax/net/ssl/SSLHandshakeException
    //   1748	1787	2049	javax/net/ssl/SSLHandshakeException
    //   2037	2046	2049	javax/net/ssl/SSLHandshakeException
    //   2338	2350	2049	javax/net/ssl/SSLHandshakeException
    //   2386	2396	2049	javax/net/ssl/SSLHandshakeException
    //   2432	2440	2049	javax/net/ssl/SSLHandshakeException
    //   2476	2492	2049	javax/net/ssl/SSLHandshakeException
    //   2528	2534	2049	javax/net/ssl/SSLHandshakeException
    //   2570	2577	2049	javax/net/ssl/SSLHandshakeException
    //   2613	2627	2049	javax/net/ssl/SSLHandshakeException
    //   3317	3324	2049	javax/net/ssl/SSLHandshakeException
    //   2691	2698	3334	java/io/IOException
    //   3258	3263	3363	java/io/IOException
    //   3733	3738	3756	java/io/IOException
    //   3908	3922	4389	java/lang/Exception
    //   3954	3968	4389	java/lang/Exception
    //   4379	4386	4389	java/lang/Exception
    //   4479	4493	4584	java/lang/Exception
    //   4525	4539	4584	java/lang/Exception
    //   4574	4581	4584	java/lang/Exception
    //   2737	2744	4643	java/io/UnsupportedEncodingException
    //   2780	2789	4643	java/io/UnsupportedEncodingException
    //   2825	2851	4643	java/io/UnsupportedEncodingException
    //   2894	2920	4643	java/io/UnsupportedEncodingException
    //   2956	2963	4643	java/io/UnsupportedEncodingException
    //   2999	3006	4643	java/io/UnsupportedEncodingException
    //   3042	3047	4643	java/io/UnsupportedEncodingException
    //   3083	3091	4643	java/io/UnsupportedEncodingException
    //   3131	3151	4643	java/io/UnsupportedEncodingException
    //   3187	3208	4643	java/io/UnsupportedEncodingException
    //   3417	3448	4643	java/io/UnsupportedEncodingException
    //   3484	3490	4643	java/io/UnsupportedEncodingException
    //   3526	3533	4643	java/io/UnsupportedEncodingException
    //   3569	3591	4643	java/io/UnsupportedEncodingException
    //   3627	3632	4643	java/io/UnsupportedEncodingException
    //   3810	3831	4643	java/io/UnsupportedEncodingException
    //   3867	3876	4643	java/io/UnsupportedEncodingException
    //   3908	3922	4643	java/io/UnsupportedEncodingException
    //   3954	3968	4643	java/io/UnsupportedEncodingException
    //   4379	4386	4643	java/io/UnsupportedEncodingException
    //   4427	4447	4643	java/io/UnsupportedEncodingException
    //   4479	4493	4643	java/io/UnsupportedEncodingException
    //   4525	4539	4643	java/io/UnsupportedEncodingException
    //   4574	4581	4643	java/io/UnsupportedEncodingException
    //   4622	4636	4643	java/io/UnsupportedEncodingException
    //   4314	4319	4708	java/io/IOException
    //   4314	4319	4726	java/lang/ArrayIndexOutOfBoundsException
    //   4314	4319	4744	java/lang/Throwable
    //   4324	4329	4762	java/io/IOException
    //   4937	4942	4986	java/io/IOException
    //   4937	4942	5004	java/lang/ArrayIndexOutOfBoundsException
    //   4937	4942	5022	java/lang/Throwable
    //   4947	4952	5040	java/io/IOException
    //   1968	1973	5058	java/io/IOException
    //   1968	1973	5076	java/lang/ArrayIndexOutOfBoundsException
    //   1968	1973	5094	java/lang/Throwable
    //   1978	1983	5112	java/io/IOException
    //   2269	2274	5130	java/io/IOException
    //   2269	2274	5148	java/lang/ArrayIndexOutOfBoundsException
    //   2269	2274	5166	java/lang/Throwable
    //   2279	2284	5184	java/io/IOException
    //   319	338	5202	java/io/FileNotFoundException
    //   374	384	5202	java/io/FileNotFoundException
    //   420	426	5202	java/io/FileNotFoundException
    //   467	488	5202	java/io/FileNotFoundException
    //   524	549	5202	java/io/FileNotFoundException
    //   699	707	5202	java/io/FileNotFoundException
    //   743	750	5202	java/io/FileNotFoundException
    //   786	801	5202	java/io/FileNotFoundException
    //   837	853	5202	java/io/FileNotFoundException
    //   889	896	5202	java/io/FileNotFoundException
    //   932	954	5202	java/io/FileNotFoundException
    //   990	999	5202	java/io/FileNotFoundException
    //   1035	1044	5202	java/io/FileNotFoundException
    //   1080	1091	5202	java/io/FileNotFoundException
    //   1127	1133	5202	java/io/FileNotFoundException
    //   1169	1177	5202	java/io/FileNotFoundException
    //   1213	1225	5202	java/io/FileNotFoundException
    //   1261	1269	5202	java/io/FileNotFoundException
    //   1305	1315	5202	java/io/FileNotFoundException
    //   1351	1358	5202	java/io/FileNotFoundException
    //   1394	1400	5202	java/io/FileNotFoundException
    //   1436	1447	5202	java/io/FileNotFoundException
    //   1488	1507	5202	java/io/FileNotFoundException
    //   1543	1557	5202	java/io/FileNotFoundException
    //   1593	1603	5202	java/io/FileNotFoundException
    //   1639	1651	5202	java/io/FileNotFoundException
    //   1687	1712	5202	java/io/FileNotFoundException
    //   1748	1787	5202	java/io/FileNotFoundException
    //   2037	2046	5202	java/io/FileNotFoundException
    //   2338	2350	5202	java/io/FileNotFoundException
    //   2386	2396	5202	java/io/FileNotFoundException
    //   2432	2440	5202	java/io/FileNotFoundException
    //   2476	2492	5202	java/io/FileNotFoundException
    //   2528	2534	5202	java/io/FileNotFoundException
    //   2570	2577	5202	java/io/FileNotFoundException
    //   2613	2627	5202	java/io/FileNotFoundException
    //   3317	3324	5202	java/io/FileNotFoundException
    //   5430	5435	5463	java/io/IOException
    //   5430	5435	5481	java/lang/ArrayIndexOutOfBoundsException
    //   5430	5435	5499	java/lang/Throwable
    //   5440	5445	5517	java/io/IOException
    //   319	338	5535	java/net/SocketTimeoutException
    //   374	384	5535	java/net/SocketTimeoutException
    //   420	426	5535	java/net/SocketTimeoutException
    //   467	488	5535	java/net/SocketTimeoutException
    //   524	549	5535	java/net/SocketTimeoutException
    //   699	707	5535	java/net/SocketTimeoutException
    //   743	750	5535	java/net/SocketTimeoutException
    //   786	801	5535	java/net/SocketTimeoutException
    //   837	853	5535	java/net/SocketTimeoutException
    //   889	896	5535	java/net/SocketTimeoutException
    //   932	954	5535	java/net/SocketTimeoutException
    //   990	999	5535	java/net/SocketTimeoutException
    //   1035	1044	5535	java/net/SocketTimeoutException
    //   1080	1091	5535	java/net/SocketTimeoutException
    //   1127	1133	5535	java/net/SocketTimeoutException
    //   1169	1177	5535	java/net/SocketTimeoutException
    //   1213	1225	5535	java/net/SocketTimeoutException
    //   1261	1269	5535	java/net/SocketTimeoutException
    //   1305	1315	5535	java/net/SocketTimeoutException
    //   1351	1358	5535	java/net/SocketTimeoutException
    //   1394	1400	5535	java/net/SocketTimeoutException
    //   1436	1447	5535	java/net/SocketTimeoutException
    //   1488	1507	5535	java/net/SocketTimeoutException
    //   1543	1557	5535	java/net/SocketTimeoutException
    //   1593	1603	5535	java/net/SocketTimeoutException
    //   1639	1651	5535	java/net/SocketTimeoutException
    //   1687	1712	5535	java/net/SocketTimeoutException
    //   1748	1787	5535	java/net/SocketTimeoutException
    //   2037	2046	5535	java/net/SocketTimeoutException
    //   2338	2350	5535	java/net/SocketTimeoutException
    //   2386	2396	5535	java/net/SocketTimeoutException
    //   2432	2440	5535	java/net/SocketTimeoutException
    //   2476	2492	5535	java/net/SocketTimeoutException
    //   2528	2534	5535	java/net/SocketTimeoutException
    //   2570	2577	5535	java/net/SocketTimeoutException
    //   2613	2627	5535	java/net/SocketTimeoutException
    //   3317	3324	5535	java/net/SocketTimeoutException
    //   2080	2101	5936	finally
    //   2115	2136	5936	finally
    //   2150	2165	5936	finally
    //   2668	2677	5936	finally
    //   2691	2698	5936	finally
    //   3350	3357	5936	finally
    //   5241	5262	5936	finally
    //   5276	5297	5936	finally
    //   5311	5326	5936	finally
    //   5566	5587	5936	finally
    //   5601	5611	5936	finally
    //   5625	5646	5936	finally
    //   5660	5691	5936	finally
    //   5705	5737	5936	finally
    //   5888	5898	5936	finally
    //   5912	5933	5936	finally
    //   6093	6103	5936	finally
    //   6117	6138	5936	finally
    //   6155	6176	5936	finally
    //   6282	6303	5936	finally
    //   6317	6338	5936	finally
    //   6352	6367	5936	finally
    //   6607	6628	5936	finally
    //   6642	6663	5936	finally
    //   6677	6692	5936	finally
    //   6932	6953	5936	finally
    //   6967	6988	5936	finally
    //   7002	7017	5936	finally
    //   7257	7278	5936	finally
    //   7292	7313	5936	finally
    //   7327	7342	5936	finally
    //   7582	7603	5936	finally
    //   7617	7638	5936	finally
    //   7652	7682	5936	finally
    //   5841	5846	6179	java/io/IOException
    //   5841	5846	6197	java/lang/ArrayIndexOutOfBoundsException
    //   5841	5846	6215	java/lang/Throwable
    //   5851	5856	6233	java/io/IOException
    //   319	338	6251	java/net/ConnectException
    //   374	384	6251	java/net/ConnectException
    //   420	426	6251	java/net/ConnectException
    //   467	488	6251	java/net/ConnectException
    //   524	549	6251	java/net/ConnectException
    //   699	707	6251	java/net/ConnectException
    //   743	750	6251	java/net/ConnectException
    //   786	801	6251	java/net/ConnectException
    //   837	853	6251	java/net/ConnectException
    //   889	896	6251	java/net/ConnectException
    //   932	954	6251	java/net/ConnectException
    //   990	999	6251	java/net/ConnectException
    //   1035	1044	6251	java/net/ConnectException
    //   1080	1091	6251	java/net/ConnectException
    //   1127	1133	6251	java/net/ConnectException
    //   1169	1177	6251	java/net/ConnectException
    //   1213	1225	6251	java/net/ConnectException
    //   1261	1269	6251	java/net/ConnectException
    //   1305	1315	6251	java/net/ConnectException
    //   1351	1358	6251	java/net/ConnectException
    //   1394	1400	6251	java/net/ConnectException
    //   1436	1447	6251	java/net/ConnectException
    //   1488	1507	6251	java/net/ConnectException
    //   1543	1557	6251	java/net/ConnectException
    //   1593	1603	6251	java/net/ConnectException
    //   1639	1651	6251	java/net/ConnectException
    //   1687	1712	6251	java/net/ConnectException
    //   1748	1787	6251	java/net/ConnectException
    //   2037	2046	6251	java/net/ConnectException
    //   2338	2350	6251	java/net/ConnectException
    //   2386	2396	6251	java/net/ConnectException
    //   2432	2440	6251	java/net/ConnectException
    //   2476	2492	6251	java/net/ConnectException
    //   2528	2534	6251	java/net/ConnectException
    //   2570	2577	6251	java/net/ConnectException
    //   2613	2627	6251	java/net/ConnectException
    //   3317	3324	6251	java/net/ConnectException
    //   6471	6476	6504	java/io/IOException
    //   6471	6476	6522	java/lang/ArrayIndexOutOfBoundsException
    //   6471	6476	6540	java/lang/Throwable
    //   6481	6486	6558	java/io/IOException
    //   319	338	6576	java/net/ProtocolException
    //   374	384	6576	java/net/ProtocolException
    //   420	426	6576	java/net/ProtocolException
    //   467	488	6576	java/net/ProtocolException
    //   524	549	6576	java/net/ProtocolException
    //   699	707	6576	java/net/ProtocolException
    //   743	750	6576	java/net/ProtocolException
    //   786	801	6576	java/net/ProtocolException
    //   837	853	6576	java/net/ProtocolException
    //   889	896	6576	java/net/ProtocolException
    //   932	954	6576	java/net/ProtocolException
    //   990	999	6576	java/net/ProtocolException
    //   1035	1044	6576	java/net/ProtocolException
    //   1080	1091	6576	java/net/ProtocolException
    //   1127	1133	6576	java/net/ProtocolException
    //   1169	1177	6576	java/net/ProtocolException
    //   1213	1225	6576	java/net/ProtocolException
    //   1261	1269	6576	java/net/ProtocolException
    //   1305	1315	6576	java/net/ProtocolException
    //   1351	1358	6576	java/net/ProtocolException
    //   1394	1400	6576	java/net/ProtocolException
    //   1436	1447	6576	java/net/ProtocolException
    //   1488	1507	6576	java/net/ProtocolException
    //   1543	1557	6576	java/net/ProtocolException
    //   1593	1603	6576	java/net/ProtocolException
    //   1639	1651	6576	java/net/ProtocolException
    //   1687	1712	6576	java/net/ProtocolException
    //   1748	1787	6576	java/net/ProtocolException
    //   2037	2046	6576	java/net/ProtocolException
    //   2338	2350	6576	java/net/ProtocolException
    //   2386	2396	6576	java/net/ProtocolException
    //   2432	2440	6576	java/net/ProtocolException
    //   2476	2492	6576	java/net/ProtocolException
    //   2528	2534	6576	java/net/ProtocolException
    //   2570	2577	6576	java/net/ProtocolException
    //   2613	2627	6576	java/net/ProtocolException
    //   3317	3324	6576	java/net/ProtocolException
    //   6796	6801	6829	java/io/IOException
    //   6796	6801	6847	java/lang/ArrayIndexOutOfBoundsException
    //   6796	6801	6865	java/lang/Throwable
    //   6806	6811	6883	java/io/IOException
    //   319	338	6901	java/lang/ArrayIndexOutOfBoundsException
    //   374	384	6901	java/lang/ArrayIndexOutOfBoundsException
    //   420	426	6901	java/lang/ArrayIndexOutOfBoundsException
    //   467	488	6901	java/lang/ArrayIndexOutOfBoundsException
    //   524	549	6901	java/lang/ArrayIndexOutOfBoundsException
    //   699	707	6901	java/lang/ArrayIndexOutOfBoundsException
    //   743	750	6901	java/lang/ArrayIndexOutOfBoundsException
    //   786	801	6901	java/lang/ArrayIndexOutOfBoundsException
    //   837	853	6901	java/lang/ArrayIndexOutOfBoundsException
    //   889	896	6901	java/lang/ArrayIndexOutOfBoundsException
    //   932	954	6901	java/lang/ArrayIndexOutOfBoundsException
    //   990	999	6901	java/lang/ArrayIndexOutOfBoundsException
    //   1035	1044	6901	java/lang/ArrayIndexOutOfBoundsException
    //   1080	1091	6901	java/lang/ArrayIndexOutOfBoundsException
    //   1127	1133	6901	java/lang/ArrayIndexOutOfBoundsException
    //   1169	1177	6901	java/lang/ArrayIndexOutOfBoundsException
    //   1213	1225	6901	java/lang/ArrayIndexOutOfBoundsException
    //   1261	1269	6901	java/lang/ArrayIndexOutOfBoundsException
    //   1305	1315	6901	java/lang/ArrayIndexOutOfBoundsException
    //   1351	1358	6901	java/lang/ArrayIndexOutOfBoundsException
    //   1394	1400	6901	java/lang/ArrayIndexOutOfBoundsException
    //   1436	1447	6901	java/lang/ArrayIndexOutOfBoundsException
    //   1488	1507	6901	java/lang/ArrayIndexOutOfBoundsException
    //   1543	1557	6901	java/lang/ArrayIndexOutOfBoundsException
    //   1593	1603	6901	java/lang/ArrayIndexOutOfBoundsException
    //   1639	1651	6901	java/lang/ArrayIndexOutOfBoundsException
    //   1687	1712	6901	java/lang/ArrayIndexOutOfBoundsException
    //   1748	1787	6901	java/lang/ArrayIndexOutOfBoundsException
    //   2037	2046	6901	java/lang/ArrayIndexOutOfBoundsException
    //   2338	2350	6901	java/lang/ArrayIndexOutOfBoundsException
    //   2386	2396	6901	java/lang/ArrayIndexOutOfBoundsException
    //   2432	2440	6901	java/lang/ArrayIndexOutOfBoundsException
    //   2476	2492	6901	java/lang/ArrayIndexOutOfBoundsException
    //   2528	2534	6901	java/lang/ArrayIndexOutOfBoundsException
    //   2570	2577	6901	java/lang/ArrayIndexOutOfBoundsException
    //   2613	2627	6901	java/lang/ArrayIndexOutOfBoundsException
    //   3317	3324	6901	java/lang/ArrayIndexOutOfBoundsException
    //   7121	7126	7154	java/io/IOException
    //   7121	7126	7172	java/lang/ArrayIndexOutOfBoundsException
    //   7121	7126	7190	java/lang/Throwable
    //   7131	7136	7208	java/io/IOException
    //   319	338	7226	java/net/UnknownHostException
    //   374	384	7226	java/net/UnknownHostException
    //   420	426	7226	java/net/UnknownHostException
    //   467	488	7226	java/net/UnknownHostException
    //   524	549	7226	java/net/UnknownHostException
    //   699	707	7226	java/net/UnknownHostException
    //   743	750	7226	java/net/UnknownHostException
    //   786	801	7226	java/net/UnknownHostException
    //   837	853	7226	java/net/UnknownHostException
    //   889	896	7226	java/net/UnknownHostException
    //   932	954	7226	java/net/UnknownHostException
    //   990	999	7226	java/net/UnknownHostException
    //   1035	1044	7226	java/net/UnknownHostException
    //   1080	1091	7226	java/net/UnknownHostException
    //   1127	1133	7226	java/net/UnknownHostException
    //   1169	1177	7226	java/net/UnknownHostException
    //   1213	1225	7226	java/net/UnknownHostException
    //   1261	1269	7226	java/net/UnknownHostException
    //   1305	1315	7226	java/net/UnknownHostException
    //   1351	1358	7226	java/net/UnknownHostException
    //   1394	1400	7226	java/net/UnknownHostException
    //   1436	1447	7226	java/net/UnknownHostException
    //   1488	1507	7226	java/net/UnknownHostException
    //   1543	1557	7226	java/net/UnknownHostException
    //   1593	1603	7226	java/net/UnknownHostException
    //   1639	1651	7226	java/net/UnknownHostException
    //   1687	1712	7226	java/net/UnknownHostException
    //   1748	1787	7226	java/net/UnknownHostException
    //   2037	2046	7226	java/net/UnknownHostException
    //   2338	2350	7226	java/net/UnknownHostException
    //   2386	2396	7226	java/net/UnknownHostException
    //   2432	2440	7226	java/net/UnknownHostException
    //   2476	2492	7226	java/net/UnknownHostException
    //   2528	2534	7226	java/net/UnknownHostException
    //   2570	2577	7226	java/net/UnknownHostException
    //   2613	2627	7226	java/net/UnknownHostException
    //   3317	3324	7226	java/net/UnknownHostException
    //   7446	7451	7479	java/io/IOException
    //   7446	7451	7497	java/lang/ArrayIndexOutOfBoundsException
    //   7446	7451	7515	java/lang/Throwable
    //   7456	7461	7533	java/io/IOException
    //   319	338	7551	java/lang/Exception
    //   374	384	7551	java/lang/Exception
    //   420	426	7551	java/lang/Exception
    //   467	488	7551	java/lang/Exception
    //   524	549	7551	java/lang/Exception
    //   699	707	7551	java/lang/Exception
    //   743	750	7551	java/lang/Exception
    //   786	801	7551	java/lang/Exception
    //   837	853	7551	java/lang/Exception
    //   889	896	7551	java/lang/Exception
    //   932	954	7551	java/lang/Exception
    //   990	999	7551	java/lang/Exception
    //   1035	1044	7551	java/lang/Exception
    //   1080	1091	7551	java/lang/Exception
    //   1127	1133	7551	java/lang/Exception
    //   1169	1177	7551	java/lang/Exception
    //   1213	1225	7551	java/lang/Exception
    //   1261	1269	7551	java/lang/Exception
    //   1305	1315	7551	java/lang/Exception
    //   1351	1358	7551	java/lang/Exception
    //   1394	1400	7551	java/lang/Exception
    //   1436	1447	7551	java/lang/Exception
    //   1488	1507	7551	java/lang/Exception
    //   1543	1557	7551	java/lang/Exception
    //   1593	1603	7551	java/lang/Exception
    //   1639	1651	7551	java/lang/Exception
    //   1687	1712	7551	java/lang/Exception
    //   1748	1787	7551	java/lang/Exception
    //   2037	2046	7551	java/lang/Exception
    //   2338	2350	7551	java/lang/Exception
    //   2386	2396	7551	java/lang/Exception
    //   2432	2440	7551	java/lang/Exception
    //   2476	2492	7551	java/lang/Exception
    //   2528	2534	7551	java/lang/Exception
    //   2570	2577	7551	java/lang/Exception
    //   2613	2627	7551	java/lang/Exception
    //   3317	3324	7551	java/lang/Exception
    //   7786	7791	7819	java/io/IOException
    //   7786	7791	7837	java/lang/ArrayIndexOutOfBoundsException
    //   7786	7791	7855	java/lang/Throwable
    //   7796	7801	7873	java/io/IOException
    //   6044	6049	7891	java/io/IOException
    //   6044	6049	7909	java/lang/ArrayIndexOutOfBoundsException
    //   6044	6049	7927	java/lang/Throwable
    //   6054	6059	7945	java/io/IOException
    //   319	338	7963	finally
    //   374	384	7963	finally
    //   420	426	7963	finally
    //   467	488	7963	finally
    //   524	549	7963	finally
    //   699	707	7963	finally
    //   743	750	7963	finally
    //   786	801	7963	finally
    //   837	853	7963	finally
    //   889	896	7963	finally
    //   932	954	7963	finally
    //   990	999	7963	finally
    //   1035	1044	7963	finally
    //   1080	1091	7963	finally
    //   1127	1133	7963	finally
    //   1169	1177	7963	finally
    //   1213	1225	7963	finally
    //   1261	1269	7963	finally
    //   1305	1315	7963	finally
    //   1351	1358	7963	finally
    //   1394	1400	7963	finally
    //   1436	1447	7963	finally
    //   1488	1507	7963	finally
    //   1543	1557	7963	finally
    //   1593	1603	7963	finally
    //   1639	1651	7963	finally
    //   1687	1712	7963	finally
    //   1748	1787	7963	finally
    //   2037	2046	7963	finally
    //   2338	2350	7963	finally
    //   2386	2396	7963	finally
    //   2432	2440	7963	finally
    //   2476	2492	7963	finally
    //   2528	2534	7963	finally
    //   2570	2577	7963	finally
    //   2613	2627	7963	finally
    //   3317	3324	7963	finally
    //   2627	2646	7978	finally
    //   2737	2744	7994	finally
    //   2780	2789	7994	finally
    //   2825	2851	7994	finally
    //   2894	2920	7994	finally
    //   2956	2963	7994	finally
    //   2999	3006	7994	finally
    //   3042	3047	7994	finally
    //   3083	3091	7994	finally
    //   3131	3151	7994	finally
    //   3187	3208	7994	finally
    //   3417	3448	7994	finally
    //   3484	3490	7994	finally
    //   3526	3533	7994	finally
    //   3569	3591	7994	finally
    //   3627	3632	7994	finally
    //   3810	3831	7994	finally
    //   3867	3876	7994	finally
    //   3908	3922	7994	finally
    //   3954	3968	7994	finally
    //   4012	4020	7994	finally
    //   4056	4063	7994	finally
    //   4099	4119	7994	finally
    //   4155	4165	7994	finally
    //   4379	4386	7994	finally
    //   4427	4447	7994	finally
    //   4479	4493	7994	finally
    //   4525	4539	7994	finally
    //   4574	4581	7994	finally
    //   4622	4636	7994	finally
    //   4695	4701	7994	finally
    //   4167	4176	8006	finally
    //   4182	4212	8006	finally
    //   4780	4790	8006	finally
    //   4798	4836	8006	finally
    //   4836	4866	8006	finally
    //   4970	4983	8006	finally
    //   4866	4886	8015	finally
    //   1811	1866	8024	finally
    //   2627	2646	8045	java/lang/Exception
    //   2668	2677	8070	java/lang/Exception
    //   2691	2698	8070	java/lang/Exception
    //   3350	3357	8070	java/lang/Exception
    //   2737	2744	8091	java/lang/Exception
    //   2780	2789	8091	java/lang/Exception
    //   2825	2851	8091	java/lang/Exception
    //   2894	2920	8091	java/lang/Exception
    //   2956	2963	8091	java/lang/Exception
    //   2999	3006	8091	java/lang/Exception
    //   3042	3047	8091	java/lang/Exception
    //   3083	3091	8091	java/lang/Exception
    //   3131	3151	8091	java/lang/Exception
    //   3187	3208	8091	java/lang/Exception
    //   3417	3448	8091	java/lang/Exception
    //   3484	3490	8091	java/lang/Exception
    //   3526	3533	8091	java/lang/Exception
    //   3569	3591	8091	java/lang/Exception
    //   3627	3632	8091	java/lang/Exception
    //   3810	3831	8091	java/lang/Exception
    //   3867	3876	8091	java/lang/Exception
    //   4012	4020	8091	java/lang/Exception
    //   4056	4063	8091	java/lang/Exception
    //   4099	4119	8091	java/lang/Exception
    //   4155	4165	8091	java/lang/Exception
    //   4427	4447	8091	java/lang/Exception
    //   4622	4636	8091	java/lang/Exception
    //   4695	4701	8091	java/lang/Exception
    //   4167	4176	8111	java/lang/Exception
    //   4182	4212	8111	java/lang/Exception
    //   4780	4790	8111	java/lang/Exception
    //   4798	4836	8111	java/lang/Exception
    //   4836	4866	8111	java/lang/Exception
    //   4970	4983	8111	java/lang/Exception
    //   4866	4886	8130	java/lang/Exception
    //   2627	2646	8149	java/net/UnknownHostException
    //   2668	2677	8174	java/net/UnknownHostException
    //   2691	2698	8174	java/net/UnknownHostException
    //   3350	3357	8174	java/net/UnknownHostException
    //   2737	2744	8195	java/net/UnknownHostException
    //   2780	2789	8195	java/net/UnknownHostException
    //   2825	2851	8195	java/net/UnknownHostException
    //   2894	2920	8195	java/net/UnknownHostException
    //   2956	2963	8195	java/net/UnknownHostException
    //   2999	3006	8195	java/net/UnknownHostException
    //   3042	3047	8195	java/net/UnknownHostException
    //   3083	3091	8195	java/net/UnknownHostException
    //   3131	3151	8195	java/net/UnknownHostException
    //   3187	3208	8195	java/net/UnknownHostException
    //   3417	3448	8195	java/net/UnknownHostException
    //   3484	3490	8195	java/net/UnknownHostException
    //   3526	3533	8195	java/net/UnknownHostException
    //   3569	3591	8195	java/net/UnknownHostException
    //   3627	3632	8195	java/net/UnknownHostException
    //   3810	3831	8195	java/net/UnknownHostException
    //   3867	3876	8195	java/net/UnknownHostException
    //   3908	3922	8195	java/net/UnknownHostException
    //   3954	3968	8195	java/net/UnknownHostException
    //   4012	4020	8195	java/net/UnknownHostException
    //   4056	4063	8195	java/net/UnknownHostException
    //   4099	4119	8195	java/net/UnknownHostException
    //   4155	4165	8195	java/net/UnknownHostException
    //   4379	4386	8195	java/net/UnknownHostException
    //   4427	4447	8195	java/net/UnknownHostException
    //   4479	4493	8195	java/net/UnknownHostException
    //   4525	4539	8195	java/net/UnknownHostException
    //   4574	4581	8195	java/net/UnknownHostException
    //   4622	4636	8195	java/net/UnknownHostException
    //   4695	4701	8195	java/net/UnknownHostException
    //   4167	4176	8215	java/net/UnknownHostException
    //   4182	4212	8215	java/net/UnknownHostException
    //   4780	4790	8215	java/net/UnknownHostException
    //   4798	4836	8215	java/net/UnknownHostException
    //   4836	4866	8215	java/net/UnknownHostException
    //   4970	4983	8215	java/net/UnknownHostException
    //   4866	4886	8234	java/net/UnknownHostException
    //   2627	2646	8253	java/lang/ArrayIndexOutOfBoundsException
    //   2668	2677	8278	java/lang/ArrayIndexOutOfBoundsException
    //   2691	2698	8278	java/lang/ArrayIndexOutOfBoundsException
    //   3350	3357	8278	java/lang/ArrayIndexOutOfBoundsException
    //   2737	2744	8299	java/lang/ArrayIndexOutOfBoundsException
    //   2780	2789	8299	java/lang/ArrayIndexOutOfBoundsException
    //   2825	2851	8299	java/lang/ArrayIndexOutOfBoundsException
    //   2894	2920	8299	java/lang/ArrayIndexOutOfBoundsException
    //   2956	2963	8299	java/lang/ArrayIndexOutOfBoundsException
    //   2999	3006	8299	java/lang/ArrayIndexOutOfBoundsException
    //   3042	3047	8299	java/lang/ArrayIndexOutOfBoundsException
    //   3083	3091	8299	java/lang/ArrayIndexOutOfBoundsException
    //   3131	3151	8299	java/lang/ArrayIndexOutOfBoundsException
    //   3187	3208	8299	java/lang/ArrayIndexOutOfBoundsException
    //   3417	3448	8299	java/lang/ArrayIndexOutOfBoundsException
    //   3484	3490	8299	java/lang/ArrayIndexOutOfBoundsException
    //   3526	3533	8299	java/lang/ArrayIndexOutOfBoundsException
    //   3569	3591	8299	java/lang/ArrayIndexOutOfBoundsException
    //   3627	3632	8299	java/lang/ArrayIndexOutOfBoundsException
    //   3810	3831	8299	java/lang/ArrayIndexOutOfBoundsException
    //   3867	3876	8299	java/lang/ArrayIndexOutOfBoundsException
    //   3908	3922	8299	java/lang/ArrayIndexOutOfBoundsException
    //   3954	3968	8299	java/lang/ArrayIndexOutOfBoundsException
    //   4012	4020	8299	java/lang/ArrayIndexOutOfBoundsException
    //   4056	4063	8299	java/lang/ArrayIndexOutOfBoundsException
    //   4099	4119	8299	java/lang/ArrayIndexOutOfBoundsException
    //   4155	4165	8299	java/lang/ArrayIndexOutOfBoundsException
    //   4379	4386	8299	java/lang/ArrayIndexOutOfBoundsException
    //   4427	4447	8299	java/lang/ArrayIndexOutOfBoundsException
    //   4479	4493	8299	java/lang/ArrayIndexOutOfBoundsException
    //   4525	4539	8299	java/lang/ArrayIndexOutOfBoundsException
    //   4574	4581	8299	java/lang/ArrayIndexOutOfBoundsException
    //   4622	4636	8299	java/lang/ArrayIndexOutOfBoundsException
    //   4695	4701	8299	java/lang/ArrayIndexOutOfBoundsException
    //   4167	4176	8319	java/lang/ArrayIndexOutOfBoundsException
    //   4182	4212	8319	java/lang/ArrayIndexOutOfBoundsException
    //   4780	4790	8319	java/lang/ArrayIndexOutOfBoundsException
    //   4798	4836	8319	java/lang/ArrayIndexOutOfBoundsException
    //   4836	4866	8319	java/lang/ArrayIndexOutOfBoundsException
    //   4970	4983	8319	java/lang/ArrayIndexOutOfBoundsException
    //   4866	4886	8338	java/lang/ArrayIndexOutOfBoundsException
    //   2627	2646	8357	java/net/ProtocolException
    //   2668	2677	8382	java/net/ProtocolException
    //   2691	2698	8382	java/net/ProtocolException
    //   3350	3357	8382	java/net/ProtocolException
    //   2737	2744	8403	java/net/ProtocolException
    //   2780	2789	8403	java/net/ProtocolException
    //   2825	2851	8403	java/net/ProtocolException
    //   2894	2920	8403	java/net/ProtocolException
    //   2956	2963	8403	java/net/ProtocolException
    //   2999	3006	8403	java/net/ProtocolException
    //   3042	3047	8403	java/net/ProtocolException
    //   3083	3091	8403	java/net/ProtocolException
    //   3131	3151	8403	java/net/ProtocolException
    //   3187	3208	8403	java/net/ProtocolException
    //   3417	3448	8403	java/net/ProtocolException
    //   3484	3490	8403	java/net/ProtocolException
    //   3526	3533	8403	java/net/ProtocolException
    //   3569	3591	8403	java/net/ProtocolException
    //   3627	3632	8403	java/net/ProtocolException
    //   3810	3831	8403	java/net/ProtocolException
    //   3867	3876	8403	java/net/ProtocolException
    //   3908	3922	8403	java/net/ProtocolException
    //   3954	3968	8403	java/net/ProtocolException
    //   4012	4020	8403	java/net/ProtocolException
    //   4056	4063	8403	java/net/ProtocolException
    //   4099	4119	8403	java/net/ProtocolException
    //   4155	4165	8403	java/net/ProtocolException
    //   4379	4386	8403	java/net/ProtocolException
    //   4427	4447	8403	java/net/ProtocolException
    //   4479	4493	8403	java/net/ProtocolException
    //   4525	4539	8403	java/net/ProtocolException
    //   4574	4581	8403	java/net/ProtocolException
    //   4622	4636	8403	java/net/ProtocolException
    //   4695	4701	8403	java/net/ProtocolException
    //   4167	4176	8423	java/net/ProtocolException
    //   4182	4212	8423	java/net/ProtocolException
    //   4780	4790	8423	java/net/ProtocolException
    //   4798	4836	8423	java/net/ProtocolException
    //   4836	4866	8423	java/net/ProtocolException
    //   4970	4983	8423	java/net/ProtocolException
    //   4866	4886	8442	java/net/ProtocolException
    //   2627	2646	8461	java/net/ConnectException
    //   2668	2677	8486	java/net/ConnectException
    //   2691	2698	8486	java/net/ConnectException
    //   3350	3357	8486	java/net/ConnectException
    //   2737	2744	8507	java/net/ConnectException
    //   2780	2789	8507	java/net/ConnectException
    //   2825	2851	8507	java/net/ConnectException
    //   2894	2920	8507	java/net/ConnectException
    //   2956	2963	8507	java/net/ConnectException
    //   2999	3006	8507	java/net/ConnectException
    //   3042	3047	8507	java/net/ConnectException
    //   3083	3091	8507	java/net/ConnectException
    //   3131	3151	8507	java/net/ConnectException
    //   3187	3208	8507	java/net/ConnectException
    //   3417	3448	8507	java/net/ConnectException
    //   3484	3490	8507	java/net/ConnectException
    //   3526	3533	8507	java/net/ConnectException
    //   3569	3591	8507	java/net/ConnectException
    //   3627	3632	8507	java/net/ConnectException
    //   3810	3831	8507	java/net/ConnectException
    //   3867	3876	8507	java/net/ConnectException
    //   3908	3922	8507	java/net/ConnectException
    //   3954	3968	8507	java/net/ConnectException
    //   4012	4020	8507	java/net/ConnectException
    //   4056	4063	8507	java/net/ConnectException
    //   4099	4119	8507	java/net/ConnectException
    //   4155	4165	8507	java/net/ConnectException
    //   4379	4386	8507	java/net/ConnectException
    //   4427	4447	8507	java/net/ConnectException
    //   4479	4493	8507	java/net/ConnectException
    //   4525	4539	8507	java/net/ConnectException
    //   4574	4581	8507	java/net/ConnectException
    //   4622	4636	8507	java/net/ConnectException
    //   4695	4701	8507	java/net/ConnectException
    //   4167	4176	8527	java/net/ConnectException
    //   4182	4212	8527	java/net/ConnectException
    //   4780	4790	8527	java/net/ConnectException
    //   4798	4836	8527	java/net/ConnectException
    //   4836	4866	8527	java/net/ConnectException
    //   4970	4983	8527	java/net/ConnectException
    //   4866	4886	8546	java/net/ConnectException
    //   2627	2646	8565	java/net/SocketTimeoutException
    //   2668	2677	8590	java/net/SocketTimeoutException
    //   2691	2698	8590	java/net/SocketTimeoutException
    //   3350	3357	8590	java/net/SocketTimeoutException
    //   2737	2744	8611	java/net/SocketTimeoutException
    //   2780	2789	8611	java/net/SocketTimeoutException
    //   2825	2851	8611	java/net/SocketTimeoutException
    //   2894	2920	8611	java/net/SocketTimeoutException
    //   2956	2963	8611	java/net/SocketTimeoutException
    //   2999	3006	8611	java/net/SocketTimeoutException
    //   3042	3047	8611	java/net/SocketTimeoutException
    //   3083	3091	8611	java/net/SocketTimeoutException
    //   3131	3151	8611	java/net/SocketTimeoutException
    //   3187	3208	8611	java/net/SocketTimeoutException
    //   3417	3448	8611	java/net/SocketTimeoutException
    //   3484	3490	8611	java/net/SocketTimeoutException
    //   3526	3533	8611	java/net/SocketTimeoutException
    //   3569	3591	8611	java/net/SocketTimeoutException
    //   3627	3632	8611	java/net/SocketTimeoutException
    //   3810	3831	8611	java/net/SocketTimeoutException
    //   3867	3876	8611	java/net/SocketTimeoutException
    //   3908	3922	8611	java/net/SocketTimeoutException
    //   3954	3968	8611	java/net/SocketTimeoutException
    //   4012	4020	8611	java/net/SocketTimeoutException
    //   4056	4063	8611	java/net/SocketTimeoutException
    //   4099	4119	8611	java/net/SocketTimeoutException
    //   4155	4165	8611	java/net/SocketTimeoutException
    //   4379	4386	8611	java/net/SocketTimeoutException
    //   4427	4447	8611	java/net/SocketTimeoutException
    //   4479	4493	8611	java/net/SocketTimeoutException
    //   4525	4539	8611	java/net/SocketTimeoutException
    //   4574	4581	8611	java/net/SocketTimeoutException
    //   4622	4636	8611	java/net/SocketTimeoutException
    //   4695	4701	8611	java/net/SocketTimeoutException
    //   4167	4176	8631	java/net/SocketTimeoutException
    //   4182	4212	8631	java/net/SocketTimeoutException
    //   4780	4790	8631	java/net/SocketTimeoutException
    //   4798	4836	8631	java/net/SocketTimeoutException
    //   4836	4866	8631	java/net/SocketTimeoutException
    //   4970	4983	8631	java/net/SocketTimeoutException
    //   4866	4886	8650	java/net/SocketTimeoutException
    //   2627	2646	8669	java/io/FileNotFoundException
    //   2668	2677	8694	java/io/FileNotFoundException
    //   2691	2698	8694	java/io/FileNotFoundException
    //   3350	3357	8694	java/io/FileNotFoundException
    //   2737	2744	8715	java/io/FileNotFoundException
    //   2780	2789	8715	java/io/FileNotFoundException
    //   2825	2851	8715	java/io/FileNotFoundException
    //   2894	2920	8715	java/io/FileNotFoundException
    //   2956	2963	8715	java/io/FileNotFoundException
    //   2999	3006	8715	java/io/FileNotFoundException
    //   3042	3047	8715	java/io/FileNotFoundException
    //   3083	3091	8715	java/io/FileNotFoundException
    //   3131	3151	8715	java/io/FileNotFoundException
    //   3187	3208	8715	java/io/FileNotFoundException
    //   3417	3448	8715	java/io/FileNotFoundException
    //   3484	3490	8715	java/io/FileNotFoundException
    //   3526	3533	8715	java/io/FileNotFoundException
    //   3569	3591	8715	java/io/FileNotFoundException
    //   3627	3632	8715	java/io/FileNotFoundException
    //   3810	3831	8715	java/io/FileNotFoundException
    //   3867	3876	8715	java/io/FileNotFoundException
    //   3908	3922	8715	java/io/FileNotFoundException
    //   3954	3968	8715	java/io/FileNotFoundException
    //   4012	4020	8715	java/io/FileNotFoundException
    //   4056	4063	8715	java/io/FileNotFoundException
    //   4099	4119	8715	java/io/FileNotFoundException
    //   4155	4165	8715	java/io/FileNotFoundException
    //   4379	4386	8715	java/io/FileNotFoundException
    //   4427	4447	8715	java/io/FileNotFoundException
    //   4479	4493	8715	java/io/FileNotFoundException
    //   4525	4539	8715	java/io/FileNotFoundException
    //   4574	4581	8715	java/io/FileNotFoundException
    //   4622	4636	8715	java/io/FileNotFoundException
    //   4695	4701	8715	java/io/FileNotFoundException
    //   4167	4176	8735	java/io/FileNotFoundException
    //   4182	4212	8735	java/io/FileNotFoundException
    //   4780	4790	8735	java/io/FileNotFoundException
    //   4798	4836	8735	java/io/FileNotFoundException
    //   4836	4866	8735	java/io/FileNotFoundException
    //   4970	4983	8735	java/io/FileNotFoundException
    //   4866	4886	8754	java/io/FileNotFoundException
    //   2627	2646	8773	javax/net/ssl/SSLHandshakeException
    //   2668	2677	8794	javax/net/ssl/SSLHandshakeException
    //   2691	2698	8794	javax/net/ssl/SSLHandshakeException
    //   3350	3357	8794	javax/net/ssl/SSLHandshakeException
    //   2737	2744	8811	javax/net/ssl/SSLHandshakeException
    //   2780	2789	8811	javax/net/ssl/SSLHandshakeException
    //   2825	2851	8811	javax/net/ssl/SSLHandshakeException
    //   2894	2920	8811	javax/net/ssl/SSLHandshakeException
    //   2956	2963	8811	javax/net/ssl/SSLHandshakeException
    //   2999	3006	8811	javax/net/ssl/SSLHandshakeException
    //   3042	3047	8811	javax/net/ssl/SSLHandshakeException
    //   3083	3091	8811	javax/net/ssl/SSLHandshakeException
    //   3131	3151	8811	javax/net/ssl/SSLHandshakeException
    //   3187	3208	8811	javax/net/ssl/SSLHandshakeException
    //   3417	3448	8811	javax/net/ssl/SSLHandshakeException
    //   3484	3490	8811	javax/net/ssl/SSLHandshakeException
    //   3526	3533	8811	javax/net/ssl/SSLHandshakeException
    //   3569	3591	8811	javax/net/ssl/SSLHandshakeException
    //   3627	3632	8811	javax/net/ssl/SSLHandshakeException
    //   3810	3831	8811	javax/net/ssl/SSLHandshakeException
    //   3867	3876	8811	javax/net/ssl/SSLHandshakeException
    //   3908	3922	8811	javax/net/ssl/SSLHandshakeException
    //   3954	3968	8811	javax/net/ssl/SSLHandshakeException
    //   4012	4020	8811	javax/net/ssl/SSLHandshakeException
    //   4056	4063	8811	javax/net/ssl/SSLHandshakeException
    //   4099	4119	8811	javax/net/ssl/SSLHandshakeException
    //   4155	4165	8811	javax/net/ssl/SSLHandshakeException
    //   4379	4386	8811	javax/net/ssl/SSLHandshakeException
    //   4427	4447	8811	javax/net/ssl/SSLHandshakeException
    //   4479	4493	8811	javax/net/ssl/SSLHandshakeException
    //   4525	4539	8811	javax/net/ssl/SSLHandshakeException
    //   4574	4581	8811	javax/net/ssl/SSLHandshakeException
    //   4622	4636	8811	javax/net/ssl/SSLHandshakeException
    //   4695	4701	8811	javax/net/ssl/SSLHandshakeException
    //   4167	4176	8827	javax/net/ssl/SSLHandshakeException
    //   4182	4212	8827	javax/net/ssl/SSLHandshakeException
    //   4780	4790	8827	javax/net/ssl/SSLHandshakeException
    //   4798	4836	8827	javax/net/ssl/SSLHandshakeException
    //   4836	4866	8827	javax/net/ssl/SSLHandshakeException
    //   4970	4983	8827	javax/net/ssl/SSLHandshakeException
    //   4866	4886	8846	javax/net/ssl/SSLHandshakeException
    //   2627	2646	8865	java/io/UnsupportedEncodingException
    //   2668	2677	8878	java/io/UnsupportedEncodingException
    //   2691	2698	8878	java/io/UnsupportedEncodingException
    //   3350	3357	8878	java/io/UnsupportedEncodingException
    //   4012	4020	8895	java/io/UnsupportedEncodingException
    //   4056	4063	8895	java/io/UnsupportedEncodingException
    //   4099	4119	8895	java/io/UnsupportedEncodingException
    //   4155	4165	8895	java/io/UnsupportedEncodingException
    //   4695	4701	8895	java/io/UnsupportedEncodingException
    //   4167	4176	8916	java/io/UnsupportedEncodingException
    //   4182	4212	8916	java/io/UnsupportedEncodingException
    //   4780	4790	8916	java/io/UnsupportedEncodingException
    //   4798	4836	8916	java/io/UnsupportedEncodingException
    //   4836	4866	8916	java/io/UnsupportedEncodingException
    //   4970	4983	8916	java/io/UnsupportedEncodingException
    //   4866	4886	8941	java/io/UnsupportedEncodingException
  }
  
  private void a(String paramString, HttpURLConnection paramHttpURLConnection)
  {
    AppMethodBeat.i(108153);
    lI(paramString);
    if (paramHttpURLConnection != null) {
      try
      {
        paramHttpURLConnection.getInputStream().close();
        paramHttpURLConnection.disconnect();
        AppMethodBeat.o(108153);
        return;
      }
      catch (Exception paramHttpURLConnection)
      {
        ab.printErrStackTrace("MicroMsg.AppBrandNetworkRequest", paramHttpURLConnection, "removeTask Exception: id %s", new Object[] { paramString });
      }
    }
    AppMethodBeat.o(108153);
  }
  
  /* Error */
  private void lI(String paramString)
  {
    // Byte code:
    //   0: aload_0
    //   1: monitorenter
    //   2: ldc_w 631
    //   5: invokestatic 31	com/tencent/matrix/trace/core/AppMethodBeat:i	(I)V
    //   8: aload_1
    //   9: ifnonnull +12 -> 21
    //   12: ldc_w 631
    //   15: invokestatic 65	com/tencent/matrix/trace/core/AppMethodBeat:o	(I)V
    //   18: aload_0
    //   19: monitorexit
    //   20: return
    //   21: aload_0
    //   22: getfield 36	com/tencent/mm/plugin/appbrand/m/d:isH	Ljava/util/ArrayList;
    //   25: astore_2
    //   26: aload_2
    //   27: monitorenter
    //   28: aload_0
    //   29: getfield 36	com/tencent/mm/plugin/appbrand/m/d:isH	Ljava/util/ArrayList;
    //   32: invokevirtual 632	java/util/ArrayList:iterator	()Ljava/util/Iterator;
    //   35: astore_3
    //   36: aload_3
    //   37: invokeinterface 347 1 0
    //   42: ifeq +36 -> 78
    //   45: aload_3
    //   46: invokeinterface 351 1 0
    //   51: checkcast 140	com/tencent/mm/plugin/appbrand/m/e
    //   54: astore 4
    //   56: aload_1
    //   57: aload 4
    //   59: getfield 163	com/tencent/mm/plugin/appbrand/m/e:hwp	Ljava/lang/String;
    //   62: invokevirtual 477	java/lang/String:equals	(Ljava/lang/Object;)Z
    //   65: ifeq -29 -> 36
    //   68: aload_0
    //   69: getfield 36	com/tencent/mm/plugin/appbrand/m/d:isH	Ljava/util/ArrayList;
    //   72: aload 4
    //   74: invokevirtual 260	java/util/ArrayList:remove	(Ljava/lang/Object;)Z
    //   77: pop
    //   78: aload_2
    //   79: monitorexit
    //   80: ldc_w 631
    //   83: invokestatic 65	com/tencent/matrix/trace/core/AppMethodBeat:o	(I)V
    //   86: goto -68 -> 18
    //   89: astore_1
    //   90: aload_0
    //   91: monitorexit
    //   92: aload_1
    //   93: athrow
    //   94: astore_1
    //   95: aload_2
    //   96: monitorexit
    //   97: ldc_w 631
    //   100: invokestatic 65	com/tencent/matrix/trace/core/AppMethodBeat:o	(I)V
    //   103: aload_1
    //   104: athrow
    // Local variable table:
    //   start	length	slot	name	signature
    //   0	105	0	this	d
    //   0	105	1	paramString	String
    //   35	11	3	localIterator	Iterator
    //   54	19	4	locale	e
    // Exception table:
    //   from	to	target	type
    //   2	8	89	finally
    //   12	18	89	finally
    //   21	28	89	finally
    //   80	86	89	finally
    //   97	105	89	finally
    //   28	36	94	finally
    //   36	78	94	finally
    //   78	80	94	finally
    //   95	97	94	finally
  }
  
  public final boolean DN(String paramString)
  {
    AppMethodBeat.i(108152);
    boolean bool = this.isA.contains(paramString);
    AppMethodBeat.o(108152);
    return bool;
  }
  
  public final e DR(String paramString)
  {
    AppMethodBeat.i(108157);
    if (paramString == null)
    {
      AppMethodBeat.o(108157);
      return null;
    }
    synchronized (this.isH)
    {
      Iterator localIterator = this.isH.iterator();
      while (localIterator.hasNext())
      {
        e locale = (e)localIterator.next();
        if (paramString.equals(locale.hwp))
        {
          AppMethodBeat.o(108157);
          return locale;
        }
      }
      AppMethodBeat.o(108157);
      return null;
    }
  }
  
  public final void a(c paramc, int paramInt, JSONObject paramJSONObject, Map<String, String> paramMap, ArrayList<String> paramArrayList, d.a parama, String paramString1, String paramString2)
  {
    AppMethodBeat.i(108155);
    com.tencent.mm.sdk.g.d.post(new d.1(this, paramc, paramJSONObject, parama, paramString1, paramInt, paramMap, paramArrayList, paramString2), "appbrand_request_thread");
    AppMethodBeat.o(108155);
  }
  
  public final void b(e parame)
  {
    AppMethodBeat.i(108151);
    ab.d("MicroMsg.AppBrandNetworkRequest", "try to abortTask");
    this.isA.add(parame.hwp);
    a(parame.hwp, parame.isX);
    AppMethodBeat.o(108151);
  }
}


/* Location:           L:\local\mybackup\temp\qq_apk\com.tencent.mm\classes9.jar
 * Qualified Name:     com.tencent.mm.plugin.appbrand.m.d
 * JD-Core Version:    0.7.0.1
 */