package com.tencent.mobileqq.app;

public final class PublicAccountDataManager$2
  implements Runnable
{
  /* Error */
  public void run()
  {
    // Byte code:
    //   0: invokestatic 20	amxz:a	()Ljava/util/LinkedList;
    //   3: astore_2
    //   4: aload_2
    //   5: monitorenter
    //   6: invokestatic 20	amxz:a	()Ljava/util/LinkedList;
    //   9: invokevirtual 26	java/util/LinkedList:size	()I
    //   12: istore_1
    //   13: iload_1
    //   14: ifgt +6 -> 20
    //   17: aload_2
    //   18: monitorexit
    //   19: return
    //   20: new 28	java/util/ArrayList
    //   23: dup
    //   24: iload_1
    //   25: invokespecial 31	java/util/ArrayList:<init>	(I)V
    //   28: astore_3
    //   29: aload_3
    //   30: invokestatic 20	amxz:a	()Ljava/util/LinkedList;
    //   33: invokeinterface 37 2 0
    //   38: pop
    //   39: invokestatic 20	amxz:a	()Ljava/util/LinkedList;
    //   42: invokevirtual 40	java/util/LinkedList:clear	()V
    //   45: aload_2
    //   46: monitorexit
    //   47: aload_3
    //   48: invokeinterface 44 1 0
    //   53: astore_2
    //   54: aload_2
    //   55: invokeinterface 50 1 0
    //   60: ifeq +40 -> 100
    //   63: aload_2
    //   64: invokeinterface 54 1 0
    //   69: checkcast 56	amyb
    //   72: invokeinterface 58 1 0
    //   77: goto -23 -> 54
    //   80: astore_2
    //   81: aload_2
    //   82: invokevirtual 61	java/lang/Exception:printStackTrace	()V
    //   85: ldc 63
    //   87: iconst_2
    //   88: ldc 65
    //   90: aload_2
    //   91: invokestatic 71	com/tencent/qphone/base/util/QLog:d	(Ljava/lang/String;ILjava/lang/String;Ljava/lang/Throwable;)V
    //   94: return
    //   95: astore_3
    //   96: aload_2
    //   97: monitorexit
    //   98: aload_3
    //   99: athrow
    //   100: return
    // Local variable table:
    //   start	length	slot	name	signature
    //   0	101	0	this	2
    //   12	13	1	i	int
    //   80	17	2	localException	java.lang.Exception
    //   28	20	3	localArrayList	java.util.ArrayList
    //   95	4	3	localObject2	Object
    // Exception table:
    //   from	to	target	type
    //   0	6	80	java/lang/Exception
    //   47	54	80	java/lang/Exception
    //   54	77	80	java/lang/Exception
    //   98	100	80	java/lang/Exception
    //   6	13	95	finally
    //   17	19	95	finally
    //   20	47	95	finally
    //   96	98	95	finally
  }
}


/* Location:           L:\local\mybackup\temp\qq_apk\com.tencent.mobileqq\classes8.jar
 * Qualified Name:     com.tencent.mobileqq.app.PublicAccountDataManager.2
 * JD-Core Version:    0.7.0.1
 */