package com.tencent.qqmail.namelist;

import com.tencent.qqmail.utilities.qmnetwork.QMCallback.ISuccessCallback;

class NameListCGIManager$1
  implements QMCallback.ISuccessCallback
{
  NameListCGIManager$1(NameListCGIManager paramNameListCGIManager, String paramString, int paramInt) {}
  
  /* Error */
  public void run(com.tencent.qqmail.utilities.qmnetwork.QMNetworkRequest paramQMNetworkRequest, com.tencent.qqmail.utilities.qmnetwork.QMNetworkResponse paramQMNetworkResponse)
  {
    // Byte code:
    //   0: iconst_3
    //   1: ldc 30
    //   3: ldc 32
    //   5: invokestatic 38	com/tencent/qqmail/utilities/log/QMLog:log	(ILjava/lang/String;Ljava/lang/String;)V
    //   8: aload_0
    //   9: getfield 18	com/tencent/qqmail/namelist/NameListCGIManager$1:val$requestFilterKey	Ljava/lang/String;
    //   12: invokestatic 44	com/tencent/qqmail/network/filter/RequestFilter:resetRequestRunningState	(Ljava/lang/String;)V
    //   15: aload_2
    //   16: invokevirtual 50	com/tencent/qqmail/utilities/qmnetwork/QMNetworkResponse:getResponseJson	()Ljava/lang/Object;
    //   19: checkcast 52	com/alibaba/fastjson/JSONObject
    //   22: astore_2
    //   23: aload_0
    //   24: getfield 16	com/tencent/qqmail/namelist/NameListCGIManager$1:this$0	Lcom/tencent/qqmail/namelist/NameListCGIManager;
    //   27: invokestatic 58	com/tencent/qqmail/namelist/NameListCGIManager:access$000	(Lcom/tencent/qqmail/namelist/NameListCGIManager;)Lcom/tencent/qqmail/model/mail/QMMailSQLiteHelper;
    //   30: invokevirtual 64	com/tencent/qqmail/model/mail/QMMailSQLiteHelper:getWritableDatabase	()Lcom/tencent/moai/database/sqlite/SQLiteDatabase;
    //   33: astore_1
    //   34: aload_2
    //   35: ldc 66
    //   37: invokevirtual 70	com/alibaba/fastjson/JSONObject:containsKey	(Ljava/lang/Object;)Z
    //   40: ifeq +29 -> 69
    //   43: aload_2
    //   44: ldc 66
    //   46: invokevirtual 74	com/alibaba/fastjson/JSONObject:get	(Ljava/lang/Object;)Ljava/lang/Object;
    //   49: checkcast 76	java/lang/String
    //   52: ldc 78
    //   54: invokevirtual 81	java/lang/String:equals	(Ljava/lang/Object;)Z
    //   57: ifeq +12 -> 69
    //   60: aload_0
    //   61: getfield 20	com/tencent/qqmail/namelist/NameListCGIManager$1:val$accountId	I
    //   64: iconst_0
    //   65: invokestatic 87	com/tencent/qqmail/model/mail/watcher/QMWatcherCenter:triggerLoadNameListSuccess	(IZ)V
    //   68: return
    //   69: aload_0
    //   70: getfield 16	com/tencent/qqmail/namelist/NameListCGIManager$1:this$0	Lcom/tencent/qqmail/namelist/NameListCGIManager;
    //   73: invokestatic 58	com/tencent/qqmail/namelist/NameListCGIManager:access$000	(Lcom/tencent/qqmail/namelist/NameListCGIManager;)Lcom/tencent/qqmail/model/mail/QMMailSQLiteHelper;
    //   76: getfield 91	com/tencent/qqmail/model/mail/QMMailSQLiteHelper:nameList	Lcom/tencent/qqmail/namelist/NameListSQLite;
    //   79: aload_1
    //   80: aload_0
    //   81: getfield 20	com/tencent/qqmail/namelist/NameListCGIManager$1:val$accountId	I
    //   84: invokevirtual 97	com/tencent/qqmail/namelist/NameListSQLite:deleteNameListContactByAccountId	(Lcom/tencent/moai/database/sqlite/SQLiteDatabase;I)V
    //   87: aload_1
    //   88: invokevirtual 102	com/tencent/moai/database/sqlite/SQLiteDatabase:beginTransaction	()V
    //   91: aload_2
    //   92: ldc 104
    //   94: invokevirtual 70	com/alibaba/fastjson/JSONObject:containsKey	(Ljava/lang/Object;)Z
    //   97: ifeq +26 -> 123
    //   100: aload_2
    //   101: ldc 104
    //   103: invokevirtual 108	com/alibaba/fastjson/JSONObject:getJSONObject	(Ljava/lang/String;)Lcom/alibaba/fastjson/JSONObject;
    //   106: astore_3
    //   107: aload_0
    //   108: getfield 16	com/tencent/qqmail/namelist/NameListCGIManager$1:this$0	Lcom/tencent/qqmail/namelist/NameListCGIManager;
    //   111: aload_1
    //   112: aload_0
    //   113: getfield 20	com/tencent/qqmail/namelist/NameListCGIManager$1:val$accountId	I
    //   116: aload_3
    //   117: getstatic 114	com/tencent/qqmail/namelist/model/NameListContact$NameListContactType:BLACK	Lcom/tencent/qqmail/namelist/model/NameListContact$NameListContactType;
    //   120: invokestatic 118	com/tencent/qqmail/namelist/NameListCGIManager:access$100	(Lcom/tencent/qqmail/namelist/NameListCGIManager;Lcom/tencent/moai/database/sqlite/SQLiteDatabase;ILcom/alibaba/fastjson/JSONObject;Lcom/tencent/qqmail/namelist/model/NameListContact$NameListContactType;)V
    //   123: aload_2
    //   124: ldc 120
    //   126: invokevirtual 70	com/alibaba/fastjson/JSONObject:containsKey	(Ljava/lang/Object;)Z
    //   129: ifeq +56 -> 185
    //   132: aload_2
    //   133: ldc 120
    //   135: invokevirtual 74	com/alibaba/fastjson/JSONObject:get	(Ljava/lang/Object;)Ljava/lang/Object;
    //   138: checkcast 76	java/lang/String
    //   141: astore_3
    //   142: aload_3
    //   143: invokestatic 126	org/apache/commons/lang3/StringUtils:isBlank	(Ljava/lang/CharSequence;)Z
    //   146: ifne +39 -> 185
    //   149: iconst_4
    //   150: ldc 30
    //   152: new 128	java/lang/StringBuilder
    //   155: dup
    //   156: invokespecial 129	java/lang/StringBuilder:<init>	()V
    //   159: ldc 131
    //   161: invokevirtual 135	java/lang/StringBuilder:append	(Ljava/lang/String;)Ljava/lang/StringBuilder;
    //   164: aload_3
    //   165: invokevirtual 135	java/lang/StringBuilder:append	(Ljava/lang/String;)Ljava/lang/StringBuilder;
    //   168: invokevirtual 139	java/lang/StringBuilder:toString	()Ljava/lang/String;
    //   171: invokestatic 38	com/tencent/qqmail/utilities/log/QMLog:log	(ILjava/lang/String;Ljava/lang/String;)V
    //   174: invokestatic 145	com/tencent/qqmail/model/mail/QMSettingManager:sharedInstance	()Lcom/tencent/qqmail/model/mail/QMSettingManager;
    //   177: aload_0
    //   178: getfield 20	com/tencent/qqmail/namelist/NameListCGIManager$1:val$accountId	I
    //   181: aload_3
    //   182: invokevirtual 149	com/tencent/qqmail/model/mail/QMSettingManager:setNameListSyncKey	(ILjava/lang/String;)V
    //   185: aload_2
    //   186: ldc 151
    //   188: invokevirtual 70	com/alibaba/fastjson/JSONObject:containsKey	(Ljava/lang/Object;)Z
    //   191: ifeq +10 -> 201
    //   194: aload_2
    //   195: ldc 151
    //   197: invokevirtual 108	com/alibaba/fastjson/JSONObject:getJSONObject	(Ljava/lang/String;)Lcom/alibaba/fastjson/JSONObject;
    //   200: pop
    //   201: aload_2
    //   202: ldc 153
    //   204: invokevirtual 70	com/alibaba/fastjson/JSONObject:containsKey	(Ljava/lang/Object;)Z
    //   207: ifeq +26 -> 233
    //   210: aload_2
    //   211: ldc 153
    //   213: invokevirtual 108	com/alibaba/fastjson/JSONObject:getJSONObject	(Ljava/lang/String;)Lcom/alibaba/fastjson/JSONObject;
    //   216: astore_3
    //   217: aload_0
    //   218: getfield 16	com/tencent/qqmail/namelist/NameListCGIManager$1:this$0	Lcom/tencent/qqmail/namelist/NameListCGIManager;
    //   221: aload_1
    //   222: aload_0
    //   223: getfield 20	com/tencent/qqmail/namelist/NameListCGIManager$1:val$accountId	I
    //   226: aload_3
    //   227: getstatic 156	com/tencent/qqmail/namelist/model/NameListContact$NameListContactType:WHITE	Lcom/tencent/qqmail/namelist/model/NameListContact$NameListContactType;
    //   230: invokestatic 118	com/tencent/qqmail/namelist/NameListCGIManager:access$100	(Lcom/tencent/qqmail/namelist/NameListCGIManager;Lcom/tencent/moai/database/sqlite/SQLiteDatabase;ILcom/alibaba/fastjson/JSONObject;Lcom/tencent/qqmail/namelist/model/NameListContact$NameListContactType;)V
    //   233: aload_2
    //   234: ldc 158
    //   236: invokevirtual 70	com/alibaba/fastjson/JSONObject:containsKey	(Ljava/lang/Object;)Z
    //   239: ifeq +10 -> 249
    //   242: aload_2
    //   243: ldc 158
    //   245: invokevirtual 108	com/alibaba/fastjson/JSONObject:getJSONObject	(Ljava/lang/String;)Lcom/alibaba/fastjson/JSONObject;
    //   248: pop
    //   249: aload_1
    //   250: invokevirtual 161	com/tencent/moai/database/sqlite/SQLiteDatabase:setTransactionSuccessful	()V
    //   253: aload_1
    //   254: invokevirtual 164	com/tencent/moai/database/sqlite/SQLiteDatabase:endTransaction	()V
    //   257: aload_0
    //   258: getfield 20	com/tencent/qqmail/namelist/NameListCGIManager$1:val$accountId	I
    //   261: iconst_1
    //   262: invokestatic 87	com/tencent/qqmail/model/mail/watcher/QMWatcherCenter:triggerLoadNameListSuccess	(IZ)V
    //   265: return
    //   266: astore_2
    //   267: bipush 6
    //   269: ldc 30
    //   271: new 128	java/lang/StringBuilder
    //   274: dup
    //   275: invokespecial 129	java/lang/StringBuilder:<init>	()V
    //   278: ldc 166
    //   280: invokevirtual 135	java/lang/StringBuilder:append	(Ljava/lang/String;)Ljava/lang/StringBuilder;
    //   283: aload_2
    //   284: invokestatic 172	android/util/Log:getStackTraceString	(Ljava/lang/Throwable;)Ljava/lang/String;
    //   287: invokevirtual 135	java/lang/StringBuilder:append	(Ljava/lang/String;)Ljava/lang/StringBuilder;
    //   290: invokevirtual 139	java/lang/StringBuilder:toString	()Ljava/lang/String;
    //   293: invokestatic 38	com/tencent/qqmail/utilities/log/QMLog:log	(ILjava/lang/String;Ljava/lang/String;)V
    //   296: aload_1
    //   297: invokevirtual 164	com/tencent/moai/database/sqlite/SQLiteDatabase:endTransaction	()V
    //   300: goto -43 -> 257
    //   303: astore_1
    //   304: bipush 6
    //   306: ldc 30
    //   308: new 128	java/lang/StringBuilder
    //   311: dup
    //   312: invokespecial 129	java/lang/StringBuilder:<init>	()V
    //   315: ldc 174
    //   317: invokevirtual 135	java/lang/StringBuilder:append	(Ljava/lang/String;)Ljava/lang/StringBuilder;
    //   320: aload_1
    //   321: invokestatic 172	android/util/Log:getStackTraceString	(Ljava/lang/Throwable;)Ljava/lang/String;
    //   324: invokevirtual 135	java/lang/StringBuilder:append	(Ljava/lang/String;)Ljava/lang/StringBuilder;
    //   327: invokevirtual 139	java/lang/StringBuilder:toString	()Ljava/lang/String;
    //   330: invokestatic 38	com/tencent/qqmail/utilities/log/QMLog:log	(ILjava/lang/String;Ljava/lang/String;)V
    //   333: goto -76 -> 257
    //   336: astore_2
    //   337: aload_1
    //   338: invokevirtual 164	com/tencent/moai/database/sqlite/SQLiteDatabase:endTransaction	()V
    //   341: aload_2
    //   342: athrow
    // Local variable table:
    //   start	length	slot	name	signature
    //   0	343	0	this	1
    //   0	343	1	paramQMNetworkRequest	com.tencent.qqmail.utilities.qmnetwork.QMNetworkRequest
    //   0	343	2	paramQMNetworkResponse	com.tencent.qqmail.utilities.qmnetwork.QMNetworkResponse
    //   106	121	3	localObject	Object
    // Exception table:
    //   from	to	target	type
    //   69	123	266	java/lang/Exception
    //   123	185	266	java/lang/Exception
    //   185	201	266	java/lang/Exception
    //   201	233	266	java/lang/Exception
    //   233	249	266	java/lang/Exception
    //   249	253	266	java/lang/Exception
    //   15	68	303	java/lang/Exception
    //   253	257	303	java/lang/Exception
    //   296	300	303	java/lang/Exception
    //   337	343	303	java/lang/Exception
    //   69	123	336	finally
    //   123	185	336	finally
    //   185	201	336	finally
    //   201	233	336	finally
    //   233	249	336	finally
    //   249	253	336	finally
    //   267	296	336	finally
  }
}


/* Location:           L:\local\mybackup\temp\qq_apk\com.tencent.tim\classes11.jar
 * Qualified Name:     com.tencent.qqmail.namelist.NameListCGIManager.1
 * JD-Core Version:    0.7.0.1
 */