package com.tencent.mm.plugin.card.model;

import com.tencent.mm.ah.b;
import com.tencent.mm.ah.b.a;
import com.tencent.mm.ah.b.b;
import com.tencent.mm.ah.f;
import com.tencent.mm.ah.m;
import com.tencent.mm.kernel.g;
import com.tencent.mm.network.k;
import com.tencent.mm.protocal.c.adq;
import com.tencent.mm.protocal.c.adr;
import com.tencent.mm.protocal.c.boo;
import com.tencent.mm.protocal.c.mj;
import com.tencent.mm.storage.ac.a;
import com.tencent.mm.storage.z;

public final class ad
  extends m
  implements k
{
  private final b dmK;
  private f dmL;
  public boolean inE = false;
  public mj inF;
  public boo inG;
  public int inH;
  
  public ad(double paramDouble1, double paramDouble2, int paramInt)
  {
    Object localObject = new b.a();
    ((b.a)localObject).ecH = new adq();
    ((b.a)localObject).ecI = new adr();
    ((b.a)localObject).uri = "/cgi-bin/micromsg-bin/getcardslayout";
    ((b.a)localObject).ecG = 984;
    ((b.a)localObject).ecJ = 0;
    ((b.a)localObject).ecK = 0;
    this.dmK = ((b.a)localObject).Kt();
    localObject = (adq)this.dmK.ecE.ecN;
    ((adq)localObject).latitude = paramDouble1;
    ((adq)localObject).longitude = paramDouble2;
    ((adq)localObject).scene = paramInt;
    ((adq)localObject).tbK = ((String)g.DP().Dz().get(ac.a.uoW, null));
  }
  
  public final int a(com.tencent.mm.network.e parame, f paramf)
  {
    this.dmL = paramf;
    return a(parame, this.dmK, this);
  }
  
  /* Error */
  public final void a(int paramInt1, int paramInt2, int paramInt3, String paramString, com.tencent.mm.network.q paramq, byte[] paramArrayOfByte)
  {
    // Byte code:
    //   0: ldc 125
    //   2: ldc 127
    //   4: iconst_2
    //   5: anewarray 129	java/lang/Object
    //   8: dup
    //   9: iconst_0
    //   10: iload_2
    //   11: invokestatic 135	java/lang/Integer:valueOf	(I)Ljava/lang/Integer;
    //   14: aastore
    //   15: dup
    //   16: iconst_1
    //   17: iload_3
    //   18: invokestatic 135	java/lang/Integer:valueOf	(I)Ljava/lang/Integer;
    //   21: aastore
    //   22: invokestatic 141	com/tencent/mm/sdk/platformtools/y:i	(Ljava/lang/String;Ljava/lang/String;[Ljava/lang/Object;)V
    //   25: aload_0
    //   26: getfield 62	com/tencent/mm/plugin/card/model/ad:dmK	Lcom/tencent/mm/ah/b;
    //   29: getfield 145	com/tencent/mm/ah/b:ecF	Lcom/tencent/mm/ah/b$c;
    //   32: getfield 148	com/tencent/mm/ah/b$c:ecN	Lcom/tencent/mm/bv/a;
    //   35: checkcast 37	com/tencent/mm/protocal/c/adr
    //   38: astore 14
    //   40: ldc 125
    //   42: new 150	java/lang/StringBuilder
    //   45: dup
    //   46: ldc 152
    //   48: invokespecial 155	java/lang/StringBuilder:<init>	(Ljava/lang/String;)V
    //   51: aload 14
    //   53: getfield 158	com/tencent/mm/protocal/c/adr:inn	Ljava/lang/String;
    //   56: invokevirtual 162	java/lang/StringBuilder:append	(Ljava/lang/String;)Ljava/lang/StringBuilder;
    //   59: invokevirtual 166	java/lang/StringBuilder:toString	()Ljava/lang/String;
    //   62: invokestatic 170	com/tencent/mm/sdk/platformtools/y:v	(Ljava/lang/String;Ljava/lang/String;)V
    //   65: aload_0
    //   66: aload 14
    //   68: getfield 173	com/tencent/mm/protocal/c/adr:tbL	Lcom/tencent/mm/protocal/c/mj;
    //   71: putfield 175	com/tencent/mm/plugin/card/model/ad:inF	Lcom/tencent/mm/protocal/c/mj;
    //   74: iload_2
    //   75: ifne +263 -> 338
    //   78: iload_3
    //   79: ifne +259 -> 338
    //   82: invokestatic 89	com/tencent/mm/kernel/g:DP	()Lcom/tencent/mm/kernel/e;
    //   85: invokevirtual 95	com/tencent/mm/kernel/e:Dz	()Lcom/tencent/mm/storage/z;
    //   88: getstatic 101	com/tencent/mm/storage/ac$a:uoW	Lcom/tencent/mm/storage/ac$a;
    //   91: aload 14
    //   93: getfield 176	com/tencent/mm/protocal/c/adr:tbK	Ljava/lang/String;
    //   96: invokevirtual 180	com/tencent/mm/storage/z:c	(Lcom/tencent/mm/storage/ac$a;Ljava/lang/Object;)V
    //   99: aload 14
    //   101: getfield 158	com/tencent/mm/protocal/c/adr:inn	Ljava/lang/String;
    //   104: astore 5
    //   106: invokestatic 186	java/lang/System:currentTimeMillis	()J
    //   109: lstore 8
    //   111: invokestatic 89	com/tencent/mm/kernel/g:DP	()Lcom/tencent/mm/kernel/e;
    //   114: invokevirtual 95	com/tencent/mm/kernel/e:Dz	()Lcom/tencent/mm/storage/z;
    //   117: getstatic 189	com/tencent/mm/storage/ac$a:uoV	Lcom/tencent/mm/storage/ac$a;
    //   120: aconst_null
    //   121: invokevirtual 107	com/tencent/mm/storage/z:get	(Lcom/tencent/mm/storage/ac$a;Ljava/lang/Object;)Ljava/lang/Object;
    //   124: checkcast 109	java/lang/String
    //   127: astore 6
    //   129: aload 6
    //   131: invokestatic 195	com/tencent/mm/sdk/platformtools/bk:bl	(Ljava/lang/String;)Z
    //   134: ifne +7 -> 141
    //   137: aload 6
    //   139: astore 5
    //   141: aload 5
    //   143: invokestatic 201	com/tencent/mm/plugin/card/d/j:yQ	(Ljava/lang/String;)Lcom/tencent/mm/protocal/c/adu;
    //   146: astore 6
    //   148: invokestatic 207	com/tencent/mm/plugin/card/model/am:aAs	()Lcom/tencent/mm/plugin/card/model/c;
    //   151: getfield 213	com/tencent/mm/plugin/card/model/c:dXw	Lcom/tencent/mm/sdk/e/e;
    //   154: ldc 215
    //   156: ldc 217
    //   158: invokeinterface 223 3 0
    //   163: pop
    //   164: aload 6
    //   166: ifnonnull +187 -> 353
    //   169: ldc 225
    //   171: ldc 227
    //   173: invokestatic 230	com/tencent/mm/sdk/platformtools/y:w	(Ljava/lang/String;Ljava/lang/String;)V
    //   176: iconst_0
    //   177: istore 12
    //   179: aload_0
    //   180: iload 12
    //   182: putfield 25	com/tencent/mm/plugin/card/model/ad:inE	Z
    //   185: aload_0
    //   186: getfield 175	com/tencent/mm/plugin/card/model/ad:inF	Lcom/tencent/mm/protocal/c/mj;
    //   189: ifnull +1202 -> 1391
    //   192: aload_0
    //   193: getfield 175	com/tencent/mm/plugin/card/model/ad:inF	Lcom/tencent/mm/protocal/c/mj;
    //   196: invokevirtual 236	com/tencent/mm/protocal/c/mj:toByteArray	()[B
    //   199: astore 5
    //   201: invokestatic 89	com/tencent/mm/kernel/g:DP	()Lcom/tencent/mm/kernel/e;
    //   204: invokevirtual 95	com/tencent/mm/kernel/e:Dz	()Lcom/tencent/mm/storage/z;
    //   207: getstatic 239	com/tencent/mm/storage/ac$a:upq	Lcom/tencent/mm/storage/ac$a;
    //   210: new 109	java/lang/String
    //   213: dup
    //   214: aload 5
    //   216: iconst_0
    //   217: aload 5
    //   219: arraylength
    //   220: ldc 241
    //   222: invokespecial 244	java/lang/String:<init>	([BIILjava/lang/String;)V
    //   225: invokevirtual 180	com/tencent/mm/storage/z:c	(Lcom/tencent/mm/storage/ac$a;Ljava/lang/Object;)V
    //   228: aload_0
    //   229: aload 14
    //   231: getfield 247	com/tencent/mm/protocal/c/adr:tbM	I
    //   234: putfield 249	com/tencent/mm/plugin/card/model/ad:inH	I
    //   237: aload_0
    //   238: getfield 249	com/tencent/mm/plugin/card/model/ad:inH	I
    //   241: ifge +8 -> 249
    //   244: aload_0
    //   245: iconst_0
    //   246: putfield 249	com/tencent/mm/plugin/card/model/ad:inH	I
    //   249: invokestatic 89	com/tencent/mm/kernel/g:DP	()Lcom/tencent/mm/kernel/e;
    //   252: invokevirtual 95	com/tencent/mm/kernel/e:Dz	()Lcom/tencent/mm/storage/z;
    //   255: getstatic 252	com/tencent/mm/storage/ac$a:ups	Lcom/tencent/mm/storage/ac$a;
    //   258: aload_0
    //   259: getfield 249	com/tencent/mm/plugin/card/model/ad:inH	I
    //   262: invokestatic 135	java/lang/Integer:valueOf	(I)Ljava/lang/Integer;
    //   265: invokevirtual 180	com/tencent/mm/storage/z:c	(Lcom/tencent/mm/storage/ac$a;Ljava/lang/Object;)V
    //   268: aload 14
    //   270: getfield 255	com/tencent/mm/protocal/c/adr:tbN	Lcom/tencent/mm/protocal/c/boo;
    //   273: ifnull +1155 -> 1428
    //   276: aload_0
    //   277: aload 14
    //   279: getfield 255	com/tencent/mm/protocal/c/adr:tbN	Lcom/tencent/mm/protocal/c/boo;
    //   282: putfield 257	com/tencent/mm/plugin/card/model/ad:inG	Lcom/tencent/mm/protocal/c/boo;
    //   285: aload 14
    //   287: getfield 255	com/tencent/mm/protocal/c/adr:tbN	Lcom/tencent/mm/protocal/c/boo;
    //   290: invokevirtual 260	com/tencent/mm/protocal/c/boo:toByteArray	()[B
    //   293: astore 5
    //   295: invokestatic 89	com/tencent/mm/kernel/g:DP	()Lcom/tencent/mm/kernel/e;
    //   298: invokevirtual 95	com/tencent/mm/kernel/e:Dz	()Lcom/tencent/mm/storage/z;
    //   301: getstatic 263	com/tencent/mm/storage/ac$a:upr	Lcom/tencent/mm/storage/ac$a;
    //   304: new 109	java/lang/String
    //   307: dup
    //   308: aload 5
    //   310: iconst_0
    //   311: aload 5
    //   313: arraylength
    //   314: ldc 241
    //   316: invokespecial 244	java/lang/String:<init>	([BIILjava/lang/String;)V
    //   319: invokevirtual 180	com/tencent/mm/storage/z:c	(Lcom/tencent/mm/storage/ac$a;Ljava/lang/Object;)V
    //   322: invokestatic 89	com/tencent/mm/kernel/g:DP	()Lcom/tencent/mm/kernel/e;
    //   325: invokevirtual 95	com/tencent/mm/kernel/e:Dz	()Lcom/tencent/mm/storage/z;
    //   328: getstatic 266	com/tencent/mm/storage/ac$a:upt	Lcom/tencent/mm/storage/ac$a;
    //   331: iconst_1
    //   332: invokestatic 271	java/lang/Boolean:valueOf	(Z)Ljava/lang/Boolean;
    //   335: invokevirtual 180	com/tencent/mm/storage/z:c	(Lcom/tencent/mm/storage/ac$a;Ljava/lang/Object;)V
    //   338: aload_0
    //   339: getfield 117	com/tencent/mm/plugin/card/model/ad:dmL	Lcom/tencent/mm/ah/f;
    //   342: iload_2
    //   343: iload_3
    //   344: aload 4
    //   346: aload_0
    //   347: invokeinterface 277 5 0
    //   352: return
    //   353: iconst_0
    //   354: istore 12
    //   356: iconst_0
    //   357: istore 13
    //   359: aload 6
    //   361: getfield 283	com/tencent/mm/protocal/c/adu:tbQ	Lcom/tencent/mm/protocal/c/nd;
    //   364: ifnull +1104 -> 1468
    //   367: aload 6
    //   369: getfield 283	com/tencent/mm/protocal/c/adu:tbQ	Lcom/tencent/mm/protocal/c/nd;
    //   372: astore 15
    //   374: new 285	java/util/HashMap
    //   377: dup
    //   378: invokespecial 286	java/util/HashMap:<init>	()V
    //   381: astore 15
    //   383: aload 15
    //   385: ldc_w 288
    //   388: iconst_2
    //   389: invokestatic 135	java/lang/Integer:valueOf	(I)Ljava/lang/Integer;
    //   392: invokeinterface 294 3 0
    //   397: pop
    //   398: aload 15
    //   400: ldc_w 296
    //   403: iconst_2
    //   404: invokestatic 135	java/lang/Integer:valueOf	(I)Ljava/lang/Integer;
    //   407: invokeinterface 294 3 0
    //   412: pop
    //   413: aload 15
    //   415: ldc_w 298
    //   418: iconst_3
    //   419: invokestatic 135	java/lang/Integer:valueOf	(I)Ljava/lang/Integer;
    //   422: invokeinterface 294 3 0
    //   427: pop
    //   428: aload 15
    //   430: ldc_w 300
    //   433: iconst_5
    //   434: invokestatic 135	java/lang/Integer:valueOf	(I)Ljava/lang/Integer;
    //   437: invokeinterface 294 3 0
    //   442: pop
    //   443: aload 6
    //   445: getfield 303	com/tencent/mm/protocal/c/adu:tbT	I
    //   448: bipush 100
    //   450: if_icmpne +866 -> 1316
    //   453: aload 15
    //   455: ldc_w 288
    //   458: iconst_4
    //   459: invokestatic 135	java/lang/Integer:valueOf	(I)Ljava/lang/Integer;
    //   462: invokeinterface 294 3 0
    //   467: pop
    //   468: invokestatic 89	com/tencent/mm/kernel/g:DP	()Lcom/tencent/mm/kernel/e;
    //   471: getfield 307	com/tencent/mm/kernel/e:dKu	Lcom/tencent/mm/cf/h;
    //   474: invokestatic 313	java/lang/Thread:currentThread	()Ljava/lang/Thread;
    //   477: invokevirtual 316	java/lang/Thread:getId	()J
    //   480: invokevirtual 322	com/tencent/mm/cf/h:eV	(J)J
    //   483: lstore 10
    //   485: aload 6
    //   487: getfield 283	com/tencent/mm/protocal/c/adu:tbQ	Lcom/tencent/mm/protocal/c/nd;
    //   490: getfield 328	com/tencent/mm/protocal/c/nd:sKP	Lcom/tencent/mm/protocal/c/nc;
    //   493: ifnull +969 -> 1462
    //   496: aload 6
    //   498: getfield 283	com/tencent/mm/protocal/c/adu:tbQ	Lcom/tencent/mm/protocal/c/nd;
    //   501: getfield 328	com/tencent/mm/protocal/c/nd:sKP	Lcom/tencent/mm/protocal/c/nc;
    //   504: getfield 334	com/tencent/mm/protocal/c/nc:sKO	Ljava/util/LinkedList;
    //   507: ifnull +955 -> 1462
    //   510: aload 6
    //   512: getfield 283	com/tencent/mm/protocal/c/adu:tbQ	Lcom/tencent/mm/protocal/c/nd;
    //   515: getfield 328	com/tencent/mm/protocal/c/nd:sKP	Lcom/tencent/mm/protocal/c/nc;
    //   518: getfield 334	com/tencent/mm/protocal/c/nc:sKO	Ljava/util/LinkedList;
    //   521: invokevirtual 340	java/util/LinkedList:size	()I
    //   524: ifle +938 -> 1462
    //   527: iconst_1
    //   528: istore 13
    //   530: aload 15
    //   532: ldc_w 288
    //   535: invokeinterface 343 2 0
    //   540: checkcast 131	java/lang/Integer
    //   543: invokevirtual 346	java/lang/Integer:intValue	()I
    //   546: istore_1
    //   547: aload 6
    //   549: getfield 283	com/tencent/mm/protocal/c/adu:tbQ	Lcom/tencent/mm/protocal/c/nd;
    //   552: getfield 328	com/tencent/mm/protocal/c/nd:sKP	Lcom/tencent/mm/protocal/c/nc;
    //   555: getfield 334	com/tencent/mm/protocal/c/nc:sKO	Ljava/util/LinkedList;
    //   558: iload_1
    //   559: ldc_w 347
    //   562: imul
    //   563: iconst_3
    //   564: iadd
    //   565: invokestatic 350	com/tencent/mm/plugin/card/d/j:c	(Ljava/util/LinkedList;I)V
    //   568: aload 6
    //   570: getfield 283	com/tencent/mm/protocal/c/adu:tbQ	Lcom/tencent/mm/protocal/c/nd;
    //   573: getfield 328	com/tencent/mm/protocal/c/nd:sKP	Lcom/tencent/mm/protocal/c/nc;
    //   576: getfield 334	com/tencent/mm/protocal/c/nc:sKO	Ljava/util/LinkedList;
    //   579: invokevirtual 340	java/util/LinkedList:size	()I
    //   582: iconst_0
    //   583: iadd
    //   584: istore 7
    //   586: iload 7
    //   588: istore_1
    //   589: iload 13
    //   591: istore 12
    //   593: aload 6
    //   595: getfield 283	com/tencent/mm/protocal/c/adu:tbQ	Lcom/tencent/mm/protocal/c/nd;
    //   598: getfield 353	com/tencent/mm/protocal/c/nd:sKQ	Lcom/tencent/mm/protocal/c/nc;
    //   601: ifnull +107 -> 708
    //   604: iload 7
    //   606: istore_1
    //   607: iload 13
    //   609: istore 12
    //   611: aload 6
    //   613: getfield 283	com/tencent/mm/protocal/c/adu:tbQ	Lcom/tencent/mm/protocal/c/nd;
    //   616: getfield 353	com/tencent/mm/protocal/c/nd:sKQ	Lcom/tencent/mm/protocal/c/nc;
    //   619: getfield 334	com/tencent/mm/protocal/c/nc:sKO	Ljava/util/LinkedList;
    //   622: ifnull +86 -> 708
    //   625: iload 7
    //   627: istore_1
    //   628: iload 13
    //   630: istore 12
    //   632: aload 6
    //   634: getfield 283	com/tencent/mm/protocal/c/adu:tbQ	Lcom/tencent/mm/protocal/c/nd;
    //   637: getfield 353	com/tencent/mm/protocal/c/nd:sKQ	Lcom/tencent/mm/protocal/c/nc;
    //   640: getfield 334	com/tencent/mm/protocal/c/nc:sKO	Ljava/util/LinkedList;
    //   643: invokevirtual 340	java/util/LinkedList:size	()I
    //   646: ifle +62 -> 708
    //   649: iconst_1
    //   650: istore 12
    //   652: aload 15
    //   654: ldc_w 296
    //   657: invokeinterface 343 2 0
    //   662: checkcast 131	java/lang/Integer
    //   665: invokevirtual 346	java/lang/Integer:intValue	()I
    //   668: istore_1
    //   669: aload 6
    //   671: getfield 283	com/tencent/mm/protocal/c/adu:tbQ	Lcom/tencent/mm/protocal/c/nd;
    //   674: getfield 353	com/tencent/mm/protocal/c/nd:sKQ	Lcom/tencent/mm/protocal/c/nc;
    //   677: getfield 334	com/tencent/mm/protocal/c/nc:sKO	Ljava/util/LinkedList;
    //   680: iload_1
    //   681: ldc_w 347
    //   684: imul
    //   685: iconst_2
    //   686: iadd
    //   687: invokestatic 350	com/tencent/mm/plugin/card/d/j:c	(Ljava/util/LinkedList;I)V
    //   690: iload 7
    //   692: aload 6
    //   694: getfield 283	com/tencent/mm/protocal/c/adu:tbQ	Lcom/tencent/mm/protocal/c/nd;
    //   697: getfield 353	com/tencent/mm/protocal/c/nd:sKQ	Lcom/tencent/mm/protocal/c/nc;
    //   700: getfield 334	com/tencent/mm/protocal/c/nc:sKO	Ljava/util/LinkedList;
    //   703: invokevirtual 340	java/util/LinkedList:size	()I
    //   706: iadd
    //   707: istore_1
    //   708: iload_1
    //   709: istore 7
    //   711: iload 12
    //   713: istore 13
    //   715: aload 6
    //   717: getfield 283	com/tencent/mm/protocal/c/adu:tbQ	Lcom/tencent/mm/protocal/c/nd;
    //   720: getfield 356	com/tencent/mm/protocal/c/nd:sKR	Lcom/tencent/mm/protocal/c/nc;
    //   723: ifnull +109 -> 832
    //   726: iload_1
    //   727: istore 7
    //   729: iload 12
    //   731: istore 13
    //   733: aload 6
    //   735: getfield 283	com/tencent/mm/protocal/c/adu:tbQ	Lcom/tencent/mm/protocal/c/nd;
    //   738: getfield 356	com/tencent/mm/protocal/c/nd:sKR	Lcom/tencent/mm/protocal/c/nc;
    //   741: getfield 334	com/tencent/mm/protocal/c/nc:sKO	Ljava/util/LinkedList;
    //   744: ifnull +88 -> 832
    //   747: iload_1
    //   748: istore 7
    //   750: iload 12
    //   752: istore 13
    //   754: aload 6
    //   756: getfield 283	com/tencent/mm/protocal/c/adu:tbQ	Lcom/tencent/mm/protocal/c/nd;
    //   759: getfield 356	com/tencent/mm/protocal/c/nd:sKR	Lcom/tencent/mm/protocal/c/nc;
    //   762: getfield 334	com/tencent/mm/protocal/c/nc:sKO	Ljava/util/LinkedList;
    //   765: invokevirtual 340	java/util/LinkedList:size	()I
    //   768: ifle +64 -> 832
    //   771: iconst_1
    //   772: istore 13
    //   774: aload 15
    //   776: ldc_w 298
    //   779: invokeinterface 343 2 0
    //   784: checkcast 131	java/lang/Integer
    //   787: invokevirtual 346	java/lang/Integer:intValue	()I
    //   790: istore 7
    //   792: aload 6
    //   794: getfield 283	com/tencent/mm/protocal/c/adu:tbQ	Lcom/tencent/mm/protocal/c/nd;
    //   797: getfield 356	com/tencent/mm/protocal/c/nd:sKR	Lcom/tencent/mm/protocal/c/nc;
    //   800: getfield 334	com/tencent/mm/protocal/c/nc:sKO	Ljava/util/LinkedList;
    //   803: iload 7
    //   805: ldc_w 347
    //   808: imul
    //   809: iconst_1
    //   810: iadd
    //   811: invokestatic 350	com/tencent/mm/plugin/card/d/j:c	(Ljava/util/LinkedList;I)V
    //   814: iload_1
    //   815: aload 6
    //   817: getfield 283	com/tencent/mm/protocal/c/adu:tbQ	Lcom/tencent/mm/protocal/c/nd;
    //   820: getfield 356	com/tencent/mm/protocal/c/nd:sKR	Lcom/tencent/mm/protocal/c/nc;
    //   823: getfield 334	com/tencent/mm/protocal/c/nc:sKO	Ljava/util/LinkedList;
    //   826: invokevirtual 340	java/util/LinkedList:size	()I
    //   829: iadd
    //   830: istore 7
    //   832: iload 7
    //   834: istore_1
    //   835: iload 13
    //   837: istore 12
    //   839: aload 6
    //   841: getfield 283	com/tencent/mm/protocal/c/adu:tbQ	Lcom/tencent/mm/protocal/c/nd;
    //   844: getfield 359	com/tencent/mm/protocal/c/nd:sKS	Lcom/tencent/mm/protocal/c/nc;
    //   847: ifnull +84 -> 931
    //   850: iload 7
    //   852: istore_1
    //   853: iload 13
    //   855: istore 12
    //   857: aload 6
    //   859: getfield 283	com/tencent/mm/protocal/c/adu:tbQ	Lcom/tencent/mm/protocal/c/nd;
    //   862: getfield 359	com/tencent/mm/protocal/c/nd:sKS	Lcom/tencent/mm/protocal/c/nc;
    //   865: getfield 334	com/tencent/mm/protocal/c/nc:sKO	Ljava/util/LinkedList;
    //   868: ifnull +63 -> 931
    //   871: iload 7
    //   873: istore_1
    //   874: iload 13
    //   876: istore 12
    //   878: aload 6
    //   880: getfield 283	com/tencent/mm/protocal/c/adu:tbQ	Lcom/tencent/mm/protocal/c/nd;
    //   883: getfield 359	com/tencent/mm/protocal/c/nd:sKS	Lcom/tencent/mm/protocal/c/nc;
    //   886: getfield 334	com/tencent/mm/protocal/c/nc:sKO	Ljava/util/LinkedList;
    //   889: invokevirtual 340	java/util/LinkedList:size	()I
    //   892: ifle +39 -> 931
    //   895: iconst_1
    //   896: istore 12
    //   898: iload 7
    //   900: aload 6
    //   902: getfield 283	com/tencent/mm/protocal/c/adu:tbQ	Lcom/tencent/mm/protocal/c/nd;
    //   905: getfield 359	com/tencent/mm/protocal/c/nd:sKS	Lcom/tencent/mm/protocal/c/nc;
    //   908: getfield 334	com/tencent/mm/protocal/c/nc:sKO	Ljava/util/LinkedList;
    //   911: invokevirtual 340	java/util/LinkedList:size	()I
    //   914: iadd
    //   915: istore_1
    //   916: aload 6
    //   918: getfield 283	com/tencent/mm/protocal/c/adu:tbQ	Lcom/tencent/mm/protocal/c/nd;
    //   921: getfield 359	com/tencent/mm/protocal/c/nd:sKS	Lcom/tencent/mm/protocal/c/nc;
    //   924: getfield 334	com/tencent/mm/protocal/c/nc:sKO	Ljava/util/LinkedList;
    //   927: iconst_0
    //   928: invokestatic 362	com/tencent/mm/plugin/card/d/j:d	(Ljava/util/LinkedList;I)V
    //   931: iload_1
    //   932: istore 7
    //   934: iload 12
    //   936: istore 13
    //   938: aload 6
    //   940: getfield 283	com/tencent/mm/protocal/c/adu:tbQ	Lcom/tencent/mm/protocal/c/nd;
    //   943: getfield 365	com/tencent/mm/protocal/c/nd:sKT	Lcom/tencent/mm/protocal/c/nc;
    //   946: ifnull +125 -> 1071
    //   949: iload_1
    //   950: istore 7
    //   952: iload 12
    //   954: istore 13
    //   956: aload 6
    //   958: getfield 283	com/tencent/mm/protocal/c/adu:tbQ	Lcom/tencent/mm/protocal/c/nd;
    //   961: getfield 365	com/tencent/mm/protocal/c/nd:sKT	Lcom/tencent/mm/protocal/c/nc;
    //   964: getfield 334	com/tencent/mm/protocal/c/nc:sKO	Ljava/util/LinkedList;
    //   967: ifnull +104 -> 1071
    //   970: iload_1
    //   971: istore 7
    //   973: iload 12
    //   975: istore 13
    //   977: aload 6
    //   979: getfield 283	com/tencent/mm/protocal/c/adu:tbQ	Lcom/tencent/mm/protocal/c/nd;
    //   982: getfield 365	com/tencent/mm/protocal/c/nd:sKT	Lcom/tencent/mm/protocal/c/nc;
    //   985: getfield 334	com/tencent/mm/protocal/c/nc:sKO	Ljava/util/LinkedList;
    //   988: invokevirtual 340	java/util/LinkedList:size	()I
    //   991: ifle +80 -> 1071
    //   994: iconst_1
    //   995: istore 13
    //   997: aload 15
    //   999: ldc_w 300
    //   1002: invokeinterface 343 2 0
    //   1007: checkcast 131	java/lang/Integer
    //   1010: invokevirtual 346	java/lang/Integer:intValue	()I
    //   1013: ldc_w 347
    //   1016: imul
    //   1017: iconst_4
    //   1018: iadd
    //   1019: istore 7
    //   1021: aload 6
    //   1023: getfield 283	com/tencent/mm/protocal/c/adu:tbQ	Lcom/tencent/mm/protocal/c/nd;
    //   1026: getfield 365	com/tencent/mm/protocal/c/nd:sKT	Lcom/tencent/mm/protocal/c/nc;
    //   1029: getfield 334	com/tencent/mm/protocal/c/nc:sKO	Ljava/util/LinkedList;
    //   1032: iload 7
    //   1034: invokestatic 350	com/tencent/mm/plugin/card/d/j:c	(Ljava/util/LinkedList;I)V
    //   1037: aload 6
    //   1039: getfield 283	com/tencent/mm/protocal/c/adu:tbQ	Lcom/tencent/mm/protocal/c/nd;
    //   1042: getfield 365	com/tencent/mm/protocal/c/nd:sKT	Lcom/tencent/mm/protocal/c/nc;
    //   1045: getfield 334	com/tencent/mm/protocal/c/nc:sKO	Ljava/util/LinkedList;
    //   1048: iload 7
    //   1050: invokestatic 362	com/tencent/mm/plugin/card/d/j:d	(Ljava/util/LinkedList;I)V
    //   1053: iload_1
    //   1054: aload 6
    //   1056: getfield 283	com/tencent/mm/protocal/c/adu:tbQ	Lcom/tencent/mm/protocal/c/nd;
    //   1059: getfield 365	com/tencent/mm/protocal/c/nd:sKT	Lcom/tencent/mm/protocal/c/nc;
    //   1062: getfield 334	com/tencent/mm/protocal/c/nc:sKO	Ljava/util/LinkedList;
    //   1065: invokevirtual 340	java/util/LinkedList:size	()I
    //   1068: iadd
    //   1069: istore 7
    //   1071: invokestatic 89	com/tencent/mm/kernel/g:DP	()Lcom/tencent/mm/kernel/e;
    //   1074: getfield 307	com/tencent/mm/kernel/e:dKu	Lcom/tencent/mm/cf/h;
    //   1077: lload 10
    //   1079: invokevirtual 369	com/tencent/mm/cf/h:hI	(J)I
    //   1082: pop
    //   1083: invokestatic 373	com/tencent/mm/plugin/card/model/am:aAx	()Lcom/tencent/mm/plugin/card/b/e;
    //   1086: ldc_w 375
    //   1089: aload 6
    //   1091: invokevirtual 381	com/tencent/mm/plugin/card/b/e:putValue	(Ljava/lang/String;Ljava/lang/Object;)V
    //   1094: invokestatic 89	com/tencent/mm/kernel/g:DP	()Lcom/tencent/mm/kernel/e;
    //   1097: invokevirtual 95	com/tencent/mm/kernel/e:Dz	()Lcom/tencent/mm/storage/z;
    //   1100: getstatic 384	com/tencent/mm/storage/ac$a:upe	Lcom/tencent/mm/storage/ac$a;
    //   1103: aload 5
    //   1105: invokevirtual 180	com/tencent/mm/storage/z:c	(Lcom/tencent/mm/storage/ac$a;Ljava/lang/Object;)V
    //   1108: iload 13
    //   1110: istore 12
    //   1112: iload 7
    //   1114: ifle -935 -> 179
    //   1117: invokestatic 186	java/lang/System:currentTimeMillis	()J
    //   1120: lstore 10
    //   1122: new 386	java/util/ArrayList
    //   1125: dup
    //   1126: invokespecial 387	java/util/ArrayList:<init>	()V
    //   1129: astore 5
    //   1131: new 389	com/tencent/mars/smc/IDKey
    //   1134: dup
    //   1135: invokespecial 390	com/tencent/mars/smc/IDKey:<init>	()V
    //   1138: astore 6
    //   1140: aload 6
    //   1142: sipush 281
    //   1145: invokevirtual 394	com/tencent/mars/smc/IDKey:SetID	(I)V
    //   1148: aload 6
    //   1150: bipush 36
    //   1152: invokevirtual 397	com/tencent/mars/smc/IDKey:SetKey	(I)V
    //   1155: aload 6
    //   1157: lconst_1
    //   1158: invokevirtual 401	com/tencent/mars/smc/IDKey:SetValue	(J)V
    //   1161: new 389	com/tencent/mars/smc/IDKey
    //   1164: dup
    //   1165: invokespecial 390	com/tencent/mars/smc/IDKey:<init>	()V
    //   1168: astore 15
    //   1170: aload 15
    //   1172: sipush 281
    //   1175: invokevirtual 394	com/tencent/mars/smc/IDKey:SetID	(I)V
    //   1178: aload 15
    //   1180: bipush 37
    //   1182: invokevirtual 397	com/tencent/mars/smc/IDKey:SetKey	(I)V
    //   1185: aload 15
    //   1187: lload 10
    //   1189: lload 8
    //   1191: lsub
    //   1192: l2i
    //   1193: i2l
    //   1194: invokevirtual 401	com/tencent/mars/smc/IDKey:SetValue	(J)V
    //   1197: new 389	com/tencent/mars/smc/IDKey
    //   1200: dup
    //   1201: invokespecial 390	com/tencent/mars/smc/IDKey:<init>	()V
    //   1204: astore 16
    //   1206: aload 16
    //   1208: sipush 281
    //   1211: invokevirtual 394	com/tencent/mars/smc/IDKey:SetID	(I)V
    //   1214: aload 16
    //   1216: bipush 38
    //   1218: invokevirtual 397	com/tencent/mars/smc/IDKey:SetKey	(I)V
    //   1221: aload 16
    //   1223: iload 7
    //   1225: i2l
    //   1226: invokevirtual 401	com/tencent/mars/smc/IDKey:SetValue	(J)V
    //   1229: new 389	com/tencent/mars/smc/IDKey
    //   1232: dup
    //   1233: invokespecial 390	com/tencent/mars/smc/IDKey:<init>	()V
    //   1236: astore 17
    //   1238: aload 17
    //   1240: sipush 281
    //   1243: invokevirtual 394	com/tencent/mars/smc/IDKey:SetID	(I)V
    //   1246: aload 17
    //   1248: bipush 40
    //   1250: invokevirtual 397	com/tencent/mars/smc/IDKey:SetKey	(I)V
    //   1253: aload 17
    //   1255: lload 10
    //   1257: lload 8
    //   1259: lsub
    //   1260: l2i
    //   1261: iload 7
    //   1263: idiv
    //   1264: i2l
    //   1265: invokevirtual 401	com/tencent/mars/smc/IDKey:SetValue	(J)V
    //   1268: aload 5
    //   1270: aload 6
    //   1272: invokevirtual 405	java/util/ArrayList:add	(Ljava/lang/Object;)Z
    //   1275: pop
    //   1276: aload 5
    //   1278: aload 15
    //   1280: invokevirtual 405	java/util/ArrayList:add	(Ljava/lang/Object;)Z
    //   1283: pop
    //   1284: aload 5
    //   1286: aload 16
    //   1288: invokevirtual 405	java/util/ArrayList:add	(Ljava/lang/Object;)Z
    //   1291: pop
    //   1292: aload 5
    //   1294: aload 17
    //   1296: invokevirtual 405	java/util/ArrayList:add	(Ljava/lang/Object;)Z
    //   1299: pop
    //   1300: getstatic 411	com/tencent/mm/plugin/report/service/h:nFQ	Lcom/tencent/mm/plugin/report/service/h;
    //   1303: aload 5
    //   1305: iconst_1
    //   1306: invokevirtual 415	com/tencent/mm/plugin/report/service/h:b	(Ljava/util/ArrayList;Z)V
    //   1309: iload 13
    //   1311: istore 12
    //   1313: goto -1134 -> 179
    //   1316: aload 6
    //   1318: getfield 303	com/tencent/mm/protocal/c/adu:tbT	I
    //   1321: bipush 102
    //   1323: if_icmpne +21 -> 1344
    //   1326: aload 15
    //   1328: ldc_w 296
    //   1331: iconst_4
    //   1332: invokestatic 135	java/lang/Integer:valueOf	(I)Ljava/lang/Integer;
    //   1335: invokeinterface 294 3 0
    //   1340: pop
    //   1341: goto -873 -> 468
    //   1344: aload 6
    //   1346: getfield 303	com/tencent/mm/protocal/c/adu:tbT	I
    //   1349: bipush 101
    //   1351: if_icmpne -883 -> 468
    //   1354: aload 15
    //   1356: ldc_w 298
    //   1359: iconst_4
    //   1360: invokestatic 135	java/lang/Integer:valueOf	(I)Ljava/lang/Integer;
    //   1363: invokeinterface 294 3 0
    //   1368: pop
    //   1369: goto -901 -> 468
    //   1372: astore 5
    //   1374: ldc 125
    //   1376: aload 5
    //   1378: ldc_w 417
    //   1381: iconst_0
    //   1382: anewarray 129	java/lang/Object
    //   1385: invokestatic 421	com/tencent/mm/sdk/platformtools/y:printErrStackTrace	(Ljava/lang/String;Ljava/lang/Throwable;Ljava/lang/String;[Ljava/lang/Object;)V
    //   1388: goto -1160 -> 228
    //   1391: invokestatic 89	com/tencent/mm/kernel/g:DP	()Lcom/tencent/mm/kernel/e;
    //   1394: invokevirtual 95	com/tencent/mm/kernel/e:Dz	()Lcom/tencent/mm/storage/z;
    //   1397: getstatic 239	com/tencent/mm/storage/ac$a:upq	Lcom/tencent/mm/storage/ac$a;
    //   1400: ldc_w 417
    //   1403: invokevirtual 180	com/tencent/mm/storage/z:c	(Lcom/tencent/mm/storage/ac$a;Ljava/lang/Object;)V
    //   1406: goto -1178 -> 228
    //   1409: astore 5
    //   1411: ldc 125
    //   1413: aload 5
    //   1415: ldc_w 417
    //   1418: iconst_0
    //   1419: anewarray 129	java/lang/Object
    //   1422: invokestatic 421	com/tencent/mm/sdk/platformtools/y:printErrStackTrace	(Ljava/lang/String;Ljava/lang/Throwable;Ljava/lang/String;[Ljava/lang/Object;)V
    //   1425: goto -1103 -> 322
    //   1428: invokestatic 89	com/tencent/mm/kernel/g:DP	()Lcom/tencent/mm/kernel/e;
    //   1431: invokevirtual 95	com/tencent/mm/kernel/e:Dz	()Lcom/tencent/mm/storage/z;
    //   1434: getstatic 263	com/tencent/mm/storage/ac$a:upr	Lcom/tencent/mm/storage/ac$a;
    //   1437: ldc_w 417
    //   1440: invokevirtual 180	com/tencent/mm/storage/z:c	(Lcom/tencent/mm/storage/ac$a;Ljava/lang/Object;)V
    //   1443: invokestatic 89	com/tencent/mm/kernel/g:DP	()Lcom/tencent/mm/kernel/e;
    //   1446: invokevirtual 95	com/tencent/mm/kernel/e:Dz	()Lcom/tencent/mm/storage/z;
    //   1449: getstatic 266	com/tencent/mm/storage/ac$a:upt	Lcom/tencent/mm/storage/ac$a;
    //   1452: iconst_0
    //   1453: invokestatic 271	java/lang/Boolean:valueOf	(Z)Ljava/lang/Boolean;
    //   1456: invokevirtual 180	com/tencent/mm/storage/z:c	(Lcom/tencent/mm/storage/ac$a;Ljava/lang/Object;)V
    //   1459: goto -1121 -> 338
    //   1462: iconst_0
    //   1463: istore 7
    //   1465: goto -879 -> 586
    //   1468: iconst_0
    //   1469: istore 7
    //   1471: iload 12
    //   1473: istore 13
    //   1475: goto -392 -> 1083
    // Local variable table:
    //   start	length	slot	name	signature
    //   0	1478	0	this	ad
    //   0	1478	1	paramInt1	int
    //   0	1478	2	paramInt2	int
    //   0	1478	3	paramInt3	int
    //   0	1478	4	paramString	String
    //   0	1478	5	paramq	com.tencent.mm.network.q
    //   0	1478	6	paramArrayOfByte	byte[]
    //   584	886	7	i	int
    //   109	1149	8	l1	long
    //   483	773	10	l2	long
    //   177	1295	12	bool1	boolean
    //   357	1117	13	bool2	boolean
    //   38	248	14	localadr	adr
    //   372	983	15	localObject	Object
    //   1204	83	16	localIDKey1	com.tencent.mars.smc.IDKey
    //   1236	59	17	localIDKey2	com.tencent.mars.smc.IDKey
    // Exception table:
    //   from	to	target	type
    //   192	228	1372	java/io/IOException
    //   285	322	1409	java/io/IOException
  }
  
  public final int getType()
  {
    return 984;
  }
}


/* Location:           L:\local\mybackup\temp\qq_apk\com.tencent.mm\classes9.jar
 * Qualified Name:     com.tencent.mm.plugin.card.model.ad
 * JD-Core Version:    0.7.0.1
 */