package com.tencent.mobileqq.vashealth;

class HealthBusinessPlugin$2
  implements Runnable
{
  HealthBusinessPlugin$2(HealthBusinessPlugin paramHealthBusinessPlugin, String paramString1, String paramString2) {}
  
  /* Error */
  public void run()
  {
    // Byte code:
    //   0: new 28	org/json/JSONObject
    //   3: dup
    //   4: invokespecial 29	org/json/JSONObject:<init>	()V
    //   7: astore_3
    //   8: new 31	org/json/JSONArray
    //   11: dup
    //   12: invokespecial 32	org/json/JSONArray:<init>	()V
    //   15: astore 4
    //   17: new 28	org/json/JSONObject
    //   20: dup
    //   21: aload_0
    //   22: getfield 17	com/tencent/mobileqq/vashealth/HealthBusinessPlugin$2:a	Ljava/lang/String;
    //   25: invokespecial 35	org/json/JSONObject:<init>	(Ljava/lang/String;)V
    //   28: ldc 37
    //   30: invokevirtual 41	org/json/JSONObject:getJSONArray	(Ljava/lang/String;)Lorg/json/JSONArray;
    //   33: astore 5
    //   35: getstatic 47	com/tencent/mobileqq/vashealth/HealthBusinessPlugin:e	Ljava/util/HashMap;
    //   38: astore_2
    //   39: aload_2
    //   40: monitorenter
    //   41: iconst_0
    //   42: istore_1
    //   43: iload_1
    //   44: aload 5
    //   46: invokevirtual 51	org/json/JSONArray:length	()I
    //   49: if_icmpge +172 -> 221
    //   52: aload 5
    //   54: iload_1
    //   55: invokevirtual 55	org/json/JSONArray:getString	(I)Ljava/lang/String;
    //   58: astore 6
    //   60: aload 6
    //   62: invokestatic 61	android/text/TextUtils:isEmpty	(Ljava/lang/CharSequence;)Z
    //   65: ifeq +6 -> 71
    //   68: goto +284 -> 352
    //   71: aload 6
    //   73: ldc 63
    //   75: invokevirtual 69	java/lang/String:startsWith	(Ljava/lang/String;)Z
    //   78: ifne +103 -> 181
    //   81: aload 6
    //   83: ldc 71
    //   85: invokevirtual 75	java/lang/String:equals	(Ljava/lang/Object;)Z
    //   88: ifeq +6 -> 94
    //   91: goto +90 -> 181
    //   94: getstatic 47	com/tencent/mobileqq/vashealth/HealthBusinessPlugin:e	Ljava/util/HashMap;
    //   97: aload 6
    //   99: invokevirtual 80	java/util/HashMap:containsKey	(Ljava/lang/Object;)Z
    //   102: ifeq +20 -> 122
    //   105: aload 4
    //   107: getstatic 47	com/tencent/mobileqq/vashealth/HealthBusinessPlugin:e	Ljava/util/HashMap;
    //   110: aload 6
    //   112: invokevirtual 84	java/util/HashMap:get	(Ljava/lang/Object;)Ljava/lang/Object;
    //   115: invokevirtual 88	org/json/JSONArray:put	(Ljava/lang/Object;)Lorg/json/JSONArray;
    //   118: pop
    //   119: goto +233 -> 352
    //   122: aload 6
    //   124: iconst_0
    //   125: invokestatic 91	com/tencent/mobileqq/vashealth/HealthBusinessPlugin:a	(Ljava/lang/String;I)Ljava/lang/String;
    //   128: astore 7
    //   130: new 28	org/json/JSONObject
    //   133: dup
    //   134: invokespecial 29	org/json/JSONObject:<init>	()V
    //   137: astore 8
    //   139: aload 8
    //   141: ldc 93
    //   143: aload 6
    //   145: invokevirtual 96	org/json/JSONObject:put	(Ljava/lang/String;Ljava/lang/Object;)Lorg/json/JSONObject;
    //   148: pop
    //   149: aload 8
    //   151: ldc 98
    //   153: aload 7
    //   155: invokevirtual 96	org/json/JSONObject:put	(Ljava/lang/String;Ljava/lang/Object;)Lorg/json/JSONObject;
    //   158: pop
    //   159: getstatic 47	com/tencent/mobileqq/vashealth/HealthBusinessPlugin:e	Ljava/util/HashMap;
    //   162: aload 6
    //   164: aload 8
    //   166: invokevirtual 101	java/util/HashMap:put	(Ljava/lang/Object;Ljava/lang/Object;)Ljava/lang/Object;
    //   169: pop
    //   170: aload 4
    //   172: aload 8
    //   174: invokevirtual 88	org/json/JSONArray:put	(Ljava/lang/Object;)Lorg/json/JSONArray;
    //   177: pop
    //   178: goto +174 -> 352
    //   181: new 28	org/json/JSONObject
    //   184: dup
    //   185: invokespecial 29	org/json/JSONObject:<init>	()V
    //   188: astore 7
    //   190: aload 7
    //   192: ldc 93
    //   194: ldc 103
    //   196: invokevirtual 96	org/json/JSONObject:put	(Ljava/lang/String;Ljava/lang/Object;)Lorg/json/JSONObject;
    //   199: pop
    //   200: aload 7
    //   202: ldc 98
    //   204: aload 6
    //   206: invokevirtual 96	org/json/JSONObject:put	(Ljava/lang/String;Ljava/lang/Object;)Lorg/json/JSONObject;
    //   209: pop
    //   210: aload 4
    //   212: aload 7
    //   214: invokevirtual 88	org/json/JSONArray:put	(Ljava/lang/Object;)Lorg/json/JSONArray;
    //   217: pop
    //   218: goto +134 -> 352
    //   221: aload_2
    //   222: monitorexit
    //   223: aload_3
    //   224: ldc 37
    //   226: aload 4
    //   228: invokevirtual 96	org/json/JSONObject:put	(Ljava/lang/String;Ljava/lang/Object;)Lorg/json/JSONObject;
    //   231: pop
    //   232: aload_0
    //   233: getfield 15	com/tencent/mobileqq/vashealth/HealthBusinessPlugin$2:this$0	Lcom/tencent/mobileqq/vashealth/HealthBusinessPlugin;
    //   236: aload_0
    //   237: getfield 19	com/tencent/mobileqq/vashealth/HealthBusinessPlugin$2:b	Ljava/lang/String;
    //   240: iconst_1
    //   241: anewarray 65	java/lang/String
    //   244: dup
    //   245: iconst_0
    //   246: aload_3
    //   247: invokevirtual 107	org/json/JSONObject:toString	()Ljava/lang/String;
    //   250: aastore
    //   251: invokestatic 110	com/tencent/mobileqq/vashealth/HealthBusinessPlugin:a	(Lcom/tencent/mobileqq/vashealth/HealthBusinessPlugin;Ljava/lang/String;[Ljava/lang/String;)V
    //   254: aload_0
    //   255: getfield 15	com/tencent/mobileqq/vashealth/HealthBusinessPlugin$2:this$0	Lcom/tencent/mobileqq/vashealth/HealthBusinessPlugin;
    //   258: getfield 113	com/tencent/mobileqq/vashealth/HealthBusinessPlugin:b	Lcom/tencent/mobileqq/widget/QQProgressDialog;
    //   261: invokevirtual 119	com/tencent/mobileqq/widget/QQProgressDialog:isShowing	()Z
    //   264: ifeq +56 -> 320
    //   267: goto +43 -> 310
    //   270: astore_3
    //   271: aload_2
    //   272: monitorexit
    //   273: aload_3
    //   274: athrow
    //   275: astore_2
    //   276: goto +45 -> 321
    //   279: astore_2
    //   280: invokestatic 124	com/tencent/qphone/base/util/QLog:isColorLevel	()Z
    //   283: ifeq +14 -> 297
    //   286: ldc 126
    //   288: iconst_2
    //   289: aload_2
    //   290: iconst_0
    //   291: anewarray 4	java/lang/Object
    //   294: invokestatic 129	com/tencent/qphone/base/util/QLog:e	(Ljava/lang/String;ILjava/lang/Throwable;[Ljava/lang/Object;)V
    //   297: aload_0
    //   298: getfield 15	com/tencent/mobileqq/vashealth/HealthBusinessPlugin$2:this$0	Lcom/tencent/mobileqq/vashealth/HealthBusinessPlugin;
    //   301: getfield 113	com/tencent/mobileqq/vashealth/HealthBusinessPlugin:b	Lcom/tencent/mobileqq/widget/QQProgressDialog;
    //   304: invokevirtual 119	com/tencent/mobileqq/widget/QQProgressDialog:isShowing	()Z
    //   307: ifeq +13 -> 320
    //   310: aload_0
    //   311: getfield 15	com/tencent/mobileqq/vashealth/HealthBusinessPlugin$2:this$0	Lcom/tencent/mobileqq/vashealth/HealthBusinessPlugin;
    //   314: getfield 113	com/tencent/mobileqq/vashealth/HealthBusinessPlugin:b	Lcom/tencent/mobileqq/widget/QQProgressDialog;
    //   317: invokevirtual 132	com/tencent/mobileqq/widget/QQProgressDialog:dismiss	()V
    //   320: return
    //   321: aload_0
    //   322: getfield 15	com/tencent/mobileqq/vashealth/HealthBusinessPlugin$2:this$0	Lcom/tencent/mobileqq/vashealth/HealthBusinessPlugin;
    //   325: getfield 113	com/tencent/mobileqq/vashealth/HealthBusinessPlugin:b	Lcom/tencent/mobileqq/widget/QQProgressDialog;
    //   328: invokevirtual 119	com/tencent/mobileqq/widget/QQProgressDialog:isShowing	()Z
    //   331: ifeq +13 -> 344
    //   334: aload_0
    //   335: getfield 15	com/tencent/mobileqq/vashealth/HealthBusinessPlugin$2:this$0	Lcom/tencent/mobileqq/vashealth/HealthBusinessPlugin;
    //   338: getfield 113	com/tencent/mobileqq/vashealth/HealthBusinessPlugin:b	Lcom/tencent/mobileqq/widget/QQProgressDialog;
    //   341: invokevirtual 132	com/tencent/mobileqq/widget/QQProgressDialog:dismiss	()V
    //   344: goto +5 -> 349
    //   347: aload_2
    //   348: athrow
    //   349: goto -2 -> 347
    //   352: iload_1
    //   353: iconst_1
    //   354: iadd
    //   355: istore_1
    //   356: goto -313 -> 43
    // Local variable table:
    //   start	length	slot	name	signature
    //   0	359	0	this	2
    //   42	314	1	i	int
    //   38	234	2	localHashMap	java.util.HashMap
    //   275	1	2	localObject1	Object
    //   279	69	2	localException	java.lang.Exception
    //   7	240	3	localJSONObject1	org.json.JSONObject
    //   270	4	3	localObject2	Object
    //   15	212	4	localJSONArray1	org.json.JSONArray
    //   33	20	5	localJSONArray2	org.json.JSONArray
    //   58	147	6	str	String
    //   128	85	7	localObject3	Object
    //   137	36	8	localJSONObject2	org.json.JSONObject
    // Exception table:
    //   from	to	target	type
    //   43	68	270	finally
    //   71	91	270	finally
    //   94	119	270	finally
    //   122	178	270	finally
    //   181	218	270	finally
    //   221	223	270	finally
    //   271	273	270	finally
    //   0	41	275	finally
    //   223	254	275	finally
    //   273	275	275	finally
    //   280	297	275	finally
    //   0	41	279	java/lang/Exception
    //   223	254	279	java/lang/Exception
    //   273	275	279	java/lang/Exception
  }
}


/* Location:           L:\local\mybackup\temp\qq_apk\com.tencent.mobileqq\classes12.jar
 * Qualified Name:     com.tencent.mobileqq.vashealth.HealthBusinessPlugin.2
 * JD-Core Version:    0.7.0.1
 */