package com.tencent.mm.app;

import android.app.Application;
import com.tencent.matrix.trace.core.AppMethodBeat;
import com.tencent.mm.loader.j.a;
import com.tencent.mm.sdk.platformtools.at;
import com.tencent.mm.sdk.platformtools.at.a;
import com.tencent.mm.sdk.platformtools.at.d;

public final class k
{
  public static String a(Application paramApplication, final String paramString)
  {
    AppMethodBeat.i(125023);
    if (!"com.tencent.mm:cuploader".equals(paramString))
    {
      at.a(new at.d()
      {
        /* Error */
        public final void b(at paramAnonymousat, String paramAnonymousString, java.lang.Throwable paramAnonymousThrowable)
        {
          // Byte code:
          //   0: ldc 30
          //   2: invokestatic 36	com/tencent/matrix/trace/core/AppMethodBeat:i	(I)V
          //   5: ldc 38
          //   7: ldc 40
          //   9: invokestatic 46	com/tencent/mm/sdk/platformtools/ac:e	(Ljava/lang/String;Ljava/lang/String;)V
          //   12: aload_0
          //   13: getfield 19	com/tencent/mm/app/k$1:cHK	Landroid/app/Application;
          //   16: astore 6
          //   18: aload_0
          //   19: getfield 21	com/tencent/mm/app/k$1:cIC	Ljava/lang/String;
          //   22: astore 4
          //   24: ldc 38
          //   26: ldc 48
          //   28: aload_2
          //   29: invokestatic 54	java/lang/String:valueOf	(Ljava/lang/Object;)Ljava/lang/String;
          //   32: invokevirtual 58	java/lang/String:concat	(Ljava/lang/String;)Ljava/lang/String;
          //   35: invokestatic 46	com/tencent/mm/sdk/platformtools/ac:e	(Ljava/lang/String;Ljava/lang/String;)V
          //   38: new 60	java/lang/StringBuilder
          //   41: dup
          //   42: sipush 2560
          //   45: invokespecial 62	java/lang/StringBuilder:<init>	(I)V
          //   48: astore 7
          //   50: new 64	android/util/StringBuilderPrinter
          //   53: dup
          //   54: aload 7
          //   56: invokespecial 67	android/util/StringBuilderPrinter:<init>	(Ljava/lang/StringBuilder;)V
          //   59: astore 8
          //   61: aload 8
          //   63: new 60	java/lang/StringBuilder
          //   66: dup
          //   67: ldc 69
          //   69: invokespecial 72	java/lang/StringBuilder:<init>	(Ljava/lang/String;)V
          //   72: getstatic 77	com/tencent/mm/loader/j/a:gMJ	Ljava/lang/String;
          //   75: invokevirtual 81	java/lang/StringBuilder:append	(Ljava/lang/String;)Ljava/lang/StringBuilder;
          //   78: invokevirtual 85	java/lang/StringBuilder:toString	()Ljava/lang/String;
          //   81: invokevirtual 88	android/util/StringBuilderPrinter:println	(Ljava/lang/String;)V
          //   84: getstatic 94	com/tencent/mm/sdk/platformtools/h:DEBUG	Z
          //   87: ifeq +739 -> 826
          //   90: aload 8
          //   92: ldc 96
          //   94: invokevirtual 88	android/util/StringBuilderPrinter:println	(Ljava/lang/String;)V
          //   97: getstatic 102	com/tencent/mm/loader/j/c:gMU	Lcom/tencent/mm/loader/j/c;
          //   100: ldc 104
          //   102: ldc 106
          //   104: invokevirtual 110	com/tencent/mm/loader/j/c:aw	(Ljava/lang/String;Ljava/lang/String;)Ljava/lang/String;
          //   107: astore 5
          //   109: aload 5
          //   111: ifnull +16 -> 127
          //   114: aload 5
          //   116: astore_1
          //   117: aload 5
          //   119: ldc 106
          //   121: invokevirtual 114	java/lang/String:equals	(Ljava/lang/Object;)Z
          //   124: ifeq +44 -> 168
          //   127: new 60	java/lang/StringBuilder
          //   130: dup
          //   131: invokespecial 115	java/lang/StringBuilder:<init>	()V
          //   134: getstatic 120	android/os/Build:DEVICE	Ljava/lang/String;
          //   137: invokevirtual 81	java/lang/StringBuilder:append	(Ljava/lang/String;)Ljava/lang/StringBuilder;
          //   140: getstatic 123	android/os/Build:FINGERPRINT	Ljava/lang/String;
          //   143: invokevirtual 81	java/lang/StringBuilder:append	(Ljava/lang/String;)Ljava/lang/StringBuilder;
          //   146: getstatic 126	android/os/Build:MANUFACTURER	Ljava/lang/String;
          //   149: invokevirtual 81	java/lang/StringBuilder:append	(Ljava/lang/String;)Ljava/lang/StringBuilder;
          //   152: getstatic 129	android/os/Build:MODEL	Ljava/lang/String;
          //   155: invokevirtual 81	java/lang/StringBuilder:append	(Ljava/lang/String;)Ljava/lang/StringBuilder;
          //   158: invokevirtual 85	java/lang/StringBuilder:toString	()Ljava/lang/String;
          //   161: invokevirtual 133	java/lang/String:hashCode	()I
          //   164: invokestatic 138	java/lang/Integer:toString	(I)Ljava/lang/String;
          //   167: astore_1
          //   168: aload 8
          //   170: ldc 140
          //   172: aload_1
          //   173: invokestatic 54	java/lang/String:valueOf	(Ljava/lang/Object;)Ljava/lang/String;
          //   176: invokevirtual 58	java/lang/String:concat	(Ljava/lang/String;)Ljava/lang/String;
          //   179: invokevirtual 88	android/util/StringBuilderPrinter:println	(Ljava/lang/String;)V
          //   182: new 60	java/lang/StringBuilder
          //   185: dup
          //   186: ldc 142
          //   188: invokespecial 72	java/lang/StringBuilder:<init>	(Ljava/lang/String;)V
          //   191: invokestatic 148	com/tencent/mm/sdk/platformtools/bs:eWj	()J
          //   194: getstatic 154	com/tencent/mm/app/d:cIh	J
          //   197: lsub
          //   198: invokevirtual 157	java/lang/StringBuilder:append	(J)Ljava/lang/StringBuilder;
          //   201: ldc 159
          //   203: invokevirtual 81	java/lang/StringBuilder:append	(Ljava/lang/String;)Ljava/lang/StringBuilder;
          //   206: astore 5
          //   208: aload 4
          //   210: astore_1
          //   211: aload 4
          //   213: ifnonnull +6 -> 219
          //   216: ldc 161
          //   218: astore_1
          //   219: aload 8
          //   221: aload 5
          //   223: aload_1
          //   224: invokevirtual 81	java/lang/StringBuilder:append	(Ljava/lang/String;)Ljava/lang/StringBuilder;
          //   227: ldc 163
          //   229: invokevirtual 81	java/lang/StringBuilder:append	(Ljava/lang/String;)Ljava/lang/StringBuilder;
          //   232: invokevirtual 85	java/lang/StringBuilder:toString	()Ljava/lang/String;
          //   235: invokevirtual 88	android/util/StringBuilderPrinter:println	(Ljava/lang/String;)V
          //   238: getstatic 94	com/tencent/mm/sdk/platformtools/h:DEBUG	Z
          //   241: ifeq +619 -> 860
          //   244: aload 8
          //   246: ldc 165
          //   248: invokevirtual 88	android/util/StringBuilderPrinter:println	(Ljava/lang/String;)V
          //   251: invokestatic 171	android/os/Environment:getDataDirectory	()Ljava/io/File;
          //   254: invokestatic 177	com/tencent/mm/vfs/e:U	(Ljava/io/File;)Lcom/tencent/mm/vfs/e;
          //   257: astore_1
          //   258: new 179	android/os/StatFs
          //   261: dup
          //   262: aload_1
          //   263: getfield 183	com/tencent/mm/vfs/e:mUri	Landroid/net/Uri;
          //   266: invokestatic 189	com/tencent/mm/vfs/q:B	(Landroid/net/Uri;)Ljava/lang/String;
          //   269: invokespecial 190	android/os/StatFs:<init>	(Ljava/lang/String;)V
          //   272: astore 4
          //   274: new 179	android/os/StatFs
          //   277: dup
          //   278: invokestatic 195	com/tencent/mm/loader/j/b:apb	()Ljava/lang/String;
          //   281: invokespecial 190	android/os/StatFs:<init>	(Ljava/lang/String;)V
          //   284: astore 5
          //   286: ldc 197
          //   288: bipush 10
          //   290: anewarray 4	java/lang/Object
          //   293: dup
          //   294: iconst_0
          //   295: aload 6
          //   297: ldc 199
          //   299: invokevirtual 205	android/content/Context:getSystemService	(Ljava/lang/String;)Ljava/lang/Object;
          //   302: checkcast 207	android/app/ActivityManager
          //   305: invokevirtual 210	android/app/ActivityManager:getMemoryClass	()I
          //   308: invokestatic 213	java/lang/Integer:valueOf	(I)Ljava/lang/Integer;
          //   311: aastore
          //   312: dup
          //   313: iconst_1
          //   314: aload 6
          //   316: ldc 199
          //   318: invokevirtual 205	android/content/Context:getSystemService	(Ljava/lang/String;)Ljava/lang/Object;
          //   321: checkcast 207	android/app/ActivityManager
          //   324: invokevirtual 216	android/app/ActivityManager:getLargeMemoryClass	()I
          //   327: invokestatic 213	java/lang/Integer:valueOf	(I)Ljava/lang/Integer;
          //   330: aastore
          //   331: dup
          //   332: iconst_2
          //   333: aload_1
          //   334: invokevirtual 220	com/tencent/mm/vfs/e:fxV	()Landroid/net/Uri;
          //   337: invokestatic 189	com/tencent/mm/vfs/q:B	(Landroid/net/Uri;)Ljava/lang/String;
          //   340: aastore
          //   341: dup
          //   342: iconst_3
          //   343: aload 4
          //   345: invokevirtual 223	android/os/StatFs:getBlockSize	()I
          //   348: invokestatic 213	java/lang/Integer:valueOf	(I)Ljava/lang/Integer;
          //   351: aastore
          //   352: dup
          //   353: iconst_4
          //   354: aload 4
          //   356: invokevirtual 226	android/os/StatFs:getBlockCount	()I
          //   359: invokestatic 213	java/lang/Integer:valueOf	(I)Ljava/lang/Integer;
          //   362: aastore
          //   363: dup
          //   364: iconst_5
          //   365: aload 4
          //   367: invokevirtual 229	android/os/StatFs:getAvailableBlocks	()I
          //   370: invokestatic 213	java/lang/Integer:valueOf	(I)Ljava/lang/Integer;
          //   373: aastore
          //   374: dup
          //   375: bipush 6
          //   377: invokestatic 195	com/tencent/mm/loader/j/b:apb	()Ljava/lang/String;
          //   380: aastore
          //   381: dup
          //   382: bipush 7
          //   384: aload 5
          //   386: invokevirtual 223	android/os/StatFs:getBlockSize	()I
          //   389: invokestatic 213	java/lang/Integer:valueOf	(I)Ljava/lang/Integer;
          //   392: aastore
          //   393: dup
          //   394: bipush 8
          //   396: aload 5
          //   398: invokevirtual 226	android/os/StatFs:getBlockCount	()I
          //   401: invokestatic 213	java/lang/Integer:valueOf	(I)Ljava/lang/Integer;
          //   404: aastore
          //   405: dup
          //   406: bipush 9
          //   408: aload 5
          //   410: invokevirtual 229	android/os/StatFs:getAvailableBlocks	()I
          //   413: invokestatic 213	java/lang/Integer:valueOf	(I)Ljava/lang/Integer;
          //   416: aastore
          //   417: invokestatic 233	java/lang/String:format	(Ljava/lang/String;[Ljava/lang/Object;)Ljava/lang/String;
          //   420: astore_1
          //   421: aload_3
          //   422: invokestatic 238	com/tencent/mm/app/af:e	(Ljava/lang/Throwable;)V
          //   425: aload 8
          //   427: ldc 240
          //   429: aload_1
          //   430: invokestatic 54	java/lang/String:valueOf	(Ljava/lang/Object;)Ljava/lang/String;
          //   433: invokevirtual 58	java/lang/String:concat	(Ljava/lang/String;)Ljava/lang/String;
          //   436: invokevirtual 88	android/util/StringBuilderPrinter:println	(Ljava/lang/String;)V
          //   439: new 242	java/util/Date
          //   442: dup
          //   443: invokespecial 243	java/util/Date:<init>	()V
          //   446: astore_1
          //   447: new 245	java/text/SimpleDateFormat
          //   450: dup
          //   451: ldc 247
          //   453: invokestatic 253	java/util/Locale:getDefault	()Ljava/util/Locale;
          //   456: invokespecial 256	java/text/SimpleDateFormat:<init>	(Ljava/lang/String;Ljava/util/Locale;)V
          //   459: astore_3
          //   460: aload 8
          //   462: new 60	java/lang/StringBuilder
          //   465: dup
          //   466: ldc_w 258
          //   469: invokespecial 72	java/lang/StringBuilder:<init>	(Ljava/lang/String;)V
          //   472: aload_3
          //   473: aload_1
          //   474: invokevirtual 261	java/text/SimpleDateFormat:format	(Ljava/util/Date;)Ljava/lang/String;
          //   477: invokevirtual 81	java/lang/StringBuilder:append	(Ljava/lang/String;)Ljava/lang/StringBuilder;
          //   480: invokevirtual 85	java/lang/StringBuilder:toString	()Ljava/lang/String;
          //   483: invokevirtual 88	android/util/StringBuilderPrinter:println	(Ljava/lang/String;)V
          //   486: aload 8
          //   488: ldc_w 263
          //   491: invokevirtual 88	android/util/StringBuilderPrinter:println	(Ljava/lang/String;)V
          //   494: aload_2
          //   495: astore_1
          //   496: invokestatic 269	com/tencent/mm/sdk/platformtools/ai:getContext	()Landroid/content/Context;
          //   499: invokestatic 275	com/tencent/mm/app/h:bm	(Landroid/content/Context;)I
          //   502: iconst_1
          //   503: if_icmpne +15 -> 518
          //   506: aload_2
          //   507: iconst_0
          //   508: invokestatic 269	com/tencent/mm/sdk/platformtools/ai:getContext	()Landroid/content/Context;
          //   511: invokestatic 278	com/tencent/mm/app/h:bn	(Landroid/content/Context;)I
          //   514: invokevirtual 282	java/lang/String:substring	(II)Ljava/lang/String;
          //   517: astore_1
          //   518: invokestatic 269	com/tencent/mm/sdk/platformtools/ai:getContext	()Landroid/content/Context;
          //   521: invokestatic 285	com/tencent/mm/sdk/platformtools/ai:getProcessName	()Ljava/lang/String;
          //   524: ldc_w 287
          //   527: invokestatic 291	com/tencent/mm/app/h:d	(Landroid/content/Context;Ljava/lang/String;Ljava/lang/String;)V
          //   530: aload 8
          //   532: aload_1
          //   533: invokevirtual 88	android/util/StringBuilderPrinter:println	(Ljava/lang/String;)V
          //   536: ldc 38
          //   538: ldc_w 293
          //   541: aload_1
          //   542: invokestatic 54	java/lang/String:valueOf	(Ljava/lang/Object;)Ljava/lang/String;
          //   545: invokevirtual 58	java/lang/String:concat	(Ljava/lang/String;)Ljava/lang/String;
          //   548: invokestatic 46	com/tencent/mm/sdk/platformtools/ac:e	(Ljava/lang/String;Ljava/lang/String;)V
          //   551: new 295	android/content/Intent
          //   554: dup
          //   555: invokespecial 296	android/content/Intent:<init>	()V
          //   558: astore_1
          //   559: aload_1
          //   560: ldc_w 298
          //   563: invokevirtual 302	android/content/Intent:setAction	(Ljava/lang/String;)Landroid/content/Intent;
          //   566: pop
          //   567: aload_1
          //   568: ldc_w 304
          //   571: getstatic 102	com/tencent/mm/loader/j/c:gMU	Lcom/tencent/mm/loader/j/c;
          //   574: ldc_w 306
          //   577: ldc_w 308
          //   580: invokevirtual 110	com/tencent/mm/loader/j/c:aw	(Ljava/lang/String;Ljava/lang/String;)Ljava/lang/String;
          //   583: invokevirtual 312	android/content/Intent:putExtra	(Ljava/lang/String;Ljava/lang/String;)Landroid/content/Intent;
          //   586: pop
          //   587: aload_1
          //   588: ldc_w 314
          //   591: aload 7
          //   593: invokevirtual 85	java/lang/StringBuilder:toString	()Ljava/lang/String;
          //   596: invokevirtual 318	java/lang/String:getBytes	()[B
          //   599: iconst_2
          //   600: invokestatic 324	android/util/Base64:encodeToString	([BI)Ljava/lang/String;
          //   603: invokevirtual 312	android/content/Intent:putExtra	(Ljava/lang/String;Ljava/lang/String;)Landroid/content/Intent;
          //   606: pop
          //   607: aload_1
          //   608: ldc_w 326
          //   611: new 60	java/lang/StringBuilder
          //   614: dup
          //   615: invokespecial 115	java/lang/StringBuilder:<init>	()V
          //   618: invokestatic 329	com/tencent/mm/loader/j/b:aoZ	()Ljava/lang/String;
          //   621: invokevirtual 81	java/lang/StringBuilder:append	(Ljava/lang/String;)Ljava/lang/StringBuilder;
          //   624: ldc_w 331
          //   627: invokevirtual 81	java/lang/StringBuilder:append	(Ljava/lang/String;)Ljava/lang/StringBuilder;
          //   630: invokevirtual 85	java/lang/StringBuilder:toString	()Ljava/lang/String;
          //   633: invokevirtual 312	android/content/Intent:putExtra	(Ljava/lang/String;Ljava/lang/String;)Landroid/content/Intent;
          //   636: pop
          //   637: aload_1
          //   638: ldc_w 333
          //   641: invokestatic 336	com/tencent/mm/loader/j/b:api	()Ljava/lang/String;
          //   644: invokevirtual 312	android/content/Intent:putExtra	(Ljava/lang/String;Ljava/lang/String;)Landroid/content/Intent;
          //   647: pop
          //   648: aload_1
          //   649: ldc_w 338
          //   652: getstatic 102	com/tencent/mm/loader/j/c:gMU	Lcom/tencent/mm/loader/j/c;
          //   655: ldc 104
          //   657: ldc 106
          //   659: invokevirtual 110	com/tencent/mm/loader/j/c:aw	(Ljava/lang/String;Ljava/lang/String;)Ljava/lang/String;
          //   662: invokevirtual 312	android/content/Intent:putExtra	(Ljava/lang/String;Ljava/lang/String;)Landroid/content/Intent;
          //   665: pop
          //   666: aload_1
          //   667: ldc_w 340
          //   670: getstatic 77	com/tencent/mm/loader/j/a:gMJ	Ljava/lang/String;
          //   673: invokevirtual 312	android/content/Intent:putExtra	(Ljava/lang/String;Ljava/lang/String;)Landroid/content/Intent;
          //   676: pop
          //   677: aload_1
          //   678: ldc_w 342
          //   681: getstatic 345	com/tencent/mm/loader/j/a:gMK	Ljava/lang/String;
          //   684: invokevirtual 312	android/content/Intent:putExtra	(Ljava/lang/String;Ljava/lang/String;)Landroid/content/Intent;
          //   687: pop
          //   688: aload_1
          //   689: ldc_w 347
          //   692: ldc_w 349
          //   695: invokevirtual 312	android/content/Intent:putExtra	(Ljava/lang/String;Ljava/lang/String;)Landroid/content/Intent;
          //   698: pop
          //   699: aload 6
          //   701: ldc_w 351
          //   704: iconst_0
          //   705: invokevirtual 355	android/content/Context:getSharedPreferences	(Ljava/lang/String;I)Landroid/content/SharedPreferences;
          //   708: astore_2
          //   709: aload_1
          //   710: ldc_w 357
          //   713: new 60	java/lang/StringBuilder
          //   716: dup
          //   717: ldc_w 359
          //   720: invokespecial 72	java/lang/StringBuilder:<init>	(Ljava/lang/String;)V
          //   723: aload_2
          //   724: ldc_w 361
          //   727: ldc_w 361
          //   730: invokeinterface 366 3 0
          //   735: invokevirtual 81	java/lang/StringBuilder:append	(Ljava/lang/String;)Ljava/lang/StringBuilder;
          //   738: invokevirtual 85	java/lang/StringBuilder:toString	()Ljava/lang/String;
          //   741: invokevirtual 312	android/content/Intent:putExtra	(Ljava/lang/String;Ljava/lang/String;)Landroid/content/Intent;
          //   744: pop
          //   745: aload_1
          //   746: aload 6
          //   748: new 60	java/lang/StringBuilder
          //   751: dup
          //   752: invokespecial 115	java/lang/StringBuilder:<init>	()V
          //   755: aload 6
          //   757: invokevirtual 369	android/content/Context:getPackageName	()Ljava/lang/String;
          //   760: invokevirtual 81	java/lang/StringBuilder:append	(Ljava/lang/String;)Ljava/lang/StringBuilder;
          //   763: ldc_w 371
          //   766: invokevirtual 81	java/lang/StringBuilder:append	(Ljava/lang/String;)Ljava/lang/StringBuilder;
          //   769: invokevirtual 85	java/lang/StringBuilder:toString	()Ljava/lang/String;
          //   772: invokevirtual 375	android/content/Intent:setClassName	(Landroid/content/Context;Ljava/lang/String;)Landroid/content/Intent;
          //   775: pop
          //   776: aload_1
          //   777: ldc_w 377
          //   780: iconst_1
          //   781: new 295	android/content/Intent
          //   784: dup
          //   785: invokespecial 296	android/content/Intent:<init>	()V
          //   788: aload 6
          //   790: new 60	java/lang/StringBuilder
          //   793: dup
          //   794: invokespecial 115	java/lang/StringBuilder:<init>	()V
          //   797: aload 6
          //   799: invokevirtual 369	android/content/Context:getPackageName	()Ljava/lang/String;
          //   802: invokevirtual 81	java/lang/StringBuilder:append	(Ljava/lang/String;)Ljava/lang/StringBuilder;
          //   805: ldc_w 379
          //   808: invokevirtual 81	java/lang/StringBuilder:append	(Ljava/lang/String;)Ljava/lang/StringBuilder;
          //   811: invokevirtual 85	java/lang/StringBuilder:toString	()Ljava/lang/String;
          //   814: invokevirtual 375	android/content/Intent:setClassName	(Landroid/content/Context;Ljava/lang/String;)Landroid/content/Intent;
          //   817: invokestatic 384	com/tencent/mm/service/c:a	(Landroid/content/Intent;Ljava/lang/String;ZLandroid/content/Intent;)V
          //   820: ldc 30
          //   822: invokestatic 387	com/tencent/matrix/trace/core/AppMethodBeat:o	(I)V
          //   825: return
          //   826: aload 8
          //   828: new 60	java/lang/StringBuilder
          //   831: dup
          //   832: ldc_w 389
          //   835: invokespecial 72	java/lang/StringBuilder:<init>	(Ljava/lang/String;)V
          //   838: invokestatic 392	com/tencent/mm/loader/j/a:aoT	()Ljava/lang/String;
          //   841: invokevirtual 81	java/lang/StringBuilder:append	(Ljava/lang/String;)Ljava/lang/StringBuilder;
          //   844: invokevirtual 85	java/lang/StringBuilder:toString	()Ljava/lang/String;
          //   847: invokevirtual 88	android/util/StringBuilderPrinter:println	(Ljava/lang/String;)V
          //   850: goto -753 -> 97
          //   853: astore_1
          //   854: ldc 30
          //   856: invokestatic 387	com/tencent/matrix/trace/core/AppMethodBeat:o	(I)V
          //   859: return
          //   860: aload 8
          //   862: new 60	java/lang/StringBuilder
          //   865: dup
          //   866: ldc_w 394
          //   869: invokespecial 72	java/lang/StringBuilder:<init>	(Ljava/lang/String;)V
          //   872: getstatic 397	com/tencent/mm/loader/j/a:TIME	Ljava/lang/String;
          //   875: invokevirtual 81	java/lang/StringBuilder:append	(Ljava/lang/String;)Ljava/lang/StringBuilder;
          //   878: ldc_w 399
          //   881: invokevirtual 81	java/lang/StringBuilder:append	(Ljava/lang/String;)Ljava/lang/StringBuilder;
          //   884: getstatic 402	com/tencent/mm/loader/j/a:HOSTNAME	Ljava/lang/String;
          //   887: invokevirtual 81	java/lang/StringBuilder:append	(Ljava/lang/String;)Ljava/lang/StringBuilder;
          //   890: ldc_w 404
          //   893: invokevirtual 81	java/lang/StringBuilder:append	(Ljava/lang/String;)Ljava/lang/StringBuilder;
          //   896: invokevirtual 85	java/lang/StringBuilder:toString	()Ljava/lang/String;
          //   899: invokevirtual 88	android/util/StringBuilderPrinter:println	(Ljava/lang/String;)V
          //   902: goto -651 -> 251
          //   905: astore_1
          //   906: ldc 161
          //   908: astore_1
          //   909: goto -488 -> 421
          // Local variable table:
          //   start	length	slot	name	signature
          //   0	912	0	this	1
          //   0	912	1	paramAnonymousat	at
          //   0	912	2	paramAnonymousString	String
          //   0	912	3	paramAnonymousThrowable	java.lang.Throwable
          //   22	344	4	localObject1	Object
          //   107	302	5	localObject2	Object
          //   16	782	6	localApplication	Application
          //   48	544	7	localStringBuilder	java.lang.StringBuilder
          //   59	802	8	localStringBuilderPrinter	android.util.StringBuilderPrinter
          // Exception table:
          //   from	to	target	type
          //   38	97	853	java/lang/Exception
          //   97	109	853	java/lang/Exception
          //   117	127	853	java/lang/Exception
          //   127	168	853	java/lang/Exception
          //   168	208	853	java/lang/Exception
          //   219	251	853	java/lang/Exception
          //   421	494	853	java/lang/Exception
          //   496	518	853	java/lang/Exception
          //   518	820	853	java/lang/Exception
          //   826	850	853	java/lang/Exception
          //   860	902	853	java/lang/Exception
          //   251	421	905	java/lang/Exception
        }
      });
      at.a(new at.a()
      {
        public final void Kr()
        {
          String str = a.gML;
        }
      });
    }
    AppMethodBeat.o(125023);
    return paramString;
  }
}


/* Location:           L:\local\mybackup\temp\qq_apk\com.tencent.mm\classes.jar
 * Qualified Name:     com.tencent.mm.app.k
 * JD-Core Version:    0.7.0.1
 */