package com.tencent.component.network.downloader.impl;

import android.content.Context;
import android.os.SystemClock;
import android.text.TextUtils;
import com.tencent.component.network.NetworkManager;
import com.tencent.component.network.downloader.common.IPInfo;
import com.tencent.component.network.downloader.strategy.DownloadGlobalStrategy;
import com.tencent.component.network.downloader.strategy.DownloadGlobalStrategy.StrategyInfo;
import com.tencent.component.network.downloader.strategy.DownloadGlobalStrategy.StrategyLib;
import com.tencent.component.network.downloader.strategy.IPStrategy;
import com.tencent.component.network.downloader.strategy.PortConfigStrategy;
import com.tencent.component.network.module.base.b;
import com.tencent.component.network.utils.NetworkUtils;
import com.tencent.component.network.utils.NetworkUtils.NetworkProxy;
import org.apache.http.client.HttpClient;

public class e
  extends a
{
  private NetworkUtils.NetworkProxy jdField_a_of_type_ComTencentComponentNetworkUtilsNetworkUtils$NetworkProxy;
  private String jdField_a_of_type_JavaLangString;
  private boolean jdField_a_of_type_Boolean;
  private String jdField_b_of_type_JavaLangString;
  private boolean jdField_b_of_type_Boolean;
  int jdField_c_of_type_Int = 0;
  private String jdField_c_of_type_JavaLangString;
  int jdField_d_of_type_Int = 0;
  long jdField_d_of_type_Long = 0L;
  private String jdField_d_of_type_JavaLangString = "";
  private int jdField_e_of_type_Int = 0;
  long jdField_e_of_type_Long = 0L;
  long f;
  long g;
  long h;
  private final long i;
  
  public e(Context paramContext, HttpClient paramHttpClient, String paramString1, String paramString2, boolean paramBoolean)
  {
    super(paramContext, paramHttpClient, paramString1, paramString2, paramBoolean);
    this.jdField_i_of_type_Long = SystemClock.uptimeMillis();
    this.jdField_f_of_type_Long = 0L;
    this.jdField_g_of_type_Long = 0L;
    this.jdField_h_of_type_Long = 0L;
  }
  
  private boolean a(int paramInt)
  {
    int j = 80;
    String str2 = b();
    if (this.jdField_a_of_type_ComTencentComponentNetworkDownloaderStrategyDownloadGlobalStrategy$StrategyLib == null) {
      this.jdField_a_of_type_ComTencentComponentNetworkDownloaderStrategyDownloadGlobalStrategy$StrategyLib = DownloadGlobalStrategy.a(this.jdField_a_of_type_AndroidContentContext).a(a(), b());
    }
    this.jdField_a_of_type_ComTencentComponentNetworkDownloaderStrategyDownloadGlobalStrategy$StrategyInfo = this.jdField_b_of_type_ComTencentComponentNetworkDownloaderStrategyDownloadGlobalStrategy$StrategyInfo;
    this.jdField_b_of_type_ComTencentComponentNetworkDownloaderStrategyDownloadGlobalStrategy$StrategyInfo = this.jdField_a_of_type_ComTencentComponentNetworkDownloaderStrategyDownloadGlobalStrategy$StrategyLib.a(paramInt);
    if (b.b()) {
      b.b("downloader", "downloader strategy: " + this.jdField_b_of_type_ComTencentComponentNetworkDownloaderStrategyDownloadGlobalStrategy$StrategyInfo.toString() + " currAttempCount:" + paramInt + " best:" + this.jdField_a_of_type_ComTencentComponentNetworkDownloaderStrategyDownloadGlobalStrategy$StrategyLib.c() + " url:" + a() + " Apn:" + NetworkManager.a() + " ISP:" + NetworkManager.a() + " threadid:" + Thread.currentThread().getId());
    }
    this.jdField_a_of_type_Boolean = this.jdField_b_of_type_ComTencentComponentNetworkDownloaderStrategyDownloadGlobalStrategy$StrategyInfo.jdField_a_of_type_Boolean;
    this.jdField_b_of_type_Boolean = this.jdField_b_of_type_ComTencentComponentNetworkDownloaderStrategyDownloadGlobalStrategy$StrategyInfo.jdField_b_of_type_Boolean;
    paramInt = this.jdField_a_of_type_ComTencentComponentNetworkDownloaderStrategyDownloadGlobalStrategy$StrategyLib.b();
    if (!com.tencent.component.network.downloader.common.a.a(paramInt))
    {
      this.jdField_a_of_type_ComTencentComponentNetworkDownloaderStrategyDownloadGlobalStrategy$StrategyLib.a(80);
      paramInt = j;
    }
    for (;;)
    {
      String str1;
      Object localObject;
      if (DownloadGlobalStrategy.d.jdField_a_of_type_Int == this.jdField_b_of_type_ComTencentComponentNetworkDownloaderStrategyDownloadGlobalStrategy$StrategyInfo.jdField_a_of_type_Int)
      {
        j = paramInt;
        if (this.jdField_a_of_type_ComTencentComponentNetworkDownloaderStrategyDownloadGlobalStrategy$StrategyInfo != null)
        {
          j = paramInt;
          if (DownloadGlobalStrategy.d.jdField_a_of_type_Int == this.jdField_a_of_type_ComTencentComponentNetworkDownloaderStrategyDownloadGlobalStrategy$StrategyInfo.jdField_a_of_type_Int)
          {
            if ((this.jdField_a_of_type_ComTencentComponentNetworkDownloaderStrategyPortConfigStrategy == null) || (!this.jdField_a_of_type_ComTencentComponentNetworkDownloaderStrategyPortConfigStrategy.a(str2))) {
              break label504;
            }
            j = this.jdField_a_of_type_ComTencentComponentNetworkDownloaderStrategyPortConfigStrategy.a(str2, paramInt);
            if ((j == paramInt) || (!com.tencent.component.network.downloader.common.a.a(j))) {
              if (b.b()) {
                b.b("downloader", "downloader strategy: Pass! port:" + paramInt + " newport:" + j + " threadId:" + Thread.currentThread().getId());
              }
            }
          }
        }
        label504:
        do
        {
          do
          {
            do
            {
              return false;
              str1 = this.jdField_a_of_type_ComTencentComponentNetworkDownloaderStrategyDownloadGlobalStrategy$StrategyLib.c();
              localObject = str1;
              if (this.jdField_b_of_type_ComTencentComponentNetworkDownloaderStrategyIPStrategy != null)
              {
                localObject = str1;
                if (!this.jdField_b_of_type_ComTencentComponentNetworkDownloaderStrategyIPStrategy.a(str2, str1))
                {
                  this.jdField_a_of_type_ComTencentComponentNetworkDownloaderStrategyDownloadGlobalStrategy$StrategyLib.c(null);
                  localObject = this.jdField_b_of_type_ComTencentComponentNetworkDownloaderStrategyIPStrategy.a(str2);
                  if (TextUtils.isEmpty((CharSequence)localObject)) {
                    break;
                  }
                  this.jdField_a_of_type_ComTencentComponentNetworkDownloaderStrategyDownloadGlobalStrategy$StrategyLib.c((String)localObject);
                }
              }
              if ((localObject != null) && (!((String)localObject).equals(this.jdField_a_of_type_ComTencentComponentNetworkDownloaderStrategyDownloadGlobalStrategy$StrategyLib.a())) && (!((String)localObject).equals(this.jdField_a_of_type_ComTencentComponentNetworkDownloaderStrategyDownloadGlobalStrategy$StrategyLib.b()))) {
                break label578;
              }
            } while (!b.b());
            b.b("downloader", "downloader strategy: Pass! Domain IP 重复. threadId:" + Thread.currentThread().getId());
            return false;
          } while (!b.b());
          b.b("downloader", "downloader strategy: Pass! Not support !80. threadId:" + Thread.currentThread().getId());
          return false;
        } while (!b.b());
        b.b("downloader", "downloader strategy: backup ip is null. Pass! threadId:" + Thread.currentThread().getId());
        return false;
        label578:
        this.jdField_b_of_type_ComTencentComponentNetworkDownloaderStrategyDownloadGlobalStrategy$StrategyInfo = this.jdField_b_of_type_ComTencentComponentNetworkDownloaderStrategyDownloadGlobalStrategy$StrategyInfo.a();
        this.jdField_b_of_type_ComTencentComponentNetworkDownloaderStrategyDownloadGlobalStrategy$StrategyInfo.a(new IPInfo((String)localObject, j));
      }
      for (;;)
      {
        return true;
        if (DownloadGlobalStrategy.e.jdField_a_of_type_Int == this.jdField_b_of_type_ComTencentComponentNetworkDownloaderStrategyDownloadGlobalStrategy$StrategyInfo.jdField_a_of_type_Int)
        {
          j = paramInt;
          if (this.jdField_a_of_type_ComTencentComponentNetworkDownloaderStrategyDownloadGlobalStrategy$StrategyInfo != null)
          {
            j = paramInt;
            if (DownloadGlobalStrategy.e.jdField_a_of_type_Int == this.jdField_a_of_type_ComTencentComponentNetworkDownloaderStrategyDownloadGlobalStrategy$StrategyInfo.jdField_a_of_type_Int)
            {
              if ((this.jdField_a_of_type_ComTencentComponentNetworkDownloaderStrategyPortConfigStrategy == null) || (!this.jdField_a_of_type_ComTencentComponentNetworkDownloaderStrategyPortConfigStrategy.a(str2))) {
                break label838;
              }
              j = this.jdField_a_of_type_ComTencentComponentNetworkDownloaderStrategyPortConfigStrategy.a(str2, paramInt);
              if ((j == paramInt) || (!com.tencent.component.network.downloader.common.a.a(j)))
              {
                if (!b.b()) {
                  break;
                }
                b.b("downloader", "downloader strategy: Pass! port:" + paramInt + " newport:" + j + " threadId:" + Thread.currentThread().getId());
                return false;
              }
            }
          }
          localObject = com.tencent.component.network.module.common.a.a().a(str2);
          if ((localObject == null) || (((String)localObject).equals(this.jdField_a_of_type_ComTencentComponentNetworkDownloaderStrategyDownloadGlobalStrategy$StrategyLib.c())) || (((String)localObject).equals(this.jdField_a_of_type_ComTencentComponentNetworkDownloaderStrategyDownloadGlobalStrategy$StrategyLib.a())))
          {
            this.jdField_a_of_type_ComTencentComponentNetworkDownloaderStrategyDownloadGlobalStrategy$StrategyLib.b(null);
            if (!b.b()) {
              break;
            }
            b.b("downloader", "downloader strategy: Pass! Domain IP 重复. threadId:" + Thread.currentThread().getId());
            return false;
            label838:
            if (!b.b()) {
              break;
            }
            b.b("downloader", "downloader strategy: Pass! Not support !80. threadId:" + Thread.currentThread().getId());
            return false;
          }
          this.jdField_a_of_type_ComTencentComponentNetworkDownloaderStrategyDownloadGlobalStrategy$StrategyLib.b((String)localObject);
          this.jdField_b_of_type_ComTencentComponentNetworkDownloaderStrategyDownloadGlobalStrategy$StrategyInfo = this.jdField_b_of_type_ComTencentComponentNetworkDownloaderStrategyDownloadGlobalStrategy$StrategyInfo.a();
          this.jdField_b_of_type_ComTencentComponentNetworkDownloaderStrategyDownloadGlobalStrategy$StrategyInfo.a(new IPInfo((String)localObject, j));
          continue;
        }
        if (DownloadGlobalStrategy.jdField_a_of_type_ComTencentComponentNetworkDownloaderStrategyDownloadGlobalStrategy$StrategyInfo.jdField_a_of_type_Int == this.jdField_b_of_type_ComTencentComponentNetworkDownloaderStrategyDownloadGlobalStrategy$StrategyInfo.jdField_a_of_type_Int)
        {
          j = paramInt;
          if (this.jdField_a_of_type_ComTencentComponentNetworkDownloaderStrategyDownloadGlobalStrategy$StrategyInfo != null)
          {
            j = paramInt;
            if (DownloadGlobalStrategy.jdField_a_of_type_ComTencentComponentNetworkDownloaderStrategyDownloadGlobalStrategy$StrategyInfo.jdField_a_of_type_Int == this.jdField_a_of_type_ComTencentComponentNetworkDownloaderStrategyDownloadGlobalStrategy$StrategyInfo.jdField_a_of_type_Int)
            {
              if ((this.jdField_a_of_type_ComTencentComponentNetworkDownloaderStrategyPortConfigStrategy == null) || (!this.jdField_a_of_type_ComTencentComponentNetworkDownloaderStrategyPortConfigStrategy.a(str2))) {
                break label1205;
              }
              j = this.jdField_a_of_type_ComTencentComponentNetworkDownloaderStrategyPortConfigStrategy.a(str2, paramInt);
              if ((j == paramInt) || (!com.tencent.component.network.downloader.common.a.a(j)))
              {
                if (!b.b()) {
                  break;
                }
                b.b("downloader", "downloader strategy: Pass! port:" + paramInt + " newport:" + j + " threadId:" + Thread.currentThread().getId());
                return false;
              }
            }
          }
        }
        label1205:
        do
        {
          str1 = this.jdField_a_of_type_ComTencentComponentNetworkDownloaderStrategyDownloadGlobalStrategy$StrategyLib.a();
          localObject = str1;
          if (this.jdField_a_of_type_ComTencentComponentNetworkDownloaderStrategyIPStrategy != null)
          {
            localObject = str1;
            if (!this.jdField_a_of_type_ComTencentComponentNetworkDownloaderStrategyIPStrategy.a(str2, str1))
            {
              this.jdField_a_of_type_ComTencentComponentNetworkDownloaderStrategyDownloadGlobalStrategy$StrategyLib.a(null);
              localObject = this.jdField_a_of_type_ComTencentComponentNetworkDownloaderStrategyIPStrategy.a(str2);
              if (TextUtils.isEmpty((CharSequence)localObject)) {
                break label1413;
              }
              this.jdField_a_of_type_ComTencentComponentNetworkDownloaderStrategyDownloadGlobalStrategy$StrategyLib.a((String)localObject);
            }
          }
          if ((localObject != null) && (!((String)localObject).equals(this.jdField_a_of_type_ComTencentComponentNetworkDownloaderStrategyDownloadGlobalStrategy$StrategyLib.c())) && (!((String)localObject).equals(this.jdField_a_of_type_ComTencentComponentNetworkDownloaderStrategyDownloadGlobalStrategy$StrategyLib.b()))) {
            break label1451;
          }
          if (!b.b()) {
            break;
          }
          b.b("downloader", "downloader strategy: Pass! Domain IP 重复. threadId:" + Thread.currentThread().getId());
          return false;
          if (!b.b()) {
            break;
          }
          b.b("downloader", "downloader strategy: Pass! Not support !80. threadId:" + Thread.currentThread().getId());
          return false;
          if (DownloadGlobalStrategy.jdField_b_of_type_ComTencentComponentNetworkDownloaderStrategyDownloadGlobalStrategy$StrategyInfo.jdField_a_of_type_Int == this.jdField_b_of_type_ComTencentComponentNetworkDownloaderStrategyDownloadGlobalStrategy$StrategyInfo.jdField_a_of_type_Int) {
            break label1276;
          }
          j = paramInt;
        } while (DownloadGlobalStrategy.c.jdField_a_of_type_Int != this.jdField_b_of_type_ComTencentComponentNetworkDownloaderStrategyDownloadGlobalStrategy$StrategyInfo.jdField_a_of_type_Int);
        label1276:
        localObject = this.jdField_a_of_type_AndroidContentContext;
        if (DownloadGlobalStrategy.c.jdField_a_of_type_Int == this.jdField_b_of_type_ComTencentComponentNetworkDownloaderStrategyDownloadGlobalStrategy$StrategyInfo.jdField_a_of_type_Int) {}
        for (boolean bool = true;; bool = false)
        {
          localObject = NetworkUtils.a((Context)localObject, bool);
          if (localObject != null) {
            break label1355;
          }
          if (!b.b()) {
            break;
          }
          b.b("downloader", "downloader strategy: proxy is null. Pass! threadId:" + Thread.currentThread().getId());
          return false;
        }
        label1355:
        if (((NetworkUtils.NetworkProxy)localObject).equals(this.jdField_a_of_type_ComTencentComponentNetworkUtilsNetworkUtils$NetworkProxy))
        {
          if (!b.b()) {
            break;
          }
          b.b("downloader", "downloader strategy: proxy 重复. Pass! threadId:" + Thread.currentThread().getId());
          return false;
        }
        this.jdField_a_of_type_ComTencentComponentNetworkUtilsNetworkUtils$NetworkProxy = ((NetworkUtils.NetworkProxy)localObject);
        return true;
        label1413:
        if (!b.b()) {
          break;
        }
        b.b("downloader", "downloader strategy: direct ip is null. Pass! threadId:" + Thread.currentThread().getId());
        return false;
        label1451:
        this.jdField_b_of_type_ComTencentComponentNetworkDownloaderStrategyDownloadGlobalStrategy$StrategyInfo = this.jdField_b_of_type_ComTencentComponentNetworkDownloaderStrategyDownloadGlobalStrategy$StrategyInfo.a();
        this.jdField_b_of_type_ComTencentComponentNetworkDownloaderStrategyDownloadGlobalStrategy$StrategyInfo.a(new IPInfo((String)localObject, j));
      }
    }
  }
  
  protected void a()
  {
    super.a();
    this.jdField_b_of_type_JavaLangString = com.tencent.component.network.downloader.common.a.b(a());
    this.jdField_e_of_type_Int = com.tencent.component.network.downloader.common.a.a(a());
    this.jdField_c_of_type_JavaLangString = com.tencent.component.network.utils.a.e.a(a());
  }
  
  /* Error */
  public void a(com.tencent.component.network.utils.thread.ThreadPool.JobContext paramJobContext, com.tencent.component.network.downloader.DownloadResult paramDownloadResult)
  {
    // Byte code:
    //   0: iconst_2
    //   1: anewarray 283	java/lang/Object
    //   4: dup
    //   5: iconst_0
    //   6: aload_0
    //   7: invokevirtual 68	com/tencent/component/network/downloader/impl/e:a	()Ljava/lang/String;
    //   10: aastore
    //   11: dup
    //   12: iconst_1
    //   13: aload_2
    //   14: aastore
    //   15: invokestatic 288	cug:a	([Ljava/lang/Object;)I
    //   18: istore 8
    //   20: lconst_0
    //   21: lstore 9
    //   23: iconst_0
    //   24: istore 4
    //   26: aload_1
    //   27: invokeinterface 292 1 0
    //   32: ifeq +11 -> 43
    //   35: aload_0
    //   36: aload_1
    //   37: aload_2
    //   38: aconst_null
    //   39: invokevirtual 295	com/tencent/component/network/downloader/impl/e:a	(Lcom/tencent/component/network/utils/thread/ThreadPool$JobContext;Lcom/tencent/component/network/downloader/DownloadResult;Lcom/tencent/component/network/downloader/DownloadReport;)V
    //   42: return
    //   43: aload_0
    //   44: getfield 61	com/tencent/component/network/downloader/impl/e:jdField_a_of_type_AndroidContentContext	Landroid/content/Context;
    //   47: invokestatic 298	com/tencent/component/network/utils/NetworkUtils:a	(Landroid/content/Context;)Z
    //   50: ifne +20 -> 70
    //   53: aload_2
    //   54: invokevirtual 303	com/tencent/component/network/downloader/DownloadResult:a	()Lcom/tencent/component/network/downloader/DownloadResult$Status;
    //   57: bipush 6
    //   59: invokevirtual 306	com/tencent/component/network/downloader/DownloadResult$Status:a	(I)V
    //   62: aload_0
    //   63: aload_1
    //   64: aload_2
    //   65: aconst_null
    //   66: invokevirtual 295	com/tencent/component/network/downloader/impl/e:a	(Lcom/tencent/component/network/utils/thread/ThreadPool$JobContext;Lcom/tencent/component/network/downloader/DownloadResult;Lcom/tencent/component/network/downloader/DownloadReport;)V
    //   69: return
    //   70: invokestatic 28	android/os/SystemClock:uptimeMillis	()J
    //   73: lstore 11
    //   75: new 308	com/tencent/component/network/downloader/DownloadReport
    //   78: dup
    //   79: invokespecial 309	com/tencent/component/network/downloader/DownloadReport:<init>	()V
    //   82: astore 24
    //   84: aload 24
    //   86: iload 8
    //   88: putfield 310	com/tencent/component/network/downloader/DownloadReport:jdField_a_of_type_Int	I
    //   91: aload 24
    //   93: aload_0
    //   94: invokevirtual 68	com/tencent/component/network/downloader/impl/e:a	()Ljava/lang/String;
    //   97: putfield 312	com/tencent/component/network/downloader/DownloadReport:jdField_a_of_type_JavaLangString	Ljava/lang/String;
    //   100: aload 24
    //   102: aload_0
    //   103: invokevirtual 55	com/tencent/component/network/downloader/impl/e:b	()Ljava/lang/String;
    //   106: putfield 314	com/tencent/component/network/downloader/DownloadReport:jdField_e_of_type_JavaLangString	Ljava/lang/String;
    //   109: aload 24
    //   111: invokestatic 319	java/lang/System:currentTimeMillis	()J
    //   114: putfield 321	com/tencent/component/network/downloader/DownloadReport:jdField_a_of_type_Long	J
    //   117: aload_0
    //   118: aconst_null
    //   119: putfield 324	com/tencent/component/network/downloader/impl/e:jdField_a_of_type_OrgApacheHttpClientMethodsHttpGet	Lorg/apache/http/client/methods/HttpGet;
    //   122: aconst_null
    //   123: astore 21
    //   125: aconst_null
    //   126: astore 20
    //   128: iconst_0
    //   129: istore 6
    //   131: iconst_0
    //   132: istore 7
    //   134: aconst_null
    //   135: astore 18
    //   137: aload_0
    //   138: ldc 34
    //   140: putfield 36	com/tencent/component/network/downloader/impl/e:jdField_d_of_type_JavaLangString	Ljava/lang/String;
    //   143: invokestatic 319	java/lang/System:currentTimeMillis	()J
    //   146: lstore 13
    //   148: aload_0
    //   149: aload_0
    //   150: invokevirtual 325	com/tencent/component/network/downloader/impl/e:b	()I
    //   153: invokespecial 326	com/tencent/component/network/downloader/impl/e:a	(I)Z
    //   156: istore 17
    //   158: iload 17
    //   160: ifne +29 -> 189
    //   163: iload 4
    //   165: istore_3
    //   166: lload 9
    //   168: lstore 11
    //   170: aload_0
    //   171: invokevirtual 327	com/tencent/component/network/downloader/impl/e:a	()Z
    //   174: ifeq -132 -> 42
    //   177: lload 11
    //   179: lstore 9
    //   181: iload_3
    //   182: istore 4
    //   184: goto -158 -> 26
    //   187: astore 18
    //   189: aload 18
    //   191: ifnull +1142 -> 1333
    //   194: aload 18
    //   196: athrow
    //   197: astore 20
    //   199: iconst_0
    //   200: istore_3
    //   201: aconst_null
    //   202: astore 18
    //   204: aconst_null
    //   205: astore 19
    //   207: ldc 88
    //   209: ldc 34
    //   211: aload 20
    //   213: invokestatic 330	com/tencent/component/network/module/base/b:d	(Ljava/lang/String;Ljava/lang/String;Ljava/lang/Throwable;)V
    //   216: aload_2
    //   217: invokevirtual 303	com/tencent/component/network/downloader/DownloadResult:a	()Lcom/tencent/component/network/downloader/DownloadResult$Status;
    //   220: aload 20
    //   222: invokevirtual 333	com/tencent/component/network/downloader/DownloadResult$Status:a	(Ljava/lang/Throwable;)V
    //   225: iload 4
    //   227: iconst_1
    //   228: iadd
    //   229: istore 5
    //   231: aload_2
    //   232: invokevirtual 336	com/tencent/component/network/downloader/DownloadResult:a	()Lcom/tencent/component/network/downloader/DownloadResult$Process;
    //   235: lload 11
    //   237: invokestatic 28	android/os/SystemClock:uptimeMillis	()J
    //   240: invokevirtual 341	com/tencent/component/network/downloader/DownloadResult$Process:a	(JJ)V
    //   243: aload_0
    //   244: getfield 61	com/tencent/component/network/downloader/impl/e:jdField_a_of_type_AndroidContentContext	Landroid/content/Context;
    //   247: invokestatic 346	com/tencent/component/network/module/common/b:a	(Landroid/content/Context;)Lcom/tencent/component/network/module/common/b;
    //   250: invokevirtual 349	com/tencent/component/network/module/common/b:a	()Lcom/tencent/component/network/utils/NetworkUtils$DNS;
    //   253: astore 23
    //   255: aload 18
    //   257: iconst_1
    //   258: invokestatic 352	cug:a	(Lorg/apache/http/protocol/HttpContext;Z)Ljava/lang/String;
    //   261: astore 21
    //   263: aload 18
    //   265: iconst_0
    //   266: invokestatic 352	cug:a	(Lorg/apache/http/protocol/HttpContext;Z)Ljava/lang/String;
    //   269: astore 22
    //   271: aload_0
    //   272: lconst_0
    //   273: putfield 38	com/tencent/component/network/downloader/impl/e:jdField_d_of_type_Long	J
    //   276: aload_0
    //   277: iconst_0
    //   278: putfield 40	com/tencent/component/network/downloader/impl/e:jdField_c_of_type_Int	I
    //   281: aload_0
    //   282: lconst_0
    //   283: putfield 42	com/tencent/component/network/downloader/impl/e:jdField_e_of_type_Long	J
    //   286: aload_0
    //   287: iconst_0
    //   288: putfield 44	com/tencent/component/network/downloader/impl/e:jdField_d_of_type_Int	I
    //   291: aload_0
    //   292: lconst_0
    //   293: putfield 46	com/tencent/component/network/downloader/impl/e:jdField_f_of_type_Long	J
    //   296: aload_0
    //   297: lconst_0
    //   298: putfield 48	com/tencent/component/network/downloader/impl/e:jdField_g_of_type_Long	J
    //   301: aload_2
    //   302: invokevirtual 303	com/tencent/component/network/downloader/DownloadResult:a	()Lcom/tencent/component/network/downloader/DownloadResult$Status;
    //   305: invokevirtual 353	com/tencent/component/network/downloader/DownloadResult$Status:a	()Z
    //   308: ifne +29 -> 337
    //   311: aload_0
    //   312: getfield 356	com/tencent/component/network/downloader/impl/e:jdField_a_of_type_ComTencentComponentNetworkDownloaderStrategyResumeTransfer	Lcom/tencent/component/network/downloader/strategy/ResumeTransfer;
    //   315: ifnull +22 -> 337
    //   318: aload_0
    //   319: getfield 356	com/tencent/component/network/downloader/impl/e:jdField_a_of_type_ComTencentComponentNetworkDownloaderStrategyResumeTransfer	Lcom/tencent/component/network/downloader/strategy/ResumeTransfer;
    //   322: aload_0
    //   323: invokevirtual 68	com/tencent/component/network/downloader/impl/e:a	()Ljava/lang/String;
    //   326: aload_2
    //   327: invokevirtual 357	com/tencent/component/network/downloader/DownloadResult:b	()Ljava/lang/String;
    //   330: aload 19
    //   332: invokeinterface 362 4 0
    //   337: aload_1
    //   338: invokeinterface 292 1 0
    //   343: ifne +942 -> 1285
    //   346: aload_0
    //   347: new 90	java/lang/StringBuilder
    //   350: dup
    //   351: invokespecial 93	java/lang/StringBuilder:<init>	()V
    //   354: aload_0
    //   355: getfield 36	com/tencent/component/network/downloader/impl/e:jdField_d_of_type_JavaLangString	Ljava/lang/String;
    //   358: invokevirtual 99	java/lang/StringBuilder:append	(Ljava/lang/String;)Ljava/lang/StringBuilder;
    //   361: ldc_w 364
    //   364: invokevirtual 99	java/lang/StringBuilder:append	(Ljava/lang/String;)Ljava/lang/StringBuilder;
    //   367: aload_2
    //   368: invokevirtual 367	com/tencent/component/network/downloader/DownloadResult:a	()Lcom/tencent/component/network/downloader/DownloadResult$Content;
    //   371: getfield 371	com/tencent/component/network/downloader/DownloadResult$Content:jdField_b_of_type_Long	J
    //   374: invokevirtual 139	java/lang/StringBuilder:append	(J)Ljava/lang/StringBuilder;
    //   377: ldc_w 373
    //   380: invokevirtual 99	java/lang/StringBuilder:append	(Ljava/lang/String;)Ljava/lang/StringBuilder;
    //   383: aload_0
    //   384: getfield 375	com/tencent/component/network/downloader/impl/e:jdField_c_of_type_Long	J
    //   387: invokevirtual 139	java/lang/StringBuilder:append	(J)Ljava/lang/StringBuilder;
    //   390: ldc_w 377
    //   393: invokevirtual 99	java/lang/StringBuilder:append	(Ljava/lang/String;)Ljava/lang/StringBuilder;
    //   396: invokevirtual 140	java/lang/StringBuilder:toString	()Ljava/lang/String;
    //   399: putfield 36	com/tencent/component/network/downloader/impl/e:jdField_d_of_type_JavaLangString	Ljava/lang/String;
    //   402: aload_2
    //   403: invokevirtual 303	com/tencent/component/network/downloader/DownloadResult:a	()Lcom/tencent/component/network/downloader/DownloadResult$Status;
    //   406: invokevirtual 353	com/tencent/component/network/downloader/DownloadResult$Status:a	()Z
    //   409: ifne +5437 -> 5846
    //   412: new 90	java/lang/StringBuilder
    //   415: dup
    //   416: invokespecial 93	java/lang/StringBuilder:<init>	()V
    //   419: ldc_w 379
    //   422: invokevirtual 99	java/lang/StringBuilder:append	(Ljava/lang/String;)Ljava/lang/StringBuilder;
    //   425: aload_0
    //   426: invokevirtual 68	com/tencent/component/network/downloader/impl/e:a	()Ljava/lang/String;
    //   429: invokevirtual 99	java/lang/StringBuilder:append	(Ljava/lang/String;)Ljava/lang/StringBuilder;
    //   432: ldc_w 381
    //   435: invokevirtual 99	java/lang/StringBuilder:append	(Ljava/lang/String;)Ljava/lang/StringBuilder;
    //   438: aload 23
    //   440: invokevirtual 384	java/lang/StringBuilder:append	(Ljava/lang/Object;)Ljava/lang/StringBuilder;
    //   443: ldc_w 386
    //   446: invokevirtual 99	java/lang/StringBuilder:append	(Ljava/lang/String;)Ljava/lang/StringBuilder;
    //   449: aload 21
    //   451: invokevirtual 99	java/lang/StringBuilder:append	(Ljava/lang/String;)Ljava/lang/StringBuilder;
    //   454: ldc_w 388
    //   457: invokevirtual 99	java/lang/StringBuilder:append	(Ljava/lang/String;)Ljava/lang/StringBuilder;
    //   460: aload 22
    //   462: invokevirtual 99	java/lang/StringBuilder:append	(Ljava/lang/String;)Ljava/lang/StringBuilder;
    //   465: ldc_w 390
    //   468: invokevirtual 99	java/lang/StringBuilder:append	(Ljava/lang/String;)Ljava/lang/StringBuilder;
    //   471: invokestatic 133	java/lang/Thread:currentThread	()Ljava/lang/Thread;
    //   474: invokevirtual 136	java/lang/Thread:getId	()J
    //   477: invokevirtual 139	java/lang/StringBuilder:append	(J)Ljava/lang/StringBuilder;
    //   480: ldc_w 392
    //   483: invokevirtual 99	java/lang/StringBuilder:append	(Ljava/lang/String;)Ljava/lang/StringBuilder;
    //   486: invokestatic 121	com/tencent/component/network/NetworkManager:a	()Ljava/lang/String;
    //   489: invokevirtual 99	java/lang/StringBuilder:append	(Ljava/lang/String;)Ljava/lang/StringBuilder;
    //   492: ldc_w 394
    //   495: invokevirtual 99	java/lang/StringBuilder:append	(Ljava/lang/String;)Ljava/lang/StringBuilder;
    //   498: aload_0
    //   499: getfield 146	com/tencent/component/network/downloader/impl/e:jdField_a_of_type_Boolean	Z
    //   502: invokevirtual 397	java/lang/StringBuilder:append	(Z)Ljava/lang/StringBuilder;
    //   505: ldc_w 399
    //   508: invokevirtual 99	java/lang/StringBuilder:append	(Ljava/lang/String;)Ljava/lang/StringBuilder;
    //   511: aload_0
    //   512: getfield 149	com/tencent/component/network/downloader/impl/e:jdField_b_of_type_Boolean	Z
    //   515: invokevirtual 397	java/lang/StringBuilder:append	(Z)Ljava/lang/StringBuilder;
    //   518: ldc_w 401
    //   521: invokevirtual 99	java/lang/StringBuilder:append	(Ljava/lang/String;)Ljava/lang/StringBuilder;
    //   524: astore 25
    //   526: aload_0
    //   527: getfield 146	com/tencent/component/network/downloader/impl/e:jdField_a_of_type_Boolean	Z
    //   530: ifeq +5869 -> 6399
    //   533: aload_0
    //   534: getfield 61	com/tencent/component/network/downloader/impl/e:jdField_a_of_type_AndroidContentContext	Landroid/content/Context;
    //   537: aload_0
    //   538: getfield 149	com/tencent/component/network/downloader/impl/e:jdField_b_of_type_Boolean	Z
    //   541: invokestatic 249	com/tencent/component/network/utils/NetworkUtils:a	(Landroid/content/Context;Z)Lcom/tencent/component/network/utils/NetworkUtils$NetworkProxy;
    //   544: astore 21
    //   546: aload 25
    //   548: aload 21
    //   550: invokevirtual 384	java/lang/StringBuilder:append	(Ljava/lang/Object;)Ljava/lang/StringBuilder;
    //   553: ldc_w 403
    //   556: invokevirtual 99	java/lang/StringBuilder:append	(Ljava/lang/String;)Ljava/lang/StringBuilder;
    //   559: aload_0
    //   560: getfield 61	com/tencent/component/network/downloader/impl/e:jdField_a_of_type_AndroidContentContext	Landroid/content/Context;
    //   563: invokestatic 298	com/tencent/component/network/utils/NetworkUtils:a	(Landroid/content/Context;)Z
    //   566: invokevirtual 397	java/lang/StringBuilder:append	(Z)Ljava/lang/StringBuilder;
    //   569: ldc_w 405
    //   572: invokevirtual 99	java/lang/StringBuilder:append	(Ljava/lang/String;)Ljava/lang/StringBuilder;
    //   575: aload_2
    //   576: invokevirtual 367	com/tencent/component/network/downloader/DownloadResult:a	()Lcom/tencent/component/network/downloader/DownloadResult$Content;
    //   579: getfield 406	com/tencent/component/network/downloader/DownloadResult$Content:jdField_a_of_type_JavaLangString	Ljava/lang/String;
    //   582: invokevirtual 99	java/lang/StringBuilder:append	(Ljava/lang/String;)Ljava/lang/StringBuilder;
    //   585: ldc_w 408
    //   588: invokevirtual 99	java/lang/StringBuilder:append	(Ljava/lang/String;)Ljava/lang/StringBuilder;
    //   591: aload_2
    //   592: invokevirtual 336	com/tencent/component/network/downloader/DownloadResult:a	()Lcom/tencent/component/network/downloader/DownloadResult$Process;
    //   595: getfield 409	com/tencent/component/network/downloader/DownloadResult$Process:jdField_c_of_type_Long	J
    //   598: invokevirtual 139	java/lang/StringBuilder:append	(J)Ljava/lang/StringBuilder;
    //   601: ldc_w 411
    //   604: invokevirtual 99	java/lang/StringBuilder:append	(Ljava/lang/String;)Ljava/lang/StringBuilder;
    //   607: invokestatic 28	android/os/SystemClock:uptimeMillis	()J
    //   610: aload_0
    //   611: getfield 30	com/tencent/component/network/downloader/impl/e:jdField_i_of_type_Long	J
    //   614: lsub
    //   615: invokevirtual 139	java/lang/StringBuilder:append	(J)Ljava/lang/StringBuilder;
    //   618: ldc_w 413
    //   621: invokevirtual 99	java/lang/StringBuilder:append	(Ljava/lang/String;)Ljava/lang/StringBuilder;
    //   624: aload_2
    //   625: invokevirtual 367	com/tencent/component/network/downloader/DownloadResult:a	()Lcom/tencent/component/network/downloader/DownloadResult$Content;
    //   628: getfield 414	com/tencent/component/network/downloader/DownloadResult$Content:jdField_a_of_type_Long	J
    //   631: invokevirtual 139	java/lang/StringBuilder:append	(J)Ljava/lang/StringBuilder;
    //   634: ldc_w 373
    //   637: invokevirtual 99	java/lang/StringBuilder:append	(Ljava/lang/String;)Ljava/lang/StringBuilder;
    //   640: aload_2
    //   641: invokevirtual 367	com/tencent/component/network/downloader/DownloadResult:a	()Lcom/tencent/component/network/downloader/DownloadResult$Content;
    //   644: getfield 371	com/tencent/component/network/downloader/DownloadResult$Content:jdField_b_of_type_Long	J
    //   647: invokevirtual 139	java/lang/StringBuilder:append	(J)Ljava/lang/StringBuilder;
    //   650: ldc_w 416
    //   653: invokevirtual 99	java/lang/StringBuilder:append	(Ljava/lang/String;)Ljava/lang/StringBuilder;
    //   656: ldc_w 418
    //   659: invokevirtual 99	java/lang/StringBuilder:append	(Ljava/lang/String;)Ljava/lang/StringBuilder;
    //   662: aload_2
    //   663: invokevirtual 367	com/tencent/component/network/downloader/DownloadResult:a	()Lcom/tencent/component/network/downloader/DownloadResult$Content;
    //   666: getfield 419	com/tencent/component/network/downloader/DownloadResult$Content:jdField_c_of_type_Long	J
    //   669: invokevirtual 139	java/lang/StringBuilder:append	(J)Ljava/lang/StringBuilder;
    //   672: ldc_w 421
    //   675: invokevirtual 99	java/lang/StringBuilder:append	(Ljava/lang/String;)Ljava/lang/StringBuilder;
    //   678: aload_0
    //   679: invokevirtual 325	com/tencent/component/network/downloader/impl/e:b	()I
    //   682: invokevirtual 109	java/lang/StringBuilder:append	(I)Ljava/lang/StringBuilder;
    //   685: ldc_w 373
    //   688: invokevirtual 99	java/lang/StringBuilder:append	(Ljava/lang/String;)Ljava/lang/StringBuilder;
    //   691: aload_0
    //   692: invokevirtual 422	com/tencent/component/network/downloader/impl/e:c	()I
    //   695: invokevirtual 109	java/lang/StringBuilder:append	(I)Ljava/lang/StringBuilder;
    //   698: ldc_w 416
    //   701: invokevirtual 99	java/lang/StringBuilder:append	(Ljava/lang/String;)Ljava/lang/StringBuilder;
    //   704: ldc_w 424
    //   707: invokevirtual 99	java/lang/StringBuilder:append	(Ljava/lang/String;)Ljava/lang/StringBuilder;
    //   710: aload_2
    //   711: invokevirtual 303	com/tencent/component/network/downloader/DownloadResult:a	()Lcom/tencent/component/network/downloader/DownloadResult$Status;
    //   714: invokevirtual 425	com/tencent/component/network/downloader/DownloadResult$Status:a	()I
    //   717: invokevirtual 109	java/lang/StringBuilder:append	(I)Ljava/lang/StringBuilder;
    //   720: ldc_w 427
    //   723: invokevirtual 99	java/lang/StringBuilder:append	(Ljava/lang/String;)Ljava/lang/StringBuilder;
    //   726: iload_3
    //   727: invokevirtual 109	java/lang/StringBuilder:append	(I)Ljava/lang/StringBuilder;
    //   730: ldc_w 429
    //   733: invokevirtual 99	java/lang/StringBuilder:append	(Ljava/lang/String;)Ljava/lang/StringBuilder;
    //   736: aload_0
    //   737: getfield 430	com/tencent/component/network/downloader/impl/e:jdField_a_of_type_JavaLangString	Ljava/lang/String;
    //   740: invokevirtual 99	java/lang/StringBuilder:append	(Ljava/lang/String;)Ljava/lang/StringBuilder;
    //   743: ldc_w 432
    //   746: invokevirtual 99	java/lang/StringBuilder:append	(Ljava/lang/String;)Ljava/lang/StringBuilder;
    //   749: astore 21
    //   751: aload_0
    //   752: getfield 74	com/tencent/component/network/downloader/impl/e:jdField_b_of_type_ComTencentComponentNetworkDownloaderStrategyDownloadGlobalStrategy$StrategyInfo	Lcom/tencent/component/network/downloader/strategy/DownloadGlobalStrategy$StrategyInfo;
    //   755: ifnull +5650 -> 6405
    //   758: aload_0
    //   759: getfield 74	com/tencent/component/network/downloader/impl/e:jdField_b_of_type_ComTencentComponentNetworkDownloaderStrategyDownloadGlobalStrategy$StrategyInfo	Lcom/tencent/component/network/downloader/strategy/DownloadGlobalStrategy$StrategyInfo;
    //   762: getfield 162	com/tencent/component/network/downloader/strategy/DownloadGlobalStrategy$StrategyInfo:jdField_a_of_type_Int	I
    //   765: istore 4
    //   767: aload 21
    //   769: iload 4
    //   771: invokevirtual 109	java/lang/StringBuilder:append	(I)Ljava/lang/StringBuilder;
    //   774: ldc_w 434
    //   777: invokevirtual 99	java/lang/StringBuilder:append	(Ljava/lang/String;)Ljava/lang/StringBuilder;
    //   780: aload_2
    //   781: invokevirtual 367	com/tencent/component/network/downloader/DownloadResult:a	()Lcom/tencent/component/network/downloader/DownloadResult$Content;
    //   784: getfield 435	com/tencent/component/network/downloader/DownloadResult$Content:jdField_c_of_type_JavaLangString	Ljava/lang/String;
    //   787: invokevirtual 99	java/lang/StringBuilder:append	(Ljava/lang/String;)Ljava/lang/StringBuilder;
    //   790: ldc_w 437
    //   793: invokevirtual 99	java/lang/StringBuilder:append	(Ljava/lang/String;)Ljava/lang/StringBuilder;
    //   796: lload 9
    //   798: invokevirtual 139	java/lang/StringBuilder:append	(J)Ljava/lang/StringBuilder;
    //   801: ldc_w 416
    //   804: invokevirtual 99	java/lang/StringBuilder:append	(Ljava/lang/String;)Ljava/lang/StringBuilder;
    //   807: ldc_w 439
    //   810: invokevirtual 99	java/lang/StringBuilder:append	(Ljava/lang/String;)Ljava/lang/StringBuilder;
    //   813: aload_0
    //   814: getfield 38	com/tencent/component/network/downloader/impl/e:jdField_d_of_type_Long	J
    //   817: invokevirtual 139	java/lang/StringBuilder:append	(J)Ljava/lang/StringBuilder;
    //   820: ldc_w 373
    //   823: invokevirtual 99	java/lang/StringBuilder:append	(Ljava/lang/String;)Ljava/lang/StringBuilder;
    //   826: aload_0
    //   827: getfield 40	com/tencent/component/network/downloader/impl/e:jdField_c_of_type_Int	I
    //   830: invokevirtual 109	java/lang/StringBuilder:append	(I)Ljava/lang/StringBuilder;
    //   833: ldc_w 416
    //   836: invokevirtual 99	java/lang/StringBuilder:append	(Ljava/lang/String;)Ljava/lang/StringBuilder;
    //   839: ldc_w 441
    //   842: invokevirtual 99	java/lang/StringBuilder:append	(Ljava/lang/String;)Ljava/lang/StringBuilder;
    //   845: aload_0
    //   846: getfield 42	com/tencent/component/network/downloader/impl/e:jdField_e_of_type_Long	J
    //   849: invokevirtual 139	java/lang/StringBuilder:append	(J)Ljava/lang/StringBuilder;
    //   852: ldc_w 373
    //   855: invokevirtual 99	java/lang/StringBuilder:append	(Ljava/lang/String;)Ljava/lang/StringBuilder;
    //   858: aload_0
    //   859: getfield 44	com/tencent/component/network/downloader/impl/e:jdField_d_of_type_Int	I
    //   862: invokevirtual 109	java/lang/StringBuilder:append	(I)Ljava/lang/StringBuilder;
    //   865: ldc_w 416
    //   868: invokevirtual 99	java/lang/StringBuilder:append	(Ljava/lang/String;)Ljava/lang/StringBuilder;
    //   871: ldc_w 443
    //   874: invokevirtual 99	java/lang/StringBuilder:append	(Ljava/lang/String;)Ljava/lang/StringBuilder;
    //   877: aload_0
    //   878: getfield 46	com/tencent/component/network/downloader/impl/e:jdField_f_of_type_Long	J
    //   881: invokevirtual 139	java/lang/StringBuilder:append	(J)Ljava/lang/StringBuilder;
    //   884: ldc_w 416
    //   887: invokevirtual 99	java/lang/StringBuilder:append	(Ljava/lang/String;)Ljava/lang/StringBuilder;
    //   890: ldc_w 445
    //   893: invokevirtual 99	java/lang/StringBuilder:append	(Ljava/lang/String;)Ljava/lang/StringBuilder;
    //   896: aload_0
    //   897: getfield 48	com/tencent/component/network/downloader/impl/e:jdField_g_of_type_Long	J
    //   900: invokevirtual 139	java/lang/StringBuilder:append	(J)Ljava/lang/StringBuilder;
    //   903: ldc_w 416
    //   906: invokevirtual 99	java/lang/StringBuilder:append	(Ljava/lang/String;)Ljava/lang/StringBuilder;
    //   909: ldc_w 447
    //   912: invokevirtual 99	java/lang/StringBuilder:append	(Ljava/lang/String;)Ljava/lang/StringBuilder;
    //   915: aload_0
    //   916: getfield 36	com/tencent/component/network/downloader/impl/e:jdField_d_of_type_JavaLangString	Ljava/lang/String;
    //   919: invokevirtual 99	java/lang/StringBuilder:append	(Ljava/lang/String;)Ljava/lang/StringBuilder;
    //   922: ldc_w 416
    //   925: invokevirtual 99	java/lang/StringBuilder:append	(Ljava/lang/String;)Ljava/lang/StringBuilder;
    //   928: ldc_w 449
    //   931: invokevirtual 99	java/lang/StringBuilder:append	(Ljava/lang/String;)Ljava/lang/StringBuilder;
    //   934: aload_0
    //   935: invokevirtual 451	com/tencent/component/network/downloader/impl/e:d	()I
    //   938: invokevirtual 109	java/lang/StringBuilder:append	(I)Ljava/lang/StringBuilder;
    //   941: ldc_w 416
    //   944: invokevirtual 99	java/lang/StringBuilder:append	(Ljava/lang/String;)Ljava/lang/StringBuilder;
    //   947: ldc_w 453
    //   950: invokevirtual 99	java/lang/StringBuilder:append	(Ljava/lang/String;)Ljava/lang/StringBuilder;
    //   953: astore 25
    //   955: aload_0
    //   956: getfield 456	com/tencent/component/network/downloader/impl/e:jdField_a_of_type_ComTencentComponentNetworkDownloaderImplA$a	Lcom/tencent/component/network/downloader/impl/a$a;
    //   959: ifnull +5452 -> 6411
    //   962: aload_0
    //   963: getfield 456	com/tencent/component/network/downloader/impl/e:jdField_a_of_type_ComTencentComponentNetworkDownloaderImplA$a	Lcom/tencent/component/network/downloader/impl/a$a;
    //   966: invokeinterface 461 1 0
    //   971: astore 21
    //   973: ldc 88
    //   975: aload 25
    //   977: aload 21
    //   979: invokevirtual 384	java/lang/StringBuilder:append	(Ljava/lang/Object;)Ljava/lang/StringBuilder;
    //   982: invokevirtual 140	java/lang/StringBuilder:toString	()Ljava/lang/String;
    //   985: aload 20
    //   987: invokestatic 330	com/tencent/component/network/module/base/b:d	(Ljava/lang/String;Ljava/lang/String;Ljava/lang/Throwable;)V
    //   990: getstatic 160	com/tencent/component/network/downloader/strategy/DownloadGlobalStrategy:d	Lcom/tencent/component/network/downloader/strategy/DownloadGlobalStrategy$StrategyInfo;
    //   993: getfield 162	com/tencent/component/network/downloader/strategy/DownloadGlobalStrategy$StrategyInfo:jdField_a_of_type_Int	I
    //   996: aload_0
    //   997: getfield 74	com/tencent/component/network/downloader/impl/e:jdField_b_of_type_ComTencentComponentNetworkDownloaderStrategyDownloadGlobalStrategy$StrategyInfo	Lcom/tencent/component/network/downloader/strategy/DownloadGlobalStrategy$StrategyInfo;
    //   1000: getfield 162	com/tencent/component/network/downloader/strategy/DownloadGlobalStrategy$StrategyInfo:jdField_a_of_type_Int	I
    //   1003: if_icmpne +37 -> 1040
    //   1006: aload_0
    //   1007: getfield 184	com/tencent/component/network/downloader/impl/e:jdField_b_of_type_ComTencentComponentNetworkDownloaderStrategyIPStrategy	Lcom/tencent/component/network/downloader/strategy/IPStrategy;
    //   1010: ifnull +30 -> 1040
    //   1013: aload_0
    //   1014: getfield 184	com/tencent/component/network/downloader/impl/e:jdField_b_of_type_ComTencentComponentNetworkDownloaderStrategyIPStrategy	Lcom/tencent/component/network/downloader/strategy/IPStrategy;
    //   1017: aload_0
    //   1018: invokevirtual 55	com/tencent/component/network/downloader/impl/e:b	()Ljava/lang/String;
    //   1021: aload_0
    //   1022: getfield 430	com/tencent/component/network/downloader/impl/e:jdField_a_of_type_JavaLangString	Ljava/lang/String;
    //   1025: invokestatic 462	com/tencent/component/network/downloader/common/a:a	(Ljava/lang/String;)Ljava/lang/String;
    //   1028: aload_2
    //   1029: invokevirtual 303	com/tencent/component/network/downloader/DownloadResult:a	()Lcom/tencent/component/network/downloader/DownloadResult$Status;
    //   1032: invokevirtual 353	com/tencent/component/network/downloader/DownloadResult$Status:a	()Z
    //   1035: invokeinterface 465 4 0
    //   1040: getstatic 237	com/tencent/component/network/downloader/strategy/DownloadGlobalStrategy:jdField_a_of_type_ComTencentComponentNetworkDownloaderStrategyDownloadGlobalStrategy$StrategyInfo	Lcom/tencent/component/network/downloader/strategy/DownloadGlobalStrategy$StrategyInfo;
    //   1043: getfield 162	com/tencent/component/network/downloader/strategy/DownloadGlobalStrategy$StrategyInfo:jdField_a_of_type_Int	I
    //   1046: aload_0
    //   1047: getfield 74	com/tencent/component/network/downloader/impl/e:jdField_b_of_type_ComTencentComponentNetworkDownloaderStrategyDownloadGlobalStrategy$StrategyInfo	Lcom/tencent/component/network/downloader/strategy/DownloadGlobalStrategy$StrategyInfo;
    //   1050: getfield 162	com/tencent/component/network/downloader/strategy/DownloadGlobalStrategy$StrategyInfo:jdField_a_of_type_Int	I
    //   1053: if_icmpne +37 -> 1090
    //   1056: aload_0
    //   1057: getfield 239	com/tencent/component/network/downloader/impl/e:jdField_a_of_type_ComTencentComponentNetworkDownloaderStrategyIPStrategy	Lcom/tencent/component/network/downloader/strategy/IPStrategy;
    //   1060: ifnull +30 -> 1090
    //   1063: aload_0
    //   1064: getfield 239	com/tencent/component/network/downloader/impl/e:jdField_a_of_type_ComTencentComponentNetworkDownloaderStrategyIPStrategy	Lcom/tencent/component/network/downloader/strategy/IPStrategy;
    //   1067: aload_0
    //   1068: invokevirtual 55	com/tencent/component/network/downloader/impl/e:b	()Ljava/lang/String;
    //   1071: aload_0
    //   1072: getfield 430	com/tencent/component/network/downloader/impl/e:jdField_a_of_type_JavaLangString	Ljava/lang/String;
    //   1075: invokestatic 462	com/tencent/component/network/downloader/common/a:a	(Ljava/lang/String;)Ljava/lang/String;
    //   1078: aload_2
    //   1079: invokevirtual 303	com/tencent/component/network/downloader/DownloadResult:a	()Lcom/tencent/component/network/downloader/DownloadResult$Status;
    //   1082: invokevirtual 353	com/tencent/component/network/downloader/DownloadResult$Status:a	()Z
    //   1085: invokeinterface 465 4 0
    //   1090: aload 24
    //   1092: invokestatic 319	java/lang/System:currentTimeMillis	()J
    //   1095: putfield 466	com/tencent/component/network/downloader/DownloadReport:jdField_b_of_type_Long	J
    //   1098: aload 24
    //   1100: aload_0
    //   1101: invokevirtual 468	com/tencent/component/network/downloader/impl/e:a	()J
    //   1104: putfield 469	com/tencent/component/network/downloader/DownloadReport:jdField_c_of_type_Long	J
    //   1107: aload 24
    //   1109: aload 19
    //   1111: putfield 472	com/tencent/component/network/downloader/DownloadReport:jdField_a_of_type_OrgApacheHttpHttpResponse	Lorg/apache/http/HttpResponse;
    //   1114: aload 24
    //   1116: iload_3
    //   1117: putfield 474	com/tencent/component/network/downloader/DownloadReport:jdField_b_of_type_Int	I
    //   1120: aload 24
    //   1122: aload 20
    //   1124: putfield 477	com/tencent/component/network/downloader/DownloadReport:jdField_a_of_type_JavaLangThrowable	Ljava/lang/Throwable;
    //   1127: aload 23
    //   1129: ifnonnull +5336 -> 6465
    //   1132: aconst_null
    //   1133: astore 19
    //   1135: aload 24
    //   1137: aload 19
    //   1139: putfield 478	com/tencent/component/network/downloader/DownloadReport:jdField_b_of_type_JavaLangString	Ljava/lang/String;
    //   1142: aload 18
    //   1144: iconst_1
    //   1145: invokestatic 480	cug:b	(Lorg/apache/http/protocol/HttpContext;Z)Ljava/lang/String;
    //   1148: astore 18
    //   1150: aload 18
    //   1152: invokestatic 201	android/text/TextUtils:isEmpty	(Ljava/lang/CharSequence;)Z
    //   1155: ifne +10 -> 1165
    //   1158: aload 24
    //   1160: aload 18
    //   1162: putfield 481	com/tencent/component/network/downloader/DownloadReport:jdField_c_of_type_JavaLangString	Ljava/lang/String;
    //   1165: aload 24
    //   1167: aload 22
    //   1169: putfield 482	com/tencent/component/network/downloader/DownloadReport:jdField_d_of_type_JavaLangString	Ljava/lang/String;
    //   1172: aload 24
    //   1174: aload_2
    //   1175: invokevirtual 367	com/tencent/component/network/downloader/DownloadResult:a	()Lcom/tencent/component/network/downloader/DownloadResult$Content;
    //   1178: getfield 435	com/tencent/component/network/downloader/DownloadResult$Content:jdField_c_of_type_JavaLangString	Ljava/lang/String;
    //   1181: putfield 484	com/tencent/component/network/downloader/DownloadReport:jdField_g_of_type_JavaLangString	Ljava/lang/String;
    //   1184: aload 24
    //   1186: invokestatic 28	android/os/SystemClock:uptimeMillis	()J
    //   1189: aload_0
    //   1190: getfield 30	com/tencent/component/network/downloader/impl/e:jdField_i_of_type_Long	J
    //   1193: lsub
    //   1194: putfield 485	com/tencent/component/network/downloader/DownloadReport:jdField_e_of_type_Long	J
    //   1197: aload 24
    //   1199: invokestatic 28	android/os/SystemClock:uptimeMillis	()J
    //   1202: aload_0
    //   1203: getfield 30	com/tencent/component/network/downloader/impl/e:jdField_i_of_type_Long	J
    //   1206: lsub
    //   1207: aload_2
    //   1208: invokevirtual 336	com/tencent/component/network/downloader/DownloadResult:a	()Lcom/tencent/component/network/downloader/DownloadResult$Process;
    //   1211: getfield 409	com/tencent/component/network/downloader/DownloadResult$Process:jdField_c_of_type_Long	J
    //   1214: lsub
    //   1215: putfield 486	com/tencent/component/network/downloader/DownloadReport:jdField_f_of_type_Long	J
    //   1218: aload 24
    //   1220: lload 9
    //   1222: putfield 487	com/tencent/component/network/downloader/DownloadReport:jdField_g_of_type_Long	J
    //   1225: aload 24
    //   1227: aload_0
    //   1228: getfield 38	com/tencent/component/network/downloader/impl/e:jdField_d_of_type_Long	J
    //   1231: putfield 488	com/tencent/component/network/downloader/DownloadReport:jdField_h_of_type_Long	J
    //   1234: aload 24
    //   1236: aload_0
    //   1237: getfield 48	com/tencent/component/network/downloader/impl/e:jdField_g_of_type_Long	J
    //   1240: putfield 489	com/tencent/component/network/downloader/DownloadReport:jdField_i_of_type_Long	J
    //   1243: aload 24
    //   1245: aload_0
    //   1246: getfield 375	com/tencent/component/network/downloader/impl/e:jdField_c_of_type_Long	J
    //   1249: putfield 492	com/tencent/component/network/downloader/DownloadReport:j	J
    //   1252: aload 24
    //   1254: lconst_0
    //   1255: putfield 495	com/tencent/component/network/downloader/DownloadReport:k	J
    //   1258: aload 24
    //   1260: aload_0
    //   1261: invokevirtual 451	com/tencent/component/network/downloader/impl/e:d	()I
    //   1264: putfield 496	com/tencent/component/network/downloader/DownloadReport:jdField_d_of_type_Int	I
    //   1267: aload 24
    //   1269: aload_2
    //   1270: invokevirtual 367	com/tencent/component/network/downloader/DownloadResult:a	()Lcom/tencent/component/network/downloader/DownloadResult$Content;
    //   1273: getfield 406	com/tencent/component/network/downloader/DownloadResult$Content:jdField_a_of_type_JavaLangString	Ljava/lang/String;
    //   1276: putfield 498	com/tencent/component/network/downloader/DownloadReport:jdField_h_of_type_JavaLangString	Ljava/lang/String;
    //   1279: aload_2
    //   1280: aload 24
    //   1282: invokevirtual 501	com/tencent/component/network/downloader/DownloadResult:a	(Lcom/tencent/component/network/downloader/DownloadReport;)V
    //   1285: aload_0
    //   1286: aload_1
    //   1287: aload_2
    //   1288: aload 24
    //   1290: invokevirtual 295	com/tencent/component/network/downloader/impl/e:a	(Lcom/tencent/component/network/utils/thread/ThreadPool$JobContext;Lcom/tencent/component/network/downloader/DownloadResult;Lcom/tencent/component/network/downloader/DownloadReport;)V
    //   1293: lload 9
    //   1295: lstore 11
    //   1297: iload 5
    //   1299: istore_3
    //   1300: aload_0
    //   1301: getfield 324	com/tencent/component/network/downloader/impl/e:jdField_a_of_type_OrgApacheHttpClientMethodsHttpGet	Lorg/apache/http/client/methods/HttpGet;
    //   1304: ifnull +22 -> 1326
    //   1307: aload_0
    //   1308: getfield 324	com/tencent/component/network/downloader/impl/e:jdField_a_of_type_OrgApacheHttpClientMethodsHttpGet	Lorg/apache/http/client/methods/HttpGet;
    //   1311: invokevirtual 506	org/apache/http/client/methods/HttpGet:abort	()V
    //   1314: aload_0
    //   1315: aconst_null
    //   1316: putfield 324	com/tencent/component/network/downloader/impl/e:jdField_a_of_type_OrgApacheHttpClientMethodsHttpGet	Lorg/apache/http/client/methods/HttpGet;
    //   1319: iload 5
    //   1321: istore_3
    //   1322: lload 9
    //   1324: lstore 11
    //   1326: aload_0
    //   1327: invokevirtual 508	com/tencent/component/network/downloader/impl/e:e	()V
    //   1330: goto -1160 -> 170
    //   1333: getstatic 511	com/tencent/component/network/downloader/impl/e:jdField_a_of_type_JavaLangThreadLocal	Ljava/lang/ThreadLocal;
    //   1336: invokevirtual 517	java/lang/ThreadLocal:get	()Ljava/lang/Object;
    //   1339: checkcast 519	com/tencent/component/network/utils/a/e$b
    //   1342: astore 22
    //   1344: aload 22
    //   1346: aload_0
    //   1347: getfield 146	com/tencent/component/network/downloader/impl/e:jdField_a_of_type_Boolean	Z
    //   1350: putfield 520	com/tencent/component/network/utils/a/e$b:jdField_a_of_type_Boolean	Z
    //   1353: aload 22
    //   1355: aload_0
    //   1356: getfield 149	com/tencent/component/network/downloader/impl/e:jdField_b_of_type_Boolean	Z
    //   1359: putfield 521	com/tencent/component/network/utils/a/e$b:jdField_b_of_type_Boolean	Z
    //   1362: aload_0
    //   1363: getfield 456	com/tencent/component/network/downloader/impl/e:jdField_a_of_type_ComTencentComponentNetworkDownloaderImplA$a	Lcom/tencent/component/network/downloader/impl/a$a;
    //   1366: ifnull +1583 -> 2949
    //   1369: aload_0
    //   1370: getfield 456	com/tencent/component/network/downloader/impl/e:jdField_a_of_type_ComTencentComponentNetworkDownloaderImplA$a	Lcom/tencent/component/network/downloader/impl/a$a;
    //   1373: invokeinterface 461 1 0
    //   1378: astore 18
    //   1380: aload 22
    //   1382: aload 18
    //   1384: putfield 524	com/tencent/component/network/utils/a/e$b:jdField_a_of_type_OrgApacheHttpHttpHost	Lorg/apache/http/HttpHost;
    //   1387: aload 24
    //   1389: iload 4
    //   1391: putfield 525	com/tencent/component/network/downloader/DownloadReport:jdField_c_of_type_Int	I
    //   1394: aload 24
    //   1396: aload_0
    //   1397: getfield 274	com/tencent/component/network/downloader/impl/e:jdField_c_of_type_JavaLangString	Ljava/lang/String;
    //   1400: putfield 527	com/tencent/component/network/downloader/DownloadReport:jdField_i_of_type_JavaLangString	Ljava/lang/String;
    //   1403: aload_0
    //   1404: aload_0
    //   1405: aload_0
    //   1406: invokevirtual 68	com/tencent/component/network/downloader/impl/e:a	()Ljava/lang/String;
    //   1409: invokevirtual 528	com/tencent/component/network/downloader/impl/e:a	(Ljava/lang/String;)Ljava/lang/String;
    //   1412: putfield 430	com/tencent/component/network/downloader/impl/e:jdField_a_of_type_JavaLangString	Ljava/lang/String;
    //   1415: aload 22
    //   1417: getfield 524	com/tencent/component/network/utils/a/e$b:jdField_a_of_type_OrgApacheHttpHttpHost	Lorg/apache/http/HttpHost;
    //   1420: ifnonnull +263 -> 1683
    //   1423: aload_0
    //   1424: getfield 430	com/tencent/component/network/downloader/impl/e:jdField_a_of_type_JavaLangString	Ljava/lang/String;
    //   1427: ldc_w 530
    //   1430: invokevirtual 533	java/lang/String:startsWith	(Ljava/lang/String;)Z
    //   1433: ifne +250 -> 1683
    //   1436: aload_0
    //   1437: getfield 74	com/tencent/component/network/downloader/impl/e:jdField_b_of_type_ComTencentComponentNetworkDownloaderStrategyDownloadGlobalStrategy$StrategyInfo	Lcom/tencent/component/network/downloader/strategy/DownloadGlobalStrategy$StrategyInfo;
    //   1440: ifnull +243 -> 1683
    //   1443: aload_0
    //   1444: getfield 74	com/tencent/component/network/downloader/impl/e:jdField_b_of_type_ComTencentComponentNetworkDownloaderStrategyDownloadGlobalStrategy$StrategyInfo	Lcom/tencent/component/network/downloader/strategy/DownloadGlobalStrategy$StrategyInfo;
    //   1447: invokevirtual 536	com/tencent/component/network/downloader/strategy/DownloadGlobalStrategy$StrategyInfo:a	()Lcom/tencent/component/network/downloader/common/IPInfo;
    //   1450: ifnull +233 -> 1683
    //   1453: aload_0
    //   1454: getfield 74	com/tencent/component/network/downloader/impl/e:jdField_b_of_type_ComTencentComponentNetworkDownloaderStrategyDownloadGlobalStrategy$StrategyInfo	Lcom/tencent/component/network/downloader/strategy/DownloadGlobalStrategy$StrategyInfo;
    //   1457: invokevirtual 536	com/tencent/component/network/downloader/strategy/DownloadGlobalStrategy$StrategyInfo:a	()Lcom/tencent/component/network/downloader/common/IPInfo;
    //   1460: getfield 537	com/tencent/component/network/downloader/common/IPInfo:jdField_a_of_type_JavaLangString	Ljava/lang/String;
    //   1463: invokestatic 201	android/text/TextUtils:isEmpty	(Ljava/lang/CharSequence;)Z
    //   1466: ifne +217 -> 1683
    //   1469: aload_0
    //   1470: getfield 74	com/tencent/component/network/downloader/impl/e:jdField_b_of_type_ComTencentComponentNetworkDownloaderStrategyDownloadGlobalStrategy$StrategyInfo	Lcom/tencent/component/network/downloader/strategy/DownloadGlobalStrategy$StrategyInfo;
    //   1473: invokevirtual 536	com/tencent/component/network/downloader/strategy/DownloadGlobalStrategy$StrategyInfo:a	()Lcom/tencent/component/network/downloader/common/IPInfo;
    //   1476: getfield 537	com/tencent/component/network/downloader/common/IPInfo:jdField_a_of_type_JavaLangString	Ljava/lang/String;
    //   1479: astore 19
    //   1481: aload 24
    //   1483: aload 19
    //   1485: putfield 481	com/tencent/component/network/downloader/DownloadReport:jdField_c_of_type_JavaLangString	Ljava/lang/String;
    //   1488: aload_0
    //   1489: invokevirtual 55	com/tencent/component/network/downloader/impl/e:b	()Ljava/lang/String;
    //   1492: astore 18
    //   1494: aload 19
    //   1496: bipush 58
    //   1498: invokestatic 540	com/tencent/component/network/downloader/common/a:a	(Ljava/lang/String;C)I
    //   1501: iconst_2
    //   1502: if_icmpge +97 -> 1599
    //   1505: aload_0
    //   1506: getfield 32	com/tencent/component/network/downloader/impl/e:jdField_e_of_type_Int	I
    //   1509: istore_3
    //   1510: iload_3
    //   1511: ifle +1444 -> 2955
    //   1514: aload_0
    //   1515: getfield 74	com/tencent/component/network/downloader/impl/e:jdField_b_of_type_ComTencentComponentNetworkDownloaderStrategyDownloadGlobalStrategy$StrategyInfo	Lcom/tencent/component/network/downloader/strategy/DownloadGlobalStrategy$StrategyInfo;
    //   1518: invokevirtual 536	com/tencent/component/network/downloader/strategy/DownloadGlobalStrategy$StrategyInfo:a	()Lcom/tencent/component/network/downloader/common/IPInfo;
    //   1521: iload_3
    //   1522: putfield 541	com/tencent/component/network/downloader/common/IPInfo:jdField_a_of_type_Int	I
    //   1525: iload_3
    //   1526: istore 5
    //   1528: iload_3
    //   1529: invokestatic 155	com/tencent/component/network/downloader/common/a:a	(I)Z
    //   1532: ifne +7 -> 1539
    //   1535: bipush 80
    //   1537: istore 5
    //   1539: new 90	java/lang/StringBuilder
    //   1542: dup
    //   1543: invokespecial 93	java/lang/StringBuilder:<init>	()V
    //   1546: aload 19
    //   1548: invokevirtual 99	java/lang/StringBuilder:append	(Ljava/lang/String;)Ljava/lang/StringBuilder;
    //   1551: ldc_w 543
    //   1554: invokevirtual 99	java/lang/StringBuilder:append	(Ljava/lang/String;)Ljava/lang/StringBuilder;
    //   1557: iload 5
    //   1559: invokevirtual 109	java/lang/StringBuilder:append	(I)Ljava/lang/StringBuilder;
    //   1562: invokevirtual 140	java/lang/StringBuilder:toString	()Ljava/lang/String;
    //   1565: astore 19
    //   1567: aload 19
    //   1569: astore 18
    //   1571: aload_0
    //   1572: getfield 266	com/tencent/component/network/downloader/impl/e:jdField_b_of_type_JavaLangString	Ljava/lang/String;
    //   1575: ifnull +24 -> 1599
    //   1578: aload_0
    //   1579: aload_0
    //   1580: getfield 430	com/tencent/component/network/downloader/impl/e:jdField_a_of_type_JavaLangString	Ljava/lang/String;
    //   1583: aload_0
    //   1584: getfield 266	com/tencent/component/network/downloader/impl/e:jdField_b_of_type_JavaLangString	Ljava/lang/String;
    //   1587: aload 19
    //   1589: invokevirtual 547	java/lang/String:replaceFirst	(Ljava/lang/String;Ljava/lang/String;)Ljava/lang/String;
    //   1592: putfield 430	com/tencent/component/network/downloader/impl/e:jdField_a_of_type_JavaLangString	Ljava/lang/String;
    //   1595: aload 19
    //   1597: astore 18
    //   1599: aload 24
    //   1601: aload_0
    //   1602: getfield 74	com/tencent/component/network/downloader/impl/e:jdField_b_of_type_ComTencentComponentNetworkDownloaderStrategyDownloadGlobalStrategy$StrategyInfo	Lcom/tencent/component/network/downloader/strategy/DownloadGlobalStrategy$StrategyInfo;
    //   1605: invokevirtual 104	com/tencent/component/network/downloader/strategy/DownloadGlobalStrategy$StrategyInfo:toString	()Ljava/lang/String;
    //   1608: putfield 549	com/tencent/component/network/downloader/DownloadReport:jdField_f_of_type_JavaLangString	Ljava/lang/String;
    //   1611: invokestatic 550	com/tencent/component/network/module/base/b:a	()Z
    //   1614: ifeq +69 -> 1683
    //   1617: ldc 88
    //   1619: new 90	java/lang/StringBuilder
    //   1622: dup
    //   1623: invokespecial 93	java/lang/StringBuilder:<init>	()V
    //   1626: ldc_w 552
    //   1629: invokevirtual 99	java/lang/StringBuilder:append	(Ljava/lang/String;)Ljava/lang/StringBuilder;
    //   1632: aload 24
    //   1634: getfield 549	com/tencent/component/network/downloader/DownloadReport:jdField_f_of_type_JavaLangString	Ljava/lang/String;
    //   1637: invokevirtual 99	java/lang/StringBuilder:append	(Ljava/lang/String;)Ljava/lang/StringBuilder;
    //   1640: ldc_w 554
    //   1643: invokevirtual 99	java/lang/StringBuilder:append	(Ljava/lang/String;)Ljava/lang/StringBuilder;
    //   1646: aload 18
    //   1648: invokevirtual 99	java/lang/StringBuilder:append	(Ljava/lang/String;)Ljava/lang/StringBuilder;
    //   1651: ldc 116
    //   1653: invokevirtual 99	java/lang/StringBuilder:append	(Ljava/lang/String;)Ljava/lang/StringBuilder;
    //   1656: aload_0
    //   1657: invokevirtual 68	com/tencent/component/network/downloader/impl/e:a	()Ljava/lang/String;
    //   1660: invokevirtual 99	java/lang/StringBuilder:append	(Ljava/lang/String;)Ljava/lang/StringBuilder;
    //   1663: ldc 179
    //   1665: invokevirtual 99	java/lang/StringBuilder:append	(Ljava/lang/String;)Ljava/lang/StringBuilder;
    //   1668: invokestatic 133	java/lang/Thread:currentThread	()Ljava/lang/Thread;
    //   1671: invokevirtual 136	java/lang/Thread:getId	()J
    //   1674: invokevirtual 139	java/lang/StringBuilder:append	(J)Ljava/lang/StringBuilder;
    //   1677: invokevirtual 140	java/lang/StringBuilder:toString	()Ljava/lang/String;
    //   1680: invokestatic 556	com/tencent/component/network/module/base/b:a	(Ljava/lang/String;Ljava/lang/String;)V
    //   1683: aload_0
    //   1684: aload_0
    //   1685: getfield 61	com/tencent/component/network/downloader/impl/e:jdField_a_of_type_AndroidContentContext	Landroid/content/Context;
    //   1688: aload_0
    //   1689: invokevirtual 68	com/tencent/component/network/downloader/impl/e:a	()Ljava/lang/String;
    //   1692: aload_0
    //   1693: invokevirtual 55	com/tencent/component/network/downloader/impl/e:b	()Ljava/lang/String;
    //   1696: aload_0
    //   1697: getfield 430	com/tencent/component/network/downloader/impl/e:jdField_a_of_type_JavaLangString	Ljava/lang/String;
    //   1700: aload_0
    //   1701: getfield 274	com/tencent/component/network/downloader/impl/e:jdField_c_of_type_JavaLangString	Ljava/lang/String;
    //   1704: aload 22
    //   1706: invokestatic 559	com/tencent/component/network/utils/a/e:a	(Landroid/content/Context;Ljava/lang/String;Ljava/lang/String;Ljava/lang/String;Ljava/lang/String;Lcom/tencent/component/network/utils/a/e$b;)Lorg/apache/http/client/methods/HttpGet;
    //   1709: putfield 324	com/tencent/component/network/downloader/impl/e:jdField_a_of_type_OrgApacheHttpClientMethodsHttpGet	Lorg/apache/http/client/methods/HttpGet;
    //   1712: aload_0
    //   1713: getfield 356	com/tencent/component/network/downloader/impl/e:jdField_a_of_type_ComTencentComponentNetworkDownloaderStrategyResumeTransfer	Lcom/tencent/component/network/downloader/strategy/ResumeTransfer;
    //   1716: ifnull +24 -> 1740
    //   1719: aload_0
    //   1720: getfield 356	com/tencent/component/network/downloader/impl/e:jdField_a_of_type_ComTencentComponentNetworkDownloaderStrategyResumeTransfer	Lcom/tencent/component/network/downloader/strategy/ResumeTransfer;
    //   1723: aload_0
    //   1724: getfield 324	com/tencent/component/network/downloader/impl/e:jdField_a_of_type_OrgApacheHttpClientMethodsHttpGet	Lorg/apache/http/client/methods/HttpGet;
    //   1727: aload_0
    //   1728: invokevirtual 68	com/tencent/component/network/downloader/impl/e:a	()Ljava/lang/String;
    //   1731: aload_0
    //   1732: invokevirtual 55	com/tencent/component/network/downloader/impl/e:b	()Ljava/lang/String;
    //   1735: invokeinterface 562 4 0
    //   1740: aload_0
    //   1741: aload_0
    //   1742: invokevirtual 68	com/tencent/component/network/downloader/impl/e:a	()Ljava/lang/String;
    //   1745: aload_0
    //   1746: invokevirtual 55	com/tencent/component/network/downloader/impl/e:b	()Ljava/lang/String;
    //   1749: aload_0
    //   1750: getfield 324	com/tencent/component/network/downloader/impl/e:jdField_a_of_type_OrgApacheHttpClientMethodsHttpGet	Lorg/apache/http/client/methods/HttpGet;
    //   1753: invokevirtual 565	com/tencent/component/network/downloader/impl/e:a	(Ljava/lang/String;Ljava/lang/String;Lorg/apache/http/HttpRequest;)V
    //   1756: aload_0
    //   1757: aload_0
    //   1758: invokevirtual 68	com/tencent/component/network/downloader/impl/e:a	()Ljava/lang/String;
    //   1761: aload_0
    //   1762: invokevirtual 55	com/tencent/component/network/downloader/impl/e:b	()Ljava/lang/String;
    //   1765: aload_0
    //   1766: getfield 324	com/tencent/component/network/downloader/impl/e:jdField_a_of_type_OrgApacheHttpClientMethodsHttpGet	Lorg/apache/http/client/methods/HttpGet;
    //   1769: invokevirtual 567	com/tencent/component/network/downloader/impl/e:b	(Ljava/lang/String;Ljava/lang/String;Lorg/apache/http/HttpRequest;)V
    //   1772: invokestatic 570	com/tencent/component/network/utils/a/e:a	()Lorg/apache/http/protocol/HttpContext;
    //   1775: astore 18
    //   1777: invokestatic 319	java/lang/System:currentTimeMillis	()J
    //   1780: lstore 15
    //   1782: lload 15
    //   1784: lload 13
    //   1786: lsub
    //   1787: lstore 9
    //   1789: aload_0
    //   1790: getfield 573	com/tencent/component/network/downloader/impl/e:jdField_a_of_type_OrgApacheHttpClientHttpClient	Lorg/apache/http/client/HttpClient;
    //   1793: aload_0
    //   1794: getfield 324	com/tencent/component/network/downloader/impl/e:jdField_a_of_type_OrgApacheHttpClientMethodsHttpGet	Lorg/apache/http/client/methods/HttpGet;
    //   1797: aload 18
    //   1799: invokeinterface 579 3 0
    //   1804: astore 19
    //   1806: aload 19
    //   1808: ifnull +2292 -> 4100
    //   1811: aload 19
    //   1813: invokeinterface 585 1 0
    //   1818: invokeinterface 590 1 0
    //   1823: istore_3
    //   1824: aload_2
    //   1825: invokevirtual 303	com/tencent/component/network/downloader/DownloadResult:a	()Lcom/tencent/component/network/downloader/DownloadResult$Status;
    //   1828: iload_3
    //   1829: putfield 593	com/tencent/component/network/downloader/DownloadResult$Status:o	I
    //   1832: sipush 200
    //   1835: iload_3
    //   1836: if_icmpeq +10 -> 1846
    //   1839: sipush 206
    //   1842: iload_3
    //   1843: if_icmpne +1126 -> 2969
    //   1846: aload_0
    //   1847: aload 19
    //   1849: aload_2
    //   1850: aload_1
    //   1851: iload_3
    //   1852: invokevirtual 596	com/tencent/component/network/downloader/impl/e:a	(Lorg/apache/http/HttpResponse;Lcom/tencent/component/network/downloader/DownloadResult;Lcom/tencent/component/network/utils/thread/ThreadPool$JobContext;I)Z
    //   1855: ifeq +6041 -> 7896
    //   1858: aload_2
    //   1859: invokevirtual 303	com/tencent/component/network/downloader/DownloadResult:a	()Lcom/tencent/component/network/downloader/DownloadResult$Status;
    //   1862: invokevirtual 598	com/tencent/component/network/downloader/DownloadResult$Status:b	()V
    //   1865: aload_2
    //   1866: invokevirtual 336	com/tencent/component/network/downloader/DownloadResult:a	()Lcom/tencent/component/network/downloader/DownloadResult$Process;
    //   1869: lload 11
    //   1871: invokestatic 28	android/os/SystemClock:uptimeMillis	()J
    //   1874: invokevirtual 341	com/tencent/component/network/downloader/DownloadResult$Process:a	(JJ)V
    //   1877: aload_0
    //   1878: getfield 61	com/tencent/component/network/downloader/impl/e:jdField_a_of_type_AndroidContentContext	Landroid/content/Context;
    //   1881: invokestatic 346	com/tencent/component/network/module/common/b:a	(Landroid/content/Context;)Lcom/tencent/component/network/module/common/b;
    //   1884: invokevirtual 349	com/tencent/component/network/module/common/b:a	()Lcom/tencent/component/network/utils/NetworkUtils$DNS;
    //   1887: astore 22
    //   1889: aload 18
    //   1891: iconst_1
    //   1892: invokestatic 352	cug:a	(Lorg/apache/http/protocol/HttpContext;Z)Ljava/lang/String;
    //   1895: astore 20
    //   1897: aload 18
    //   1899: iconst_0
    //   1900: invokestatic 352	cug:a	(Lorg/apache/http/protocol/HttpContext;Z)Ljava/lang/String;
    //   1903: astore 21
    //   1905: aload_0
    //   1906: lconst_0
    //   1907: putfield 38	com/tencent/component/network/downloader/impl/e:jdField_d_of_type_Long	J
    //   1910: aload_0
    //   1911: iconst_0
    //   1912: putfield 40	com/tencent/component/network/downloader/impl/e:jdField_c_of_type_Int	I
    //   1915: aload_0
    //   1916: lconst_0
    //   1917: putfield 42	com/tencent/component/network/downloader/impl/e:jdField_e_of_type_Long	J
    //   1920: aload_0
    //   1921: iconst_0
    //   1922: putfield 44	com/tencent/component/network/downloader/impl/e:jdField_d_of_type_Int	I
    //   1925: aload_0
    //   1926: lconst_0
    //   1927: putfield 46	com/tencent/component/network/downloader/impl/e:jdField_f_of_type_Long	J
    //   1930: aload_0
    //   1931: lconst_0
    //   1932: putfield 48	com/tencent/component/network/downloader/impl/e:jdField_g_of_type_Long	J
    //   1935: aload_2
    //   1936: invokevirtual 303	com/tencent/component/network/downloader/DownloadResult:a	()Lcom/tencent/component/network/downloader/DownloadResult$Status;
    //   1939: invokevirtual 353	com/tencent/component/network/downloader/DownloadResult$Status:a	()Z
    //   1942: ifne +29 -> 1971
    //   1945: aload_0
    //   1946: getfield 356	com/tencent/component/network/downloader/impl/e:jdField_a_of_type_ComTencentComponentNetworkDownloaderStrategyResumeTransfer	Lcom/tencent/component/network/downloader/strategy/ResumeTransfer;
    //   1949: ifnull +22 -> 1971
    //   1952: aload_0
    //   1953: getfield 356	com/tencent/component/network/downloader/impl/e:jdField_a_of_type_ComTencentComponentNetworkDownloaderStrategyResumeTransfer	Lcom/tencent/component/network/downloader/strategy/ResumeTransfer;
    //   1956: aload_0
    //   1957: invokevirtual 68	com/tencent/component/network/downloader/impl/e:a	()Ljava/lang/String;
    //   1960: aload_2
    //   1961: invokevirtual 357	com/tencent/component/network/downloader/DownloadResult:b	()Ljava/lang/String;
    //   1964: aload 19
    //   1966: invokeinterface 362 4 0
    //   1971: aload_1
    //   1972: invokeinterface 292 1 0
    //   1977: ifne +940 -> 2917
    //   1980: aload_0
    //   1981: new 90	java/lang/StringBuilder
    //   1984: dup
    //   1985: invokespecial 93	java/lang/StringBuilder:<init>	()V
    //   1988: aload_0
    //   1989: getfield 36	com/tencent/component/network/downloader/impl/e:jdField_d_of_type_JavaLangString	Ljava/lang/String;
    //   1992: invokevirtual 99	java/lang/StringBuilder:append	(Ljava/lang/String;)Ljava/lang/StringBuilder;
    //   1995: ldc_w 364
    //   1998: invokevirtual 99	java/lang/StringBuilder:append	(Ljava/lang/String;)Ljava/lang/StringBuilder;
    //   2001: aload_2
    //   2002: invokevirtual 367	com/tencent/component/network/downloader/DownloadResult:a	()Lcom/tencent/component/network/downloader/DownloadResult$Content;
    //   2005: getfield 371	com/tencent/component/network/downloader/DownloadResult$Content:jdField_b_of_type_Long	J
    //   2008: invokevirtual 139	java/lang/StringBuilder:append	(J)Ljava/lang/StringBuilder;
    //   2011: ldc_w 373
    //   2014: invokevirtual 99	java/lang/StringBuilder:append	(Ljava/lang/String;)Ljava/lang/StringBuilder;
    //   2017: aload_0
    //   2018: getfield 375	com/tencent/component/network/downloader/impl/e:jdField_c_of_type_Long	J
    //   2021: invokevirtual 139	java/lang/StringBuilder:append	(J)Ljava/lang/StringBuilder;
    //   2024: ldc_w 377
    //   2027: invokevirtual 99	java/lang/StringBuilder:append	(Ljava/lang/String;)Ljava/lang/StringBuilder;
    //   2030: invokevirtual 140	java/lang/StringBuilder:toString	()Ljava/lang/String;
    //   2033: putfield 36	com/tencent/component/network/downloader/impl/e:jdField_d_of_type_JavaLangString	Ljava/lang/String;
    //   2036: aload_2
    //   2037: invokevirtual 303	com/tencent/component/network/downloader/DownloadResult:a	()Lcom/tencent/component/network/downloader/DownloadResult$Status;
    //   2040: invokevirtual 353	com/tencent/component/network/downloader/DownloadResult$Status:a	()Z
    //   2043: ifne +4432 -> 6475
    //   2046: new 90	java/lang/StringBuilder
    //   2049: dup
    //   2050: invokespecial 93	java/lang/StringBuilder:<init>	()V
    //   2053: ldc_w 379
    //   2056: invokevirtual 99	java/lang/StringBuilder:append	(Ljava/lang/String;)Ljava/lang/StringBuilder;
    //   2059: aload_0
    //   2060: invokevirtual 68	com/tencent/component/network/downloader/impl/e:a	()Ljava/lang/String;
    //   2063: invokevirtual 99	java/lang/StringBuilder:append	(Ljava/lang/String;)Ljava/lang/StringBuilder;
    //   2066: ldc_w 381
    //   2069: invokevirtual 99	java/lang/StringBuilder:append	(Ljava/lang/String;)Ljava/lang/StringBuilder;
    //   2072: aload 22
    //   2074: invokevirtual 384	java/lang/StringBuilder:append	(Ljava/lang/Object;)Ljava/lang/StringBuilder;
    //   2077: ldc_w 386
    //   2080: invokevirtual 99	java/lang/StringBuilder:append	(Ljava/lang/String;)Ljava/lang/StringBuilder;
    //   2083: aload 20
    //   2085: invokevirtual 99	java/lang/StringBuilder:append	(Ljava/lang/String;)Ljava/lang/StringBuilder;
    //   2088: ldc_w 388
    //   2091: invokevirtual 99	java/lang/StringBuilder:append	(Ljava/lang/String;)Ljava/lang/StringBuilder;
    //   2094: aload 21
    //   2096: invokevirtual 99	java/lang/StringBuilder:append	(Ljava/lang/String;)Ljava/lang/StringBuilder;
    //   2099: ldc_w 390
    //   2102: invokevirtual 99	java/lang/StringBuilder:append	(Ljava/lang/String;)Ljava/lang/StringBuilder;
    //   2105: invokestatic 133	java/lang/Thread:currentThread	()Ljava/lang/Thread;
    //   2108: invokevirtual 136	java/lang/Thread:getId	()J
    //   2111: invokevirtual 139	java/lang/StringBuilder:append	(J)Ljava/lang/StringBuilder;
    //   2114: ldc_w 392
    //   2117: invokevirtual 99	java/lang/StringBuilder:append	(Ljava/lang/String;)Ljava/lang/StringBuilder;
    //   2120: invokestatic 121	com/tencent/component/network/NetworkManager:a	()Ljava/lang/String;
    //   2123: invokevirtual 99	java/lang/StringBuilder:append	(Ljava/lang/String;)Ljava/lang/StringBuilder;
    //   2126: ldc_w 394
    //   2129: invokevirtual 99	java/lang/StringBuilder:append	(Ljava/lang/String;)Ljava/lang/StringBuilder;
    //   2132: aload_0
    //   2133: getfield 146	com/tencent/component/network/downloader/impl/e:jdField_a_of_type_Boolean	Z
    //   2136: invokevirtual 397	java/lang/StringBuilder:append	(Z)Ljava/lang/StringBuilder;
    //   2139: ldc_w 399
    //   2142: invokevirtual 99	java/lang/StringBuilder:append	(Ljava/lang/String;)Ljava/lang/StringBuilder;
    //   2145: aload_0
    //   2146: getfield 149	com/tencent/component/network/downloader/impl/e:jdField_b_of_type_Boolean	Z
    //   2149: invokevirtual 397	java/lang/StringBuilder:append	(Z)Ljava/lang/StringBuilder;
    //   2152: ldc_w 401
    //   2155: invokevirtual 99	java/lang/StringBuilder:append	(Ljava/lang/String;)Ljava/lang/StringBuilder;
    //   2158: astore 23
    //   2160: aload_0
    //   2161: getfield 146	com/tencent/component/network/downloader/impl/e:jdField_a_of_type_Boolean	Z
    //   2164: ifeq +4864 -> 7028
    //   2167: aload_0
    //   2168: getfield 61	com/tencent/component/network/downloader/impl/e:jdField_a_of_type_AndroidContentContext	Landroid/content/Context;
    //   2171: aload_0
    //   2172: getfield 149	com/tencent/component/network/downloader/impl/e:jdField_b_of_type_Boolean	Z
    //   2175: invokestatic 249	com/tencent/component/network/utils/NetworkUtils:a	(Landroid/content/Context;Z)Lcom/tencent/component/network/utils/NetworkUtils$NetworkProxy;
    //   2178: astore 20
    //   2180: aload 23
    //   2182: aload 20
    //   2184: invokevirtual 384	java/lang/StringBuilder:append	(Ljava/lang/Object;)Ljava/lang/StringBuilder;
    //   2187: ldc_w 403
    //   2190: invokevirtual 99	java/lang/StringBuilder:append	(Ljava/lang/String;)Ljava/lang/StringBuilder;
    //   2193: aload_0
    //   2194: getfield 61	com/tencent/component/network/downloader/impl/e:jdField_a_of_type_AndroidContentContext	Landroid/content/Context;
    //   2197: invokestatic 298	com/tencent/component/network/utils/NetworkUtils:a	(Landroid/content/Context;)Z
    //   2200: invokevirtual 397	java/lang/StringBuilder:append	(Z)Ljava/lang/StringBuilder;
    //   2203: ldc_w 405
    //   2206: invokevirtual 99	java/lang/StringBuilder:append	(Ljava/lang/String;)Ljava/lang/StringBuilder;
    //   2209: aload_2
    //   2210: invokevirtual 367	com/tencent/component/network/downloader/DownloadResult:a	()Lcom/tencent/component/network/downloader/DownloadResult$Content;
    //   2213: getfield 406	com/tencent/component/network/downloader/DownloadResult$Content:jdField_a_of_type_JavaLangString	Ljava/lang/String;
    //   2216: invokevirtual 99	java/lang/StringBuilder:append	(Ljava/lang/String;)Ljava/lang/StringBuilder;
    //   2219: ldc_w 408
    //   2222: invokevirtual 99	java/lang/StringBuilder:append	(Ljava/lang/String;)Ljava/lang/StringBuilder;
    //   2225: aload_2
    //   2226: invokevirtual 336	com/tencent/component/network/downloader/DownloadResult:a	()Lcom/tencent/component/network/downloader/DownloadResult$Process;
    //   2229: getfield 409	com/tencent/component/network/downloader/DownloadResult$Process:jdField_c_of_type_Long	J
    //   2232: invokevirtual 139	java/lang/StringBuilder:append	(J)Ljava/lang/StringBuilder;
    //   2235: ldc_w 411
    //   2238: invokevirtual 99	java/lang/StringBuilder:append	(Ljava/lang/String;)Ljava/lang/StringBuilder;
    //   2241: invokestatic 28	android/os/SystemClock:uptimeMillis	()J
    //   2244: aload_0
    //   2245: getfield 30	com/tencent/component/network/downloader/impl/e:jdField_i_of_type_Long	J
    //   2248: lsub
    //   2249: invokevirtual 139	java/lang/StringBuilder:append	(J)Ljava/lang/StringBuilder;
    //   2252: ldc_w 413
    //   2255: invokevirtual 99	java/lang/StringBuilder:append	(Ljava/lang/String;)Ljava/lang/StringBuilder;
    //   2258: aload_2
    //   2259: invokevirtual 367	com/tencent/component/network/downloader/DownloadResult:a	()Lcom/tencent/component/network/downloader/DownloadResult$Content;
    //   2262: getfield 414	com/tencent/component/network/downloader/DownloadResult$Content:jdField_a_of_type_Long	J
    //   2265: invokevirtual 139	java/lang/StringBuilder:append	(J)Ljava/lang/StringBuilder;
    //   2268: ldc_w 373
    //   2271: invokevirtual 99	java/lang/StringBuilder:append	(Ljava/lang/String;)Ljava/lang/StringBuilder;
    //   2274: aload_2
    //   2275: invokevirtual 367	com/tencent/component/network/downloader/DownloadResult:a	()Lcom/tencent/component/network/downloader/DownloadResult$Content;
    //   2278: getfield 371	com/tencent/component/network/downloader/DownloadResult$Content:jdField_b_of_type_Long	J
    //   2281: invokevirtual 139	java/lang/StringBuilder:append	(J)Ljava/lang/StringBuilder;
    //   2284: ldc_w 416
    //   2287: invokevirtual 99	java/lang/StringBuilder:append	(Ljava/lang/String;)Ljava/lang/StringBuilder;
    //   2290: ldc_w 418
    //   2293: invokevirtual 99	java/lang/StringBuilder:append	(Ljava/lang/String;)Ljava/lang/StringBuilder;
    //   2296: aload_2
    //   2297: invokevirtual 367	com/tencent/component/network/downloader/DownloadResult:a	()Lcom/tencent/component/network/downloader/DownloadResult$Content;
    //   2300: getfield 419	com/tencent/component/network/downloader/DownloadResult$Content:jdField_c_of_type_Long	J
    //   2303: invokevirtual 139	java/lang/StringBuilder:append	(J)Ljava/lang/StringBuilder;
    //   2306: ldc_w 421
    //   2309: invokevirtual 99	java/lang/StringBuilder:append	(Ljava/lang/String;)Ljava/lang/StringBuilder;
    //   2312: aload_0
    //   2313: invokevirtual 325	com/tencent/component/network/downloader/impl/e:b	()I
    //   2316: invokevirtual 109	java/lang/StringBuilder:append	(I)Ljava/lang/StringBuilder;
    //   2319: ldc_w 373
    //   2322: invokevirtual 99	java/lang/StringBuilder:append	(Ljava/lang/String;)Ljava/lang/StringBuilder;
    //   2325: aload_0
    //   2326: invokevirtual 422	com/tencent/component/network/downloader/impl/e:c	()I
    //   2329: invokevirtual 109	java/lang/StringBuilder:append	(I)Ljava/lang/StringBuilder;
    //   2332: ldc_w 416
    //   2335: invokevirtual 99	java/lang/StringBuilder:append	(Ljava/lang/String;)Ljava/lang/StringBuilder;
    //   2338: ldc_w 424
    //   2341: invokevirtual 99	java/lang/StringBuilder:append	(Ljava/lang/String;)Ljava/lang/StringBuilder;
    //   2344: aload_2
    //   2345: invokevirtual 303	com/tencent/component/network/downloader/DownloadResult:a	()Lcom/tencent/component/network/downloader/DownloadResult$Status;
    //   2348: invokevirtual 425	com/tencent/component/network/downloader/DownloadResult$Status:a	()I
    //   2351: invokevirtual 109	java/lang/StringBuilder:append	(I)Ljava/lang/StringBuilder;
    //   2354: ldc_w 427
    //   2357: invokevirtual 99	java/lang/StringBuilder:append	(Ljava/lang/String;)Ljava/lang/StringBuilder;
    //   2360: iload_3
    //   2361: invokevirtual 109	java/lang/StringBuilder:append	(I)Ljava/lang/StringBuilder;
    //   2364: ldc_w 429
    //   2367: invokevirtual 99	java/lang/StringBuilder:append	(Ljava/lang/String;)Ljava/lang/StringBuilder;
    //   2370: aload_0
    //   2371: getfield 430	com/tencent/component/network/downloader/impl/e:jdField_a_of_type_JavaLangString	Ljava/lang/String;
    //   2374: invokevirtual 99	java/lang/StringBuilder:append	(Ljava/lang/String;)Ljava/lang/StringBuilder;
    //   2377: ldc_w 432
    //   2380: invokevirtual 99	java/lang/StringBuilder:append	(Ljava/lang/String;)Ljava/lang/StringBuilder;
    //   2383: astore 20
    //   2385: aload_0
    //   2386: getfield 74	com/tencent/component/network/downloader/impl/e:jdField_b_of_type_ComTencentComponentNetworkDownloaderStrategyDownloadGlobalStrategy$StrategyInfo	Lcom/tencent/component/network/downloader/strategy/DownloadGlobalStrategy$StrategyInfo;
    //   2389: ifnull +4645 -> 7034
    //   2392: aload_0
    //   2393: getfield 74	com/tencent/component/network/downloader/impl/e:jdField_b_of_type_ComTencentComponentNetworkDownloaderStrategyDownloadGlobalStrategy$StrategyInfo	Lcom/tencent/component/network/downloader/strategy/DownloadGlobalStrategy$StrategyInfo;
    //   2396: getfield 162	com/tencent/component/network/downloader/strategy/DownloadGlobalStrategy$StrategyInfo:jdField_a_of_type_Int	I
    //   2399: istore 4
    //   2401: aload 20
    //   2403: iload 4
    //   2405: invokevirtual 109	java/lang/StringBuilder:append	(I)Ljava/lang/StringBuilder;
    //   2408: ldc_w 434
    //   2411: invokevirtual 99	java/lang/StringBuilder:append	(Ljava/lang/String;)Ljava/lang/StringBuilder;
    //   2414: aload_2
    //   2415: invokevirtual 367	com/tencent/component/network/downloader/DownloadResult:a	()Lcom/tencent/component/network/downloader/DownloadResult$Content;
    //   2418: getfield 435	com/tencent/component/network/downloader/DownloadResult$Content:jdField_c_of_type_JavaLangString	Ljava/lang/String;
    //   2421: invokevirtual 99	java/lang/StringBuilder:append	(Ljava/lang/String;)Ljava/lang/StringBuilder;
    //   2424: ldc_w 437
    //   2427: invokevirtual 99	java/lang/StringBuilder:append	(Ljava/lang/String;)Ljava/lang/StringBuilder;
    //   2430: lload 9
    //   2432: invokevirtual 139	java/lang/StringBuilder:append	(J)Ljava/lang/StringBuilder;
    //   2435: ldc_w 416
    //   2438: invokevirtual 99	java/lang/StringBuilder:append	(Ljava/lang/String;)Ljava/lang/StringBuilder;
    //   2441: ldc_w 439
    //   2444: invokevirtual 99	java/lang/StringBuilder:append	(Ljava/lang/String;)Ljava/lang/StringBuilder;
    //   2447: aload_0
    //   2448: getfield 38	com/tencent/component/network/downloader/impl/e:jdField_d_of_type_Long	J
    //   2451: invokevirtual 139	java/lang/StringBuilder:append	(J)Ljava/lang/StringBuilder;
    //   2454: ldc_w 373
    //   2457: invokevirtual 99	java/lang/StringBuilder:append	(Ljava/lang/String;)Ljava/lang/StringBuilder;
    //   2460: aload_0
    //   2461: getfield 40	com/tencent/component/network/downloader/impl/e:jdField_c_of_type_Int	I
    //   2464: invokevirtual 109	java/lang/StringBuilder:append	(I)Ljava/lang/StringBuilder;
    //   2467: ldc_w 416
    //   2470: invokevirtual 99	java/lang/StringBuilder:append	(Ljava/lang/String;)Ljava/lang/StringBuilder;
    //   2473: ldc_w 441
    //   2476: invokevirtual 99	java/lang/StringBuilder:append	(Ljava/lang/String;)Ljava/lang/StringBuilder;
    //   2479: aload_0
    //   2480: getfield 42	com/tencent/component/network/downloader/impl/e:jdField_e_of_type_Long	J
    //   2483: invokevirtual 139	java/lang/StringBuilder:append	(J)Ljava/lang/StringBuilder;
    //   2486: ldc_w 373
    //   2489: invokevirtual 99	java/lang/StringBuilder:append	(Ljava/lang/String;)Ljava/lang/StringBuilder;
    //   2492: aload_0
    //   2493: getfield 44	com/tencent/component/network/downloader/impl/e:jdField_d_of_type_Int	I
    //   2496: invokevirtual 109	java/lang/StringBuilder:append	(I)Ljava/lang/StringBuilder;
    //   2499: ldc_w 416
    //   2502: invokevirtual 99	java/lang/StringBuilder:append	(Ljava/lang/String;)Ljava/lang/StringBuilder;
    //   2505: ldc_w 443
    //   2508: invokevirtual 99	java/lang/StringBuilder:append	(Ljava/lang/String;)Ljava/lang/StringBuilder;
    //   2511: aload_0
    //   2512: getfield 46	com/tencent/component/network/downloader/impl/e:jdField_f_of_type_Long	J
    //   2515: invokevirtual 139	java/lang/StringBuilder:append	(J)Ljava/lang/StringBuilder;
    //   2518: ldc_w 416
    //   2521: invokevirtual 99	java/lang/StringBuilder:append	(Ljava/lang/String;)Ljava/lang/StringBuilder;
    //   2524: ldc_w 445
    //   2527: invokevirtual 99	java/lang/StringBuilder:append	(Ljava/lang/String;)Ljava/lang/StringBuilder;
    //   2530: aload_0
    //   2531: getfield 48	com/tencent/component/network/downloader/impl/e:jdField_g_of_type_Long	J
    //   2534: invokevirtual 139	java/lang/StringBuilder:append	(J)Ljava/lang/StringBuilder;
    //   2537: ldc_w 416
    //   2540: invokevirtual 99	java/lang/StringBuilder:append	(Ljava/lang/String;)Ljava/lang/StringBuilder;
    //   2543: ldc_w 447
    //   2546: invokevirtual 99	java/lang/StringBuilder:append	(Ljava/lang/String;)Ljava/lang/StringBuilder;
    //   2549: aload_0
    //   2550: getfield 36	com/tencent/component/network/downloader/impl/e:jdField_d_of_type_JavaLangString	Ljava/lang/String;
    //   2553: invokevirtual 99	java/lang/StringBuilder:append	(Ljava/lang/String;)Ljava/lang/StringBuilder;
    //   2556: ldc_w 416
    //   2559: invokevirtual 99	java/lang/StringBuilder:append	(Ljava/lang/String;)Ljava/lang/StringBuilder;
    //   2562: ldc_w 449
    //   2565: invokevirtual 99	java/lang/StringBuilder:append	(Ljava/lang/String;)Ljava/lang/StringBuilder;
    //   2568: aload_0
    //   2569: invokevirtual 451	com/tencent/component/network/downloader/impl/e:d	()I
    //   2572: invokevirtual 109	java/lang/StringBuilder:append	(I)Ljava/lang/StringBuilder;
    //   2575: ldc_w 416
    //   2578: invokevirtual 99	java/lang/StringBuilder:append	(Ljava/lang/String;)Ljava/lang/StringBuilder;
    //   2581: ldc_w 453
    //   2584: invokevirtual 99	java/lang/StringBuilder:append	(Ljava/lang/String;)Ljava/lang/StringBuilder;
    //   2587: astore 23
    //   2589: aload_0
    //   2590: getfield 456	com/tencent/component/network/downloader/impl/e:jdField_a_of_type_ComTencentComponentNetworkDownloaderImplA$a	Lcom/tencent/component/network/downloader/impl/a$a;
    //   2593: ifnull +4447 -> 7040
    //   2596: aload_0
    //   2597: getfield 456	com/tencent/component/network/downloader/impl/e:jdField_a_of_type_ComTencentComponentNetworkDownloaderImplA$a	Lcom/tencent/component/network/downloader/impl/a$a;
    //   2600: invokeinterface 461 1 0
    //   2605: astore 20
    //   2607: ldc 88
    //   2609: aload 23
    //   2611: aload 20
    //   2613: invokevirtual 384	java/lang/StringBuilder:append	(Ljava/lang/Object;)Ljava/lang/StringBuilder;
    //   2616: invokevirtual 140	java/lang/StringBuilder:toString	()Ljava/lang/String;
    //   2619: aconst_null
    //   2620: invokestatic 330	com/tencent/component/network/module/base/b:d	(Ljava/lang/String;Ljava/lang/String;Ljava/lang/Throwable;)V
    //   2623: getstatic 160	com/tencent/component/network/downloader/strategy/DownloadGlobalStrategy:d	Lcom/tencent/component/network/downloader/strategy/DownloadGlobalStrategy$StrategyInfo;
    //   2626: getfield 162	com/tencent/component/network/downloader/strategy/DownloadGlobalStrategy$StrategyInfo:jdField_a_of_type_Int	I
    //   2629: aload_0
    //   2630: getfield 74	com/tencent/component/network/downloader/impl/e:jdField_b_of_type_ComTencentComponentNetworkDownloaderStrategyDownloadGlobalStrategy$StrategyInfo	Lcom/tencent/component/network/downloader/strategy/DownloadGlobalStrategy$StrategyInfo;
    //   2633: getfield 162	com/tencent/component/network/downloader/strategy/DownloadGlobalStrategy$StrategyInfo:jdField_a_of_type_Int	I
    //   2636: if_icmpne +37 -> 2673
    //   2639: aload_0
    //   2640: getfield 184	com/tencent/component/network/downloader/impl/e:jdField_b_of_type_ComTencentComponentNetworkDownloaderStrategyIPStrategy	Lcom/tencent/component/network/downloader/strategy/IPStrategy;
    //   2643: ifnull +30 -> 2673
    //   2646: aload_0
    //   2647: getfield 184	com/tencent/component/network/downloader/impl/e:jdField_b_of_type_ComTencentComponentNetworkDownloaderStrategyIPStrategy	Lcom/tencent/component/network/downloader/strategy/IPStrategy;
    //   2650: aload_0
    //   2651: invokevirtual 55	com/tencent/component/network/downloader/impl/e:b	()Ljava/lang/String;
    //   2654: aload_0
    //   2655: getfield 430	com/tencent/component/network/downloader/impl/e:jdField_a_of_type_JavaLangString	Ljava/lang/String;
    //   2658: invokestatic 462	com/tencent/component/network/downloader/common/a:a	(Ljava/lang/String;)Ljava/lang/String;
    //   2661: aload_2
    //   2662: invokevirtual 303	com/tencent/component/network/downloader/DownloadResult:a	()Lcom/tencent/component/network/downloader/DownloadResult$Status;
    //   2665: invokevirtual 353	com/tencent/component/network/downloader/DownloadResult$Status:a	()Z
    //   2668: invokeinterface 465 4 0
    //   2673: getstatic 237	com/tencent/component/network/downloader/strategy/DownloadGlobalStrategy:jdField_a_of_type_ComTencentComponentNetworkDownloaderStrategyDownloadGlobalStrategy$StrategyInfo	Lcom/tencent/component/network/downloader/strategy/DownloadGlobalStrategy$StrategyInfo;
    //   2676: getfield 162	com/tencent/component/network/downloader/strategy/DownloadGlobalStrategy$StrategyInfo:jdField_a_of_type_Int	I
    //   2679: aload_0
    //   2680: getfield 74	com/tencent/component/network/downloader/impl/e:jdField_b_of_type_ComTencentComponentNetworkDownloaderStrategyDownloadGlobalStrategy$StrategyInfo	Lcom/tencent/component/network/downloader/strategy/DownloadGlobalStrategy$StrategyInfo;
    //   2683: getfield 162	com/tencent/component/network/downloader/strategy/DownloadGlobalStrategy$StrategyInfo:jdField_a_of_type_Int	I
    //   2686: if_icmpne +37 -> 2723
    //   2689: aload_0
    //   2690: getfield 239	com/tencent/component/network/downloader/impl/e:jdField_a_of_type_ComTencentComponentNetworkDownloaderStrategyIPStrategy	Lcom/tencent/component/network/downloader/strategy/IPStrategy;
    //   2693: ifnull +30 -> 2723
    //   2696: aload_0
    //   2697: getfield 239	com/tencent/component/network/downloader/impl/e:jdField_a_of_type_ComTencentComponentNetworkDownloaderStrategyIPStrategy	Lcom/tencent/component/network/downloader/strategy/IPStrategy;
    //   2700: aload_0
    //   2701: invokevirtual 55	com/tencent/component/network/downloader/impl/e:b	()Ljava/lang/String;
    //   2704: aload_0
    //   2705: getfield 430	com/tencent/component/network/downloader/impl/e:jdField_a_of_type_JavaLangString	Ljava/lang/String;
    //   2708: invokestatic 462	com/tencent/component/network/downloader/common/a:a	(Ljava/lang/String;)Ljava/lang/String;
    //   2711: aload_2
    //   2712: invokevirtual 303	com/tencent/component/network/downloader/DownloadResult:a	()Lcom/tencent/component/network/downloader/DownloadResult$Status;
    //   2715: invokevirtual 353	com/tencent/component/network/downloader/DownloadResult$Status:a	()Z
    //   2718: invokeinterface 465 4 0
    //   2723: aload 24
    //   2725: invokestatic 319	java/lang/System:currentTimeMillis	()J
    //   2728: putfield 466	com/tencent/component/network/downloader/DownloadReport:jdField_b_of_type_Long	J
    //   2731: aload 24
    //   2733: aload_0
    //   2734: invokevirtual 468	com/tencent/component/network/downloader/impl/e:a	()J
    //   2737: putfield 469	com/tencent/component/network/downloader/DownloadReport:jdField_c_of_type_Long	J
    //   2740: aload 24
    //   2742: aload 19
    //   2744: putfield 472	com/tencent/component/network/downloader/DownloadReport:jdField_a_of_type_OrgApacheHttpHttpResponse	Lorg/apache/http/HttpResponse;
    //   2747: aload 24
    //   2749: iload_3
    //   2750: putfield 474	com/tencent/component/network/downloader/DownloadReport:jdField_b_of_type_Int	I
    //   2753: aload 24
    //   2755: aconst_null
    //   2756: putfield 477	com/tencent/component/network/downloader/DownloadReport:jdField_a_of_type_JavaLangThrowable	Ljava/lang/Throwable;
    //   2759: aload 22
    //   2761: ifnonnull +4333 -> 7094
    //   2764: aconst_null
    //   2765: astore 19
    //   2767: aload 24
    //   2769: aload 19
    //   2771: putfield 478	com/tencent/component/network/downloader/DownloadReport:jdField_b_of_type_JavaLangString	Ljava/lang/String;
    //   2774: aload 18
    //   2776: iconst_1
    //   2777: invokestatic 480	cug:b	(Lorg/apache/http/protocol/HttpContext;Z)Ljava/lang/String;
    //   2780: astore 18
    //   2782: aload 18
    //   2784: invokestatic 201	android/text/TextUtils:isEmpty	(Ljava/lang/CharSequence;)Z
    //   2787: ifne +10 -> 2797
    //   2790: aload 24
    //   2792: aload 18
    //   2794: putfield 481	com/tencent/component/network/downloader/DownloadReport:jdField_c_of_type_JavaLangString	Ljava/lang/String;
    //   2797: aload 24
    //   2799: aload 21
    //   2801: putfield 482	com/tencent/component/network/downloader/DownloadReport:jdField_d_of_type_JavaLangString	Ljava/lang/String;
    //   2804: aload 24
    //   2806: aload_2
    //   2807: invokevirtual 367	com/tencent/component/network/downloader/DownloadResult:a	()Lcom/tencent/component/network/downloader/DownloadResult$Content;
    //   2810: getfield 435	com/tencent/component/network/downloader/DownloadResult$Content:jdField_c_of_type_JavaLangString	Ljava/lang/String;
    //   2813: putfield 484	com/tencent/component/network/downloader/DownloadReport:jdField_g_of_type_JavaLangString	Ljava/lang/String;
    //   2816: aload 24
    //   2818: invokestatic 28	android/os/SystemClock:uptimeMillis	()J
    //   2821: aload_0
    //   2822: getfield 30	com/tencent/component/network/downloader/impl/e:jdField_i_of_type_Long	J
    //   2825: lsub
    //   2826: putfield 485	com/tencent/component/network/downloader/DownloadReport:jdField_e_of_type_Long	J
    //   2829: aload 24
    //   2831: invokestatic 28	android/os/SystemClock:uptimeMillis	()J
    //   2834: aload_0
    //   2835: getfield 30	com/tencent/component/network/downloader/impl/e:jdField_i_of_type_Long	J
    //   2838: lsub
    //   2839: aload_2
    //   2840: invokevirtual 336	com/tencent/component/network/downloader/DownloadResult:a	()Lcom/tencent/component/network/downloader/DownloadResult$Process;
    //   2843: getfield 409	com/tencent/component/network/downloader/DownloadResult$Process:jdField_c_of_type_Long	J
    //   2846: lsub
    //   2847: putfield 486	com/tencent/component/network/downloader/DownloadReport:jdField_f_of_type_Long	J
    //   2850: aload 24
    //   2852: lload 9
    //   2854: putfield 487	com/tencent/component/network/downloader/DownloadReport:jdField_g_of_type_Long	J
    //   2857: aload 24
    //   2859: aload_0
    //   2860: getfield 38	com/tencent/component/network/downloader/impl/e:jdField_d_of_type_Long	J
    //   2863: putfield 488	com/tencent/component/network/downloader/DownloadReport:jdField_h_of_type_Long	J
    //   2866: aload 24
    //   2868: aload_0
    //   2869: getfield 48	com/tencent/component/network/downloader/impl/e:jdField_g_of_type_Long	J
    //   2872: putfield 489	com/tencent/component/network/downloader/DownloadReport:jdField_i_of_type_Long	J
    //   2875: aload 24
    //   2877: aload_0
    //   2878: getfield 375	com/tencent/component/network/downloader/impl/e:jdField_c_of_type_Long	J
    //   2881: putfield 492	com/tencent/component/network/downloader/DownloadReport:j	J
    //   2884: aload 24
    //   2886: lconst_0
    //   2887: putfield 495	com/tencent/component/network/downloader/DownloadReport:k	J
    //   2890: aload 24
    //   2892: aload_0
    //   2893: invokevirtual 451	com/tencent/component/network/downloader/impl/e:d	()I
    //   2896: putfield 496	com/tencent/component/network/downloader/DownloadReport:jdField_d_of_type_Int	I
    //   2899: aload 24
    //   2901: aload_2
    //   2902: invokevirtual 367	com/tencent/component/network/downloader/DownloadResult:a	()Lcom/tencent/component/network/downloader/DownloadResult$Content;
    //   2905: getfield 406	com/tencent/component/network/downloader/DownloadResult$Content:jdField_a_of_type_JavaLangString	Ljava/lang/String;
    //   2908: putfield 498	com/tencent/component/network/downloader/DownloadReport:jdField_h_of_type_JavaLangString	Ljava/lang/String;
    //   2911: aload_2
    //   2912: aload 24
    //   2914: invokevirtual 501	com/tencent/component/network/downloader/DownloadResult:a	(Lcom/tencent/component/network/downloader/DownloadReport;)V
    //   2917: aload_0
    //   2918: aload_1
    //   2919: aload_2
    //   2920: aload 24
    //   2922: invokevirtual 295	com/tencent/component/network/downloader/impl/e:a	(Lcom/tencent/component/network/utils/thread/ThreadPool$JobContext;Lcom/tencent/component/network/downloader/DownloadResult;Lcom/tencent/component/network/downloader/DownloadReport;)V
    //   2925: aload_0
    //   2926: getfield 324	com/tencent/component/network/downloader/impl/e:jdField_a_of_type_OrgApacheHttpClientMethodsHttpGet	Lorg/apache/http/client/methods/HttpGet;
    //   2929: ifnull +15 -> 2944
    //   2932: aload_0
    //   2933: getfield 324	com/tencent/component/network/downloader/impl/e:jdField_a_of_type_OrgApacheHttpClientMethodsHttpGet	Lorg/apache/http/client/methods/HttpGet;
    //   2936: invokevirtual 506	org/apache/http/client/methods/HttpGet:abort	()V
    //   2939: aload_0
    //   2940: aconst_null
    //   2941: putfield 324	com/tencent/component/network/downloader/impl/e:jdField_a_of_type_OrgApacheHttpClientMethodsHttpGet	Lorg/apache/http/client/methods/HttpGet;
    //   2944: aload_0
    //   2945: invokevirtual 508	com/tencent/component/network/downloader/impl/e:e	()V
    //   2948: return
    //   2949: aconst_null
    //   2950: astore 18
    //   2952: goto -1572 -> 1380
    //   2955: aload_0
    //   2956: getfield 74	com/tencent/component/network/downloader/impl/e:jdField_b_of_type_ComTencentComponentNetworkDownloaderStrategyDownloadGlobalStrategy$StrategyInfo	Lcom/tencent/component/network/downloader/strategy/DownloadGlobalStrategy$StrategyInfo;
    //   2959: invokevirtual 536	com/tencent/component/network/downloader/strategy/DownloadGlobalStrategy$StrategyInfo:a	()Lcom/tencent/component/network/downloader/common/IPInfo;
    //   2962: getfield 541	com/tencent/component/network/downloader/common/IPInfo:jdField_a_of_type_Int	I
    //   2965: istore_3
    //   2966: goto -1441 -> 1525
    //   2969: aload_2
    //   2970: invokevirtual 303	com/tencent/component/network/downloader/DownloadResult:a	()Lcom/tencent/component/network/downloader/DownloadResult$Status;
    //   2973: iconst_3
    //   2974: invokevirtual 306	com/tencent/component/network/downloader/DownloadResult$Status:a	(I)V
    //   2977: aload_0
    //   2978: getfield 356	com/tencent/component/network/downloader/impl/e:jdField_a_of_type_ComTencentComponentNetworkDownloaderStrategyResumeTransfer	Lcom/tencent/component/network/downloader/strategy/ResumeTransfer;
    //   2981: ifnull +4915 -> 7896
    //   2984: aload_0
    //   2985: getfield 356	com/tencent/component/network/downloader/impl/e:jdField_a_of_type_ComTencentComponentNetworkDownloaderStrategyResumeTransfer	Lcom/tencent/component/network/downloader/strategy/ResumeTransfer;
    //   2988: aload_0
    //   2989: invokevirtual 68	com/tencent/component/network/downloader/impl/e:a	()Ljava/lang/String;
    //   2992: iconst_1
    //   2993: invokeinterface 601 3 0
    //   2998: iload 4
    //   3000: iconst_1
    //   3001: iadd
    //   3002: istore 5
    //   3004: aload_2
    //   3005: invokevirtual 336	com/tencent/component/network/downloader/DownloadResult:a	()Lcom/tencent/component/network/downloader/DownloadResult$Process;
    //   3008: lload 11
    //   3010: invokestatic 28	android/os/SystemClock:uptimeMillis	()J
    //   3013: invokevirtual 341	com/tencent/component/network/downloader/DownloadResult$Process:a	(JJ)V
    //   3016: aload_0
    //   3017: getfield 61	com/tencent/component/network/downloader/impl/e:jdField_a_of_type_AndroidContentContext	Landroid/content/Context;
    //   3020: invokestatic 346	com/tencent/component/network/module/common/b:a	(Landroid/content/Context;)Lcom/tencent/component/network/module/common/b;
    //   3023: invokevirtual 349	com/tencent/component/network/module/common/b:a	()Lcom/tencent/component/network/utils/NetworkUtils$DNS;
    //   3026: astore 22
    //   3028: aload 18
    //   3030: iconst_1
    //   3031: invokestatic 352	cug:a	(Lorg/apache/http/protocol/HttpContext;Z)Ljava/lang/String;
    //   3034: astore 20
    //   3036: aload 18
    //   3038: iconst_0
    //   3039: invokestatic 352	cug:a	(Lorg/apache/http/protocol/HttpContext;Z)Ljava/lang/String;
    //   3042: astore 21
    //   3044: aload_0
    //   3045: lconst_0
    //   3046: putfield 38	com/tencent/component/network/downloader/impl/e:jdField_d_of_type_Long	J
    //   3049: aload_0
    //   3050: iconst_0
    //   3051: putfield 40	com/tencent/component/network/downloader/impl/e:jdField_c_of_type_Int	I
    //   3054: aload_0
    //   3055: lconst_0
    //   3056: putfield 42	com/tencent/component/network/downloader/impl/e:jdField_e_of_type_Long	J
    //   3059: aload_0
    //   3060: iconst_0
    //   3061: putfield 44	com/tencent/component/network/downloader/impl/e:jdField_d_of_type_Int	I
    //   3064: aload_0
    //   3065: lconst_0
    //   3066: putfield 46	com/tencent/component/network/downloader/impl/e:jdField_f_of_type_Long	J
    //   3069: aload_0
    //   3070: lconst_0
    //   3071: putfield 48	com/tencent/component/network/downloader/impl/e:jdField_g_of_type_Long	J
    //   3074: aload_2
    //   3075: invokevirtual 303	com/tencent/component/network/downloader/DownloadResult:a	()Lcom/tencent/component/network/downloader/DownloadResult$Status;
    //   3078: invokevirtual 353	com/tencent/component/network/downloader/DownloadResult$Status:a	()Z
    //   3081: ifne +29 -> 3110
    //   3084: aload_0
    //   3085: getfield 356	com/tencent/component/network/downloader/impl/e:jdField_a_of_type_ComTencentComponentNetworkDownloaderStrategyResumeTransfer	Lcom/tencent/component/network/downloader/strategy/ResumeTransfer;
    //   3088: ifnull +22 -> 3110
    //   3091: aload_0
    //   3092: getfield 356	com/tencent/component/network/downloader/impl/e:jdField_a_of_type_ComTencentComponentNetworkDownloaderStrategyResumeTransfer	Lcom/tencent/component/network/downloader/strategy/ResumeTransfer;
    //   3095: aload_0
    //   3096: invokevirtual 68	com/tencent/component/network/downloader/impl/e:a	()Ljava/lang/String;
    //   3099: aload_2
    //   3100: invokevirtual 357	com/tencent/component/network/downloader/DownloadResult:b	()Ljava/lang/String;
    //   3103: aload 19
    //   3105: invokeinterface 362 4 0
    //   3110: aload_1
    //   3111: invokeinterface 292 1 0
    //   3116: ifne +940 -> 4056
    //   3119: aload_0
    //   3120: new 90	java/lang/StringBuilder
    //   3123: dup
    //   3124: invokespecial 93	java/lang/StringBuilder:<init>	()V
    //   3127: aload_0
    //   3128: getfield 36	com/tencent/component/network/downloader/impl/e:jdField_d_of_type_JavaLangString	Ljava/lang/String;
    //   3131: invokevirtual 99	java/lang/StringBuilder:append	(Ljava/lang/String;)Ljava/lang/StringBuilder;
    //   3134: ldc_w 364
    //   3137: invokevirtual 99	java/lang/StringBuilder:append	(Ljava/lang/String;)Ljava/lang/StringBuilder;
    //   3140: aload_2
    //   3141: invokevirtual 367	com/tencent/component/network/downloader/DownloadResult:a	()Lcom/tencent/component/network/downloader/DownloadResult$Content;
    //   3144: getfield 371	com/tencent/component/network/downloader/DownloadResult$Content:jdField_b_of_type_Long	J
    //   3147: invokevirtual 139	java/lang/StringBuilder:append	(J)Ljava/lang/StringBuilder;
    //   3150: ldc_w 373
    //   3153: invokevirtual 99	java/lang/StringBuilder:append	(Ljava/lang/String;)Ljava/lang/StringBuilder;
    //   3156: aload_0
    //   3157: getfield 375	com/tencent/component/network/downloader/impl/e:jdField_c_of_type_Long	J
    //   3160: invokevirtual 139	java/lang/StringBuilder:append	(J)Ljava/lang/StringBuilder;
    //   3163: ldc_w 377
    //   3166: invokevirtual 99	java/lang/StringBuilder:append	(Ljava/lang/String;)Ljava/lang/StringBuilder;
    //   3169: invokevirtual 140	java/lang/StringBuilder:toString	()Ljava/lang/String;
    //   3172: putfield 36	com/tencent/component/network/downloader/impl/e:jdField_d_of_type_JavaLangString	Ljava/lang/String;
    //   3175: aload_2
    //   3176: invokevirtual 303	com/tencent/component/network/downloader/DownloadResult:a	()Lcom/tencent/component/network/downloader/DownloadResult$Status;
    //   3179: invokevirtual 353	com/tencent/component/network/downloader/DownloadResult$Status:a	()Z
    //   3182: ifne +3922 -> 7104
    //   3185: new 90	java/lang/StringBuilder
    //   3188: dup
    //   3189: invokespecial 93	java/lang/StringBuilder:<init>	()V
    //   3192: ldc_w 379
    //   3195: invokevirtual 99	java/lang/StringBuilder:append	(Ljava/lang/String;)Ljava/lang/StringBuilder;
    //   3198: aload_0
    //   3199: invokevirtual 68	com/tencent/component/network/downloader/impl/e:a	()Ljava/lang/String;
    //   3202: invokevirtual 99	java/lang/StringBuilder:append	(Ljava/lang/String;)Ljava/lang/StringBuilder;
    //   3205: ldc_w 381
    //   3208: invokevirtual 99	java/lang/StringBuilder:append	(Ljava/lang/String;)Ljava/lang/StringBuilder;
    //   3211: aload 22
    //   3213: invokevirtual 384	java/lang/StringBuilder:append	(Ljava/lang/Object;)Ljava/lang/StringBuilder;
    //   3216: ldc_w 386
    //   3219: invokevirtual 99	java/lang/StringBuilder:append	(Ljava/lang/String;)Ljava/lang/StringBuilder;
    //   3222: aload 20
    //   3224: invokevirtual 99	java/lang/StringBuilder:append	(Ljava/lang/String;)Ljava/lang/StringBuilder;
    //   3227: ldc_w 388
    //   3230: invokevirtual 99	java/lang/StringBuilder:append	(Ljava/lang/String;)Ljava/lang/StringBuilder;
    //   3233: aload 21
    //   3235: invokevirtual 99	java/lang/StringBuilder:append	(Ljava/lang/String;)Ljava/lang/StringBuilder;
    //   3238: ldc_w 390
    //   3241: invokevirtual 99	java/lang/StringBuilder:append	(Ljava/lang/String;)Ljava/lang/StringBuilder;
    //   3244: invokestatic 133	java/lang/Thread:currentThread	()Ljava/lang/Thread;
    //   3247: invokevirtual 136	java/lang/Thread:getId	()J
    //   3250: invokevirtual 139	java/lang/StringBuilder:append	(J)Ljava/lang/StringBuilder;
    //   3253: ldc_w 392
    //   3256: invokevirtual 99	java/lang/StringBuilder:append	(Ljava/lang/String;)Ljava/lang/StringBuilder;
    //   3259: invokestatic 121	com/tencent/component/network/NetworkManager:a	()Ljava/lang/String;
    //   3262: invokevirtual 99	java/lang/StringBuilder:append	(Ljava/lang/String;)Ljava/lang/StringBuilder;
    //   3265: ldc_w 394
    //   3268: invokevirtual 99	java/lang/StringBuilder:append	(Ljava/lang/String;)Ljava/lang/StringBuilder;
    //   3271: aload_0
    //   3272: getfield 146	com/tencent/component/network/downloader/impl/e:jdField_a_of_type_Boolean	Z
    //   3275: invokevirtual 397	java/lang/StringBuilder:append	(Z)Ljava/lang/StringBuilder;
    //   3278: ldc_w 399
    //   3281: invokevirtual 99	java/lang/StringBuilder:append	(Ljava/lang/String;)Ljava/lang/StringBuilder;
    //   3284: aload_0
    //   3285: getfield 149	com/tencent/component/network/downloader/impl/e:jdField_b_of_type_Boolean	Z
    //   3288: invokevirtual 397	java/lang/StringBuilder:append	(Z)Ljava/lang/StringBuilder;
    //   3291: ldc_w 401
    //   3294: invokevirtual 99	java/lang/StringBuilder:append	(Ljava/lang/String;)Ljava/lang/StringBuilder;
    //   3297: astore 23
    //   3299: aload_0
    //   3300: getfield 146	com/tencent/component/network/downloader/impl/e:jdField_a_of_type_Boolean	Z
    //   3303: ifeq +4354 -> 7657
    //   3306: aload_0
    //   3307: getfield 61	com/tencent/component/network/downloader/impl/e:jdField_a_of_type_AndroidContentContext	Landroid/content/Context;
    //   3310: aload_0
    //   3311: getfield 149	com/tencent/component/network/downloader/impl/e:jdField_b_of_type_Boolean	Z
    //   3314: invokestatic 249	com/tencent/component/network/utils/NetworkUtils:a	(Landroid/content/Context;Z)Lcom/tencent/component/network/utils/NetworkUtils$NetworkProxy;
    //   3317: astore 20
    //   3319: aload 23
    //   3321: aload 20
    //   3323: invokevirtual 384	java/lang/StringBuilder:append	(Ljava/lang/Object;)Ljava/lang/StringBuilder;
    //   3326: ldc_w 403
    //   3329: invokevirtual 99	java/lang/StringBuilder:append	(Ljava/lang/String;)Ljava/lang/StringBuilder;
    //   3332: aload_0
    //   3333: getfield 61	com/tencent/component/network/downloader/impl/e:jdField_a_of_type_AndroidContentContext	Landroid/content/Context;
    //   3336: invokestatic 298	com/tencent/component/network/utils/NetworkUtils:a	(Landroid/content/Context;)Z
    //   3339: invokevirtual 397	java/lang/StringBuilder:append	(Z)Ljava/lang/StringBuilder;
    //   3342: ldc_w 405
    //   3345: invokevirtual 99	java/lang/StringBuilder:append	(Ljava/lang/String;)Ljava/lang/StringBuilder;
    //   3348: aload_2
    //   3349: invokevirtual 367	com/tencent/component/network/downloader/DownloadResult:a	()Lcom/tencent/component/network/downloader/DownloadResult$Content;
    //   3352: getfield 406	com/tencent/component/network/downloader/DownloadResult$Content:jdField_a_of_type_JavaLangString	Ljava/lang/String;
    //   3355: invokevirtual 99	java/lang/StringBuilder:append	(Ljava/lang/String;)Ljava/lang/StringBuilder;
    //   3358: ldc_w 408
    //   3361: invokevirtual 99	java/lang/StringBuilder:append	(Ljava/lang/String;)Ljava/lang/StringBuilder;
    //   3364: aload_2
    //   3365: invokevirtual 336	com/tencent/component/network/downloader/DownloadResult:a	()Lcom/tencent/component/network/downloader/DownloadResult$Process;
    //   3368: getfield 409	com/tencent/component/network/downloader/DownloadResult$Process:jdField_c_of_type_Long	J
    //   3371: invokevirtual 139	java/lang/StringBuilder:append	(J)Ljava/lang/StringBuilder;
    //   3374: ldc_w 411
    //   3377: invokevirtual 99	java/lang/StringBuilder:append	(Ljava/lang/String;)Ljava/lang/StringBuilder;
    //   3380: invokestatic 28	android/os/SystemClock:uptimeMillis	()J
    //   3383: aload_0
    //   3384: getfield 30	com/tencent/component/network/downloader/impl/e:jdField_i_of_type_Long	J
    //   3387: lsub
    //   3388: invokevirtual 139	java/lang/StringBuilder:append	(J)Ljava/lang/StringBuilder;
    //   3391: ldc_w 413
    //   3394: invokevirtual 99	java/lang/StringBuilder:append	(Ljava/lang/String;)Ljava/lang/StringBuilder;
    //   3397: aload_2
    //   3398: invokevirtual 367	com/tencent/component/network/downloader/DownloadResult:a	()Lcom/tencent/component/network/downloader/DownloadResult$Content;
    //   3401: getfield 414	com/tencent/component/network/downloader/DownloadResult$Content:jdField_a_of_type_Long	J
    //   3404: invokevirtual 139	java/lang/StringBuilder:append	(J)Ljava/lang/StringBuilder;
    //   3407: ldc_w 373
    //   3410: invokevirtual 99	java/lang/StringBuilder:append	(Ljava/lang/String;)Ljava/lang/StringBuilder;
    //   3413: aload_2
    //   3414: invokevirtual 367	com/tencent/component/network/downloader/DownloadResult:a	()Lcom/tencent/component/network/downloader/DownloadResult$Content;
    //   3417: getfield 371	com/tencent/component/network/downloader/DownloadResult$Content:jdField_b_of_type_Long	J
    //   3420: invokevirtual 139	java/lang/StringBuilder:append	(J)Ljava/lang/StringBuilder;
    //   3423: ldc_w 416
    //   3426: invokevirtual 99	java/lang/StringBuilder:append	(Ljava/lang/String;)Ljava/lang/StringBuilder;
    //   3429: ldc_w 418
    //   3432: invokevirtual 99	java/lang/StringBuilder:append	(Ljava/lang/String;)Ljava/lang/StringBuilder;
    //   3435: aload_2
    //   3436: invokevirtual 367	com/tencent/component/network/downloader/DownloadResult:a	()Lcom/tencent/component/network/downloader/DownloadResult$Content;
    //   3439: getfield 419	com/tencent/component/network/downloader/DownloadResult$Content:jdField_c_of_type_Long	J
    //   3442: invokevirtual 139	java/lang/StringBuilder:append	(J)Ljava/lang/StringBuilder;
    //   3445: ldc_w 421
    //   3448: invokevirtual 99	java/lang/StringBuilder:append	(Ljava/lang/String;)Ljava/lang/StringBuilder;
    //   3451: aload_0
    //   3452: invokevirtual 325	com/tencent/component/network/downloader/impl/e:b	()I
    //   3455: invokevirtual 109	java/lang/StringBuilder:append	(I)Ljava/lang/StringBuilder;
    //   3458: ldc_w 373
    //   3461: invokevirtual 99	java/lang/StringBuilder:append	(Ljava/lang/String;)Ljava/lang/StringBuilder;
    //   3464: aload_0
    //   3465: invokevirtual 422	com/tencent/component/network/downloader/impl/e:c	()I
    //   3468: invokevirtual 109	java/lang/StringBuilder:append	(I)Ljava/lang/StringBuilder;
    //   3471: ldc_w 416
    //   3474: invokevirtual 99	java/lang/StringBuilder:append	(Ljava/lang/String;)Ljava/lang/StringBuilder;
    //   3477: ldc_w 424
    //   3480: invokevirtual 99	java/lang/StringBuilder:append	(Ljava/lang/String;)Ljava/lang/StringBuilder;
    //   3483: aload_2
    //   3484: invokevirtual 303	com/tencent/component/network/downloader/DownloadResult:a	()Lcom/tencent/component/network/downloader/DownloadResult$Status;
    //   3487: invokevirtual 425	com/tencent/component/network/downloader/DownloadResult$Status:a	()I
    //   3490: invokevirtual 109	java/lang/StringBuilder:append	(I)Ljava/lang/StringBuilder;
    //   3493: ldc_w 427
    //   3496: invokevirtual 99	java/lang/StringBuilder:append	(Ljava/lang/String;)Ljava/lang/StringBuilder;
    //   3499: iload_3
    //   3500: invokevirtual 109	java/lang/StringBuilder:append	(I)Ljava/lang/StringBuilder;
    //   3503: ldc_w 429
    //   3506: invokevirtual 99	java/lang/StringBuilder:append	(Ljava/lang/String;)Ljava/lang/StringBuilder;
    //   3509: aload_0
    //   3510: getfield 430	com/tencent/component/network/downloader/impl/e:jdField_a_of_type_JavaLangString	Ljava/lang/String;
    //   3513: invokevirtual 99	java/lang/StringBuilder:append	(Ljava/lang/String;)Ljava/lang/StringBuilder;
    //   3516: ldc_w 432
    //   3519: invokevirtual 99	java/lang/StringBuilder:append	(Ljava/lang/String;)Ljava/lang/StringBuilder;
    //   3522: astore 20
    //   3524: aload_0
    //   3525: getfield 74	com/tencent/component/network/downloader/impl/e:jdField_b_of_type_ComTencentComponentNetworkDownloaderStrategyDownloadGlobalStrategy$StrategyInfo	Lcom/tencent/component/network/downloader/strategy/DownloadGlobalStrategy$StrategyInfo;
    //   3528: ifnull +4135 -> 7663
    //   3531: aload_0
    //   3532: getfield 74	com/tencent/component/network/downloader/impl/e:jdField_b_of_type_ComTencentComponentNetworkDownloaderStrategyDownloadGlobalStrategy$StrategyInfo	Lcom/tencent/component/network/downloader/strategy/DownloadGlobalStrategy$StrategyInfo;
    //   3535: getfield 162	com/tencent/component/network/downloader/strategy/DownloadGlobalStrategy$StrategyInfo:jdField_a_of_type_Int	I
    //   3538: istore 4
    //   3540: aload 20
    //   3542: iload 4
    //   3544: invokevirtual 109	java/lang/StringBuilder:append	(I)Ljava/lang/StringBuilder;
    //   3547: ldc_w 434
    //   3550: invokevirtual 99	java/lang/StringBuilder:append	(Ljava/lang/String;)Ljava/lang/StringBuilder;
    //   3553: aload_2
    //   3554: invokevirtual 367	com/tencent/component/network/downloader/DownloadResult:a	()Lcom/tencent/component/network/downloader/DownloadResult$Content;
    //   3557: getfield 435	com/tencent/component/network/downloader/DownloadResult$Content:jdField_c_of_type_JavaLangString	Ljava/lang/String;
    //   3560: invokevirtual 99	java/lang/StringBuilder:append	(Ljava/lang/String;)Ljava/lang/StringBuilder;
    //   3563: ldc_w 437
    //   3566: invokevirtual 99	java/lang/StringBuilder:append	(Ljava/lang/String;)Ljava/lang/StringBuilder;
    //   3569: lload 9
    //   3571: invokevirtual 139	java/lang/StringBuilder:append	(J)Ljava/lang/StringBuilder;
    //   3574: ldc_w 416
    //   3577: invokevirtual 99	java/lang/StringBuilder:append	(Ljava/lang/String;)Ljava/lang/StringBuilder;
    //   3580: ldc_w 439
    //   3583: invokevirtual 99	java/lang/StringBuilder:append	(Ljava/lang/String;)Ljava/lang/StringBuilder;
    //   3586: aload_0
    //   3587: getfield 38	com/tencent/component/network/downloader/impl/e:jdField_d_of_type_Long	J
    //   3590: invokevirtual 139	java/lang/StringBuilder:append	(J)Ljava/lang/StringBuilder;
    //   3593: ldc_w 373
    //   3596: invokevirtual 99	java/lang/StringBuilder:append	(Ljava/lang/String;)Ljava/lang/StringBuilder;
    //   3599: aload_0
    //   3600: getfield 40	com/tencent/component/network/downloader/impl/e:jdField_c_of_type_Int	I
    //   3603: invokevirtual 109	java/lang/StringBuilder:append	(I)Ljava/lang/StringBuilder;
    //   3606: ldc_w 416
    //   3609: invokevirtual 99	java/lang/StringBuilder:append	(Ljava/lang/String;)Ljava/lang/StringBuilder;
    //   3612: ldc_w 441
    //   3615: invokevirtual 99	java/lang/StringBuilder:append	(Ljava/lang/String;)Ljava/lang/StringBuilder;
    //   3618: aload_0
    //   3619: getfield 42	com/tencent/component/network/downloader/impl/e:jdField_e_of_type_Long	J
    //   3622: invokevirtual 139	java/lang/StringBuilder:append	(J)Ljava/lang/StringBuilder;
    //   3625: ldc_w 373
    //   3628: invokevirtual 99	java/lang/StringBuilder:append	(Ljava/lang/String;)Ljava/lang/StringBuilder;
    //   3631: aload_0
    //   3632: getfield 44	com/tencent/component/network/downloader/impl/e:jdField_d_of_type_Int	I
    //   3635: invokevirtual 109	java/lang/StringBuilder:append	(I)Ljava/lang/StringBuilder;
    //   3638: ldc_w 416
    //   3641: invokevirtual 99	java/lang/StringBuilder:append	(Ljava/lang/String;)Ljava/lang/StringBuilder;
    //   3644: ldc_w 443
    //   3647: invokevirtual 99	java/lang/StringBuilder:append	(Ljava/lang/String;)Ljava/lang/StringBuilder;
    //   3650: aload_0
    //   3651: getfield 46	com/tencent/component/network/downloader/impl/e:jdField_f_of_type_Long	J
    //   3654: invokevirtual 139	java/lang/StringBuilder:append	(J)Ljava/lang/StringBuilder;
    //   3657: ldc_w 416
    //   3660: invokevirtual 99	java/lang/StringBuilder:append	(Ljava/lang/String;)Ljava/lang/StringBuilder;
    //   3663: ldc_w 445
    //   3666: invokevirtual 99	java/lang/StringBuilder:append	(Ljava/lang/String;)Ljava/lang/StringBuilder;
    //   3669: aload_0
    //   3670: getfield 48	com/tencent/component/network/downloader/impl/e:jdField_g_of_type_Long	J
    //   3673: invokevirtual 139	java/lang/StringBuilder:append	(J)Ljava/lang/StringBuilder;
    //   3676: ldc_w 416
    //   3679: invokevirtual 99	java/lang/StringBuilder:append	(Ljava/lang/String;)Ljava/lang/StringBuilder;
    //   3682: ldc_w 447
    //   3685: invokevirtual 99	java/lang/StringBuilder:append	(Ljava/lang/String;)Ljava/lang/StringBuilder;
    //   3688: aload_0
    //   3689: getfield 36	com/tencent/component/network/downloader/impl/e:jdField_d_of_type_JavaLangString	Ljava/lang/String;
    //   3692: invokevirtual 99	java/lang/StringBuilder:append	(Ljava/lang/String;)Ljava/lang/StringBuilder;
    //   3695: ldc_w 416
    //   3698: invokevirtual 99	java/lang/StringBuilder:append	(Ljava/lang/String;)Ljava/lang/StringBuilder;
    //   3701: ldc_w 449
    //   3704: invokevirtual 99	java/lang/StringBuilder:append	(Ljava/lang/String;)Ljava/lang/StringBuilder;
    //   3707: aload_0
    //   3708: invokevirtual 451	com/tencent/component/network/downloader/impl/e:d	()I
    //   3711: invokevirtual 109	java/lang/StringBuilder:append	(I)Ljava/lang/StringBuilder;
    //   3714: ldc_w 416
    //   3717: invokevirtual 99	java/lang/StringBuilder:append	(Ljava/lang/String;)Ljava/lang/StringBuilder;
    //   3720: ldc_w 453
    //   3723: invokevirtual 99	java/lang/StringBuilder:append	(Ljava/lang/String;)Ljava/lang/StringBuilder;
    //   3726: astore 23
    //   3728: aload_0
    //   3729: getfield 456	com/tencent/component/network/downloader/impl/e:jdField_a_of_type_ComTencentComponentNetworkDownloaderImplA$a	Lcom/tencent/component/network/downloader/impl/a$a;
    //   3732: ifnull +3937 -> 7669
    //   3735: aload_0
    //   3736: getfield 456	com/tencent/component/network/downloader/impl/e:jdField_a_of_type_ComTencentComponentNetworkDownloaderImplA$a	Lcom/tencent/component/network/downloader/impl/a$a;
    //   3739: invokeinterface 461 1 0
    //   3744: astore 20
    //   3746: ldc 88
    //   3748: aload 23
    //   3750: aload 20
    //   3752: invokevirtual 384	java/lang/StringBuilder:append	(Ljava/lang/Object;)Ljava/lang/StringBuilder;
    //   3755: invokevirtual 140	java/lang/StringBuilder:toString	()Ljava/lang/String;
    //   3758: aconst_null
    //   3759: invokestatic 330	com/tencent/component/network/module/base/b:d	(Ljava/lang/String;Ljava/lang/String;Ljava/lang/Throwable;)V
    //   3762: getstatic 160	com/tencent/component/network/downloader/strategy/DownloadGlobalStrategy:d	Lcom/tencent/component/network/downloader/strategy/DownloadGlobalStrategy$StrategyInfo;
    //   3765: getfield 162	com/tencent/component/network/downloader/strategy/DownloadGlobalStrategy$StrategyInfo:jdField_a_of_type_Int	I
    //   3768: aload_0
    //   3769: getfield 74	com/tencent/component/network/downloader/impl/e:jdField_b_of_type_ComTencentComponentNetworkDownloaderStrategyDownloadGlobalStrategy$StrategyInfo	Lcom/tencent/component/network/downloader/strategy/DownloadGlobalStrategy$StrategyInfo;
    //   3772: getfield 162	com/tencent/component/network/downloader/strategy/DownloadGlobalStrategy$StrategyInfo:jdField_a_of_type_Int	I
    //   3775: if_icmpne +37 -> 3812
    //   3778: aload_0
    //   3779: getfield 184	com/tencent/component/network/downloader/impl/e:jdField_b_of_type_ComTencentComponentNetworkDownloaderStrategyIPStrategy	Lcom/tencent/component/network/downloader/strategy/IPStrategy;
    //   3782: ifnull +30 -> 3812
    //   3785: aload_0
    //   3786: getfield 184	com/tencent/component/network/downloader/impl/e:jdField_b_of_type_ComTencentComponentNetworkDownloaderStrategyIPStrategy	Lcom/tencent/component/network/downloader/strategy/IPStrategy;
    //   3789: aload_0
    //   3790: invokevirtual 55	com/tencent/component/network/downloader/impl/e:b	()Ljava/lang/String;
    //   3793: aload_0
    //   3794: getfield 430	com/tencent/component/network/downloader/impl/e:jdField_a_of_type_JavaLangString	Ljava/lang/String;
    //   3797: invokestatic 462	com/tencent/component/network/downloader/common/a:a	(Ljava/lang/String;)Ljava/lang/String;
    //   3800: aload_2
    //   3801: invokevirtual 303	com/tencent/component/network/downloader/DownloadResult:a	()Lcom/tencent/component/network/downloader/DownloadResult$Status;
    //   3804: invokevirtual 353	com/tencent/component/network/downloader/DownloadResult$Status:a	()Z
    //   3807: invokeinterface 465 4 0
    //   3812: getstatic 237	com/tencent/component/network/downloader/strategy/DownloadGlobalStrategy:jdField_a_of_type_ComTencentComponentNetworkDownloaderStrategyDownloadGlobalStrategy$StrategyInfo	Lcom/tencent/component/network/downloader/strategy/DownloadGlobalStrategy$StrategyInfo;
    //   3815: getfield 162	com/tencent/component/network/downloader/strategy/DownloadGlobalStrategy$StrategyInfo:jdField_a_of_type_Int	I
    //   3818: aload_0
    //   3819: getfield 74	com/tencent/component/network/downloader/impl/e:jdField_b_of_type_ComTencentComponentNetworkDownloaderStrategyDownloadGlobalStrategy$StrategyInfo	Lcom/tencent/component/network/downloader/strategy/DownloadGlobalStrategy$StrategyInfo;
    //   3822: getfield 162	com/tencent/component/network/downloader/strategy/DownloadGlobalStrategy$StrategyInfo:jdField_a_of_type_Int	I
    //   3825: if_icmpne +37 -> 3862
    //   3828: aload_0
    //   3829: getfield 239	com/tencent/component/network/downloader/impl/e:jdField_a_of_type_ComTencentComponentNetworkDownloaderStrategyIPStrategy	Lcom/tencent/component/network/downloader/strategy/IPStrategy;
    //   3832: ifnull +30 -> 3862
    //   3835: aload_0
    //   3836: getfield 239	com/tencent/component/network/downloader/impl/e:jdField_a_of_type_ComTencentComponentNetworkDownloaderStrategyIPStrategy	Lcom/tencent/component/network/downloader/strategy/IPStrategy;
    //   3839: aload_0
    //   3840: invokevirtual 55	com/tencent/component/network/downloader/impl/e:b	()Ljava/lang/String;
    //   3843: aload_0
    //   3844: getfield 430	com/tencent/component/network/downloader/impl/e:jdField_a_of_type_JavaLangString	Ljava/lang/String;
    //   3847: invokestatic 462	com/tencent/component/network/downloader/common/a:a	(Ljava/lang/String;)Ljava/lang/String;
    //   3850: aload_2
    //   3851: invokevirtual 303	com/tencent/component/network/downloader/DownloadResult:a	()Lcom/tencent/component/network/downloader/DownloadResult$Status;
    //   3854: invokevirtual 353	com/tencent/component/network/downloader/DownloadResult$Status:a	()Z
    //   3857: invokeinterface 465 4 0
    //   3862: aload 24
    //   3864: invokestatic 319	java/lang/System:currentTimeMillis	()J
    //   3867: putfield 466	com/tencent/component/network/downloader/DownloadReport:jdField_b_of_type_Long	J
    //   3870: aload 24
    //   3872: aload_0
    //   3873: invokevirtual 468	com/tencent/component/network/downloader/impl/e:a	()J
    //   3876: putfield 469	com/tencent/component/network/downloader/DownloadReport:jdField_c_of_type_Long	J
    //   3879: aload 24
    //   3881: aload 19
    //   3883: putfield 472	com/tencent/component/network/downloader/DownloadReport:jdField_a_of_type_OrgApacheHttpHttpResponse	Lorg/apache/http/HttpResponse;
    //   3886: aload 24
    //   3888: iload_3
    //   3889: putfield 474	com/tencent/component/network/downloader/DownloadReport:jdField_b_of_type_Int	I
    //   3892: aload 24
    //   3894: aconst_null
    //   3895: putfield 477	com/tencent/component/network/downloader/DownloadReport:jdField_a_of_type_JavaLangThrowable	Ljava/lang/Throwable;
    //   3898: aload 22
    //   3900: ifnonnull +3823 -> 7723
    //   3903: aconst_null
    //   3904: astore 19
    //   3906: aload 24
    //   3908: aload 19
    //   3910: putfield 478	com/tencent/component/network/downloader/DownloadReport:jdField_b_of_type_JavaLangString	Ljava/lang/String;
    //   3913: aload 18
    //   3915: iconst_1
    //   3916: invokestatic 480	cug:b	(Lorg/apache/http/protocol/HttpContext;Z)Ljava/lang/String;
    //   3919: astore 18
    //   3921: aload 18
    //   3923: invokestatic 201	android/text/TextUtils:isEmpty	(Ljava/lang/CharSequence;)Z
    //   3926: ifne +10 -> 3936
    //   3929: aload 24
    //   3931: aload 18
    //   3933: putfield 481	com/tencent/component/network/downloader/DownloadReport:jdField_c_of_type_JavaLangString	Ljava/lang/String;
    //   3936: aload 24
    //   3938: aload 21
    //   3940: putfield 482	com/tencent/component/network/downloader/DownloadReport:jdField_d_of_type_JavaLangString	Ljava/lang/String;
    //   3943: aload 24
    //   3945: aload_2
    //   3946: invokevirtual 367	com/tencent/component/network/downloader/DownloadResult:a	()Lcom/tencent/component/network/downloader/DownloadResult$Content;
    //   3949: getfield 435	com/tencent/component/network/downloader/DownloadResult$Content:jdField_c_of_type_JavaLangString	Ljava/lang/String;
    //   3952: putfield 484	com/tencent/component/network/downloader/DownloadReport:jdField_g_of_type_JavaLangString	Ljava/lang/String;
    //   3955: aload 24
    //   3957: invokestatic 28	android/os/SystemClock:uptimeMillis	()J
    //   3960: aload_0
    //   3961: getfield 30	com/tencent/component/network/downloader/impl/e:jdField_i_of_type_Long	J
    //   3964: lsub
    //   3965: putfield 485	com/tencent/component/network/downloader/DownloadReport:jdField_e_of_type_Long	J
    //   3968: aload 24
    //   3970: invokestatic 28	android/os/SystemClock:uptimeMillis	()J
    //   3973: aload_0
    //   3974: getfield 30	com/tencent/component/network/downloader/impl/e:jdField_i_of_type_Long	J
    //   3977: lsub
    //   3978: aload_2
    //   3979: invokevirtual 336	com/tencent/component/network/downloader/DownloadResult:a	()Lcom/tencent/component/network/downloader/DownloadResult$Process;
    //   3982: getfield 409	com/tencent/component/network/downloader/DownloadResult$Process:jdField_c_of_type_Long	J
    //   3985: lsub
    //   3986: putfield 486	com/tencent/component/network/downloader/DownloadReport:jdField_f_of_type_Long	J
    //   3989: aload 24
    //   3991: lload 9
    //   3993: putfield 487	com/tencent/component/network/downloader/DownloadReport:jdField_g_of_type_Long	J
    //   3996: aload 24
    //   3998: aload_0
    //   3999: getfield 38	com/tencent/component/network/downloader/impl/e:jdField_d_of_type_Long	J
    //   4002: putfield 488	com/tencent/component/network/downloader/DownloadReport:jdField_h_of_type_Long	J
    //   4005: aload 24
    //   4007: aload_0
    //   4008: getfield 48	com/tencent/component/network/downloader/impl/e:jdField_g_of_type_Long	J
    //   4011: putfield 489	com/tencent/component/network/downloader/DownloadReport:jdField_i_of_type_Long	J
    //   4014: aload 24
    //   4016: aload_0
    //   4017: getfield 375	com/tencent/component/network/downloader/impl/e:jdField_c_of_type_Long	J
    //   4020: putfield 492	com/tencent/component/network/downloader/DownloadReport:j	J
    //   4023: aload 24
    //   4025: lconst_0
    //   4026: putfield 495	com/tencent/component/network/downloader/DownloadReport:k	J
    //   4029: aload 24
    //   4031: aload_0
    //   4032: invokevirtual 451	com/tencent/component/network/downloader/impl/e:d	()I
    //   4035: putfield 496	com/tencent/component/network/downloader/DownloadReport:jdField_d_of_type_Int	I
    //   4038: aload 24
    //   4040: aload_2
    //   4041: invokevirtual 367	com/tencent/component/network/downloader/DownloadResult:a	()Lcom/tencent/component/network/downloader/DownloadResult$Content;
    //   4044: getfield 406	com/tencent/component/network/downloader/DownloadResult$Content:jdField_a_of_type_JavaLangString	Ljava/lang/String;
    //   4047: putfield 498	com/tencent/component/network/downloader/DownloadReport:jdField_h_of_type_JavaLangString	Ljava/lang/String;
    //   4050: aload_2
    //   4051: aload 24
    //   4053: invokevirtual 501	com/tencent/component/network/downloader/DownloadResult:a	(Lcom/tencent/component/network/downloader/DownloadReport;)V
    //   4056: aload_0
    //   4057: aload_1
    //   4058: aload_2
    //   4059: aload 24
    //   4061: invokevirtual 295	com/tencent/component/network/downloader/impl/e:a	(Lcom/tencent/component/network/utils/thread/ThreadPool$JobContext;Lcom/tencent/component/network/downloader/DownloadResult;Lcom/tencent/component/network/downloader/DownloadReport;)V
    //   4064: lload 9
    //   4066: lstore 11
    //   4068: iload 5
    //   4070: istore_3
    //   4071: aload_0
    //   4072: getfield 324	com/tencent/component/network/downloader/impl/e:jdField_a_of_type_OrgApacheHttpClientMethodsHttpGet	Lorg/apache/http/client/methods/HttpGet;
    //   4075: ifnull -2749 -> 1326
    //   4078: aload_0
    //   4079: getfield 324	com/tencent/component/network/downloader/impl/e:jdField_a_of_type_OrgApacheHttpClientMethodsHttpGet	Lorg/apache/http/client/methods/HttpGet;
    //   4082: invokevirtual 506	org/apache/http/client/methods/HttpGet:abort	()V
    //   4085: aload_0
    //   4086: aconst_null
    //   4087: putfield 324	com/tencent/component/network/downloader/impl/e:jdField_a_of_type_OrgApacheHttpClientMethodsHttpGet	Lorg/apache/http/client/methods/HttpGet;
    //   4090: lload 9
    //   4092: lstore 11
    //   4094: iload 5
    //   4096: istore_3
    //   4097: goto -2771 -> 1326
    //   4100: aload_2
    //   4101: invokevirtual 303	com/tencent/component/network/downloader/DownloadResult:a	()Lcom/tencent/component/network/downloader/DownloadResult$Status;
    //   4104: iconst_3
    //   4105: invokevirtual 306	com/tencent/component/network/downloader/DownloadResult$Status:a	(I)V
    //   4108: iload 7
    //   4110: istore_3
    //   4111: goto -1113 -> 2998
    //   4114: astore 20
    //   4116: iconst_0
    //   4117: istore_3
    //   4118: goto -3911 -> 207
    //   4121: aconst_null
    //   4122: astore 22
    //   4124: ldc 88
    //   4126: aload 26
    //   4128: aload 22
    //   4130: invokevirtual 384	java/lang/StringBuilder:append	(Ljava/lang/Object;)Ljava/lang/StringBuilder;
    //   4133: invokevirtual 140	java/lang/StringBuilder:toString	()Ljava/lang/String;
    //   4136: aload 19
    //   4138: invokestatic 330	com/tencent/component/network/module/base/b:d	(Ljava/lang/String;Ljava/lang/String;Ljava/lang/Throwable;)V
    //   4141: getstatic 160	com/tencent/component/network/downloader/strategy/DownloadGlobalStrategy:d	Lcom/tencent/component/network/downloader/strategy/DownloadGlobalStrategy$StrategyInfo;
    //   4144: getfield 162	com/tencent/component/network/downloader/strategy/DownloadGlobalStrategy$StrategyInfo:jdField_a_of_type_Int	I
    //   4147: aload_0
    //   4148: getfield 74	com/tencent/component/network/downloader/impl/e:jdField_b_of_type_ComTencentComponentNetworkDownloaderStrategyDownloadGlobalStrategy$StrategyInfo	Lcom/tencent/component/network/downloader/strategy/DownloadGlobalStrategy$StrategyInfo;
    //   4151: getfield 162	com/tencent/component/network/downloader/strategy/DownloadGlobalStrategy$StrategyInfo:jdField_a_of_type_Int	I
    //   4154: if_icmpne +37 -> 4191
    //   4157: aload_0
    //   4158: getfield 184	com/tencent/component/network/downloader/impl/e:jdField_b_of_type_ComTencentComponentNetworkDownloaderStrategyIPStrategy	Lcom/tencent/component/network/downloader/strategy/IPStrategy;
    //   4161: ifnull +30 -> 4191
    //   4164: aload_0
    //   4165: getfield 184	com/tencent/component/network/downloader/impl/e:jdField_b_of_type_ComTencentComponentNetworkDownloaderStrategyIPStrategy	Lcom/tencent/component/network/downloader/strategy/IPStrategy;
    //   4168: aload_0
    //   4169: invokevirtual 55	com/tencent/component/network/downloader/impl/e:b	()Ljava/lang/String;
    //   4172: aload_0
    //   4173: getfield 430	com/tencent/component/network/downloader/impl/e:jdField_a_of_type_JavaLangString	Ljava/lang/String;
    //   4176: invokestatic 462	com/tencent/component/network/downloader/common/a:a	(Ljava/lang/String;)Ljava/lang/String;
    //   4179: aload_2
    //   4180: invokevirtual 303	com/tencent/component/network/downloader/DownloadResult:a	()Lcom/tencent/component/network/downloader/DownloadResult$Status;
    //   4183: invokevirtual 353	com/tencent/component/network/downloader/DownloadResult$Status:a	()Z
    //   4186: invokeinterface 465 4 0
    //   4191: getstatic 237	com/tencent/component/network/downloader/strategy/DownloadGlobalStrategy:jdField_a_of_type_ComTencentComponentNetworkDownloaderStrategyDownloadGlobalStrategy$StrategyInfo	Lcom/tencent/component/network/downloader/strategy/DownloadGlobalStrategy$StrategyInfo;
    //   4194: getfield 162	com/tencent/component/network/downloader/strategy/DownloadGlobalStrategy$StrategyInfo:jdField_a_of_type_Int	I
    //   4197: aload_0
    //   4198: getfield 74	com/tencent/component/network/downloader/impl/e:jdField_b_of_type_ComTencentComponentNetworkDownloaderStrategyDownloadGlobalStrategy$StrategyInfo	Lcom/tencent/component/network/downloader/strategy/DownloadGlobalStrategy$StrategyInfo;
    //   4201: getfield 162	com/tencent/component/network/downloader/strategy/DownloadGlobalStrategy$StrategyInfo:jdField_a_of_type_Int	I
    //   4204: if_icmpne +37 -> 4241
    //   4207: aload_0
    //   4208: getfield 239	com/tencent/component/network/downloader/impl/e:jdField_a_of_type_ComTencentComponentNetworkDownloaderStrategyIPStrategy	Lcom/tencent/component/network/downloader/strategy/IPStrategy;
    //   4211: ifnull +30 -> 4241
    //   4214: aload_0
    //   4215: getfield 239	com/tencent/component/network/downloader/impl/e:jdField_a_of_type_ComTencentComponentNetworkDownloaderStrategyIPStrategy	Lcom/tencent/component/network/downloader/strategy/IPStrategy;
    //   4218: aload_0
    //   4219: invokevirtual 55	com/tencent/component/network/downloader/impl/e:b	()Ljava/lang/String;
    //   4222: aload_0
    //   4223: getfield 430	com/tencent/component/network/downloader/impl/e:jdField_a_of_type_JavaLangString	Ljava/lang/String;
    //   4226: invokestatic 462	com/tencent/component/network/downloader/common/a:a	(Ljava/lang/String;)Ljava/lang/String;
    //   4229: aload_2
    //   4230: invokevirtual 303	com/tencent/component/network/downloader/DownloadResult:a	()Lcom/tencent/component/network/downloader/DownloadResult$Status;
    //   4233: invokevirtual 353	com/tencent/component/network/downloader/DownloadResult$Status:a	()Z
    //   4236: invokeinterface 465 4 0
    //   4241: aload 24
    //   4243: invokestatic 319	java/lang/System:currentTimeMillis	()J
    //   4246: putfield 466	com/tencent/component/network/downloader/DownloadReport:jdField_b_of_type_Long	J
    //   4249: aload 24
    //   4251: aload_0
    //   4252: invokevirtual 468	com/tencent/component/network/downloader/impl/e:a	()J
    //   4255: putfield 469	com/tencent/component/network/downloader/DownloadReport:jdField_c_of_type_Long	J
    //   4258: aload 24
    //   4260: aload 21
    //   4262: putfield 472	com/tencent/component/network/downloader/DownloadReport:jdField_a_of_type_OrgApacheHttpHttpResponse	Lorg/apache/http/HttpResponse;
    //   4265: aload 24
    //   4267: iload_3
    //   4268: putfield 474	com/tencent/component/network/downloader/DownloadReport:jdField_b_of_type_Int	I
    //   4271: aload 24
    //   4273: aload 19
    //   4275: putfield 477	com/tencent/component/network/downloader/DownloadReport:jdField_a_of_type_JavaLangThrowable	Ljava/lang/Throwable;
    //   4278: aload 25
    //   4280: ifnonnull +1556 -> 5836
    //   4283: aconst_null
    //   4284: astore 19
    //   4286: aload 24
    //   4288: aload 19
    //   4290: putfield 478	com/tencent/component/network/downloader/DownloadReport:jdField_b_of_type_JavaLangString	Ljava/lang/String;
    //   4293: aload 20
    //   4295: iconst_1
    //   4296: invokestatic 480	cug:b	(Lorg/apache/http/protocol/HttpContext;Z)Ljava/lang/String;
    //   4299: astore 19
    //   4301: aload 19
    //   4303: invokestatic 201	android/text/TextUtils:isEmpty	(Ljava/lang/CharSequence;)Z
    //   4306: ifne +10 -> 4316
    //   4309: aload 24
    //   4311: aload 19
    //   4313: putfield 481	com/tencent/component/network/downloader/DownloadReport:jdField_c_of_type_JavaLangString	Ljava/lang/String;
    //   4316: aload 24
    //   4318: aload 23
    //   4320: putfield 482	com/tencent/component/network/downloader/DownloadReport:jdField_d_of_type_JavaLangString	Ljava/lang/String;
    //   4323: aload 24
    //   4325: aload_2
    //   4326: invokevirtual 367	com/tencent/component/network/downloader/DownloadResult:a	()Lcom/tencent/component/network/downloader/DownloadResult$Content;
    //   4329: getfield 435	com/tencent/component/network/downloader/DownloadResult$Content:jdField_c_of_type_JavaLangString	Ljava/lang/String;
    //   4332: putfield 484	com/tencent/component/network/downloader/DownloadReport:jdField_g_of_type_JavaLangString	Ljava/lang/String;
    //   4335: aload 24
    //   4337: invokestatic 28	android/os/SystemClock:uptimeMillis	()J
    //   4340: aload_0
    //   4341: getfield 30	com/tencent/component/network/downloader/impl/e:jdField_i_of_type_Long	J
    //   4344: lsub
    //   4345: putfield 485	com/tencent/component/network/downloader/DownloadReport:jdField_e_of_type_Long	J
    //   4348: aload 24
    //   4350: invokestatic 28	android/os/SystemClock:uptimeMillis	()J
    //   4353: aload_0
    //   4354: getfield 30	com/tencent/component/network/downloader/impl/e:jdField_i_of_type_Long	J
    //   4357: lsub
    //   4358: aload_2
    //   4359: invokevirtual 336	com/tencent/component/network/downloader/DownloadResult:a	()Lcom/tencent/component/network/downloader/DownloadResult$Process;
    //   4362: getfield 409	com/tencent/component/network/downloader/DownloadResult$Process:jdField_c_of_type_Long	J
    //   4365: lsub
    //   4366: putfield 486	com/tencent/component/network/downloader/DownloadReport:jdField_f_of_type_Long	J
    //   4369: aload 24
    //   4371: lload 9
    //   4373: putfield 487	com/tencent/component/network/downloader/DownloadReport:jdField_g_of_type_Long	J
    //   4376: aload 24
    //   4378: aload_0
    //   4379: getfield 38	com/tencent/component/network/downloader/impl/e:jdField_d_of_type_Long	J
    //   4382: putfield 488	com/tencent/component/network/downloader/DownloadReport:jdField_h_of_type_Long	J
    //   4385: aload 24
    //   4387: aload_0
    //   4388: getfield 48	com/tencent/component/network/downloader/impl/e:jdField_g_of_type_Long	J
    //   4391: putfield 489	com/tencent/component/network/downloader/DownloadReport:jdField_i_of_type_Long	J
    //   4394: aload 24
    //   4396: aload_0
    //   4397: getfield 375	com/tencent/component/network/downloader/impl/e:jdField_c_of_type_Long	J
    //   4400: putfield 492	com/tencent/component/network/downloader/DownloadReport:j	J
    //   4403: aload 24
    //   4405: lconst_0
    //   4406: putfield 495	com/tencent/component/network/downloader/DownloadReport:k	J
    //   4409: aload 24
    //   4411: aload_0
    //   4412: invokevirtual 451	com/tencent/component/network/downloader/impl/e:d	()I
    //   4415: putfield 496	com/tencent/component/network/downloader/DownloadReport:jdField_d_of_type_Int	I
    //   4418: aload 24
    //   4420: aload_2
    //   4421: invokevirtual 367	com/tencent/component/network/downloader/DownloadResult:a	()Lcom/tencent/component/network/downloader/DownloadResult$Content;
    //   4424: getfield 406	com/tencent/component/network/downloader/DownloadResult$Content:jdField_a_of_type_JavaLangString	Ljava/lang/String;
    //   4427: putfield 498	com/tencent/component/network/downloader/DownloadReport:jdField_h_of_type_JavaLangString	Ljava/lang/String;
    //   4430: aload_2
    //   4431: aload 24
    //   4433: invokevirtual 501	com/tencent/component/network/downloader/DownloadResult:a	(Lcom/tencent/component/network/downloader/DownloadReport;)V
    //   4436: aload_0
    //   4437: aload_1
    //   4438: aload_2
    //   4439: aload 24
    //   4441: invokevirtual 295	com/tencent/component/network/downloader/impl/e:a	(Lcom/tencent/component/network/utils/thread/ThreadPool$JobContext;Lcom/tencent/component/network/downloader/DownloadResult;Lcom/tencent/component/network/downloader/DownloadReport;)V
    //   4444: aload_0
    //   4445: getfield 324	com/tencent/component/network/downloader/impl/e:jdField_a_of_type_OrgApacheHttpClientMethodsHttpGet	Lorg/apache/http/client/methods/HttpGet;
    //   4448: ifnull +15 -> 4463
    //   4451: aload_0
    //   4452: getfield 324	com/tencent/component/network/downloader/impl/e:jdField_a_of_type_OrgApacheHttpClientMethodsHttpGet	Lorg/apache/http/client/methods/HttpGet;
    //   4455: invokevirtual 506	org/apache/http/client/methods/HttpGet:abort	()V
    //   4458: aload_0
    //   4459: aconst_null
    //   4460: putfield 324	com/tencent/component/network/downloader/impl/e:jdField_a_of_type_OrgApacheHttpClientMethodsHttpGet	Lorg/apache/http/client/methods/HttpGet;
    //   4463: aload_0
    //   4464: invokevirtual 508	com/tencent/component/network/downloader/impl/e:e	()V
    //   4467: aload 18
    //   4469: athrow
    //   4470: astore 18
    //   4472: aconst_null
    //   4473: astore 19
    //   4475: iload 6
    //   4477: istore_3
    //   4478: aload_2
    //   4479: invokevirtual 336	com/tencent/component/network/downloader/DownloadResult:a	()Lcom/tencent/component/network/downloader/DownloadResult$Process;
    //   4482: lload 11
    //   4484: invokestatic 28	android/os/SystemClock:uptimeMillis	()J
    //   4487: invokevirtual 341	com/tencent/component/network/downloader/DownloadResult$Process:a	(JJ)V
    //   4490: aload_0
    //   4491: getfield 61	com/tencent/component/network/downloader/impl/e:jdField_a_of_type_AndroidContentContext	Landroid/content/Context;
    //   4494: invokestatic 346	com/tencent/component/network/module/common/b:a	(Landroid/content/Context;)Lcom/tencent/component/network/module/common/b;
    //   4497: invokevirtual 349	com/tencent/component/network/module/common/b:a	()Lcom/tencent/component/network/utils/NetworkUtils$DNS;
    //   4500: astore 25
    //   4502: aload 20
    //   4504: iconst_1
    //   4505: invokestatic 352	cug:a	(Lorg/apache/http/protocol/HttpContext;Z)Ljava/lang/String;
    //   4508: astore 22
    //   4510: aload 20
    //   4512: iconst_0
    //   4513: invokestatic 352	cug:a	(Lorg/apache/http/protocol/HttpContext;Z)Ljava/lang/String;
    //   4516: astore 23
    //   4518: aload_0
    //   4519: lconst_0
    //   4520: putfield 38	com/tencent/component/network/downloader/impl/e:jdField_d_of_type_Long	J
    //   4523: aload_0
    //   4524: iconst_0
    //   4525: putfield 40	com/tencent/component/network/downloader/impl/e:jdField_c_of_type_Int	I
    //   4528: aload_0
    //   4529: lconst_0
    //   4530: putfield 42	com/tencent/component/network/downloader/impl/e:jdField_e_of_type_Long	J
    //   4533: aload_0
    //   4534: iconst_0
    //   4535: putfield 44	com/tencent/component/network/downloader/impl/e:jdField_d_of_type_Int	I
    //   4538: aload_0
    //   4539: lconst_0
    //   4540: putfield 46	com/tencent/component/network/downloader/impl/e:jdField_f_of_type_Long	J
    //   4543: aload_0
    //   4544: lconst_0
    //   4545: putfield 48	com/tencent/component/network/downloader/impl/e:jdField_g_of_type_Long	J
    //   4548: aload_2
    //   4549: invokevirtual 303	com/tencent/component/network/downloader/DownloadResult:a	()Lcom/tencent/component/network/downloader/DownloadResult$Status;
    //   4552: invokevirtual 353	com/tencent/component/network/downloader/DownloadResult$Status:a	()Z
    //   4555: ifne +29 -> 4584
    //   4558: aload_0
    //   4559: getfield 356	com/tencent/component/network/downloader/impl/e:jdField_a_of_type_ComTencentComponentNetworkDownloaderStrategyResumeTransfer	Lcom/tencent/component/network/downloader/strategy/ResumeTransfer;
    //   4562: ifnull +22 -> 4584
    //   4565: aload_0
    //   4566: getfield 356	com/tencent/component/network/downloader/impl/e:jdField_a_of_type_ComTencentComponentNetworkDownloaderStrategyResumeTransfer	Lcom/tencent/component/network/downloader/strategy/ResumeTransfer;
    //   4569: aload_0
    //   4570: invokevirtual 68	com/tencent/component/network/downloader/impl/e:a	()Ljava/lang/String;
    //   4573: aload_2
    //   4574: invokevirtual 357	com/tencent/component/network/downloader/DownloadResult:b	()Ljava/lang/String;
    //   4577: aload 21
    //   4579: invokeinterface 362 4 0
    //   4584: aload_1
    //   4585: invokeinterface 292 1 0
    //   4590: ifne -154 -> 4436
    //   4593: aload_0
    //   4594: new 90	java/lang/StringBuilder
    //   4597: dup
    //   4598: invokespecial 93	java/lang/StringBuilder:<init>	()V
    //   4601: aload_0
    //   4602: getfield 36	com/tencent/component/network/downloader/impl/e:jdField_d_of_type_JavaLangString	Ljava/lang/String;
    //   4605: invokevirtual 99	java/lang/StringBuilder:append	(Ljava/lang/String;)Ljava/lang/StringBuilder;
    //   4608: ldc_w 364
    //   4611: invokevirtual 99	java/lang/StringBuilder:append	(Ljava/lang/String;)Ljava/lang/StringBuilder;
    //   4614: aload_2
    //   4615: invokevirtual 367	com/tencent/component/network/downloader/DownloadResult:a	()Lcom/tencent/component/network/downloader/DownloadResult$Content;
    //   4618: getfield 371	com/tencent/component/network/downloader/DownloadResult$Content:jdField_b_of_type_Long	J
    //   4621: invokevirtual 139	java/lang/StringBuilder:append	(J)Ljava/lang/StringBuilder;
    //   4624: ldc_w 373
    //   4627: invokevirtual 99	java/lang/StringBuilder:append	(Ljava/lang/String;)Ljava/lang/StringBuilder;
    //   4630: aload_0
    //   4631: getfield 375	com/tencent/component/network/downloader/impl/e:jdField_c_of_type_Long	J
    //   4634: invokevirtual 139	java/lang/StringBuilder:append	(J)Ljava/lang/StringBuilder;
    //   4637: ldc_w 377
    //   4640: invokevirtual 99	java/lang/StringBuilder:append	(Ljava/lang/String;)Ljava/lang/StringBuilder;
    //   4643: invokevirtual 140	java/lang/StringBuilder:toString	()Ljava/lang/String;
    //   4646: putfield 36	com/tencent/component/network/downloader/impl/e:jdField_d_of_type_JavaLangString	Ljava/lang/String;
    //   4649: aload_2
    //   4650: invokevirtual 303	com/tencent/component/network/downloader/DownloadResult:a	()Lcom/tencent/component/network/downloader/DownloadResult$Status;
    //   4653: invokevirtual 353	com/tencent/component/network/downloader/DownloadResult$Status:a	()Z
    //   4656: ifne +567 -> 5223
    //   4659: new 90	java/lang/StringBuilder
    //   4662: dup
    //   4663: invokespecial 93	java/lang/StringBuilder:<init>	()V
    //   4666: ldc_w 379
    //   4669: invokevirtual 99	java/lang/StringBuilder:append	(Ljava/lang/String;)Ljava/lang/StringBuilder;
    //   4672: aload_0
    //   4673: invokevirtual 68	com/tencent/component/network/downloader/impl/e:a	()Ljava/lang/String;
    //   4676: invokevirtual 99	java/lang/StringBuilder:append	(Ljava/lang/String;)Ljava/lang/StringBuilder;
    //   4679: ldc_w 381
    //   4682: invokevirtual 99	java/lang/StringBuilder:append	(Ljava/lang/String;)Ljava/lang/StringBuilder;
    //   4685: aload 25
    //   4687: invokevirtual 384	java/lang/StringBuilder:append	(Ljava/lang/Object;)Ljava/lang/StringBuilder;
    //   4690: ldc_w 386
    //   4693: invokevirtual 99	java/lang/StringBuilder:append	(Ljava/lang/String;)Ljava/lang/StringBuilder;
    //   4696: aload 22
    //   4698: invokevirtual 99	java/lang/StringBuilder:append	(Ljava/lang/String;)Ljava/lang/StringBuilder;
    //   4701: ldc_w 388
    //   4704: invokevirtual 99	java/lang/StringBuilder:append	(Ljava/lang/String;)Ljava/lang/StringBuilder;
    //   4707: aload 23
    //   4709: invokevirtual 99	java/lang/StringBuilder:append	(Ljava/lang/String;)Ljava/lang/StringBuilder;
    //   4712: ldc_w 390
    //   4715: invokevirtual 99	java/lang/StringBuilder:append	(Ljava/lang/String;)Ljava/lang/StringBuilder;
    //   4718: invokestatic 133	java/lang/Thread:currentThread	()Ljava/lang/Thread;
    //   4721: invokevirtual 136	java/lang/Thread:getId	()J
    //   4724: invokevirtual 139	java/lang/StringBuilder:append	(J)Ljava/lang/StringBuilder;
    //   4727: ldc_w 392
    //   4730: invokevirtual 99	java/lang/StringBuilder:append	(Ljava/lang/String;)Ljava/lang/StringBuilder;
    //   4733: invokestatic 121	com/tencent/component/network/NetworkManager:a	()Ljava/lang/String;
    //   4736: invokevirtual 99	java/lang/StringBuilder:append	(Ljava/lang/String;)Ljava/lang/StringBuilder;
    //   4739: ldc_w 394
    //   4742: invokevirtual 99	java/lang/StringBuilder:append	(Ljava/lang/String;)Ljava/lang/StringBuilder;
    //   4745: aload_0
    //   4746: getfield 146	com/tencent/component/network/downloader/impl/e:jdField_a_of_type_Boolean	Z
    //   4749: invokevirtual 397	java/lang/StringBuilder:append	(Z)Ljava/lang/StringBuilder;
    //   4752: ldc_w 399
    //   4755: invokevirtual 99	java/lang/StringBuilder:append	(Ljava/lang/String;)Ljava/lang/StringBuilder;
    //   4758: aload_0
    //   4759: getfield 149	com/tencent/component/network/downloader/impl/e:jdField_b_of_type_Boolean	Z
    //   4762: invokevirtual 397	java/lang/StringBuilder:append	(Z)Ljava/lang/StringBuilder;
    //   4765: ldc_w 401
    //   4768: invokevirtual 99	java/lang/StringBuilder:append	(Ljava/lang/String;)Ljava/lang/StringBuilder;
    //   4771: astore 26
    //   4773: aload_0
    //   4774: getfield 146	com/tencent/component/network/downloader/impl/e:jdField_a_of_type_Boolean	Z
    //   4777: ifeq +999 -> 5776
    //   4780: aload_0
    //   4781: getfield 61	com/tencent/component/network/downloader/impl/e:jdField_a_of_type_AndroidContentContext	Landroid/content/Context;
    //   4784: aload_0
    //   4785: getfield 149	com/tencent/component/network/downloader/impl/e:jdField_b_of_type_Boolean	Z
    //   4788: invokestatic 249	com/tencent/component/network/utils/NetworkUtils:a	(Landroid/content/Context;Z)Lcom/tencent/component/network/utils/NetworkUtils$NetworkProxy;
    //   4791: astore 22
    //   4793: aload 26
    //   4795: aload 22
    //   4797: invokevirtual 384	java/lang/StringBuilder:append	(Ljava/lang/Object;)Ljava/lang/StringBuilder;
    //   4800: ldc_w 403
    //   4803: invokevirtual 99	java/lang/StringBuilder:append	(Ljava/lang/String;)Ljava/lang/StringBuilder;
    //   4806: aload_0
    //   4807: getfield 61	com/tencent/component/network/downloader/impl/e:jdField_a_of_type_AndroidContentContext	Landroid/content/Context;
    //   4810: invokestatic 298	com/tencent/component/network/utils/NetworkUtils:a	(Landroid/content/Context;)Z
    //   4813: invokevirtual 397	java/lang/StringBuilder:append	(Z)Ljava/lang/StringBuilder;
    //   4816: ldc_w 405
    //   4819: invokevirtual 99	java/lang/StringBuilder:append	(Ljava/lang/String;)Ljava/lang/StringBuilder;
    //   4822: aload_2
    //   4823: invokevirtual 367	com/tencent/component/network/downloader/DownloadResult:a	()Lcom/tencent/component/network/downloader/DownloadResult$Content;
    //   4826: getfield 406	com/tencent/component/network/downloader/DownloadResult$Content:jdField_a_of_type_JavaLangString	Ljava/lang/String;
    //   4829: invokevirtual 99	java/lang/StringBuilder:append	(Ljava/lang/String;)Ljava/lang/StringBuilder;
    //   4832: ldc_w 408
    //   4835: invokevirtual 99	java/lang/StringBuilder:append	(Ljava/lang/String;)Ljava/lang/StringBuilder;
    //   4838: aload_2
    //   4839: invokevirtual 336	com/tencent/component/network/downloader/DownloadResult:a	()Lcom/tencent/component/network/downloader/DownloadResult$Process;
    //   4842: getfield 409	com/tencent/component/network/downloader/DownloadResult$Process:jdField_c_of_type_Long	J
    //   4845: invokevirtual 139	java/lang/StringBuilder:append	(J)Ljava/lang/StringBuilder;
    //   4848: ldc_w 411
    //   4851: invokevirtual 99	java/lang/StringBuilder:append	(Ljava/lang/String;)Ljava/lang/StringBuilder;
    //   4854: invokestatic 28	android/os/SystemClock:uptimeMillis	()J
    //   4857: aload_0
    //   4858: getfield 30	com/tencent/component/network/downloader/impl/e:jdField_i_of_type_Long	J
    //   4861: lsub
    //   4862: invokevirtual 139	java/lang/StringBuilder:append	(J)Ljava/lang/StringBuilder;
    //   4865: ldc_w 413
    //   4868: invokevirtual 99	java/lang/StringBuilder:append	(Ljava/lang/String;)Ljava/lang/StringBuilder;
    //   4871: aload_2
    //   4872: invokevirtual 367	com/tencent/component/network/downloader/DownloadResult:a	()Lcom/tencent/component/network/downloader/DownloadResult$Content;
    //   4875: getfield 414	com/tencent/component/network/downloader/DownloadResult$Content:jdField_a_of_type_Long	J
    //   4878: invokevirtual 139	java/lang/StringBuilder:append	(J)Ljava/lang/StringBuilder;
    //   4881: ldc_w 373
    //   4884: invokevirtual 99	java/lang/StringBuilder:append	(Ljava/lang/String;)Ljava/lang/StringBuilder;
    //   4887: aload_2
    //   4888: invokevirtual 367	com/tencent/component/network/downloader/DownloadResult:a	()Lcom/tencent/component/network/downloader/DownloadResult$Content;
    //   4891: getfield 371	com/tencent/component/network/downloader/DownloadResult$Content:jdField_b_of_type_Long	J
    //   4894: invokevirtual 139	java/lang/StringBuilder:append	(J)Ljava/lang/StringBuilder;
    //   4897: ldc_w 416
    //   4900: invokevirtual 99	java/lang/StringBuilder:append	(Ljava/lang/String;)Ljava/lang/StringBuilder;
    //   4903: ldc_w 418
    //   4906: invokevirtual 99	java/lang/StringBuilder:append	(Ljava/lang/String;)Ljava/lang/StringBuilder;
    //   4909: aload_2
    //   4910: invokevirtual 367	com/tencent/component/network/downloader/DownloadResult:a	()Lcom/tencent/component/network/downloader/DownloadResult$Content;
    //   4913: getfield 419	com/tencent/component/network/downloader/DownloadResult$Content:jdField_c_of_type_Long	J
    //   4916: invokevirtual 139	java/lang/StringBuilder:append	(J)Ljava/lang/StringBuilder;
    //   4919: ldc_w 421
    //   4922: invokevirtual 99	java/lang/StringBuilder:append	(Ljava/lang/String;)Ljava/lang/StringBuilder;
    //   4925: aload_0
    //   4926: invokevirtual 325	com/tencent/component/network/downloader/impl/e:b	()I
    //   4929: invokevirtual 109	java/lang/StringBuilder:append	(I)Ljava/lang/StringBuilder;
    //   4932: ldc_w 373
    //   4935: invokevirtual 99	java/lang/StringBuilder:append	(Ljava/lang/String;)Ljava/lang/StringBuilder;
    //   4938: aload_0
    //   4939: invokevirtual 422	com/tencent/component/network/downloader/impl/e:c	()I
    //   4942: invokevirtual 109	java/lang/StringBuilder:append	(I)Ljava/lang/StringBuilder;
    //   4945: ldc_w 416
    //   4948: invokevirtual 99	java/lang/StringBuilder:append	(Ljava/lang/String;)Ljava/lang/StringBuilder;
    //   4951: ldc_w 424
    //   4954: invokevirtual 99	java/lang/StringBuilder:append	(Ljava/lang/String;)Ljava/lang/StringBuilder;
    //   4957: aload_2
    //   4958: invokevirtual 303	com/tencent/component/network/downloader/DownloadResult:a	()Lcom/tencent/component/network/downloader/DownloadResult$Status;
    //   4961: invokevirtual 425	com/tencent/component/network/downloader/DownloadResult$Status:a	()I
    //   4964: invokevirtual 109	java/lang/StringBuilder:append	(I)Ljava/lang/StringBuilder;
    //   4967: ldc_w 427
    //   4970: invokevirtual 99	java/lang/StringBuilder:append	(Ljava/lang/String;)Ljava/lang/StringBuilder;
    //   4973: iload_3
    //   4974: invokevirtual 109	java/lang/StringBuilder:append	(I)Ljava/lang/StringBuilder;
    //   4977: ldc_w 429
    //   4980: invokevirtual 99	java/lang/StringBuilder:append	(Ljava/lang/String;)Ljava/lang/StringBuilder;
    //   4983: aload_0
    //   4984: getfield 430	com/tencent/component/network/downloader/impl/e:jdField_a_of_type_JavaLangString	Ljava/lang/String;
    //   4987: invokevirtual 99	java/lang/StringBuilder:append	(Ljava/lang/String;)Ljava/lang/StringBuilder;
    //   4990: ldc_w 432
    //   4993: invokevirtual 99	java/lang/StringBuilder:append	(Ljava/lang/String;)Ljava/lang/StringBuilder;
    //   4996: astore 22
    //   4998: aload_0
    //   4999: getfield 74	com/tencent/component/network/downloader/impl/e:jdField_b_of_type_ComTencentComponentNetworkDownloaderStrategyDownloadGlobalStrategy$StrategyInfo	Lcom/tencent/component/network/downloader/strategy/DownloadGlobalStrategy$StrategyInfo;
    //   5002: ifnull +780 -> 5782
    //   5005: aload_0
    //   5006: getfield 74	com/tencent/component/network/downloader/impl/e:jdField_b_of_type_ComTencentComponentNetworkDownloaderStrategyDownloadGlobalStrategy$StrategyInfo	Lcom/tencent/component/network/downloader/strategy/DownloadGlobalStrategy$StrategyInfo;
    //   5009: getfield 162	com/tencent/component/network/downloader/strategy/DownloadGlobalStrategy$StrategyInfo:jdField_a_of_type_Int	I
    //   5012: istore 4
    //   5014: aload 22
    //   5016: iload 4
    //   5018: invokevirtual 109	java/lang/StringBuilder:append	(I)Ljava/lang/StringBuilder;
    //   5021: ldc_w 434
    //   5024: invokevirtual 99	java/lang/StringBuilder:append	(Ljava/lang/String;)Ljava/lang/StringBuilder;
    //   5027: aload_2
    //   5028: invokevirtual 367	com/tencent/component/network/downloader/DownloadResult:a	()Lcom/tencent/component/network/downloader/DownloadResult$Content;
    //   5031: getfield 435	com/tencent/component/network/downloader/DownloadResult$Content:jdField_c_of_type_JavaLangString	Ljava/lang/String;
    //   5034: invokevirtual 99	java/lang/StringBuilder:append	(Ljava/lang/String;)Ljava/lang/StringBuilder;
    //   5037: ldc_w 437
    //   5040: invokevirtual 99	java/lang/StringBuilder:append	(Ljava/lang/String;)Ljava/lang/StringBuilder;
    //   5043: lload 9
    //   5045: invokevirtual 139	java/lang/StringBuilder:append	(J)Ljava/lang/StringBuilder;
    //   5048: ldc_w 416
    //   5051: invokevirtual 99	java/lang/StringBuilder:append	(Ljava/lang/String;)Ljava/lang/StringBuilder;
    //   5054: ldc_w 439
    //   5057: invokevirtual 99	java/lang/StringBuilder:append	(Ljava/lang/String;)Ljava/lang/StringBuilder;
    //   5060: aload_0
    //   5061: getfield 38	com/tencent/component/network/downloader/impl/e:jdField_d_of_type_Long	J
    //   5064: invokevirtual 139	java/lang/StringBuilder:append	(J)Ljava/lang/StringBuilder;
    //   5067: ldc_w 373
    //   5070: invokevirtual 99	java/lang/StringBuilder:append	(Ljava/lang/String;)Ljava/lang/StringBuilder;
    //   5073: aload_0
    //   5074: getfield 40	com/tencent/component/network/downloader/impl/e:jdField_c_of_type_Int	I
    //   5077: invokevirtual 109	java/lang/StringBuilder:append	(I)Ljava/lang/StringBuilder;
    //   5080: ldc_w 416
    //   5083: invokevirtual 99	java/lang/StringBuilder:append	(Ljava/lang/String;)Ljava/lang/StringBuilder;
    //   5086: ldc_w 441
    //   5089: invokevirtual 99	java/lang/StringBuilder:append	(Ljava/lang/String;)Ljava/lang/StringBuilder;
    //   5092: aload_0
    //   5093: getfield 42	com/tencent/component/network/downloader/impl/e:jdField_e_of_type_Long	J
    //   5096: invokevirtual 139	java/lang/StringBuilder:append	(J)Ljava/lang/StringBuilder;
    //   5099: ldc_w 373
    //   5102: invokevirtual 99	java/lang/StringBuilder:append	(Ljava/lang/String;)Ljava/lang/StringBuilder;
    //   5105: aload_0
    //   5106: getfield 44	com/tencent/component/network/downloader/impl/e:jdField_d_of_type_Int	I
    //   5109: invokevirtual 109	java/lang/StringBuilder:append	(I)Ljava/lang/StringBuilder;
    //   5112: ldc_w 416
    //   5115: invokevirtual 99	java/lang/StringBuilder:append	(Ljava/lang/String;)Ljava/lang/StringBuilder;
    //   5118: ldc_w 443
    //   5121: invokevirtual 99	java/lang/StringBuilder:append	(Ljava/lang/String;)Ljava/lang/StringBuilder;
    //   5124: aload_0
    //   5125: getfield 46	com/tencent/component/network/downloader/impl/e:jdField_f_of_type_Long	J
    //   5128: invokevirtual 139	java/lang/StringBuilder:append	(J)Ljava/lang/StringBuilder;
    //   5131: ldc_w 416
    //   5134: invokevirtual 99	java/lang/StringBuilder:append	(Ljava/lang/String;)Ljava/lang/StringBuilder;
    //   5137: ldc_w 445
    //   5140: invokevirtual 99	java/lang/StringBuilder:append	(Ljava/lang/String;)Ljava/lang/StringBuilder;
    //   5143: aload_0
    //   5144: getfield 48	com/tencent/component/network/downloader/impl/e:jdField_g_of_type_Long	J
    //   5147: invokevirtual 139	java/lang/StringBuilder:append	(J)Ljava/lang/StringBuilder;
    //   5150: ldc_w 416
    //   5153: invokevirtual 99	java/lang/StringBuilder:append	(Ljava/lang/String;)Ljava/lang/StringBuilder;
    //   5156: ldc_w 447
    //   5159: invokevirtual 99	java/lang/StringBuilder:append	(Ljava/lang/String;)Ljava/lang/StringBuilder;
    //   5162: aload_0
    //   5163: getfield 36	com/tencent/component/network/downloader/impl/e:jdField_d_of_type_JavaLangString	Ljava/lang/String;
    //   5166: invokevirtual 99	java/lang/StringBuilder:append	(Ljava/lang/String;)Ljava/lang/StringBuilder;
    //   5169: ldc_w 416
    //   5172: invokevirtual 99	java/lang/StringBuilder:append	(Ljava/lang/String;)Ljava/lang/StringBuilder;
    //   5175: ldc_w 449
    //   5178: invokevirtual 99	java/lang/StringBuilder:append	(Ljava/lang/String;)Ljava/lang/StringBuilder;
    //   5181: aload_0
    //   5182: invokevirtual 451	com/tencent/component/network/downloader/impl/e:d	()I
    //   5185: invokevirtual 109	java/lang/StringBuilder:append	(I)Ljava/lang/StringBuilder;
    //   5188: ldc_w 416
    //   5191: invokevirtual 99	java/lang/StringBuilder:append	(Ljava/lang/String;)Ljava/lang/StringBuilder;
    //   5194: ldc_w 453
    //   5197: invokevirtual 99	java/lang/StringBuilder:append	(Ljava/lang/String;)Ljava/lang/StringBuilder;
    //   5200: astore 26
    //   5202: aload_0
    //   5203: getfield 456	com/tencent/component/network/downloader/impl/e:jdField_a_of_type_ComTencentComponentNetworkDownloaderImplA$a	Lcom/tencent/component/network/downloader/impl/a$a;
    //   5206: ifnull -1085 -> 4121
    //   5209: aload_0
    //   5210: getfield 456	com/tencent/component/network/downloader/impl/e:jdField_a_of_type_ComTencentComponentNetworkDownloaderImplA$a	Lcom/tencent/component/network/downloader/impl/a$a;
    //   5213: invokeinterface 461 1 0
    //   5218: astore 22
    //   5220: goto -1096 -> 4124
    //   5223: invokestatic 86	com/tencent/component/network/module/base/b:b	()Z
    //   5226: ifeq -1085 -> 4141
    //   5229: new 90	java/lang/StringBuilder
    //   5232: dup
    //   5233: invokespecial 93	java/lang/StringBuilder:<init>	()V
    //   5236: ldc_w 603
    //   5239: invokevirtual 99	java/lang/StringBuilder:append	(Ljava/lang/String;)Ljava/lang/StringBuilder;
    //   5242: aload_0
    //   5243: invokevirtual 68	com/tencent/component/network/downloader/impl/e:a	()Ljava/lang/String;
    //   5246: invokevirtual 99	java/lang/StringBuilder:append	(Ljava/lang/String;)Ljava/lang/StringBuilder;
    //   5249: ldc_w 381
    //   5252: invokevirtual 99	java/lang/StringBuilder:append	(Ljava/lang/String;)Ljava/lang/StringBuilder;
    //   5255: aload 25
    //   5257: invokevirtual 384	java/lang/StringBuilder:append	(Ljava/lang/Object;)Ljava/lang/StringBuilder;
    //   5260: ldc_w 386
    //   5263: invokevirtual 99	java/lang/StringBuilder:append	(Ljava/lang/String;)Ljava/lang/StringBuilder;
    //   5266: aload 22
    //   5268: invokevirtual 99	java/lang/StringBuilder:append	(Ljava/lang/String;)Ljava/lang/StringBuilder;
    //   5271: ldc_w 388
    //   5274: invokevirtual 99	java/lang/StringBuilder:append	(Ljava/lang/String;)Ljava/lang/StringBuilder;
    //   5277: aload 23
    //   5279: invokevirtual 99	java/lang/StringBuilder:append	(Ljava/lang/String;)Ljava/lang/StringBuilder;
    //   5282: ldc_w 390
    //   5285: invokevirtual 99	java/lang/StringBuilder:append	(Ljava/lang/String;)Ljava/lang/StringBuilder;
    //   5288: invokestatic 133	java/lang/Thread:currentThread	()Ljava/lang/Thread;
    //   5291: invokevirtual 136	java/lang/Thread:getId	()J
    //   5294: invokevirtual 139	java/lang/StringBuilder:append	(J)Ljava/lang/StringBuilder;
    //   5297: ldc_w 392
    //   5300: invokevirtual 99	java/lang/StringBuilder:append	(Ljava/lang/String;)Ljava/lang/StringBuilder;
    //   5303: invokestatic 121	com/tencent/component/network/NetworkManager:a	()Ljava/lang/String;
    //   5306: invokevirtual 99	java/lang/StringBuilder:append	(Ljava/lang/String;)Ljava/lang/StringBuilder;
    //   5309: ldc_w 394
    //   5312: invokevirtual 99	java/lang/StringBuilder:append	(Ljava/lang/String;)Ljava/lang/StringBuilder;
    //   5315: aload_0
    //   5316: getfield 146	com/tencent/component/network/downloader/impl/e:jdField_a_of_type_Boolean	Z
    //   5319: invokevirtual 397	java/lang/StringBuilder:append	(Z)Ljava/lang/StringBuilder;
    //   5322: ldc_w 399
    //   5325: invokevirtual 99	java/lang/StringBuilder:append	(Ljava/lang/String;)Ljava/lang/StringBuilder;
    //   5328: aload_0
    //   5329: getfield 149	com/tencent/component/network/downloader/impl/e:jdField_b_of_type_Boolean	Z
    //   5332: invokevirtual 397	java/lang/StringBuilder:append	(Z)Ljava/lang/StringBuilder;
    //   5335: ldc_w 401
    //   5338: invokevirtual 99	java/lang/StringBuilder:append	(Ljava/lang/String;)Ljava/lang/StringBuilder;
    //   5341: astore 26
    //   5343: aload_0
    //   5344: getfield 146	com/tencent/component/network/downloader/impl/e:jdField_a_of_type_Boolean	Z
    //   5347: ifeq +441 -> 5788
    //   5350: aload_0
    //   5351: getfield 61	com/tencent/component/network/downloader/impl/e:jdField_a_of_type_AndroidContentContext	Landroid/content/Context;
    //   5354: aload_0
    //   5355: getfield 149	com/tencent/component/network/downloader/impl/e:jdField_b_of_type_Boolean	Z
    //   5358: invokestatic 249	com/tencent/component/network/utils/NetworkUtils:a	(Landroid/content/Context;Z)Lcom/tencent/component/network/utils/NetworkUtils$NetworkProxy;
    //   5361: astore 22
    //   5363: aload 26
    //   5365: aload 22
    //   5367: invokevirtual 384	java/lang/StringBuilder:append	(Ljava/lang/Object;)Ljava/lang/StringBuilder;
    //   5370: ldc_w 408
    //   5373: invokevirtual 99	java/lang/StringBuilder:append	(Ljava/lang/String;)Ljava/lang/StringBuilder;
    //   5376: aload_2
    //   5377: invokevirtual 336	com/tencent/component/network/downloader/DownloadResult:a	()Lcom/tencent/component/network/downloader/DownloadResult$Process;
    //   5380: getfield 409	com/tencent/component/network/downloader/DownloadResult$Process:jdField_c_of_type_Long	J
    //   5383: invokevirtual 139	java/lang/StringBuilder:append	(J)Ljava/lang/StringBuilder;
    //   5386: ldc_w 411
    //   5389: invokevirtual 99	java/lang/StringBuilder:append	(Ljava/lang/String;)Ljava/lang/StringBuilder;
    //   5392: invokestatic 28	android/os/SystemClock:uptimeMillis	()J
    //   5395: aload_0
    //   5396: getfield 30	com/tencent/component/network/downloader/impl/e:jdField_i_of_type_Long	J
    //   5399: lsub
    //   5400: invokevirtual 139	java/lang/StringBuilder:append	(J)Ljava/lang/StringBuilder;
    //   5403: ldc_w 413
    //   5406: invokevirtual 99	java/lang/StringBuilder:append	(Ljava/lang/String;)Ljava/lang/StringBuilder;
    //   5409: aload_2
    //   5410: invokevirtual 367	com/tencent/component/network/downloader/DownloadResult:a	()Lcom/tencent/component/network/downloader/DownloadResult$Content;
    //   5413: getfield 414	com/tencent/component/network/downloader/DownloadResult$Content:jdField_a_of_type_Long	J
    //   5416: invokevirtual 139	java/lang/StringBuilder:append	(J)Ljava/lang/StringBuilder;
    //   5419: ldc_w 373
    //   5422: invokevirtual 99	java/lang/StringBuilder:append	(Ljava/lang/String;)Ljava/lang/StringBuilder;
    //   5425: aload_2
    //   5426: invokevirtual 367	com/tencent/component/network/downloader/DownloadResult:a	()Lcom/tencent/component/network/downloader/DownloadResult$Content;
    //   5429: getfield 371	com/tencent/component/network/downloader/DownloadResult$Content:jdField_b_of_type_Long	J
    //   5432: invokevirtual 139	java/lang/StringBuilder:append	(J)Ljava/lang/StringBuilder;
    //   5435: ldc_w 416
    //   5438: invokevirtual 99	java/lang/StringBuilder:append	(Ljava/lang/String;)Ljava/lang/StringBuilder;
    //   5441: ldc_w 418
    //   5444: invokevirtual 99	java/lang/StringBuilder:append	(Ljava/lang/String;)Ljava/lang/StringBuilder;
    //   5447: aload_2
    //   5448: invokevirtual 367	com/tencent/component/network/downloader/DownloadResult:a	()Lcom/tencent/component/network/downloader/DownloadResult$Content;
    //   5451: getfield 419	com/tencent/component/network/downloader/DownloadResult$Content:jdField_c_of_type_Long	J
    //   5454: invokevirtual 139	java/lang/StringBuilder:append	(J)Ljava/lang/StringBuilder;
    //   5457: ldc_w 421
    //   5460: invokevirtual 99	java/lang/StringBuilder:append	(Ljava/lang/String;)Ljava/lang/StringBuilder;
    //   5463: aload_0
    //   5464: invokevirtual 325	com/tencent/component/network/downloader/impl/e:b	()I
    //   5467: invokevirtual 109	java/lang/StringBuilder:append	(I)Ljava/lang/StringBuilder;
    //   5470: ldc_w 373
    //   5473: invokevirtual 99	java/lang/StringBuilder:append	(Ljava/lang/String;)Ljava/lang/StringBuilder;
    //   5476: aload_0
    //   5477: invokevirtual 422	com/tencent/component/network/downloader/impl/e:c	()I
    //   5480: invokevirtual 109	java/lang/StringBuilder:append	(I)Ljava/lang/StringBuilder;
    //   5483: ldc_w 416
    //   5486: invokevirtual 99	java/lang/StringBuilder:append	(Ljava/lang/String;)Ljava/lang/StringBuilder;
    //   5489: ldc_w 427
    //   5492: invokevirtual 99	java/lang/StringBuilder:append	(Ljava/lang/String;)Ljava/lang/StringBuilder;
    //   5495: iload_3
    //   5496: invokevirtual 109	java/lang/StringBuilder:append	(I)Ljava/lang/StringBuilder;
    //   5499: ldc_w 405
    //   5502: invokevirtual 99	java/lang/StringBuilder:append	(Ljava/lang/String;)Ljava/lang/StringBuilder;
    //   5505: aload_2
    //   5506: invokevirtual 367	com/tencent/component/network/downloader/DownloadResult:a	()Lcom/tencent/component/network/downloader/DownloadResult$Content;
    //   5509: getfield 406	com/tencent/component/network/downloader/DownloadResult$Content:jdField_a_of_type_JavaLangString	Ljava/lang/String;
    //   5512: invokevirtual 99	java/lang/StringBuilder:append	(Ljava/lang/String;)Ljava/lang/StringBuilder;
    //   5515: ldc_w 429
    //   5518: invokevirtual 99	java/lang/StringBuilder:append	(Ljava/lang/String;)Ljava/lang/StringBuilder;
    //   5521: aload_0
    //   5522: getfield 430	com/tencent/component/network/downloader/impl/e:jdField_a_of_type_JavaLangString	Ljava/lang/String;
    //   5525: invokevirtual 99	java/lang/StringBuilder:append	(Ljava/lang/String;)Ljava/lang/StringBuilder;
    //   5528: ldc_w 432
    //   5531: invokevirtual 99	java/lang/StringBuilder:append	(Ljava/lang/String;)Ljava/lang/StringBuilder;
    //   5534: astore 22
    //   5536: aload_0
    //   5537: getfield 74	com/tencent/component/network/downloader/impl/e:jdField_b_of_type_ComTencentComponentNetworkDownloaderStrategyDownloadGlobalStrategy$StrategyInfo	Lcom/tencent/component/network/downloader/strategy/DownloadGlobalStrategy$StrategyInfo;
    //   5540: ifnull +254 -> 5794
    //   5543: aload_0
    //   5544: getfield 74	com/tencent/component/network/downloader/impl/e:jdField_b_of_type_ComTencentComponentNetworkDownloaderStrategyDownloadGlobalStrategy$StrategyInfo	Lcom/tencent/component/network/downloader/strategy/DownloadGlobalStrategy$StrategyInfo;
    //   5547: getfield 162	com/tencent/component/network/downloader/strategy/DownloadGlobalStrategy$StrategyInfo:jdField_a_of_type_Int	I
    //   5550: istore 4
    //   5552: aload 22
    //   5554: iload 4
    //   5556: invokevirtual 109	java/lang/StringBuilder:append	(I)Ljava/lang/StringBuilder;
    //   5559: ldc_w 434
    //   5562: invokevirtual 99	java/lang/StringBuilder:append	(Ljava/lang/String;)Ljava/lang/StringBuilder;
    //   5565: aload_2
    //   5566: invokevirtual 367	com/tencent/component/network/downloader/DownloadResult:a	()Lcom/tencent/component/network/downloader/DownloadResult$Content;
    //   5569: getfield 435	com/tencent/component/network/downloader/DownloadResult$Content:jdField_c_of_type_JavaLangString	Ljava/lang/String;
    //   5572: invokevirtual 99	java/lang/StringBuilder:append	(Ljava/lang/String;)Ljava/lang/StringBuilder;
    //   5575: ldc_w 437
    //   5578: invokevirtual 99	java/lang/StringBuilder:append	(Ljava/lang/String;)Ljava/lang/StringBuilder;
    //   5581: lload 9
    //   5583: invokevirtual 139	java/lang/StringBuilder:append	(J)Ljava/lang/StringBuilder;
    //   5586: ldc_w 416
    //   5589: invokevirtual 99	java/lang/StringBuilder:append	(Ljava/lang/String;)Ljava/lang/StringBuilder;
    //   5592: ldc_w 439
    //   5595: invokevirtual 99	java/lang/StringBuilder:append	(Ljava/lang/String;)Ljava/lang/StringBuilder;
    //   5598: aload_0
    //   5599: getfield 38	com/tencent/component/network/downloader/impl/e:jdField_d_of_type_Long	J
    //   5602: invokevirtual 139	java/lang/StringBuilder:append	(J)Ljava/lang/StringBuilder;
    //   5605: ldc_w 373
    //   5608: invokevirtual 99	java/lang/StringBuilder:append	(Ljava/lang/String;)Ljava/lang/StringBuilder;
    //   5611: aload_0
    //   5612: getfield 40	com/tencent/component/network/downloader/impl/e:jdField_c_of_type_Int	I
    //   5615: invokevirtual 109	java/lang/StringBuilder:append	(I)Ljava/lang/StringBuilder;
    //   5618: ldc_w 416
    //   5621: invokevirtual 99	java/lang/StringBuilder:append	(Ljava/lang/String;)Ljava/lang/StringBuilder;
    //   5624: ldc_w 441
    //   5627: invokevirtual 99	java/lang/StringBuilder:append	(Ljava/lang/String;)Ljava/lang/StringBuilder;
    //   5630: aload_0
    //   5631: getfield 42	com/tencent/component/network/downloader/impl/e:jdField_e_of_type_Long	J
    //   5634: invokevirtual 139	java/lang/StringBuilder:append	(J)Ljava/lang/StringBuilder;
    //   5637: ldc_w 373
    //   5640: invokevirtual 99	java/lang/StringBuilder:append	(Ljava/lang/String;)Ljava/lang/StringBuilder;
    //   5643: aload_0
    //   5644: getfield 44	com/tencent/component/network/downloader/impl/e:jdField_d_of_type_Int	I
    //   5647: invokevirtual 109	java/lang/StringBuilder:append	(I)Ljava/lang/StringBuilder;
    //   5650: ldc_w 416
    //   5653: invokevirtual 99	java/lang/StringBuilder:append	(Ljava/lang/String;)Ljava/lang/StringBuilder;
    //   5656: ldc_w 443
    //   5659: invokevirtual 99	java/lang/StringBuilder:append	(Ljava/lang/String;)Ljava/lang/StringBuilder;
    //   5662: aload_0
    //   5663: getfield 46	com/tencent/component/network/downloader/impl/e:jdField_f_of_type_Long	J
    //   5666: invokevirtual 139	java/lang/StringBuilder:append	(J)Ljava/lang/StringBuilder;
    //   5669: ldc_w 416
    //   5672: invokevirtual 99	java/lang/StringBuilder:append	(Ljava/lang/String;)Ljava/lang/StringBuilder;
    //   5675: ldc_w 445
    //   5678: invokevirtual 99	java/lang/StringBuilder:append	(Ljava/lang/String;)Ljava/lang/StringBuilder;
    //   5681: aload_0
    //   5682: getfield 48	com/tencent/component/network/downloader/impl/e:jdField_g_of_type_Long	J
    //   5685: invokevirtual 139	java/lang/StringBuilder:append	(J)Ljava/lang/StringBuilder;
    //   5688: ldc_w 416
    //   5691: invokevirtual 99	java/lang/StringBuilder:append	(Ljava/lang/String;)Ljava/lang/StringBuilder;
    //   5694: ldc_w 447
    //   5697: invokevirtual 99	java/lang/StringBuilder:append	(Ljava/lang/String;)Ljava/lang/StringBuilder;
    //   5700: aload_0
    //   5701: getfield 36	com/tencent/component/network/downloader/impl/e:jdField_d_of_type_JavaLangString	Ljava/lang/String;
    //   5704: invokevirtual 99	java/lang/StringBuilder:append	(Ljava/lang/String;)Ljava/lang/StringBuilder;
    //   5707: ldc_w 416
    //   5710: invokevirtual 99	java/lang/StringBuilder:append	(Ljava/lang/String;)Ljava/lang/StringBuilder;
    //   5713: ldc_w 449
    //   5716: invokevirtual 99	java/lang/StringBuilder:append	(Ljava/lang/String;)Ljava/lang/StringBuilder;
    //   5719: aload_0
    //   5720: invokevirtual 451	com/tencent/component/network/downloader/impl/e:d	()I
    //   5723: invokevirtual 109	java/lang/StringBuilder:append	(I)Ljava/lang/StringBuilder;
    //   5726: ldc_w 416
    //   5729: invokevirtual 99	java/lang/StringBuilder:append	(Ljava/lang/String;)Ljava/lang/StringBuilder;
    //   5732: ldc_w 453
    //   5735: invokevirtual 99	java/lang/StringBuilder:append	(Ljava/lang/String;)Ljava/lang/StringBuilder;
    //   5738: astore 26
    //   5740: aload_0
    //   5741: getfield 456	com/tencent/component/network/downloader/impl/e:jdField_a_of_type_ComTencentComponentNetworkDownloaderImplA$a	Lcom/tencent/component/network/downloader/impl/a$a;
    //   5744: ifnull +56 -> 5800
    //   5747: aload_0
    //   5748: getfield 456	com/tencent/component/network/downloader/impl/e:jdField_a_of_type_ComTencentComponentNetworkDownloaderImplA$a	Lcom/tencent/component/network/downloader/impl/a$a;
    //   5751: invokeinterface 461 1 0
    //   5756: astore 22
    //   5758: ldc 88
    //   5760: aload 26
    //   5762: aload 22
    //   5764: invokevirtual 384	java/lang/StringBuilder:append	(Ljava/lang/Object;)Ljava/lang/StringBuilder;
    //   5767: invokevirtual 140	java/lang/StringBuilder:toString	()Ljava/lang/String;
    //   5770: invokestatic 143	com/tencent/component/network/module/base/b:b	(Ljava/lang/String;Ljava/lang/String;)V
    //   5773: goto -1632 -> 4141
    //   5776: aconst_null
    //   5777: astore 22
    //   5779: goto -986 -> 4793
    //   5782: iconst_0
    //   5783: istore 4
    //   5785: goto -771 -> 5014
    //   5788: aconst_null
    //   5789: astore 22
    //   5791: goto -428 -> 5363
    //   5794: iconst_0
    //   5795: istore 4
    //   5797: goto -245 -> 5552
    //   5800: aconst_null
    //   5801: astore 22
    //   5803: goto -45 -> 5758
    //   5806: astore 22
    //   5808: ldc 88
    //   5810: ldc_w 605
    //   5813: aload 22
    //   5815: invokestatic 607	com/tencent/component/network/module/base/b:c	(Ljava/lang/String;Ljava/lang/String;Ljava/lang/Throwable;)V
    //   5818: goto -1627 -> 4191
    //   5821: astore 22
    //   5823: ldc 88
    //   5825: ldc_w 609
    //   5828: aload 22
    //   5830: invokestatic 607	com/tencent/component/network/module/base/b:c	(Ljava/lang/String;Ljava/lang/String;Ljava/lang/Throwable;)V
    //   5833: goto -1592 -> 4241
    //   5836: aload 25
    //   5838: invokevirtual 612	com/tencent/component/network/utils/NetworkUtils$DNS:toString	()Ljava/lang/String;
    //   5841: astore 19
    //   5843: goto -1557 -> 4286
    //   5846: invokestatic 86	com/tencent/component/network/module/base/b:b	()Z
    //   5849: ifeq -4859 -> 990
    //   5852: new 90	java/lang/StringBuilder
    //   5855: dup
    //   5856: invokespecial 93	java/lang/StringBuilder:<init>	()V
    //   5859: ldc_w 603
    //   5862: invokevirtual 99	java/lang/StringBuilder:append	(Ljava/lang/String;)Ljava/lang/StringBuilder;
    //   5865: aload_0
    //   5866: invokevirtual 68	com/tencent/component/network/downloader/impl/e:a	()Ljava/lang/String;
    //   5869: invokevirtual 99	java/lang/StringBuilder:append	(Ljava/lang/String;)Ljava/lang/StringBuilder;
    //   5872: ldc_w 381
    //   5875: invokevirtual 99	java/lang/StringBuilder:append	(Ljava/lang/String;)Ljava/lang/StringBuilder;
    //   5878: aload 23
    //   5880: invokevirtual 384	java/lang/StringBuilder:append	(Ljava/lang/Object;)Ljava/lang/StringBuilder;
    //   5883: ldc_w 386
    //   5886: invokevirtual 99	java/lang/StringBuilder:append	(Ljava/lang/String;)Ljava/lang/StringBuilder;
    //   5889: aload 21
    //   5891: invokevirtual 99	java/lang/StringBuilder:append	(Ljava/lang/String;)Ljava/lang/StringBuilder;
    //   5894: ldc_w 388
    //   5897: invokevirtual 99	java/lang/StringBuilder:append	(Ljava/lang/String;)Ljava/lang/StringBuilder;
    //   5900: aload 22
    //   5902: invokevirtual 99	java/lang/StringBuilder:append	(Ljava/lang/String;)Ljava/lang/StringBuilder;
    //   5905: ldc_w 390
    //   5908: invokevirtual 99	java/lang/StringBuilder:append	(Ljava/lang/String;)Ljava/lang/StringBuilder;
    //   5911: invokestatic 133	java/lang/Thread:currentThread	()Ljava/lang/Thread;
    //   5914: invokevirtual 136	java/lang/Thread:getId	()J
    //   5917: invokevirtual 139	java/lang/StringBuilder:append	(J)Ljava/lang/StringBuilder;
    //   5920: ldc_w 392
    //   5923: invokevirtual 99	java/lang/StringBuilder:append	(Ljava/lang/String;)Ljava/lang/StringBuilder;
    //   5926: invokestatic 121	com/tencent/component/network/NetworkManager:a	()Ljava/lang/String;
    //   5929: invokevirtual 99	java/lang/StringBuilder:append	(Ljava/lang/String;)Ljava/lang/StringBuilder;
    //   5932: ldc_w 394
    //   5935: invokevirtual 99	java/lang/StringBuilder:append	(Ljava/lang/String;)Ljava/lang/StringBuilder;
    //   5938: aload_0
    //   5939: getfield 146	com/tencent/component/network/downloader/impl/e:jdField_a_of_type_Boolean	Z
    //   5942: invokevirtual 397	java/lang/StringBuilder:append	(Z)Ljava/lang/StringBuilder;
    //   5945: ldc_w 399
    //   5948: invokevirtual 99	java/lang/StringBuilder:append	(Ljava/lang/String;)Ljava/lang/StringBuilder;
    //   5951: aload_0
    //   5952: getfield 149	com/tencent/component/network/downloader/impl/e:jdField_b_of_type_Boolean	Z
    //   5955: invokevirtual 397	java/lang/StringBuilder:append	(Z)Ljava/lang/StringBuilder;
    //   5958: ldc_w 401
    //   5961: invokevirtual 99	java/lang/StringBuilder:append	(Ljava/lang/String;)Ljava/lang/StringBuilder;
    //   5964: astore 25
    //   5966: aload_0
    //   5967: getfield 146	com/tencent/component/network/downloader/impl/e:jdField_a_of_type_Boolean	Z
    //   5970: ifeq +447 -> 6417
    //   5973: aload_0
    //   5974: getfield 61	com/tencent/component/network/downloader/impl/e:jdField_a_of_type_AndroidContentContext	Landroid/content/Context;
    //   5977: aload_0
    //   5978: getfield 149	com/tencent/component/network/downloader/impl/e:jdField_b_of_type_Boolean	Z
    //   5981: invokestatic 249	com/tencent/component/network/utils/NetworkUtils:a	(Landroid/content/Context;Z)Lcom/tencent/component/network/utils/NetworkUtils$NetworkProxy;
    //   5984: astore 21
    //   5986: aload 25
    //   5988: aload 21
    //   5990: invokevirtual 384	java/lang/StringBuilder:append	(Ljava/lang/Object;)Ljava/lang/StringBuilder;
    //   5993: ldc_w 408
    //   5996: invokevirtual 99	java/lang/StringBuilder:append	(Ljava/lang/String;)Ljava/lang/StringBuilder;
    //   5999: aload_2
    //   6000: invokevirtual 336	com/tencent/component/network/downloader/DownloadResult:a	()Lcom/tencent/component/network/downloader/DownloadResult$Process;
    //   6003: getfield 409	com/tencent/component/network/downloader/DownloadResult$Process:jdField_c_of_type_Long	J
    //   6006: invokevirtual 139	java/lang/StringBuilder:append	(J)Ljava/lang/StringBuilder;
    //   6009: ldc_w 411
    //   6012: invokevirtual 99	java/lang/StringBuilder:append	(Ljava/lang/String;)Ljava/lang/StringBuilder;
    //   6015: invokestatic 28	android/os/SystemClock:uptimeMillis	()J
    //   6018: aload_0
    //   6019: getfield 30	com/tencent/component/network/downloader/impl/e:jdField_i_of_type_Long	J
    //   6022: lsub
    //   6023: invokevirtual 139	java/lang/StringBuilder:append	(J)Ljava/lang/StringBuilder;
    //   6026: ldc_w 413
    //   6029: invokevirtual 99	java/lang/StringBuilder:append	(Ljava/lang/String;)Ljava/lang/StringBuilder;
    //   6032: aload_2
    //   6033: invokevirtual 367	com/tencent/component/network/downloader/DownloadResult:a	()Lcom/tencent/component/network/downloader/DownloadResult$Content;
    //   6036: getfield 414	com/tencent/component/network/downloader/DownloadResult$Content:jdField_a_of_type_Long	J
    //   6039: invokevirtual 139	java/lang/StringBuilder:append	(J)Ljava/lang/StringBuilder;
    //   6042: ldc_w 373
    //   6045: invokevirtual 99	java/lang/StringBuilder:append	(Ljava/lang/String;)Ljava/lang/StringBuilder;
    //   6048: aload_2
    //   6049: invokevirtual 367	com/tencent/component/network/downloader/DownloadResult:a	()Lcom/tencent/component/network/downloader/DownloadResult$Content;
    //   6052: getfield 371	com/tencent/component/network/downloader/DownloadResult$Content:jdField_b_of_type_Long	J
    //   6055: invokevirtual 139	java/lang/StringBuilder:append	(J)Ljava/lang/StringBuilder;
    //   6058: ldc_w 416
    //   6061: invokevirtual 99	java/lang/StringBuilder:append	(Ljava/lang/String;)Ljava/lang/StringBuilder;
    //   6064: ldc_w 418
    //   6067: invokevirtual 99	java/lang/StringBuilder:append	(Ljava/lang/String;)Ljava/lang/StringBuilder;
    //   6070: aload_2
    //   6071: invokevirtual 367	com/tencent/component/network/downloader/DownloadResult:a	()Lcom/tencent/component/network/downloader/DownloadResult$Content;
    //   6074: getfield 419	com/tencent/component/network/downloader/DownloadResult$Content:jdField_c_of_type_Long	J
    //   6077: invokevirtual 139	java/lang/StringBuilder:append	(J)Ljava/lang/StringBuilder;
    //   6080: ldc_w 421
    //   6083: invokevirtual 99	java/lang/StringBuilder:append	(Ljava/lang/String;)Ljava/lang/StringBuilder;
    //   6086: aload_0
    //   6087: invokevirtual 325	com/tencent/component/network/downloader/impl/e:b	()I
    //   6090: invokevirtual 109	java/lang/StringBuilder:append	(I)Ljava/lang/StringBuilder;
    //   6093: ldc_w 373
    //   6096: invokevirtual 99	java/lang/StringBuilder:append	(Ljava/lang/String;)Ljava/lang/StringBuilder;
    //   6099: aload_0
    //   6100: invokevirtual 422	com/tencent/component/network/downloader/impl/e:c	()I
    //   6103: invokevirtual 109	java/lang/StringBuilder:append	(I)Ljava/lang/StringBuilder;
    //   6106: ldc_w 416
    //   6109: invokevirtual 99	java/lang/StringBuilder:append	(Ljava/lang/String;)Ljava/lang/StringBuilder;
    //   6112: ldc_w 427
    //   6115: invokevirtual 99	java/lang/StringBuilder:append	(Ljava/lang/String;)Ljava/lang/StringBuilder;
    //   6118: iload_3
    //   6119: invokevirtual 109	java/lang/StringBuilder:append	(I)Ljava/lang/StringBuilder;
    //   6122: ldc_w 405
    //   6125: invokevirtual 99	java/lang/StringBuilder:append	(Ljava/lang/String;)Ljava/lang/StringBuilder;
    //   6128: aload_2
    //   6129: invokevirtual 367	com/tencent/component/network/downloader/DownloadResult:a	()Lcom/tencent/component/network/downloader/DownloadResult$Content;
    //   6132: getfield 406	com/tencent/component/network/downloader/DownloadResult$Content:jdField_a_of_type_JavaLangString	Ljava/lang/String;
    //   6135: invokevirtual 99	java/lang/StringBuilder:append	(Ljava/lang/String;)Ljava/lang/StringBuilder;
    //   6138: ldc_w 429
    //   6141: invokevirtual 99	java/lang/StringBuilder:append	(Ljava/lang/String;)Ljava/lang/StringBuilder;
    //   6144: aload_0
    //   6145: getfield 430	com/tencent/component/network/downloader/impl/e:jdField_a_of_type_JavaLangString	Ljava/lang/String;
    //   6148: invokevirtual 99	java/lang/StringBuilder:append	(Ljava/lang/String;)Ljava/lang/StringBuilder;
    //   6151: ldc_w 432
    //   6154: invokevirtual 99	java/lang/StringBuilder:append	(Ljava/lang/String;)Ljava/lang/StringBuilder;
    //   6157: astore 21
    //   6159: aload_0
    //   6160: getfield 74	com/tencent/component/network/downloader/impl/e:jdField_b_of_type_ComTencentComponentNetworkDownloaderStrategyDownloadGlobalStrategy$StrategyInfo	Lcom/tencent/component/network/downloader/strategy/DownloadGlobalStrategy$StrategyInfo;
    //   6163: ifnull +260 -> 6423
    //   6166: aload_0
    //   6167: getfield 74	com/tencent/component/network/downloader/impl/e:jdField_b_of_type_ComTencentComponentNetworkDownloaderStrategyDownloadGlobalStrategy$StrategyInfo	Lcom/tencent/component/network/downloader/strategy/DownloadGlobalStrategy$StrategyInfo;
    //   6170: getfield 162	com/tencent/component/network/downloader/strategy/DownloadGlobalStrategy$StrategyInfo:jdField_a_of_type_Int	I
    //   6173: istore 4
    //   6175: aload 21
    //   6177: iload 4
    //   6179: invokevirtual 109	java/lang/StringBuilder:append	(I)Ljava/lang/StringBuilder;
    //   6182: ldc_w 434
    //   6185: invokevirtual 99	java/lang/StringBuilder:append	(Ljava/lang/String;)Ljava/lang/StringBuilder;
    //   6188: aload_2
    //   6189: invokevirtual 367	com/tencent/component/network/downloader/DownloadResult:a	()Lcom/tencent/component/network/downloader/DownloadResult$Content;
    //   6192: getfield 435	com/tencent/component/network/downloader/DownloadResult$Content:jdField_c_of_type_JavaLangString	Ljava/lang/String;
    //   6195: invokevirtual 99	java/lang/StringBuilder:append	(Ljava/lang/String;)Ljava/lang/StringBuilder;
    //   6198: ldc_w 437
    //   6201: invokevirtual 99	java/lang/StringBuilder:append	(Ljava/lang/String;)Ljava/lang/StringBuilder;
    //   6204: lload 9
    //   6206: invokevirtual 139	java/lang/StringBuilder:append	(J)Ljava/lang/StringBuilder;
    //   6209: ldc_w 416
    //   6212: invokevirtual 99	java/lang/StringBuilder:append	(Ljava/lang/String;)Ljava/lang/StringBuilder;
    //   6215: ldc_w 439
    //   6218: invokevirtual 99	java/lang/StringBuilder:append	(Ljava/lang/String;)Ljava/lang/StringBuilder;
    //   6221: aload_0
    //   6222: getfield 38	com/tencent/component/network/downloader/impl/e:jdField_d_of_type_Long	J
    //   6225: invokevirtual 139	java/lang/StringBuilder:append	(J)Ljava/lang/StringBuilder;
    //   6228: ldc_w 373
    //   6231: invokevirtual 99	java/lang/StringBuilder:append	(Ljava/lang/String;)Ljava/lang/StringBuilder;
    //   6234: aload_0
    //   6235: getfield 40	com/tencent/component/network/downloader/impl/e:jdField_c_of_type_Int	I
    //   6238: invokevirtual 109	java/lang/StringBuilder:append	(I)Ljava/lang/StringBuilder;
    //   6241: ldc_w 416
    //   6244: invokevirtual 99	java/lang/StringBuilder:append	(Ljava/lang/String;)Ljava/lang/StringBuilder;
    //   6247: ldc_w 441
    //   6250: invokevirtual 99	java/lang/StringBuilder:append	(Ljava/lang/String;)Ljava/lang/StringBuilder;
    //   6253: aload_0
    //   6254: getfield 42	com/tencent/component/network/downloader/impl/e:jdField_e_of_type_Long	J
    //   6257: invokevirtual 139	java/lang/StringBuilder:append	(J)Ljava/lang/StringBuilder;
    //   6260: ldc_w 373
    //   6263: invokevirtual 99	java/lang/StringBuilder:append	(Ljava/lang/String;)Ljava/lang/StringBuilder;
    //   6266: aload_0
    //   6267: getfield 44	com/tencent/component/network/downloader/impl/e:jdField_d_of_type_Int	I
    //   6270: invokevirtual 109	java/lang/StringBuilder:append	(I)Ljava/lang/StringBuilder;
    //   6273: ldc_w 416
    //   6276: invokevirtual 99	java/lang/StringBuilder:append	(Ljava/lang/String;)Ljava/lang/StringBuilder;
    //   6279: ldc_w 443
    //   6282: invokevirtual 99	java/lang/StringBuilder:append	(Ljava/lang/String;)Ljava/lang/StringBuilder;
    //   6285: aload_0
    //   6286: getfield 46	com/tencent/component/network/downloader/impl/e:jdField_f_of_type_Long	J
    //   6289: invokevirtual 139	java/lang/StringBuilder:append	(J)Ljava/lang/StringBuilder;
    //   6292: ldc_w 416
    //   6295: invokevirtual 99	java/lang/StringBuilder:append	(Ljava/lang/String;)Ljava/lang/StringBuilder;
    //   6298: ldc_w 445
    //   6301: invokevirtual 99	java/lang/StringBuilder:append	(Ljava/lang/String;)Ljava/lang/StringBuilder;
    //   6304: aload_0
    //   6305: getfield 48	com/tencent/component/network/downloader/impl/e:jdField_g_of_type_Long	J
    //   6308: invokevirtual 139	java/lang/StringBuilder:append	(J)Ljava/lang/StringBuilder;
    //   6311: ldc_w 416
    //   6314: invokevirtual 99	java/lang/StringBuilder:append	(Ljava/lang/String;)Ljava/lang/StringBuilder;
    //   6317: ldc_w 447
    //   6320: invokevirtual 99	java/lang/StringBuilder:append	(Ljava/lang/String;)Ljava/lang/StringBuilder;
    //   6323: aload_0
    //   6324: getfield 36	com/tencent/component/network/downloader/impl/e:jdField_d_of_type_JavaLangString	Ljava/lang/String;
    //   6327: invokevirtual 99	java/lang/StringBuilder:append	(Ljava/lang/String;)Ljava/lang/StringBuilder;
    //   6330: ldc_w 416
    //   6333: invokevirtual 99	java/lang/StringBuilder:append	(Ljava/lang/String;)Ljava/lang/StringBuilder;
    //   6336: ldc_w 449
    //   6339: invokevirtual 99	java/lang/StringBuilder:append	(Ljava/lang/String;)Ljava/lang/StringBuilder;
    //   6342: aload_0
    //   6343: invokevirtual 451	com/tencent/component/network/downloader/impl/e:d	()I
    //   6346: invokevirtual 109	java/lang/StringBuilder:append	(I)Ljava/lang/StringBuilder;
    //   6349: ldc_w 416
    //   6352: invokevirtual 99	java/lang/StringBuilder:append	(Ljava/lang/String;)Ljava/lang/StringBuilder;
    //   6355: ldc_w 453
    //   6358: invokevirtual 99	java/lang/StringBuilder:append	(Ljava/lang/String;)Ljava/lang/StringBuilder;
    //   6361: astore 25
    //   6363: aload_0
    //   6364: getfield 456	com/tencent/component/network/downloader/impl/e:jdField_a_of_type_ComTencentComponentNetworkDownloaderImplA$a	Lcom/tencent/component/network/downloader/impl/a$a;
    //   6367: ifnull +62 -> 6429
    //   6370: aload_0
    //   6371: getfield 456	com/tencent/component/network/downloader/impl/e:jdField_a_of_type_ComTencentComponentNetworkDownloaderImplA$a	Lcom/tencent/component/network/downloader/impl/a$a;
    //   6374: invokeinterface 461 1 0
    //   6379: astore 21
    //   6381: ldc 88
    //   6383: aload 25
    //   6385: aload 21
    //   6387: invokevirtual 384	java/lang/StringBuilder:append	(Ljava/lang/Object;)Ljava/lang/StringBuilder;
    //   6390: invokevirtual 140	java/lang/StringBuilder:toString	()Ljava/lang/String;
    //   6393: invokestatic 143	com/tencent/component/network/module/base/b:b	(Ljava/lang/String;Ljava/lang/String;)V
    //   6396: goto -5406 -> 990
    //   6399: aconst_null
    //   6400: astore 21
    //   6402: goto -5856 -> 546
    //   6405: iconst_0
    //   6406: istore 4
    //   6408: goto -5641 -> 767
    //   6411: aconst_null
    //   6412: astore 21
    //   6414: goto -5441 -> 973
    //   6417: aconst_null
    //   6418: astore 21
    //   6420: goto -434 -> 5986
    //   6423: iconst_0
    //   6424: istore 4
    //   6426: goto -251 -> 6175
    //   6429: aconst_null
    //   6430: astore 21
    //   6432: goto -51 -> 6381
    //   6435: astore 21
    //   6437: ldc 88
    //   6439: ldc_w 605
    //   6442: aload 21
    //   6444: invokestatic 607	com/tencent/component/network/module/base/b:c	(Ljava/lang/String;Ljava/lang/String;Ljava/lang/Throwable;)V
    //   6447: goto -5407 -> 1040
    //   6450: astore 21
    //   6452: ldc 88
    //   6454: ldc_w 609
    //   6457: aload 21
    //   6459: invokestatic 607	com/tencent/component/network/module/base/b:c	(Ljava/lang/String;Ljava/lang/String;Ljava/lang/Throwable;)V
    //   6462: goto -5372 -> 1090
    //   6465: aload 23
    //   6467: invokevirtual 612	com/tencent/component/network/utils/NetworkUtils$DNS:toString	()Ljava/lang/String;
    //   6470: astore 19
    //   6472: goto -5337 -> 1135
    //   6475: invokestatic 86	com/tencent/component/network/module/base/b:b	()Z
    //   6478: ifeq -3855 -> 2623
    //   6481: new 90	java/lang/StringBuilder
    //   6484: dup
    //   6485: invokespecial 93	java/lang/StringBuilder:<init>	()V
    //   6488: ldc_w 603
    //   6491: invokevirtual 99	java/lang/StringBuilder:append	(Ljava/lang/String;)Ljava/lang/StringBuilder;
    //   6494: aload_0
    //   6495: invokevirtual 68	com/tencent/component/network/downloader/impl/e:a	()Ljava/lang/String;
    //   6498: invokevirtual 99	java/lang/StringBuilder:append	(Ljava/lang/String;)Ljava/lang/StringBuilder;
    //   6501: ldc_w 381
    //   6504: invokevirtual 99	java/lang/StringBuilder:append	(Ljava/lang/String;)Ljava/lang/StringBuilder;
    //   6507: aload 22
    //   6509: invokevirtual 384	java/lang/StringBuilder:append	(Ljava/lang/Object;)Ljava/lang/StringBuilder;
    //   6512: ldc_w 386
    //   6515: invokevirtual 99	java/lang/StringBuilder:append	(Ljava/lang/String;)Ljava/lang/StringBuilder;
    //   6518: aload 20
    //   6520: invokevirtual 99	java/lang/StringBuilder:append	(Ljava/lang/String;)Ljava/lang/StringBuilder;
    //   6523: ldc_w 388
    //   6526: invokevirtual 99	java/lang/StringBuilder:append	(Ljava/lang/String;)Ljava/lang/StringBuilder;
    //   6529: aload 21
    //   6531: invokevirtual 99	java/lang/StringBuilder:append	(Ljava/lang/String;)Ljava/lang/StringBuilder;
    //   6534: ldc_w 390
    //   6537: invokevirtual 99	java/lang/StringBuilder:append	(Ljava/lang/String;)Ljava/lang/StringBuilder;
    //   6540: invokestatic 133	java/lang/Thread:currentThread	()Ljava/lang/Thread;
    //   6543: invokevirtual 136	java/lang/Thread:getId	()J
    //   6546: invokevirtual 139	java/lang/StringBuilder:append	(J)Ljava/lang/StringBuilder;
    //   6549: ldc_w 392
    //   6552: invokevirtual 99	java/lang/StringBuilder:append	(Ljava/lang/String;)Ljava/lang/StringBuilder;
    //   6555: invokestatic 121	com/tencent/component/network/NetworkManager:a	()Ljava/lang/String;
    //   6558: invokevirtual 99	java/lang/StringBuilder:append	(Ljava/lang/String;)Ljava/lang/StringBuilder;
    //   6561: ldc_w 394
    //   6564: invokevirtual 99	java/lang/StringBuilder:append	(Ljava/lang/String;)Ljava/lang/StringBuilder;
    //   6567: aload_0
    //   6568: getfield 146	com/tencent/component/network/downloader/impl/e:jdField_a_of_type_Boolean	Z
    //   6571: invokevirtual 397	java/lang/StringBuilder:append	(Z)Ljava/lang/StringBuilder;
    //   6574: ldc_w 399
    //   6577: invokevirtual 99	java/lang/StringBuilder:append	(Ljava/lang/String;)Ljava/lang/StringBuilder;
    //   6580: aload_0
    //   6581: getfield 149	com/tencent/component/network/downloader/impl/e:jdField_b_of_type_Boolean	Z
    //   6584: invokevirtual 397	java/lang/StringBuilder:append	(Z)Ljava/lang/StringBuilder;
    //   6587: ldc_w 401
    //   6590: invokevirtual 99	java/lang/StringBuilder:append	(Ljava/lang/String;)Ljava/lang/StringBuilder;
    //   6593: astore 23
    //   6595: aload_0
    //   6596: getfield 146	com/tencent/component/network/downloader/impl/e:jdField_a_of_type_Boolean	Z
    //   6599: ifeq +447 -> 7046
    //   6602: aload_0
    //   6603: getfield 61	com/tencent/component/network/downloader/impl/e:jdField_a_of_type_AndroidContentContext	Landroid/content/Context;
    //   6606: aload_0
    //   6607: getfield 149	com/tencent/component/network/downloader/impl/e:jdField_b_of_type_Boolean	Z
    //   6610: invokestatic 249	com/tencent/component/network/utils/NetworkUtils:a	(Landroid/content/Context;Z)Lcom/tencent/component/network/utils/NetworkUtils$NetworkProxy;
    //   6613: astore 20
    //   6615: aload 23
    //   6617: aload 20
    //   6619: invokevirtual 384	java/lang/StringBuilder:append	(Ljava/lang/Object;)Ljava/lang/StringBuilder;
    //   6622: ldc_w 408
    //   6625: invokevirtual 99	java/lang/StringBuilder:append	(Ljava/lang/String;)Ljava/lang/StringBuilder;
    //   6628: aload_2
    //   6629: invokevirtual 336	com/tencent/component/network/downloader/DownloadResult:a	()Lcom/tencent/component/network/downloader/DownloadResult$Process;
    //   6632: getfield 409	com/tencent/component/network/downloader/DownloadResult$Process:jdField_c_of_type_Long	J
    //   6635: invokevirtual 139	java/lang/StringBuilder:append	(J)Ljava/lang/StringBuilder;
    //   6638: ldc_w 411
    //   6641: invokevirtual 99	java/lang/StringBuilder:append	(Ljava/lang/String;)Ljava/lang/StringBuilder;
    //   6644: invokestatic 28	android/os/SystemClock:uptimeMillis	()J
    //   6647: aload_0
    //   6648: getfield 30	com/tencent/component/network/downloader/impl/e:jdField_i_of_type_Long	J
    //   6651: lsub
    //   6652: invokevirtual 139	java/lang/StringBuilder:append	(J)Ljava/lang/StringBuilder;
    //   6655: ldc_w 413
    //   6658: invokevirtual 99	java/lang/StringBuilder:append	(Ljava/lang/String;)Ljava/lang/StringBuilder;
    //   6661: aload_2
    //   6662: invokevirtual 367	com/tencent/component/network/downloader/DownloadResult:a	()Lcom/tencent/component/network/downloader/DownloadResult$Content;
    //   6665: getfield 414	com/tencent/component/network/downloader/DownloadResult$Content:jdField_a_of_type_Long	J
    //   6668: invokevirtual 139	java/lang/StringBuilder:append	(J)Ljava/lang/StringBuilder;
    //   6671: ldc_w 373
    //   6674: invokevirtual 99	java/lang/StringBuilder:append	(Ljava/lang/String;)Ljava/lang/StringBuilder;
    //   6677: aload_2
    //   6678: invokevirtual 367	com/tencent/component/network/downloader/DownloadResult:a	()Lcom/tencent/component/network/downloader/DownloadResult$Content;
    //   6681: getfield 371	com/tencent/component/network/downloader/DownloadResult$Content:jdField_b_of_type_Long	J
    //   6684: invokevirtual 139	java/lang/StringBuilder:append	(J)Ljava/lang/StringBuilder;
    //   6687: ldc_w 416
    //   6690: invokevirtual 99	java/lang/StringBuilder:append	(Ljava/lang/String;)Ljava/lang/StringBuilder;
    //   6693: ldc_w 418
    //   6696: invokevirtual 99	java/lang/StringBuilder:append	(Ljava/lang/String;)Ljava/lang/StringBuilder;
    //   6699: aload_2
    //   6700: invokevirtual 367	com/tencent/component/network/downloader/DownloadResult:a	()Lcom/tencent/component/network/downloader/DownloadResult$Content;
    //   6703: getfield 419	com/tencent/component/network/downloader/DownloadResult$Content:jdField_c_of_type_Long	J
    //   6706: invokevirtual 139	java/lang/StringBuilder:append	(J)Ljava/lang/StringBuilder;
    //   6709: ldc_w 421
    //   6712: invokevirtual 99	java/lang/StringBuilder:append	(Ljava/lang/String;)Ljava/lang/StringBuilder;
    //   6715: aload_0
    //   6716: invokevirtual 325	com/tencent/component/network/downloader/impl/e:b	()I
    //   6719: invokevirtual 109	java/lang/StringBuilder:append	(I)Ljava/lang/StringBuilder;
    //   6722: ldc_w 373
    //   6725: invokevirtual 99	java/lang/StringBuilder:append	(Ljava/lang/String;)Ljava/lang/StringBuilder;
    //   6728: aload_0
    //   6729: invokevirtual 422	com/tencent/component/network/downloader/impl/e:c	()I
    //   6732: invokevirtual 109	java/lang/StringBuilder:append	(I)Ljava/lang/StringBuilder;
    //   6735: ldc_w 416
    //   6738: invokevirtual 99	java/lang/StringBuilder:append	(Ljava/lang/String;)Ljava/lang/StringBuilder;
    //   6741: ldc_w 427
    //   6744: invokevirtual 99	java/lang/StringBuilder:append	(Ljava/lang/String;)Ljava/lang/StringBuilder;
    //   6747: iload_3
    //   6748: invokevirtual 109	java/lang/StringBuilder:append	(I)Ljava/lang/StringBuilder;
    //   6751: ldc_w 405
    //   6754: invokevirtual 99	java/lang/StringBuilder:append	(Ljava/lang/String;)Ljava/lang/StringBuilder;
    //   6757: aload_2
    //   6758: invokevirtual 367	com/tencent/component/network/downloader/DownloadResult:a	()Lcom/tencent/component/network/downloader/DownloadResult$Content;
    //   6761: getfield 406	com/tencent/component/network/downloader/DownloadResult$Content:jdField_a_of_type_JavaLangString	Ljava/lang/String;
    //   6764: invokevirtual 99	java/lang/StringBuilder:append	(Ljava/lang/String;)Ljava/lang/StringBuilder;
    //   6767: ldc_w 429
    //   6770: invokevirtual 99	java/lang/StringBuilder:append	(Ljava/lang/String;)Ljava/lang/StringBuilder;
    //   6773: aload_0
    //   6774: getfield 430	com/tencent/component/network/downloader/impl/e:jdField_a_of_type_JavaLangString	Ljava/lang/String;
    //   6777: invokevirtual 99	java/lang/StringBuilder:append	(Ljava/lang/String;)Ljava/lang/StringBuilder;
    //   6780: ldc_w 432
    //   6783: invokevirtual 99	java/lang/StringBuilder:append	(Ljava/lang/String;)Ljava/lang/StringBuilder;
    //   6786: astore 20
    //   6788: aload_0
    //   6789: getfield 74	com/tencent/component/network/downloader/impl/e:jdField_b_of_type_ComTencentComponentNetworkDownloaderStrategyDownloadGlobalStrategy$StrategyInfo	Lcom/tencent/component/network/downloader/strategy/DownloadGlobalStrategy$StrategyInfo;
    //   6792: ifnull +260 -> 7052
    //   6795: aload_0
    //   6796: getfield 74	com/tencent/component/network/downloader/impl/e:jdField_b_of_type_ComTencentComponentNetworkDownloaderStrategyDownloadGlobalStrategy$StrategyInfo	Lcom/tencent/component/network/downloader/strategy/DownloadGlobalStrategy$StrategyInfo;
    //   6799: getfield 162	com/tencent/component/network/downloader/strategy/DownloadGlobalStrategy$StrategyInfo:jdField_a_of_type_Int	I
    //   6802: istore 4
    //   6804: aload 20
    //   6806: iload 4
    //   6808: invokevirtual 109	java/lang/StringBuilder:append	(I)Ljava/lang/StringBuilder;
    //   6811: ldc_w 434
    //   6814: invokevirtual 99	java/lang/StringBuilder:append	(Ljava/lang/String;)Ljava/lang/StringBuilder;
    //   6817: aload_2
    //   6818: invokevirtual 367	com/tencent/component/network/downloader/DownloadResult:a	()Lcom/tencent/component/network/downloader/DownloadResult$Content;
    //   6821: getfield 435	com/tencent/component/network/downloader/DownloadResult$Content:jdField_c_of_type_JavaLangString	Ljava/lang/String;
    //   6824: invokevirtual 99	java/lang/StringBuilder:append	(Ljava/lang/String;)Ljava/lang/StringBuilder;
    //   6827: ldc_w 437
    //   6830: invokevirtual 99	java/lang/StringBuilder:append	(Ljava/lang/String;)Ljava/lang/StringBuilder;
    //   6833: lload 9
    //   6835: invokevirtual 139	java/lang/StringBuilder:append	(J)Ljava/lang/StringBuilder;
    //   6838: ldc_w 416
    //   6841: invokevirtual 99	java/lang/StringBuilder:append	(Ljava/lang/String;)Ljava/lang/StringBuilder;
    //   6844: ldc_w 439
    //   6847: invokevirtual 99	java/lang/StringBuilder:append	(Ljava/lang/String;)Ljava/lang/StringBuilder;
    //   6850: aload_0
    //   6851: getfield 38	com/tencent/component/network/downloader/impl/e:jdField_d_of_type_Long	J
    //   6854: invokevirtual 139	java/lang/StringBuilder:append	(J)Ljava/lang/StringBuilder;
    //   6857: ldc_w 373
    //   6860: invokevirtual 99	java/lang/StringBuilder:append	(Ljava/lang/String;)Ljava/lang/StringBuilder;
    //   6863: aload_0
    //   6864: getfield 40	com/tencent/component/network/downloader/impl/e:jdField_c_of_type_Int	I
    //   6867: invokevirtual 109	java/lang/StringBuilder:append	(I)Ljava/lang/StringBuilder;
    //   6870: ldc_w 416
    //   6873: invokevirtual 99	java/lang/StringBuilder:append	(Ljava/lang/String;)Ljava/lang/StringBuilder;
    //   6876: ldc_w 441
    //   6879: invokevirtual 99	java/lang/StringBuilder:append	(Ljava/lang/String;)Ljava/lang/StringBuilder;
    //   6882: aload_0
    //   6883: getfield 42	com/tencent/component/network/downloader/impl/e:jdField_e_of_type_Long	J
    //   6886: invokevirtual 139	java/lang/StringBuilder:append	(J)Ljava/lang/StringBuilder;
    //   6889: ldc_w 373
    //   6892: invokevirtual 99	java/lang/StringBuilder:append	(Ljava/lang/String;)Ljava/lang/StringBuilder;
    //   6895: aload_0
    //   6896: getfield 44	com/tencent/component/network/downloader/impl/e:jdField_d_of_type_Int	I
    //   6899: invokevirtual 109	java/lang/StringBuilder:append	(I)Ljava/lang/StringBuilder;
    //   6902: ldc_w 416
    //   6905: invokevirtual 99	java/lang/StringBuilder:append	(Ljava/lang/String;)Ljava/lang/StringBuilder;
    //   6908: ldc_w 443
    //   6911: invokevirtual 99	java/lang/StringBuilder:append	(Ljava/lang/String;)Ljava/lang/StringBuilder;
    //   6914: aload_0
    //   6915: getfield 46	com/tencent/component/network/downloader/impl/e:jdField_f_of_type_Long	J
    //   6918: invokevirtual 139	java/lang/StringBuilder:append	(J)Ljava/lang/StringBuilder;
    //   6921: ldc_w 416
    //   6924: invokevirtual 99	java/lang/StringBuilder:append	(Ljava/lang/String;)Ljava/lang/StringBuilder;
    //   6927: ldc_w 445
    //   6930: invokevirtual 99	java/lang/StringBuilder:append	(Ljava/lang/String;)Ljava/lang/StringBuilder;
    //   6933: aload_0
    //   6934: getfield 48	com/tencent/component/network/downloader/impl/e:jdField_g_of_type_Long	J
    //   6937: invokevirtual 139	java/lang/StringBuilder:append	(J)Ljava/lang/StringBuilder;
    //   6940: ldc_w 416
    //   6943: invokevirtual 99	java/lang/StringBuilder:append	(Ljava/lang/String;)Ljava/lang/StringBuilder;
    //   6946: ldc_w 447
    //   6949: invokevirtual 99	java/lang/StringBuilder:append	(Ljava/lang/String;)Ljava/lang/StringBuilder;
    //   6952: aload_0
    //   6953: getfield 36	com/tencent/component/network/downloader/impl/e:jdField_d_of_type_JavaLangString	Ljava/lang/String;
    //   6956: invokevirtual 99	java/lang/StringBuilder:append	(Ljava/lang/String;)Ljava/lang/StringBuilder;
    //   6959: ldc_w 416
    //   6962: invokevirtual 99	java/lang/StringBuilder:append	(Ljava/lang/String;)Ljava/lang/StringBuilder;
    //   6965: ldc_w 449
    //   6968: invokevirtual 99	java/lang/StringBuilder:append	(Ljava/lang/String;)Ljava/lang/StringBuilder;
    //   6971: aload_0
    //   6972: invokevirtual 451	com/tencent/component/network/downloader/impl/e:d	()I
    //   6975: invokevirtual 109	java/lang/StringBuilder:append	(I)Ljava/lang/StringBuilder;
    //   6978: ldc_w 416
    //   6981: invokevirtual 99	java/lang/StringBuilder:append	(Ljava/lang/String;)Ljava/lang/StringBuilder;
    //   6984: ldc_w 453
    //   6987: invokevirtual 99	java/lang/StringBuilder:append	(Ljava/lang/String;)Ljava/lang/StringBuilder;
    //   6990: astore 23
    //   6992: aload_0
    //   6993: getfield 456	com/tencent/component/network/downloader/impl/e:jdField_a_of_type_ComTencentComponentNetworkDownloaderImplA$a	Lcom/tencent/component/network/downloader/impl/a$a;
    //   6996: ifnull +62 -> 7058
    //   6999: aload_0
    //   7000: getfield 456	com/tencent/component/network/downloader/impl/e:jdField_a_of_type_ComTencentComponentNetworkDownloaderImplA$a	Lcom/tencent/component/network/downloader/impl/a$a;
    //   7003: invokeinterface 461 1 0
    //   7008: astore 20
    //   7010: ldc 88
    //   7012: aload 23
    //   7014: aload 20
    //   7016: invokevirtual 384	java/lang/StringBuilder:append	(Ljava/lang/Object;)Ljava/lang/StringBuilder;
    //   7019: invokevirtual 140	java/lang/StringBuilder:toString	()Ljava/lang/String;
    //   7022: invokestatic 143	com/tencent/component/network/module/base/b:b	(Ljava/lang/String;Ljava/lang/String;)V
    //   7025: goto -4402 -> 2623
    //   7028: aconst_null
    //   7029: astore 20
    //   7031: goto -4851 -> 2180
    //   7034: iconst_0
    //   7035: istore 4
    //   7037: goto -4636 -> 2401
    //   7040: aconst_null
    //   7041: astore 20
    //   7043: goto -4436 -> 2607
    //   7046: aconst_null
    //   7047: astore 20
    //   7049: goto -434 -> 6615
    //   7052: iconst_0
    //   7053: istore 4
    //   7055: goto -251 -> 6804
    //   7058: aconst_null
    //   7059: astore 20
    //   7061: goto -51 -> 7010
    //   7064: astore 20
    //   7066: ldc 88
    //   7068: ldc_w 605
    //   7071: aload 20
    //   7073: invokestatic 607	com/tencent/component/network/module/base/b:c	(Ljava/lang/String;Ljava/lang/String;Ljava/lang/Throwable;)V
    //   7076: goto -4403 -> 2673
    //   7079: astore 20
    //   7081: ldc 88
    //   7083: ldc_w 609
    //   7086: aload 20
    //   7088: invokestatic 607	com/tencent/component/network/module/base/b:c	(Ljava/lang/String;Ljava/lang/String;Ljava/lang/Throwable;)V
    //   7091: goto -4368 -> 2723
    //   7094: aload 22
    //   7096: invokevirtual 612	com/tencent/component/network/utils/NetworkUtils$DNS:toString	()Ljava/lang/String;
    //   7099: astore 19
    //   7101: goto -4334 -> 2767
    //   7104: invokestatic 86	com/tencent/component/network/module/base/b:b	()Z
    //   7107: ifeq -3345 -> 3762
    //   7110: new 90	java/lang/StringBuilder
    //   7113: dup
    //   7114: invokespecial 93	java/lang/StringBuilder:<init>	()V
    //   7117: ldc_w 603
    //   7120: invokevirtual 99	java/lang/StringBuilder:append	(Ljava/lang/String;)Ljava/lang/StringBuilder;
    //   7123: aload_0
    //   7124: invokevirtual 68	com/tencent/component/network/downloader/impl/e:a	()Ljava/lang/String;
    //   7127: invokevirtual 99	java/lang/StringBuilder:append	(Ljava/lang/String;)Ljava/lang/StringBuilder;
    //   7130: ldc_w 381
    //   7133: invokevirtual 99	java/lang/StringBuilder:append	(Ljava/lang/String;)Ljava/lang/StringBuilder;
    //   7136: aload 22
    //   7138: invokevirtual 384	java/lang/StringBuilder:append	(Ljava/lang/Object;)Ljava/lang/StringBuilder;
    //   7141: ldc_w 386
    //   7144: invokevirtual 99	java/lang/StringBuilder:append	(Ljava/lang/String;)Ljava/lang/StringBuilder;
    //   7147: aload 20
    //   7149: invokevirtual 99	java/lang/StringBuilder:append	(Ljava/lang/String;)Ljava/lang/StringBuilder;
    //   7152: ldc_w 388
    //   7155: invokevirtual 99	java/lang/StringBuilder:append	(Ljava/lang/String;)Ljava/lang/StringBuilder;
    //   7158: aload 21
    //   7160: invokevirtual 99	java/lang/StringBuilder:append	(Ljava/lang/String;)Ljava/lang/StringBuilder;
    //   7163: ldc_w 390
    //   7166: invokevirtual 99	java/lang/StringBuilder:append	(Ljava/lang/String;)Ljava/lang/StringBuilder;
    //   7169: invokestatic 133	java/lang/Thread:currentThread	()Ljava/lang/Thread;
    //   7172: invokevirtual 136	java/lang/Thread:getId	()J
    //   7175: invokevirtual 139	java/lang/StringBuilder:append	(J)Ljava/lang/StringBuilder;
    //   7178: ldc_w 392
    //   7181: invokevirtual 99	java/lang/StringBuilder:append	(Ljava/lang/String;)Ljava/lang/StringBuilder;
    //   7184: invokestatic 121	com/tencent/component/network/NetworkManager:a	()Ljava/lang/String;
    //   7187: invokevirtual 99	java/lang/StringBuilder:append	(Ljava/lang/String;)Ljava/lang/StringBuilder;
    //   7190: ldc_w 394
    //   7193: invokevirtual 99	java/lang/StringBuilder:append	(Ljava/lang/String;)Ljava/lang/StringBuilder;
    //   7196: aload_0
    //   7197: getfield 146	com/tencent/component/network/downloader/impl/e:jdField_a_of_type_Boolean	Z
    //   7200: invokevirtual 397	java/lang/StringBuilder:append	(Z)Ljava/lang/StringBuilder;
    //   7203: ldc_w 399
    //   7206: invokevirtual 99	java/lang/StringBuilder:append	(Ljava/lang/String;)Ljava/lang/StringBuilder;
    //   7209: aload_0
    //   7210: getfield 149	com/tencent/component/network/downloader/impl/e:jdField_b_of_type_Boolean	Z
    //   7213: invokevirtual 397	java/lang/StringBuilder:append	(Z)Ljava/lang/StringBuilder;
    //   7216: ldc_w 401
    //   7219: invokevirtual 99	java/lang/StringBuilder:append	(Ljava/lang/String;)Ljava/lang/StringBuilder;
    //   7222: astore 23
    //   7224: aload_0
    //   7225: getfield 146	com/tencent/component/network/downloader/impl/e:jdField_a_of_type_Boolean	Z
    //   7228: ifeq +447 -> 7675
    //   7231: aload_0
    //   7232: getfield 61	com/tencent/component/network/downloader/impl/e:jdField_a_of_type_AndroidContentContext	Landroid/content/Context;
    //   7235: aload_0
    //   7236: getfield 149	com/tencent/component/network/downloader/impl/e:jdField_b_of_type_Boolean	Z
    //   7239: invokestatic 249	com/tencent/component/network/utils/NetworkUtils:a	(Landroid/content/Context;Z)Lcom/tencent/component/network/utils/NetworkUtils$NetworkProxy;
    //   7242: astore 20
    //   7244: aload 23
    //   7246: aload 20
    //   7248: invokevirtual 384	java/lang/StringBuilder:append	(Ljava/lang/Object;)Ljava/lang/StringBuilder;
    //   7251: ldc_w 408
    //   7254: invokevirtual 99	java/lang/StringBuilder:append	(Ljava/lang/String;)Ljava/lang/StringBuilder;
    //   7257: aload_2
    //   7258: invokevirtual 336	com/tencent/component/network/downloader/DownloadResult:a	()Lcom/tencent/component/network/downloader/DownloadResult$Process;
    //   7261: getfield 409	com/tencent/component/network/downloader/DownloadResult$Process:jdField_c_of_type_Long	J
    //   7264: invokevirtual 139	java/lang/StringBuilder:append	(J)Ljava/lang/StringBuilder;
    //   7267: ldc_w 411
    //   7270: invokevirtual 99	java/lang/StringBuilder:append	(Ljava/lang/String;)Ljava/lang/StringBuilder;
    //   7273: invokestatic 28	android/os/SystemClock:uptimeMillis	()J
    //   7276: aload_0
    //   7277: getfield 30	com/tencent/component/network/downloader/impl/e:jdField_i_of_type_Long	J
    //   7280: lsub
    //   7281: invokevirtual 139	java/lang/StringBuilder:append	(J)Ljava/lang/StringBuilder;
    //   7284: ldc_w 413
    //   7287: invokevirtual 99	java/lang/StringBuilder:append	(Ljava/lang/String;)Ljava/lang/StringBuilder;
    //   7290: aload_2
    //   7291: invokevirtual 367	com/tencent/component/network/downloader/DownloadResult:a	()Lcom/tencent/component/network/downloader/DownloadResult$Content;
    //   7294: getfield 414	com/tencent/component/network/downloader/DownloadResult$Content:jdField_a_of_type_Long	J
    //   7297: invokevirtual 139	java/lang/StringBuilder:append	(J)Ljava/lang/StringBuilder;
    //   7300: ldc_w 373
    //   7303: invokevirtual 99	java/lang/StringBuilder:append	(Ljava/lang/String;)Ljava/lang/StringBuilder;
    //   7306: aload_2
    //   7307: invokevirtual 367	com/tencent/component/network/downloader/DownloadResult:a	()Lcom/tencent/component/network/downloader/DownloadResult$Content;
    //   7310: getfield 371	com/tencent/component/network/downloader/DownloadResult$Content:jdField_b_of_type_Long	J
    //   7313: invokevirtual 139	java/lang/StringBuilder:append	(J)Ljava/lang/StringBuilder;
    //   7316: ldc_w 416
    //   7319: invokevirtual 99	java/lang/StringBuilder:append	(Ljava/lang/String;)Ljava/lang/StringBuilder;
    //   7322: ldc_w 418
    //   7325: invokevirtual 99	java/lang/StringBuilder:append	(Ljava/lang/String;)Ljava/lang/StringBuilder;
    //   7328: aload_2
    //   7329: invokevirtual 367	com/tencent/component/network/downloader/DownloadResult:a	()Lcom/tencent/component/network/downloader/DownloadResult$Content;
    //   7332: getfield 419	com/tencent/component/network/downloader/DownloadResult$Content:jdField_c_of_type_Long	J
    //   7335: invokevirtual 139	java/lang/StringBuilder:append	(J)Ljava/lang/StringBuilder;
    //   7338: ldc_w 421
    //   7341: invokevirtual 99	java/lang/StringBuilder:append	(Ljava/lang/String;)Ljava/lang/StringBuilder;
    //   7344: aload_0
    //   7345: invokevirtual 325	com/tencent/component/network/downloader/impl/e:b	()I
    //   7348: invokevirtual 109	java/lang/StringBuilder:append	(I)Ljava/lang/StringBuilder;
    //   7351: ldc_w 373
    //   7354: invokevirtual 99	java/lang/StringBuilder:append	(Ljava/lang/String;)Ljava/lang/StringBuilder;
    //   7357: aload_0
    //   7358: invokevirtual 422	com/tencent/component/network/downloader/impl/e:c	()I
    //   7361: invokevirtual 109	java/lang/StringBuilder:append	(I)Ljava/lang/StringBuilder;
    //   7364: ldc_w 416
    //   7367: invokevirtual 99	java/lang/StringBuilder:append	(Ljava/lang/String;)Ljava/lang/StringBuilder;
    //   7370: ldc_w 427
    //   7373: invokevirtual 99	java/lang/StringBuilder:append	(Ljava/lang/String;)Ljava/lang/StringBuilder;
    //   7376: iload_3
    //   7377: invokevirtual 109	java/lang/StringBuilder:append	(I)Ljava/lang/StringBuilder;
    //   7380: ldc_w 405
    //   7383: invokevirtual 99	java/lang/StringBuilder:append	(Ljava/lang/String;)Ljava/lang/StringBuilder;
    //   7386: aload_2
    //   7387: invokevirtual 367	com/tencent/component/network/downloader/DownloadResult:a	()Lcom/tencent/component/network/downloader/DownloadResult$Content;
    //   7390: getfield 406	com/tencent/component/network/downloader/DownloadResult$Content:jdField_a_of_type_JavaLangString	Ljava/lang/String;
    //   7393: invokevirtual 99	java/lang/StringBuilder:append	(Ljava/lang/String;)Ljava/lang/StringBuilder;
    //   7396: ldc_w 429
    //   7399: invokevirtual 99	java/lang/StringBuilder:append	(Ljava/lang/String;)Ljava/lang/StringBuilder;
    //   7402: aload_0
    //   7403: getfield 430	com/tencent/component/network/downloader/impl/e:jdField_a_of_type_JavaLangString	Ljava/lang/String;
    //   7406: invokevirtual 99	java/lang/StringBuilder:append	(Ljava/lang/String;)Ljava/lang/StringBuilder;
    //   7409: ldc_w 432
    //   7412: invokevirtual 99	java/lang/StringBuilder:append	(Ljava/lang/String;)Ljava/lang/StringBuilder;
    //   7415: astore 20
    //   7417: aload_0
    //   7418: getfield 74	com/tencent/component/network/downloader/impl/e:jdField_b_of_type_ComTencentComponentNetworkDownloaderStrategyDownloadGlobalStrategy$StrategyInfo	Lcom/tencent/component/network/downloader/strategy/DownloadGlobalStrategy$StrategyInfo;
    //   7421: ifnull +260 -> 7681
    //   7424: aload_0
    //   7425: getfield 74	com/tencent/component/network/downloader/impl/e:jdField_b_of_type_ComTencentComponentNetworkDownloaderStrategyDownloadGlobalStrategy$StrategyInfo	Lcom/tencent/component/network/downloader/strategy/DownloadGlobalStrategy$StrategyInfo;
    //   7428: getfield 162	com/tencent/component/network/downloader/strategy/DownloadGlobalStrategy$StrategyInfo:jdField_a_of_type_Int	I
    //   7431: istore 4
    //   7433: aload 20
    //   7435: iload 4
    //   7437: invokevirtual 109	java/lang/StringBuilder:append	(I)Ljava/lang/StringBuilder;
    //   7440: ldc_w 434
    //   7443: invokevirtual 99	java/lang/StringBuilder:append	(Ljava/lang/String;)Ljava/lang/StringBuilder;
    //   7446: aload_2
    //   7447: invokevirtual 367	com/tencent/component/network/downloader/DownloadResult:a	()Lcom/tencent/component/network/downloader/DownloadResult$Content;
    //   7450: getfield 435	com/tencent/component/network/downloader/DownloadResult$Content:jdField_c_of_type_JavaLangString	Ljava/lang/String;
    //   7453: invokevirtual 99	java/lang/StringBuilder:append	(Ljava/lang/String;)Ljava/lang/StringBuilder;
    //   7456: ldc_w 437
    //   7459: invokevirtual 99	java/lang/StringBuilder:append	(Ljava/lang/String;)Ljava/lang/StringBuilder;
    //   7462: lload 9
    //   7464: invokevirtual 139	java/lang/StringBuilder:append	(J)Ljava/lang/StringBuilder;
    //   7467: ldc_w 416
    //   7470: invokevirtual 99	java/lang/StringBuilder:append	(Ljava/lang/String;)Ljava/lang/StringBuilder;
    //   7473: ldc_w 439
    //   7476: invokevirtual 99	java/lang/StringBuilder:append	(Ljava/lang/String;)Ljava/lang/StringBuilder;
    //   7479: aload_0
    //   7480: getfield 38	com/tencent/component/network/downloader/impl/e:jdField_d_of_type_Long	J
    //   7483: invokevirtual 139	java/lang/StringBuilder:append	(J)Ljava/lang/StringBuilder;
    //   7486: ldc_w 373
    //   7489: invokevirtual 99	java/lang/StringBuilder:append	(Ljava/lang/String;)Ljava/lang/StringBuilder;
    //   7492: aload_0
    //   7493: getfield 40	com/tencent/component/network/downloader/impl/e:jdField_c_of_type_Int	I
    //   7496: invokevirtual 109	java/lang/StringBuilder:append	(I)Ljava/lang/StringBuilder;
    //   7499: ldc_w 416
    //   7502: invokevirtual 99	java/lang/StringBuilder:append	(Ljava/lang/String;)Ljava/lang/StringBuilder;
    //   7505: ldc_w 441
    //   7508: invokevirtual 99	java/lang/StringBuilder:append	(Ljava/lang/String;)Ljava/lang/StringBuilder;
    //   7511: aload_0
    //   7512: getfield 42	com/tencent/component/network/downloader/impl/e:jdField_e_of_type_Long	J
    //   7515: invokevirtual 139	java/lang/StringBuilder:append	(J)Ljava/lang/StringBuilder;
    //   7518: ldc_w 373
    //   7521: invokevirtual 99	java/lang/StringBuilder:append	(Ljava/lang/String;)Ljava/lang/StringBuilder;
    //   7524: aload_0
    //   7525: getfield 44	com/tencent/component/network/downloader/impl/e:jdField_d_of_type_Int	I
    //   7528: invokevirtual 109	java/lang/StringBuilder:append	(I)Ljava/lang/StringBuilder;
    //   7531: ldc_w 416
    //   7534: invokevirtual 99	java/lang/StringBuilder:append	(Ljava/lang/String;)Ljava/lang/StringBuilder;
    //   7537: ldc_w 443
    //   7540: invokevirtual 99	java/lang/StringBuilder:append	(Ljava/lang/String;)Ljava/lang/StringBuilder;
    //   7543: aload_0
    //   7544: getfield 46	com/tencent/component/network/downloader/impl/e:jdField_f_of_type_Long	J
    //   7547: invokevirtual 139	java/lang/StringBuilder:append	(J)Ljava/lang/StringBuilder;
    //   7550: ldc_w 416
    //   7553: invokevirtual 99	java/lang/StringBuilder:append	(Ljava/lang/String;)Ljava/lang/StringBuilder;
    //   7556: ldc_w 445
    //   7559: invokevirtual 99	java/lang/StringBuilder:append	(Ljava/lang/String;)Ljava/lang/StringBuilder;
    //   7562: aload_0
    //   7563: getfield 48	com/tencent/component/network/downloader/impl/e:jdField_g_of_type_Long	J
    //   7566: invokevirtual 139	java/lang/StringBuilder:append	(J)Ljava/lang/StringBuilder;
    //   7569: ldc_w 416
    //   7572: invokevirtual 99	java/lang/StringBuilder:append	(Ljava/lang/String;)Ljava/lang/StringBuilder;
    //   7575: ldc_w 447
    //   7578: invokevirtual 99	java/lang/StringBuilder:append	(Ljava/lang/String;)Ljava/lang/StringBuilder;
    //   7581: aload_0
    //   7582: getfield 36	com/tencent/component/network/downloader/impl/e:jdField_d_of_type_JavaLangString	Ljava/lang/String;
    //   7585: invokevirtual 99	java/lang/StringBuilder:append	(Ljava/lang/String;)Ljava/lang/StringBuilder;
    //   7588: ldc_w 416
    //   7591: invokevirtual 99	java/lang/StringBuilder:append	(Ljava/lang/String;)Ljava/lang/StringBuilder;
    //   7594: ldc_w 449
    //   7597: invokevirtual 99	java/lang/StringBuilder:append	(Ljava/lang/String;)Ljava/lang/StringBuilder;
    //   7600: aload_0
    //   7601: invokevirtual 451	com/tencent/component/network/downloader/impl/e:d	()I
    //   7604: invokevirtual 109	java/lang/StringBuilder:append	(I)Ljava/lang/StringBuilder;
    //   7607: ldc_w 416
    //   7610: invokevirtual 99	java/lang/StringBuilder:append	(Ljava/lang/String;)Ljava/lang/StringBuilder;
    //   7613: ldc_w 453
    //   7616: invokevirtual 99	java/lang/StringBuilder:append	(Ljava/lang/String;)Ljava/lang/StringBuilder;
    //   7619: astore 23
    //   7621: aload_0
    //   7622: getfield 456	com/tencent/component/network/downloader/impl/e:jdField_a_of_type_ComTencentComponentNetworkDownloaderImplA$a	Lcom/tencent/component/network/downloader/impl/a$a;
    //   7625: ifnull +62 -> 7687
    //   7628: aload_0
    //   7629: getfield 456	com/tencent/component/network/downloader/impl/e:jdField_a_of_type_ComTencentComponentNetworkDownloaderImplA$a	Lcom/tencent/component/network/downloader/impl/a$a;
    //   7632: invokeinterface 461 1 0
    //   7637: astore 20
    //   7639: ldc 88
    //   7641: aload 23
    //   7643: aload 20
    //   7645: invokevirtual 384	java/lang/StringBuilder:append	(Ljava/lang/Object;)Ljava/lang/StringBuilder;
    //   7648: invokevirtual 140	java/lang/StringBuilder:toString	()Ljava/lang/String;
    //   7651: invokestatic 143	com/tencent/component/network/module/base/b:b	(Ljava/lang/String;Ljava/lang/String;)V
    //   7654: goto -3892 -> 3762
    //   7657: aconst_null
    //   7658: astore 20
    //   7660: goto -4341 -> 3319
    //   7663: iconst_0
    //   7664: istore 4
    //   7666: goto -4126 -> 3540
    //   7669: aconst_null
    //   7670: astore 20
    //   7672: goto -3926 -> 3746
    //   7675: aconst_null
    //   7676: astore 20
    //   7678: goto -434 -> 7244
    //   7681: iconst_0
    //   7682: istore 4
    //   7684: goto -251 -> 7433
    //   7687: aconst_null
    //   7688: astore 20
    //   7690: goto -51 -> 7639
    //   7693: astore 20
    //   7695: ldc 88
    //   7697: ldc_w 605
    //   7700: aload 20
    //   7702: invokestatic 607	com/tencent/component/network/module/base/b:c	(Ljava/lang/String;Ljava/lang/String;Ljava/lang/Throwable;)V
    //   7705: goto -3893 -> 3812
    //   7708: astore 20
    //   7710: ldc 88
    //   7712: ldc_w 609
    //   7715: aload 20
    //   7717: invokestatic 607	com/tencent/component/network/module/base/b:c	(Ljava/lang/String;Ljava/lang/String;Ljava/lang/Throwable;)V
    //   7720: goto -3858 -> 3862
    //   7723: aload 22
    //   7725: invokevirtual 612	com/tencent/component/network/utils/NetworkUtils$DNS:toString	()Ljava/lang/String;
    //   7728: astore 19
    //   7730: goto -3824 -> 3906
    //   7733: astore 22
    //   7735: aconst_null
    //   7736: astore 19
    //   7738: aload 18
    //   7740: astore 20
    //   7742: aload 22
    //   7744: astore 18
    //   7746: iload 6
    //   7748: istore_3
    //   7749: goto -3271 -> 4478
    //   7752: astore 22
    //   7754: aconst_null
    //   7755: astore 19
    //   7757: aload 18
    //   7759: astore 20
    //   7761: aload 22
    //   7763: astore 18
    //   7765: iload 6
    //   7767: istore_3
    //   7768: goto -3290 -> 4478
    //   7771: astore 23
    //   7773: aconst_null
    //   7774: astore 22
    //   7776: aload 18
    //   7778: astore 20
    //   7780: aload 19
    //   7782: astore 21
    //   7784: aload 23
    //   7786: astore 18
    //   7788: aload 22
    //   7790: astore 19
    //   7792: iload 6
    //   7794: istore_3
    //   7795: goto -3317 -> 4478
    //   7798: astore 22
    //   7800: aload 18
    //   7802: astore 20
    //   7804: aload 19
    //   7806: astore 21
    //   7808: aload 22
    //   7810: astore 18
    //   7812: aconst_null
    //   7813: astore 19
    //   7815: goto -3337 -> 4478
    //   7818: astore 23
    //   7820: aconst_null
    //   7821: astore 22
    //   7823: aload 18
    //   7825: astore 20
    //   7827: aload 19
    //   7829: astore 21
    //   7831: aload 23
    //   7833: astore 18
    //   7835: aload 22
    //   7837: astore 19
    //   7839: goto -3361 -> 4478
    //   7842: astore 23
    //   7844: aload 18
    //   7846: astore 21
    //   7848: aload 19
    //   7850: astore 22
    //   7852: aload 23
    //   7854: astore 18
    //   7856: aload 20
    //   7858: astore 19
    //   7860: aload 21
    //   7862: astore 20
    //   7864: aload 22
    //   7866: astore 21
    //   7868: goto -3390 -> 4478
    //   7871: astore 20
    //   7873: iconst_0
    //   7874: istore_3
    //   7875: aconst_null
    //   7876: astore 19
    //   7878: goto -7671 -> 207
    //   7881: astore 20
    //   7883: aconst_null
    //   7884: astore 19
    //   7886: iconst_0
    //   7887: istore_3
    //   7888: goto -7681 -> 207
    //   7891: astore 20
    //   7893: goto -7686 -> 207
    //   7896: goto -4898 -> 2998
    // Local variable table:
    //   start	length	slot	name	signature
    //   0	7899	0	this	e
    //   0	7899	1	paramJobContext	com.tencent.component.network.utils.thread.ThreadPool.JobContext
    //   0	7899	2	paramDownloadResult	com.tencent.component.network.downloader.DownloadResult
    //   165	7723	3	j	int
    //   24	7659	4	k	int
    //   229	3866	5	m	int
    //   129	7664	6	n	int
    //   132	3977	7	i1	int
    //   18	69	8	i2	int
    //   21	7442	9	l1	long
    //   73	4410	11	l2	long
    //   146	1639	13	l3	long
    //   1780	3	15	l4	long
    //   156	3	17	bool	boolean
    //   135	1	18	localObject1	Object
    //   187	8	18	localUnknownHostException	java.net.UnknownHostException
    //   202	4266	18	localObject2	Object
    //   4470	3269	18	localObject3	Object
    //   7744	111	18	localObject4	Object
    //   205	7680	19	localObject5	Object
    //   126	1	20	localObject6	Object
    //   197	926	20	localThrowable1	java.lang.Throwable
    //   1895	1856	20	localObject7	Object
    //   4114	2405	20	localThrowable2	java.lang.Throwable
    //   6613	447	20	localObject8	Object
    //   7064	8	20	localException1	java.lang.Exception
    //   7079	69	20	localException2	java.lang.Exception
    //   7242	447	20	localObject9	Object
    //   7693	8	20	localException3	java.lang.Exception
    //   7708	8	20	localException4	java.lang.Exception
    //   7740	123	20	localObject10	Object
    //   7871	1	20	localThrowable3	java.lang.Throwable
    //   7881	1	20	localThrowable4	java.lang.Throwable
    //   7891	1	20	localThrowable5	java.lang.Throwable
    //   123	6308	21	localObject11	Object
    //   6435	8	21	localException5	java.lang.Exception
    //   6450	709	21	localException6	java.lang.Exception
    //   7782	85	21	localObject12	Object
    //   269	5533	22	localObject13	Object
    //   5806	8	22	localException7	java.lang.Exception
    //   5821	1903	22	localException8	java.lang.Exception
    //   7733	10	22	localObject14	Object
    //   7752	10	22	localObject15	Object
    //   7774	15	22	localObject16	Object
    //   7798	11	22	localObject17	Object
    //   7821	44	22	localObject18	Object
    //   253	7389	23	localObject19	Object
    //   7771	14	23	localObject20	Object
    //   7818	14	23	localObject21	Object
    //   7842	11	23	localObject22	Object
    //   82	4358	24	localDownloadReport	com.tencent.component.network.downloader.DownloadReport
    //   524	5860	25	localObject23	Object
    //   4126	1635	26	localStringBuilder	java.lang.StringBuilder
    // Exception table:
    //   from	to	target	type
    //   148	158	187	java/net/UnknownHostException
    //   194	197	197	java/lang/Throwable
    //   1333	1380	197	java/lang/Throwable
    //   1380	1494	197	java/lang/Throwable
    //   1494	1510	197	java/lang/Throwable
    //   1514	1525	197	java/lang/Throwable
    //   1528	1535	197	java/lang/Throwable
    //   1539	1567	197	java/lang/Throwable
    //   1571	1595	197	java/lang/Throwable
    //   1599	1683	197	java/lang/Throwable
    //   1683	1740	197	java/lang/Throwable
    //   1740	1777	197	java/lang/Throwable
    //   2955	2966	197	java/lang/Throwable
    //   1811	1824	4114	java/lang/Throwable
    //   4100	4108	4114	java/lang/Throwable
    //   194	197	4470	finally
    //   1333	1380	4470	finally
    //   1380	1494	4470	finally
    //   1494	1510	4470	finally
    //   1514	1525	4470	finally
    //   1528	1535	4470	finally
    //   1539	1567	4470	finally
    //   1571	1595	4470	finally
    //   1599	1683	4470	finally
    //   1683	1740	4470	finally
    //   1740	1777	4470	finally
    //   2955	2966	4470	finally
    //   4164	4191	5806	java/lang/Exception
    //   4214	4241	5821	java/lang/Exception
    //   1013	1040	6435	java/lang/Exception
    //   1063	1090	6450	java/lang/Exception
    //   2646	2673	7064	java/lang/Exception
    //   2696	2723	7079	java/lang/Exception
    //   3785	3812	7693	java/lang/Exception
    //   3835	3862	7708	java/lang/Exception
    //   1777	1782	7733	finally
    //   1789	1806	7752	finally
    //   1811	1824	7771	finally
    //   4100	4108	7771	finally
    //   1824	1832	7798	finally
    //   1846	1865	7798	finally
    //   2969	2998	7798	finally
    //   207	216	7818	finally
    //   216	225	7842	finally
    //   1777	1782	7871	java/lang/Throwable
    //   1789	1806	7881	java/lang/Throwable
    //   1824	1832	7891	java/lang/Throwable
    //   1846	1865	7891	java/lang/Throwable
    //   2969	2998	7891	java/lang/Throwable
  }
}


/* Location:           L:\local\mybackup\temp\qq_apk\com.tencent.minihd.qq\assets\exlibs.2.jar\classes.jar
 * Qualified Name:     com.tencent.component.network.downloader.impl.e
 * JD-Core Version:    0.7.0.1
 */