package com.tencent.beacon.event;

import android.os.Build.VERSION;
import java.util.Calendar;
import java.util.HashMap;
import java.util.Iterator;
import java.util.Map;
import java.util.Random;
import java.util.Set;

public final class g
  implements Cloneable
{
  private int A = 1;
  private int a = 12;
  private int b = 60;
  private int c = 12;
  private int d = 60;
  private int e = 20;
  private int f = 10485760;
  private boolean g = false;
  private int h = 30;
  private boolean i = true;
  private boolean j = true;
  private Set<String> k = null;
  private Map<String, Float> l = null;
  private boolean m = false;
  private float n = 1.0F;
  private boolean o = false;
  private int p = 600;
  private boolean q = true;
  private boolean r = false;
  private boolean s = false;
  private boolean t = false;
  private int u = 180;
  private boolean v = true;
  private boolean w = false;
  private boolean x = true;
  private String y;
  private boolean z = false;
  
  private void a(int paramInt)
  {
    if (paramInt > 0) {}
    try
    {
      this.a = paramInt;
      return;
    }
    finally
    {
      localObject = finally;
      throw localObject;
    }
  }
  
  private void b(int paramInt)
  {
    if (paramInt > 0) {}
    try
    {
      this.b = paramInt;
      return;
    }
    finally
    {
      localObject = finally;
      throw localObject;
    }
  }
  
  private void c(int paramInt)
  {
    if (paramInt > 0) {}
    try
    {
      this.c = paramInt;
      return;
    }
    finally
    {
      localObject = finally;
      throw localObject;
    }
  }
  
  private void d(int paramInt)
  {
    if (paramInt > 0) {}
    try
    {
      this.d = paramInt;
      return;
    }
    finally
    {
      localObject = finally;
      throw localObject;
    }
  }
  
  private void e(int paramInt)
  {
    if (paramInt > 0) {}
    try
    {
      this.e = paramInt;
      return;
    }
    finally
    {
      localObject = finally;
      throw localObject;
    }
  }
  
  private void f(int paramInt)
  {
    if (paramInt > 0) {}
    try
    {
      this.f = paramInt;
      return;
    }
    finally
    {
      localObject = finally;
      throw localObject;
    }
  }
  
  public static void g() {}
  
  private g z()
  {
    try
    {
      g localg = new g();
      localg.d(this.d);
      localg.c(this.c);
      localg.e(this.e);
      localg.f(this.f);
      localg.b(this.b);
      localg.a(this.a);
      return localg;
    }
    finally
    {
      localObject = finally;
      throw localObject;
    }
  }
  
  public final int a()
  {
    try
    {
      int i1 = this.a;
      return i1;
    }
    finally
    {
      localObject = finally;
      throw localObject;
    }
  }
  
  /* Error */
  public final void a(Map<String, String> paramMap)
  {
    // Byte code:
    //   0: aload_0
    //   1: monitorenter
    //   2: aload_1
    //   3: ifnull +1431 -> 1434
    //   6: aload_1
    //   7: ldc 120
    //   9: invokeinterface 126 2 0
    //   14: checkcast 128	java/lang/String
    //   17: astore_3
    //   18: aload_3
    //   19: ifnull +26 -> 45
    //   22: aload_3
    //   23: invokestatic 134	java/lang/Integer:valueOf	(Ljava/lang/String;)Ljava/lang/Integer;
    //   26: invokevirtual 137	java/lang/Integer:intValue	()I
    //   29: istore_2
    //   30: iload_2
    //   31: ifle +14 -> 45
    //   34: iload_2
    //   35: bipush 50
    //   37: if_icmpgt +8 -> 45
    //   40: aload_0
    //   41: iload_2
    //   42: putfield 47	com/tencent/beacon/event/g:a	I
    //   45: aload_1
    //   46: ldc 139
    //   48: invokeinterface 126 2 0
    //   53: checkcast 128	java/lang/String
    //   56: astore_3
    //   57: aload_3
    //   58: ifnull +29 -> 87
    //   61: aload_3
    //   62: invokestatic 134	java/lang/Integer:valueOf	(Ljava/lang/String;)Ljava/lang/Integer;
    //   65: invokevirtual 137	java/lang/Integer:intValue	()I
    //   68: istore_2
    //   69: iload_2
    //   70: bipush 10
    //   72: if_icmplt +15 -> 87
    //   75: iload_2
    //   76: sipush 600
    //   79: if_icmpgt +8 -> 87
    //   82: aload_0
    //   83: iload_2
    //   84: putfield 49	com/tencent/beacon/event/g:b	I
    //   87: aload_1
    //   88: ldc 141
    //   90: invokeinterface 126 2 0
    //   95: checkcast 128	java/lang/String
    //   98: astore_3
    //   99: aload_3
    //   100: ifnull +26 -> 126
    //   103: aload_3
    //   104: invokestatic 134	java/lang/Integer:valueOf	(Ljava/lang/String;)Ljava/lang/Integer;
    //   107: invokevirtual 137	java/lang/Integer:intValue	()I
    //   110: istore_2
    //   111: iload_2
    //   112: ifle +14 -> 126
    //   115: iload_2
    //   116: bipush 50
    //   118: if_icmpgt +8 -> 126
    //   121: aload_0
    //   122: iload_2
    //   123: putfield 51	com/tencent/beacon/event/g:c	I
    //   126: aload_1
    //   127: ldc 143
    //   129: invokeinterface 126 2 0
    //   134: checkcast 128	java/lang/String
    //   137: astore_3
    //   138: aload_3
    //   139: ifnull +29 -> 168
    //   142: aload_3
    //   143: invokestatic 134	java/lang/Integer:valueOf	(Ljava/lang/String;)Ljava/lang/Integer;
    //   146: invokevirtual 137	java/lang/Integer:intValue	()I
    //   149: istore_2
    //   150: iload_2
    //   151: bipush 30
    //   153: if_icmplt +15 -> 168
    //   156: iload_2
    //   157: sipush 600
    //   160: if_icmpgt +8 -> 168
    //   163: aload_0
    //   164: iload_2
    //   165: putfield 53	com/tencent/beacon/event/g:d	I
    //   168: aload_1
    //   169: ldc 145
    //   171: invokeinterface 126 2 0
    //   176: checkcast 128	java/lang/String
    //   179: astore_3
    //   180: aload_3
    //   181: ifnull +26 -> 207
    //   184: aload_3
    //   185: invokestatic 134	java/lang/Integer:valueOf	(Ljava/lang/String;)Ljava/lang/Integer;
    //   188: invokevirtual 137	java/lang/Integer:intValue	()I
    //   191: istore_2
    //   192: iload_2
    //   193: ifle +14 -> 207
    //   196: iload_2
    //   197: bipush 100
    //   199: if_icmpgt +8 -> 207
    //   202: aload_0
    //   203: iload_2
    //   204: putfield 55	com/tencent/beacon/event/g:e	I
    //   207: aload_1
    //   208: ldc 147
    //   210: invokeinterface 126 2 0
    //   215: checkcast 128	java/lang/String
    //   218: astore_3
    //   219: aload_3
    //   220: ifnull +28 -> 248
    //   223: aload_3
    //   224: invokestatic 134	java/lang/Integer:valueOf	(Ljava/lang/String;)Ljava/lang/Integer;
    //   227: invokevirtual 137	java/lang/Integer:intValue	()I
    //   230: istore_2
    //   231: iload_2
    //   232: ldc 148
    //   234: if_icmplt +14 -> 248
    //   237: iload_2
    //   238: ldc 56
    //   240: if_icmpgt +8 -> 248
    //   243: aload_0
    //   244: iload_2
    //   245: putfield 58	com/tencent/beacon/event/g:f	I
    //   248: aload_1
    //   249: ldc 150
    //   251: invokeinterface 126 2 0
    //   256: checkcast 128	java/lang/String
    //   259: astore_3
    //   260: aload_3
    //   261: ifnull +11 -> 272
    //   264: aload_3
    //   265: invokestatic 134	java/lang/Integer:valueOf	(Ljava/lang/String;)Ljava/lang/Integer;
    //   268: invokevirtual 137	java/lang/Integer:intValue	()I
    //   271: pop
    //   272: aload_1
    //   273: ldc 152
    //   275: invokeinterface 126 2 0
    //   280: checkcast 128	java/lang/String
    //   283: astore_3
    //   284: aload_3
    //   285: ifnull +11 -> 296
    //   288: aload_3
    //   289: invokestatic 134	java/lang/Integer:valueOf	(Ljava/lang/String;)Ljava/lang/Integer;
    //   292: invokevirtual 137	java/lang/Integer:intValue	()I
    //   295: pop
    //   296: aload_1
    //   297: ldc 154
    //   299: invokeinterface 126 2 0
    //   304: checkcast 128	java/lang/String
    //   307: astore_3
    //   308: aload_3
    //   309: ifnull +25 -> 334
    //   312: aload_3
    //   313: invokevirtual 158	java/lang/String:toLowerCase	()Ljava/lang/String;
    //   316: ldc 159
    //   318: invokevirtual 163	java/lang/String:equals	(Ljava/lang/Object;)Z
    //   321: ifne +13 -> 334
    //   324: aload_3
    //   325: invokevirtual 158	java/lang/String:toLowerCase	()Ljava/lang/String;
    //   328: ldc 164
    //   330: invokevirtual 163	java/lang/String:equals	(Ljava/lang/Object;)Z
    //   333: pop
    //   334: aload_1
    //   335: ldc 166
    //   337: invokeinterface 126 2 0
    //   342: checkcast 128	java/lang/String
    //   345: astore_3
    //   346: aload_3
    //   347: ifnull +29 -> 376
    //   350: aload_3
    //   351: invokestatic 134	java/lang/Integer:valueOf	(Ljava/lang/String;)Ljava/lang/Integer;
    //   354: invokevirtual 137	java/lang/Integer:intValue	()I
    //   357: istore_2
    //   358: iload_2
    //   359: bipush 10
    //   361: if_icmplt +15 -> 376
    //   364: iload_2
    //   365: sipush 300
    //   368: if_icmpgt +8 -> 376
    //   371: aload_0
    //   372: iload_2
    //   373: putfield 62	com/tencent/beacon/event/g:h	I
    //   376: aload_1
    //   377: ldc 168
    //   379: invokeinterface 126 2 0
    //   384: checkcast 128	java/lang/String
    //   387: astore_3
    //   388: aload_3
    //   389: ifnull +20 -> 409
    //   392: aload_3
    //   393: invokevirtual 158	java/lang/String:toLowerCase	()Ljava/lang/String;
    //   396: ldc 159
    //   398: invokevirtual 163	java/lang/String:equals	(Ljava/lang/Object;)Z
    //   401: ifeq +1036 -> 1437
    //   404: aload_0
    //   405: iconst_1
    //   406: putfield 64	com/tencent/beacon/event/g:i	Z
    //   409: aload_1
    //   410: ldc 170
    //   412: invokeinterface 126 2 0
    //   417: checkcast 128	java/lang/String
    //   420: astore_3
    //   421: aload_3
    //   422: ifnull +20 -> 442
    //   425: aload_3
    //   426: invokevirtual 158	java/lang/String:toLowerCase	()Ljava/lang/String;
    //   429: ldc 159
    //   431: invokevirtual 163	java/lang/String:equals	(Ljava/lang/Object;)Z
    //   434: ifeq +1036 -> 1470
    //   437: aload_0
    //   438: iconst_1
    //   439: putfield 66	com/tencent/beacon/event/g:j	Z
    //   442: aload_1
    //   443: ldc 172
    //   445: invokeinterface 126 2 0
    //   450: checkcast 128	java/lang/String
    //   453: astore_3
    //   454: aload_3
    //   455: ifnull +171 -> 626
    //   458: aload_3
    //   459: invokevirtual 158	java/lang/String:toLowerCase	()Ljava/lang/String;
    //   462: ldc 159
    //   464: invokevirtual 163	java/lang/String:equals	(Ljava/lang/Object;)Z
    //   467: ifeq +1023 -> 1490
    //   470: aload_1
    //   471: ldc 174
    //   473: invokeinterface 126 2 0
    //   478: checkcast 128	java/lang/String
    //   481: astore_3
    //   482: aload_3
    //   483: ifnull +25 -> 508
    //   486: aload_3
    //   487: invokevirtual 158	java/lang/String:toLowerCase	()Ljava/lang/String;
    //   490: ldc 159
    //   492: invokevirtual 163	java/lang/String:equals	(Ljava/lang/Object;)Z
    //   495: ifne +13 -> 508
    //   498: aload_3
    //   499: invokevirtual 158	java/lang/String:toLowerCase	()Ljava/lang/String;
    //   502: ldc 164
    //   504: invokevirtual 163	java/lang/String:equals	(Ljava/lang/Object;)Z
    //   507: pop
    //   508: aload_1
    //   509: ldc 176
    //   511: invokeinterface 126 2 0
    //   516: checkcast 128	java/lang/String
    //   519: astore_3
    //   520: aload_3
    //   521: ifnull +11 -> 532
    //   524: aload_3
    //   525: invokestatic 181	java/lang/Long:valueOf	(Ljava/lang/String;)Ljava/lang/Long;
    //   528: invokevirtual 185	java/lang/Long:longValue	()J
    //   531: pop2
    //   532: aload_1
    //   533: ldc 187
    //   535: invokeinterface 126 2 0
    //   540: checkcast 128	java/lang/String
    //   543: ifnull +11 -> 554
    //   546: aload_3
    //   547: invokestatic 134	java/lang/Integer:valueOf	(Ljava/lang/String;)Ljava/lang/Integer;
    //   550: invokevirtual 137	java/lang/Integer:intValue	()I
    //   553: pop
    //   554: aload_1
    //   555: ldc 189
    //   557: invokeinterface 126 2 0
    //   562: checkcast 128	java/lang/String
    //   565: astore_3
    //   566: aload_3
    //   567: ifnull +11 -> 578
    //   570: aload_3
    //   571: invokestatic 134	java/lang/Integer:valueOf	(Ljava/lang/String;)Ljava/lang/Integer;
    //   574: invokevirtual 137	java/lang/Integer:intValue	()I
    //   577: pop
    //   578: aload_1
    //   579: ldc 191
    //   581: invokeinterface 126 2 0
    //   586: checkcast 128	java/lang/String
    //   589: astore_3
    //   590: aload_3
    //   591: ifnull +11 -> 602
    //   594: aload_3
    //   595: invokestatic 134	java/lang/Integer:valueOf	(Ljava/lang/String;)Ljava/lang/Integer;
    //   598: invokevirtual 137	java/lang/Integer:intValue	()I
    //   601: pop
    //   602: aload_1
    //   603: ldc 193
    //   605: invokeinterface 126 2 0
    //   610: checkcast 128	java/lang/String
    //   613: astore_3
    //   614: aload_3
    //   615: ifnull +11 -> 626
    //   618: aload_3
    //   619: invokestatic 134	java/lang/Integer:valueOf	(Ljava/lang/String;)Ljava/lang/Integer;
    //   622: invokevirtual 137	java/lang/Integer:intValue	()I
    //   625: pop
    //   626: aload_1
    //   627: ldc 195
    //   629: invokeinterface 126 2 0
    //   634: checkcast 128	java/lang/String
    //   637: astore_3
    //   638: aload_3
    //   639: ifnull +20 -> 659
    //   642: aload_3
    //   643: invokevirtual 158	java/lang/String:toLowerCase	()Ljava/lang/String;
    //   646: ldc 159
    //   648: invokevirtual 163	java/lang/String:equals	(Ljava/lang/Object;)Z
    //   651: ifeq +852 -> 1503
    //   654: aload_0
    //   655: iconst_1
    //   656: putfield 76	com/tencent/beacon/event/g:o	Z
    //   659: aload_1
    //   660: ldc 197
    //   662: invokeinterface 126 2 0
    //   667: checkcast 128	java/lang/String
    //   670: astore_3
    //   671: aload_3
    //   672: ifnull +29 -> 701
    //   675: aload_3
    //   676: invokestatic 134	java/lang/Integer:valueOf	(Ljava/lang/String;)Ljava/lang/Integer;
    //   679: invokevirtual 137	java/lang/Integer:intValue	()I
    //   682: istore_2
    //   683: iload_2
    //   684: bipush 60
    //   686: if_icmplt +15 -> 701
    //   689: iload_2
    //   690: sipush 1200
    //   693: if_icmpgt +8 -> 701
    //   696: aload_0
    //   697: iload_2
    //   698: putfield 78	com/tencent/beacon/event/g:p	I
    //   701: aload_1
    //   702: ldc 199
    //   704: invokeinterface 126 2 0
    //   709: checkcast 128	java/lang/String
    //   712: astore_3
    //   713: aload_3
    //   714: ifnull +20 -> 734
    //   717: aload_3
    //   718: invokevirtual 158	java/lang/String:toLowerCase	()Ljava/lang/String;
    //   721: ldc 159
    //   723: invokevirtual 163	java/lang/String:equals	(Ljava/lang/Object;)Z
    //   726: ifeq +797 -> 1523
    //   729: aload_0
    //   730: iconst_1
    //   731: putfield 80	com/tencent/beacon/event/g:q	Z
    //   734: aload_1
    //   735: ldc 201
    //   737: invokeinterface 126 2 0
    //   742: checkcast 128	java/lang/String
    //   745: astore_3
    //   746: aload_3
    //   747: ifnull +25 -> 772
    //   750: aload_3
    //   751: invokevirtual 158	java/lang/String:toLowerCase	()Ljava/lang/String;
    //   754: ldc 159
    //   756: invokevirtual 163	java/lang/String:equals	(Ljava/lang/Object;)Z
    //   759: ifne +13 -> 772
    //   762: aload_3
    //   763: invokevirtual 158	java/lang/String:toLowerCase	()Ljava/lang/String;
    //   766: ldc 164
    //   768: invokevirtual 163	java/lang/String:equals	(Ljava/lang/Object;)Z
    //   771: pop
    //   772: aload_1
    //   773: ldc 203
    //   775: invokeinterface 126 2 0
    //   780: checkcast 128	java/lang/String
    //   783: astore_3
    //   784: aload_3
    //   785: ifnull +25 -> 810
    //   788: aload_3
    //   789: invokevirtual 158	java/lang/String:toLowerCase	()Ljava/lang/String;
    //   792: ldc 159
    //   794: invokevirtual 163	java/lang/String:equals	(Ljava/lang/Object;)Z
    //   797: ifne +13 -> 810
    //   800: aload_3
    //   801: invokevirtual 158	java/lang/String:toLowerCase	()Ljava/lang/String;
    //   804: ldc 164
    //   806: invokevirtual 163	java/lang/String:equals	(Ljava/lang/Object;)Z
    //   809: pop
    //   810: aload_1
    //   811: ldc 205
    //   813: invokeinterface 126 2 0
    //   818: checkcast 128	java/lang/String
    //   821: astore_3
    //   822: aload_3
    //   823: ifnull +25 -> 848
    //   826: aload_3
    //   827: invokevirtual 158	java/lang/String:toLowerCase	()Ljava/lang/String;
    //   830: ldc 159
    //   832: invokevirtual 163	java/lang/String:equals	(Ljava/lang/Object;)Z
    //   835: ifne +13 -> 848
    //   838: aload_3
    //   839: invokevirtual 158	java/lang/String:toLowerCase	()Ljava/lang/String;
    //   842: ldc 164
    //   844: invokevirtual 163	java/lang/String:equals	(Ljava/lang/Object;)Z
    //   847: pop
    //   848: aload_1
    //   849: ldc 207
    //   851: invokeinterface 126 2 0
    //   856: checkcast 128	java/lang/String
    //   859: astore_3
    //   860: aload_3
    //   861: ifnull +11 -> 872
    //   864: aload_3
    //   865: invokestatic 134	java/lang/Integer:valueOf	(Ljava/lang/String;)Ljava/lang/Integer;
    //   868: invokevirtual 137	java/lang/Integer:intValue	()I
    //   871: pop
    //   872: aload_1
    //   873: ldc 209
    //   875: invokeinterface 126 2 0
    //   880: checkcast 128	java/lang/String
    //   883: astore_3
    //   884: aload_3
    //   885: ifnull +11 -> 896
    //   888: aload_3
    //   889: invokestatic 134	java/lang/Integer:valueOf	(Ljava/lang/String;)Ljava/lang/Integer;
    //   892: invokevirtual 137	java/lang/Integer:intValue	()I
    //   895: pop
    //   896: aload_1
    //   897: ldc 211
    //   899: invokeinterface 126 2 0
    //   904: checkcast 128	java/lang/String
    //   907: astore_3
    //   908: aload_3
    //   909: ifnull +20 -> 929
    //   912: aload_3
    //   913: invokevirtual 158	java/lang/String:toLowerCase	()Ljava/lang/String;
    //   916: ldc 159
    //   918: invokevirtual 163	java/lang/String:equals	(Ljava/lang/Object;)Z
    //   921: ifeq +622 -> 1543
    //   924: aload_0
    //   925: iconst_1
    //   926: putfield 82	com/tencent/beacon/event/g:r	Z
    //   929: aload_1
    //   930: ldc 213
    //   932: invokeinterface 126 2 0
    //   937: checkcast 128	java/lang/String
    //   940: astore_3
    //   941: aload_3
    //   942: ifnull +20 -> 962
    //   945: aload_3
    //   946: invokevirtual 158	java/lang/String:toLowerCase	()Ljava/lang/String;
    //   949: ldc 159
    //   951: invokevirtual 163	java/lang/String:equals	(Ljava/lang/Object;)Z
    //   954: ifeq +609 -> 1563
    //   957: aload_0
    //   958: iconst_1
    //   959: putfield 84	com/tencent/beacon/event/g:s	Z
    //   962: aload_1
    //   963: ldc 215
    //   965: invokeinterface 126 2 0
    //   970: checkcast 128	java/lang/String
    //   973: astore_3
    //   974: aload_3
    //   975: ifnull +20 -> 995
    //   978: aload_3
    //   979: invokevirtual 158	java/lang/String:toLowerCase	()Ljava/lang/String;
    //   982: ldc 159
    //   984: invokevirtual 163	java/lang/String:equals	(Ljava/lang/Object;)Z
    //   987: ifeq +596 -> 1583
    //   990: aload_0
    //   991: iconst_1
    //   992: putfield 86	com/tencent/beacon/event/g:t	Z
    //   995: aload_0
    //   996: getfield 84	com/tencent/beacon/event/g:s	Z
    //   999: ifeq +45 -> 1044
    //   1002: aload_1
    //   1003: ldc 217
    //   1005: invokeinterface 126 2 0
    //   1010: checkcast 128	java/lang/String
    //   1013: astore_3
    //   1014: aload_3
    //   1015: ifnull +29 -> 1044
    //   1018: aload_3
    //   1019: invokestatic 134	java/lang/Integer:valueOf	(Ljava/lang/String;)Ljava/lang/Integer;
    //   1022: invokevirtual 137	java/lang/Integer:intValue	()I
    //   1025: istore_2
    //   1026: iload_2
    //   1027: bipush 60
    //   1029: if_icmplt +15 -> 1044
    //   1032: iload_2
    //   1033: sipush 3600
    //   1036: if_icmpgt +8 -> 1044
    //   1039: aload_0
    //   1040: iload_2
    //   1041: putfield 88	com/tencent/beacon/event/g:u	I
    //   1044: aload_1
    //   1045: ldc 219
    //   1047: invokeinterface 126 2 0
    //   1052: checkcast 128	java/lang/String
    //   1055: astore_3
    //   1056: aload_3
    //   1057: ifnull +20 -> 1077
    //   1060: aload_3
    //   1061: invokevirtual 158	java/lang/String:toLowerCase	()Ljava/lang/String;
    //   1064: ldc 159
    //   1066: invokevirtual 163	java/lang/String:equals	(Ljava/lang/Object;)Z
    //   1069: ifeq +534 -> 1603
    //   1072: aload_0
    //   1073: iconst_1
    //   1074: putfield 90	com/tencent/beacon/event/g:v	Z
    //   1077: aload_1
    //   1078: ldc 221
    //   1080: invokeinterface 126 2 0
    //   1085: checkcast 128	java/lang/String
    //   1088: astore_3
    //   1089: aload_3
    //   1090: ifnull +20 -> 1110
    //   1093: aload_3
    //   1094: invokevirtual 158	java/lang/String:toLowerCase	()Ljava/lang/String;
    //   1097: ldc 159
    //   1099: invokevirtual 163	java/lang/String:equals	(Ljava/lang/Object;)Z
    //   1102: ifeq +521 -> 1623
    //   1105: aload_0
    //   1106: iconst_1
    //   1107: putfield 92	com/tencent/beacon/event/g:w	Z
    //   1110: aload_1
    //   1111: ldc 223
    //   1113: invokeinterface 126 2 0
    //   1118: checkcast 128	java/lang/String
    //   1121: astore_3
    //   1122: aload_3
    //   1123: ifnull +25 -> 1148
    //   1126: aload_3
    //   1127: invokevirtual 158	java/lang/String:toLowerCase	()Ljava/lang/String;
    //   1130: ldc 159
    //   1132: invokevirtual 163	java/lang/String:equals	(Ljava/lang/Object;)Z
    //   1135: ifne +13 -> 1148
    //   1138: aload_3
    //   1139: invokevirtual 158	java/lang/String:toLowerCase	()Ljava/lang/String;
    //   1142: ldc 164
    //   1144: invokevirtual 163	java/lang/String:equals	(Ljava/lang/Object;)Z
    //   1147: pop
    //   1148: aload_1
    //   1149: ldc 225
    //   1151: invokeinterface 126 2 0
    //   1156: checkcast 128	java/lang/String
    //   1159: astore_3
    //   1160: aload_3
    //   1161: ifnull +20 -> 1181
    //   1164: aload_3
    //   1165: invokevirtual 158	java/lang/String:toLowerCase	()Ljava/lang/String;
    //   1168: ldc 159
    //   1170: invokevirtual 163	java/lang/String:equals	(Ljava/lang/Object;)Z
    //   1173: ifeq +470 -> 1643
    //   1176: aload_0
    //   1177: iconst_1
    //   1178: putfield 60	com/tencent/beacon/event/g:g	Z
    //   1181: aload_1
    //   1182: ldc 227
    //   1184: invokeinterface 126 2 0
    //   1189: checkcast 128	java/lang/String
    //   1192: astore_3
    //   1193: aload_3
    //   1194: ifnull +19 -> 1213
    //   1197: aload_3
    //   1198: invokevirtual 158	java/lang/String:toLowerCase	()Ljava/lang/String;
    //   1201: ldc 159
    //   1203: invokevirtual 163	java/lang/String:equals	(Ljava/lang/Object;)Z
    //   1206: ifeq +457 -> 1663
    //   1209: iconst_1
    //   1210: putstatic 231	com/tencent/beacon/d/a:b	Z
    //   1213: aload_1
    //   1214: ldc 233
    //   1216: invokeinterface 126 2 0
    //   1221: pop
    //   1222: aload_1
    //   1223: ldc 235
    //   1225: invokeinterface 126 2 0
    //   1230: checkcast 128	java/lang/String
    //   1233: astore_3
    //   1234: aload_3
    //   1235: ifnull +20 -> 1255
    //   1238: aload_3
    //   1239: invokevirtual 158	java/lang/String:toLowerCase	()Ljava/lang/String;
    //   1242: ldc 159
    //   1244: invokevirtual 163	java/lang/String:equals	(Ljava/lang/Object;)Z
    //   1247: ifeq +435 -> 1682
    //   1250: aload_0
    //   1251: iconst_1
    //   1252: putfield 94	com/tencent/beacon/event/g:x	Z
    //   1255: aload_0
    //   1256: aload_1
    //   1257: ldc 237
    //   1259: invokeinterface 126 2 0
    //   1264: checkcast 128	java/lang/String
    //   1267: putfield 239	com/tencent/beacon/event/g:y	Ljava/lang/String;
    //   1270: aload_1
    //   1271: ldc 241
    //   1273: invokeinterface 126 2 0
    //   1278: checkcast 128	java/lang/String
    //   1281: astore_3
    //   1282: aload_3
    //   1283: ifnull +17 -> 1300
    //   1286: aload_3
    //   1287: ldc 159
    //   1289: invokevirtual 245	java/lang/String:equalsIgnoreCase	(Ljava/lang/String;)Z
    //   1292: ifeq +410 -> 1702
    //   1295: aload_0
    //   1296: iconst_1
    //   1297: putfield 72	com/tencent/beacon/event/g:m	Z
    //   1300: aload_1
    //   1301: ldc 247
    //   1303: invokeinterface 126 2 0
    //   1308: checkcast 128	java/lang/String
    //   1311: astore_3
    //   1312: aload_3
    //   1313: ifnull +53 -> 1366
    //   1316: aload_3
    //   1317: invokevirtual 250	java/lang/String:trim	()Ljava/lang/String;
    //   1320: astore_3
    //   1321: aload_3
    //   1322: invokevirtual 253	java/lang/String:length	()I
    //   1325: ifle +41 -> 1366
    //   1328: aload_3
    //   1329: ldc 255
    //   1331: invokevirtual 259	java/lang/String:split	(Ljava/lang/String;)[Ljava/lang/String;
    //   1334: astore_3
    //   1335: aload_3
    //   1336: arraylength
    //   1337: istore_2
    //   1338: iload_2
    //   1339: iconst_2
    //   1340: if_icmpne +26 -> 1366
    //   1343: aload_0
    //   1344: aload_3
    //   1345: iconst_0
    //   1346: aaload
    //   1347: invokestatic 264	java/lang/Float:valueOf	(Ljava/lang/String;)Ljava/lang/Float;
    //   1350: invokevirtual 268	java/lang/Float:floatValue	()F
    //   1353: aload_3
    //   1354: iconst_1
    //   1355: aaload
    //   1356: invokestatic 264	java/lang/Float:valueOf	(Ljava/lang/String;)Ljava/lang/Float;
    //   1359: invokevirtual 268	java/lang/Float:floatValue	()F
    //   1362: fdiv
    //   1363: putfield 74	com/tencent/beacon/event/g:n	F
    //   1366: aload_1
    //   1367: ldc_w 270
    //   1370: invokeinterface 126 2 0
    //   1375: checkcast 128	java/lang/String
    //   1378: astore_3
    //   1379: aload_3
    //   1380: ifnull +20 -> 1400
    //   1383: aload_3
    //   1384: invokevirtual 158	java/lang/String:toLowerCase	()Ljava/lang/String;
    //   1387: ldc 159
    //   1389: invokevirtual 163	java/lang/String:equals	(Ljava/lang/Object;)Z
    //   1392: ifeq +327 -> 1719
    //   1395: aload_0
    //   1396: iconst_1
    //   1397: putfield 96	com/tencent/beacon/event/g:z	Z
    //   1400: aload_1
    //   1401: ldc_w 272
    //   1404: invokeinterface 126 2 0
    //   1409: checkcast 128	java/lang/String
    //   1412: astore_1
    //   1413: aload_1
    //   1414: ifnull +20 -> 1434
    //   1417: aload_1
    //   1418: invokestatic 134	java/lang/Integer:valueOf	(Ljava/lang/String;)Ljava/lang/Integer;
    //   1421: invokevirtual 137	java/lang/Integer:intValue	()I
    //   1424: istore_2
    //   1425: iload_2
    //   1426: ifle +8 -> 1434
    //   1429: aload_0
    //   1430: iload_2
    //   1431: putfield 98	com/tencent/beacon/event/g:A	I
    //   1434: aload_0
    //   1435: monitorexit
    //   1436: return
    //   1437: aload_3
    //   1438: invokevirtual 158	java/lang/String:toLowerCase	()Ljava/lang/String;
    //   1441: ldc 164
    //   1443: invokevirtual 163	java/lang/String:equals	(Ljava/lang/Object;)Z
    //   1446: ifeq -1037 -> 409
    //   1449: aload_0
    //   1450: iconst_0
    //   1451: putfield 64	com/tencent/beacon/event/g:i	Z
    //   1454: goto -1045 -> 409
    //   1457: astore_1
    //   1458: aload_1
    //   1459: invokestatic 275	com/tencent/beacon/d/a:a	(Ljava/lang/Throwable;)V
    //   1462: goto -28 -> 1434
    //   1465: astore_1
    //   1466: aload_0
    //   1467: monitorexit
    //   1468: aload_1
    //   1469: athrow
    //   1470: aload_3
    //   1471: invokevirtual 158	java/lang/String:toLowerCase	()Ljava/lang/String;
    //   1474: ldc 164
    //   1476: invokevirtual 163	java/lang/String:equals	(Ljava/lang/Object;)Z
    //   1479: ifeq -1037 -> 442
    //   1482: aload_0
    //   1483: iconst_0
    //   1484: putfield 66	com/tencent/beacon/event/g:j	Z
    //   1487: goto -1045 -> 442
    //   1490: aload_3
    //   1491: invokevirtual 158	java/lang/String:toLowerCase	()Ljava/lang/String;
    //   1494: ldc 164
    //   1496: invokevirtual 163	java/lang/String:equals	(Ljava/lang/Object;)Z
    //   1499: pop
    //   1500: goto -874 -> 626
    //   1503: aload_3
    //   1504: invokevirtual 158	java/lang/String:toLowerCase	()Ljava/lang/String;
    //   1507: ldc 164
    //   1509: invokevirtual 163	java/lang/String:equals	(Ljava/lang/Object;)Z
    //   1512: ifeq -853 -> 659
    //   1515: aload_0
    //   1516: iconst_0
    //   1517: putfield 76	com/tencent/beacon/event/g:o	Z
    //   1520: goto -861 -> 659
    //   1523: aload_3
    //   1524: invokevirtual 158	java/lang/String:toLowerCase	()Ljava/lang/String;
    //   1527: ldc 164
    //   1529: invokevirtual 163	java/lang/String:equals	(Ljava/lang/Object;)Z
    //   1532: ifeq -798 -> 734
    //   1535: aload_0
    //   1536: iconst_0
    //   1537: putfield 80	com/tencent/beacon/event/g:q	Z
    //   1540: goto -806 -> 734
    //   1543: aload_3
    //   1544: invokevirtual 158	java/lang/String:toLowerCase	()Ljava/lang/String;
    //   1547: ldc 164
    //   1549: invokevirtual 163	java/lang/String:equals	(Ljava/lang/Object;)Z
    //   1552: ifeq -623 -> 929
    //   1555: aload_0
    //   1556: iconst_0
    //   1557: putfield 82	com/tencent/beacon/event/g:r	Z
    //   1560: goto -631 -> 929
    //   1563: aload_3
    //   1564: invokevirtual 158	java/lang/String:toLowerCase	()Ljava/lang/String;
    //   1567: ldc 164
    //   1569: invokevirtual 163	java/lang/String:equals	(Ljava/lang/Object;)Z
    //   1572: ifeq -610 -> 962
    //   1575: aload_0
    //   1576: iconst_0
    //   1577: putfield 84	com/tencent/beacon/event/g:s	Z
    //   1580: goto -618 -> 962
    //   1583: aload_3
    //   1584: invokevirtual 158	java/lang/String:toLowerCase	()Ljava/lang/String;
    //   1587: ldc 164
    //   1589: invokevirtual 163	java/lang/String:equals	(Ljava/lang/Object;)Z
    //   1592: ifeq -597 -> 995
    //   1595: aload_0
    //   1596: iconst_0
    //   1597: putfield 86	com/tencent/beacon/event/g:t	Z
    //   1600: goto -605 -> 995
    //   1603: aload_3
    //   1604: invokevirtual 158	java/lang/String:toLowerCase	()Ljava/lang/String;
    //   1607: ldc 164
    //   1609: invokevirtual 163	java/lang/String:equals	(Ljava/lang/Object;)Z
    //   1612: ifeq -535 -> 1077
    //   1615: aload_0
    //   1616: iconst_0
    //   1617: putfield 90	com/tencent/beacon/event/g:v	Z
    //   1620: goto -543 -> 1077
    //   1623: aload_3
    //   1624: invokevirtual 158	java/lang/String:toLowerCase	()Ljava/lang/String;
    //   1627: ldc 164
    //   1629: invokevirtual 163	java/lang/String:equals	(Ljava/lang/Object;)Z
    //   1632: ifeq -522 -> 1110
    //   1635: aload_0
    //   1636: iconst_0
    //   1637: putfield 92	com/tencent/beacon/event/g:w	Z
    //   1640: goto -530 -> 1110
    //   1643: aload_3
    //   1644: invokevirtual 158	java/lang/String:toLowerCase	()Ljava/lang/String;
    //   1647: ldc 164
    //   1649: invokevirtual 163	java/lang/String:equals	(Ljava/lang/Object;)Z
    //   1652: ifeq -471 -> 1181
    //   1655: aload_0
    //   1656: iconst_0
    //   1657: putfield 60	com/tencent/beacon/event/g:g	Z
    //   1660: goto -479 -> 1181
    //   1663: aload_3
    //   1664: invokevirtual 158	java/lang/String:toLowerCase	()Ljava/lang/String;
    //   1667: ldc 164
    //   1669: invokevirtual 163	java/lang/String:equals	(Ljava/lang/Object;)Z
    //   1672: ifeq -459 -> 1213
    //   1675: iconst_0
    //   1676: putstatic 231	com/tencent/beacon/d/a:b	Z
    //   1679: goto -466 -> 1213
    //   1682: aload_3
    //   1683: invokevirtual 158	java/lang/String:toLowerCase	()Ljava/lang/String;
    //   1686: ldc 164
    //   1688: invokevirtual 163	java/lang/String:equals	(Ljava/lang/Object;)Z
    //   1691: ifeq -436 -> 1255
    //   1694: aload_0
    //   1695: iconst_0
    //   1696: putfield 94	com/tencent/beacon/event/g:x	Z
    //   1699: goto -444 -> 1255
    //   1702: aload_3
    //   1703: ldc 164
    //   1705: invokevirtual 245	java/lang/String:equalsIgnoreCase	(Ljava/lang/String;)Z
    //   1708: ifeq -408 -> 1300
    //   1711: aload_0
    //   1712: iconst_0
    //   1713: putfield 72	com/tencent/beacon/event/g:m	Z
    //   1716: goto -416 -> 1300
    //   1719: aload_3
    //   1720: invokevirtual 158	java/lang/String:toLowerCase	()Ljava/lang/String;
    //   1723: ldc 164
    //   1725: invokevirtual 163	java/lang/String:equals	(Ljava/lang/Object;)Z
    //   1728: ifeq -328 -> 1400
    //   1731: aload_0
    //   1732: iconst_0
    //   1733: putfield 96	com/tencent/beacon/event/g:z	Z
    //   1736: goto -336 -> 1400
    //   1739: astore_3
    //   1740: goto -374 -> 1366
    // Local variable table:
    //   start	length	slot	name	signature
    //   0	1743	0	this	g
    //   0	1743	1	paramMap	Map<String, String>
    //   29	1402	2	i1	int
    //   17	1703	3	localObject	Object
    //   1739	1	3	localException	Exception
    // Exception table:
    //   from	to	target	type
    //   6	18	1457	java/lang/Exception
    //   22	30	1457	java/lang/Exception
    //   40	45	1457	java/lang/Exception
    //   45	57	1457	java/lang/Exception
    //   61	69	1457	java/lang/Exception
    //   82	87	1457	java/lang/Exception
    //   87	99	1457	java/lang/Exception
    //   103	111	1457	java/lang/Exception
    //   121	126	1457	java/lang/Exception
    //   126	138	1457	java/lang/Exception
    //   142	150	1457	java/lang/Exception
    //   163	168	1457	java/lang/Exception
    //   168	180	1457	java/lang/Exception
    //   184	192	1457	java/lang/Exception
    //   202	207	1457	java/lang/Exception
    //   207	219	1457	java/lang/Exception
    //   223	231	1457	java/lang/Exception
    //   243	248	1457	java/lang/Exception
    //   248	260	1457	java/lang/Exception
    //   264	272	1457	java/lang/Exception
    //   272	284	1457	java/lang/Exception
    //   288	296	1457	java/lang/Exception
    //   296	308	1457	java/lang/Exception
    //   312	334	1457	java/lang/Exception
    //   334	346	1457	java/lang/Exception
    //   350	358	1457	java/lang/Exception
    //   371	376	1457	java/lang/Exception
    //   376	388	1457	java/lang/Exception
    //   392	409	1457	java/lang/Exception
    //   409	421	1457	java/lang/Exception
    //   425	442	1457	java/lang/Exception
    //   442	454	1457	java/lang/Exception
    //   458	482	1457	java/lang/Exception
    //   486	508	1457	java/lang/Exception
    //   508	520	1457	java/lang/Exception
    //   524	532	1457	java/lang/Exception
    //   532	554	1457	java/lang/Exception
    //   554	566	1457	java/lang/Exception
    //   570	578	1457	java/lang/Exception
    //   578	590	1457	java/lang/Exception
    //   594	602	1457	java/lang/Exception
    //   602	614	1457	java/lang/Exception
    //   618	626	1457	java/lang/Exception
    //   626	638	1457	java/lang/Exception
    //   642	659	1457	java/lang/Exception
    //   659	671	1457	java/lang/Exception
    //   675	683	1457	java/lang/Exception
    //   696	701	1457	java/lang/Exception
    //   701	713	1457	java/lang/Exception
    //   717	734	1457	java/lang/Exception
    //   734	746	1457	java/lang/Exception
    //   750	772	1457	java/lang/Exception
    //   772	784	1457	java/lang/Exception
    //   788	810	1457	java/lang/Exception
    //   810	822	1457	java/lang/Exception
    //   826	848	1457	java/lang/Exception
    //   848	860	1457	java/lang/Exception
    //   864	872	1457	java/lang/Exception
    //   872	884	1457	java/lang/Exception
    //   888	896	1457	java/lang/Exception
    //   896	908	1457	java/lang/Exception
    //   912	929	1457	java/lang/Exception
    //   929	941	1457	java/lang/Exception
    //   945	962	1457	java/lang/Exception
    //   962	974	1457	java/lang/Exception
    //   978	995	1457	java/lang/Exception
    //   995	1014	1457	java/lang/Exception
    //   1018	1026	1457	java/lang/Exception
    //   1039	1044	1457	java/lang/Exception
    //   1044	1056	1457	java/lang/Exception
    //   1060	1077	1457	java/lang/Exception
    //   1077	1089	1457	java/lang/Exception
    //   1093	1110	1457	java/lang/Exception
    //   1110	1122	1457	java/lang/Exception
    //   1126	1148	1457	java/lang/Exception
    //   1148	1160	1457	java/lang/Exception
    //   1164	1181	1457	java/lang/Exception
    //   1181	1193	1457	java/lang/Exception
    //   1197	1213	1457	java/lang/Exception
    //   1213	1234	1457	java/lang/Exception
    //   1238	1255	1457	java/lang/Exception
    //   1255	1282	1457	java/lang/Exception
    //   1286	1300	1457	java/lang/Exception
    //   1300	1312	1457	java/lang/Exception
    //   1316	1338	1457	java/lang/Exception
    //   1366	1379	1457	java/lang/Exception
    //   1383	1400	1457	java/lang/Exception
    //   1400	1413	1457	java/lang/Exception
    //   1417	1425	1457	java/lang/Exception
    //   1429	1434	1457	java/lang/Exception
    //   1437	1454	1457	java/lang/Exception
    //   1470	1487	1457	java/lang/Exception
    //   1490	1500	1457	java/lang/Exception
    //   1503	1520	1457	java/lang/Exception
    //   1523	1540	1457	java/lang/Exception
    //   1543	1560	1457	java/lang/Exception
    //   1563	1580	1457	java/lang/Exception
    //   1583	1600	1457	java/lang/Exception
    //   1603	1620	1457	java/lang/Exception
    //   1623	1640	1457	java/lang/Exception
    //   1643	1660	1457	java/lang/Exception
    //   1663	1679	1457	java/lang/Exception
    //   1682	1699	1457	java/lang/Exception
    //   1702	1716	1457	java/lang/Exception
    //   1719	1736	1457	java/lang/Exception
    //   6	18	1465	finally
    //   22	30	1465	finally
    //   40	45	1465	finally
    //   45	57	1465	finally
    //   61	69	1465	finally
    //   82	87	1465	finally
    //   87	99	1465	finally
    //   103	111	1465	finally
    //   121	126	1465	finally
    //   126	138	1465	finally
    //   142	150	1465	finally
    //   163	168	1465	finally
    //   168	180	1465	finally
    //   184	192	1465	finally
    //   202	207	1465	finally
    //   207	219	1465	finally
    //   223	231	1465	finally
    //   243	248	1465	finally
    //   248	260	1465	finally
    //   264	272	1465	finally
    //   272	284	1465	finally
    //   288	296	1465	finally
    //   296	308	1465	finally
    //   312	334	1465	finally
    //   334	346	1465	finally
    //   350	358	1465	finally
    //   371	376	1465	finally
    //   376	388	1465	finally
    //   392	409	1465	finally
    //   409	421	1465	finally
    //   425	442	1465	finally
    //   442	454	1465	finally
    //   458	482	1465	finally
    //   486	508	1465	finally
    //   508	520	1465	finally
    //   524	532	1465	finally
    //   532	554	1465	finally
    //   554	566	1465	finally
    //   570	578	1465	finally
    //   578	590	1465	finally
    //   594	602	1465	finally
    //   602	614	1465	finally
    //   618	626	1465	finally
    //   626	638	1465	finally
    //   642	659	1465	finally
    //   659	671	1465	finally
    //   675	683	1465	finally
    //   696	701	1465	finally
    //   701	713	1465	finally
    //   717	734	1465	finally
    //   734	746	1465	finally
    //   750	772	1465	finally
    //   772	784	1465	finally
    //   788	810	1465	finally
    //   810	822	1465	finally
    //   826	848	1465	finally
    //   848	860	1465	finally
    //   864	872	1465	finally
    //   872	884	1465	finally
    //   888	896	1465	finally
    //   896	908	1465	finally
    //   912	929	1465	finally
    //   929	941	1465	finally
    //   945	962	1465	finally
    //   962	974	1465	finally
    //   978	995	1465	finally
    //   995	1014	1465	finally
    //   1018	1026	1465	finally
    //   1039	1044	1465	finally
    //   1044	1056	1465	finally
    //   1060	1077	1465	finally
    //   1077	1089	1465	finally
    //   1093	1110	1465	finally
    //   1110	1122	1465	finally
    //   1126	1148	1465	finally
    //   1148	1160	1465	finally
    //   1164	1181	1465	finally
    //   1181	1193	1465	finally
    //   1197	1213	1465	finally
    //   1213	1234	1465	finally
    //   1238	1255	1465	finally
    //   1255	1282	1465	finally
    //   1286	1300	1465	finally
    //   1300	1312	1465	finally
    //   1316	1338	1465	finally
    //   1343	1366	1465	finally
    //   1366	1379	1465	finally
    //   1383	1400	1465	finally
    //   1400	1413	1465	finally
    //   1417	1425	1465	finally
    //   1429	1434	1465	finally
    //   1437	1454	1465	finally
    //   1458	1462	1465	finally
    //   1470	1487	1465	finally
    //   1490	1500	1465	finally
    //   1503	1520	1465	finally
    //   1523	1540	1465	finally
    //   1543	1560	1465	finally
    //   1563	1580	1465	finally
    //   1583	1600	1465	finally
    //   1603	1620	1465	finally
    //   1623	1640	1465	finally
    //   1643	1660	1465	finally
    //   1663	1679	1465	finally
    //   1682	1699	1465	finally
    //   1702	1716	1465	finally
    //   1719	1736	1465	finally
    //   1343	1366	1739	java/lang/Exception
  }
  
  public final void a(Set<String> paramSet)
  {
    try
    {
      this.k = paramSet;
      return;
    }
    finally
    {
      paramSet = finally;
      throw paramSet;
    }
  }
  
  public final boolean a(String paramString)
  {
    boolean bool2 = false;
    boolean bool1 = bool2;
    try
    {
      if (this.k != null)
      {
        bool1 = bool2;
        if (this.k.size() > 0) {
          bool1 = this.k.contains(paramString);
        }
      }
      return bool1;
    }
    finally {}
  }
  
  public final int b()
  {
    try
    {
      int i1 = this.b;
      return i1;
    }
    finally
    {
      localObject = finally;
      throw localObject;
    }
  }
  
  public final void b(Set<String> paramSet)
  {
    try
    {
      if (this.l == null) {
        this.l = new HashMap();
      }
      paramSet = paramSet.iterator();
      while (paramSet.hasNext())
      {
        String[] arrayOfString = ((String)paramSet.next()).split(",");
        int i1 = arrayOfString.length;
        if (i1 == 3) {
          try
          {
            float f1 = Float.valueOf(arrayOfString[1]).floatValue() / Float.valueOf(arrayOfString[2]).floatValue();
            this.l.put(arrayOfString[0].toLowerCase(), Float.valueOf(f1));
          }
          catch (Exception localException) {}
        }
      }
      return;
    }
    finally {}
  }
  
  public final boolean b(String paramString)
  {
    for (;;)
    {
      try
      {
        boolean bool;
        if (this.l != null)
        {
          Object localObject = this.l.get(paramString);
          if (localObject != null) {}
        }
        else
        {
          bool = true;
          return bool;
        }
        int i1 = (int)(((Float)this.l.get(paramString.toLowerCase())).floatValue() * 1000.0F);
        int i2 = new Random().nextInt(1000);
        if (i2 + 1 > i1) {
          bool = false;
        } else {
          bool = true;
        }
      }
      finally {}
    }
  }
  
  public final int c()
  {
    try
    {
      int i1 = this.c;
      return i1;
    }
    finally
    {
      localObject = finally;
      throw localObject;
    }
  }
  
  public final int d()
  {
    try
    {
      int i1 = this.d;
      return i1;
    }
    finally
    {
      localObject = finally;
      throw localObject;
    }
  }
  
  public final int e()
  {
    try
    {
      int i1 = this.e;
      return i1;
    }
    finally
    {
      localObject = finally;
      throw localObject;
    }
  }
  
  public final int f()
  {
    try
    {
      int i1 = this.f;
      return i1;
    }
    finally
    {
      localObject = finally;
      throw localObject;
    }
  }
  
  public final int h()
  {
    return this.h;
  }
  
  public final boolean i()
  {
    return this.i;
  }
  
  public final boolean j()
  {
    return this.j;
  }
  
  public final boolean k()
  {
    return this.w;
  }
  
  public final boolean l()
  {
    boolean bool2 = true;
    boolean bool1 = bool2;
    try
    {
      if (this.m)
      {
        Calendar localCalendar = Calendar.getInstance();
        int i1 = localCalendar.get(11);
        int i2 = localCalendar.get(12);
        bool1 = bool2;
        if (i1 == 0)
        {
          bool1 = bool2;
          if (i2 >= 0)
          {
            bool1 = bool2;
            if (30 >= i2)
            {
              i1 = (int)(this.n * 1000.0F);
              i2 = new Random().nextInt(1000);
              bool1 = bool2;
              if (i2 + 1 > i1) {
                bool1 = false;
              }
            }
          }
        }
      }
      return bool1;
    }
    finally {}
  }
  
  public final boolean m()
  {
    if (Integer.parseInt(Build.VERSION.SDK) < 8) {
      return false;
    }
    return this.o;
  }
  
  public final int n()
  {
    return this.p;
  }
  
  public final boolean o()
  {
    return this.r;
  }
  
  public final boolean p()
  {
    return this.s;
  }
  
  public final boolean q()
  {
    return this.t;
  }
  
  public final int r()
  {
    return this.u;
  }
  
  public final boolean s()
  {
    return this.v;
  }
  
  public final boolean t()
  {
    return this.g;
  }
  
  public final boolean u()
  {
    return this.x;
  }
  
  public final String v()
  {
    return this.y;
  }
  
  public final int w()
  {
    return this.A;
  }
  
  public final boolean x()
  {
    return this.z;
  }
  
  public final boolean y()
  {
    return this.q;
  }
}


/* Location:           L:\local\mybackup\temp\qq_apk\com.tencent.mobileqq\classes.jar
 * Qualified Name:     com.tencent.beacon.event.g
 * JD-Core Version:    0.7.0.1
 */