package com.tencent.qapmsdk.base.reporter.uploaddata.runnable;

import com.tencent.qapmsdk.base.reporter.uploaddata.AthenaUpload;
import com.tencent.qapmsdk.common.reporter.IReporter.ReportResultCallback;
import com.tencent.qapmsdk.common.util.FileUtil;
import com.tencent.qapmsdk.common.util.FileUtil.Companion;
import java.io.File;
import java.net.URL;
import java.util.ArrayList;
import java.util.Collection;
import java.util.Iterator;
import java.util.List;
import kotlin.Metadata;
import kotlin.collections.CollectionsKt;
import kotlin.jvm.internal.Intrinsics;
import org.jetbrains.annotations.NotNull;
import org.jetbrains.annotations.Nullable;
import org.json.JSONObject;

@Metadata(bv={1, 0, 3}, d1={""}, d2={"Lcom/tencent/qapmsdk/base/reporter/uploaddata/runnable/AthenaFileUploadRunnable;", "Lcom/tencent/qapmsdk/base/reporter/uploaddata/AthenaUpload;", "Ljava/lang/Runnable;", "url", "Ljava/net/URL;", "jsonObject", "Lorg/json/JSONObject;", "filePaths", "", "", "callback", "Lcom/tencent/qapmsdk/common/reporter/IReporter$ReportResultCallback;", "(Ljava/net/URL;Lorg/json/JSONObject;Ljava/util/List;Lcom/tencent/qapmsdk/common/reporter/IReporter$ReportResultCallback;)V", "buffer", "Ljava/lang/StringBuffer;", "getBuffer", "()Ljava/lang/StringBuffer;", "cleanOriginal", "", "generateEndStream", "generateFileStream", "fileName", "generateJsonStream", "getUploadGzipFiles", "Ljava/util/ArrayList;", "Ljava/io/File;", "Lkotlin/collections/ArrayList;", "request", "run", "Companion", "qapmbase_release"}, k=1, mv={1, 1, 15})
public final class AthenaFileUploadRunnable
  extends AthenaUpload
  implements Runnable
{
  private static final String BOUNDARY = "27182818284590452353602874713526";
  public static final AthenaFileUploadRunnable.Companion Companion = new AthenaFileUploadRunnable.Companion(null);
  private static final String TAG = "QAPM_base_AthenaFileUploadRunnable";
  @NotNull
  private final StringBuffer buffer;
  private final IReporter.ReportResultCallback callback;
  private final List<String> filePaths;
  private final JSONObject jsonObject;
  
  public AthenaFileUploadRunnable(@NotNull URL paramURL, @NotNull JSONObject paramJSONObject, @NotNull List<String> paramList, @Nullable IReporter.ReportResultCallback paramReportResultCallback)
  {
    super(paramURL);
    this.jsonObject = paramJSONObject;
    this.filePaths = paramList;
    this.callback = paramReportResultCallback;
    this.buffer = new StringBuffer(512);
  }
  
  private final void cleanOriginal()
  {
    Object localObject2 = (Iterable)this.filePaths;
    Object localObject1 = (Collection)new ArrayList();
    localObject2 = ((Iterable)localObject2).iterator();
    while (((Iterator)localObject2).hasNext())
    {
      Object localObject3 = ((Iterator)localObject2).next();
      int i;
      if (((CharSequence)localObject3).length() > 0) {
        i = 1;
      } else {
        i = 0;
      }
      if (i != 0) {
        ((Collection)localObject1).add(localObject3);
      }
    }
    localObject1 = ((Iterable)localObject1).iterator();
    while (((Iterator)localObject1).hasNext())
    {
      localObject2 = new File((String)((Iterator)localObject1).next());
      if ((((File)localObject2).isFile()) && (((File)localObject2).canRead())) {
        ((File)localObject2).delete();
      }
    }
  }
  
  private final String generateEndStream()
  {
    Object localObject = this.buffer;
    ((StringBuffer)localObject).delete(0, ((StringBuffer)localObject).length());
    localObject = this.buffer;
    ((StringBuffer)localObject).append("--");
    ((StringBuffer)localObject).append("27182818284590452353602874713526");
    ((StringBuffer)localObject).append("\r\n");
    localObject = this.buffer.toString();
    Intrinsics.checkExpressionValueIsNotNull(localObject, "buffer.toString()");
    return localObject;
  }
  
  private final String generateFileStream(String paramString)
  {
    StringBuffer localStringBuffer = this.buffer;
    localStringBuffer.delete(0, localStringBuffer.length());
    localStringBuffer = this.buffer;
    localStringBuffer.append("--");
    localStringBuffer.append("27182818284590452353602874713526");
    localStringBuffer.append("\r\n");
    localStringBuffer.append("Content-Disposition: form-data; name=\"files\"; filename=\"");
    localStringBuffer.append(paramString);
    localStringBuffer.append("\"");
    localStringBuffer.append("\r\n");
    localStringBuffer.append("Content-Type: application/octet-stream");
    localStringBuffer.append("\r\n\r\n");
    paramString = this.buffer.toString();
    Intrinsics.checkExpressionValueIsNotNull(paramString, "buffer.toString()");
    return paramString;
  }
  
  private final String generateJsonStream()
  {
    Object localObject = this.buffer;
    ((StringBuffer)localObject).delete(0, ((StringBuffer)localObject).length());
    localObject = this.buffer;
    ((StringBuffer)localObject).append("--");
    ((StringBuffer)localObject).append("27182818284590452353602874713526");
    ((StringBuffer)localObject).append("\r\n");
    ((StringBuffer)localObject).append("Content-Disposition: form-data; name=\"_json\"\r\n\r\n");
    ((StringBuffer)localObject).append(this.jsonObject.toString());
    ((StringBuffer)localObject).append("\r\n");
    localObject = this.buffer.toString();
    Intrinsics.checkExpressionValueIsNotNull(localObject, "buffer.toString()");
    return localObject;
  }
  
  private final ArrayList<File> getUploadGzipFiles()
  {
    ArrayList localArrayList = new ArrayList();
    Object localObject2 = (Iterable)this.filePaths;
    Object localObject1 = (Collection)new ArrayList();
    localObject2 = ((Iterable)localObject2).iterator();
    Object localObject3;
    while (((Iterator)localObject2).hasNext())
    {
      localObject3 = ((Iterator)localObject2).next();
      Object localObject4 = (String)localObject3;
      int i = ((CharSequence)localObject4).length();
      int j = 0;
      if (i == 0) {
        i = 1;
      } else {
        i = 0;
      }
      if (i != 0)
      {
        i = j;
      }
      else
      {
        localObject4 = new File((String)localObject4);
        i = j;
        if (((File)localObject4).isFile())
        {
          i = j;
          if (((File)localObject4).canRead()) {
            i = 1;
          }
        }
      }
      if (i != 0) {
        ((Collection)localObject1).add(localObject3);
      }
    }
    localObject1 = ((Iterable)localObject1).iterator();
    while (((Iterator)localObject1).hasNext())
    {
      localObject2 = (String)((Iterator)localObject1).next();
      localObject3 = new StringBuilder();
      ((StringBuilder)localObject3).append((String)localObject2);
      ((StringBuilder)localObject3).append(".gz");
      localObject3 = ((StringBuilder)localObject3).toString();
      if (FileUtil.Companion.zipFiles(CollectionsKt.listOf(localObject2), (String)localObject3, true)) {
        localArrayList.add(new File((String)localObject3));
      }
    }
    return localArrayList;
  }
  
  @NotNull
  public final StringBuffer getBuffer()
  {
    return this.buffer;
  }
  
  public void request()
  {
    run();
  }
  
  /* Error */
  public void run()
  {
    // Byte code:
    //   0: aload_0
    //   1: invokespecial 224	com/tencent/qapmsdk/base/reporter/uploaddata/runnable/AthenaFileUploadRunnable:getUploadGzipFiles	()Ljava/util/ArrayList;
    //   4: astore 7
    //   6: aload 7
    //   8: invokevirtual 227	java/util/ArrayList:isEmpty	()Z
    //   11: ifeq +25 -> 36
    //   14: aload_0
    //   15: getfield 87	com/tencent/qapmsdk/base/reporter/uploaddata/runnable/AthenaFileUploadRunnable:callback	Lcom/tencent/qapmsdk/common/reporter/IReporter$ReportResultCallback;
    //   18: astore_2
    //   19: aload_2
    //   20: ifnull +15 -> 35
    //   23: aload_2
    //   24: sipush 601
    //   27: ldc 229
    //   29: iconst_0
    //   30: invokeinterface 235 4 0
    //   35: return
    //   36: new 237	java/util/HashMap
    //   39: dup
    //   40: invokespecial 238	java/util/HashMap:<init>	()V
    //   43: astore_2
    //   44: aload_2
    //   45: checkcast 240	java/util/Map
    //   48: ldc 242
    //   50: ldc 244
    //   52: invokeinterface 248 3 0
    //   57: pop
    //   58: aload_0
    //   59: aload_2
    //   60: invokevirtual 252	com/tencent/qapmsdk/base/reporter/uploaddata/runnable/AthenaFileUploadRunnable:connectionBuilder	(Ljava/util/HashMap;)Ljava/net/HttpURLConnection;
    //   63: astore 6
    //   65: aload 6
    //   67: ifnull +940 -> 1007
    //   70: new 254	java/io/DataOutputStream
    //   73: dup
    //   74: aload 6
    //   76: invokevirtual 260	java/net/HttpURLConnection:getOutputStream	()Ljava/io/OutputStream;
    //   79: invokespecial 263	java/io/DataOutputStream:<init>	(Ljava/io/OutputStream;)V
    //   82: checkcast 265	java/io/Closeable
    //   85: astore 8
    //   87: aconst_null
    //   88: checkcast 222	java/lang/Throwable
    //   91: astore 4
    //   93: aload 4
    //   95: astore_2
    //   96: aload 8
    //   98: checkcast 254	java/io/DataOutputStream
    //   101: astore 10
    //   103: aload 4
    //   105: astore_2
    //   106: aload 10
    //   108: aload_0
    //   109: invokespecial 267	com/tencent/qapmsdk/base/reporter/uploaddata/runnable/AthenaFileUploadRunnable:generateJsonStream	()Ljava/lang/String;
    //   112: invokevirtual 270	java/io/DataOutputStream:writeBytes	(Ljava/lang/String;)V
    //   115: aload 4
    //   117: astore_2
    //   118: aload 7
    //   120: checkcast 99	java/lang/Iterable
    //   123: invokeinterface 109 1 0
    //   128: astore 11
    //   130: aload 4
    //   132: astore_2
    //   133: aload 11
    //   135: invokeinterface 115 1 0
    //   140: ifeq +159 -> 299
    //   143: aload 4
    //   145: astore_2
    //   146: aload 11
    //   148: invokeinterface 119 1 0
    //   153: checkcast 135	java/io/File
    //   156: astore_3
    //   157: aload 4
    //   159: astore_2
    //   160: aload_3
    //   161: invokevirtual 273	java/io/File:getName	()Ljava/lang/String;
    //   164: astore 5
    //   166: aload 4
    //   168: astore_2
    //   169: aload 5
    //   171: ldc_w 275
    //   174: invokestatic 168	kotlin/jvm/internal/Intrinsics:checkExpressionValueIsNotNull	(Ljava/lang/Object;Ljava/lang/String;)V
    //   177: aload 4
    //   179: astore_2
    //   180: aload 10
    //   182: aload_0
    //   183: aload 5
    //   185: invokespecial 277	com/tencent/qapmsdk/base/reporter/uploaddata/runnable/AthenaFileUploadRunnable:generateFileStream	(Ljava/lang/String;)Ljava/lang/String;
    //   188: invokevirtual 270	java/io/DataOutputStream:writeBytes	(Ljava/lang/String;)V
    //   191: aload 4
    //   193: astore_2
    //   194: new 279	java/io/FileInputStream
    //   197: dup
    //   198: aload_3
    //   199: invokespecial 282	java/io/FileInputStream:<init>	(Ljava/io/File;)V
    //   202: checkcast 265	java/io/Closeable
    //   205: astore 9
    //   207: aload 4
    //   209: astore_2
    //   210: aconst_null
    //   211: checkcast 222	java/lang/Throwable
    //   214: astore 5
    //   216: aload 5
    //   218: astore_3
    //   219: aload 9
    //   221: checkcast 279	java/io/FileInputStream
    //   224: astore_2
    //   225: aload 5
    //   227: astore_3
    //   228: aload_2
    //   229: checkcast 284	java/io/InputStream
    //   232: aload 10
    //   234: checkcast 286	java/io/OutputStream
    //   237: aload_2
    //   238: invokevirtual 289	java/io/FileInputStream:available	()I
    //   241: ldc_w 290
    //   244: invokestatic 296	java/lang/Math:min	(II)I
    //   247: invokestatic 302	kotlin/io/ByteStreamsKt:copyTo	(Ljava/io/InputStream;Ljava/io/OutputStream;I)J
    //   250: pop2
    //   251: aload 4
    //   253: astore_2
    //   254: aload 9
    //   256: aload 5
    //   258: invokestatic 308	kotlin/io/CloseableKt:closeFinally	(Ljava/io/Closeable;Ljava/lang/Throwable;)V
    //   261: aload 4
    //   263: astore_2
    //   264: aload 10
    //   266: ldc 160
    //   268: invokevirtual 270	java/io/DataOutputStream:writeBytes	(Ljava/lang/String;)V
    //   271: goto -141 -> 130
    //   274: astore 5
    //   276: goto +8 -> 284
    //   279: astore_2
    //   280: aload_2
    //   281: astore_3
    //   282: aload_2
    //   283: athrow
    //   284: aload 4
    //   286: astore_2
    //   287: aload 9
    //   289: aload_3
    //   290: invokestatic 308	kotlin/io/CloseableKt:closeFinally	(Ljava/io/Closeable;Ljava/lang/Throwable;)V
    //   293: aload 4
    //   295: astore_2
    //   296: aload 5
    //   298: athrow
    //   299: aload 4
    //   301: astore_2
    //   302: aload 10
    //   304: aload_0
    //   305: invokespecial 310	com/tencent/qapmsdk/base/reporter/uploaddata/runnable/AthenaFileUploadRunnable:generateEndStream	()Ljava/lang/String;
    //   308: invokevirtual 270	java/io/DataOutputStream:writeBytes	(Ljava/lang/String;)V
    //   311: aload 4
    //   313: astore_2
    //   314: getstatic 316	kotlin/Unit:INSTANCE	Lkotlin/Unit;
    //   317: astore_3
    //   318: aload 8
    //   320: aload 4
    //   322: invokestatic 308	kotlin/io/CloseableKt:closeFinally	(Ljava/io/Closeable;Ljava/lang/Throwable;)V
    //   325: new 318	java/io/BufferedInputStream
    //   328: dup
    //   329: aload 6
    //   331: invokevirtual 322	java/net/HttpURLConnection:getInputStream	()Ljava/io/InputStream;
    //   334: invokespecial 325	java/io/BufferedInputStream:<init>	(Ljava/io/InputStream;)V
    //   337: checkcast 265	java/io/Closeable
    //   340: astore 4
    //   342: aconst_null
    //   343: checkcast 222	java/lang/Throwable
    //   346: astore_3
    //   347: aload_3
    //   348: astore_2
    //   349: aload 4
    //   351: checkcast 318	java/io/BufferedInputStream
    //   354: astore 5
    //   356: aload_3
    //   357: astore_2
    //   358: getstatic 197	com/tencent/qapmsdk/common/util/FileUtil:Companion	Lcom/tencent/qapmsdk/common/util/FileUtil$Companion;
    //   361: aload 5
    //   363: checkcast 284	java/io/InputStream
    //   366: sipush 8192
    //   369: invokevirtual 329	com/tencent/qapmsdk/common/util/FileUtil$Companion:readStream	(Ljava/io/InputStream;I)Ljava/lang/String;
    //   372: astore 5
    //   374: aload_3
    //   375: astore_2
    //   376: getstatic 316	kotlin/Unit:INSTANCE	Lkotlin/Unit;
    //   379: astore 8
    //   381: aload 4
    //   383: aload_3
    //   384: invokestatic 308	kotlin/io/CloseableKt:closeFinally	(Ljava/io/Closeable;Ljava/lang/Throwable;)V
    //   387: getstatic 334	com/tencent/qapmsdk/common/logger/Logger:INSTANCE	Lcom/tencent/qapmsdk/common/logger/Logger;
    //   390: iconst_2
    //   391: anewarray 121	java/lang/String
    //   394: dup
    //   395: iconst_0
    //   396: ldc 54
    //   398: aastore
    //   399: dup
    //   400: iconst_1
    //   401: aload 5
    //   403: aastore
    //   404: invokevirtual 338	com/tencent/qapmsdk/common/logger/Logger:i	([Ljava/lang/String;)V
    //   407: aload 6
    //   409: invokevirtual 341	java/net/HttpURLConnection:getResponseCode	()I
    //   412: istore_1
    //   413: iload_1
    //   414: sipush 200
    //   417: if_icmpeq +97 -> 514
    //   420: iload_1
    //   421: sipush 400
    //   424: if_icmpeq +62 -> 486
    //   427: iload_1
    //   428: sipush 500
    //   431: if_icmpeq +31 -> 462
    //   434: aload_0
    //   435: invokespecial 343	com/tencent/qapmsdk/base/reporter/uploaddata/runnable/AthenaFileUploadRunnable:cleanOriginal	()V
    //   438: aload_0
    //   439: getfield 87	com/tencent/qapmsdk/base/reporter/uploaddata/runnable/AthenaFileUploadRunnable:callback	Lcom/tencent/qapmsdk/common/reporter/IReporter$ReportResultCallback;
    //   442: astore_2
    //   443: aload_2
    //   444: ifnull +563 -> 1007
    //   447: aload_2
    //   448: sipush 700
    //   451: aload 5
    //   453: iconst_0
    //   454: invokeinterface 235 4 0
    //   459: goto +548 -> 1007
    //   462: aload_0
    //   463: getfield 87	com/tencent/qapmsdk/base/reporter/uploaddata/runnable/AthenaFileUploadRunnable:callback	Lcom/tencent/qapmsdk/common/reporter/IReporter$ReportResultCallback;
    //   466: astore_2
    //   467: aload_2
    //   468: ifnull +539 -> 1007
    //   471: aload_2
    //   472: sipush 500
    //   475: aload 5
    //   477: iconst_0
    //   478: invokeinterface 235 4 0
    //   483: goto +524 -> 1007
    //   486: aload_0
    //   487: invokespecial 343	com/tencent/qapmsdk/base/reporter/uploaddata/runnable/AthenaFileUploadRunnable:cleanOriginal	()V
    //   490: aload_0
    //   491: getfield 87	com/tencent/qapmsdk/base/reporter/uploaddata/runnable/AthenaFileUploadRunnable:callback	Lcom/tencent/qapmsdk/common/reporter/IReporter$ReportResultCallback;
    //   494: astore_2
    //   495: aload_2
    //   496: ifnull +511 -> 1007
    //   499: aload_2
    //   500: sipush 400
    //   503: aload 5
    //   505: iconst_0
    //   506: invokeinterface 235 4 0
    //   511: goto +496 -> 1007
    //   514: aload_0
    //   515: aload 5
    //   517: invokevirtual 347	com/tencent/qapmsdk/base/reporter/uploaddata/runnable/AthenaFileUploadRunnable:isSucceeded	(Ljava/lang/String;)Z
    //   520: ifeq +25 -> 545
    //   523: aload_0
    //   524: getfield 87	com/tencent/qapmsdk/base/reporter/uploaddata/runnable/AthenaFileUploadRunnable:callback	Lcom/tencent/qapmsdk/common/reporter/IReporter$ReportResultCallback;
    //   527: astore_2
    //   528: aload_2
    //   529: ifnull +37 -> 566
    //   532: aload_2
    //   533: sipush 200
    //   536: iconst_0
    //   537: invokeinterface 351 3 0
    //   542: goto +24 -> 566
    //   545: aload_0
    //   546: getfield 87	com/tencent/qapmsdk/base/reporter/uploaddata/runnable/AthenaFileUploadRunnable:callback	Lcom/tencent/qapmsdk/common/reporter/IReporter$ReportResultCallback;
    //   549: astore_2
    //   550: aload_2
    //   551: ifnull +15 -> 566
    //   554: aload_2
    //   555: sipush 700
    //   558: aload 5
    //   560: iconst_0
    //   561: invokeinterface 235 4 0
    //   566: aload_0
    //   567: invokespecial 343	com/tencent/qapmsdk/base/reporter/uploaddata/runnable/AthenaFileUploadRunnable:cleanOriginal	()V
    //   570: goto +437 -> 1007
    //   573: astore_3
    //   574: goto +8 -> 582
    //   577: astore_3
    //   578: aload_3
    //   579: astore_2
    //   580: aload_3
    //   581: athrow
    //   582: aload 4
    //   584: aload_2
    //   585: invokestatic 308	kotlin/io/CloseableKt:closeFinally	(Ljava/io/Closeable;Ljava/lang/Throwable;)V
    //   588: aload_3
    //   589: athrow
    //   590: astore_3
    //   591: goto +8 -> 599
    //   594: astore_3
    //   595: aload_3
    //   596: astore_2
    //   597: aload_3
    //   598: athrow
    //   599: aload 8
    //   601: aload_2
    //   602: invokestatic 308	kotlin/io/CloseableKt:closeFinally	(Ljava/io/Closeable;Ljava/lang/Throwable;)V
    //   605: aload_3
    //   606: athrow
    //   607: astore_2
    //   608: goto +351 -> 959
    //   611: astore_2
    //   612: getstatic 334	com/tencent/qapmsdk/common/logger/Logger:INSTANCE	Lcom/tencent/qapmsdk/common/logger/Logger;
    //   615: ldc 54
    //   617: aload_2
    //   618: invokevirtual 355	com/tencent/qapmsdk/common/logger/Logger:exception	(Ljava/lang/String;Ljava/lang/Throwable;)V
    //   621: aload 7
    //   623: checkcast 99	java/lang/Iterable
    //   626: invokeinterface 109 1 0
    //   631: astore_2
    //   632: aload_2
    //   633: invokeinterface 115 1 0
    //   638: ifeq +19 -> 657
    //   641: aload_2
    //   642: invokeinterface 119 1 0
    //   647: checkcast 135	java/io/File
    //   650: invokevirtual 147	java/io/File:delete	()Z
    //   653: pop
    //   654: goto -22 -> 632
    //   657: aload 6
    //   659: ifnull +392 -> 1051
    //   662: aload 6
    //   664: invokevirtual 358	java/net/HttpURLConnection:disconnect	()V
    //   667: return
    //   668: astore_2
    //   669: getstatic 334	com/tencent/qapmsdk/common/logger/Logger:INSTANCE	Lcom/tencent/qapmsdk/common/logger/Logger;
    //   672: ldc 54
    //   674: aload_2
    //   675: checkcast 222	java/lang/Throwable
    //   678: invokevirtual 355	com/tencent/qapmsdk/common/logger/Logger:exception	(Ljava/lang/String;Ljava/lang/Throwable;)V
    //   681: aload 7
    //   683: checkcast 99	java/lang/Iterable
    //   686: invokeinterface 109 1 0
    //   691: astore_2
    //   692: aload_2
    //   693: invokeinterface 115 1 0
    //   698: ifeq +19 -> 717
    //   701: aload_2
    //   702: invokeinterface 119 1 0
    //   707: checkcast 135	java/io/File
    //   710: invokevirtual 147	java/io/File:delete	()Z
    //   713: pop
    //   714: goto -22 -> 692
    //   717: aload 6
    //   719: ifnull +332 -> 1051
    //   722: goto -60 -> 662
    //   725: astore_2
    //   726: getstatic 334	com/tencent/qapmsdk/common/logger/Logger:INSTANCE	Lcom/tencent/qapmsdk/common/logger/Logger;
    //   729: astore_3
    //   730: new 185	java/lang/StringBuilder
    //   733: dup
    //   734: invokespecial 186	java/lang/StringBuilder:<init>	()V
    //   737: astore 4
    //   739: aload 4
    //   741: aload_2
    //   742: invokevirtual 361	java/lang/StringBuilder:append	(Ljava/lang/Object;)Ljava/lang/StringBuilder;
    //   745: pop
    //   746: aload 4
    //   748: ldc_w 363
    //   751: invokevirtual 189	java/lang/StringBuilder:append	(Ljava/lang/String;)Ljava/lang/StringBuilder;
    //   754: pop
    //   755: aload_3
    //   756: iconst_2
    //   757: anewarray 121	java/lang/String
    //   760: dup
    //   761: iconst_0
    //   762: ldc 54
    //   764: aastore
    //   765: dup
    //   766: iconst_1
    //   767: aload 4
    //   769: invokevirtual 192	java/lang/StringBuilder:toString	()Ljava/lang/String;
    //   772: aastore
    //   773: invokevirtual 366	com/tencent/qapmsdk/common/logger/Logger:e	([Ljava/lang/String;)V
    //   776: aload_0
    //   777: getfield 87	com/tencent/qapmsdk/base/reporter/uploaddata/runnable/AthenaFileUploadRunnable:callback	Lcom/tencent/qapmsdk/common/reporter/IReporter$ReportResultCallback;
    //   780: astore_2
    //   781: aload_2
    //   782: ifnull +16 -> 798
    //   785: aload_2
    //   786: sipush 601
    //   789: ldc_w 368
    //   792: iconst_0
    //   793: invokeinterface 235 4 0
    //   798: aload 7
    //   800: checkcast 99	java/lang/Iterable
    //   803: invokeinterface 109 1 0
    //   808: astore_2
    //   809: aload_2
    //   810: invokeinterface 115 1 0
    //   815: ifeq +19 -> 834
    //   818: aload_2
    //   819: invokeinterface 119 1 0
    //   824: checkcast 135	java/io/File
    //   827: invokevirtual 147	java/io/File:delete	()Z
    //   830: pop
    //   831: goto -22 -> 809
    //   834: aload 6
    //   836: ifnull +215 -> 1051
    //   839: goto -177 -> 662
    //   842: astore_2
    //   843: getstatic 334	com/tencent/qapmsdk/common/logger/Logger:INSTANCE	Lcom/tencent/qapmsdk/common/logger/Logger;
    //   846: astore_3
    //   847: new 185	java/lang/StringBuilder
    //   850: dup
    //   851: invokespecial 186	java/lang/StringBuilder:<init>	()V
    //   854: astore 4
    //   856: aload 4
    //   858: aload_2
    //   859: invokevirtual 361	java/lang/StringBuilder:append	(Ljava/lang/Object;)Ljava/lang/StringBuilder;
    //   862: pop
    //   863: aload 4
    //   865: ldc_w 370
    //   868: invokevirtual 189	java/lang/StringBuilder:append	(Ljava/lang/String;)Ljava/lang/StringBuilder;
    //   871: pop
    //   872: aload_3
    //   873: iconst_2
    //   874: anewarray 121	java/lang/String
    //   877: dup
    //   878: iconst_0
    //   879: ldc 54
    //   881: aastore
    //   882: dup
    //   883: iconst_1
    //   884: aload 4
    //   886: invokevirtual 192	java/lang/StringBuilder:toString	()Ljava/lang/String;
    //   889: aastore
    //   890: invokevirtual 366	com/tencent/qapmsdk/common/logger/Logger:e	([Ljava/lang/String;)V
    //   893: aload_0
    //   894: getfield 87	com/tencent/qapmsdk/base/reporter/uploaddata/runnable/AthenaFileUploadRunnable:callback	Lcom/tencent/qapmsdk/common/reporter/IReporter$ReportResultCallback;
    //   897: astore_2
    //   898: aload_2
    //   899: ifnull +16 -> 915
    //   902: aload_2
    //   903: sipush 600
    //   906: ldc_w 372
    //   909: iconst_0
    //   910: invokeinterface 235 4 0
    //   915: aload 7
    //   917: checkcast 99	java/lang/Iterable
    //   920: invokeinterface 109 1 0
    //   925: astore_2
    //   926: aload_2
    //   927: invokeinterface 115 1 0
    //   932: ifeq +19 -> 951
    //   935: aload_2
    //   936: invokeinterface 119 1 0
    //   941: checkcast 135	java/io/File
    //   944: invokevirtual 147	java/io/File:delete	()Z
    //   947: pop
    //   948: goto -22 -> 926
    //   951: aload 6
    //   953: ifnull +98 -> 1051
    //   956: goto -294 -> 662
    //   959: aload 7
    //   961: checkcast 99	java/lang/Iterable
    //   964: invokeinterface 109 1 0
    //   969: astore_3
    //   970: aload_3
    //   971: invokeinterface 115 1 0
    //   976: ifeq +19 -> 995
    //   979: aload_3
    //   980: invokeinterface 119 1 0
    //   985: checkcast 135	java/io/File
    //   988: invokevirtual 147	java/io/File:delete	()Z
    //   991: pop
    //   992: goto -22 -> 970
    //   995: aload 6
    //   997: ifnull +8 -> 1005
    //   1000: aload 6
    //   1002: invokevirtual 358	java/net/HttpURLConnection:disconnect	()V
    //   1005: aload_2
    //   1006: athrow
    //   1007: aload 7
    //   1009: checkcast 99	java/lang/Iterable
    //   1012: invokeinterface 109 1 0
    //   1017: astore_2
    //   1018: aload_2
    //   1019: invokeinterface 115 1 0
    //   1024: ifeq +19 -> 1043
    //   1027: aload_2
    //   1028: invokeinterface 119 1 0
    //   1033: checkcast 135	java/io/File
    //   1036: invokevirtual 147	java/io/File:delete	()Z
    //   1039: pop
    //   1040: goto -22 -> 1018
    //   1043: aload 6
    //   1045: ifnull +6 -> 1051
    //   1048: goto -386 -> 662
    //   1051: return
    // Local variable table:
    //   start	length	slot	name	signature
    //   0	1052	0	this	AthenaFileUploadRunnable
    //   412	20	1	i	int
    //   18	246	2	localObject1	Object
    //   279	4	2	localThrowable1	java.lang.Throwable
    //   286	316	2	localObject2	Object
    //   607	1	2	localObject3	Object
    //   611	7	2	localThrowable2	java.lang.Throwable
    //   631	11	2	localIterator1	Iterator
    //   668	7	2	localException	java.lang.Exception
    //   691	11	2	localIterator2	Iterator
    //   725	17	2	localFileNotFoundException	java.io.FileNotFoundException
    //   780	39	2	localObject4	Object
    //   842	17	2	localOutOfMemoryError	java.lang.OutOfMemoryError
    //   897	131	2	localObject5	Object
    //   156	228	3	localObject6	Object
    //   573	1	3	localObject7	Object
    //   577	12	3	localThrowable3	java.lang.Throwable
    //   590	1	3	localObject8	Object
    //   594	12	3	localThrowable4	java.lang.Throwable
    //   729	251	3	localObject9	Object
    //   91	794	4	localObject10	Object
    //   164	93	5	localObject11	Object
    //   274	23	5	localObject12	Object
    //   354	205	5	localObject13	Object
    //   63	981	6	localHttpURLConnection	java.net.HttpURLConnection
    //   4	1004	7	localArrayList	ArrayList
    //   85	515	8	localObject14	Object
    //   205	83	9	localCloseable	java.io.Closeable
    //   101	202	10	localDataOutputStream	java.io.DataOutputStream
    //   128	19	11	localIterator3	Iterator
    // Exception table:
    //   from	to	target	type
    //   219	225	274	finally
    //   228	251	274	finally
    //   282	284	274	finally
    //   219	225	279	java/lang/Throwable
    //   228	251	279	java/lang/Throwable
    //   349	356	573	finally
    //   358	374	573	finally
    //   376	381	573	finally
    //   580	582	573	finally
    //   349	356	577	java/lang/Throwable
    //   358	374	577	java/lang/Throwable
    //   376	381	577	java/lang/Throwable
    //   96	103	590	finally
    //   106	115	590	finally
    //   118	130	590	finally
    //   133	143	590	finally
    //   146	157	590	finally
    //   160	166	590	finally
    //   169	177	590	finally
    //   180	191	590	finally
    //   194	207	590	finally
    //   210	216	590	finally
    //   254	261	590	finally
    //   264	271	590	finally
    //   287	293	590	finally
    //   296	299	590	finally
    //   302	311	590	finally
    //   314	318	590	finally
    //   597	599	590	finally
    //   96	103	594	java/lang/Throwable
    //   106	115	594	java/lang/Throwable
    //   118	130	594	java/lang/Throwable
    //   133	143	594	java/lang/Throwable
    //   146	157	594	java/lang/Throwable
    //   160	166	594	java/lang/Throwable
    //   169	177	594	java/lang/Throwable
    //   180	191	594	java/lang/Throwable
    //   194	207	594	java/lang/Throwable
    //   210	216	594	java/lang/Throwable
    //   254	261	594	java/lang/Throwable
    //   264	271	594	java/lang/Throwable
    //   287	293	594	java/lang/Throwable
    //   296	299	594	java/lang/Throwable
    //   302	311	594	java/lang/Throwable
    //   314	318	594	java/lang/Throwable
    //   70	93	607	finally
    //   318	347	607	finally
    //   381	413	607	finally
    //   434	443	607	finally
    //   447	459	607	finally
    //   462	467	607	finally
    //   471	483	607	finally
    //   486	495	607	finally
    //   499	511	607	finally
    //   514	528	607	finally
    //   532	542	607	finally
    //   545	550	607	finally
    //   554	566	607	finally
    //   566	570	607	finally
    //   582	590	607	finally
    //   599	607	607	finally
    //   612	621	607	finally
    //   669	681	607	finally
    //   726	781	607	finally
    //   785	798	607	finally
    //   843	898	607	finally
    //   902	915	607	finally
    //   70	93	611	java/lang/Throwable
    //   318	347	611	java/lang/Throwable
    //   381	413	611	java/lang/Throwable
    //   434	443	611	java/lang/Throwable
    //   447	459	611	java/lang/Throwable
    //   462	467	611	java/lang/Throwable
    //   471	483	611	java/lang/Throwable
    //   486	495	611	java/lang/Throwable
    //   499	511	611	java/lang/Throwable
    //   514	528	611	java/lang/Throwable
    //   532	542	611	java/lang/Throwable
    //   545	550	611	java/lang/Throwable
    //   554	566	611	java/lang/Throwable
    //   566	570	611	java/lang/Throwable
    //   582	590	611	java/lang/Throwable
    //   599	607	611	java/lang/Throwable
    //   70	93	668	java/lang/Exception
    //   318	347	668	java/lang/Exception
    //   381	413	668	java/lang/Exception
    //   434	443	668	java/lang/Exception
    //   447	459	668	java/lang/Exception
    //   462	467	668	java/lang/Exception
    //   471	483	668	java/lang/Exception
    //   486	495	668	java/lang/Exception
    //   499	511	668	java/lang/Exception
    //   514	528	668	java/lang/Exception
    //   532	542	668	java/lang/Exception
    //   545	550	668	java/lang/Exception
    //   554	566	668	java/lang/Exception
    //   566	570	668	java/lang/Exception
    //   582	590	668	java/lang/Exception
    //   599	607	668	java/lang/Exception
    //   70	93	725	java/io/FileNotFoundException
    //   318	347	725	java/io/FileNotFoundException
    //   381	413	725	java/io/FileNotFoundException
    //   434	443	725	java/io/FileNotFoundException
    //   447	459	725	java/io/FileNotFoundException
    //   462	467	725	java/io/FileNotFoundException
    //   471	483	725	java/io/FileNotFoundException
    //   486	495	725	java/io/FileNotFoundException
    //   499	511	725	java/io/FileNotFoundException
    //   514	528	725	java/io/FileNotFoundException
    //   532	542	725	java/io/FileNotFoundException
    //   545	550	725	java/io/FileNotFoundException
    //   554	566	725	java/io/FileNotFoundException
    //   566	570	725	java/io/FileNotFoundException
    //   582	590	725	java/io/FileNotFoundException
    //   599	607	725	java/io/FileNotFoundException
    //   70	93	842	java/lang/OutOfMemoryError
    //   318	347	842	java/lang/OutOfMemoryError
    //   381	413	842	java/lang/OutOfMemoryError
    //   434	443	842	java/lang/OutOfMemoryError
    //   447	459	842	java/lang/OutOfMemoryError
    //   462	467	842	java/lang/OutOfMemoryError
    //   471	483	842	java/lang/OutOfMemoryError
    //   486	495	842	java/lang/OutOfMemoryError
    //   499	511	842	java/lang/OutOfMemoryError
    //   514	528	842	java/lang/OutOfMemoryError
    //   532	542	842	java/lang/OutOfMemoryError
    //   545	550	842	java/lang/OutOfMemoryError
    //   554	566	842	java/lang/OutOfMemoryError
    //   566	570	842	java/lang/OutOfMemoryError
    //   582	590	842	java/lang/OutOfMemoryError
    //   599	607	842	java/lang/OutOfMemoryError
  }
}


/* Location:           L:\local\mybackup\temp\qq_apk\com.tencent.mobileqq\classes10.jar
 * Qualified Name:     com.tencent.qapmsdk.base.reporter.uploaddata.runnable.AthenaFileUploadRunnable
 * JD-Core Version:    0.7.0.1
 */